{
  "type": "Feature",
  "properties": {
    "gn:country":"GR",
    "gn:fcode":"PPL",
    "gn:population":0,
    "iso:country":"GR",
    "name:ceb_x_preferred":[
        "Apolakki\u00e1"
    ],
    "name:ell_x_preferred":[
        "\u0391\u03c0\u03bf\u03bb\u03b1\u03ba\u03ba\u03b9\u03ac \u03a1\u03cc\u03b4\u03bf\u03c5"
    ],
    "name:eng_x_preferred":[
        "Apolakkia"
    ],
    "name:fin_x_preferred":[
        "Apolakki\u00e1"
    ],
    "name:nld_x_preferred":[
        "Apolakkia"
    ],
    "name:swe_x_preferred":[
        "Apolakki\u00e1"
    ],
    "name:und_x_variant":[
        "Apollachia"
    ],
    "qs_pg:aaroncc":"GR",
    "qs_pg:gn_country":"GR",
    "qs_pg:gn_fcode":"PPL",
    "qs_pg:gn_pop":0,
    "qs_pg:name":"Apolakkia",
    "qs_pg:name_adm0":"\u0395\u03bb\u03bb\u03ac\u03b4\u03b1",
    "qs_pg:name_adm1":"Aegean",
    "qs_pg:photos":39,
    "qs_pg:photos_1k":8,
    "qs_pg:photos_9k":1,
    "qs_pg:photos_9r":2,
    "qs_pg:photos_all":39,
    "qs_pg:photos_sr":2,
    "qs_pg:pop_sr":0,
    "qs_pg:qs_pg_placetype":"locality",
    "qs_pg:qs_pg_placetype_gp":"Town",
    "qs_pg:woe_adm0":23424833,
    "woe:adm0_id":23424833,
    "woe:name_adm0":"\u0395\u03bb\u03bb\u03ac\u03b4\u03b1",
    "woe:name_adm1":"Aegean",
    "woe:placetype":"Town",
    "wof:name":"Apolakkia",
    "wof:placetype":"locality"
},
  "geometry": {"coordinates":[27.78872,36.06658],"type":"Point"}
}