{
  "type": "Feature",
  "properties": {
    "gn:admin1_code":"ESYE43",
    "gn:admin2_code":"46.0",
    "gn:admin3_code":"9313",
    "gn:asciiname":"Chamezi",
    "gn:country_code":"GR",
    "gn:dem":433,
    "gn:feature_class":"P",
    "gn:feature_code":"PPL",
    "gn:name":"Cham\u00e9zi",
    "gn:population":0,
    "gn:timezone":"Europe/Athens",
    "iso:country":"GR",
    "name:ell_x_preferred":[
        "Cham\u00e9zi"
    ],
    "name:ell_x_variant":[
        "\u03a7\u03b1\u03bc\u03ad\u03b6\u03b9",
        "Cham\u00e9zion",
        "\u03a7\u03b1\u03bc\u03ad\u03b6\u03b9\u03bf\u03bd"
    ],
    "name:und_x_variant":[
        "Khama\u00edzi",
        "Kham\u00e9zion"
    ],
    "wof:name":"Chamezi",
    "wof:placetype":"locality"
},
  "geometry": {"coordinates":[26.01879,35.17558],"type":"Point"}
}