{
  "type": "Feature",
  "properties": {
    "gn:country":"GR",
    "gn:fcode":"PPLA3",
    "gn:population":91617,
    "iso:country":"GR",
    "name:ara_x_preferred":[
        "\u0643\u0627\u0644\u0627\u0645\u0627\u0631\u064a\u0627"
    ],
    "name:bul_x_preferred":[
        "\u041a\u0430\u043b\u0430\u043c\u0430\u0440\u0438\u044f"
    ],
    "name:ceb_x_preferred":[
        "Kalamari\u00e1"
    ],
    "name:deu_x_preferred":[
        "Kalamaria"
    ],
    "name:ell_x_preferred":[
        "\u039a\u03b1\u03bb\u03b1\u03bc\u03b1\u03c1\u03b9\u03ac"
    ],
    "name:eng_x_preferred":[
        "Kalamaria"
    ],
    "name:est_x_preferred":[
        "Kalamari\u00e1"
    ],
    "name:fas_x_preferred":[
        "\u06a9\u0627\u0644\u0627\u0645\u0627\u0631\u06cc\u0627"
    ],
    "name:fin_x_preferred":[
        "Kalamari\u00e1"
    ],
    "name:fra_x_preferred":[
        "Kalamaria"
    ],
    "name:hun_x_preferred":[
        "Kalamari\u00e1"
    ],
    "name:ita_x_preferred":[
        "Kalamaria"
    ],
    "name:kor_x_preferred":[
        "\uce7c\ub77c\ub9c8\ub9ac\uc544"
    ],
    "name:lit_x_preferred":[
        "Kalamarija"
    ],
    "name:mkd_x_preferred":[
        "\u041a\u0430\u043b\u0430\u043c\u0430\u0440\u0438\u0458\u0430"
    ],
    "name:nld_x_preferred":[
        "Kalamaria"
    ],
    "name:nno_x_preferred":[
        "Kalamari\u00e1"
    ],
    "name:pol_x_preferred":[
        "Kalamaria"
    ],
    "name:por_x_preferred":[
        "Calam\u00e1ria"
    ],
    "name:ron_x_preferred":[
        "Kalamaria"
    ],
    "name:rus_x_preferred":[
        "\u041a\u0430\u043b\u0430\u043c\u0430\u0440\u0438\u044f"
    ],
    "name:rus_x_variant":[
        "\u041a\u0430\u043b\u0430\u043c\u0430\u0440\u044c\u044f"
    ],
    "name:spa_x_preferred":[
        "Kalamari\u00e1"
    ],
    "name:srp_x_preferred":[
        "\u041a\u0430\u043b\u0430\u043c\u0430\u0440\u0438\u0458\u0430"
    ],
    "name:swe_x_preferred":[
        "Kalamaria"
    ],
    "name:tur_x_preferred":[
        "Kalamarya"
    ],
    "name:ukr_x_preferred":[
        "\u041a\u0430\u043b\u0430\u043c\u0430\u0440\u0456\u044f"
    ],
    "name:urd_x_preferred":[
        "\u06a9\u0627\u0644\u0627\u0645\u0627\u0631\u06cc\u0627"
    ],
    "name:vie_x_preferred":[
        "Kalamaria"
    ],
    "name:vol_x_preferred":[
        "Kalamaria"
    ],
    "name:zho_x_preferred":[
        "\u5361\u62c9\u9a6c\u91cc\u4e9a"
    ],
    "qs_pg:aaroncc":"GR",
    "qs_pg:gn_country":"GR",
    "qs_pg:gn_fcode":"PPLA3",
    "qs_pg:gn_pop":91617,
    "qs_pg:name":"Kalamaria",
    "qs_pg:name_adm0":"\u0395\u03bb\u03bb\u03ac\u03b4\u03b1",
    "qs_pg:name_adm1":"Macedonia and Thrace",
    "qs_pg:photos":22,
    "qs_pg:photos_1k":4,
    "qs_pg:photos_9k":3,
    "qs_pg:photos_9r":5,
    "qs_pg:photos_all":585,
    "qs_pg:photos_sr":1,
    "qs_pg:pop_sr":8,
    "qs_pg:qs_pg_placetype":"localadmin",
    "qs_pg:qs_pg_placetype_gp":"LocalAdmin",
    "qs_pg:woe_adm0":23424833,
    "woe:adm0_id":23424833,
    "woe:name_adm0":"\u0395\u03bb\u03bb\u03ac\u03b4\u03b1",
    "woe:name_adm1":"Macedonia and Thrace",
    "woe:placetype":"LocalAdmin",
    "wof:name":"Kalamaria",
    "wof:placetype":"localadmin",
    "wof:population":91617
},
  "geometry": {"coordinates":[22.95028,40.5825],"type":"Point"}
}