{
  "type": "Feature",
  "properties": {
    "gn:admin1_code":"ESYE24",
    "gn:admin2_code":"29.0",
    "gn:admin3_code":"9158",
    "gn:asciiname":"Bralos",
    "gn:country_code":"GR",
    "gn:dem":540,
    "gn:feature_class":"P",
    "gn:feature_code":"PPL",
    "gn:name":"Br\u00e1los",
    "gn:population":114,
    "gn:timezone":"Europe/Athens",
    "iso:country":"GR",
    "name:ceb_x_preferred":[
        "Br\u00e1los"
    ],
    "name:ell_x_preferred":[
        "\u039c\u03c0\u03c1\u03ac\u03bb\u03bf\u03c2"
    ],
    "name:ell_x_variant":[
        "\u039c\u03c0\u03c1\u03ac\u03bb\u03bf\u03c2 \u03a6\u03b8\u03b9\u03ce\u03c4\u03b9\u03b4\u03b1\u03c2"
    ],
    "name:eng_x_preferred":[
        "Bralos"
    ],
    "name:eng_x_variant":[
        "Mpralos"
    ],
    "name:fin_x_preferred":[
        "Br\u00e1los"
    ],
    "name:ron_x_preferred":[
        "Bralos"
    ],
    "name:swe_x_preferred":[
        "Br\u00e1los"
    ],
    "name:und_x_variant":[
        "K\u00e1to Br\u00e1llos",
        "Br\u00e1llos"
    ],
    "wof:name":"Bralos",
    "wof:placetype":"locality",
    "wof:population":114
},
  "geometry": {"coordinates":[22.46432,38.72652],"type":"Point"}
}