{
  "type": "Feature",
  "properties": {
    "gn:admin1_code":"ESYE24",
    "gn:admin2_code":"30.0",
    "gn:admin3_code":"9157",
    "gn:asciiname":"Pavlopoulon",
    "gn:country_code":"GR",
    "gn:dem":762,
    "gn:feature_class":"P",
    "gn:feature_code":"PPL",
    "gn:name":"Pavl\u00f3poulon",
    "gn:population":23,
    "gn:timezone":"Europe/Athens",
    "iso:country":"GR",
    "name:ell_x_preferred":[
        "\u03a0\u03b1\u03c5\u03bb\u03cc\u03c0\u03bf\u03c5\u03bb\u03bf"
    ],
    "name:eng_x_preferred":[
        "Pavlopoulo"
    ],
    "wof:name":"Pavlopoulon",
    "wof:placetype":"locality",
    "wof:population":23
},
  "geometry": {"coordinates":[21.72602,38.99614],"type":"Point"}
}