{
  "type": "Feature",
  "properties": {
    "gn:admin1_code":"ESYE25",
    "gn:admin2_code":"36.0",
    "gn:admin3_code":"9234.0",
    "gn:asciiname":"Galanaiika",
    "gn:country_code":"GR",
    "gn:dem":293,
    "gn:feature_class":"P",
    "gn:feature_code":"PPL",
    "gn:name":"Galana\u00edika",
    "gn:population":0,
    "gn:timezone":"Europe/Athens",
    "iso:country":"GR",
    "name:ell_x_preferred":[
        "Galana\u00edika"
    ],
    "name:ell_x_variant":[
        "\u0393\u03b1\u03bb\u03b1\u03bd\u03b1\u03af\u03b9\u03ba\u03b1"
    ],
    "wof:name":"Galanaiika",
    "wof:placetype":"locality"
},
  "geometry": {"coordinates":[23.15462,37.70654],"type":"Point"}
}