{
  "type": "Feature",
  "properties": {
    "gn:admin1_code":"ESYE24",
    "gn:admin2_code":"34.0",
    "gn:admin3_code":"9152",
    "gn:asciiname":"Fleves",
    "gn:country_code":"GR",
    "gn:dem":102,
    "gn:feature_class":"P",
    "gn:feature_code":"PPL",
    "gn:name":"Fl\u00e9ves",
    "gn:population":0,
    "gn:timezone":"Europe/Athens",
    "iso:country":"GR",
    "name:ell_x_preferred":[
        "\u03a6\u03bb\u03ad\u03b2\u03b5\u03c2"
    ],
    "name:und_x_variant":[
        "Fleva",
        "Fl\u00e9ves"
    ],
    "wof:name":"Fleves",
    "wof:placetype":"locality"
},
  "geometry": {"coordinates":[24.14731,38.45008],"type":"Point"}
}