{
  "type": "Feature",
  "properties": {
    "gn:admin1_code":"ESYE43",
    "gn:admin2_code":"46.0",
    "gn:admin3_code":"9311",
    "gn:asciiname":"Potamoi",
    "gn:country_code":"GR",
    "gn:dem":-1,
    "gn:feature_class":"P",
    "gn:feature_code":"PPL",
    "gn:name":"Pot\u00e1moi",
    "gn:population":405,
    "gn:timezone":"Europe/Athens",
    "iso:country":"GR",
    "name:ell_x_preferred":[
        "\u03a0\u03bf\u03c4\u03ac\u03bc\u03bf\u03b9"
    ],
    "name:ell_x_variant":[
        "\u03a0\u03bf\u03c4\u03b1\u03bc\u03bf\u03af"
    ],
    "name:eng_x_preferred":[
        "Potamoi"
    ],
    "name:und_x_variant":[
        "Pot\u00e1moi"
    ],
    "wof:name":"Potamoi",
    "wof:placetype":"locality",
    "wof:population":405
},
  "geometry": {"coordinates":[25.70652,35.01285],"type":"Point"}
}