{
  "type": "Feature",
  "properties": {
    "gn:admin1_code":"ESYE43",
    "gn:admin2_code":"46.0",
    "gn:admin3_code":"9311",
    "gn:asciiname":"Potamoi",
    "gn:country_code":"GR",
    "gn:dem":-1,
    "gn:feature_class":"P",
    "gn:feature_code":"PPL",
    "gn:name":"Pot\u00e1moi",
    "gn:population":405,
    "gn:timezone":"Europe/Athens",
    "iso:country":"GR",
    "name:ast_x_preferred":[
        "Oce\u00e1nidos"
    ],
    "name:bre_x_preferred":[
        "Potamoi"
    ],
    "name:cat_x_preferred":[
        "Oce\u00e0nit"
    ],
    "name:ell_x_preferred":[
        "\u03a0\u03bf\u03c4\u03ac\u03bc\u03bf\u03b9"
    ],
    "name:ell_x_variant":[
        "\u03a0\u03bf\u03c4\u03b1\u03bc\u03bf\u03af"
    ],
    "name:eng_x_preferred":[
        "Potamoi"
    ],
    "name:epo_x_preferred":[
        "Oceanido"
    ],
    "name:eus_x_preferred":[
        "Ozeanida"
    ],
    "name:fra_x_preferred":[
        "Dieu fleuve"
    ],
    "name:glg_x_preferred":[
        "Oce\u00e1nidas"
    ],
    "name:ind_x_preferred":[
        "Potamoi"
    ],
    "name:ita_x_preferred":[
        "Potamoi"
    ],
    "name:jpn_x_preferred":[
        "\u30dd\u30bf\u30e2\u30a4"
    ],
    "name:kor_x_preferred":[
        "\ud3ec\ud0c0\ubaa8\uc774"
    ],
    "name:lit_x_preferred":[
        "Potamai"
    ],
    "name:pol_x_preferred":[
        "Potamoi"
    ],
    "name:por_x_preferred":[
        "Potamoi"
    ],
    "name:spa_x_preferred":[
        "Oce\u00e1nidas"
    ],
    "name:und_x_variant":[
        "Pot\u00e1moi"
    ],
    "wof:name":"Potamoi",
    "wof:placetype":"locality",
    "wof:population":405
},
  "geometry": {"coordinates":[25.70652,35.01285],"type":"Point"}
}