{
  "type": "Feature",
  "properties": {
    "gn:population":2649,
    "iso:country":"GR",
    "name:ara_x_preferred":[
        "\u0644\u0627\u064a\u064a\u0646\u0627\u060c \u062b\u064a\u0633\u0627\u0644\u0648\u0646\u064a\u0643\u064a"
    ],
    "name:ara_x_variant":[
        "\u0644\u0627\u064a\u064a\u0646\u0627"
    ],
    "name:bul_x_preferred":[
        "\u041b\u044a\u0433\u0438\u043d\u043e\u0432\u043e"
    ],
    "name:ceb_x_preferred":[
        "Lagyn\u00e1"
    ],
    "name:ell_x_preferred":[
        "\u039b\u03b1\u03b3\u03c5\u03bd\u03ac"
    ],
    "name:eng_x_preferred":[
        "Lagyna"
    ],
    "name:mkd_x_preferred":[
        "\u041b\u0430\u0438\u043d\u0430"
    ],
    "name:nld_x_preferred":[
        "Lagyna"
    ],
    "name:nno_x_preferred":[
        "Lagyn\u00e1"
    ],
    "name:swe_x_preferred":[
        "Lagyn\u00e1"
    ],
    "name:und_x_variant":[
        "La\u00efn\u00e1"
    ],
    "qs:a0":"Greece",
    "qs:a1":"*\u039a\u0395\u039d\u03a4\u03a1\u0399\u039a\u0397 \u039c\u0391\u039a\u0395\u0394\u039f\u039d\u0399\u0391",
    "qs:a1_alt":"KENTRIKH MAKEDONIA",
    "qs:a1r":"0",
    "qs:a2_alt":"SERRES",
    "qs:adm0":"Greece",
    "qs:la_lc":"*",
    "qs:level":"locality",
    "qs:loc":"\u039b\u0391\u0393\u03a5\u039d\u0391",
    "qs:loc_alt":"LAGYNA",
    "qs:pop":0,
    "qs:type":"buffered point",
    "wof:name":"\u039b\u0391\u0393\u03a5\u039d\u0391",
    "wof:placetype":"locality",
    "wof:population":2649
},
  "geometry": {"coordinates":[23.010538,40.724133],"type":"Point"}
}