{
  "type": "Feature",
  "properties": {
    "gn:admin1_code":"ESYE25",
    "gn:admin2_code":"40.0",
    "gn:admin3_code":"9257",
    "gn:asciiname":"Vounaria",
    "gn:country_code":"GR",
    "gn:dem":98,
    "gn:feature_class":"P",
    "gn:feature_code":"PPL",
    "gn:name":"Voun\u00e1ria",
    "gn:population":0,
    "gn:timezone":"Europe/Athens",
    "iso:country":"GR",
    "name:eng_x_preferred":[
        "Vounaria"
    ],
    "wof:name":"Vounaria",
    "wof:placetype":"locality"
},
  "geometry": {"coordinates":[21.92609,36.8376],"type":"Point"}
}