{
  "type": "Feature",
  "properties": {
    "gn:admin1_code":"ESYE42",
    "gn:admin2_code":"49.0",
    "gn:admin3_code":"9283",
    "gn:asciiname":"Merichas",
    "gn:country_code":"GR",
    "gn:dem":6,
    "gn:feature_class":"P",
    "gn:feature_code":"PPL",
    "gn:name":"M\u00e9richas",
    "gn:population":0,
    "gn:timezone":"Europe/Athens",
    "iso:country":"GR",
    "name:ell_x_preferred":[
        "\u039c\u03ad\u03c1\u03b9\u03c7\u03b1\u03c2"
    ],
    "name:und_x_variant":[
        "Ammos M\u00e9ryion",
        "M\u00e9rikha",
        "M\u00e9rikhas",
        "M\u00e9richas"
    ],
    "wof:name":"Merichas",
    "wof:placetype":"locality"
},
  "geometry": {"coordinates":[24.39767,37.38715],"type":"Point"}
}