{
  "type": "Feature",
  "properties": {
    "gn:admin1_code":"ESYE11",
    "gn:admin2_code":"3.0",
    "gn:admin3_code":"9016",
    "gn:asciiname":"Paneri",
    "gn:country_code":"GR",
    "gn:dem":722,
    "gn:feature_class":"P",
    "gn:feature_code":"PPL",
    "gn:name":"Pan\u00e9ri",
    "gn:population":0,
    "gn:timezone":"Europe/Athens",
    "iso:country":"GR",
    "name:ell_x_preferred":[
        "Pan\u00e9ri"
    ],
    "name:ell_x_variant":[
        "\u03a0\u03b1\u03bd\u03ad\u03c1\u03b9",
        "Pan\u00e9rion",
        "\u03a0\u03b1\u03bd\u03ad\u03c1\u03b9\u03bf\u03bd"
    ],
    "wof:name":"Paneri",
    "wof:placetype":"locality"
},
  "geometry": {"coordinates":[24.91551,41.20161],"type":"Point"}
}