{
  "type": "Feature",
  "properties": {
    "gn:admin1_code":"ESYE24",
    "gn:admin2_code":"29.0",
    "gn:admin3_code":"9161",
    "gn:asciiname":"Palirroia",
    "gn:country_code":"GR",
    "gn:dem":0,
    "gn:feature_class":"P",
    "gn:feature_code":"PPL",
    "gn:name":"Pal\u00edrroia",
    "gn:population":36,
    "gn:timezone":"Europe/Athens",
    "iso:country":"GR",
    "name:ell_x_preferred":[
        "\u03a0\u03b1\u03bb\u03af\u03c1\u03c1\u03bf\u03b9\u03b1"
    ],
    "name:eng_x_preferred":[
        "Palirroia"
    ],
    "wof:name":"Palirroia",
    "wof:placetype":"locality",
    "wof:population":36
},
  "geometry": {"coordinates":[23.07474,38.66563],"type":"Point"}
}