{
  "type": "Feature",
  "properties": {
    "gn:population":1182,
    "iso:country":"GR",
    "name:ell_x_preferred":[
        "\u03a0\u03b1\u03bb\u03b1\u03b9\u03bf\u03bc\u03bf\u03bd\u03ac\u03c3\u03c4\u03b7\u03c1\u03bf\u03bd"
    ],
    "name:ell_x_variant":[
        "\u03a0\u03b1\u03bb\u03b1\u03b9\u03bf\u03bc\u03bf\u03bd\u03ac\u03c3\u03c4\u03b7\u03c1\u03bf"
    ],
    "name:und_x_variant":[
        "Bel\u00e9tsi"
    ],
    "qs:a0":"Greece",
    "qs:a1":"*\u0398\u0395\u03a3\u03a3\u0391\u039b\u0399\u0391",
    "qs:a1_alt":"UESSALIA",
    "qs:a1r":"0",
    "qs:a2_alt":"TRIKALA",
    "qs:adm0":"Greece",
    "qs:la_lc":"*",
    "qs:level":"locality",
    "qs:loc":"\u03a0\u0391\u039b\u0391\u0399\u039f\u039c\u039f\u039d\u0391\u03a3\u03a4\u0397\u03a1\u039f\u039d",
    "qs:loc_alt":"PALAIOMONASURON",
    "qs:pop":0,
    "qs:type":"buffered point",
    "wof:name":"\u03a0\u0391\u039b\u0391\u0399\u039f\u039c\u039f\u039d\u0391\u03a3\u03a4\u0397\u03a1\u039f\u039d",
    "wof:placetype":"locality",
    "wof:population":1182
},
  "geometry": {"coordinates":[21.656505,39.461513],"type":"Point"}
}