{
  "type": "Feature",
  "properties": {
    "gn:admin1_code":"ESYE21",
    "gn:admin2_code":"20.0",
    "gn:admin3_code":"9075",
    "gn:asciiname":"Plakidia",
    "gn:country_code":"GR",
    "gn:dem":378,
    "gn:feature_class":"P",
    "gn:feature_code":"PPL",
    "gn:name":"Plak\u00eddia",
    "gn:population":0,
    "gn:timezone":"Europe/Athens",
    "iso:country":"GR",
    "name:ell_x_preferred":[
        "Plak\u00eddia"
    ],
    "name:ell_x_variant":[
        "\u03a0\u03bb\u03b1\u03ba\u03af\u03b4\u03b9\u03b1"
    ],
    "wof:name":"Plakidia",
    "wof:placetype":"locality"
},
  "geometry": {"coordinates":[21.04108,39.28689],"type":"Point"}
}