{
  "type": "Feature",
  "properties": {
    "gn:admin1_code":"ESYE13",
    "gn:admin2_code":"11.0",
    "gn:admin3_code":"9067",
    "gn:asciiname":"Karyochori",
    "gn:country_code":"GR",
    "gn:dem":713,
    "gn:feature_class":"P",
    "gn:feature_code":"PPL",
    "gn:name":"Karyoch\u00f3ri",
    "gn:population":0,
    "gn:timezone":"Europe/Athens",
    "iso:country":"GR",
    "name:bul_x_preferred":[
        "\u041a\u043e\u0437\u043b\u0443\u043a\u044c\u043e\u0439"
    ],
    "name:ell_x_preferred":[
        "Karyoch\u00f3ri"
    ],
    "name:ell_x_variant":[
        "\u039a\u03b1\u03c1\u03c5\u03bf\u03c7\u03ce\u03c1\u03b9",
        "Karyoch\u00f3rion",
        "\u039a\u03b1\u03c1\u03c5\u03bf\u03c7\u03ce\u03c1\u03b9\u03bf\u03bd",
        "\u039a\u03b1\u03c1\u03c5\u03bf\u03c7\u03ce\u03c1\u03b9 \u039a\u03bf\u03b6\u03ac\u03bd\u03b7\u03c2"
    ],
    "name:mkd_x_preferred":[
        "\u041a\u043e\u0437\u043b\u0443\u045c\u043e\u0458"
    ],
    "name:und_x_variant":[
        "Kariokh\u00f3ri",
        "Kariokh\u00f3rion"
    ],
    "wof:name":"Karyochori",
    "wof:placetype":"locality"
},
  "geometry": {"coordinates":[21.7765,40.50265],"type":"Point"}
}