{
  "type": "Feature",
  "properties": {
    "gn:country":"GR",
    "gn:fcode":"PPL",
    "gn:population":1594,
    "iso:country":"GR",
    "name:ell_x_preferred":[
        "\u03a1\u03b9\u03b6\u03cc\u03bc\u03c5\u03bb\u03bf\u03c2"
    ],
    "name:eng_x_preferred":[
        "Rizomylos"
    ],
    "name:und_x_variant":[
        "Riz\u00f3milos"
    ],
    "qs_pg:aaroncc":"GR",
    "qs_pg:gn_country":"GR",
    "qs_pg:gn_fcode":"PPL",
    "qs_pg:gn_pop":1594,
    "qs_pg:name":"Rizomilos",
    "qs_pg:name_adm0":"\u0395\u03bb\u03bb\u03ac\u03b4\u03b1",
    "qs_pg:name_adm1":"Thessaly and Continental Greece",
    "qs_pg:photos_9k":1,
    "qs_pg:photos_9r":1,
    "qs_pg:photos_all":6,
    "qs_pg:photos_sr":0,
    "qs_pg:pop_sr":3,
    "qs_pg:qs_pg_placetype":"locality",
    "qs_pg:qs_pg_placetype_gp":"Town",
    "qs_pg:woe_adm0":23424833,
    "woe:adm0_id":23424833,
    "woe:name_adm0":"\u0395\u03bb\u03bb\u03ac\u03b4\u03b1",
    "woe:name_adm1":"Thessaly and Continental Greece",
    "woe:placetype":"Town",
    "wof:name":"Rizomilos",
    "wof:placetype":"locality",
    "wof:population":1482
},
  "geometry": {"coordinates":[22.75,39.43333],"type":"Point"}
}