{
  "type": "Feature",
  "properties": {
    "gn:admin1_code":"ESYE31",
    "gn:admin2_code":"445406.0",
    "gn:admin3_code":"9217",
    "gn:asciiname":"Rapentosa",
    "gn:country_code":"GR",
    "gn:dem":416,
    "gn:feature_class":"P",
    "gn:feature_code":"PPL",
    "gn:name":"Rapent\u00f3sa",
    "gn:population":106,
    "gn:timezone":"Europe/Athens",
    "iso:country":"GR",
    "name:ell_x_preferred":[
        "\u03a1\u03b1\u03c0\u03b5\u03bd\u03c4\u03ce\u03c3\u03b1"
    ],
    "name:eng_x_preferred":[
        "Rapentosa"
    ],
    "wof:name":"Rapentosa",
    "wof:placetype":"locality",
    "wof:population":106
},
  "geometry": {"coordinates":[23.90355,38.09313],"type":"Point"}
}