{
  "type": "Feature",
  "properties": {
    "gn:admin1_code":"ESYE14",
    "gn:admin2_code":"24.0",
    "gn:admin3_code":"9105",
    "gn:asciiname":"Glafyra",
    "gn:country_code":"GR",
    "gn:dem":360,
    "gn:feature_class":"P",
    "gn:feature_code":"PPL",
    "gn:name":"Glafyr\u00e1",
    "gn:population":0,
    "gn:timezone":"Europe/Athens",
    "iso:country":"GR",
    "name:ell_x_preferred":[
        "Glafyr\u00e1"
    ],
    "name:ell_x_variant":[
        "\u0393\u03bb\u03b1\u03c6\u03c5\u03c1\u03ac"
    ],
    "name:und_x_variant":[
        "K\u00e1pourna",
        "Glafira\u00ed",
        "Glafir\u00e1"
    ],
    "wof:name":"Glafyra",
    "wof:placetype":"locality"
},
  "geometry": {"coordinates":[22.88793,39.44021],"type":"Point"}
}