{
  "type": "Feature",
  "properties": {
    "gn:admin1_code":"ESYE12",
    "gn:admin2_code":"13.0",
    "gn:admin3_code":"9034",
    "gn:asciiname":"Vathoulo",
    "gn:country_code":"GR",
    "gn:dem":338,
    "gn:feature_class":"P",
    "gn:feature_code":"PPL",
    "gn:name":"Vathoul\u00f3",
    "gn:population":0,
    "gn:timezone":"Europe/Athens",
    "iso:country":"GR",
    "name:ell_x_preferred":[
        "\u0392\u03b1\u03b8\u03bf\u03c5\u03bb\u03cc"
    ],
    "name:und_x_variant":[
        "Kuchukch\u00ed",
        "Vathoul\u00f3"
    ],
    "wof:name":"Vathoulo",
    "wof:placetype":"locality"
},
  "geometry": {"coordinates":[23.11456,40.80519],"type":"Point"}
}