{
  "type": "Feature",
  "properties": {
    "gn:gn_country":"GR",
    "gn:gn_fcode":"PPL",
    "gn:gn_pop":0,
    "gn:population":138,
    "iso:country":"GR",
    "name:arm_x_preferred":[
        "\u0539\u0578\u056c\u0561\u0580\u056b\u0561"
    ],
    "name:dut_x_preferred":[
        "Tholaria"
    ],
    "name:ell_x_preferred":[
        "\u0398\u03bf\u03bb\u03ac\u03c1\u03b9\u03b1"
    ],
    "name:eng_x_preferred":[
        "Tholaria"
    ],
    "name:gre_x_preferred":[
        "\u0398\u03bf\u03bb\u03ac\u03c1\u03b9\u03b1 \u0391\u03bc\u03bf\u03c1\u03b3\u03bf\u03cd"
    ],
    "name:swe_x_preferred":[
        "Thol\u00e1ria"
    ],
    "name:unk_x_variant":[
        "Thol\u00e1ria"
    ],
    "qs_pg:aaroncc":"GR",
    "qs_pg:gn_country":"GR",
    "qs_pg:gn_fcode":"PPL",
    "qs_pg:gn_pop":0,
    "qs_pg:name":"Tholaria",
    "qs_pg:name_adm0":"\u0395\u03bb\u03bb\u03ac\u03b4\u03b1",
    "qs_pg:name_adm1":"Aegean",
    "qs_pg:photos":111,
    "qs_pg:photos_1k":22,
    "qs_pg:photos_9k":1,
    "qs_pg:photos_9r":3,
    "qs_pg:photos_all":111,
    "qs_pg:photos_sr":3,
    "qs_pg:pop_sr":0,
    "qs_pg:qs_pg_placetype":"locality",
    "qs_pg:qs_pg_placetype_gp":"Town",
    "qs_pg:woe_adm0":23424833,
    "woe:adm0_id":23424833,
    "woe:name_adm0":"\u0395\u03bb\u03bb\u03ac\u03b4\u03b1",
    "woe:name_adm1":"Aegean",
    "woe:placetype":"Town",
    "wof:name":"Tholaria",
    "wof:placetype":"locality",
    "wof:population":138
},
  "geometry": {"coordinates":[25.98333,36.91667],"type":"Point"}
}