{
  "type": "Feature",
  "properties": {
    "gn:admin1_code":"ESYE22",
    "gn:admin2_code":"27.0",
    "gn:admin3_code":"9120",
    "gn:asciiname":"Michata",
    "gn:country_code":"GR",
    "gn:dem":445,
    "gn:feature_class":"P",
    "gn:feature_code":"PPL",
    "gn:name":"Mich\u00e1ta",
    "gn:population":0,
    "gn:timezone":"Europe/Athens",
    "iso:country":"GR",
    "name:ell_x_preferred":[
        "Mich\u00e1ta"
    ],
    "name:ell_x_variant":[
        "\u039c\u03b9\u03c7\u03ac\u03c4\u03b1",
        "\u039c\u03b9\u03c7\u03ac\u03c4\u03b1 \u039a\u03b5\u03c6\u03b1\u03bb\u03bb\u03bf\u03bd\u03b9\u03ac\u03c2"
    ],
    "name:ron_x_preferred":[
        "Michata"
    ],
    "name:und_x_variant":[
        "Mikh\u00e1ta"
    ],
    "wof:name":"Michata",
    "wof:placetype":"locality"
},
  "geometry": {"coordinates":[20.59472,38.16506],"type":"Point"}
}