{
  "type": "Feature",
  "properties": {
    "gn:gn_country":"GR",
    "gn:gn_fcode":"ADM3",
    "gn:gn_pop":13032,
    "gn:population":13032,
    "iso:country":"GR",
    "name:ell_x_preferred":[
        "\u039f\u03c1\u03c7\u03bf\u03bc\u03b5\u03bd\u03bf\u03cd"
    ],
    "qs_pg:aaroncc":"GR",
    "qs_pg:gn_country":"GR",
    "qs_pg:gn_fcode":"ADM3",
    "qs_pg:gn_pop":13032,
    "qs_pg:name":"Dimos Orchomenos",
    "qs_pg:photos_9r":0,
    "qs_pg:photos_sr":0,
    "qs_pg:pop_sr":6,
    "qs_pg:qs_pg_placetype":"localadmin",
    "wof:name":"Dimos Orchomenos",
    "wof:placetype":"localadmin",
    "wof:population":13032
},
  "geometry": {"coordinates":[23.10392,38.49247],"type":"Point"}
}