{
  "type": "Feature",
  "properties": {
    "gn:admin1_code":"ESYE25",
    "gn:admin2_code":"42.0",
    "gn:admin3_code":"9251",
    "gn:asciiname":"Kalyves",
    "gn:country_code":"GR",
    "gn:dem":166,
    "gn:feature_class":"P",
    "gn:feature_code":"PPL",
    "gn:name":"Kalyves",
    "gn:population":3,
    "gn:timezone":"Europe/Athens",
    "iso:country":"GR",
    "name:ara_x_preferred":[
        "\u0643\u0627\u0644\u064a\u0641\u0633"
    ],
    "name:ceb_x_preferred":[
        "Kal\u00edvai"
    ],
    "name:deu_x_preferred":[
        "Kalyves"
    ],
    "name:ell_x_preferred":[
        "\u039a\u03b1\u03bb\u03cd\u03b2\u03b5\u03c2"
    ],
    "name:ell_x_variant":[
        "\u039a\u03b1\u03bb\u03cd\u03b2\u03b5\u03c2 \u03a7\u03b1\u03bd\u03af\u03c9\u03bd"
    ],
    "name:eng_x_preferred":[
        "Kalyves"
    ],
    "name:fin_x_preferred":[
        "Kal\u00fdves"
    ],
    "name:fra_x_preferred":[
        "Kalyv\u00e8s"
    ],
    "name:nld_x_preferred":[
        "Kalyves"
    ],
    "name:nno_x_preferred":[
        "Kal\u00fdves"
    ],
    "name:por_x_preferred":[
        "Kalives"
    ],
    "name:und_x_variant":[
        "Kalives"
    ],
    "wof:name":"Kalyves",
    "wof:placetype":"locality",
    "wof:population":3
},
  "geometry": {"coordinates":[22.99401,36.65081],"type":"Point"}
}