{
  "type": "Feature",
  "properties": {
    "gn:admin1_code":"ESYE25",
    "gn:admin2_code":"42.0",
    "gn:admin3_code":"9251",
    "gn:asciiname":"Kalyves",
    "gn:country_code":"GR",
    "gn:dem":166,
    "gn:feature_class":"P",
    "gn:feature_code":"PPL",
    "gn:name":"Kalyves",
    "gn:population":3,
    "gn:timezone":"Europe/Athens",
    "iso:country":"GR",
    "name:ell_x_preferred":[
        "\u039a\u03b1\u03bb\u03cd\u03b2\u03b5\u03c2"
    ],
    "name:eng_x_preferred":[
        "Kalyves"
    ],
    "name:und_x_variant":[
        "Kalives"
    ],
    "wof:name":"Kalyves",
    "wof:placetype":"locality",
    "wof:population":3
},
  "geometry": {"coordinates":[22.99401,36.65081],"type":"Point"}
}