{
  "type": "Feature",
  "properties": {
    "gn:admin1_code":"ESYE22",
    "gn:asciiname":"Megali Vigla",
    "gn:country_code":"GR",
    "gn:dem":208,
    "gn:feature_class":"P",
    "gn:feature_code":"PPL",
    "gn:name":"Meg\u00e1li V\u00edgla",
    "gn:population":0,
    "gn:timezone":"Europe/Athens",
    "iso:country":"GR",
    "name:ell_x_preferred":[
        "Meg\u00e1li V\u00edgla"
    ],
    "name:ell_x_variant":[
        "\u039c\u03b5\u03b3\u03ac\u03bb\u03b7 \u0392\u03af\u03b3\u03bb\u03b1"
    ],
    "wof:name":"Megali Vigla",
    "wof:placetype":"locality"
},
  "geometry": {"coordinates":[20.16196,39.20493],"type":"Point"}
}