{
  "type": "Feature",
  "properties": {
    "gn:admin1_code":"ESYE25",
    "gn:admin2_code":"42.0",
    "gn:admin3_code":"9252",
    "gn:asciiname":"Foundaiika",
    "gn:cc2":"GR",
    "gn:country_code":"GR",
    "gn:dem":524,
    "gn:feature_class":"P",
    "gn:feature_code":"PPL",
    "gn:name":"Founda\u00edika",
    "gn:population":0,
    "gn:timezone":"Europe/Athens",
    "iso:country":"GR",
    "name:ell_x_preferred":[
        "\u03a6\u03bf\u03c5\u03bd\u03c4\u03b1\u03af\u03b9\u03ba\u03b1"
    ],
    "name:ell_x_variant":[
        "\u03a6\u03bf\u03c5\u03bd\u03c4\u03b1\u0390\u03b9\u03ba\u03b1"
    ],
    "name:und_x_variant":[
        "Found\u00e9\u00efka",
        "Founda\u00edika"
    ],
    "wof:name":"Foundaiika",
    "wof:placetype":"locality"
},
  "geometry": {"coordinates":[22.27937,37.23231],"type":"Point"}
}