{
  "type": "Feature",
  "properties": {
    "gn:gn_country":"GR",
    "gn:gn_fcode":"PPL",
    "gn:gn_pop":122,
    "gn:population":49,
    "iso:country":"GR",
    "name:ell_x_preferred":[
        "\u03a0\u03b5\u03c4\u03c1\u03ac\u03bb\u03c9\u03bd\u03b1"
    ],
    "name:eng_x_preferred":[
        "Petralona"
    ],
    "name:unk_x_variant":[
        "Arakhov\u00edtsa"
    ],
    "qs_pg:aaroncc":"GR",
    "qs_pg:gn_country":"GR",
    "qs_pg:gn_fcode":"PPL",
    "qs_pg:gn_pop":122,
    "qs_pg:name":"Petralona",
    "qs_pg:name_adm0":"\u0395\u03bb\u03bb\u03ac\u03b4\u03b1",
    "qs_pg:name_adm1":"Thessaly and Continental Greece",
    "qs_pg:photos_9r":0,
    "qs_pg:photos_sr":0,
    "qs_pg:pop_sr":1,
    "qs_pg:qs_pg_placetype":"locality",
    "qs_pg:qs_pg_placetype_gp":"Town",
    "qs_pg:woe_adm0":23424833,
    "woe:adm0_id":23424833,
    "woe:name_adm0":"\u0395\u03bb\u03bb\u03ac\u03b4\u03b1",
    "woe:name_adm1":"Thessaly and Continental Greece",
    "woe:placetype":"Town",
    "wof:name":"Petralona",
    "wof:placetype":"locality",
    "wof:population":49
},
  "geometry": {"coordinates":[21.8175,39.01111],"type":"Point"}
}