{
  "type": "Feature",
  "properties": {
    "gn:gn_country":"GR",
    "gn:gn_fcode":"PPL",
    "gn:gn_pop":0,
    "iso:country":"GR",
    "name:unk_x_variant":[
        "Goni\u00e9s"
    ],
    "qs_pg:aaroncc":"GR",
    "qs_pg:gn_country":"GR",
    "qs_pg:gn_fcode":"PPL",
    "qs_pg:gn_pop":0,
    "qs_pg:name":"Goniai",
    "qs_pg:name_adm0":"\u0395\u03bb\u03bb\u03ac\u03b4\u03b1",
    "qs_pg:name_adm1":"Crete",
    "qs_pg:photos":51,
    "qs_pg:photos_1k":10,
    "qs_pg:photos_9k":1,
    "qs_pg:photos_9r":2,
    "qs_pg:photos_all":51,
    "qs_pg:photos_sr":2,
    "qs_pg:pop_sr":0,
    "qs_pg:qs_pg_placetype":"locality",
    "qs_pg:qs_pg_placetype_gp":"Town",
    "qs_pg:woe_adm0":23424833,
    "woe:adm0_id":23424833,
    "woe:name_adm0":"\u0395\u03bb\u03bb\u03ac\u03b4\u03b1",
    "woe:name_adm1":"Crete",
    "woe:placetype":"Town",
    "wof:name":"Goniai",
    "wof:placetype":"locality"
},
  "geometry": {"coordinates":[24.92821,35.29616],"type":"Point"}
}