{
  "type": "Feature",
  "properties": {
    "gn:gn_country":"GR",
    "gn:gn_fcode":"PPL",
    "gn:gn_pop":60,
    "gn:population":60,
    "iso:country":"GR",
    "name:ceb_x_preferred":[
        "Pigadia"
    ],
    "name:deu_x_preferred":[
        "Pigadia"
    ],
    "name:ell_x_preferred":[
        "\u03a0\u03b9\u03b3\u03ac\u03b4\u03b9\u03b1"
    ],
    "name:ell_x_variant":[
        "\u03a0\u03b7\u03b3\u03ac\u03b4\u03b9\u03b1"
    ],
    "name:lat_x_preferred":[
        "Pigadia"
    ],
    "name:unk_x_variant":[
        "Pig\u00e1dhia"
    ],
    "qs_pg:aaroncc":"GR",
    "qs_pg:gn_country":"GR",
    "qs_pg:gn_fcode":"PPL",
    "qs_pg:gn_pop":60,
    "qs_pg:name":"Pigadia",
    "qs_pg:name_adm0":"\u0395\u03bb\u03bb\u03ac\u03b4\u03b1",
    "qs_pg:name_adm1":"Peloponnese Western Greece and the Ionian Islands",
    "qs_pg:photos_9r":0,
    "qs_pg:photos_sr":0,
    "qs_pg:pop_sr":1,
    "qs_pg:qs_pg_placetype":"locality",
    "qs_pg:qs_pg_placetype_gp":"Town",
    "qs_pg:woe_adm0":23424833,
    "woe:adm0_id":23424833,
    "woe:name_adm0":"\u0395\u03bb\u03bb\u03ac\u03b4\u03b1",
    "woe:name_adm1":"Peloponnese Western Greece and the Ionian Islands",
    "woe:placetype":"Town",
    "wof:name":"Pigadia",
    "wof:placetype":"locality",
    "wof:population":60
},
  "geometry": {"coordinates":[21.39167,39.07806],"type":"Point"}
}