{
  "type": "Feature",
  "properties": {
    "gn:admin1_code":"ESYE22",
    "gn:admin2_code":"25.0",
    "gn:admin3_code":"9118",
    "gn:asciiname":"Agios Georgios Virou",
    "gn:country_code":"GR",
    "gn:dem":84,
    "gn:feature_class":"P",
    "gn:feature_code":"PPL",
    "gn:name":"Agios Ge\u00f3rgios Viro\u00fa",
    "gn:population":89,
    "gn:timezone":"Europe/Athens",
    "iso:country":"GR",
    "name:ell_x_preferred":[
        "\u0386\u03b3\u03b9\u03bf\u03c2 \u0393\u03b5\u03ce\u03c1\u03b3\u03b9\u03bf\u03c2 \u0392\u03b9\u03c1\u03bf\u03cd"
    ],
    "name:eng_x_preferred":[
        "Agios Georgios Virou"
    ],
    "name:und_x_variant":[
        "Agios Georgios Viros"
    ],
    "wof:name":"Agios Georgios Virou",
    "wof:placetype":"locality",
    "wof:population":89
},
  "geometry": {"coordinates":[19.87682,39.5899],"type":"Point"}
}