{
  "type": "Feature",
  "properties": {
    "gn:admin1_code":"ESYE25",
    "gn:admin2_code":"40.0",
    "gn:admin3_code":"9258",
    "gn:asciiname":"Agrilia",
    "gn:country_code":"GR",
    "gn:dem":283,
    "gn:feature_class":"P",
    "gn:feature_code":"PPL",
    "gn:name":"Agrili\u00e1",
    "gn:population":0,
    "gn:timezone":"Europe/Athens",
    "iso:country":"GR",
    "name:ell_x_preferred":[
        "Agrili\u00e1"
    ],
    "name:ell_x_variant":[
        "\u0391\u03b3\u03c1\u03b9\u03bb\u03b9\u03ac"
    ],
    "wof:name":"Agrilia",
    "wof:placetype":"locality"
},
  "geometry": {"coordinates":[21.8091,37.30756],"type":"Point"}
}