{
  "type": "Feature",
  "properties": {
    "gn:gn_country":"GR",
    "gn:gn_fcode":"PPL",
    "gn:gn_pop":0,
    "iso:country":"GR",
    "name:ell_x_preferred":[
        "\u0386\u03b3\u03b9\u03bf\u03c2 \u0399\u03c9\u03ac\u03bd\u03bd\u03b7\u03c2"
    ],
    "name:eng_x_preferred":[
        "Agios Ioannis"
    ],
    "name:gre_x_preferred":[
        "\u0386\u03b3\u03b9\u03bf\u03c2 \u0399\u03c9\u03ac\u03bd\u03bd\u03b7\u03c2 \u0391\u03b3\u03af\u03bf\u03c5 \u0394\u03b7\u03bc\u03b7\u03c4\u03c1\u03af\u03bf\u03c5  \u039c\u03b1\u03b3\u03bd\u03b7\u03c3\u03af\u03b1\u03c2"
    ],
    "qs_pg:aaroncc":"GR",
    "qs_pg:gn_country":"GR",
    "qs_pg:gn_fcode":"PPL",
    "qs_pg:gn_pop":0,
    "qs_pg:name":"Agios Ioanis",
    "qs_pg:name_adm0":"\u0395\u03bb\u03bb\u03ac\u03b4\u03b1",
    "qs_pg:name_adm1":"Thessaly and Continental Greece",
    "qs_pg:photos":245,
    "qs_pg:photos_1k":50,
    "qs_pg:photos_9k":1,
    "qs_pg:photos_9r":4,
    "qs_pg:photos_all":245,
    "qs_pg:photos_sr":4,
    "qs_pg:pop_sr":0,
    "qs_pg:qs_pg_placetype":"locality",
    "qs_pg:qs_pg_placetype_gp":"Town",
    "qs_pg:woe_adm0":23424833,
    "woe:adm0_id":23424833,
    "woe:name_adm0":"\u0395\u03bb\u03bb\u03ac\u03b4\u03b1",
    "woe:name_adm1":"Thessaly and Continental Greece",
    "woe:placetype":"Town",
    "wof:name":"Agios Ioanis",
    "wof:placetype":"locality"
},
  "geometry": {"coordinates":[23.16407,39.41531],"type":"Point"}
}