{
  "type": "Feature",
  "properties": {
    "gn:gn_country":"GR",
    "gn:gn_fcode":"ADM3",
    "gn:gn_pop":307,
    "gn:population":307,
    "iso:country":"GR",
    "name:ell_x_preferred":[
        "\u0391\u03b3\u03af\u03bf\u03c5 \u0395\u03c5\u03c3\u03c4\u03c1\u03b1\u03c4\u03af\u03bf\u03c5"
    ],
    "name:ell_x_variant":[
        "\u0386\u03b3\u03b9\u03bf\u03c2 \u0395\u03c5\u03c3\u03c4\u03c1\u03ac\u03c4\u03b9\u03bf\u03c2"
    ],
    "qs_pg:aaroncc":"GR",
    "qs_pg:gn_country":"GR",
    "qs_pg:gn_fcode":"ADM3",
    "qs_pg:gn_pop":307,
    "qs_pg:name":"Dimos Agios Efstratios",
    "qs_pg:photos_9r":0,
    "qs_pg:photos_sr":0,
    "qs_pg:pop_sr":2,
    "qs_pg:qs_pg_placetype":"localadmin",
    "wof:name":"Dimos Agios Efstratios",
    "wof:placetype":"localadmin",
    "wof:population":307
},
  "geometry": {"coordinates":[25.0065,39.51762],"type":"Point"}
}