{
  "type": "Feature",
  "properties": {
    "gn:admin1_code":"ESYE43",
    "gn:admin2_code":"43.0",
    "gn:admin3_code":"9323",
    "gn:asciiname":"Ano Psathogiannos",
    "gn:country_code":"GR",
    "gn:dem":180,
    "gn:feature_class":"P",
    "gn:feature_code":"PPL",
    "gn:name":"\u00c1no Psathogi\u00e1nnos",
    "gn:population":0,
    "gn:timezone":"Europe/Athens",
    "iso:country":"GR",
    "name:ell_x_preferred":[
        "\u00c1no Psathogi\u00e1nnos"
    ],
    "name:und_x_variant":[
        "\u0386\u03bd\u03c9 \u03a8\u03b1\u03b8\u03bf\u03b3\u03b9\u03ac\u03bd\u03bd\u03bf\u03c2"
    ],
    "wof:name":"Ano Psathogiannos",
    "wof:placetype":"locality"
},
  "geometry": {"coordinates":[23.86667000000001,35.47517],"type":"Point"}
}