{
  "type": "Feature",
  "properties": {
    "gn:admin1_code":"ESYE12",
    "gn:admin2_code":"13.0",
    "gn:admin3_code":"9039",
    "gn:asciiname":"Galini",
    "gn:country_code":"GR",
    "gn:dem":179,
    "gn:feature_class":"P",
    "gn:feature_code":"PPL",
    "gn:name":"Gal\u00edni",
    "gn:population":0,
    "gn:timezone":"Europe/Athens",
    "iso:country":"GR",
    "name:ceb_x_preferred":[
        "Galini"
    ],
    "name:ell_x_preferred":[
        "\u0393\u03b1\u03bb\u03ae\u03bd\u03b7"
    ],
    "name:mkd_x_preferred":[
        "\u041a\u0443\u0447\u043a\u0430\u0440"
    ],
    "name:swe_x_preferred":[
        "Galini"
    ],
    "name:und_x_variant":[
        "Gal\u00edni"
    ],
    "wof:name":"Galini",
    "wof:placetype":"locality"
},
  "geometry": {"coordinates":[22.92831,40.7124],"type":"Point"}
}