{
  "type": "Feature",
  "properties": {
    "gn:admin1_code":"ESYE42",
    "gn:admin2_code":"49.0",
    "gn:admin3_code":"9287",
    "gn:asciiname":"Empourios",
    "gn:country_code":"GR",
    "gn:dem":4,
    "gn:feature_class":"P",
    "gn:feature_code":"PPL",
    "gn:name":"Empour\u00edos",
    "gn:population":16,
    "gn:timezone":"Europe/Athens",
    "iso:country":"GR",
    "name:ell_x_preferred":[
        "\u0395\u03bc\u03c0\u03bf\u03c5\u03c1\u03b5\u03b9\u03cc\u03c2"
    ],
    "name:eng_x_preferred":[
        "Empourios"
    ],
    "name:und_x_variant":[
        "Empoureios"
    ],
    "wof:name":"Empourios",
    "wof:placetype":"locality",
    "wof:population":16
},
  "geometry": {"coordinates":[24.39206,36.70971],"type":"Point"}
}