{
  "type": "Feature",
  "properties": {
    "gn:admin1_code":"ESYE42",
    "gn:admin2_code":"49.0",
    "gn:admin3_code":"9300",
    "gn:asciiname":"Chrousa",
    "gn:country_code":"GR",
    "gn:dem":114,
    "gn:feature_class":"P",
    "gn:feature_code":"PPL",
    "gn:name":"Chro\u00fasa",
    "gn:population":0,
    "gn:timezone":"Europe/Athens",
    "iso:country":"GR",
    "name:ell_x_preferred":[
        "Chro\u00fasa"
    ],
    "name:ell_x_variant":[
        "\u03a7\u03c1\u03bf\u03cd\u03c3\u03b1"
    ],
    "name:und_x_variant":[
        "Khro\u00fasa"
    ],
    "wof:name":"Chrousa",
    "wof:placetype":"locality"
},
  "geometry": {"coordinates":[24.92477,37.39739],"type":"Point"}
}