{
  "type": "Feature",
  "properties": {
    "gn:admin1_code":"ESYE24",
    "gn:admin2_code":"34.0",
    "gn:admin3_code":"9148",
    "gn:asciiname":"Platania",
    "gn:country_code":"GR",
    "gn:dem":413,
    "gn:feature_class":"P",
    "gn:feature_code":"PPL",
    "gn:name":"Plat\u00e1nia",
    "gn:population":0,
    "gn:timezone":"Europe/Athens",
    "iso:country":"GR",
    "wof:name":"Platania",
    "wof:placetype":"locality"
},
  "geometry": {"coordinates":[23.69746,38.62051],"type":"Point"}
}