{
  "type": "Feature",
  "properties": {
    "gn:admin1_code":"ESYE24",
    "gn:admin2_code":"34.0",
    "gn:admin3_code":"9148",
    "gn:asciiname":"Makrimalli",
    "gn:country_code":"GR",
    "gn:dem":167,
    "gn:feature_class":"P",
    "gn:feature_code":"PPL",
    "gn:name":"Makrim\u00e1lli",
    "gn:population":0,
    "gn:timezone":"Europe/Athens",
    "iso:country":"GR",
    "wof:name":"Makrimalli",
    "wof:placetype":"locality"
},
  "geometry": {"coordinates":[23.66483,38.60238],"type":"Point"}
}