{
  "type": "Feature",
  "properties": {
    "gn:admin1_code":"ESYE14",
    "gn:admin2_code":"22.0",
    "gn:admin3_code":"9113",
    "gn:asciiname":"Vlataneoi",
    "gn:country_code":"GR",
    "gn:dem":1117,
    "gn:feature_class":"P",
    "gn:feature_code":"PPL",
    "gn:name":"Vlatan\u00e9oi",
    "gn:population":0,
    "gn:timezone":"Europe/Athens",
    "iso:country":"GR",
    "name:ell_x_preferred":[
        "Vlatan\u00e9oi"
    ],
    "name:ell_x_variant":[
        "\u0392\u03bb\u03b1\u03c4\u03b1\u03bd\u03ad\u03bf\u03b9"
    ],
    "wof:name":"Vlataneoi",
    "wof:placetype":"locality"
},
  "geometry": {"coordinates":[21.52072,39.52492],"type":"Point"}
}