{
  "type": "Feature",
  "properties": {
    "gn:country":"GR",
    "gn:fcode":"PPL",
    "gn:population":678,
    "iso:country":"GR",
    "name:arz_x_preferred":[
        "\u0643\u0627\u062a\u0648 \u0627\u062c\u064a\u0648\u0633 \u0627\u0648\u0627\u0646\u064a\u0633"
    ],
    "name:bul_x_preferred":[
        "\u041a\u0430\u0442\u043e \u0410\u0433\u0438\u043e\u0441 \u0419\u043e\u0430\u043d\u0438\u0441"
    ],
    "name:ceb_x_preferred":[
        "K\u00e1to \u00c1gios Io\u00e1nnis"
    ],
    "name:ell_x_preferred":[
        "\u039a\u03ac\u03c4\u03c9 \u0386\u03b3\u03b9\u03bf\u03c2 \u0399\u03c9\u03ac\u03bd\u03bd\u03b7\u03c2"
    ],
    "name:ell_x_variant":[
        "\u039a\u03ac\u03c4\u03c9 \u0386\u03b3\u03b9\u03bf\u03c2 \u0399\u03c9\u03ac\u03bd\u03bd\u03b7\u03c2 \u03a0\u03b9\u03b5\u03c1\u03af\u03b1\u03c2"
    ],
    "name:eng_x_preferred":[
        "Kato Agios Ioannis"
    ],
    "name:fra_x_preferred":[
        "K\u00e1to \u00c1gios Io\u00e1nnis"
    ],
    "name:mkd_x_preferred":[
        "\u0414\u043e\u043b\u043d\u043e \u0418\u0432\u0430\u043d\u043e\u0432\u043e"
    ],
    "name:nld_x_preferred":[
        "Kato Agios Ioannis"
    ],
    "name:swe_x_preferred":[
        "K\u00e1to \u00c1gios Io\u00e1nnis"
    ],
    "name:und_x_variant":[
        "Agios Ioanis Gigenon"
    ],
    "qs_pg:aaroncc":"GR",
    "qs_pg:gn_country":"GR",
    "qs_pg:gn_fcode":"PPL",
    "qs_pg:gn_pop":678,
    "qs_pg:name":"Kato Ag. Ioannis",
    "qs_pg:name_adm0":"\u0395\u03bb\u03bb\u03ac\u03b4\u03b1",
    "qs_pg:name_adm1":"Macedonia and Thrace",
    "qs_pg:photos_9r":0,
    "qs_pg:photos_sr":0,
    "qs_pg:pop_sr":2,
    "qs_pg:qs_pg_placetype":"locality",
    "qs_pg:qs_pg_placetype_gp":"Town",
    "qs_pg:woe_adm0":23424833,
    "woe:adm0_id":23424833,
    "woe:name_adm0":"\u0395\u03bb\u03bb\u03ac\u03b4\u03b1",
    "woe:name_adm1":"Macedonia and Thrace",
    "woe:placetype":"Town",
    "wof:name":"Kato Ag. Ioannis",
    "wof:placetype":"locality",
    "wof:population":678
},
  "geometry": {"coordinates":[22.52583,40.32639],"type":"Point"}
}