{
  "type": "Feature",
  "properties": {
    "gn:admin1_code":"ESYE23",
    "gn:admin2_code":"31.0",
    "gn:admin3_code":"9123",
    "gn:asciiname":"Ayia Varvara Paravolas",
    "gn:country_code":"GR",
    "gn:dem":122,
    "gn:feature_class":"P",
    "gn:feature_code":"PPL",
    "gn:name":"Ay\u00eda Varv\u00e1ra Parav\u00f3las",
    "gn:population":46,
    "gn:timezone":"Europe/Athens",
    "iso:country":"GR",
    "name:ell_x_preferred":[
        "\u0391\u03b3\u03af\u03b1 \u0392\u03b1\u03c1\u03b2\u03ac\u03c1\u03b1 \u03a0\u03b1\u03c1\u03b1\u03b2\u03cc\u03bb\u03b1\u03c2"
    ],
    "name:eng_x_preferred":[
        "Agia Varvara Paravolas"
    ],
    "wof:name":"Ayia Varvara Paravolas",
    "wof:placetype":"locality",
    "wof:population":46
},
  "geometry": {"coordinates":[21.50396,38.62163],"type":"Point"}
}