{
  "type": "Feature",
  "properties": {
    "gn:admin1_code":"ESYE42",
    "gn:admin2_code":"47.0",
    "gn:admin3_code":"9296",
    "gn:asciiname":"Charami",
    "gn:country_code":"GR",
    "gn:dem":5,
    "gn:feature_class":"P",
    "gn:feature_code":"PPL",
    "gn:name":"Char\u00e1mi",
    "gn:population":0,
    "gn:timezone":"Europe/Athens",
    "iso:country":"GR",
    "name:ell_x_preferred":[
        "Char\u00e1mion"
    ],
    "name:ell_x_variant":[
        "\u03a7\u03b1\u03c1\u03ac\u03bc\u03b9\u03bf\u03bd",
        "Char\u00e1mi",
        "\u03a7\u03b1\u03c1\u03ac\u03bc\u03b9"
    ],
    "wof:name":"Charami",
    "wof:placetype":"locality"
},
  "geometry": {"coordinates":[28.0937,36.16655],"type":"Point"}
}