{
  "type": "Feature",
  "properties": {
    "gn:admin1_code":"ESYE12",
    "gn:admin2_code":"6.0",
    "gn:admin3_code":"9040",
    "gn:asciiname":"Kokkinia",
    "gn:country_code":"GR",
    "gn:dem":298,
    "gn:feature_class":"P",
    "gn:feature_code":"PPL",
    "gn:name":"Kokkini\u00e1",
    "gn:population":0,
    "gn:timezone":"Europe/Athens",
    "iso:country":"GR",
    "name:bul_x_preferred":[
        "\u041a\u043e\u043a\u0438\u043d\u0438\u044f"
    ],
    "name:ell_x_preferred":[
        "\u039a\u03bf\u03ba\u03ba\u03b9\u03bd\u03b9\u03ac"
    ],
    "name:und_x_variant":[
        "K\u00fasovon",
        "Kokkini\u00e1"
    ],
    "wof:name":"Kokkinia",
    "wof:placetype":"locality"
},
  "geometry": {"coordinates":[23.00881,41.0737],"type":"Point"}
}