{
  "type": "Feature",
  "properties": {
    "gn:country":"GR",
    "gn:fcode":"ADM3",
    "gn:population":8987,
    "iso:country":"GR",
    "name:ell_x_preferred":[
        "\u03a0\u03c9\u03b3\u03c9\u03bd\u03af\u03bf\u03c5"
    ],
    "qs_pg:aaroncc":"GR",
    "qs_pg:gn_country":"GR",
    "qs_pg:gn_fcode":"ADM3",
    "qs_pg:gn_pop":8987,
    "qs_pg:name":"Dimos Pogoni",
    "qs_pg:photos_9r":0,
    "qs_pg:photos_sr":0,
    "qs_pg:pop_sr":5,
    "qs_pg:qs_pg_placetype":"localadmin",
    "wof:name":"Dimos Pogoni",
    "wof:placetype":"localadmin",
    "wof:population":8987
},
  "geometry": {"coordinates":[20.50857,39.91976],"type":"Point"}
}