{
  "type": "Feature",
  "properties": {
    "gn:admin1_code":"ESYE23",
    "gn:admin2_code":"38.0",
    "gn:admin3_code":"9134",
    "gn:asciiname":"Latsaiika",
    "gn:country_code":"GR",
    "gn:dem":765,
    "gn:feature_class":"P",
    "gn:feature_code":"PPL",
    "gn:name":"Latsa\u00edika",
    "gn:population":0,
    "gn:timezone":"Europe/Athens",
    "iso:country":"GR",
    "name:ell_x_preferred":[
        "\u039b\u03b1\u03c4\u03c3\u03b1\u03af\u03b9\u03ba\u03b1"
    ],
    "name:und_x_variant":[
        "Lasta\u00edika",
        "Lats\u00e9\u00efka",
        "Latsa\u00edika"
    ],
    "wof:name":"Latsaiika",
    "wof:placetype":"locality"
},
  "geometry": {"coordinates":[21.83847,38.15083],"type":"Point"}
}