{
  "type": "Feature",
  "properties": {
    "gn:admin1_code":"ESYE25",
    "gn:admin2_code":"40.0",
    "gn:admin3_code":"9256",
    "gn:asciiname":"Stenyklaros",
    "gn:country_code":"GR",
    "gn:dem":86,
    "gn:feature_class":"P",
    "gn:feature_code":"PPL",
    "gn:name":"Sten\u00fdklaros",
    "gn:population":0,
    "gn:timezone":"Europe/Athens",
    "iso:country":"GR",
    "name:ell_x_preferred":[
        "Sten\u00fdklaros"
    ],
    "name:ell_x_variant":[
        "\u03a3\u03c4\u03b5\u03bd\u03cd\u03ba\u03bb\u03b1\u03c1\u03bf\u03c2"
    ],
    "name:und_x_variant":[
        "Sten\u00edklaros"
    ],
    "wof:name":"Stenyklaros",
    "wof:placetype":"locality"
},
  "geometry": {"coordinates":[21.9446,37.24006],"type":"Point"}
}