{
  "type": "Feature",
  "properties": {
    "gn:admin1_code":"ESYE14",
    "gn:admin2_code":"21.0",
    "gn:admin3_code":"9100",
    "gn:asciiname":"Kalivia",
    "gn:country_code":"GR",
    "gn:dem":74,
    "gn:feature_class":"P",
    "gn:feature_code":"PPL",
    "gn:name":"Kal\u00edvia",
    "gn:population":0,
    "gn:timezone":"Europe/Athens",
    "iso:country":"GR",
    "wof:name":"Kalivia",
    "wof:placetype":"locality"
},
  "geometry": {"coordinates":[22.43333,39.65],"type":"Point"}
}