{
  "type": "Feature",
  "properties": {
    "gn:admin1_code":"ESYE25",
    "gn:admin2_code":"40.0",
    "gn:admin3_code":"9255",
    "gn:asciiname":"Trypes",
    "gn:country_code":"GR",
    "gn:dem":616,
    "gn:feature_class":"P",
    "gn:feature_code":"PPL",
    "gn:name":"Tr\u00fdpes",
    "gn:population":0,
    "gn:timezone":"Europe/Athens",
    "iso:country":"GR",
    "name:ell_x_preferred":[
        "Tr\u00fdpes"
    ],
    "name:ell_x_variant":[
        "\u03a4\u03c1\u03cd\u03c0\u03b5\u03c2",
        "Tr\u00fdpai",
        "\u03a4\u03c1\u03cd\u03c0\u03b1\u03b9"
    ],
    "name:und_x_variant":[
        "Tr\u00edpes",
        "Tr\u00edpai"
    ],
    "wof:name":"Trypes",
    "wof:placetype":"locality"
},
  "geometry": {"coordinates":[21.86898,36.94297],"type":"Point"}
}