{
  "type": "Feature",
  "properties": {
    "gn:gn_country":"GR",
    "gn:gn_fcode":"PPL",
    "gn:gn_pop":718,
    "gn:population":718,
    "iso:country":"GR",
    "name:ell_x_preferred":[
        "\u03a3\u03b5\u03bb\u03bb\u03ac\u03b4\u03b5\u03c2"
    ],
    "name:ell_x_variant":[
        "\u03a3\u03b5\u03bb\u03bb\u03ac\u03b4\u03b5\u03c2 \u0386\u03c1\u03c4\u03b1\u03c2"
    ],
    "name:eng_x_preferred":[
        "Sellades"
    ],
    "name:nld_x_preferred":[
        "Sellades"
    ],
    "name:ron_x_preferred":[
        "Sellades"
    ],
    "name:swe_x_preferred":[
        "Sell\u00e1des"
    ],
    "name:unk_x_variant":[
        "Sell\u00e1dhes"
    ],
    "qs_pg:aaroncc":"GR",
    "qs_pg:gn_country":"GR",
    "qs_pg:gn_fcode":"PPL",
    "qs_pg:gn_pop":718,
    "qs_pg:name":"Sell\u00e1des",
    "qs_pg:photos_9r":0,
    "qs_pg:photos_sr":0,
    "qs_pg:pop_sr":2,
    "qs_pg:qs_pg_placetype":"locality",
    "wof:name":"Sell\u00e1des",
    "wof:placetype":"locality",
    "wof:population":718
},
  "geometry": {"coordinates":[21.0775,39.10889],"type":"Point"}
}