{
  "type": "Feature",
  "properties": {
    "gn:admin1_code":"ESYE25",
    "gn:admin2_code":"41.0",
    "gn:admin3_code":"9241",
    "gn:asciiname":"Levidion",
    "gn:country_code":"GR",
    "gn:dem":857,
    "gn:feature_class":"P",
    "gn:feature_code":"PPL",
    "gn:name":"Lev\u00eddion",
    "gn:population":1025,
    "gn:timezone":"Europe/Athens",
    "iso:country":"GR",
    "name:ell_x_preferred":[
        "\u039b\u03b5\u03b2\u03af\u03b4\u03b9"
    ],
    "name:eng_x_preferred":[
        "Levidi"
    ],
    "name:und_x_variant":[
        "Levidi",
        "Lev\u00eddhi",
        "Lev\u00eddhion"
    ],
    "wof:name":"Levidion",
    "wof:placetype":"locality",
    "wof:population":1025
},
  "geometry": {"coordinates":[22.29586,37.68269],"type":"Point"}
}