{
  "type": "Feature",
  "properties": {
    "gn:admin1_code":"ESYE14",
    "gn:admin2_code":"24.0",
    "gn:admin3_code":"9107",
    "gn:asciiname":"Koutsilochori",
    "gn:country_code":"GR",
    "gn:dem":245,
    "gn:feature_class":"P",
    "gn:feature_code":"PPL",
    "gn:name":"Koutsiloch\u00f3ri",
    "gn:population":0,
    "gn:timezone":"Europe/Athens",
    "iso:country":"GR",
    "name:ell_x_preferred":[
        "Koutsiloch\u00f3ri"
    ],
    "name:ell_x_variant":[
        "\u039a\u03bf\u03c5\u03c4\u03c3\u03b9\u03bb\u03bf\u03c7\u03ce\u03c1\u03b9"
    ],
    "name:und_x_variant":[
        "Katsilokh\u00f3ri"
    ],
    "wof:name":"Koutsilochori",
    "wof:placetype":"locality"
},
  "geometry": {"coordinates":[23.22372,39.23686],"type":"Point"}
}