{
  "type": "Feature",
  "properties": {
    "gn:admin1_code":"ESYE41",
    "gn:admin2_code":"51.0",
    "gn:admin3_code":"9261",
    "gn:asciiname":"Yerania",
    "gn:country_code":"GR",
    "gn:dem":13,
    "gn:feature_class":"P",
    "gn:feature_code":"PPL",
    "gn:name":"Yer\u00e1nia",
    "gn:population":10,
    "gn:timezone":"Europe/Athens",
    "iso:country":"GR",
    "name:ell_x_preferred":[
        "\u0393\u03b5\u03c1\u03ac\u03bd\u03b9\u03b1"
    ],
    "name:und_x_variant":[
        "Y\u00e9ra"
    ],
    "wof:name":"Yerania",
    "wof:placetype":"locality",
    "wof:population":10
},
  "geometry": {"coordinates":[26.43594,39.09783],"type":"Point"}
}