{
  "type": "Feature",
  "properties": {
    "gn:admin1_code":"ESYE14",
    "gn:admin2_code":"24.0",
    "gn:admin3_code":"9109",
    "gn:asciiname":"Isomata",
    "gn:country_code":"GR",
    "gn:dem":157,
    "gn:feature_class":"P",
    "gn:feature_code":"PPL",
    "gn:name":"Is\u00f3mata",
    "gn:population":49,
    "gn:timezone":"Europe/Athens",
    "iso:country":"GR",
    "name:ell_x_preferred":[
        "\u0399\u03c3\u03ce\u03bc\u03b1\u03c4\u03b1"
    ],
    "name:ell_x_variant":[
        "\u0399\u03c3\u03b9\u03ce\u03bc\u03b1\u03c4\u03b1"
    ],
    "name:eng_x_preferred":[
        "Isomata"
    ],
    "name:eng_x_variant":[
        "Isiomata"
    ],
    "wof:name":"Isomata",
    "wof:placetype":"locality",
    "wof:population":49
},
  "geometry": {"coordinates":[23.90719,39.183],"type":"Point"}
}