{
  "type": "Feature",
  "properties": {
    "gn:admin1_code":"ESYE13",
    "gn:admin2_code":"8.0",
    "gn:admin3_code":"9072",
    "gn:asciiname":"Tropaiouchos",
    "gn:country_code":"GR",
    "gn:dem":688,
    "gn:feature_class":"P",
    "gn:feature_code":"PPL",
    "gn:name":"Tropaio\u00fachos",
    "gn:population":323,
    "gn:timezone":"Europe/Athens",
    "iso:country":"GR",
    "name:ell_x_historical":[
        "\u039c\u03b1\u03c7\u03b1\u03bb\u03ac\u03c2"
    ],
    "name:ell_x_preferred":[
        "\u03a4\u03c1\u03bf\u03c0\u03b1\u03b9\u03bf\u03cd\u03c7\u03bf\u03c2"
    ],
    "name:ell_x_variant":[
        "\u039c\u03b1\u03c7\u03b1\u03bb\u03ac\u03c2"
    ],
    "name:eng_x_preferred":[
        "Tropaiouchos"
    ],
    "name:und_x_variant":[
        "Mahal\u00e1s",
        "Tropaio\u00fakhos",
        "Tropaio\u00fachos"
    ],
    "wof:name":"Tropaiouchos",
    "wof:placetype":"locality",
    "wof:population":323
},
  "geometry": {"coordinates":[21.44126,40.74046],"type":"Point"}
}