{
  "type": "Feature",
  "properties": {
    "gn:admin1_code":"ESYE13",
    "gn:admin2_code":"11.0",
    "gn:admin3_code":"9066",
    "gn:asciiname":"Glykokerasia",
    "gn:country_code":"GR",
    "gn:dem":789,
    "gn:feature_class":"P",
    "gn:feature_code":"PPL",
    "gn:name":"Glykokerasi\u00e1",
    "gn:population":0,
    "gn:timezone":"Europe/Athens",
    "iso:country":"GR",
    "name:ell_x_preferred":[
        "Glykokerasi\u00e1"
    ],
    "name:ell_x_variant":[
        "\u0393\u03bb\u03c5\u03ba\u03bf\u03ba\u03b5\u03c1\u03b1\u03c3\u03b9\u03ac"
    ],
    "name:und_x_variant":[
        "Glikokerasi\u00e1",
        "Glikokeras\u00e9a"
    ],
    "wof:name":"Glykokerasia",
    "wof:placetype":"locality"
},
  "geometry": {"coordinates":[21.27501,40.25816],"type":"Point"}
}