{
  "type": "Feature",
  "properties": {
    "gn:gn_country":"GR",
    "gn:gn_fcode":"PPL",
    "gn:gn_pop":42,
    "gn:population":42,
    "iso:country":"GR",
    "name:bul_x_preferred":[
        "\u041b\u0438\u043c\u0438\u043d \u041b\u0438\u0442\u043e\u0445\u043e\u0440\u0443"
    ],
    "name:ell_x_preferred":[
        "\u03a3\u03ba\u03ac\u03bb\u03b1 \u039b\u03b9\u03c4\u03bf\u03c7\u03ce\u03c1\u03bf\u03c5"
    ],
    "name:eng_x_preferred":[
        "Limenas Litochorou"
    ],
    "name:gre_x_preferred":[
        "\u039b\u03b9\u03bc\u03ad\u03bd\u03b1\u03c2 \u039b\u03b9\u03c4\u03bf\u03c7\u03ce\u03c1\u03bf\u03c5"
    ],
    "name:mkd_x_preferred":[
        "Pristani\u0161te na Litohorou"
    ],
    "name:unk_x_variant":[
        "\u00c1yioi The\u00f3dhoroi"
    ],
    "qs_pg:aaroncc":"GR",
    "qs_pg:gn_country":"GR",
    "qs_pg:gn_fcode":"PPL",
    "qs_pg:gn_pop":42,
    "qs_pg:name":"Lim\u00edn Litoch\u00f3rou",
    "qs_pg:photos_9r":0,
    "qs_pg:photos_sr":0,
    "qs_pg:pop_sr":1,
    "qs_pg:qs_pg_placetype":"locality",
    "wof:name":"Lim\u00edn Litoch\u00f3rou",
    "wof:placetype":"locality",
    "wof:population":42
},
  "geometry": {"coordinates":[22.54222,40.14944],"type":"Point"}
}