{
  "type": "Feature",
  "properties": {
    "gn:admin1_code":"ESYE24",
    "gn:admin2_code":"34.0",
    "gn:admin3_code":"9155",
    "gn:asciiname":"Moni Agiou Georgiou Arma",
    "gn:country_code":"GR",
    "gn:dem":327,
    "gn:feature_class":"P",
    "gn:feature_code":"PPLR",
    "gn:name":"Mon\u00ed Ag\u00edou Georg\u00edou \u00c1rma",
    "gn:population":3,
    "gn:timezone":"Europe/Athens",
    "iso:country":"GR",
    "name:ell_x_preferred":[
        "\u039c\u03bf\u03bd\u03ae \u0391\u03b3\u03af\u03bf\u03c5 \u0393\u03b5\u03c9\u03c1\u03b3\u03af\u03bf\u03c5 \u0386\u03c1\u03bc\u03b1"
    ],
    "name:eng_x_preferred":[
        "Moni Agiou Georgiou Arma"
    ],
    "wof:name":"Moni Agiou Georgiou Arma",
    "wof:placetype":"locality",
    "wof:population":3
},
  "geometry": {"coordinates":[23.77017,38.44357],"type":"Point"}
}