{
  "type": "Feature",
  "properties": {
    "gn:admin1_code":"ESYE11",
    "gn:admin2_code":"3.0",
    "gn:admin3_code":"9018",
    "gn:asciiname":"Exokhi",
    "gn:cc2":"GR",
    "gn:country_code":"GR",
    "gn:dem":25,
    "gn:feature_class":"P",
    "gn:feature_code":"PPL",
    "gn:name":"Exokh\u00ed",
    "gn:population":0,
    "gn:timezone":"Europe/Athens",
    "iso:country":"GR",
    "name:und_x_variant":[
        "Giz\u00f3la",
        "Giz\u00e9la"
    ],
    "wof:name":"Exokhi",
    "wof:placetype":"locality"
},
  "geometry": {"coordinates":[24.86043,41.03159],"type":"Point"}
}