{
  "type": "Feature",
  "properties": {
    "gn:admin1_code":"ESYE11",
    "gn:admin2_code":"3.0",
    "gn:admin3_code":"9017",
    "gn:asciiname":"Neochori",
    "gn:country_code":"GR",
    "gn:dem":100,
    "gn:feature_class":"P",
    "gn:feature_code":"PPL",
    "gn:name":"Neoch\u00f3ri",
    "gn:population":0,
    "gn:timezone":"Europe/Athens",
    "iso:country":"GR",
    "name:bul_x_preferred":[
        "\u041d\u0435\u043e\u0445\u043e\u0440\u0438"
    ],
    "name:ceb_x_preferred":[
        "Neochori"
    ],
    "name:deu_x_preferred":[
        "Neochori"
    ],
    "name:ell_x_preferred":[
        "Neoch\u00f3ri"
    ],
    "name:ell_x_variant":[
        "\u039d\u03b5\u03bf\u03c7\u03ce\u03c1\u03b9",
        "Neokh\u00f3rion",
        "Neoch\u00f3rion",
        "\u039d\u03b5\u03bf\u03c7\u03ce\u03c1\u03b9\u03bf\u03bd"
    ],
    "name:rus_x_preferred":[
        "\u041d\u0435\u043e\u0445\u043e\u0440\u0438\u043e\u043d"
    ],
    "name:swe_x_preferred":[
        "Neochori"
    ],
    "wof:name":"Neochori",
    "wof:placetype":"locality"
},
  "geometry": {"coordinates":[24.63296,41.22087],"type":"Point"}
}