{
  "type": "Feature",
  "properties": {
    "gn:admin1_code":"ESYE23",
    "gn:admin2_code":"39.0",
    "gn:admin3_code":"9135.0",
    "gn:asciiname":"Ano Kourtesi",
    "gn:country_code":"GR",
    "gn:dem":41,
    "gn:feature_class":"P",
    "gn:feature_code":"PPL",
    "gn:name":"Ano Kourt\u00e9si",
    "gn:population":0,
    "gn:timezone":"Europe/Athens",
    "iso:country":"GR",
    "name:ell_x_preferred":[
        "\u0386\u03bd\u03c9 \u039a\u03bf\u03c5\u03c1\u03c4\u03ad\u03c3\u03b9"
    ],
    "wof:name":"Ano Kourtesi",
    "wof:placetype":"locality"
},
  "geometry": {"coordinates":[21.32927,37.96573],"type":"Point"}
}