{
  "type": "Feature",
  "properties": {
    "gn:country":"GR",
    "gn:fcode":"PPL",
    "gn:population":312,
    "iso:country":"GR",
    "name:ell_x_preferred":[
        "\u0391\u03c1\u03ba\u03bf\u03c7\u03ce\u03c1\u03b9"
    ],
    "name:ell_x_variant":[
        "\u0391\u03c1\u03ba\u03bf\u03c7\u03ce\u03c1\u03b9\u03bf\u03bd"
    ],
    "name:und_x_variant":[
        "Arkokh\u00f3rion"
    ],
    "qs_pg:aaroncc":"GR",
    "qs_pg:gn_country":"GR",
    "qs_pg:gn_fcode":"PPL",
    "qs_pg:gn_pop":312,
    "qs_pg:name":"Arkoch\u00f3rion",
    "qs_pg:photos_9r":0,
    "qs_pg:photos_sr":0,
    "qs_pg:pop_sr":2,
    "qs_pg:qs_pg_placetype":"locality",
    "wof:name":"Arkoch\u00f3rion",
    "wof:placetype":"locality",
    "wof:population":312
},
  "geometry": {"coordinates":[22.07194,40.58806],"type":"Point"}
}