{
  "type": "Feature",
  "properties": {
    "gn:admin1_code":"ESYE42",
    "gn:admin2_code":"47.0",
    "gn:admin3_code":"9275.0",
    "gn:asciiname":"Livadia",
    "gn:country_code":"GR",
    "gn:dem":3,
    "gn:feature_class":"P",
    "gn:feature_code":"PPL",
    "gn:name":"Livadia",
    "gn:population":0,
    "gn:timezone":"Europe/Athens",
    "iso:country":"GR",
    "name:bul_x_preferred":[
        "\u041b\u0438\u0432\u0430\u0434\u0438\u044f"
    ],
    "name:cat_x_preferred":[
        "Liv\u00e0dia"
    ],
    "name:ceb_x_preferred":[
        "Livadia"
    ],
    "name:deu_x_preferred":[
        "Liwadija"
    ],
    "name:eng_x_historical":[
        "Livadhia"
    ],
    "name:eng_x_preferred":[
        "Livadhia"
    ],
    "name:est_x_preferred":[
        "Liv\u00e1dia"
    ],
    "name:fin_x_preferred":[
        "Liv\u00e1dia"
    ],
    "name:fra_x_preferred":[
        "Livadia"
    ],
    "name:hye_x_preferred":[
        "\u053c\u056b\u057e\u0561\u0564\u056b\u0561"
    ],
    "name:ita_x_preferred":[
        "Livadia"
    ],
    "name:nld_x_preferred":[
        "Livadia"
    ],
    "name:rus_x_preferred":[
        "\u041b\u0438\u0432\u0430\u0434\u0438\u044f"
    ],
    "name:srp_x_preferred":[
        "\u041b\u0438\u0432\u0430\u0434\u0438\u0458\u0430"
    ],
    "name:swe_x_preferred":[
        "Livadia"
    ],
    "name:ukr_x_preferred":[
        "\u041b\u0456\u0432\u0430\u0434\u0456\u044f"
    ],
    "wof:name":"Livadia",
    "wof:placetype":"locality"
},
  "geometry": {"coordinates":[26.34215,36.54238],"type":"Point"}
}