{
  "type": "Feature",
  "properties": {
    "gn:admin1_code":"ESYE42",
    "gn:admin2_code":"47.0",
    "gn:admin3_code":"9275.0",
    "gn:asciiname":"Livadia",
    "gn:country_code":"GR",
    "gn:dem":3,
    "gn:feature_class":"P",
    "gn:feature_code":"PPL",
    "gn:name":"Livadia",
    "gn:population":0,
    "gn:timezone":"Europe/Athens",
    "iso:country":"GR",
    "name:eng_x_historical":[
        "Livadhia"
    ],
    "name:eng_x_preferred":[
        "Livadhia"
    ],
    "wof:name":"Livadia",
    "wof:placetype":"locality"
},
  "geometry": {"coordinates":[26.34215,36.54238],"type":"Point"}
}