{
  "type": "Feature",
  "properties": {
    "gn:admin1_code":"ESYE31",
    "gn:admin2_code":"406101.0",
    "gn:admin3_code":"9213",
    "gn:asciiname":"Palaia Loutra",
    "gn:country_code":"GR",
    "gn:dem":277,
    "gn:feature_class":"P",
    "gn:feature_code":"PPL",
    "gn:name":"Palai\u00e1 Loutr\u00e1",
    "gn:population":25,
    "gn:timezone":"Europe/Athens",
    "iso:country":"GR",
    "name:ell_x_preferred":[
        "\u03a0\u03b1\u03bb\u03b1\u03b9\u03ac \u039b\u03bf\u03c5\u03c4\u03c1\u03ac"
    ],
    "name:eng_x_preferred":[
        "Palaia Loutra"
    ],
    "name:und_x_variant":[
        "Mo\u00faskha K\u00e1to",
        "Palai\u00e1 Loutr\u00e1"
    ],
    "wof:name":"Palaia Loutra",
    "wof:placetype":"locality",
    "wof:population":25
},
  "geometry": {"coordinates":[23.35755,37.62606],"type":"Point"}
}