{
  "type": "Feature",
  "properties": {
    "gn:admin1_code":"ESYE25",
    "gn:admin2_code":"40.0",
    "gn:admin3_code":"9257",
    "gn:asciiname":"Lachanada",
    "gn:country_code":"GR",
    "gn:dem":105,
    "gn:feature_class":"P",
    "gn:feature_code":"PPL",
    "gn:name":"Lachan\u00e1da",
    "gn:population":0,
    "gn:timezone":"Europe/Athens",
    "iso:country":"GR",
    "name:ell_x_preferred":[
        "Lachan\u00e1da"
    ],
    "name:ell_x_variant":[
        "\u039b\u03b1\u03c7\u03b1\u03bd\u03ac\u03b4\u03b1"
    ],
    "name:und_x_variant":[
        "Lakhan\u00e1dha"
    ],
    "wof:name":"Lachanada",
    "wof:placetype":"locality"
},
  "geometry": {"coordinates":[21.81339,36.82178],"type":"Point"}
}