{
  "type": "Feature",
  "properties": {
    "gn:country":"GR",
    "gn:fcode":"PPL",
    "gn:population":213,
    "iso:country":"GR",
    "name:ell_x_preferred":[
        "\u0391\u03c1\u03c7\u03bf\u03bd\u03c4\u03b9\u03ba\u03cc"
    ],
    "name:ell_x_variant":[
        "\u0391\u03c1\u03c7\u03bf\u03bd\u03c4\u03b9\u03ba\u03cc\u03bd"
    ],
    "name:und_x_variant":[
        "\u00c1lari"
    ],
    "qs_pg:aaroncc":"GR",
    "qs_pg:gn_country":"GR",
    "qs_pg:gn_fcode":"PPL",
    "qs_pg:gn_pop":213,
    "qs_pg:name":"Archontik\u00f3n",
    "qs_pg:photos_9r":0,
    "qs_pg:photos_sr":0,
    "qs_pg:pop_sr":2,
    "qs_pg:qs_pg_placetype":"locality",
    "wof:name":"Archontik\u00f3n",
    "wof:placetype":"locality",
    "wof:population":213
},
  "geometry": {"coordinates":[22.45833,40.78917],"type":"Point"}
}