{
  "type": "Feature",
  "properties": {
    "gn:admin1_code":"ESYE12",
    "gn:admin2_code":"13.0",
    "gn:admin3_code":"9034",
    "gn:asciiname":"Mesokomo",
    "gn:country_code":"GR",
    "gn:dem":245,
    "gn:feature_class":"P",
    "gn:feature_code":"PPL",
    "gn:name":"Mes\u00f3komo",
    "gn:population":0,
    "gn:timezone":"Europe/Athens",
    "iso:country":"GR",
    "name:bul_x_preferred":[
        "\u041c\u0435\u0441\u043e\u043a\u043e\u043c\u043e"
    ],
    "name:ell_x_preferred":[
        "\u039c\u03b5\u03c3\u03cc\u03ba\u03c9\u03bc\u03bf"
    ],
    "name:mkd_x_preferred":[
        "\u0413\u0438\u0440\u0435\u0432\u043e"
    ],
    "wof:name":"Mesokomo",
    "wof:placetype":"locality"
},
  "geometry": {"coordinates":[23.35384,40.56826],"type":"Point"}
}