{
  "type": "Feature",
  "properties": {
    "gn:gn_country":"GR",
    "gn:gn_fcode":"PPL",
    "gn:gn_pop":241,
    "gn:population":189,
    "iso:country":"GR",
    "name:ell_x_preferred":[
        "\u03a3\u03b3\u03bf\u03c5\u03c1\u03ac\u03b4\u03b5\u03c2"
    ],
    "name:unk_x_variant":[
        "Sgour\u00e1dhes"
    ],
    "qs_pg:aaroncc":"GR",
    "qs_pg:gn_country":"GR",
    "qs_pg:gn_fcode":"PPL",
    "qs_pg:gn_pop":241,
    "qs_pg:name":"Sgouradhes",
    "qs_pg:name_adm0":"\u0395\u03bb\u03bb\u03ac\u03b4\u03b1",
    "qs_pg:name_adm1":"Peloponnese Western Greece and the Ionian Islands",
    "qs_pg:photos_9r":0,
    "qs_pg:photos_sr":0,
    "qs_pg:pop_sr":2,
    "qs_pg:qs_pg_placetype":"locality",
    "qs_pg:qs_pg_placetype_gp":"Town",
    "qs_pg:woe_adm0":23424833,
    "woe:adm0_id":23424833,
    "woe:name_adm0":"\u0395\u03bb\u03bb\u03ac\u03b4\u03b1",
    "woe:name_adm1":"Peloponnese Western Greece and the Ionian Islands",
    "woe:placetype":"Town",
    "wof:name":"Sgouradhes",
    "wof:placetype":"locality",
    "wof:population":189
},
  "geometry": {"coordinates":[19.82333,39.72833],"type":"Point"}
}