{
  "type": "Feature",
  "properties": {
    "gn:admin1_code":"ESYE23",
    "gn:admin2_code":"31.0",
    "gn:admin3_code":"9125",
    "gn:asciiname":"Tsitzouraiika",
    "gn:country_code":"GR",
    "gn:dem":288,
    "gn:feature_class":"P",
    "gn:feature_code":"PPL",
    "gn:name":"Tsitzoura\u00edika",
    "gn:population":0,
    "gn:timezone":"Europe/Athens",
    "iso:country":"GR",
    "name:ell_x_preferred":[
        "Tsitzoura\u00edika"
    ],
    "name:ell_x_variant":[
        "\u03a4\u03c3\u03b9\u03c4\u03b6\u03bf\u03c5\u03c1\u03b1\u03af\u03b9\u03ba\u03b1"
    ],
    "wof:name":"Tsitzouraiika",
    "wof:placetype":"locality"
},
  "geometry": {"coordinates":[21.29597,38.78625],"type":"Point"}
}