{
  "type": "Feature",
  "properties": {
    "gn:admin1_code":"ESYE22",
    "gn:admin2_code":"25.0",
    "gn:admin3_code":"9118",
    "gn:asciiname":"Agia Triada",
    "gn:country_code":"GR",
    "gn:dem":52,
    "gn:feature_class":"P",
    "gn:feature_code":"PPL",
    "gn:name":"Agia Tri\u00e1da",
    "gn:population":192,
    "gn:timezone":"Europe/Athens",
    "iso:country":"GR",
    "name:ell_x_preferred":[
        "\u0391\u03b3\u03af\u03b1 \u03a4\u03c1\u03b9\u03ac\u03b4\u03b1"
    ],
    "name:eng_x_preferred":[
        "Agia Triada"
    ],
    "wof:name":"Agia Triada",
    "wof:placetype":"locality",
    "wof:population":192
},
  "geometry": {"coordinates":[19.84406,39.60744],"type":"Point"}
}