{
  "type": "Feature",
  "properties": {
    "gn:gn_country":"GR",
    "gn:gn_fcode":"PPL",
    "gn:gn_pop":1000,
    "gn:population":127,
    "iso:country":"GR",
    "name:deu_x_preferred":[
        "Kap Sounion"
    ],
    "name:ell_x_preferred":[
        "\u03a3\u03bf\u03cd\u03bd\u03b9\u03bf"
    ],
    "name:ell_x_variant":[
        "\u03a3\u03bf\u03cd\u03bd\u03b9\u03bf\u03bd",
        "\u039a\u03ac\u03c4\u03c9 \u03a3\u03bf\u03cd\u03bd\u03b9\u03bf",
        "\u039a\u03ac\u03c4\u03c9 \u03a3\u03bf\u03cd\u03bd\u03b9\u03bf\u03bd"
    ],
    "name:eng_x_preferred":[
        "Sounion"
    ],
    "name:eng_x_variant":[
        "Sounio"
    ],
    "name:fra_x_preferred":[
        "Sounion"
    ],
    "name:lat_x_preferred":[
        "Sunium"
    ],
    "name:nld_x_preferred":[
        "Sounion"
    ],
    "name:pol_x_preferred":[
        "Sunion"
    ],
    "name:rus_x_preferred":[
        "\u0421\u0443\u043d\u0438\u043e\u043d"
    ],
    "name:spa_x_preferred":[
        "Suni\u00f3n"
    ],
    "name:unk_x_variant":[
        "So\u00fanion"
    ],
    "qs_pg:aaroncc":"GR",
    "qs_pg:gn_country":"GR",
    "qs_pg:gn_fcode":"PPL",
    "qs_pg:gn_pop":1000,
    "qs_pg:name":"K\u00e1to So\u00fanion",
    "qs_pg:photos_9r":0,
    "qs_pg:photos_sr":0,
    "qs_pg:pop_sr":2,
    "qs_pg:qs_pg_placetype":"locality",
    "wof:name":"K\u00e1to So\u00fanion",
    "wof:placetype":"locality",
    "wof:population":127
},
  "geometry": {"coordinates":[24.01551,37.66004],"type":"Point"}
}