{
  "type": "Feature",
  "properties": {
    "gn:admin1_code":"ESYE23",
    "gn:admin2_code":"39.0",
    "gn:admin3_code":"9141",
    "gn:asciiname":"Vrochitsa",
    "gn:country_code":"GR",
    "gn:dem":85,
    "gn:feature_class":"P",
    "gn:feature_code":"PPL",
    "gn:name":"Vroch\u00edtsa",
    "gn:population":0,
    "gn:timezone":"Europe/Athens",
    "iso:country":"GR",
    "name:ell_x_preferred":[
        "Vroch\u00edtsa"
    ],
    "name:ell_x_variant":[
        "\u0392\u03c1\u03bf\u03c7\u03af\u03c4\u03c3\u03b1",
        "\u0392\u03c1\u03bf\u03c7\u03af\u03c4\u03c3\u03b1 \u0397\u03bb\u03b5\u03af\u03b1\u03c2"
    ],
    "name:und_x_variant":[
        "Vorkhitsa",
        "Vrokh\u00edtsa"
    ],
    "wof:name":"Vrochitsa",
    "wof:placetype":"locality"
},
  "geometry": {"coordinates":[21.44789,37.73856],"type":"Point"}
}