{
  "type": "Feature",
  "properties": {
    "gn:country":"GR",
    "gn:fcode":"PPL",
    "gn:population":5318,
    "iso:country":"GR",
    "name:ara_x_preferred":[
        "\u0645\u0648\u0631\u0646\u064a\u0633\u060c \u0647\u0627\u0646\u064a\u0627"
    ],
    "name:ara_x_variant":[
        "\u0645\u0648\u0631\u0646\u064a\u0633"
    ],
    "name:cat_x_preferred":[
        "Murni\u00e9s"
    ],
    "name:ceb_x_preferred":[
        "Mourni\u00e9s"
    ],
    "name:ell_x_preferred":[
        "\u039c\u03bf\u03c5\u03c1\u03bd\u03b9\u03ad\u03c2"
    ],
    "name:ell_x_variant":[
        "\u039c\u03bf\u03c5\u03c1\u03bd\u03b9\u03b1\u03af",
        "\u039c\u03bf\u03c5\u03c1\u03bd\u03b9\u03ad\u03c2 \u03a7\u03b1\u03bd\u03af\u03c9\u03bd"
    ],
    "name:eng_x_preferred":[
        "Mournies"
    ],
    "name:fin_x_preferred":[
        "Mourni\u00e9s"
    ],
    "name:fra_x_preferred":[
        "Mourni\u00e9s"
    ],
    "name:lat_x_preferred":[
        "Murniae"
    ],
    "name:nld_x_preferred":[
        "Mournies"
    ],
    "name:nno_x_preferred":[
        "Mourni\u00e9s"
    ],
    "name:swe_x_preferred":[
        "Mourni\u00e9s"
    ],
    "name:und_x_variant":[
        "Mourni\u00f3n"
    ],
    "qs_pg:aaroncc":"GR",
    "qs_pg:gn_country":"GR",
    "qs_pg:gn_fcode":"PPL",
    "qs_pg:gn_pop":5318,
    "qs_pg:name":"Mourniai",
    "qs_pg:name_adm0":"\u0395\u03bb\u03bb\u03ac\u03b4\u03b1",
    "qs_pg:name_adm1":"Crete",
    "qs_pg:photos_9r":0,
    "qs_pg:photos_sr":0,
    "qs_pg:pop_sr":5,
    "qs_pg:qs_pg_placetype":"locality",
    "qs_pg:qs_pg_placetype_gp":"Town",
    "qs_pg:woe_adm0":23424833,
    "woe:adm0_id":23424833,
    "woe:name_adm0":"\u0395\u03bb\u03bb\u03ac\u03b4\u03b1",
    "woe:name_adm1":"Crete",
    "woe:placetype":"Town",
    "wof:name":"Mourniai",
    "wof:placetype":"locality",
    "wof:population":5318
},
  "geometry": {"coordinates":[24.01253,35.48228],"type":"Point"}
}