{
  "type": "Feature",
  "properties": {
    "gn:gn_country":"GR",
    "gn:gn_fcode":"PPL",
    "gn:gn_pop":1336,
    "gn:population":1336,
    "iso:country":"GR",
    "name:ara_x_preferred":[
        "\u0623\u0643\u0633\u0648\u0633\u060c \u0628\u064a\u0644\u0627"
    ],
    "name:bul_x_preferred":[
        "\u0412\u0435\u0445\u0442\u0438 \u041f\u0430\u0437\u0430\u0440"
    ],
    "name:ell_x_preferred":[
        "\u0391\u03be\u03cc\u03c2"
    ],
    "name:ell_x_variant":[
        "\u0391\u03be\u03cc\u03c2 \u03a0\u03ad\u03bb\u03bb\u03b1\u03c2"
    ],
    "name:eng_x_preferred":[
        "Axos"
    ],
    "name:mkd_x_preferred":[
        "\u0412\u0435\u0445\u0442\u0438 \u041f\u0430\u0437\u0430\u0440"
    ],
    "name:nld_x_preferred":[
        "Axos"
    ],
    "name:swe_x_preferred":[
        "Ax\u00f3s"
    ],
    "name:unk_x_variant":[
        "Eskij\u00e9"
    ],
    "qs_pg:aaroncc":"GR",
    "qs_pg:gn_country":"GR",
    "qs_pg:gn_fcode":"PPL",
    "qs_pg:gn_pop":1336,
    "qs_pg:name":"Axos",
    "qs_pg:name_adm0":"\u0395\u03bb\u03bb\u03ac\u03b4\u03b1",
    "qs_pg:name_adm1":"Macedonia and Thrace",
    "qs_pg:photos_9r":0,
    "qs_pg:photos_sr":0,
    "qs_pg:pop_sr":3,
    "qs_pg:qs_pg_placetype":"locality",
    "qs_pg:qs_pg_placetype_gp":"Town",
    "qs_pg:woe_adm0":23424833,
    "woe:adm0_id":23424833,
    "woe:name_adm0":"\u0395\u03bb\u03bb\u03ac\u03b4\u03b1",
    "woe:name_adm1":"Macedonia and Thrace",
    "woe:placetype":"Town",
    "wof:name":"Axos",
    "wof:placetype":"locality",
    "wof:population":1336
},
  "geometry": {"coordinates":[22.35583,40.79889],"type":"Point"}
}