{
  "type": "Feature",
  "properties": {
    "gn:gn_country":"GR",
    "gn:gn_fcode":"PPL",
    "gn:gn_pop":22,
    "gn:population":16,
    "iso:country":"GR",
    "name:ell_x_preferred":[
        "\u0392\u03bf\u03c5\u03bd\u03cc\u03c1\u03b5\u03b9\u03b1"
    ],
    "name:ell_x_variant":[
        "\u0392\u03bf\u03c5\u03bd\u03cc\u03c1\u03b9\u03b1"
    ],
    "name:eng_x_preferred":[
        "Vounoreia"
    ],
    "name:unk_x_variant":[
        "Sinoikism\u00f3s V\u00edndria"
    ],
    "qs_pg:aaroncc":"GR",
    "qs_pg:gn_country":"GR",
    "qs_pg:gn_fcode":"PPL",
    "qs_pg:gn_pop":22,
    "qs_pg:name":"Voun\u00f3reia",
    "qs_pg:photos_9r":0,
    "qs_pg:photos_sr":0,
    "qs_pg:pop_sr":1,
    "qs_pg:qs_pg_placetype":"locality",
    "wof:name":"Voun\u00f3reia",
    "wof:placetype":"locality",
    "wof:population":16
},
  "geometry": {"coordinates":[21.02556,39.47944],"type":"Point"}
}