{
  "type": "Feature",
  "properties": {
    "gn:admin1_code":"ESYE22",
    "gn:admin2_code":"25.0",
    "gn:admin3_code":"9118",
    "gn:asciiname":"Afionitika",
    "gn:country_code":"GR",
    "gn:dem":25,
    "gn:feature_class":"P",
    "gn:feature_code":"PPL",
    "gn:name":"Afion\u00edtika",
    "gn:population":3,
    "gn:timezone":"Europe/Athens",
    "iso:country":"GR",
    "name:ell_x_preferred":[
        "\u0391\u03c6\u03b9\u03c9\u03bd\u03af\u03c4\u03b9\u03ba\u03b1"
    ],
    "name:eng_x_preferred":[
        "Afionitika"
    ],
    "wof:name":"Afionitika",
    "wof:placetype":"locality",
    "wof:population":3
},
  "geometry": {"coordinates":[19.65561,39.7361],"type":"Point"}
}