{
  "type": "Feature",
  "properties": {
    "gn:admin1_code":"ESYE43",
    "gn:admin2_code":"46.0",
    "gn:admin3_code":"9312",
    "gn:asciiname":"Kaminaki",
    "gn:country_code":"GR",
    "gn:dem":850,
    "gn:feature_class":"P",
    "gn:feature_code":"PPL",
    "gn:name":"Kamin\u00e1ki",
    "gn:population":0,
    "gn:timezone":"Europe/Athens",
    "iso:country":"GR",
    "name:ell_x_preferred":[
        "\u039a\u03b1\u03bc\u03b9\u03bd\u03ac\u03ba\u03b9"
    ],
    "name:ell_x_variant":[
        "\u039a\u03b1\u03bc\u03b9\u03bd\u03ac\u03ba\u03b9\u03bf\u03bd"
    ],
    "name:und_x_variant":[
        "Kamin\u00e1ki",
        "Kamin\u00e1kion"
    ],
    "wof:name":"Kaminaki",
    "wof:placetype":"locality"
},
  "geometry": {"coordinates":[25.4661,35.15649000000001],"type":"Point"}
}