{
  "type": "Feature",
  "properties": {
    "gn:admin1_code":"ESYE41",
    "gn:admin2_code":"51.0",
    "gn:admin3_code":"9263",
    "gn:asciiname":"Kalliopi",
    "gn:country_code":"GR",
    "gn:dem":21,
    "gn:feature_class":"P",
    "gn:feature_code":"PPL",
    "gn:name":"Kalli\u00f3pi",
    "gn:population":0,
    "gn:timezone":"Europe/Athens",
    "iso:country":"GR",
    "name:ell_x_preferred":[
        "\u039a\u03b1\u03bb\u03bb\u03b9\u03cc\u03c0\u03b7"
    ],
    "name:und_x_variant":[
        "Kalli\u00f3pi"
    ],
    "wof:name":"Kalliopi",
    "wof:placetype":"locality"
},
  "geometry": {"coordinates":[25.3396,39.92032],"type":"Point"}
}