{
  "type": "Feature",
  "properties": {
    "gn:admin1_code":"ESYE41",
    "gn:admin2_code":"51.0",
    "gn:admin3_code":"9261",
    "gn:asciiname":"Skala Neon Kydonion",
    "gn:country_code":"GR",
    "gn:dem":5,
    "gn:feature_class":"P",
    "gn:feature_code":"PPL",
    "gn:name":"Sk\u00e1la N\u00e9on Kydoni\u00f3n",
    "gn:population":55,
    "gn:timezone":"Europe/Athens",
    "iso:country":"GR",
    "name:ell_x_preferred":[
        "\u03a3\u03ba\u03ac\u03bb\u03b1 \u039d\u03ad\u03c9\u03bd \u039a\u03c5\u03b4\u03c9\u03bd\u03b9\u03ce\u03bd"
    ],
    "wof:name":"Skala Neon Kydonion",
    "wof:placetype":"locality",
    "wof:population":55
},
  "geometry": {"coordinates":[26.45137,39.23292],"type":"Point"}
}