{
  "type": "Feature",
  "properties": {
    "gn:gn_country":"GR",
    "gn:gn_fcode":"PPLA3",
    "gn:gn_pop":10380,
    "gn:population":10380,
    "iso:country":"GR",
    "name:cat_x_preferred":[
        "Fars\u00e0lia"
    ],
    "name:deu_x_preferred":[
        "Farsala"
    ],
    "name:ell_x_preferred":[
        "\u03a6\u03ac\u03c1\u03c3\u03b1\u03bb\u03b1"
    ],
    "name:eng_x_preferred":[
        "Farsala"
    ],
    "name:fra_x_preferred":[
        "Pharsale"
    ],
    "name:ita_x_preferred":[
        "Farsala"
    ],
    "name:lat_x_preferred":[
        "Pharsalus"
    ],
    "name:nld_x_preferred":[
        "Pharsalus"
    ],
    "name:nor_x_preferred":[
        "Farsalos"
    ],
    "name:spa_x_preferred":[
        "Farsalia"
    ],
    "name:unk_x_variant":[
        "F\u00e1rsalos"
    ],
    "qs_pg:aaroncc":"GR",
    "qs_pg:gn_country":"GR",
    "qs_pg:gn_fcode":"PPLA3",
    "qs_pg:gn_pop":10380,
    "qs_pg:name":"Farsala",
    "qs_pg:name_adm0":"\u0395\u03bb\u03bb\u03ac\u03b4\u03b1",
    "qs_pg:name_adm1":"Thessaly and Continental Greece",
    "qs_pg:photos_9k":1,
    "qs_pg:photos_9r":2,
    "qs_pg:photos_all":52,
    "qs_pg:photos_sr":0,
    "qs_pg:pop_sr":6,
    "qs_pg:qs_pg_placetype":"localadmin",
    "qs_pg:qs_pg_placetype_gp":"LocalAdmin",
    "qs_pg:woe_adm0":23424833,
    "woe:adm0_id":23424833,
    "woe:name_adm0":"\u0395\u03bb\u03bb\u03ac\u03b4\u03b1",
    "woe:name_adm1":"Thessaly and Continental Greece",
    "woe:placetype":"LocalAdmin",
    "wof:name":"Farsala",
    "wof:placetype":"localadmin",
    "wof:population":10380
},
  "geometry": {"coordinates":[22.38472,39.29472],"type":"Point"}
}