{
  "type": "Feature",
  "properties": {
    "gn:country":"GR",
    "gn:fcode":"PPLA3",
    "gn:population":10380,
    "iso:country":"GR",
    "name:ara_x_preferred":[
        "\u0641\u0627\u0631\u0633\u0627\u0644\u0627"
    ],
    "name:bul_x_preferred":[
        "\u0424\u0430\u0440\u0441\u0430\u043b\u0430"
    ],
    "name:cat_x_preferred":[
        "Fars\u00e0lia"
    ],
    "name:ceb_x_preferred":[
        "F\u00e1rsala"
    ],
    "name:ces_x_preferred":[
        "Farsala"
    ],
    "name:dan_x_preferred":[
        "Farsalos"
    ],
    "name:deu_x_preferred":[
        "Farsala"
    ],
    "name:ell_x_preferred":[
        "\u03a6\u03ac\u03c1\u03c3\u03b1\u03bb\u03b1"
    ],
    "name:eng_x_preferred":[
        "Farsala"
    ],
    "name:eus_x_preferred":[
        "Farsalia"
    ],
    "name:fas_x_preferred":[
        "\u0641\u0627\u0631\u0633\u0627\u0644"
    ],
    "name:fin_x_preferred":[
        "F\u00e1rsala"
    ],
    "name:fra_x_preferred":[
        "Pharsale"
    ],
    "name:ita_x_preferred":[
        "Farsala"
    ],
    "name:jpn_x_preferred":[
        "\u30d5\u30a1\u30eb\u30b5\u30e9"
    ],
    "name:kor_x_preferred":[
        "\ud30c\ub974\uc0b4\ub77c"
    ],
    "name:lat_x_preferred":[
        "Pharsalus"
    ],
    "name:nld_x_preferred":[
        "Pharsalus"
    ],
    "name:nld_x_variant":[
        "Farsala"
    ],
    "name:nno_x_preferred":[
        "F\u00e1rsala"
    ],
    "name:nor_x_preferred":[
        "Farsalos"
    ],
    "name:pol_x_preferred":[
        "Farsala"
    ],
    "name:ron_x_preferred":[
        "Farsala"
    ],
    "name:rus_x_preferred":[
        "\u0424\u0430\u0440\u0441\u0430\u043b\u0430"
    ],
    "name:spa_x_preferred":[
        "Farsalia"
    ],
    "name:spa_x_variant":[
        "Farsala"
    ],
    "name:srp_x_preferred":[
        "\u0424\u0430\u0440\u0441\u0430\u043b\u0430"
    ],
    "name:swe_x_preferred":[
        "F\u00e1rsala"
    ],
    "name:tur_x_preferred":[
        "Farsala"
    ],
    "name:und_x_variant":[
        "F\u00e1rsalos"
    ],
    "name:vie_x_preferred":[
        "Farsala"
    ],
    "qs_pg:aaroncc":"GR",
    "qs_pg:gn_country":"GR",
    "qs_pg:gn_fcode":"PPLA3",
    "qs_pg:gn_pop":10380,
    "qs_pg:name":"Farsala",
    "qs_pg:name_adm0":"\u0395\u03bb\u03bb\u03ac\u03b4\u03b1",
    "qs_pg:name_adm1":"Thessaly and Continental Greece",
    "qs_pg:photos_9k":1,
    "qs_pg:photos_9r":2,
    "qs_pg:photos_all":52,
    "qs_pg:photos_sr":0,
    "qs_pg:pop_sr":6,
    "qs_pg:qs_pg_placetype":"localadmin",
    "qs_pg:qs_pg_placetype_gp":"LocalAdmin",
    "qs_pg:woe_adm0":23424833,
    "woe:adm0_id":23424833,
    "woe:name_adm0":"\u0395\u03bb\u03bb\u03ac\u03b4\u03b1",
    "woe:name_adm1":"Thessaly and Continental Greece",
    "woe:placetype":"LocalAdmin",
    "wof:name":"Farsala",
    "wof:placetype":"localadmin",
    "wof:population":10380
},
  "geometry": {"coordinates":[22.38472,39.29472],"type":"Point"}
}