{
  "type": "Feature",
  "properties": {
    "gn:admin1_code":"ESYE24",
    "gn:admin2_code":"34.0",
    "gn:admin3_code":"9151",
    "gn:asciiname":"Stouppaioi",
    "gn:country_code":"GR",
    "gn:dem":236,
    "gn:feature_class":"P",
    "gn:feature_code":"PPL",
    "gn:name":"Stouppa\u00edoi",
    "gn:population":0,
    "gn:timezone":"Europe/Athens",
    "iso:country":"GR",
    "name:ell_x_preferred":[
        "\u03a3\u03c4\u03bf\u03c5\u03c0\u03c0\u03b1\u03af\u03bf\u03b9"
    ],
    "name:und_x_variant":[
        "Stoupa\u00edoi",
        "Stouppa\u00edoi"
    ],
    "wof:name":"Stouppaioi",
    "wof:placetype":"locality"
},
  "geometry": {"coordinates":[24.31231,38.12297],"type":"Point"}
}