{
  "type": "Feature",
  "properties": {
    "gn:gn_country":"GR",
    "gn:gn_fcode":"PPL",
    "gn:gn_pop":52,
    "gn:population":52,
    "iso:country":"GR",
    "name:ell_x_preferred":[
        "\u039c\u03bf\u03bd\u03bf\u03bb\u03af\u03b8\u03b9"
    ],
    "name:ell_x_variant":[
        "\u039c\u03bf\u03bd\u03bf\u03bb\u03af\u03b8\u03b9\u03bf\u03bd"
    ],
    "name:unk_x_variant":[
        "Monol\u00edthi"
    ],
    "qs_pg:aaroncc":"GR",
    "qs_pg:gn_country":"GR",
    "qs_pg:gn_fcode":"PPL",
    "qs_pg:gn_pop":52,
    "qs_pg:name":"Monolithi",
    "qs_pg:name_adm0":"\u0395\u03bb\u03bb\u03ac\u03b4\u03b1",
    "qs_pg:name_adm1":"Macedonia and Thrace",
    "qs_pg:photos_9r":0,
    "qs_pg:photos_sr":0,
    "qs_pg:pop_sr":1,
    "qs_pg:qs_pg_placetype":"locality",
    "qs_pg:qs_pg_placetype_gp":"Town",
    "qs_pg:woe_adm0":23424833,
    "woe:adm0_id":23424833,
    "woe:name_adm0":"\u0395\u03bb\u03bb\u03ac\u03b4\u03b1",
    "woe:name_adm1":"Macedonia and Thrace",
    "woe:placetype":"Town",
    "wof:name":"Monolithi",
    "wof:placetype":"locality",
    "wof:population":52
},
  "geometry": {"coordinates":[22.86056,41.14833],"type":"Point"}
}