{
  "type": "Feature",
  "properties": {
    "gn:admin1_code":"ESYE43",
    "gn:admin2_code":"45.0",
    "gn:admin3_code":"9304",
    "gn:asciiname":"Larani",
    "gn:country_code":"GR",
    "gn:dem":421,
    "gn:feature_class":"P",
    "gn:feature_code":"PPL",
    "gn:name":"Lar\u00e1ni",
    "gn:population":0,
    "gn:timezone":"Europe/Athens",
    "iso:country":"GR",
    "name:ell_x_preferred":[
        "\u039b\u03b1\u03c1\u03ac\u03bd\u03b9"
    ],
    "name:ell_x_variant":[
        "\u039b\u03b1\u03c1\u03ac\u03bd\u03b9\u03bf\u03bd"
    ],
    "name:und_x_variant":[
        "Lar\u00e1nia",
        "Lar\u00e1ni",
        "Lar\u00e1nion"
    ],
    "wof:name":"Larani",
    "wof:placetype":"locality"
},
  "geometry": {"coordinates":[25.06586,35.10693],"type":"Point"}
}