{
  "type": "Feature",
  "properties": {
    "gn:admin1_code":"ESYE13",
    "gn:admin2_code":"9.0",
    "gn:admin3_code":"9063",
    "gn:asciiname":"Aposkepos",
    "gn:country_code":"GR",
    "gn:dem":881,
    "gn:feature_class":"P",
    "gn:feature_code":"PPL",
    "gn:name":"Ap\u00f3skepos",
    "gn:population":139,
    "gn:timezone":"Europe/Athens",
    "iso:country":"GR",
    "name:ell_x_historical":[
        "\u0386\u03c0\u03bf\u03c3\u03ba\u03b5\u03c0"
    ],
    "name:ell_x_preferred":[
        "\u0391\u03c0\u03cc\u03c3\u03ba\u03b5\u03c0\u03bf\u03c2"
    ],
    "name:ell_x_variant":[
        "\u0386\u03c0\u03bf\u03c3\u03ba\u03b5\u03c0"
    ],
    "name:eng_x_preferred":[
        "Aposkepos"
    ],
    "name:und_x_variant":[
        "Ap\u00f3skepas",
        "Ap\u00f3skepos"
    ],
    "wof:name":"Aposkepos",
    "wof:placetype":"locality",
    "wof:population":139
},
  "geometry": {"coordinates":[21.25102,40.55909000000001],"type":"Point"}
}