{
  "type": "Feature",
  "properties": {
    "iso:country":"GR",
    "name:ell_x_preferred":[
        "\u039a\u03c1\u03b1\u03c4\u03b9\u03ba\u03cc\u03c2 \u0391\u03b5\u03c1\u03bf\u03bb\u03b9\u03bc\u03ad\u03bd\u03b1\u03c2 \u039a\u03bf\u03b6\u03ac\u03bd\u03b7\u03c2 \u00ab\u03a6\u03af\u03bb\u03b9\u03c0\u03c0\u03bf\u03c2\u00bb"
    ],
    "name:fas_x_preferred":[
        "\u0641\u0631\u0648\u062f\u06af\u0627\u0647 \u0645\u0644\u06cc \u06a9\u0648\u0632\u0627\u0646\u06cc"
    ],
    "name:ind_x_preferred":[
        "Bandar Udara Nasional Kozani \"Filippos\""
    ],
    "name:msa_x_preferred":[
        "Lapangan Terbang Filippos"
    ],
    "name:pol_x_preferred":[
        "Port lotniczy Kozani"
    ],
    "name:swe_x_preferred":[
        "Kozani National Airport \"Filippos\""
    ],
    "name:tgk_x_preferred":[
        "\u0424\u0443\u0440\u0443\u0434\u0433\u043e\u04b3\u0438 \u043c\u0438\u043b\u043b\u04e3 \u043a\u0443\u0437\u043e\u043d\u0438"
    ],
    "name:ukr_x_preferred":[
        "\u041d\u0430\u0446\u0456\u043e\u043d\u0430\u043b\u044c\u043d\u0438\u0439 \u0430\u0435\u0440\u043e\u043f\u043e\u0440\u0442 \u041a\u043e\u0437\u0430\u043d\u0456 \u00ab\u0424\u0456\u043b\u0456\u043f\u043f\u043e\u0441\u00bb"
    ],
    "name:vie_x_preferred":[
        "S\u00e2n bay qu\u1ed1c gia Kozani"
    ],
    "oa:elevation_ft":"2059",
    "oa:type":"medium_airport",
    "wd:wordcount":78,
    "woe:hierarchy":{
        "country_id":23424833,
        "county_id":12591095,
        "localadmin_id":24544439,
        "planet_id":1,
        "state_id":12577881
    },
    "wof:name":"Kozani Airport",
    "wof:placetype":"campus"
},
  "geometry": {"coordinates":[21.840833333333,40.286111111111],"type":"Point"}
}