{
  "type": "Feature",
  "properties": {
    "gn:admin1_code":"ESYE43",
    "gn:admin2_code":"45.0",
    "gn:admin3_code":"9309",
    "gn:asciiname":"Kato Vatheia",
    "gn:country_code":"GR",
    "gn:dem":186,
    "gn:feature_class":"P",
    "gn:feature_code":"PPL",
    "gn:name":"K\u00e1to V\u00e1theia",
    "gn:population":86,
    "gn:timezone":"Europe/Athens",
    "iso:country":"GR",
    "name:ell_x_preferred":[
        "\u039a\u03ac\u03c4\u03c9 \u0392\u03ac\u03b8\u03b5\u03b9\u03b1"
    ],
    "name:eng_x_preferred":[
        "Kato Vatheia"
    ],
    "name:und_x_variant":[
        "V\u00e1thia",
        "K\u00e1to V\u00e1thia"
    ],
    "wof:name":"Kato Vatheia",
    "wof:placetype":"locality",
    "wof:population":86
},
  "geometry": {"coordinates":[25.24658,35.29993],"type":"Point"}
}