{
  "type": "Feature",
  "properties": {
    "gn:admin1_code":"ESYE25",
    "gn:admin2_code":"37.0",
    "gn:admin3_code":"9246",
    "gn:asciiname":"Zemeno",
    "gn:country_code":"GR",
    "gn:dem":556,
    "gn:feature_class":"P",
    "gn:feature_code":"PPL",
    "gn:name":"Zemen\u00f3",
    "gn:population":240,
    "gn:timezone":"Europe/Athens",
    "iso:country":"GR",
    "name:ell_x_preferred":[
        "\u0396\u03b5\u03bc\u03b5\u03bd\u03cc"
    ],
    "name:ell_x_variant":[
        "\u0396\u03b5\u03bc\u03b5\u03bd\u03cc\u03bd"
    ],
    "name:eng_x_preferred":[
        "Zemeno"
    ],
    "name:und_x_variant":[
        "Zemen\u00f3n"
    ],
    "wof:name":"Zemeno",
    "wof:placetype":"locality",
    "wof:population":240
},
  "geometry": {"coordinates":[22.60647,38.0297],"type":"Point"}
}