{
  "type": "Feature",
  "properties": {
    "gn:country":"GR",
    "gn:fcode":"PPL",
    "gn:population":0,
    "iso:country":"GR",
    "name:ell_x_colloquial":[
        "\u03a4\u03c1\u03b9\u03bf\u03b2\u03b1\u03c3\u03ac\u03bb\u03bf\u03c2"
    ],
    "name:ell_x_preferred":[
        "\u03a4\u03c1\u03b9\u03bf\u03b2\u03ac\u03c3\u03b1\u03bb\u03bf\u03c2"
    ],
    "name:ell_x_variant":[
        "\u03a4\u03c1\u03b9\u03bf\u03b2\u03b1\u03c3\u03ac\u03bb\u03bf\u03c2"
    ],
    "name:eng_x_preferred":[
        "Triovasalos"
    ],
    "name:und_x_variant":[
        "Triov\u00e1salon"
    ],
    "qs_pg:aaroncc":"GR",
    "qs_pg:gn_country":"GR",
    "qs_pg:gn_fcode":"PPL",
    "qs_pg:gn_pop":0,
    "qs_pg:name":"Triovasalos",
    "qs_pg:name_adm0":"\u0395\u03bb\u03bb\u03ac\u03b4\u03b1",
    "qs_pg:name_adm1":"Aegean",
    "qs_pg:photos":84,
    "qs_pg:photos_1k":17,
    "qs_pg:photos_9k":1,
    "qs_pg:photos_9r":3,
    "qs_pg:photos_all":84,
    "qs_pg:photos_sr":3,
    "qs_pg:pop_sr":0,
    "qs_pg:qs_pg_placetype":"locality",
    "qs_pg:qs_pg_placetype_gp":"Town",
    "qs_pg:woe_adm0":23424833,
    "woe:adm0_id":23424833,
    "woe:name_adm0":"\u0395\u03bb\u03bb\u03ac\u03b4\u03b1",
    "woe:name_adm1":"Aegean",
    "woe:placetype":"Town",
    "wof:name":"Triovasalos",
    "wof:placetype":"locality",
    "wof:population":838
},
  "geometry": {"coordinates":[24.43333,36.75],"type":"Point"}
}