{
  "type": "Feature",
  "properties": {
    "gn:gn_country":"GR",
    "gn:gn_fcode":"PPL",
    "gn:gn_pop":464,
    "gn:population":464,
    "iso:country":"GR",
    "name:bul_x_preferred":[
        "\u0424\u043e\u0442\u0438\u043d\u0430"
    ],
    "name:ceb_x_preferred":[
        "Fotein\u00e1"
    ],
    "name:ell_x_preferred":[
        "\u03a6\u03c9\u03c4\u03b5\u03b9\u03bd\u03ac"
    ],
    "name:ell_x_variant":[
        "\u03a6\u03c9\u03c4\u03b5\u03b9\u03bd\u03ac \u03a0\u03b9\u03b5\u03c1\u03af\u03b1\u03c2"
    ],
    "name:eng_x_preferred":[
        "Foteina"
    ],
    "name:nld_x_preferred":[
        "Foteina"
    ],
    "name:swe_x_preferred":[
        "Fotein\u00e1"
    ],
    "name:unk_x_variant":[
        "Fotina"
    ],
    "qs_pg:aaroncc":"GR",
    "qs_pg:gn_country":"GR",
    "qs_pg:gn_fcode":"PPL",
    "qs_pg:gn_pop":464,
    "qs_pg:name":"Foteino",
    "qs_pg:name_adm0":"\u0395\u03bb\u03bb\u03ac\u03b4\u03b1",
    "qs_pg:name_adm1":"Thessaly and Continental Greece",
    "qs_pg:photos_9r":0,
    "qs_pg:photos_sr":0,
    "qs_pg:pop_sr":2,
    "qs_pg:qs_pg_placetype":"locality",
    "qs_pg:qs_pg_placetype_gp":"Town",
    "qs_pg:woe_adm0":23424833,
    "woe:adm0_id":23424833,
    "woe:name_adm0":"\u0395\u03bb\u03bb\u03ac\u03b4\u03b1",
    "woe:name_adm1":"Thessaly and Continental Greece",
    "woe:placetype":"Town",
    "wof:name":"Foteino",
    "wof:placetype":"locality",
    "wof:population":464
},
  "geometry": {"coordinates":[22.31389,40.22056],"type":"Point"}
}