{
  "type": "Feature",
  "properties": {
    "gn:admin1_code":"ESYE23",
    "gn:admin2_code":"31.0",
    "gn:admin3_code":"9123",
    "gn:asciiname":"Sykia",
    "gn:country_code":"GR",
    "gn:dem":22,
    "gn:feature_class":"P",
    "gn:feature_code":"PPL",
    "gn:name":"Syki\u00e1",
    "gn:population":0,
    "gn:timezone":"Europe/Athens",
    "iso:country":"GR",
    "name:ceb_x_preferred":[
        "Sykia"
    ],
    "name:ell_x_preferred":[
        "Syki\u00e1"
    ],
    "name:ell_x_variant":[
        "\u03a3\u03c5\u03ba\u03b9\u03ac"
    ],
    "name:swe_x_preferred":[
        "Sykia"
    ],
    "name:und_x_variant":[
        "Siki\u00e1"
    ],
    "wof:name":"Sykia",
    "wof:placetype":"locality"
},
  "geometry": {"coordinates":[21.40156,38.53736],"type":"Point"}
}