{
  "type": "Feature",
  "properties": {
    "gn:admin1_code":"ESYE21",
    "gn:admin2_code":"17.0",
    "gn:admin3_code":"9080",
    "gn:asciiname":"Rouga",
    "gn:country_code":"GR",
    "gn:dem":877,
    "gn:feature_class":"P",
    "gn:feature_code":"PPL",
    "gn:name":"Ro\u00faga",
    "gn:population":2,
    "gn:timezone":"Europe/Athens",
    "iso:country":"GR",
    "name:ell_x_preferred":[
        "\u03a1\u03bf\u03cd\u03b3\u03b1"
    ],
    "name:eng_x_preferred":[
        "Rouga"
    ],
    "wof:name":"Rouga",
    "wof:placetype":"locality",
    "wof:population":2
},
  "geometry": {"coordinates":[21.04421,39.50906],"type":"Point"}
}