{
  "type": "Feature",
  "properties": {
    "iso:country":"GR",
    "name:ell_x_preferred":[
        "\u0386\u03bd\u03c9 \u039a\u03c5\u03c8\u03ad\u03bb\u03b7"
    ],
    "wof:name":"Ano Kypseli",
    "wof:placetype":"neighbourhood"
},
  "geometry": {"coordinates":[23.74846615480707,38.00591990537084],"type":"Point"}
}