{
  "type": "Feature",
  "properties": {
    "gn:admin1_code":"ESYE12",
    "gn:admin2_code":"13.0",
    "gn:admin3_code":"9029",
    "gn:asciiname":"Kato Karampournou",
    "gn:cc2":"GR",
    "gn:country_code":"GR",
    "gn:dem":12,
    "gn:feature_class":"P",
    "gn:feature_code":"PPL",
    "gn:name":"K\u00e1to Karampourno\u00fa",
    "gn:population":0,
    "gn:timezone":"Europe/Athens",
    "iso:country":"GR",
    "name:und_x_variant":[
        "Karabourno\u00fa",
        "K\u00e1to Karaburn\u00fa",
        "Emvolos",
        "\u00c9mvolo"
    ],
    "wof:name":"Kato Karampournou",
    "wof:placetype":"locality"
},
  "geometry": {"coordinates":[22.83667,40.4875],"type":"Point"}
}