{
  "type": "Feature",
  "properties": {
    "gn:population":3580,
    "iso:country":"GR",
    "name:ara_x_preferred":[
        "\u0623\u064a\u064a\u0627 \u062a\u0631\u064a\u0627\u0633\u060c \u062b\u064a\u0633\u0627\u0644\u0648\u0646\u064a\u0643\u064a"
    ],
    "name:ara_x_variant":[
        "\u0623\u064a\u064a\u0627 \u062a\u0631\u064a\u0627\u0633"
    ],
    "name:bul_x_preferred":[
        "\u0411\u0435\u043b \u043a\u0430\u043c\u0435\u043d"
    ],
    "name:bul_x_variant":[
        "\u0410\u0433\u0438\u044f \u0422\u0440\u0438\u0430\u0434\u0430"
    ],
    "name:ceb_x_preferred":[
        "Ag\u00eda Tri\u00e1da"
    ],
    "name:ell_x_preferred":[
        "\u0394\u03c1\u03bf\u03c3\u03bf\u03c0\u03b7\u03b3\u03ae \u03a6\u03bb\u03ce\u03c1\u03b9\u03bd\u03b1\u03c2"
    ],
    "name:ell_x_variant":[
        "\u0391\u03b3\u03af\u03b1 \u03a4\u03c1\u03b9\u03ac\u03b4\u03b1",
        "\u0391\u03b3\u03af\u03b1 \u03a4\u03c1\u03b9\u03ac\u03c2",
        "\u0391\u03b3\u03af\u03b1 \u03a4\u03c1\u03b9\u03ac\u03b4\u03b1 \u0398\u03b5\u03c3\u03c3\u03b1\u03bb\u03bf\u03bd\u03af\u03ba\u03b7\u03c2"
    ],
    "name:eng_x_preferred":[
        "Agia Triada"
    ],
    "name:mkd_x_preferred":[
        "\u0411\u0435\u043b \u041a\u0430\u043c\u0435\u043d"
    ],
    "name:nld_x_preferred":[
        "Agia Triada"
    ],
    "name:nno_x_preferred":[
        "Aj\u00eda Tri\u00e1da i Thessalon\u00edki"
    ],
    "name:sqi_x_preferred":[
        "Bellkameni"
    ],
    "name:swe_x_preferred":[
        "Ag\u00eda Tri\u00e1da"
    ],
    "name:und_x_variant":[
        "Sk\u00e1la Ay\u00edas Tri\u00e1dhos"
    ],
    "qs:a0":"Greece",
    "qs:a1":"*\u039a\u0395\u039d\u03a4\u03a1\u0399\u039a\u0397 \u039c\u0391\u039a\u0395\u0394\u039f\u039d\u0399\u0391",
    "qs:a1_alt":"KENTRIKH MAKEDONIA",
    "qs:a1r":"0",
    "qs:a2_alt":"SERRES",
    "qs:adm0":"Greece",
    "qs:la_lc":"*",
    "qs:level":"locality",
    "qs:loc":"\u0391\u0393\u0399\u0391 \u03a4\u03a1\u0399\u0391\u03a3",
    "qs:loc_alt":"AGIA TRIAS",
    "qs:pop":0,
    "qs:type":"buffered point",
    "wd:wordcount":2455,
    "wof:name":"\u0391\u0393\u0399\u0391 \u03a4\u03a1\u0399\u0391\u03a3",
    "wof:placetype":"locality",
    "wof:population":3580
},
  "geometry": {"coordinates":[22.876187,40.499832],"type":"Point"}
}