{
  "type": "Feature",
  "properties": {
    "gn:admin1_code":"ESYE22",
    "gn:admin2_code":"25.0",
    "gn:admin3_code":"9118",
    "gn:asciiname":"Plagia",
    "gn:country_code":"GR",
    "gn:dem":141,
    "gn:feature_class":"P",
    "gn:feature_code":"PPL",
    "gn:name":"Plagi\u00e1",
    "gn:population":14,
    "gn:timezone":"Europe/Athens",
    "iso:country":"GR",
    "name:ell_x_preferred":[
        "\u03a0\u03bb\u03b1\u03b3\u03b9\u03ac"
    ],
    "name:eng_x_preferred":[
        "Plagia"
    ],
    "wof:name":"Plagia",
    "wof:placetype":"locality",
    "wof:population":14
},
  "geometry": {"coordinates":[19.93289,39.74765],"type":"Point"}
}