{
  "type": "Feature",
  "properties": {
    "gn:admin1_code":"ESYE43",
    "gn:admin2_code":"43.0",
    "gn:admin3_code":"9321",
    "gn:asciiname":"Agioi Apostoloi",
    "gn:country_code":"GR",
    "gn:dem":489,
    "gn:feature_class":"P",
    "gn:feature_code":"PPL",
    "gn:name":"\u00c1gioi Ap\u00f3stoloi",
    "gn:population":0,
    "gn:timezone":"Europe/Athens",
    "iso:country":"GR",
    "name:ell_x_preferred":[
        "\u00c1gioi Ap\u00f3stoloi"
    ],
    "name:ell_x_variant":[
        "\u0386\u03b3\u03b9\u03bf\u03b9 \u0391\u03c0\u03cc\u03c3\u03c4\u03bf\u03bb\u03bf\u03b9"
    ],
    "name:fra_x_preferred":[
        "Agioi Apostoloi"
    ],
    "wof:name":"Agioi Apostoloi",
    "wof:placetype":"locality"
},
  "geometry": {"coordinates":[23.74827,35.32371],"type":"Point"}
}