{
  "type": "Feature",
  "properties": {
    "gn:admin1_code":"ESYE43",
    "gn:admin2_code":"43.0",
    "gn:admin3_code":"9323",
    "gn:asciiname":"Palaia Roumata",
    "gn:country_code":"GR",
    "gn:dem":369,
    "gn:feature_class":"P",
    "gn:feature_code":"PPL",
    "gn:name":"Palai\u00e1 Ro\u00famata",
    "gn:population":0,
    "gn:timezone":"Europe/Athens",
    "iso:country":"GR",
    "name:und_x_variant":[
        "Palea Roumata",
        "Palia Roumata"
    ],
    "wof:name":"Palaia Roumata",
    "wof:placetype":"locality"
},
  "geometry": {"coordinates":[23.78033,35.40048],"type":"Point"}
}