{
  "type": "Feature",
  "properties": {
    "gn:admin1_code":"ESYE24",
    "gn:admin2_code":"34.0",
    "gn:admin3_code":"9151",
    "gn:asciiname":"Thymi",
    "gn:country_code":"GR",
    "gn:dem":244,
    "gn:feature_class":"P",
    "gn:feature_code":"PPL",
    "gn:name":"Th\u00fdmi",
    "gn:population":0,
    "gn:timezone":"Europe/Athens",
    "iso:country":"GR",
    "name:ell_x_preferred":[
        "Th\u00fdmi"
    ],
    "name:ell_x_variant":[
        "\u0398\u03cd\u03bc\u03b9",
        "Th\u00fdmion",
        "\u0398\u03cd\u03bc\u03b9\u03bf\u03bd"
    ],
    "name:und_x_variant":[
        "Th\u00edmi",
        "Th\u00edmion"
    ],
    "wof:name":"Thymi",
    "wof:placetype":"locality"
},
  "geometry": {"coordinates":[24.56375,38.09644],"type":"Point"}
}