{
  "type": "Feature",
  "properties": {
    "gn:admin1_code":"ESYE43",
    "gn:admin2_code":"45.0",
    "gn:admin3_code":"9309",
    "gn:asciiname":"Khokhlakiai",
    "gn:cc2":"GR",
    "gn:country_code":"GR",
    "gn:dem":318,
    "gn:feature_class":"P",
    "gn:feature_code":"PPL",
    "gn:name":"Khokhlak\u00edai",
    "gn:population":0,
    "gn:timezone":"Europe/Athens",
    "iso:country":"GR",
    "name:und_x_variant":[
        "Khokhlaki\u00e9s",
        "Khokhlak\u00edai"
    ],
    "wof:name":"Khokhlakiai",
    "wof:placetype":"locality"
},
  "geometry": {"coordinates":[25.25396,35.24695],"type":"Point"}
}