{
  "type": "Feature",
  "properties": {
    "gn:admin1_code":"ESYE22",
    "gn:admin2_code":"28.0",
    "gn:admin3_code":"9116",
    "gn:asciiname":"Tsilivi",
    "gn:country_code":"GR",
    "gn:dem":6,
    "gn:feature_class":"P",
    "gn:feature_code":"PPL",
    "gn:name":"Tsilivi",
    "gn:population":0,
    "gn:timezone":"Europe/Athens",
    "iso:country":"GR",
    "name:ell_x_preferred":[
        "\u03a4\u03c3\u03b9\u03bb\u03b9\u03b2\u03af"
    ],
    "name:ell_x_variant":[
        "\u03a4\u03c3\u03b9\u03bb\u03b9\u03b2\u03ae\u03c2"
    ],
    "wof:name":"Tsilivi",
    "wof:placetype":"locality"
},
  "geometry": {"coordinates":[20.87256,37.81168],"type":"Point"}
}