{
  "type": "Feature",
  "properties": {
    "gn:admin1_code":"ESYE24",
    "gn:admin2_code":"34.0",
    "gn:admin3_code":"9150",
    "gn:asciiname":"Polilofon",
    "gn:country_code":"GR",
    "gn:dem":504,
    "gn:feature_class":"P",
    "gn:feature_code":"PPL",
    "gn:name":"Pol\u00edlofon",
    "gn:population":20,
    "gn:timezone":"Europe/Athens",
    "iso:country":"GR",
    "name:ell_x_preferred":[
        "\u03a0\u03bf\u03bb\u03cd\u03bb\u03bf\u03c6\u03bf"
    ],
    "name:eng_x_preferred":[
        "Polylofo"
    ],
    "name:und_x_variant":[
        "Gourgov\u00edtsa",
        "Gourgouv\u00edtsa",
        "Gorgov\u00edtsa",
        "Pol\u00edlofon"
    ],
    "wof:name":"Polilofon",
    "wof:placetype":"locality",
    "wof:population":20
},
  "geometry": {"coordinates":[23.09607,38.85774],"type":"Point"}
}