{
  "type": "Feature",
  "properties": {
    "gn:admin1_code":"ESYE24",
    "gn:admin2_code":"34.0",
    "gn:admin3_code":"9155",
    "gn:asciiname":"Kamari",
    "gn:country_code":"GR",
    "gn:dem":271,
    "gn:feature_class":"P",
    "gn:feature_code":"PPL",
    "gn:name":"Kam\u00e1ri",
    "gn:population":22,
    "gn:timezone":"Europe/Athens",
    "iso:country":"GR",
    "name:ara_x_preferred":[
        "\u0643\u0627\u0645\u0627\u0631\u064a"
    ],
    "name:bul_x_preferred":[
        "\u041a\u0430\u043c\u0430\u0440\u0438"
    ],
    "name:deu_x_preferred":[
        "Kamari"
    ],
    "name:ell_x_preferred":[
        "\u039a\u03b1\u03bc\u03ac\u03c1\u03b9"
    ],
    "name:ell_x_variant":[
        "\u039a\u03b1\u03bc\u03ac\u03c1\u03b9 \u0398\u03ae\u03c1\u03b1\u03c2"
    ],
    "name:eng_x_preferred":[
        "Kamari"
    ],
    "name:fas_x_preferred":[
        "\u06a9\u0627\u0645\u0627\u0631\u06cc"
    ],
    "name:fin_x_preferred":[
        "Kam\u00e1ri"
    ],
    "name:hun_x_preferred":[
        "Kamari"
    ],
    "name:ron_x_preferred":[
        "Kamari"
    ],
    "name:und_x_variant":[
        "Kam\u00f3ri",
        "Kam\u00e1rion"
    ],
    "name:zho_x_preferred":[
        "\u5361\u9a6c\u91cc"
    ],
    "wof:name":"Kamari",
    "wof:placetype":"locality",
    "wof:population":22
},
  "geometry": {"coordinates":[23.76628,38.46207],"type":"Point"}
}