{
  "type": "Feature",
  "properties": {
    "gn:admin1_code":"ESYE24",
    "gn:admin2_code":"34.0",
    "gn:admin3_code":"9155",
    "gn:asciiname":"Kamari",
    "gn:country_code":"GR",
    "gn:dem":271,
    "gn:feature_class":"P",
    "gn:feature_code":"PPL",
    "gn:name":"Kam\u00e1ri",
    "gn:population":22,
    "gn:timezone":"Europe/Athens",
    "iso:country":"GR",
    "name:ell_x_preferred":[
        "\u039a\u03b1\u03bc\u03ac\u03c1\u03b9"
    ],
    "name:eng_x_preferred":[
        "Kamari"
    ],
    "name:und_x_variant":[
        "Kam\u00f3ri",
        "Kam\u00e1ri",
        "Kam\u00e1rion"
    ],
    "wof:name":"Kamari",
    "wof:placetype":"locality",
    "wof:population":22
},
  "geometry": {"coordinates":[23.76628,38.46207],"type":"Point"}
}