{
  "type": "Feature",
  "properties": {
    "gn:country":"GR",
    "gn:fcode":"PPL",
    "gn:population":150,
    "iso:country":"GR",
    "name:bul_x_historical":[
        "\u0421\u043a\u0443\u043c\u0441\u043a\u043e"
    ],
    "name:bul_x_preferred":[
        "\u0421\u043a\u0443\u043c\u0441\u043a\u043e"
    ],
    "name:bul_x_variant":[
        "\u0412\u0440\u0430\u0445\u043e\u0441"
    ],
    "name:ell_x_historical":[
        "\u03a3\u03ba\u03bf\u03cd\u03bc\u03c4\u03c3\u03b9\u03ba\u03bf"
    ],
    "name:ell_x_preferred":[
        "\u0392\u03c1\u03ac\u03c7\u03bf\u03c2"
    ],
    "name:ell_x_variant":[
        "\u03a3\u03ba\u03bf\u03cd\u03bc\u03c4\u03c3\u03b9\u03ba\u03bf"
    ],
    "name:eng_x_historical":[
        "Skoumtsikon"
    ],
    "name:eng_x_preferred":[
        "Vrachos"
    ],
    "name:eng_x_variant":[
        "Skoumtsikon"
    ],
    "name:und_x_variant":[
        "Vr\u00e1khos"
    ],
    "qs_pg:aaroncc":"GR",
    "qs_pg:gn_country":"GR",
    "qs_pg:gn_fcode":"PPL",
    "qs_pg:gn_pop":150,
    "qs_pg:name":"Vr\u00e1chos",
    "qs_pg:photos_9r":0,
    "qs_pg:photos_sr":0,
    "qs_pg:pop_sr":1,
    "qs_pg:qs_pg_placetype":"locality",
    "wof:name":"Vr\u00e1chos",
    "wof:placetype":"locality",
    "wof:population":33
},
  "geometry": {"coordinates":[21.08889,40.355],"type":"Point"}
}