{
  "type": "Feature",
  "properties": {
    "gn:admin1_code":"ESYE24",
    "gn:admin2_code":"32.0",
    "gn:admin3_code":"9166",
    "gn:asciiname":"Dichori",
    "gn:country_code":"GR",
    "gn:dem":1120,
    "gn:feature_class":"P",
    "gn:feature_code":"PPL",
    "gn:name":"Dich\u00f3ri",
    "gn:population":0,
    "gn:timezone":"Europe/Athens",
    "iso:country":"GR",
    "name:ell_x_preferred":[
        "Dich\u00f3ri"
    ],
    "name:ell_x_variant":[
        "\u0394\u03b9\u03c7\u03ce\u03c1\u03b9",
        "Dich\u00f3rion",
        "\u0394\u03b9\u03c7\u03ce\u03c1\u03b9\u03bf\u03bd"
    ],
    "name:und_x_variant":[
        "Kostar\u00edtsa",
        "Dhikh\u00f3rion"
    ],
    "wof:name":"Dichori",
    "wof:placetype":"locality"
},
  "geometry": {"coordinates":[22.0687,38.65272],"type":"Point"}
}