{
  "type": "Feature",
  "properties": {
    "gn:admin1_code":"ESYE25",
    "gn:admin2_code":"41.0",
    "gn:admin3_code":"9238",
    "gn:asciiname":"Voutsis",
    "gn:country_code":"GR",
    "gn:dem":570,
    "gn:feature_class":"P",
    "gn:feature_code":"PPL",
    "gn:name":"Vo\u00fatsis",
    "gn:population":0,
    "gn:timezone":"Europe/Athens",
    "iso:country":"GR",
    "name:ell_x_preferred":[
        "\u0392\u03bf\u03cd\u03c4\u03c3\u03b7\u03c2"
    ],
    "name:und_x_variant":[
        "Vo\u00fatsi",
        "Vo\u00fatsis"
    ],
    "wof:name":"Voutsis",
    "wof:placetype":"locality"
},
  "geometry": {"coordinates":[21.8588,37.76802],"type":"Point"}
}