{
  "type": "Feature",
  "properties": {
    "gn:admin1_code":"ESYE25",
    "gn:admin2_code":"36.0",
    "gn:admin3_code":"9233",
    "gn:asciiname":"Chantakia",
    "gn:country_code":"GR",
    "gn:dem":156,
    "gn:feature_class":"P",
    "gn:feature_code":"PPL",
    "gn:name":"Chant\u00e1kia",
    "gn:population":33,
    "gn:timezone":"Europe/Athens",
    "iso:country":"GR",
    "name:ell_x_preferred":[
        "\u03a7\u03b1\u03bd\u03c4\u03ac\u03ba\u03b9\u03b1"
    ],
    "name:eng_x_preferred":[
        "Chantakia"
    ],
    "name:und_x_variant":[
        "Hantakia"
    ],
    "wof:name":"Chantakia",
    "wof:placetype":"locality",
    "wof:population":33
},
  "geometry": {"coordinates":[22.66264,37.66768],"type":"Point"}
}