{
  "type": "Feature",
  "properties": {
    "gn:gn_country":"GR",
    "gn:gn_fcode":"PPL",
    "gn:gn_pop":207,
    "gn:population":207,
    "iso:country":"GR",
    "name:ell_x_preferred":[
        "\u039c\u03bf\u03c5\u03b6\u03b1\u03ba\u03b1\u03af\u03b9\u03ba\u03b1"
    ],
    "name:unk_x_variant":[
        "Mouzak\u00e9\u00efka"
    ],
    "qs_pg:aaroncc":"GR",
    "qs_pg:gn_country":"GR",
    "qs_pg:gn_fcode":"PPL",
    "qs_pg:gn_pop":207,
    "qs_pg:name":"Mouzakaiika",
    "qs_pg:name_adm0":"\u0395\u03bb\u03bb\u03ac\u03b4\u03b1",
    "qs_pg:name_adm1":"Epirus and Western Macedonia",
    "qs_pg:photos_9r":0,
    "qs_pg:photos_sr":0,
    "qs_pg:pop_sr":2,
    "qs_pg:qs_pg_placetype":"locality",
    "qs_pg:qs_pg_placetype_gp":"Town",
    "qs_pg:woe_adm0":23424833,
    "woe:adm0_id":23424833,
    "woe:name_adm0":"\u0395\u03bb\u03bb\u03ac\u03b4\u03b1",
    "woe:name_adm1":"Epirus and Western Macedonia",
    "woe:placetype":"Town",
    "wof:name":"Mouzakaiika",
    "wof:placetype":"locality",
    "wof:population":207
},
  "geometry": {"coordinates":[20.59806,39.27472],"type":"Point"}
}