{
  "type": "Feature",
  "properties": {
    "gn:gn_country":"GR",
    "gn:gn_fcode":"PPL",
    "gn:gn_pop":537,
    "gn:population":537,
    "iso:country":"GR",
    "name:bul_x_preferred":[
        "\u0414\u0430\u0443\u0442\u043e\u0432\u043e"
    ],
    "name:ceb_x_preferred":[
        "Eleo\u00fasa"
    ],
    "name:ell_x_preferred":[
        "\u0395\u03bb\u03b5\u03bf\u03cd\u03c3\u03b1"
    ],
    "name:ell_x_variant":[
        "\u0395\u03bb\u03b5\u03bf\u03cd\u03c3\u03b1 \u0398\u03b5\u03c3\u03c3\u03b1\u03bb\u03bf\u03bd\u03af\u03ba\u03b7\u03c2"
    ],
    "name:eng_x_preferred":[
        "Eleousa"
    ],
    "name:mkd_x_preferred":[
        "\u0414\u0430\u0443\u0442\u043e\u0432\u043e"
    ],
    "name:nld_x_preferred":[
        "Eleousa"
    ],
    "name:swe_x_preferred":[
        "Eleo\u00fasa"
    ],
    "name:unk_x_variant":[
        "Elaio\u00fasa"
    ],
    "qs_pg:aaroncc":"GR",
    "qs_pg:gn_country":"GR",
    "qs_pg:gn_fcode":"PPL",
    "qs_pg:gn_pop":537,
    "qs_pg:name":"Eleo\u00fasa",
    "qs_pg:photos_9r":0,
    "qs_pg:photos_sr":0,
    "qs_pg:pop_sr":2,
    "qs_pg:qs_pg_placetype":"locality",
    "wof:name":"Eleo\u00fasa",
    "wof:placetype":"locality",
    "wof:population":537
},
  "geometry": {"coordinates":[22.62611,40.7475],"type":"Point"}
}