{
  "type": "Feature",
  "properties": {
    "gn:admin1_code":"ESYE43",
    "gn:admin2_code":"45.0",
    "gn:admin3_code":"9306",
    "gn:asciiname":"Kavrochori",
    "gn:country_code":"GR",
    "gn:dem":69,
    "gn:feature_class":"P",
    "gn:feature_code":"PPL",
    "gn:name":"Kavroch\u00f3ri",
    "gn:population":503,
    "gn:timezone":"Europe/Athens",
    "iso:country":"GR",
    "name:ell_x_preferred":[
        "\u039a\u03b1\u03b2\u03c1\u03bf\u03c7\u03ce\u03c1\u03b9"
    ],
    "name:ell_x_variant":[
        "\u039a\u03b1\u03b2\u03c1\u03bf\u03c7\u03ce\u03c1\u03b9\u03bf\u03bd"
    ],
    "name:eng_x_preferred":[
        "Kavrochori"
    ],
    "name:und_x_variant":[
        "Kavrokh\u00f3ri",
        "Kavrokh\u00f3rion"
    ],
    "wof:name":"Kavrochori",
    "wof:placetype":"locality",
    "wof:population":503
},
  "geometry": {"coordinates":[25.04651,35.30812],"type":"Point"}
}