{
  "type": "Feature",
  "properties": {
    "gn:admin1_code":"ESYE23",
    "gn:admin2_code":"31.0",
    "gn:admin3_code":"9128",
    "gn:asciiname":"Klepa",
    "gn:country_code":"GR",
    "gn:dem":849,
    "gn:feature_class":"P",
    "gn:feature_code":"PPL",
    "gn:name":"Klep\u00e1",
    "gn:population":0,
    "gn:timezone":"Europe/Athens",
    "iso:country":"GR",
    "name:ceb_x_preferred":[
        "Klepa"
    ],
    "name:ell_x_preferred":[
        "\u039a\u03bb\u03b5\u03c0\u03ac"
    ],
    "name:swe_x_preferred":[
        "Klepa"
    ],
    "name:und_x_variant":[
        "Kiep\u00e1",
        "Klep\u00e1"
    ],
    "wof:name":"Klepa",
    "wof:placetype":"locality"
},
  "geometry": {"coordinates":[21.89858,38.68079],"type":"Point"}
}