{
  "type": "Feature",
  "properties": {
    "gn:country":"GR",
    "gn:fcode":"PPL",
    "gn:population":154,
    "iso:country":"GR",
    "name:ceb_x_preferred":[
        "Limni"
    ],
    "name:ell_x_preferred":[
        "\u039b\u03af\u03bc\u03bd\u03b7"
    ],
    "name:eng_x_preferred":[
        "Limni"
    ],
    "name:swe_x_preferred":[
        "Limni"
    ],
    "name:und_x_variant":[
        "L\u00edmni"
    ],
    "qs_pg:aaroncc":"GR",
    "qs_pg:gn_country":"GR",
    "qs_pg:gn_fcode":"PPL",
    "qs_pg:gn_pop":154,
    "qs_pg:name":"Limni",
    "qs_pg:name_adm0":"\u0395\u03bb\u03bb\u03ac\u03b4\u03b1",
    "qs_pg:name_adm1":"Epirus and Western Macedonia",
    "qs_pg:photos_9k":1,
    "qs_pg:photos_9r":1,
    "qs_pg:photos_all":4,
    "qs_pg:photos_sr":0,
    "qs_pg:pop_sr":1,
    "qs_pg:qs_pg_placetype":"locality",
    "qs_pg:qs_pg_placetype_gp":"Town",
    "qs_pg:woe_adm0":23424833,
    "woe:adm0_id":23424833,
    "woe:name_adm0":"\u0395\u03bb\u03bb\u03ac\u03b4\u03b1",
    "woe:name_adm1":"Epirus and Western Macedonia",
    "woe:placetype":"Town",
    "wof:name":"Limni",
    "wof:placetype":"locality",
    "wof:population":99
},
  "geometry": {"coordinates":[20.53917,39.91417],"type":"Point"}
}