{
  "type": "Feature",
  "properties": {
    "gn:admin1_code":"ESYE22",
    "gn:admin2_code":"25.0",
    "gn:admin3_code":"9118",
    "gn:asciiname":"Alykes",
    "gn:country_code":"GR",
    "gn:dem":-1,
    "gn:feature_class":"P",
    "gn:feature_code":"PPL",
    "gn:name":"Alyk\u00e9s",
    "gn:population":0,
    "gn:timezone":"Europe/Athens",
    "iso:country":"GR",
    "name:ell_x_preferred":[
        "Alyk\u00e9s"
    ],
    "name:ell_x_variant":[
        "\u0391\u03bb\u03c5\u03ba\u03ad\u03c2",
        "\u0394\u03ae\u03bc\u03bf\u03c2 \u0391\u03bb\u03c5\u03ba\u03ce\u03bd"
    ],
    "name:fin_x_preferred":[
        "Alyk\u00e9s"
    ],
    "name:ita_x_preferred":[
        "Alykes"
    ],
    "name:nno_x_preferred":[
        "Alyk\u00e9s"
    ],
    "name:ron_x_preferred":[
        "Alykes"
    ],
    "name:und_x_variant":[
        "Mok\u00edlas"
    ],
    "wof:name":"Alykes",
    "wof:placetype":"locality"
},
  "geometry": {"coordinates":[20.05828,39.44306],"type":"Point"}
}