{
  "type": "Feature",
  "properties": {
    "gn:admin1_code":"ESYE23",
    "gn:admin2_code":"31.0",
    "gn:admin3_code":"9128",
    "gn:asciiname":"Kydonia",
    "gn:country_code":"GR",
    "gn:dem":891,
    "gn:feature_class":"P",
    "gn:feature_code":"PPL",
    "gn:name":"Kydoni\u00e1",
    "gn:population":0,
    "gn:timezone":"Europe/Athens",
    "iso:country":"GR",
    "name:ara_x_preferred":[
        "\u0643\u064a\u062f\u0648\u0646\u064a\u0627"
    ],
    "name:bul_x_preferred":[
        "\u041a\u0438\u0434\u043e\u043d\u0438\u044f"
    ],
    "name:cat_x_preferred":[
        "Cid\u00f2nia"
    ],
    "name:deu_x_preferred":[
        "Kydonia"
    ],
    "name:ell_x_preferred":[
        "Kydoni\u00e1"
    ],
    "name:ell_x_variant":[
        "\u039a\u03c5\u03b4\u03c9\u03bd\u03b9\u03ac",
        "\u039a\u03c5\u03b4\u03c9\u03bd\u03af\u03b1"
    ],
    "name:fin_x_preferred":[
        "Kydonia"
    ],
    "name:fra_x_preferred":[
        "Cydonia"
    ],
    "name:ita_x_preferred":[
        "Cidonia"
    ],
    "name:por_x_preferred":[
        "Cid\u00f4nia"
    ],
    "name:rus_x_preferred":[
        "\u041a\u0438\u0434\u043e\u043d\u0438\u044f"
    ],
    "name:spa_x_preferred":[
        "Cidonia"
    ],
    "name:swe_x_preferred":[
        "Kydonia"
    ],
    "name:tur_x_preferred":[
        "Kidonya"
    ],
    "name:ukr_x_preferred":[
        "\u041a\u0456\u0434\u043e\u043d\u0456\u044f"
    ],
    "name:und_x_variant":[
        "Oxi\u00e1",
        "Zil\u00edsta",
        "Kidhoni\u00e1",
        "Kidhon\u00e9a"
    ],
    "name:urd_x_preferred":[
        "\u06a9\u06cc\u062f\u0648\u0646\u06cc\u0627"
    ],
    "wof:name":"Kydonia",
    "wof:placetype":"locality"
},
  "geometry": {"coordinates":[21.96142,38.71089],"type":"Point"}
}