{
  "type": "Feature",
  "properties": {
    "gn:admin1_code":"ESYE23",
    "gn:admin2_code":"31.0",
    "gn:admin3_code":"9128",
    "gn:asciiname":"Kydonia",
    "gn:country_code":"GR",
    "gn:dem":891,
    "gn:feature_class":"P",
    "gn:feature_code":"PPL",
    "gn:name":"Kydoni\u00e1",
    "gn:population":0,
    "gn:timezone":"Europe/Athens",
    "iso:country":"GR",
    "name:ell_x_preferred":[
        "Kydoni\u00e1"
    ],
    "name:ell_x_variant":[
        "\u039a\u03c5\u03b4\u03c9\u03bd\u03b9\u03ac"
    ],
    "name:und_x_variant":[
        "Oxi\u00e1",
        "Zil\u00edsta",
        "Kidhoni\u00e1",
        "Kidhon\u00e9a"
    ],
    "wof:name":"Kydonia",
    "wof:placetype":"locality"
},
  "geometry": {"coordinates":[21.96142,38.71089],"type":"Point"}
}