{
  "type": "Feature",
  "properties": {
    "gn:population":2838,
    "iso:country":"GR",
    "name:ara_x_preferred":[
        "\u0623\u0633\u0628\u0631\u0648\u0628\u0627\u0644\u062a\u0627"
    ],
    "name:bul_x_preferred":[
        "\u0410\u0441\u043f\u0440\u043e\u0432\u0430\u043b\u0442\u0430"
    ],
    "name:deu_x_preferred":[
        "Asprovalta"
    ],
    "name:ell_x_preferred":[
        "\u0391\u03c3\u03c0\u03c1\u03bf\u03b2\u03ac\u03bb\u03c4\u03b1"
    ],
    "name:ell_x_variant":[
        "\u0391\u03c3\u03c0\u03c1\u03bf\u03b2\u03ac\u03bb\u03c4\u03b1 \u0398\u03b5\u03c3\u03c3\u03b1\u03bb\u03bf\u03bd\u03af\u03ba\u03b7\u03c2"
    ],
    "name:eng_x_preferred":[
        "Asprovalta"
    ],
    "name:mkd_x_preferred":[
        "\u0410\u0441\u043f\u0440\u043e\u0432\u0430\u043b\u0442\u0430"
    ],
    "name:nld_x_preferred":[
        "Asprovalta"
    ],
    "name:nno_x_preferred":[
        "Asprov\u00e1lta"
    ],
    "name:sqi_x_preferred":[
        "Asprovalta"
    ],
    "name:srp_x_preferred":[
        "\u0410\u0441\u043f\u0440\u043e\u0432\u0430\u043b\u0442\u0430"
    ],
    "name:swe_x_preferred":[
        "Asprov\u00e1lta"
    ],
    "name:unk_x_variant":[
        "Asprov\u00e1lta"
    ],
    "qs:a0":"Greece",
    "qs:a1":"*\u039a\u0395\u039d\u03a4\u03a1\u0399\u039a\u0397 \u039c\u0391\u039a\u0395\u0394\u039f\u039d\u0399\u0391",
    "qs:a1_alt":"KENTRIKH MAKEDONIA",
    "qs:a1r":"0",
    "qs:a2_alt":"SERRES",
    "qs:adm0":"Greece",
    "qs:la_lc":"*",
    "qs:level":"locality",
    "qs:loc":"\u0391\u03a3\u03a0\u03a1\u039f\u0392\u0391\u039b\u03a4\u0391",
    "qs:loc_alt":"ASPROBALTA",
    "qs:pop":0,
    "qs:type":"buffered point",
    "wd:population":2838,
    "wd:wordcount":109,
    "wof:name":"\u0391\u03a3\u03a0\u03a1\u039f\u0392\u0391\u039b\u03a4\u0391",
    "wof:placetype":"locality",
    "wof:population":2838
},
  "geometry": {"coordinates":[23.70553,40.71999],"type":"Point"}
}