{
  "type": "Feature",
  "properties": {
    "gn:country":"GR",
    "gn:fcode":"PPL",
    "gn:population":1444,
    "iso:country":"GR",
    "name:ara_x_preferred":[
        "\u064a\u064a\u0631\u064a\u064a\u0631\u064a\u060c \u0625\u0631\u0627\u0643\u0644\u064a\u0648\u0646"
    ],
    "name:ara_x_variant":[
        "\u064a\u064a\u0631\u064a\u064a\u0631\u064a"
    ],
    "name:ceb_x_preferred":[
        "G\u00e9rgeri"
    ],
    "name:ell_x_preferred":[
        "\u0393\u03ad\u03c1\u03b3\u03b5\u03c1\u03b7"
    ],
    "name:ell_x_variant":[
        "G\u00e9rgeri",
        "\u0393\u03ad\u03c1\u03b3\u03b5\u03c1\u03b7 \u0397\u03c1\u03b1\u03ba\u03bb\u03b5\u03af\u03bf\u03c5"
    ],
    "name:eng_x_preferred":[
        "Gergeri"
    ],
    "name:fra_x_preferred":[
        "Gergeri"
    ],
    "name:nld_x_preferred":[
        "Gergeri"
    ],
    "name:nno_x_preferred":[
        "J\u00e9rjeri"
    ],
    "name:swe_x_preferred":[
        "G\u00e9rgeri"
    ],
    "name:und_x_variant":[
        "Y\u00e9ryeri"
    ],
    "qs_pg:aaroncc":"GR",
    "qs_pg:gn_country":"GR",
    "qs_pg:gn_fcode":"PPL",
    "qs_pg:gn_pop":1444,
    "qs_pg:name":"G\u00e9rgeri",
    "qs_pg:photos_9r":0,
    "qs_pg:photos_sr":0,
    "qs_pg:pop_sr":3,
    "qs_pg:qs_pg_placetype":"locality",
    "wof:name":"G\u00e9rgeri",
    "wof:placetype":"locality",
    "wof:population":1444
},
  "geometry": {"coordinates":[24.94963,35.13281],"type":"Point"}
}