{
  "type": "Feature",
  "properties": {
    "gn:admin1_code":"ESYE41",
    "gn:admin2_code":"51.0",
    "gn:admin3_code":"9261",
    "gn:asciiname":"Sykaminia",
    "gn:country_code":"GR",
    "gn:dem":313,
    "gn:feature_class":"P",
    "gn:feature_code":"PPL",
    "gn:name":"Sykamini\u00e1",
    "gn:population":0,
    "gn:timezone":"Europe/Athens",
    "iso:country":"GR",
    "name:ell_x_preferred":[
        "\u03a3\u03c5\u03ba\u03b1\u03bc\u03b9\u03bd\u03ad\u03b1"
    ],
    "name:ell_x_variant":[
        "\u03a3\u03ba\u03b1\u03bc\u03bd\u03b9\u03ac",
        "Sykamini\u00e1",
        "\u03a3\u03c5\u03ba\u03b1\u03bc\u03b9\u03bd\u03b9\u03ac"
    ],
    "name:eng_x_preferred":[
        "Sykaminea"
    ],
    "name:und_x_variant":[
        "Sikami\u00e1",
        "Skammia",
        "Sikamin\u00e9a",
        "Sikaminia",
        "Sykamin\u00e9a"
    ],
    "wof:name":"Sykaminia",
    "wof:placetype":"locality"
},
  "geometry": {"coordinates":[26.29513,39.36109],"type":"Point"}
}