{
  "type": "Feature",
  "properties": {
    "gn:admin1_code":"ESYE23",
    "gn:admin2_code":"31.0",
    "gn:admin3_code":"9128",
    "gn:asciiname":"Ano Mammako",
    "gn:country_code":"GR",
    "gn:dem":103,
    "gn:feature_class":"P",
    "gn:feature_code":"PPL",
    "gn:name":"\u00c1no Mamm\u00e1ko",
    "gn:population":0,
    "gn:timezone":"Europe/Athens",
    "iso:country":"GR",
    "name:ell_x_preferred":[
        "\u0386\u03bd\u03c9 \u039c\u03b1\u03bc\u03bc\u03ac\u03ba\u03bf"
    ],
    "name:und_x_variant":[
        "\u00c1no Mam\u00e1kon",
        "\u00c1no Mamm\u00e1ko"
    ],
    "wof:name":"Ano Mammako",
    "wof:placetype":"locality"
},
  "geometry": {"coordinates":[21.71733,38.35728],"type":"Point"}
}