{
  "type": "Feature",
  "properties": {
    "gn:admin1_code":"ESYE43",
    "gn:admin2_code":"43.0",
    "gn:admin3_code":"9323",
    "gn:asciiname":"Episkopi",
    "gn:country_code":"GR",
    "gn:dem":169,
    "gn:feature_class":"P",
    "gn:feature_code":"PPL",
    "gn:name":"Episkop\u00ed",
    "gn:population":0,
    "gn:timezone":"Europe/Athens",
    "iso:country":"GR",
    "name:ell_x_preferred":[
        "Episkop\u00ed"
    ],
    "name:ell_x_variant":[
        "\u0395\u03c0\u03b9\u03c3\u03ba\u03bf\u03c0\u03ae"
    ],
    "wof:name":"Episkopi",
    "wof:placetype":"locality"
},
  "geometry": {"coordinates":[23.76091,35.48653],"type":"Point"}
}