{
  "type": "Feature",
  "properties": {
    "gn:admin1_code":"ESYE24",
    "gn:admin2_code":"30.0",
    "gn:admin3_code":"9157",
    "gn:asciiname":"Dhermation",
    "gn:country_code":"GR",
    "gn:dem":1009,
    "gn:feature_class":"P",
    "gn:feature_code":"PPL",
    "gn:name":"Dherm\u00e1tion",
    "gn:population":21,
    "gn:timezone":"Europe/Athens",
    "iso:country":"GR",
    "name:ell_x_preferred":[
        "\u0394\u03b5\u03c1\u03bc\u03ac\u03c4\u03b9"
    ],
    "name:eng_x_preferred":[
        "Dermati"
    ],
    "name:und_x_variant":[
        "Dherm\u00e1ti",
        "Dherm\u00e1tion"
    ],
    "wof:name":"Dhermation",
    "wof:placetype":"locality",
    "wof:population":21
},
  "geometry": {"coordinates":[21.68701,38.79423],"type":"Point"}
}