{
  "type": "Feature",
  "properties": {
    "gn:admin1_code":"ESYE43",
    "gn:admin2_code":"45.0",
    "gn:admin3_code":"9307",
    "gn:asciiname":"Demati",
    "gn:country_code":"GR",
    "gn:dem":192,
    "gn:feature_class":"P",
    "gn:feature_code":"PPL",
    "gn:name":"Dem\u00e1ti",
    "gn:population":0,
    "gn:timezone":"Europe/Athens",
    "iso:country":"GR",
    "name:ell_x_preferred":[
        "Dem\u00e1ti"
    ],
    "name:ell_x_variant":[
        "\u0394\u03b5\u03bc\u03ac\u03c4\u03b9",
        "Dem\u00e1tion",
        "\u0394\u03b5\u03bc\u03ac\u03c4\u03b9\u03bf\u03bd"
    ],
    "name:und_x_variant":[
        "Dhem\u00e1ti",
        "Dhem\u00e1tion"
    ],
    "wof:name":"Demati",
    "wof:placetype":"locality"
},
  "geometry": {"coordinates":[25.29159,35.03325],"type":"Point"}
}