{
  "type": "Feature",
  "properties": {
    "gn:admin1_code":"ESYE12",
    "gn:admin2_code":"5.0",
    "gn:admin3_code":"9054",
    "gn:asciiname":"Xirotopos",
    "gn:country_code":"GR",
    "gn:dem":719,
    "gn:feature_class":"P",
    "gn:feature_code":"PPL",
    "gn:name":"Xir\u00f3topos",
    "gn:population":138,
    "gn:timezone":"Europe/Athens",
    "iso:country":"GR",
    "name:ell_x_preferred":[
        "\u039e\u03b7\u03c1\u03cc\u03c4\u03bf\u03c0\u03bf\u03c2"
    ],
    "name:eng_x_preferred":[
        "Ksirotopos"
    ],
    "name:und_x_variant":[
        "Mert\u00e1ti",
        "Xir\u00f3topos"
    ],
    "wof:name":"Xirotopos",
    "wof:placetype":"locality",
    "wof:population":138
},
  "geometry": {"coordinates":[23.54585,41.19451],"type":"Point"}
}