{
  "type": "Feature",
  "properties": {
    "gn:country":"GR",
    "gn:fcode":"PPL",
    "gn:population":275,
    "iso:country":"GR",
    "name:ell_x_preferred":[
        "\u0391\u03c3\u03c6\u03ac\u03ba\u03b1"
    ],
    "name:eng_x_preferred":[
        "Asfaka"
    ],
    "qs_pg:aaroncc":"GR",
    "qs_pg:gn_country":"GR",
    "qs_pg:gn_fcode":"PPL",
    "qs_pg:gn_pop":275,
    "qs_pg:name":"Asf\u00e1ka",
    "qs_pg:photos_9r":0,
    "qs_pg:photos_sr":0,
    "qs_pg:pop_sr":2,
    "qs_pg:qs_pg_placetype":"locality",
    "wof:name":"Asf\u00e1ka",
    "wof:placetype":"locality",
    "wof:population":269
},
  "geometry": {"coordinates":[20.75361,39.77528],"type":"Point"}
}