{
  "type": "Feature",
  "properties": {
    "gn:country":"GR",
    "gn:fcode":"PPL",
    "gn:population":963,
    "iso:country":"GR",
    "name:ell_x_preferred":[
        "\u039c\u03b5\u03b3\u03ac\u03bb\u03b7 \u0392\u03c1\u03cd\u03c3\u03b7"
    ],
    "name:eng_x_preferred":[
        "Megali Vrysi"
    ],
    "name:und_x_variant":[
        "Meg\u00e1li Vr\u00edsi"
    ],
    "qs_pg:aaroncc":"GR",
    "qs_pg:gn_country":"GR",
    "qs_pg:gn_fcode":"PPL",
    "qs_pg:gn_pop":963,
    "qs_pg:name":"Megali Vrisi",
    "qs_pg:name_adm0":"\u0395\u03bb\u03bb\u03ac\u03b4\u03b1",
    "qs_pg:name_adm1":"Thessaly and Continental Greece",
    "qs_pg:photos_9k":1,
    "qs_pg:photos_9r":1,
    "qs_pg:photos_all":1,
    "qs_pg:photos_sr":0,
    "qs_pg:pop_sr":2,
    "qs_pg:qs_pg_placetype":"locality",
    "qs_pg:qs_pg_placetype_gp":"Town",
    "qs_pg:woe_adm0":23424833,
    "woe:adm0_id":23424833,
    "woe:name_adm0":"\u0395\u03bb\u03bb\u03ac\u03b4\u03b1",
    "woe:name_adm1":"Thessaly and Continental Greece",
    "woe:placetype":"Town",
    "wof:name":"Megali Vrisi",
    "wof:placetype":"locality",
    "wof:population":989
},
  "geometry": {"coordinates":[22.48333,38.88333],"type":"Point"}
}