{
  "type": "Feature",
  "properties": {
    "gn:population":5752,
    "iso:country":"GR",
    "name:ara_x_preferred":[
        "\u0643\u0627\u062a\u0648 \u0623\u0643\u064a\u0627"
    ],
    "name:ceb_x_preferred":[
        "K\u00e1to Acha\u1e2fa"
    ],
    "name:ell_x_preferred":[
        "\u039a\u03ac\u03c4\u03c9 \u0391\u03c7\u03b1\u0390\u03b1"
    ],
    "name:ell_x_variant":[
        "\u039a\u03ac\u03c4\u03c9 \u0391\u03c7\u03b1\u0390\u03b1 \u0391\u03c7\u03b1\u0390\u03b1\u03c2"
    ],
    "name:eng_x_preferred":[
        "Kato Achaia"
    ],
    "name:fin_x_preferred":[
        "K\u00e1to Acha\u1e2fa"
    ],
    "name:jpn_x_preferred":[
        "\u30ab\u30c8\u30fb\u30a2\u30cf\u30a4\u30a2"
    ],
    "name:nld_x_preferred":[
        "Kato Achaia"
    ],
    "name:nno_x_preferred":[
        "K\u00e1to Akha\u00eda"
    ],
    "name:ron_x_preferred":[
        "Kato Achaia"
    ],
    "name:rus_x_preferred":[
        "\u041a\u0430\u0442\u043e-\u0410\u0445\u0430\u0438\u044f"
    ],
    "name:swe_x_preferred":[
        "K\u00e1to Acha\u1e2fa"
    ],
    "name:unk_x_variant":[
        "K\u00e1to Akha\u00efa"
    ],
    "qs:a0":"Greece",
    "qs:a1":"*\u0394\u03a5\u03a4\u0399\u039a\u0397 \u0395\u039b\u039b\u0391\u0394\u0391",
    "qs:a1_alt":"DYTIKH ELLADA",
    "qs:a1r":"0",
    "qs:a2_alt":"AXAIA",
    "qs:adm0":"Greece",
    "qs:la_lc":"*",
    "qs:level":"locality",
    "qs:loc":"\u039a\u0391\u03a4\u03a9 \u0391\u03a7\u0391\u0399\u0391",
    "qs:loc_alt":"KATW AXAIA",
    "qs:pop":0,
    "qs:type":"buffered point",
    "wd:wordcount":157,
    "wof:name":"\u039a\u0391\u03a4\u03a9 \u0391\u03a7\u0391\u0399\u0391",
    "wof:placetype":"locality",
    "wof:population":5752
},
  "geometry": {"coordinates":[21.541122,38.143291],"type":"Point"}
}