{
  "type": "Feature",
  "properties": {
    "gn:admin1_code":"ESYE25",
    "gn:admin2_code":"40.0",
    "gn:admin3_code":"9256",
    "gn:asciiname":"Drosopigi",
    "gn:country_code":"GR",
    "gn:dem":373,
    "gn:feature_class":"P",
    "gn:feature_code":"PPL",
    "gn:name":"Drosopig\u00ed",
    "gn:population":0,
    "gn:timezone":"Europe/Athens",
    "iso:country":"GR",
    "name:ceb_x_preferred":[
        "Drosopigi"
    ],
    "name:ell_x_preferred":[
        "Drosopig\u00ed"
    ],
    "name:ell_x_variant":[
        "\u0394\u03c1\u03bf\u03c3\u03bf\u03c0\u03b7\u03b3\u03ae"
    ],
    "name:swe_x_preferred":[
        "Drosopigi"
    ],
    "name:und_x_variant":[
        "Vidh\u00edsova",
        "Dhrosopiy\u00ed"
    ],
    "wof:name":"Drosopigi",
    "wof:placetype":"locality"
},
  "geometry": {"coordinates":[21.8479,37.23924],"type":"Point"}
}