{
  "type": "Feature",
  "properties": {
    "gn:admin1_code":"ESYE12",
    "gn:admin2_code":"5.0",
    "gn:admin3_code":"9053",
    "gn:asciiname":"Nea Petra",
    "gn:country_code":"GR",
    "gn:dem":74,
    "gn:feature_class":"P",
    "gn:feature_code":"PPL",
    "gn:name":"N\u00e9a P\u00e9tra",
    "gn:population":277,
    "gn:timezone":"Europe/Athens",
    "iso:country":"GR",
    "name:ell_x_preferred":[
        "\u039d\u03ad\u03b1 \u03a0\u03ad\u03c4\u03c1\u03b1"
    ],
    "name:eng_x_preferred":[
        "Nea Petra"
    ],
    "name:und_x_variant":[
        "N\u00e9a P\u00e9tra"
    ],
    "wof:name":"Nea Petra",
    "wof:placetype":"locality",
    "wof:population":277
},
  "geometry": {"coordinates":[23.78524,40.99306],"type":"Point"}
}