{
  "type": "Feature",
  "properties": {
    "gn:population":244,
    "iso:country":"GR",
    "name:ara_x_preferred":[
        "\u0643\u0627\u0646\u062c\u0631\u0633\u0648\u0627\u062a\u0633\u064a\u0643"
    ],
    "name:ceb_x_preferred":[
        "Kangersuatsiaq"
    ],
    "name:ces_x_preferred":[
        "Kangersuatsiaq"
    ],
    "name:dan_x_preferred":[
        "Kangersuatsiaq"
    ],
    "name:dan_x_variant":[
        "Pr\u00f8ven"
    ],
    "name:deu_x_preferred":[
        "Kangersuatsiaq"
    ],
    "name:eng_x_preferred":[
        "Kangersuatsiaq"
    ],
    "name:fra_x_preferred":[
        "Kangersuatsiaq"
    ],
    "name:isl_x_preferred":[
        "Kangersuatsiaq"
    ],
    "name:ita_x_preferred":[
        "Kangersuatsiaq"
    ],
    "name:kal_x_preferred":[
        "Kangersuatsiaq"
    ],
    "name:kat_x_preferred":[
        "\u10d9\u10d0\u10dc\u10d2\u10d4\u10e0\u10e1\u10e3\u10d0\u10e2\u10e1\u10d8\u10d0\u10d9\u10d8"
    ],
    "name:nld_x_preferred":[
        "Kangersuatsiaq"
    ],
    "name:nob_x_preferred":[
        "Kangersuatsiaq"
    ],
    "name:nor_x_preferred":[
        "Kangersuatsiaq"
    ],
    "name:pol_x_preferred":[
        "Kangersuatsiaq"
    ],
    "name:por_x_preferred":[
        "Kangersuatsiaq"
    ],
    "name:rus_x_preferred":[
        "\u041a\u0430\u043d\u0433\u0435\u0440\u0441\u0443\u0430\u0442\u0441\u0438\u0430\u043a"
    ],
    "name:spa_x_preferred":[
        "Kangersuatsiaq"
    ],
    "name:swe_x_preferred":[
        "Kangersuatsiaq"
    ],
    "name:unk_x_variant":[
        "Kangerssuatsiaq"
    ],
    "qs:a0":"Kalaallit Nunaat#Gr\u00f8nland",
    "qs:a1":"*Qaasuitsup Kommunia",
    "qs:a1r":"0",
    "qs:adm0":"Kalaallit Nunaat#Gr\u00f8nland",
    "qs:la_lc":"*",
    "qs:level":"locality",
    "qs:loc":"Kangersuatsiaq",
    "qs:loc_alt":"Kangersuatsiaq",
    "qs:pop":0,
    "qs:type":"buffered point",
    "wd:wordcount":176,
    "wof:name":"Kangersuatsiaq",
    "wof:placetype":"locality",
    "wof:population":244
},
  "geometry": {"coordinates":[-55.5882,72.374554],"type":"Point"}
}