{
  "type": "Feature",
  "properties": {
    "gn:admin1_code":"ESYE43",
    "gn:admin2_code":"45.0",
    "gn:admin3_code":"9307",
    "gn:asciiname":"Kato Poulies",
    "gn:country_code":"GR",
    "gn:dem":350,
    "gn:feature_class":"P",
    "gn:feature_code":"PPL",
    "gn:name":"K\u00e1to Pouli\u00e9s",
    "gn:population":0,
    "gn:timezone":"Europe/Athens",
    "iso:country":"GR",
    "name:ell_x_preferred":[
        "K\u00e1to Pouli\u00e9s"
    ],
    "name:ell_x_variant":[
        "\u039a\u03ac\u03c4\u03c9 \u03a0\u03bf\u03c5\u03bb\u03b9\u03ad\u03c2",
        "K\u00e1to Pouli\u00e1",
        "\u039a\u03ac\u03c4\u03c9 \u03a0\u03bf\u03c5\u03bb\u03b9\u03ac"
    ],
    "wof:name":"Kato Poulies",
    "wof:placetype":"locality"
},
  "geometry": {"coordinates":[25.26174,35.11376],"type":"Point"}
}