{
  "type": "Feature",
  "properties": {
    "gn:admin1_code":"ESYE14",
    "gn:admin2_code":"21.0",
    "gn:admin3_code":"9101",
    "gn:asciiname":"Parapotamos",
    "gn:country_code":"GR",
    "gn:dem":41,
    "gn:feature_class":"P",
    "gn:feature_code":"PPL",
    "gn:name":"Parap\u00f3tamos",
    "gn:population":0,
    "gn:timezone":"Europe/Athens",
    "iso:country":"GR",
    "name:ara_x_preferred":[
        "\u0628\u0627\u0631\u0627\u0628\u0648\u062a\u0627\u0645\u0648\u0633"
    ],
    "name:ceb_x_preferred":[
        "Parap\u00f3tamos"
    ],
    "name:deu_x_preferred":[
        "Parapotamos"
    ],
    "name:ell_x_preferred":[
        "\u03a0\u03b1\u03c1\u03b1\u03c0\u03cc\u03c4\u03b1\u03bc\u03bf\u03c2"
    ],
    "name:ell_x_variant":[
        "\u03a0\u03b1\u03c1\u03b1\u03c0\u03cc\u03c4\u03b1\u03bc\u03bf\u03c2 \u0398\u03b5\u03c3\u03c0\u03c1\u03c9\u03c4\u03af\u03b1\u03c2"
    ],
    "name:fin_x_preferred":[
        "Parap\u00f3tamos"
    ],
    "name:ita_x_preferred":[
        "Parapotamos"
    ],
    "name:nno_x_preferred":[
        "Parap\u00f3tamos"
    ],
    "name:sqi_x_preferred":[
        "Varfanji"
    ],
    "name:und_x_variant":[
        "Baxil\u00e1r"
    ],
    "wof:name":"Parapotamos",
    "wof:placetype":"locality"
},
  "geometry": {"coordinates":[22.46936,39.82953],"type":"Point"}
}