{
  "type": "Feature",
  "properties": {
    "gn:admin1_code":"ESYE14",
    "gn:admin2_code":"21.0",
    "gn:admin3_code":"9101",
    "gn:asciiname":"Parapotamos",
    "gn:country_code":"GR",
    "gn:dem":41,
    "gn:feature_class":"P",
    "gn:feature_code":"PPL",
    "gn:name":"Parap\u00f3tamos",
    "gn:population":0,
    "gn:timezone":"Europe/Athens",
    "iso:country":"GR",
    "name:ell_x_preferred":[
        "\u03a0\u03b1\u03c1\u03b1\u03c0\u03cc\u03c4\u03b1\u03bc\u03bf\u03c2"
    ],
    "name:und_x_variant":[
        "Baxil\u00e1r",
        "Parap\u00f3tamos"
    ],
    "wof:name":"Parapotamos",
    "wof:placetype":"locality"
},
  "geometry": {"coordinates":[22.46936,39.82953],"type":"Point"}
}