{
  "type": "Feature",
  "properties": {
    "gn:admin1_code":"ESYE31",
    "gn:admin2_code":"445406.0",
    "gn:admin3_code":"9219",
    "gn:asciiname":"Ano Daskaleio",
    "gn:country_code":"GR",
    "gn:dem":136,
    "gn:feature_class":"P",
    "gn:feature_code":"PPL",
    "gn:name":"Ano Daskalei\u00f3",
    "gn:population":139,
    "gn:timezone":"Europe/Athens",
    "iso:country":"GR",
    "name:ell_x_historical":[
        "\u039c\u03c0\u03bf\u03c5\u03b6\u03b1\u03bb\u03ac\u03b4\u03b5\u03c2"
    ],
    "name:ell_x_preferred":[
        "\u0386\u03bd\u03c9 \u0394\u03b1\u03c3\u03ba\u03b1\u03bb\u03b5\u03b9\u03cc"
    ],
    "name:ell_x_variant":[
        "\u039c\u03c0\u03bf\u03c5\u03b6\u03b1\u03bb\u03ac\u03b4\u03b5\u03c2"
    ],
    "name:eng_x_preferred":[
        "Ano Daskaleio"
    ],
    "wof:name":"Ano Daskaleio",
    "wof:placetype":"locality",
    "wof:population":139
},
  "geometry": {"coordinates":[24.03912,37.80677],"type":"Point"}
}