{
  "type": "Feature",
  "properties": {
    "gn:gn_country":"GR",
    "gn:gn_fcode":"PPL",
    "gn:gn_pop":378,
    "gn:population":378,
    "iso:country":"GR",
    "name:ell_x_preferred":[
        "\u0391\u03c1\u03c7\u03ac\u03b3\u03b3\u03b5\u03bb\u03bf\u03c2"
    ],
    "name:unk_x_variant":[
        "V\u00e1ltos"
    ],
    "qs_pg:aaroncc":"GR",
    "qs_pg:gn_country":"GR",
    "qs_pg:gn_fcode":"PPL",
    "qs_pg:gn_pop":378,
    "qs_pg:name":"Arch\u00e1ngelos",
    "qs_pg:photos_9r":0,
    "qs_pg:photos_sr":0,
    "qs_pg:pop_sr":2,
    "qs_pg:qs_pg_placetype":"locality",
    "wof:name":"Arch\u00e1ngelos",
    "wof:placetype":"locality",
    "wof:population":378
},
  "geometry": {"coordinates":[22.25194,40.68056],"type":"Point"}
}