{
  "type": "Feature",
  "properties": {
    "gn:admin1_code":"ESYE22",
    "gn:admin2_code":"26.0",
    "gn:admin3_code":"9121",
    "gn:asciiname":"Kavallos",
    "gn:country_code":"GR",
    "gn:dem":454,
    "gn:feature_class":"P",
    "gn:feature_code":"PPL",
    "gn:name":"K\u00e1vallos",
    "gn:population":180,
    "gn:timezone":"Europe/Athens",
    "iso:country":"GR",
    "name:ell_x_preferred":[
        "\u039a\u03ac\u03b2\u03b1\u03bb\u03bb\u03bf\u03c2"
    ],
    "name:eng_x_preferred":[
        "Kavallos"
    ],
    "wof:name":"Kavallos",
    "wof:placetype":"locality",
    "wof:population":180
},
  "geometry": {"coordinates":[20.66056,38.78681],"type":"Point"}
}