{
  "type": "Feature",
  "properties": {
    "gn:gn_country":"GR",
    "gn:gn_fcode":"PPL",
    "gn:gn_pop":973,
    "gn:population":973,
    "iso:country":"GR",
    "name:alb_x_preferred":[
        "Vola"
    ],
    "name:ara_x_preferred":[
        "\u0633\u064a\u0641\u0648\u062a\u0627\u060c \u062b\u064a\u0633\u0628\u0631\u0648\u062a\u064a\u0627"
    ],
    "name:bul_x_preferred":[
        "\u0421\u0438\u0432\u043e\u0442\u0430"
    ],
    "name:dut_x_preferred":[
        "Syvota"
    ],
    "name:ell_x_preferred":[
        "\u03a3\u03cd\u03b2\u03bf\u03c4\u03b1"
    ],
    "name:eng_x_preferred":[
        "Syvota"
    ],
    "name:fre_x_preferred":[
        "Syvota"
    ],
    "name:ger_x_preferred":[
        "Syvota"
    ],
    "name:gre_x_preferred":[
        "\u03a3\u03cd\u03b2\u03bf\u03c4\u03b1 \u0398\u03b5\u03c3\u03c0\u03c1\u03c9\u03c4\u03af\u03b1\u03c2"
    ],
    "name:ita_x_preferred":[
        "Syvota"
    ],
    "name:jpn_x_preferred":[
        "\u30b7\u30f4\u30a9\u30bf"
    ],
    "name:nno_x_preferred":[
        "S\u00fdvota"
    ],
    "name:rus_x_preferred":[
        "\u0421\u0438\u0432\u043e\u0442\u0430"
    ],
    "name:spa_x_preferred":[
        "S\u00edbota"
    ],
    "name:srp_x_preferred":[
        "Sivota Grcka"
    ],
    "name:swe_x_preferred":[
        "S\u00fdvota"
    ],
    "name:unk_x_variant":[
        "V\u00f3lia"
    ],
    "qs_pg:aaroncc":"GR",
    "qs_pg:gn_country":"GR",
    "qs_pg:gn_fcode":"PPL",
    "qs_pg:gn_pop":973,
    "qs_pg:name":"S\u00fdvota",
    "qs_pg:photos_9r":0,
    "qs_pg:photos_sr":0,
    "qs_pg:pop_sr":2,
    "qs_pg:qs_pg_placetype":"locality",
    "wof:name":"S\u00fdvota",
    "wof:placetype":"locality",
    "wof:population":973
},
  "geometry": {"coordinates":[20.25,39.40667],"type":"Point"}
}