{
  "type": "Feature",
  "properties": {
    "gn:admin1_code":"ESYE24",
    "gn:admin2_code":"30.0",
    "gn:admin3_code":"9157",
    "gn:asciiname":"Papparousion",
    "gn:country_code":"GR",
    "gn:dem":702,
    "gn:feature_class":"P",
    "gn:feature_code":"PPL",
    "gn:name":"Papparo\u00fasion",
    "gn:population":12,
    "gn:timezone":"Europe/Athens",
    "iso:country":"GR",
    "name:ell_x_preferred":[
        "\u03a0\u03b1\u03c0\u03c0\u03b1\u03c1\u03bf\u03cd\u03c3\u03b9"
    ],
    "name:eng_x_preferred":[
        "Papparousi"
    ],
    "name:und_x_variant":[
        "Panay\u00eda",
        "Papparo\u00fasion"
    ],
    "wof:name":"Papparousion",
    "wof:placetype":"locality",
    "wof:population":12
},
  "geometry": {"coordinates":[21.68811,38.92104000000001],"type":"Point"}
}