{
  "type": "Feature",
  "properties": {
    "gn:gn_country":"GR",
    "gn:gn_fcode":"PPL",
    "gn:gn_pop":729,
    "gn:population":729,
    "iso:country":"GR",
    "name:bul_x_preferred":[
        "\u041b\u0430\u043d\u0433\u0430\u0434\u0438\u043a\u0438\u044f"
    ],
    "name:dut_x_preferred":[
        "Lagkadikia"
    ],
    "name:ell_x_preferred":[
        "\u039b\u03b1\u03b3\u03ba\u03b1\u03b4\u03af\u03ba\u03b9\u03b1"
    ],
    "name:eng_x_historical":[
        "Langavuk"
    ],
    "name:eng_x_preferred":[
        "Langadh\u00edkia"
    ],
    "name:eng_x_variant":[
        "Lagkad\u00edkia",
        "Langavuk",
        "Lagkadikia"
    ],
    "name:gre_x_preferred":[
        "\u039b\u03b1\u03b3\u03ba\u03b1\u03b4\u03af\u03ba\u03b9\u03b1 \u0398\u03b5\u03c3\u03c3\u03b1\u03bb\u03bf\u03bd\u03af\u03ba\u03b7\u03c2"
    ],
    "name:mac_x_preferred":[
        "\u0409\u0430\u043d\u0433\u0430\u0432\u0438\u0447"
    ],
    "name:swe_x_preferred":[
        "Lagkadikia"
    ],
    "qs_pg:aaroncc":"GR",
    "qs_pg:gn_country":"GR",
    "qs_pg:gn_fcode":"PPL",
    "qs_pg:gn_pop":729,
    "qs_pg:name":"Lagkadikia",
    "qs_pg:name_adm0":"\u0395\u03bb\u03bb\u03ac\u03b4\u03b1",
    "qs_pg:name_adm1":"Macedonia and Thrace",
    "qs_pg:photos_9r":0,
    "qs_pg:photos_sr":0,
    "qs_pg:pop_sr":5,
    "qs_pg:qs_pg_placetype":"locality",
    "qs_pg:qs_pg_placetype_gp":"Town",
    "qs_pg:woe_adm0":23424833,
    "woe:adm0_id":23424833,
    "woe:name_adm0":"\u0395\u03bb\u03bb\u03ac\u03b4\u03b1",
    "woe:name_adm1":"Macedonia and Thrace",
    "woe:placetype":"Town",
    "wof:name":"Lagkadikia",
    "wof:placetype":"locality",
    "wof:population":729
},
  "geometry": {"coordinates":[23.24653,40.63569],"type":"Point"}
}