{
  "type": "Feature",
  "properties": {
    "gn:admin1_code":"ESYE13",
    "gn:admin2_code":"8.0",
    "gn:admin3_code":"9071",
    "gn:asciiname":"Kotas",
    "gn:country_code":"GR",
    "gn:dem":888,
    "gn:feature_class":"P",
    "gn:feature_code":"PPL",
    "gn:name":"K\u00f3tas",
    "gn:population":22,
    "gn:timezone":"Europe/Athens",
    "iso:country":"GR",
    "name:ell_x_historical":[
        "\u03a1\u03bf\u03cd\u03bb\u03b9\u03b1",
        "\u039a\u03b1\u03c4\u03c9\u03c7\u03ce\u03c1\u03b9"
    ],
    "name:ell_x_preferred":[
        "\u039a\u03ce\u03c4\u03b1\u03c2"
    ],
    "name:ell_x_variant":[
        "\u03a1\u03bf\u03cd\u03bb\u03b9\u03b1",
        "\u039a\u03b1\u03c4\u03c9\u03c7\u03ce\u03c1\u03b9"
    ],
    "name:eng_x_historical":[
        "Katochori",
        "Roulia"
    ],
    "name:eng_x_preferred":[
        "Kotas"
    ],
    "name:eng_x_variant":[
        "Katochori",
        "Roulia"
    ],
    "name:und_x_variant":[
        "Ro\u00falia",
        "K\u00f3tta",
        "Katokh\u00f3ri",
        "K\u00f3tas"
    ],
    "wof:name":"Kotas",
    "wof:placetype":"locality",
    "wof:population":22
},
  "geometry": {"coordinates":[21.17054,40.69332],"type":"Point"}
}