{
  "type": "Feature",
  "properties": {
    "gn:gn_country":"GR",
    "gn:gn_fcode":"PPL",
    "gn:gn_pop":60,
    "gn:population":60,
    "iso:country":"GR",
    "name:ell_x_preferred":[
        "Iti\u00e1"
    ],
    "name:ell_x_variant":[
        "\u0399\u03c4\u03b9\u03ac"
    ],
    "name:unk_x_variant":[
        "Tserko\u00faviana"
    ],
    "qs_pg:aaroncc":"GR",
    "qs_pg:gn_country":"GR",
    "qs_pg:gn_fcode":"PPL",
    "qs_pg:gn_pop":60,
    "qs_pg:name":"It\u00e9a",
    "qs_pg:photos_9r":0,
    "qs_pg:photos_sr":0,
    "qs_pg:pop_sr":1,
    "qs_pg:qs_pg_placetype":"locality",
    "wof:name":"It\u00e9a",
    "wof:placetype":"locality",
    "wof:population":60
},
  "geometry": {"coordinates":[21.42389,39.28972],"type":"Point"}
}