{
  "type": "Feature",
  "properties": {
    "gn:admin1_code":"ESYE42",
    "gn:admin2_code":"47.0",
    "gn:admin3_code":"9276.0",
    "gn:asciiname":"Kamari",
    "gn:country_code":"GR",
    "gn:dem":117,
    "gn:feature_class":"P",
    "gn:feature_code":"PPL",
    "gn:name":"Kam\u00e1ri",
    "gn:population":86,
    "gn:timezone":"Europe/Athens",
    "iso:country":"GR",
    "name:ell_x_preferred":[
        "\u039a\u03b1\u03bc\u03ac\u03c1\u03b9"
    ],
    "name:eng_x_preferred":[
        "Kamari"
    ],
    "wof:name":"Kamari",
    "wof:placetype":"locality",
    "wof:population":86
},
  "geometry": {"coordinates":[26.93577,36.98566],"type":"Point"}
}