{
  "type": "Feature",
  "properties": {
    "gn:gn_country":"GR",
    "gn:gn_fcode":"PPL",
    "gn:gn_pop":374,
    "gn:population":313,
    "iso:country":"GR",
    "name:ell_x_preferred":[
        "\u03a7\u03b1\u03bd\u03cc\u03c0\u03bf\u03c5\u03bb\u03bf"
    ],
    "name:ell_x_variant":[
        "\u03a7\u03b1\u03bd\u03cc\u03c0\u03bf\u03c5\u03bb\u03bf\u03bd"
    ],
    "name:eng_x_preferred":[
        "Chanopoulo"
    ],
    "name:unk_x_variant":[
        "Khan\u00f3poulon"
    ],
    "qs_pg:aaroncc":"GR",
    "qs_pg:gn_country":"GR",
    "qs_pg:gn_fcode":"PPL",
    "qs_pg:gn_pop":374,
    "qs_pg:name":"Chan\u00f3poulon",
    "qs_pg:photos_9r":0,
    "qs_pg:photos_sr":0,
    "qs_pg:pop_sr":2,
    "qs_pg:qs_pg_placetype":"locality",
    "wof:name":"Chan\u00f3poulon",
    "wof:placetype":"locality",
    "wof:population":313
},
  "geometry": {"coordinates":[20.93556,39.20417],"type":"Point"}
}