{
  "type": "Feature",
  "properties": {
    "gn:admin1_code":"ESYE43",
    "gn:admin2_code":"46.0",
    "gn:admin3_code":"9311",
    "gn:asciiname":"Sykia",
    "gn:country_code":"GR",
    "gn:dem":233,
    "gn:feature_class":"P",
    "gn:feature_code":"PPL",
    "gn:name":"Syki\u00e1",
    "gn:population":2,
    "gn:timezone":"Europe/Athens",
    "iso:country":"GR",
    "name:ceb_x_preferred":[
        "Sykia"
    ],
    "name:ell_x_preferred":[
        "\u03a3\u03c5\u03ba\u03b9\u03ac"
    ],
    "name:eng_x_preferred":[
        "Sykia"
    ],
    "name:swe_x_preferred":[
        "Sykia"
    ],
    "name:und_x_variant":[
        "Siki\u00e1",
        "Sik\u00e9a",
        "Syki\u00e1"
    ],
    "wof:name":"Sykia",
    "wof:placetype":"locality",
    "wof:population":2
},
  "geometry": {"coordinates":[25.59966,35.04211],"type":"Point"}
}