{
  "type": "Feature",
  "properties": {
    "gn:gn_country":"GR",
    "gn:gn_fcode":"PPL",
    "gn:gn_pop":27,
    "gn:population":27,
    "iso:country":"GR",
    "name:ell_x_preferred":[
        "\u0395\u03bb\u03b5\u03c5\u03b8\u03b5\u03c1\u03bf\u03c7\u03ce\u03c1\u03b9"
    ],
    "name:ell_x_variant":[
        "\u0395\u03bb\u03b5\u03c5\u03b8\u03b5\u03c1\u03bf\u03c7\u03ce\u03c1\u03b9\u03bf\u03bd"
    ],
    "name:unk_x_variant":[
        "Eleftheroch\u00f3ri"
    ],
    "qs_pg:aaroncc":"GR",
    "qs_pg:gn_country":"GR",
    "qs_pg:gn_fcode":"PPL",
    "qs_pg:gn_pop":27,
    "qs_pg:name":"Eleftheroch\u00f3rion",
    "qs_pg:photos_9r":0,
    "qs_pg:photos_sr":0,
    "qs_pg:pop_sr":1,
    "qs_pg:qs_pg_placetype":"locality",
    "wof:name":"Eleftheroch\u00f3rion",
    "wof:placetype":"locality",
    "wof:population":27
},
  "geometry": {"coordinates":[22.36806,40.87972],"type":"Point"}
}