{
  "type": "Feature",
  "properties": {
    "gn:admin1_code":"ESYE42",
    "gn:admin2_code":"49.0",
    "gn:admin3_code":"9301",
    "gn:asciiname":"Skalados",
    "gn:country_code":"GR",
    "gn:dem":281,
    "gn:feature_class":"P",
    "gn:feature_code":"PPL",
    "gn:name":"Skal\u00e1dos",
    "gn:population":0,
    "gn:timezone":"Europe/Athens",
    "iso:country":"GR",
    "name:und_x_variant":[
        "Skal\u00e1dos",
        "\u03a3\u03ba\u03b1\u03bb\u03ac\u03b4\u03bf\u03c2"
    ],
    "wof:name":"Skalados",
    "wof:placetype":"locality"
},
  "geometry": {"coordinates":[25.16387000000001,37.59066],"type":"Point"}
}