{
  "type": "Feature",
  "properties": {
    "gn:admin1_code":"ESYE43",
    "gn:admin2_code":"43.0",
    "gn:admin3_code":"9322",
    "gn:asciiname":"Latziana",
    "gn:country_code":"GR",
    "gn:dem":225,
    "gn:feature_class":"P",
    "gn:feature_code":"PPL",
    "gn:name":"Latzian\u00e1",
    "gn:population":17,
    "gn:timezone":"Europe/Athens",
    "iso:country":"GR",
    "name:ell_x_preferred":[
        "\u039b\u03b1\u03c4\u03b6\u03b9\u03b1\u03bd\u03ac"
    ],
    "name:eng_x_preferred":[
        "Latziana"
    ],
    "name:und_x_variant":[
        "Lats\u00edana",
        "Latzian\u00e1"
    ],
    "wof:name":"Latziana",
    "wof:placetype":"locality",
    "wof:population":17
},
  "geometry": {"coordinates":[23.6972,35.43731],"type":"Point"}
}