{
  "type": "Feature",
  "properties": {
    "gn:admin1_code":"ESYE22",
    "gn:admin2_code":"27.0",
    "gn:admin3_code":"9120",
    "gn:asciiname":"Riza",
    "gn:country_code":"GR",
    "gn:dem":243,
    "gn:feature_class":"P",
    "gn:feature_code":"PPL",
    "gn:name":"R\u00edza",
    "gn:population":0,
    "gn:timezone":"Europe/Athens",
    "iso:country":"GR",
    "name:bel_x_preferred":[
        "\u0410\u0431\u043a\u043b\u0430\u0434 \u0456\u043a\u043e\u043d\u044b"
    ],
    "name:ell_x_preferred":[
        "R\u00edza"
    ],
    "name:ell_x_variant":[
        "\u03a1\u03af\u03b6\u03b1"
    ],
    "name:fin_x_preferred":[
        "Riisa"
    ],
    "name:hrv_x_preferred":[
        "Riza"
    ],
    "name:ita_x_preferred":[
        "Riza"
    ],
    "name:jpn_x_preferred":[
        "\u30ea\u30b6"
    ],
    "name:pol_x_preferred":[
        "Ryza"
    ],
    "name:rus_x_preferred":[
        "\u041e\u043a\u043b\u0430\u0434 \u0438\u043a\u043e\u043d\u044b"
    ],
    "name:ukr_x_preferred":[
        "\u0428\u0430\u0442\u0438 \u0456\u043a\u043e\u043d\u0438"
    ],
    "wof:name":"Riza",
    "wof:placetype":"locality"
},
  "geometry": {"coordinates":[20.46531,38.27164000000001],"type":"Point"}
}