{
  "type": "Feature",
  "properties": {
    "gn:admin1_code":"ESYE12",
    "gn:admin2_code":"13.0",
    "gn:admin3_code":"9027",
    "gn:asciiname":"Mesopotamo",
    "gn:country_code":"GR",
    "gn:dem":114,
    "gn:feature_class":"P",
    "gn:feature_code":"PPL",
    "gn:name":"Mesop\u00f3tamo",
    "gn:population":0,
    "gn:timezone":"Europe/Athens",
    "iso:country":"GR",
    "name:ell_x_preferred":[
        "\u039c\u03b5\u03c3\u03bf\u03c0\u03cc\u03c4\u03b1\u03bc\u03bf"
    ],
    "name:ell_x_variant":[
        "\u039c\u03b5\u03c3\u03bf\u03c0\u03cc\u03c4\u03b1\u03bc\u03bf\u03bd"
    ],
    "name:eng_x_preferred":[
        "Mesop\u00f3tamo"
    ],
    "name:und_x_variant":[
        "Mesop\u00f3tamon"
    ],
    "wof:name":"Mesopotamo",
    "wof:placetype":"locality"
},
  "geometry": {"coordinates":[23.43993,40.61433],"type":"Point"}
}