{
  "type": "Feature",
  "properties": {
    "gn:admin1_code":"ESYE11",
    "gn:admin2_code":"3.0",
    "gn:admin3_code":"9017",
    "gn:asciiname":"Lefki",
    "gn:country_code":"GR",
    "gn:dem":44,
    "gn:feature_class":"P",
    "gn:feature_code":"PPL",
    "gn:name":"L\u00e9fki",
    "gn:population":0,
    "gn:timezone":"Europe/Athens",
    "iso:country":"GR",
    "name:ell_x_preferred":[
        "L\u00e9fki"
    ],
    "name:ell_x_variant":[
        "\u039b\u03b5\u03cd\u03ba\u03b7"
    ],
    "name:und_x_variant":[
        "Bedel\u00ed-Chik",
        "L\u00e9vki"
    ],
    "wof:name":"Lefki",
    "wof:placetype":"locality"
},
  "geometry": {"coordinates":[24.87068,41.08174],"type":"Point"}
}