{
  "type": "Feature",
  "properties": {
    "gn:admin1_code":"ESYE25",
    "gn:admin2_code":"37.0",
    "gn:admin3_code":"9247",
    "gn:asciiname":"Kato Dhiminio",
    "gn:country_code":"GR",
    "gn:dem":4,
    "gn:feature_class":"P",
    "gn:feature_code":"PPL",
    "gn:name":"K\u00e1to Dhimini\u00f3",
    "gn:population":1201,
    "gn:timezone":"Europe/Athens",
    "iso:country":"GR",
    "name:ell_x_preferred":[
        "\u039a\u03ac\u03c4\u03c9 \u0394\u03b9\u03bc\u03b7\u03bd\u03b9\u03cc"
    ],
    "name:eng_x_preferred":[
        "Kato Diminio"
    ],
    "name:und_x_variant":[
        "K\u00e1to Dhimini\u00f3",
        "K\u00e1to Dhimini\u00f3n"
    ],
    "wof:name":"Kato Dhiminio",
    "wof:placetype":"locality",
    "wof:population":1201
},
  "geometry": {"coordinates":[22.73294,38.0249],"type":"Point"}
}