{
  "type": "Feature",
  "properties": {
    "gn:admin1_code":"ESYE41",
    "gn:asciiname":"Droutsoulas",
    "gn:country_code":"GR",
    "gn:dem":420,
    "gn:feature_class":"P",
    "gn:feature_code":"PPL",
    "gn:name":"Dro\u00fatsoulas",
    "gn:population":0,
    "gn:timezone":"Europe/Athens",
    "iso:country":"GR",
    "name:ell_x_preferred":[
        "Dro\u00fatsoulas"
    ],
    "name:ell_x_variant":[
        "\u0394\u03c1\u03bf\u03cd\u03c4\u03c3\u03bf\u03c5\u03bb\u03b1\u03c2"
    ],
    "wof:name":"Droutsoulas",
    "wof:placetype":"locality"
},
  "geometry": {"coordinates":[26.19186,37.60387],"type":"Point"}
}