{
  "type": "Feature",
  "properties": {
    "gn:gn_country":"GR",
    "gn:gn_fcode":"PPL",
    "gn:gn_pop":583,
    "gn:population":417,
    "iso:country":"GR",
    "name:ell_x_preferred":[
        "\u0386\u03bb\u03c9\u03c1\u03bf\u03c2"
    ],
    "name:eng_x_preferred":[
        "Aloros"
    ],
    "name:unk_x_variant":[
        "Ro\u00fadhinon"
    ],
    "qs_pg:aaroncc":"GR",
    "qs_pg:gn_country":"GR",
    "qs_pg:gn_fcode":"PPL",
    "qs_pg:gn_pop":583,
    "qs_pg:name":"Aloros",
    "qs_pg:name_adm0":"\u0395\u03bb\u03bb\u03ac\u03b4\u03b1",
    "qs_pg:name_adm1":"Macedonia and Thrace",
    "qs_pg:photos_9r":0,
    "qs_pg:photos_sr":0,
    "qs_pg:pop_sr":2,
    "qs_pg:qs_pg_placetype":"locality",
    "qs_pg:qs_pg_placetype_gp":"Town",
    "qs_pg:woe_adm0":23424833,
    "woe:adm0_id":23424833,
    "woe:name_adm0":"\u0395\u03bb\u03bb\u03ac\u03b4\u03b1",
    "woe:name_adm1":"Macedonia and Thrace",
    "woe:placetype":"Town",
    "wof:name":"Aloros",
    "wof:placetype":"locality",
    "wof:population":417
},
  "geometry": {"coordinates":[22.08528,40.92667],"type":"Point"}
}