{
  "type": "Feature",
  "properties": {
    "gn:population":1650,
    "iso:country":"GR",
    "name:ara_x_preferred":[
        "\u0645\u0627\u0646\u0648\u0644\u0627\u062f\u0627"
    ],
    "name:cat_x_preferred":[
        "Manolada"
    ],
    "name:ceb_x_preferred":[
        "Manol\u00e1s"
    ],
    "name:ell_x_preferred":[
        "\u039c\u03b1\u03bd\u03c9\u03bb\u03ac\u03b4\u03b1 \u0397\u03bb\u03b5\u03af\u03b1\u03c2"
    ],
    "name:ell_x_variant":[
        "\u039c\u03b1\u03bd\u03bf\u03bb\u03ac\u03c2",
        "\u039c\u03b1\u03bd\u03bf\u03bb\u03ac\u03b4\u03b1"
    ],
    "name:eng_x_preferred":[
        "Manolada"
    ],
    "name:nld_x_preferred":[
        "Manolada"
    ],
    "name:ron_x_preferred":[
        "Manolada"
    ],
    "name:rus_x_preferred":[
        "\u041c\u0430\u043d\u043e\u043b\u0430\u0441"
    ],
    "name:swe_x_preferred":[
        "Manol\u00e1s"
    ],
    "name:und_x_variant":[
        "Manol\u00e1da"
    ],
    "qs:a0":"Greece",
    "qs:a1":"*\u0394\u03a5\u03a4\u0399\u039a\u0397 \u0395\u039b\u039b\u0391\u0394\u0391",
    "qs:a1_alt":"DYTIKH ELLADA",
    "qs:a1r":"0",
    "qs:a2_alt":"HLEIA",
    "qs:adm0":"Greece",
    "qs:la_lc":"*",
    "qs:level":"locality",
    "qs:loc":"\u039c\u0391\u039d\u039f\u039b\u0391\u03a3",
    "qs:loc_alt":"MANOLAS",
    "qs:pop":0,
    "qs:type":"buffered point",
    "wd:wordcount":136,
    "wof:name":"\u039c\u0391\u039d\u039f\u039b\u0391\u03a3",
    "wof:placetype":"locality",
    "wof:population":1650
},
  "geometry": {"coordinates":[21.348299,38.047016],"type":"Point"}
}