{
  "type": "Feature",
  "properties": {
    "gn:admin1_code":"ESYE23",
    "gn:admin2_code":"38.0",
    "gn:admin3_code":"9131",
    "gn:asciiname":"Bartzavalaiika",
    "gn:country_code":"GR",
    "gn:dem":4,
    "gn:feature_class":"P",
    "gn:feature_code":"PPL",
    "gn:name":"Bartzavala\u00edika",
    "gn:population":0,
    "gn:timezone":"Europe/Athens",
    "iso:country":"GR",
    "name:ell_x_preferred":[
        "Bartzavala\u00edika"
    ],
    "name:ell_x_variant":[
        "\u039c\u03c0\u03b1\u03c1\u03c4\u03b6\u03b1\u03b2\u03b1\u03bb\u03b1\u03af\u03b9\u03ba\u03b1"
    ],
    "wof:name":"Bartzavalaiika",
    "wof:placetype":"locality"
},
  "geometry": {"coordinates":[21.42669,38.18158],"type":"Point"}
}