{
  "type": "Feature",
  "properties": {
    "gn:gn_country":"GR",
    "gn:gn_fcode":"PPL",
    "gn:gn_pop":90,
    "gn:population":73,
    "iso:country":"GR",
    "name:ell_x_preferred":[
        "\u0386\u03b3\u03b9\u03bf\u03c2 \u0391\u03bd\u03b4\u03c1\u03ad\u03b1\u03c2"
    ],
    "name:ell_x_variant":[
        "\u039b\u03b9\u03b2\u03b9\u03ac\u03c7\u03bf\u03b2\u03bf"
    ],
    "name:eng_x_preferred":[
        "Agios Andreas"
    ],
    "name:unk_x_variant":[
        "Livi\u00e1khovon"
    ],
    "qs_pg:aaroncc":"GR",
    "qs_pg:gn_country":"GR",
    "qs_pg:gn_fcode":"PPL",
    "qs_pg:gn_pop":90,
    "qs_pg:name":"Agios Andreas",
    "qs_pg:name_adm0":"\u0395\u03bb\u03bb\u03ac\u03b4\u03b1",
    "qs_pg:name_adm1":"Epirus and Western Macedonia",
    "qs_pg:photos_9r":0,
    "qs_pg:photos_sr":0,
    "qs_pg:pop_sr":1,
    "qs_pg:qs_pg_placetype":"locality",
    "qs_pg:qs_pg_placetype_gp":"Town",
    "qs_pg:woe_adm0":23424833,
    "woe:adm0_id":23424833,
    "woe:name_adm0":"\u0395\u03bb\u03bb\u03ac\u03b4\u03b1",
    "woe:name_adm1":"Epirus and Western Macedonia",
    "woe:placetype":"Town",
    "wof:name":"Agios Andreas",
    "wof:placetype":"locality",
    "wof:population":73
},
  "geometry": {"coordinates":[20.70861,39.47083],"type":"Point"}
}