{
  "type": "Feature",
  "properties": {
    "gn:admin1_code":"ESYE23",
    "gn:admin2_code":"31.0",
    "gn:admin3_code":"9123",
    "gn:asciiname":"Skalitina",
    "gn:country_code":"GR",
    "gn:dem":715,
    "gn:feature_class":"P",
    "gn:feature_code":"PPL",
    "gn:name":"Skalit\u00edna",
    "gn:population":23,
    "gn:timezone":"Europe/Athens",
    "iso:country":"GR",
    "name:ell_x_preferred":[
        "\u03a3\u03ba\u03b1\u03bb\u03b9\u03c4\u03af\u03bd\u03b1"
    ],
    "name:eng_x_preferred":[
        "Skalitina"
    ],
    "wof:name":"Skalitina",
    "wof:placetype":"locality",
    "wof:population":23
},
  "geometry": {"coordinates":[21.49778,38.80047],"type":"Point"}
}