{
  "type": "Feature",
  "properties": {
    "gn:admin1_code":"ESYE31",
    "gn:admin2_code":"445406.0",
    "gn:admin3_code":"9227",
    "gn:asciiname":"Drosopigi",
    "gn:country_code":"GR",
    "gn:dem":567,
    "gn:feature_class":"P",
    "gn:feature_code":"PPL",
    "gn:name":"Drosopig\u00ed",
    "gn:population":156,
    "gn:timezone":"Europe/Athens",
    "iso:country":"GR",
    "name:ceb_x_preferred":[
        "Drosopigi"
    ],
    "name:ell_x_preferred":[
        "\u0394\u03c1\u03bf\u03c3\u03bf\u03c0\u03b7\u03b3\u03ae"
    ],
    "name:eng_x_preferred":[
        "Drosopigi"
    ],
    "name:swe_x_preferred":[
        "Drosopigi"
    ],
    "name:und_x_variant":[
        "Drosopighi"
    ],
    "wof:name":"Drosopigi",
    "wof:placetype":"locality",
    "wof:population":156
},
  "geometry": {"coordinates":[23.8287,38.16733],"type":"Point"}
}