{
  "type": "Feature",
  "properties": {
    "gn:admin1_code":"ESYE23",
    "gn:admin2_code":"39.0",
    "gn:admin3_code":"9141.0",
    "gn:asciiname":"Itia",
    "gn:country_code":"GR",
    "gn:dem":23,
    "gn:feature_class":"P",
    "gn:feature_code":"PPL",
    "gn:name":"Iti\u00e1",
    "gn:population":0,
    "gn:timezone":"Europe/Athens",
    "iso:country":"GR",
    "name:ell_x_preferred":[
        "\u0399\u03c4\u03b9\u03ac"
    ],
    "name:nld_x_preferred":[
        "Itia"
    ],
    "name:por_x_preferred":[
        "Itia"
    ],
    "wof:name":"Itia",
    "wof:placetype":"locality"
},
  "geometry": {"coordinates":[21.41377,37.69513],"type":"Point"}
}