{
  "type": "Feature",
  "properties": {
    "gn:admin1_code":"ESYE43",
    "gn:admin2_code":"43.0",
    "gn:admin3_code":"9325",
    "gn:asciiname":"Somata",
    "gn:country_code":"GR",
    "gn:dem":492,
    "gn:feature_class":"P",
    "gn:feature_code":"PPL",
    "gn:name":"Somat\u00e1",
    "gn:population":0,
    "gn:timezone":"Europe/Athens",
    "iso:country":"GR",
    "name:ell_x_preferred":[
        "Somat\u00e1"
    ],
    "name:ell_x_variant":[
        "\u03a3\u03c9\u03bc\u03b1\u03c4\u03ac",
        "Sinoikism\u00f3s Somat\u00e1s"
    ],
    "wof:name":"Somata",
    "wof:placetype":"locality"
},
  "geometry": {"coordinates":[24.01502,35.40926],"type":"Point"}
}