{
  "type": "Feature",
  "properties": {
    "gn:admin1_code":"ESYE23",
    "gn:admin2_code":"31.0",
    "gn:admin3_code":"9127",
    "gn:asciiname":"Karvailaiika",
    "gn:country_code":"GR",
    "gn:dem":62,
    "gn:feature_class":"P",
    "gn:feature_code":"PPL",
    "gn:name":"Karvaila\u00edika",
    "gn:population":0,
    "gn:timezone":"Europe/Athens",
    "iso:country":"GR",
    "name:ell_x_preferred":[
        "\u039a\u03b1\u03c1\u03b2\u03b1\u03b9\u03bb\u03b1\u03af\u03b9\u03ba\u03b1"
    ],
    "name:und_x_variant":[
        "Karal\u00e9\u00efka",
        "Karvaila\u00edika"
    ],
    "wof:name":"Karvailaiika",
    "wof:placetype":"locality"
},
  "geometry": {"coordinates":[21.53783,38.3875],"type":"Point"}
}