{
  "type": "Feature",
  "properties": {
    "gn:admin1_code":"ESYE23",
    "gn:admin2_code":"39.0",
    "gn:admin3_code":"9136",
    "gn:asciiname":"Platia",
    "gn:country_code":"GR",
    "gn:dem":567,
    "gn:feature_class":"P",
    "gn:feature_code":"PPL",
    "gn:name":"Plat\u00eda",
    "gn:population":6,
    "gn:timezone":"Europe/Athens",
    "iso:country":"GR",
    "name:ell_x_preferred":[
        "\u03a0\u03bb\u03b1\u03c4\u03b5\u03af\u03b1"
    ],
    "name:eng_x_preferred":[
        "Plateia"
    ],
    "wof:name":"Platia",
    "wof:placetype":"locality",
    "wof:population":6
},
  "geometry": {"coordinates":[21.86464,37.41332],"type":"Point"}
}