{
  "type": "Feature",
  "properties": {
    "gn:admin1_code":"ESYE43",
    "gn:admin2_code":"43.0",
    "gn:admin3_code":"9323",
    "gn:asciiname":"Marouliachana",
    "gn:country_code":"GR",
    "gn:dem":107,
    "gn:feature_class":"P",
    "gn:feature_code":"PPL",
    "gn:name":"Marouliachan\u00e1",
    "gn:population":0,
    "gn:timezone":"Europe/Athens",
    "iso:country":"GR",
    "name:ell_x_preferred":[
        "Marouliachan\u00e1"
    ],
    "name:ell_x_variant":[
        "\u039c\u03b1\u03c1\u03bf\u03c5\u03bb\u03b9\u03b1\u03c7\u03b1\u03bd\u03ac"
    ],
    "wof:name":"Marouliachana",
    "wof:placetype":"locality"
},
  "geometry": {"coordinates":[23.83162,35.50005],"type":"Point"}
}