{
  "type": "Feature",
  "properties": {
    "gn:admin1_code":"ESYE22",
    "gn:admin2_code":"25.0",
    "gn:admin3_code":"9118",
    "gn:asciiname":"Peroulion",
    "gn:country_code":"GR",
    "gn:dem":63,
    "gn:feature_class":"P",
    "gn:feature_code":"PPL",
    "gn:name":"Pero\u00falion",
    "gn:population":39,
    "gn:timezone":"Europe/Athens",
    "iso:country":"GR",
    "name:ell_x_preferred":[
        "\u03a0\u03b5\u03c1\u03bf\u03cd\u03bb\u03b9"
    ],
    "name:eng_x_preferred":[
        "Perouli"
    ],
    "name:und_x_variant":[
        "Pero\u00fali",
        "Pelo\u00fani",
        "Pero\u00falion"
    ],
    "wof:name":"Peroulion",
    "wof:placetype":"locality",
    "wof:population":39
},
  "geometry": {"coordinates":[19.8638,39.80072],"type":"Point"}
}