{
  "type": "Feature",
  "properties": {
    "gn:admin1_code":"ESYE41",
    "gn:admin2_code":"51.0",
    "gn:admin3_code":"9263",
    "gn:asciiname":"Ayios Dhimitrios",
    "gn:cc2":"GR",
    "gn:country_code":"GR",
    "gn:dem":134,
    "gn:feature_class":"P",
    "gn:feature_code":"PPL",
    "gn:name":"\u00c1yios Dhim\u00edtrios",
    "gn:population":0,
    "gn:timezone":"Europe/Athens",
    "iso:country":"GR",
    "name:ell_x_preferred":[
        "\u0386\u03b3\u03b9\u03bf\u03c2 \u0394\u03b7\u03bc\u03ae\u03c4\u03c1\u03b9\u03bf\u03c2"
    ],
    "name:und_x_variant":[
        "Ler\u00e1",
        "\u00c1yios Dhim\u00edtrios"
    ],
    "wof:name":"Ayios Dhimitrios",
    "wof:placetype":"locality"
},
  "geometry": {"coordinates":[25.15388,39.91239],"type":"Point"}
}