{
  "type": "Feature",
  "properties": {
    "gn:admin1_code":"ESYE24",
    "gn:admin2_code":"34.0",
    "gn:admin3_code":"9151",
    "gn:asciiname":"Elaiochori",
    "gn:country_code":"GR",
    "gn:dem":224,
    "gn:feature_class":"P",
    "gn:feature_code":"PPL",
    "gn:name":"Elaioch\u00f3ri",
    "gn:population":0,
    "gn:timezone":"Europe/Athens",
    "iso:country":"GR",
    "name:ell_x_preferred":[
        "Elaioch\u00f3ri"
    ],
    "name:ell_x_variant":[
        "\u0395\u03bb\u03b1\u03b9\u03bf\u03c7\u03ce\u03c1\u03b9",
        "Elaioch\u00f3rion",
        "\u0395\u03bb\u03b1\u03b9\u03bf\u03c7\u03ce\u03c1\u03b9\u03bf\u03bd"
    ],
    "name:und_x_variant":[
        "Karal\u00eddhes",
        "Elaiokh\u00f3rion"
    ],
    "wof:name":"Elaiochori",
    "wof:placetype":"locality"
},
  "geometry": {"coordinates":[24.24803,38.21803],"type":"Point"}
}