{
  "type": "Feature",
  "properties": {
    "gn:admin1_code":"ESYE14",
    "gn:admin2_code":"24.0",
    "gn:admin3_code":"9104",
    "gn:asciiname":"Kokkotoi",
    "gn:country_code":"GR",
    "gn:dem":491,
    "gn:feature_class":"P",
    "gn:feature_code":"PPL",
    "gn:name":"Kokkoto\u00ed",
    "gn:population":180,
    "gn:timezone":"Europe/Athens",
    "iso:country":"GR",
    "name:ell_x_preferred":[
        "\u039a\u03bf\u03ba\u03ba\u03c9\u03c4\u03bf\u03af"
    ],
    "name:eng_x_preferred":[
        "Kokkotoi"
    ],
    "name:und_x_variant":[
        "Kokot\u00ed",
        "Kokkoto\u00ed"
    ],
    "wof:name":"Kokkotoi",
    "wof:placetype":"locality",
    "wof:population":180
},
  "geometry": {"coordinates":[22.77462,39.07874],"type":"Point"}
}