{
  "type": "Feature",
  "properties": {
    "gn:country":"GR",
    "gn:fcode":"PPL",
    "gn:population":154,
    "iso:country":"GR",
    "name:ell_x_preferred":[
        "\u03a1\u03b5\u03c0\u03b5\u03c4\u03af\u03c4\u03c3\u03b1"
    ],
    "name:eng_x_preferred":[
        "Repetista"
    ],
    "name:und_x_variant":[
        "Repet\u00edsta"
    ],
    "qs_pg:aaroncc":"GR",
    "qs_pg:gn_country":"GR",
    "qs_pg:gn_fcode":"PPL",
    "qs_pg:gn_pop":154,
    "qs_pg:name":"Repetista",
    "qs_pg:name_adm0":"\u0395\u03bb\u03bb\u03ac\u03b4\u03b1",
    "qs_pg:name_adm1":"Epirus and Western Macedonia",
    "qs_pg:photos_9r":0,
    "qs_pg:photos_sr":0,
    "qs_pg:pop_sr":1,
    "qs_pg:qs_pg_placetype":"locality",
    "qs_pg:qs_pg_placetype_gp":"Town",
    "qs_pg:woe_adm0":23424833,
    "woe:adm0_id":23424833,
    "woe:name_adm0":"\u0395\u03bb\u03bb\u03ac\u03b4\u03b1",
    "woe:name_adm1":"Epirus and Western Macedonia",
    "woe:placetype":"Town",
    "wof:name":"Repetista",
    "wof:placetype":"locality",
    "wof:population":100
},
  "geometry": {"coordinates":[20.58056,39.84528],"type":"Point"}
}