{
  "type": "Feature",
  "properties": {
    "gn:admin1_code":"ESYE31",
    "gn:admin2_code":"445406.0",
    "gn:admin3_code":"9219.0",
    "gn:asciiname":"Koritizes",
    "gn:country_code":"GR",
    "gn:dem":143,
    "gn:feature_class":"P",
    "gn:feature_code":"PPL",
    "gn:name":"Korit\u00edzes",
    "gn:population":0,
    "gn:timezone":"Europe/Athens",
    "iso:country":"GR",
    "name:ell_x_preferred":[
        "Korit\u00edzes"
    ],
    "name:ell_x_variant":[
        "\u039a\u03bf\u03c1\u03b9\u03c4\u03af\u03b6\u03b5\u03c2"
    ],
    "wof:name":"Koritizes",
    "wof:placetype":"locality"
},
  "geometry": {"coordinates":[24.04761,37.81025],"type":"Point"}
}