{
  "type": "Feature",
  "properties": {
    "gn:country":"GR",
    "gn:fcode":"PPL",
    "gn:population":426,
    "iso:country":"GR",
    "name:ell_x_preferred":[
        "Mil\u00e9a"
    ],
    "name:ell_x_variant":[
        "\u039c\u03b7\u03bb\u03b9\u03ac",
        "Mili\u00e1"
    ],
    "name:und_x_variant":[
        "Mesa\u00eda Mili\u00e1"
    ],
    "qs_pg:aaroncc":"GR",
    "qs_pg:gn_country":"GR",
    "qs_pg:gn_fcode":"PPL",
    "qs_pg:gn_pop":426,
    "qs_pg:name":"Mil\u00e9a",
    "qs_pg:photos_9r":0,
    "qs_pg:photos_sr":0,
    "qs_pg:pop_sr":2,
    "qs_pg:qs_pg_placetype":"locality",
    "wof:name":"Mil\u00e9a",
    "wof:placetype":"locality",
    "wof:population":426
},
  "geometry": {"coordinates":[22.29583,40.25028],"type":"Point"}
}