{
  "type": "Feature",
  "properties": {
    "gn:admin1_code":"ESYE43",
    "gn:admin2_code":"43.0",
    "gn:admin3_code":"9324",
    "gn:asciiname":"Palaia Agia Roumeli",
    "gn:country_code":"GR",
    "gn:dem":53,
    "gn:feature_class":"P",
    "gn:feature_code":"PPL",
    "gn:name":"Palai\u00e1 Ag\u00eda Roum\u00e9li",
    "gn:population":0,
    "gn:timezone":"Europe/Athens",
    "iso:country":"GR",
    "name:ell_x_preferred":[
        "Palai\u00e1 Ag\u00eda Roum\u00e9li"
    ],
    "name:ell_x_variant":[
        "\u03a0\u03b1\u03bb\u03b1\u03b9\u03ac \u0391\u03b3\u03af\u03b1 \u03a1\u03bf\u03c5\u03bc\u03ad\u03bb\u03b7"
    ],
    "wof:name":"Palaia Agia Roumeli",
    "wof:placetype":"locality"
},
  "geometry": {"coordinates":[23.96445,35.23938],"type":"Point"}
}