{
  "type": "Feature",
  "properties": {
    "gn:admin1_code":"ESYE14",
    "gn:admin2_code":"23.0",
    "gn:admin3_code":"9094",
    "gn:asciiname":"Meligos",
    "gn:country_code":"GR",
    "gn:dem":410,
    "gn:feature_class":"P",
    "gn:feature_code":"PPL",
    "gn:name":"Melig\u00f3s",
    "gn:population":36,
    "gn:timezone":"Europe/Athens",
    "iso:country":"GR",
    "name:ell_x_preferred":[
        "\u039c\u03b5\u03bb\u03b9\u03b3\u03cc\u03c2"
    ],
    "name:eng_x_preferred":[
        "Meligos"
    ],
    "wof:name":"Meligos",
    "wof:placetype":"locality",
    "wof:population":36
},
  "geometry": {"coordinates":[21.6512,39.40966],"type":"Point"}
}