{
  "type": "Feature",
  "properties": {
    "gn:country":"GR",
    "gn:fcode":"ADM3",
    "gn:population":5983,
    "iso:country":"GR",
    "name:cat_x_preferred":[
        "Viannos"
    ],
    "name:ceb_x_preferred":[
        "Dimos Viannos"
    ],
    "name:deu_x_preferred":[
        "Viannos"
    ],
    "name:ell_x_preferred":[
        "\u0392\u03b9\u03ac\u03bd\u03bd\u03bf\u03c5"
    ],
    "name:ell_x_variant":[
        "\u0394\u03ae\u03bc\u03bf\u03c2 \u0392\u03b9\u03ac\u03bd\u03bd\u03bf\u03c5"
    ],
    "name:fin_x_preferred":[
        "Vi\u00e1nnos"
    ],
    "name:fra_x_preferred":[
        "Vi\u00e1nnos"
    ],
    "name:ita_x_preferred":[
        "Viannos"
    ],
    "name:nld_x_preferred":[
        "Viannos"
    ],
    "name:nno_x_preferred":[
        "Vi\u00e1nnos"
    ],
    "name:pol_x_preferred":[
        "Wianos"
    ],
    "name:por_x_preferred":[
        "Vi\u00e1nnos"
    ],
    "name:rus_x_preferred":[
        "\u0412\u044c\u044f\u043d\u043e\u0441"
    ],
    "name:spa_x_preferred":[
        "Viannos"
    ],
    "name:swe_x_preferred":[
        "Dimos Viannos"
    ],
    "name:tur_x_preferred":[
        "Viannos"
    ],
    "name:vie_x_preferred":[
        "Viannos"
    ],
    "qs_pg:aaroncc":"GR",
    "qs_pg:gn_country":"GR",
    "qs_pg:gn_fcode":"ADM3",
    "qs_pg:gn_pop":5983,
    "qs_pg:name":"Viannos",
    "qs_pg:name_adm0":"\u0395\u03bb\u03bb\u03ac\u03b4\u03b1",
    "qs_pg:name_adm1":"Crete",
    "qs_pg:photos_9k":1,
    "qs_pg:photos_9r":1,
    "qs_pg:photos_all":2,
    "qs_pg:photos_sr":0,
    "qs_pg:pop_sr":5,
    "qs_pg:qs_pg_placetype":"locality",
    "qs_pg:qs_pg_placetype_gp":"Town",
    "qs_pg:woe_adm0":23424833,
    "woe:adm0_id":23424833,
    "woe:name_adm0":"\u0395\u03bb\u03bb\u03ac\u03b4\u03b1",
    "woe:name_adm1":"Crete",
    "woe:placetype":"Town",
    "wof:name":"Viannos",
    "wof:placetype":"locality",
    "wof:population":5983
},
  "geometry": {"coordinates":[25.42553,35.04517],"type":"Point"}
}