{
  "type": "Feature",
  "properties": {
    "gn:admin1_code":"ESYE22",
    "gn:admin2_code":"27.0",
    "gn:admin3_code":"9120",
    "gn:asciiname":"Kornelos",
    "gn:country_code":"GR",
    "gn:dem":355,
    "gn:feature_class":"P",
    "gn:feature_code":"PPL",
    "gn:name":"Korn\u00e9los",
    "gn:population":0,
    "gn:timezone":"Europe/Athens",
    "iso:country":"GR",
    "name:ell_x_preferred":[
        "Korn\u00e9los"
    ],
    "name:ell_x_variant":[
        "\u039a\u03bf\u03c1\u03bd\u03ad\u03bb\u03bf\u03c2"
    ],
    "name:und_x_variant":[
        "Korn\u00e9lou",
        "Korn\u00e9llos"
    ],
    "wof:name":"Kornelos",
    "wof:placetype":"locality"
},
  "geometry": {"coordinates":[20.76317,38.10986],"type":"Point"}
}