{
  "type": "Feature",
  "properties": {
    "gn:admin1_code":"ESYE42",
    "gn:admin2_code":"49.0",
    "gn:admin3_code":"9300",
    "gn:asciiname":"Chalandriani",
    "gn:country_code":"GR",
    "gn:dem":236,
    "gn:feature_class":"P",
    "gn:feature_code":"PPL",
    "gn:name":"Chalandrian\u00ed",
    "gn:population":0,
    "gn:timezone":"Europe/Athens",
    "iso:country":"GR",
    "name:ell_x_preferred":[
        "Chalandrian\u00ed"
    ],
    "name:ell_x_variant":[
        "\u03a7\u03b1\u03bb\u03b1\u03bd\u03b4\u03c1\u03b9\u03b1\u03bd\u03ae"
    ],
    "name:und_x_variant":[
        "Khalandhrian\u00ed",
        "Khalandrian\u00ed"
    ],
    "wof:name":"Chalandriani",
    "wof:placetype":"locality"
},
  "geometry": {"coordinates":[24.93433,37.48316],"type":"Point"}
}