{
  "type": "Feature",
  "properties": {
    "gn:admin1_code":"ESYE31",
    "gn:admin2_code":"445406.0",
    "gn:admin3_code":"9218.0",
    "gn:asciiname":"Paradeisos",
    "gn:country_code":"GR",
    "gn:dem":102,
    "gn:feature_class":"P",
    "gn:feature_code":"PPL",
    "gn:name":"Par\u00e1deisos",
    "gn:population":0,
    "gn:timezone":"Europe/Athens",
    "iso:country":"GR",
    "name:ell_x_preferred":[
        "Par\u00e1deisos"
    ],
    "name:ell_x_variant":[
        "\u03a0\u03b1\u03c1\u03ac\u03b4\u03b5\u03b9\u03c3\u03bf\u03c2"
    ],
    "wof:name":"Paradeisos",
    "wof:placetype":"locality"
},
  "geometry": {"coordinates":[23.87675,37.85305],"type":"Point"}
}