{
  "type": "Feature",
  "properties": {
    "gn:admin1_code":"ESYE12",
    "gn:admin2_code":"5.0",
    "gn:admin3_code":"9050",
    "gn:asciiname":"Agios Dimitrios",
    "gn:country_code":"GR",
    "gn:dem":73,
    "gn:feature_class":"P",
    "gn:feature_code":"PPL",
    "gn:name":"\u00c1gios Dim\u00edtrios",
    "gn:population":292,
    "gn:timezone":"Europe/Athens",
    "iso:country":"GR",
    "name:bul_x_preferred":[
        "\u0421\u0442\u0430\u0440\u0430 \u0431\u0430\u043d\u044f"
    ],
    "name:ell_x_historical":[
        "\u03a0\u03b1\u03bb\u03b7\u03cc\u03c4\u03c1\u03bf"
    ],
    "name:ell_x_preferred":[
        "\u0386\u03b3\u03b9\u03bf\u03c2 \u0394\u03b7\u03bc\u03ae\u03c4\u03c1\u03b9\u03bf\u03c2"
    ],
    "name:ell_x_variant":[
        "\u00c1gios Dim\u00edtrios",
        "\u03a0\u03b1\u03bb\u03b7\u03cc\u03c4\u03c1\u03bf"
    ],
    "name:eng_x_historical":[
        "Paliotro"
    ],
    "name:eng_x_preferred":[
        "Agios Dimitrios"
    ],
    "name:eng_x_variant":[
        "Paliotro"
    ],
    "name:und_x_variant":[
        "Pali\u00f3stros",
        "Pali\u00f3tros",
        "Pali\u00f3trous",
        "\u00c1yios Dhim\u00edtrios"
    ],
    "wof:name":"Agios Dimitrios",
    "wof:placetype":"locality",
    "wof:population":292
},
  "geometry": {"coordinates":[23.70557,40.88435],"type":"Point"}
}