{
  "type": "Feature",
  "properties": {
    "gn:admin1_code":"ESYE25",
    "gn:admin2_code":"36.0",
    "gn:admin3_code":"9234",
    "gn:asciiname":"Koutroumbaiika",
    "gn:country_code":"GR",
    "gn:dem":273,
    "gn:feature_class":"P",
    "gn:feature_code":"PPL",
    "gn:name":"Koutroumba\u00edika",
    "gn:population":8,
    "gn:timezone":"Europe/Athens",
    "iso:country":"GR",
    "name:ell_x_preferred":[
        "\u039a\u03bf\u03c5\u03c4\u03c1\u03bf\u03c5\u03bc\u03c0\u03ad\u03b9\u03ba\u03b1"
    ],
    "name:ell_x_variant":[
        "\u039a\u03bf\u03c5\u03c4\u03c1\u03bf\u03c5\u03bc\u03c0\u03b1\u03af\u03b9\u03ba\u03b1"
    ],
    "name:eng_x_preferred":[
        "Koutroumpeiika"
    ],
    "name:eng_x_variant":[
        "Koutroumpaiika"
    ],
    "name:und_x_variant":[
        "Koutroumb\u00e9\u00efka",
        "Koutroumba\u00edika"
    ],
    "wof:name":"Koutroumbaiika",
    "wof:placetype":"locality",
    "wof:population":8
},
  "geometry": {"coordinates":[23.16392,37.55155],"type":"Point"}
}