{
  "type": "Feature",
  "properties": {
    "gn:admin1_code":"ESYE25",
    "gn:admin2_code":"42.0",
    "gn:admin3_code":"9252",
    "gn:asciiname":"Yeoryitsion",
    "gn:cc2":"GR",
    "gn:country_code":"GR",
    "gn:dem":868,
    "gn:feature_class":"P",
    "gn:feature_code":"PPL",
    "gn:name":"Yeory\u00edtsion",
    "gn:population":0,
    "gn:timezone":"Europe/Athens",
    "iso:country":"GR",
    "name:ell_x_preferred":[
        "\u0393\u03b5\u03c9\u03c1\u03b3\u03af\u03c4\u03c3\u03b9"
    ],
    "name:und_x_variant":[
        "Yeory\u00edtsi",
        "Yeor\u00edtsi",
        "Yeory\u00edtsion"
    ],
    "wof:name":"Yeoryitsion",
    "wof:placetype":"locality"
},
  "geometry": {"coordinates":[22.27654,37.1914],"type":"Point"}
}