{
  "type": "Feature",
  "properties": {
    "gn:admin1_code":"ESYE11",
    "gn:admin2_code":"2.0",
    "gn:admin3_code":"9019",
    "gn:asciiname":"Passos",
    "gn:country_code":"GR",
    "gn:dem":49,
    "gn:feature_class":"P",
    "gn:feature_code":"PPL",
    "gn:name":"P\u00e1ssos",
    "gn:population":0,
    "gn:timezone":"Europe/Athens",
    "iso:country":"GR",
    "name:ceb_x_preferred":[
        "Passos"
    ],
    "name:deu_x_preferred":[
        "Passos"
    ],
    "name:ell_x_preferred":[
        "\u03a0\u03ac\u03c3\u03c3\u03bf\u03c2"
    ],
    "name:ell_x_variant":[
        "P\u00e1ssos"
    ],
    "name:fas_x_preferred":[
        "\u067e\u0627\u0633\u0648\u0633"
    ],
    "name:fra_x_preferred":[
        "Passos"
    ],
    "name:heb_x_preferred":[
        "\u05e4\u05d0\u05e1\u05d5\u05e1"
    ],
    "name:nld_x_preferred":[
        "Passos"
    ],
    "name:pol_x_preferred":[
        "Passos"
    ],
    "name:por_x_preferred":[
        "Passos"
    ],
    "name:rus_x_preferred":[
        "\u041f\u0430\u0441\u0441\u0443\u0448"
    ],
    "name:swe_x_preferred":[
        "Passos"
    ],
    "name:ukr_x_preferred":[
        "\u041f\u0430\u0441\u0441\u0443\u0448"
    ],
    "wof:name":"Passos",
    "wof:placetype":"locality"
},
  "geometry": {"coordinates":[25.5839,41.09569],"type":"Point"}
}