{
  "type": "Feature",
  "properties": {
    "gn:admin1_code":"ESYE14",
    "gn:admin2_code":"23.0",
    "gn:admin3_code":"9094",
    "gn:asciiname":"Zamanatiko",
    "gn:country_code":"GR",
    "gn:dem":806,
    "gn:feature_class":"P",
    "gn:feature_code":"PPL",
    "gn:name":"Zaman\u00e1tiko",
    "gn:population":0,
    "gn:timezone":"Europe/Athens",
    "iso:country":"GR",
    "name:ell_x_preferred":[
        "Zaman\u00e1tiko"
    ],
    "name:ell_x_variant":[
        "\u0396\u03b1\u03bc\u03b1\u03bd\u03ac\u03c4\u03b9\u03ba\u03bf"
    ],
    "wof:name":"Zamanatiko",
    "wof:placetype":"locality"
},
  "geometry": {"coordinates":[21.59006,39.34642],"type":"Point"}
}