{
  "type": "Feature",
  "properties": {
    "gn:admin1_code":"ESYE23",
    "gn:admin2_code":"38.0",
    "gn:admin3_code":"9130",
    "gn:asciiname":"Peristera",
    "gn:country_code":"GR",
    "gn:dem":1027,
    "gn:feature_class":"P",
    "gn:feature_code":"PPL",
    "gn:name":"Perist\u00e9ra",
    "gn:population":0,
    "gn:timezone":"Europe/Athens",
    "iso:country":"GR",
    "name:ell_x_preferred":[
        "Perist\u00e9ra"
    ],
    "name:ell_x_variant":[
        "\u03a0\u03b5\u03c1\u03b9\u03c3\u03c4\u03ad\u03c1\u03b1"
    ],
    "wof:name":"Peristera",
    "wof:placetype":"locality"
},
  "geometry": {"coordinates":[22.24628,38.02192],"type":"Point"}
}