{
  "type": "Feature",
  "properties": {
    "gn:admin1_code":"ESYE23",
    "gn:admin2_code":"38.0",
    "gn:admin3_code":"9130",
    "gn:asciiname":"Peristera",
    "gn:country_code":"GR",
    "gn:dem":1027,
    "gn:feature_class":"P",
    "gn:feature_code":"PPL",
    "gn:name":"Perist\u00e9ra",
    "gn:population":0,
    "gn:timezone":"Europe/Athens",
    "iso:country":"GR",
    "name:ceb_x_preferred":[
        "Nis\u00ed Perist\u00e9ra"
    ],
    "name:ell_x_preferred":[
        "Perist\u00e9ra"
    ],
    "name:ell_x_variant":[
        "\u03a0\u03b5\u03c1\u03b9\u03c3\u03c4\u03ad\u03c1\u03b1",
        "\u03a0\u03b5\u03c1\u03b9\u03c3\u03c4\u03ad\u03c1\u03b1 \u0391\u03bb\u03bf\u03bd\u03bd\u03ae\u03c3\u03bf\u03c5"
    ],
    "name:fin_x_preferred":[
        "Perist\u00e9ra"
    ],
    "name:fra_x_preferred":[
        "Peristera"
    ],
    "name:glg_x_preferred":[
        "Peristera"
    ],
    "name:heb_x_preferred":[
        "\u05e4\u05e8\u05d9\u05e1\u05d8\u05e8\u05d4"
    ],
    "name:nno_x_preferred":[
        "Perist\u00e9ra"
    ],
    "name:por_x_preferred":[
        "Peristera"
    ],
    "name:rus_x_preferred":[
        "\u041f\u0435\u0440\u0438\u0441\u0442\u0435\u0440\u0430"
    ],
    "name:spa_x_preferred":[
        "Peristera"
    ],
    "name:swe_x_preferred":[
        "Nis\u00ed Perist\u00e9ra"
    ],
    "name:tur_x_preferred":[
        "G\u00fcvercin Adas\u0131"
    ],
    "name:ukr_x_preferred":[
        "\u041f\u0435\u0440\u0456\u0441\u0442\u0435\u0440\u0430"
    ],
    "name:zho_x_preferred":[
        "\u6d3e\u91cc\u65af\u6cf0\u62c9\u5cf6"
    ],
    "wof:name":"Peristera",
    "wof:placetype":"locality"
},
  "geometry": {"coordinates":[22.24628,38.02192],"type":"Point"}
}