{
  "type": "Feature",
  "properties": {
    "gn:admin1_code":"ESYE13",
    "gn:admin2_code":"9.0",
    "gn:admin3_code":"9064",
    "gn:asciiname":"Kato Ptelea",
    "gn:country_code":"GR",
    "gn:dem":810,
    "gn:feature_class":"P",
    "gn:feature_code":"PPL",
    "gn:name":"K\u00e1to Ptel\u00e9a",
    "gn:population":57,
    "gn:timezone":"Europe/Athens",
    "iso:country":"GR",
    "name:ell_x_preferred":[
        "\u039a\u03ac\u03c4\u03c9 \u03a0\u03c4\u03b5\u03bb\u03ad\u03b1"
    ],
    "name:eng_x_preferred":[
        "Kato Ptelea"
    ],
    "name:und_x_variant":[
        "K\u00e1to Fteli\u00e1",
        "K\u00e1to Ptel\u00e9a"
    ],
    "wof:name":"Kato Ptelea",
    "wof:placetype":"locality",
    "wof:population":57
},
  "geometry": {"coordinates":[21.07312,40.46642],"type":"Point"}
}