{
  "type": "Feature",
  "properties": {
    "gn:admin1_code":"ESYE41",
    "gn:asciiname":"Oxea",
    "gn:country_code":"GR",
    "gn:dem":510,
    "gn:feature_class":"P",
    "gn:feature_code":"PPL",
    "gn:name":"Ox\u00e9a",
    "gn:population":0,
    "gn:timezone":"Europe/Athens",
    "iso:country":"GR",
    "name:ell_x_preferred":[
        "Ox\u00e9a"
    ],
    "name:ell_x_variant":[
        "\u039f\u03be\u03ad\u03b1"
    ],
    "wof:name":"Oxea",
    "wof:placetype":"locality"
},
  "geometry": {"coordinates":[26.29328,37.6409],"type":"Point"}
}