{
  "type": "Feature",
  "properties": {
    "gn:admin1_code":"ESYE43",
    "gn:admin2_code":"43.0",
    "gn:admin3_code":"9322",
    "gn:asciiname":"Karefiliana",
    "gn:country_code":"GR",
    "gn:dem":119,
    "gn:feature_class":"P",
    "gn:feature_code":"PPL",
    "gn:name":"Karefilian\u00e1",
    "gn:population":55,
    "gn:timezone":"Europe/Athens",
    "iso:country":"GR",
    "name:ell_x_preferred":[
        "\u039a\u03b1\u03c1\u03b5\u03c6\u03b9\u03bb\u03b9\u03b1\u03bd\u03ac"
    ],
    "name:eng_x_preferred":[
        "Karefiliana"
    ],
    "name:und_x_variant":[
        "Karafiliann\u00e1",
        "Karefilian\u00e1"
    ],
    "wof:name":"Karefiliana",
    "wof:placetype":"locality",
    "wof:population":55
},
  "geometry": {"coordinates":[23.60378,35.49563],"type":"Point"}
}