{
  "type": "Feature",
  "properties": {
    "gn:admin1_code":"ESYE24",
    "gn:admin2_code":"32.0",
    "gn:admin3_code":"9165",
    "gn:asciiname":"Agioi Pantes",
    "gn:country_code":"GR",
    "gn:dem":78,
    "gn:feature_class":"P",
    "gn:feature_code":"PPL",
    "gn:name":"\u00c1gioi P\u00e1ntes",
    "gn:population":0,
    "gn:timezone":"Europe/Athens",
    "iso:country":"GR",
    "name:ell_x_preferred":[
        "\u00c1gioi P\u00e1ntes"
    ],
    "name:ell_x_variant":[
        "\u0386\u03b3\u03b9\u03bf\u03b9 \u03a0\u03ac\u03bd\u03c4\u03b5\u03c2"
    ],
    "name:und_x_variant":[
        "V\u00eddhavi",
        "\u00c1yioi P\u00e1ndes"
    ],
    "wof:name":"Agioi Pantes",
    "wof:placetype":"locality"
},
  "geometry": {"coordinates":[22.29484,38.36813],"type":"Point"}
}