{
  "type": "Feature",
  "properties": {
    "gn:admin1_code":"ESYE43",
    "gn:admin2_code":"45.0",
    "gn:admin3_code":"9309.0",
    "gn:asciiname":"Drapanos",
    "gn:country_code":"GR",
    "gn:dem":55,
    "gn:elevation":"53.0",
    "gn:feature_class":"P",
    "gn:feature_code":"PPL",
    "gn:name":"Dr\u00e1panos",
    "gn:population":13,
    "gn:timezone":"Europe/Athens",
    "iso:country":"GR",
    "name:ell_x_preferred":[
        "\u0394\u03c1\u03ac\u03c0\u03b1\u03bd\u03bf\u03c2"
    ],
    "name:eng_x_preferred":[
        "Drapanos"
    ],
    "wof:name":"Drapanos",
    "wof:placetype":"locality",
    "wof:population":13
},
  "geometry": {"coordinates":[25.37717,35.31684],"type":"Point"}
}