{
  "type": "Feature",
  "properties": {
    "gn:admin1_code":"ESYE43",
    "gn:admin2_code":"43.0",
    "gn:admin3_code":"9321",
    "gn:asciiname":"Koulouridiana",
    "gn:country_code":"GR",
    "gn:dem":638,
    "gn:feature_class":"P",
    "gn:feature_code":"PPL",
    "gn:name":"Koulouridian\u00e1",
    "gn:population":0,
    "gn:timezone":"Europe/Athens",
    "iso:country":"GR",
    "name:ell_x_preferred":[
        "Koulouridian\u00e1"
    ],
    "name:ell_x_variant":[
        "\u039a\u03bf\u03c5\u03bb\u03bf\u03c5\u03c1\u03b9\u03b4\u03b9\u03b1\u03bd\u03ac"
    ],
    "name:und_x_variant":[
        "Sinaikism\u00f3s Koulourian\u00e1",
        "Koulourian\u00e1"
    ],
    "wof:name":"Koulouridiana",
    "wof:placetype":"locality"
},
  "geometry": {"coordinates":[23.82963,35.3427],"type":"Point"}
}