{
  "type": "Feature",
  "properties": {
    "gn:admin1_code":"ESYE23",
    "gn:admin2_code":"31.0",
    "gn:admin3_code":"9126",
    "gn:asciiname":"Mavrovoros",
    "gn:country_code":"GR",
    "gn:dem":259,
    "gn:feature_class":"P",
    "gn:feature_code":"PPL",
    "gn:name":"Mavrovor\u00f3s",
    "gn:population":0,
    "gn:timezone":"Europe/Athens",
    "iso:country":"GR",
    "name:ell_x_preferred":[
        "Mavrovor\u00f3s"
    ],
    "name:ell_x_variant":[
        "\u039c\u03b1\u03c5\u03c1\u03bf\u03b2\u03bf\u03c1\u03cc\u03c2"
    ],
    "wof:name":"Mavrovoros",
    "wof:placetype":"locality"
},
  "geometry": {"coordinates":[21.63786,38.58],"type":"Point"}
}