{
  "type": "Feature",
  "properties": {
    "iso:country":"GR",
    "name:dut_x_preferred":[
        "Finikas"
    ],
    "name:eng_x_preferred":[
        "Foinikas"
    ],
    "name:fin_x_preferred":[
        "Fo\u00ednikas"
    ],
    "name:fre_x_preferred":[
        "Finikas"
    ],
    "name:ger_x_preferred":[
        "Finikas"
    ],
    "name:gre_x_preferred":[
        "\u0394\u03ae\u03bc\u03bf\u03c2 \u03a6\u03bf\u03af\u03bd\u03b9\u03ba\u03b1"
    ],
    "name:ita_x_preferred":[
        "Finikas"
    ],
    "name:nno_x_preferred":[
        "F\u00ednikas"
    ],
    "qs_pg:aaroncc":"GR",
    "qs_pg:name":"Foinikas",
    "qs_pg:name_adm0":"\u0395\u03bb\u03bb\u03ac\u03b4\u03b1",
    "qs_pg:name_adm1":"Crete",
    "qs_pg:photos":55,
    "qs_pg:photos_1k":11,
    "qs_pg:photos_9k":1,
    "qs_pg:photos_9r":2,
    "qs_pg:photos_all":55,
    "qs_pg:photos_sr":2,
    "qs_pg:pop_sr":0,
    "qs_pg:qs_pg_placetype":"locality",
    "qs_pg:qs_pg_placetype_gp":"Town",
    "qs_pg:woe_adm0":23424833,
    "woe:adm0_id":23424833,
    "woe:name_adm0":"\u0395\u03bb\u03bb\u03ac\u03b4\u03b1",
    "woe:name_adm1":"Crete",
    "woe:placetype":"Town",
    "wof:name":"Foinikas",
    "wof:placetype":"locality"
},
  "geometry": {"coordinates":[24.465522,35.189249],"type":"Point"}
}