{
  "type": "Feature",
  "properties": {
    "gn:admin1_code":"ESYE25",
    "gn:admin2_code":"36.0",
    "gn:admin3_code":"9234",
    "gn:asciiname":"Gatzia",
    "gn:country_code":"GR",
    "gn:dem":491,
    "gn:feature_class":"P",
    "gn:feature_code":"PPL",
    "gn:name":"G\u00e1tzia",
    "gn:population":47,
    "gn:timezone":"Europe/Athens",
    "iso:country":"GR",
    "name:ell_x_preferred":[
        "\u0393\u03ba\u03ac\u03c4\u03b6\u03b9\u03b1"
    ],
    "name:eng_x_preferred":[
        "Gkatzia"
    ],
    "name:und_x_variant":[
        "Gatza",
        "G\u00e1tzia"
    ],
    "wof:name":"Gatzia",
    "wof:placetype":"locality",
    "wof:population":47
},
  "geometry": {"coordinates":[22.92696,37.63755],"type":"Point"}
}