{
  "type": "Feature",
  "properties": {
    "gn:admin1_code":"ESYE22",
    "gn:asciiname":"Limnionas",
    "gn:country_code":"GR",
    "gn:dem":38,
    "gn:feature_class":"P",
    "gn:feature_code":"PPL",
    "gn:name":"Limnionas",
    "gn:population":0,
    "gn:timezone":"Europe/Athens",
    "iso:country":"GR",
    "wof:name":"Limnionas",
    "wof:placetype":"locality"
},
  "geometry": {"coordinates":[20.6955,37.7528],"type":"Point"}
}