{
  "type": "Feature",
  "properties": {
    "gn:admin1_code":"ESYE43",
    "gn:admin2_code":"44.0",
    "gn:admin3_code":"9318",
    "gn:asciiname":"Viranepiskopi",
    "gn:country_code":"GR",
    "gn:dem":79,
    "gn:feature_class":"P",
    "gn:feature_code":"PPL",
    "gn:name":"Viranepiskop\u00ed",
    "gn:population":122,
    "gn:timezone":"Europe/Athens",
    "iso:country":"GR",
    "name:ell_x_colloquial":[
        "\u0392\u03b9\u03c1\u03ac\u03bd \u0395\u03c0\u03b9\u03c3\u03ba\u03bf\u03c0\u03ae"
    ],
    "name:ell_x_historical":[
        "\u0392\u03b9\u03c1\u03ac\u03bd \u0395\u03c0\u03b9\u03c3\u03ba\u03bf\u03c0\u03ae"
    ],
    "name:ell_x_preferred":[
        "\u0392\u03b9\u03c1\u03b1\u03bd\u03b5\u03c0\u03b9\u03c3\u03ba\u03bf\u03c0\u03ae"
    ],
    "name:ell_x_variant":[
        "\u0392\u03b9\u03c1\u03ac\u03bd \u0395\u03c0\u03b9\u03c3\u03ba\u03bf\u03c0\u03ae"
    ],
    "name:eng_x_colloquial":[
        "Viran Episkopi"
    ],
    "name:eng_x_historical":[
        "Viran Episkopi"
    ],
    "name:eng_x_preferred":[
        "Viranepiskopi"
    ],
    "name:eng_x_variant":[
        "Viran Episkopi"
    ],
    "name:und_x_variant":[
        "Viranepiskop\u00ed"
    ],
    "wof:name":"Viranepiskopi",
    "wof:placetype":"locality",
    "wof:population":122
},
  "geometry": {"coordinates":[24.61586,35.37009000000001],"type":"Point"}
}