{
  "type": "Feature",
  "properties": {
    "gn:admin1_code":"ESYE23",
    "gn:admin2_code":"39.0",
    "gn:admin3_code":"9139",
    "gn:asciiname":"Oraia",
    "gn:country_code":"GR",
    "gn:dem":113,
    "gn:feature_class":"P",
    "gn:feature_code":"PPL",
    "gn:name":"Ora\u00eda",
    "gn:population":0,
    "gn:timezone":"Europe/Athens",
    "iso:country":"GR",
    "name:ell_x_preferred":[
        "Ora\u00eda"
    ],
    "name:ell_x_variant":[
        "\u03a9\u03c1\u03b1\u03af\u03b1"
    ],
    "wof:name":"Oraia",
    "wof:placetype":"locality"
},
  "geometry": {"coordinates":[21.49458,37.85642],"type":"Point"}
}