{
  "type": "Feature",
  "properties": {
    "gn:admin1_code":"ESYE41",
    "gn:admin2_code":"50.0",
    "gn:admin3_code":"9266",
    "gn:asciiname":"Koskinas",
    "gn:country_code":"GR",
    "gn:dem":6,
    "gn:feature_class":"P",
    "gn:feature_code":"PPL",
    "gn:name":"Koskin\u00e1s",
    "gn:population":20,
    "gn:timezone":"Europe/Athens",
    "iso:country":"GR",
    "name:ell_x_preferred":[
        "\u039a\u03bf\u03c3\u03ba\u03b9\u03bd\u03ac\u03c2"
    ],
    "name:eng_x_preferred":[
        "Koskinas"
    ],
    "wof:name":"Koskinas",
    "wof:placetype":"locality",
    "wof:population":20
},
  "geometry": {"coordinates":[25.92971,38.46728],"type":"Point"}
}