{
  "type": "Feature",
  "properties": {
    "gn:gn_country":"GR",
    "gn:gn_fcode":"PPL",
    "gn:gn_pop":0,
    "iso:country":"GR",
    "name:ara_x_preferred":[
        "\u0643\u062a\u0627\u0646\u064a\u0629"
    ],
    "name:azb_x_preferred":[
        "\u0645\u0627\u0647\u0645\u06cc\u0632\u062c\u0627"
    ],
    "name:aze_x_preferred":[
        "Mahm\u0131zca"
    ],
    "name:bak_x_preferred":[
        "\u0415\u0442\u0435\u043d \u04af\u043b\u04d9\u043d"
    ],
    "name:bel_x_preferred":[
        "\u0417\u0430\u0440\u043d\u0456\u0446\u0430"
    ],
    "name:bul_x_preferred":[
        "\u041b\u0443\u043b\u0438\u0447\u043a\u0430"
    ],
    "name:cat_x_preferred":[
        "Lin\u00e0ria"
    ],
    "name:ceb_x_preferred":[
        "Linaria"
    ],
    "name:ces_x_preferred":[
        "Lnice"
    ],
    "name:dan_x_preferred":[
        "Torskemund"
    ],
    "name:deu_x_preferred":[
        "Leinkr\u00e4uter"
    ],
    "name:ell_x_preferred":[
        "\u039b\u03b9\u03bd\u03b1\u03c1\u03b9\u03ac"
    ],
    "name:est_x_preferred":[
        "K\u00e4okannus"
    ],
    "name:fas_x_preferred":[
        "\u06a9\u062a\u0627\u0646\u06cc"
    ],
    "name:fin_x_preferred":[
        "Kannusruohot"
    ],
    "name:fra_x_preferred":[
        "Linaria"
    ],
    "name:frr_x_preferred":[
        "Liinkr\u00fc\u00fcs"
    ],
    "name:heb_x_preferred":[
        "\u05e4\u05e9\u05ea\u05e0\u05d9\u05ea"
    ],
    "name:hrv_x_preferred":[
        "Lanilist"
    ],
    "name:hsb_x_preferred":[
        "Len\u010dk"
    ],
    "name:hye_x_preferred":[
        "\u053f\u057f\u0561\u057e\u0561\u056d\u0578\u057f"
    ],
    "name:ita_x_preferred":[
        "Linaria"
    ],
    "name:kat_x_preferred":[
        "\u10e1\u10d4\u10da\u10d8\u10ed\u10d0"
    ],
    "name:kaz_x_preferred":[
        "\u0421\u0438\u044f\u043a\u04e9\u043a"
    ],
    "name:lit_x_preferred":[
        "Lina\u017eol\u0117"
    ],
    "name:nld_x_preferred":[
        "Vlasleeuwenbek"
    ],
    "name:pol_x_preferred":[
        "Lnica"
    ],
    "name:por_x_preferred":[
        "Linaria"
    ],
    "name:ron_x_preferred":[
        "Linaria"
    ],
    "name:rus_x_preferred":[
        "\u041b\u044c\u043d\u044f\u043d\u043a\u0430"
    ],
    "name:spa_x_preferred":[
        "Linaria"
    ],
    "name:swe_x_preferred":[
        "Sporrar"
    ],
    "name:ukr_x_preferred":[
        "\u041b\u044c\u043e\u043d\u043e\u043a"
    ],
    "name:war_x_preferred":[
        "Linaria"
    ],
    "name:zho_x_preferred":[
        "\u67f3\u7a7f\u9c7c\u5c5e"
    ],
    "qs_pg:aaroncc":"GR",
    "qs_pg:gn_country":"GR",
    "qs_pg:gn_fcode":"PPL",
    "qs_pg:gn_pop":0,
    "qs_pg:name":"Linaria",
    "qs_pg:name_adm0":"\u0395\u03bb\u03bb\u03ac\u03b4\u03b1",
    "qs_pg:name_adm1":"Thessaly and Continental Greece",
    "qs_pg:photos":30,
    "qs_pg:photos_1k":6,
    "qs_pg:photos_9k":1,
    "qs_pg:photos_9r":2,
    "qs_pg:photos_all":30,
    "qs_pg:photos_sr":2,
    "qs_pg:pop_sr":0,
    "qs_pg:qs_pg_placetype":"locality",
    "qs_pg:qs_pg_placetype_gp":"Town",
    "qs_pg:woe_adm0":23424833,
    "woe:adm0_id":23424833,
    "woe:name_adm0":"\u0395\u03bb\u03bb\u03ac\u03b4\u03b1",
    "woe:name_adm1":"Thessaly and Continental Greece",
    "woe:placetype":"Town",
    "wof:name":"Linaria",
    "wof:placetype":"locality"
},
  "geometry": {"coordinates":[24.53333,38.83333],"type":"Point"}
}