{
  "type": "Feature",
  "properties": {
    "gn:admin1_code":"ESYE23",
    "gn:admin2_code":"31.0",
    "gn:admin3_code":"9128",
    "gn:asciiname":"Spartorachi",
    "gn:country_code":"GR",
    "gn:dem":-1,
    "gn:feature_class":"P",
    "gn:feature_code":"PPL",
    "gn:name":"Spartor\u00e1chi",
    "gn:population":30,
    "gn:timezone":"Europe/Athens",
    "iso:country":"GR",
    "name:ell_x_preferred":[
        "\u03a3\u03c0\u03b1\u03c1\u03c4\u03bf\u03c1\u03ac\u03c7\u03b7"
    ],
    "wof:name":"Spartorachi",
    "wof:placetype":"locality",
    "wof:population":30
},
  "geometry": {"coordinates":[21.75812,38.33223],"type":"Point"}
}