{
  "type": "Feature",
  "properties": {
    "iso:country":"GR",
    "name:ara_x_preferred":[
        "\u0623\u0631\u063a\u0627\u0644\u0627\u0633\u062a\u064a"
    ],
    "name:dut_x_preferred":[
        "Argalasti"
    ],
    "name:eng_x_preferred":[
        "Argalasti"
    ],
    "name:fin_x_preferred":[
        "Argalast\u00ed"
    ],
    "name:fre_x_preferred":[
        "Argalasti"
    ],
    "name:ger_x_preferred":[
        "Argalasti"
    ],
    "name:gre_x_preferred":[
        "\u0391\u03c1\u03b3\u03b1\u03bb\u03b1\u03c3\u03c4\u03ae \u039c\u03b1\u03b3\u03bd\u03b7\u03c3\u03af\u03b1\u03c2"
    ],
    "name:ita_x_preferred":[
        "Argalasti"
    ],
    "name:jpn_x_preferred":[
        "\u30a2\u30eb\u30ac\u30e9\u30b9\u30c6\u30a3"
    ],
    "name:nno_x_preferred":[
        "Argalast\u00ed"
    ],
    "name:pol_x_preferred":[
        "Argalasti"
    ],
    "name:spa_x_preferred":[
        "Argalasti"
    ],
    "name:swe_x_preferred":[
        "Argalast\u00ed"
    ],
    "qs_pg:aaroncc":"GR",
    "qs_pg:name":"Argalasti",
    "qs_pg:name_adm0":"\u0395\u03bb\u03bb\u03ac\u03b4\u03b1",
    "qs_pg:name_adm1":"Thessaly and Continental Greece",
    "qs_pg:photos":68,
    "qs_pg:photos_1k":14,
    "qs_pg:photos_9k":1,
    "qs_pg:photos_9r":2,
    "qs_pg:photos_all":68,
    "qs_pg:photos_sr":2,
    "qs_pg:pop_sr":0,
    "qs_pg:qs_pg_placetype":"locality",
    "qs_pg:qs_pg_placetype_gp":"Town",
    "qs_pg:woe_adm0":23424833,
    "woe:adm0_id":23424833,
    "woe:name_adm0":"\u0395\u03bb\u03bb\u03ac\u03b4\u03b1",
    "woe:name_adm1":"Thessaly and Continental Greece",
    "woe:placetype":"Town",
    "wof:name":"Argalasti",
    "wof:placetype":"locality"
},
  "geometry": {"coordinates":[23.2158275,39.2269485],"type":"Point"}
}