{
  "type": "Feature",
  "properties": {
    "gn:admin1_code":"ESYE42",
    "gn:admin2_code":"49.0",
    "gn:admin3_code":"9301",
    "gn:asciiname":"Venardatos",
    "gn:country_code":"GR",
    "gn:dem":178,
    "gn:feature_class":"P",
    "gn:feature_code":"PPL",
    "gn:name":"Venard\u00e1tos",
    "gn:population":0,
    "gn:timezone":"Europe/Athens",
    "iso:country":"GR",
    "name:und_x_variant":[
        "Venard\u00e1tos",
        "\u0392\u03b5\u03bd\u03b1\u03c1\u03b4\u03ac\u03c4\u03bf\u03c2"
    ],
    "wof:name":"Venardatos",
    "wof:placetype":"locality"
},
  "geometry": {"coordinates":[25.04409,37.63427],"type":"Point"}
}