{
  "type": "Feature",
  "properties": {
    "gn:admin1_code":"ESYE11",
    "gn:admin2_code":"1.0",
    "gn:admin3_code":"9008",
    "gn:asciiname":"Ampelakia",
    "gn:country_code":"GR",
    "gn:dem":172,
    "gn:feature_class":"P",
    "gn:feature_code":"PPL",
    "gn:name":"Ampel\u00e1kia",
    "gn:population":0,
    "gn:timezone":"Europe/Athens",
    "iso:country":"GR",
    "name:ara_x_preferred":[
        "\u0623\u0645\u0628\u064a\u0644\u0627\u0643\u064a\u0627"
    ],
    "name:ceb_x_preferred":[
        "Ampel\u00e1kia"
    ],
    "name:ell_x_preferred":[
        "Ampel\u00e1kia"
    ],
    "name:ell_x_variant":[
        "\u0391\u03bc\u03c0\u03b5\u03bb\u03ac\u03ba\u03b9\u03b1",
        "Ambel\u00e1kia",
        "\u0391\u03bc\u03c0\u03b5\u03bb\u03ac\u03ba\u03b9\u03b1 \u03a3\u03b1\u03bb\u03b1\u03bc\u03af\u03bd\u03b1\u03c2"
    ],
    "name:fin_x_preferred":[
        "Ampel\u00e1kia"
    ],
    "name:ita_x_preferred":[
        "Ampelakia"
    ],
    "name:ron_x_preferred":[
        "Ampelakia"
    ],
    "wof:name":"Ampelakia",
    "wof:placetype":"locality"
},
  "geometry": {"coordinates":[26.39588,41.48102],"type":"Point"}
}