{
  "type": "Feature",
  "properties": {
    "gn:admin1_code":"ESYE11",
    "gn:admin2_code":"4.0",
    "gn:admin3_code":"9002",
    "gn:asciiname":"Nea Sevasteia",
    "gn:country_code":"GR",
    "gn:dem":89,
    "gn:feature_class":"P",
    "gn:feature_code":"PPL",
    "gn:name":"N\u00e9a Sev\u00e1steia",
    "gn:population":0,
    "gn:timezone":"Europe/Athens",
    "iso:country":"GR",
    "name:ell_x_preferred":[
        "N\u00e9a Sev\u00e1steia"
    ],
    "name:ell_x_variant":[
        "\u039d\u03ad\u03b1 \u03a3\u03b5\u03b2\u03ac\u03c3\u03c4\u03b5\u03b9\u03b1",
        "N\u00e9a Sev\u00e1stia"
    ],
    "wof:name":"Nea Sevasteia",
    "wof:placetype":"locality"
},
  "geometry": {"coordinates":[24.13072,41.12348],"type":"Point"}
}