{
  "type": "Feature",
  "properties": {
    "gn:admin1_code":"ESYE24",
    "gn:admin2_code":"29.0",
    "gn:admin3_code":"9164",
    "gn:asciiname":"Akhinos",
    "gn:country_code":"GR",
    "gn:dem":34,
    "gn:feature_class":"P",
    "gn:feature_code":"PPL",
    "gn:name":"Akhin\u00f3s",
    "gn:population":726,
    "gn:timezone":"Europe/Athens",
    "iso:country":"GR",
    "name:ell_x_preferred":[
        "\u0391\u03c7\u03b9\u03bd\u03cc\u03c2"
    ],
    "name:eng_x_preferred":[
        "Achinos"
    ],
    "name:und_x_variant":[
        "Ekhin\u00f3s",
        "Akhin\u00f3s"
    ],
    "wof:name":"Akhinos",
    "wof:placetype":"locality",
    "wof:population":726
},
  "geometry": {"coordinates":[22.72483,38.89284],"type":"Point"}
}