{
  "type": "Feature",
  "properties": {
    "gn:admin1_code":"ESYE23",
    "gn:admin2_code":"38.0",
    "gn:admin3_code":"9134",
    "gn:asciiname":"Krini",
    "gn:country_code":"GR",
    "gn:dem":185,
    "gn:feature_class":"P",
    "gn:feature_code":"PPL",
    "gn:name":"Kr\u00edni",
    "gn:population":0,
    "gn:timezone":"Europe/Athens",
    "iso:country":"GR",
    "name:ceb_x_preferred":[
        "Krini"
    ],
    "name:ell_x_preferred":[
        "\u039a\u03c1\u03ae\u03bd\u03b7"
    ],
    "name:swe_x_preferred":[
        "Krini"
    ],
    "name:und_x_variant":[
        "Vel\u00edzi",
        "Kr\u00edni"
    ],
    "wof:name":"Krini",
    "wof:placetype":"locality"
},
  "geometry": {"coordinates":[21.74906,38.18456],"type":"Point"}
}