{
  "type": "Feature",
  "properties": {
    "gn:admin1_code":"ESYE13",
    "gn:admin2_code":"11.0",
    "gn:admin3_code":"9068",
    "gn:asciiname":"Kapnochori",
    "gn:country_code":"GR",
    "gn:dem":689,
    "gn:feature_class":"P",
    "gn:feature_code":"PPL",
    "gn:name":"Kapnoch\u00f3ri",
    "gn:population":0,
    "gn:timezone":"Europe/Athens",
    "iso:country":"GR",
    "name:bul_x_preferred":[
        "\u041a\u0430\u043f\u043d\u043e\u0445\u043e\u0440\u0438"
    ],
    "name:ell_x_preferred":[
        "Kapnoch\u00f3ri"
    ],
    "name:ell_x_variant":[
        "\u039a\u03b1\u03c0\u03bd\u03bf\u03c7\u03ce\u03c1\u03b9",
        "Kapnoch\u00f3rion",
        "\u039a\u03b1\u03c0\u03bd\u03bf\u03c7\u03ce\u03c1\u03b9\u03bf\u03bd",
        "\u039a\u03b1\u03c0\u03bd\u03bf\u03c7\u03ce\u03c1\u03b9 \u039a\u03bf\u03b6\u03ac\u03bd\u03b7\u03c2"
    ],
    "name:mkd_x_preferred":[
        "\u0421\u043e\u0444\u0443\u043b\u0435\u0440"
    ],
    "name:und_x_variant":[
        "Sofoul\u00e1r",
        "Soful\u00e1r",
        "Kapnokh\u00f3rion"
    ],
    "wof:name":"Kapnochori",
    "wof:placetype":"locality"
},
  "geometry": {"coordinates":[21.97623,40.35872],"type":"Point"}
}