{
  "type": "Feature",
  "properties": {
    "gn:admin1_code":"ESYE14",
    "gn:admin2_code":"23.0",
    "gn:admin3_code":"9096",
    "gn:asciiname":"Anogeio",
    "gn:country_code":"GR",
    "gn:dem":119,
    "gn:feature_class":"P",
    "gn:feature_code":"PPL",
    "gn:name":"An\u00f3geio",
    "gn:population":0,
    "gn:timezone":"Europe/Athens",
    "iso:country":"GR",
    "name:ell_x_preferred":[
        "An\u00f3geio"
    ],
    "name:ell_x_variant":[
        "\u0391\u03bd\u03ce\u03b3\u03b5\u03b9\u03bf",
        "An\u00f3geion",
        "\u0391\u03bd\u03ce\u03b3\u03b5\u03b9\u03bf\u03bd",
        "\u0394\u03ae\u03bc\u03bf\u03c2 \u0391\u03bd\u03ce\u03b3\u03b5\u03b9\u03bf\u03c5"
    ],
    "name:fin_x_preferred":[
        "An\u00f3geio"
    ],
    "name:ita_x_preferred":[
        "Anogeio"
    ],
    "name:nno_x_preferred":[
        "An\u00f3jo"
    ],
    "name:und_x_variant":[
        "An\u00f3yi",
        "An\u00f3yion"
    ],
    "wof:name":"Anogeio",
    "wof:placetype":"locality"
},
  "geometry": {"coordinates":[22.06053,39.29144],"type":"Point"}
}