{
  "type": "Feature",
  "properties": {
    "gn:admin1_code":"ESYE25",
    "gn:admin2_code":"40.0",
    "gn:admin3_code":"9257",
    "gn:asciiname":"Agios Isidoros",
    "gn:country_code":"GR",
    "gn:dem":121,
    "gn:feature_class":"P",
    "gn:feature_code":"PPL",
    "gn:name":"\u00c1gios Is\u00eddoros",
    "gn:population":0,
    "gn:timezone":"Europe/Athens",
    "iso:country":"GR",
    "name:ell_x_preferred":[
        "\u00c1gios Is\u00eddoros"
    ],
    "name:ell_x_variant":[
        "\u0386\u03b3\u03b9\u03bf\u03c2 \u0399\u03c3\u03af\u03b4\u03c9\u03c1\u03bf\u03c2"
    ],
    "name:und_x_variant":[
        "Monsouli",
        "Mouso\u00fali",
        "\u00c1yios Is\u00eddhoros"
    ],
    "wof:name":"Agios Isidoros",
    "wof:placetype":"locality"
},
  "geometry": {"coordinates":[21.91484,36.79846],"type":"Point"}
}