{
  "type": "Feature",
  "properties": {
    "gn:admin1_code":"ESYE43",
    "gn:admin2_code":"43.0",
    "gn:admin3_code":"9321",
    "gn:asciiname":"Tzinaliana",
    "gn:country_code":"GR",
    "gn:dem":505,
    "gn:feature_class":"P",
    "gn:feature_code":"PPL",
    "gn:name":"Tzinalian\u00e1",
    "gn:population":0,
    "gn:timezone":"Europe/Athens",
    "iso:country":"GR",
    "name:ell_x_preferred":[
        "Tzinalian\u00e1"
    ],
    "name:ell_x_variant":[
        "\u03a4\u03b6\u03b9\u03bd\u03b1\u03bb\u03b9\u03b1\u03bd\u03ac"
    ],
    "wof:name":"Tzinaliana",
    "wof:placetype":"locality"
},
  "geometry": {"coordinates":[23.71169,35.29592],"type":"Point"}
}