{
  "type": "Feature",
  "properties": {
    "gn:gn_country":"GR",
    "gn:gn_fcode":"PPL",
    "gn:gn_pop":2455,
    "gn:population":2236,
    "iso:country":"GR",
    "name:bul_x_preferred":[
        "\u041d\u0438\u043a\u0438\u0449\u0430\u043d"
    ],
    "name:ell_x_preferred":[
        "\u039d\u03b9\u03ba\u03ae\u03c3\u03b9\u03b1\u03bd\u03b7"
    ],
    "name:eng_x_preferred":[
        "Nikisiani"
    ],
    "name:mkd_x_preferred":[
        "\u041d\u0438\u043a\u0438\u0448\u0458\u0430\u043d"
    ],
    "name:unk_x_variant":[
        "Nik\u00edsiani"
    ],
    "qs_pg:aaroncc":"GR",
    "qs_pg:gn_country":"GR",
    "qs_pg:gn_fcode":"PPL",
    "qs_pg:gn_pop":2455,
    "qs_pg:name":"Nikisiani",
    "qs_pg:name_adm0":"\u0395\u03bb\u03bb\u03ac\u03b4\u03b1",
    "qs_pg:name_adm1":"Macedonia and Thrace",
    "qs_pg:photos_9k":1,
    "qs_pg:photos_9r":1,
    "qs_pg:photos_all":2,
    "qs_pg:photos_sr":0,
    "qs_pg:pop_sr":4,
    "qs_pg:qs_pg_placetype":"locality",
    "qs_pg:qs_pg_placetype_gp":"Town",
    "qs_pg:woe_adm0":23424833,
    "woe:adm0_id":23424833,
    "woe:name_adm0":"\u0395\u03bb\u03bb\u03ac\u03b4\u03b1",
    "woe:name_adm1":"Macedonia and Thrace",
    "woe:placetype":"Town",
    "wof:name":"Nikisiani",
    "wof:placetype":"locality",
    "wof:population":2236
},
  "geometry": {"coordinates":[24.15,40.95],"type":"Point"}
}