{
  "type": "Feature",
  "properties": {
    "gn:admin1_code":"ESYE42",
    "gn:admin2_code":"49.0",
    "gn:admin3_code":"9301",
    "gn:asciiname":"Perastra",
    "gn:country_code":"GR",
    "gn:dem":49,
    "gn:feature_class":"P",
    "gn:feature_code":"PPL",
    "gn:name":"Per\u00e1stra",
    "gn:population":0,
    "gn:timezone":"Europe/Athens",
    "iso:country":"GR",
    "name:und_x_variant":[
        "Per\u00e1stra",
        "\u03a0\u03b5\u03c1\u03ac\u03c3\u03c4\u03c1\u03b1"
    ],
    "wof:name":"Perastra",
    "wof:placetype":"locality"
},
  "geometry": {"coordinates":[25.14903,37.59728],"type":"Point"}
}