{
  "type": "Feature",
  "properties": {
    "gn:admin1_code":"ESYE13",
    "gn:admin2_code":"8.0",
    "gn:admin3_code":"9070",
    "gn:asciiname":"Antigonos",
    "gn:country_code":"GR",
    "gn:dem":569,
    "gn:feature_class":"P",
    "gn:feature_code":"PPL",
    "gn:name":"Ant\u00edgonos",
    "gn:population":424,
    "gn:timezone":"Europe/Athens",
    "iso:country":"GR",
    "name:ell_x_preferred":[
        "\u0391\u03bd\u03c4\u03af\u03b3\u03bf\u03bd\u03bf\u03c2"
    ],
    "name:eng_x_preferred":[
        "Antigonos"
    ],
    "name:und_x_variant":[
        "K\u00edssa",
        "And\u00edgonon",
        "Kosel\u00e9r",
        "And\u00edgonos",
        "Ant\u00edgonos"
    ],
    "wof:name":"Antigonos",
    "wof:placetype":"locality",
    "wof:population":424
},
  "geometry": {"coordinates":[21.76171,40.63985],"type":"Point"}
}