{
  "type": "Feature",
  "properties": {
    "gn:population":1493,
    "iso:country":"GR",
    "name:ara_x_preferred":[
        "\u0643\u0648\u064a\u0644\u0627\u060c \u0643\u0648\u0632\u0627\u0646\u064a"
    ],
    "name:ara_x_variant":[
        "\u0643\u0648\u064a\u0644\u0627"
    ],
    "name:bul_x_preferred":[
        "\u041a\u0438\u043b\u0430"
    ],
    "name:ceb_x_preferred":[
        "Ko\u00edla"
    ],
    "name:ell_x_preferred":[
        "\u039a\u03bf\u03af\u03bb\u03b1"
    ],
    "name:ell_x_variant":[
        "\u039a\u03bf\u03af\u03bb\u03b1 \u039a\u03bf\u03b6\u03ac\u03bd\u03b7\u03c2"
    ],
    "name:eng_x_preferred":[
        "Koila"
    ],
    "name:mkd_x_preferred":[
        "\u0418\u0441\u043b\u0430\u043c\u043b\u0438"
    ],
    "name:nld_x_preferred":[
        "Koila"
    ],
    "name:rus_x_preferred":[
        "\u041a\u0438\u043b\u0430"
    ],
    "name:swe_x_preferred":[
        "Ko\u00edla"
    ],
    "name:und_x_variant":[
        "Islaml\u00ed"
    ],
    "qs:a0":"Greece",
    "qs:a1":"*\u0394\u03a5\u03a4\u0399\u039a\u0397 \u039c\u0391\u039a\u0395\u0394\u039f\u039d\u0399\u0391",
    "qs:a1_alt":"DYTIKH MAKEDONIA",
    "qs:a1r":"0",
    "qs:a2_alt":"KOZANH",
    "qs:adm0":"Greece",
    "qs:la_lc":"*",
    "qs:level":"locality",
    "qs:loc":"\u039a\u039f\u0399\u039b\u0391",
    "qs:loc_alt":"KOILA",
    "qs:pop":0,
    "qs:type":"buffered point",
    "wof:name":"\u039a\u039f\u0399\u039b\u0391",
    "wof:placetype":"locality",
    "wof:population":1493
},
  "geometry": {"coordinates":[21.790372,40.331558],"type":"Point"}
}