{
  "type": "Feature",
  "properties": {
    "gn:population":1137,
    "iso:country":"GR",
    "name:ara_x_preferred":[
        "\u0628\u0631\u0627\u0645\u0627\u0646\u062a\u0627"
    ],
    "name:ell_x_preferred":[
        "\u0394\u03ae\u03bc\u03bf\u03c2 \u03a0\u03c1\u03b1\u03bc\u03ac\u03bd\u03c4\u03c9\u03bd"
    ],
    "name:ell_x_variant":[
        "\u03a0\u03c1\u03ac\u03bc\u03b1\u03bd\u03c4\u03b1",
        "\u03a0\u03c1\u03ac\u03bc\u03b1\u03bd\u03c4\u03b1 \u0399\u03c9\u03b1\u03bd\u03bd\u03af\u03bd\u03c9\u03bd"
    ],
    "name:eng_x_preferred":[
        "Pramanta"
    ],
    "name:fin_x_preferred":[
        "Pr\u00e1manta"
    ],
    "name:fra_x_preferred":[
        "Pramanta"
    ],
    "name:ita_x_preferred":[
        "Pramanta"
    ],
    "name:jpn_x_preferred":[
        "\u30d7\u30e9\u30de\u30f3\u30bf"
    ],
    "name:nld_x_preferred":[
        "Pramanta"
    ],
    "name:nno_x_preferred":[
        "Pr\u00e1manda"
    ],
    "name:swe_x_preferred":[
        "Pr\u00e1manta"
    ],
    "name:unk_x_variant":[
        "Pr\u00e1manda"
    ],
    "qs:a0":"Greece",
    "qs:a1":"*\u0397\u03a0\u0395\u0399\u03a1\u039f\u03a3",
    "qs:a1_alt":"HPEIROS",
    "qs:a1r":"0",
    "qs:a2_alt":"IVANNINA",
    "qs:adm0":"Greece",
    "qs:la_lc":"*",
    "qs:level":"locality",
    "qs:loc":"\u03a0\u03a1\u0391\u039c\u0391\u039d\u03a4\u0391",
    "qs:loc_alt":"PRAMANTA",
    "qs:pop":0,
    "qs:type":"buffered point",
    "wd:wordcount":169,
    "wof:name":"\u03a0\u03a1\u0391\u039c\u0391\u039d\u03a4\u0391",
    "wof:placetype":"locality",
    "wof:population":1137
},
  "geometry": {"coordinates":[21.098542,39.522713],"type":"Point"}
}