{
  "type": "Feature",
  "properties": {
    "gn:gn_country":"GR",
    "gn:gn_fcode":"ADM3",
    "gn:gn_pop":51773,
    "gn:population":51773,
    "iso:country":"GR",
    "name:ell_x_preferred":[
        "\u03a7\u03af\u03bf\u03c5"
    ],
    "qs_pg:aaroncc":"GR",
    "qs_pg:gn_country":"GR",
    "qs_pg:gn_fcode":"ADM3",
    "qs_pg:gn_pop":51773,
    "qs_pg:name":"Dimos Chios",
    "qs_pg:photos_9r":0,
    "qs_pg:photos_sr":0,
    "qs_pg:pop_sr":8,
    "qs_pg:qs_pg_placetype":"localadmin",
    "wof:name":"Dimos Chios",
    "wof:placetype":"localadmin",
    "wof:population":51773
},
  "geometry": {"coordinates":[26.01646,38.40198],"type":"Point"}
}