{
  "type": "Feature",
  "properties": {
    "gn:admin1_code":"ESYE24",
    "gn:admin2_code":"29.0",
    "gn:admin3_code":"9164",
    "gn:asciiname":"Akhladhion",
    "gn:country_code":"GR",
    "gn:dem":2,
    "gn:feature_class":"P",
    "gn:feature_code":"PPL",
    "gn:name":"Akhl\u00e1dhion",
    "gn:population":384,
    "gn:timezone":"Europe/Athens",
    "iso:country":"GR",
    "name:ell_x_preferred":[
        "\u0391\u03c7\u03bb\u03ac\u03b4\u03b9"
    ],
    "name:ell_x_variant":[
        "\u0391\u03c7\u03bb\u03ac\u03b4\u03b9\u03bf\u03bd"
    ],
    "name:eng_x_preferred":[
        "Achladi"
    ],
    "name:und_x_variant":[
        "Akhl\u00e1dhi",
        "Akhl\u00e1dhion"
    ],
    "wof:name":"Akhladhion",
    "wof:placetype":"locality",
    "wof:population":384
},
  "geometry": {"coordinates":[22.80859,38.88766],"type":"Point"}
}