{
  "type": "Feature",
  "properties": {
    "gn:admin1_code":"ESYE21",
    "gn:admin2_code":"20.0",
    "gn:admin3_code":"9075",
    "gn:asciiname":"Strana",
    "gn:country_code":"GR",
    "gn:dem":905,
    "gn:feature_class":"P",
    "gn:feature_code":"PPL",
    "gn:name":"Stran\u00e1",
    "gn:population":0,
    "gn:timezone":"Europe/Athens",
    "iso:country":"GR",
    "name:ell_x_preferred":[
        "\u03a3\u03c4\u03c1\u03b1\u03bd\u03ac"
    ],
    "name:und_x_variant":[
        "Sinoikism\u00f3s Theodho\u00falia",
        "Stran\u00e1"
    ],
    "wof:name":"Strana",
    "wof:placetype":"locality"
},
  "geometry": {"coordinates":[21.08978,39.48569000000001],"type":"Point"}
}