{
  "type": "Feature",
  "properties": {
    "gn:admin1_code":"ESYE14",
    "gn:admin2_code":"24.0",
    "gn:admin3_code":"9104",
    "gn:asciiname":"Mamalaiika",
    "gn:country_code":"GR",
    "gn:dem":92,
    "gn:feature_class":"P",
    "gn:feature_code":"PPL",
    "gn:name":"Mamala\u00edika",
    "gn:population":0,
    "gn:timezone":"Europe/Athens",
    "iso:country":"GR",
    "name:ell_x_preferred":[
        "\u039c\u03b1\u03bc\u03b1\u03bb\u03b1\u03af\u03b9\u03ba\u03b1"
    ],
    "name:eng_x_preferred":[
        "Mamalaiika"
    ],
    "name:und_x_variant":[
        "Mamal\u00e9\u00efka",
        "Mamala\u00edika"
    ],
    "wof:name":"Mamalaiika",
    "wof:placetype":"locality"
},
  "geometry": {"coordinates":[22.70582000000001,39.22959],"type":"Point"}
}