{
  "type": "Feature",
  "properties": {
    "iso:country":"GR",
    "qs:a0":"Greece",
    "qs:a1":"*\u0394\u03a5\u03a4\u0399\u039a\u0397 \u039c\u0391\u039a\u0395\u0394\u039f\u039d\u0399\u0391",
    "qs:a1_alt":"DYTIKH MAKEDONIA",
    "qs:a1r":"0",
    "qs:a2_alt":"KOZANH",
    "qs:adm0":"Greece",
    "qs:la_lc":"*",
    "qs:level":"locality",
    "qs:loc":"\u039b\u0395\u03a5\u039a\u039f\u0392\u03a1\u03a5\u03a3\u0397",
    "qs:loc_alt":"LEYKOBRYSH",
    "qs:pop":0,
    "qs:type":"buffered point",
    "wof:name":"\u039b\u0395\u03a5\u039a\u039f\u0392\u03a1\u03a5\u03a3\u0397",
    "wof:placetype":"locality"
},
  "geometry": {"coordinates":[21.78088,40.273624],"type":"Point"}
}