{
  "type": "Feature",
  "properties": {
    "gn:admin1_code":"ESYE12",
    "gn:admin2_code":"5.0",
    "gn:admin3_code":"9054",
    "gn:asciiname":"Oinoussa",
    "gn:country_code":"GR",
    "gn:dem":144,
    "gn:feature_class":"P",
    "gn:feature_code":"PPL",
    "gn:name":"Oino\u00fassa",
    "gn:population":517,
    "gn:timezone":"Europe/Athens",
    "iso:country":"GR",
    "name:bul_x_preferred":[
        "\u0414\u0435\u0440\u0432\u0435\u0448\u0435\u043d"
    ],
    "name:ceb_x_preferred":[
        "Oino\u00fassa"
    ],
    "name:ell_x_preferred":[
        "\u039f\u03b9\u03bd\u03bf\u03cd\u03c3\u03c3\u03b1"
    ],
    "name:ell_x_variant":[
        "\u039f\u03b9\u03bd\u03bf\u03cd\u03c3\u03c3\u03b1 \u03a3\u03b5\u03c1\u03c1\u03ce\u03bd"
    ],
    "name:eng_x_preferred":[
        "Oinoussa"
    ],
    "name:swe_x_preferred":[
        "Oino\u00fassa"
    ],
    "name:und_x_variant":[
        "Oino\u00fasa"
    ],
    "wof:name":"Oinoussa",
    "wof:placetype":"locality",
    "wof:population":517
},
  "geometry": {"coordinates":[23.62576,41.10237],"type":"Point"}
}