{
  "type": "Feature",
  "properties": {
    "gn:admin1_code":"ESYE11",
    "gn:admin2_code":"4.0",
    "gn:admin3_code":"9001",
    "gn:asciiname":"Vathyspilo",
    "gn:country_code":"GR",
    "gn:dem":168,
    "gn:feature_class":"P",
    "gn:feature_code":"PPL",
    "gn:name":"Vath\u00fdspilo",
    "gn:population":0,
    "gn:timezone":"Europe/Athens",
    "iso:country":"GR",
    "name:ell_x_preferred":[
        "Vath\u00fdspilo"
    ],
    "name:ell_x_variant":[
        "\u0392\u03b1\u03b8\u03cd\u03c3\u03c0\u03b7\u03bb\u03bf",
        "Vath\u00fdspilon",
        "\u0392\u03b1\u03b8\u03cd\u03c3\u03c0\u03b7\u03bb\u03bf\u03bd"
    ],
    "name:und_x_variant":[
        "Buj\u00e1k",
        "Vath\u00edspilon"
    ],
    "wof:name":"Vathyspilo",
    "wof:placetype":"locality"
},
  "geometry": {"coordinates":[24.29424,41.09224],"type":"Point"}
}