{
  "type": "Feature",
  "properties": {
    "gn:admin1_code":"ESYE22",
    "gn:admin2_code":"26.0",
    "gn:admin3_code":"9121",
    "gn:asciiname":"Agios Christoforos",
    "gn:country_code":"GR",
    "gn:dem":103,
    "gn:feature_class":"P",
    "gn:feature_code":"PPL",
    "gn:name":"\u00c1gios Christ\u00f3foros",
    "gn:population":138,
    "gn:timezone":"Europe/Athens",
    "iso:country":"GR",
    "name:bul_x_preferred":[
        "\u0422\u0440\u0435\u0431\u0438\u0449\u0430"
    ],
    "name:ell_x_historical":[
        "\u03a0\u03b1\u03bb\u03b1\u03b9\u03bf\u03ba\u03b1\u03c4\u03bf\u03cd\u03bd\u03b1"
    ],
    "name:ell_x_preferred":[
        "\u0386\u03b3\u03b9\u03bf\u03c2 \u03a7\u03c1\u03b9\u03c3\u03c4\u03cc\u03c6\u03bf\u03c1\u03bf\u03c2"
    ],
    "name:ell_x_variant":[
        "\u03a0\u03b1\u03bb\u03b1\u03b9\u03bf\u03ba\u03b1\u03c4\u03bf\u03cd\u03bd\u03b1"
    ],
    "name:eng_x_historical":[
        "Palaiokatouna"
    ],
    "name:eng_x_preferred":[
        "Palaiokatouna"
    ],
    "name:eng_x_variant":[
        "Agios Christoforos"
    ],
    "name:mkd_x_preferred":[
        "\u0422\u0440\u0435\u043f\u0438\u0448\u0442\u0430"
    ],
    "name:nno_x_preferred":[
        "\u00c1jos Khrist\u00f3foros"
    ],
    "name:und_x_variant":[
        "Palaiokato\u00fana"
    ],
    "wof:name":"Agios Christoforos",
    "wof:placetype":"locality",
    "wof:population":138
},
  "geometry": {"coordinates":[20.68919,38.70062],"type":"Point"}
}