{
  "type": "Feature",
  "properties": {
    "iso:country":"GR",
    "name:ara_x_preferred":[
        "\u062f\u0648\u0643\u0633\u0627\u062a\u0648"
    ],
    "name:bul_x_preferred":[
        "\u0414\u043e\u043a\u0441\u0430\u0442"
    ],
    "name:ceb_x_preferred":[
        "Doxato"
    ],
    "name:ell_x_preferred":[
        "Dox\u00e1ton"
    ],
    "name:ell_x_variant":[
        "\u0394\u03bf\u03be\u03ac\u03c4\u03bf\u03bd",
        "\u0394\u03bf\u03be\u03ac\u03c4\u03bf \u0394\u03c1\u03ac\u03bc\u03b1\u03c2"
    ],
    "name:eng_x_preferred":[
        "Doxato"
    ],
    "name:fin_x_preferred":[
        "Dox\u00e1to"
    ],
    "name:fra_x_preferred":[
        "Doxato"
    ],
    "name:heb_x_preferred":[
        "\u05d3\u05d5\u05e7\u05e1\u05d8\u05d5"
    ],
    "name:ita_x_preferred":[
        "Doxato"
    ],
    "name:jpn_x_preferred":[
        "\u30c9\u30af\u30b5\u30c8"
    ],
    "name:mkd_x_preferred":[
        "\u0414\u043e\u043a\u0441\u0430\u0442"
    ],
    "name:nld_x_preferred":[
        "Doxato"
    ],
    "name:nno_x_preferred":[
        "Dox\u00e1to"
    ],
    "name:pol_x_preferred":[
        "Doksato"
    ],
    "name:rus_x_preferred":[
        "\u0414\u043e\u043a\u0441\u0430\u0442\u043e"
    ],
    "name:rus_x_variant":[
        "\u0414\u043e\u043a\u0441\u0430\u0442\u043e\u043d"
    ],
    "name:spa_x_preferred":[
        "Doxato"
    ],
    "name:swe_x_preferred":[
        "Doxato"
    ],
    "name:tur_x_preferred":[
        "Doksat"
    ],
    "name:vie_x_preferred":[
        "Doxato"
    ],
    "qs:a0":"Greece",
    "qs:a1":"*\u0391\u039d\u0391\u03a4\u039f\u039b\u0399\u039a\u0397 \u039c\u0391\u039a\u0395\u0394\u039f\u039d\u0399\u0391 \u039a\u0391\u0399 \u0398\u03a1\u0391\u039a\u0397",
    "qs:a1_alt":"ANATOLIKH MAKEDONIA KAI URAKH",
    "qs:a1r":"0",
    "qs:a2_alt":"DRAMA",
    "qs:adm0":"Greece",
    "qs:la_lc":"*",
    "qs:level":"locality",
    "qs:loc":"\u0394\u039f\u039e\u0391\u03a4\u039f\u039d",
    "qs:loc_alt":"DOJATON",
    "qs:pop":0,
    "qs:type":"buffered point",
    "wof:name":"\u0394\u039f\u039e\u0391\u03a4\u039f\u039d",
    "wof:placetype":"locality"
},
  "geometry": {"coordinates":[24.231074,41.092663],"type":"Point"}
}