{
  "type": "Feature",
  "properties": {
    "gn:admin1_code":"ESYE31",
    "gn:admin2_code":"445407.0",
    "gn:admin3_code":"9230",
    "gn:asciiname":"Agios Sotir",
    "gn:country_code":"GR",
    "gn:dem":382,
    "gn:feature_class":"P",
    "gn:feature_code":"PPL",
    "gn:name":"Agios Sot\u00edr",
    "gn:population":488,
    "gn:timezone":"Europe/Athens",
    "iso:country":"GR",
    "name:ell_x_preferred":[
        "\u0386\u03b3\u03b9\u03bf\u03c2 \u03a3\u03c9\u03c4\u03ae\u03c1\u03b1\u03c2"
    ],
    "name:ell_x_variant":[
        "\u0386\u03b3\u03b9\u03bf\u03c2 \u03a3\u03c9\u03c4\u03ae\u03c1"
    ],
    "name:eng_x_preferred":[
        "Agios Sotiras"
    ],
    "name:eng_x_variant":[
        "Agios Sotir"
    ],
    "name:und_x_variant":[
        "Aghios Sotir",
        "Aghios Sotiras"
    ],
    "wof:name":"Agios Sotir",
    "wof:placetype":"locality",
    "wof:population":488
},
  "geometry": {"coordinates":[23.4189,38.10633],"type":"Point"}
}