{
  "type": "Feature",
  "properties": {
    "gn:population":2514,
    "iso:country":"GR",
    "name:ara_x_preferred":[
        "\u062a\u0633\u0627\u0631\u064a\u062a\u0633\u0627\u0646\u064a"
    ],
    "name:bul_x_preferred":[
        "\u0426\u0430\u0440\u0438\u0446\u0430\u043d\u0438"
    ],
    "name:ell_x_preferred":[
        "\u03a4\u03c3\u03b1\u03c1\u03b9\u03c4\u03c3\u03ac\u03bd\u03b7 \u039b\u03ac\u03c1\u03b9\u03c3\u03b1\u03c2"
    ],
    "name:ell_x_variant":[
        "\u03a4\u03c3\u03b1\u03c1\u03af\u03c4\u03c3\u03b1\u03bd\u03b7"
    ],
    "name:eng_x_preferred":[
        "Tsaritsani"
    ],
    "name:ita_x_preferred":[
        "Tsaritsani"
    ],
    "name:jpn_x_preferred":[
        "\u30c4\u30a1\u30ea\u30c4\u30a1\u30cb"
    ],
    "name:mkd_x_preferred":[
        "\u0426\u0430\u0440\u0438\u0447\u0430\u043d\u0438"
    ],
    "name:nld_x_preferred":[
        "Tsaritsani"
    ],
    "name:nno_x_preferred":[
        "Tsarits\u00e1ni"
    ],
    "name:ron_x_preferred":[
        "Tsaritsani"
    ],
    "name:rus_x_preferred":[
        "\u0426\u0430\u0440\u0438\u0446\u0430\u043d\u0438"
    ],
    "name:swe_x_preferred":[
        "Tsar\u00edtsani"
    ],
    "name:unk_x_variant":[
        "Tsar\u00edtsani"
    ],
    "qs:a0":"Greece",
    "qs:a1":"*\u0398\u0395\u03a3\u03a3\u0391\u039b\u0399\u0391",
    "qs:a1_alt":"UESSALIA",
    "qs:a1r":"0",
    "qs:a2_alt":"LARISA",
    "qs:adm0":"Greece",
    "qs:la_lc":"*",
    "qs:level":"locality",
    "qs:loc":"\u03a4\u03a3\u0391\u03a1\u0399\u03a4\u03a3\u0391\u039d\u0397",
    "qs:loc_alt":"TSARITSANH",
    "qs:pop":0,
    "qs:type":"buffered point",
    "wd:wordcount":495,
    "wof:name":"\u03a4\u03a3\u0391\u03a1\u0399\u03a4\u03a3\u0391\u039d\u0397",
    "wof:placetype":"locality",
    "wof:population":2514
},
  "geometry": {"coordinates":[22.229065,39.880108],"type":"Point"}
}