{
  "type": "Feature",
  "properties": {
    "gn:admin1_code":"ESYE43",
    "gn:admin2_code":"45.0",
    "gn:admin3_code":"9307",
    "gn:asciiname":"Ano Poulies",
    "gn:country_code":"GR",
    "gn:dem":382,
    "gn:feature_class":"P",
    "gn:feature_code":"PPL",
    "gn:name":"\u00c1no Pouli\u00e9s",
    "gn:population":0,
    "gn:timezone":"Europe/Athens",
    "iso:country":"GR",
    "name:ell_x_preferred":[
        "\u00c1no Pouli\u00e9s"
    ],
    "name:ell_x_variant":[
        "\u0386\u03bd\u03c9 \u03a0\u03bf\u03c5\u03bb\u03b9\u03ad\u03c2",
        "\u0386\u03bd\u03c9 \u03a0\u03bf\u03c5\u03bb\u03b9\u03ac"
    ],
    "name:und_x_variant":[
        "Ep\u00e1no Po\u00falia",
        "\u00c1no Pouli\u00e1"
    ],
    "wof:name":"Ano Poulies",
    "wof:placetype":"locality"
},
  "geometry": {"coordinates":[25.2665,35.11694],"type":"Point"}
}