{
  "type": "Feature",
  "properties": {
    "gn:gn_country":"GR",
    "gn:gn_fcode":"PPL",
    "gn:gn_pop":918,
    "gn:population":918,
    "iso:country":"GR",
    "name:azb_x_preferred":[
        "\u067e\u0627\u0631\u0627\u0644\u06cc\u0645\u0646\u06cc"
    ],
    "name:aze_x_preferred":[
        "Paralimni"
    ],
    "name:bul_x_preferred":[
        "\u041f\u0430\u0440\u0430\u043b\u0438\u043c\u043d\u0438"
    ],
    "name:deu_x_preferred":[
        "Paralimni"
    ],
    "name:ell_x_preferred":[
        "Paral\u00edmni"
    ],
    "name:ell_x_variant":[
        "\u03a0\u03b1\u03c1\u03b1\u03bb\u03af\u03bc\u03bd\u03b7",
        "\u03a0\u03b1\u03c1\u03b1\u03bb\u03af\u03bc\u03bd\u03b9"
    ],
    "name:est_x_preferred":[
        "Paral\u00edmni"
    ],
    "name:fas_x_preferred":[
        "\u067e\u0627\u0631\u0627\u0644\u06cc\u0645\u0646\u06cc"
    ],
    "name:fin_x_preferred":[
        "Paral\u00edmni"
    ],
    "name:fra_x_preferred":[
        "Paral\u00edmni"
    ],
    "name:heb_x_preferred":[
        "\u05e4\u05d0\u05e8\u05d0\u05dc\u05d9\u05de\u05e0\u05d9"
    ],
    "name:ind_x_preferred":[
        "Paralimni"
    ],
    "name:ita_x_preferred":[
        "Paralimni"
    ],
    "name:kor_x_preferred":[
        "\ud30c\ub784\ub9bc\ub2c8"
    ],
    "name:lit_x_preferred":[
        "Paralimnis"
    ],
    "name:mkd_x_preferred":[
        "\u041f\u0430\u0440\u0430\u043b\u0438\u043c\u043d\u0438"
    ],
    "name:nld_x_preferred":[
        "Paralimni"
    ],
    "name:nno_x_preferred":[
        "Paral\u00edmni"
    ],
    "name:nor_x_preferred":[
        "Paralimni"
    ],
    "name:pol_x_preferred":[
        "Paralimni"
    ],
    "name:por_x_preferred":[
        "Paralimni"
    ],
    "name:rus_x_preferred":[
        "\u041f\u0430\u0440\u0430\u043b\u0438\u043c\u043d\u0438"
    ],
    "name:spa_x_preferred":[
        "Paralimni"
    ],
    "name:srp_x_preferred":[
        "\u041f\u0430\u0440\u0430\u043b\u0438\u043c\u043d\u0438"
    ],
    "name:swe_x_preferred":[
        "Paralimni"
    ],
    "name:tur_x_preferred":[
        "Paralimni"
    ],
    "name:ukr_x_preferred":[
        "\u041f\u0430\u0440\u0430\u043b\u0456\u043c\u043d\u0456"
    ],
    "name:urd_x_preferred":[
        "\u067e\u0627\u0631\u0627\u0644\u06cc\u0645\u06cc\u0646\u06cc"
    ],
    "name:zho_x_preferred":[
        "\u5e15\u62c9\u5229\u59c6\u5c3c"
    ],
    "qs_pg:aaroncc":"GR",
    "qs_pg:gn_country":"GR",
    "qs_pg:gn_fcode":"PPL",
    "qs_pg:gn_pop":918,
    "qs_pg:name":"Paralimni",
    "qs_pg:name_adm0":"\u0395\u03bb\u03bb\u03ac\u03b4\u03b1",
    "qs_pg:name_adm1":"Macedonia and Thrace",
    "qs_pg:photos_9k":1,
    "qs_pg:photos_9r":1,
    "qs_pg:photos_all":4,
    "qs_pg:photos_sr":0,
    "qs_pg:pop_sr":2,
    "qs_pg:qs_pg_placetype":"locality",
    "qs_pg:qs_pg_placetype_gp":"Town",
    "qs_pg:woe_adm0":23424833,
    "woe:adm0_id":23424833,
    "woe:name_adm0":"\u0395\u03bb\u03bb\u03ac\u03b4\u03b1",
    "woe:name_adm1":"Macedonia and Thrace",
    "woe:placetype":"Town",
    "wof:name":"Paralimni",
    "wof:placetype":"locality",
    "wof:population":918
},
  "geometry": {"coordinates":[22.45333,40.74861],"type":"Point"}
}