{
  "type": "Feature",
  "properties": {
    "gn:admin1_code":"ESYE41",
    "gn:asciiname":"Dafni",
    "gn:country_code":"GR",
    "gn:dem":293,
    "gn:feature_class":"P",
    "gn:feature_code":"PPL",
    "gn:name":"D\u00e1fni",
    "gn:population":0,
    "gn:timezone":"Europe/Athens",
    "iso:country":"GR",
    "name:bul_x_preferred":[
        "\u0414\u0430\u0444\u043d\u0438"
    ],
    "name:ceb_x_preferred":[
        "Dafni"
    ],
    "name:deu_x_preferred":[
        "Daphni"
    ],
    "name:ell_x_preferred":[
        "D\u00e1fni"
    ],
    "name:ell_x_variant":[
        "\u0394\u03ac\u03c6\u03bd\u03b7"
    ],
    "name:fin_x_preferred":[
        "D\u00e1fni"
    ],
    "name:fra_x_preferred":[
        "Dafni"
    ],
    "name:heb_x_preferred":[
        "\u05d3\u05e4\u05e0\u05d9"
    ],
    "name:ita_x_preferred":[
        "Dafni"
    ],
    "name:nld_x_preferred":[
        "Dafni"
    ],
    "name:pol_x_preferred":[
        "Dafni"
    ],
    "name:rus_x_preferred":[
        "\u0414\u0430\u0444\u043d\u0438"
    ],
    "name:sco_x_preferred":[
        "Dafni"
    ],
    "name:slk_x_preferred":[
        "Dafni"
    ],
    "name:swe_x_preferred":[
        "Dafni"
    ],
    "name:ukr_x_preferred":[
        "\u0414\u0430\u0444\u043d\u0456"
    ],
    "wof:name":"Dafni",
    "wof:placetype":"locality"
},
  "geometry": {"coordinates":[26.16397000000001,37.60282],"type":"Point"}
}