{
  "type": "Feature",
  "properties": {
    "gn:admin1_code":"ESYE41",
    "gn:asciiname":"Dafni",
    "gn:country_code":"GR",
    "gn:dem":293,
    "gn:feature_class":"P",
    "gn:feature_code":"PPL",
    "gn:name":"D\u00e1fni",
    "gn:population":0,
    "gn:timezone":"Europe/Athens",
    "iso:country":"GR",
    "name:ell_x_preferred":[
        "D\u00e1fni"
    ],
    "name:ell_x_variant":[
        "\u0394\u03ac\u03c6\u03bd\u03b7"
    ],
    "wof:name":"Dafni",
    "wof:placetype":"locality"
},
  "geometry": {"coordinates":[26.16397000000001,37.60282],"type":"Point"}
}