{
  "type": "Feature",
  "properties": {
    "gn:admin1_code":"ESYE25",
    "gn:admin2_code":"42.0",
    "gn:admin3_code":"9248",
    "gn:asciiname":"Pagkia",
    "gn:country_code":"GR",
    "gn:dem":179,
    "gn:feature_class":"P",
    "gn:feature_code":"PPL",
    "gn:name":"P\u00e1gkia",
    "gn:population":18,
    "gn:timezone":"Europe/Athens",
    "iso:country":"GR",
    "name:ell_x_preferred":[
        "\u03a0\u03ac\u03b3\u03ba\u03b9\u03b1"
    ],
    "name:eng_x_preferred":[
        "Pagkia"
    ],
    "name:und_x_variant":[
        "P\u00e1ngia"
    ],
    "wof:name":"Pagkia",
    "wof:placetype":"locality",
    "wof:population":18
},
  "geometry": {"coordinates":[22.37293,36.51281],"type":"Point"}
}