{
  "type": "Feature",
  "properties": {
    "gn:admin1_code":"ESYE25",
    "gn:admin2_code":"42.0",
    "gn:admin3_code":"9251",
    "gn:asciiname":"Favaiika",
    "gn:country_code":"GR",
    "gn:dem":56,
    "gn:feature_class":"P",
    "gn:feature_code":"PPL",
    "gn:name":"Fava\u00edika",
    "gn:population":0,
    "gn:timezone":"Europe/Athens",
    "iso:country":"GR",
    "wof:name":"Favaiika",
    "wof:placetype":"locality"
},
  "geometry": {"coordinates":[22.91868,36.68104],"type":"Point"}
}