{
  "type": "Feature",
  "properties": {
    "gn:admin1_code":"ESYE41",
    "gn:admin2_code":"51.0",
    "gn:admin3_code":"9261",
    "gn:asciiname":"Pigi",
    "gn:country_code":"GR",
    "gn:dem":127,
    "gn:feature_class":"P",
    "gn:feature_code":"PPL",
    "gn:name":"Pig\u00ed",
    "gn:population":350,
    "gn:timezone":"Europe/Athens",
    "iso:country":"GR",
    "name:ceb_x_preferred":[
        "Pigi"
    ],
    "name:ell_x_preferred":[
        "\u03a0\u03b7\u03b3\u03ae"
    ],
    "name:swe_x_preferred":[
        "Pigi"
    ],
    "name:und_x_variant":[
        "Piy\u00ed",
        "Pig\u00ed"
    ],
    "wof:name":"Pigi",
    "wof:placetype":"locality",
    "wof:population":350
},
  "geometry": {"coordinates":[26.41761,39.18207],"type":"Point"}
}