{
  "type": "Feature",
  "properties": {
    "gn:gn_country":"GR",
    "gn:gn_fcode":"PPL",
    "gn:gn_pop":78,
    "gn:population":78,
    "iso:country":"GR",
    "name:ell_x_preferred":[
        "\u0386\u03b3\u03b9\u03bf\u03c2 \u0393\u03b5\u03ce\u03c1\u03b3\u03b9\u03bf\u03c2"
    ],
    "name:unk_x_variant":[
        "\u00c1yios Ye\u00f3ryios"
    ],
    "qs_pg:aaroncc":"GR",
    "qs_pg:gn_country":"GR",
    "qs_pg:gn_fcode":"PPL",
    "qs_pg:gn_pop":78,
    "qs_pg:name":"\u00c1gios Ge\u00f3rgios",
    "qs_pg:photos_9r":0,
    "qs_pg:photos_sr":0,
    "qs_pg:pop_sr":1,
    "qs_pg:qs_pg_placetype":"locality",
    "wof:name":"\u00c1gios Ge\u00f3rgios",
    "wof:placetype":"locality",
    "wof:population":78
},
  "geometry": {"coordinates":[21.12556,39.38417],"type":"Point"}
}