{
  "type": "Feature",
  "properties": {
    "gn:admin1_code":"ESYE21",
    "gn:admin2_code":"20.0",
    "gn:admin3_code":"9074",
    "gn:asciiname":"Fisota",
    "gn:country_code":"GR",
    "gn:dem":521,
    "gn:feature_class":"P",
    "gn:feature_code":"PPL",
    "gn:name":"Fisot\u00e1",
    "gn:population":0,
    "gn:timezone":"Europe/Athens",
    "iso:country":"GR",
    "name:ell_x_preferred":[
        "Fisot\u00e1"
    ],
    "name:ell_x_variant":[
        "\u03a6\u03b9\u03c3\u03bf\u03c4\u03ac"
    ],
    "wof:name":"Fisota",
    "wof:placetype":"locality"
},
  "geometry": {"coordinates":[21.27517000000001,39.28758],"type":"Point"}
}