{
  "type": "Feature",
  "properties": {
    "gn:country":"GR",
    "gn:fcode":"PPL",
    "gn:population":0,
    "iso:country":"GR",
    "name:ell_x_preferred":[
        "\u039a\u03b1\u03bb\u03bf\u03b3\u03c1\u03ad\u03b6\u03b1"
    ],
    "name:eng_x_preferred":[
        "Kalogreza"
    ],
    "name:nld_x_preferred":[
        "Kalogreza"
    ],
    "name:rus_x_preferred":[
        "\u041a\u0430\u043b\u043e\u0433\u0440\u0435\u0437\u0430"
    ],
    "name:und_x_variant":[
        "Kalogr\u00e9za"
    ],
    "qs_pg:aaroncc":"GR",
    "qs_pg:gn_country":"GR",
    "qs_pg:gn_fcode":"PPL",
    "qs_pg:gn_pop":0,
    "qs_pg:name":"Kalogreza",
    "qs_pg:name_adm0":"\u0395\u03bb\u03bb\u03ac\u03b4\u03b1",
    "qs_pg:name_adm1":"Attica",
    "qs_pg:photos":88,
    "qs_pg:photos_1k":18,
    "qs_pg:photos_9k":1,
    "qs_pg:photos_9r":3,
    "qs_pg:photos_all":88,
    "qs_pg:photos_sr":3,
    "qs_pg:pop_sr":0,
    "qs_pg:qs_pg_placetype":"locality",
    "qs_pg:qs_pg_placetype_gp":"Town",
    "qs_pg:woe_adm0":23424833,
    "woe:adm0_id":23424833,
    "woe:name_adm0":"\u0395\u03bb\u03bb\u03ac\u03b4\u03b1",
    "woe:name_adm1":"Attica",
    "woe:placetype":"Town",
    "wof:name":"Kalogreza",
    "wof:placetype":"locality"
},
  "geometry": {"coordinates":[23.76667,38.03333],"type":"Point"}
}