{
  "type": "Feature",
  "properties": {
    "gn:country":"GR",
    "gn:fcode":"ADM3",
    "gn:population":11329,
    "iso:country":"GR",
    "name:ell_x_preferred":[
        "\u0395\u03c1\u03c5\u03bc\u03ac\u03bd\u03b8\u03bf\u03c5"
    ],
    "qs_pg:aaroncc":"GR",
    "qs_pg:gn_country":"GR",
    "qs_pg:gn_fcode":"ADM3",
    "qs_pg:gn_pop":11329,
    "qs_pg:name":"Dimos Erymanthos",
    "qs_pg:photos_9r":0,
    "qs_pg:photos_sr":0,
    "qs_pg:pop_sr":6,
    "qs_pg:qs_pg_placetype":"localadmin",
    "wof:name":"Dimos Erymanthos",
    "wof:placetype":"localadmin",
    "wof:population":11329
},
  "geometry": {"coordinates":[21.76798,38.02458],"type":"Point"}
}