{
  "type": "Feature",
  "properties": {
    "gn:admin1_code":"ESYE23",
    "gn:admin2_code":"39.0",
    "gn:admin3_code":"9135",
    "gn:asciiname":"Katsapaiika",
    "gn:country_code":"GR",
    "gn:dem":16,
    "gn:feature_class":"P",
    "gn:feature_code":"PPL",
    "gn:name":"Katsapa\u00edika",
    "gn:population":0,
    "gn:timezone":"Europe/Athens",
    "iso:country":"GR",
    "name:ell_x_preferred":[
        "Katsapa\u00edika"
    ],
    "name:ell_x_variant":[
        "\u039a\u03b1\u03c4\u03c3\u03b1\u03c0\u03b1\u03af\u03b9\u03ba\u03b1"
    ],
    "wof:name":"Katsapaiika",
    "wof:placetype":"locality"
},
  "geometry": {"coordinates":[21.31081,37.94169],"type":"Point"}
}