{
  "type": "Feature",
  "properties": {
    "gn:admin1_code":"ESYE14",
    "gn:admin2_code":"21.0",
    "gn:admin3_code":"9100",
    "gn:asciiname":"Amygdalia",
    "gn:country_code":"GR",
    "gn:dem":93,
    "gn:feature_class":"P",
    "gn:feature_code":"PPL",
    "gn:name":"Amygdali\u00e1",
    "gn:population":220,
    "gn:timezone":"Europe/Athens",
    "iso:country":"GR",
    "name:ell_x_preferred":[
        "\u0391\u03bc\u03c5\u03b3\u03b4\u03b1\u03bb\u03b9\u03ac"
    ],
    "name:ell_x_variant":[
        "\u0391\u03bc\u03c5\u03b3\u03b4\u03b1\u03bb\u03ad\u03b1"
    ],
    "name:eng_x_preferred":[
        "Amygdalia"
    ],
    "name:und_x_variant":[
        "Go\u00fanitsa",
        "Amigdhal\u00e9a",
        "Amygdali\u00e1"
    ],
    "wof:name":"Amygdalia",
    "wof:placetype":"locality",
    "wof:population":220
},
  "geometry": {"coordinates":[22.26369,39.65428],"type":"Point"}
}