{
  "type": "Feature",
  "properties": {
    "gn:admin1_code":"ESYE24",
    "gn:admin2_code":"29.0",
    "gn:admin3_code":"9160",
    "gn:asciiname":"Ypati",
    "gn:country_code":"GR",
    "gn:dem":394,
    "gn:feature_class":"P",
    "gn:feature_code":"PPL",
    "gn:name":"Yp\u00e1ti",
    "gn:population":496,
    "gn:timezone":"Europe/Athens",
    "iso:country":"GR",
    "name:ell_x_preferred":[
        "\u03a5\u03c0\u03ac\u03c4\u03b7"
    ],
    "name:ell_x_variant":[
        "Yp\u00e1ti"
    ],
    "name:eng_x_preferred":[
        "Ypati"
    ],
    "name:und_x_variant":[
        "Ip\u00e1ti"
    ],
    "wof:name":"Ypati",
    "wof:placetype":"locality",
    "wof:population":496
},
  "geometry": {"coordinates":[22.24156,38.87139000000001],"type":"Point"}
}