{
  "type": "Feature",
  "properties": {
    "gn:population":1302,
    "iso:country":"GR",
    "name:ara_x_preferred":[
        "\u062b\u0648\u0631\u064a\u0627"
    ],
    "name:ceb_x_preferred":[
        "Thour\u00eda"
    ],
    "name:ell_x_preferred":[
        "\u0394\u03ae\u03bc\u03bf\u03c2 \u0398\u03bf\u03c5\u03c1\u03af\u03b1\u03c2"
    ],
    "name:ell_x_variant":[
        "\u0398\u03bf\u03c5\u03c1\u03af\u03b1"
    ],
    "name:eng_x_preferred":[
        "Thouria"
    ],
    "name:fin_x_preferred":[
        "Thour\u00eda"
    ],
    "name:ita_x_preferred":[
        "Thouria"
    ],
    "name:jpn_x_preferred":[
        "\u30c8\u30a5\u30ea\u30a2"
    ],
    "name:nld_x_preferred":[
        "Thouria"
    ],
    "name:nno_x_preferred":[
        "Thour\u00eda"
    ],
    "name:swe_x_preferred":[
        "Thour\u00eda"
    ],
    "name:unk_x_variant":[
        "Thour\u00eda"
    ],
    "qs:a0":"Greece",
    "qs:a1":"*\u03a0\u0395\u039b\u039f\u03a0\u039f\u039d\u039d\u0397\u03a3\u039f\u03a3",
    "qs:a1_alt":"PELOPONNHSOS",
    "qs:a1r":"0",
    "qs:a2_alt":"MESSHNIA",
    "qs:adm0":"Greece",
    "qs:la_lc":"*",
    "qs:level":"locality",
    "qs:loc":"\u0398\u039f\u03a5\u03a1\u0399\u0391",
    "qs:loc_alt":"UOYRIA",
    "qs:pop":0,
    "qs:type":"buffered point",
    "wd:wordcount":69,
    "wof:name":"\u0398\u039f\u03a5\u03a1\u0399\u0391",
    "wof:placetype":"locality",
    "wof:population":1302
},
  "geometry": {"coordinates":[22.050349,37.084206],"type":"Point"}
}