{
  "type": "Feature",
  "properties": {
    "gn:admin1_code":"ESYE25",
    "gn:admin2_code":"40.0",
    "gn:admin3_code":"9257",
    "gn:asciiname":"Varakes",
    "gn:country_code":"GR",
    "gn:dem":113,
    "gn:feature_class":"P",
    "gn:feature_code":"PPL",
    "gn:name":"Var\u00e1kes",
    "gn:population":0,
    "gn:timezone":"Europe/Athens",
    "iso:country":"GR",
    "name:ell_x_preferred":[
        "\u0392\u03b1\u03c1\u03ac\u03ba\u03b5\u03c2"
    ],
    "name:ell_x_variant":[
        "\u0392\u03b1\u03c1\u03ac\u03ba\u03b1\u03b9"
    ],
    "name:und_x_variant":[
        "Var\u00e1kais",
        "Var\u00e1kkes",
        "Var\u00e1kas",
        "Var\u00e1kes",
        "Var\u00e1kai"
    ],
    "wof:name":"Varakes",
    "wof:placetype":"locality"
},
  "geometry": {"coordinates":[21.71473,36.86651],"type":"Point"}
}