{
  "type": "Feature",
  "properties": {
    "gn:admin1_code":"ESYE12",
    "gn:admin2_code":"16.0",
    "gn:admin3_code":"9047",
    "gn:asciiname":"Palaion Zazakon",
    "gn:country_code":"GR",
    "gn:dem":580,
    "gn:feature_class":"P",
    "gn:feature_code":"PPL",
    "gn:name":"Palai\u00f3n Z\u00e1zakon",
    "gn:population":0,
    "gn:timezone":"Europe/Athens",
    "iso:country":"GR",
    "wof:name":"Palaion Zazakon",
    "wof:placetype":"locality"
},
  "geometry": {"coordinates":[22.26944,40.21222],"type":"Point"}
}