{
  "type": "Feature",
  "properties": {
    "gn:admin1_code":"ESYE41",
    "gn:asciiname":"Profitis Ilias",
    "gn:country_code":"GR",
    "gn:dem":584,
    "gn:feature_class":"P",
    "gn:feature_code":"PPL",
    "gn:name":"Prof\u00edtis Il\u00edas",
    "gn:population":0,
    "gn:timezone":"Europe/Athens",
    "iso:country":"GR",
    "name:ceb_x_preferred":[
        "Profitis Ilias"
    ],
    "name:deu_x_preferred":[
        "Profitis Ilias"
    ],
    "name:ell_x_preferred":[
        "Prof\u00edtis Il\u00edas"
    ],
    "name:ell_x_variant":[
        "\u03a0\u03c1\u03bf\u03c6\u03ae\u03c4\u03b7\u03c2 \u0397\u03bb\u03af\u03b1\u03c2"
    ],
    "name:fin_x_preferred":[
        "Prof\u00edtis Il\u00edas"
    ],
    "name:fra_x_preferred":[
        "Prof\u00edtis Il\u00edas"
    ],
    "name:swe_x_preferred":[
        "Profitis Ilias"
    ],
    "wof:name":"Profitis Ilias",
    "wof:placetype":"locality"
},
  "geometry": {"coordinates":[26.07804,37.58948],"type":"Point"}
}