{
  "type": "Feature",
  "properties": {
    "gn:admin1_code":"ESYE25",
    "gn:admin2_code":"40.0",
    "gn:admin3_code":"9256",
    "gn:asciiname":"Vasiliko",
    "gn:country_code":"GR",
    "gn:dem":126,
    "gn:feature_class":"P",
    "gn:feature_code":"PPL",
    "gn:name":"Vasilik\u00f3",
    "gn:population":0,
    "gn:timezone":"Europe/Athens",
    "iso:country":"GR",
    "name:ceb_x_preferred":[
        "Vasiliko"
    ],
    "name:ell_x_preferred":[
        "Vasilik\u00f3"
    ],
    "name:ell_x_variant":[
        "\u0392\u03b1\u03c3\u03b9\u03bb\u03b9\u03ba\u03cc",
        "\u0392\u03b1\u03c3\u03b9\u03bb\u03b9\u03ba\u03cc\u03bd"
    ],
    "name:swe_x_preferred":[
        "Vasiliko"
    ],
    "name:und_x_variant":[
        "\u00c1no Vasilik\u00f3n II",
        "Vasilik\u00f3n"
    ],
    "wof:name":"Vasiliko",
    "wof:placetype":"locality"
},
  "geometry": {"coordinates":[21.8948,37.26678],"type":"Point"}
}