{
  "type": "Feature",
  "properties": {
    "gn:admin1_code":"ESYE43",
    "gn:admin2_code":"45.0",
    "gn:admin3_code":"9307",
    "gn:asciiname":"Sklaverokhorion",
    "gn:cc2":"GR",
    "gn:country_code":"GR",
    "gn:dem":326,
    "gn:feature_class":"P",
    "gn:feature_code":"PPL",
    "gn:name":"Sklaverokh\u00f3rion",
    "gn:population":0,
    "gn:timezone":"Europe/Athens",
    "iso:country":"GR",
    "name:und_x_variant":[
        "Sklavokh\u00f3ri",
        "Sklaverokh\u00f3ri",
        "Sklaverokh\u00f3rion"
    ],
    "wof:name":"Sklaverokhorion",
    "wof:placetype":"locality"
},
  "geometry": {"coordinates":[25.32134,35.20744000000001],"type":"Point"}
}