{
  "type": "Feature",
  "properties": {
    "gn:gn_country":"GR",
    "gn:gn_fcode":"PPL",
    "gn:gn_pop":128,
    "gn:population":48,
    "iso:country":"GR",
    "name:ell_x_preferred":[
        "\u039a\u03bf\u03c5\u03c1\u03bf\u03cd\u03bd\u03b9\u03b1"
    ],
    "name:eng_x_preferred":[
        "Kourounia"
    ],
    "qs_pg:aaroncc":"GR",
    "qs_pg:gn_country":"GR",
    "qs_pg:gn_fcode":"PPL",
    "qs_pg:gn_pop":128,
    "qs_pg:name":"Kourounia",
    "qs_pg:name_adm0":"\u0395\u03bb\u03bb\u03ac\u03b4\u03b1",
    "qs_pg:name_adm1":"Aegean",
    "qs_pg:photos_9r":0,
    "qs_pg:photos_sr":0,
    "qs_pg:pop_sr":1,
    "qs_pg:qs_pg_placetype":"locality",
    "qs_pg:qs_pg_placetype_gp":"Town",
    "qs_pg:woe_adm0":23424833,
    "woe:adm0_id":23424833,
    "woe:name_adm0":"\u0395\u03bb\u03bb\u03ac\u03b4\u03b1",
    "woe:name_adm1":"Aegean",
    "woe:placetype":"Town",
    "wof:name":"Kourounia",
    "wof:placetype":"locality",
    "wof:population":48
},
  "geometry": {"coordinates":[25.91402,38.56756],"type":"Point"}
}