{
  "type": "Feature",
  "properties": {
    "gn:population":5184,
    "iso:country":"GR",
    "name:ara_x_preferred":[
        "\u0623\u0644\u064a\u0641\u064a\u0631\u064a"
    ],
    "name:ceb_x_preferred":[
        "Aliv\u00e9ri"
    ],
    "name:deu_x_preferred":[
        "Aliveri"
    ],
    "name:ell_x_preferred":[
        "\u0391\u03bb\u03b9\u03b2\u03ad\u03c1\u03b9"
    ],
    "name:ell_x_variant":[
        "\u0391\u03bb\u03b9\u03b2\u03ad\u03c1\u03b9\u03bf\u03bd",
        "Aliv\u00e9ri",
        "\u0391\u03bb\u03b9\u03b2\u03ad\u03c1\u03b9 \u0395\u03cd\u03b2\u03bf\u03b9\u03b1\u03c2"
    ],
    "name:eng_x_preferred":[
        "Aliveri"
    ],
    "name:fin_x_preferred":[
        "Aliv\u00e9ri"
    ],
    "name:lat_x_preferred":[
        "Aliberium"
    ],
    "name:nld_x_preferred":[
        "Aliveri"
    ],
    "name:nno_x_preferred":[
        "Aliv\u00e9ri"
    ],
    "name:pol_x_preferred":[
        "Aliweri"
    ],
    "name:rus_x_preferred":[
        "\u0410\u043b\u0438\u0432\u0435\u0440\u0438\u043e\u043d"
    ],
    "name:swe_x_preferred":[
        "Aliv\u00e9ri"
    ],
    "name:und_x_variant":[
        "Aliv\u00e9rion"
    ],
    "qs:a0":"Greece",
    "qs:a1":"*\u03a3\u03a4\u0395\u03a1\u0395\u0391 \u0395\u039b\u039b\u0391\u0394\u0391",
    "qs:a1_alt":"STEREA ELLADA",
    "qs:a1r":"0",
    "qs:a2_alt":"EYVOIA",
    "qs:adm0":"Greece",
    "qs:la_lc":"*",
    "qs:level":"locality",
    "qs:loc":"\u0391\u039b\u0399\u0392\u0395\u03a1\u0399\u039f\u039d",
    "qs:loc_alt":"ALIBERION",
    "qs:pop":0,
    "qs:type":"buffered point",
    "wd:wordcount":202,
    "wof:name":"\u0391\u039b\u0399\u0392\u0395\u03a1\u0399\u039f\u039d",
    "wof:placetype":"locality",
    "wof:population":5184
},
  "geometry": {"coordinates":[24.039778,38.410022],"type":"Point"}
}