{
  "type": "Feature",
  "properties": {
    "gn:admin1_code":"ESYE22",
    "gn:admin2_code":"25.0",
    "gn:admin3_code":"9118",
    "gn:asciiname":"Sarakinatika",
    "gn:country_code":"GR",
    "gn:dem":192,
    "gn:feature_class":"P",
    "gn:feature_code":"PPL",
    "gn:name":"Sarakin\u00e1tika",
    "gn:population":31,
    "gn:timezone":"Europe/Athens",
    "iso:country":"GR",
    "name:ell_x_preferred":[
        "\u03a3\u03b1\u03c1\u03b1\u03ba\u03b7\u03bd\u03ac\u03c4\u03b9\u03ba\u03b1"
    ],
    "name:eng_x_preferred":[
        "Sarakinatika"
    ],
    "wof:name":"Sarakinatika",
    "wof:placetype":"locality",
    "wof:population":31
},
  "geometry": {"coordinates":[19.93439,39.75049],"type":"Point"}
}