{
  "type": "Feature",
  "properties": {
    "gn:admin1_code":"ESYE43",
    "gn:admin2_code":"46.0",
    "gn:admin3_code":"9310",
    "gn:asciiname":"Perampela",
    "gn:country_code":"GR",
    "gn:dem":550,
    "gn:feature_class":"P",
    "gn:feature_code":"PPL",
    "gn:name":"Per\u00e1mpela",
    "gn:population":5,
    "gn:timezone":"Europe/Athens",
    "iso:country":"GR",
    "name:ell_x_preferred":[
        "\u03a0\u03b5\u03c1\u03ac\u03bc\u03c0\u03b5\u03bb\u03b1"
    ],
    "name:eng_x_preferred":[
        "Perampela"
    ],
    "name:und_x_variant":[
        "Per\u00e1mpela"
    ],
    "wof:name":"Perampela",
    "wof:placetype":"locality",
    "wof:population":5
},
  "geometry": {"coordinates":[25.64735,35.28882],"type":"Point"}
}