{
  "type": "Feature",
  "properties": {
    "gn:admin1_code":"ESYE43",
    "gn:admin2_code":"44.0",
    "gn:admin3_code":"9314",
    "gn:asciiname":"Mixorrouma",
    "gn:country_code":"GR",
    "gn:dem":341,
    "gn:feature_class":"P",
    "gn:feature_code":"PPL",
    "gn:name":"Mix\u00f3rrouma",
    "gn:population":0,
    "gn:timezone":"Europe/Athens",
    "iso:country":"GR",
    "wof:name":"Mixorrouma",
    "wof:placetype":"locality"
},
  "geometry": {"coordinates":[24.50449,35.21547],"type":"Point"}
}