{
  "type": "Feature",
  "properties": {
    "gn:admin1_code":"ESYE25",
    "gn:admin2_code":"41.0",
    "gn:admin3_code":"9238",
    "gn:asciiname":"Pirris",
    "gn:cc2":"GR",
    "gn:country_code":"GR",
    "gn:dem":168,
    "gn:feature_class":"P",
    "gn:feature_code":"PPL",
    "gn:name":"Pirr\u00eds",
    "gn:population":0,
    "gn:timezone":"Europe/Athens",
    "iso:country":"GR",
    "name:und_x_variant":[
        "Pir\u00ed",
        "Pirr\u00eds"
    ],
    "wof:name":"Pirris",
    "wof:placetype":"locality"
},
  "geometry": {"coordinates":[21.84114,37.6162],"type":"Point"}
}