{
  "type": "Feature",
  "properties": {
    "gn:gn_country":"GR",
    "gn:gn_fcode":"PPL",
    "gn:gn_pop":0,
    "iso:country":"GR",
    "name:deu_x_preferred":[
        "Evdilos"
    ],
    "name:ell_x_preferred":[
        "\u00c9vdilos"
    ],
    "name:ell_x_variant":[
        "\u0395\u03cd\u03b4\u03b7\u03bb\u03bf\u03c2",
        "\u0394\u03ae\u03bc\u03bf\u03c2 \u0395\u03c5\u03b4\u03ae\u03bb\u03bf\u03c5"
    ],
    "name:eng_x_preferred":[
        "Evdilos"
    ],
    "name:fin_x_preferred":[
        "\u00c9vdilos"
    ],
    "name:fra_x_preferred":[
        "Evdilos"
    ],
    "name:ita_x_preferred":[
        "Evdilos"
    ],
    "name:jpn_x_preferred":[
        "\u30a8\u30f4\u30c7\u30a3\u30ed\u30b9"
    ],
    "name:nld_x_preferred":[
        "Evdilos"
    ],
    "name:nno_x_preferred":[
        "\u00c9vdilos"
    ],
    "name:pol_x_preferred":[
        "Ewdilos"
    ],
    "name:unk_x_variant":[
        "\u00c9vdhilos"
    ],
    "qs_pg:aaroncc":"GR",
    "qs_pg:gn_country":"GR",
    "qs_pg:gn_fcode":"PPL",
    "qs_pg:gn_pop":0,
    "qs_pg:name":"Evdhilos",
    "qs_pg:name_adm0":"\u0395\u03bb\u03bb\u03ac\u03b4\u03b1",
    "qs_pg:name_adm1":"Aegean",
    "qs_pg:photos":17,
    "qs_pg:photos_1k":3,
    "qs_pg:photos_9k":1,
    "qs_pg:photos_9r":1,
    "qs_pg:photos_all":17,
    "qs_pg:photos_sr":1,
    "qs_pg:pop_sr":0,
    "qs_pg:qs_pg_placetype":"locality",
    "qs_pg:qs_pg_placetype_gp":"Town",
    "qs_pg:woe_adm0":23424833,
    "woe:adm0_id":23424833,
    "woe:name_adm0":"\u0395\u03bb\u03bb\u03ac\u03b4\u03b1",
    "woe:name_adm1":"Aegean",
    "woe:placetype":"Town",
    "wof:name":"Evdhilos",
    "wof:placetype":"locality"
},
  "geometry": {"coordinates":[26.18333,37.61667],"type":"Point"}
}