{
  "type": "Feature",
  "properties": {
    "gn:admin1_code":"ESYE23",
    "gn:admin2_code":"39.0",
    "gn:admin3_code":"9141",
    "gn:asciiname":"Pefki",
    "gn:country_code":"GR",
    "gn:dem":564,
    "gn:feature_class":"P",
    "gn:feature_code":"PPL",
    "gn:name":"P\u00e9fki",
    "gn:population":0,
    "gn:timezone":"Europe/Athens",
    "iso:country":"GR",
    "name:ell_x_preferred":[
        "P\u00e9fki"
    ],
    "name:ell_x_variant":[
        "\u03a0\u03b5\u03cd\u03ba\u03b7"
    ],
    "name:und_x_variant":[
        "Bend\u00e9ni",
        "P\u00e9vki"
    ],
    "wof:name":"Pefki",
    "wof:placetype":"locality"
},
  "geometry": {"coordinates":[21.65783,37.77378],"type":"Point"}
}