{
  "type": "Feature",
  "properties": {
    "gn:admin1_code":"ESYE23",
    "gn:admin2_code":"39.0",
    "gn:admin3_code":"9141",
    "gn:asciiname":"Pefki",
    "gn:country_code":"GR",
    "gn:dem":564,
    "gn:feature_class":"P",
    "gn:feature_code":"PPL",
    "gn:name":"P\u00e9fki",
    "gn:population":0,
    "gn:timezone":"Europe/Athens",
    "iso:country":"GR",
    "name:ara_x_preferred":[
        "\u0628\u064a\u0641\u0643\u064a"
    ],
    "name:bul_x_preferred":[
        "\u041f\u0435\u0444\u043a\u0438"
    ],
    "name:ceb_x_preferred":[
        "P\u00e9fki"
    ],
    "name:ell_x_preferred":[
        "P\u00e9fki"
    ],
    "name:ell_x_variant":[
        "\u03a0\u03b5\u03cd\u03ba\u03b7"
    ],
    "name:fas_x_preferred":[
        "\u067e\u0641\u06a9\u06cc"
    ],
    "name:fin_x_preferred":[
        "P\u00e9fki"
    ],
    "name:ita_x_preferred":[
        "Pefki"
    ],
    "name:nno_x_preferred":[
        "P\u00e9vki"
    ],
    "name:pol_x_preferred":[
        "Pefki"
    ],
    "name:ron_x_preferred":[
        "Pefki"
    ],
    "name:rus_x_preferred":[
        "\u041f\u0435\u0444\u043a\u0438"
    ],
    "name:sco_x_preferred":[
        "Pefki"
    ],
    "name:swe_x_preferred":[
        "P\u00e9fki"
    ],
    "name:tur_x_preferred":[
        "Pefki"
    ],
    "name:ukr_x_preferred":[
        "\u041f\u0435\u0444\u043a\u0456"
    ],
    "name:und_x_variant":[
        "Bend\u00e9ni",
        "P\u00e9vki"
    ],
    "name:urd_x_preferred":[
        "\u067e\u06cc\u0641\u06a9\u06cc"
    ],
    "wof:name":"Pefki",
    "wof:placetype":"locality"
},
  "geometry": {"coordinates":[21.65783,37.77378],"type":"Point"}
}