{
  "type": "Feature",
  "properties": {
    "iso:country":"GR",
    "qs:a0":"Greece",
    "qs:a1":"*\u039a\u0395\u039d\u03a4\u03a1\u0399\u039a\u0397 \u039c\u0391\u039a\u0395\u0394\u039f\u039d\u0399\u0391",
    "qs:a1_alt":"KENTRIKH MAKEDONIA",
    "qs:a1r":"0",
    "qs:a2_alt":"XALKIDIKH",
    "qs:adm0":"Greece",
    "qs:la_lc":"*",
    "qs:level":"locality",
    "qs:loc":"\u039d\u0395\u0391 \u039c\u039f\u03a5\u0394\u0391\u039d\u0399\u0391",
    "qs:loc_alt":"NEA MOYDANIA",
    "qs:pop":0,
    "qs:type":"buffered point",
    "wof:name":"\u039d\u0395\u0391 \u039c\u039f\u03a5\u0394\u0391\u039d\u0399\u0391",
    "wof:placetype":"locality"
},
  "geometry": {"coordinates":[23.288057,40.241085],"type":"Point"}
}