{
  "type": "Feature",
  "properties": {
    "gn:admin1_code":"ESYE25",
    "gn:admin2_code":"37.0",
    "gn:admin3_code":"9247",
    "gn:asciiname":"Kefalarion",
    "gn:country_code":"GR",
    "gn:dem":803,
    "gn:feature_class":"P",
    "gn:feature_code":"PPL",
    "gn:name":"Kefal\u00e1rion",
    "gn:population":251,
    "gn:timezone":"Europe/Athens",
    "iso:country":"GR",
    "name:ell_x_preferred":[
        "\u039a\u03b5\u03c6\u03b1\u03bb\u03ac\u03c1\u03b9"
    ],
    "name:ell_x_variant":[
        "\u039a\u03b5\u03c6\u03b1\u03bb\u03ac\u03c1\u03b9\u03bf\u03bd"
    ],
    "name:eng_x_preferred":[
        "Kefalari"
    ],
    "name:und_x_variant":[
        "Do\u00fasa",
        "Kefal\u00e1ri",
        "Do\u00fasia",
        "Kefal\u00e1rion"
    ],
    "wof:name":"Kefalarion",
    "wof:placetype":"locality",
    "wof:population":251
},
  "geometry": {"coordinates":[22.51223,37.92214],"type":"Point"}
}