{
  "type": "Feature",
  "properties": {
    "gn:admin1_code":"ESYE13",
    "gn:admin2_code":"10.0",
    "gn:admin3_code":"9061",
    "gn:asciiname":"Mikrokleisoura",
    "gn:country_code":"GR",
    "gn:dem":573,
    "gn:feature_class":"P",
    "gn:feature_code":"PPL",
    "gn:name":"Mikrokleiso\u00fara",
    "gn:population":0,
    "gn:timezone":"Europe/Athens",
    "iso:country":"GR",
    "name:bul_x_preferred":[
        "\u041c\u0438\u043a\u0440\u043e\u043a\u043b\u0438\u0441\u0443\u0440\u0430"
    ],
    "name:ell_x_preferred":[
        "Mikrokleiso\u00fara"
    ],
    "name:ell_x_variant":[
        "\u039c\u03b9\u03ba\u03c1\u03bf\u03ba\u03bb\u03b5\u03b9\u03c3\u03bf\u03cd\u03c1\u03b1"
    ],
    "name:und_x_variant":[
        "Sadov\u00edtsa",
        "Mikrokliso\u00fara"
    ],
    "wof:name":"Mikrokleisoura",
    "wof:placetype":"locality"
},
  "geometry": {"coordinates":[21.54715,40.14761],"type":"Point"}
}