{
  "type": "Feature",
  "properties": {
    "gn:admin1_code":"ESYE14",
    "gn:admin2_code":"23.0",
    "gn:admin3_code":"9096",
    "gn:asciiname":"Yefiria",
    "gn:cc2":"GR",
    "gn:country_code":"GR",
    "gn:dem":111,
    "gn:feature_class":"P",
    "gn:feature_code":"PPL",
    "gn:name":"Yef\u00edria",
    "gn:population":0,
    "gn:timezone":"Europe/Athens",
    "iso:country":"GR",
    "name:ell_x_preferred":[
        "\u0393\u03b5\u03c6\u03cd\u03c1\u03b9\u03b1"
    ],
    "name:und_x_variant":[
        "Koprindz\u00ed",
        "Koprinj\u00ed",
        "Yef\u00edria"
    ],
    "wof:name":"Yefiria",
    "wof:placetype":"locality"
},
  "geometry": {"coordinates":[22.1923,39.29146],"type":"Point"}
}