{
  "type": "Feature",
  "properties": {
    "gn:admin1_code":"ESYE23",
    "gn:admin2_code":"39.0",
    "gn:admin3_code":"9138",
    "gn:asciiname":"Skhinoi",
    "gn:cc2":"GR",
    "gn:country_code":"GR",
    "gn:dem":161,
    "gn:feature_class":"P",
    "gn:feature_code":"PPL",
    "gn:name":"Skh\u00ednoi",
    "gn:population":0,
    "gn:timezone":"Europe/Athens",
    "iso:country":"GR",
    "name:und_x_variant":[
        "Beskh\u00ednoi",
        "Skh\u00ednoi"
    ],
    "wof:name":"Skhinoi",
    "wof:placetype":"locality"
},
  "geometry": {"coordinates":[21.67778,37.48002],"type":"Point"}
}