{
  "type": "Feature",
  "properties": {
    "gn:population":3714,
    "iso:country":"GR",
    "name:ara_x_preferred":[
        "\u0644\u064a\u062e\u0627\u064a\u0646\u0627"
    ],
    "name:bul_x_preferred":[
        "\u041b\u0435\u0445\u0435\u043d\u0430"
    ],
    "name:ceb_x_preferred":[
        "Lechain\u00e1"
    ],
    "name:cym_x_preferred":[
        "Lechaina"
    ],
    "name:ell_x_preferred":[
        "\u039b\u03b5\u03c7\u03b1\u03b9\u03bd\u03ac"
    ],
    "name:ell_x_variant":[
        "Lechain\u00e1",
        "\u039b\u03b5\u03c7\u03b1\u03b9\u03bd\u03ac \u0397\u03bb\u03b5\u03af\u03b1\u03c2"
    ],
    "name:eng_x_preferred":[
        "Lechaina"
    ],
    "name:fin_x_preferred":[
        "Lechain\u00e1"
    ],
    "name:fra_x_preferred":[
        "Lechaina"
    ],
    "name:ita_x_preferred":[
        "Lechaina"
    ],
    "name:jpn_x_preferred":[
        "\u30ec\u30d8\u30ca"
    ],
    "name:nld_x_preferred":[
        "Lechaina"
    ],
    "name:nno_x_preferred":[
        "Lekhen\u00e1"
    ],
    "name:ron_x_preferred":[
        "Lechaina"
    ],
    "name:rus_x_preferred":[
        "\u041b\u0435\u0445\u0435\u043d\u0430"
    ],
    "name:swe_x_preferred":[
        "Lechain\u00e1"
    ],
    "name:und_x_variant":[
        "Lekhain\u00e1"
    ],
    "qs:a0":"Greece",
    "qs:a1":"*\u0394\u03a5\u03a4\u0399\u039a\u0397 \u0395\u039b\u039b\u0391\u0394\u0391",
    "qs:a1_alt":"DYTIKH ELLADA",
    "qs:a1r":"0",
    "qs:a2_alt":"HLEIA",
    "qs:adm0":"Greece",
    "qs:la_lc":"*",
    "qs:level":"locality",
    "qs:loc":"\u039b\u0395\u03a7\u0391\u0399\u039d\u0391",
    "qs:loc_alt":"LEXAINA",
    "qs:pop":0,
    "qs:type":"buffered point",
    "wd:wordcount":222,
    "wof:name":"\u039b\u0395\u03a7\u0391\u0399\u039d\u0391",
    "wof:placetype":"locality",
    "wof:population":3714
},
  "geometry": {"coordinates":[21.261032,37.937927],"type":"Point"}
}