{
  "type": "Feature",
  "properties": {
    "gn:admin1_code":"ESYE14",
    "gn:admin2_code":"21.0",
    "gn:admin3_code":"9103",
    "gn:asciiname":"Avra",
    "gn:country_code":"GR",
    "gn:dem":132,
    "gn:feature_class":"P",
    "gn:feature_code":"PPL",
    "gn:name":"\u00c1vra",
    "gn:population":0,
    "gn:timezone":"Europe/Athens",
    "iso:country":"GR",
    "name:ceb_x_preferred":[
        "Avra"
    ],
    "name:deu_x_preferred":[
        "Avra"
    ],
    "name:ell_x_preferred":[
        "\u00c1vra"
    ],
    "name:ell_x_variant":[
        "\u0391\u03cd\u03c1\u03b1"
    ],
    "name:fra_x_preferred":[
        "Avra"
    ],
    "name:swe_x_preferred":[
        "Avra"
    ],
    "name:und_x_variant":[
        "Sarikayi\u00e1s",
        "Sarikay\u00e1s",
        "A\u1e2fra"
    ],
    "wof:name":"Avra",
    "wof:placetype":"locality"
},
  "geometry": {"coordinates":[22.32575,39.38831],"type":"Point"}
}