{
  "type": "Feature",
  "properties": {
    "gn:admin1_code":"ESYE43",
    "gn:admin2_code":"45.0",
    "gn:admin3_code":"9308",
    "gn:asciiname":"Platia Peramata",
    "gn:country_code":"GR",
    "gn:dem":29,
    "gn:feature_class":"P",
    "gn:feature_code":"PPL",
    "gn:name":"Plati\u00e1 Per\u00e1mata",
    "gn:population":0,
    "gn:timezone":"Europe/Athens",
    "iso:country":"GR",
    "name:ell_x_preferred":[
        "Plati\u00e1 Per\u00e1mata"
    ],
    "name:ell_x_variant":[
        "\u03a0\u03bb\u03b1\u03c4\u03b9\u03ac \u03a0\u03b5\u03c1\u03ac\u03bc\u03b1\u03c4\u03b1"
    ],
    "wof:name":"Platia Peramata",
    "wof:placetype":"locality"
},
  "geometry": {"coordinates":[24.84987000000001,34.94212],"type":"Point"}
}