{
  "type": "Feature",
  "properties": {
    "gn:admin1_code":"ESYE25",
    "gn:admin2_code":"42.0",
    "gn:admin3_code":"9248",
    "gn:asciiname":"Gialia",
    "gn:country_code":"GR",
    "gn:dem":23,
    "gn:feature_class":"P",
    "gn:feature_code":"PPL",
    "gn:name":"Giali\u00e1",
    "gn:population":7,
    "gn:timezone":"Europe/Athens",
    "iso:country":"GR",
    "name:bul_x_preferred":[
        "\u0413\u0438\u0430\u043b\u0438\u044f"
    ],
    "name:ceb_x_preferred":[
        "Giali\u00e1"
    ],
    "name:ell_x_preferred":[
        "\u0393\u03b9\u03b1\u03bb\u03b9\u03ac"
    ],
    "name:eng_x_preferred":[
        "Gialia"
    ],
    "name:hye_x_preferred":[
        "\u0533\u056b\u0561\u056c\u056b\u0561"
    ],
    "name:pol_x_preferred":[
        "Jalia"
    ],
    "name:swe_x_preferred":[
        "Giali\u00e1"
    ],
    "name:urd_x_preferred":[
        "\u06cc\u0627\u0644\u0627"
    ],
    "wof:name":"Gialia",
    "wof:placetype":"locality",
    "wof:population":7
},
  "geometry": {"coordinates":[22.4135,36.4779],"type":"Point"}
}