{
  "type": "Feature",
  "properties": {
    "gn:admin1_code":"ESYE43",
    "gn:admin2_code":"43.0",
    "gn:admin3_code":"9322",
    "gn:asciiname":"Kontoudiana",
    "gn:country_code":"GR",
    "gn:dem":359,
    "gn:feature_class":"P",
    "gn:feature_code":"PPL",
    "gn:name":"Kontoudian\u00e1",
    "gn:population":7,
    "gn:timezone":"Europe/Athens",
    "iso:country":"GR",
    "name:ell_x_preferred":[
        "\u039a\u03bf\u03bd\u03c4\u03bf\u03c5\u03b4\u03b9\u03b1\u03bd\u03ac"
    ],
    "name:eng_x_preferred":[
        "Kontoudiana"
    ],
    "name:und_x_variant":[
        "Kontoudian\u00e1"
    ],
    "wof:name":"Kontoudiana",
    "wof:placetype":"locality",
    "wof:population":7
},
  "geometry": {"coordinates":[23.71446,35.39918],"type":"Point"}
}