{
  "type": "Feature",
  "properties": {
    "gn:admin1_code":"ESYE25",
    "gn:admin2_code":"41.0",
    "gn:admin3_code":"9240.0",
    "gn:asciiname":"Petra",
    "gn:country_code":"GR",
    "gn:dem":182,
    "gn:feature_class":"P",
    "gn:feature_code":"PPL",
    "gn:name":"Petra",
    "gn:population":0,
    "gn:timezone":"Europe/Athens",
    "iso:country":"GR",
    "name:ell_x_preferred":[
        "\u03a0\u03ad\u03c4\u03c1\u03b1"
    ],
    "name:ell_x_variant":[
        "\u03a0\u03ad\u03c4\u03c1\u03b1 \u0391\u03c1\u03ba\u03b1\u03b4\u03af\u03b1\u03c2"
    ],
    "wof:name":"Petra",
    "wof:placetype":"locality"
},
  "geometry": {"coordinates":[22.88415,37.21206],"type":"Point"}
}