{
  "type": "Feature",
  "properties": {
    "gn:admin1_code":"ESYE25",
    "gn:asciiname":"Panayaiika",
    "gn:country_code":"GR",
    "gn:dem":141,
    "gn:feature_class":"P",
    "gn:feature_code":"PPL",
    "gn:name":"Panaya\u00edika",
    "gn:population":0,
    "gn:timezone":"Europe/Athens",
    "iso:country":"GR",
    "wof:name":"Panayaiika",
    "wof:placetype":"locality"
},
  "geometry": {"coordinates":[21.40197,37.91996],"type":"Point"}
}