{
  "type": "Feature",
  "properties": {
    "gn:admin1_code":"ESYE31",
    "gn:admin2_code":"445406.0",
    "gn:admin3_code":"9219",
    "gn:asciiname":"Maristra",
    "gn:country_code":"GR",
    "gn:dem":123,
    "gn:feature_class":"P",
    "gn:feature_code":"PPL",
    "gn:name":"Mar\u00edstra",
    "gn:population":34,
    "gn:timezone":"Europe/Athens",
    "iso:country":"GR",
    "name:ell_x_preferred":[
        "\u039c\u03b1\u03c1\u03af\u03c3\u03c4\u03c1\u03b1"
    ],
    "name:eng_x_preferred":[
        "Maristra"
    ],
    "wof:name":"Maristra",
    "wof:placetype":"locality",
    "wof:population":34
},
  "geometry": {"coordinates":[24.03736,37.82772],"type":"Point"}
}