{
  "type": "Feature",
  "properties": {
    "gn:admin1_code":"ESYE25",
    "gn:admin2_code":"41.0",
    "gn:admin3_code":"9239",
    "gn:asciiname":"Vastas",
    "gn:country_code":"GR",
    "gn:dem":850,
    "gn:feature_class":"P",
    "gn:feature_code":"PPL",
    "gn:name":"V\u00e1stas",
    "gn:population":0,
    "gn:timezone":"Europe/Athens",
    "iso:country":"GR",
    "name:ell_x_preferred":[
        "\u0392\u03ac\u03c3\u03c4\u03b1\u03c2"
    ],
    "name:und_x_variant":[
        "V\u00e1stas",
        "V\u00e1sta"
    ],
    "wof:name":"Vastas",
    "wof:placetype":"locality"
},
  "geometry": {"coordinates":[21.9861,37.36648],"type":"Point"}
}