{
  "type": "Feature",
  "properties": {
    "gn:admin1_code":"ESYE22",
    "gn:admin2_code":"25.0",
    "gn:admin3_code":"9118",
    "gn:asciiname":"Temploni",
    "gn:country_code":"GR",
    "gn:dem":113,
    "gn:feature_class":"P",
    "gn:feature_code":"PPL",
    "gn:name":"Templ\u00f3ni",
    "gn:population":356,
    "gn:timezone":"Europe/Athens",
    "iso:country":"GR",
    "name:ell_x_preferred":[
        "\u03a4\u03b5\u03bc\u03c0\u03bb\u03cc\u03bd\u03b9"
    ],
    "name:eng_x_preferred":[
        "Temploni"
    ],
    "wof:name":"Temploni",
    "wof:placetype":"locality",
    "wof:population":356
},
  "geometry": {"coordinates":[19.8047,39.64003],"type":"Point"}
}