{
  "type": "Feature",
  "properties": {
    "gn:admin1_code":"ESYE12",
    "gn:admin2_code":"7.0",
    "gn:admin3_code":"9044",
    "gn:asciiname":"Mandria Kaltsa",
    "gn:country_code":"GR",
    "gn:dem":116,
    "gn:feature_class":"P",
    "gn:feature_code":"PPL",
    "gn:name":"Mandri\u00e1 Kalts\u00e1",
    "gn:population":0,
    "gn:timezone":"Europe/Athens",
    "iso:country":"GR",
    "wof:name":"Mandria Kaltsa",
    "wof:placetype":"locality"
},
  "geometry": {"coordinates":[22.45722,40.8225],"type":"Point"}
}