{
  "type": "Feature",
  "properties": {
    "gn:admin1_code":"ESYE25",
    "gn:admin2_code":"42.0",
    "gn:admin3_code":"9252",
    "gn:asciiname":"Kouremenos",
    "gn:cc2":"GR",
    "gn:country_code":"GR",
    "gn:dem":471,
    "gn:feature_class":"P",
    "gn:feature_code":"PPL",
    "gn:name":"Kourem\u00e9nos",
    "gn:population":0,
    "gn:timezone":"Europe/Athens",
    "iso:country":"GR",
    "name:ell_x_preferred":[
        "\u039a\u03bf\u03c5\u03c1\u03b5\u03bc\u03ad\u03bd\u03bf\u03c2"
    ],
    "name:und_x_variant":[
        "Kourem\u00e9no",
        "Kourem\u00e9nos"
    ],
    "wof:name":"Kouremenos",
    "wof:placetype":"locality"
},
  "geometry": {"coordinates":[22.37336,37.20717],"type":"Point"}
}