{
  "type": "Feature",
  "properties": {
    "gn:admin1_code":"ESYE43",
    "gn:admin2_code":"45.0",
    "gn:admin3_code":"9304",
    "gn:asciiname":"Krotos",
    "gn:country_code":"GR",
    "gn:dem":418,
    "gn:feature_class":"P",
    "gn:feature_code":"PPL",
    "gn:name":"Kr\u00f3tos",
    "gn:population":0,
    "gn:timezone":"Europe/Athens",
    "iso:country":"GR",
    "name:aze_x_preferred":[
        "Krotos"
    ],
    "name:deu_x_preferred":[
        "Krotos"
    ],
    "name:ell_x_preferred":[
        "\u039a\u03c1\u03cc\u03c4\u03bf\u03c2"
    ],
    "name:fra_x_preferred":[
        "Crotos"
    ],
    "name:ita_x_preferred":[
        "Croto"
    ],
    "name:rus_x_preferred":[
        "\u041a\u0440\u043e\u0442\u043e\u0441"
    ],
    "name:spa_x_preferred":[
        "Croto"
    ],
    "name:srp_x_preferred":[
        "\u041a\u0440\u043e\u0442"
    ],
    "name:swe_x_preferred":[
        "Krotos"
    ],
    "wof:name":"Krotos",
    "wof:placetype":"locality"
},
  "geometry": {"coordinates":[24.95553,34.96102],"type":"Point"}
}