{
  "type": "Feature",
  "properties": {
    "gn:admin1_code":"ESYE43",
    "gn:admin2_code":"45.0",
    "gn:admin3_code":"9304",
    "gn:asciiname":"Krotos",
    "gn:country_code":"GR",
    "gn:dem":418,
    "gn:feature_class":"P",
    "gn:feature_code":"PPL",
    "gn:name":"Kr\u00f3tos",
    "gn:population":0,
    "gn:timezone":"Europe/Athens",
    "iso:country":"GR",
    "wof:name":"Krotos",
    "wof:placetype":"locality"
},
  "geometry": {"coordinates":[24.95553,34.96102],"type":"Point"}
}