{
  "type": "Feature",
  "properties": {
    "gn:admin1_code":"ESYE22",
    "gn:admin2_code":"25.0",
    "gn:admin3_code":"9118",
    "gn:asciiname":"Omali",
    "gn:country_code":"GR",
    "gn:dem":336,
    "gn:feature_class":"P",
    "gn:feature_code":"PPL",
    "gn:name":"Omal\u00ed",
    "gn:population":39,
    "gn:timezone":"Europe/Athens",
    "iso:country":"GR",
    "name:ell_x_preferred":[
        "\u039f\u03bc\u03b1\u03bb\u03ae"
    ],
    "wof:name":"Omali",
    "wof:placetype":"locality",
    "wof:population":39
},
  "geometry": {"coordinates":[19.81813,39.74376],"type":"Point"}
}