{
  "type": "Feature",
  "properties": {
    "gn:country":"GR",
    "gn:fcode":"ADM3",
    "gn:population":39870,
    "iso:country":"GR",
    "name:ceb_x_preferred":[
        "Dimos Moschato-Tavros"
    ],
    "name:deu_x_preferred":[
        "Moschato-Tavros"
    ],
    "name:ell_x_preferred":[
        "\u039c\u03bf\u03c3\u03c7\u03ac\u03c4\u03bf\u03c5 - \u03a4\u03b1\u03cd\u03c1\u03bf\u03c5"
    ],
    "name:ell_x_variant":[
        "\u0394\u03ae\u03bc\u03bf\u03c2 \u039c\u03bf\u03c3\u03c7\u03ac\u03c4\u03bf\u03c5-\u03a4\u03b1\u03cd\u03c1\u03bf\u03c5"
    ],
    "name:fin_x_preferred":[
        "Mosch\u00e1to-T\u00e1vros"
    ],
    "name:fra_x_preferred":[
        "Mosch\u00e1to-T\u00e1vros"
    ],
    "name:ita_x_preferred":[
        "Moschato-Tavros"
    ],
    "name:nld_x_preferred":[
        "Moschato-Tavros"
    ],
    "name:nno_x_preferred":[
        "Moskh\u00e1to-T\u00e1vros"
    ],
    "name:pol_x_preferred":[
        "Moschato-Tawros"
    ],
    "name:rus_x_preferred":[
        "\u041c\u043e\u0441\u0445\u0430\u0442\u043e\u043d-\u0422\u0430\u0432\u0440\u043e\u0441"
    ],
    "name:srp_x_preferred":[
        "\u041c\u043e\u0441\u0445\u0430\u0442\u043e-\u0422\u0430\u0432\u0440\u043e\u0441"
    ],
    "name:swe_x_preferred":[
        "Dimos Moschato-Tavros"
    ],
    "name:tur_x_preferred":[
        "Moshato-Tavros"
    ],
    "name:vie_x_preferred":[
        "Moschato-Tavros"
    ],
    "qs_pg:aaroncc":"GR",
    "qs_pg:gn_country":"GR",
    "qs_pg:gn_fcode":"ADM3",
    "qs_pg:gn_pop":39870,
    "qs_pg:name":"Moschato-Tavros",
    "qs_pg:name_adm0":"\u0395\u03bb\u03bb\u03ac\u03b4\u03b1",
    "qs_pg:name_adm1":"Attica",
    "qs_pg:photos_9k":18,
    "qs_pg:photos_9r":12,
    "qs_pg:photos_all":4082,
    "qs_pg:photos_sr":0,
    "qs_pg:pop_sr":7,
    "qs_pg:qs_pg_placetype":"localadmin",
    "qs_pg:qs_pg_placetype_gp":"LocalAdmin",
    "qs_pg:woe_adm0":23424833,
    "woe:adm0_id":23424833,
    "woe:name_adm0":"\u0395\u03bb\u03bb\u03ac\u03b4\u03b1",
    "woe:name_adm1":"Attica",
    "woe:placetype":"LocalAdmin",
    "wof:name":"Moschato-Tavros",
    "wof:placetype":"localadmin",
    "wof:population":40413
},
  "geometry": {"coordinates":[23.68876,37.96117],"type":"Point"}
}