{
  "type": "Feature",
  "properties": {
    "gn:gn_country":"GR",
    "gn:gn_fcode":"ADM3",
    "gn:gn_pop":39870,
    "gn:population":40413,
    "iso:country":"GR",
    "name:ell_x_preferred":[
        "\u039c\u03bf\u03c3\u03c7\u03ac\u03c4\u03bf\u03c5 - \u03a4\u03b1\u03cd\u03c1\u03bf\u03c5"
    ],
    "qs_pg:aaroncc":"GR",
    "qs_pg:gn_country":"GR",
    "qs_pg:gn_fcode":"ADM3",
    "qs_pg:gn_pop":39870,
    "qs_pg:name":"Moschato-Tavros",
    "qs_pg:name_adm0":"\u0395\u03bb\u03bb\u03ac\u03b4\u03b1",
    "qs_pg:name_adm1":"Attica",
    "qs_pg:photos_9k":18,
    "qs_pg:photos_9r":12,
    "qs_pg:photos_all":4082,
    "qs_pg:photos_sr":0,
    "qs_pg:pop_sr":7,
    "qs_pg:qs_pg_placetype":"localadmin",
    "qs_pg:qs_pg_placetype_gp":"LocalAdmin",
    "qs_pg:woe_adm0":23424833,
    "woe:adm0_id":23424833,
    "woe:name_adm0":"\u0395\u03bb\u03bb\u03ac\u03b4\u03b1",
    "woe:name_adm1":"Attica",
    "woe:placetype":"LocalAdmin",
    "wof:name":"Moschato-Tavros",
    "wof:placetype":"localadmin",
    "wof:population":40413
},
  "geometry": {"coordinates":[23.68876,37.96117],"type":"Point"}
}