{
  "type": "Feature",
  "properties": {
    "gn:gn_country":"GR",
    "gn:gn_fcode":"PPL",
    "gn:gn_pop":304,
    "gn:population":304,
    "iso:country":"GR",
    "name:ceb_x_preferred":[
        "Fotein\u00f3"
    ],
    "name:ell_x_preferred":[
        "\u03a6\u03c9\u03c4\u03b5\u03b9\u03bd\u03cc"
    ],
    "name:ell_x_variant":[
        "\u03a6\u03c9\u03c4\u03b5\u03b9\u03bd\u03cc\u03bd",
        "\u03a6\u03c9\u03c4\u03b5\u03b9\u03bd\u03cc \u0386\u03c1\u03c4\u03b1\u03c2"
    ],
    "name:eng_x_preferred":[
        "Foteino"
    ],
    "name:nld_x_preferred":[
        "Foteino"
    ],
    "name:swe_x_preferred":[
        "Fotein\u00f3"
    ],
    "name:unk_x_variant":[
        "Khosian\u00e1"
    ],
    "qs_pg:aaroncc":"GR",
    "qs_pg:gn_country":"GR",
    "qs_pg:gn_fcode":"PPL",
    "qs_pg:gn_pop":304,
    "qs_pg:name":"Fotein\u00f3n",
    "qs_pg:photos_9r":0,
    "qs_pg:photos_sr":0,
    "qs_pg:pop_sr":2,
    "qs_pg:qs_pg_placetype":"locality",
    "wof:name":"Fotein\u00f3n",
    "wof:placetype":"locality",
    "wof:population":304
},
  "geometry": {"coordinates":[21.10833,39.13361],"type":"Point"}
}