{
  "type": "Feature",
  "properties": {
    "gn:admin1_code":"ESYE21",
    "gn:admin2_code":"20.0",
    "gn:admin3_code":"9076",
    "gn:asciiname":"Sykies",
    "gn:country_code":"GR",
    "gn:dem":2,
    "gn:feature_class":"P",
    "gn:feature_code":"PPL",
    "gn:name":"Syki\u00e9s",
    "gn:population":0,
    "gn:timezone":"Europe/Athens",
    "iso:country":"GR",
    "name:ara_x_preferred":[
        "\u0633\u064a\u0643\u064a\u064a\u0633"
    ],
    "name:bul_x_preferred":[
        "\u0421\u0438\u043a\u0438\u0435\u0441"
    ],
    "name:ceb_x_preferred":[
        "Syki\u00e9s"
    ],
    "name:deu_x_preferred":[
        "Sykies"
    ],
    "name:ell_x_preferred":[
        "\u03a3\u03c5\u03ba\u03b9\u03ad\u03c2"
    ],
    "name:ell_x_variant":[
        "\u03a3\u03c5\u03ba\u03b9\u03ad\u03c2 \u0398\u03b5\u03c3\u03c3\u03b1\u03bb\u03bf\u03bd\u03af\u03ba\u03b7\u03c2"
    ],
    "name:fas_x_preferred":[
        "\u0633\u06cc\u06af\u0632"
    ],
    "name:fin_x_preferred":[
        "Syki\u00e9s"
    ],
    "name:fra_x_preferred":[
        "Syki\u00e9s"
    ],
    "name:ita_x_preferred":[
        "Sykies"
    ],
    "name:mkd_x_preferred":[
        "\u0421\u0438\u043a\u0458\u0435\u0441"
    ],
    "name:nno_x_preferred":[
        "Syki\u00e9s"
    ],
    "name:pol_x_preferred":[
        "Sikies"
    ],
    "name:ron_x_preferred":[
        "Sykies"
    ],
    "name:srp_x_preferred":[
        "\u0421\u0438\u043a\u0438\u0458\u0435\u0441"
    ],
    "name:swe_x_preferred":[
        "Syki\u00e9s"
    ],
    "name:ukr_x_preferred":[
        "\u0421\u0456\u043a\u0456\u0435\u0441"
    ],
    "name:und_x_variant":[
        "Sik\u00e9ai",
        "Siki\u00e9s",
        "Syk\u00e9ai"
    ],
    "name:urd_x_preferred":[
        "\u0633\u06cc\u06a9\u06cc\u0626\u0633"
    ],
    "wof:name":"Sykies",
    "wof:placetype":"locality"
},
  "geometry": {"coordinates":[21.05365,39.06229],"type":"Point"}
}