{
  "type": "Feature",
  "properties": {
    "gn:admin1_code":"ESYE21",
    "gn:admin2_code":"20.0",
    "gn:admin3_code":"9076",
    "gn:asciiname":"Sykies",
    "gn:country_code":"GR",
    "gn:dem":2,
    "gn:feature_class":"P",
    "gn:feature_code":"PPL",
    "gn:name":"Syki\u00e9s",
    "gn:population":0,
    "gn:timezone":"Europe/Athens",
    "iso:country":"GR",
    "name:ell_x_preferred":[
        "\u03a3\u03c5\u03ba\u03b9\u03ad\u03c2"
    ],
    "name:und_x_variant":[
        "Sik\u00e9ai",
        "Syki\u00e9s",
        "Siki\u00e9s",
        "Syk\u00e9ai"
    ],
    "wof:name":"Sykies",
    "wof:placetype":"locality"
},
  "geometry": {"coordinates":[21.05365,39.06229],"type":"Point"}
}