{
  "type": "Feature",
  "properties": {
    "gn:admin1_code":"ESYE43",
    "gn:admin2_code":"43.0",
    "gn:admin3_code":"9319",
    "gn:asciiname":"Vatoudiaris",
    "gn:country_code":"GR",
    "gn:dem":419,
    "gn:feature_class":"P",
    "gn:feature_code":"PPL",
    "gn:name":"Vatoudi\u00e1ris",
    "gn:population":0,
    "gn:timezone":"Europe/Athens",
    "iso:country":"GR",
    "name:ell_x_preferred":[
        "Vatoudi\u00e1ris"
    ],
    "name:ell_x_variant":[
        "\u0392\u03b1\u03c4\u03bf\u03c5\u03b4\u03b9\u03ac\u03c1\u03b7\u03c2",
        "Vatoudhi\u00e1ris"
    ],
    "wof:name":"Vatoudiaris",
    "wof:placetype":"locality"
},
  "geometry": {"coordinates":[24.18147,35.3325],"type":"Point"}
}