{
  "type": "Feature",
  "properties": {
    "gn:admin1_code":"ESYE43",
    "gn:admin2_code":"45.0",
    "gn:admin3_code":"9305",
    "gn:asciiname":"Silamos",
    "gn:country_code":"GR",
    "gn:dem":202,
    "gn:feature_class":"P",
    "gn:feature_code":"PPL",
    "gn:name":"S\u00edlamos",
    "gn:population":0,
    "gn:timezone":"Europe/Athens",
    "iso:country":"GR",
    "name:ell_x_preferred":[
        "S\u00edlamos"
    ],
    "name:ell_x_variant":[
        "\u03a3\u03af\u03bb\u03b1\u03bc\u03bf\u03c2"
    ],
    "wof:name":"Silamos",
    "wof:placetype":"locality"
},
  "geometry": {"coordinates":[25.15069,35.26846],"type":"Point"}
}