{
  "type": "Feature",
  "properties": {
    "gn:admin1_code":"ESYE24",
    "gn:admin2_code":"30.0",
    "gn:admin3_code":"9156",
    "gn:asciiname":"Paliochori",
    "gn:country_code":"GR",
    "gn:dem":553,
    "gn:feature_class":"P",
    "gn:feature_code":"PPL",
    "gn:name":"Palioch\u00f3ri",
    "gn:population":0,
    "gn:timezone":"Europe/Athens",
    "iso:country":"GR",
    "name:ell_x_preferred":[
        "\u03a0\u03b1\u03bb\u03b1\u03b9\u03bf\u03c7\u03ce\u03c1\u03b9"
    ],
    "name:ell_x_variant":[
        "Palioch\u00f3ri",
        "\u03a0\u03b1\u03bb\u03b9\u03bf\u03c7\u03ce\u03c1\u03b9",
        "Palioch\u00f3rion",
        "\u03a0\u03b1\u03bb\u03b9\u03bf\u03c7\u03ce\u03c1\u03b9\u03bf\u03bd"
    ],
    "name:und_x_variant":[
        "Palaiokh\u00f3ri",
        "Paliokh\u00f3ri",
        "Palaiokh\u00f3rion"
    ],
    "wof:name":"Paliochori",
    "wof:placetype":"locality"
},
  "geometry": {"coordinates":[21.57783,38.90339],"type":"Point"}
}