{
  "type": "Feature",
  "properties": {
    "gn:gn_country":"GR",
    "gn:gn_fcode":"PPL",
    "gn:gn_pop":978,
    "gn:population":557,
    "iso:country":"GR",
    "name:ara_x_preferred":[
        "\u0623\u064a\u064a\u0627 \u0628\u0627\u0631\u0627\u0633\u0643\u064a\u0641\u064a\u060c \u0633\u064a\u0631\u0631\u064a"
    ],
    "name:bul_x_preferred":[
        "\u0421\u0443\u0445\u0430 \u0431\u0430\u043d\u044f"
    ],
    "name:ell_x_preferred":[
        "Ag\u00eda Paraskev\u00ed"
    ],
    "name:ell_x_variant":[
        "\u0391\u03b3\u03af\u03b1 \u03a0\u03b1\u03c1\u03b1\u03c3\u03ba\u03b5\u03c5\u03ae",
        "\u0391\u03b3\u03af\u03b1 \u03a0\u03b1\u03c1\u03b1\u03c3\u03ba\u03b5\u03c5\u03ae \u03a3\u03b5\u03c1\u03c1\u03ce\u03bd"
    ],
    "name:eng_x_preferred":[
        "Agia Paraskevi"
    ],
    "name:mkd_x_preferred":[
        "\u0421\u0443\u0445\u0430 \u0411\u0430\u045a\u0430"
    ],
    "name:nld_x_preferred":[
        "Agia Paraskevi Serres"
    ],
    "name:rus_x_preferred":[
        "\u0410\u0439\u044f \u041f\u0430\u0440\u0430\u0441\u043a\u0435\u0432\u0438"
    ],
    "name:swe_x_preferred":[
        "Ag\u00eda Paraskev\u00ed"
    ],
    "name:unk_x_variant":[
        "Xil\u00f3tron"
    ],
    "qs_pg:aaroncc":"GR",
    "qs_pg:gn_country":"GR",
    "qs_pg:gn_fcode":"PPL",
    "qs_pg:gn_pop":978,
    "qs_pg:name":"Ayia Paraskevi",
    "qs_pg:name_adm0":"\u0395\u03bb\u03bb\u03ac\u03b4\u03b1",
    "qs_pg:name_adm1":"Macedonia and Thrace",
    "qs_pg:photos_9r":0,
    "qs_pg:photos_sr":0,
    "qs_pg:pop_sr":2,
    "qs_pg:qs_pg_placetype":"locality",
    "qs_pg:qs_pg_placetype_gp":"Town",
    "qs_pg:woe_adm0":23424833,
    "woe:adm0_id":23424833,
    "woe:name_adm0":"\u0395\u03bb\u03bb\u03ac\u03b4\u03b1",
    "woe:name_adm1":"Macedonia and Thrace",
    "woe:placetype":"Town",
    "wof:name":"Ayia Paraskevi",
    "wof:placetype":"locality",
    "wof:population":557
},
  "geometry": {"coordinates":[23.46667,40.95],"type":"Point"}
}