{
  "type": "Feature",
  "properties": {
    "gn:admin1_code":"ESYE22",
    "gn:admin2_code":"25.0",
    "gn:admin3_code":"9118",
    "gn:asciiname":"Stavros",
    "gn:country_code":"GR",
    "gn:dem":158,
    "gn:feature_class":"P",
    "gn:feature_code":"PPL",
    "gn:name":"Stavr\u00f3s",
    "gn:population":0,
    "gn:timezone":"Europe/Athens",
    "iso:country":"GR",
    "name:ceb_x_preferred":[
        "Stavros"
    ],
    "name:deu_x_preferred":[
        "Stavros"
    ],
    "name:ell_x_preferred":[
        "\u03a3\u03c4\u03b1\u03c5\u03c1\u03cc\u03c2"
    ],
    "name:swe_x_preferred":[
        "Stavros"
    ],
    "name:und_x_variant":[
        "Chalidi\u00e1ta",
        "Stavr\u00f3s"
    ],
    "wof:name":"Stavros",
    "wof:placetype":"locality"
},
  "geometry": {"coordinates":[19.91067,39.53731],"type":"Point"}
}