{
  "type": "Feature",
  "properties": {
    "gn:gn_country":"GR",
    "gn:gn_fcode":"PPL",
    "gn:gn_pop":1410,
    "gn:population":1410,
    "iso:country":"GR",
    "name:ara_x_preferred":[
        "\u0631\u064a\u0632\u0648\u0645\u0627\u060c \u062a\u0631\u064a\u0643\u0627\u0644\u0627"
    ],
    "name:dut_x_preferred":[
        "Rizoma"
    ],
    "name:ell_x_preferred":[
        "\u03a1\u03af\u03b6\u03c9\u03bc\u03b1"
    ],
    "name:eng_x_preferred":[
        "Rizoma"
    ],
    "name:gre_x_preferred":[
        "\u03a1\u03af\u03b6\u03c9\u03bc\u03b1 \u03a4\u03c1\u03b9\u03ba\u03ac\u03bb\u03c9\u03bd"
    ],
    "name:nno_x_preferred":[
        "R\u00edzoma"
    ],
    "name:swe_x_preferred":[
        "R\u00edzoma"
    ],
    "name:unk_x_variant":[
        "Skl\u00e1taina"
    ],
    "qs_pg:aaroncc":"GR",
    "qs_pg:gn_country":"GR",
    "qs_pg:gn_fcode":"PPL",
    "qs_pg:gn_pop":1410,
    "qs_pg:name":"Rizoma",
    "qs_pg:name_adm0":"\u0395\u03bb\u03bb\u03ac\u03b4\u03b1",
    "qs_pg:name_adm1":"Thessaly and Continental Greece",
    "qs_pg:photos_9r":0,
    "qs_pg:photos_sr":0,
    "qs_pg:pop_sr":3,
    "qs_pg:qs_pg_placetype":"locality",
    "qs_pg:qs_pg_placetype_gp":"Town",
    "qs_pg:woe_adm0":23424833,
    "woe:adm0_id":23424833,
    "woe:name_adm0":"\u0395\u03bb\u03bb\u03ac\u03b4\u03b1",
    "woe:name_adm1":"Thessaly and Continental Greece",
    "woe:placetype":"Town",
    "wof:name":"Rizoma",
    "wof:placetype":"locality",
    "wof:population":1410
},
  "geometry": {"coordinates":[21.735,39.665],"type":"Point"}
}