{
  "type": "Feature",
  "properties": {
    "gn:admin1_code":"ESYE25",
    "gn:admin2_code":"37.0",
    "gn:admin3_code":"9244.0",
    "gn:asciiname":"Agios Filippos",
    "gn:country_code":"GR",
    "gn:dem":164,
    "gn:feature_class":"P",
    "gn:feature_code":"PPL",
    "gn:name":"\u00c1gios F\u00edlippos",
    "gn:population":0,
    "gn:timezone":"Europe/Athens",
    "iso:country":"GR",
    "name:ell_x_preferred":[
        "\u00c1gios F\u00edlippos"
    ],
    "name:ell_x_variant":[
        "\u0386\u03b3\u03b9\u03bf\u03c2 \u03a6\u03af\u03bb\u03b9\u03c0\u03c0\u03bf\u03c2"
    ],
    "wof:name":"Agios Filippos",
    "wof:placetype":"locality"
},
  "geometry": {"coordinates":[23.121,37.94548],"type":"Point"}
}