{
  "type": "Feature",
  "properties": {
    "gn:admin1_code":"ESYE31",
    "gn:admin2_code":"445406.0",
    "gn:admin3_code":"9227.0",
    "gn:asciiname":"Skala Markopoulou",
    "gn:country_code":"GR",
    "gn:dem":6,
    "gn:feature_class":"P",
    "gn:feature_code":"PPL",
    "gn:name":"Sk\u00e1la Mark\u00f3poulou",
    "gn:population":0,
    "gn:timezone":"Europe/Athens",
    "iso:country":"GR",
    "name:ell_x_preferred":[
        "Sk\u00e1la Mark\u00f3poulou"
    ],
    "name:ell_x_variant":[
        "\u03a3\u03ba\u03ac\u03bb\u03b1 \u039c\u03b1\u03c1\u03ba\u03cc\u03c0\u03bf\u03c5\u03bb\u03bf\u03c5"
    ],
    "wof:name":"Skala Markopoulou",
    "wof:placetype":"locality"
},
  "geometry": {"coordinates":[23.8122,38.32178],"type":"Point"}
}