{
  "type": "Feature",
  "properties": {
    "gn:admin1_code":"ESYE14",
    "gn:admin2_code":"24.0",
    "gn:admin3_code":"9105",
    "gn:asciiname":"Sesklo",
    "gn:country_code":"GR",
    "gn:dem":206,
    "gn:feature_class":"P",
    "gn:feature_code":"PPL",
    "gn:name":"S\u00e9sklo",
    "gn:population":0,
    "gn:timezone":"Europe/Athens",
    "iso:country":"GR",
    "name:cat_x_preferred":[
        "Sesklo"
    ],
    "name:ces_x_preferred":[
        "Sesklo"
    ],
    "name:ell_x_preferred":[
        "S\u00e9sklo"
    ],
    "name:ell_x_variant":[
        "\u03a3\u03ad\u03c3\u03ba\u03bb\u03bf",
        "\u03a3\u03ad\u03c3\u03ba\u03bb\u03bf\u03bd"
    ],
    "name:fra_x_preferred":[
        "S\u00e9sklo"
    ],
    "name:ita_x_preferred":[
        "Sesklo"
    ],
    "name:lfn_x_preferred":[
        "Cultur Sesclo"
    ],
    "name:slk_x_preferred":[
        "Sesklo"
    ],
    "name:slv_x_preferred":[
        "Sesklo"
    ],
    "name:spa_x_preferred":[
        "Sesklo"
    ],
    "name:swe_x_preferred":[
        "Sesklo"
    ],
    "name:und_x_variant":[
        "S\u00e9skoulo",
        "S\u00e9skoulon",
        "S\u00e9sklon"
    ],
    "wof:name":"Sesklo",
    "wof:placetype":"locality"
},
  "geometry": {"coordinates":[22.83415,39.35459],"type":"Point"}
}