{
  "type": "Feature",
  "properties": {
    "iso:country":"GR",
    "name:ara_x_preferred":[
        "\u0625\u064a\u0648\u0633"
    ],
    "name:cat_x_preferred":[
        "\u00cdos"
    ],
    "name:ceb_x_preferred":[
        "N\u00edsos \u00cdos"
    ],
    "name:ces_x_preferred":[
        "Ios"
    ],
    "name:dan_x_preferred":[
        "Ios"
    ],
    "name:deu_x_preferred":[
        "Ios"
    ],
    "name:ell_x_preferred":[
        "\u038a\u03bf\u03c2"
    ],
    "name:fin_x_preferred":[
        "\u00cdos"
    ],
    "name:fra_x_preferred":[
        "Ios"
    ],
    "name:glg_x_preferred":[
        "Ios"
    ],
    "name:heb_x_preferred":[
        "\u05d0\u05d9\u05d5\u05e1"
    ],
    "name:hun_x_preferred":[
        "\u00cdosz"
    ],
    "name:ind_x_preferred":[
        "Ios"
    ],
    "name:ita_x_preferred":[
        "Io"
    ],
    "name:jpn_x_preferred":[
        "\u30a4\u30aa\u30b9\u5cf6"
    ],
    "name:kor_x_preferred":[
        "\uc774\uc624\uc2a4\uc12c"
    ],
    "name:lat_x_preferred":[
        "Ios"
    ],
    "name:nld_x_preferred":[
        "Ios"
    ],
    "name:nno_x_preferred":[
        "\u00cdos"
    ],
    "name:nor_x_preferred":[
        "Ios"
    ],
    "name:pol_x_preferred":[
        "Ios"
    ],
    "name:por_x_preferred":[
        "Ios"
    ],
    "name:ron_x_preferred":[
        "Ios"
    ],
    "name:rus_x_preferred":[
        "\u0418\u043e\u0441"
    ],
    "name:spa_x_preferred":[
        "Ios"
    ],
    "name:sqi_x_preferred":[
        "Ios"
    ],
    "name:srp_x_preferred":[
        "\u0408\u043e\u0441"
    ],
    "name:swe_x_preferred":[
        "Ios"
    ],
    "name:tha_x_preferred":[
        "\u0e40\u0e01\u0e32\u0e30\u0e2d\u0e35\u0e2d\u0e2d\u0e2a"
    ],
    "name:tur_x_preferred":[
        "\u0130os"
    ],
    "name:ukr_x_preferred":[
        "\u0406\u043e\u0441"
    ],
    "name:vie_x_preferred":[
        "Ios"
    ],
    "name:zho_x_preferred":[
        "\u4f0a\u5967\u65af\u5cf6"
    ],
    "qs_pg:aaroncc":"GR",
    "qs_pg:name":"Ios",
    "qs_pg:name_adm0":"\u0395\u03bb\u03bb\u03ac\u03b4\u03b1",
    "qs_pg:name_adm1":"Aegean",
    "qs_pg:photos":303,
    "qs_pg:photos_1k":61,
    "qs_pg:photos_9k":1,
    "qs_pg:photos_9r":5,
    "qs_pg:photos_all":303,
    "qs_pg:photos_sr":5,
    "qs_pg:pop_sr":0,
    "qs_pg:qs_pg_placetype":"locality",
    "qs_pg:qs_pg_placetype_gp":"Town",
    "qs_pg:woe_adm0":23424833,
    "woe:adm0_id":23424833,
    "woe:name_adm0":"\u0395\u03bb\u03bb\u03ac\u03b4\u03b1",
    "woe:name_adm1":"Aegean",
    "woe:placetype":"Town",
    "wof:name":"Ios",
    "wof:placetype":"locality"
},
  "geometry": {"coordinates":[25.282105,36.722099],"type":"Point"}
}