{
  "type": "Feature",
  "properties": {
    "gn:admin1_code":"ESYE25",
    "gn:admin2_code":"41.0",
    "gn:admin3_code":"9238",
    "gn:asciiname":"Vlongos",
    "gn:country_code":"GR",
    "gn:dem":1079,
    "gn:feature_class":"P",
    "gn:feature_code":"PPL",
    "gn:name":"Vl\u00f3ngos",
    "gn:population":0,
    "gn:timezone":"Europe/Athens",
    "iso:country":"GR",
    "name:ell_x_preferred":[
        "Vl\u00f3ngos"
    ],
    "name:ell_x_variant":[
        "\u0392\u03bb\u03cc\u03b3\u03b3\u03bf\u03c2"
    ],
    "wof:name":"Vlongos",
    "wof:placetype":"locality"
},
  "geometry": {"coordinates":[21.99613,37.59431],"type":"Point"}
}