{
  "type": "Feature",
  "properties": {
    "gn:admin1_code":"ESYE11",
    "gn:admin2_code":"4.0",
    "gn:admin3_code":"9001",
    "gn:asciiname":"Agapi",
    "gn:country_code":"GR",
    "gn:dem":202,
    "gn:feature_class":"P",
    "gn:feature_code":"PPL",
    "gn:name":"Ag\u00e1pi",
    "gn:population":0,
    "gn:timezone":"Europe/Athens",
    "iso:country":"GR",
    "name:ell_x_preferred":[
        "\u0391\u03b3\u03ac\u03c0\u03b7"
    ],
    "name:und_x_variant":[
        "Himitl\u00ed",
        "Ag\u00e1pi"
    ],
    "wof:name":"Agapi",
    "wof:placetype":"locality"
},
  "geometry": {"coordinates":[24.30382,41.10334],"type":"Point"}
}