{
  "type": "Feature",
  "properties": {
    "gn:population":4191,
    "iso:country":"GR",
    "name:ara_x_preferred":[
        "\u0643\u0648\u0631\u064a\u0646\u0648\u0633"
    ],
    "name:bul_x_preferred":[
        "\u041a\u043e\u0440\u0438\u043d\u043e\u0441"
    ],
    "name:deu_x_preferred":[
        "Korinos"
    ],
    "name:dut_x_preferred":[
        "Korinos"
    ],
    "name:ell_x_preferred":[
        "\u039a\u03bf\u03c1\u03b9\u03bd\u03cc\u03c2"
    ],
    "name:eng_x_preferred":[
        "Korinos"
    ],
    "name:fre_x_preferred":[
        "Korinos"
    ],
    "name:ger_x_preferred":[
        "Korinos"
    ],
    "name:gre_x_preferred":[
        "\u039a\u03bf\u03c1\u03b9\u03bd\u03cc\u03c2"
    ],
    "name:ita_x_preferred":[
        "Korinos"
    ],
    "name:jpn_x_preferred":[
        "\u30b3\u30ea\u30ce\u30b9"
    ],
    "name:nld_x_preferred":[
        "Korinos"
    ],
    "name:nno_x_preferred":[
        "Korin\u00f3s"
    ],
    "name:pol_x_preferred":[
        "Korinos"
    ],
    "name:swe_x_preferred":[
        "Korin\u00f3s"
    ],
    "name:unk_x_variant":[
        "Korin\u00f3s"
    ],
    "qs:a0":"Greece",
    "qs:a1":"*\u039a\u0395\u039d\u03a4\u03a1\u0399\u039a\u0397 \u039c\u0391\u039a\u0395\u0394\u039f\u039d\u0399\u0391",
    "qs:a1_alt":"KENTRIKH MAKEDONIA",
    "qs:a1r":"0",
    "qs:a2_alt":"PIERIA",
    "qs:adm0":"Greece",
    "qs:la_lc":"*",
    "qs:level":"locality",
    "qs:loc":"\u039a\u039f\u03a1\u0399\u039d\u039f\u03a3",
    "qs:loc_alt":"KORINOS",
    "qs:pop":0,
    "qs:type":"buffered point",
    "wd:population":3487,
    "wd:wordcount":381,
    "wof:name":"\u039a\u039f\u03a1\u0399\u039d\u039f\u03a3",
    "wof:placetype":"locality",
    "wof:population":3487
},
  "geometry": {"coordinates":[22.588739,40.31522],"type":"Point"}
}