{
  "type": "Feature",
  "properties": {
    "gn:admin1_code":"ESYE25",
    "gn:admin2_code":"37.0",
    "gn:admin3_code":"9244.0",
    "gn:asciiname":"Sesi",
    "gn:country_code":"GR",
    "gn:dem":60,
    "gn:feature_class":"P",
    "gn:feature_code":"PPL",
    "gn:name":"S\u00e9si",
    "gn:population":0,
    "gn:timezone":"Europe/Athens",
    "iso:country":"GR",
    "name:ell_x_preferred":[
        "S\u00e9si"
    ],
    "name:ell_x_variant":[
        "\u03a3\u03ad\u03c3\u03b9"
    ],
    "wof:name":"Sesi",
    "wof:placetype":"locality"
},
  "geometry": {"coordinates":[23.12563,37.93053],"type":"Point"}
}