{
  "type": "Feature",
  "properties": {
    "gn:admin1_code":"ESYE12",
    "gn:admin2_code":"6.0",
    "gn:admin3_code":"9040",
    "gn:asciiname":"Kyriakaiika",
    "gn:country_code":"GR",
    "gn:dem":166,
    "gn:feature_class":"P",
    "gn:feature_code":"PPL",
    "gn:name":"Kyriaka\u00edika",
    "gn:population":0,
    "gn:timezone":"Europe/Athens",
    "iso:country":"GR",
    "name:ell_x_preferred":[
        "Kyriaka\u00edika"
    ],
    "name:ell_x_variant":[
        "\u039a\u03c5\u03c1\u03b9\u03b1\u03ba\u03b1\u03af\u03b9\u03ba\u03b1"
    ],
    "name:und_x_variant":[
        "Synoikism\u00f3s Sarakatsana\u00edon"
    ],
    "wof:name":"Kyriakaiika",
    "wof:placetype":"locality"
},
  "geometry": {"coordinates":[22.7764,40.97981],"type":"Point"}
}