{
  "type": "Feature",
  "properties": {
    "gn:population":1141,
    "iso:country":"GR",
    "name:ara_x_preferred":[
        "\u0628\u064a\u0631\u0627\u0643\u0648\u0631\u0627"
    ],
    "name:deu_x_preferred":[
        "Perachora"
    ],
    "name:ell_x_preferred":[
        "\u03a0\u03b5\u03c1\u03b1\u03c7\u03ce\u03c1\u03b1 \u039a\u03bf\u03c1\u03b9\u03bd\u03b8\u03af\u03b1\u03c2"
    ],
    "name:ell_x_variant":[
        "\u03a0\u03b5\u03c1\u03b1\u03c7\u03ce\u03c1\u03b1",
        "Perach\u00f3ra"
    ],
    "name:eng_x_preferred":[
        "Perachora"
    ],
    "name:fin_x_preferred":[
        "Perach\u00f3ra"
    ],
    "name:nld_x_preferred":[
        "Perachora"
    ],
    "name:rus_x_preferred":[
        "\u041f\u0435\u0440\u0430\u0445\u043e\u0440\u0430"
    ],
    "name:spa_x_preferred":[
        "Peracora"
    ],
    "name:sqi_x_preferred":[
        "Perahora"
    ],
    "name:swe_x_preferred":[
        "Perach\u00f3ra"
    ],
    "name:ukr_x_preferred":[
        "\u041f\u0435\u0440\u0430\u0445\u043e\u0440\u0430"
    ],
    "name:unk_x_variant":[
        "Perakh\u00f3ra"
    ],
    "qs:a0":"Greece",
    "qs:a1":"*\u03a0\u0395\u039b\u039f\u03a0\u039f\u039d\u039d\u0397\u03a3\u039f\u03a3",
    "qs:a1_alt":"PELOPONNHSOS",
    "qs:a1r":"0",
    "qs:a2_alt":"KORINUIA",
    "qs:adm0":"Greece",
    "qs:la_lc":"*",
    "qs:level":"locality",
    "qs:loc":"\u03a0\u0395\u03a1\u0391\u03a7\u03a9\u03a1\u0391",
    "qs:loc_alt":"PERAXVRA",
    "qs:pop":0,
    "qs:type":"buffered point",
    "wd:wordcount":196,
    "wof:name":"\u03a0\u0395\u03a1\u0391\u03a7\u03a9\u03a1\u0391",
    "wof:placetype":"locality",
    "wof:population":1141
},
  "geometry": {"coordinates":[22.869398,38.028892],"type":"Point"}
}