{
  "type": "Feature",
  "properties": {
    "gn:country":"GR",
    "gn:fcode":"PPL",
    "gn:population":50,
    "iso:country":"GR",
    "name:ell_x_preferred":[
        "Petr\u00edlo"
    ],
    "name:ell_x_variant":[
        "\u03a0\u03b5\u03c4\u03c1\u03af\u03bb\u03bf",
        "\u03a0\u03b5\u03c4\u03c1\u03af\u03bb\u03bf\u03bd"
    ],
    "name:und_x_variant":[
        "Argyra\u00ed\u00efka"
    ],
    "qs_pg:aaroncc":"GR",
    "qs_pg:gn_country":"GR",
    "qs_pg:gn_fcode":"PPL",
    "qs_pg:gn_pop":50,
    "qs_pg:name":"Petr\u00edlon",
    "qs_pg:photos_9r":0,
    "qs_pg:photos_sr":0,
    "qs_pg:pop_sr":1,
    "qs_pg:qs_pg_placetype":"locality",
    "wof:name":"Petr\u00edlon",
    "wof:placetype":"locality",
    "wof:population":50
},
  "geometry": {"coordinates":[21.59278,39.27417],"type":"Point"}
}