{
  "type": "Feature",
  "properties": {
    "gn:admin1_code":"ESYE25",
    "gn:admin2_code":"37.0",
    "gn:admin3_code":"9246",
    "gn:asciiname":"Stomio",
    "gn:country_code":"GR",
    "gn:dem":4,
    "gn:feature_class":"P",
    "gn:feature_code":"PPL",
    "gn:name":"St\u00f3mio",
    "gn:population":169,
    "gn:timezone":"Europe/Athens",
    "iso:country":"GR",
    "name:deu_x_preferred":[
        "Stomio"
    ],
    "name:ell_x_preferred":[
        "\u03a3\u03c4\u03cc\u03bc\u03b9\u03bf"
    ],
    "name:eng_x_preferred":[
        "Stomio"
    ],
    "name:nld_x_preferred":[
        "Stomio"
    ],
    "name:und_x_variant":[
        "St\u00f3mion"
    ],
    "wof:name":"Stomio",
    "wof:placetype":"locality",
    "wof:population":169
},
  "geometry": {"coordinates":[22.4709,38.13256],"type":"Point"}
}