{
  "type": "Feature",
  "properties": {
    "gn:admin1_code":"ESYE13",
    "gn:admin2_code":"10.0",
    "gn:admin3_code":"9061",
    "gn:asciiname":"Kritharakia",
    "gn:country_code":"GR",
    "gn:dem":763,
    "gn:feature_class":"P",
    "gn:feature_code":"PPL",
    "gn:name":"Krithar\u00e1kia",
    "gn:population":0,
    "gn:timezone":"Europe/Athens",
    "iso:country":"GR",
    "name:ell_x_preferred":[
        "Krithar\u00e1kia"
    ],
    "name:ell_x_variant":[
        "\u039a\u03c1\u03b9\u03b8\u03b1\u03c1\u03ac\u03ba\u03b9\u03b1"
    ],
    "wof:name":"Kritharakia",
    "wof:placetype":"locality"
},
  "geometry": {"coordinates":[21.359,40.18956],"type":"Point"}
}