{
  "type": "Feature",
  "properties": {
    "gn:admin1_code":"ESYE14",
    "gn:admin2_code":"21.0",
    "gn:admin3_code":"9097",
    "gn:asciiname":"Sklithro",
    "gn:country_code":"GR",
    "gn:dem":445,
    "gn:feature_class":"P",
    "gn:feature_code":"PPL",
    "gn:name":"Skl\u00edthro",
    "gn:population":0,
    "gn:timezone":"Europe/Athens",
    "iso:country":"GR",
    "name:ell_x_preferred":[
        "Skl\u00edthro"
    ],
    "name:ell_x_variant":[
        "\u03a3\u03ba\u03bb\u03ae\u03b8\u03c1\u03bf",
        "Skl\u00edthron",
        "\u03a3\u03ba\u03bb\u03ae\u03b8\u03c1\u03bf\u03bd"
    ],
    "wof:name":"Sklithro",
    "wof:placetype":"locality"
},
  "geometry": {"coordinates":[22.87389,39.60861],"type":"Point"}
}