{
  "type": "Feature",
  "properties": {
    "gn:admin1_code":"ESYE24",
    "gn:admin2_code":"29.0",
    "gn:admin3_code":"9162",
    "gn:asciiname":"Koutsoufliani",
    "gn:country_code":"GR",
    "gn:dem":460,
    "gn:feature_class":"P",
    "gn:feature_code":"PPL",
    "gn:name":"Koutso\u00fafliani",
    "gn:population":66,
    "gn:timezone":"Europe/Athens",
    "iso:country":"GR",
    "name:ell_x_preferred":[
        "\u039a\u03bf\u03c5\u03c4\u03c3\u03bf\u03cd\u03c6\u03bb\u03b9\u03b1\u03bd\u03b7"
    ],
    "name:eng_x_preferred":[
        "Koutsoufliani"
    ],
    "wof:name":"Koutsoufliani",
    "wof:placetype":"locality",
    "wof:population":66
},
  "geometry": {"coordinates":[21.9974,38.8913],"type":"Point"}
}