{
  "type": "Feature",
  "properties": {
    "gn:gn_country":"GR",
    "gn:gn_fcode":"PPL",
    "gn:gn_pop":182,
    "gn:population":182,
    "iso:country":"GR",
    "name:ara_x_preferred":[
        "\u0625\u0644\u0627\u062a\u064a\u060c \u062a\u0631\u064a\u0643\u0627\u0644\u0627"
    ],
    "name:ara_x_variant":[
        "\u0625\u0644\u0627\u062a\u064a"
    ],
    "name:ceb_x_preferred":[
        "El\u00e1ti"
    ],
    "name:ell_x_preferred":[
        "\u0395\u03bb\u03ac\u03c4\u03b7"
    ],
    "name:ell_x_variant":[
        "\u0395\u03bb\u03ac\u03c4\u03b7 \u03a4\u03c1\u03b9\u03ba\u03ac\u03bb\u03c9\u03bd"
    ],
    "name:eng_x_preferred":[
        "Elati"
    ],
    "name:nld_x_preferred":[
        "Elati"
    ],
    "name:nno_x_preferred":[
        "El\u00e1ti i Tr\u00edkala"
    ],
    "name:swe_x_preferred":[
        "El\u00e1ti"
    ],
    "name:unk_x_variant":[
        "Sekl\u00edsta"
    ],
    "qs_pg:aaroncc":"GR",
    "qs_pg:gn_country":"GR",
    "qs_pg:gn_fcode":"PPL",
    "qs_pg:gn_pop":182,
    "qs_pg:name":"Elati",
    "qs_pg:name_adm0":"\u0395\u03bb\u03bb\u03ac\u03b4\u03b1",
    "qs_pg:name_adm1":"Epirus and Western Macedonia",
    "qs_pg:photos_9k":1,
    "qs_pg:photos_9r":1,
    "qs_pg:photos_all":9,
    "qs_pg:photos_sr":0,
    "qs_pg:pop_sr":1,
    "qs_pg:qs_pg_placetype":"locality",
    "qs_pg:qs_pg_placetype_gp":"Town",
    "qs_pg:woe_adm0":23424833,
    "woe:adm0_id":23424833,
    "woe:name_adm0":"\u0395\u03bb\u03bb\u03ac\u03b4\u03b1",
    "woe:name_adm1":"Epirus and Western Macedonia",
    "woe:placetype":"Town",
    "wof:name":"Elati",
    "wof:placetype":"locality",
    "wof:population":182
},
  "geometry": {"coordinates":[21.31667,39.29694],"type":"Point"}
}