{
  "type": "Feature",
  "properties": {
    "gn:admin1_code":"ESYE24",
    "gn:admin2_code":"32.0",
    "gn:admin3_code":"9166",
    "gn:asciiname":"Skaloma",
    "gn:country_code":"GR",
    "gn:dem":6,
    "gn:feature_class":"P",
    "gn:feature_code":"PPL",
    "gn:name":"Sk\u00e1loma",
    "gn:population":0,
    "gn:timezone":"Europe/Athens",
    "iso:country":"GR",
    "name:ell_x_preferred":[
        "\u03a3\u03ba\u03ac\u03bb\u03c9\u03bc\u03b1"
    ],
    "name:und_x_variant":[
        "Sk\u00e1loma",
        "Kara\u1e2fskos"
    ],
    "wof:name":"Skaloma",
    "wof:placetype":"locality"
},
  "geometry": {"coordinates":[21.99797,38.39692],"type":"Point"}
}