{
  "type": "Feature",
  "properties": {
    "gn:admin1_code":"ESYE25",
    "gn:admin2_code":"41.0",
    "gn:admin3_code":"9237",
    "gn:asciiname":"Vervena",
    "gn:cc2":"GR",
    "gn:country_code":"GR",
    "gn:dem":1146,
    "gn:feature_class":"P",
    "gn:feature_code":"PPL",
    "gn:name":"V\u00e9rvena",
    "gn:population":0,
    "gn:timezone":"Europe/Athens",
    "iso:country":"GR",
    "name:und_x_variant":[
        "V\u00e9rvaina",
        "V\u00e9rvena"
    ],
    "wof:name":"Vervena",
    "wof:placetype":"locality"
},
  "geometry": {"coordinates":[22.46483,37.3715],"type":"Point"}
}