{
  "type": "Feature",
  "properties": {
    "gn:admin1_code":"ESYE24",
    "gn:admin2_code":"34.0",
    "gn:admin3_code":"9152",
    "gn:asciiname":"Lepoura",
    "gn:country_code":"GR",
    "gn:dem":95,
    "gn:feature_class":"P",
    "gn:feature_code":"PPL",
    "gn:name":"L\u00e9poura",
    "gn:population":0,
    "gn:timezone":"Europe/Athens",
    "iso:country":"GR",
    "name:ell_x_preferred":[
        "L\u00e9poura"
    ],
    "name:ell_x_variant":[
        "\u039b\u03ad\u03c0\u03bf\u03c5\u03c1\u03b1"
    ],
    "wof:name":"Lepoura",
    "wof:placetype":"locality"
},
  "geometry": {"coordinates":[24.10614,38.40572],"type":"Point"}
}