{
  "type": "Feature",
  "properties": {
    "gn:gn_country":"GR",
    "gn:gn_fcode":"PPL",
    "gn:gn_pop":976,
    "gn:population":1179,
    "iso:country":"GR",
    "name:bul_x_preferred":[
        "\u041a\u0430\u043b\u0438\u0442\u0435\u0430"
    ],
    "name:ell_x_preferred":[
        "\u039a\u03b1\u03bb\u03bb\u03b9\u03b8\u03ad\u03b1"
    ],
    "name:eng_x_preferred":[
        "Kallithea"
    ],
    "name:rus_x_preferred":[
        "\u041a\u0430\u043b\u043b\u0438\u0444\u0435\u044f"
    ],
    "name:unk_x_variant":[
        "Met\u00f3khi Rossik\u00f3n"
    ],
    "qs_pg:aaroncc":"GR",
    "qs_pg:gn_country":"GR",
    "qs_pg:gn_fcode":"PPL",
    "qs_pg:gn_pop":976,
    "qs_pg:name":"Kallithea",
    "qs_pg:name_adm0":"\u0395\u03bb\u03bb\u03ac\u03b4\u03b1",
    "qs_pg:name_adm1":"Macedonia and Thrace",
    "qs_pg:photos":519,
    "qs_pg:photos_1k":105,
    "qs_pg:photos_9k":2,
    "qs_pg:photos_9r":5,
    "qs_pg:photos_all":519,
    "qs_pg:photos_sr":7,
    "qs_pg:pop_sr":2,
    "qs_pg:qs_pg_placetype":"locality",
    "qs_pg:qs_pg_placetype_gp":"Town",
    "qs_pg:woe_adm0":23424833,
    "woe:adm0_id":23424833,
    "woe:name_adm0":"\u0395\u03bb\u03bb\u03ac\u03b4\u03b1",
    "woe:name_adm1":"Macedonia and Thrace",
    "woe:placetype":"Town",
    "wof:name":"Kallithea",
    "wof:placetype":"locality",
    "wof:population":1179
},
  "geometry": {"coordinates":[23.44637,40.07374],"type":"Point"}
}