{
  "type": "Feature",
  "properties": {
    "gn:admin1_code":"ESYE25",
    "gn:admin2_code":"40.0",
    "gn:admin3_code":"9258",
    "gn:asciiname":"Avlon",
    "gn:cc2":"GR",
    "gn:country_code":"GR",
    "gn:dem":588,
    "gn:feature_class":"P",
    "gn:feature_code":"PPL",
    "gn:name":"Avl\u00f3n",
    "gn:population":0,
    "gn:timezone":"Europe/Athens",
    "iso:country":"GR",
    "name:ell_x_preferred":[
        "\u0391\u03c5\u03bb\u03ce\u03bd\u03b1\u03c2"
    ],
    "name:ell_x_variant":[
        "\u0391\u03c5\u03bb\u03ce\u03bd"
    ],
    "name:und_x_variant":[
        "Karamoustaf\u00e1",
        "Avl\u00f3n"
    ],
    "wof:name":"Avlon",
    "wof:placetype":"locality"
},
  "geometry": {"coordinates":[21.80202,37.36525],"type":"Point"}
}