{
  "type": "Feature",
  "properties": {
    "gn:admin1_code":"ESYE23",
    "gn:admin2_code":"38.0",
    "gn:admin3_code":"9132",
    "gn:asciiname":"Manesi",
    "gn:country_code":"GR",
    "gn:dem":382,
    "gn:feature_class":"P",
    "gn:feature_code":"PPL",
    "gn:name":"Man\u00e9si",
    "gn:population":0,
    "gn:timezone":"Europe/Athens",
    "iso:country":"GR",
    "name:ell_x_preferred":[
        "Man\u00e9si"
    ],
    "name:ell_x_variant":[
        "\u039c\u03b1\u03bd\u03ad\u03c3\u03b9",
        "Man\u00e9sion",
        "\u039c\u03b1\u03bd\u03ad\u03c3\u03b9\u03bf\u03bd"
    ],
    "wof:name":"Manesi",
    "wof:placetype":"locality"
},
  "geometry": {"coordinates":[21.67453,37.981],"type":"Point"}
}