{
  "type": "Feature",
  "properties": {
    "gn:admin1_code":"ESYE31",
    "gn:admin2_code":"445407.0",
    "gn:admin3_code":"9230",
    "gn:asciiname":"Pournari",
    "gn:country_code":"GR",
    "gn:dem":297,
    "gn:feature_class":"P",
    "gn:feature_code":"PPL",
    "gn:name":"Pourn\u00e1ri",
    "gn:population":92,
    "gn:timezone":"Europe/Athens",
    "iso:country":"GR",
    "name:ell_x_preferred":[
        "\u03a0\u03bf\u03c5\u03c1\u03bd\u03ac\u03c1\u03b9"
    ],
    "name:eng_x_preferred":[
        "Pournari"
    ],
    "wof:name":"Pournari",
    "wof:placetype":"locality",
    "wof:population":92
},
  "geometry": {"coordinates":[23.44088,38.15292],"type":"Point"}
}