{
  "type": "Feature",
  "properties": {
    "gn:admin1_code":"ESYE14",
    "gn:admin2_code":"21.0",
    "gn:admin3_code":"9103",
    "gn:asciiname":"Iperia",
    "gn:country_code":"GR",
    "gn:dem":111,
    "gn:feature_class":"P",
    "gn:feature_code":"PPL",
    "gn:name":"Iperia",
    "gn:population":0,
    "gn:timezone":"Europe/Athens",
    "iso:country":"GR",
    "wof:name":"Iperia",
    "wof:placetype":"locality"
},
  "geometry": {"coordinates":[22.265,39.38885],"type":"Point"}
}