{
  "type": "Feature",
  "properties": {
    "gn:gn_country":"GR",
    "gn:gn_fcode":"PPL",
    "gn:gn_pop":2556,
    "gn:population":3840,
    "iso:country":"GR",
    "name:ell_x_preferred":[
        "\u03a0\u03bf\u03c4\u03b1\u03bc\u03cc\u03c2"
    ],
    "name:eng_x_preferred":[
        "Potamos"
    ],
    "qs_pg:aaroncc":"GR",
    "qs_pg:gn_country":"GR",
    "qs_pg:gn_fcode":"PPL",
    "qs_pg:gn_pop":2556,
    "qs_pg:name":"Potamos",
    "qs_pg:name_adm0":"\u0395\u03bb\u03bb\u03ac\u03b4\u03b1",
    "qs_pg:name_adm1":"Peloponnese Western Greece and the Ionian Islands",
    "qs_pg:photos":92,
    "qs_pg:photos_1k":19,
    "qs_pg:photos_9k":1,
    "qs_pg:photos_9r":3,
    "qs_pg:photos_all":92,
    "qs_pg:photos_sr":3,
    "qs_pg:pop_sr":4,
    "qs_pg:qs_pg_placetype":"locality",
    "qs_pg:qs_pg_placetype_gp":"Town",
    "qs_pg:woe_adm0":23424833,
    "woe:adm0_id":23424833,
    "woe:name_adm0":"\u0395\u03bb\u03bb\u03ac\u03b4\u03b1",
    "woe:name_adm1":"Peloponnese Western Greece and the Ionian Islands",
    "woe:placetype":"Town",
    "wof:name":"Potamos",
    "wof:placetype":"locality",
    "wof:population":3840
},
  "geometry": {"coordinates":[19.87556,39.625],"type":"Point"}
}