{
  "type": "Feature",
  "properties": {
    "gn:admin1_code":"ESYE14",
    "gn:admin2_code":"21.0",
    "gn:admin3_code":"9097",
    "gn:asciiname":"Skiti",
    "gn:country_code":"GR",
    "gn:dem":332,
    "gn:feature_class":"P",
    "gn:feature_code":"PPL",
    "gn:name":"Sk\u00edti",
    "gn:population":0,
    "gn:timezone":"Europe/Athens",
    "iso:country":"GR",
    "name:ell_x_preferred":[
        "Sk\u00edti"
    ],
    "name:ell_x_variant":[
        "\u03a3\u03ba\u03ae\u03c4\u03b7",
        "\u03a3\u03ba\u03ae\u03c4\u03b7 \u039b\u03ac\u03c1\u03b9\u03c3\u03b1\u03c2"
    ],
    "name:spa_x_preferred":[
        "Skiti"
    ],
    "wof:name":"Skiti",
    "wof:placetype":"locality"
},
  "geometry": {"coordinates":[22.82531,39.68011],"type":"Point"}
}