{
  "type": "Feature",
  "properties": {
    "gn:admin1_code":"ESYE25",
    "gn:admin2_code":"40.0",
    "gn:admin3_code":"9255",
    "gn:asciiname":"Panaiika",
    "gn:country_code":"GR",
    "gn:dem":448,
    "gn:feature_class":"P",
    "gn:feature_code":"PPL",
    "gn:name":"Pana\u00edika",
    "gn:population":0,
    "gn:timezone":"Europe/Athens",
    "iso:country":"GR",
    "name:ell_x_preferred":[
        "\u03a0\u03b1\u03bd\u03b1\u03af\u03b9\u03ba\u03b1"
    ],
    "name:und_x_variant":[
        "An\u00e1zogli",
        "Pane\u00efka",
        "Pana\u00edika"
    ],
    "wof:name":"Panaiika",
    "wof:placetype":"locality"
},
  "geometry": {"coordinates":[21.85033,36.89761],"type":"Point"}
}