{
  "type": "Feature",
  "properties": {
    "gn:admin1_code":"ESYE23",
    "gn:admin2_code":"39.0",
    "gn:admin3_code":"9141",
    "gn:asciiname":"Arvanitis",
    "gn:country_code":"GR",
    "gn:dem":65,
    "gn:feature_class":"P",
    "gn:feature_code":"PPL",
    "gn:name":"Arvan\u00edtis",
    "gn:population":0,
    "gn:timezone":"Europe/Athens",
    "iso:country":"GR",
    "name:ell_x_preferred":[
        "\u0391\u03c1\u03b2\u03b1\u03bd\u03af\u03c4\u03b7\u03c2"
    ],
    "name:und_x_variant":[
        "Arva\u0144iti",
        "Arvan\u00edtis"
    ],
    "wof:name":"Arvanitis",
    "wof:placetype":"locality"
},
  "geometry": {"coordinates":[21.52231,37.72272],"type":"Point"}
}