{
  "type": "Feature",
  "properties": {
    "gn:admin1_code":"ESYE24",
    "gn:admin2_code":"34.0",
    "gn:admin3_code":"9153",
    "gn:asciiname":"Palaiovrysi",
    "gn:country_code":"GR",
    "gn:dem":351,
    "gn:feature_class":"P",
    "gn:feature_code":"PPL",
    "gn:name":"Palai\u00f3vrysi",
    "gn:population":0,
    "gn:timezone":"Europe/Athens",
    "iso:country":"GR",
    "name:ell_x_preferred":[
        "Palai\u00f3vrysi"
    ],
    "name:ell_x_variant":[
        "\u03a0\u03b1\u03bb\u03b1\u03b9\u03cc\u03b2\u03c1\u03c5\u03c3\u03b7"
    ],
    "name:und_x_variant":[
        "Pali\u00f3vrisi",
        "Palai\u00f3vrisi"
    ],
    "wof:name":"Palaiovrysi",
    "wof:placetype":"locality"
},
  "geometry": {"coordinates":[23.39367,38.85578],"type":"Point"}
}