{
  "type": "Feature",
  "properties": {
    "gn:admin1_code":"ESYE13",
    "gn:admin2_code":"11.0",
    "gn:admin3_code":"9066",
    "gn:asciiname":"Lefki",
    "gn:country_code":"GR",
    "gn:dem":773,
    "gn:feature_class":"P",
    "gn:feature_code":"PPL",
    "gn:name":"L\u00e9fki",
    "gn:population":0,
    "gn:timezone":"Europe/Athens",
    "iso:country":"GR",
    "name:ell_x_preferred":[
        "L\u00e9fki"
    ],
    "name:ell_x_variant":[
        "\u039b\u03b5\u03cd\u03ba\u03b7"
    ],
    "name:und_x_variant":[
        "Sar\u00f3tsiani",
        "L\u00e9vki"
    ],
    "wof:name":"Lefki",
    "wof:placetype":"locality"
},
  "geometry": {"coordinates":[21.19756,40.3004],"type":"Point"}
}