{
  "type": "Feature",
  "properties": {
    "gn:admin1_code":"ESYE25",
    "gn:admin2_code":"42.0",
    "gn:admin3_code":"9248",
    "gn:asciiname":"Lefkias",
    "gn:country_code":"GR",
    "gn:dem":212,
    "gn:feature_class":"P",
    "gn:feature_code":"PPL",
    "gn:name":"Lefki\u00e1s",
    "gn:population":0,
    "gn:timezone":"Europe/Athens",
    "iso:country":"GR",
    "name:ell_x_preferred":[
        "Lefki\u00e1s"
    ],
    "name:ell_x_variant":[
        "\u039b\u03b5\u03c5\u03ba\u03b9\u03ac\u03c2"
    ],
    "name:und_x_variant":[
        "Levki\u00e1s"
    ],
    "wof:name":"Lefkias",
    "wof:placetype":"locality"
},
  "geometry": {"coordinates":[22.38792,36.62639],"type":"Point"}
}