{
  "type": "Feature",
  "properties": {
    "gn:admin1_code":"ESYE23",
    "gn:admin2_code":"31.0",
    "gn:admin3_code":"9123",
    "gn:asciiname":"Skiadaiika",
    "gn:country_code":"GR",
    "gn:dem":880,
    "gn:feature_class":"P",
    "gn:feature_code":"PPL",
    "gn:name":"Skiada\u00edika",
    "gn:population":21,
    "gn:timezone":"Europe/Athens",
    "iso:country":"GR",
    "name:ell_x_preferred":[
        "\u03a3\u03ba\u03b9\u03b1\u03b4\u03b1\u03af\u03b9\u03ba\u03b1"
    ],
    "name:eng_x_preferred":[
        "Skiadaiika"
    ],
    "wof:name":"Skiadaiika",
    "wof:placetype":"locality",
    "wof:population":21
},
  "geometry": {"coordinates":[21.55683,38.8552],"type":"Point"}
}