{
  "type": "Feature",
  "properties": {
    "gn:admin1_code":"ESYE31",
    "gn:admin2_code":"445406.0",
    "gn:admin3_code":"9219",
    "gn:asciiname":"Manoutso",
    "gn:country_code":"GR",
    "gn:dem":158,
    "gn:feature_class":"P",
    "gn:feature_code":"PPL",
    "gn:name":"Mano\u00fatso",
    "gn:population":95,
    "gn:timezone":"Europe/Athens",
    "iso:country":"GR",
    "name:ell_x_preferred":[
        "\u039c\u03b1\u03bd\u03bf\u03cd\u03c4\u03c3\u03bf"
    ],
    "name:eng_x_preferred":[
        "Manoutso"
    ],
    "wof:name":"Manoutso",
    "wof:placetype":"locality",
    "wof:population":95
},
  "geometry": {"coordinates":[24.00217,37.76929000000001],"type":"Point"}
}