{
  "type": "Feature",
  "properties": {
    "gn:admin1_code":"ESYE24",
    "gn:admin2_code":"34.0",
    "gn:admin3_code":"9150",
    "gn:asciiname":"Palaiokhorion",
    "gn:country_code":"GR",
    "gn:dem":288,
    "gn:feature_class":"P",
    "gn:feature_code":"PPLL",
    "gn:name":"Palaiokh\u00f3rion",
    "gn:population":0,
    "gn:timezone":"Europe/Athens",
    "iso:country":"GR",
    "name:ell_x_preferred":[
        "\u03a0\u03b1\u03bb\u03b1\u03b9\u03bf\u03c7\u03ce\u03c1\u03b9"
    ],
    "name:eng_x_preferred":[
        "Palaiochori"
    ],
    "name:und_x_variant":[
        "Paliokh\u00f3ri",
        "Palaiokh\u00f3rion"
    ],
    "wof:name":"Palaiokhorion",
    "wof:placetype":"locality"
},
  "geometry": {"coordinates":[22.89553,38.84846],"type":"Point"}
}