{
  "type": "Feature",
  "properties": {
    "gn:population":3783,
    "iso:country":"GR",
    "name:cat_x_preferred":[
        "M\u00edkonos"
    ],
    "name:deu_x_preferred":[
        "Mykonos"
    ],
    "name:ell_x_preferred":[
        "\u039c\u03cd\u03ba\u03bf\u03bd\u03bf\u03c2"
    ],
    "name:ell_x_variant":[
        "\u03a7\u03ce\u03c1\u03b1",
        "\u03a7\u03c9\u03c1\u03b1"
    ],
    "name:eng_x_preferred":[
        "Mykonos"
    ],
    "name:eng_x_variant":[
        "Chora"
    ],
    "name:fra_x_preferred":[
        "Myconos"
    ],
    "name:ita_x_preferred":[
        "Mykonos"
    ],
    "name:spa_x_preferred":[
        "M\u00edkonos"
    ],
    "name:und_x_variant":[
        "Kamenaki"
    ],
    "qs:a0":"Greece",
    "qs:a1":"*\u039d\u039f\u03a4\u0399\u039f \u0391\u0399\u0393\u0391\u0399\u039f",
    "qs:a1_alt":"NOTIO AIGAIO",
    "qs:a1r":"0",
    "qs:a2_alt":"KYKLADES",
    "qs:adm0":"Greece",
    "qs:la_lc":"*",
    "qs:level":"locality",
    "qs:loc":"\u039c\u03a5\u039a\u039f\u039d\u039f\u03a3",
    "qs:loc_alt":"MYKONOS",
    "qs:pop":0,
    "qs:type":"buffered point",
    "wof:name":"\u039c\u03a5\u039a\u039f\u039d\u039f\u03a3",
    "wof:placetype":"locality",
    "wof:population":3783
},
  "geometry": {"coordinates":[25.329754,37.443775],"type":"Point"}
}