{
  "type": "Feature",
  "properties": {
    "gn:admin1_code":"ESYE11",
    "gn:admin2_code":"3.0",
    "gn:admin3_code":"9017",
    "gn:asciiname":"Likovounion",
    "gn:cc2":"GR",
    "gn:country_code":"GR",
    "gn:dem":348,
    "gn:feature_class":"P",
    "gn:feature_code":"PPL",
    "gn:name":"Likovo\u00fanion",
    "gn:population":0,
    "gn:timezone":"Europe/Athens",
    "iso:country":"GR",
    "name:und_x_variant":[
        "Asikl\u00e1r",
        "Likovo\u00fani",
        "Likovo\u00fanion"
    ],
    "wof:name":"Likovounion",
    "wof:placetype":"locality"
},
  "geometry": {"coordinates":[24.53333,41.25],"type":"Point"}
}