{
  "type": "Feature",
  "properties": {
    "gn:gn_country":"GR",
    "gn:gn_fcode":"PPL",
    "gn:gn_pop":2085,
    "gn:population":2085,
    "iso:country":"GR",
    "name:ara_x_preferred":[
        "\u063a\u0627\u0644\u0627\u062a\u064a\u0646\u064a"
    ],
    "name:bul_x_preferred":[
        "\u0413\u0430\u043b\u0430\u0442\u0438\u043d\u0438"
    ],
    "name:ceb_x_preferred":[
        "Galatin\u00ed"
    ],
    "name:ell_x_preferred":[
        "\u0393\u03b1\u03bb\u03b1\u03c4\u03b9\u03bd\u03ae"
    ],
    "name:ell_x_variant":[
        "\u0393\u03b1\u03bb\u03b1\u03c4\u03b9\u03bd\u03ae \u039a\u03bf\u03b6\u03ac\u03bd\u03b7\u03c2"
    ],
    "name:eng_x_preferred":[
        "Galatini"
    ],
    "name:mkd_x_preferred":[
        "\u041a\u043e\u043d\u0441\u043a\u043e"
    ],
    "name:nld_x_preferred":[
        "Galatini"
    ],
    "name:swe_x_preferred":[
        "Galatin\u00ed"
    ],
    "name:unk_x_variant":[
        "Kontsik\u00f3n"
    ],
    "name:urd_x_preferred":[
        "Trianda"
    ],
    "qs_pg:aaroncc":"GR",
    "qs_pg:gn_country":"GR",
    "qs_pg:gn_fcode":"PPL",
    "qs_pg:gn_pop":2085,
    "qs_pg:name":"Galatini",
    "qs_pg:name_adm0":"\u0395\u03bb\u03bb\u03ac\u03b4\u03b1",
    "qs_pg:name_adm1":"Epirus and Western Macedonia",
    "qs_pg:photos_9r":0,
    "qs_pg:photos_sr":0,
    "qs_pg:pop_sr":4,
    "qs_pg:qs_pg_placetype":"locality",
    "qs_pg:qs_pg_placetype_gp":"Town",
    "qs_pg:woe_adm0":23424833,
    "woe:adm0_id":23424833,
    "woe:name_adm0":"\u0395\u03bb\u03bb\u03ac\u03b4\u03b1",
    "woe:name_adm1":"Epirus and Western Macedonia",
    "woe:placetype":"Town",
    "wof:name":"Galatini",
    "wof:placetype":"locality",
    "wof:population":2085
},
  "geometry": {"coordinates":[21.55,40.31667],"type":"Point"}
}