{
  "type": "Feature",
  "properties": {
    "gn:admin1_code":"ESYE25",
    "gn:admin2_code":"41.0",
    "gn:admin3_code":"9238",
    "gn:asciiname":"Bouliaris",
    "gn:country_code":"GR",
    "gn:dem":707,
    "gn:feature_class":"P",
    "gn:feature_code":"PPL",
    "gn:name":"Bouli\u00e1ris",
    "gn:population":0,
    "gn:timezone":"Europe/Athens",
    "iso:country":"GR",
    "name:ell_x_preferred":[
        "\u039c\u03c0\u03bf\u03c5\u03bb\u03b9\u03ac\u03c1\u03b7\u03c2"
    ],
    "name:und_x_variant":[
        "Boli\u00e1ri",
        "Bouli\u00e1ri",
        "Bouli\u00e1ris"
    ],
    "wof:name":"Bouliaris",
    "wof:placetype":"locality"
},
  "geometry": {"coordinates":[22.0133,37.73732],"type":"Point"}
}