{
  "type": "Feature",
  "properties": {
    "gn:admin1_code":"ESYE23",
    "gn:admin2_code":"31.0",
    "gn:admin3_code":"9127",
    "gn:asciiname":"Chrysovergi",
    "gn:country_code":"GR",
    "gn:dem":72,
    "gn:feature_class":"P",
    "gn:feature_code":"PPL",
    "gn:name":"Chrysov\u00e9rgi",
    "gn:population":0,
    "gn:timezone":"Europe/Athens",
    "iso:country":"GR",
    "name:ell_x_preferred":[
        "Chrysov\u00e9rgi"
    ],
    "name:ell_x_variant":[
        "\u03a7\u03c1\u03c5\u03c3\u03bf\u03b2\u03ad\u03c1\u03b3\u03b9",
        "Chrysov\u00e9rgion",
        "\u03a7\u03c1\u03c5\u03c3\u03bf\u03b2\u03ad\u03c1\u03b3\u03b9\u03bf\u03bd"
    ],
    "name:und_x_variant":[
        "Khrisov\u00e9ryi",
        "Khrisov\u00e9ryion"
    ],
    "wof:name":"Chrysovergi",
    "wof:placetype":"locality"
},
  "geometry": {"coordinates":[21.35166,38.49892],"type":"Point"}
}