{
  "type": "Feature",
  "properties": {
    "gn:country":"GR",
    "gn:fcode":"ADM3",
    "gn:population":11798,
    "iso:country":"GR",
    "name:ell_x_preferred":[
        "\u03a3\u03b9\u03b8\u03c9\u03bd\u03af\u03b1\u03c2"
    ],
    "qs_pg:aaroncc":"GR",
    "qs_pg:gn_country":"GR",
    "qs_pg:gn_fcode":"ADM3",
    "qs_pg:gn_pop":11798,
    "qs_pg:name":"Dimos Sithonia",
    "qs_pg:photos_9r":0,
    "qs_pg:photos_sr":0,
    "qs_pg:pop_sr":6,
    "qs_pg:qs_pg_placetype":"localadmin",
    "wof:name":"Dimos Sithonia",
    "wof:placetype":"localadmin",
    "wof:population":11798
},
  "geometry": {"coordinates":[23.82803,40.12819],"type":"Point"}
}