{
  "type": "Feature",
  "properties": {
    "gn:admin1_code":"ESYE21",
    "gn:admin2_code":"17.0",
    "gn:admin3_code":"9082",
    "gn:asciiname":"Ampelos",
    "gn:country_code":"GR",
    "gn:dem":584,
    "gn:feature_class":"P",
    "gn:feature_code":"PPL",
    "gn:name":"\u00c1mpelos",
    "gn:population":1,
    "gn:timezone":"Europe/Athens",
    "iso:country":"GR",
    "name:ell_x_preferred":[
        "\u0386\u03bc\u03c0\u03b5\u03bb\u03bf\u03c2"
    ],
    "name:eng_x_preferred":[
        "Ampelos"
    ],
    "wof:name":"Ampelos",
    "wof:placetype":"locality",
    "wof:population":1
},
  "geometry": {"coordinates":[20.95952,39.76673],"type":"Point"}
}