{
  "type": "Feature",
  "properties": {
    "gn:admin1_code":"ESYE21",
    "gn:admin2_code":"17.0",
    "gn:admin3_code":"9082",
    "gn:asciiname":"Ampelos",
    "gn:country_code":"GR",
    "gn:dem":584,
    "gn:feature_class":"P",
    "gn:feature_code":"PPL",
    "gn:name":"\u00c1mpelos",
    "gn:population":1,
    "gn:timezone":"Europe/Athens",
    "iso:country":"GR",
    "name:bre_x_preferred":[
        "Ampelos"
    ],
    "name:cat_x_preferred":[
        "\u00c0mpel"
    ],
    "name:deu_x_preferred":[
        "Ampelos"
    ],
    "name:ell_x_preferred":[
        "\u0386\u03bc\u03c0\u03b5\u03bb\u03bf\u03c2"
    ],
    "name:eng_x_preferred":[
        "Ampelos"
    ],
    "name:fra_x_preferred":[
        "Amp\u00e9los"
    ],
    "name:glg_x_preferred":[
        "Ampelo"
    ],
    "name:ita_x_preferred":[
        "Ampelo"
    ],
    "name:kat_x_preferred":[
        "\u10d0\u10db\u10de\u10d4\u10da\u10dd\u10e1\u10d8"
    ],
    "name:rus_x_preferred":[
        "\u0410\u043c\u043f\u0435\u043b"
    ],
    "name:slv_x_preferred":[
        "Ampelos"
    ],
    "name:spa_x_preferred":[
        "\u00c1mpelo"
    ],
    "name:srp_x_preferred":[
        "\u0410\u043c\u043f\u0435\u043b"
    ],
    "name:ukr_x_preferred":[
        "\u0410\u043c\u043f\u0435\u043b"
    ],
    "wof:name":"Ampelos",
    "wof:placetype":"locality",
    "wof:population":1
},
  "geometry": {"coordinates":[20.95952,39.76673],"type":"Point"}
}