{
  "type": "Feature",
  "properties": {
    "gn:admin1_code":"ESYE25",
    "gn:admin2_code":"41.0",
    "gn:admin3_code":"9238",
    "gn:asciiname":"Langadhia",
    "gn:country_code":"GR",
    "gn:dem":935,
    "gn:feature_class":"P",
    "gn:feature_code":"PPL",
    "gn:name":"Lang\u00e1dhia",
    "gn:population":1363,
    "gn:timezone":"Europe/Athens",
    "iso:country":"GR",
    "name:deu_x_preferred":[
        "Langadia"
    ],
    "name:ell_x_preferred":[
        "\u039b\u03b1\u03b3\u03ba\u03ac\u03b4\u03b9\u03b1"
    ],
    "name:eng_x_preferred":[
        "Lagkadia"
    ],
    "name:und_x_variant":[
        "Langadia",
        "Lang\u00e1dhia"
    ],
    "wof:name":"Langadhia",
    "wof:placetype":"locality",
    "wof:population":1363
},
  "geometry": {"coordinates":[22.03002,37.68186],"type":"Point"}
}