{
  "type": "Feature",
  "properties": {
    "gn:admin1_code":"ESYE23",
    "gn:admin2_code":"38.0",
    "gn:admin3_code":"9131",
    "gn:asciiname":"Thomaiika",
    "gn:country_code":"GR",
    "gn:dem":59,
    "gn:feature_class":"P",
    "gn:feature_code":"PPL",
    "gn:name":"Thoma\u00edika",
    "gn:population":0,
    "gn:timezone":"Europe/Athens",
    "iso:country":"GR",
    "name:ell_x_preferred":[
        "\u0398\u03c9\u03bc\u03b1\u03af\u03b9\u03ba\u03b1"
    ],
    "name:und_x_variant":[
        "Thom\u00e9\u00efka",
        "Thoma\u00edika"
    ],
    "wof:name":"Thomaiika",
    "wof:placetype":"locality"
},
  "geometry": {"coordinates":[21.60608,38.10417],"type":"Point"}
}