{
  "type": "Feature",
  "properties": {
    "gn:admin1_code":"ESYE25",
    "gn:admin2_code":"37.0",
    "gn:admin3_code":"9243.0",
    "gn:asciiname":"Evangelistria",
    "gn:country_code":"GR",
    "gn:dem":37,
    "gn:feature_class":"P",
    "gn:feature_code":"PPL",
    "gn:name":"Evangel\u00edstria",
    "gn:population":0,
    "gn:timezone":"Europe/Athens",
    "iso:country":"GR",
    "name:ell_x_preferred":[
        "Evangel\u00edstria"
    ],
    "name:ell_x_variant":[
        "\u0395\u03c5\u03b1\u03b3\u03b3\u03b5\u03bb\u03af\u03c3\u03c4\u03c1\u03b9\u03b1"
    ],
    "wof:name":"Evangelistria",
    "wof:placetype":"locality"
},
  "geometry": {"coordinates":[22.94495,37.93804],"type":"Point"}
}