{
  "type": "Feature",
  "properties": {
    "gn:admin1_code":"ESYE13",
    "gn:admin2_code":"9.0",
    "gn:admin3_code":"9063",
    "gn:asciiname":"Agios Nikolaos Korisou",
    "gn:country_code":"GR",
    "gn:dem":822,
    "gn:feature_class":"P",
    "gn:feature_code":"PPL",
    "gn:name":"\u00c1gios Nik\u00f3laos Koriso\u00fa",
    "gn:population":22,
    "gn:timezone":"Europe/Athens",
    "iso:country":"GR",
    "name:ell_x_preferred":[
        "\u0386\u03b3\u03b9\u03bf\u03c2 \u039d\u03b9\u03ba\u03cc\u03bb\u03b1\u03bf\u03c2 \u039a\u03bf\u03c1\u03b7\u03c3\u03bf\u03cd"
    ],
    "name:eng_x_preferred":[
        "Agios Nikolaos Korisou"
    ],
    "name:und_x_variant":[
        "Tsir\u00edlovon",
        "\u00c1yios Nik\u00f3laos",
        "\u00c1gios Nik\u00f3laos"
    ],
    "wof:name":"Agios Nikolaos Korisou",
    "wof:placetype":"locality",
    "wof:population":22
},
  "geometry": {"coordinates":[21.39698,40.50016],"type":"Point"}
}