{
  "type": "Feature",
  "properties": {
    "gn:admin1_code":"ESYE43",
    "gn:admin2_code":"46.0",
    "gn:admin3_code":"9313",
    "gn:asciiname":"Agia Fotia Siteias",
    "gn:country_code":"GR",
    "gn:dem":281,
    "gn:feature_class":"P",
    "gn:feature_code":"PPL",
    "gn:name":"Ag\u00eda Foti\u00e1 Site\u00edas",
    "gn:population":267,
    "gn:timezone":"Europe/Athens",
    "iso:country":"GR",
    "name:ell_x_preferred":[
        "\u0391\u03b3\u03af\u03b1 \u03a6\u03c9\u03c4\u03b9\u03ac \u03a3\u03b7\u03c4\u03b5\u03af\u03b1\u03c2"
    ],
    "name:eng_x_preferred":[
        "Agia Fotia Siteias"
    ],
    "name:und_x_variant":[
        "Ag\u00eda Foti\u00e1"
    ],
    "wof:name":"Agia Fotia Siteias",
    "wof:placetype":"locality",
    "wof:population":267
},
  "geometry": {"coordinates":[25.10764,35.01574],"type":"Point"}
}