{
  "type": "Feature",
  "properties": {
    "gn:admin1_code":"ESYE21",
    "gn:admin2_code":"17.0",
    "gn:admin3_code":"9084",
    "gn:asciiname":"Goulas",
    "gn:country_code":"GR",
    "gn:dem":605,
    "gn:feature_class":"P",
    "gn:feature_code":"PPL",
    "gn:name":"Go\u00falas",
    "gn:population":83,
    "gn:timezone":"Europe/Athens",
    "iso:country":"GR",
    "name:ell_x_preferred":[
        "\u0393\u03bf\u03cd\u03bb\u03b1\u03c2"
    ],
    "name:eng_x_preferred":[
        "Goulas"
    ],
    "wof:name":"Goulas",
    "wof:placetype":"locality",
    "wof:population":83
},
  "geometry": {"coordinates":[20.96305,39.60668],"type":"Point"}
}