{
  "type": "Feature",
  "properties": {
    "gn:country":"GR",
    "gn:fcode":"PPL",
    "gn:population":641,
    "iso:country":"GR",
    "name:ell_x_preferred":[
        "\u039a\u03bf\u03bc\u03c0\u03af\u03c4\u03c3\u03b9"
    ],
    "name:eng_x_preferred":[
        "Kompitsi"
    ],
    "name:und_x_variant":[
        "Komb\u00edtsion"
    ],
    "qs_pg:aaroncc":"GR",
    "qs_pg:gn_country":"GR",
    "qs_pg:gn_fcode":"PPL",
    "qs_pg:gn_pop":641,
    "qs_pg:name":"Kombitsion",
    "qs_pg:name_adm0":"\u0395\u03bb\u03bb\u03ac\u03b4\u03b1",
    "qs_pg:name_adm1":"Peloponnese Western Greece and the Ionian Islands",
    "qs_pg:photos_9k":1,
    "qs_pg:photos_9r":1,
    "qs_pg:photos_all":1,
    "qs_pg:photos_sr":0,
    "qs_pg:pop_sr":2,
    "qs_pg:qs_pg_placetype":"locality",
    "qs_pg:qs_pg_placetype_gp":"Town",
    "qs_pg:woe_adm0":23424833,
    "woe:adm0_id":23424833,
    "woe:name_adm0":"\u0395\u03bb\u03bb\u03ac\u03b4\u03b1",
    "woe:name_adm1":"Peloponnese Western Greece and the Ionian Islands",
    "woe:placetype":"Town",
    "wof:name":"Kombitsion",
    "wof:placetype":"locality",
    "wof:population":733
},
  "geometry": {"coordinates":[19.86944,39.60083],"type":"Point"}
}