{
  "type": "Feature",
  "properties": {
    "gn:admin1_code":"ESYE43",
    "gn:admin2_code":"45.0",
    "gn:admin3_code":"9309.0",
    "gn:asciiname":"Amnissos",
    "gn:country_code":"GR",
    "gn:dem":2,
    "gn:feature_class":"P",
    "gn:feature_code":"PPL",
    "gn:name":"Amnissos",
    "gn:population":0,
    "gn:timezone":"Europe/Athens",
    "iso:country":"GR",
    "wof:name":"Amnissos",
    "wof:placetype":"locality"
},
  "geometry": {"coordinates":[25.20849,35.3316],"type":"Point"}
}