{
  "type": "Feature",
  "properties": {
    "gn:admin1_code":"ESYE42",
    "gn:admin2_code":"49.0",
    "gn:admin3_code":"9301",
    "gn:asciiname":"Volax",
    "gn:country_code":"GR",
    "gn:dem":281,
    "gn:feature_class":"P",
    "gn:feature_code":"PPL",
    "gn:name":"V\u00f3lax",
    "gn:population":0,
    "gn:timezone":"Europe/Athens",
    "iso:country":"GR",
    "name:und_x_variant":[
        "V\u00f3lakas",
        "V\u00f3lax",
        "\u0392\u03cc\u03bb\u03b1\u03be"
    ],
    "wof:name":"Volax",
    "wof:placetype":"locality"
},
  "geometry": {"coordinates":[25.17816,37.59221],"type":"Point"}
}