{
  "type": "Feature",
  "properties": {
    "gn:admin1_code":"ESYE24",
    "gn:admin2_code":"29.0",
    "gn:admin3_code":"9160",
    "gn:asciiname":"Ano Dhamasta",
    "gn:country_code":"GR",
    "gn:dem":37,
    "gn:feature_class":"P",
    "gn:feature_code":"PPL",
    "gn:name":"\u00c1no Dham\u00e1sta",
    "gn:population":145,
    "gn:timezone":"Europe/Athens",
    "iso:country":"GR",
    "name:ell_x_preferred":[
        "\u0386\u03bd\u03c9 \u0394\u03b1\u03bc\u03ac\u03c3\u03c4\u03b1"
    ],
    "name:eng_x_preferred":[
        "Ano Damasta"
    ],
    "name:und_x_variant":[
        "\u00c1no Dham\u00e1sta"
    ],
    "wof:name":"Ano Dhamasta",
    "wof:placetype":"locality",
    "wof:population":145
},
  "geometry": {"coordinates":[22.47017,38.79858],"type":"Point"}
}