{
  "type": "Feature",
  "properties": {
    "gn:admin1_code":"ESYE43",
    "gn:admin2_code":"46.0",
    "gn:admin3_code":"9313",
    "gn:asciiname":"Zakathos",
    "gn:country_code":"GR",
    "gn:dem":673,
    "gn:feature_class":"P",
    "gn:feature_code":"PPL",
    "gn:name":"Z\u00e1kathos",
    "gn:population":0,
    "gn:timezone":"Europe/Athens",
    "iso:country":"GR",
    "name:ell_x_preferred":[
        "Z\u00e1kathos"
    ],
    "name:ell_x_variant":[
        "\u0396\u03ac\u03ba\u03b1\u03b8\u03bf\u03c2"
    ],
    "wof:name":"Zakathos",
    "wof:placetype":"locality"
},
  "geometry": {"coordinates":[26.16531,35.10203],"type":"Point"}
}