{
  "type": "Feature",
  "properties": {
    "gn:admin1_code":"ESYE23",
    "gn:admin2_code":"31.0",
    "gn:admin3_code":"9129",
    "gn:asciiname":"Varnakas",
    "gn:country_code":"GR",
    "gn:dem":337,
    "gn:feature_class":"P",
    "gn:feature_code":"PPL",
    "gn:name":"V\u00e1rnakas",
    "gn:population":0,
    "gn:timezone":"Europe/Athens",
    "iso:country":"GR",
    "name:ell_x_preferred":[
        "\u0392\u03ac\u03c1\u03bd\u03b1\u03ba\u03b1\u03c2"
    ],
    "name:und_x_variant":[
        "V\u00e1rnakos",
        "V\u00e1rnakas"
    ],
    "wof:name":"Varnakas",
    "wof:placetype":"locality"
},
  "geometry": {"coordinates":[20.99031,38.72089],"type":"Point"}
}