{
  "type": "Feature",
  "properties": {
    "gn:admin1_code":"ESYE21",
    "gn:admin2_code":"17.0",
    "gn:admin3_code":"9081",
    "gn:asciiname":"Kollaiika",
    "gn:country_code":"GR",
    "gn:dem":421,
    "gn:feature_class":"P",
    "gn:feature_code":"PPL",
    "gn:name":"Kolla\u00edika",
    "gn:population":21,
    "gn:timezone":"Europe/Athens",
    "iso:country":"GR",
    "name:ell_x_preferred":[
        "\u039a\u03bf\u03bb\u03bb\u03b1\u03af\u03b9\u03ba\u03b1"
    ],
    "name:eng_x_preferred":[
        "Kolaiika"
    ],
    "name:und_x_variant":[
        "Kolla\u00edika"
    ],
    "wof:name":"Kollaiika",
    "wof:placetype":"locality",
    "wof:population":21
},
  "geometry": {"coordinates":[20.75086,39.44122],"type":"Point"}
}