{
  "type": "Feature",
  "properties": {
    "gn:admin1_code":"ESYE11",
    "gn:admin2_code":"4.0",
    "gn:admin3_code":"9002",
    "gn:asciiname":"Mikrochori",
    "gn:country_code":"GR",
    "gn:dem":89,
    "gn:feature_class":"P",
    "gn:feature_code":"PPL",
    "gn:name":"Mikroch\u00f3ri",
    "gn:population":0,
    "gn:timezone":"Europe/Athens",
    "iso:country":"GR",
    "name:ell_x_preferred":[
        "Mikroch\u00f3ri"
    ],
    "name:ell_x_variant":[
        "\u039c\u03b9\u03ba\u03c1\u03bf\u03c7\u03ce\u03c1\u03b9",
        "Mikroch\u00f3rion",
        "\u039c\u03b9\u03ba\u03c1\u03bf\u03c7\u03ce\u03c1\u03b9\u03bf\u03bd"
    ],
    "name:und_x_variant":[
        "Mikr\u00f3n Khor\u00edon",
        "Kuch\u00fak-K\u00f3\u00ef",
        "Mikrokh\u00f3rion"
    ],
    "wof:name":"Mikrochori",
    "wof:placetype":"locality"
},
  "geometry": {"coordinates":[24.17655,41.10215],"type":"Point"}
}