{
  "type": "Feature",
  "properties": {
    "gn:admin1_code":"ESYE14",
    "gn:admin2_code":"23.0",
    "gn:admin3_code":"9094",
    "gn:asciiname":"Vagenia",
    "gn:country_code":"GR",
    "gn:dem":617,
    "gn:feature_class":"P",
    "gn:feature_code":"PPL",
    "gn:name":"Vag\u00e9nia",
    "gn:population":0,
    "gn:timezone":"Europe/Athens",
    "iso:country":"GR",
    "name:ell_x_preferred":[
        "Vag\u00e9nia"
    ],
    "name:ell_x_variant":[
        "\u0392\u03b1\u03b3\u03ad\u03bd\u03b9\u03b1"
    ],
    "wof:name":"Vagenia",
    "wof:placetype":"locality"
},
  "geometry": {"coordinates":[21.60958,39.37289000000001],"type":"Point"}
}