{
  "type": "Feature",
  "properties": {
    "gn:admin1_code":"ESYE25",
    "gn:admin2_code":"37.0",
    "gn:admin3_code":"9247",
    "gn:asciiname":"Amigdhalea",
    "gn:country_code":"GR",
    "gn:dem":719,
    "gn:feature_class":"P",
    "gn:feature_code":"PPL",
    "gn:name":"Amigdhal\u00e9a",
    "gn:population":14,
    "gn:timezone":"Europe/Athens",
    "iso:country":"GR",
    "name:ell_x_colloquial":[
        "\u039c\u03c5\u03b3\u03b4\u03b1\u03bb\u03ad\u03b6\u03b1"
    ],
    "name:ell_x_preferred":[
        "\u0391\u03bc\u03c5\u03b3\u03b4\u03b1\u03bb\u03b9\u03ac"
    ],
    "name:ell_x_variant":[
        "\u0391\u03bc\u03c5\u03b3\u03b4\u03b1\u03bb\u03ad\u03b1",
        "\u039c\u03c5\u03b3\u03b4\u03b1\u03bb\u03ad\u03b6\u03b1"
    ],
    "name:eng_x_preferred":[
        "Amygdalia"
    ],
    "name:und_x_variant":[
        "Migdhal\u00e9za",
        "Amigdhal\u00e9a"
    ],
    "wof:name":"Amigdhalea",
    "wof:placetype":"locality",
    "wof:population":14
},
  "geometry": {"coordinates":[22.31778,37.8468],"type":"Point"}
}