{
  "type": "Feature",
  "properties": {
    "gn:admin1_code":"ESYE11",
    "gn:admin2_code":"4.0",
    "gn:admin3_code":"9004",
    "gn:asciiname":"Marmaria",
    "gn:country_code":"GR",
    "gn:dem":256,
    "gn:feature_class":"P",
    "gn:feature_code":"PPL",
    "gn:name":"Marmari\u00e1",
    "gn:population":0,
    "gn:timezone":"Europe/Athens",
    "iso:country":"GR",
    "name:ell_x_preferred":[
        "\u039c\u03b1\u03c1\u03bc\u03b1\u03c1\u03b9\u03ac"
    ],
    "name:und_x_variant":[
        "Doal\u00e1r",
        "Marmari\u00e1"
    ],
    "wof:name":"Marmaria",
    "wof:placetype":"locality"
},
  "geometry": {"coordinates":[24.33764,41.16871],"type":"Point"}
}