{
  "type": "Feature",
  "properties": {
    "gn:admin1_code":"ESYE13",
    "gn:admin2_code":"11.0",
    "gn:admin3_code":"9067",
    "gn:asciiname":"Milochori",
    "gn:country_code":"GR",
    "gn:dem":673,
    "gn:feature_class":"P",
    "gn:feature_code":"PPL",
    "gn:name":"Miloch\u00f3ri",
    "gn:population":0,
    "gn:timezone":"Europe/Athens",
    "iso:country":"GR",
    "name:ell_x_preferred":[
        "Miloch\u00f3ri"
    ],
    "name:ell_x_variant":[
        "\u039c\u03b7\u03bb\u03bf\u03c7\u03ce\u03c1\u03b9",
        "Miloch\u00f3rion",
        "\u039c\u03b7\u03bb\u03bf\u03c7\u03ce\u03c1\u03b9\u03bf\u03bd"
    ],
    "name:und_x_variant":[
        "L\u00ednga",
        "Milokh\u00f3ri",
        "Milokh\u00f3rion"
    ],
    "wof:name":"Milochori",
    "wof:placetype":"locality"
},
  "geometry": {"coordinates":[21.53739,40.50424],"type":"Point"}
}