{
  "type": "Feature",
  "properties": {
    "gn:admin1_code":"ESYE24",
    "gn:admin2_code":"29.0",
    "gn:admin3_code":"9159",
    "gn:asciiname":"Palamas",
    "gn:country_code":"GR",
    "gn:dem":717,
    "gn:feature_class":"P",
    "gn:feature_code":"PPL",
    "gn:name":"Palam\u00e1s",
    "gn:population":114,
    "gn:timezone":"Europe/Athens",
    "iso:country":"GR",
    "name:ell_x_preferred":[
        "\u03a0\u03b1\u03bb\u03b1\u03bc\u03ac\u03c2"
    ],
    "name:eng_x_preferred":[
        "Palamas"
    ],
    "wof:name":"Palamas",
    "wof:placetype":"locality",
    "wof:population":114
},
  "geometry": {"coordinates":[22.4006,39.02942],"type":"Point"}
}