{
  "type": "Feature",
  "properties": {
    "gn:admin1_code":"ESYE24",
    "gn:admin2_code":"29.0",
    "gn:admin3_code":"9159",
    "gn:asciiname":"Palamas",
    "gn:country_code":"GR",
    "gn:dem":717,
    "gn:feature_class":"P",
    "gn:feature_code":"PPL",
    "gn:name":"Palam\u00e1s",
    "gn:population":114,
    "gn:timezone":"Europe/Athens",
    "iso:country":"GR",
    "name:ara_x_preferred":[
        "\u0628\u0627\u0644\u0627\u0645\u0627\u0633"
    ],
    "name:ceb_x_preferred":[
        "Dimos Palamas"
    ],
    "name:deu_x_preferred":[
        "Palamas"
    ],
    "name:ell_x_preferred":[
        "\u03a0\u03b1\u03bb\u03b1\u03bc\u03ac\u03c2"
    ],
    "name:ell_x_variant":[
        "\u0394\u03ae\u03bc\u03bf\u03c2 \u03a0\u03b1\u03bb\u03b1\u03bc\u03ac"
    ],
    "name:eng_x_preferred":[
        "Palamas"
    ],
    "name:fin_x_preferred":[
        "Palam\u00e1s"
    ],
    "name:fra_x_preferred":[
        "Palamas"
    ],
    "name:ita_x_preferred":[
        "Palamas"
    ],
    "name:nld_x_preferred":[
        "Palamas"
    ],
    "name:nno_x_preferred":[
        "Palam\u00e1s"
    ],
    "name:pol_x_preferred":[
        "Palamas"
    ],
    "name:spa_x_preferred":[
        "Palam\u00e1s"
    ],
    "name:swe_x_preferred":[
        "Dimos Palamas"
    ],
    "name:tur_x_preferred":[
        "Palamas"
    ],
    "name:vie_x_preferred":[
        "Palamas"
    ],
    "wof:name":"Palamas",
    "wof:placetype":"locality",
    "wof:population":114
},
  "geometry": {"coordinates":[22.4006,39.02942],"type":"Point"}
}