{
  "type": "Feature",
  "properties": {
    "gn:country":"GR",
    "gn:fcode":"PPL",
    "gn:population":761,
    "iso:country":"GR",
    "name:ara_x_preferred":[
        "\u0623\u0648\u062b\u0648\u0646\u0648\u064a\u060c \u0643\u064a\u0631\u0643\u064a\u0631\u0627"
    ],
    "name:ara_x_variant":[
        "\u0623\u0648\u062b\u0648\u0646\u0648\u064a"
    ],
    "name:arz_x_preferred":[
        "\u0627\u0648\u062b\u0648\u0646\u0648\u0649"
    ],
    "name:bel_x_preferred":[
        "\u0410\u0444\u0430\u043d\u0456"
    ],
    "name:ceb_x_preferred":[
        "Othono\u00ed"
    ],
    "name:ces_x_preferred":[
        "Othoni"
    ],
    "name:deu_x_preferred":[
        "Othoni"
    ],
    "name:ell_x_preferred":[
        "\u039f\u03b8\u03c9\u03bd\u03bf\u03af"
    ],
    "name:eng_x_preferred":[
        "Othonoi"
    ],
    "name:epo_x_preferred":[
        "Otoni"
    ],
    "name:est_x_preferred":[
        "Othono\u00ed"
    ],
    "name:fas_x_preferred":[
        "\u0627\u0648\u062b\u0648\u0646\u0648\u06cc"
    ],
    "name:fin_x_preferred":[
        "Othono\u00ed"
    ],
    "name:fra_x_preferred":[
        "Othoni"
    ],
    "name:glg_x_preferred":[
        "Othonoi - \u039f\u03b8\u03c9\u03bd\u03bf\u03af"
    ],
    "name:ita_x_preferred":[
        "Fan\u00f2"
    ],
    "name:jpn_x_preferred":[
        "\u30aa\u30c8\u30cb\u5cf6"
    ],
    "name:nld_x_preferred":[
        "Othoni"
    ],
    "name:nno_x_preferred":[
        "Othon\u00ed"
    ],
    "name:nob_x_preferred":[
        "Othoni"
    ],
    "name:rus_x_preferred":[
        "\u041e\u0442\u043e\u043d\u0438"
    ],
    "name:spa_x_preferred":[
        "Othono\u00ed"
    ],
    "name:sqi_x_preferred":[
        "Thonuzi"
    ],
    "name:srp_x_preferred":[
        "\u041e\u0442\u043e\u043d\u0438"
    ],
    "name:swe_x_preferred":[
        "Othono\u00ed"
    ],
    "name:ukr_x_preferred":[
        "\u041e\u0442\u043e\u043d\u0456"
    ],
    "name:und_x_variant":[
        "\u00c1mmos"
    ],
    "name:zho_x_preferred":[
        "\u5967\u7d22\u5c3c\u5cf6"
    ],
    "qs_pg:aaroncc":"GR",
    "qs_pg:gn_country":"GR",
    "qs_pg:gn_fcode":"PPL",
    "qs_pg:gn_pop":761,
    "qs_pg:name":"Othono\u00ed",
    "qs_pg:photos_9r":0,
    "qs_pg:photos_sr":0,
    "qs_pg:pop_sr":2,
    "qs_pg:qs_pg_placetype":"locality",
    "wof:name":"Othono\u00ed",
    "wof:placetype":"locality",
    "wof:population":761
},
  "geometry": {"coordinates":[19.40972,39.84361],"type":"Point"}
}