{
  "type": "Feature",
  "properties": {
    "gn:admin1_code":"ESYE11",
    "gn:admin2_code":"4.0",
    "gn:admin3_code":"9002",
    "gn:asciiname":"Dentrakia",
    "gn:country_code":"GR",
    "gn:dem":750,
    "gn:feature_class":"P",
    "gn:feature_code":"PPL",
    "gn:name":"Dentr\u00e1kia",
    "gn:population":0,
    "gn:timezone":"Europe/Athens",
    "iso:country":"GR",
    "name:ell_x_preferred":[
        "Dentr\u00e1kia"
    ],
    "name:ell_x_variant":[
        "\u0394\u03b5\u03bd\u03c4\u03c1\u03ac\u03ba\u03b9\u03b1",
        "\u0394\u03b5\u03bd\u03b4\u03c1\u03ac\u03ba\u03b9\u03b1"
    ],
    "name:und_x_variant":[
        "Dendhr\u00e1kia",
        "Kr\u00e1nista",
        "Dhendr\u00e1kia"
    ],
    "wof:name":"Dentrakia",
    "wof:placetype":"locality"
},
  "geometry": {"coordinates":[24.17784,41.27186],"type":"Point"}
}