{
  "type": "Feature",
  "properties": {
    "gn:admin1_code":"ESYE14",
    "gn:asciiname":"Diaselo",
    "gn:country_code":"GR",
    "gn:dem":297,
    "gn:feature_class":"P",
    "gn:feature_code":"PPL",
    "gn:name":"Di\u00e1selo",
    "gn:population":0,
    "gn:timezone":"Europe/Athens",
    "iso:country":"GR",
    "name:ell_x_preferred":[
        "Di\u00e1selo"
    ],
    "name:ell_x_variant":[
        "\u0394\u03b9\u03ac\u03c3\u03b5\u03bb\u03bf"
    ],
    "wof:name":"Diaselo",
    "wof:placetype":"locality"
},
  "geometry": {"coordinates":[23.93304,39.24275],"type":"Point"}
}