{
  "type": "Feature",
  "properties": {
    "gn:country":"GR",
    "gn:fcode":"PPL",
    "gn:population":585,
    "iso:country":"GR",
    "name:ell_x_preferred":[
        "\u03a6\u03c5\u03c4\u03b5\u03af\u03b1"
    ],
    "name:und_x_variant":[
        "Fit\u00eda"
    ],
    "qs_pg:aaroncc":"GR",
    "qs_pg:gn_country":"GR",
    "qs_pg:gn_fcode":"PPL",
    "qs_pg:gn_pop":585,
    "qs_pg:name":"Fyte\u00eda",
    "qs_pg:photos_9r":0,
    "qs_pg:photos_sr":0,
    "qs_pg:pop_sr":2,
    "qs_pg:qs_pg_placetype":"locality",
    "wof:name":"Fyte\u00eda",
    "wof:placetype":"locality",
    "wof:population":585
},
  "geometry": {"coordinates":[22.10944,40.56278],"type":"Point"}
}