{
  "type": "Feature",
  "properties": {
    "gn:admin1_code":"ESYE22",
    "gn:admin2_code":"27.0",
    "gn:admin3_code":"9120",
    "gn:asciiname":"Antipata",
    "gn:country_code":"GR",
    "gn:dem":236,
    "gn:feature_class":"P",
    "gn:feature_code":"PPL",
    "gn:name":"Antip\u00e1ta",
    "gn:population":0,
    "gn:timezone":"Europe/Athens",
    "iso:country":"GR",
    "name:ell_x_preferred":[
        "Antip\u00e1ta"
    ],
    "name:ell_x_variant":[
        "\u0391\u03bd\u03c4\u03b9\u03c0\u03ac\u03c4\u03b1"
    ],
    "name:und_x_variant":[
        "Pilaro\u00fa",
        "Andip\u00e1ta"
    ],
    "wof:name":"Antipata",
    "wof:placetype":"locality"
},
  "geometry": {"coordinates":[20.56303,38.32414],"type":"Point"}
}