{
  "type": "Feature",
  "properties": {
    "gn:admin1_code":"ESYE23",
    "gn:admin2_code":"38.0",
    "gn:admin3_code":"9130",
    "gn:asciiname":"Ayioi Theodhoroi",
    "gn:country_code":"GR",
    "gn:dem":205,
    "gn:feature_class":"P",
    "gn:feature_code":"PPL",
    "gn:name":"\u00c1yioi The\u00f3dhoroi",
    "gn:population":0,
    "gn:timezone":"Europe/Athens",
    "iso:country":"GR",
    "wof:name":"Ayioi Theodhoroi",
    "wof:placetype":"locality"
},
  "geometry": {"coordinates":[21.96383,38.2693],"type":"Point"}
}