{
  "type": "Feature",
  "properties": {
    "gn:admin1_code":"ESYE43",
    "gn:admin2_code":"45.0",
    "gn:admin3_code":"9307",
    "gn:asciiname":"Tsoutsouros",
    "gn:cc2":"GR",
    "gn:country_code":"GR",
    "gn:dem":12,
    "gn:feature_class":"P",
    "gn:feature_code":"PPL",
    "gn:name":"Tso\u00fatsouros",
    "gn:population":0,
    "gn:timezone":"Europe/Athens",
    "iso:country":"GR",
    "name:und_x_variant":[
        "Tso\u00fatsouras",
        "Tso\u00fatsouros"
    ],
    "wof:name":"Tsoutsouros",
    "wof:placetype":"locality"
},
  "geometry": {"coordinates":[25.28877,34.98641],"type":"Point"}
}