{
  "type": "Feature",
  "properties": {
    "gn:admin1_code":"ESYE21",
    "gn:admin2_code":"19.0",
    "gn:admin3_code":"9090",
    "gn:asciiname":"Agios Thomas",
    "gn:country_code":"GR",
    "gn:dem":25,
    "gn:feature_class":"P",
    "gn:feature_code":"PPL",
    "gn:name":"\u00c1gios Thom\u00e1s",
    "gn:population":0,
    "gn:timezone":"Europe/Athens",
    "iso:country":"GR",
    "name:ell_x_preferred":[
        "\u00c1gios Thom\u00e1s"
    ],
    "name:ell_x_variant":[
        "\u0386\u03b3\u03b9\u03bf\u03c2 \u0398\u03c9\u03bc\u03ac\u03c2"
    ],
    "name:und_x_variant":[
        "Tourkovo\u00fani",
        "\u00c1yios Thom\u00e1s"
    ],
    "wof:name":"Agios Thomas",
    "wof:placetype":"locality"
},
  "geometry": {"coordinates":[20.78794,38.97539],"type":"Point"}
}