{
  "type": "Feature",
  "properties": {
    "gn:admin1_code":"ESYE31",
    "gn:admin2_code":"406101.0",
    "gn:admin3_code":"9209",
    "gn:asciiname":"Livadhion",
    "gn:country_code":"GR",
    "gn:dem":249,
    "gn:feature_class":"P",
    "gn:feature_code":"PPL",
    "gn:name":"Liv\u00e1dhion",
    "gn:population":77,
    "gn:timezone":"Europe/Athens",
    "iso:country":"GR",
    "name:ell_x_preferred":[
        "\u039b\u03b9\u03b2\u03ac\u03b4\u03b9"
    ],
    "name:eng_x_preferred":[
        "Livadi"
    ],
    "wof:name":"Livadhion",
    "wof:placetype":"locality",
    "wof:population":77
},
  "geometry": {"coordinates":[22.99181,36.18174000000001],"type":"Point"}
}