{
  "type": "Feature",
  "properties": {
    "iso:country":"GR",
    "name:ara_x_preferred":[
        "\u0646\u064a\u0627 \u0625\u0628\u064a\u062f\u0627\u0648\u0631\u0648\u0633"
    ],
    "name:ceb_x_preferred":[
        "N\u00e9a Ep\u00eddavros"
    ],
    "name:deu_x_preferred":[
        "Nea Epidavros"
    ],
    "name:ell_x_preferred":[
        "\u039d\u03ad\u03b1 \u0395\u03c0\u03af\u03b4\u03b1\u03c5\u03c1\u03bf\u03c2 \u0391\u03c1\u03b3\u03bf\u03bb\u03af\u03b4\u03b1\u03c2"
    ],
    "name:eng_x_preferred":[
        "Nea Epidavros"
    ],
    "name:fin_x_preferred":[
        "N\u00e9a Ep\u00eddavros"
    ],
    "name:hye_x_preferred":[
        "\u0546\u0565\u0561 \u0537\u057a\u056b\u0564\u0561\u057e\u0580\u0578\u057d"
    ],
    "name:ita_x_preferred":[
        "Nea Epidauros"
    ],
    "name:nld_x_preferred":[
        "Nea Epidavros"
    ],
    "name:ron_x_preferred":[
        "Nea Epidavros"
    ],
    "name:rus_x_preferred":[
        "\u041d\u0435\u0430-\u042d\u043f\u0438\u0434\u0430\u0432\u0440\u043e\u0441"
    ],
    "name:slk_x_preferred":[
        "Nea Epidauros"
    ],
    "name:swe_x_preferred":[
        "N\u00e9a Ep\u00eddavros"
    ],
    "qs_pg:aaroncc":"GR",
    "qs_pg:name":"Nea Epidhavros",
    "qs_pg:name_adm0":"\u0395\u03bb\u03bb\u03ac\u03b4\u03b1",
    "qs_pg:name_adm1":"Peloponnese Western Greece and the Ionian Islands",
    "qs_pg:photos":72,
    "qs_pg:photos_1k":15,
    "qs_pg:photos_9k":1,
    "qs_pg:photos_9r":2,
    "qs_pg:photos_all":72,
    "qs_pg:photos_sr":2,
    "qs_pg:pop_sr":0,
    "qs_pg:qs_pg_placetype":"locality",
    "qs_pg:qs_pg_placetype_gp":"Town",
    "qs_pg:woe_adm0":23424833,
    "woe:adm0_id":23424833,
    "woe:name_adm0":"\u0395\u03bb\u03bb\u03ac\u03b4\u03b1",
    "woe:name_adm1":"Peloponnese Western Greece and the Ionian Islands",
    "woe:placetype":"Town",
    "wof:name":"Nea Epidhavros",
    "wof:placetype":"locality"
},
  "geometry": {"coordinates":[23.13225,37.676823],"type":"Point"}
}