{
  "type": "Feature",
  "properties": {
    "gn:admin1_code":"ESYE42",
    "gn:asciiname":"Lazareta",
    "gn:country_code":"GR",
    "gn:dem":13,
    "gn:feature_class":"P",
    "gn:feature_code":"PPL",
    "gn:name":"Lazar\u00e9ta",
    "gn:population":0,
    "gn:timezone":"Europe/Athens",
    "iso:country":"GR",
    "name:ell_x_preferred":[
        "\u039b\u03b1\u03b6\u03b1\u03c1\u03ad\u03c4\u03b1"
    ],
    "name:und_x_variant":[
        "Lazar\u00e9ton",
        "Lazar\u00e9ta"
    ],
    "wof:name":"Lazareta",
    "wof:placetype":"locality"
},
  "geometry": {"coordinates":[24.94416,37.42987],"type":"Point"}
}