{
  "type": "Feature",
  "properties": {
    "gn:admin1_code":"ESYE23",
    "gn:admin2_code":"39.0",
    "gn:admin3_code":"9137",
    "gn:asciiname":"Smila",
    "gn:country_code":"GR",
    "gn:dem":61,
    "gn:feature_class":"P",
    "gn:feature_code":"PPL",
    "gn:name":"Sm\u00edla",
    "gn:population":0,
    "gn:timezone":"Europe/Athens",
    "iso:country":"GR",
    "name:ell_x_preferred":[
        "\u03a3\u03bc\u03af\u03bb\u03b1"
    ],
    "name:und_x_variant":[
        "Sm\u00edla"
    ],
    "wof:name":"Smila",
    "wof:placetype":"locality"
},
  "geometry": {"coordinates":[21.55294,37.67872],"type":"Point"}
}