{
  "type": "Feature",
  "properties": {
    "gn:admin1_code":"ESYE43",
    "gn:admin2_code":"45.0",
    "gn:admin3_code":"9305",
    "gn:asciiname":"Giofyros",
    "gn:country_code":"GR",
    "gn:dem":9,
    "gn:elevation":"13.0",
    "gn:feature_class":"P",
    "gn:feature_code":"PPL",
    "gn:name":"Giofyros",
    "gn:population":0,
    "gn:timezone":"Europe/Athens",
    "iso:country":"GR",
    "wof:name":"Giofyros",
    "wof:placetype":"locality"
},
  "geometry": {"coordinates":[25.10754,35.32507000000001],"type":"Point"}
}