{
  "type": "Feature",
  "properties": {
    "gn:admin1_code":"ESYE24",
    "gn:admin2_code":"32.0",
    "gn:admin3_code":"9165",
    "gn:asciiname":"Stromi",
    "gn:country_code":"GR",
    "gn:dem":863,
    "gn:feature_class":"P",
    "gn:feature_code":"PPL",
    "gn:name":"Str\u00f3mi",
    "gn:population":0,
    "gn:timezone":"Europe/Athens",
    "iso:country":"GR",
    "name:ell_x_preferred":[
        "\u03a3\u03c4\u03c1\u03cc\u03bc\u03b7"
    ],
    "name:und_x_variant":[
        "Stromni",
        "Str\u00f3mi"
    ],
    "wof:name":"Stromi",
    "wof:placetype":"locality"
},
  "geometry": {"coordinates":[22.25723,38.70752],"type":"Point"}
}