{
  "type": "Feature",
  "properties": {
    "gn:admin1_code":"ESYE25",
    "gn:admin2_code":"42.0",
    "gn:admin3_code":"9248",
    "gn:asciiname":"Alika",
    "gn:country_code":"GR",
    "gn:dem":96,
    "gn:feature_class":"P",
    "gn:feature_code":"PPL",
    "gn:name":"\u00c1lika",
    "gn:population":82,
    "gn:timezone":"Europe/Athens",
    "iso:country":"GR",
    "name:ell_x_preferred":[
        "\u0386\u03bb\u03b9\u03ba\u03b1"
    ],
    "name:eng_x_preferred":[
        "Alika"
    ],
    "name:fas_x_preferred":[
        "\u0627\u0644\u06cc\u06a9\u0627"
    ],
    "wof:name":"Alika",
    "wof:placetype":"locality",
    "wof:population":82
},
  "geometry": {"coordinates":[22.4312,36.46991],"type":"Point"}
}