{
  "type": "Feature",
  "properties": {
    "gn:gn_country":"GR",
    "gn:gn_fcode":"PPL",
    "gn:gn_pop":513,
    "gn:population":513,
    "iso:country":"GR",
    "name:ell_x_preferred":[
        "\u039c\u03b1\u03bb\u03b1\u03ba\u03ac\u03c3\u03b9"
    ],
    "name:ell_x_variant":[
        "\u039c\u03b1\u03bb\u03b1\u03ba\u03ac\u03c3\u03b9\u03bf\u03bd",
        "\u0394\u03ae\u03bc\u03bf\u03c2 \u039c\u03b1\u03bb\u03b1\u03ba\u03b1\u03c3\u03af\u03bf\u03c5"
    ],
    "name:eng_x_preferred":[
        "Malakasi"
    ],
    "name:fra_x_preferred":[
        "Malakasi"
    ],
    "name:ita_x_preferred":[
        "Malakasi"
    ],
    "name:jpn_x_preferred":[
        "\u30de\u30e9\u30ab\u30b7"
    ],
    "name:nld_x_preferred":[
        "Malakasi"
    ],
    "name:nno_x_preferred":[
        "Malak\u00e1si"
    ],
    "name:swe_x_preferred":[
        "Malak\u00e1si"
    ],
    "name:unk_x_variant":[
        "Malak\u00e1si"
    ],
    "qs_pg:aaroncc":"GR",
    "qs_pg:gn_country":"GR",
    "qs_pg:gn_fcode":"PPL",
    "qs_pg:gn_pop":513,
    "qs_pg:name":"Malak\u00e1sion",
    "qs_pg:photos_9r":0,
    "qs_pg:photos_sr":0,
    "qs_pg:pop_sr":2,
    "qs_pg:qs_pg_placetype":"locality",
    "wof:name":"Malak\u00e1sion",
    "wof:placetype":"locality",
    "wof:population":513
},
  "geometry": {"coordinates":[21.285,39.78111],"type":"Point"}
}