{
  "type": "Feature",
  "properties": {
    "gn:admin1_code":"ESYE25",
    "gn:admin2_code":"42.0",
    "gn:admin3_code":"9248",
    "gn:asciiname":"Chalikia Vatta",
    "gn:country_code":"GR",
    "gn:dem":5,
    "gn:feature_class":"P",
    "gn:feature_code":"PPL",
    "gn:name":"Chaliki\u00e1 V\u00e1tta",
    "gn:population":22,
    "gn:timezone":"Europe/Athens",
    "iso:country":"GR",
    "name:ell_x_preferred":[
        "\u03a7\u03b1\u03bb\u03b9\u03ba\u03b9\u03ac \u0392\u03ac\u03c4\u03c4\u03b1"
    ],
    "name:ell_x_variant":[
        "\u03a7\u03b1\u03bb\u03b9\u03ba\u03b9\u03ac \u0392\u03ac\u03c4\u03b1"
    ],
    "name:eng_x_preferred":[
        "Chalikia Vatta"
    ],
    "name:und_x_variant":[
        "Khalki\u00e1",
        "Khal\u00edkia"
    ],
    "wof:name":"Chalikia Vatta",
    "wof:placetype":"locality",
    "wof:population":22
},
  "geometry": {"coordinates":[22.47717,36.61723],"type":"Point"}
}