{
  "type": "Feature",
  "properties": {
    "gn:gn_country":"GR",
    "gn:gn_fcode":"PPL",
    "gn:gn_pop":24,
    "gn:population":24,
    "iso:country":"GR",
    "name:ell_x_preferred":[
        "Lev\u00e9ntis"
    ],
    "name:ell_x_variant":[
        "\u039b\u03b5\u03b2\u03ad\u03bd\u03c4\u03b7\u03c2"
    ],
    "qs_pg:aaroncc":"GR",
    "qs_pg:gn_country":"GR",
    "qs_pg:gn_fcode":"PPL",
    "qs_pg:gn_pop":24,
    "qs_pg:name":"Lev\u00e9ntis",
    "qs_pg:photos_9r":0,
    "qs_pg:photos_sr":0,
    "qs_pg:pop_sr":1,
    "qs_pg:qs_pg_placetype":"locality",
    "wof:name":"Lev\u00e9ntis",
    "wof:placetype":"locality",
    "wof:population":24
},
  "geometry": {"coordinates":[22.03167,40.35972],"type":"Point"}
}