{
  "type": "Feature",
  "properties": {
    "gn:admin1_code":"ESYE11",
    "gn:admin2_code":"1.0",
    "gn:admin3_code":"9008",
    "gn:asciiname":"Palaia Sayini",
    "gn:cc2":"GR",
    "gn:country_code":"GR",
    "gn:dem":27,
    "gn:feature_class":"P",
    "gn:feature_code":"PPL",
    "gn:name":"Palai\u00e1 Say\u00edni",
    "gn:population":0,
    "gn:timezone":"Europe/Athens",
    "iso:country":"GR",
    "name:und_x_variant":[
        "Say\u00edni",
        "Palai\u00e1 Say\u00edni"
    ],
    "wof:name":"Palaia Sayini",
    "wof:placetype":"locality"
},
  "geometry": {"coordinates":[26.55421,41.47566],"type":"Point"}
}