{
  "type": "Feature",
  "properties": {
    "gn:admin1_code":"ESYE14",
    "gn:admin2_code":"21.0",
    "gn:admin3_code":"9100.0",
    "gn:asciiname":"Amfithea",
    "gn:country_code":"GR",
    "gn:dem":72,
    "gn:feature_class":"P",
    "gn:feature_code":"PPL",
    "gn:name":"Amfith\u00e9a",
    "gn:population":33,
    "gn:timezone":"Europe/Athens",
    "iso:country":"GR",
    "name:ell_x_preferred":[
        "\u0391\u03bc\u03c6\u03b9\u03b8\u03ad\u03b1"
    ],
    "name:eng_x_preferred":[
        "Amfithea"
    ],
    "wof:name":"Amfithea",
    "wof:placetype":"locality",
    "wof:population":33
},
  "geometry": {"coordinates":[22.48271,39.74184],"type":"Point"}
}