{
  "type": "Feature",
  "properties": {
    "gn:gn_country":"GR",
    "gn:gn_fcode":"PPL",
    "gn:gn_pop":1497,
    "gn:population":1159,
    "iso:country":"GR",
    "name:ara_x_preferred":[
        "\u0646\u064a\u0648\u0646 \u0645\u0648\u0646\u0627\u0633\u062a\u064a\u0631\u064a\u0648\u0646\u060c \u0641\u062b\u064a\u0648\u062a\u064a\u0633"
    ],
    "name:ell_x_preferred":[
        "\u039d\u03ad\u03bf\u03bd \u039c\u03bf\u03bd\u03b1\u03c3\u03c4\u03ae\u03c1\u03b9\u03bf\u03bd"
    ],
    "name:ell_x_variant":[
        "\u039d\u03ad\u03bf \u039c\u03bf\u03bd\u03b1\u03c3\u03c4\u03ae\u03c1\u03b9\u03bf",
        "\u039d\u03ad\u03bf \u039c\u03bf\u03bd\u03b1\u03c3\u03c4\u03ae\u03c1\u03b9"
    ],
    "name:eng_x_preferred":[
        "Neo Monastiri"
    ],
    "name:gre_x_preferred":[
        "\u039d\u03ad\u03bf \u039c\u03bf\u03bd\u03b1\u03c3\u03c4\u03ae\u03c1\u03b9 \u03a6\u03b8\u03b9\u03ce\u03c4\u03b9\u03b4\u03b1\u03c2"
    ],
    "name:nno_x_preferred":[
        "N\u00e9o Monast\u00edri"
    ],
    "name:swe_x_preferred":[
        "N\u00e9on Monast\u00edrion"
    ],
    "name:unk_x_variant":[
        "Ts\u00f3mba"
    ],
    "qs_pg:aaroncc":"GR",
    "qs_pg:gn_country":"GR",
    "qs_pg:gn_fcode":"PPL",
    "qs_pg:gn_pop":1497,
    "qs_pg:name":"Neon Monastirion",
    "qs_pg:name_adm0":"\u0395\u03bb\u03bb\u03ac\u03b4\u03b1",
    "qs_pg:name_adm1":"Thessaly and Continental Greece",
    "qs_pg:photos_9k":1,
    "qs_pg:photos_9r":1,
    "qs_pg:photos_all":3,
    "qs_pg:photos_sr":0,
    "qs_pg:pop_sr":3,
    "qs_pg:qs_pg_placetype":"locality",
    "qs_pg:qs_pg_placetype_gp":"Town",
    "qs_pg:woe_adm0":23424833,
    "woe:adm0_id":23424833,
    "woe:name_adm0":"\u0395\u03bb\u03bb\u03ac\u03b4\u03b1",
    "woe:name_adm1":"Thessaly and Continental Greece",
    "woe:placetype":"Town",
    "wof:name":"Neon Monastirion",
    "wof:placetype":"locality",
    "wof:population":1159
},
  "geometry": {"coordinates":[22.25,39.23333],"type":"Point"}
}