{
  "type": "Feature",
  "properties": {
    "gn:admin1_code":"ESYE25",
    "gn:admin2_code":"41.0",
    "gn:admin3_code":"9238",
    "gn:asciiname":"Vyziki",
    "gn:country_code":"GR",
    "gn:dem":710,
    "gn:feature_class":"P",
    "gn:feature_code":"PPL",
    "gn:name":"Vyz\u00edki",
    "gn:population":0,
    "gn:timezone":"Europe/Athens",
    "iso:country":"GR",
    "name:ell_x_preferred":[
        "Vyz\u00edki"
    ],
    "name:ell_x_variant":[
        "\u0392\u03c5\u03b6\u03af\u03ba\u03b9",
        "Vyz\u00edkion",
        "\u0392\u03c5\u03b6\u03af\u03ba\u03b9\u03bf\u03bd",
        "\u0392\u03c5\u03b6\u03af\u03ba\u03b9 \u0391\u03c1\u03ba\u03b1\u03b4\u03af\u03b1\u03c2"
    ],
    "name:fra_x_preferred":[
        "Vyzikion"
    ],
    "name:und_x_variant":[
        "Viz\u00edtsi",
        "Viz\u00edkion"
    ],
    "wof:name":"Vyziki",
    "wof:placetype":"locality"
},
  "geometry": {"coordinates":[21.96187,37.72051],"type":"Point"}
}