{
  "type": "Feature",
  "properties": {
    "gn:admin1_code":"ESYE14",
    "gn:admin2_code":"21.0",
    "gn:admin3_code":"9098",
    "gn:asciiname":"Lefki",
    "gn:country_code":"GR",
    "gn:dem":430,
    "gn:feature_class":"P",
    "gn:feature_code":"PPL",
    "gn:name":"L\u00e9fki",
    "gn:population":0,
    "gn:timezone":"Europe/Athens",
    "iso:country":"GR",
    "name:ell_x_preferred":[
        "L\u00e9fki"
    ],
    "name:ell_x_variant":[
        "\u039b\u03b5\u03cd\u03ba\u03b7"
    ],
    "name:und_x_variant":[
        "Sk\u00f3mba",
        "L\u00e9vki"
    ],
    "wof:name":"Lefki",
    "wof:placetype":"locality"
},
  "geometry": {"coordinates":[22.18242,39.80294],"type":"Point"}
}