{
  "type": "Feature",
  "properties": {
    "gn:gn_country":"GR",
    "gn:gn_fcode":"PPL",
    "gn:gn_pop":0,
    "gn:population":316,
    "iso:country":"GR",
    "name:dut_x_preferred":[
        "Sellia"
    ],
    "name:ell_x_preferred":[
        "\u03a3\u03b5\u03bb\u03bb\u03af\u03b1"
    ],
    "name:eng_x_preferred":[
        "Sellia"
    ],
    "name:gre_x_preferred":[
        "\u03a3\u03b5\u03bb\u03bb\u03b9\u03ac \u03a7\u03b1\u03bd\u03af\u03c9\u03bd"
    ],
    "qs_pg:aaroncc":"GR",
    "qs_pg:gn_country":"GR",
    "qs_pg:gn_fcode":"PPL",
    "qs_pg:gn_pop":0,
    "qs_pg:name":"Sellia",
    "qs_pg:name_adm0":"\u0395\u03bb\u03bb\u03ac\u03b4\u03b1",
    "qs_pg:name_adm1":"Crete",
    "qs_pg:photos":29,
    "qs_pg:photos_1k":6,
    "qs_pg:photos_9k":1,
    "qs_pg:photos_9r":2,
    "qs_pg:photos_all":31,
    "qs_pg:photos_sr":2,
    "qs_pg:pop_sr":0,
    "qs_pg:qs_pg_placetype":"locality",
    "qs_pg:qs_pg_placetype_gp":"Town",
    "qs_pg:woe_adm0":23424833,
    "woe:adm0_id":23424833,
    "woe:name_adm0":"\u0395\u03bb\u03bb\u03ac\u03b4\u03b1",
    "woe:name_adm1":"Crete",
    "woe:placetype":"Town",
    "wof:name":"Sellia",
    "wof:placetype":"locality",
    "wof:population":316
},
  "geometry": {"coordinates":[24.38072,35.20537],"type":"Point"}
}