{
  "type": "Feature",
  "properties": {
    "gn:admin1_code":"ESYE13",
    "gn:admin2_code":"11.0",
    "gn:admin3_code":"9069",
    "gn:asciiname":"Prosilio",
    "gn:country_code":"GR",
    "gn:dem":495,
    "gn:feature_class":"P",
    "gn:feature_code":"PPL",
    "gn:name":"Pros\u00edlio",
    "gn:population":0,
    "gn:timezone":"Europe/Athens",
    "iso:country":"GR",
    "name:ell_x_preferred":[
        "Pros\u00edlio"
    ],
    "name:ell_x_variant":[
        "\u03a0\u03c1\u03bf\u03c3\u03ae\u03bb\u03b9\u03bf",
        "Pros\u00edlion",
        "\u03a0\u03c1\u03bf\u03c3\u03ae\u03bb\u03b9\u03bf\u03bd"
    ],
    "wof:name":"Prosilio",
    "wof:placetype":"locality"
},
  "geometry": {"coordinates":[21.94433,40.15096],"type":"Point"}
}