{
  "type": "Feature",
  "properties": {
    "gn:admin1_code":"ESYE24",
    "gn:admin2_code":"34.0",
    "gn:admin3_code":"9152",
    "gn:asciiname":"Porto Boufalo",
    "gn:country_code":"GR",
    "gn:dem":8,
    "gn:feature_class":"P",
    "gn:feature_code":"PPL",
    "gn:name":"P\u00f3rto Bo\u00fafalo",
    "gn:population":0,
    "gn:timezone":"Europe/Athens",
    "iso:country":"GR",
    "name:ell_x_preferred":[
        "P\u00f3rto Bo\u00fafalo"
    ],
    "name:ell_x_variant":[
        "\u03a0\u03cc\u03c1\u03c4\u03bf \u039c\u03c0\u03bf\u03cd\u03c6\u03b1\u03bb\u03bf"
    ],
    "name:und_x_variant":[
        "Portombo\u00fafalos",
        "P\u00f3rto Vo\u00fafalo",
        "Bo\u00fafalon"
    ],
    "wof:name":"Porto Boufalo",
    "wof:placetype":"locality"
},
  "geometry": {"coordinates":[24.12028,38.30114],"type":"Point"}
}