{
  "type": "Feature",
  "properties": {
    "gn:country":"GR",
    "gn:fcode":"PPL",
    "gn:population":2993,
    "iso:country":"GR",
    "name:ara_x_preferred":[
        "\u0643\u0627\u062a\u0633\u064a\u0643\u0627\u0633\u060c \u0625\u0648\u0627\u0646\u064a\u0646\u0627"
    ],
    "name:ara_x_variant":[
        "\u0643\u0627\u062a\u0633\u064a\u0643\u0627\u0633"
    ],
    "name:arz_x_preferred":[
        "\u0643\u0627\u062a\u0633\u064a\u0643\u0627\u0633"
    ],
    "name:ast_x_preferred":[
        "Katsikas"
    ],
    "name:bul_x_preferred":[
        "\u041a\u0430\u0446\u0438\u043a\u0430\u0441"
    ],
    "name:ceb_x_preferred":[
        "Katsik\u00e1s"
    ],
    "name:ell_x_preferred":[
        "\u039a\u03b1\u03c4\u03c3\u03b9\u03ba\u03ac\u03c2"
    ],
    "name:ell_x_variant":[
        "\u039a\u03b1\u03c4\u03c3\u03b9\u03ba\u03ac\u03c2 \u0399\u03c9\u03b1\u03bd\u03bd\u03af\u03bd\u03c9\u03bd"
    ],
    "name:eng_x_preferred":[
        "Katsikas"
    ],
    "name:fin_x_preferred":[
        "Katsik\u00e1s"
    ],
    "name:hye_x_preferred":[
        "\u053f\u0561\u0581\u056b\u056f\u0561\u057d"
    ],
    "name:mkd_x_preferred":[
        "\u041a\u0430\u0446\u0438\u043a\u0430\u0441"
    ],
    "name:nld_x_preferred":[
        "Katsikas"
    ],
    "name:nno_x_preferred":[
        "Katsik\u00e1s"
    ],
    "name:rus_x_preferred":[
        "\u041a\u0430\u0446\u0438\u043a\u0430\u0441"
    ],
    "name:swe_x_preferred":[
        "Katsik\u00e1s"
    ],
    "name:und_x_variant":[
        "Katsik\u00e1"
    ],
    "qs_pg:aaroncc":"GR",
    "qs_pg:gn_country":"GR",
    "qs_pg:gn_fcode":"PPL",
    "qs_pg:gn_pop":2993,
    "qs_pg:name":"Katsikas",
    "qs_pg:name_adm0":"\u0395\u03bb\u03bb\u03ac\u03b4\u03b1",
    "qs_pg:name_adm1":"Epirus and Western Macedonia",
    "qs_pg:photos_9k":1,
    "qs_pg:photos_9r":3,
    "qs_pg:photos_all":92,
    "qs_pg:photos_sr":0,
    "qs_pg:pop_sr":4,
    "qs_pg:qs_pg_placetype":"locality",
    "qs_pg:qs_pg_placetype_gp":"Town",
    "qs_pg:woe_adm0":23424833,
    "woe:adm0_id":23424833,
    "woe:name_adm0":"\u0395\u03bb\u03bb\u03ac\u03b4\u03b1",
    "woe:name_adm1":"Epirus and Western Macedonia",
    "woe:placetype":"Town",
    "wof:name":"Katsikas",
    "wof:placetype":"locality",
    "wof:population":3885
},
  "geometry": {"coordinates":[20.8875,39.6225],"type":"Point"}
}