{
  "type": "Feature",
  "properties": {
    "gn:admin1_code":"ESYE23",
    "gn:admin2_code":"31.0",
    "gn:admin3_code":"9126",
    "gn:asciiname":"Agios Theodoros",
    "gn:country_code":"GR",
    "gn:dem":720,
    "gn:feature_class":"P",
    "gn:feature_code":"PPL",
    "gn:name":"\u00c1gios The\u00f3doros",
    "gn:population":0,
    "gn:timezone":"Europe/Athens",
    "iso:country":"GR",
    "name:ceb_x_preferred":[
        "Agios Theodoros"
    ],
    "name:dan_x_preferred":[
        "Agios Theodoros"
    ],
    "name:deu_x_preferred":[
        "Agios Theodoros"
    ],
    "name:ell_x_preferred":[
        "\u00c1gios The\u00f3doros"
    ],
    "name:ell_x_variant":[
        "\u0386\u03b3\u03b9\u03bf\u03c2 \u0398\u03b5\u03cc\u03b4\u03c9\u03c1\u03bf\u03c2"
    ],
    "name:hye_x_preferred":[
        "\u0531\u0575\u0578\u057d \u0539\u0565\u0578\u0564\u0578\u0580\u0578\u057d"
    ],
    "name:swe_x_preferred":[
        "Agios Theodoros"
    ],
    "name:und_x_variant":[
        "Makhal\u00e1s",
        "\u00c1yios The\u00f3dhoros"
    ],
    "wof:name":"Agios Theodoros",
    "wof:placetype":"locality"
},
  "geometry": {"coordinates":[21.75181,38.68056],"type":"Point"}
}