{
  "type": "Feature",
  "properties": {
    "gn:admin1_code":"ESYE24",
    "gn:admin2_code":"34.0",
    "gn:admin3_code":"9153",
    "gn:asciiname":"Kirinthos",
    "gn:country_code":"GR",
    "gn:dem":59,
    "gn:feature_class":"P",
    "gn:feature_code":"PPL",
    "gn:name":"K\u00edrinthos",
    "gn:population":0,
    "gn:timezone":"Europe/Athens",
    "iso:country":"GR",
    "name:ell_x_preferred":[
        "\u039a\u03ae\u03c1\u03b9\u03bd\u03b8\u03bf\u03c2"
    ],
    "name:und_x_variant":[
        "Skil\u00f3yianni",
        "K\u00edrinthos"
    ],
    "wof:name":"Kirinthos",
    "wof:placetype":"locality"
},
  "geometry": {"coordinates":[23.44392,38.80974000000001],"type":"Point"}
}