{
  "type": "Feature",
  "properties": {
    "gn:admin1_code":"ESYE25",
    "gn:admin2_code":"37.0",
    "gn:admin3_code":"9244",
    "gn:asciiname":"Sterna",
    "gn:country_code":"GR",
    "gn:dem":64,
    "gn:feature_class":"P",
    "gn:feature_code":"PPL",
    "gn:name":"St\u00e9rna",
    "gn:population":23,
    "gn:timezone":"Europe/Athens",
    "iso:country":"GR",
    "name:ell_x_preferred":[
        "\u03a3\u03c4\u03ad\u03c1\u03bd\u03b1"
    ],
    "name:eng_x_preferred":[
        "Sterna"
    ],
    "wof:name":"Sterna",
    "wof:placetype":"locality",
    "wof:population":23
},
  "geometry": {"coordinates":[22.8934,38.04875],"type":"Point"}
}