{
  "type": "Feature",
  "properties": {
    "gn:admin1_code":"ESYE23",
    "gn:admin2_code":"39.0",
    "gn:admin3_code":"9135",
    "gn:asciiname":"Brinia",
    "gn:country_code":"GR",
    "gn:dem":0,
    "gn:feature_class":"P",
    "gn:feature_code":"PPL",
    "gn:name":"Br\u00ednia",
    "gn:population":0,
    "gn:timezone":"Europe/Athens",
    "iso:country":"GR",
    "name:ell_x_preferred":[
        "Br\u00ednia"
    ],
    "name:ell_x_variant":[
        "\u039c\u03c0\u03c1\u03af\u03bd\u03b9\u03b1"
    ],
    "name:und_x_variant":[
        "Kamenitsota\u00edika"
    ],
    "wof:name":"Brinia",
    "wof:placetype":"locality"
},
  "geometry": {"coordinates":[21.31936,38.04083],"type":"Point"}
}