{
  "type": "Feature",
  "properties": {
    "gn:admin1_code":"ESYE25",
    "gn:admin2_code":"37.0",
    "gn:admin3_code":"9246",
    "gn:asciiname":"Khelidhoreo",
    "gn:country_code":"GR",
    "gn:dem":640,
    "gn:feature_class":"P",
    "gn:feature_code":"PPL",
    "gn:name":"Khelidh\u00f3reo",
    "gn:population":32,
    "gn:timezone":"Europe/Athens",
    "iso:country":"GR",
    "name:ell_x_preferred":[
        "\u03a7\u03b5\u03bb\u03c5\u03b4\u03cc\u03c1\u03b5\u03bf"
    ],
    "name:eng_x_preferred":[
        "Chelydoreo"
    ],
    "name:und_x_variant":[
        "Ko\u00fatos",
        "Khelidh\u00f3rion",
        "Khelidh\u00f3reon"
    ],
    "wof:name":"Khelidhoreo",
    "wof:placetype":"locality",
    "wof:population":32
},
  "geometry": {"coordinates":[22.40923,38.07698],"type":"Point"}
}