{
  "type": "Feature",
  "properties": {
    "gn:admin1_code":"ESYE11",
    "gn:admin2_code":"2.0",
    "gn:admin3_code":"9021",
    "gn:asciiname":"Thrylorio",
    "gn:country_code":"GR",
    "gn:dem":67,
    "gn:feature_class":"P",
    "gn:feature_code":"PPL",
    "gn:name":"Thryl\u00f3rio",
    "gn:population":0,
    "gn:timezone":"Europe/Athens",
    "iso:country":"GR",
    "name:ell_x_preferred":[
        "Thryl\u00f3rio"
    ],
    "name:ell_x_variant":[
        "\u0398\u03c1\u03c5\u03bb\u03cc\u03c1\u03b9\u03bf",
        "Thryl\u00f3rion",
        "\u0398\u03c1\u03c5\u03bb\u03cc\u03c1\u03b9\u03bf\u03bd"
    ],
    "name:und_x_variant":[
        "Thrill\u00f3rion",
        "Thril\u00f3rion"
    ],
    "wof:name":"Thrylorio",
    "wof:placetype":"locality"
},
  "geometry": {"coordinates":[25.48253,41.07683],"type":"Point"}
}