{
  "type": "Feature",
  "properties": {
    "gn:admin1_code":"ESYE31",
    "gn:admin2_code":"445406.0",
    "gn:admin3_code":"9219.0",
    "gn:asciiname":"Mokriza",
    "gn:country_code":"GR",
    "gn:dem":101,
    "gn:feature_class":"P",
    "gn:feature_code":"PPL",
    "gn:name":"M\u00f3kriza",
    "gn:population":0,
    "gn:timezone":"Europe/Athens",
    "iso:country":"GR",
    "name:ell_x_preferred":[
        "M\u00f3kriza"
    ],
    "name:ell_x_variant":[
        "\u039c\u03cc\u03ba\u03c1\u03b9\u03b6\u03b1"
    ],
    "wof:name":"Mokriza",
    "wof:placetype":"locality"
},
  "geometry": {"coordinates":[23.97714,37.77149],"type":"Point"}
}