{
  "type": "Feature",
  "properties": {
    "gn:admin1_code":"ESYE43",
    "gn:admin2_code":"46.0",
    "gn:admin3_code":"9310",
    "gn:asciiname":"Peponides",
    "gn:country_code":"GR",
    "gn:dem":198,
    "gn:feature_class":"P",
    "gn:feature_code":"PPL",
    "gn:name":"Pep\u00f3nides",
    "gn:population":7,
    "gn:timezone":"Europe/Athens",
    "iso:country":"GR",
    "name:ell_x_preferred":[
        "\u03a0\u03b5\u03c0\u03cc\u03bd\u03b7\u03b4\u03b5\u03c2"
    ],
    "name:eng_x_preferred":[
        "Peponides"
    ],
    "wof:name":"Peponides",
    "wof:placetype":"locality",
    "wof:population":7
},
  "geometry": {"coordinates":[25.65283,35.20864],"type":"Point"}
}