{
  "type": "Feature",
  "properties": {
    "gn:admin1_code":"ESYE25",
    "gn:admin2_code":"40.0",
    "gn:admin3_code":"9253",
    "gn:asciiname":"Lakkos",
    "gn:country_code":"GR",
    "gn:dem":309,
    "gn:feature_class":"P",
    "gn:feature_code":"PPL",
    "gn:name":"L\u00e1kkos",
    "gn:population":0,
    "gn:timezone":"Europe/Athens",
    "iso:country":"GR",
    "name:ell_x_preferred":[
        "L\u00e1kkos"
    ],
    "name:ell_x_variant":[
        "\u039b\u03ac\u03ba\u03ba\u03bf\u03c2"
    ],
    "wof:name":"Lakkos",
    "wof:placetype":"locality"
},
  "geometry": {"coordinates":[22.25724,36.89228],"type":"Point"}
}