{
  "type": "Feature",
  "properties": {
    "gn:admin1_code":"ESYE11",
    "gn:admin2_code":"14.0",
    "gn:admin3_code":"9014",
    "gn:asciiname":"Kokkinokhori",
    "gn:country_code":"GR",
    "gn:dem":228,
    "gn:feature_class":"P",
    "gn:feature_code":"PPL",
    "gn:name":"Kokkinokh\u00f3ri",
    "gn:population":278,
    "gn:timezone":"Europe/Athens",
    "iso:country":"GR",
    "name:ell_x_preferred":[
        "\u039a\u03bf\u03ba\u03ba\u03b9\u03bd\u03bf\u03c7\u03ce\u03c1\u03b9"
    ],
    "name:eng_x_preferred":[
        "Kokkinochori"
    ],
    "name:und_x_variant":[
        "Sarl\u00ed",
        "Kokkinokh\u00f3ri",
        "Kokkinokh\u00f3rion"
    ],
    "wof:name":"Kokkinokhori",
    "wof:placetype":"locality",
    "wof:population":278
},
  "geometry": {"coordinates":[24.00229,40.81387],"type":"Point"}
}