{
  "type": "Feature",
  "properties": {
    "gn:admin1_code":"ESYE22",
    "gn:admin2_code":"26.0",
    "gn:admin3_code":"9121",
    "gn:asciiname":"Frinion",
    "gn:country_code":"GR",
    "gn:dem":26,
    "gn:feature_class":"P",
    "gn:feature_code":"PPL",
    "gn:name":"Fr\u00ednion",
    "gn:population":494,
    "gn:timezone":"Europe/Athens",
    "iso:country":"GR",
    "name:ell_x_preferred":[
        "\u03a6\u03c1\u03cd\u03bd\u03b9"
    ],
    "name:eng_x_preferred":[
        "Fryni"
    ],
    "name:und_x_variant":[
        "Fr\u00edni",
        "Fr\u00ednion"
    ],
    "wof:name":"Frinion",
    "wof:placetype":"locality",
    "wof:population":494
},
  "geometry": {"coordinates":[20.68502,38.82647],"type":"Point"}
}