{
  "type": "Feature",
  "properties": {
    "gn:country":"GR",
    "gn:fcode":"PPL",
    "gn:population":137,
    "iso:country":"GR",
    "name:ell_x_preferred":[
        "\u039e\u03ad\u03c7\u03c9\u03c1\u03bf"
    ],
    "name:ell_x_variant":[
        "\u039e\u03ad\u03c7\u03c9\u03c1\u03bf\u03bd"
    ],
    "name:und_x_variant":[
        "M\u00e9mkou"
    ],
    "qs_pg:aaroncc":"GR",
    "qs_pg:gn_country":"GR",
    "qs_pg:gn_fcode":"PPL",
    "qs_pg:gn_pop":137,
    "qs_pg:name":"X\u00e9choron",
    "qs_pg:photos_9r":0,
    "qs_pg:photos_sr":0,
    "qs_pg:pop_sr":1,
    "qs_pg:qs_pg_placetype":"locality",
    "wof:name":"X\u00e9choron",
    "wof:placetype":"locality",
    "wof:population":137
},
  "geometry": {"coordinates":[20.37167,39.65611],"type":"Point"}
}