{
  "type": "Feature",
  "properties": {
    "gn:admin1_code":"ESYE13",
    "gn:admin2_code":"8.0",
    "gn:admin3_code":"9070",
    "gn:asciiname":"Sklithro",
    "gn:country_code":"GR",
    "gn:dem":675,
    "gn:feature_class":"P",
    "gn:feature_code":"PPL",
    "gn:name":"Skl\u00edthro",
    "gn:population":532,
    "gn:timezone":"Europe/Athens",
    "iso:country":"GR",
    "name:ell_x_historical":[
        "\u0396\u03b5\u03bb\u03b5\u03bd\u03af\u03c4\u03c3\u03b9\u03bf\u03bd",
        "\u0396\u03b5\u03bb\u03b5\u03bd\u03af\u03c4\u03c3\u03b9",
        "\u0396\u03ad\u03bb\u03b5\u03bd\u03b9\u03c4\u03c2"
    ],
    "name:ell_x_preferred":[
        "\u03a3\u03ba\u03bb\u03ae\u03b8\u03c1\u03bf"
    ],
    "name:ell_x_variant":[
        "\u03a3\u03ba\u03bb\u03ae\u03b8\u03c1\u03bf\u03bd",
        "\u0396\u03b5\u03bb\u03b5\u03bd\u03af\u03c4\u03c3\u03b9\u03bf\u03bd",
        "\u0396\u03b5\u03bb\u03b5\u03bd\u03af\u03c4\u03c3\u03b9",
        "\u0396\u03ad\u03bb\u03b5\u03bd\u03b9\u03c4\u03c2"
    ],
    "name:eng_x_preferred":[
        "Sklithro"
    ],
    "name:und_x_variant":[
        "Sk\u00e9lidhron",
        "Zelen\u00edtsion",
        "Skl\u00edthron",
        "Skl\u00edthro"
    ],
    "wof:name":"Sklithro",
    "wof:placetype":"locality",
    "wof:population":532
},
  "geometry": {"coordinates":[21.5048,40.62192],"type":"Point"}
}