{
  "type": "Feature",
  "properties": {
    "gn:admin1_code":"ESYE12",
    "gn:admin2_code":"16.0",
    "gn:admin3_code":"9047",
    "gn:asciiname":"Ano Milia",
    "gn:country_code":"GR",
    "gn:dem":950,
    "gn:feature_class":"P",
    "gn:feature_code":"PPL",
    "gn:name":"\u00c1no Mili\u00e1",
    "gn:population":0,
    "gn:timezone":"Europe/Athens",
    "iso:country":"GR",
    "name:ell_x_preferred":[
        "\u0386\u03bd\u03c9 \u039c\u03b7\u03bb\u03b9\u03ac"
    ],
    "name:und_x_variant":[
        "Er\u00edpia \u00c1no Mil\u00e9as",
        "\u00c1no Mili\u00e1",
        "Ere\u00edpia Ano Mil\u00e9as"
    ],
    "wof:name":"Ano Milia",
    "wof:placetype":"locality"
},
  "geometry": {"coordinates":[22.27027,40.24773],"type":"Point"}
}