{
  "type": "Feature",
  "properties": {
    "gn:admin1_code":"ESYE23",
    "gn:admin2_code":"31.0",
    "gn:admin3_code":"9128",
    "gn:asciiname":"Gavros",
    "gn:cc2":"GR",
    "gn:country_code":"GR",
    "gn:dem":759,
    "gn:feature_class":"P",
    "gn:feature_code":"PPL",
    "gn:name":"G\u00e1vros",
    "gn:population":0,
    "gn:timezone":"Europe/Athens",
    "iso:country":"GR",
    "name:ell_x_preferred":[
        "\u0393\u03ac\u03b2\u03c1\u03bf\u03c2"
    ],
    "name:und_x_variant":[
        "Dh\u00e9lga"
    ],
    "wof:name":"Gavros",
    "wof:placetype":"locality"
},
  "geometry": {"coordinates":[21.88253,38.50996],"type":"Point"}
}