{
  "type": "Feature",
  "properties": {
    "gn:admin1_code":"ESYE25",
    "gn:admin2_code":"41.0",
    "gn:admin3_code":"9240.0",
    "gn:asciiname":"Fokiano",
    "gn:country_code":"GR",
    "gn:dem":4,
    "gn:feature_class":"P",
    "gn:feature_code":"PPL",
    "gn:name":"Fokian\u00f3",
    "gn:population":0,
    "gn:timezone":"Europe/Athens",
    "iso:country":"GR",
    "name:ell_x_preferred":[
        "Fokian\u00f3"
    ],
    "name:ell_x_variant":[
        "\u03a6\u03c9\u03ba\u03b9\u03b1\u03bd\u03cc"
    ],
    "wof:name":"Fokiano",
    "wof:placetype":"locality"
},
  "geometry": {"coordinates":[22.96586,37.07318],"type":"Point"}
}