{
  "type": "Feature",
  "properties": {
    "gn:population":3466,
    "iso:country":"GR",
    "name:ara_x_preferred":[
        "\u062e\u0648\u0631\u062a\u064a\u0627\u062a\u064a\u0633"
    ],
    "name:bul_x_preferred":[
        "\u0425\u043e\u0440\u0442\u0430\u0447"
    ],
    "name:ceb_x_preferred":[
        "Chorti\u00e1tis"
    ],
    "name:deu_x_preferred":[
        "Chortiatis"
    ],
    "name:ell_x_preferred":[
        "\u03a7\u03bf\u03c1\u03c4\u03b9\u03ac\u03c4\u03b7\u03c2"
    ],
    "name:ell_x_variant":[
        "Khorti\u00e1tis",
        "Chorti\u00e1tis",
        "Chorti\u00e1ti",
        "\u03a7\u03bf\u03c1\u03c4\u03b9\u03ac\u03c4\u03b7",
        "\u03a7\u03bf\u03c1\u03c4\u03b9\u03ac\u03c4\u03b7\u03c2 \u0398\u03b5\u03c3\u03c3\u03b1\u03bb\u03bf\u03bd\u03af\u03ba\u03b7\u03c2"
    ],
    "name:eng_x_preferred":[
        "Chortiatis"
    ],
    "name:fin_x_preferred":[
        "Chorti\u00e1tis"
    ],
    "name:fra_x_preferred":[
        "Chortiatis"
    ],
    "name:ita_x_preferred":[
        "Chortiatis"
    ],
    "name:jpn_x_preferred":[
        "\u30db\u30eb\u30c6\u30a3\u30a2\u30c6\u30a3\u30b9"
    ],
    "name:mkd_x_preferred":[
        "\u0425\u043e\u0440\u0442\u0430\u0447"
    ],
    "name:nld_x_preferred":[
        "Chortiatis"
    ],
    "name:nno_x_preferred":[
        "Khorti\u00e1tis i Thessalon\u00edki"
    ],
    "name:swe_x_preferred":[
        "Chorti\u00e1tis"
    ],
    "qs:a0":"Greece",
    "qs:a1":"*\u039a\u0395\u039d\u03a4\u03a1\u0399\u039a\u0397 \u039c\u0391\u039a\u0395\u0394\u039f\u039d\u0399\u0391",
    "qs:a1_alt":"KENTRIKH MAKEDONIA",
    "qs:a1r":"0",
    "qs:a2_alt":"SERRES",
    "qs:adm0":"Greece",
    "qs:la_lc":"*",
    "qs:level":"locality",
    "qs:loc":"\u03a7\u039f\u03a1\u03a4\u0399\u0391\u03a4\u0397\u03a3",
    "qs:loc_alt":"XORTIAUS",
    "qs:pop":0,
    "qs:type":"buffered point",
    "wof:name":"\u03a7\u039f\u03a1\u03a4\u0399\u0391\u03a4\u0397\u03a3",
    "wof:placetype":"locality",
    "wof:population":3466
},
  "geometry": {"coordinates":[23.100441,40.611233],"type":"Point"}
}