{
  "type": "Feature",
  "properties": {
    "gn:country":"GR",
    "gn:fcode":"PPL",
    "gn:population":96,
    "iso:country":"GR",
    "name:ell_x_preferred":[
        "\u039a\u03bf\u03c5\u03c1\u03b5\u03bc\u03ac\u03b4\u03b9"
    ],
    "name:ell_x_variant":[
        "\u039a\u03bf\u03c5\u03c1\u03b5\u03bc\u03ac\u03b4\u03b9\u03bf\u03bd"
    ],
    "name:und_x_variant":[
        "Keram\u00e1hi"
    ],
    "qs_pg:aaroncc":"GR",
    "qs_pg:gn_country":"GR",
    "qs_pg:gn_fcode":"PPL",
    "qs_pg:gn_pop":96,
    "qs_pg:name":"Kourem\u00e1dion",
    "qs_pg:photos_9r":0,
    "qs_pg:photos_sr":0,
    "qs_pg:pop_sr":1,
    "qs_pg:qs_pg_placetype":"locality",
    "wof:name":"Kourem\u00e1dion",
    "wof:placetype":"locality",
    "wof:population":96
},
  "geometry": {"coordinates":[20.46611,39.75278],"type":"Point"}
}