{
  "type": "Feature",
  "properties": {
    "gn:admin1_code":"ESYE11",
    "gn:admin2_code":"4.0",
    "gn:admin3_code":"9001",
    "gn:asciiname":"Kalamonas",
    "gn:country_code":"GR",
    "gn:dem":54,
    "gn:feature_class":"P",
    "gn:feature_code":"PPL",
    "gn:name":"Kalam\u00f3nas",
    "gn:population":0,
    "gn:timezone":"Europe/Athens",
    "iso:country":"GR",
    "name:ell_x_preferred":[
        "\u039a\u03b1\u03bb\u03b1\u03bc\u03ce\u03bd\u03b1\u03c2"
    ],
    "name:ell_x_variant":[
        "\u039a\u03b1\u03bb\u03b1\u03bc\u03ce\u03bd"
    ],
    "name:und_x_variant":[
        "Bosin\u00f3s",
        "Kalam\u00f3nas",
        "Kalam\u00f3n"
    ],
    "wof:name":"Kalamonas",
    "wof:placetype":"locality"
},
  "geometry": {"coordinates":[24.2125,41.01188],"type":"Point"}
}