{
  "type": "Feature",
  "properties": {
    "gn:admin1_code":"ESYE43",
    "gn:admin2_code":"46.0",
    "gn:admin3_code":"9310.0",
    "gn:asciiname":"Katharon",
    "gn:country_code":"GR",
    "gn:dem":1131,
    "gn:feature_class":"P",
    "gn:feature_code":"PPL",
    "gn:name":"Kathar\u00f3n",
    "gn:population":18,
    "gn:timezone":"Europe/Athens",
    "iso:country":"GR",
    "name:ell_x_preferred":[
        "\u039a\u03b1\u03b8\u03b1\u03c1\u03cc"
    ],
    "name:eng_x_preferred":[
        "Katharo"
    ],
    "name:und_x_variant":[
        "Katharo"
    ],
    "wof:name":"Katharon",
    "wof:placetype":"locality",
    "wof:population":18
},
  "geometry": {"coordinates":[25.56619,35.14728],"type":"Point"}
}