{
  "type": "Feature",
  "properties": {
    "gn:gn_country":"GR",
    "gn:gn_fcode":"ADM3",
    "gn:gn_pop":26567,
    "gn:population":30741,
    "iso:country":"GR",
    "name:ell_x_preferred":[
        "\u0392\u03c1\u03b9\u03bb\u03b7\u03c3\u03c3\u03af\u03c9\u03bd"
    ],
    "qs_pg:aaroncc":"GR",
    "qs_pg:gn_country":"GR",
    "qs_pg:gn_fcode":"ADM3",
    "qs_pg:gn_pop":26567,
    "qs_pg:name":"Vrilissia",
    "qs_pg:name_adm0":"\u0395\u03bb\u03bb\u03ac\u03b4\u03b1",
    "qs_pg:name_adm1":"Attica",
    "qs_pg:photos":1,
    "qs_pg:photos_1k":1,
    "qs_pg:photos_9k":1,
    "qs_pg:photos_9r":4,
    "qs_pg:photos_all":196,
    "qs_pg:photos_sr":1,
    "qs_pg:pop_sr":7,
    "qs_pg:qs_pg_placetype":"localadmin",
    "qs_pg:qs_pg_placetype_gp":"LocalAdmin",
    "qs_pg:woe_adm0":23424833,
    "woe:adm0_id":23424833,
    "woe:name_adm0":"\u0395\u03bb\u03bb\u03ac\u03b4\u03b1",
    "woe:name_adm1":"Attica",
    "woe:placetype":"LocalAdmin",
    "wof:name":"Vrilissia",
    "wof:placetype":"localadmin",
    "wof:population":30741
},
  "geometry": {"coordinates":[23.83736,38.03916],"type":"Point"}
}