{
  "type": "Feature",
  "properties": {
    "gn:population":1526,
    "iso:country":"GR",
    "name:ell_x_preferred":[
        "\u0391\u03b3\u03b3\u03b5\u03bb\u03bf\u03c7\u03ce\u03c1\u03b9\u03bf\u03bd"
    ],
    "name:ell_x_variant":[
        "\u0391\u03b3\u03b3\u03b5\u03bb\u03bf\u03c7\u03ce\u03c1\u03b9"
    ],
    "name:unk_x_variant":[
        "Vet\u00edsta"
    ],
    "qs:a0":"Greece",
    "qs:a1":"*\u039a\u0395\u039d\u03a4\u03a1\u0399\u039a\u0397 \u039c\u0391\u039a\u0395\u0394\u039f\u039d\u0399\u0391",
    "qs:a1_alt":"KENTRIKH MAKEDONIA",
    "qs:a1r":"0",
    "qs:a2_alt":"HMAUIA",
    "qs:adm0":"Greece",
    "qs:la_lc":"*",
    "qs:level":"locality",
    "qs:loc":"\u0391\u0393\u0393\u0395\u039b\u039f\u03a7\u03a9\u03a1\u0399\u039f\u039d",
    "qs:loc_alt":"AGGELOXVRION",
    "qs:pop":0,
    "qs:type":"buffered point",
    "wof:name":"\u0391\u0393\u0393\u0395\u039b\u039f\u03a7\u03a9\u03a1\u0399\u039f\u039d",
    "wof:placetype":"locality",
    "wof:population":1526
},
  "geometry": {"coordinates":[22.202377,40.676045],"type":"Point"}
}