{
  "type": "Feature",
  "properties": {
    "gn:admin1_code":"ESYE42",
    "gn:admin2_code":"49.0",
    "gn:admin3_code":"9288",
    "gn:asciiname":"Avyssalos",
    "gn:country_code":"GR",
    "gn:dem":6,
    "gn:feature_class":"P",
    "gn:feature_code":"PPL",
    "gn:name":"Avyssal\u00f3s",
    "gn:population":18,
    "gn:timezone":"Europe/Athens",
    "iso:country":"GR",
    "name:ell_x_preferred":[
        "\u0391\u03b2\u03c5\u03c3\u03c3\u03b1\u03bb\u03cc\u03c2"
    ],
    "name:eng_x_preferred":[
        "Avyssalos"
    ],
    "name:und_x_variant":[
        "Avisalos",
        "Avesalos",
        "Avesal\u00f3s"
    ],
    "wof:name":"Avyssalos",
    "wof:placetype":"locality",
    "wof:population":18
},
  "geometry": {"coordinates":[24.43763,37.16367],"type":"Point"}
}