{
  "type": "Feature",
  "properties": {
    "gn:admin1_code":"ESYE43",
    "gn:admin2_code":"46.0",
    "gn:admin3_code":"9310",
    "gn:asciiname":"Flamouriana",
    "gn:country_code":"GR",
    "gn:dem":108,
    "gn:feature_class":"P",
    "gn:feature_code":"PPL",
    "gn:name":"Flamourian\u00e1",
    "gn:population":100,
    "gn:timezone":"Europe/Athens",
    "iso:country":"GR",
    "name:ell_x_preferred":[
        "\u03a6\u03bb\u03b1\u03bc\u03bf\u03c5\u03c1\u03b9\u03b1\u03bd\u03ac"
    ],
    "name:eng_x_preferred":[
        "Flamouriana"
    ],
    "name:und_x_variant":[
        "Met\u00f3khi Flamourian\u00f3",
        "Flamourian\u00f3",
        "Flamourian\u00e1"
    ],
    "wof:name":"Flamouriana",
    "wof:placetype":"locality",
    "wof:population":100
},
  "geometry": {"coordinates":[25.66199,35.18845],"type":"Point"}
}