{
  "type": "Feature",
  "properties": {
    "gn:admin1_code":"ESYE25",
    "gn:admin2_code":"36.0",
    "gn:admin3_code":"9236",
    "gn:asciiname":"Piryiotika",
    "gn:country_code":"GR",
    "gn:dem":109,
    "gn:feature_class":"P",
    "gn:feature_code":"PPL",
    "gn:name":"Piryi\u00f3tika",
    "gn:population":335,
    "gn:timezone":"Europe/Athens",
    "iso:country":"GR",
    "name:ell_x_preferred":[
        "\u03a0\u03c5\u03c1\u03b3\u03b9\u03ce\u03c4\u03b9\u03ba\u03b1"
    ],
    "name:eng_x_preferred":[
        "Pyrgiotika"
    ],
    "wof:name":"Piryiotika",
    "wof:placetype":"locality",
    "wof:population":335
},
  "geometry": {"coordinates":[22.87903,37.58152000000001],"type":"Point"}
}