{
  "type": "Feature",
  "properties": {
    "gn:gn_country":"GR",
    "gn:gn_fcode":"PPL",
    "gn:gn_pop":0,
    "iso:country":"GR",
    "qs_pg:aaroncc":"GR",
    "qs_pg:gn_country":"GR",
    "qs_pg:gn_fcode":"PPL",
    "qs_pg:gn_pop":0,
    "qs_pg:name":"Agia Paraskevi",
    "qs_pg:name_adm0":"\u0395\u03bb\u03bb\u03ac\u03b4\u03b1",
    "qs_pg:name_adm1":"Aegean",
    "qs_pg:photos":3,
    "qs_pg:photos_1k":1,
    "qs_pg:photos_9k":1,
    "qs_pg:photos_9r":1,
    "qs_pg:photos_all":3,
    "qs_pg:photos_sr":1,
    "qs_pg:pop_sr":0,
    "qs_pg:qs_pg_placetype":"locality",
    "qs_pg:qs_pg_placetype_gp":"Town",
    "qs_pg:woe_adm0":23424833,
    "woe:adm0_id":23424833,
    "woe:name_adm0":"\u0395\u03bb\u03bb\u03ac\u03b4\u03b1",
    "woe:name_adm1":"Aegean",
    "woe:placetype":"Town",
    "wof:name":"Agia Paraskevi",
    "wof:placetype":"locality"
},
  "geometry": {"coordinates":[25.48431,36.39996],"type":"Point"}
}