{
  "type": "Feature",
  "properties": {
    "gn:gn_country":"GR",
    "gn:gn_fcode":"PPL",
    "gn:gn_pop":0,
    "iso:country":"GR",
    "name:ara_x_preferred":[
        "\u0623\u063a\u064a\u0627 \u0628\u0627\u0631\u0627\u0633\u0643\u064a\u0641\u064a"
    ],
    "name:bul_x_preferred":[
        "\u0410\u0433\u0438\u044f \u041f\u0430\u0440\u0430\u0441\u043a\u0435\u0432\u0438"
    ],
    "name:ceb_x_preferred":[
        "Ag\u00eda Paraskev\u00ed"
    ],
    "name:deu_x_preferred":[
        "Agia Paraskevi"
    ],
    "name:ell_x_preferred":[
        "\u0391\u03b3\u03af\u03b1 \u03a0\u03b1\u03c1\u03b1\u03c3\u03ba\u03b5\u03c5\u03ae \u0391\u03c4\u03c4\u03b9\u03ba\u03ae\u03c2"
    ],
    "name:fas_x_preferred":[
        "\u0622\u06cc\u0647 \u0628\u0627\u0631\u0627\u0633\u06a9\u0648\u06cc"
    ],
    "name:fin_x_preferred":[
        "Ag\u00eda Paraskev\u00ed"
    ],
    "name:fra_x_preferred":[
        "Agia Paraskevi"
    ],
    "name:ita_x_preferred":[
        "Agia Paraskevi"
    ],
    "name:nld_x_preferred":[
        "Agia Paraskevi"
    ],
    "name:nno_x_preferred":[
        "Aj\u00eda Paraskev\u00ed"
    ],
    "name:pol_x_preferred":[
        "Ajia Paraskiewi"
    ],
    "name:ron_x_preferred":[
        "Agia Paraskevi"
    ],
    "name:sco_x_preferred":[
        "Agia Paraskevi"
    ],
    "name:srp_x_preferred":[
        "\u0410\u0458\u0430 \u041f\u0430\u0440\u0430\u0441\u043a\u0435\u0432\u0438"
    ],
    "name:swe_x_preferred":[
        "Ag\u00eda Paraskev\u00ed"
    ],
    "name:tur_x_preferred":[
        "Aya Paraskevi"
    ],
    "name:ukr_x_preferred":[
        "\u0410\u044f-\u041f\u0430\u0440\u0430\u0441\u043a\u0435\u0432\u0456"
    ],
    "name:urd_x_preferred":[
        "\u0622\u0626\u06cc\u0627 \u067e\u0627\u0631\u0627\u0633\u06a9\u06cc\u0648\u06cc"
    ],
    "name:vie_x_preferred":[
        "Aghia Paraskevi"
    ],
    "name:zho_x_preferred":[
        "\u5723\u5e15\u62c9\u65af\u51ef\u7ef4"
    ],
    "qs_pg:aaroncc":"GR",
    "qs_pg:gn_country":"GR",
    "qs_pg:gn_fcode":"PPL",
    "qs_pg:gn_pop":0,
    "qs_pg:name":"Agia Paraskevi",
    "qs_pg:name_adm0":"\u0395\u03bb\u03bb\u03ac\u03b4\u03b1",
    "qs_pg:name_adm1":"Aegean",
    "qs_pg:photos":3,
    "qs_pg:photos_1k":1,
    "qs_pg:photos_9k":1,
    "qs_pg:photos_9r":1,
    "qs_pg:photos_all":3,
    "qs_pg:photos_sr":1,
    "qs_pg:pop_sr":0,
    "qs_pg:qs_pg_placetype":"locality",
    "qs_pg:qs_pg_placetype_gp":"Town",
    "qs_pg:woe_adm0":23424833,
    "woe:adm0_id":23424833,
    "woe:name_adm0":"\u0395\u03bb\u03bb\u03ac\u03b4\u03b1",
    "woe:name_adm1":"Aegean",
    "woe:placetype":"Town",
    "wof:name":"Agia Paraskevi",
    "wof:placetype":"locality"
},
  "geometry": {"coordinates":[25.48431,36.39996],"type":"Point"}
}