{
  "type": "Feature",
  "properties": {
    "gn:population":2129,
    "iso:country":"GR",
    "name:ara_x_preferred":[
        "\u0641\u064a\u0644\u064a\u0627\u062a\u064a\u0633"
    ],
    "name:cat_x_preferred":[
        "Kestrine"
    ],
    "name:ceb_x_preferred":[
        "Dimos Filiates"
    ],
    "name:deu_x_preferred":[
        "Filiates"
    ],
    "name:ell_x_preferred":[
        "\u0394\u03ae\u03bc\u03bf\u03c2 \u03a6\u03b9\u03bb\u03b9\u03b1\u03c4\u03ce\u03bd"
    ],
    "name:ell_x_variant":[
        "\u03a6\u03b9\u03bb\u03b9\u03ac\u03c4\u03b5\u03c2"
    ],
    "name:eng_x_preferred":[
        "Filiates Municipality"
    ],
    "name:fin_x_preferred":[
        "Fili\u00e1tes"
    ],
    "name:fra_x_preferred":[
        "Filiates"
    ],
    "name:ita_x_preferred":[
        "Filiates"
    ],
    "name:jpn_x_preferred":[
        "\u30d5\u30a3\u30ea\u30a2\u30c6\u30b9"
    ],
    "name:nld_x_preferred":[
        "Filiates"
    ],
    "name:nno_x_preferred":[
        "Fili\u00e1tes"
    ],
    "name:pol_x_preferred":[
        "Filiates"
    ],
    "name:rus_x_preferred":[
        "\u0424\u0438\u043b\u044c\u044f\u0442\u0435"
    ],
    "name:spa_x_preferred":[
        "Filiates"
    ],
    "name:sqi_x_preferred":[
        "Filati"
    ],
    "name:swe_x_preferred":[
        "Fili\u00e1tes"
    ],
    "name:tur_x_preferred":[
        "Filat"
    ],
    "name:unk_x_variant":[
        "Fili\u00e1tes"
    ],
    "name:vie_x_preferred":[
        "Filiates"
    ],
    "qs:a0":"Greece",
    "qs:a1":"*\u0397\u03a0\u0395\u0399\u03a1\u039f\u03a3",
    "qs:a1_alt":"HPEIROS",
    "qs:a1r":"0",
    "qs:a2_alt":"UESPRVTIA",
    "qs:adm0":"Greece",
    "qs:la_lc":"*",
    "qs:level":"locality",
    "qs:loc":"\u03a6\u0399\u039b\u0399\u0391\u03a4\u0395\u03a3",
    "qs:loc_alt":"FILIATES",
    "qs:pop":0,
    "qs:type":"buffered point",
    "wd:wordcount":1057,
    "wof:name":"\u03a6\u0399\u039b\u0399\u0391\u03a4\u0395\u03a3",
    "wof:placetype":"locality",
    "wof:population":2129
},
  "geometry": {"coordinates":[20.308655,39.600692],"type":"Point"}
}