{
  "type": "Feature",
  "properties": {
    "gn:admin1_code":"ESYE11",
    "gn:admin2_code":"4.0",
    "gn:admin3_code":"9003",
    "gn:asciiname":"Dasoto",
    "gn:country_code":"GR",
    "gn:dem":624,
    "gn:feature_class":"P",
    "gn:feature_code":"PPL",
    "gn:name":"Dasot\u00f3",
    "gn:population":0,
    "gn:timezone":"Europe/Athens",
    "iso:country":"GR",
    "name:ell_x_preferred":[
        "Dasot\u00f3"
    ],
    "name:ell_x_variant":[
        "\u0394\u03b1\u03c3\u03c9\u03c4\u03cc",
        "Dasot\u00f3n",
        "\u0394\u03b1\u03c3\u03c9\u03c4\u03cc\u03bd"
    ],
    "name:und_x_variant":[
        "Kuman\u00edtsi",
        "Dhasot\u00f3n"
    ],
    "wof:name":"Dasoto",
    "wof:placetype":"locality"
},
  "geometry": {"coordinates":[23.80102,41.34693],"type":"Point"}
}