{
  "type": "Feature",
  "properties": {
    "gn:admin1_code":"ESYE24",
    "gn:admin2_code":"29.0",
    "gn:admin3_code":"9160",
    "gn:asciiname":"Kastanea",
    "gn:country_code":"GR",
    "gn:dem":1043,
    "gn:feature_class":"P",
    "gn:feature_code":"PPL",
    "gn:name":"Kastan\u00e9a",
    "gn:population":207,
    "gn:timezone":"Europe/Athens",
    "iso:country":"GR",
    "name:ell_x_preferred":[
        "\u039a\u03b1\u03c3\u03c4\u03b1\u03bd\u03ad\u03b1"
    ],
    "name:ell_x_variant":[
        "\u039a\u03b1\u03c3\u03c4\u03b1\u03bd\u03b9\u03ac"
    ],
    "name:und_x_variant":[
        "Kastani\u00e1",
        "Kastan\u00e9a"
    ],
    "wof:name":"Kastanea",
    "wof:placetype":"locality",
    "wof:population":207
},
  "geometry": {"coordinates":[22.21122,38.84736],"type":"Point"}
}