{
  "type": "Feature",
  "properties": {
    "gn:admin1_code":"ESYE23",
    "gn:admin2_code":"31.0",
    "gn:admin3_code":"9128",
    "gn:asciiname":"Ano Vasiliki",
    "gn:country_code":"GR",
    "gn:dem":132,
    "gn:feature_class":"P",
    "gn:feature_code":"PPL",
    "gn:name":"\u00c1no Vasilik\u00ed",
    "gn:population":0,
    "gn:timezone":"Europe/Athens",
    "iso:country":"GR",
    "name:ell_x_preferred":[
        "\u00c1no Vasilik\u00ed"
    ],
    "name:ell_x_variant":[
        "\u0386\u03bd\u03c9 \u0392\u03b1\u03c3\u03b9\u03bb\u03b9\u03ba\u03ae"
    ],
    "wof:name":"Ano Vasiliki",
    "wof:placetype":"locality"
},
  "geometry": {"coordinates":[21.60572,38.37772],"type":"Point"}
}