{
  "type": "Feature",
  "properties": {
    "iso:country":"GR",
    "qs:a0":"Greece",
    "qs:a1":"*\u0392\u039f\u03a1\u0395\u0399\u039f \u0391\u0399\u0393\u0391\u0399\u039f",
    "qs:a1_alt":"BOREIO AIGAIO",
    "qs:a1r":"0",
    "qs:a2_alt":"SAMOS",
    "qs:adm0":"Greece",
    "qs:la_lc":"*",
    "qs:level":"locality",
    "qs:loc":"\u03a7\u03a9\u03a1\u0391",
    "qs:loc_alt":"XVRA",
    "qs:pop":0,
    "qs:type":"buffered point",
    "wof:name":"\u03a7\u03a9\u03a1\u0391",
    "wof:placetype":"locality"
},
  "geometry": {"coordinates":[26.90477,37.703647],"type":"Point"}
}