{
  "type": "Feature",
  "properties": {
    "gn:country":"GR",
    "gn:fcode":"PPL",
    "gn:population":239,
    "iso:country":"GR",
    "name:ell_x_preferred":[
        "\u039a\u03bf\u03c5\u03c1\u03b1\u03bc\u03ac\u03b4\u03b5\u03c2"
    ],
    "name:eng_x_preferred":[
        "Kouramades"
    ],
    "name:und_x_variant":[
        "Kouram\u00e1dhes"
    ],
    "qs_pg:aaroncc":"GR",
    "qs_pg:gn_country":"GR",
    "qs_pg:gn_fcode":"PPL",
    "qs_pg:gn_pop":239,
    "qs_pg:name":"Kouram\u00e1des",
    "qs_pg:photos_9r":0,
    "qs_pg:photos_sr":0,
    "qs_pg:pop_sr":2,
    "qs_pg:qs_pg_placetype":"locality",
    "wof:name":"Kouram\u00e1des",
    "wof:placetype":"locality",
    "wof:population":255
},
  "geometry": {"coordinates":[19.85278,39.57],"type":"Point"}
}