{
  "type": "Feature",
  "properties": {
    "gn:admin1_code":"ESYE22",
    "gn:admin2_code":"27.0",
    "gn:admin3_code":"9120",
    "gn:asciiname":"Dorizata",
    "gn:country_code":"GR",
    "gn:dem":93,
    "gn:feature_class":"P",
    "gn:feature_code":"PPL",
    "gn:name":"Doriz\u00e1ta",
    "gn:population":0,
    "gn:timezone":"Europe/Athens",
    "iso:country":"GR",
    "name:ell_x_preferred":[
        "\u0394\u03bf\u03c1\u03b9\u03b6\u03ac\u03c4\u03b1"
    ],
    "name:und_x_variant":[
        "Doriz\u00e1ta",
        "Dhoriz\u00e1ta"
    ],
    "wof:name":"Dorizata",
    "wof:placetype":"locality"
},
  "geometry": {"coordinates":[20.57103,38.12072],"type":"Point"}
}