{
  "type": "Feature",
  "properties": {
    "gn:admin1_code":"ESYE23",
    "gn:admin2_code":"31.0",
    "gn:admin3_code":"9123",
    "gn:asciiname":"Strongilaiika",
    "gn:country_code":"GR",
    "gn:dem":43,
    "gn:feature_class":"P",
    "gn:feature_code":"PPL",
    "gn:name":"Strongila\u00edika",
    "gn:population":26,
    "gn:timezone":"Europe/Athens",
    "iso:country":"GR",
    "name:ell_x_preferred":[
        "\u03a3\u03c4\u03c1\u03bf\u03b3\u03b3\u03c5\u03bb\u03b1\u03af\u03b9\u03ba\u03b1"
    ],
    "name:eng_x_preferred":[
        "Strongylaiika"
    ],
    "wof:name":"Strongilaiika",
    "wof:placetype":"locality",
    "wof:population":26
},
  "geometry": {"coordinates":[21.42016,38.58709],"type":"Point"}
}