{
  "type": "Feature",
  "properties": {
    "gn:admin1_code":"ESYE13",
    "gn:admin2_code":"11.0",
    "gn:admin3_code":"9066",
    "gn:asciiname":"Boioy",
    "gn:country_code":"GR",
    "gn:dem":1018,
    "gn:feature_class":"P",
    "gn:feature_code":"PPL",
    "gn:name":"Boioy",
    "gn:population":0,
    "gn:timezone":"Europe/Athens",
    "iso:country":"GR",
    "name:und_x_variant":[
        "Anasel\u00edtsa",
        "Boioy",
        "V\u00f3\u00efon",
        "Eparkh\u00eda Vo\u1e2fou"
    ],
    "wof:name":"Boioy",
    "wof:placetype":"locality"
},
  "geometry": {"coordinates":[21.55,40.26667],"type":"Point"}
}