{
  "type": "Feature",
  "properties": {
    "gn:admin1_code":"ESYE25",
    "gn:admin2_code":"41.0",
    "gn:admin3_code":"9239",
    "gn:asciiname":"Lykaio",
    "gn:country_code":"GR",
    "gn:dem":809,
    "gn:feature_class":"P",
    "gn:feature_code":"PPL",
    "gn:name":"L\u00fdkaio",
    "gn:population":0,
    "gn:timezone":"Europe/Athens",
    "iso:country":"GR",
    "name:ell_x_preferred":[
        "L\u00fdkaio"
    ],
    "name:ell_x_variant":[
        "\u039b\u03cd\u03ba\u03b1\u03b9\u03bf",
        "L\u00fdkaion",
        "\u039b\u03cd\u03ba\u03b1\u03b9\u03bf\u03bd"
    ],
    "name:und_x_variant":[
        "Derbo\u00fani",
        "L\u00edkaion"
    ],
    "wof:name":"Lykaio",
    "wof:placetype":"locality"
},
  "geometry": {"coordinates":[22.00239,37.41457],"type":"Point"}
}