{
  "type": "Feature",
  "properties": {
    "gn:admin1_code":"ESYE11",
    "gn:admin2_code":"4.0",
    "gn:admin3_code":"9003",
    "gn:asciiname":"Delta",
    "gn:country_code":"GR",
    "gn:dem":513,
    "gn:feature_class":"P",
    "gn:feature_code":"PPL",
    "gn:name":"D\u00e9lta",
    "gn:population":0,
    "gn:timezone":"Europe/Athens",
    "iso:country":"GR",
    "name:bul_x_preferred":[
        "\u0412\u0438\u0442\u043e\u0432\u043e"
    ],
    "name:ell_x_preferred":[
        "D\u00e9lta"
    ],
    "name:ell_x_variant":[
        "\u0394\u03ad\u03bb\u03c4\u03b1"
    ],
    "name:und_x_variant":[
        "V\u00edtova",
        "Dh\u00e9lta"
    ],
    "wof:name":"Delta",
    "wof:placetype":"locality"
},
  "geometry": {"coordinates":[24.0779,41.4161],"type":"Point"}
}