{
  "type": "Feature",
  "properties": {
    "gn:gn_country":"GR",
    "gn:gn_fcode":"ADM3",
    "gn:gn_pop":18229,
    "gn:population":18229,
    "iso:country":"GR",
    "name:ell_x_preferred":[
        "\u039d\u03ac\u03be\u03bf\u03c5 & \u039c\u03b9\u03ba\u03c1\u03ce\u03bd \u039a\u03c5\u03ba\u03bb\u03ac\u03b4\u03c9\u03bd"
    ],
    "qs_pg:aaroncc":"GR",
    "qs_pg:gn_country":"GR",
    "qs_pg:gn_fcode":"ADM3",
    "qs_pg:gn_pop":18229,
    "qs_pg:name":"Dimos Naxos and Lesser Cyclades",
    "qs_pg:photos_9r":0,
    "qs_pg:photos_sr":0,
    "qs_pg:pop_sr":6,
    "qs_pg:qs_pg_placetype":"localadmin",
    "wof:name":"Dimos Naxos and Lesser Cyclades",
    "wof:placetype":"localadmin",
    "wof:population":18229
},
  "geometry": {"coordinates":[25.50046,37.04314],"type":"Point"}
}