{
  "type": "Feature",
  "properties": {
    "iso:country":"GR",
    "name:ceb_x_preferred":[
        "Polonia"
    ],
    "name:deu_x_preferred":[
        "Polonia"
    ],
    "name:epo_x_preferred":[
        "Polonia"
    ],
    "name:fra_x_preferred":[
        "Polonia"
    ],
    "name:ita_x_preferred":[
        "Polonia"
    ],
    "name:jpn_x_preferred":[
        "\u30dd\u30ed\u30cb\u30a2"
    ],
    "name:nld_x_preferred":[
        "Polonia"
    ],
    "name:pol_x_preferred":[
        "Polonia"
    ],
    "name:ron_x_preferred":[
        "Polonia"
    ],
    "name:rus_x_preferred":[
        "\u041f\u043e\u043b\u043e\u043d\u0438\u044f"
    ],
    "name:spa_x_preferred":[
        "Polonia"
    ],
    "name:swe_x_preferred":[
        "Polonia"
    ],
    "name:ukr_x_preferred":[
        "\u041f\u043e\u043b\u043e\u043d\u0456\u044f"
    ],
    "qs_pg:aaroncc":"GR",
    "qs_pg:name":"Polonia",
    "qs_pg:name_adm0":"\u0395\u03bb\u03bb\u03ac\u03b4\u03b1",
    "qs_pg:name_adm1":"Aegean",
    "qs_pg:photos":96,
    "qs_pg:photos_1k":19,
    "qs_pg:photos_9k":1,
    "qs_pg:photos_9r":3,
    "qs_pg:photos_all":96,
    "qs_pg:photos_sr":3,
    "qs_pg:pop_sr":0,
    "qs_pg:qs_pg_placetype":"locality",
    "qs_pg:qs_pg_placetype_gp":"Town",
    "qs_pg:woe_adm0":23424833,
    "woe:adm0_id":23424833,
    "woe:name_adm0":"\u0395\u03bb\u03bb\u03ac\u03b4\u03b1",
    "woe:name_adm1":"Aegean",
    "woe:placetype":"Town",
    "wof:name":"Polonia",
    "wof:placetype":"locality"
},
  "geometry": {"coordinates":[24.5229915,36.76426],"type":"Point"}
}