{
  "type": "Feature",
  "properties": {
    "gn:admin1_code":"ESYE14",
    "gn:admin2_code":"24.0",
    "gn:admin3_code":"9107",
    "gn:asciiname":"Syki",
    "gn:country_code":"GR",
    "gn:dem":290,
    "gn:feature_class":"P",
    "gn:feature_code":"PPL",
    "gn:name":"Syk\u00ed",
    "gn:population":0,
    "gn:timezone":"Europe/Athens",
    "iso:country":"GR",
    "name:ell_x_preferred":[
        "Syk\u00ed"
    ],
    "name:ell_x_variant":[
        "\u03a3\u03c5\u03ba\u03ae"
    ],
    "name:und_x_variant":[
        "Sik\u00ed"
    ],
    "wof:name":"Syki",
    "wof:placetype":"locality"
},
  "geometry": {"coordinates":[23.26064,39.28517],"type":"Point"}
}