{
  "type": "Feature",
  "properties": {
    "gn:admin1_code":"ESYE11",
    "gn:admin2_code":"2.0",
    "gn:admin3_code":"9022",
    "gn:asciiname":"Kassiteres",
    "gn:country_code":"GR",
    "gn:dem":322,
    "gn:feature_class":"P",
    "gn:feature_code":"PPL",
    "gn:name":"Kassiter\u00e9s",
    "gn:population":0,
    "gn:timezone":"Europe/Athens",
    "iso:country":"GR",
    "name:ell_x_preferred":[
        "Kassiter\u00e9s"
    ],
    "name:ell_x_variant":[
        "\u039a\u03b1\u03c3\u03c3\u03b9\u03c4\u03b5\u03c1\u03ad\u03c2",
        "\u039a\u03b1\u03c3\u03c3\u03b9\u03c4\u03b5\u03c1\u03b1\u03af"
    ],
    "name:und_x_variant":[
        "Kassitar\u00e1",
        "Kassiter\u00e1",
        "Kassitera\u00ed"
    ],
    "wof:name":"Kassiteres",
    "wof:placetype":"locality"
},
  "geometry": {"coordinates":[25.7378,40.99718],"type":"Point"}
}