{
  "type": "Feature",
  "properties": {
    "gn:admin1_code":"ESYE43",
    "gn:admin2_code":"45.0",
    "gn:admin3_code":"9303",
    "gn:asciiname":"Kastri",
    "gn:country_code":"GR",
    "gn:dem":10,
    "gn:feature_class":"P",
    "gn:feature_code":"PPL",
    "gn:name":"Kastr\u00ed",
    "gn:population":0,
    "gn:timezone":"Europe/Athens",
    "iso:country":"GR",
    "wof:name":"Kastri",
    "wof:placetype":"locality"
},
  "geometry": {"coordinates":[25.37799,34.99963],"type":"Point"}
}