{
  "type": "Feature",
  "properties": {
    "gn:admin1_code":"ESYE43",
    "gn:admin2_code":"44.0",
    "gn:admin3_code":"9317",
    "gn:asciiname":"Skepasti",
    "gn:country_code":"GR",
    "gn:dem":71,
    "gn:feature_class":"P",
    "gn:feature_code":"PPL",
    "gn:name":"Skepast\u00ed",
    "gn:population":0,
    "gn:timezone":"Europe/Athens",
    "iso:country":"GR",
    "wof:name":"Skepasti",
    "wof:placetype":"locality"
},
  "geometry": {"coordinates":[24.7231,35.41361],"type":"Point"}
}