{
  "type": "Feature",
  "properties": {
    "gn:admin1_code":"ESYE12",
    "gn:admin2_code":"15.0",
    "gn:admin3_code":"9060",
    "gn:asciiname":"Neos Marmaras",
    "gn:country_code":"GR",
    "gn:dem":12,
    "gn:feature_class":"P",
    "gn:feature_code":"PPL",
    "gn:name":"N\u00e9os Marmar\u00e1s",
    "gn:population":3158,
    "gn:timezone":"Europe/Athens",
    "iso:country":"GR",
    "name:ara_x_preferred":[
        "\u0646\u064a\u0648\u0633 \u0645\u0627\u0631\u0645\u0627\u0631\u0627\u0633"
    ],
    "name:bul_x_preferred":[
        "\u041d\u0435\u043e\u0441 \u041c\u0430\u0440\u043c\u0430\u0440\u0430\u0441"
    ],
    "name:cat_x_preferred":[
        "Neos Marmaras"
    ],
    "name:ceb_x_preferred":[
        "N\u00e9os Marmar\u00e1s"
    ],
    "name:deu_x_preferred":[
        "Neos Marmaras"
    ],
    "name:ell_x_preferred":[
        "\u039d\u03ad\u03bf\u03c2 \u039c\u03b1\u03c1\u03bc\u03b1\u03c1\u03ac\u03c2"
    ],
    "name:eng_x_preferred":[
        "Neos Marmaras"
    ],
    "name:ltz_x_preferred":[
        "Neos Marmaras"
    ],
    "name:nno_x_preferred":[
        "N\u00e9os Marmar\u00e1s"
    ],
    "name:pnt_x_preferred":[
        "\u039d\u03ad\u03bf\u03c2 \u039c\u03b1\u03c1\u03bc\u03b1\u03c1\u03ac\u03c2"
    ],
    "name:srp_x_preferred":[
        "\u041d\u0435\u043e\u0441 \u041c\u0430\u0440\u043c\u0430\u0440\u0430\u0441"
    ],
    "name:swe_x_preferred":[
        "Neos Marmaras"
    ],
    "name:tur_x_preferred":[
        "Neos Marmaras"
    ],
    "name:und_x_variant":[
        "Marmar\u00e1s"
    ],
    "wof:name":"Neos Marmaras",
    "wof:placetype":"locality",
    "wof:population":3158
},
  "geometry": {"coordinates":[23.78323,40.0961],"type":"Point"}
}