{
  "type": "Feature",
  "properties": {
    "gn:admin1_code":"ESYE12",
    "gn:admin2_code":"15.0",
    "gn:admin3_code":"9060",
    "gn:asciiname":"Neos Marmaras",
    "gn:country_code":"GR",
    "gn:dem":12,
    "gn:feature_class":"P",
    "gn:feature_code":"PPL",
    "gn:name":"N\u00e9os Marmar\u00e1s",
    "gn:population":3158,
    "gn:timezone":"Europe/Athens",
    "iso:country":"GR",
    "name:ell_x_preferred":[
        "\u039d\u03ad\u03bf\u03c2 \u039c\u03b1\u03c1\u03bc\u03b1\u03c1\u03ac\u03c2"
    ],
    "name:eng_x_preferred":[
        "Neos Marmaras"
    ],
    "name:und_x_variant":[
        "Marmar\u00e1s",
        "N\u00e9os Marmar\u00e1s"
    ],
    "wof:name":"Neos Marmaras",
    "wof:placetype":"locality",
    "wof:population":3158
},
  "geometry": {"coordinates":[23.78323,40.0961],"type":"Point"}
}