{
  "type": "Feature",
  "properties": {
    "gn:gn_country":"GR",
    "gn:gn_fcode":"PPL",
    "gn:gn_pop":58,
    "gn:population":38,
    "iso:country":"GR",
    "name:ell_x_preferred":[
        "\u0391\u03bb\u03b5\u03c0\u03bf\u03c7\u03ce\u03c1\u03b9"
    ],
    "name:ell_x_variant":[
        "Alepoch\u00f3ri",
        "\u0391\u03bb\u03b5\u03c0\u03bf\u03c7\u03ce\u03c1\u03b9\u03bf\u03bd"
    ],
    "name:eng_x_preferred":[
        "Alepochori"
    ],
    "name:unk_x_variant":[
        "Alepokh\u00f3rion"
    ],
    "qs_pg:aaroncc":"GR",
    "qs_pg:gn_country":"GR",
    "qs_pg:gn_fcode":"PPL",
    "qs_pg:gn_pop":58,
    "qs_pg:name":"Alepoch\u00f3rion",
    "qs_pg:photos_9r":0,
    "qs_pg:photos_sr":0,
    "qs_pg:pop_sr":1,
    "qs_pg:qs_pg_placetype":"locality",
    "wof:name":"Alepoch\u00f3rion",
    "wof:placetype":"locality",
    "wof:population":38
},
  "geometry": {"coordinates":[19.87139,39.55667],"type":"Point"}
}