{
  "type": "Feature",
  "properties": {
    "gn:admin1_code":"ESYE31",
    "gn:admin2_code":"445406.0",
    "gn:admin3_code":"9227.0",
    "gn:asciiname":"Kalyviza",
    "gn:country_code":"GR",
    "gn:dem":129,
    "gn:feature_class":"P",
    "gn:feature_code":"PPL",
    "gn:name":"Kal\u00fdviza",
    "gn:population":0,
    "gn:timezone":"Europe/Athens",
    "iso:country":"GR",
    "name:ell_x_preferred":[
        "Kal\u00fdviza"
    ],
    "name:ell_x_variant":[
        "\u039a\u03b1\u03bb\u03cd\u03b2\u03b9\u03b6\u03b1"
    ],
    "wof:name":"Kalyviza",
    "wof:placetype":"locality"
},
  "geometry": {"coordinates":[23.81605,38.30471],"type":"Point"}
}