{
  "type": "Feature",
  "properties": {
    "gn:admin1_code":"ESYE24",
    "gn:admin2_code":"30.0",
    "gn:admin3_code":"9157",
    "gn:asciiname":"Stefanion",
    "gn:country_code":"GR",
    "gn:dem":906,
    "gn:feature_class":"P",
    "gn:feature_code":"PPL",
    "gn:name":"Stef\u00e1nion",
    "gn:population":10,
    "gn:timezone":"Europe/Athens",
    "iso:country":"GR",
    "name:ell_x_preferred":[
        "\u03a3\u03c4\u03b5\u03c6\u03ac\u03bd\u03b9"
    ],
    "name:eng_x_preferred":[
        "Stefani"
    ],
    "name:und_x_variant":[
        "Stef\u00e1ni",
        "Stef\u00e1nion"
    ],
    "wof:name":"Stefanion",
    "wof:placetype":"locality",
    "wof:population":10
},
  "geometry": {"coordinates":[21.70124,38.88803],"type":"Point"}
}