{
  "type": "Feature",
  "properties": {
    "gn:admin1_code":"ESYE14",
    "gn:admin2_code":"24.0",
    "gn:admin3_code":"9104",
    "gn:asciiname":"Neraidha",
    "gn:country_code":"GR",
    "gn:dem":332,
    "gn:feature_class":"P",
    "gn:feature_code":"PPL",
    "gn:name":"Ner\u00e1\u00efdha",
    "gn:population":70,
    "gn:timezone":"Europe/Athens",
    "iso:country":"GR",
    "name:ell_x_preferred":[
        "\u039d\u03b5\u03c1\u03ac\u03b9\u03b4\u03b1"
    ],
    "name:ell_x_variant":[
        "\u039d\u03b5\u03c1\u03ac\u03ca\u03b4\u03b1"
    ],
    "name:eng_x_preferred":[
        "Neraida"
    ],
    "name:und_x_variant":[
        "Kelemen\u00ed",
        "Kelemen\u00edon",
        "Ner\u00e1\u00efdha"
    ],
    "wof:name":"Neraidha",
    "wof:placetype":"locality",
    "wof:population":70
},
  "geometry": {"coordinates":[22.60671,39.17224],"type":"Point"}
}