{
  "type": "Feature",
  "properties": {
    "gn:admin1_code":"ESYE13",
    "gn:admin2_code":"11.0",
    "gn:admin3_code":"9069",
    "gn:asciiname":"Neraida",
    "gn:country_code":"GR",
    "gn:dem":388,
    "gn:feature_class":"P",
    "gn:feature_code":"PPL",
    "gn:name":"Ner\u00e1ida",
    "gn:population":0,
    "gn:timezone":"Europe/Athens",
    "iso:country":"GR",
    "name:ell_x_preferred":[
        "Ner\u00e1ida"
    ],
    "name:ell_x_variant":[
        "\u039d\u03b5\u03c1\u03ac\u03b9\u03b4\u03b1"
    ],
    "name:und_x_variant":[
        "N\u00e9a Ir\u00e1klia",
        "Ner\u00e1\u00efdha"
    ],
    "wof:name":"Neraida",
    "wof:placetype":"locality"
},
  "geometry": {"coordinates":[21.96728,40.23972],"type":"Point"}
}