{
  "type": "Feature",
  "properties": {
    "gn:admin1_code":"ESYE25",
    "gn:admin2_code":"37.0",
    "gn:admin3_code":"9244.0",
    "gn:asciiname":"Ano Charvati",
    "gn:country_code":"GR",
    "gn:dem":371,
    "gn:feature_class":"P",
    "gn:feature_code":"PPL",
    "gn:name":"\u00c1no Charv\u00e1ti",
    "gn:population":0,
    "gn:timezone":"Europe/Athens",
    "iso:country":"GR",
    "name:ell_x_preferred":[
        "\u00c1no Charv\u00e1ti"
    ],
    "name:ell_x_variant":[
        "\u0386\u03bd\u03c9 \u03a7\u03b1\u03c1\u03b2\u03ac\u03c4\u03b9"
    ],
    "wof:name":"Ano Charvati",
    "wof:placetype":"locality"
},
  "geometry": {"coordinates":[23.03391,37.98424],"type":"Point"}
}