{
  "type": "Feature",
  "properties": {
    "gn:admin1_code":"ESYE25",
    "gn:admin2_code":"36.0",
    "gn:admin3_code":"9233",
    "gn:asciiname":"Mpozionelaiika",
    "gn:country_code":"GR",
    "gn:dem":228,
    "gn:feature_class":"P",
    "gn:feature_code":"PPL",
    "gn:name":"Mpozionela\u00edika",
    "gn:population":39,
    "gn:timezone":"Europe/Athens",
    "iso:country":"GR",
    "name:ell_x_preferred":[
        "\u039c\u03c0\u03bf\u03b6\u03b9\u03bf\u03bd\u03b5\u03bb\u03b1\u03af\u03b9\u03ba\u03b1"
    ],
    "name:eng_x_preferred":[
        "Mpozionelaiika"
    ],
    "wof:name":"Mpozionelaiika",
    "wof:placetype":"locality",
    "wof:population":39
},
  "geometry": {"coordinates":[22.62845,37.62467],"type":"Point"}
}