{
  "type": "Feature",
  "properties": {
    "gn:gn_country":"GR",
    "gn:gn_fcode":"PPL",
    "gn:gn_pop":222,
    "gn:population":222,
    "iso:country":"GR",
    "name:ell_x_preferred":[
        "\u03a6\u03ac\u03c1\u03c3\u03b1"
    ],
    "name:eng_x_preferred":[
        "Farsa"
    ],
    "name:nld_x_preferred":[
        "Farsa"
    ],
    "name:swe_x_preferred":[
        "F\u00e1rsa"
    ],
    "name:unk_x_variant":[
        "F\u00e1rsa"
    ],
    "qs_pg:aaroncc":"GR",
    "qs_pg:gn_country":"GR",
    "qs_pg:gn_fcode":"PPL",
    "qs_pg:gn_pop":222,
    "qs_pg:name":"Farsa",
    "qs_pg:name_adm0":"\u0395\u03bb\u03bb\u03ac\u03b4\u03b1",
    "qs_pg:name_adm1":"Peloponnese Western Greece and the Ionian Islands",
    "qs_pg:photos_9k":1,
    "qs_pg:photos_9r":1,
    "qs_pg:photos_all":2,
    "qs_pg:photos_sr":0,
    "qs_pg:pop_sr":2,
    "qs_pg:qs_pg_placetype":"locality",
    "qs_pg:qs_pg_placetype_gp":"Town",
    "qs_pg:woe_adm0":23424833,
    "woe:adm0_id":23424833,
    "woe:name_adm0":"\u0395\u03bb\u03bb\u03ac\u03b4\u03b1",
    "woe:name_adm1":"Peloponnese Western Greece and the Ionian Islands",
    "woe:placetype":"Town",
    "wof:name":"Farsa",
    "wof:placetype":"locality",
    "wof:population":222
},
  "geometry": {"coordinates":[20.48333,38.23333],"type":"Point"}
}