{
  "type": "Feature",
  "properties": {
    "gn:admin1_code":"ESYE23",
    "gn:admin2_code":"31.0",
    "gn:admin3_code":"9126",
    "gn:asciiname":"Amvrakia",
    "gn:country_code":"GR",
    "gn:dem":703,
    "gn:feature_class":"P",
    "gn:feature_code":"PPL",
    "gn:name":"Amvrak\u00eda",
    "gn:population":0,
    "gn:timezone":"Europe/Athens",
    "iso:country":"GR",
    "name:ell_x_preferred":[
        "\u0391\u03bc\u03b2\u03c1\u03b1\u03ba\u03af\u03b1"
    ],
    "name:und_x_variant":[
        "Dhrim\u00f3n Amvrakia",
        "Amvrak\u00eda"
    ],
    "wof:name":"Amvrakia",
    "wof:placetype":"locality"
},
  "geometry": {"coordinates":[21.71478,38.66561],"type":"Point"}
}