{
  "type": "Feature",
  "properties": {
    "gn:admin1_code":"ESYE43",
    "gn:admin2_code":"43.0",
    "gn:admin3_code":"9319",
    "gn:asciiname":"Machairoi",
    "gn:country_code":"GR",
    "gn:dem":109,
    "gn:feature_class":"P",
    "gn:feature_code":"PPL",
    "gn:name":"Machairo\u00ed",
    "gn:population":54,
    "gn:timezone":"Europe/Athens",
    "iso:country":"GR",
    "name:ell_x_preferred":[
        "\u039c\u03b1\u03c7\u03b1\u03b9\u03c1\u03bf\u03af"
    ],
    "name:eng_x_preferred":[
        "Machairoi"
    ],
    "wof:name":"Machairoi",
    "wof:placetype":"locality",
    "wof:population":54
},
  "geometry": {"coordinates":[24.1319,35.41382],"type":"Point"}
}