{
  "type": "Feature",
  "properties": {
    "gn:country":"GR",
    "gn:fcode":"PPL",
    "gn:population":776,
    "iso:country":"GR",
    "name:ceb_x_preferred":[
        "Giann\u00e1des"
    ],
    "name:deu_x_preferred":[
        "Giannades"
    ],
    "name:ell_x_preferred":[
        "\u0393\u03b9\u03b1\u03bd\u03bd\u03ac\u03b4\u03b5\u03c2"
    ],
    "name:ell_x_variant":[
        "\u0393\u03b9\u03b1\u03bd\u03bd\u03ac\u03b4\u03b5\u03c2 \u039a\u03ad\u03c1\u03ba\u03c5\u03c1\u03b1\u03c2"
    ],
    "name:eng_x_preferred":[
        "Giannades"
    ],
    "name:nld_x_preferred":[
        "Giannades"
    ],
    "name:swe_x_preferred":[
        "Giann\u00e1des"
    ],
    "name:und_x_variant":[
        "Yiann\u00e1dhes"
    ],
    "qs_pg:aaroncc":"GR",
    "qs_pg:gn_country":"GR",
    "qs_pg:gn_fcode":"PPL",
    "qs_pg:gn_pop":776,
    "qs_pg:name":"Giann\u00e1des",
    "qs_pg:photos_9r":0,
    "qs_pg:photos_sr":0,
    "qs_pg:pop_sr":2,
    "qs_pg:qs_pg_placetype":"locality",
    "wof:name":"Giann\u00e1des",
    "wof:placetype":"locality",
    "wof:population":565
},
  "geometry": {"coordinates":[19.75944,39.63],"type":"Point"}
}