{
  "type": "Feature",
  "properties": {
    "gn:admin1_code":"ESYE23",
    "gn:admin2_code":"31.0",
    "gn:admin3_code":"9126",
    "gn:asciiname":"Pamfion",
    "gn:cc2":"GR",
    "gn:country_code":"GR",
    "gn:dem":28,
    "gn:feature_class":"P",
    "gn:feature_code":"PPL",
    "gn:name":"P\u00e1mfion",
    "gn:population":0,
    "gn:timezone":"Europe/Athens",
    "iso:country":"GR",
    "name:und_x_variant":[
        "Go\u00fastiani"
    ],
    "wof:name":"Pamfion",
    "wof:placetype":"locality"
},
  "geometry": {"coordinates":[21.64809,38.50724],"type":"Point"}
}