{
  "type": "Feature",
  "properties": {
    "gn:admin1_code":"ESYE12",
    "gn:admin2_code":"5.0",
    "gn:admin3_code":"9050",
    "gn:asciiname":"Ivira",
    "gn:country_code":"GR",
    "gn:dem":68,
    "gn:feature_class":"P",
    "gn:feature_code":"PPL",
    "gn:name":"\u00cdvira",
    "gn:population":615,
    "gn:timezone":"Europe/Athens",
    "iso:country":"GR",
    "name:bul_x_preferred":[
        "\u0418\u0432\u0438\u0440\u0430"
    ],
    "name:ell_x_preferred":[
        "\u038a\u03b2\u03b7\u03c1\u03b1"
    ],
    "name:ell_x_variant":[
        "\u00cdvira"
    ],
    "name:eng_x_preferred":[
        "Ivira"
    ],
    "wof:name":"Ivira",
    "wof:placetype":"locality",
    "wof:population":615
},
  "geometry": {"coordinates":[23.69857,40.89537],"type":"Point"}
}