{
  "type": "Feature",
  "properties": {
    "gn:admin1_code":"ESYE25",
    "gn:admin2_code":"40.0",
    "gn:admin3_code":"9255",
    "gn:asciiname":"Spitali",
    "gn:country_code":"GR",
    "gn:dem":106,
    "gn:feature_class":"P",
    "gn:feature_code":"PPL",
    "gn:name":"Spit\u00e1li",
    "gn:population":0,
    "gn:timezone":"Europe/Athens",
    "iso:country":"GR",
    "name:bul_x_preferred":[
        "\u0421\u043f\u0438\u0442\u0430\u043b\u0438"
    ],
    "name:ceb_x_preferred":[
        "Spit\u00e1li"
    ],
    "name:ell_x_preferred":[
        "\u03a3\u03c0\u03b9\u03c4\u03ac\u03bb\u03b9"
    ],
    "name:ell_x_variant":[
        "\u03a3\u03c0\u03b9\u03c4\u03ac\u03bb\u03b9\u03bf\u03bd",
        "\u03a3\u03c0\u03b9\u03c4\u03ac\u03bb\u03b9 \u039b\u03b5\u03bc\u03b5\u03c3\u03bf\u03cd"
    ],
    "name:fra_x_preferred":[
        "Spit\u00e1li"
    ],
    "name:pol_x_preferred":[
        "Spitali"
    ],
    "name:swe_x_preferred":[
        "Spit\u00e1li"
    ],
    "name:und_x_variant":[
        "Miserliou",
        "Spit\u00e1lion"
    ],
    "wof:name":"Spitali",
    "wof:placetype":"locality"
},
  "geometry": {"coordinates":[21.95458,37.0781],"type":"Point"}
}