{
  "type": "Feature",
  "properties": {
    "gn:admin1_code":"ESYE14",
    "gn:admin2_code":"21.0",
    "gn:admin3_code":"9099",
    "gn:asciiname":"Galini",
    "gn:country_code":"GR",
    "gn:dem":68,
    "gn:feature_class":"P",
    "gn:feature_code":"PPL",
    "gn:name":"Gal\u00edni",
    "gn:population":0,
    "gn:timezone":"Europe/Athens",
    "iso:country":"GR",
    "name:ceb_x_preferred":[
        "Galini"
    ],
    "name:ell_x_preferred":[
        "Gal\u00edni"
    ],
    "name:ell_x_variant":[
        "\u0393\u03b1\u03bb\u03ae\u03bd\u03b7"
    ],
    "name:swe_x_preferred":[
        "Galini"
    ],
    "name:und_x_variant":[
        "\u00c1no Plat\u00edkambos"
    ],
    "wof:name":"Galini",
    "wof:placetype":"locality"
},
  "geometry": {"coordinates":[22.51614,39.62342],"type":"Point"}
}