{
  "type": "Feature",
  "properties": {
    "gn:admin1_code":"ESYE11",
    "gn:admin2_code":"2.0",
    "gn:admin3_code":"9021",
    "gn:asciiname":"Sarakini",
    "gn:country_code":"GR",
    "gn:dem":468,
    "gn:feature_class":"P",
    "gn:feature_code":"PPL",
    "gn:name":"Sarakin\u00ed",
    "gn:population":0,
    "gn:timezone":"Europe/Athens",
    "iso:country":"GR",
    "name:ell_x_preferred":[
        "Sarakin\u00ed"
    ],
    "name:ell_x_variant":[
        "\u03a3\u03b1\u03c1\u03b1\u03ba\u03b7\u03bd\u03ae",
        "\u03a3\u03b1\u03c1\u03b1\u03ba\u03af\u03bd\u03b9 \u0391\u03c1\u03ba\u03b1\u03b4\u03af\u03b1\u03c2"
    ],
    "name:ron_x_preferred":[
        "Sarakini"
    ],
    "wof:name":"Sarakini",
    "wof:placetype":"locality"
},
  "geometry": {"coordinates":[25.55199,41.28815],"type":"Point"}
}