{
  "type": "Feature",
  "properties": {
    "gn:admin1_code":"ESYE22",
    "gn:admin2_code":"25.0",
    "gn:admin3_code":"9119",
    "gn:asciiname":"Moungelatika",
    "gn:country_code":"GR",
    "gn:dem":69,
    "gn:feature_class":"P",
    "gn:feature_code":"PPL",
    "gn:name":"Moungel\u00e1tika",
    "gn:population":0,
    "gn:timezone":"Europe/Athens",
    "iso:country":"GR",
    "name:ell_x_preferred":[
        "\u039c\u03bf\u03c5\u03b3\u03b3\u03b5\u03bb\u03ac\u03c4\u03b9\u03ba\u03b1"
    ],
    "name:und_x_variant":[
        "Moungel\u00e1tika",
        "Moukel\u00e1tika",
        "Mougkel\u00e1tika"
    ],
    "wof:name":"Moungelatika",
    "wof:placetype":"locality"
},
  "geometry": {"coordinates":[20.14011,39.23547],"type":"Point"}
}