{
  "type": "Feature",
  "properties": {
    "gn:admin1_code":"ESYE43",
    "gn:admin2_code":"46.0",
    "gn:admin3_code":"9311",
    "gn:asciiname":"Anatoli",
    "gn:country_code":"GR",
    "gn:dem":610,
    "gn:feature_class":"P",
    "gn:feature_code":"PPL",
    "gn:name":"Anatol\u00ed",
    "gn:population":119,
    "gn:timezone":"Europe/Athens",
    "iso:country":"GR",
    "name:ell_x_preferred":[
        "\u0391\u03bd\u03b1\u03c4\u03bf\u03bb\u03ae"
    ],
    "name:eng_x_preferred":[
        "Anatoli"
    ],
    "wof:name":"Anatoli",
    "wof:placetype":"locality",
    "wof:population":119
},
  "geometry": {"coordinates":[25.64398,35.0456],"type":"Point"}
}