{
  "type": "Feature",
  "properties": {
    "gn:admin1_code":"ESYE42",
    "gn:admin2_code":"47.0",
    "gn:admin3_code":"9296",
    "gn:asciiname":"Gennadi",
    "gn:country_code":"GR",
    "gn:dem":33,
    "gn:feature_class":"P",
    "gn:feature_code":"PPL",
    "gn:name":"Gennadi",
    "gn:population":655,
    "gn:timezone":"Europe/Athens",
    "iso:country":"GR",
    "name:ceb_x_preferred":[
        "Gennadi"
    ],
    "name:deu_x_preferred":[
        "Gennadi"
    ],
    "name:ell_x_preferred":[
        "\u0393\u03b5\u03bd\u03bd\u03ac\u03b4\u03b9"
    ],
    "name:ell_x_variant":[
        "Yenn\u00e1dhion"
    ],
    "name:eng_x_preferred":[
        "Gennadi"
    ],
    "name:nno_x_preferred":[
        "Jenn\u00e1di"
    ],
    "name:pol_x_preferred":[
        "Jenadi"
    ],
    "name:swe_x_preferred":[
        "Gennadi"
    ],
    "name:tur_x_preferred":[
        "Gennadi"
    ],
    "name:und_x_variant":[
        "Iannadi",
        "Yiann\u00e1dhi",
        "Yenn\u00e1dhi",
        "Genn\u00e1dion",
        "\u0393\u03b5\u03bd\u03bd\u03ac\u03b4\u03b9\u03bf\u03bd"
    ],
    "wof:name":"Gennadi",
    "wof:placetype":"locality",
    "wof:population":655
},
  "geometry": {"coordinates":[27.92326,36.02361],"type":"Point"}
}