{
  "type": "Feature",
  "properties": {
    "gn:admin1_code":"ESYE23",
    "gn:admin2_code":"38.0",
    "gn:admin3_code":"9131",
    "gn:asciiname":"Samallikaiika",
    "gn:country_code":"GR",
    "gn:dem":28,
    "gn:feature_class":"P",
    "gn:feature_code":"PPL",
    "gn:name":"Samallika\u00edika",
    "gn:population":0,
    "gn:timezone":"Europe/Athens",
    "iso:country":"GR",
    "name:ell_x_preferred":[
        "Samallika\u00edika"
    ],
    "name:ell_x_variant":[
        "\u03a3\u03b1\u03bc\u03b1\u03bb\u03bb\u03b9\u03ba\u03b1\u03af\u03b9\u03ba\u03b1"
    ],
    "wof:name":"Samallikaiika",
    "wof:placetype":"locality"
},
  "geometry": {"coordinates":[21.47208,38.10194],"type":"Point"}
}