{
  "type": "Feature",
  "properties": {
    "gn:admin1_code":"ESYE24",
    "gn:admin2_code":"33.0",
    "gn:admin3_code":"9146",
    "gn:asciiname":"Stroviki",
    "gn:country_code":"GR",
    "gn:dem":94,
    "gn:feature_class":"P",
    "gn:feature_code":"PPL",
    "gn:name":"Strov\u00edki",
    "gn:population":0,
    "gn:timezone":"Europe/Athens",
    "iso:country":"GR",
    "name:ell_x_preferred":[
        "\u03a3\u03c4\u03c1\u03bf\u03b2\u03af\u03ba\u03b9"
    ],
    "name:ell_x_variant":[
        "\u03a3\u03c4\u03c1\u03bf\u03b2\u03af\u03ba\u03b9\u03bf\u03bd"
    ],
    "name:und_x_variant":[
        "Strov\u00edki",
        "Strov\u00edkion"
    ],
    "wof:name":"Stroviki",
    "wof:placetype":"locality"
},
  "geometry": {"coordinates":[23.10528,38.47892],"type":"Point"}
}