{
  "type": "Feature",
  "properties": {
    "gn:admin1_code":"ESYE12",
    "gn:admin2_code":"13.0",
    "gn:admin3_code":"9027",
    "gn:asciiname":"Drymia",
    "gn:country_code":"GR",
    "gn:dem":318,
    "gn:feature_class":"P",
    "gn:feature_code":"PPL",
    "gn:name":"Drymi\u00e1",
    "gn:population":0,
    "gn:timezone":"Europe/Athens",
    "iso:country":"GR",
    "name:ell_x_preferred":[
        "Drymi\u00e1"
    ],
    "name:ell_x_variant":[
        "\u0394\u03c1\u03c5\u03bc\u03b9\u03ac",
        "Dhrimi\u00e1"
    ],
    "wof:name":"Drymia",
    "wof:placetype":"locality"
},
  "geometry": {"coordinates":[23.25226,40.72359],"type":"Point"}
}