{
  "type": "Feature",
  "properties": {
    "gn:country":"GR",
    "gn:fcode":"PPL",
    "gn:population":2454,
    "iso:country":"GR",
    "name:ara_x_preferred":[
        "\u0628\u064a\u0631\u064a\u0633\u062a\u0627\u0633\u064a\u0633"
    ],
    "name:arz_x_preferred":[
        "\u0628\u064a\u0631\u064a\u0633\u062a\u0627\u0633\u064a\u0633"
    ],
    "name:ast_x_preferred":[
        "Peristasi"
    ],
    "name:bul_x_preferred":[
        "\u041f\u0435\u0440\u0438\u0441\u0442\u0430\u0441\u0438"
    ],
    "name:ceb_x_preferred":[
        "Per\u00edstasi"
    ],
    "name:ell_x_preferred":[
        "\u03a0\u03b5\u03c1\u03af\u03c3\u03c4\u03b1\u03c3\u03b9\u03c2"
    ],
    "name:ell_x_variant":[
        "\u03a0\u03b5\u03c1\u03af\u03c3\u03c4\u03b1\u03c3\u03b7",
        "\u03a0\u03b5\u03c1\u03af\u03c3\u03c4\u03b1\u03c3\u03b7 \u03a0\u03b9\u03b5\u03c1\u03af\u03b1\u03c2"
    ],
    "name:eng_x_preferred":[
        "Peristasi"
    ],
    "name:fin_x_preferred":[
        "Per\u00edstasi"
    ],
    "name:fra_x_preferred":[
        "Per\u00edstasi"
    ],
    "name:ita_x_preferred":[
        "Peristasi"
    ],
    "name:mkd_x_preferred":[
        "\u041f\u0435\u0440\u0438\u0441\u0442\u0430\u0441\u0438"
    ],
    "name:nld_x_preferred":[
        "Peristasi"
    ],
    "name:nno_x_preferred":[
        "Per\u00edstasi"
    ],
    "name:pnt_x_preferred":[
        "\u03a0\u03b5\u03c1\u03af\u03c3\u03c4\u03b1\u03c3\u03b7"
    ],
    "name:swe_x_preferred":[
        "Per\u00edstasi"
    ],
    "qs_pg:aaroncc":"GR",
    "qs_pg:gn_country":"GR",
    "qs_pg:gn_fcode":"PPL",
    "qs_pg:gn_pop":2454,
    "qs_pg:name":"Peristasi",
    "qs_pg:name_adm0":"\u0395\u03bb\u03bb\u03ac\u03b4\u03b1",
    "qs_pg:name_adm1":"Macedonia and Thrace",
    "qs_pg:photos_9k":1,
    "qs_pg:photos_9r":1,
    "qs_pg:photos_all":5,
    "qs_pg:photos_sr":0,
    "qs_pg:pop_sr":4,
    "qs_pg:qs_pg_placetype":"locality",
    "qs_pg:qs_pg_placetype_gp":"Town",
    "qs_pg:woe_adm0":23424833,
    "woe:adm0_id":23424833,
    "woe:name_adm0":"\u0395\u03bb\u03bb\u03ac\u03b4\u03b1",
    "woe:name_adm1":"Macedonia and Thrace",
    "woe:placetype":"Town",
    "wof:name":"Peristasi",
    "wof:placetype":"locality",
    "wof:population":2454
},
  "geometry": {"coordinates":[22.54111,40.27417],"type":"Point"}
}