{
  "type": "Feature",
  "properties": {
    "gn:admin1_code":"ESYE25",
    "gn:admin2_code":"41.0",
    "gn:admin3_code":"9237",
    "gn:asciiname":"Cheimerini Meligou",
    "gn:country_code":"GR",
    "gn:dem":49,
    "gn:feature_class":"P",
    "gn:feature_code":"PPL",
    "gn:name":"Cheimerin\u00ed Meligo\u00fa",
    "gn:population":0,
    "gn:timezone":"Europe/Athens",
    "iso:country":"GR",
    "name:ell_x_preferred":[
        "Cheimerin\u00ed Meligo\u00fa"
    ],
    "name:ell_x_variant":[
        "\u03a7\u03b5\u03b9\u03bc\u03b5\u03c1\u03b9\u03bd\u03ae \u039c\u03b5\u03bb\u03b9\u03b3\u03bf\u03cd"
    ],
    "name:und_x_variant":[
        "Meligo\u00fa",
        "Melingo\u00fa",
        "Khimerin\u00ed Meligo\u00fa"
    ],
    "wof:name":"Cheimerini Meligou",
    "wof:placetype":"locality"
},
  "geometry": {"coordinates":[22.72588,37.39791],"type":"Point"}
}