{
  "type": "Feature",
  "properties": {
    "gn:admin1_code":"ESYE31",
    "gn:admin2_code":"445406.0",
    "gn:admin3_code":"9226.0",
    "gn:asciiname":"Sochoria",
    "gn:country_code":"GR",
    "gn:dem":81,
    "gn:feature_class":"P",
    "gn:feature_code":"PPL",
    "gn:name":"Soch\u00f3ria",
    "gn:population":0,
    "gn:timezone":"Europe/Athens",
    "iso:country":"GR",
    "name:ell_x_preferred":[
        "Soch\u00f3ria"
    ],
    "name:ell_x_variant":[
        "\u03a3\u03c9\u03c7\u03ce\u03c1\u03b9\u03b1"
    ],
    "wof:name":"Sochoria",
    "wof:placetype":"locality"
},
  "geometry": {"coordinates":[23.98214,37.98571],"type":"Point"}
}