{
  "type": "Feature",
  "properties": {
    "gn:gn_country":"GR",
    "gn:gn_fcode":"PPL",
    "gn:gn_pop":69470,
    "iso:country":"GR",
    "name:ara_x_preferred":[
        "\u0645\u0627\u0631\u0648\u0633\u064a"
    ],
    "name:arz_x_preferred":[
        "\u0645\u0627\u0631\u0648\u0633\u0649"
    ],
    "name:bul_x_preferred":[
        "\u041c\u0430\u0440\u0443\u0441\u0438"
    ],
    "name:cat_x_preferred":[
        "Marousi"
    ],
    "name:ceb_x_preferred":[
        "Maro\u00fasi"
    ],
    "name:cym_x_preferred":[
        "Marousi"
    ],
    "name:dan_x_preferred":[
        "Marousi"
    ],
    "name:deu_x_preferred":[
        "Marousi"
    ],
    "name:ell_x_preferred":[
        "\u039c\u03b1\u03c1\u03bf\u03cd\u03c3\u03b9"
    ],
    "name:eng_x_preferred":[
        "Marousi"
    ],
    "name:fas_x_preferred":[
        "\u0645\u0627\u0631\u0648\u0633\u06cc"
    ],
    "name:fin_x_preferred":[
        "Amaro\u00fasio"
    ],
    "name:fra_x_preferred":[
        "Maro\u00fassi"
    ],
    "name:heb_x_preferred":[
        "\u05de\u05d0\u05e8\u05d5\u05e1\u05d9"
    ],
    "name:hun_x_preferred":[
        "Amar\u00faszi"
    ],
    "name:hye_x_preferred":[
        "\u0531\u0574\u0561\u0580\u0578\u0582\u057d\u056b\u0578\u0576"
    ],
    "name:ita_x_preferred":[
        "Amarousio"
    ],
    "name:jpn_x_preferred":[
        "\u30de\u30eb\u30fc\u30b7"
    ],
    "name:lit_x_preferred":[
        "Amarusijas"
    ],
    "name:nld_x_preferred":[
        "Amarousio"
    ],
    "name:nno_x_preferred":[
        "Maro\u00fasi"
    ],
    "name:pol_x_preferred":[
        "Marusi"
    ],
    "name:por_x_preferred":[
        "Marusi"
    ],
    "name:ron_x_preferred":[
        "Amarousion"
    ],
    "name:rus_x_preferred":[
        "\u0410\u043c\u0430\u0440\u0443\u0441\u0438\u043e\u043d"
    ],
    "name:sco_x_preferred":[
        "Marousi"
    ],
    "name:slv_x_preferred":[
        "Marousi"
    ],
    "name:spa_x_preferred":[
        "Marusi"
    ],
    "name:srp_x_preferred":[
        "\u041c\u0430\u0440\u0443\u0441\u0438"
    ],
    "name:swe_x_preferred":[
        "Maro\u00fasi"
    ],
    "name:tur_x_preferred":[
        "Marusi"
    ],
    "name:ukr_x_preferred":[
        "\u041c\u0430\u0440\u0443\u0441\u0456"
    ],
    "name:urd_x_preferred":[
        "\u0645\u0627\u0631\u0624\u0633\u06cc"
    ],
    "name:vie_x_preferred":[
        "Marousi"
    ],
    "name:zho_x_preferred":[
        "\u963f\u9a6c\u9c81\u897f\u5965"
    ],
    "qs_pg:aaroncc":"GR",
    "qs_pg:gn_country":"GR",
    "qs_pg:gn_fcode":"PPL",
    "qs_pg:gn_pop":69470,
    "qs_pg:name":"Marousi",
    "qs_pg:name_adm0":"\u0395\u03bb\u03bb\u03ac\u03b4\u03b1",
    "qs_pg:name_adm1":"Attica",
    "qs_pg:photos":323,
    "qs_pg:photos_1k":65,
    "qs_pg:photos_9k":1,
    "qs_pg:photos_9r":5,
    "qs_pg:photos_all":323,
    "qs_pg:photos_sr":5,
    "qs_pg:pop_sr":8,
    "qs_pg:qs_pg_placetype":"locality",
    "qs_pg:qs_pg_placetype_gp":"Town",
    "qs_pg:woe_adm0":23424833,
    "woe:adm0_id":23424833,
    "woe:name_adm0":"\u0395\u03bb\u03bb\u03ac\u03b4\u03b1",
    "woe:name_adm1":"Attica",
    "woe:placetype":"Town",
    "wof:name":"Marousi",
    "wof:placetype":"locality",
    "wof:population":69470
},
  "geometry": {"coordinates":[23.806,38.05404],"type":"Point"}
}