{
  "type": "Feature",
  "properties": {
    "gn:country":"GR",
    "gn:fcode":"ADM3",
    "gn:population":15410,
    "iso:country":"GR",
    "name:ell_x_preferred":[
        "\u0396\u03b7\u03c1\u03bf\u03cd"
    ],
    "qs_pg:aaroncc":"GR",
    "qs_pg:gn_country":"GR",
    "qs_pg:gn_fcode":"ADM3",
    "qs_pg:gn_pop":15410,
    "qs_pg:name":"Dimos Ziros",
    "qs_pg:photos_9r":0,
    "qs_pg:photos_sr":0,
    "qs_pg:pop_sr":6,
    "qs_pg:qs_pg_placetype":"localadmin",
    "wof:name":"Dimos Ziros",
    "wof:placetype":"localadmin",
    "wof:population":15410
},
  "geometry": {"coordinates":[20.84097,39.28318],"type":"Point"}
}