{
  "type": "Feature",
  "properties": {
    "gn:admin1_code":"ESYE24",
    "gn:admin2_code":"32.0",
    "gn:admin3_code":"9166",
    "gn:asciiname":"Paralia Sergoulas",
    "gn:cc2":"GR",
    "gn:country_code":"GR",
    "gn:dem":5,
    "gn:feature_class":"P",
    "gn:feature_code":"PPL",
    "gn:name":"Paral\u00eda Sergo\u00falas",
    "gn:population":0,
    "gn:timezone":"Europe/Athens",
    "iso:country":"GR",
    "name:und_x_variant":[
        "Milos",
        "Sk\u00e1la S\u00e9rgoulas",
        "Paral\u00eda Sergo\u00falas"
    ],
    "wof:name":"Paralia Sergoulas",
    "wof:placetype":"locality"
},
  "geometry": {"coordinates":[22.05621,38.39283],"type":"Point"}
}