{
  "type": "Feature",
  "properties": {
    "gn:admin1_code":"ESYE24",
    "gn:admin2_code":"29.0",
    "gn:admin3_code":"9162",
    "gn:asciiname":"Palaiokastro",
    "gn:country_code":"GR",
    "gn:dem":787,
    "gn:feature_class":"P",
    "gn:feature_code":"PPL",
    "gn:name":"Palai\u00f3kastro",
    "gn:population":74,
    "gn:timezone":"Europe/Athens",
    "iso:country":"GR",
    "name:ceb_x_preferred":[
        "Palaiokastro"
    ],
    "name:ell_x_preferred":[
        "\u03a0\u03b1\u03bb\u03b1\u03b9\u03cc\u03ba\u03b1\u03c3\u03c4\u03c1\u03bf"
    ],
    "name:ell_x_variant":[
        "\u03a0\u03b1\u03bb\u03b1\u03b9\u03cc\u03ba\u03b1\u03c3\u03c4\u03c1\u03bf\u03bd",
        "Palai\u00f3kastro"
    ],
    "name:eng_x_preferred":[
        "Palaiokastro"
    ],
    "name:fra_x_preferred":[
        "Palaiokastro"
    ],
    "name:ita_x_preferred":[
        "Paleocastro"
    ],
    "name:por_x_preferred":[
        "Paleocastro"
    ],
    "name:swe_x_preferred":[
        "Palaiokastro"
    ],
    "name:und_x_variant":[
        "Palai\u00f3kastron"
    ],
    "wof:name":"Palaiokastro",
    "wof:placetype":"locality",
    "wof:population":74
},
  "geometry": {"coordinates":[21.89932,38.98323],"type":"Point"}
}