{
  "type": "Feature",
  "properties": {
    "gn:admin1_code":"ESYE12",
    "gn:admin2_code":"5.0",
    "gn:admin3_code":"9049",
    "gn:asciiname":"Nea Fyli",
    "gn:country_code":"GR",
    "gn:dem":212,
    "gn:feature_class":"P",
    "gn:feature_code":"PPL",
    "gn:name":"N\u00e9a Fyl\u00ed",
    "gn:population":170,
    "gn:timezone":"Europe/Athens",
    "iso:country":"GR",
    "name:ell_x_preferred":[
        "\u039d\u03ad\u03b1 \u03a6\u03c5\u03bb\u03ae"
    ],
    "name:ell_x_variant":[
        "N\u00e9a Fyl\u00ed",
        "N\u00e9a Fil\u00ed"
    ],
    "name:eng_x_preferred":[
        "Nea Fyli"
    ],
    "wof:name":"Nea Fyli",
    "wof:placetype":"locality",
    "wof:population":170
},
  "geometry": {"coordinates":[23.92555,40.87036],"type":"Point"}
}