{
  "type": "Feature",
  "properties": {
    "gn:admin1_code":"ESYE43",
    "gn:admin2_code":"46.0",
    "gn:admin3_code":"9313",
    "gn:asciiname":"Lydia",
    "gn:country_code":"GR",
    "gn:dem":64,
    "gn:feature_class":"P",
    "gn:feature_code":"PPL",
    "gn:name":"L\u00fddia",
    "gn:population":0,
    "gn:timezone":"Europe/Athens",
    "iso:country":"GR",
    "name:ell_x_preferred":[
        "L\u00fddia"
    ],
    "name:ell_x_variant":[
        "\u039b\u03cd\u03b4\u03b9\u03b1"
    ],
    "wof:name":"Lydia",
    "wof:placetype":"locality"
},
  "geometry": {"coordinates":[26.23486,35.1936],"type":"Point"}
}