{
  "type": "Feature",
  "properties": {
    "gn:admin1_code":"ESYE23",
    "gn:admin2_code":"31.0",
    "gn:admin3_code":"9123",
    "gn:asciiname":"Varia",
    "gn:country_code":"GR",
    "gn:dem":24,
    "gn:feature_class":"P",
    "gn:feature_code":"PPL",
    "gn:name":"Vari\u00e1",
    "gn:population":126,
    "gn:timezone":"Europe/Athens",
    "iso:country":"GR",
    "name:ell_x_preferred":[
        "\u0392\u03b1\u03c1\u03b5\u03b9\u03ac"
    ],
    "name:eng_x_preferred":[
        "Vareia"
    ],
    "wof:name":"Varia",
    "wof:placetype":"locality",
    "wof:population":126
},
  "geometry": {"coordinates":[21.58322,38.59584],"type":"Point"}
}