{
  "type": "Feature",
  "properties": {
    "gn:admin1_code":"ESYE23",
    "gn:admin2_code":"38.0",
    "gn:admin3_code":"9133",
    "gn:asciiname":"Michas",
    "gn:country_code":"GR",
    "gn:dem":910,
    "gn:feature_class":"P",
    "gn:feature_code":"PPL",
    "gn:name":"M\u00edchas",
    "gn:population":0,
    "gn:timezone":"Europe/Athens",
    "iso:country":"GR",
    "name:ell_x_preferred":[
        "M\u00edchas"
    ],
    "name:ell_x_variant":[
        "\u039c\u03af\u03c7\u03b1\u03c2"
    ],
    "name:und_x_variant":[
        "Ayia Marina",
        "Th\u00e9retron M\u00edkha"
    ],
    "wof:name":"Michas",
    "wof:placetype":"locality"
},
  "geometry": {"coordinates":[21.88983,38.02064],"type":"Point"}
}