{
  "type": "Feature",
  "properties": {
    "gn:gn_country":"GR",
    "gn:gn_fcode":"PPL",
    "gn:gn_pop":317,
    "gn:population":317,
    "iso:country":"GR",
    "name:bul_x_preferred":[
        "\u041f\u0440\u0430\u0441\u0438\u043d\u0430\u0434\u0430"
    ],
    "name:dut_x_preferred":[
        "Prasinada"
    ],
    "name:ell_x_preferred":[
        "\u03a0\u03c1\u03b1\u03c3\u03b9\u03bd\u03ac\u03b4\u03b1"
    ],
    "name:eng_x_preferred":[
        "Prasinada"
    ],
    "name:gre_x_preferred":[
        "\u03a0\u03c1\u03b1\u03c3\u03b9\u03bd\u03ac\u03b4\u03b1 \u0397\u03bc\u03b1\u03b8\u03af\u03b1\u03c2"
    ],
    "name:mac_x_preferred":[
        "\u0413\u043e\u043b\u0435\u043c\u043e \u0410\u043b\u0430\u0431\u043e\u0440"
    ],
    "name:swe_x_preferred":[
        "Prasin\u00e1da"
    ],
    "name:unk_x_variant":[
        "M\u00e9ga Al\u00e1mboron"
    ],
    "qs_pg:aaroncc":"GR",
    "qs_pg:gn_country":"GR",
    "qs_pg:gn_fcode":"PPL",
    "qs_pg:gn_pop":317,
    "qs_pg:name":"Prasinadha",
    "qs_pg:name_adm0":"\u0395\u03bb\u03bb\u03ac\u03b4\u03b1",
    "qs_pg:name_adm1":"Macedonia and Thrace",
    "qs_pg:photos_9r":0,
    "qs_pg:photos_sr":0,
    "qs_pg:pop_sr":2,
    "qs_pg:qs_pg_placetype":"locality",
    "qs_pg:qs_pg_placetype_gp":"Town",
    "qs_pg:woe_adm0":23424833,
    "woe:adm0_id":23424833,
    "woe:name_adm0":"\u0395\u03bb\u03bb\u03ac\u03b4\u03b1",
    "woe:name_adm1":"Macedonia and Thrace",
    "woe:placetype":"Town",
    "wof:name":"Prasinadha",
    "wof:placetype":"locality",
    "wof:population":317
},
  "geometry": {"coordinates":[22.51454,40.56106],"type":"Point"}
}