{
  "type": "Feature",
  "properties": {
    "gn:admin1_code":"ESYE31",
    "gn:admin2_code":"445406.0",
    "gn:admin3_code":"9218.0",
    "gn:asciiname":"Agios Georgios",
    "gn:country_code":"GR",
    "gn:dem":89,
    "gn:feature_class":"P",
    "gn:feature_code":"PPL",
    "gn:name":"\u00c1gios Ge\u00f3rgios",
    "gn:population":0,
    "gn:timezone":"Europe/Athens",
    "iso:country":"GR",
    "name:bul_x_preferred":[
        "\u0410\u0433\u0438\u043e\u0441 \u0413\u0435\u043e\u0440\u0433\u0438\u043e\u0441"
    ],
    "name:ceb_x_preferred":[
        "Agios Georgios"
    ],
    "name:deu_x_preferred":[
        "Agios Georgios"
    ],
    "name:ell_x_preferred":[
        "\u00c1gios Ge\u00f3rgios"
    ],
    "name:ell_x_variant":[
        "\u0386\u03b3\u03b9\u03bf\u03c2 \u0393\u03b5\u03ce\u03c1\u03b3\u03b9\u03bf\u03c2"
    ],
    "name:fin_x_preferred":[
        "\u00c1gios Ge\u00f3rgios"
    ],
    "name:fra_x_preferred":[
        "Agios Georgios"
    ],
    "name:hye_x_preferred":[
        "\u0531\u0575\u0578\u057d \u0535\u0578\u0580\u0563\u056b\u0578\u057d"
    ],
    "name:ita_x_preferred":[
        "Agios Georgios"
    ],
    "name:spa_x_preferred":[
        "Agios Georgios"
    ],
    "name:swe_x_preferred":[
        "Agios Georgios"
    ],
    "wof:name":"Agios Georgios",
    "wof:placetype":"locality"
},
  "geometry": {"coordinates":[23.88101,37.8447],"type":"Point"}
}