{
  "type": "Feature",
  "properties": {
    "gn:gn_country":"GR",
    "gn:gn_fcode":"PPL",
    "gn:gn_pop":0,
    "iso:country":"GR",
    "name:cat_x_preferred":[
        "Plaka"
    ],
    "name:deu_x_preferred":[
        "Plaka"
    ],
    "name:ell_x_preferred":[
        "Pl\u00e1ka"
    ],
    "name:ell_x_variant":[
        "\u03a0\u03bb\u03ac\u03ba\u03b1"
    ],
    "name:epo_x_preferred":[
        "Plaka"
    ],
    "name:fin_x_preferred":[
        "Pl\u00e1ka"
    ],
    "name:fra_x_preferred":[
        "Pl\u00e1ka"
    ],
    "name:grc_x_preferred":[
        "Prasiai"
    ],
    "name:grc_x_variant":[
        "\u03a0\u03c1\u03b1\u03c3\u03b9\u03b1\u03b9"
    ],
    "name:ita_x_preferred":[
        "Plaka"
    ],
    "name:kor_x_preferred":[
        "\ud50c\ub77c\uce74"
    ],
    "name:lat_x_preferred":[
        "Placa"
    ],
    "name:nld_x_preferred":[
        "Plaka"
    ],
    "name:nno_x_preferred":[
        "Pl\u00e1ka"
    ],
    "name:nor_x_preferred":[
        "Plaka"
    ],
    "name:pol_x_preferred":[
        "Plaka"
    ],
    "name:por_x_preferred":[
        "Plaka"
    ],
    "name:rus_x_preferred":[
        "\u041f\u043b\u0430\u043a\u0430"
    ],
    "name:spa_x_preferred":[
        "Plaka"
    ],
    "name:swe_x_preferred":[
        "Plaka"
    ],
    "name:tur_x_preferred":[
        "Plaka"
    ],
    "name:ukr_x_preferred":[
        "\u041f\u043b\u0430\u043a\u0430"
    ],
    "name:zho_x_preferred":[
        "\u666e\u62c9\u5361"
    ],
    "qs_pg:aaroncc":"GR",
    "qs_pg:gn_country":"GR",
    "qs_pg:gn_fcode":"PPL",
    "qs_pg:gn_pop":0,
    "qs_pg:name":"Plaka",
    "qs_pg:name_adm0":"\u0395\u03bb\u03bb\u03ac\u03b4\u03b1",
    "qs_pg:name_adm1":"Peloponnese Western Greece and the Ionian Islands",
    "qs_pg:photos":39,
    "qs_pg:photos_1k":8,
    "qs_pg:photos_9k":1,
    "qs_pg:photos_9r":2,
    "qs_pg:photos_all":39,
    "qs_pg:photos_sr":2,
    "qs_pg:pop_sr":0,
    "qs_pg:qs_pg_placetype":"locality",
    "qs_pg:qs_pg_placetype_gp":"Town",
    "qs_pg:woe_adm0":23424833,
    "woe:adm0_id":23424833,
    "woe:name_adm0":"\u0395\u03bb\u03bb\u03ac\u03b4\u03b1",
    "woe:name_adm1":"Peloponnese Western Greece and the Ionian Islands",
    "woe:placetype":"Town",
    "wof:name":"Plaka",
    "wof:placetype":"locality"
},
  "geometry": {"coordinates":[22.89334,37.14818],"type":"Point"}
}