{
  "type": "Feature",
  "properties": {
    "gn:admin1_code":"ESYE24",
    "gn:admin2_code":"30.0",
    "gn:admin3_code":"9157",
    "gn:asciiname":"Kalesmenon",
    "gn:country_code":"GR",
    "gn:dem":537,
    "gn:feature_class":"P",
    "gn:feature_code":"PPL",
    "gn:name":"Kalesm\u00e9non",
    "gn:population":77,
    "gn:timezone":"Europe/Athens",
    "iso:country":"GR",
    "name:ell_x_preferred":[
        "\u039a\u03b1\u03bb\u03b5\u03c3\u03bc\u03ad\u03bd\u03bf"
    ],
    "name:ell_x_variant":[
        "\u039a\u03b1\u03bb\u03b5\u03c3\u03bc\u03ad\u03bd\u03bf \u0395\u03c5\u03c1\u03c5\u03c4\u03b1\u03bd\u03af\u03b1\u03c2"
    ],
    "name:eng_x_preferred":[
        "Kalesmeno"
    ],
    "name:und_x_variant":[
        "Kalesmeno"
    ],
    "wof:name":"Kalesmenon",
    "wof:placetype":"locality",
    "wof:population":77
},
  "geometry": {"coordinates":[21.70916,38.93678],"type":"Point"}
}