{
  "type": "Feature",
  "properties": {
    "gn:gn_country":"GR",
    "gn:gn_fcode":"PPLA3",
    "gn:gn_pop":43525,
    "gn:population":46899,
    "iso:country":"GR",
    "name:ara_x_preferred":[
        "\u0623\u063a\u0631\u064a\u0646\u064a\u0648"
    ],
    "name:bod_x_preferred":[
        "\u0f68\u0f42\u0f0b\u0f62\u0f72\u0f0b\u0f53\u0f72\u0f60\u0f7c\u0f0d"
    ],
    "name:bul_x_preferred":[
        "\u0410\u0433\u0440\u0438\u043d\u0438\u043e"
    ],
    "name:cat_x_preferred":[
        "Agr\u00ednion"
    ],
    "name:ceb_x_preferred":[
        "Agr\u00ednio"
    ],
    "name:deu_x_preferred":[
        "Agrinio"
    ],
    "name:ell_x_preferred":[
        "\u0391\u03b3\u03c1\u03af\u03bd\u03b9\u03bf"
    ],
    "name:ell_x_variant":[
        "\u0391\u03b3\u03c1\u03af\u03bd\u03b9\u03bf\u03bd"
    ],
    "name:eng_x_preferred":[
        "Agrinio"
    ],
    "name:epo_x_preferred":[
        "Agrinio"
    ],
    "name:eus_x_preferred":[
        "Agrinio"
    ],
    "name:fas_x_preferred":[
        "\u0622\u06af\u0631\u06cc\u0646\u06cc\u0648"
    ],
    "name:fin_x_preferred":[
        "Agr\u00ednio"
    ],
    "name:fra_x_preferred":[
        "Agr\u00ednio"
    ],
    "name:heb_x_preferred":[
        "\u05d0\u05d2\u05e8\u05d9\u05e0\u05d9\u05d5"
    ],
    "name:hye_x_preferred":[
        "\u0531\u0563\u0580\u056b\u0576\u056b\u0578\u0576"
    ],
    "name:ind_x_preferred":[
        "Agrinio"
    ],
    "name:ita_x_preferred":[
        "Agrinio"
    ],
    "name:jpn_x_preferred":[
        "\u30a2\u30b0\u30ea\u30cb\u30aa"
    ],
    "name:kor_x_preferred":[
        "\uc544\uadf8\ub9ac\ub2c8\uc624"
    ],
    "name:lat_x_preferred":[
        "Agrinium"
    ],
    "name:lav_x_preferred":[
        "Agrinja"
    ],
    "name:lit_x_preferred":[
        "Agrinijas"
    ],
    "name:nld_x_preferred":[
        "Agrinion"
    ],
    "name:nno_x_preferred":[
        "Agr\u00ednio"
    ],
    "name:pol_x_preferred":[
        "Agrinio"
    ],
    "name:ron_x_preferred":[
        "Agrinion"
    ],
    "name:rus_x_preferred":[
        "\u0410\u0433\u0440\u0438\u043d\u0438\u043e\u043d"
    ],
    "name:spa_x_preferred":[
        "Agrinio"
    ],
    "name:srp_x_preferred":[
        "\u0410\u0433\u0440\u0438\u043d\u0438\u043e\u043d"
    ],
    "name:swe_x_preferred":[
        "Agrinio"
    ],
    "name:tur_x_preferred":[
        "Agrinio"
    ],
    "name:ukr_x_preferred":[
        "\u0410\u0433\u0440\u0456\u043d\u0456\u043e\u043d"
    ],
    "name:unk_x_variant":[
        "Agr\u00ednio"
    ],
    "name:urd_x_preferred":[
        "\u0627\u06af\u0631\u06cc\u0646\u06cc\u0648"
    ],
    "name:vie_x_preferred":[
        "Agrinio"
    ],
    "qs_pg:aaroncc":"GR",
    "qs_pg:gn_country":"GR",
    "qs_pg:gn_fcode":"PPLA3",
    "qs_pg:gn_pop":43525,
    "qs_pg:name":"Agrinio",
    "qs_pg:name_adm0":"\u0395\u03bb\u03bb\u03ac\u03b4\u03b1",
    "qs_pg:name_adm1":"Peloponnese Western Greece and the Ionian Islands",
    "qs_pg:photos_9k":1,
    "qs_pg:photos_9r":4,
    "qs_pg:photos_all":156,
    "qs_pg:photos_sr":0,
    "qs_pg:pop_sr":8,
    "qs_pg:qs_pg_placetype":"localadmin",
    "qs_pg:qs_pg_placetype_gp":"LocalAdmin",
    "qs_pg:woe_adm0":23424833,
    "woe:adm0_id":23424833,
    "woe:name_adm0":"\u0395\u03bb\u03bb\u03ac\u03b4\u03b1",
    "woe:name_adm1":"Peloponnese Western Greece and the Ionian Islands",
    "woe:placetype":"LocalAdmin",
    "wof:name":"Agrinio",
    "wof:placetype":"localadmin",
    "wof:population":46899
},
  "geometry": {"coordinates":[21.40778,38.62139],"type":"Point"}
}