{
  "type": "Feature",
  "properties": {
    "gn:gn_country":"GR",
    "gn:gn_fcode":"PPLA3",
    "gn:gn_pop":43525,
    "gn:population":46899,
    "iso:country":"GR",
    "name:cat_x_preferred":[
        "Agr\u00ednion"
    ],
    "name:deu_x_preferred":[
        "Agrinio"
    ],
    "name:ell_x_preferred":[
        "\u0391\u03b3\u03c1\u03af\u03bd\u03b9\u03bf"
    ],
    "name:ell_x_variant":[
        "\u0391\u03b3\u03c1\u03af\u03bd\u03b9\u03bf\u03bd"
    ],
    "name:eng_x_preferred":[
        "Agrinio"
    ],
    "name:ita_x_preferred":[
        "Agrinio"
    ],
    "name:lat_x_preferred":[
        "Agrinium"
    ],
    "name:nld_x_preferred":[
        "Agrinion"
    ],
    "name:pol_x_preferred":[
        "Agrinio"
    ],
    "name:ron_x_preferred":[
        "Agrinion"
    ],
    "name:rus_x_preferred":[
        "\u0410\u0433\u0440\u0438\u043d\u0438\u043e\u043d"
    ],
    "name:unk_x_variant":[
        "Agr\u00ednio"
    ],
    "qs_pg:aaroncc":"GR",
    "qs_pg:gn_country":"GR",
    "qs_pg:gn_fcode":"PPLA3",
    "qs_pg:gn_pop":43525,
    "qs_pg:name":"Agrinio",
    "qs_pg:name_adm0":"\u0395\u03bb\u03bb\u03ac\u03b4\u03b1",
    "qs_pg:name_adm1":"Peloponnese Western Greece and the Ionian Islands",
    "qs_pg:photos_9k":1,
    "qs_pg:photos_9r":4,
    "qs_pg:photos_all":156,
    "qs_pg:photos_sr":0,
    "qs_pg:pop_sr":8,
    "qs_pg:qs_pg_placetype":"localadmin",
    "qs_pg:qs_pg_placetype_gp":"LocalAdmin",
    "qs_pg:woe_adm0":23424833,
    "woe:adm0_id":23424833,
    "woe:name_adm0":"\u0395\u03bb\u03bb\u03ac\u03b4\u03b1",
    "woe:name_adm1":"Peloponnese Western Greece and the Ionian Islands",
    "woe:placetype":"LocalAdmin",
    "wof:name":"Agrinio",
    "wof:placetype":"localadmin",
    "wof:population":46899
},
  "geometry": {"coordinates":[21.40778,38.62139],"type":"Point"}
}