{
  "type": "Feature",
  "properties": {
    "gn:admin1_code":"ESYE11",
    "gn:admin2_code":"1.0",
    "gn:admin3_code":"9006",
    "gn:asciiname":"Doriko",
    "gn:country_code":"GR",
    "gn:dem":84,
    "gn:feature_class":"P",
    "gn:feature_code":"PPL",
    "gn:name":"Dorik\u00f3",
    "gn:population":0,
    "gn:timezone":"Europe/Athens",
    "iso:country":"GR",
    "name:ell_x_preferred":[
        "Dorik\u00f3"
    ],
    "name:ell_x_variant":[
        "\u0394\u03c9\u03c1\u03b9\u03ba\u03cc",
        "Dhorik\u00f3n",
        "Dorik\u00f3n",
        "\u0394\u03c9\u03c1\u03b9\u03ba\u03cc\u03bd"
    ],
    "wof:name":"Doriko",
    "wof:placetype":"locality"
},
  "geometry": {"coordinates":[25.97986,40.90811],"type":"Point"}
}