{
  "type": "Feature",
  "properties": {
    "gn:admin1_code":"ESYE24",
    "gn:admin2_code":"30.0",
    "gn:admin3_code":"9156",
    "gn:asciiname":"Gefyraki",
    "gn:country_code":"GR",
    "gn:dem":858,
    "gn:feature_class":"P",
    "gn:feature_code":"PPL",
    "gn:name":"Gefyr\u00e1ki",
    "gn:population":0,
    "gn:timezone":"Europe/Athens",
    "iso:country":"GR",
    "name:ell_x_preferred":[
        "\u0393\u03b5\u03c6\u03c5\u03c1\u03ac\u03ba\u03b9"
    ],
    "name:und_x_variant":[
        "Yefir\u00e1ki",
        "Gefyr\u00e1ki"
    ],
    "wof:name":"Gefyraki",
    "wof:placetype":"locality"
},
  "geometry": {"coordinates":[21.63814,39.09047],"type":"Point"}
}