{
  "type": "Feature",
  "properties": {
    "gn:gn_fcode":"PPL",
    "gn:gn_pop":0,
    "iso:country":"GR",
    "name:ara_x_preferred":[
        "\u0623\u0643\u0631\u0648\u062a\u064a\u0631\u064a"
    ],
    "name:bel_x_preferred":[
        "\u0410\u043a\u0440\u0430\u0442\u044b\u0440\u044b"
    ],
    "name:cat_x_preferred":[
        "Akrotiri"
    ],
    "name:deu_x_preferred":[
        "Akrotiri"
    ],
    "name:ell_x_preferred":[
        "\u0391\u03ba\u03c1\u03c9\u03c4\u03ae\u03c1\u03b9"
    ],
    "name:ell_x_variant":[
        "\u0391\u03ba\u03c1\u03c9\u03c4\u03ae\u03c1\u03b9 \u0398\u03ae\u03c1\u03b1\u03c2"
    ],
    "name:eng_x_preferred":[
        "Akrotiri"
    ],
    "name:fas_x_preferred":[
        "santorini"
    ],
    "name:fin_x_preferred":[
        "Akrot\u00edri"
    ],
    "name:fra_x_preferred":[
        "Akrotiri"
    ],
    "name:glg_x_preferred":[
        "Akrotiri"
    ],
    "name:ita_x_preferred":[
        "Akrotiri"
    ],
    "name:jpn_x_preferred":[
        "\u30a2\u30af\u30ed\u30c6\u30a3\u30ea"
    ],
    "name:lat_x_preferred":[
        "Acroterium"
    ],
    "name:nld_x_preferred":[
        "Akrotiri"
    ],
    "name:nob_x_preferred":[
        "Akrotiri"
    ],
    "name:pol_x_preferred":[
        "Akrotiri"
    ],
    "name:por_x_preferred":[
        "Acrot\u00edri"
    ],
    "name:rus_x_preferred":[
        "\u0410\u043a\u0440\u043e\u0442\u0438\u0440\u0438"
    ],
    "name:slv_x_preferred":[
        "Akrotiri"
    ],
    "name:spa_x_preferred":[
        "Acrotiri"
    ],
    "name:swe_x_preferred":[
        "Akrotiri"
    ],
    "name:unk_x_variant":[
        "Akrot\u00edrion"
    ],
    "qs_pg:aaroncc":"GR",
    "qs_pg:gn_fcode":"PPL",
    "qs_pg:gn_pop":0,
    "qs_pg:name":"Akrotiri",
    "qs_pg:name_adm0":"\u0395\u03bb\u03bb\u03ac\u03b4\u03b1",
    "qs_pg:name_adm1":"Aegean",
    "qs_pg:photos":567,
    "qs_pg:photos_1k":115,
    "qs_pg:photos_9k":3,
    "qs_pg:photos_9r":5,
    "qs_pg:photos_all":567,
    "qs_pg:photos_sr":8,
    "qs_pg:pop_sr":0,
    "qs_pg:qs_pg_placetype":"locality",
    "qs_pg:qs_pg_placetype_gp":"Town",
    "qs_pg:woe_adm0":23424833,
    "woe:adm0_id":23424833,
    "woe:name_adm0":"\u0395\u03bb\u03bb\u03ac\u03b4\u03b1",
    "woe:name_adm1":"Aegean",
    "woe:placetype":"Town",
    "wof:name":"Akrotiri",
    "wof:placetype":"locality"
},
  "geometry": {"coordinates":[25.372581,36.360174],"type":"Point"}
}