{
  "type": "Feature",
  "properties": {
    "gn:admin1_code":"ESYE12",
    "gn:admin2_code":"13.0",
    "gn:admin3_code":"9027",
    "gn:asciiname":"Vamvakia",
    "gn:country_code":"GR",
    "gn:dem":141,
    "gn:feature_class":"P",
    "gn:feature_code":"PPL",
    "gn:name":"Vamvaki\u00e1",
    "gn:population":0,
    "gn:timezone":"Europe/Athens",
    "iso:country":"GR",
    "name:ell_x_preferred":[
        "Vamvaki\u00e1"
    ],
    "name:ell_x_variant":[
        "\u0392\u03b1\u03bc\u03b2\u03b1\u03ba\u03b9\u03ac"
    ],
    "wof:name":"Vamvakia",
    "wof:placetype":"locality"
},
  "geometry": {"coordinates":[23.61023,40.68896],"type":"Point"}
}