{
  "type": "Feature",
  "properties": {
    "gn:admin1_code":"ESYE25",
    "gn:admin2_code":"42.0",
    "gn:admin3_code":"9250",
    "gn:asciiname":"Sotiraiika",
    "gn:country_code":"GR",
    "gn:dem":160,
    "gn:feature_class":"P",
    "gn:feature_code":"PPL",
    "gn:name":"Sotira\u00edika",
    "gn:population":0,
    "gn:timezone":"Europe/Athens",
    "iso:country":"GR",
    "name:ell_x_preferred":[
        "Sotira\u00edika"
    ],
    "name:ell_x_variant":[
        "\u03a3\u03c9\u03c4\u03b7\u03c1\u03b1\u03af\u03b9\u03ba\u03b1"
    ],
    "name:und_x_variant":[
        "Sotir\u00e9ika"
    ],
    "wof:name":"Sotiraiika",
    "wof:placetype":"locality"
},
  "geometry": {"coordinates":[22.72142,36.89287],"type":"Point"}
}