{
  "type": "Feature",
  "properties": {
    "gn:admin1_code":"ESYE25",
    "gn:admin2_code":"36.0",
    "gn:admin3_code":"9233",
    "gn:asciiname":"Kefalari",
    "gn:country_code":"GR",
    "gn:dem":21,
    "gn:feature_class":"P",
    "gn:feature_code":"PPL",
    "gn:name":"Kefal\u00e1ri",
    "gn:population":677,
    "gn:timezone":"Europe/Athens",
    "iso:country":"GR",
    "name:deu_x_preferred":[
        "Kefalari"
    ],
    "name:ell_x_preferred":[
        "\u039a\u03b5\u03c6\u03b1\u03bb\u03ac\u03c1\u03b9"
    ],
    "name:eng_x_preferred":[
        "Kefalari"
    ],
    "name:und_x_variant":[
        "Kefal\u00e1ri",
        "Kefal\u00e1rion"
    ],
    "wof:name":"Kefalari",
    "wof:placetype":"locality",
    "wof:population":677
},
  "geometry": {"coordinates":[22.69114,37.59852],"type":"Point"}
}