{
  "type": "Feature",
  "properties": {
    "gn:country":"GR",
    "gn:fcode":"PPL",
    "gn:population":196,
    "iso:country":"GR",
    "name:ell_x_preferred":[
        "\u039b\u03cc\u03c6\u03bf\u03c2"
    ],
    "name:und_x_variant":[
        "K\u00e1to Filippa\u00edoi"
    ],
    "qs_pg:aaroncc":"GR",
    "qs_pg:gn_country":"GR",
    "qs_pg:gn_fcode":"PPL",
    "qs_pg:gn_pop":196,
    "qs_pg:name":"Lofos",
    "qs_pg:name_adm0":"\u0395\u03bb\u03bb\u03ac\u03b4\u03b1",
    "qs_pg:name_adm1":"Thessaly and Continental Greece",
    "qs_pg:photos_9r":0,
    "qs_pg:photos_sr":0,
    "qs_pg:pop_sr":1,
    "qs_pg:qs_pg_placetype":"locality",
    "qs_pg:qs_pg_placetype_gp":"Town",
    "qs_pg:woe_adm0":23424833,
    "woe:adm0_id":23424833,
    "woe:name_adm0":"\u0395\u03bb\u03bb\u03ac\u03b4\u03b1",
    "woe:name_adm1":"Thessaly and Continental Greece",
    "woe:placetype":"Town",
    "wof:name":"Lofos",
    "wof:placetype":"locality",
    "wof:population":196
},
  "geometry": {"coordinates":[22.17944,40.01472],"type":"Point"}
}