{
  "type": "Feature",
  "properties": {
    "gn:admin1_code":"ESYE22",
    "gn:admin2_code":"25.0",
    "gn:admin3_code":"9118",
    "gn:asciiname":"Agios Martinos",
    "gn:country_code":"GR",
    "gn:dem":173,
    "gn:feature_class":"P",
    "gn:feature_code":"PPL",
    "gn:name":"Agios Mart\u00ednos",
    "gn:population":110,
    "gn:timezone":"Europe/Athens",
    "iso:country":"GR",
    "name:ell_x_preferred":[
        "\u0386\u03b3\u03b9\u03bf\u03c2 \u039c\u03b1\u03c1\u03c4\u03af\u03bd\u03bf\u03c2"
    ],
    "name:eng_x_preferred":[
        "Agios Martinos"
    ],
    "wof:name":"Agios Martinos",
    "wof:placetype":"locality",
    "wof:population":110
},
  "geometry": {"coordinates":[19.84787,39.78819],"type":"Point"}
}