{
  "type": "Feature",
  "properties": {
    "gn:admin1_code":"ESYE25",
    "gn:admin2_code":"41.0",
    "gn:admin3_code":"9239",
    "gn:asciiname":"Anavryto",
    "gn:country_code":"GR",
    "gn:dem":690,
    "gn:feature_class":"P",
    "gn:feature_code":"PPL",
    "gn:name":"Anavryt\u00f3",
    "gn:population":0,
    "gn:timezone":"Europe/Athens",
    "iso:country":"GR",
    "name:ell_x_preferred":[
        "Anavryt\u00f3"
    ],
    "name:ell_x_variant":[
        "\u0391\u03bd\u03b1\u03b2\u03c1\u03c5\u03c4\u03cc",
        "Anavryt\u00f3n",
        "\u0391\u03bd\u03b1\u03b2\u03c1\u03c5\u03c4\u03cc\u03bd"
    ],
    "name:und_x_variant":[
        "Anavrit\u00f3n",
        "\u00c1no Anavrit\u00f3n"
    ],
    "wof:name":"Anavryto",
    "wof:placetype":"locality"
},
  "geometry": {"coordinates":[22.23493,37.34034000000001],"type":"Point"}
}