{
  "type": "Feature",
  "properties": {
    "gn:admin1_code":"ESYE25",
    "gn:admin2_code":"41.0",
    "gn:admin3_code":"9238",
    "gn:asciiname":"Rados",
    "gn:country_code":"GR",
    "gn:dem":1193,
    "gn:feature_class":"P",
    "gn:feature_code":"PPL",
    "gn:name":"R\u00e1dos",
    "gn:population":0,
    "gn:timezone":"Europe/Athens",
    "iso:country":"GR",
    "name:ell_x_preferred":[
        "R\u00e1dos"
    ],
    "name:ell_x_variant":[
        "\u03a1\u03ac\u03b4\u03bf\u03c2"
    ],
    "name:und_x_variant":[
        "R\u00e1dhon",
        "R\u00e1dhos"
    ],
    "wof:name":"Rados",
    "wof:placetype":"locality"
},
  "geometry": {"coordinates":[22.10001,37.61647],"type":"Point"}
}