{
  "type": "Feature",
  "properties": {
    "gn:admin1_code":"ESYE41",
    "gn:asciiname":"Therma",
    "gn:country_code":"GR",
    "gn:dem":17,
    "gn:feature_class":"P",
    "gn:feature_code":"PPL",
    "gn:name":"Th\u00e9rma",
    "gn:population":0,
    "gn:timezone":"Europe/Athens",
    "iso:country":"GR",
    "name:ell_x_preferred":[
        "Th\u00e9rma"
    ],
    "name:ell_x_variant":[
        "\u0398\u03ad\u03c1\u03bc\u03b1"
    ],
    "wof:name":"Therma",
    "wof:placetype":"locality"
},
  "geometry": {"coordinates":[26.30452,37.62399],"type":"Point"}
}