{
  "type": "Feature",
  "properties": {
    "gn:admin1_code":"ESYE41",
    "gn:asciiname":"Therma",
    "gn:country_code":"GR",
    "gn:dem":17,
    "gn:feature_class":"P",
    "gn:feature_code":"PPL",
    "gn:name":"Th\u00e9rma",
    "gn:population":0,
    "gn:timezone":"Europe/Athens",
    "iso:country":"GR",
    "name:ara_x_preferred":[
        "\u062b\u064a\u0631\u0645\u0627"
    ],
    "name:cat_x_preferred":[
        "Therma"
    ],
    "name:ell_x_preferred":[
        "Th\u00e9rma"
    ],
    "name:ell_x_variant":[
        "\u0398\u03ad\u03c1\u03bc\u03b1"
    ],
    "name:fin_x_preferred":[
        "Therme"
    ],
    "name:heb_x_preferred":[
        "\u05ea\u05e8\u05de\u05d4"
    ],
    "name:ita_x_preferred":[
        "Therma"
    ],
    "name:lit_x_preferred":[
        "Term\u0117"
    ],
    "name:mkd_x_preferred":[
        "\u0422\u0435\u0440\u043c\u0430"
    ],
    "name:spa_x_preferred":[
        "Terma"
    ],
    "wof:name":"Therma",
    "wof:placetype":"locality"
},
  "geometry": {"coordinates":[26.30452,37.62399],"type":"Point"}
}