{
  "type": "Feature",
  "properties": {
    "gn:admin1_code":"ESYE43",
    "gn:admin2_code":"45.0",
    "gn:admin3_code":"9302",
    "gn:asciiname":"Khoudhetsion",
    "gn:country_code":"GR",
    "gn:dem":446,
    "gn:feature_class":"P",
    "gn:feature_code":"PPL",
    "gn:name":"Khoudh\u00e9tsion",
    "gn:population":0,
    "gn:timezone":"Europe/Athens",
    "iso:country":"GR",
    "name:ell_x_preferred":[
        "\u03a7\u03bf\u03c5\u03b4\u03ad\u03c4\u03c3\u03b9"
    ],
    "name:eng_x_preferred":[
        "Choudetsi"
    ],
    "name:und_x_variant":[
        "Houdetsi"
    ],
    "wof:name":"Khoudhetsion",
    "wof:placetype":"locality"
},
  "geometry": {"coordinates":[25.17852,35.1931],"type":"Point"}
}