{
  "type": "Feature",
  "properties": {
    "gn:admin1_code":"ESYE25",
    "gn:admin2_code":"41.0",
    "gn:admin3_code":"9238",
    "gn:asciiname":"Doxa",
    "gn:country_code":"GR",
    "gn:dem":615,
    "gn:feature_class":"P",
    "gn:feature_code":"PPL",
    "gn:name":"D\u00f3xa",
    "gn:population":0,
    "gn:timezone":"Europe/Athens",
    "iso:country":"GR",
    "name:bul_x_preferred":[
        "\u0414\u043e\u043a\u0441\u0430"
    ],
    "name:cat_x_preferred":[
        "Doxa"
    ],
    "name:ces_x_preferred":[
        "Doxa"
    ],
    "name:dan_x_preferred":[
        "Doxa"
    ],
    "name:deu_x_preferred":[
        "Doxa"
    ],
    "name:ell_x_preferred":[
        "D\u00f3xa"
    ],
    "name:ell_x_variant":[
        "\u0394\u03cc\u03be\u03b1"
    ],
    "name:est_x_preferred":[
        "Doxa"
    ],
    "name:fas_x_preferred":[
        "\u062f\u0648\u06a9\u0633\u0627"
    ],
    "name:fra_x_preferred":[
        "Doxa"
    ],
    "name:hun_x_preferred":[
        "Doxa"
    ],
    "name:ita_x_preferred":[
        "Doxa"
    ],
    "name:jpn_x_preferred":[
        "\u30c9\u30af\u30b5"
    ],
    "name:pol_x_preferred":[
        "Doksa"
    ],
    "name:por_x_preferred":[
        "Doxa"
    ],
    "name:rus_x_preferred":[
        "\u0414\u043e\u043a\u0441\u0430"
    ],
    "name:slk_x_preferred":[
        "Doxa"
    ],
    "name:slv_x_preferred":[
        "D\u00f3xa"
    ],
    "name:spa_x_preferred":[
        "Doxa"
    ],
    "name:swe_x_preferred":[
        "Doxa"
    ],
    "name:tur_x_preferred":[
        "Doxa"
    ],
    "name:und_x_variant":[
        "Veretebo\u00fa",
        "Vertebo\u00faga",
        "Vredebo\u00faga",
        "Dh\u00f3xa"
    ],
    "wof:name":"Doxa",
    "wof:placetype":"locality"
},
  "geometry": {"coordinates":[21.92169,37.70713],"type":"Point"}
}