{
  "type": "Feature",
  "properties": {
    "gn:admin1_code":"ESYE25",
    "gn:admin2_code":"41.0",
    "gn:admin3_code":"9238",
    "gn:asciiname":"Doxa",
    "gn:country_code":"GR",
    "gn:dem":615,
    "gn:feature_class":"P",
    "gn:feature_code":"PPL",
    "gn:name":"D\u00f3xa",
    "gn:population":0,
    "gn:timezone":"Europe/Athens",
    "iso:country":"GR",
    "name:ell_x_preferred":[
        "D\u00f3xa"
    ],
    "name:ell_x_variant":[
        "\u0394\u03cc\u03be\u03b1"
    ],
    "name:und_x_variant":[
        "Veretebo\u00fa",
        "Vertebo\u00faga",
        "Vredebo\u00faga",
        "Dh\u00f3xa"
    ],
    "wof:name":"Doxa",
    "wof:placetype":"locality"
},
  "geometry": {"coordinates":[21.92169,37.70713],"type":"Point"}
}