{
  "type": "Feature",
  "properties": {
    "gn:country":"GR",
    "gn:fcode":"PPL",
    "gn:population":180,
    "iso:country":"GR",
    "name:ell_x_preferred":[
        "\u03a6\u03b1\u03bd\u03ac\u03c1\u03b9"
    ],
    "name:ell_x_variant":[
        "\u03a6\u03b1\u03bd\u03ac\u03c1\u03b9\u03bf\u03bd"
    ],
    "name:und_x_variant":[
        "Fan\u00e1ri"
    ],
    "qs_pg:aaroncc":"GR",
    "qs_pg:gn_country":"GR",
    "qs_pg:gn_fcode":"PPL",
    "qs_pg:gn_pop":180,
    "qs_pg:name":"Fan\u00e1rion",
    "qs_pg:photos_9r":0,
    "qs_pg:photos_sr":0,
    "qs_pg:pop_sr":1,
    "qs_pg:qs_pg_placetype":"locality",
    "wof:name":"Fan\u00e1rion",
    "wof:placetype":"locality",
    "wof:population":180
},
  "geometry": {"coordinates":[22.95639,40.89444],"type":"Point"}
}