{
  "type": "Feature",
  "properties": {
    "gn:admin1_code":"ESYE25",
    "gn:admin2_code":"42.0",
    "gn:admin3_code":"9248",
    "gn:asciiname":"Episkopi",
    "gn:country_code":"GR",
    "gn:dem":117,
    "gn:feature_class":"P",
    "gn:feature_code":"PPL",
    "gn:name":"Episkop\u00ed",
    "gn:population":0,
    "gn:timezone":"Europe/Athens",
    "iso:country":"GR",
    "name:ceb_x_preferred":[
        "Episkop\u00ed"
    ],
    "name:deu_x_preferred":[
        "Episkopi"
    ],
    "name:fin_x_preferred":[
        "Episkop\u00ed"
    ],
    "name:pol_x_preferred":[
        "Episkopi"
    ],
    "name:swe_x_preferred":[
        "Episkopi"
    ],
    "wof:name":"Episkopi",
    "wof:placetype":"locality"
},
  "geometry": {"coordinates":[22.38446,36.5318],"type":"Point"}
}