{
  "type": "Feature",
  "properties": {
    "iso:country":"GR",
    "name:deu_x_preferred":[
        "Flugplatz Kastelli"
    ],
    "name:eng_x_preferred":[
        "Kastelli Airport"
    ],
    "name:eng_x_variant":[
        "LGTL"
    ],
    "name:jpn_x_preferred":[
        "\u30ab\u30b9\u30c6\u30ea\u7a7a\u8ecd\u57fa\u5730"
    ],
    "name:msa_x_preferred":[
        "Lapangan Terbang Kasteli AB"
    ],
    "name:ron_x_preferred":[
        "Aeroportul Kastelli"
    ],
    "oa:elevation_ft":"1180",
    "oa:type":"small_airport",
    "wd:wordcount":497,
    "woe:hierarchy":{
        "country_id":23424833,
        "county_id":12591114,
        "localadmin_id":24543962,
        "planet_id":1,
        "state_id":12577885
    },
    "wof:name":"Kasteli Airport",
    "wof:placetype":"campus"
},
  "geometry": {"coordinates":[25.329167,35.193055],"type":"Point"}
}