{
  "type": "Feature",
  "properties": {
    "gn:admin1_code":"ESYE24",
    "gn:admin2_code":"34.0",
    "gn:admin3_code":"9151",
    "gn:asciiname":"Zacharia",
    "gn:country_code":"GR",
    "gn:dem":334,
    "gn:feature_class":"P",
    "gn:feature_code":"PPL",
    "gn:name":"Zachari\u00e1",
    "gn:population":0,
    "gn:timezone":"Europe/Athens",
    "iso:country":"GR",
    "name:ell_x_preferred":[
        "Zachari\u00e1"
    ],
    "name:ell_x_variant":[
        "\u0396\u03b1\u03c7\u03b1\u03c1\u03b9\u03ac"
    ],
    "name:und_x_variant":[
        "Zakh\u00f3ria",
        "Zakhari\u00e1"
    ],
    "wof:name":"Zacharia",
    "wof:placetype":"locality"
},
  "geometry": {"coordinates":[24.55506,38.10914],"type":"Point"}
}