{
  "type": "Feature",
  "properties": {
    "gn:admin1_code":"ESYE25",
    "gn:admin2_code":"41.0",
    "gn:admin3_code":"9238",
    "gn:asciiname":"Anaziri",
    "gn:country_code":"GR",
    "gn:dem":135,
    "gn:feature_class":"P",
    "gn:feature_code":"PPL",
    "gn:name":"Anaz\u00edri",
    "gn:population":0,
    "gn:timezone":"Europe/Athens",
    "iso:country":"GR",
    "name:ell_x_preferred":[
        "\u0391\u03bd\u03b1\u03b6\u03ae\u03c1\u03b7"
    ],
    "name:und_x_variant":[
        "\u00c9va",
        "Anaz\u00edri"
    ],
    "wof:name":"Anaziri",
    "wof:placetype":"locality"
},
  "geometry": {"coordinates":[21.8927,37.60565],"type":"Point"}
}