{
  "type": "Feature",
  "properties": {
    "gn:admin1_code":"ESYE12",
    "gn:admin2_code":"13.0",
    "gn:admin3_code":"9027",
    "gn:asciiname":"Xiropotamos",
    "gn:country_code":"GR",
    "gn:dem":364,
    "gn:feature_class":"P",
    "gn:feature_code":"PPL",
    "gn:name":"Xirop\u00f3tamos",
    "gn:population":0,
    "gn:timezone":"Europe/Athens",
    "iso:country":"GR",
    "name:ell_x_preferred":[
        "\u039e\u03b7\u03c1\u03bf\u03c0\u03cc\u03c4\u03b1\u03bc\u03bf\u03c2"
    ],
    "name:und_x_variant":[
        "No\u00fadha",
        "Xirop\u00f3tamos"
    ],
    "wof:name":"Xiropotamos",
    "wof:placetype":"locality"
},
  "geometry": {"coordinates":[23.48393,40.76271],"type":"Point"}
}