{
  "type": "Feature",
  "properties": {
    "gn:admin1_code":"ESYE22",
    "gn:admin2_code":"25.0",
    "gn:admin3_code":"9119",
    "gn:asciiname":"Kalodhikatika",
    "gn:country_code":"GR",
    "gn:dem":49,
    "gn:feature_class":"P",
    "gn:feature_code":"PPL",
    "gn:name":"Kalodhik\u00e1tika",
    "gn:population":0,
    "gn:timezone":"Europe/Athens",
    "iso:country":"GR",
    "wof:name":"Kalodhikatika",
    "wof:placetype":"locality"
},
  "geometry": {"coordinates":[20.13333,39.23333],"type":"Point"}
}