{
  "type": "Feature",
  "properties": {
    "gn:admin1_code":"ESYE13",
    "gn:admin2_code":"10.0",
    "gn:admin3_code":"9061",
    "gn:asciiname":"Despotis",
    "gn:country_code":"GR",
    "gn:dem":669,
    "gn:feature_class":"P",
    "gn:feature_code":"PPL",
    "gn:name":"Desp\u00f3tis",
    "gn:population":0,
    "gn:timezone":"Europe/Athens",
    "iso:country":"GR",
    "name:bul_x_preferred":[
        "\u0414\u0435\u0441\u043f\u043e\u0442\u0438\u0441"
    ],
    "name:ell_x_preferred":[
        "Desp\u00f3tis"
    ],
    "name:ell_x_variant":[
        "\u0394\u03b5\u03c3\u03c0\u03cc\u03c4\u03b7\u03c2",
        "\u0394\u03b5\u03c3\u03c0\u03cc\u03c4\u03b7\u03c2 \u0393\u03c1\u03b5\u03b2\u03b5\u03bd\u03ce\u03bd"
    ],
    "name:mkd_x_preferred":[
        "\u0421\u043d\u0438\u0445\u043e\u0432\u043e"
    ],
    "name:und_x_variant":[
        "Sin\u00edkhovon",
        "Dhesp\u00f3tis"
    ],
    "wof:name":"Despotis",
    "wof:placetype":"locality"
},
  "geometry": {"coordinates":[21.42981,40.01172],"type":"Point"}
}