{
  "type": "Feature",
  "properties": {
    "gn:admin1_code":"ESYE25",
    "gn:admin2_code":"40.0",
    "gn:admin3_code":"9254",
    "gn:asciiname":"Akovitika",
    "gn:country_code":"GR",
    "gn:dem":4,
    "gn:feature_class":"P",
    "gn:feature_code":"PPL",
    "gn:name":"Akov\u00edtika",
    "gn:population":0,
    "gn:timezone":"Europe/Athens",
    "iso:country":"GR",
    "name:ell_x_preferred":[
        "Akov\u00edtika"
    ],
    "name:ell_x_variant":[
        "\u0391\u03ba\u03bf\u03b2\u03af\u03c4\u03b9\u03ba\u03b1"
    ],
    "wof:name":"Akovitika",
    "wof:placetype":"locality"
},
  "geometry": {"coordinates":[22.08131,37.03639],"type":"Point"}
}