{
  "type": "Feature",
  "properties": {
    "gn:admin1_code":"ESYE23",
    "gn:admin2_code":"31.0",
    "gn:admin3_code":"9125.0",
    "gn:asciiname":"Maraneli",
    "gn:country_code":"GR",
    "gn:dem":183,
    "gn:feature_class":"P",
    "gn:feature_code":"PPL",
    "gn:name":"Maraneli",
    "gn:population":0,
    "gn:timezone":"Europe/Athens",
    "iso:country":"GR",
    "name:ell_x_preferred":[
        "\u039c\u03b1\u03c1\u03b1\u03bd\u03ad\u03bb\u03b9"
    ],
    "wof:name":"Maraneli",
    "wof:placetype":"locality"
},
  "geometry": {"coordinates":[21.35661,38.91559],"type":"Point"}
}