{
  "type": "Feature",
  "properties": {
    "gn:admin1_code":"ESYE12",
    "gn:admin2_code":"13.0",
    "gn:admin3_code":"9030",
    "gn:asciiname":"Ano Scholari",
    "gn:country_code":"GR",
    "gn:dem":177,
    "gn:feature_class":"P",
    "gn:feature_code":"PPL",
    "gn:name":"\u00c1no Schol\u00e1ri",
    "gn:population":178,
    "gn:timezone":"Europe/Athens",
    "iso:country":"GR",
    "name:ell_x_preferred":[
        "\u0386\u03bd\u03c9 \u03a3\u03c7\u03bf\u03bb\u03ac\u03c1\u03b9"
    ],
    "name:ell_x_variant":[
        "\u00c1no Schol\u00e1ri",
        "\u00c1no Schol\u00e1rion",
        "\u0386\u03bd\u03c9 \u03a3\u03c7\u03bf\u03bb\u03ac\u03c1\u03b9\u03bf\u03bd"
    ],
    "name:eng_x_preferred":[
        "Ano Scholari"
    ],
    "name:und_x_variant":[
        "Skhol\u00e1rion",
        "Basisl\u00ed",
        "\u00c1no Skhol\u00e1rion"
    ],
    "wof:name":"Ano Scholari",
    "wof:placetype":"locality",
    "wof:population":178
},
  "geometry": {"coordinates":[23.00242,40.4668],"type":"Point"}
}