{
  "type": "Feature",
  "properties": {
    "gn:admin1_code":"ESYE14",
    "gn:admin2_code":"24.0",
    "gn:admin3_code":"9110",
    "gn:asciiname":"Kolios",
    "gn:country_code":"GR",
    "gn:dem":1,
    "gn:feature_class":"P",
    "gn:feature_code":"PPL",
    "gn:name":"Kolios",
    "gn:population":0,
    "gn:timezone":"Europe/Athens",
    "iso:country":"GR",
    "wof:name":"Kolios",
    "wof:placetype":"locality"
},
  "geometry": {"coordinates":[23.44685,39.14063],"type":"Point"}
}