{
  "type": "Feature",
  "properties": {
    "gn:admin1_code":"ESYE43",
    "gn:admin2_code":"43.0",
    "gn:admin3_code":"9319",
    "gn:asciiname":"Asprosikia",
    "gn:country_code":"GR",
    "gn:dem":53,
    "gn:feature_class":"P",
    "gn:feature_code":"PPL",
    "gn:name":"Asprosiki\u00e1",
    "gn:population":0,
    "gn:timezone":"Europe/Athens",
    "iso:country":"GR",
    "wof:name":"Asprosikia",
    "wof:placetype":"locality"
},
  "geometry": {"coordinates":[24.25095,35.35371],"type":"Point"}
}