{
  "type": "Feature",
  "properties": {
    "gn:gn_country":"GR",
    "gn:gn_fcode":"PPL",
    "gn:gn_pop":1214,
    "gn:population":1214,
    "iso:country":"GR",
    "name:ara_x_preferred":[
        "\u0643\u0627\u0633\u062a\u0627\u0646\u064a\u064a\u060c \u0625\u0641\u0631\u0648\u0633"
    ],
    "name:ara_x_variant":[
        "\u0643\u0627\u0633\u062a\u0627\u0646\u064a\u064a"
    ],
    "name:bul_x_preferred":[
        "\u0427\u0435\u0440\u0435\u043a\u044c\u043e\u0439"
    ],
    "name:ceb_x_preferred":[
        "Kastani\u00e9s"
    ],
    "name:ell_x_preferred":[
        "\u039a\u03b1\u03c3\u03c4\u03b1\u03bd\u03ad\u03b1\u03b9"
    ],
    "name:ell_x_variant":[
        "\u039a\u03b1\u03c3\u03c4\u03b1\u03bd\u03b9\u03ad\u03c2",
        "\u039a\u03b1\u03c3\u03c4\u03b1\u03bd\u03b9\u03ad\u03c2 \u0388\u03b2\u03c1\u03bf\u03c5"
    ],
    "name:eng_x_preferred":[
        "Kastanies"
    ],
    "name:est_x_preferred":[
        "Kastani\u00e9s"
    ],
    "name:ita_x_preferred":[
        "Kastanies"
    ],
    "name:jpn_x_preferred":[
        "\u30ab\u30b9\u30bf\u30cb\u30b9"
    ],
    "name:nld_x_preferred":[
        "Kastanies"
    ],
    "name:ron_x_preferred":[
        "Kastanies"
    ],
    "name:rus_x_preferred":[
        "\u041a\u0430\u0441\u0442\u0430\u043d\u0435\u044d"
    ],
    "name:swe_x_preferred":[
        "Kastani\u00e9s"
    ],
    "name:tur_x_preferred":[
        "Kestanelik"
    ],
    "name:unk_x_variant":[
        "Kastan\u00e9ai"
    ],
    "name:zho_x_preferred":[
        "\u5361\u65af\u5854\u5c3c\u65af"
    ],
    "qs_pg:aaroncc":"GR",
    "qs_pg:gn_country":"GR",
    "qs_pg:gn_fcode":"PPL",
    "qs_pg:gn_pop":1214,
    "qs_pg:name":"Kastaneai",
    "qs_pg:name_adm0":"\u0395\u03bb\u03bb\u03ac\u03b4\u03b1",
    "qs_pg:name_adm1":"Macedonia and Thrace",
    "qs_pg:photos_9k":1,
    "qs_pg:photos_9r":1,
    "qs_pg:photos_all":1,
    "qs_pg:photos_sr":0,
    "qs_pg:pop_sr":3,
    "qs_pg:qs_pg_placetype":"locality",
    "qs_pg:qs_pg_placetype_gp":"Town",
    "qs_pg:woe_adm0":23424833,
    "woe:adm0_id":23424833,
    "woe:name_adm0":"\u0395\u03bb\u03bb\u03ac\u03b4\u03b1",
    "woe:name_adm1":"Macedonia and Thrace",
    "woe:placetype":"Town",
    "wof:name":"Kastaneai",
    "wof:placetype":"locality",
    "wof:population":1214
},
  "geometry": {"coordinates":[26.46667,41.65],"type":"Point"}
}