{
  "type": "Feature",
  "properties": {
    "gn:admin1_code":"ESYE24",
    "gn:admin2_code":"29.0",
    "gn:admin3_code":"9163",
    "gn:asciiname":"Agnandi",
    "gn:country_code":"GR",
    "gn:dem":432,
    "gn:feature_class":"P",
    "gn:feature_code":"PPL",
    "gn:name":"\u00c1gnandi",
    "gn:population":218,
    "gn:timezone":"Europe/Athens",
    "iso:country":"GR",
    "name:ell_x_preferred":[
        "\u0386\u03b3\u03bd\u03b1\u03bd\u03c4\u03b7"
    ],
    "name:eng_x_preferred":[
        "Agnanti"
    ],
    "wof:name":"Agnandi",
    "wof:placetype":"locality",
    "wof:population":218
},
  "geometry": {"coordinates":[22.87946,38.71281],"type":"Point"}
}