{
  "type": "Feature",
  "properties": {
    "gn:admin1_code":"ESYE41",
    "gn:admin2_code":"51.0",
    "gn:admin3_code":"9261",
    "gn:asciiname":"Kleio",
    "gn:country_code":"GR",
    "gn:dem":320,
    "gn:feature_class":"P",
    "gn:feature_code":"PPL",
    "gn:name":"Klei\u00f3",
    "gn:population":356,
    "gn:timezone":"Europe/Athens",
    "iso:country":"GR",
    "name:ell_x_preferred":[
        "\u039a\u03bb\u03b5\u03b9\u03ce"
    ],
    "name:und_x_variant":[
        "Klio\u00fa",
        "Kli\u00f3",
        "Klei\u00f3"
    ],
    "wof:name":"Kleio",
    "wof:placetype":"locality",
    "wof:population":356
},
  "geometry": {"coordinates":[26.32247000000001,39.34659],"type":"Point"}
}