{
  "type": "Feature",
  "properties": {
    "gn:country":"GR",
    "gn:fcode":"PPL",
    "gn:population":850,
    "iso:country":"GR",
    "name:arz_x_preferred":[
        "\u0643\u0627\u0645\u064a\u0646\u064a\u0627"
    ],
    "name:ceb_x_preferred":[
        "Kam\u00ednia"
    ],
    "name:ell_x_historical":[
        "\u0394\u03b5\u03c1\u03b2\u03ad\u03bd\u03b9"
    ],
    "name:ell_x_preferred":[
        "\u039a\u03b1\u03bc\u03af\u03bd\u03b9\u03b1"
    ],
    "name:ell_x_variant":[
        "\u0394\u03b5\u03c1\u03b2\u03ad\u03bd\u03b9",
        "\u039a\u03b1\u03bc\u03af\u03bd\u03b9\u03b1 \u0391\u03c7\u03b1\u0390\u03b1\u03c2"
    ],
    "name:eng_x_preferred":[
        "Kaminia"
    ],
    "name:nld_x_preferred":[
        "Kaminia"
    ],
    "name:ron_x_preferred":[
        "Kaminia"
    ],
    "name:swe_x_preferred":[
        "Kam\u00ednia"
    ],
    "qs_pg:aaroncc":"GR",
    "qs_pg:gn_country":"GR",
    "qs_pg:gn_fcode":"PPL",
    "qs_pg:gn_pop":850,
    "qs_pg:name":"Kaminia",
    "qs_pg:name_adm0":"\u0395\u03bb\u03bb\u03ac\u03b4\u03b1",
    "qs_pg:name_adm1":"Peloponnese Western Greece and the Ionian Islands",
    "qs_pg:photos_9r":0,
    "qs_pg:photos_sr":0,
    "qs_pg:pop_sr":2,
    "qs_pg:qs_pg_placetype":"locality",
    "qs_pg:qs_pg_placetype_gp":"Town",
    "qs_pg:woe_adm0":23424833,
    "woe:adm0_id":23424833,
    "woe:name_adm0":"\u0395\u03bb\u03bb\u03ac\u03b4\u03b1",
    "woe:name_adm1":"Peloponnese Western Greece and the Ionian Islands",
    "woe:placetype":"Town",
    "wof:name":"Kaminia",
    "wof:placetype":"locality",
    "wof:population":716
},
  "geometry": {"coordinates":[21.61667,38.15],"type":"Point"}
}