{
  "type": "Feature",
  "properties": {
    "gn:country":"GR",
    "gn:fcode":"PPL",
    "gn:population":1473,
    "iso:country":"GR",
    "name:ell_x_preferred":[
        "\u039d\u03b7\u03c3\u03af\u03bf\u03bd"
    ],
    "name:ell_x_variant":[
        "\u039d\u03b7\u03c3\u03af"
    ],
    "name:und_x_variant":[
        "Nis\u00ed"
    ],
    "qs_pg:aaroncc":"GR",
    "qs_pg:gn_country":"GR",
    "qs_pg:gn_fcode":"PPL",
    "qs_pg:gn_pop":1473,
    "qs_pg:name":"Nision",
    "qs_pg:name_adm0":"\u0395\u03bb\u03bb\u03ac\u03b4\u03b1",
    "qs_pg:name_adm1":"Macedonia and Thrace",
    "qs_pg:photos_9k":1,
    "qs_pg:photos_9r":1,
    "qs_pg:photos_all":5,
    "qs_pg:photos_sr":0,
    "qs_pg:pop_sr":3,
    "qs_pg:qs_pg_placetype":"locality",
    "qs_pg:qs_pg_placetype_gp":"Town",
    "qs_pg:woe_adm0":23424833,
    "woe:adm0_id":23424833,
    "woe:name_adm0":"\u0395\u03bb\u03bb\u03ac\u03b4\u03b1",
    "woe:name_adm1":"Macedonia and Thrace",
    "woe:placetype":"Town",
    "wof:name":"Nision",
    "wof:placetype":"locality",
    "wof:population":1473
},
  "geometry": {"coordinates":[22.38778,40.63694],"type":"Point"}
}