{
  "type": "Feature",
  "properties": {
    "gn:admin1_code":"ESYE11",
    "gn:admin2_code":"14.0",
    "gn:admin3_code":"9012",
    "gn:asciiname":"Aspri Ammos",
    "gn:country_code":"GR",
    "gn:dem":18,
    "gn:feature_class":"P",
    "gn:feature_code":"PPL",
    "gn:name":"\u00c1spri \u00c1mmos",
    "gn:population":48,
    "gn:timezone":"Europe/Athens",
    "iso:country":"GR",
    "name:ell_x_preferred":[
        "\u0386\u03c3\u03c0\u03c1\u03b7 \u0386\u03bc\u03bc\u03bf\u03c2"
    ],
    "name:eng_x_preferred":[
        "Aspri Ammos"
    ],
    "wof:name":"Aspri Ammos",
    "wof:placetype":"locality",
    "wof:population":48
},
  "geometry": {"coordinates":[24.45381,40.94811],"type":"Point"}
}