{
  "type": "Feature",
  "properties": {
    "gn:admin1_code":"ESYE21",
    "gn:admin2_code":"17.0",
    "gn:admin3_code":"9081",
    "gn:asciiname":"Zoodochos Pigi Agias Anastasias",
    "gn:country_code":"GR",
    "gn:dem":494,
    "gn:feature_class":"P",
    "gn:feature_code":"PPL",
    "gn:name":"Zood\u00f3chos Pig\u00ed Ag\u00edas Anastas\u00edas",
    "gn:population":16,
    "gn:timezone":"Europe/Athens",
    "iso:country":"GR",
    "name:ell_x_preferred":[
        "\u0396\u03c9\u03bf\u03b4\u03cc\u03c7\u03bf\u03c2 \u03a0\u03b7\u03b3\u03ae \u0391\u03b3\u03af\u03b1\u03c2 \u0391\u03bd\u03b1\u03c3\u03c4\u03b1\u03c3\u03af\u03b1\u03c2"
    ],
    "name:eng_x_preferred":[
        "Zoodochos Pigi Agias Anastasias"
    ],
    "wof:name":"Zoodochos Pigi Agias Anastasias",
    "wof:placetype":"locality",
    "wof:population":16
},
  "geometry": {"coordinates":[20.72908,39.57525],"type":"Point"}
}