{
  "type": "Feature",
  "properties": {
    "gn:gn_country":"GR",
    "gn:gn_fcode":"PPL",
    "gn:gn_pop":269,
    "gn:population":386,
    "iso:country":"GR",
    "name:cze_x_preferred":[
        "Sidari"
    ],
    "name:dut_x_preferred":[
        "Sidari"
    ],
    "name:ell_x_preferred":[
        "\u03a3\u03b9\u03b4\u03ac\u03c1\u03b9"
    ],
    "name:eng_x_preferred":[
        "Sidari"
    ],
    "name:fin_x_preferred":[
        "Sid\u00e1ri"
    ],
    "name:fre_x_preferred":[
        "Sidari"
    ],
    "name:ger_x_preferred":[
        "Sidari"
    ],
    "name:gre_x_preferred":[
        "\u03a3\u03b9\u03b4\u03ac\u03c1\u03b9 \u039a\u03ad\u03c1\u03ba\u03c5\u03c1\u03b1\u03c2"
    ],
    "name:lat_x_preferred":[
        "Sidarium"
    ],
    "name:pol_x_preferred":[
        "Sidari"
    ],
    "name:rus_x_preferred":[
        "\u0421\u0438\u0434\u0430\u0440\u0438\u043e\u043d"
    ],
    "name:swe_x_preferred":[
        "Sid\u00e1ri"
    ],
    "name:unk_x_variant":[
        "Sidh\u00e1rion"
    ],
    "qs_pg:aaroncc":"GR",
    "qs_pg:gn_country":"GR",
    "qs_pg:gn_fcode":"PPL",
    "qs_pg:gn_pop":269,
    "qs_pg:name":"Sid\u00e1rion",
    "qs_pg:photos_9r":0,
    "qs_pg:photos_sr":0,
    "qs_pg:pop_sr":2,
    "qs_pg:qs_pg_placetype":"locality",
    "wof:name":"Sid\u00e1rion",
    "wof:placetype":"locality",
    "wof:population":386
},
  "geometry": {"coordinates":[19.70667,39.78583],"type":"Point"}
}