{
  "type": "Feature",
  "properties": {
    "gn:admin1_code":"ESYE42",
    "gn:admin2_code":"49.0",
    "gn:admin3_code":"9290.0",
    "gn:asciiname":"Kanalia",
    "gn:country_code":"GR",
    "gn:dem":36,
    "gn:feature_class":"P",
    "gn:feature_code":"PPLL",
    "gn:name":"Kan\u00e1lia",
    "gn:population":0,
    "gn:timezone":"Europe/Athens",
    "iso:country":"GR",
    "name:ell_x_preferred":[
        "\u039a\u03b1\u03bd\u03ac\u03bb\u03b9\u03b1"
    ],
    "name:eng_x_preferred":[
        "Kanalia"
    ],
    "wof:name":"Kanalia",
    "wof:placetype":"locality"
},
  "geometry": {"coordinates":[25.30596,37.43531],"type":"Point"}
}