{
  "type": "Feature",
  "properties": {
    "gn:admin1_code":"ESYE25",
    "gn:admin2_code":"42.0",
    "gn:admin3_code":"9248",
    "gn:asciiname":"Klainianika",
    "gn:cc2":"GR",
    "gn:country_code":"GR",
    "gn:dem":399,
    "gn:feature_class":"P",
    "gn:feature_code":"PPL",
    "gn:name":"Kla\u00efni\u00e1nika",
    "gn:population":0,
    "gn:timezone":"Europe/Athens",
    "iso:country":"GR",
    "name:und_x_variant":[
        "Klaini\u00e1noi",
        "Kla\u00efni\u00e1nika"
    ],
    "wof:name":"Klainianika",
    "wof:placetype":"locality"
},
  "geometry": {"coordinates":[22.40661,36.72467],"type":"Point"}
}