{
  "type": "Feature",
  "properties": {
    "gn:admin1_code":"ESYE24",
    "gn:admin2_code":"34.0",
    "gn:admin3_code":"9153",
    "gn:asciiname":"Kerasia",
    "gn:country_code":"GR",
    "gn:dem":553,
    "gn:feature_class":"P",
    "gn:feature_code":"PPL",
    "gn:name":"Kerasi\u00e1",
    "gn:population":0,
    "gn:timezone":"Europe/Athens",
    "iso:country":"GR",
    "name:ell_x_preferred":[
        "\u039a\u03b5\u03c1\u03b1\u03c3\u03b9\u03ac"
    ],
    "name:ell_x_variant":[
        "\u039a\u03b5\u03c1\u03b1\u03c3\u03ad\u03b1"
    ],
    "name:und_x_variant":[
        "Kerasi\u00e1",
        "Keras\u00e9a"
    ],
    "wof:name":"Kerasia",
    "wof:placetype":"locality"
},
  "geometry": {"coordinates":[23.32493,38.91122],"type":"Point"}
}