{
  "type": "Feature",
  "properties": {
    "gn:admin1_code":"ESYE12",
    "gn:admin2_code":"15.0",
    "gn:admin3_code":"9060",
    "gn:asciiname":"Galini Neou Marmara",
    "gn:country_code":"GR",
    "gn:dem":8,
    "gn:feature_class":"P",
    "gn:feature_code":"PPL",
    "gn:name":"Gal\u00edni N\u00e9ou Marmar\u00e1",
    "gn:population":34,
    "gn:timezone":"Europe/Athens",
    "iso:country":"GR",
    "name:ell_x_preferred":[
        "\u0393\u03b1\u03bb\u03ae\u03bd\u03b7 \u039d\u03ad\u03bf\u03c5 \u039c\u03b1\u03c1\u03bc\u03b1\u03c1\u03ac"
    ],
    "name:eng_x_preferred":[
        "Galini Neou Marmara"
    ],
    "wof:name":"Galini Neou Marmara",
    "wof:placetype":"locality",
    "wof:population":34
},
  "geometry": {"coordinates":[23.8163,40.02403],"type":"Point"}
}