{
  "type": "Feature",
  "properties": {
    "gn:admin1_code":"ESYE43",
    "gn:admin2_code":"43.0",
    "gn:admin3_code":"9323",
    "gn:asciiname":"Neriana",
    "gn:country_code":"GR",
    "gn:dem":75,
    "gn:feature_class":"P",
    "gn:feature_code":"PPL",
    "gn:name":"Nerian\u00e1",
    "gn:population":0,
    "gn:timezone":"Europe/Athens",
    "iso:country":"GR",
    "name:ell_x_preferred":[
        "Nerian\u00e1"
    ],
    "name:ell_x_variant":[
        "\u039d\u03b5\u03c1\u03b9\u03b1\u03bd\u03ac"
    ],
    "wof:name":"Neriana",
    "wof:placetype":"locality"
},
  "geometry": {"coordinates":[23.81325,35.48587],"type":"Point"}
}