{
  "type": "Feature",
  "properties": {
    "gn:admin1_code":"ESYE25",
    "gn:admin2_code":"40.0",
    "gn:admin3_code":"9254",
    "gn:asciiname":"Mikra Mantineia",
    "gn:country_code":"GR",
    "gn:dem":34,
    "gn:feature_class":"P",
    "gn:feature_code":"PPL",
    "gn:name":"Mikr\u00e1 Mant\u00edneia",
    "gn:population":670,
    "gn:timezone":"Europe/Athens",
    "iso:country":"GR",
    "name:ell_x_preferred":[
        "\u039c\u03b9\u03ba\u03c1\u03ae \u039c\u03b1\u03bd\u03c4\u03af\u03bd\u03b5\u03b9\u03b1"
    ],
    "name:ell_x_variant":[
        "\u039c\u03b9\u03ba\u03c1\u03ac \u039c\u03b1\u03bd\u03c4\u03af\u03bd\u03b5\u03b9\u03b1"
    ],
    "name:eng_x_preferred":[
        "Mikri Mantineia"
    ],
    "name:eng_x_variant":[
        "Mikra Mantineia"
    ],
    "name:und_x_variant":[
        "Mikr\u00e9s Mand\u00ednies",
        "Mikra Mantin\u00eda",
        "Mikr\u00e1 Mand\u00ednia",
        "Mikri Mantinia",
        "Mikra Mantinia"
    ],
    "wof:name":"Mikra Mantineia",
    "wof:placetype":"locality",
    "wof:population":670
},
  "geometry": {"coordinates":[22.15337,36.9861],"type":"Point"}
}