{
  "type": "Feature",
  "properties": {
    "gn:admin1_code":"ESYE23",
    "gn:admin2_code":"38.0",
    "gn:admin3_code":"9132",
    "gn:asciiname":"Kakavoulaiika",
    "gn:country_code":"GR",
    "gn:dem":347,
    "gn:feature_class":"P",
    "gn:feature_code":"PPL",
    "gn:name":"Kakavoula\u00edika",
    "gn:population":0,
    "gn:timezone":"Europe/Athens",
    "iso:country":"GR",
    "name:ell_x_preferred":[
        "Kakavoula\u00edika"
    ],
    "name:ell_x_variant":[
        "\u039a\u03b1\u03ba\u03b1\u03b2\u03bf\u03c5\u03bb\u03b1\u03af\u03b9\u03ba\u03b1"
    ],
    "wof:name":"Kakavoulaiika",
    "wof:placetype":"locality"
},
  "geometry": {"coordinates":[21.75611,38.04458],"type":"Point"}
}