{
  "type": "Feature",
  "properties": {
    "gn:country":"GR",
    "gn:fcode":"PPL",
    "gn:population":201,
    "iso:country":"GR",
    "name:ell_x_preferred":[
        "Sm\u00e9rtos"
    ],
    "name:ell_x_variant":[
        "\u03a3\u03bc\u03ad\u03c1\u03c4\u03bf\u03c2"
    ],
    "qs_pg:aaroncc":"GR",
    "qs_pg:gn_country":"GR",
    "qs_pg:gn_fcode":"PPL",
    "qs_pg:gn_pop":201,
    "qs_pg:name":"Smertos",
    "qs_pg:name_adm0":"\u0395\u03bb\u03bb\u03ac\u03b4\u03b1",
    "qs_pg:name_adm1":"Epirus and Western Macedonia",
    "qs_pg:photos_9k":1,
    "qs_pg:photos_9r":1,
    "qs_pg:photos_all":2,
    "qs_pg:photos_sr":0,
    "qs_pg:pop_sr":2,
    "qs_pg:qs_pg_placetype":"locality",
    "qs_pg:qs_pg_placetype_gp":"Town",
    "qs_pg:woe_adm0":23424833,
    "woe:adm0_id":23424833,
    "woe:name_adm0":"\u0395\u03bb\u03bb\u03ac\u03b4\u03b1",
    "woe:name_adm1":"Epirus and Western Macedonia",
    "woe:placetype":"Town",
    "wof:name":"Smertos",
    "wof:placetype":"locality",
    "wof:population":201
},
  "geometry": {"coordinates":[20.23778,39.60472],"type":"Point"}
}