{
  "type": "Feature",
  "properties": {
    "gn:gn_country":"GR",
    "gn:gn_fcode":"PPL",
    "gn:gn_pop":30,
    "gn:population":31,
    "iso:country":"GR",
    "name:ell_x_preferred":[
        "\u0392\u03c1\u03c5\u03c3\u03bf\u03cd\u03bb\u03b5\u03c2"
    ],
    "name:eng_x_preferred":[
        "Vrysoules"
    ],
    "name:unk_x_variant":[
        "Vryso\u00fales"
    ],
    "qs_pg:aaroncc":"GR",
    "qs_pg:gn_country":"GR",
    "qs_pg:gn_fcode":"PPL",
    "qs_pg:gn_pop":30,
    "qs_pg:name":"Vrysoules",
    "qs_pg:name_adm0":"\u0395\u03bb\u03bb\u03ac\u03b4\u03b1",
    "qs_pg:name_adm1":"Epirus and Western Macedonia",
    "qs_pg:photos_9r":0,
    "qs_pg:photos_sr":0,
    "qs_pg:pop_sr":1,
    "qs_pg:qs_pg_placetype":"locality",
    "qs_pg:qs_pg_placetype_gp":"Town",
    "qs_pg:woe_adm0":23424833,
    "woe:adm0_id":23424833,
    "woe:name_adm0":"\u0395\u03bb\u03bb\u03ac\u03b4\u03b1",
    "woe:name_adm1":"Epirus and Western Macedonia",
    "woe:placetype":"Town",
    "wof:name":"Vrysoules",
    "wof:placetype":"locality",
    "wof:population":31
},
  "geometry": {"coordinates":[20.95222,39.18972],"type":"Point"}
}