{
  "type": "Feature",
  "properties": {
    "gn:admin1_code":"ESYE31",
    "gn:admin2_code":"445408.0",
    "gn:admin3_code":"9186",
    "gn:asciiname":"Asteroskopeio",
    "gn:country_code":"GR",
    "gn:dem":106,
    "gn:feature_class":"P",
    "gn:feature_code":"PPLL",
    "gn:name":"Asteroskope\u00edo",
    "gn:population":0,
    "gn:timezone":"Europe/Athens",
    "iso:country":"GR",
    "name:ell_x_preferred":[
        "\u0391\u03c3\u03c4\u03b5\u03c1\u03bf\u03c3\u03ba\u03bf\u03c0\u03b5\u03af\u03bf"
    ],
    "name:eng_x_preferred":[
        "Asteroskopeio"
    ],
    "name:rus_x_preferred":[
        "\u0410\u0441\u0442\u0435\u0440\u043e\u0441\u043a\u043e\u043f\u0438\u043e"
    ],
    "name:ukr_x_preferred":[
        "\u0410\u0441\u0442\u0435\u0440\u043e\u0441\u043a\u043e\u043f\u0456\u043e"
    ],
    "wof:name":"Asteroskopeio",
    "wof:placetype":"locality"
},
  "geometry": {"coordinates":[23.71827,37.97327],"type":"Point"}
}