{
  "type": "Feature",
  "properties": {
    "gn:admin1_code":"ESYE25",
    "gn:admin2_code":"41.0",
    "gn:admin3_code":"9238",
    "gn:asciiname":"Ochthia",
    "gn:country_code":"GR",
    "gn:dem":492,
    "gn:feature_class":"P",
    "gn:feature_code":"PPL",
    "gn:name":"\u00d3chthia",
    "gn:population":0,
    "gn:timezone":"Europe/Athens",
    "iso:country":"GR",
    "name:ell_x_preferred":[
        "\u00d3chthia"
    ],
    "name:ell_x_variant":[
        "\u038c\u03c7\u03b8\u03b9\u03b1"
    ],
    "name:und_x_variant":[
        "Karas\u00e1ni",
        "Karakh\u00e1sani",
        "\u00d3khthia"
    ],
    "wof:name":"Ochthia",
    "wof:placetype":"locality"
},
  "geometry": {"coordinates":[21.89917,37.65608],"type":"Point"}
}