{
  "type": "Feature",
  "properties": {
    "gn:admin1_code":"ESYE12",
    "gn:admin2_code":"12.0",
    "gn:admin3_code":"9023",
    "gn:asciiname":"Platy",
    "gn:country_code":"GR",
    "gn:dem":5,
    "gn:feature_class":"P",
    "gn:feature_code":"PPL",
    "gn:name":"Plat\u00fd",
    "gn:population":2228,
    "gn:timezone":"Europe/Athens",
    "iso:country":"GR",
    "name:ell_x_preferred":[
        "\u03a0\u03bb\u03b1\u03c4\u03cd"
    ],
    "name:und_x_variant":[
        "Plat\u00ed",
        "Plat\u00fd"
    ],
    "wof:name":"Platy",
    "wof:placetype":"locality",
    "wof:population":2228
},
  "geometry": {"coordinates":[22.53458,40.64241],"type":"Point"}
}