{
  "type": "Feature",
  "properties": {
    "gn:country":"GR",
    "gn:fcode":"PPL",
    "gn:population":204,
    "iso:country":"GR",
    "name:ell_x_preferred":[
        "\u039c\u03b5\u03c3\u03cc\u03b3\u03b5\u03b9\u03bf"
    ],
    "name:eng_x_preferred":[
        "Mesogeio"
    ],
    "name:und_x_variant":[
        "Mes\u00f3yion"
    ],
    "qs_pg:aaroncc":"GR",
    "qs_pg:gn_country":"GR",
    "qs_pg:gn_fcode":"PPL",
    "qs_pg:gn_pop":204,
    "qs_pg:name":"Mes\u00f3geion",
    "qs_pg:photos_9r":0,
    "qs_pg:photos_sr":0,
    "qs_pg:pop_sr":2,
    "qs_pg:qs_pg_placetype":"locality",
    "wof:name":"Mes\u00f3geion",
    "wof:placetype":"locality",
    "wof:population":109
},
  "geometry": {"coordinates":[26.82222,37.72722],"type":"Point"}
}