{
  "type": "Feature",
  "properties": {
    "gn:admin1_code":"ESYE13",
    "gn:admin2_code":"9.0",
    "gn:admin3_code":"9063",
    "gn:asciiname":"Poreia",
    "gn:country_code":"GR",
    "gn:dem":676,
    "gn:elevation":"680.0",
    "gn:feature_class":"P",
    "gn:feature_code":"PPL",
    "gn:name":"Porei\u00e1",
    "gn:population":512,
    "gn:timezone":"Europe/Athens",
    "iso:country":"GR",
    "name:ell_x_historical":[
        "\u03a0\u03bf\u03c1\u03b9\u03ac",
        "\u038a\u03b6\u03b3\u03ba\u03bb\u03b9\u03bc\u03c0\u03b9",
        "\u038a\u03b6\u03b3\u03bb\u03b9\u03bc\u03c0\u03b9",
        "\u038a\u03c3\u03b3\u03bb\u03b9\u03bc\u03c0\u03b9",
        "\u038a\u03b6\u03bb\u03b9\u03bc\u03c0\u03b9"
    ],
    "name:ell_x_preferred":[
        "\u03a0\u03bf\u03c1\u03b5\u03b9\u03ac"
    ],
    "name:ell_x_variant":[
        "\u03a0\u03bf\u03c1\u03b9\u03ac",
        "\u038a\u03b6\u03b3\u03ba\u03bb\u03b9\u03bc\u03c0\u03b9",
        "\u038a\u03b6\u03b3\u03bb\u03b9\u03bc\u03c0\u03b9",
        "\u038a\u03c3\u03b3\u03bb\u03b9\u03bc\u03c0\u03b9",
        "\u038a\u03b6\u03bb\u03b9\u03bc\u03c0\u03b9"
    ],
    "name:eng_x_preferred":[
        "Poreia"
    ],
    "name:eng_x_variant":[
        "Poria"
    ],
    "name:und_x_variant":[
        "\u00cdxglimbi",
        "Pori\u00e1",
        "Porei\u00e1"
    ],
    "wof:name":"Poreia",
    "wof:placetype":"locality",
    "wof:population":512
},
  "geometry": {"coordinates":[21.2124,40.4885],"type":"Point"}
}