{
  "type": "Feature",
  "properties": {
    "gn:gn_country":"GR",
    "gn:gn_fcode":"PPL",
    "gn:gn_pop":222,
    "gn:population":222,
    "iso:country":"GR",
    "name:ell_x_preferred":[
        "\u039d\u03ad\u03bf\u03c2 \u03a0\u03c1\u03cc\u03b4\u03c1\u03bf\u03bc\u03bf\u03c2"
    ],
    "name:unk_x_variant":[
        "N\u00e9os Pr\u00f3dhromos"
    ],
    "qs_pg:aaroncc":"GR",
    "qs_pg:gn_country":"GR",
    "qs_pg:gn_fcode":"PPL",
    "qs_pg:gn_pop":222,
    "qs_pg:name":"N\u00e9os Pr\u00f3dromos",
    "qs_pg:photos_9r":0,
    "qs_pg:photos_sr":0,
    "qs_pg:pop_sr":2,
    "qs_pg:qs_pg_placetype":"locality",
    "wof:name":"N\u00e9os Pr\u00f3dromos",
    "wof:placetype":"locality",
    "wof:population":222
},
  "geometry": {"coordinates":[22.43361,40.53611],"type":"Point"}
}