{
  "type": "Feature",
  "properties": {
    "gn:population":1068,
    "iso:country":"GR",
    "name:ell_x_preferred":[
        "\u0391\u03c1\u03af\u03c3\u03b2\u03b7"
    ],
    "name:und_x_variant":[
        "Irj\u00e1n"
    ],
    "qs:a0":"Greece",
    "qs:a1":"*\u0391\u039d\u0391\u03a4\u039f\u039b\u0399\u039a\u0397 \u039c\u0391\u039a\u0395\u0394\u039f\u039d\u0399\u0391 \u039a\u0391\u0399 \u0398\u03a1\u0391\u039a\u0397",
    "qs:a1_alt":"ANATOLIKH MAKEDONIA KAI URAKH",
    "qs:a1r":"0",
    "qs:a2_alt":"RODOPH",
    "qs:adm0":"Greece",
    "qs:la_lc":"*",
    "qs:level":"locality",
    "qs:loc":"\u0391\u03a1\u0399\u03a3\u0392\u0397",
    "qs:loc_alt":"ARISBH",
    "qs:pop":0,
    "qs:type":"buffered point",
    "wof:name":"\u0391\u03a1\u0399\u03a3\u0392\u0397",
    "wof:placetype":"locality",
    "wof:population":1068
},
  "geometry": {"coordinates":[25.589741,41.070198],"type":"Point"}
}