{
  "type": "Feature",
  "properties": {
    "gn:admin1_code":"ESYE42",
    "gn:admin2_code":"49.0",
    "gn:admin3_code":"9268",
    "gn:asciiname":"Kapparia",
    "gn:country_code":"GR",
    "gn:dem":252,
    "gn:feature_class":"P",
    "gn:feature_code":"PPL",
    "gn:name":"Kappari\u00e1",
    "gn:population":0,
    "gn:timezone":"Europe/Athens",
    "iso:country":"GR",
    "name:ell_x_preferred":[
        "\u039a\u03b1\u03c0\u03c0\u03b1\u03c1\u03b9\u03ac"
    ],
    "name:und_x_variant":[
        "Vorin\u00f3",
        "Vorin\u00e1",
        "Kappari\u00e1"
    ],
    "wof:name":"Kapparia",
    "wof:placetype":"locality"
},
  "geometry": {"coordinates":[24.9078,37.7723],"type":"Point"}
}