{
  "type": "Feature",
  "properties": {
    "gn:admin1_code":"ESYE14",
    "gn:admin2_code":"24.0",
    "gn:admin3_code":"9104",
    "gn:asciiname":"Loutro",
    "gn:country_code":"GR",
    "gn:dem":6,
    "gn:feature_class":"P",
    "gn:feature_code":"PPL",
    "gn:name":"Loutr\u00f3",
    "gn:population":15,
    "gn:timezone":"Europe/Athens",
    "iso:country":"GR",
    "name:deu_x_preferred":[
        "Loutro"
    ],
    "name:ell_x_preferred":[
        "\u039b\u03bf\u03c5\u03c4\u03c1\u03cc"
    ],
    "name:eng_x_preferred":[
        "Loutro"
    ],
    "name:und_x_variant":[
        "Kal\u00edvia Pteleo\u00fa"
    ],
    "wof:name":"Loutro",
    "wof:placetype":"locality",
    "wof:population":15
},
  "geometry": {"coordinates":[22.96349,39.03395],"type":"Point"}
}