{
  "type": "Feature",
  "properties": {
    "gn:admin1_code":"ESYE42",
    "gn:admin2_code":"49.0",
    "gn:admin3_code":"9292.0",
    "gn:asciiname":"Atsipapi",
    "gn:country_code":"GR",
    "gn:dem":520,
    "gn:feature_class":"P",
    "gn:feature_code":"PPL",
    "gn:name":"Atsip\u00e1pi",
    "gn:population":15,
    "gn:timezone":"Europe/Athens",
    "iso:country":"GR",
    "name:ell_x_preferred":[
        "\u0391\u03c4\u03c3\u03b9\u03c0\u03ac\u03c0\u03b7"
    ],
    "name:eng_x_preferred":[
        "Atsipapi"
    ],
    "wof:name":"Atsipapi",
    "wof:placetype":"locality",
    "wof:population":15
},
  "geometry": {"coordinates":[25.56263,37.1134],"type":"Point"}
}