{
  "type": "Feature",
  "properties": {
    "gn:admin1_code":"ESYE25",
    "gn:admin2_code":"40.0",
    "gn:admin3_code":"9255",
    "gn:asciiname":"Kalamaras",
    "gn:country_code":"GR",
    "gn:dem":40,
    "gn:feature_class":"P",
    "gn:feature_code":"PPL",
    "gn:name":"Kalamar\u00e1s",
    "gn:population":0,
    "gn:timezone":"Europe/Athens",
    "iso:country":"GR",
    "name:ell_x_preferred":[
        "\u039a\u03b1\u03bb\u03b1\u03bc\u03b1\u03c1\u03ac\u03c2"
    ],
    "name:und_x_variant":[
        "Kalamar\u00e1",
        "Kalamar\u00e1s"
    ],
    "wof:name":"Kalamaras",
    "wof:placetype":"locality"
},
  "geometry": {"coordinates":[21.96368,37.10942],"type":"Point"}
}