{
  "type": "Feature",
  "properties": {
    "gn:admin1_code":"ESYE31",
    "gn:admin2_code":"445406.0",
    "gn:admin3_code":"9219",
    "gn:asciiname":"Togani Lakizas",
    "gn:country_code":"GR",
    "gn:dem":155,
    "gn:feature_class":"P",
    "gn:feature_code":"PPL",
    "gn:name":"Tog\u00e1ni L\u00e1kizas",
    "gn:population":40,
    "gn:timezone":"Europe/Athens",
    "iso:country":"GR",
    "name:ell_x_preferred":[
        "\u03a4\u03bf\u03b3\u03ac\u03bd\u03b9 \u039b\u03ac\u03ba\u03b9\u03b6\u03b1\u03c2"
    ],
    "name:eng_x_preferred":[
        "Togani Lakizas"
    ],
    "wof:name":"Togani Lakizas",
    "wof:placetype":"locality",
    "wof:population":40
},
  "geometry": {"coordinates":[24.01118,37.78021],"type":"Point"}
}