{
  "type": "Feature",
  "properties": {
    "gn:admin1_code":"ESYE23",
    "gn:admin2_code":"31.0",
    "gn:admin3_code":"9128",
    "gn:asciiname":"Pezoulia",
    "gn:country_code":"GR",
    "gn:dem":324,
    "gn:feature_class":"P",
    "gn:feature_code":"PPL",
    "gn:name":"Pezo\u00falia",
    "gn:population":0,
    "gn:timezone":"Europe/Athens",
    "iso:country":"GR",
    "name:ell_x_preferred":[
        "Pezo\u00falia"
    ],
    "name:ell_x_variant":[
        "\u03a0\u03b5\u03b6\u03bf\u03cd\u03bb\u03b9\u03b1"
    ],
    "wof:name":"Pezoulia",
    "wof:placetype":"locality"
},
  "geometry": {"coordinates":[21.70506,38.38047],"type":"Point"}
}