{
  "type": "Feature",
  "properties": {
    "gn:admin1_code":"ESYE43",
    "gn:admin2_code":"43.0",
    "gn:admin3_code":"9322",
    "gn:asciiname":"Tzortziana",
    "gn:country_code":"GR",
    "gn:dem":540,
    "gn:feature_class":"P",
    "gn:feature_code":"PPLL",
    "gn:name":"Tzortzian\u00e1",
    "gn:population":0,
    "gn:timezone":"Europe/Athens",
    "iso:country":"GR",
    "name:ell_x_preferred":[
        "\u03a4\u03b6\u03c9\u03c1\u03c4\u03b6\u03b9\u03b1\u03bd\u03ac"
    ],
    "name:eng_x_preferred":[
        "Tzortziana"
    ],
    "name:und_x_variant":[
        "Tzortzian\u00e1"
    ],
    "wof:name":"Tzortziana",
    "wof:placetype":"locality"
},
  "geometry": {"coordinates":[23.62522,35.40777999999999],"type":"Point"}
}