{
  "type": "Feature",
  "properties": {
    "gn:admin1_code":"ESYE43",
    "gn:admin2_code":"46.0",
    "gn:admin3_code":"9310",
    "gn:asciiname":"Pyrgos Vrachasiou",
    "gn:country_code":"GR",
    "gn:dem":74,
    "gn:feature_class":"P",
    "gn:feature_code":"PPL",
    "gn:name":"P\u00fdrgos Vrachas\u00edou",
    "gn:population":48,
    "gn:timezone":"Europe/Athens",
    "iso:country":"GR",
    "name:ell_x_preferred":[
        "\u03a0\u03cd\u03c1\u03b3\u03bf\u03c2 \u0392\u03c1\u03b1\u03c7\u03b1\u03c3\u03af\u03bf\u03c5"
    ],
    "name:eng_x_preferred":[
        "Pyrgos Vrachasiou"
    ],
    "wof:name":"Pyrgos Vrachasiou",
    "wof:placetype":"locality",
    "wof:population":48
},
  "geometry": {"coordinates":[25.51656,35.29089000000001],"type":"Point"}
}