{
  "type": "Feature",
  "properties": {
    "gn:admin1_code":"ESYE14",
    "gn:admin2_code":"21.0",
    "gn:admin3_code":"9102",
    "gn:asciiname":"Platanoulia",
    "gn:country_code":"GR",
    "gn:dem":88,
    "gn:feature_class":"P",
    "gn:feature_code":"PPL",
    "gn:name":"Platano\u00falia",
    "gn:population":0,
    "gn:timezone":"Europe/Athens",
    "iso:country":"GR",
    "name:ell_x_preferred":[
        "\u03a0\u03bb\u03b1\u03c4\u03b1\u03bd\u03bf\u03cd\u03bb\u03b9\u03b1"
    ],
    "name:ell_x_variant":[
        "\u03a0\u03bb\u03b1\u03c4\u03b1\u03bd\u03bf\u03cd\u03bb\u03b9\u03b1 \u039b\u03ac\u03c1\u03b9\u03c3\u03b1\u03c2"
    ],
    "name:und_x_variant":[
        "Chatal\u00e1r",
        "Platano\u00falia"
    ],
    "wof:name":"Platanoulia",
    "wof:placetype":"locality"
},
  "geometry": {"coordinates":[22.30808,39.67708],"type":"Point"}
}