{
  "type": "Feature",
  "properties": {
    "gn:admin1_code":"ESYE25",
    "gn:admin2_code":"40.0",
    "gn:admin3_code":"9255",
    "gn:asciiname":"Ano Voutaina",
    "gn:country_code":"GR",
    "gn:dem":617,
    "gn:feature_class":"P",
    "gn:feature_code":"PPL",
    "gn:name":"\u00c1no Vo\u00fataina",
    "gn:population":0,
    "gn:timezone":"Europe/Athens",
    "iso:country":"GR",
    "name:ell_x_preferred":[
        "\u0386\u03bd\u03c9 \u0392\u03bf\u03cd\u03c4\u03b1\u03b9\u03bd\u03b1"
    ],
    "name:und_x_variant":[
        "Vo\u00fatina",
        "\u00c1no Vo\u00fatina",
        "\u00c1no Vo\u00fataina"
    ],
    "wof:name":"Ano Voutaina",
    "wof:placetype":"locality"
},
  "geometry": {"coordinates":[21.77084,37.13993],"type":"Point"}
}