{
  "type": "Feature",
  "properties": {
    "gn:country":"GR",
    "gn:fcode":"PPL",
    "gn:population":221,
    "iso:country":"GR",
    "name:ell_x_preferred":[
        "\u0396\u03b5\u03c1\u03b2\u03bf\u03c7\u03ce\u03c1\u03b9"
    ],
    "name:ell_x_variant":[
        "\u0396\u03b5\u03c1\u03b2\u03bf\u03c7\u03ce\u03c1\u03b9\u03bf\u03bd"
    ],
    "name:und_x_variant":[
        "Dhragoum\u00ed"
    ],
    "qs_pg:aaroncc":"GR",
    "qs_pg:gn_country":"GR",
    "qs_pg:gn_fcode":"PPL",
    "qs_pg:gn_pop":221,
    "qs_pg:name":"Zervoch\u00f3rion",
    "qs_pg:photos_9r":0,
    "qs_pg:photos_sr":0,
    "qs_pg:pop_sr":2,
    "qs_pg:qs_pg_placetype":"locality",
    "wof:name":"Zervoch\u00f3rion",
    "wof:placetype":"locality",
    "wof:population":221
},
  "geometry": {"coordinates":[20.56278,39.41222],"type":"Point"}
}