{
  "type": "Feature",
  "properties": {
    "gn:gn_country":"GR",
    "gn:gn_fcode":"PPL",
    "gn:gn_pop":517,
    "gn:population":517,
    "iso:country":"GR",
    "name:dut_x_preferred":[
        "Perdikaki"
    ],
    "name:ell_x_preferred":[
        "\u03a0\u03b5\u03c1\u03b4\u03b9\u03ba\u03ac\u03ba\u03b9"
    ],
    "name:ell_x_variant":[
        "\u03a0\u03b5\u03c1\u03b4\u03b9\u03ba\u03ac\u03ba\u03b9\u03bf\u03bd"
    ],
    "name:eng_x_preferred":[
        "Perdikaki"
    ],
    "name:gre_x_preferred":[
        "\u03a0\u03b5\u03c1\u03b4\u03b9\u03ba\u03ac\u03ba\u03b9 \u0391\u03b9\u03c4\u03c9\u03bb\u03bf\u03b1\u03ba\u03b1\u03c1\u03bd\u03b1\u03bd\u03af\u03b1\u03c2"
    ],
    "name:swe_x_preferred":[
        "Perdik\u00e1ki"
    ],
    "name:unk_x_variant":[
        "Sakar\u00e9tsi"
    ],
    "qs_pg:aaroncc":"GR",
    "qs_pg:gn_country":"GR",
    "qs_pg:gn_fcode":"PPL",
    "qs_pg:gn_pop":517,
    "qs_pg:name":"Perdik\u00e1kion",
    "qs_pg:photos_9r":0,
    "qs_pg:photos_sr":0,
    "qs_pg:pop_sr":2,
    "qs_pg:qs_pg_placetype":"locality",
    "wof:name":"Perdik\u00e1kion",
    "wof:placetype":"locality",
    "wof:population":517
},
  "geometry": {"coordinates":[21.36167,39.04833],"type":"Point"}
}