{
  "type": "Feature",
  "properties": {
    "gn:admin1_code":"ESYE25",
    "gn:admin2_code":"37.0",
    "gn:admin3_code":"9244.0",
    "gn:asciiname":"Avra",
    "gn:country_code":"GR",
    "gn:dem":150,
    "gn:feature_class":"P",
    "gn:feature_code":"PPL",
    "gn:name":"\u00c1vra",
    "gn:population":0,
    "gn:timezone":"Europe/Athens",
    "iso:country":"GR",
    "name:ceb_x_preferred":[
        "Avra"
    ],
    "name:deu_x_preferred":[
        "Avra"
    ],
    "name:ell_x_preferred":[
        "\u00c1vra"
    ],
    "name:ell_x_variant":[
        "\u0391\u03cd\u03c1\u03b1"
    ],
    "name:fra_x_preferred":[
        "Avra"
    ],
    "name:swe_x_preferred":[
        "Avra"
    ],
    "wof:name":"Avra",
    "wof:placetype":"locality"
},
  "geometry": {"coordinates":[23.00948,37.97281],"type":"Point"}
}