{
  "type": "Feature",
  "properties": {
    "gn:admin1_code":"ESYE25",
    "gn:admin2_code":"42.0",
    "gn:admin3_code":"9252",
    "gn:asciiname":"Anthokhorion",
    "gn:cc2":"GR",
    "gn:country_code":"GR",
    "gn:dem":237,
    "gn:feature_class":"P",
    "gn:feature_code":"PPL",
    "gn:name":"Anthokh\u00f3rion",
    "gn:population":0,
    "gn:timezone":"Europe/Athens",
    "iso:country":"GR",
    "name:ell_x_preferred":[
        "\u0391\u03bd\u03b8\u03bf\u03c7\u03ce\u03c1\u03b9\u03bf"
    ],
    "name:ell_x_variant":[
        "\u0391\u03bd\u03b8\u03bf\u03c7\u03ce\u03c1\u03b9\u03bf\u03bd"
    ],
    "name:und_x_variant":[
        "Katsoul\u00e9\u00efka",
        "Katsoula\u00edika",
        "Anthokh\u00f3rion"
    ],
    "wof:name":"Anthokhorion",
    "wof:placetype":"locality"
},
  "geometry": {"coordinates":[22.46052,36.9513],"type":"Point"}
}