{
  "type": "Feature",
  "properties": {
    "gn:admin1_code":"ESYE43",
    "gn:admin2_code":"43.0",
    "gn:admin3_code":"9323",
    "gn:asciiname":"Dromonero",
    "gn:country_code":"GR",
    "gn:dem":390,
    "gn:feature_class":"P",
    "gn:feature_code":"PPL",
    "gn:name":"Drom\u00f3nero",
    "gn:population":0,
    "gn:timezone":"Europe/Athens",
    "iso:country":"GR",
    "name:ell_x_preferred":[
        "Drom\u00f3nero"
    ],
    "name:ell_x_variant":[
        "\u0394\u03c1\u03bf\u03bc\u03cc\u03bd\u03b5\u03c1\u03bf",
        "Drom\u00f3neron",
        "\u0394\u03c1\u03bf\u03bc\u03cc\u03bd\u03b5\u03c1\u03bf\u03bd"
    ],
    "wof:name":"Dromonero",
    "wof:placetype":"locality"
},
  "geometry": {"coordinates":[23.76532000000001,35.43874],"type":"Point"}
}