{
  "type": "Feature",
  "properties": {
    "gn:admin1_code":"ESYE25",
    "gn:admin2_code":"42.0",
    "gn:admin3_code":"9248",
    "gn:asciiname":"Korogonianika",
    "gn:country_code":"GR",
    "gn:dem":381,
    "gn:feature_class":"P",
    "gn:feature_code":"PPL",
    "gn:name":"Korogoni\u00e1nika",
    "gn:population":3,
    "gn:timezone":"Europe/Athens",
    "iso:country":"GR",
    "name:ell_x_preferred":[
        "\u039a\u03bf\u03c1\u03bf\u03b3\u03bf\u03bd\u03b9\u03ac\u03bd\u03b9\u03ba\u03b1"
    ],
    "name:eng_x_preferred":[
        "Korogonianika"
    ],
    "name:und_x_variant":[
        "Korogom\u00e1nika",
        "Koroyi\u00e1nnika"
    ],
    "wof:name":"Korogonianika",
    "wof:placetype":"locality",
    "wof:population":3
},
  "geometry": {"coordinates":[22.48333,36.44616],"type":"Point"}
}