{
  "type": "Feature",
  "properties": {
    "gn:country":"GR",
    "gn:fcode":"PPL",
    "gn:population":0,
    "iso:country":"GR",
    "name:ell_x_preferred":[
        "\u039a\u03ac\u03bc\u03c0\u03bf\u03c2"
    ],
    "name:ell_x_variant":[
        "\u039a\u03ac\u03bc\u03c0\u03bf\u03c2 \u03a0\u03ac\u03c4\u03bc\u03bf\u03c5"
    ],
    "name:eng_x_preferred":[
        "Kampos"
    ],
    "name:und_x_variant":[
        "K\u00e1mpos"
    ],
    "qs_pg:aaroncc":"GR",
    "qs_pg:gn_country":"GR",
    "qs_pg:gn_fcode":"PPL",
    "qs_pg:gn_pop":0,
    "qs_pg:name":"Kambos",
    "qs_pg:name_adm0":"\u0395\u03bb\u03bb\u03ac\u03b4\u03b1",
    "qs_pg:name_adm1":"Aegean",
    "qs_pg:photos":53,
    "qs_pg:photos_1k":11,
    "qs_pg:photos_9k":1,
    "qs_pg:photos_9r":2,
    "qs_pg:photos_all":53,
    "qs_pg:photos_sr":2,
    "qs_pg:pop_sr":0,
    "qs_pg:qs_pg_placetype":"locality",
    "qs_pg:qs_pg_placetype_gp":"Town",
    "qs_pg:woe_adm0":23424833,
    "woe:adm0_id":23424833,
    "woe:name_adm0":"\u0395\u03bb\u03bb\u03ac\u03b4\u03b1",
    "woe:name_adm1":"Aegean",
    "woe:placetype":"Town",
    "wof:name":"Kambos",
    "wof:placetype":"locality",
    "wof:population":633
},
  "geometry": {"coordinates":[26.56667,37.35],"type":"Point"}
}