{
  "type": "Feature",
  "properties": {
    "gn:country":"GR",
    "gn:fcode":"PPL",
    "gn:population":67,
    "iso:country":"GR",
    "name:ell_x_preferred":[
        "\u039a\u03bf\u03c4\u03cd\u03bb\u03b7"
    ],
    "name:und_x_variant":[
        "Kot\u00edli"
    ],
    "qs_pg:aaroncc":"GR",
    "qs_pg:gn_country":"GR",
    "qs_pg:gn_fcode":"PPL",
    "qs_pg:gn_pop":67,
    "qs_pg:name":"Kot\u00fdli",
    "qs_pg:photos_9r":0,
    "qs_pg:photos_sr":0,
    "qs_pg:pop_sr":1,
    "qs_pg:qs_pg_placetype":"locality",
    "wof:name":"Kot\u00fdli",
    "wof:placetype":"locality",
    "wof:population":67
},
  "geometry": {"coordinates":[22.66306,40.97389],"type":"Point"}
}