{
  "type": "Feature",
  "properties": {
    "gn:admin1_code":"ESYE25",
    "gn:admin2_code":"37.0",
    "gn:admin3_code":"9243",
    "gn:asciiname":"Kavos Korfou",
    "gn:country_code":"GR",
    "gn:dem":20,
    "gn:feature_class":"P",
    "gn:feature_code":"PPL",
    "gn:name":"K\u00e1vos K\u00f3rfou",
    "gn:population":14,
    "gn:timezone":"Europe/Athens",
    "iso:country":"GR",
    "name:ell_x_preferred":[
        "\u039a\u03ac\u03b2\u03bf\u03c2 \u039a\u03cc\u03c1\u03c6\u03bf\u03c5"
    ],
    "name:eng_x_preferred":[
        "Kavos Korfou"
    ],
    "wof:name":"Kavos Korfou",
    "wof:placetype":"locality",
    "wof:population":14
},
  "geometry": {"coordinates":[23.13206,37.75994],"type":"Point"}
}