{
  "type": "Feature",
  "properties": {
    "gn:gn_country":"GR",
    "gn:gn_fcode":"PPL",
    "gn:gn_pop":766,
    "gn:population":766,
    "iso:country":"GR",
    "name:ell_x_preferred":[
        "\u03a0\u03c1\u03bf\u03b2\u03b1\u03c4\u03ce\u03bd"
    ],
    "name:ell_x_variant":[
        "Provat\u00f3nas",
        "\u03a0\u03c1\u03bf\u03b2\u03b1\u03c4\u03ce\u03bd\u03b1\u03c2"
    ],
    "qs_pg:aaroncc":"GR",
    "qs_pg:gn_country":"GR",
    "qs_pg:gn_fcode":"PPL",
    "qs_pg:gn_pop":766,
    "qs_pg:name":"Provat\u00f3n",
    "qs_pg:photos_9r":0,
    "qs_pg:photos_sr":0,
    "qs_pg:pop_sr":2,
    "qs_pg:qs_pg_placetype":"locality",
    "wof:name":"Provat\u00f3n",
    "wof:placetype":"locality",
    "wof:population":766
},
  "geometry": {"coordinates":[26.25833,41.0225],"type":"Point"}
}