{
  "type": "Feature",
  "properties": {
    "iso:country":"GR",
    "name:arz_x_preferred":[
        "\u0633\u064a\u062f\u0627\u0631\u0649"
    ],
    "name:ceb_x_preferred":[
        "Sid\u00e1ri"
    ],
    "name:ces_x_preferred":[
        "Sidari"
    ],
    "name:deu_x_preferred":[
        "Sidari"
    ],
    "name:ell_x_preferred":[
        "\u03a3\u03b9\u03b4\u03ac\u03c1\u03b9 \u039a\u03ad\u03c1\u03ba\u03c5\u03c1\u03b1\u03c2"
    ],
    "name:eng_x_preferred":[
        "Sidari"
    ],
    "name:fin_x_preferred":[
        "Sid\u00e1ri"
    ],
    "name:fra_x_preferred":[
        "Sidari"
    ],
    "name:fra_x_variant":[
        "Sid\u00e1ri"
    ],
    "name:lat_x_preferred":[
        "Sidarium"
    ],
    "name:nld_x_preferred":[
        "Sidari"
    ],
    "name:pol_x_preferred":[
        "Sidari"
    ],
    "name:rus_x_preferred":[
        "\u0421\u0438\u0434\u0430\u0440\u0438\u043e\u043d"
    ],
    "name:swe_x_preferred":[
        "Sid\u00e1ri"
    ],
    "name:swe_x_variant":[
        "Profitis Ilias"
    ],
    "qs_pg:aaroncc":"GR",
    "qs_pg:name":"Sidari",
    "qs_pg:name_adm0":"\u0395\u03bb\u03bb\u03ac\u03b4\u03b1",
    "qs_pg:name_adm1":"Peloponnese Western Greece and the Ionian Islands",
    "qs_pg:photos":303,
    "qs_pg:photos_1k":61,
    "qs_pg:photos_9k":1,
    "qs_pg:photos_9r":5,
    "qs_pg:photos_all":303,
    "qs_pg:photos_sr":5,
    "qs_pg:pop_sr":0,
    "qs_pg:qs_pg_placetype":"locality",
    "qs_pg:qs_pg_placetype_gp":"Town",
    "qs_pg:woe_adm0":23424833,
    "woe:adm0_id":23424833,
    "woe:name_adm0":"\u0395\u03bb\u03bb\u03ac\u03b4\u03b1",
    "woe:name_adm1":"Peloponnese Western Greece and the Ionian Islands",
    "woe:placetype":"Town",
    "wof:name":"Sidari",
    "wof:placetype":"locality"
},
  "geometry": {"coordinates":[19.709365,39.786906],"type":"Point"}
}