{
  "type": "Feature",
  "properties": {
    "gn:admin1_code":"ESYE31",
    "gn:admin2_code":"445407.0",
    "gn:admin3_code":"9231.0",
    "gn:asciiname":"Panorama",
    "gn:country_code":"GR",
    "gn:dem":33,
    "gn:feature_class":"P",
    "gn:feature_code":"PPL",
    "gn:name":"Pan\u00f3rama",
    "gn:population":0,
    "gn:timezone":"Europe/Athens",
    "iso:country":"GR",
    "name:ell_x_preferred":[
        "Pan\u00f3rama"
    ],
    "name:ell_x_variant":[
        "\u03a0\u03b1\u03bd\u03cc\u03c1\u03b1\u03bc\u03b1"
    ],
    "wof:name":"Panorama",
    "wof:placetype":"locality"
},
  "geometry": {"coordinates":[23.31713,37.9745],"type":"Point"}
}