{
  "type": "Feature",
  "properties": {
    "gn:population":4323,
    "iso:country":"GR",
    "name:ara_x_preferred":[
        "\u0623\u064a\u062a\u0648\u0644\u064a\u0643\u0648"
    ],
    "name:ceb_x_preferred":[
        "Aitolik\u00f3"
    ],
    "name:cym_x_preferred":[
        "Aitoliko"
    ],
    "name:deu_x_preferred":[
        "Etoliko"
    ],
    "name:ell_x_preferred":[
        "\u0391\u03b9\u03c4\u03c9\u03bb\u03b9\u03ba\u03cc"
    ],
    "name:ell_x_variant":[
        "\u0391\u03b9\u03c4\u03c9\u03bb\u03b9\u03ba\u03cc\u03bd",
        "\u0391\u03b9\u03c4\u03c9\u03bb\u03b9\u03ba\u03cc \u0391\u03b9\u03c4\u03c9\u03bb\u03bf\u03b1\u03ba\u03b1\u03c1\u03bd\u03b1\u03bd\u03af\u03b1\u03c2"
    ],
    "name:eng_x_preferred":[
        "Aitoliko"
    ],
    "name:fin_x_preferred":[
        "Aitolik\u00f3"
    ],
    "name:fra_x_preferred":[
        "Aitoliko"
    ],
    "name:ita_x_preferred":[
        "Aitoliko"
    ],
    "name:jpn_x_preferred":[
        "\u30a8\u30c8\u30ea\u30b3"
    ],
    "name:nld_x_preferred":[
        "Aitoliko"
    ],
    "name:nno_x_preferred":[
        "Etolik\u00f3"
    ],
    "name:pol_x_preferred":[
        "Etoliko"
    ],
    "name:ron_x_preferred":[
        "Aitoliko"
    ],
    "name:swe_x_preferred":[
        "Aitolik\u00f3"
    ],
    "name:unk_x_variant":[
        "Etolikon"
    ],
    "qs:a0":"Greece",
    "qs:a1":"*\u0394\u03a5\u03a4\u0399\u039a\u0397 \u0395\u039b\u039b\u0391\u0394\u0391",
    "qs:a1_alt":"DYTIKH ELLADA",
    "qs:a1r":"0",
    "qs:a2_alt":"AITVLIA KAI AKARNANIA",
    "qs:adm0":"Greece",
    "qs:la_lc":"*",
    "qs:level":"locality",
    "qs:loc":"\u0391\u0399\u03a4\u03a9\u039b\u0399\u039a\u039f\u039d",
    "qs:loc_alt":"AITVLIKON",
    "qs:pop":0,
    "qs:type":"buffered point",
    "wd:wordcount":922,
    "wof:name":"\u0391\u0399\u03a4\u03a9\u039b\u0399\u039a\u039f\u039d",
    "wof:placetype":"locality",
    "wof:population":4323
},
  "geometry": {"coordinates":[21.352947,38.43856],"type":"Point"}
}