{
  "type": "Feature",
  "properties": {
    "gn:population":2009,
    "iso:country":"GR",
    "name:ara_x_preferred":[
        "\u0645\u0627\u0643\u0631\u064a\u064a\u064a\u0627\u0644\u0648\u0633\u060c \u0628\u064a\u0631\u064a\u0627"
    ],
    "name:ara_x_variant":[
        "\u0645\u0627\u0643\u0631\u064a\u064a\u064a\u0627\u0644\u0648\u0633"
    ],
    "name:bul_x_preferred":[
        "\u041c\u0430\u043a\u0440\u0438\u044f\u043b\u043e\u0441"
    ],
    "name:ceb_x_preferred":[
        "Makr\u00fdgialos"
    ],
    "name:ell_x_preferred":[
        "\u039c\u03b1\u03ba\u03c1\u03cd\u03b3\u03b9\u03b1\u03bb\u03bf\u03c2"
    ],
    "name:ell_x_variant":[
        "\u039c\u03b1\u03ba\u03c1\u03cd\u03b3\u03b9\u03b1\u03bb\u03bf\u03c2 \u03a0\u03b9\u03b5\u03c1\u03af\u03b1\u03c2"
    ],
    "name:eng_x_preferred":[
        "Makrygialos"
    ],
    "name:hun_x_preferred":[
        "Makrigialos"
    ],
    "name:lat_x_preferred":[
        "Macrygialus"
    ],
    "name:nld_x_preferred":[
        "Makrygialos"
    ],
    "name:nno_x_preferred":[
        "Makr\u00fdjalos"
    ],
    "name:rus_x_preferred":[
        "\u041c\u0430\u043a\u0440\u0438\u044f\u043b\u043e\u0441"
    ],
    "name:swe_x_preferred":[
        "Makr\u00fdgialos"
    ],
    "name:und_x_variant":[
        "Makr\u00edyialos"
    ],
    "qs:a0":"Greece",
    "qs:a1":"*\u039a\u0395\u039d\u03a4\u03a1\u0399\u039a\u0397 \u039c\u0391\u039a\u0395\u0394\u039f\u039d\u0399\u0391",
    "qs:a1_alt":"KENTRIKH MAKEDONIA",
    "qs:a1r":"0",
    "qs:a2_alt":"PIERIA",
    "qs:adm0":"Greece",
    "qs:la_lc":"*",
    "qs:level":"locality",
    "qs:loc":"\u039c\u0391\u039a\u03a1\u03a5\u0393\u0399\u0391\u039b\u039f\u03a3",
    "qs:loc_alt":"MAKRYGIALOS",
    "qs:pop":0,
    "qs:type":"buffered point",
    "wof:name":"\u039c\u0391\u039a\u03a1\u03a5\u0393\u0399\u0391\u039b\u039f\u03a3",
    "wof:placetype":"locality",
    "wof:population":2009
},
  "geometry": {"coordinates":[22.603309,40.415401],"type":"Point"}
}