{
  "type": "Feature",
  "properties": {
    "gn:admin1_code":"ESYE21",
    "gn:admin2_code":"20.0",
    "gn:admin3_code":"9075",
    "gn:asciiname":"Tsoumanikaiika",
    "gn:country_code":"GR",
    "gn:dem":731,
    "gn:feature_class":"P",
    "gn:feature_code":"PPL",
    "gn:name":"Tsoumanika\u00edika",
    "gn:population":0,
    "gn:timezone":"Europe/Athens",
    "iso:country":"GR",
    "wof:name":"Tsoumanikaiika",
    "wof:placetype":"locality"
},
  "geometry": {"coordinates":[21.31667,39.35],"type":"Point"}
}