{
  "type": "Feature",
  "properties": {
    "gn:admin1_code":"ESYE11",
    "gn:admin2_code":"14.0",
    "gn:admin3_code":"9014",
    "gn:asciiname":"Avli",
    "gn:country_code":"GR",
    "gn:dem":146,
    "gn:feature_class":"P",
    "gn:feature_code":"PPL",
    "gn:name":"Avl\u00ed",
    "gn:population":504,
    "gn:timezone":"Europe/Athens",
    "iso:country":"GR",
    "name:ell_x_historical":[
        "\u0393\u03ad\u03c6\u03c5\u03c1\u03b1 \u0391\u03c5\u03bb\u03ae\u03c2"
    ],
    "name:ell_x_preferred":[
        "\u0391\u03c5\u03bb\u03ae"
    ],
    "name:ell_x_variant":[
        "Avl\u00ed",
        "\u0393\u03ad\u03c6\u03c5\u03c1\u03b1 \u0391\u03c5\u03bb\u03ae\u03c2"
    ],
    "name:eng_x_historical":[
        "Gefyra Avlis",
        "Gefyria Avlis"
    ],
    "name:eng_x_preferred":[
        "Avli"
    ],
    "name:eng_x_variant":[
        "Gefyra Avlis",
        "Gefyria Avlis"
    ],
    "wof:name":"Avli",
    "wof:placetype":"locality",
    "wof:population":504
},
  "geometry": {"coordinates":[24.17889,40.87302],"type":"Point"}
}