{
  "type": "Feature",
  "properties": {
    "gn:admin1_code":"ESYE24",
    "gn:admin2_code":"34.0",
    "gn:admin3_code":"9148",
    "gn:asciiname":"Agriosikea",
    "gn:cc2":"GR",
    "gn:country_code":"GR",
    "gn:dem":456,
    "gn:feature_class":"P",
    "gn:feature_code":"PPL",
    "gn:name":"Agriosik\u00e9a",
    "gn:population":0,
    "gn:timezone":"Europe/Athens",
    "iso:country":"GR",
    "name:und_x_variant":[
        "Agrosik\u00e9a",
        "Agrosiki\u00e1",
        "Agriosiki\u00e1",
        "Agriosik\u00e9a"
    ],
    "wof:name":"Agriosikea",
    "wof:placetype":"locality"
},
  "geometry": {"coordinates":[23.79093,38.66645],"type":"Point"}
}