{
  "type": "Feature",
  "properties": {
    "gn:admin1_code":"ESYE23",
    "gn:admin2_code":"31.0",
    "gn:admin3_code":"9125",
    "gn:asciiname":"Kampraki",
    "gn:country_code":"GR",
    "gn:dem":457,
    "gn:feature_class":"P",
    "gn:feature_code":"PPL",
    "gn:name":"Kampr\u00e1ki",
    "gn:population":0,
    "gn:timezone":"Europe/Athens",
    "iso:country":"GR",
    "name:ell_x_preferred":[
        "Kampr\u00e1ki"
    ],
    "name:ell_x_variant":[
        "Kampr\u00e1kion",
        "\u039a\u03b1\u03bc\u03c0\u03c1\u03ac\u03ba\u03b9",
        "\u039a\u03b1\u03bc\u03c0\u03c1\u03ac\u03ba\u03b9\u03bf\u03bd"
    ],
    "wof:name":"Kampraki",
    "wof:placetype":"locality"
},
  "geometry": {"coordinates":[21.295,39.00167],"type":"Point"}
}