{
  "type": "Feature",
  "properties": {
    "gn:admin1_code":"ESYE13",
    "gn:admin2_code":"11.0",
    "gn:admin3_code":"9066",
    "gn:asciiname":"Rodochori",
    "gn:country_code":"GR",
    "gn:dem":722,
    "gn:feature_class":"P",
    "gn:feature_code":"PPL",
    "gn:name":"Rodochori",
    "gn:population":0,
    "gn:timezone":"Europe/Athens",
    "iso:country":"GR",
    "name:bul_x_preferred":[
        "\u0420\u043e\u0434\u043e\u0445\u043e\u0440\u0438"
    ],
    "name:mkd_x_preferred":[
        "\u0420\u0430\u0434\u043e\u0432\u0438\u0448\u0442\u0430"
    ],
    "wof:name":"Rodochori",
    "wof:placetype":"locality"
},
  "geometry": {"coordinates":[21.29189,40.20884],"type":"Point"}
}