{
  "type": "Feature",
  "properties": {
    "gn:admin1_code":"ESYE25",
    "gn:admin2_code":"41.0",
    "gn:admin3_code":"9240",
    "gn:asciiname":"Platanaki",
    "gn:country_code":"GR",
    "gn:dem":915,
    "gn:feature_class":"P",
    "gn:feature_code":"PPL",
    "gn:name":"Platan\u00e1ki",
    "gn:population":0,
    "gn:timezone":"Europe/Athens",
    "iso:country":"GR",
    "name:ell_x_preferred":[
        "Platan\u00e1ki"
    ],
    "name:ell_x_variant":[
        "\u03a0\u03bb\u03b1\u03c4\u03b1\u03bd\u03ac\u03ba\u03b9",
        "Platan\u00e1kion",
        "\u03a0\u03bb\u03b1\u03c4\u03b1\u03bd\u03ac\u03ba\u03b9\u03bf\u03bd"
    ],
    "wof:name":"Platanaki",
    "wof:placetype":"locality"
},
  "geometry": {"coordinates":[22.66741,37.17063],"type":"Point"}
}