{
  "type": "Feature",
  "properties": {
    "gn:country":"GR",
    "gn:fcode":"PPL",
    "gn:population":92,
    "iso:country":"GR",
    "name:ell_x_preferred":[
        "\u039a\u03bf\u03bb\u03c9\u03bd\u03b9\u03ac\u03c4\u03b9"
    ],
    "name:ell_x_variant":[
        "\u039a\u03bf\u03bb\u03c9\u03bd\u03b9\u03ac\u03c4\u03b9\u03bf\u03bd"
    ],
    "name:eng_x_preferred":[
        "Koloniati"
    ],
    "name:und_x_variant":[
        "Koloni\u00e1tes"
    ],
    "qs_pg:aaroncc":"GR",
    "qs_pg:gn_country":"GR",
    "qs_pg:gn_fcode":"PPL",
    "qs_pg:gn_pop":92,
    "qs_pg:name":"Koloni\u00e1tion",
    "qs_pg:photos_9r":0,
    "qs_pg:photos_sr":0,
    "qs_pg:pop_sr":1,
    "qs_pg:qs_pg_placetype":"locality",
    "wof:name":"Koloni\u00e1tion",
    "wof:placetype":"locality",
    "wof:population":77
},
  "geometry": {"coordinates":[20.88806,39.57806],"type":"Point"}
}