{
  "type": "Feature",
  "properties": {
    "gn:admin1_code":"ESYE21",
    "gn:admin2_code":"20.0",
    "gn:admin3_code":"9075",
    "gn:asciiname":"Ntiveraiika",
    "gn:country_code":"GR",
    "gn:dem":162,
    "gn:feature_class":"P",
    "gn:feature_code":"PPL",
    "gn:name":"Ntivera\u00edika",
    "gn:population":0,
    "gn:timezone":"Europe/Athens",
    "iso:country":"GR",
    "name:ell_x_preferred":[
        "Ntivera\u00edika"
    ],
    "name:ell_x_variant":[
        "\u039d\u03c4\u03b9\u03b2\u03b5\u03c1\u03b1\u03af\u03b9\u03ba\u03b1"
    ],
    "name:und_x_variant":[
        "Tsop\u00e1dhes",
        "Sini\u00e1gkos",
        "Sini\u00e1ngos",
        "P\u00e9rama"
    ],
    "wof:name":"Ntiveraiika",
    "wof:placetype":"locality"
},
  "geometry": {"coordinates":[21.01431,39.26517],"type":"Point"}
}