{
  "type": "Feature",
  "properties": {
    "gn:admin1_code":"ESYE42",
    "gn:admin2_code":"49.0",
    "gn:admin3_code":"9287",
    "gn:asciiname":"Trypiti",
    "gn:country_code":"GR",
    "gn:dem":138,
    "gn:elevation":"103.0",
    "gn:feature_class":"P",
    "gn:feature_code":"PPL",
    "gn:name":"Trypit\u00ed",
    "gn:population":540,
    "gn:timezone":"Europe/Athens",
    "iso:country":"GR",
    "name:ceb_x_preferred":[
        "Tripit\u00ed"
    ],
    "name:ell_x_preferred":[
        "\u03a4\u03c1\u03c5\u03c0\u03b7\u03c4\u03ae"
    ],
    "name:eng_x_preferred":[
        "Tripiti"
    ],
    "name:eng_x_variant":[
        "Trypiti"
    ],
    "name:ita_x_preferred":[
        "Tripiti"
    ],
    "name:rus_x_preferred":[
        "\u0422\u0440\u0438\u043f\u0438\u0442\u0438"
    ],
    "name:swe_x_preferred":[
        "Tripit\u00ed"
    ],
    "name:ukr_x_preferred":[
        "\u0422\u0440\u0456\u043f\u0456\u0442\u0456"
    ],
    "name:und_x_variant":[
        "Tripit\u00ed",
        "Trypiti"
    ],
    "wof:name":"Trypiti",
    "wof:placetype":"locality",
    "wof:population":540
},
  "geometry": {"coordinates":[24.42765,36.73718],"type":"Point"}
}