{
  "type": "Feature",
  "properties": {
    "gn:admin1_code":"ESYE23",
    "gn:admin2_code":"31.0",
    "gn:admin3_code":"9123",
    "gn:asciiname":"Varkoulia",
    "gn:country_code":"GR",
    "gn:dem":303,
    "gn:feature_class":"P",
    "gn:feature_code":"PPL",
    "gn:name":"Varko\u00falia",
    "gn:population":21,
    "gn:timezone":"Europe/Athens",
    "iso:country":"GR",
    "name:ell_x_preferred":[
        "\u0392\u03b1\u03c1\u03ba\u03bf\u03cd\u03bb\u03b9\u03b1"
    ],
    "name:eng_x_preferred":[
        "Varkoulia"
    ],
    "wof:name":"Varkoulia",
    "wof:placetype":"locality",
    "wof:population":21
},
  "geometry": {"coordinates":[21.47152,38.70064],"type":"Point"}
}