{
  "type": "Feature",
  "properties": {
    "gn:admin1_code":"ESYE24",
    "gn:admin2_code":"34.0",
    "gn:admin3_code":"9148",
    "gn:asciiname":"Steni Dhirfios",
    "gn:cc2":"GR",
    "gn:country_code":"GR",
    "gn:dem":426,
    "gn:feature_class":"P",
    "gn:feature_code":"PPL",
    "gn:name":"Sten\u00ed Dh\u00edrfios",
    "gn:population":0,
    "gn:timezone":"Europe/Athens",
    "iso:country":"GR",
    "name:ell_x_preferred":[
        "\u03a3\u03c4\u03b5\u03bd\u03ae \u0394\u03af\u03c1\u03c6\u03c5\u03bf\u03c2"
    ],
    "name:und_x_variant":[
        "Sten\u00ed",
        "Sten\u00ed Dh\u00edrfios"
    ],
    "wof:name":"Steni Dhirfios",
    "wof:placetype":"locality"
},
  "geometry": {"coordinates":[23.83806,38.58125],"type":"Point"}
}