{
  "type": "Feature",
  "properties": {
    "gn:elevation":125,
    "gn:population":1292,
    "iso:country":"GR",
    "name:ara_x_preferred":[
        "\u0625\u0643\u0633\u0627\u0628\u0644\u0627\u062a\u0627\u0646\u0648\u0633"
    ],
    "name:arz_x_preferred":[
        "\u0627\u0643\u0633\u0627\u0628\u0644\u0627\u062a\u0627\u0646\u0648\u0633"
    ],
    "name:bul_x_preferred":[
        "\u041a\u044a\u043f\u0438\u043d\u044f\u043d\u0438"
    ],
    "name:ceb_x_preferred":[
        "Exapl\u00e1tanos"
    ],
    "name:deu_x_preferred":[
        "Exaplatanos"
    ],
    "name:ell_x_preferred":[
        "\u0394\u03ae\u03bc\u03bf\u03c2 \u0395\u03be\u03b1\u03c0\u03bb\u03b1\u03c4\u03ac\u03bd\u03bf\u03c5"
    ],
    "name:ell_x_variant":[
        "\u0395\u03be\u03b1\u03c0\u03bb\u03ac\u03c4\u03b1\u03bd\u03bf\u03c2"
    ],
    "name:eng_x_preferred":[
        "Exaplatanos"
    ],
    "name:eng_x_variant":[
        "Exaplatanos municipality"
    ],
    "name:fin_x_preferred":[
        "Exapl\u00e1tanos"
    ],
    "name:fra_x_preferred":[
        "Exaplatanos"
    ],
    "name:ita_x_preferred":[
        "Exaplatanos"
    ],
    "name:jpn_x_preferred":[
        "\u30a8\u30af\u30b5\u30d7\u30e9\u30bf\u30ce\u30b9"
    ],
    "name:mkd_x_preferred":[
        "\u041a\u0430\u043f\u0438\u045a\u0430\u043d\u0438"
    ],
    "name:nld_x_preferred":[
        "Exaplatanos"
    ],
    "name:nno_x_preferred":[
        "Exapl\u00e1tanos"
    ],
    "name:swe_x_preferred":[
        "Exapl\u00e1tanos"
    ],
    "name:und_x_variant":[
        "Kap\u00edniani"
    ],
    "name:zho_x_preferred":[
        "\u57c3\u514b\u8428\u666e\u62c9\u5854\u8bfa\u65af"
    ],
    "qs:a0":"Greece",
    "qs:a1":"*\u039a\u0395\u039d\u03a4\u03a1\u0399\u039a\u0397 \u039c\u0391\u039a\u0395\u0394\u039f\u039d\u0399\u0391",
    "qs:a1_alt":"KENTRIKH MAKEDONIA",
    "qs:a1r":"0",
    "qs:a2_alt":"PELLA",
    "qs:adm0":"Greece",
    "qs:la_lc":"*",
    "qs:level":"locality",
    "qs:loc":"\u0395\u039e\u0391\u03a0\u039b\u0391\u03a4\u0391\u039d\u039f\u03a3",
    "qs:loc_alt":"EJAPLATANOS",
    "qs:pop":0,
    "qs:type":"buffered point",
    "wd:wordcount":119,
    "wof:name":"\u0395\u039e\u0391\u03a0\u039b\u0391\u03a4\u0391\u039d\u039f\u03a3",
    "wof:placetype":"locality",
    "wof:population":1292
},
  "geometry": {"coordinates":[22.130588,40.977528],"type":"Point"}
}