{
  "type": "Feature",
  "properties": {
    "gn:gn_country":"GR",
    "gn:gn_fcode":"PPL",
    "gn:gn_pop":10,
    "gn:population":10,
    "iso:country":"GR",
    "name:ell_x_preferred":[
        "Aron\u00e1tika"
    ],
    "name:ell_x_variant":[
        "\u0391\u03c1\u03c9\u03bd\u03ac\u03c4\u03b9\u03ba\u03b1"
    ],
    "qs_pg:aaroncc":"GR",
    "qs_pg:gn_country":"GR",
    "qs_pg:gn_fcode":"PPL",
    "qs_pg:gn_pop":10,
    "qs_pg:name":"Aron\u00e1tika",
    "qs_pg:photos_9r":0,
    "qs_pg:photos_sr":0,
    "qs_pg:pop_sr":1,
    "qs_pg:qs_pg_placetype":"locality",
    "wof:name":"Aron\u00e1tika",
    "wof:placetype":"locality",
    "wof:population":10
},
  "geometry": {"coordinates":[20.13139,39.22556],"type":"Point"}
}