{
  "type": "Feature",
  "properties": {
    "gn:gn_country":"GR",
    "gn:gn_fcode":"PPLA3",
    "gn:gn_pop":1129,
    "gn:population":1129,
    "iso:country":"GR",
    "name:ara_x_preferred":[
        "\u0623\u0633\u062a\u064a\u0628\u0627\u0644\u064a\u0627"
    ],
    "name:cat_x_preferred":[
        "Astip\u00e0lea"
    ],
    "name:ceb_x_preferred":[
        "Astyp\u00e1laia"
    ],
    "name:ces_x_preferred":[
        "Astypalaia"
    ],
    "name:dan_x_preferred":[
        "Astip\u00e1lea"
    ],
    "name:deu_x_preferred":[
        "Astypalea"
    ],
    "name:ell_x_preferred":[
        "\u0391\u03c3\u03c4\u03c5\u03c0\u03ac\u03bb\u03b1\u03b9\u03b1"
    ],
    "name:est_x_preferred":[
        "Astyp\u00e1laia saar"
    ],
    "name:fin_x_preferred":[
        "Astyp\u00e1laia"
    ],
    "name:fra_x_preferred":[
        "Astypal\u00e9e"
    ],
    "name:glg_x_preferred":[
        "Astipalea"
    ],
    "name:heb_x_preferred":[
        "\u05d0\u05e1\u05d8\u05d9\u05e4\u05dc\u05d9\u05d4"
    ],
    "name:hrv_x_preferred":[
        "Astipalea"
    ],
    "name:ind_x_preferred":[
        "Astipalea"
    ],
    "name:ita_x_preferred":[
        "Stampalia"
    ],
    "name:jpn_x_preferred":[
        "\u30a2\u30b9\u30c6\u30a3\u30d1\u30ec\u30a2\u5cf6"
    ],
    "name:lat_x_preferred":[
        "Astypalaea"
    ],
    "name:mkd_x_preferred":[
        "\u0410\u0441\u0442\u0438\u043f\u0430\u043b\u0435\u0430"
    ],
    "name:nld_x_preferred":[
        "Astipalaia"
    ],
    "name:nno_x_preferred":[
        "Astyp\u00e1lea"
    ],
    "name:nor_x_preferred":[
        "Astypalaia"
    ],
    "name:pol_x_preferred":[
        "Astipalea"
    ],
    "name:por_x_preferred":[
        "Astipaleia"
    ],
    "name:rus_x_preferred":[
        "\u0410\u0441\u0442\u0438\u043f\u0430\u043b\u0435\u044f"
    ],
    "name:spa_x_preferred":[
        "Astipalea"
    ],
    "name:srp_x_preferred":[
        "\u0410\u0441\u0442\u0438\u043f\u0430\u043b\u0435\u0430"
    ],
    "name:swe_x_preferred":[
        "Astypalaia"
    ],
    "name:tha_x_preferred":[
        "\u0e2d\u0e31\u0e2a\u0e15\u0e34\u0e1e\u0e32\u0e40\u0e25\u0e35\u0e22"
    ],
    "name:ukr_x_preferred":[
        "\u0410\u0441\u0442\u0438\u043f\u0430\u043b\u0435\u044f"
    ],
    "name:unk_x_variant":[
        "Castello"
    ],
    "name:vie_x_preferred":[
        "Astypalea"
    ],
    "name:zho_x_preferred":[
        "\u65af\u5766\u5e15\u5229\u4e9e\u5cf6"
    ],
    "qs_pg:aaroncc":"GR",
    "qs_pg:gn_country":"GR",
    "qs_pg:gn_fcode":"PPLA3",
    "qs_pg:gn_pop":1129,
    "qs_pg:name":"Astypalaia",
    "qs_pg:name_adm0":"\u0395\u03bb\u03bb\u03ac\u03b4\u03b1",
    "qs_pg:name_adm1":"Aegean",
    "qs_pg:photos":241,
    "qs_pg:photos_1k":49,
    "qs_pg:photos_9k":5,
    "qs_pg:photos_9r":7,
    "qs_pg:photos_all":1056,
    "qs_pg:photos_sr":4,
    "qs_pg:pop_sr":3,
    "qs_pg:qs_pg_placetype":"localadmin",
    "qs_pg:qs_pg_placetype_gp":"LocalAdmin",
    "qs_pg:woe_adm0":23424833,
    "woe:adm0_id":23424833,
    "woe:name_adm0":"\u0395\u03bb\u03bb\u03ac\u03b4\u03b1",
    "woe:name_adm1":"Aegean",
    "woe:placetype":"LocalAdmin",
    "wof:name":"Astypalaia",
    "wof:placetype":"localadmin",
    "wof:population":1129
},
  "geometry": {"coordinates":[26.35,36.55],"type":"Point"}
}