{
  "type": "Feature",
  "properties": {
    "gn:gn_country":"GR",
    "gn:gn_fcode":"PPLA3",
    "gn:gn_pop":1129,
    "gn:population":1129,
    "iso:country":"GR",
    "name:ell_x_preferred":[
        "\u0391\u03c3\u03c4\u03c5\u03c0\u03ac\u03bb\u03b1\u03b9\u03b1"
    ],
    "name:unk_x_variant":[
        "Castello"
    ],
    "qs_pg:aaroncc":"GR",
    "qs_pg:gn_country":"GR",
    "qs_pg:gn_fcode":"PPLA3",
    "qs_pg:gn_pop":1129,
    "qs_pg:name":"Astypalaia",
    "qs_pg:name_adm0":"\u0395\u03bb\u03bb\u03ac\u03b4\u03b1",
    "qs_pg:name_adm1":"Aegean",
    "qs_pg:photos":241,
    "qs_pg:photos_1k":49,
    "qs_pg:photos_9k":5,
    "qs_pg:photos_9r":7,
    "qs_pg:photos_all":1056,
    "qs_pg:photos_sr":4,
    "qs_pg:pop_sr":3,
    "qs_pg:qs_pg_placetype":"localadmin",
    "qs_pg:qs_pg_placetype_gp":"LocalAdmin",
    "qs_pg:woe_adm0":23424833,
    "woe:adm0_id":23424833,
    "woe:name_adm0":"\u0395\u03bb\u03bb\u03ac\u03b4\u03b1",
    "woe:name_adm1":"Aegean",
    "woe:placetype":"LocalAdmin",
    "wof:name":"Astypalaia",
    "wof:placetype":"localadmin",
    "wof:population":1129
},
  "geometry": {"coordinates":[26.35,36.55],"type":"Point"}
}