{
  "type": "Feature",
  "properties": {
    "gn:admin1_code":"ESYE23",
    "gn:admin2_code":"31.0",
    "gn:admin3_code":"9123",
    "gn:asciiname":"Potamoula Mesolongiou",
    "gn:country_code":"GR",
    "gn:dem":295,
    "gn:feature_class":"P",
    "gn:feature_code":"PPL",
    "gn:name":"Potamo\u00fala Mesolong\u00edou",
    "gn:population":22,
    "gn:timezone":"Europe/Athens",
    "iso:country":"GR",
    "name:ell_x_preferred":[
        "\u03a0\u03bf\u03c4\u03b1\u03bc\u03bf\u03cd\u03bb\u03b1 \u039c\u03b5\u03c3\u03bf\u03bb\u03bf\u03b3\u03b3\u03af\u03bf\u03c5"
    ],
    "name:eng_x_preferred":[
        "Potamoula Mesol\u03bfngiou"
    ],
    "wof:name":"Potamoula Mesolongiou",
    "wof:placetype":"locality",
    "wof:population":22
},
  "geometry": {"coordinates":[21.5646,38.46344000000001],"type":"Point"}
}