{
  "type": "Feature",
  "properties": {
    "gn:population":1529,
    "iso:country":"GR",
    "name:bul_x_preferred":[
        "\u0421\u0442\u0430\u0432\u0440\u043e\u0441"
    ],
    "name:dut_x_preferred":[
        "stavros verias"
    ],
    "name:ell_x_preferred":[
        "Stavr\u00f3s"
    ],
    "name:ell_x_variant":[
        "\u03a3\u03c4\u03b1\u03c5\u03c1\u03cc\u03c2"
    ],
    "name:eng_x_preferred":[
        "stavros verias"
    ],
    "name:ger_x_preferred":[
        "stavros  verias"
    ],
    "name:gre_x_preferred":[
        "\u03a3\u03c4\u03b1\u03c5\u03c1\u03cc\u03c2 \u0397\u03bc\u03b1\u03b8\u03af\u03b1\u03c2"
    ],
    "qs:a0":"Greece",
    "qs:a1":"*\u039a\u0395\u039d\u03a4\u03a1\u0399\u039a\u0397 \u039c\u0391\u039a\u0395\u0394\u039f\u039d\u0399\u0391",
    "qs:a1_alt":"KENTRIKH MAKEDONIA",
    "qs:a1r":"0",
    "qs:a2_alt":"HMAUIA",
    "qs:adm0":"Greece",
    "qs:la_lc":"*",
    "qs:level":"locality",
    "qs:loc":"\u03a3\u03a4\u0391\u03a5\u03a1\u039f\u03a3",
    "qs:loc_alt":"STAYROS",
    "qs:pop":0,
    "qs:type":"buffered point",
    "wof:name":"\u03a3\u03a4\u0391\u03a5\u03a1\u039f\u03a3",
    "wof:placetype":"locality",
    "wof:population":1529
},
  "geometry": {"coordinates":[22.310681,40.588393],"type":"Point"}
}