{
  "type": "Feature",
  "properties": {
    "gn:admin1_code":"ESYE24",
    "gn:admin2_code":"29.0",
    "gn:admin3_code":"9159",
    "gn:asciiname":"Makrolivadhon",
    "gn:country_code":"GR",
    "gn:dem":588,
    "gn:feature_class":"P",
    "gn:feature_code":"PPL",
    "gn:name":"Makrol\u00edvadhon",
    "gn:population":202,
    "gn:timezone":"Europe/Athens",
    "iso:country":"GR",
    "name:ell_x_preferred":[
        "\u039c\u03b1\u03ba\u03c1\u03bf\u03bb\u03af\u03b2\u03b1\u03b4\u03bf"
    ],
    "name:ell_x_variant":[
        "\u039c\u03b1\u03ba\u03c1\u03bf\u03bb\u03af\u03b2\u03b1\u03b4\u03bf\u03bd"
    ],
    "name:eng_x_preferred":[
        "Makrolivado"
    ],
    "name:und_x_variant":[
        "Dhram\u00e1la",
        "Makrol\u00edradhon",
        "Makrol\u00edvadhon"
    ],
    "wof:name":"Makrolivadhon",
    "wof:placetype":"locality",
    "wof:population":202
},
  "geometry": {"coordinates":[22.41913,39.03749000000001],"type":"Point"}
}