{
  "type": "Feature",
  "properties": {
    "gn:admin1_code":"ESYE43",
    "gn:admin2_code":"43.0",
    "gn:admin3_code":"9325",
    "gn:asciiname":"Argoulides",
    "gn:country_code":"GR",
    "gn:dem":120,
    "gn:feature_class":"P",
    "gn:feature_code":"PPL",
    "gn:name":"Argoulid\u00e9s",
    "gn:population":0,
    "gn:timezone":"Europe/Athens",
    "iso:country":"GR",
    "name:ell_x_preferred":[
        "Argoulid\u00e9s"
    ],
    "name:ell_x_variant":[
        "\u0391\u03c1\u03b3\u03bf\u03c5\u03bb\u03b9\u03b4\u03ad\u03c2",
        "Argoulidh\u00e9s"
    ],
    "wof:name":"Argoulides",
    "wof:placetype":"locality"
},
  "geometry": {"coordinates":[24.09653,35.52397],"type":"Point"}
}