{
  "type": "Feature",
  "properties": {
    "gn:country":"GR",
    "gn:fcode":"PPL",
    "gn:population":1502,
    "iso:country":"GR",
    "name:ell_x_preferred":[
        "\u039d\u03b9\u03ba\u03cc\u03ba\u03bb\u03b5\u03b9\u03b1"
    ],
    "name:ell_x_variant":[
        "Nik\u00f3kleia"
    ],
    "name:eng_x_preferred":[
        "Nikokleia"
    ],
    "name:und_x_variant":[
        "Nikosl\u00e1vi"
    ],
    "qs_pg:aaroncc":"GR",
    "qs_pg:gn_country":"GR",
    "qs_pg:gn_fcode":"PPL",
    "qs_pg:gn_pop":1502,
    "qs_pg:name":"Nikoklia",
    "qs_pg:name_adm0":"\u0395\u03bb\u03bb\u03ac\u03b4\u03b1",
    "qs_pg:name_adm1":"Macedonia and Thrace",
    "qs_pg:photos_9r":0,
    "qs_pg:photos_sr":0,
    "qs_pg:pop_sr":3,
    "qs_pg:qs_pg_placetype":"locality",
    "qs_pg:qs_pg_placetype_gp":"Town",
    "qs_pg:woe_adm0":23424833,
    "woe:adm0_id":23424833,
    "woe:name_adm0":"\u0395\u03bb\u03bb\u03ac\u03b4\u03b1",
    "woe:name_adm1":"Macedonia and Thrace",
    "woe:placetype":"Town",
    "wof:name":"Nikoklia",
    "wof:placetype":"locality",
    "wof:population":737
},
  "geometry": {"coordinates":[23.43333,40.93333],"type":"Point"}
}