{
  "type": "Feature",
  "properties": {
    "gn:admin1_code":"ESYE23",
    "gn:admin2_code":"31.0",
    "gn:admin3_code":"9127",
    "gn:asciiname":"Pendalofon",
    "gn:country_code":"GR",
    "gn:dem":17,
    "gn:feature_class":"P",
    "gn:feature_code":"PPL",
    "gn:name":"Pend\u00e1lofon",
    "gn:population":889,
    "gn:timezone":"Europe/Athens",
    "iso:country":"GR",
    "name:ell_x_historical":[
        "\u03a0\u03bf\u03b4\u03bf\u03bb\u03bf\u03b2\u03af\u03c4\u03c3\u03b1"
    ],
    "name:ell_x_preferred":[
        "\u03a0\u03b5\u03bd\u03c4\u03ac\u03bb\u03bf\u03c6\u03bf"
    ],
    "name:ell_x_variant":[
        "\u03a0\u03bf\u03b4\u03bf\u03bb\u03bf\u03b2\u03af\u03c4\u03c3\u03b1"
    ],
    "name:eng_x_preferred":[
        "Pentalofo"
    ],
    "name:und_x_variant":[
        "Podholov\u00edtsa",
        "Pent\u00e1lofos",
        "Pet\u00e1lofon",
        "Pend\u00e1lofos",
        "Pend\u00e1lofon"
    ],
    "wof:name":"Pendalofon",
    "wof:placetype":"locality",
    "wof:population":889
},
  "geometry": {"coordinates":[21.24683,38.48487],"type":"Point"}
}