{
  "type": "Feature",
  "properties": {
    "gn:admin1_code":"ESYE23",
    "gn:admin2_code":"31.0",
    "gn:admin3_code":"9123",
    "gn:asciiname":"Dyo Remata",
    "gn:country_code":"GR",
    "gn:dem":133,
    "gn:feature_class":"P",
    "gn:feature_code":"PPL",
    "gn:name":"Dy\u00f3 R\u00e9mata",
    "gn:population":0,
    "gn:timezone":"Europe/Athens",
    "iso:country":"GR",
    "name:ell_x_preferred":[
        "Dy\u00f3 R\u00e9mata"
    ],
    "name:ell_x_variant":[
        "\u0394\u03c5\u03cc \u03a1\u03ad\u03bc\u03b1\u03c4\u03b1"
    ],
    "name:und_x_variant":[
        "Dh\u00edo Remmata",
        "Dh\u00edo R\u00e9mata"
    ],
    "wof:name":"Dyo Remata",
    "wof:placetype":"locality"
},
  "geometry": {"coordinates":[21.42961,38.632],"type":"Point"}
}