{
  "type": "Feature",
  "properties": {
    "gn:admin1_code":"ESYE25",
    "gn:admin2_code":"40.0",
    "gn:admin3_code":"9257",
    "gn:asciiname":"Arapolakka",
    "gn:country_code":"GR",
    "gn:dem":155,
    "gn:feature_class":"P",
    "gn:feature_code":"PPL",
    "gn:name":"Arap\u00f3lakka",
    "gn:population":0,
    "gn:timezone":"Europe/Athens",
    "iso:country":"GR",
    "name:ell_x_preferred":[
        "\u0391\u03c1\u03b1\u03c0\u03cc\u03bb\u03b1\u03ba\u03ba\u03b1"
    ],
    "name:und_x_variant":[
        "Arapol\u00e1ka",
        "Arap\u00f3lakka"
    ],
    "wof:name":"Arapolakka",
    "wof:placetype":"locality"
},
  "geometry": {"coordinates":[21.77288,36.8995],"type":"Point"}
}