{
  "type": "Feature",
  "properties": {
    "gn:population":725,
    "iso:country":"GR",
    "name:ara_x_preferred":[
        "\u0623\u063a\u064a\u0648\u0633 \u0633\u064a\u0631\u0627\u0641\u064a\u0645"
    ],
    "name:dut_x_preferred":[
        "Agios Serafim"
    ],
    "name:ell_x_preferred":[
        "\u0386\u03b3\u03b9\u03bf\u03c2 \u03a3\u03b5\u03c1\u03b1\u03c6\u03b5\u03af\u03bc \u03a6\u03b8\u03b9\u03ce\u03c4\u03b9\u03b4\u03b1\u03c2"
    ],
    "name:ell_x_variant":[
        "\u0386\u03b3\u03b9\u03bf\u03c2 \u03a3\u03b5\u03c1\u03b1\u03c6\u03b5\u03af\u03bc"
    ],
    "name:eng_x_preferred":[
        "Agios Serafeim"
    ],
    "name:gre_x_preferred":[
        "\u0386\u03b3\u03b9\u03bf\u03c2 \u03a3\u03b5\u03c1\u03b1\u03c6\u03b5\u03af\u03bc \u03a6\u03b8\u03b9\u03ce\u03c4\u03b9\u03b4\u03b1\u03c2"
    ],
    "name:swe_x_preferred":[
        "\u00c1yios Seraf\u00edm"
    ],
    "name:unk_x_variant":[
        "Dervis\u00e1dhes"
    ],
    "qs:a0":"Greece",
    "qs:a1":"*\u03a3\u03a4\u0395\u03a1\u0395\u0391 \u0395\u039b\u039b\u0391\u0394\u0391",
    "qs:a1_alt":"STEREA ELLADA",
    "qs:a1r":"0",
    "qs:a2_alt":"FUIVTIDA",
    "qs:adm0":"Greece",
    "qs:la_lc":"*",
    "qs:level":"locality",
    "qs:loc":"\u0391\u0393\u0399\u039f\u03a3 \u03a3\u0395\u03a1\u0391\u03a6\u0395\u0399\u039c",
    "qs:loc_alt":"AGIOS SERAFEIM",
    "qs:pop":0,
    "qs:type":"buffered point",
    "wd:wordcount":100,
    "wof:name":"\u0391\u0393\u0399\u039f\u03a3 \u03a3\u0395\u03a1\u0391\u03a6\u0395\u0399\u039c",
    "wof:placetype":"locality",
    "wof:population":725
},
  "geometry": {"coordinates":[22.703591,38.801822],"type":"Point"}
}