{
  "type": "Feature",
  "properties": {
    "gn:admin1_code":"ESYE24",
    "gn:admin2_code":"29.0",
    "gn:admin3_code":"9162",
    "gn:asciiname":"Paliourion",
    "gn:country_code":"GR",
    "gn:dem":90,
    "gn:feature_class":"P",
    "gn:feature_code":"PPL",
    "gn:name":"Palio\u00farion",
    "gn:population":128,
    "gn:timezone":"Europe/Athens",
    "iso:country":"GR",
    "name:ell_x_preferred":[
        "\u03a0\u03b1\u03bb\u03b9\u03bf\u03cd\u03c1\u03b9"
    ],
    "name:ell_x_variant":[
        "\u03a0\u03b1\u03bb\u03b9\u03bf\u03cd\u03c1\u03b9\u03bf\u03bd"
    ],
    "name:eng_x_preferred":[
        "Paliouri"
    ],
    "name:und_x_variant":[
        "Paliouri",
        "Palio\u00farion"
    ],
    "wof:name":"Paliourion",
    "wof:placetype":"locality",
    "wof:population":128
},
  "geometry": {"coordinates":[22.215,38.94399],"type":"Point"}
}