{
  "type": "Feature",
  "properties": {
    "gn:admin1_code":"ESYE12",
    "gn:admin2_code":"12.0",
    "gn:admin3_code":"9024",
    "gn:asciiname":"Agia Marina",
    "gn:country_code":"GR",
    "gn:dem":36,
    "gn:feature_class":"P",
    "gn:feature_code":"PPL",
    "gn:name":"Ag\u00eda Mar\u00edna",
    "gn:population":732,
    "gn:timezone":"Europe/Athens",
    "iso:country":"GR",
    "name:ceb_x_preferred":[
        "Agia Marina"
    ],
    "name:deu_x_preferred":[
        "Agia Marina"
    ],
    "name:ell_x_preferred":[
        "\u0391\u03b3\u03af\u03b1 \u039c\u03b1\u03c1\u03af\u03bd\u03b1"
    ],
    "name:fin_x_preferred":[
        "Ag\u00eda Mar\u00edna"
    ],
    "name:hye_x_preferred":[
        "\u0531\u0575\u056b\u0561 \u0544\u0561\u0580\u056b\u0576\u0561"
    ],
    "name:rus_x_preferred":[
        "\u0410\u0439\u0438\u044f-\u041c\u0430\u0440\u0438\u043d\u0430"
    ],
    "name:swe_x_preferred":[
        "Agia Marina"
    ],
    "name:und_x_variant":[
        "Ay\u00eda Mar\u00edna",
        "Ag\u00eda Mar\u00edna"
    ],
    "wof:name":"Agia Marina",
    "wof:placetype":"locality",
    "wof:population":732
},
  "geometry": {"coordinates":[22.21533,40.59722],"type":"Point"}
}