{
  "type": "Feature",
  "properties": {
    "gn:admin1_code":"ESYE23",
    "gn:admin2_code":"38.0",
    "gn:admin3_code":"9130",
    "gn:asciiname":"Solos",
    "gn:country_code":"GR",
    "gn:dem":1052,
    "gn:feature_class":"P",
    "gn:feature_code":"PPL",
    "gn:name":"S\u00f3los",
    "gn:population":0,
    "gn:timezone":"Europe/Athens",
    "iso:country":"GR",
    "name:ell_x_preferred":[
        "S\u00f3los"
    ],
    "name:ell_x_variant":[
        "\u03a3\u03cc\u03bb\u03bf\u03c2"
    ],
    "wof:name":"Solos",
    "wof:placetype":"locality"
},
  "geometry": {"coordinates":[22.24767,38.01144],"type":"Point"}
}