{
  "type": "Feature",
  "properties": {
    "gn:admin1_code":"ESYE22",
    "gn:admin2_code":"25.0",
    "gn:admin3_code":"9118",
    "gn:asciiname":"Agios Vlasios",
    "gn:country_code":"GR",
    "gn:dem":22,
    "gn:feature_class":"P",
    "gn:feature_code":"PPL",
    "gn:name":"\u00c1gios Vl\u00e1sios",
    "gn:population":0,
    "gn:timezone":"Europe/Athens",
    "iso:country":"GR",
    "name:ell_x_preferred":[
        "\u00c1gios Vl\u00e1sios"
    ],
    "name:ell_x_variant":[
        "\u0386\u03b3\u03b9\u03bf\u03c2 \u0392\u03bb\u03ac\u03c3\u03b9\u03bf\u03c2"
    ],
    "name:und_x_variant":[
        "Kan\u00e1li Arvanttiko",
        "\u00c1yios Nik\u00f3laos",
        "\u00c1gios Nik\u00f3laos"
    ],
    "wof:name":"Agios Vlasios",
    "wof:placetype":"locality"
},
  "geometry": {"coordinates":[19.86242,39.61303],"type":"Point"}
}