{
  "type": "Feature",
  "properties": {
    "gn:admin1_code":"ESYE22",
    "gn:admin2_code":"27.0",
    "gn:admin3_code":"9120",
    "gn:asciiname":"Markata",
    "gn:country_code":"GR",
    "gn:dem":205,
    "gn:feature_class":"P",
    "gn:feature_code":"PPL",
    "gn:name":"Mark\u00e1ta",
    "gn:population":0,
    "gn:timezone":"Europe/Athens",
    "iso:country":"GR",
    "name:ell_x_preferred":[
        "Mark\u00e1ta"
    ],
    "name:ell_x_variant":[
        "\u039c\u03b1\u03c1\u03ba\u03ac\u03c4\u03b1"
    ],
    "wof:name":"Markata",
    "wof:placetype":"locality"
},
  "geometry": {"coordinates":[20.55833,38.3075],"type":"Point"}
}