{
  "type": "Feature",
  "properties": {
    "gn:admin1_code":"ESYE24",
    "gn:admin2_code":"34.0",
    "gn:admin3_code":"9152",
    "gn:asciiname":"Koilion",
    "gn:cc2":"GR",
    "gn:country_code":"GR",
    "gn:dem":65,
    "gn:feature_class":"P",
    "gn:feature_code":"PPL",
    "gn:name":"Ko\u00edlion",
    "gn:population":0,
    "gn:timezone":"Europe/Athens",
    "iso:country":"GR",
    "name:und_x_variant":[
        "Ko\u00edli",
        "Ko\u00edlion",
        "\u039a\u03bf\u03af\u03bb\u03b9\u03bf\u03bd"
    ],
    "wof:name":"Koilion",
    "wof:placetype":"locality"
},
  "geometry": {"coordinates":[24.05983,38.54011],"type":"Point"}
}