{
  "type": "Feature",
  "properties": {
    "gn:gn_country":"GR",
    "gn:gn_fcode":"PPL",
    "gn:gn_pop":360,
    "gn:population":368,
    "iso:country":"GR",
    "name:dut_x_preferred":[
        "Agios Konstantinos"
    ],
    "name:ell_x_preferred":[
        "\u0386\u03b3\u03b9\u03bf\u03c2 \u039a\u03c9\u03bd\u03c3\u03c4\u03b1\u03bd\u03c4\u03af\u03bd\u03bf\u03c2"
    ],
    "name:eng_x_preferred":[
        "Agios Konstantinos"
    ],
    "name:ger_x_preferred":[
        "Agios Konstandinos"
    ],
    "name:gre_x_preferred":[
        "\u0386\u03b3\u03b9\u03bf\u03c2 \u039a\u03c9\u03bd\u03c3\u03c4\u03b1\u03bd\u03c4\u03af\u03bd\u03bf\u03c2 \u03a3\u03ac\u03bc\u03bf\u03c5"
    ],
    "name:rus_x_preferred":[
        "\u0410\u0439\u043e\u0441-\u041a\u043e\u043d\u0441\u0442\u0430\u043d\u0434\u0438\u043d\u043e\u0441"
    ],
    "name:unk_x_variant":[
        "\u00c1yios Konstand\u00ednos"
    ],
    "qs_pg:aaroncc":"GR",
    "qs_pg:gn_country":"GR",
    "qs_pg:gn_fcode":"PPL",
    "qs_pg:gn_pop":360,
    "qs_pg:name":"\u00c1gios Konstant\u00ednos",
    "qs_pg:photos_9r":0,
    "qs_pg:photos_sr":0,
    "qs_pg:pop_sr":2,
    "qs_pg:qs_pg_placetype":"locality",
    "wof:name":"\u00c1gios Konstant\u00ednos",
    "wof:placetype":"locality",
    "wof:population":368
},
  "geometry": {"coordinates":[26.81528,37.80583],"type":"Point"}
}