{
  "type": "Feature",
  "properties": {
    "gn:admin1_code":"ESYE24",
    "gn:admin2_code":"34.0",
    "gn:admin3_code":"9152",
    "gn:asciiname":"Koutourla",
    "gn:cc2":"GR",
    "gn:country_code":"GR",
    "gn:dem":463,
    "gn:feature_class":"P",
    "gn:feature_code":"PPL",
    "gn:name":"Ko\u00fatourla",
    "gn:population":0,
    "gn:timezone":"Europe/Athens",
    "iso:country":"GR",
    "name:und_x_variant":[
        "Ko\u00fatourlo",
        "Ko\u00fatourla"
    ],
    "wof:name":"Koutourla",
    "wof:placetype":"locality"
},
  "geometry": {"coordinates":[23.93605,38.64017],"type":"Point"}
}