{
  "type": "Feature",
  "properties": {
    "gn:admin1_code":"ESYE11",
    "gn:admin2_code":"2.0",
    "gn:admin3_code":"9021",
    "gn:asciiname":"Mikro Kranovouni",
    "gn:country_code":"GR",
    "gn:dem":22,
    "gn:feature_class":"P",
    "gn:feature_code":"PPL",
    "gn:name":"Mikr\u00f3 Kranovo\u00fani",
    "gn:population":0,
    "gn:timezone":"Europe/Athens",
    "iso:country":"GR",
    "name:ell_x_preferred":[
        "Mikr\u00f3 Kranovo\u00fani"
    ],
    "name:ell_x_variant":[
        "\u039c\u03b9\u03ba\u03c1\u03cc \u039a\u03c1\u03b1\u03bd\u03bf\u03b2\u03bf\u03cd\u03bd\u03b9",
        "Mikr\u00f3n Kranovo\u00fanion",
        "\u039c\u03b9\u03ba\u03c1\u03cc\u03bd \u039a\u03c1\u03b1\u03bd\u03bf\u03b2\u03bf\u03cd\u03bd\u03b9\u03bf\u03bd"
    ],
    "wof:name":"Mikro Kranovouni",
    "wof:placetype":"locality"
},
  "geometry": {"coordinates":[25.33312,41.0528],"type":"Point"}
}