{
  "type": "Feature",
  "properties": {
    "gn:admin1_code":"ESYE42",
    "gn:admin2_code":"49.0",
    "gn:admin3_code":"9292.0",
    "gn:asciiname":"Myrisis",
    "gn:country_code":"GR",
    "gn:dem":390,
    "gn:feature_class":"P",
    "gn:feature_code":"PPL",
    "gn:name":"Myr\u00edsis",
    "gn:population":55,
    "gn:timezone":"Europe/Athens",
    "iso:country":"GR",
    "name:ell_x_preferred":[
        "\u039c\u03c5\u03c1\u03af\u03c3\u03b7\u03c2"
    ],
    "name:eng_x_preferred":[
        "Myrisis"
    ],
    "wof:name":"Myrisis",
    "wof:placetype":"locality",
    "wof:population":55
},
  "geometry": {"coordinates":[25.50981,37.15557],"type":"Point"}
}