{
  "type": "Feature",
  "properties": {
    "gn:admin1_code":"ESYE11",
    "gn:admin2_code":"1.0",
    "gn:admin3_code":"9006",
    "gn:asciiname":"Aetochori",
    "gn:country_code":"GR",
    "gn:dem":86,
    "gn:feature_class":"P",
    "gn:feature_code":"PPL",
    "gn:name":"Aetoch\u00f3ri",
    "gn:population":0,
    "gn:timezone":"Europe/Athens",
    "iso:country":"GR",
    "name:ell_x_preferred":[
        "Aetoch\u00f3ri"
    ],
    "name:ell_x_variant":[
        "\u0391\u03b5\u03c4\u03bf\u03c7\u03ce\u03c1\u03b9",
        "Aetoch\u00f3rion",
        "\u0391\u03b5\u03c4\u03bf\u03c7\u03ce\u03c1\u03b9\u03bf\u03bd"
    ],
    "name:und_x_variant":[
        "A\u00ebtokh\u00f3ri",
        "A\u00ebtokh\u00f3rion"
    ],
    "wof:name":"Aetochori",
    "wof:placetype":"locality"
},
  "geometry": {"coordinates":[25.99871,40.89879000000001],"type":"Point"}
}