{
  "type": "Feature",
  "properties": {
    "gn:population":1118,
    "iso:country":"GR",
    "name:ell_x_preferred":[
        "Koutseli\u00f3n"
    ],
    "name:ell_x_variant":[
        "\u039a\u03bf\u03c5\u03c4\u03c3\u03b5\u03bb\u03b9\u03cc",
        "\u039a\u03bf\u03c5\u03c4\u03c3\u03b5\u03bb\u03b9\u03cc\u03bd"
    ],
    "name:eng_x_preferred":[
        "Koutselio"
    ],
    "name:und_x_variant":[
        "Koutsoli\u00f3"
    ],
    "qs:a0":"Greece",
    "qs:a1":"*\u0397\u03a0\u0395\u0399\u03a1\u039f\u03a3",
    "qs:a1_alt":"HPEIROS",
    "qs:a1r":"0",
    "qs:a2_alt":"IVANNINA",
    "qs:adm0":"Greece",
    "qs:la_lc":"*",
    "qs:level":"locality",
    "qs:loc":"\u039a\u039f\u03a5\u03a4\u03a3\u0395\u039b\u0399\u039f\u039d",
    "qs:loc_alt":"KOYTSELION",
    "qs:pop":0,
    "qs:type":"buffered point",
    "wof:name":"\u039a\u039f\u03a5\u03a4\u03a3\u0395\u039b\u0399\u039f\u039d",
    "wof:placetype":"locality",
    "wof:population":1118
},
  "geometry": {"coordinates":[20.911589,39.588947],"type":"Point"}
}