{
  "type": "Feature",
  "properties": {
    "gn:admin1_code":"ESYE13",
    "gn:admin2_code":"10.0",
    "gn:admin3_code":"9061",
    "gn:asciiname":"Mesolouri",
    "gn:country_code":"GR",
    "gn:dem":1013,
    "gn:feature_class":"P",
    "gn:feature_code":"PPL",
    "gn:name":"Mesolo\u00fari",
    "gn:population":0,
    "gn:timezone":"Europe/Athens",
    "iso:country":"GR",
    "name:bul_x_preferred":[
        "\u041c\u0435\u0441\u043e\u043b\u0443\u0440\u0438"
    ],
    "name:ceb_x_preferred":[
        "Mesolo\u00fari"
    ],
    "name:deu_x_preferred":[
        "Mesolouri"
    ],
    "name:ell_x_preferred":[
        "\u039c\u03b5\u03c3\u03bf\u03bb\u03bf\u03cd\u03c1\u03b9\u03bf\u03bd"
    ],
    "name:ell_x_variant":[
        "\u039c\u03b5\u03c3\u03bf\u03bb\u03bf\u03cd\u03c1\u03b9 \u0393\u03c1\u03b5\u03b2\u03b5\u03bd\u03ce\u03bd"
    ],
    "name:fin_x_preferred":[
        "Mesolo\u00fari"
    ],
    "name:fra_x_preferred":[
        "Mesolouri"
    ],
    "name:ita_x_preferred":[
        "Mesolouri"
    ],
    "name:mkd_x_preferred":[
        "\u041c\u0435\u0441\u043e\u043b\u043e\u0432\u043e"
    ],
    "name:nld_x_preferred":[
        "Mesolouri"
    ],
    "name:nno_x_preferred":[
        "Mesolo\u00fari"
    ],
    "name:swe_x_preferred":[
        "Mesolo\u00fari"
    ],
    "name:und_x_variant":[
        "Mesolo\u00farion",
        "\u039c\u03b5\u03c3\u03bf\u03bb\u03bf\u03cd\u03c1\u03b9"
    ],
    "wof:name":"Mesolouri",
    "wof:placetype":"locality"
},
  "geometry": {"coordinates":[21.15097,40.11333],"type":"Point"}
}