{
  "type": "Feature",
  "properties": {
    "gn:admin1_code":"ESYE13",
    "gn:admin2_code":"10.0",
    "gn:admin3_code":"9061",
    "gn:asciiname":"Mesolouri",
    "gn:country_code":"GR",
    "gn:dem":1013,
    "gn:feature_class":"P",
    "gn:feature_code":"PPL",
    "gn:name":"Mesolo\u00fari",
    "gn:population":0,
    "gn:timezone":"Europe/Athens",
    "iso:country":"GR",
    "name:ell_x_preferred":[
        "\u039c\u03b5\u03c3\u03bf\u03bb\u03bf\u03cd\u03c1\u03b9\u03bf\u03bd"
    ],
    "name:und_x_variant":[
        "Mesolo\u00fari",
        "Mesolo\u00farion",
        "\u039c\u03b5\u03c3\u03bf\u03bb\u03bf\u03cd\u03c1\u03b9"
    ],
    "wof:name":"Mesolouri",
    "wof:placetype":"locality"
},
  "geometry": {"coordinates":[21.15097,40.11333],"type":"Point"}
}