{
  "type": "Feature",
  "properties": {
    "iso:country":"GR",
    "name:arz_x_preferred":[
        "\u067e\u0627\u0646\u0648\u0631\u0645\u0648\u0633 \u062a\u064a\u0646\u0648\u0633"
    ],
    "name:ceb_x_preferred":[
        "P\u00e1normos"
    ],
    "name:ces_x_preferred":[
        "Panormos"
    ],
    "name:deu_x_preferred":[
        "Panormos"
    ],
    "name:ell_x_preferred":[
        "\u03a0\u03ac\u03bd\u03bf\u03c1\u03bc\u03bf\u03c2 \u03a4\u03ae\u03bd\u03bf\u03c5"
    ],
    "name:ell_x_variant":[
        "P\u00fdrgos",
        "\u03a0\u03cd\u03c1\u03b3\u03bf\u03c2"
    ],
    "name:eng_x_preferred":[
        "Panormos"
    ],
    "name:fin_x_preferred":[
        "P\u00e1normos"
    ],
    "name:fra_x_preferred":[
        "Panormos"
    ],
    "name:fra_x_variant":[
        "P\u00e1normos"
    ],
    "name:hye_x_preferred":[
        "\u054a\u056b\u0580\u0563\u0578\u057d"
    ],
    "name:ita_x_preferred":[
        "Panormos"
    ],
    "name:jpn_x_preferred":[
        "\u30d1\u30ce\u30eb\u30e2\u30b9"
    ],
    "name:nld_x_preferred":[
        "Panormos"
    ],
    "name:nno_x_preferred":[
        "P\u00e1normos"
    ],
    "name:rus_x_preferred":[
        "\u041f\u0430\u043d\u043e\u0440\u043c\u043e\u0441"
    ],
    "name:swe_x_preferred":[
        "P\u00e1normos"
    ],
    "qs:a0":"Greece",
    "qs:a1":"*\u039d\u039f\u03a4\u0399\u039f \u0391\u0399\u0393\u0391\u0399\u039f",
    "qs:a1_alt":"NOTIO AIGAIO",
    "qs:a1r":"0",
    "qs:a2_alt":"KYKLADES",
    "qs:adm0":"Greece",
    "qs:la_lc":"*",
    "qs:level":"locality",
    "qs:loc":"\u03a0\u0391\u039d\u039f\u03a1\u039c\u039f\u03a3",
    "qs:loc_alt":"PANORMOS",
    "qs:pop":0,
    "qs:type":"buffered point",
    "wd:wordcount":126,
    "wof:name":"\u03a0\u0391\u039d\u039f\u03a1\u039c\u039f\u03a3",
    "wof:placetype":"locality"
},
  "geometry": {"coordinates":[25.04175,37.639663],"type":"Point"}
}