{
  "type": "Feature",
  "properties": {
    "gn:admin1_code":"ESYE14",
    "gn:admin2_code":"21.0",
    "gn:admin3_code":"9103",
    "gn:asciiname":"Ypereia",
    "gn:country_code":"GR",
    "gn:dem":111,
    "gn:feature_class":"P",
    "gn:feature_code":"PPL",
    "gn:name":"Yp\u00e9reia",
    "gn:population":0,
    "gn:timezone":"Europe/Athens",
    "iso:country":"GR",
    "name:ell_x_preferred":[
        "Yp\u00e9reia"
    ],
    "name:ell_x_variant":[
        "\u03a5\u03c0\u03ad\u03c1\u03b5\u03b9\u03b1"
    ],
    "name:und_x_variant":[
        "Khatz\u00f3mbasis",
        "Haji\u00f3basi",
        "Haj\u00f3basis"
    ],
    "wof:name":"Ypereia",
    "wof:placetype":"locality"
},
  "geometry": {"coordinates":[22.26619,39.38872],"type":"Point"}
}