{
  "type": "Feature",
  "properties": {
    "gn:gn_country":"GR",
    "gn:gn_fcode":"PPL",
    "gn:gn_pop":500,
    "gn:population":500,
    "iso:country":"GR",
    "name:bul_x_preferred":[
        "\u041f\u0435\u0440\u0438\u0432\u043e\u043b\u0438"
    ],
    "name:ceb_x_preferred":[
        "Periv\u00f3lion- PREVALE"
    ],
    "name:ell_x_preferred":[
        "\u03a0\u03b5\u03c1\u03b9\u03b2\u03cc\u03bb\u03b9 \u0393\u03c1\u03b5\u03b2\u03b5\u03bd\u03ce\u03bd"
    ],
    "name:eng_x_preferred":[
        "Perivoli"
    ],
    "name:fin_x_preferred":[
        "Periv\u00f3li"
    ],
    "name:fra_x_preferred":[
        "Perivoli"
    ],
    "name:ita_x_preferred":[
        "Perivoli"
    ],
    "name:jpn_x_preferred":[
        "\u30da\u30ea\u30f4\u30a9\u30ea"
    ],
    "name:mkd_x_preferred":[
        "\u041f\u0435\u0440\u0438\u0432\u043e\u043b\u0438"
    ],
    "name:nld_x_preferred":[
        "Perivoli"
    ],
    "name:nno_x_preferred":[
        "Periv\u00f3li"
    ],
    "name:rus_x_preferred":[
        "\u041f\u0435\u0440\u0438\u0432\u043e\u043b\u0438\u043e\u043d"
    ],
    "name:swe_x_preferred":[
        "Periv\u00f3lion- PREVALE"
    ],
    "name:unk_x_variant":[
        "Periv\u00f3li"
    ],
    "qs_pg:aaroncc":"GR",
    "qs_pg:gn_country":"GR",
    "qs_pg:gn_fcode":"PPL",
    "qs_pg:gn_pop":500,
    "qs_pg:name":"Periv\u00f3lion- PREVALE",
    "qs_pg:photos_9r":0,
    "qs_pg:photos_sr":0,
    "qs_pg:pop_sr":2,
    "qs_pg:qs_pg_placetype":"locality",
    "wof:name":"Periv\u00f3lion- PREVALE",
    "wof:placetype":"locality",
    "wof:population":500
},
  "geometry": {"coordinates":[21.11639,39.97944],"type":"Point"}
}