{
  "type": "Feature",
  "properties": {
    "gn:admin1_code":"ESYE23",
    "gn:admin2_code":"31.0",
    "gn:admin3_code":"9124.0",
    "gn:asciiname":"Aktio",
    "gn:country_code":"GR",
    "gn:dem":4,
    "gn:feature_class":"P",
    "gn:feature_code":"PPL",
    "gn:name":"\u00c1ktio",
    "gn:population":180,
    "gn:timezone":"Europe/Athens",
    "iso:country":"GR",
    "name:ell_x_preferred":[
        "\u0386\u03ba\u03c4\u03b9\u03bf"
    ],
    "name:eng_x_preferred":[
        "Aktio"
    ],
    "wof:name":"Aktio",
    "wof:placetype":"locality",
    "wof:population":180
},
  "geometry": {"coordinates":[20.79673,38.91778],"type":"Point"}
}