{
  "type": "Feature",
  "properties": {
    "gn:gn_country":"GR",
    "gn:gn_fcode":"ADM3",
    "gn:gn_pop":19053,
    "gn:population":19053,
    "iso:country":"GR",
    "name:ell_x_preferred":[
        "\u0395\u03bc\u03bc\u03b1\u03bd\u03bf\u03c5\u03ae\u03bb \u03a0\u03b1\u03c0\u03c0\u03ac"
    ],
    "qs_pg:aaroncc":"GR",
    "qs_pg:gn_country":"GR",
    "qs_pg:gn_fcode":"ADM3",
    "qs_pg:gn_pop":19053,
    "qs_pg:name":"Dimos Emmanouil Pappas",
    "qs_pg:photos_9r":0,
    "qs_pg:photos_sr":0,
    "qs_pg:pop_sr":6,
    "qs_pg:qs_pg_placetype":"localadmin",
    "wof:name":"Dimos Emmanouil Pappas",
    "wof:placetype":"localadmin",
    "wof:population":19053
},
  "geometry": {"coordinates":[23.68147,41.05346],"type":"Point"}
}