{
  "type": "Feature",
  "properties": {
    "gn:admin1_code":"ESYE31",
    "gn:admin2_code":"445406.0",
    "gn:admin3_code":"9226.0",
    "gn:asciiname":"Agios Kosmas",
    "gn:country_code":"GR",
    "gn:dem":43,
    "gn:feature_class":"P",
    "gn:feature_code":"PPL",
    "gn:name":"\u00c1gios Kosm\u00e1s",
    "gn:population":0,
    "gn:timezone":"Europe/Athens",
    "iso:country":"GR",
    "name:bul_x_preferred":[
        "\u0410\u0433\u0438\u043e\u0441 \u041a\u043e\u0441\u043c\u0430\u0441"
    ],
    "name:ell_x_preferred":[
        "\u00c1gios Kosm\u00e1s"
    ],
    "name:ell_x_variant":[
        "\u0386\u03b3\u03b9\u03bf\u03c2 \u039a\u03bf\u03c3\u03bc\u03ac\u03c2",
        "\u0394\u03ae\u03bc\u03bf\u03c2 \u039a\u03bf\u03c3\u03bc\u03ac \u03c4\u03bf\u03c5 \u0391\u03b9\u03c4\u03c9\u03bb\u03bf\u03cd"
    ],
    "name:fin_x_preferred":[
        "\u00c1gios Kosm\u00e1s"
    ],
    "name:ita_x_preferred":[
        "Kosmas"
    ],
    "name:mkd_x_preferred":[
        "\u0427\u0438\u0440\u0430\u043a"
    ],
    "name:ron_x_preferred":[
        "Kosmas o Aitolos"
    ],
    "wof:name":"Agios Kosmas",
    "wof:placetype":"locality"
},
  "geometry": {"coordinates":[23.99931,37.96179],"type":"Point"}
}