{
  "type": "Feature",
  "properties": {
    "gn:admin1_code":"ESYE11",
    "gn:admin2_code":"14.0",
    "gn:admin3_code":"9013",
    "gn:asciiname":"Makrychori",
    "gn:country_code":"GR",
    "gn:dem":224,
    "gn:feature_class":"P",
    "gn:feature_code":"PPL",
    "gn:name":"Makrych\u00f3ri",
    "gn:population":84,
    "gn:timezone":"Europe/Athens",
    "iso:country":"GR",
    "name:ell_x_preferred":[
        "\u039c\u03b1\u03ba\u03c1\u03c5\u03c7\u03ce\u03c1\u03b9"
    ],
    "name:ell_x_variant":[
        "Makrych\u00f3ri",
        "Makrych\u00f3rion",
        "\u039c\u03b1\u03ba\u03c1\u03c5\u03c7\u03ce\u03c1\u03b9\u03bf\u03bd"
    ],
    "name:eng_x_preferred":[
        "Makrychori"
    ],
    "name:und_x_variant":[
        "Makrikh\u00f3ri",
        "Mikrokh\u00f3rion",
        "Uz\u00fan-K\u00f3\u00ef",
        "Makrikh\u00f3rion"
    ],
    "wof:name":"Makrychori",
    "wof:placetype":"locality",
    "wof:population":84
},
  "geometry": {"coordinates":[24.6176,41.04088],"type":"Point"}
}