{
  "type": "Feature",
  "properties": {
    "gn:admin1_code":"ESYE11",
    "gn:admin2_code":"14.0",
    "gn:admin3_code":"9013",
    "gn:asciiname":"Makrychori",
    "gn:country_code":"GR",
    "gn:dem":224,
    "gn:feature_class":"P",
    "gn:feature_code":"PPL",
    "gn:name":"Makrych\u00f3ri",
    "gn:population":84,
    "gn:timezone":"Europe/Athens",
    "iso:country":"GR",
    "name:ara_x_preferred":[
        "\u0645\u0627\u0643\u0631\u064a\u062e\u0648\u0631\u064a"
    ],
    "name:bul_x_preferred":[
        "\u041c\u0430\u043a\u0440\u0438\u0445\u043e\u0440\u0438"
    ],
    "name:ceb_x_preferred":[
        "Makrych\u00f3ri"
    ],
    "name:ell_x_preferred":[
        "\u039c\u03b1\u03ba\u03c1\u03c5\u03c7\u03ce\u03c1\u03b9"
    ],
    "name:ell_x_variant":[
        "Makrych\u00f3ri",
        "Makrych\u00f3rion",
        "\u039c\u03b1\u03ba\u03c1\u03c5\u03c7\u03ce\u03c1\u03b9\u03bf\u03bd",
        "\u039c\u03b1\u03ba\u03c1\u03c5\u03c7\u03ce\u03c1\u03b9 \u039b\u03ac\u03c1\u03b9\u03c3\u03b1\u03c2"
    ],
    "name:eng_x_preferred":[
        "Makrychori"
    ],
    "name:fin_x_preferred":[
        "Makrych\u00f3ri"
    ],
    "name:ita_x_preferred":[
        "Makrychori"
    ],
    "name:nno_x_preferred":[
        "Makrykh\u00f3ri"
    ],
    "name:ron_x_preferred":[
        "Makrychori"
    ],
    "name:swe_x_preferred":[
        "Makrych\u00f3ri"
    ],
    "name:und_x_variant":[
        "Makrikh\u00f3ri",
        "Mikrokh\u00f3rion",
        "Uz\u00fan-K\u00f3\u00ef",
        "Makrikh\u00f3rion"
    ],
    "wof:name":"Makrychori",
    "wof:placetype":"locality",
    "wof:population":84
},
  "geometry": {"coordinates":[24.6176,41.04088],"type":"Point"}
}