{
  "type": "Feature",
  "properties": {
    "gn:admin1_code":"ESYE23",
    "gn:admin2_code":"31.0",
    "gn:admin3_code":"9123",
    "gn:asciiname":"Andhronaiika",
    "gn:country_code":"GR",
    "gn:dem":592,
    "gn:feature_class":"P",
    "gn:feature_code":"PPL",
    "gn:name":"Andhrona\u00edika",
    "gn:population":7,
    "gn:timezone":"Europe/Athens",
    "iso:country":"GR",
    "name:ell_x_preferred":[
        "\u0391\u03bd\u03b4\u03c1\u03c9\u03bd\u03b1\u03af\u03b9\u03ba\u03b1"
    ],
    "name:ell_x_variant":[
        "\u0391\u03bd\u03b4\u03c1\u03c9\u03bd\u03b1\u03af\u03ca\u03ba\u03b1"
    ],
    "name:eng_x_preferred":[
        "Andronaiika"
    ],
    "wof:name":"Andhronaiika",
    "wof:placetype":"locality",
    "wof:population":7
},
  "geometry": {"coordinates":[21.53063,38.77414],"type":"Point"}
}