{
  "type": "Feature",
  "properties": {
    "gn:admin1_code":"ESYE23",
    "gn:admin2_code":"31.0",
    "gn:admin3_code":"9127",
    "gn:asciiname":"Mastron",
    "gn:country_code":"GR",
    "gn:dem":13,
    "gn:feature_class":"P",
    "gn:feature_code":"PPL",
    "gn:name":"M\u00e1stron",
    "gn:population":406,
    "gn:timezone":"Europe/Athens",
    "iso:country":"GR",
    "name:ell_x_preferred":[
        "\u039c\u03ac\u03c3\u03c4\u03c1\u03bf"
    ],
    "name:eng_x_preferred":[
        "Mastro"
    ],
    "name:und_x_variant":[
        "M\u00e1storas",
        "M\u00e1stro",
        "M\u00e1stron"
    ],
    "wof:name":"Mastron",
    "wof:placetype":"locality",
    "wof:population":406
},
  "geometry": {"coordinates":[21.27821,38.43672],"type":"Point"}
}