{
  "type": "Feature",
  "properties": {
    "gn:admin1_code":"ESYE23",
    "gn:admin2_code":"38.0",
    "gn:admin3_code":"9132",
    "gn:asciiname":"Mikroulaiika",
    "gn:country_code":"GR",
    "gn:dem":343,
    "gn:feature_class":"P",
    "gn:feature_code":"PPL",
    "gn:name":"Mikroula\u00edika",
    "gn:population":0,
    "gn:timezone":"Europe/Athens",
    "iso:country":"GR",
    "name:ell_x_preferred":[
        "\u039c\u03b9\u03ba\u03c1\u03bf\u03c5\u03bb\u03b1\u03af\u03b9\u03ba\u03b1"
    ],
    "name:und_x_variant":[
        "Mikroul\u00e9\u00efka",
        "Mikroula\u00edika"
    ],
    "wof:name":"Mikroulaiika",
    "wof:placetype":"locality"
},
  "geometry": {"coordinates":[21.71294,38.00781],"type":"Point"}
}