{
  "type": "Feature",
  "properties": {
    "gn:admin1_code":"ESYE25",
    "gn:admin2_code":"41.0",
    "gn:admin3_code":"9237",
    "gn:asciiname":"Prosilia",
    "gn:country_code":"GR",
    "gn:dem":236,
    "gn:feature_class":"P",
    "gn:feature_code":"PPL",
    "gn:name":"Pros\u00edlia",
    "gn:population":0,
    "gn:timezone":"Europe/Athens",
    "iso:country":"GR",
    "name:ell_x_preferred":[
        "\u03a0\u03c1\u03bf\u03c3\u03ae\u03bb\u03b9\u03b1"
    ],
    "name:und_x_variant":[
        "Arts\u00edna",
        "Pros\u00edlia"
    ],
    "wof:name":"Prosilia",
    "wof:placetype":"locality"
},
  "geometry": {"coordinates":[22.64602,37.43798],"type":"Point"}
}