{
  "type": "Feature",
  "properties": {
    "gn:gn_country":"GR",
    "gn:gn_fcode":"PPL",
    "gn:gn_pop":249,
    "gn:population":249,
    "iso:country":"GR",
    "name:bul_x_preferred":[
        "\u041c\u0438\u0440\u043e\u0444\u0438\u043b\u043e"
    ],
    "name:ceb_x_preferred":[
        "Myr\u00f3fyllo"
    ],
    "name:ell_x_preferred":[
        "\u039c\u03c5\u03c1\u03cc\u03c6\u03c5\u03bb\u03bb\u03bf"
    ],
    "name:ell_x_variant":[
        "\u039c\u03c5\u03c1\u03cc\u03c6\u03c5\u03bb\u03bb\u03bf\u03bd",
        "\u039c\u03c5\u03c1\u03cc\u03c6\u03c5\u03bb\u03bb\u03bf \u03a4\u03c1\u03b9\u03ba\u03ac\u03bb\u03c9\u03bd"
    ],
    "name:eng_x_preferred":[
        "Myrofyllo"
    ],
    "name:fin_x_preferred":[
        "Myr\u00f3fyllo"
    ],
    "name:ita_x_preferred":[
        "Myrofyllo"
    ],
    "name:jpn_x_preferred":[
        "\u30df\u30ed\u30d5\u30a3\u30ed"
    ],
    "name:nld_x_preferred":[
        "Myrofyllo"
    ],
    "name:nno_x_preferred":[
        "Myr\u00f3fyllo"
    ],
    "name:swe_x_preferred":[
        "Myr\u00f3fyllo"
    ],
    "name:unk_x_variant":[
        "Mir\u00f3fillon"
    ],
    "qs_pg:aaroncc":"GR",
    "qs_pg:gn_country":"GR",
    "qs_pg:gn_fcode":"PPL",
    "qs_pg:gn_pop":249,
    "qs_pg:name":"Myr\u00f3fyllon",
    "qs_pg:photos_9r":0,
    "qs_pg:photos_sr":0,
    "qs_pg:pop_sr":2,
    "qs_pg:qs_pg_placetype":"locality",
    "wof:name":"Myr\u00f3fyllon",
    "wof:placetype":"locality",
    "wof:population":249
},
  "geometry": {"coordinates":[21.32472,39.36694],"type":"Point"}
}