{
  "type": "Feature",
  "properties": {
    "gn:admin1_code":"ESYE43",
    "gn:admin2_code":"43.0",
    "gn:admin3_code":"9320.0",
    "gn:asciiname":"Metochia",
    "gn:country_code":"GR",
    "gn:dem":127,
    "gn:feature_class":"P",
    "gn:feature_code":"PPLL",
    "gn:name":"Met\u00f3chia",
    "gn:population":0,
    "gn:timezone":"Europe/Athens",
    "iso:country":"GR",
    "name:ell_x_preferred":[
        "\u039c\u03b5\u03c4\u03cc\u03c7\u03b9\u03b1"
    ],
    "name:eng_x_preferred":[
        "Metochia"
    ],
    "wof:name":"Metochia",
    "wof:placetype":"locality"
},
  "geometry": {"coordinates":[24.09431,34.85652],"type":"Point"}
}