{
  "type": "Feature",
  "properties": {
    "gn:admin1_code":"ESYE43",
    "gn:admin2_code":"45.0",
    "gn:admin3_code":"9306",
    "gn:asciiname":"Paralia Fodele",
    "gn:country_code":"GR",
    "gn:dem":5,
    "gn:feature_class":"P",
    "gn:feature_code":"PPL",
    "gn:name":"Paral\u00eda F\u00f3dele",
    "gn:population":66,
    "gn:timezone":"Europe/Athens",
    "iso:country":"GR",
    "name:ell_x_preferred":[
        "\u03a0\u03b1\u03c1\u03b1\u03bb\u03af\u03b1 \u03a6\u03cc\u03b4\u03b5\u03bb\u03b5"
    ],
    "name:eng_x_preferred":[
        "Paralia Fodele"
    ],
    "wof:name":"Paralia Fodele",
    "wof:placetype":"locality",
    "wof:population":66
},
  "geometry": {"coordinates":[24.95321,35.40115],"type":"Point"}
}