{
  "type": "Feature",
  "properties": {
    "gn:admin1_code":"ESYE13",
    "gn:admin2_code":"11.0",
    "gn:admin3_code":"9066",
    "gn:asciiname":"Dafnero",
    "gn:country_code":"GR",
    "gn:dem":692,
    "gn:feature_class":"P",
    "gn:feature_code":"PPL",
    "gn:name":"Dafner\u00f3",
    "gn:population":0,
    "gn:timezone":"Europe/Athens",
    "iso:country":"GR",
    "name:bul_x_preferred":[
        "\u0414\u0430\u0444\u043d\u0435\u0440\u043e"
    ],
    "name:ell_x_preferred":[
        "Dafner\u00f3"
    ],
    "name:ell_x_variant":[
        "\u0394\u03b1\u03c6\u03bd\u03b5\u03c1\u03cc",
        "Dafner\u00f3n",
        "\u0394\u03b1\u03c6\u03bd\u03b5\u03c1\u03cc\u03bd",
        "\u0394\u03b1\u03c6\u03bd\u03b5\u03c1\u03cc \u039a\u03bf\u03b6\u03ac\u03bd\u03b7\u03c2"
    ],
    "name:mkd_x_preferred":[
        "\u0412\u0430\u0458\u043f\u0435\u0448"
    ],
    "name:und_x_variant":[
        "V\u00e1\u00efpes",
        "Dhafner\u00f3n"
    ],
    "wof:name":"Dafnero",
    "wof:placetype":"locality"
},
  "geometry": {"coordinates":[21.59099,40.17963],"type":"Point"}
}