{
  "type": "Feature",
  "properties": {
    "gn:population":1116,
    "iso:country":"GR",
    "name:ell_x_preferred":[
        "\u039b\u03bf\u03c5\u03c4\u03c1\u03ac"
    ],
    "name:und_x_variant":[
        "Loutr\u00e1"
    ],
    "qs:a0":"Greece",
    "qs:a1":"*\u0392\u039f\u03a1\u0395\u0399\u039f \u0391\u0399\u0393\u0391\u0399\u039f",
    "qs:a1_alt":"BOREIO AIGAIO",
    "qs:a1r":"0",
    "qs:a2_alt":"LESBOS",
    "qs:adm0":"Greece",
    "qs:la_lc":"*",
    "qs:level":"locality",
    "qs:loc":"\u039b\u039f\u03a5\u03a4\u03a1\u0391",
    "qs:loc_alt":"LOYTRA",
    "qs:pop":0,
    "qs:type":"buffered point",
    "wof:name":"\u039b\u039f\u03a5\u03a4\u03a1\u0391",
    "wof:placetype":"locality",
    "wof:population":1116
},
  "geometry": {"coordinates":[26.545044,39.057064],"type":"Point"}
}