{
  "type": "Feature",
  "properties": {
    "gn:admin1_code":"ESYE12",
    "gn:admin2_code":"15.0",
    "gn:admin3_code":"9057",
    "gn:asciiname":"Agia Paraskevi",
    "gn:country_code":"GR",
    "gn:dem":219,
    "gn:feature_class":"P",
    "gn:feature_code":"PPL",
    "gn:name":"Ag\u00eda Paraskev\u00ed",
    "gn:population":294,
    "gn:timezone":"Europe/Athens",
    "iso:country":"GR",
    "name:ell_x_preferred":[
        "\u0391\u03b3\u03af\u03b1 \u03a0\u03b1\u03c1\u03b1\u03c3\u03ba\u03b5\u03c5\u03ae"
    ],
    "name:ell_x_variant":[
        "Ag\u00eda Paraskev\u00ed",
        "Ay\u00eda Paraskev\u00ed"
    ],
    "name:eng_x_preferred":[
        "Agia Paraskevi"
    ],
    "wof:name":"Agia Paraskevi",
    "wof:placetype":"locality",
    "wof:population":294
},
  "geometry": {"coordinates":[23.60771,39.95337],"type":"Point"}
}