{
  "type": "Feature",
  "properties": {
    "gn:admin1_code":"ESYE43",
    "gn:admin2_code":"45.0",
    "gn:admin3_code":"9304",
    "gn:asciiname":"Rizikas",
    "gn:country_code":"GR",
    "gn:dem":270,
    "gn:feature_class":"P",
    "gn:feature_code":"PPL",
    "gn:name":"R\u00edzikas",
    "gn:population":0,
    "gn:timezone":"Europe/Athens",
    "iso:country":"GR",
    "name:ell_x_preferred":[
        "R\u00edzikas"
    ],
    "name:ell_x_variant":[
        "\u03a1\u03af\u03b6\u03b9\u03ba\u03b1\u03c2"
    ],
    "wof:name":"Rizikas",
    "wof:placetype":"locality"
},
  "geometry": {"coordinates":[25.04324,35.05944],"type":"Point"}
}