{
  "type": "Feature",
  "properties": {
    "iso:country":"GR",
    "name:ara_x_preferred":[
        "\u0633\u064a\u0631\u064a\u0641\u0648\u0633"
    ],
    "name:ast_x_preferred":[
        "Serifos"
    ],
    "name:bel_x_preferred":[
        "\u0421\u0435\u0440\u044b\u0444\u0430\u0441"
    ],
    "name:bul_x_preferred":[
        "\u0421\u0435\u0440\u0438\u0444\u043e\u0441"
    ],
    "name:cat_x_preferred":[
        "S\u00e8rifos"
    ],
    "name:ceb_x_preferred":[
        "S\u00e9rifos"
    ],
    "name:ces_x_preferred":[
        "Serifos"
    ],
    "name:dan_x_preferred":[
        "Serifos"
    ],
    "name:deu_x_preferred":[
        "Serifos"
    ],
    "name:ell_x_preferred":[
        "\u03a3\u03ad\u03c1\u03b9\u03c6\u03bf\u03c2"
    ],
    "name:est_x_preferred":[
        "S\u00e9rifos"
    ],
    "name:fas_x_preferred":[
        "\u0633\u0631\u06cc\u0641\u0648\u0633"
    ],
    "name:fin_x_preferred":[
        "S\u00e9rifos"
    ],
    "name:fra_x_preferred":[
        "S\u00e9rifos"
    ],
    "name:glg_x_preferred":[
        "Serifos"
    ],
    "name:heb_x_preferred":[
        "\u05e1\u05e8\u05d9\u05e4\u05d5\u05e1"
    ],
    "name:hrv_x_preferred":[
        "Serifos"
    ],
    "name:hye_x_preferred":[
        "\u054d\u0565\u0580\u056b\u0586\u0578\u057d"
    ],
    "name:ita_x_preferred":[
        "Serifo"
    ],
    "name:jpn_x_preferred":[
        "\u30bb\u30ea\u30d5\u30a9\u30b9\u5cf6"
    ],
    "name:lat_x_preferred":[
        "Seriphos"
    ],
    "name:nld_x_preferred":[
        "Serifos"
    ],
    "name:nno_x_preferred":[
        "S\u00e9rifos"
    ],
    "name:pol_x_preferred":[
        "Serifos"
    ],
    "name:por_x_preferred":[
        "S\u00e9rifos"
    ],
    "name:ron_x_preferred":[
        "Serifos"
    ],
    "name:rus_x_preferred":[
        "\u0421\u0435\u0440\u0438\u0444\u043e\u0441"
    ],
    "name:spa_x_preferred":[
        "Serifos"
    ],
    "name:sqi_x_preferred":[
        "Serifos"
    ],
    "name:srp_x_preferred":[
        "\u0421\u0435\u0440\u0438\u0444\u043e\u0441"
    ],
    "name:swe_x_preferred":[
        "Serifos"
    ],
    "name:tur_x_preferred":[
        "Koyunluca"
    ],
    "name:ukr_x_preferred":[
        "\u0421\u0435\u0440\u0456\u0444\u043e\u0441"
    ],
    "name:vie_x_preferred":[
        "Serifos"
    ],
    "name:zho_x_preferred":[
        "\u585e\u91cc\u798f\u65af\u5cf6"
    ],
    "qs_pg:aaroncc":"GR",
    "qs_pg:name":"Serifos",
    "qs_pg:name_adm0":"\u0395\u03bb\u03bb\u03ac\u03b4\u03b1",
    "qs_pg:name_adm1":"Aegean",
    "qs_pg:photos":222,
    "qs_pg:photos_1k":45,
    "qs_pg:photos_9k":1,
    "qs_pg:photos_9r":4,
    "qs_pg:photos_all":222,
    "qs_pg:photos_sr":4,
    "qs_pg:pop_sr":0,
    "qs_pg:qs_pg_placetype":"locality",
    "qs_pg:qs_pg_placetype_gp":"Town",
    "qs_pg:woe_adm0":23424833,
    "woe:adm0_id":23424833,
    "woe:name_adm0":"\u0395\u03bb\u03bb\u03ac\u03b4\u03b1",
    "woe:name_adm1":"Aegean",
    "woe:placetype":"Town",
    "wof:name":"Serifos",
    "wof:placetype":"locality"
},
  "geometry": {"coordinates":[24.506694,37.1539715],"type":"Point"}
}