{
  "type": "Feature",
  "properties": {
    "gn:admin1_code":"ESYE41",
    "gn:admin2_code":"51.0",
    "gn:admin3_code":"9261",
    "gn:asciiname":"Kedro",
    "gn:country_code":"GR",
    "gn:dem":12,
    "gn:feature_class":"P",
    "gn:feature_code":"PPL",
    "gn:name":"K\u00e9dro",
    "gn:population":89,
    "gn:timezone":"Europe/Athens",
    "iso:country":"GR",
    "name:ell_x_preferred":[
        "\u039a\u03ad\u03b4\u03c1\u03bf"
    ],
    "wof:name":"Kedro",
    "wof:placetype":"locality",
    "wof:population":89
},
  "geometry": {"coordinates":[26.51018,39.10362],"type":"Point"}
}