{
  "type": "Feature",
  "properties": {
    "gn:gn_country":"GR",
    "gn:gn_fcode":"PPL",
    "gn:gn_pop":804,
    "gn:population":3115,
    "iso:country":"GR",
    "name:ell_x_historical":[
        "\u03a0\u03b1\u03c1\u03b1\u03bb\u03af\u03b1",
        "\u0394\u03c1\u03ac\u03bc\u03b5\u03c3\u03b9"
    ],
    "name:ell_x_preferred":[
        "\u03a0\u03b1\u03c1\u03b1\u03bb\u03af\u03b1 \u0391\u03c5\u03bb\u03af\u03b4\u03bf\u03c2"
    ],
    "name:ell_x_variant":[
        "\u03a0\u03b1\u03c1\u03b1\u03bb\u03af\u03b1",
        "\u0394\u03c1\u03ac\u03bc\u03b5\u03c3\u03b9",
        "\u03a0\u03b1\u03c1\u03b1\u03bb\u03af\u03b1 \u0391\u03c5\u03bb\u03af\u03b4\u03b1\u03c2"
    ],
    "name:eng_x_preferred":[
        "Paralia Avlidos"
    ],
    "name:unk_x_variant":[
        "Dhr\u00e1mesi"
    ],
    "qs_pg:aaroncc":"GR",
    "qs_pg:gn_country":"GR",
    "qs_pg:gn_fcode":"PPL",
    "qs_pg:gn_pop":804,
    "qs_pg:name":"Paralia Avlidhos",
    "qs_pg:name_adm0":"\u0395\u03bb\u03bb\u03ac\u03b4\u03b1",
    "qs_pg:name_adm1":"Thessaly and Continental Greece",
    "qs_pg:photos_9k":1,
    "qs_pg:photos_9r":1,
    "qs_pg:photos_all":5,
    "qs_pg:photos_sr":0,
    "qs_pg:pop_sr":2,
    "qs_pg:qs_pg_placetype":"locality",
    "qs_pg:qs_pg_placetype_gp":"Town",
    "qs_pg:woe_adm0":23424833,
    "woe:adm0_id":23424833,
    "woe:name_adm0":"\u0395\u03bb\u03bb\u03ac\u03b4\u03b1",
    "woe:name_adm1":"Thessaly and Continental Greece",
    "woe:placetype":"Town",
    "wof:name":"Paralia Avlidhos",
    "wof:placetype":"locality",
    "wof:population":3115
},
  "geometry": {"coordinates":[23.63333,38.38333],"type":"Point"}
}