{
  "type": "Feature",
  "properties": {
    "gn:admin1_code":"ESYE43",
    "gn:admin2_code":"46.0",
    "gn:admin3_code":"9312",
    "gn:asciiname":"Mesa Lasithion",
    "gn:cc2":"GR",
    "gn:country_code":"GR",
    "gn:dem":854,
    "gn:feature_class":"P",
    "gn:feature_code":"PPL",
    "gn:name":"M\u00e9sa Las\u00edthion",
    "gn:population":0,
    "gn:timezone":"Europe/Athens",
    "iso:country":"GR",
    "name:und_x_variant":[
        "Lats\u00eddha",
        "M\u00e9sa Las\u00edthion"
    ],
    "wof:name":"Mesa Lasithion",
    "wof:placetype":"locality"
},
  "geometry": {"coordinates":[25.51293,35.1817],"type":"Point"}
}