{
  "type": "Feature",
  "properties": {
    "gn:admin1_code":"ESYE43",
    "gn:admin2_code":"43.0",
    "gn:admin3_code":"9319",
    "gn:asciiname":"Nipos",
    "gn:country_code":"GR",
    "gn:dem":174,
    "gn:feature_class":"P",
    "gn:feature_code":"PPL",
    "gn:name":"N\u00edpos",
    "gn:population":0,
    "gn:timezone":"Europe/Athens",
    "iso:country":"GR",
    "name:ell_x_preferred":[
        "\u039d\u03af\u03c0\u03bf\u03c2"
    ],
    "name:und_x_variant":[
        "N\u00edppos",
        "N\u00edpos"
    ],
    "wof:name":"Nipos",
    "wof:placetype":"locality"
},
  "geometry": {"coordinates":[24.16937,35.37882000000001],"type":"Point"}
}