{
  "type": "Feature",
  "properties": {
    "gn:admin1_code":"ESYE43",
    "gn:admin2_code":"43.0",
    "gn:admin3_code":"9320",
    "gn:asciiname":"Ampelos",
    "gn:country_code":"GR",
    "gn:dem":321,
    "gn:feature_class":"P",
    "gn:feature_code":"PPL",
    "gn:name":"\u00c1mpelos",
    "gn:population":10,
    "gn:timezone":"Europe/Athens",
    "iso:country":"GR",
    "name:ell_x_preferred":[
        "\u0386\u03bc\u03c0\u03b5\u03bb\u03bf\u03c2"
    ],
    "name:eng_x_preferred":[
        "Ampelos"
    ],
    "name:und_x_variant":[
        "\u00c1mbelos",
        "\u00c1mpelos"
    ],
    "wof:name":"Ampelos",
    "wof:placetype":"locality",
    "wof:population":10
},
  "geometry": {"coordinates":[24.05578,34.84448],"type":"Point"}
}