{
  "type": "Feature",
  "properties": {
    "gn:gn_country":"GR",
    "gn:gn_fcode":"PPL",
    "gn:gn_pop":471,
    "gn:population":471,
    "iso:country":"GR",
    "name:ell_x_preferred":[
        "\u0391\u03bc\u03ac\u03c1\u03b1\u03bd\u03c4\u03b1"
    ],
    "name:unk_x_variant":[
        "S\u00farlovon"
    ],
    "qs_pg:aaroncc":"GR",
    "qs_pg:gn_country":"GR",
    "qs_pg:gn_fcode":"PPL",
    "qs_pg:gn_pop":471,
    "qs_pg:name":"Am\u00e1ranta",
    "qs_pg:photos_9r":0,
    "qs_pg:photos_sr":0,
    "qs_pg:pop_sr":2,
    "qs_pg:qs_pg_placetype":"locality",
    "wof:name":"Am\u00e1ranta",
    "wof:placetype":"locality",
    "wof:population":471
},
  "geometry": {"coordinates":[22.80944,41.18611],"type":"Point"}
}