{
  "type": "Feature",
  "properties": {
    "gn:admin1_code":"ESYE11",
    "gn:admin2_code":"14.0",
    "gn:admin3_code":"9014",
    "gn:asciiname":"Orfanio",
    "gn:country_code":"GR",
    "gn:dem":46,
    "gn:feature_class":"P",
    "gn:feature_code":"PPL",
    "gn:name":"Orf\u00e1nio",
    "gn:population":656,
    "gn:timezone":"Europe/Athens",
    "iso:country":"GR",
    "name:bul_x_preferred":[
        "\u041e\u0440\u0444\u0430\u043d\u043e"
    ],
    "name:ceb_x_preferred":[
        "Orf\u00e1nio"
    ],
    "name:ell_x_preferred":[
        "\u039f\u03c1\u03c6\u03ac\u03bd\u03b9\u03bf"
    ],
    "name:ell_x_variant":[
        "\u039f\u03c1\u03c6\u03ac\u03bd\u03b9"
    ],
    "name:eng_x_preferred":[
        "Orfanio"
    ],
    "name:fin_x_preferred":[
        "Orf\u00e1ni"
    ],
    "name:ita_x_preferred":[
        "Orfani"
    ],
    "name:mkd_x_preferred":[
        "\u041e\u0440\u0444\u0430\u043d"
    ],
    "name:nno_x_preferred":[
        "Orf\u00e1ni"
    ],
    "name:sco_x_preferred":[
        "Orfani"
    ],
    "name:swe_x_preferred":[
        "Orf\u00e1nio"
    ],
    "name:und_x_variant":[
        "Orf\u00e1nion"
    ],
    "wof:name":"Orfanio",
    "wof:placetype":"locality",
    "wof:population":656
},
  "geometry": {"coordinates":[23.95105,40.7758],"type":"Point"}
}