{
  "type": "Feature",
  "properties": {
    "gn:gn_country":"GR",
    "gn:gn_fcode":"PPL",
    "gn:gn_pop":910,
    "gn:population":910,
    "iso:country":"GR",
    "name:bul_x_preferred":[
        "Nera\u00efdoch\u00f3ri"
    ],
    "name:ceb_x_preferred":[
        "Pi\u00e1leia"
    ],
    "name:ell_x_preferred":[
        "\u03a0\u03b9\u03ac\u03bb\u03b5\u03b9\u03b1"
    ],
    "name:ell_x_variant":[
        "\u03a0\u03b9\u03b1\u03bb\u03b5\u03af\u03b1 \u03a4\u03c1\u03b9\u03ba\u03ac\u03bb\u03c9\u03bd"
    ],
    "name:eng_x_preferred":[
        "Pialeia"
    ],
    "name:fin_x_preferred":[
        "Pi\u00e1leia"
    ],
    "name:fra_x_preferred":[
        "Pialeia"
    ],
    "name:ita_x_preferred":[
        "Pialeia"
    ],
    "name:jpn_x_preferred":[
        "\u30d4\u30e3\u30ea\u30a2"
    ],
    "name:nld_x_preferred":[
        "Pialeia"
    ],
    "name:nno_x_preferred":[
        "Pial\u00eda"
    ],
    "name:swe_x_preferred":[
        "Pi\u00e1leia"
    ],
    "name:unk_x_variant":[
        "Karvounolepen\u00edtsa"
    ],
    "qs_pg:aaroncc":"GR",
    "qs_pg:gn_country":"GR",
    "qs_pg:gn_fcode":"PPL",
    "qs_pg:gn_pop":910,
    "qs_pg:name":"Pi\u00e1leia",
    "qs_pg:photos_9r":0,
    "qs_pg:photos_sr":0,
    "qs_pg:pop_sr":2,
    "qs_pg:qs_pg_placetype":"locality",
    "wof:name":"Pi\u00e1leia",
    "wof:placetype":"locality",
    "wof:population":910
},
  "geometry": {"coordinates":[21.59417,39.50528],"type":"Point"}
}