{
  "type": "Feature",
  "properties": {
    "gn:admin1_code":"ESYE23",
    "gn:admin2_code":"38.0",
    "gn:admin3_code":"9130",
    "gn:asciiname":"Kato Salmeniko",
    "gn:country_code":"GR",
    "gn:dem":247,
    "gn:feature_class":"P",
    "gn:feature_code":"PPL",
    "gn:name":"K\u00e1to Salm\u00e9niko",
    "gn:population":0,
    "gn:timezone":"Europe/Athens",
    "iso:country":"GR",
    "name:ell_x_preferred":[
        "K\u00e1to Salm\u00e9niko"
    ],
    "name:ell_x_variant":[
        "\u039a\u03ac\u03c4\u03c9 \u03a3\u03b1\u03bb\u03bc\u03b5\u03bd\u03af\u03ba\u03bf",
        "\u039a\u03ac\u03c4\u03c9 \u03a3\u03b1\u03bb\u03bc\u03b5\u03bd\u03af\u03ba\u03bf\u03bd"
    ],
    "name:und_x_variant":[
        "Salmen\u00edkon",
        "K\u00e1to Salm\u00e9nikon",
        "K\u00e1to Salmen\u00edkos"
    ],
    "wof:name":"Kato Salmeniko",
    "wof:placetype":"locality"
},
  "geometry": {"coordinates":[21.94031,38.26533],"type":"Point"}
}