{
  "type": "Feature",
  "properties": {
    "gn:admin1_code":"ESYE43",
    "gn:admin2_code":"43.0",
    "gn:admin3_code":"9323",
    "gn:asciiname":"Spilia",
    "gn:country_code":"GR",
    "gn:dem":45,
    "gn:feature_class":"P",
    "gn:feature_code":"PPL",
    "gn:name":"Spili\u00e1",
    "gn:population":0,
    "gn:timezone":"Europe/Athens",
    "iso:country":"GR",
    "name:ceb_x_preferred":[
        "Spilia"
    ],
    "name:ell_x_preferred":[
        "Spili\u00e1"
    ],
    "name:ell_x_variant":[
        "\u03a3\u03c0\u03b7\u03bb\u03b9\u03ac"
    ],
    "name:swe_x_preferred":[
        "Spilia"
    ],
    "wof:name":"Spilia",
    "wof:placetype":"locality"
},
  "geometry": {"coordinates":[23.77899,35.51363],"type":"Point"}
}