{
  "type": "Feature",
  "properties": {
    "gn:admin1_code":"ESYE11",
    "gn:admin2_code":"4.0",
    "gn:admin3_code":"9003",
    "gn:asciiname":"Kato Vrontou",
    "gn:country_code":"GR",
    "gn:dem":626,
    "gn:feature_class":"P",
    "gn:feature_code":"PPL",
    "gn:name":"K\u00e1to Vronto\u00fa",
    "gn:population":0,
    "gn:timezone":"Europe/Athens",
    "iso:country":"GR",
    "name:ell_x_preferred":[
        "K\u00e1to Vronto\u00fa"
    ],
    "name:ell_x_variant":[
        "\u039a\u03ac\u03c4\u03c9 \u0392\u03c1\u03bf\u03bd\u03c4\u03bf\u03cd"
    ],
    "name:und_x_variant":[
        "Vrundi",
        "K\u00e1to Vrondo\u00fa"
    ],
    "wof:name":"Kato Vrontou",
    "wof:placetype":"locality"
},
  "geometry": {"coordinates":[23.75638,41.27416],"type":"Point"}
}