{
  "type": "Feature",
  "properties": {
    "gn:admin1_code":"ESYE22",
    "gn:admin2_code":"25.0",
    "gn:admin3_code":"9118",
    "gn:asciiname":"Kouknikades",
    "gn:country_code":"GR",
    "gn:dem":53,
    "gn:feature_class":"P",
    "gn:feature_code":"PPL",
    "gn:name":"Kouknik\u00e1des",
    "gn:population":56,
    "gn:timezone":"Europe/Athens",
    "iso:country":"GR",
    "name:ell_x_preferred":[
        "\u039a\u03bf\u03c5\u03ba\u03bd\u03b9\u03ba\u03ac\u03b4\u03b5\u03c2"
    ],
    "name:eng_x_preferred":[
        "Kouknikades"
    ],
    "wof:name":"Kouknikades",
    "wof:placetype":"locality",
    "wof:population":56
},
  "geometry": {"coordinates":[19.67681,39.77292],"type":"Point"}
}