{
  "type": "Feature",
  "properties": {
    "gn:admin1_code":"ESYE22",
    "gn:admin2_code":"26.0",
    "gn:admin3_code":"9121",
    "gn:asciiname":"Kalavros",
    "gn:country_code":"GR",
    "gn:dem":389,
    "gn:feature_class":"P",
    "gn:feature_code":"PPL",
    "gn:name":"Kalavr\u00f3s",
    "gn:population":22,
    "gn:timezone":"Europe/Athens",
    "iso:country":"GR",
    "name:ell_x_preferred":[
        "\u039a\u03b1\u03bb\u03b1\u03b2\u03c1\u03cc\u03c2"
    ],
    "name:eng_x_preferred":[
        "Kalavros"
    ],
    "wof:name":"Kalavros",
    "wof:placetype":"locality",
    "wof:population":22
},
  "geometry": {"coordinates":[20.64962,38.80948],"type":"Point"}
}