{
  "type": "Feature",
  "properties": {
    "gn:admin1_code":"ESYE25",
    "gn:admin2_code":"42.0",
    "gn:admin3_code":"9248",
    "gn:asciiname":"Agios Georgios Minas",
    "gn:country_code":"GR",
    "gn:dem":119,
    "gn:feature_class":"P",
    "gn:feature_code":"PPL",
    "gn:name":"\u00c1gios Ge\u00f3rgios M\u00ednas",
    "gn:population":4,
    "gn:timezone":"Europe/Athens",
    "iso:country":"GR",
    "name:ell_x_preferred":[
        "\u0386\u03b3\u03b9\u03bf\u03c2 \u0393\u03b5\u03ce\u03c1\u03b3\u03b9\u03bf\u03c2 \u039c\u03af\u03bd\u03b1\u03c2"
    ],
    "name:eng_x_preferred":[
        "Agios Georgios Minas"
    ],
    "wof:name":"Agios Georgios Minas",
    "wof:placetype":"locality",
    "wof:population":4
},
  "geometry": {"coordinates":[22.40696,36.54524],"type":"Point"}
}