{
  "type": "Feature",
  "properties": {
    "gn:admin1_code":"ESYE43",
    "gn:admin2_code":"45.0",
    "gn:admin3_code":"9309",
    "gn:asciiname":"Stamnoi",
    "gn:country_code":"GR",
    "gn:dem":302,
    "gn:feature_class":"P",
    "gn:feature_code":"PPL",
    "gn:name":"Stamno\u00ed",
    "gn:population":0,
    "gn:timezone":"Europe/Athens",
    "iso:country":"GR",
    "wof:name":"Stamnoi",
    "wof:placetype":"locality"
},
  "geometry": {"coordinates":[25.24075,35.27001],"type":"Point"}
}