{
  "type": "Feature",
  "properties": {
    "gn:admin1_code":"ESYE25",
    "gn:admin2_code":"41.0",
    "gn:admin3_code":"9241",
    "gn:asciiname":"Makri",
    "gn:country_code":"GR",
    "gn:dem":715,
    "gn:feature_class":"P",
    "gn:feature_code":"PPL",
    "gn:name":"M\u00e1kri",
    "gn:population":0,
    "gn:timezone":"Europe/Athens",
    "iso:country":"GR",
    "name:ell_x_preferred":[
        "\u039c\u03ac\u03ba\u03c1\u03b7"
    ],
    "name:fra_x_preferred":[
        "Makri"
    ],
    "name:und_x_variant":[
        "Bol\u00e9ta",
        "M\u00e1kri"
    ],
    "wof:name":"Makri",
    "wof:placetype":"locality"
},
  "geometry": {"coordinates":[22.32591,37.47197],"type":"Point"}
}