{
  "type": "Feature",
  "properties": {
    "gn:admin1_code":"ESYE23",
    "gn:admin2_code":"31.0",
    "gn:admin3_code":"9123",
    "gn:asciiname":"Stamatoyiannaiika",
    "gn:country_code":"GR",
    "gn:dem":297,
    "gn:feature_class":"P",
    "gn:feature_code":"PPL",
    "gn:name":"Stamatoyianna\u00edika",
    "gn:population":74,
    "gn:timezone":"Europe/Athens",
    "iso:country":"GR",
    "name:ell_x_preferred":[
        "\u03a3\u03c4\u03b1\u03bc\u03b1\u03c4\u03bf\u03b3\u03b9\u03b1\u03bd\u03bd\u03b1\u03af\u03b9\u03ba\u03b1"
    ],
    "name:eng_x_preferred":[
        "Stamatogiannaiika"
    ],
    "name:und_x_variant":[
        "Stamatoyiann\u00e9\u00efka",
        "Stamatoyianna\u00edika"
    ],
    "wof:name":"Stamatoyiannaiika",
    "wof:placetype":"locality",
    "wof:population":74
},
  "geometry": {"coordinates":[21.46857,38.71451],"type":"Point"}
}