{
  "type": "Feature",
  "properties": {
    "gn:admin1_code":"ESYE24",
    "gn:admin2_code":"34.0",
    "gn:admin3_code":"9152",
    "gn:asciiname":"Trakhilion",
    "gn:cc2":"GR",
    "gn:country_code":"GR",
    "gn:dem":415,
    "gn:feature_class":"P",
    "gn:feature_code":"PPL",
    "gn:name":"Trakh\u00edlion",
    "gn:population":0,
    "gn:timezone":"Europe/Athens",
    "iso:country":"GR",
    "name:und_x_variant":[
        "Trakh\u00edli",
        "Trakh\u00edlion"
    ],
    "wof:name":"Trakhilion",
    "wof:placetype":"locality"
},
  "geometry": {"coordinates":[24.00676,38.51056],"type":"Point"}
}