{
  "type": "Feature",
  "properties": {
    "gn:gn_country":"GR",
    "gn:gn_fcode":"PPL",
    "gn:gn_pop":631,
    "gn:population":631,
    "iso:country":"GR",
    "name:bul_x_preferred":[
        "\u041d\u0435\u0438 \u041f\u043e\u0440\u0438"
    ],
    "name:dut_x_preferred":[
        "Neoi Poroi"
    ],
    "name:ell_x_preferred":[
        "\u039d\u03ad\u03bf\u03b9 \u03a0\u03cc\u03c1\u03bf\u03b9"
    ],
    "name:eng_x_preferred":[
        "Neoi Poroi"
    ],
    "name:ger_x_preferred":[
        "Pori"
    ],
    "name:gre_x_preferred":[
        "\u039d\u03ad\u03bf\u03b9 \u03a0\u03cc\u03c1\u03bf\u03b9 \u03a0\u03b9\u03b5\u03c1\u03af\u03b1\u03c2"
    ],
    "name:hun_x_preferred":[
        "Nei Pori"
    ],
    "name:rus_x_preferred":[
        "Neori poroi"
    ],
    "name:srp_x_preferred":[
        "Nei Pori"
    ],
    "name:swe_x_preferred":[
        "N\u00e9oi P\u00f3roi"
    ],
    "name:unk_x_variant":[
        "Nova Purlija"
    ],
    "qs_pg:aaroncc":"GR",
    "qs_pg:gn_country":"GR",
    "qs_pg:gn_fcode":"PPL",
    "qs_pg:gn_pop":631,
    "qs_pg:name":"Neoi Poroi",
    "qs_pg:name_adm0":"\u0395\u03bb\u03bb\u03ac\u03b4\u03b1",
    "qs_pg:name_adm1":"Macedonia and Thrace",
    "qs_pg:photos":82,
    "qs_pg:photos_1k":17,
    "qs_pg:photos_9k":1,
    "qs_pg:photos_9r":3,
    "qs_pg:photos_all":82,
    "qs_pg:photos_sr":3,
    "qs_pg:pop_sr":2,
    "qs_pg:qs_pg_placetype":"locality",
    "qs_pg:qs_pg_placetype_gp":"Town",
    "qs_pg:woe_adm0":23424833,
    "woe:adm0_id":23424833,
    "woe:name_adm0":"\u0395\u03bb\u03bb\u03ac\u03b4\u03b1",
    "woe:name_adm1":"Macedonia and Thrace",
    "woe:placetype":"Town",
    "wof:name":"Neoi Poroi",
    "wof:placetype":"locality",
    "wof:population":631
},
  "geometry": {"coordinates":[22.65139,39.97639],"type":"Point"}
}