{
  "type": "Feature",
  "properties": {
    "gn:gn_country":"GR",
    "gn:gn_fcode":"PPL",
    "gn:gn_pop":0,
    "iso:country":"GR",
    "name:ell_x_preferred":[
        "\u039a\u03b1\u03bb\u03b1\u03bc\u03ac\u03ba\u03b9"
    ],
    "name:ell_x_variant":[
        "\u039a\u03b1\u03bb\u03b1\u03bc\u03ac\u03ba\u03b9\u03bf\u03bd"
    ],
    "name:unk_x_variant":[
        "\u00c1no Kalam\u00e1ki"
    ],
    "qs_pg:aaroncc":"GR",
    "qs_pg:gn_country":"GR",
    "qs_pg:gn_fcode":"PPL",
    "qs_pg:gn_pop":0,
    "qs_pg:name":"Kalamakion",
    "qs_pg:name_adm0":"\u0395\u03bb\u03bb\u03ac\u03b4\u03b1",
    "qs_pg:name_adm1":"Thessaly and Continental Greece",
    "qs_pg:photos_9k":1,
    "qs_pg:photos_9r":1,
    "qs_pg:photos_all":1,
    "qs_pg:photos_sr":0,
    "qs_pg:pop_sr":0,
    "qs_pg:qs_pg_placetype":"locality",
    "qs_pg:qs_pg_placetype_gp":"Town",
    "qs_pg:woe_adm0":23424833,
    "woe:adm0_id":23424833,
    "woe:name_adm0":"\u0395\u03bb\u03bb\u03ac\u03b4\u03b1",
    "woe:name_adm1":"Thessaly and Continental Greece",
    "woe:placetype":"Town",
    "wof:name":"Kalamakion",
    "wof:placetype":"locality"
},
  "geometry": {"coordinates":[22.75,39.56667],"type":"Point"}
}