{
  "type": "Feature",
  "properties": {
    "gn:admin1_code":"ESYE13",
    "gn:admin2_code":"9.0",
    "gn:admin3_code":"9065",
    "gn:asciiname":"Spilios",
    "gn:country_code":"GR",
    "gn:dem":866,
    "gn:feature_class":"P",
    "gn:feature_code":"PPL",
    "gn:name":"Sp\u00edlios",
    "gn:population":14,
    "gn:timezone":"Europe/Athens",
    "iso:country":"GR",
    "name:ell_x_preferred":[
        "\u03a3\u03c0\u03ae\u03bb\u03b9\u03bf\u03c2"
    ],
    "name:eng_x_preferred":[
        "Spilios"
    ],
    "name:und_x_variant":[
        "Sp\u00edlios"
    ],
    "wof:name":"Spilios",
    "wof:placetype":"locality",
    "wof:population":14
},
  "geometry": {"coordinates":[21.20416,40.358],"type":"Point"}
}