{
  "type": "Feature",
  "properties": {
    "gn:admin1_code":"ESYE25",
    "gn:admin2_code":"36.0",
    "gn:admin3_code":"9234",
    "gn:asciiname":"Kokkinadhes",
    "gn:country_code":"GR",
    "gn:dem":297,
    "gn:feature_class":"P",
    "gn:feature_code":"PPL",
    "gn:name":"Kokkin\u00e1dhes",
    "gn:population":51,
    "gn:timezone":"Europe/Athens",
    "iso:country":"GR",
    "name:ell_x_preferred":[
        "\u039a\u03bf\u03ba\u03ba\u03b9\u03bd\u03ac\u03b4\u03b5\u03c2"
    ],
    "name:eng_x_preferred":[
        "Kokkinades"
    ],
    "wof:name":"Kokkinadhes",
    "wof:placetype":"locality",
    "wof:population":51
},
  "geometry": {"coordinates":[22.9855,37.59443],"type":"Point"}
}