{
  "type": "Feature",
  "properties": {
    "gn:admin1_code":"ESYE43",
    "gn:admin2_code":"45.0",
    "gn:admin3_code":"9302",
    "gn:asciiname":"Vathipetron",
    "gn:cc2":"GR",
    "gn:country_code":"GR",
    "gn:dem":529,
    "gn:feature_class":"P",
    "gn:feature_code":"PPL",
    "gn:name":"Vath\u00edpetron",
    "gn:population":0,
    "gn:timezone":"Europe/Athens",
    "iso:country":"GR",
    "name:und_x_variant":[
        "Vath\u00edpetra",
        "Vath\u00edpetron"
    ],
    "wof:name":"Vathipetron",
    "wof:placetype":"locality"
},
  "geometry": {"coordinates":[25.15809,35.2053],"type":"Point"}
}