{
  "type": "Feature",
  "properties": {
    "gn:gn_country":"GR",
    "gn:gn_fcode":"PPL",
    "gn:gn_pop":4561,
    "gn:population":5392,
    "iso:country":"GR",
    "name:ara_x_preferred":[
        "\u0628\u0644\u0627\u063a\u064a\u0627\u0631\u064a"
    ],
    "name:bul_x_preferred":[
        "\u041f\u043b\u0430\u044f\u0440\u0438"
    ],
    "name:dut_x_preferred":[
        "Plagiari"
    ],
    "name:ell_x_preferred":[
        "\u03a0\u03bb\u03b1\u03b3\u03b9\u03ac\u03c1\u03b9\u03bf\u03bd"
    ],
    "name:ell_x_variant":[
        "\u03a0\u03bb\u03b1\u03b3\u03b9\u03ac\u03c1\u03b9"
    ],
    "name:eng_x_preferred":[
        "Plagiari"
    ],
    "name:gre_x_preferred":[
        "\u03a0\u03bb\u03b1\u03b3\u03b9\u03ac\u03c1\u03b9 \u0398\u03b5\u03c3\u03c3\u03b1\u03bb\u03bf\u03bd\u03af\u03ba\u03b7\u03c2"
    ],
    "name:mac_x_preferred":[
        "\u0423\u0437\u0443\u043d \u0410\u043b\u0438"
    ],
    "name:nno_x_preferred":[
        "Plaj\u00e1ri"
    ],
    "name:swe_x_preferred":[
        "Plagi\u00e1ri"
    ],
    "name:unk_x_variant":[
        "Uz\u00fan-Al\u00ed"
    ],
    "qs_pg:aaroncc":"GR",
    "qs_pg:gn_country":"GR",
    "qs_pg:gn_fcode":"PPL",
    "qs_pg:gn_pop":4561,
    "qs_pg:name":"Plagi\u00e1rion",
    "qs_pg:photos_9r":0,
    "qs_pg:photos_sr":0,
    "qs_pg:pop_sr":4,
    "qs_pg:qs_pg_placetype":"locality",
    "wof:name":"Plagi\u00e1rion",
    "wof:placetype":"locality",
    "wof:population":5392
},
  "geometry": {"coordinates":[22.95803,40.47365],"type":"Point"}
}