{
  "type": "Feature",
  "properties": {
    "gn:population":6282,
    "iso:country":"GR",
    "name:ara_x_preferred":[
        "\u063a\u0627\u0631\u063a\u0627\u0644\u064a\u0627\u0646\u0648\u064a"
    ],
    "name:ceb_x_preferred":[
        "Gargali\u00e1noi"
    ],
    "name:deu_x_preferred":[
        "Gargaliani"
    ],
    "name:ell_x_preferred":[
        "\u0393\u03b1\u03c1\u03b3\u03b1\u03bb\u03b9\u03ac\u03bd\u03bf\u03b9"
    ],
    "name:eng_x_preferred":[
        "Gargalianoi"
    ],
    "name:fin_x_preferred":[
        "Gargali\u00e1noi"
    ],
    "name:fra_x_preferred":[
        "Gargalianoi"
    ],
    "name:ita_x_preferred":[
        "Gargalianoi"
    ],
    "name:jpn_x_preferred":[
        "\u30ac\u30eb\u30ac\u30ea\u30e3\u30cb"
    ],
    "name:nld_x_preferred":[
        "Gargalianoi"
    ],
    "name:nno_x_preferred":[
        "Gargali\u00e1ni"
    ],
    "name:por_x_preferred":[
        "Gargaliani"
    ],
    "name:ron_x_preferred":[
        "Gargalianoi"
    ],
    "name:rus_x_preferred":[
        "\u0413\u0430\u0440\u0433\u0430\u043b\u044c\u044f\u043d\u0438"
    ],
    "name:swe_x_preferred":[
        "Gargali\u00e1noi"
    ],
    "qs:a0":"Greece",
    "qs:a1":"*\u03a0\u0395\u039b\u039f\u03a0\u039f\u039d\u039d\u0397\u03a3\u039f\u03a3",
    "qs:a1_alt":"PELOPONNHSOS",
    "qs:a1r":"0",
    "qs:a2_alt":"MESSHNIA",
    "qs:adm0":"Greece",
    "qs:la_lc":"*",
    "qs:level":"locality",
    "qs:loc":"\u0393\u0391\u03a1\u0393\u0391\u039b\u0399\u0391\u039d\u039f\u0399",
    "qs:loc_alt":"GARGALIANOI",
    "qs:pop":0,
    "qs:type":"buffered point",
    "wd:wordcount":143,
    "wof:name":"\u0393\u0391\u03a1\u0393\u0391\u039b\u0399\u0391\u039d\u039f\u0399",
    "wof:placetype":"locality",
    "wof:population":6282
},
  "geometry": {"coordinates":[21.638924,37.067173],"type":"Point"}
}