{
  "type": "Feature",
  "properties": {
    "gn:admin1_code":"ESYE23",
    "gn:admin2_code":"31.0",
    "gn:admin3_code":"9128",
    "gn:asciiname":"Platanos",
    "gn:country_code":"GR",
    "gn:dem":859,
    "gn:feature_class":"P",
    "gn:feature_code":"PPL",
    "gn:name":"Pl\u00e1tanos",
    "gn:population":0,
    "gn:timezone":"Europe/Athens",
    "iso:country":"GR",
    "name:ell_x_preferred":[
        "\u03a0\u03bb\u03ac\u03c4\u03b1\u03bd\u03bf\u03c2"
    ],
    "name:und_x_variant":[
        "Platano",
        "Pl\u00e1tanos"
    ],
    "wof:name":"Platanos",
    "wof:placetype":"locality"
},
  "geometry": {"coordinates":[21.79206,38.59897],"type":"Point"}
}