{
  "type": "Feature",
  "properties": {
    "gn:admin1_code":"ESYE23",
    "gn:admin2_code":"31.0",
    "gn:admin3_code":"9128",
    "gn:asciiname":"Platanos",
    "gn:country_code":"GR",
    "gn:dem":859,
    "gn:feature_class":"P",
    "gn:feature_code":"PPL",
    "gn:name":"Pl\u00e1tanos",
    "gn:population":0,
    "gn:timezone":"Europe/Athens",
    "iso:country":"GR",
    "name:bul_x_preferred":[
        "\u041f\u043b\u0430\u0442\u0430\u043d\u043e\u0441"
    ],
    "name:deu_x_preferred":[
        "Platanos"
    ],
    "name:ell_x_preferred":[
        "\u03a0\u03bb\u03ac\u03c4\u03b1\u03bd\u03bf\u03c2"
    ],
    "name:ell_x_variant":[
        "\u03a0\u03bb\u03ac\u03c4\u03b1\u03bd\u03bf\u03c2 \u0391\u03b9\u03c4\u03c9\u03bb\u03bf\u03b1\u03ba\u03b1\u03c1\u03bd\u03b1\u03bd\u03af\u03b1\u03c2"
    ],
    "name:fin_x_preferred":[
        "Pl\u00e1tanos"
    ],
    "name:ita_x_preferred":[
        "Platanos"
    ],
    "name:nld_x_preferred":[
        "Platanos"
    ],
    "name:ron_x_preferred":[
        "Platanos"
    ],
    "name:und_x_variant":[
        "Platano",
        "Pl\u00e1tanos"
    ],
    "wof:name":"Platanos",
    "wof:placetype":"locality"
},
  "geometry": {"coordinates":[21.79206,38.59897],"type":"Point"}
}