{
  "type": "Feature",
  "properties": {
    "gn:admin1_code":"ESYE41",
    "gn:asciiname":"Pigi",
    "gn:country_code":"GR",
    "gn:dem":416,
    "gn:feature_class":"P",
    "gn:feature_code":"PPL",
    "gn:name":"Pig\u00ed",
    "gn:population":0,
    "gn:timezone":"Europe/Athens",
    "iso:country":"GR",
    "name:ceb_x_preferred":[
        "Pigi"
    ],
    "name:ell_x_preferred":[
        "Pig\u00ed"
    ],
    "name:ell_x_variant":[
        "\u03a0\u03b7\u03b3\u03ae"
    ],
    "name:swe_x_preferred":[
        "Pigi"
    ],
    "wof:name":"Pigi",
    "wof:placetype":"locality"
},
  "geometry": {"coordinates":[26.14153,37.61865],"type":"Point"}
}