{
  "type": "Feature",
  "properties": {
    "gn:admin1_code":"ESYE11",
    "gn:admin2_code":"2.0",
    "gn:admin3_code":"9021",
    "gn:asciiname":"Mikro Doukato",
    "gn:country_code":"GR",
    "gn:dem":41,
    "gn:feature_class":"P",
    "gn:feature_code":"PPL",
    "gn:name":"Mikr\u00f3 Douk\u00e1to",
    "gn:population":0,
    "gn:timezone":"Europe/Athens",
    "iso:country":"GR",
    "name:ell_x_preferred":[
        "Mikr\u00f3 Douk\u00e1to"
    ],
    "name:ell_x_variant":[
        "\u039c\u03b9\u03ba\u03c1\u03cc \u0394\u03bf\u03c5\u03ba\u03ac\u03c4\u03bf",
        "\u039c\u03b9\u03ba\u03c1\u03cc\u03bd \u0394\u03bf\u03c5\u03ba\u03ac\u03c4\u03bf\u03bd"
    ],
    "name:und_x_variant":[
        "Mikr\u00f3n Dhouk\u00e1ton",
        "Mikr\u00f3n Douk\u00e1ton"
    ],
    "wof:name":"Mikro Doukato",
    "wof:placetype":"locality"
},
  "geometry": {"coordinates":[25.40815,41.0375],"type":"Point"}
}