{
  "type": "Feature",
  "properties": {
    "gn:gn_country":"GR",
    "gn:gn_fcode":"PPL",
    "gn:gn_pop":239,
    "gn:population":239,
    "iso:country":"GR",
    "name:ell_x_preferred":[
        "\u039b\u03b9\u03bc\u03ad\u03c1\u03b9"
    ],
    "name:ell_x_variant":[
        "\u039b\u03b9\u03bc\u03ad\u03c1\u03b9\u03bf\u03bd"
    ],
    "name:unk_x_variant":[
        "K\u00f3niavi"
    ],
    "qs_pg:aaroncc":"GR",
    "qs_pg:gn_country":"GR",
    "qs_pg:gn_fcode":"PPL",
    "qs_pg:gn_pop":239,
    "qs_pg:name":"Limerion",
    "qs_pg:name_adm0":"\u0395\u03bb\u03bb\u03ac\u03b4\u03b1",
    "qs_pg:name_adm1":"Thessaly and Continental Greece",
    "qs_pg:photos_9r":0,
    "qs_pg:photos_sr":0,
    "qs_pg:pop_sr":2,
    "qs_pg:qs_pg_placetype":"locality",
    "qs_pg:qs_pg_placetype_gp":"Town",
    "qs_pg:woe_adm0":23424833,
    "woe:adm0_id":23424833,
    "woe:name_adm0":"\u0395\u03bb\u03bb\u03ac\u03b4\u03b1",
    "woe:name_adm1":"Thessaly and Continental Greece",
    "woe:placetype":"Town",
    "wof:name":"Limerion",
    "wof:placetype":"locality",
    "wof:population":239
},
  "geometry": {"coordinates":[21.53528,39.06806],"type":"Point"}
}