{
  "type": "Feature",
  "properties": {
    "gn:admin1_code":"ESYE22",
    "gn:admin2_code":"27.0",
    "gn:admin3_code":"9120",
    "gn:asciiname":"Vary",
    "gn:country_code":"GR",
    "gn:dem":450,
    "gn:feature_class":"P",
    "gn:feature_code":"PPL",
    "gn:name":"Var\u00fd",
    "gn:population":0,
    "gn:timezone":"Europe/Athens",
    "iso:country":"GR",
    "name:ara_x_preferred":[
        "\u0641\u0627\u0631\u064a"
    ],
    "name:ceb_x_preferred":[
        "Vary"
    ],
    "name:deu_x_preferred":[
        "Wary"
    ],
    "name:ell_x_preferred":[
        "Var\u00fd"
    ],
    "name:ell_x_variant":[
        "\u0392\u03b1\u03c1\u03cd"
    ],
    "name:epo_x_preferred":[
        "Vari"
    ],
    "name:hun_x_preferred":[
        "V\u00e1ri"
    ],
    "name:hye_x_preferred":[
        "\u054e\u0561\u0580\u056b"
    ],
    "name:rue_x_preferred":[
        "\u0412\u0430\u0440\u044b"
    ],
    "name:rus_x_preferred":[
        "\u0412\u0430\u0440\u044b"
    ],
    "name:ukr_x_preferred":[
        "\u0412\u0430\u0440\u0438"
    ],
    "name:und_x_variant":[
        "Var\u00ed"
    ],
    "name:zho_x_preferred":[
        "\u74e6\u91cc"
    ],
    "wof:name":"Vary",
    "wof:placetype":"locality"
},
  "geometry": {"coordinates":[20.58003,38.38561],"type":"Point"}
}