{
  "type": "Feature",
  "properties": {
    "gn:admin1_code":"ESYE22",
    "gn:admin2_code":"27.0",
    "gn:admin3_code":"9120",
    "gn:asciiname":"Vary",
    "gn:country_code":"GR",
    "gn:dem":450,
    "gn:feature_class":"P",
    "gn:feature_code":"PPL",
    "gn:name":"Var\u00fd",
    "gn:population":0,
    "gn:timezone":"Europe/Athens",
    "iso:country":"GR",
    "name:ell_x_preferred":[
        "Var\u00fd"
    ],
    "name:ell_x_variant":[
        "\u0392\u03b1\u03c1\u03cd"
    ],
    "name:und_x_variant":[
        "Var\u00ed"
    ],
    "wof:name":"Vary",
    "wof:placetype":"locality"
},
  "geometry": {"coordinates":[20.58003,38.38561],"type":"Point"}
}