{
  "type": "Feature",
  "properties": {
    "gn:admin1_code":"ESYE11",
    "gn:admin2_code":"14.0",
    "gn:admin3_code":"9012",
    "gn:asciiname":"Lydia",
    "gn:country_code":"GR",
    "gn:dem":83,
    "gn:feature_class":"P",
    "gn:feature_code":"PPL",
    "gn:name":"Lyd\u00eda",
    "gn:population":808,
    "gn:timezone":"Europe/Athens",
    "iso:country":"GR",
    "name:ell_x_preferred":[
        "\u039b\u03c5\u03b4\u03af\u03b1"
    ],
    "name:ell_x_variant":[
        "Lyd\u00eda"
    ],
    "name:eng_x_preferred":[
        "Lydia"
    ],
    "name:und_x_variant":[
        "Idhr\u00f3milos",
        "Idhr\u00f3miloi"
    ],
    "wof:name":"Lydia",
    "wof:placetype":"locality",
    "wof:population":808
},
  "geometry": {"coordinates":[24.28153,41.03061],"type":"Point"}
}