{
  "type": "Feature",
  "properties": {
    "gn:admin1_code":"ESYE23",
    "gn:admin2_code":"38.0",
    "gn:admin3_code":"9134",
    "gn:asciiname":"Moira",
    "gn:country_code":"GR",
    "gn:dem":834,
    "gn:feature_class":"P",
    "gn:feature_code":"PPL",
    "gn:name":"Mo\u00edra",
    "gn:population":0,
    "gn:timezone":"Europe/Athens",
    "iso:country":"GR",
    "name:ell_x_preferred":[
        "\u039c\u03bf\u03af\u03c1\u03b1"
    ],
    "name:und_x_variant":[
        "M\u00edra",
        "Mo\u00edra"
    ],
    "wof:name":"Moira",
    "wof:placetype":"locality"
},
  "geometry": {"coordinates":[21.85422,38.15258],"type":"Point"}
}