{
  "type": "Feature",
  "properties": {
    "gn:admin1_code":"ESYE23",
    "gn:admin2_code":"38.0",
    "gn:admin3_code":"9134",
    "gn:asciiname":"Moira",
    "gn:country_code":"GR",
    "gn:dem":834,
    "gn:feature_class":"P",
    "gn:feature_code":"PPL",
    "gn:name":"Mo\u00edra",
    "gn:population":0,
    "gn:timezone":"Europe/Athens",
    "iso:country":"GR",
    "name:ceb_x_preferred":[
        "Moira"
    ],
    "name:ces_x_preferred":[
        "Moira"
    ],
    "name:deu_x_preferred":[
        "Moira"
    ],
    "name:ell_x_preferred":[
        "\u039c\u03bf\u03af\u03c1\u03b1"
    ],
    "name:fra_x_preferred":[
        "Moira"
    ],
    "name:ita_x_preferred":[
        "Moira"
    ],
    "name:jpn_x_preferred":[
        "\u30e2\u30a4\u30e9"
    ],
    "name:lit_x_preferred":[
        "Moira"
    ],
    "name:nld_x_preferred":[
        "Moira"
    ],
    "name:pol_x_preferred":[
        "Moira"
    ],
    "name:por_x_preferred":[
        "Moira"
    ],
    "name:rus_x_preferred":[
        "\u041c\u043e\u0439\u0440\u0430"
    ],
    "name:swe_x_preferred":[
        "Moira"
    ],
    "name:und_x_variant":[
        "M\u00edra",
        "Mo\u00edra"
    ],
    "wof:name":"Moira",
    "wof:placetype":"locality"
},
  "geometry": {"coordinates":[21.85422,38.15258],"type":"Point"}
}