{
  "type": "Feature",
  "properties": {
    "gn:admin1_code":"ESYE11",
    "gn:admin2_code":"14.0",
    "gn:admin3_code":"9014",
    "gn:asciiname":"Melissokomeio",
    "gn:country_code":"GR",
    "gn:dem":139,
    "gn:feature_class":"P",
    "gn:feature_code":"PPL",
    "gn:name":"Melissokome\u00edo",
    "gn:population":284,
    "gn:timezone":"Europe/Athens",
    "iso:country":"GR",
    "name:ell_x_preferred":[
        "\u039c\u03b5\u03bb\u03b9\u03c3\u03c3\u03bf\u03ba\u03bf\u03bc\u03b5\u03af\u03bf"
    ],
    "name:ell_x_variant":[
        "Melissokome\u00edo",
        "Melissokome\u00edon",
        "\u039c\u03b5\u03bb\u03b9\u03c3\u03c3\u03bf\u03ba\u03bf\u03bc\u03b5\u03af\u03bf\u03bd"
    ],
    "name:eng_x_preferred":[
        "Melissokomeio"
    ],
    "name:und_x_variant":[
        "Chitakl\u00ed",
        "Melisokh\u00f3ri",
        "Melissokomi\u00f3",
        "Melissokom\u00edon"
    ],
    "wof:name":"Melissokomeio",
    "wof:placetype":"locality",
    "wof:population":284
},
  "geometry": {"coordinates":[24.16559,40.8707],"type":"Point"}
}