{
  "type": "Feature",
  "properties": {
    "gn:admin1_code":"ESYE14",
    "gn:admin2_code":"23.0",
    "gn:admin3_code":"9096",
    "gn:asciiname":"Othomaniko",
    "gn:country_code":"GR",
    "gn:dem":114,
    "gn:feature_class":"P",
    "gn:feature_code":"PPL",
    "gn:name":"Othomanik\u00f3",
    "gn:population":0,
    "gn:timezone":"Europe/Athens",
    "iso:country":"GR",
    "name:ell_x_preferred":[
        "Othomanik\u00f3"
    ],
    "name:ell_x_variant":[
        "\u039f\u03b8\u03c9\u03bc\u03b1\u03bd\u03b9\u03ba\u03cc",
        "\u039f\u03b8\u03c9\u03bc\u03b1\u03bd\u03b9\u03ba\u03cc\u03bd"
    ],
    "name:und_x_variant":[
        "Mikr\u00f3 Karal\u00e1ri",
        "Othomanik\u00f3n"
    ],
    "wof:name":"Othomaniko",
    "wof:placetype":"locality"
},
  "geometry": {"coordinates":[22.1898,39.24677],"type":"Point"}
}