{
  "type": "Feature",
  "properties": {
    "gn:admin1_code":"ESYE23",
    "gn:admin2_code":"31.0",
    "gn:admin3_code":"9126",
    "gn:asciiname":"Mantra",
    "gn:country_code":"GR",
    "gn:dem":423,
    "gn:feature_class":"P",
    "gn:feature_code":"PPL",
    "gn:name":"M\u00e1ntra",
    "gn:population":0,
    "gn:timezone":"Europe/Athens",
    "iso:country":"GR",
    "name:ell_x_preferred":[
        "M\u00e1ntra"
    ],
    "name:ell_x_variant":[
        "\u039c\u03ac\u03bd\u03c4\u03c1\u03b1"
    ],
    "name:und_x_variant":[
        "M\u00e1ndhra",
        "M\u00e1ndra"
    ],
    "wof:name":"Mantra",
    "wof:placetype":"locality"
},
  "geometry": {"coordinates":[21.68633,38.58917],"type":"Point"}
}