{
  "type": "Feature",
  "properties": {
    "gn:admin1_code":"ESYE25",
    "gn:admin2_code":"40.0",
    "gn:admin3_code":"9258",
    "gn:asciiname":"Ai Seris",
    "gn:country_code":"GR",
    "gn:dem":156,
    "gn:feature_class":"P",
    "gn:feature_code":"PPL",
    "gn:name":"Ai S\u00e9ris",
    "gn:population":0,
    "gn:timezone":"Europe/Athens",
    "iso:country":"GR",
    "name:ell_x_preferred":[
        "Ai S\u00e9ris"
    ],
    "name:ell_x_variant":[
        "\u0391\u03b7 \u03a3\u03ad\u03c1\u03b7\u03c2"
    ],
    "wof:name":"Ai Seris",
    "wof:placetype":"locality"
},
  "geometry": {"coordinates":[21.73327,37.31407],"type":"Point"}
}