{
  "type": "Feature",
  "properties": {
    "gn:admin1_code":"ESYE41",
    "gn:admin2_code":"51.0",
    "gn:admin3_code":"9261",
    "gn:asciiname":"Alyfanta",
    "gn:cc2":"GR",
    "gn:country_code":"GR",
    "gn:dem":169,
    "gn:feature_class":"P",
    "gn:feature_code":"PPL",
    "gn:name":"Alyfant\u00e1",
    "gn:population":0,
    "gn:timezone":"Europe/Athens",
    "iso:country":"GR",
    "name:ell_x_preferred":[
        "\u0391\u03bb\u03c5\u03c6\u03b1\u03bd\u03c4\u03ac"
    ],
    "name:und_x_variant":[
        "Alifanda",
        "Alyfant\u00e1"
    ],
    "wof:name":"Alyfanta",
    "wof:placetype":"locality"
},
  "geometry": {"coordinates":[26.53263,39.10336],"type":"Point"}
}