{
  "type": "Feature",
  "properties": {
    "gn:gn_country":"GR",
    "gn:gn_fcode":"PPL",
    "gn:gn_pop":5187,
    "gn:population":5187,
    "iso:country":"GR",
    "name:deu_x_preferred":[
        "Skiathos"
    ],
    "name:ell_x_preferred":[
        "\u03a3\u03ba\u03b9\u03ac\u03b8\u03bf\u03c2"
    ],
    "name:eng_x_colloquial":[
        "Skiathos City"
    ],
    "name:eng_x_preferred":[
        "Skiathos"
    ],
    "name:eng_x_variant":[
        "Skiathos City"
    ],
    "name:fin_x_preferred":[
        "Ski\u00e1thos"
    ],
    "name:fra_x_preferred":[
        "Skiathos"
    ],
    "name:ita_x_preferred":[
        "Sciato"
    ],
    "name:nld_x_preferred":[
        "Skiathos"
    ],
    "name:nor_x_preferred":[
        "Skiathos"
    ],
    "name:pol_x_preferred":[
        "Skiatos"
    ],
    "name:ron_x_preferred":[
        "skiathos"
    ],
    "name:spa_x_preferred":[
        "Sc\u00edathos"
    ],
    "name:swe_x_preferred":[
        "Ski\u00e1thos"
    ],
    "qs_pg:aaroncc":"GR",
    "qs_pg:gn_country":"GR",
    "qs_pg:gn_fcode":"PPL",
    "qs_pg:gn_pop":5187,
    "qs_pg:name":"Skiathos",
    "qs_pg:name_adm0":"\u0395\u03bb\u03bb\u03ac\u03b4\u03b1",
    "qs_pg:name_adm1":"Thessaly and Continental Greece",
    "qs_pg:photos":3052,
    "qs_pg:photos_1k":618,
    "qs_pg:photos_9k":14,
    "qs_pg:photos_9r":11,
    "qs_pg:photos_all":3052,
    "qs_pg:photos_sr":20,
    "qs_pg:pop_sr":5,
    "qs_pg:qs_pg_placetype":"locality",
    "qs_pg:qs_pg_placetype_gp":"Town",
    "qs_pg:woe_adm0":23424833,
    "woe:adm0_id":23424833,
    "woe:name_adm0":"\u0395\u03bb\u03bb\u03ac\u03b4\u03b1",
    "woe:name_adm1":"Thessaly and Continental Greece",
    "woe:placetype":"Town",
    "wof:name":"Skiathos",
    "wof:placetype":"locality",
    "wof:population":5187
},
  "geometry": {"coordinates":[23.49089,39.16227],"type":"Point"}
}