{
  "type": "Feature",
  "properties": {
    "gn:admin1_code":"ESYE43",
    "gn:admin2_code":"45.0",
    "gn:admin3_code":"9309",
    "gn:asciiname":"Voros",
    "gn:country_code":"GR",
    "gn:dem":251,
    "gn:feature_class":"P",
    "gn:feature_code":"PPL",
    "gn:name":"Vor\u00f3s",
    "gn:population":40,
    "gn:timezone":"Europe/Athens",
    "iso:country":"GR",
    "name:ell_x_preferred":[
        "\u0392\u03bf\u03c1\u03cc\u03c2"
    ],
    "name:eng_x_preferred":[
        "Voros"
    ],
    "name:ita_x_preferred":[
        "Voros"
    ],
    "name:und_x_variant":[
        "Vorro\u00fa",
        "Vor\u00f3s"
    ],
    "wof:name":"Voros",
    "wof:placetype":"locality",
    "wof:population":40
},
  "geometry": {"coordinates":[25.29933,35.28448],"type":"Point"}
}