{
  "type": "Feature",
  "properties": {
    "gn:gn_country":"GR",
    "gn:gn_fcode":"PPL",
    "gn:gn_pop":1045,
    "gn:population":1049,
    "iso:country":"GR",
    "name:ell_x_preferred":[
        "\u03a0\u03bf\u03bb\u03c5\u03ba\u03ac\u03c1\u03c0\u03b9\u03bf\u03bd"
    ],
    "name:ell_x_variant":[
        "\u03a0\u03bf\u03bb\u03c5\u03ba\u03ac\u03c1\u03c0\u03b9"
    ],
    "name:unk_x_variant":[
        "P\u00f3liani"
    ],
    "qs_pg:aaroncc":"GR",
    "qs_pg:gn_country":"GR",
    "qs_pg:gn_fcode":"PPL",
    "qs_pg:gn_pop":1045,
    "qs_pg:name":"Polyk\u00e1rpion",
    "qs_pg:photos_9r":0,
    "qs_pg:photos_sr":0,
    "qs_pg:pop_sr":3,
    "qs_pg:qs_pg_placetype":"locality",
    "wof:name":"Polyk\u00e1rpion",
    "wof:placetype":"locality",
    "wof:population":1049
},
  "geometry": {"coordinates":[22.01361,40.92722],"type":"Point"}
}