{
  "type": "Feature",
  "properties": {
    "gn:admin1_code":"ESYE23",
    "gn:admin2_code":"38.0",
    "gn:admin3_code":"9131",
    "gn:asciiname":"Logothetis",
    "gn:country_code":"GR",
    "gn:dem":83,
    "gn:feature_class":"P",
    "gn:feature_code":"PPL",
    "gn:name":"Logoth\u00e9tis",
    "gn:population":0,
    "gn:timezone":"Europe/Athens",
    "iso:country":"GR",
    "name:ell_x_preferred":[
        "\u039b\u03bf\u03b3\u03bf\u03b8\u03ad\u03c4\u03b7\u03c2"
    ],
    "name:rus_x_preferred":[
        "\u041b\u043e\u0433\u043e\u0444\u0435\u0442"
    ],
    "name:und_x_variant":[
        "Logotheti",
        "Logoth\u00e9tis"
    ],
    "wof:name":"Logothetis",
    "wof:placetype":"locality"
},
  "geometry": {"coordinates":[21.55356,38.0945],"type":"Point"}
}