{
  "type": "Feature",
  "properties": {
    "gn:admin1_code":"ESYE31",
    "gn:admin2_code":"445407.0",
    "gn:admin3_code":"9231",
    "gn:asciiname":"Koumintri",
    "gn:country_code":"GR",
    "gn:dem":23,
    "gn:feature_class":"P",
    "gn:feature_code":"PPL",
    "gn:name":"Koum\u00edntri",
    "gn:population":298,
    "gn:timezone":"Europe/Athens",
    "iso:country":"GR",
    "name:ell_x_preferred":[
        "\u039a\u03bf\u03c5\u03bc\u03af\u03bd\u03c4\u03c1\u03b9"
    ],
    "name:eng_x_preferred":[
        "Koumintri"
    ],
    "wof:name":"Koumintri",
    "wof:placetype":"locality",
    "wof:population":298
},
  "geometry": {"coordinates":[23.40309,38.00286],"type":"Point"}
}