{
  "type": "Feature",
  "properties": {
    "gn:admin1_code":"ESYE25",
    "gn:admin2_code":"37.0",
    "gn:admin3_code":"9246",
    "gn:asciiname":"Petalou",
    "gn:country_code":"GR",
    "gn:dem":52,
    "gn:feature_class":"P",
    "gn:feature_code":"PPL",
    "gn:name":"Petalo\u00fa",
    "gn:population":218,
    "gn:timezone":"Europe/Athens",
    "iso:country":"GR",
    "name:ell_x_preferred":[
        "\u03a0\u03b5\u03c4\u03b1\u03bb\u03bf\u03cd"
    ],
    "name:eng_x_preferred":[
        "Petalou"
    ],
    "wof:name":"Petalou",
    "wof:placetype":"locality",
    "wof:population":218
},
  "geometry": {"coordinates":[22.39941,38.12983],"type":"Point"}
}