{
  "type": "Feature",
  "properties": {
    "gn:admin1_code":"ESYE25",
    "gn:admin2_code":"37.0",
    "gn:admin3_code":"9245",
    "gn:asciiname":"Aidhonia",
    "gn:country_code":"GR",
    "gn:dem":365,
    "gn:feature_class":"P",
    "gn:feature_code":"PPL",
    "gn:name":"A\u00efdh\u00f3nia",
    "gn:population":200,
    "gn:timezone":"Europe/Athens",
    "iso:country":"GR",
    "name:ell_x_preferred":[
        "\u0391\u03b7\u03b4\u03cc\u03bd\u03b9\u03b1"
    ],
    "name:eng_x_preferred":[
        "Aidonia"
    ],
    "name:und_x_variant":[
        "B\u00f3tsika",
        "A\u00efdh\u00f3nia",
        "Aidonia"
    ],
    "wof:name":"Aidhonia",
    "wof:placetype":"locality",
    "wof:population":200
},
  "geometry": {"coordinates":[22.57805,37.84142],"type":"Point"}
}