{
  "type": "Feature",
  "properties": {
    "gn:admin1_code":"ESYE23",
    "gn:admin2_code":"31.0",
    "gn:admin3_code":"9127",
    "gn:asciiname":"Koutsocheri",
    "gn:country_code":"GR",
    "gn:dem":175,
    "gn:feature_class":"P",
    "gn:feature_code":"PPL",
    "gn:name":"Koutsoch\u00e9ri",
    "gn:population":0,
    "gn:timezone":"Europe/Athens",
    "iso:country":"GR",
    "name:ell_x_preferred":[
        "Koutsoch\u00e9ri"
    ],
    "name:ell_x_variant":[
        "\u039a\u03bf\u03c5\u03c4\u03c3\u03bf\u03c7\u03ad\u03c1\u03b9",
        "Koutsoch\u00e9rion",
        "\u039a\u03bf\u03c5\u03c4\u03c3\u03bf\u03c7\u03ad\u03c1\u03b9\u03bf\u03bd"
    ],
    "name:und_x_variant":[
        "Koutsokh\u00e9ri",
        "Koutsokh\u00e9rion"
    ],
    "wof:name":"Koutsocheri",
    "wof:placetype":"locality"
},
  "geometry": {"coordinates":[21.5695,38.41564],"type":"Point"}
}