{
  "type": "Feature",
  "properties": {
    "gn:admin1_code":"ESYE41",
    "gn:admin2_code":"51.0",
    "gn:admin3_code":"9263",
    "gn:asciiname":"Koroni",
    "gn:country_code":"GR",
    "gn:dem":103,
    "gn:feature_class":"P",
    "gn:feature_code":"PPL",
    "gn:name":"Koroni",
    "gn:population":0,
    "gn:timezone":"Europe/Athens",
    "iso:country":"GR",
    "name:als_x_preferred":[
        "Koroni"
    ],
    "name:ara_x_preferred":[
        "\u0643\u0648\u0631\u0648\u0646\u064a"
    ],
    "name:cat_x_preferred":[
        "Korone"
    ],
    "name:ceb_x_preferred":[
        "Kor\u00f3ni"
    ],
    "name:deu_x_preferred":[
        "Koroni"
    ],
    "name:ell_x_preferred":[
        "\u039a\u03bf\u03c1\u03ce\u03bd\u03b7"
    ],
    "name:fin_x_preferred":[
        "Kor\u00f3ni"
    ],
    "name:fra_x_preferred":[
        "Coron"
    ],
    "name:ind_x_preferred":[
        "Koroni"
    ],
    "name:ita_x_preferred":[
        "Corone"
    ],
    "name:lat_x_preferred":[
        "Corone"
    ],
    "name:nno_x_preferred":[
        "Kor\u00f3ni"
    ],
    "name:ron_x_preferred":[
        "Koroni"
    ],
    "name:rus_x_preferred":[
        "\u041a\u043e\u0440\u043e\u043d\u0438"
    ],
    "name:szl_x_preferred":[
        "Koroni"
    ],
    "name:tha_x_preferred":[
        "\u0e42\u0e04\u0e42\u0e23\u0e19\u0e34"
    ],
    "name:tur_x_preferred":[
        "Koron"
    ],
    "name:vec_x_preferred":[
        "Coron"
    ],
    "wof:name":"Koroni",
    "wof:placetype":"locality"
},
  "geometry": {"coordinates":[25.16927,39.92848],"type":"Point"}
}