{
  "type": "Feature",
  "properties": {
    "gn:admin1_code":"ESYE41",
    "gn:admin2_code":"51.0",
    "gn:admin3_code":"9263",
    "gn:asciiname":"Koroni",
    "gn:country_code":"GR",
    "gn:dem":103,
    "gn:feature_class":"P",
    "gn:feature_code":"PPL",
    "gn:name":"Koroni",
    "gn:population":0,
    "gn:timezone":"Europe/Athens",
    "iso:country":"GR",
    "wof:name":"Koroni",
    "wof:placetype":"locality"
},
  "geometry": {"coordinates":[25.16927,39.92848],"type":"Point"}
}