{
  "type": "Feature",
  "properties": {
    "gn:admin1_code":"ESYE43",
    "gn:admin2_code":"43.0",
    "gn:admin3_code":"9319",
    "gn:asciiname":"Asigonia",
    "gn:country_code":"GR",
    "gn:dem":403,
    "gn:feature_class":"P",
    "gn:feature_code":"PPL",
    "gn:name":"Asigon\u00eda",
    "gn:population":0,
    "gn:timezone":"Europe/Athens",
    "iso:country":"GR",
    "name:ell_x_preferred":[
        "\u0391\u03c3\u03ae \u0393\u03c9\u03bd\u03b9\u03ac"
    ],
    "name:eng_x_preferred":[
        "Asi Gonia"
    ],
    "wof:name":"Asigonia",
    "wof:placetype":"locality"
},
  "geometry": {"coordinates":[24.28408,35.27421],"type":"Point"}
}