{
  "type": "Feature",
  "properties": {
    "gn:admin1_code":"ESYE42",
    "gn:admin2_code":"49.0",
    "gn:admin3_code":"9292.0",
    "gn:asciiname":"Agioi Pantes",
    "gn:country_code":"GR",
    "gn:dem":28,
    "gn:feature_class":"P",
    "gn:feature_code":"PPL",
    "gn:name":"\u00c1gioi P\u00e1ntes",
    "gn:population":103,
    "gn:timezone":"Europe/Athens",
    "iso:country":"GR",
    "name:ell_x_preferred":[
        "\u0386\u03b3\u03b9\u03bf\u03b9 \u03a0\u03ac\u03bd\u03c4\u03b5\u03c2"
    ],
    "name:eng_x_preferred":[
        "Agioi Pantes"
    ],
    "wof:name":"Agioi Pantes",
    "wof:placetype":"locality",
    "wof:population":103
},
  "geometry": {"coordinates":[25.37187,37.06265],"type":"Point"}
}