{
  "type": "Feature",
  "properties": {
    "gn:admin1_code":"ESYE22",
    "gn:admin2_code":"26.0",
    "gn:admin3_code":"9121",
    "gn:asciiname":"Manasi",
    "gn:country_code":"GR",
    "gn:dem":557,
    "gn:feature_class":"P",
    "gn:feature_code":"PPL",
    "gn:name":"Man\u00e1si",
    "gn:population":62,
    "gn:timezone":"Europe/Athens",
    "iso:country":"GR",
    "name:ell_x_preferred":[
        "\u039c\u03b1\u03bd\u03ac\u03c3\u03b7"
    ],
    "name:eng_x_preferred":[
        "Manasi"
    ],
    "wof:name":"Manasi",
    "wof:placetype":"locality",
    "wof:population":62
},
  "geometry": {"coordinates":[20.60997,38.69412],"type":"Point"}
}