{
  "type": "Feature",
  "properties": {
    "gn:admin1_code":"ESYE23",
    "gn:admin2_code":"38.0",
    "gn:admin3_code":"9134",
    "gn:asciiname":"Pournarokastro",
    "gn:country_code":"GR",
    "gn:dem":656,
    "gn:feature_class":"P",
    "gn:feature_code":"PPL",
    "gn:name":"Pournar\u00f3kastro",
    "gn:population":0,
    "gn:timezone":"Europe/Athens",
    "iso:country":"GR",
    "name:ell_x_preferred":[
        "Pournar\u00f3kastro"
    ],
    "name:ell_x_variant":[
        "\u03a0\u03bf\u03c5\u03c1\u03bd\u03b1\u03c1\u03cc\u03ba\u03b1\u03c3\u03c4\u03c1\u03bf",
        "\u03a0\u03bf\u03c5\u03c1\u03bd\u03b1\u03c1\u03cc\u03ba\u03b1\u03c3\u03c4\u03c1\u03bf\u03bd"
    ],
    "name:und_x_variant":[
        "Pournar\u00f3kastron",
        "Pourkar\u00f3kastron"
    ],
    "wof:name":"Pournarokastro",
    "wof:placetype":"locality"
},
  "geometry": {"coordinates":[21.81228,38.20983],"type":"Point"}
}