{
  "type": "Feature",
  "properties": {
    "gn:admin1_code":"ESYE25",
    "gn:admin2_code":"41.0",
    "gn:admin3_code":"9239",
    "gn:asciiname":"Krionerion",
    "gn:cc2":"GR",
    "gn:country_code":"GR",
    "gn:dem":461,
    "gn:feature_class":"P",
    "gn:feature_code":"PPL",
    "gn:name":"Krion\u00e9rion",
    "gn:population":0,
    "gn:timezone":"Europe/Athens",
    "iso:country":"GR",
    "name:und_x_variant":[
        "Egl\u00e9nova",
        "Kri\u00f3neron",
        "Krion\u00e9rion"
    ],
    "wof:name":"Krionerion",
    "wof:placetype":"locality"
},
  "geometry": {"coordinates":[21.99574,37.54189],"type":"Point"}
}