{
  "type": "Feature",
  "properties": {
    "gn:admin1_code":"ESYE41",
    "gn:admin2_code":"50.0",
    "gn:admin3_code":"9266",
    "gn:asciiname":"Trachylia",
    "gn:country_code":"GR",
    "gn:dem":7,
    "gn:feature_class":"P",
    "gn:feature_code":"PPL",
    "gn:name":"Trachylia",
    "gn:population":15,
    "gn:timezone":"Europe/Athens",
    "iso:country":"GR",
    "name:ell_x_preferred":[
        "\u03a4\u03c1\u03b1\u03c7\u03cd\u03bb\u03b9\u03b1"
    ],
    "name:und_x_variant":[
        "Trachilia"
    ],
    "wof:name":"Trachylia",
    "wof:placetype":"locality",
    "wof:population":15
},
  "geometry": {"coordinates":[25.90374,38.22173],"type":"Point"}
}