{
  "type": "Feature",
  "properties": {
    "gn:admin1_code":"ESYE42",
    "gn:admin2_code":"47.0",
    "gn:admin3_code":"9284",
    "gn:asciiname":"Asomatos",
    "gn:country_code":"GR",
    "gn:dem":292,
    "gn:feature_class":"P",
    "gn:feature_code":"PPL",
    "gn:name":"As\u00f3matos",
    "gn:population":0,
    "gn:timezone":"Europe/Athens",
    "iso:country":"GR",
    "name:deu_x_preferred":[
        "Asomatos"
    ],
    "name:ell_x_preferred":[
        "\u0391\u03c3\u03ce\u03bc\u03b1\u03c4\u03bf\u03c2"
    ],
    "name:hye_x_preferred":[
        "\u0531\u057d\u0578\u0574\u0561\u057f\u0578\u057d"
    ],
    "name:rus_x_preferred":[
        "\u0410\u0441\u043e\u043c\u0430\u0442\u043e\u0441"
    ],
    "wof:name":"Asomatos",
    "wof:placetype":"locality"
},
  "geometry": {"coordinates":[27.22139,36.85139],"type":"Point"}
}