{
  "type": "Feature",
  "properties": {
    "gn:admin1_code":"ESYE42",
    "gn:admin2_code":"47.0",
    "gn:admin3_code":"9284",
    "gn:asciiname":"Asomatos",
    "gn:country_code":"GR",
    "gn:dem":292,
    "gn:feature_class":"P",
    "gn:feature_code":"PPL",
    "gn:name":"As\u00f3matos",
    "gn:population":0,
    "gn:timezone":"Europe/Athens",
    "iso:country":"GR",
    "wof:name":"Asomatos",
    "wof:placetype":"locality"
},
  "geometry": {"coordinates":[27.22139,36.85139],"type":"Point"}
}