{
  "type": "Feature",
  "properties": {
    "gn:admin1_code":"ESYE43",
    "gn:admin2_code":"45.0",
    "gn:admin3_code":"9308",
    "gn:asciiname":"Skourvoula",
    "gn:country_code":"GR",
    "gn:dem":345,
    "gn:feature_class":"P",
    "gn:feature_code":"PPL",
    "gn:name":"Sko\u00farvoula",
    "gn:population":0,
    "gn:timezone":"Europe/Athens",
    "iso:country":"GR",
    "wof:name":"Skourvoula",
    "wof:placetype":"locality"
},
  "geometry": {"coordinates":[24.84404,35.10699],"type":"Point"}
}