{
  "type": "Feature",
  "properties": {
    "gn:admin1_code":"ESYE12",
    "gn:admin2_code":"5.0",
    "gn:admin3_code":"9049",
    "gn:asciiname":"Mesolakkia",
    "gn:country_code":"GR",
    "gn:dem":413,
    "gn:feature_class":"P",
    "gn:feature_code":"PPL",
    "gn:name":"Mesolakki\u00e1",
    "gn:population":16,
    "gn:timezone":"Europe/Athens",
    "iso:country":"GR",
    "name:bul_x_preferred":[
        "\u041b\u043e\u043a\u0432\u0438\u0446\u0430"
    ],
    "name:ell_x_preferred":[
        "\u039c\u03b5\u03c3\u03bf\u03bb\u03b1\u03ba\u03ba\u03b9\u03ac"
    ],
    "name:ell_x_variant":[
        "\u039c\u03b5\u03c3\u03bf\u03bb\u03b1\u03ba\u03ba\u03b9\u03ac \u03a3\u03b5\u03c1\u03c1\u03ce\u03bd"
    ],
    "name:eng_x_preferred":[
        "Mesolakkia"
    ],
    "name:mkd_x_preferred":[
        "\u041b\u043e\u043a\u0432\u0438\u0446\u0430"
    ],
    "name:und_x_variant":[
        "Lakov\u00edkia",
        "Mesolakki\u00e1"
    ],
    "wof:name":"Mesolakkia",
    "wof:placetype":"locality",
    "wof:population":16
},
  "geometry": {"coordinates":[23.93422,40.83164],"type":"Point"}
}