{
  "type": "Feature",
  "properties": {
    "gn:admin1_code":"ESYE14",
    "gn:admin2_code":"23.0",
    "gn:admin3_code":"9094",
    "gn:asciiname":"Keramargio",
    "gn:country_code":"GR",
    "gn:dem":719,
    "gn:feature_class":"P",
    "gn:feature_code":"PPL",
    "gn:name":"Keramargi\u00f3",
    "gn:population":0,
    "gn:timezone":"Europe/Athens",
    "iso:country":"GR",
    "wof:name":"Keramargio",
    "wof:placetype":"locality"
},
  "geometry": {"coordinates":[21.57611,39.39],"type":"Point"}
}