{
  "type": "Feature",
  "properties": {
    "gn:admin1_code":"ESYE23",
    "gn:admin2_code":"39.0",
    "gn:admin3_code":"9139",
    "gn:asciiname":"Simopoulo",
    "gn:country_code":"GR",
    "gn:dem":196,
    "gn:feature_class":"P",
    "gn:feature_code":"PPL",
    "gn:name":"Sim\u00f3poulo",
    "gn:population":0,
    "gn:timezone":"Europe/Athens",
    "iso:country":"GR",
    "name:ell_x_preferred":[
        "Sim\u00f3poulo"
    ],
    "name:ell_x_variant":[
        "\u03a3\u03b9\u03bc\u03cc\u03c0\u03bf\u03c5\u03bb\u03bf",
        "Sim\u00f3poulon",
        "\u03a3\u03b9\u03bc\u03cc\u03c0\u03bf\u03c5\u03bb\u03bf\u03bd",
        "\u03a3\u03b9\u03bc\u03cc\u03c0\u03bf\u03c5\u03bb\u03bf \u0397\u03bb\u03b5\u03af\u03b1\u03c2"
    ],
    "name:nno_x_preferred":[
        "Sim\u00f3poulo"
    ],
    "name:ron_x_preferred":[
        "Simopoulo"
    ],
    "wof:name":"Simopoulo",
    "wof:placetype":"locality"
},
  "geometry": {"coordinates":[21.57011,37.84925],"type":"Point"}
}