{
  "type": "Feature",
  "properties": {
    "gn:admin1_code":"ESYE23",
    "gn:admin2_code":"31.0",
    "gn:admin3_code":"9128",
    "gn:asciiname":"Platanitis",
    "gn:country_code":"GR",
    "gn:dem":2,
    "gn:feature_class":"P",
    "gn:feature_code":"PPL",
    "gn:name":"Platan\u00edtis",
    "gn:population":0,
    "gn:timezone":"Europe/Athens",
    "iso:country":"GR",
    "name:ell_x_preferred":[
        "Platan\u00edtis"
    ],
    "name:ell_x_variant":[
        "\u03a0\u03bb\u03b1\u03c4\u03b1\u03bd\u03af\u03c4\u03b7\u03c2",
        "\u03a0\u03bb\u03b1\u03c4\u03b1\u03bd\u03af\u03c4\u03b7\u03c2 \u0391\u03b9\u03c4\u03c9\u03bb\u03bf\u03b1\u03ba\u03b1\u03c1\u03bd\u03b1\u03bd\u03af\u03b1\u03c2"
    ],
    "name:und_x_variant":[
        "K\u00e1to Platan\u00edtis"
    ],
    "wof:name":"Platanitis",
    "wof:placetype":"locality"
},
  "geometry": {"coordinates":[21.77725,38.36261],"type":"Point"}
}