{
  "type": "Feature",
  "properties": {
    "gn:admin1_code":"ESYE25",
    "gn:admin2_code":"41.0",
    "gn:admin3_code":"9241",
    "gn:asciiname":"Sangas",
    "gn:country_code":"GR",
    "gn:dem":733,
    "gn:feature_class":"P",
    "gn:feature_code":"PPL",
    "gn:name":"S\u00e1ngas",
    "gn:population":125,
    "gn:timezone":"Europe/Athens",
    "iso:country":"GR",
    "name:ell_x_preferred":[
        "\u03a3\u03ac\u03b3\u03ba\u03b1\u03c2"
    ],
    "name:und_x_variant":[
        "S\u00e1nga",
        "S\u00e1ngas",
        "Sanga"
    ],
    "wof:name":"Sangas",
    "wof:placetype":"locality",
    "wof:population":125
},
  "geometry": {"coordinates":[22.45849,37.66997],"type":"Point"}
}