{
  "type": "Feature",
  "properties": {
    "gn:admin1_code":"ESYE23",
    "gn:admin2_code":"31.0",
    "gn:admin3_code":"9123",
    "gn:asciiname":"Levkon",
    "gn:cc2":"GR",
    "gn:country_code":"GR",
    "gn:dem":503,
    "gn:feature_class":"P",
    "gn:feature_code":"PPL",
    "gn:name":"Levk\u00f3n",
    "gn:population":0,
    "gn:timezone":"Europe/Athens",
    "iso:country":"GR",
    "name:ell_x_preferred":[
        "\u039b\u03b5\u03c5\u03ba\u03cc"
    ],
    "name:und_x_variant":[
        "K\u00e1to Pr\u00f3stovas",
        "K\u00e1to Prostov\u00e1",
        "Levk\u00f3n"
    ],
    "wof:name":"Levkon",
    "wof:placetype":"locality"
},
  "geometry": {"coordinates":[21.62212,38.61251],"type":"Point"}
}