{
  "type": "Feature",
  "properties": {
    "gn:admin1_code":"ESYE22",
    "gn:admin2_code":"27.0",
    "gn:admin3_code":"9120",
    "gn:asciiname":"Ano Valtes",
    "gn:country_code":"GR",
    "gn:dem":379,
    "gn:feature_class":"P",
    "gn:feature_code":"PPL",
    "gn:name":"\u00c1no V\u00e1ltes",
    "gn:population":0,
    "gn:timezone":"Europe/Athens",
    "iso:country":"GR",
    "name:ell_x_preferred":[
        "\u00c1no V\u00e1ltes"
    ],
    "name:ell_x_variant":[
        "\u0386\u03bd\u03c9 \u0392\u03ac\u03bb\u03c4\u03b5\u03c2"
    ],
    "name:und_x_variant":[
        "V\u00e1lta",
        "\u00c1no V\u00e1ltai"
    ],
    "wof:name":"Ano Valtes",
    "wof:placetype":"locality"
},
  "geometry": {"coordinates":[20.74642,38.09683],"type":"Point"}
}