{
  "type": "Feature",
  "properties": {
    "gn:population":1108,
    "iso:country":"GR",
    "name:ell_x_preferred":[
        "\u03a0\u03c1\u03bf\u03ba\u03cc\u03c0\u03b9\u03bf\u03bd"
    ],
    "name:ell_x_variant":[
        "Prok\u00f3pi",
        "\u03a0\u03c1\u03bf\u03ba\u03cc\u03c0\u03b9"
    ],
    "name:und_x_variant":[
        "Prok\u00f3pion"
    ],
    "qs:a0":"Greece",
    "qs:a1":"*\u03a3\u03a4\u0395\u03a1\u0395\u0391 \u0395\u039b\u039b\u0391\u0394\u0391",
    "qs:a1_alt":"STEREA ELLADA",
    "qs:a1r":"0",
    "qs:a2_alt":"EYVOIA",
    "qs:adm0":"Greece",
    "qs:la_lc":"*",
    "qs:level":"locality",
    "qs:loc":"\u03a0\u03a1\u039f\u039a\u039f\u03a0\u0399\u039f\u039d",
    "qs:loc_alt":"PROKOPION",
    "qs:pop":0,
    "qs:type":"buffered point",
    "wof:name":"\u03a0\u03a1\u039f\u039a\u039f\u03a0\u0399\u039f\u039d",
    "wof:placetype":"locality",
    "wof:population":1108
},
  "geometry": {"coordinates":[23.489094,38.736694],"type":"Point"}
}