{
  "type": "Feature",
  "properties": {
    "gn:country":"GR",
    "gn:fcode":"PPLA3",
    "gn:population":2079,
    "iso:country":"GR",
    "name:bul_x_preferred":[
        "\u0422\u043e\u043f\u043e\u043b\u044f\u043d"
    ],
    "name:bul_x_variant":[
        "\u0422\u043e\u043f\u043e\u043b\u0435\u0300\u043d",
        "\u0425\u0440\u0438\u0441\u043e"
    ],
    "name:ell_x_historical":[
        "\u03a4\u03bf\u03c0\u03bf\u03bb\u03b9\u03ac\u03bd\u03b7"
    ],
    "name:ell_x_preferred":[
        "\u03a7\u03c1\u03c5\u03c3\u03cc\u03bd"
    ],
    "name:ell_x_variant":[
        "Chrys\u00f3",
        "\u03a7\u03c1\u03c5\u03c3\u03cc",
        "\u03a4\u03bf\u03c0\u03bf\u03bb\u03b9\u03ac\u03bd\u03b7"
    ],
    "name:eng_x_preferred":[
        "Chryso"
    ],
    "name:mkd_x_preferred":[
        "\u0422\u043e\u043f\u043e\u043b\u0458\u0430\u043d"
    ],
    "name:mkd_x_variant":[
        "\u0425\u0440\u0438\u0441\u043e"
    ],
    "name:nno_x_preferred":[
        "Khr\u00fdso"
    ],
    "name:und_x_variant":[
        "Top\u00f3liani"
    ],
    "qs_pg:aaroncc":"GR",
    "qs_pg:gn_country":"GR",
    "qs_pg:gn_fcode":"PPLA3",
    "qs_pg:gn_pop":2079,
    "qs_pg:name":"Chrys\u00f3",
    "qs_pg:photos_9r":0,
    "qs_pg:photos_sr":0,
    "qs_pg:pop_sr":4,
    "qs_pg:qs_pg_placetype":"locality",
    "wof:name":"Chrys\u00f3",
    "wof:placetype":"locality",
    "wof:population":1571
},
  "geometry": {"coordinates":[23.65,41.06667],"type":"Point"}
}