{
  "type": "Feature",
  "properties": {
    "gn:admin1_code":"ESYE14",
    "gn:admin2_code":"23.0",
    "gn:admin3_code":"9091",
    "gn:asciiname":"Melanydro",
    "gn:country_code":"GR",
    "gn:dem":444,
    "gn:feature_class":"P",
    "gn:feature_code":"PPL",
    "gn:name":"Mel\u00e1nydro",
    "gn:population":0,
    "gn:timezone":"Europe/Athens",
    "iso:country":"GR",
    "name:ell_x_preferred":[
        "\u039c\u03b5\u03bb\u03ac\u03bd\u03c5\u03b4\u03c1\u03bf"
    ],
    "name:ell_x_variant":[
        "\u039c\u03b5\u03bb\u03ac\u03bd\u03c5\u03b4\u03c1\u03bf\u03bd"
    ],
    "name:und_x_variant":[
        "Bouzi\u00e1rikon",
        "Mouzi\u00e1rikon",
        "Mouziar\u00edkou",
        "Mouz\u00e1rkio",
        "Mel\u00e1nydro",
        "Mel\u00e1nydron"
    ],
    "wof:name":"Melanydro",
    "wof:placetype":"locality"
},
  "geometry": {"coordinates":[21.42442,39.26911],"type":"Point"}
}