{
  "type": "Feature",
  "properties": {
    "gn:gn_country":"GR",
    "gn:gn_fcode":"PPL",
    "gn:gn_pop":1207,
    "gn:population":1207,
    "iso:country":"GR",
    "name:ell_x_preferred":[
        "\u039c\u03b9\u03ba\u03c1\u03cc\u03ba\u03b1\u03bc\u03c0\u03bf\u03c2"
    ],
    "name:unk_x_variant":[
        "Hojal\u00e1r"
    ],
    "qs_pg:aaroncc":"GR",
    "qs_pg:gn_country":"GR",
    "qs_pg:gn_fcode":"PPL",
    "qs_pg:gn_pop":1207,
    "qs_pg:name":"Mikr\u00f3kampos",
    "qs_pg:photos_9r":0,
    "qs_pg:photos_sr":0,
    "qs_pg:pop_sr":3,
    "qs_pg:qs_pg_placetype":"locality",
    "wof:name":"Mikr\u00f3kampos",
    "wof:placetype":"locality",
    "wof:population":1207
},
  "geometry": {"coordinates":[22.76972,40.83861],"type":"Point"}
}