{
  "type": "Feature",
  "properties": {
    "gn:admin1_code":"ESYE12",
    "gn:admin2_code":"5.0",
    "gn:admin3_code":"9054",
    "gn:asciiname":"Agios Ioannis",
    "gn:country_code":"GR",
    "gn:dem":72,
    "gn:feature_class":"P",
    "gn:feature_code":"PPL",
    "gn:name":"\u00c1gios Io\u00e1nnis",
    "gn:population":723,
    "gn:timezone":"Europe/Athens",
    "iso:country":"GR",
    "name:ell_x_preferred":[
        "\u0386\u03b3\u03b9\u03bf\u03c2 \u0399\u03c9\u03ac\u03bd\u03bd\u03b7\u03c2"
    ],
    "name:ell_x_variant":[
        "\u00c1gios Io\u00e1nnis",
        "\u00c1yios Io\u00e1nnis"
    ],
    "name:eng_x_preferred":[
        "Agios Ioannis"
    ],
    "wof:name":"Agios Ioannis",
    "wof:placetype":"locality",
    "wof:population":723
},
  "geometry": {"coordinates":[23.58022,41.09973],"type":"Point"}
}