{
  "type": "Feature",
  "properties": {
    "gn:gn_country":"GR",
    "gn:gn_fcode":"ADM3",
    "gn:gn_pop":8172,
    "gn:population":8172,
    "iso:country":"GR",
    "name:ell_x_preferred":[
        "\u039b\u03ad\u03c1\u03bf\u03c5"
    ],
    "qs_pg:aaroncc":"GR",
    "qs_pg:gn_country":"GR",
    "qs_pg:gn_fcode":"ADM3",
    "qs_pg:gn_pop":8172,
    "qs_pg:name":"Dimos Leros",
    "qs_pg:photos_9r":0,
    "qs_pg:photos_sr":0,
    "qs_pg:pop_sr":5,
    "qs_pg:qs_pg_placetype":"localadmin",
    "wof:name":"Dimos Leros",
    "wof:placetype":"localadmin",
    "wof:population":8172
},
  "geometry": {"coordinates":[26.75989,37.1292],"type":"Point"}
}