{
  "type": "Feature",
  "properties": {
    "gn:admin1_code":"ESYE43",
    "gn:admin2_code":"43.0",
    "gn:admin3_code":"9321",
    "gn:asciiname":"Kalamios",
    "gn:country_code":"GR",
    "gn:dem":502,
    "gn:feature_class":"P",
    "gn:feature_code":"PPL",
    "gn:name":"Kalami\u00f3s",
    "gn:population":0,
    "gn:timezone":"Europe/Athens",
    "iso:country":"GR",
    "name:ell_x_preferred":[
        "\u039a\u03b1\u03bb\u03b1\u03bc\u03b9\u03cc\u03c2"
    ],
    "name:und_x_variant":[
        "Kalamio\u00fa",
        "Kalami\u00f3s"
    ],
    "wof:name":"Kalamios",
    "wof:placetype":"locality"
},
  "geometry": {"coordinates":[23.62893,35.30331],"type":"Point"}
}