{
  "type": "Feature",
  "properties": {
    "gn:admin1_code":"ESYE25",
    "gn:admin2_code":"37.0",
    "gn:admin3_code":"9246",
    "gn:asciiname":"Mendouryianika",
    "gn:country_code":"GR",
    "gn:dem":86,
    "gn:feature_class":"P",
    "gn:feature_code":"PPL",
    "gn:name":"Mendouryi\u00e1nika",
    "gn:population":127,
    "gn:timezone":"Europe/Athens",
    "iso:country":"GR",
    "name:ell_x_preferred":[
        "\u039c\u03b5\u03bd\u03c4\u03bf\u03c5\u03c1\u03b3\u03b9\u03ac\u03bd\u03b9\u03ba\u03b1"
    ],
    "name:ell_x_variant":[
        "\u039c\u03b5\u03bd\u03c4\u03bf\u03c5\u03c1\u03b9\u03ac\u03bd\u03b9\u03ba\u03b1"
    ],
    "name:eng_x_preferred":[
        "Mentourgiannika"
    ],
    "name:und_x_variant":[
        "Mendouri\u00e1nika",
        "Mendouryi\u00e1nika"
    ],
    "wof:name":"Mendouryianika",
    "wof:placetype":"locality",
    "wof:population":127
},
  "geometry": {"coordinates":[22.43683,38.11857],"type":"Point"}
}