{
  "type": "Feature",
  "properties": {
    "gn:gn_country":"GR",
    "gn:gn_fcode":"PPL",
    "gn:gn_pop":302,
    "gn:population":207,
    "iso:country":"GR",
    "name:ell_x_preferred":[
        "\u0396\u03c5\u03b3\u03cc\u03c2"
    ],
    "name:eng_x_preferred":[
        "Zygos"
    ],
    "name:unk_x_variant":[
        "Zig\u00f3s"
    ],
    "qs_pg:aaroncc":"GR",
    "qs_pg:gn_country":"GR",
    "qs_pg:gn_fcode":"PPL",
    "qs_pg:gn_pop":302,
    "qs_pg:name":"Zyg\u00f3s",
    "qs_pg:photos_9r":0,
    "qs_pg:photos_sr":0,
    "qs_pg:pop_sr":2,
    "qs_pg:qs_pg_placetype":"locality",
    "wof:name":"Zyg\u00f3s",
    "wof:placetype":"locality",
    "wof:population":207
},
  "geometry": {"coordinates":[19.79889,39.72556],"type":"Point"}
}