{
  "type": "Feature",
  "properties": {
    "gn:country":"GR",
    "gn:fcode":"PPL",
    "gn:population":763,
    "iso:country":"GR",
    "name:arz_x_preferred":[
        "\u0645\u0627\u0631\u0627\u062b\u064a\u0627"
    ],
    "name:ceb_x_preferred":[
        "Marath\u00e9a"
    ],
    "name:ell_x_preferred":[
        "\u039c\u03b1\u03c1\u03b1\u03b8\u03ad\u03b1"
    ],
    "name:ell_x_variant":[
        "\u039c\u03b1\u03c1\u03b1\u03b8\u03ad\u03b1 \u039a\u03b1\u03c1\u03b4\u03af\u03c4\u03c3\u03b1\u03c2"
    ],
    "name:eng_x_preferred":[
        "Marathea"
    ],
    "name:nld_x_preferred":[
        "Marathea"
    ],
    "name:swe_x_preferred":[
        "Marath\u00e9a"
    ],
    "name:und_x_variant":[
        "V\u00e1nari"
    ],
    "qs_pg:aaroncc":"GR",
    "qs_pg:gn_country":"GR",
    "qs_pg:gn_fcode":"PPL",
    "qs_pg:gn_pop":763,
    "qs_pg:name":"Marathea",
    "qs_pg:name_adm0":"\u0395\u03bb\u03bb\u03ac\u03b4\u03b1",
    "qs_pg:name_adm1":"Thessaly and Continental Greece",
    "qs_pg:photos_9r":0,
    "qs_pg:photos_sr":0,
    "qs_pg:pop_sr":2,
    "qs_pg:qs_pg_placetype":"locality",
    "qs_pg:qs_pg_placetype_gp":"Town",
    "qs_pg:woe_adm0":23424833,
    "woe:adm0_id":23424833,
    "woe:name_adm0":"\u0395\u03bb\u03bb\u03ac\u03b4\u03b1",
    "woe:name_adm1":"Thessaly and Continental Greece",
    "woe:placetype":"Town",
    "wof:name":"Marathea",
    "wof:placetype":"locality",
    "wof:population":763
},
  "geometry": {"coordinates":[21.99583,39.53],"type":"Point"}
}