{
  "type": "Feature",
  "properties": {
    "gn:admin1_code":"ESYE23",
    "gn:admin2_code":"38.0",
    "gn:admin3_code":"9132",
    "gn:asciiname":"Chamokelles",
    "gn:country_code":"GR",
    "gn:dem":295,
    "gn:feature_class":"P",
    "gn:feature_code":"PPL",
    "gn:name":"Chamok\u00e9lles",
    "gn:population":0,
    "gn:timezone":"Europe/Athens",
    "iso:country":"GR",
    "name:ell_x_preferred":[
        "Chamok\u00e9lles"
    ],
    "name:ell_x_variant":[
        "\u03a7\u03b1\u03bc\u03bf\u03ba\u03ad\u03bb\u03bb\u03b5\u03c2"
    ],
    "name:und_x_variant":[
        "Kham\u00f3keles",
        "Khamok\u00e9lles"
    ],
    "wof:name":"Chamokelles",
    "wof:placetype":"locality"
},
  "geometry": {"coordinates":[21.79517,38.07242],"type":"Point"}
}