{
  "type": "Feature",
  "properties": {
    "gn:admin1_code":"ESYE25",
    "gn:admin2_code":"40.0",
    "gn:admin3_code":"9256",
    "gn:asciiname":"Andania",
    "gn:country_code":"GR",
    "gn:dem":85,
    "gn:feature_class":"P",
    "gn:feature_code":"PPL",
    "gn:name":"Andan\u00eda",
    "gn:population":0,
    "gn:timezone":"Europe/Athens",
    "iso:country":"GR",
    "name:ell_x_preferred":[
        "Andan\u00eda"
    ],
    "name:ell_x_variant":[
        "\u0391\u03bd\u03b4\u03b1\u03bd\u03af\u03b1"
    ],
    "name:und_x_variant":[
        "Sandh\u00e1kion",
        "Sandh\u00e1ni",
        "Andhan\u00eda"
    ],
    "wof:name":"Andania",
    "wof:placetype":"locality"
},
  "geometry": {"coordinates":[21.98478,37.26646],"type":"Point"}
}