{
  "type": "Feature",
  "properties": {
    "gn:admin1_code":"ESYE23",
    "gn:admin2_code":"39.0",
    "gn:admin3_code":"9137",
    "gn:asciiname":"Miraka",
    "gn:country_code":"GR",
    "gn:dem":100,
    "gn:feature_class":"P",
    "gn:feature_code":"PPL",
    "gn:name":"Mir\u00e1ka",
    "gn:population":0,
    "gn:timezone":"Europe/Athens",
    "iso:country":"GR",
    "name:ell_x_preferred":[
        "\u039c\u03b9\u03c1\u03ac\u03ba\u03b1"
    ],
    "name:ell_x_variant":[
        "\u0391\u03c1\u03c7\u03b1\u03af\u03b1 \u03a0\u03af\u03c3\u03b1"
    ],
    "name:und_x_variant":[
        "Moir\u00e1kia",
        "Mir\u00e1ka",
        "Archea Pisa"
    ],
    "wof:name":"Miraka",
    "wof:placetype":"locality"
},
  "geometry": {"coordinates":[21.65406,37.64456],"type":"Point"}
}