{
  "type": "Feature",
  "properties": {
    "gn:admin1_code":"ESYE21",
    "gn:admin2_code":"20.0",
    "gn:admin3_code":"9075",
    "gn:asciiname":"Loutsa",
    "gn:country_code":"GR",
    "gn:dem":454,
    "gn:feature_class":"P",
    "gn:feature_code":"PPL",
    "gn:name":"Lo\u00fatsa",
    "gn:population":0,
    "gn:timezone":"Europe/Athens",
    "iso:country":"GR",
    "name:ell_x_preferred":[
        "Lo\u00fatsa"
    ],
    "name:ell_x_variant":[
        "\u039b\u03bf\u03cd\u03c4\u03c3\u03b1"
    ],
    "wof:name":"Loutsa",
    "wof:placetype":"locality"
},
  "geometry": {"coordinates":[21.08939,39.33222],"type":"Point"}
}