{
  "type": "Feature",
  "properties": {
    "gn:admin1_code":"ESYE25",
    "gn:admin2_code":"40.0",
    "gn:admin3_code":"9253",
    "gn:asciiname":"Karyovouni",
    "gn:country_code":"GR",
    "gn:dem":491,
    "gn:feature_class":"P",
    "gn:feature_code":"PPL",
    "gn:name":"Karyovo\u00fani",
    "gn:population":0,
    "gn:timezone":"Europe/Athens",
    "iso:country":"GR",
    "name:ell_x_preferred":[
        "Karyovo\u00fani"
    ],
    "name:ell_x_variant":[
        "\u039a\u03b1\u03c1\u03c5\u03bf\u03b2\u03bf\u03cd\u03bd\u03b9",
        "Karyovo\u00fanion",
        "\u039a\u03b1\u03c1\u03c5\u03bf\u03b2\u03bf\u03cd\u03bd\u03b9\u03bf\u03bd"
    ],
    "name:und_x_variant":[
        "Ar\u00e1khova",
        "Kariovouni",
        "Kariovo\u00fanion"
    ],
    "wof:name":"Karyovouni",
    "wof:placetype":"locality"
},
  "geometry": {"coordinates":[22.34238,36.85669],"type":"Point"}
}