{
  "type": "Feature",
  "properties": {
    "gn:admin1_code":"ESYE23",
    "gn:admin2_code":"38.0",
    "gn:admin3_code":"9130",
    "gn:asciiname":"Eptapitta",
    "gn:country_code":"GR",
    "gn:dem":282,
    "gn:feature_class":"P",
    "gn:feature_code":"PPL",
    "gn:name":"Eptap\u00edtta",
    "gn:population":14,
    "gn:timezone":"Europe/Athens",
    "iso:country":"GR",
    "name:ell_x_preferred":[
        "\u0395\u03c0\u03c4\u03b1\u03c0\u03af\u03c4\u03c4\u03b1"
    ],
    "name:eng_x_preferred":[
        "Eptapitta"
    ],
    "wof:name":"Eptapitta",
    "wof:placetype":"locality",
    "wof:population":14
},
  "geometry": {"coordinates":[22.00505,38.22673],"type":"Point"}
}