{
  "type": "Feature",
  "properties": {
    "gn:admin1_code":"ESYE43",
    "gn:admin2_code":"43.0",
    "gn:admin3_code":"9323",
    "gn:asciiname":"Zympragos",
    "gn:country_code":"GR",
    "gn:dem":293,
    "gn:feature_class":"P",
    "gn:feature_code":"PPL",
    "gn:name":"Zymprag\u00f3s",
    "gn:population":0,
    "gn:timezone":"Europe/Athens",
    "iso:country":"GR",
    "name:bul_x_preferred":[
        "\u0417\u0438\u043c\u0431\u0440\u0430\u0433\u043e\u0441"
    ],
    "name:ell_x_preferred":[
        "Zymprag\u00f3s"
    ],
    "name:ell_x_variant":[
        "\u0396\u03c5\u03bc\u03c0\u03c1\u03b1\u03b3\u03cc\u03c2",
        "\u0396\u03c5\u03bc\u03c0\u03c1\u03b1\u03b3\u03bf\u03cd \u03a7\u03b1\u03bd\u03af\u03c9\u03bd"
    ],
    "name:und_x_variant":[
        "Simbrago\u00fa",
        "Zimbrago\u00fa",
        "Zimvrago\u00fa",
        "Zimbrag\u00f3s"
    ],
    "wof:name":"Zympragos",
    "wof:placetype":"locality"
},
  "geometry": {"coordinates":[23.75627,35.43771],"type":"Point"}
}