{
  "type": "Feature",
  "properties": {
    "gn:admin1_code":"ESYE25",
    "gn:admin2_code":"37.0",
    "gn:admin3_code":"9247",
    "gn:asciiname":"Lavka",
    "gn:country_code":"GR",
    "gn:dem":691,
    "gn:feature_class":"P",
    "gn:feature_code":"PPL",
    "gn:name":"L\u00e1vka",
    "gn:population":362,
    "gn:timezone":"Europe/Athens",
    "iso:country":"GR",
    "name:ell_x_preferred":[
        "\u039b\u03b1\u03cd\u03ba\u03b1"
    ],
    "name:eng_x_preferred":[
        "Lafka"
    ],
    "wof:name":"Lavka",
    "wof:placetype":"locality",
    "wof:population":362
},
  "geometry": {"coordinates":[22.39014,37.83423],"type":"Point"}
}