{
  "type": "Feature",
  "properties": {
    "gn:admin1_code":"ESYE31",
    "gn:admin2_code":"445406.0",
    "gn:admin3_code":"9219",
    "gn:asciiname":"Sakka",
    "gn:country_code":"GR",
    "gn:dem":165,
    "gn:feature_class":"P",
    "gn:feature_code":"PPL",
    "gn:name":"S\u00e1kka",
    "gn:population":97,
    "gn:timezone":"Europe/Athens",
    "iso:country":"GR",
    "name:ell_x_preferred":[
        "\u03a3\u03ac\u03ba\u03ba\u03b1"
    ],
    "name:eng_x_preferred":[
        "Sakka"
    ],
    "wof:name":"Sakka",
    "wof:placetype":"locality",
    "wof:population":97
},
  "geometry": {"coordinates":[23.98646,37.77577],"type":"Point"}
}