{
  "type": "Feature",
  "properties": {
    "gn:admin1_code":"ESYE25",
    "gn:admin2_code":"40.0",
    "gn:admin3_code":"9253",
    "gn:asciiname":"Sotirianika",
    "gn:country_code":"GR",
    "gn:dem":327,
    "gn:feature_class":"P",
    "gn:feature_code":"PPL",
    "gn:name":"Sotiri\u00e1nika",
    "gn:population":83,
    "gn:timezone":"Europe/Athens",
    "iso:country":"GR",
    "name:ell_x_preferred":[
        "\u03a3\u03c9\u03c4\u03b7\u03c1\u03b9\u03ac\u03bd\u03b9\u03ba\u03b1"
    ],
    "name:eng_x_preferred":[
        "Sotirianika"
    ],
    "wof:name":"Sotirianika",
    "wof:placetype":"locality",
    "wof:population":83
},
  "geometry": {"coordinates":[22.19367,36.96855],"type":"Point"}
}