{
  "type": "Feature",
  "properties": {
    "gn:admin1_code":"ESYE24",
    "gn:admin2_code":"34.0",
    "gn:asciiname":"Paralia Chiliadou",
    "gn:country_code":"GR",
    "gn:dem":3,
    "gn:feature_class":"P",
    "gn:feature_code":"PPL",
    "gn:name":"Paralia Chiliadou",
    "gn:population":0,
    "gn:timezone":"Europe/Athens",
    "iso:country":"GR",
    "name:und_x_variant":[
        "\u03a0\u03b1\u03c1\u03b1\u03bb\u03af\u03b1 \u03a7\u03b9\u03bb\u03b9\u03b1\u03b4\u03bf\u03cd"
    ],
    "wof:name":"Paralia Chiliadou",
    "wof:placetype":"locality"
},
  "geometry": {"coordinates":[23.92685,38.66795],"type":"Point"}
}