{
  "type": "Feature",
  "properties": {
    "gn:admin1_code":"ESYE25",
    "gn:admin2_code":"40.0",
    "gn:admin3_code":"9254",
    "gn:asciiname":"Kato Karveli",
    "gn:country_code":"GR",
    "gn:dem":515,
    "gn:feature_class":"P",
    "gn:feature_code":"PPL",
    "gn:name":"K\u00e1to Karv\u00e9li",
    "gn:population":0,
    "gn:timezone":"Europe/Athens",
    "iso:country":"GR",
    "name:ell_x_preferred":[
        "K\u00e1to Karv\u00e9li"
    ],
    "name:ell_x_variant":[
        "\u039a\u03ac\u03c4\u03c9 \u039a\u03b1\u03c1\u03b2\u03ad\u03bb\u03b9",
        "\u039a\u03ac\u03c4\u03c9 \u039a\u03b1\u03c1\u03b2\u03ad\u03bb\u03b9\u03bf\u03bd"
    ],
    "name:und_x_variant":[
        "Khan\u00e1kia",
        "K\u00e1to Karv\u00e9lion"
    ],
    "wof:name":"Kato Karveli",
    "wof:placetype":"locality"
},
  "geometry": {"coordinates":[22.16546,37.06947],"type":"Point"}
}