{
  "type": "Feature",
  "properties": {
    "gn:admin1_code":"ESYE11",
    "gn:admin2_code":"14.0",
    "gn:admin3_code":"9011",
    "gn:asciiname":"Kastro",
    "gn:country_code":"GR",
    "gn:dem":504,
    "gn:feature_class":"P",
    "gn:feature_code":"PPL",
    "gn:name":"K\u00e1stro",
    "gn:population":9,
    "gn:timezone":"Europe/Athens",
    "iso:country":"GR",
    "name:ell_x_preferred":[
        "\u039a\u03ac\u03c3\u03c4\u03c1\u03bf"
    ],
    "name:ell_x_variant":[
        "K\u00e1stro",
        "\u039a\u03ac\u03c3\u03c4\u03c1\u03bf\u03bd"
    ],
    "name:eng_x_preferred":[
        "Kastro"
    ],
    "name:und_x_variant":[
        "K\u00e1stron"
    ],
    "wof:name":"Kastro",
    "wof:placetype":"locality",
    "wof:population":9
},
  "geometry": {"coordinates":[24.65491,40.67066],"type":"Point"}
}