{
  "type": "Feature",
  "properties": {
    "gn:gn_country":"GR",
    "iso:country":"GR",
    "name:ara_x_preferred":[
        "\u062f\u0631\u0627\u0628\u064a\u062a\u0633\u0648\u0646\u0627"
    ],
    "name:bul_x_preferred":[
        "\u0414\u0440\u0430\u043f\u0435\u0446\u043e\u043d\u0430"
    ],
    "name:dut_x_preferred":[
        "Drapetsona"
    ],
    "name:eng_x_preferred":[
        "Drapetsona"
    ],
    "name:fin_x_preferred":[
        "Drapets\u00f3na"
    ],
    "name:fre_x_preferred":[
        "Drapetsona"
    ],
    "name:gre_x_preferred":[
        "\u0394\u03c1\u03b1\u03c0\u03b5\u03c4\u03c3\u03ce\u03bd\u03b1"
    ],
    "name:hrv_x_preferred":[
        "Drapetsona"
    ],
    "name:ita_x_preferred":[
        "Drapetsona"
    ],
    "name:jpn_x_preferred":[
        "\u30c9\u30e9\u30da\u30c4\u30a9\u30ca"
    ],
    "name:nno_x_preferred":[
        "Drapets\u00f3na"
    ],
    "name:pol_x_preferred":[
        "Drapetsona"
    ],
    "name:rum_x_preferred":[
        "Drapetsona"
    ],
    "name:sco_x_preferred":[
        "Drapetsona"
    ],
    "name:spa_x_preferred":[
        "Drapetsona"
    ],
    "name:swe_x_preferred":[
        "Drapets\u00f3na"
    ],
    "name:urd_x_preferred":[
        "\u062f\u0631\u0627\u067e\u06cc\u062a\u0633\u0648\u0646\u0627"
    ],
    "qs_pg:aaroncc":"GR",
    "qs_pg:gn_country":"GR",
    "qs_pg:name":"Drapetsona",
    "qs_pg:name_adm0":"\u0395\u03bb\u03bb\u03ac\u03b4\u03b1",
    "qs_pg:name_adm1":"Attica",
    "qs_pg:photos":582,
    "qs_pg:photos_1k":118,
    "qs_pg:photos_9k":3,
    "qs_pg:photos_9r":5,
    "qs_pg:photos_all":582,
    "qs_pg:photos_sr":8,
    "qs_pg:pop_sr":0,
    "qs_pg:qs_pg_placetype":"locality",
    "qs_pg:qs_pg_placetype_gp":"Town",
    "qs_pg:woe_adm0":23424833,
    "woe:adm0_id":23424833,
    "woe:name_adm0":"\u0395\u03bb\u03bb\u03ac\u03b4\u03b1",
    "woe:name_adm1":"Attica",
    "woe:placetype":"Town",
    "wof:name":"Drapetsona",
    "wof:placetype":"locality"
},
  "geometry": {"coordinates":[23.635153,37.94528],"type":"Point"}
}