{
  "type": "Feature",
  "properties": {
    "gn:country":"GR",
    "gn:fcode":"ADM3",
    "gn:population":397156,
    "iso:country":"GR",
    "name:ell_x_preferred":[
        "\u0398\u03b5\u03c3\u03c3\u03b1\u03bb\u03bf\u03bd\u03af\u03ba\u03b7\u03c2"
    ],
    "qs_pg:aaroncc":"GR",
    "qs_pg:gn_country":"GR",
    "qs_pg:gn_fcode":"ADM3",
    "qs_pg:gn_pop":397156,
    "qs_pg:name":"Dimos Thessaloniki",
    "qs_pg:photos_9r":0,
    "qs_pg:photos_sr":0,
    "qs_pg:pop_sr":10,
    "qs_pg:qs_pg_placetype":"localadmin",
    "wof:name":"Dimos Thessaloniki",
    "wof:placetype":"localadmin",
    "wof:population":397156
},
  "geometry": {"coordinates":[22.95369,40.62334],"type":"Point"}
}