{
  "type": "Feature",
  "properties": {
    "gn:gn_country":"GR",
    "gn:gn_fcode":"PPL",
    "gn:gn_pop":1585,
    "gn:population":1899,
    "iso:country":"GR",
    "name:ara_x_preferred":[
        "\u063a\u064a\u062a\u0627\u0646\u064a\u0648\u0646\u060c \u0632\u0627\u0643\u064a\u0646\u062b\u0648\u0633"
    ],
    "name:ell_x_preferred":[
        "\u0393\u03b1\u03ca\u03c4\u03ac\u03bd\u03b9"
    ],
    "name:ell_x_variant":[
        "\u0393\u03b1\u03ca\u03c4\u03ac\u03bd\u03b9 \u0396\u03b1\u03ba\u03cd\u03bd\u03b8\u03bf\u03c5"
    ],
    "name:eng_x_preferred":[
        "Gaitani"
    ],
    "name:nld_x_preferred":[
        "Gaitani"
    ],
    "name:ron_x_preferred":[
        "Gaitani"
    ],
    "name:swe_x_preferred":[
        "Ga\u00eft\u00e1nion"
    ],
    "name:unk_x_variant":[
        "Ga\u00eft\u00e1ni"
    ],
    "qs_pg:aaroncc":"GR",
    "qs_pg:gn_country":"GR",
    "qs_pg:gn_fcode":"PPL",
    "qs_pg:gn_pop":1585,
    "qs_pg:name":"Gaitanion",
    "qs_pg:name_adm0":"\u0395\u03bb\u03bb\u03ac\u03b4\u03b1",
    "qs_pg:name_adm1":"Peloponnese Western Greece and the Ionian Islands",
    "qs_pg:photos_9r":0,
    "qs_pg:photos_sr":0,
    "qs_pg:pop_sr":3,
    "qs_pg:qs_pg_placetype":"locality",
    "qs_pg:qs_pg_placetype_gp":"Town",
    "qs_pg:woe_adm0":23424833,
    "woe:adm0_id":23424833,
    "woe:name_adm0":"\u0395\u03bb\u03bb\u03ac\u03b4\u03b1",
    "woe:name_adm1":"Peloponnese Western Greece and the Ionian Islands",
    "woe:placetype":"Town",
    "wof:name":"Gaitanion",
    "wof:placetype":"locality",
    "wof:population":1899
},
  "geometry": {"coordinates":[20.86667,37.78333],"type":"Point"}
}