{
  "type": "Feature",
  "properties": {
    "gn:population":3987,
    "iso:country":"GR",
    "name:ell_x_preferred":[
        "\u03a6\u03ac\u03bb\u03b1\u03bd\u03bd\u03b1"
    ],
    "name:ell_x_variant":[
        "\u03a6\u03ac\u03bb\u03b1\u03bd\u03b7"
    ],
    "name:eng_x_preferred":[
        "Falanna"
    ],
    "name:und_x_variant":[
        "Tat\u00e1r"
    ],
    "qs:a0":"Greece",
    "qs:a1":"*\u0398\u0395\u03a3\u03a3\u0391\u039b\u0399\u0391",
    "qs:a1_alt":"UESSALIA",
    "qs:a1r":"0",
    "qs:a2_alt":"LARISA",
    "qs:adm0":"Greece",
    "qs:la_lc":"*",
    "qs:level":"locality",
    "qs:loc":"\u03a6\u0391\u039b\u0391\u039d\u039d\u0391",
    "qs:loc_alt":"FALANNA",
    "qs:pop":0,
    "qs:type":"buffered point",
    "wof:name":"\u03a6\u0391\u039b\u0391\u039d\u039d\u0391",
    "wof:placetype":"locality",
    "wof:population":3987
},
  "geometry": {"coordinates":[22.400511,39.7196],"type":"Point"}
}