{
  "type": "Feature",
  "properties": {
    "gn:admin1_code":"ESYE24",
    "gn:admin2_code":"29.0",
    "gn:admin3_code":"9164",
    "gn:asciiname":"Kouvela",
    "gn:country_code":"GR",
    "gn:dem":2,
    "gn:feature_class":"P",
    "gn:feature_code":"PPL",
    "gn:name":"Kouv\u00e9la",
    "gn:population":65,
    "gn:timezone":"Europe/Athens",
    "iso:country":"GR",
    "name:ell_x_preferred":[
        "\u039a\u03bf\u03c5\u03b2\u03ad\u03bb\u03b1"
    ],
    "name:eng_x_preferred":[
        "Kouvela"
    ],
    "wof:name":"Kouvela",
    "wof:placetype":"locality",
    "wof:population":65
},
  "geometry": {"coordinates":[22.74374,38.87288],"type":"Point"}
}