{
  "type": "Feature",
  "properties": {
    "gn:admin1_code":"ESYE43",
    "gn:admin2_code":"44.0",
    "gn:admin3_code":"9318",
    "gn:asciiname":"Goulediana",
    "gn:country_code":"GR",
    "gn:dem":451,
    "gn:feature_class":"P",
    "gn:feature_code":"PPL",
    "gn:name":"Gouledian\u00e1",
    "gn:population":73,
    "gn:timezone":"Europe/Athens",
    "iso:country":"GR",
    "name:ell_x_preferred":[
        "\u0393\u03bf\u03c5\u03bb\u03b5\u03b4\u03b9\u03b1\u03bd\u03ac"
    ],
    "name:eng_x_preferred":[
        "Goulediana"
    ],
    "wof:name":"Goulediana",
    "wof:placetype":"locality",
    "wof:population":73
},
  "geometry": {"coordinates":[24.49839,35.28358],"type":"Point"}
}