{
  "type": "Feature",
  "properties": {
    "gn:gn_country":"GR",
    "gn:gn_fcode":"PPL",
    "gn:gn_pop":193,
    "gn:population":85,
    "iso:country":"GR",
    "name:ell_x_preferred":[
        "\u039c\u03b1\u03c5\u03c1\u03bf\u03bd\u03cc\u03c1\u03bf\u03c2"
    ],
    "name:eng_x_preferred":[
        "Mavronoros"
    ],
    "name:unk_x_variant":[
        "Mavron\u00f3ros"
    ],
    "qs_pg:aaroncc":"GR",
    "qs_pg:gn_country":"GR",
    "qs_pg:gn_fcode":"PPL",
    "qs_pg:gn_pop":193,
    "qs_pg:name":"Mavronoros",
    "qs_pg:name_adm0":"\u0395\u03bb\u03bb\u03ac\u03b4\u03b1",
    "qs_pg:name_adm1":"Epirus and Western Macedonia",
    "qs_pg:photos_9k":1,
    "qs_pg:photos_9r":1,
    "qs_pg:photos_all":3,
    "qs_pg:photos_sr":0,
    "qs_pg:pop_sr":1,
    "qs_pg:qs_pg_placetype":"locality",
    "qs_pg:qs_pg_placetype_gp":"Town",
    "qs_pg:woe_adm0":23424833,
    "woe:adm0_id":23424833,
    "woe:name_adm0":"\u0395\u03bb\u03bb\u03ac\u03b4\u03b1",
    "woe:name_adm1":"Epirus and Western Macedonia",
    "woe:placetype":"Town",
    "wof:name":"Mavronoros",
    "wof:placetype":"locality",
    "wof:population":85
},
  "geometry": {"coordinates":[20.53472,39.85361],"type":"Point"}
}