{
  "type": "Feature",
  "properties": {
    "gn:gn_country":"GR",
    "gn:gn_fcode":"ADM3",
    "gn:gn_pop":13350,
    "gn:population":13350,
    "iso:country":"GR",
    "name:ell_x_preferred":[
        "\u039c\u03c5\u03bb\u03bf\u03c0\u03bf\u03c4\u03ac\u03bc\u03bf\u03c5"
    ],
    "name:fin_x_preferred":[
        "Mylop\u00f3tamos"
    ],
    "name:nld_x_preferred":[
        "Mylopotamos"
    ],
    "name:rus_x_preferred":[
        "\u041c\u0438\u043b\u043e\u043f\u043e\u0442\u0430\u043c\u043e\u0441"
    ],
    "qs_pg:aaroncc":"GR",
    "qs_pg:gn_country":"GR",
    "qs_pg:gn_fcode":"ADM3",
    "qs_pg:gn_pop":13350,
    "qs_pg:name":"Mylopotamos",
    "qs_pg:name_adm0":"\u0395\u03bb\u03bb\u03ac\u03b4\u03b1",
    "qs_pg:name_adm1":"Crete",
    "qs_pg:photos_9k":5,
    "qs_pg:photos_9r":7,
    "qs_pg:photos_all":1071,
    "qs_pg:photos_sr":0,
    "qs_pg:pop_sr":6,
    "qs_pg:qs_pg_placetype":"localadmin",
    "qs_pg:qs_pg_placetype_gp":"LocalAdmin",
    "qs_pg:woe_adm0":23424833,
    "woe:adm0_id":23424833,
    "woe:name_adm0":"\u0395\u03bb\u03bb\u03ac\u03b4\u03b1",
    "woe:name_adm1":"Crete",
    "woe:placetype":"LocalAdmin",
    "wof:name":"Mylopotamos",
    "wof:placetype":"localadmin",
    "wof:population":13350
},
  "geometry": {"coordinates":[24.77638,35.34289],"type":"Point"}
}