{
  "type": "Feature",
  "properties": {
    "gn:admin1_code":"ESYE11",
    "gn:admin2_code":"2.0",
    "gn:admin3_code":"9022",
    "gn:asciiname":"Iasio",
    "gn:country_code":"GR",
    "gn:dem":68,
    "gn:feature_class":"P",
    "gn:feature_code":"PPL",
    "gn:name":"I\u00e1sio",
    "gn:population":0,
    "gn:timezone":"Europe/Athens",
    "iso:country":"GR",
    "name:ell_x_preferred":[
        "I\u00e1sio"
    ],
    "name:ell_x_variant":[
        "\u0399\u03ac\u03c3\u03b9\u03bf",
        "I\u00e1sion",
        "\u0399\u03ac\u03c3\u03b9\u03bf\u03bd"
    ],
    "wof:name":"Iasio",
    "wof:placetype":"locality"
},
  "geometry": {"coordinates":[25.71446,41.07495],"type":"Point"}
}