{
  "type": "Feature",
  "properties": {
    "gn:admin1_code":"ESYE25",
    "gn:admin2_code":"40.0",
    "gn:admin3_code":"9254",
    "gn:asciiname":"Anemomylos",
    "gn:country_code":"GR",
    "gn:dem":28,
    "gn:feature_class":"P",
    "gn:feature_code":"PPL",
    "gn:name":"Anem\u00f3mylos",
    "gn:population":0,
    "gn:timezone":"Europe/Athens",
    "iso:country":"GR",
    "name:ell_x_preferred":[
        "Anem\u00f3mylos"
    ],
    "name:ell_x_variant":[
        "\u0391\u03bd\u03b5\u03bc\u03cc\u03bc\u03c5\u03bb\u03bf\u03c2"
    ],
    "name:und_x_variant":[
        "Gli\u00e1ra",
        "Gli\u00e1ta",
        "Anem\u00f3milos"
    ],
    "wof:name":"Anemomylos",
    "wof:placetype":"locality"
},
  "geometry": {"coordinates":[22.00594,37.13491],"type":"Point"}
}