{
  "type": "Feature",
  "properties": {
    "gn:admin1_code":"ESYE43",
    "gn:admin2_code":"43.0",
    "gn:admin3_code":"9322",
    "gn:asciiname":"Aikyrgiannis",
    "gn:country_code":"GR",
    "gn:dem":265,
    "gn:feature_class":"P",
    "gn:feature_code":"PPL",
    "gn:name":"A\u00efkyrgi\u00e1nnis",
    "gn:population":36,
    "gn:timezone":"Europe/Athens",
    "iso:country":"GR",
    "name:ell_x_historical":[
        "\u0386\u03b3\u03b9\u03bf\u03c2 \u039a\u03c5\u03c1-\u0393\u03b9\u03ac\u03bd\u03bd\u03b7\u03c2"
    ],
    "name:ell_x_preferred":[
        "\u0391\u03ca\u03ba\u03c5\u03c1\u03b3\u03b9\u03ac\u03bd\u03bd\u03b7\u03c2"
    ],
    "name:ell_x_variant":[
        "\u0386\u03b3\u03b9\u03bf\u03c2 \u039a\u03c5\u03c1-\u0393\u03b9\u03ac\u03bd\u03bd\u03b7\u03c2"
    ],
    "name:eng_x_preferred":[
        "Aikyrgiannis"
    ],
    "name:und_x_variant":[
        "A\u00efkyrgi\u00e1nnis",
        "A\u00efkiryi\u00e1nnis"
    ],
    "wof:name":"Aikyrgiannis",
    "wof:placetype":"locality",
    "wof:population":36
},
  "geometry": {"coordinates":[23.68015,35.43364000000001],"type":"Point"}
}