{
  "type": "Feature",
  "properties": {
    "gn:country":"GR",
    "gn:fcode":"PPL",
    "gn:population":56,
    "iso:country":"GR",
    "name:ell_x_preferred":[
        "Kouval\u00e1ta"
    ],
    "name:ell_x_variant":[
        "\u039a\u03bf\u03c5\u03b2\u03b1\u03bb\u03ac\u03c4\u03b1"
    ],
    "qs_pg:aaroncc":"GR",
    "qs_pg:gn_country":"GR",
    "qs_pg:gn_fcode":"PPL",
    "qs_pg:gn_pop":56,
    "qs_pg:name":"Kouval\u00e1ta",
    "qs_pg:photos_9r":0,
    "qs_pg:photos_sr":0,
    "qs_pg:pop_sr":1,
    "qs_pg:qs_pg_placetype":"locality",
    "wof:name":"Kouval\u00e1ta",
    "wof:placetype":"locality",
    "wof:population":56
},
  "geometry": {"coordinates":[20.41667,38.23333],"type":"Point"}
}