{
  "type": "Feature",
  "properties": {
    "gn:gn_country":"GR",
    "gn:gn_fcode":"PPL",
    "gn:gn_pop":469,
    "gn:population":469,
    "iso:country":"GR",
    "name:ell_x_preferred":[
        "\u0391\u03bd\u03b8\u03bf\u03c7\u03ce\u03c1\u03b9"
    ],
    "name:ell_x_variant":[
        "\u0391\u03bd\u03b8\u03bf\u03c7\u03ce\u03c1\u03b9\u03bf\u03bd"
    ],
    "name:unk_x_variant":[
        "Floresaioi"
    ],
    "qs_pg:aaroncc":"GR",
    "qs_pg:gn_country":"GR",
    "qs_pg:gn_fcode":"PPL",
    "qs_pg:gn_pop":469,
    "qs_pg:name":"Anthoch\u00f3rion",
    "qs_pg:photos_9r":0,
    "qs_pg:photos_sr":0,
    "qs_pg:pop_sr":2,
    "qs_pg:qs_pg_placetype":"locality",
    "wof:name":"Anthoch\u00f3rion",
    "wof:placetype":"locality",
    "wof:population":469
},
  "geometry": {"coordinates":[21.66389,39.35722],"type":"Point"}
}