{
  "type": "Feature",
  "properties": {
    "gn:admin1_code":"ESYE22",
    "gn:admin2_code":"27.0",
    "gn:admin3_code":"9120",
    "gn:asciiname":"Xenopoulo",
    "gn:country_code":"GR",
    "gn:dem":317,
    "gn:feature_class":"P",
    "gn:feature_code":"PPL",
    "gn:name":"Xen\u00f3poulo",
    "gn:population":0,
    "gn:timezone":"Europe/Athens",
    "iso:country":"GR",
    "name:ell_x_preferred":[
        "Xen\u00f3poulo"
    ],
    "name:ell_x_variant":[
        "\u039e\u03b5\u03bd\u03cc\u03c0\u03bf\u03c5\u03bb\u03bf",
        "\u039e\u03b5\u03bd\u03cc\u03c0\u03bf\u03c5\u03bb\u03bf\u03bd",
        "\u039e\u03b5\u03bd\u03cc\u03c0\u03bf\u03c5\u03bb\u03bf \u039a\u03b5\u03c6\u03b1\u03bb\u03bf\u03bd\u03b9\u03ac\u03c2"
    ],
    "name:ron_x_preferred":[
        "Xenopoulo"
    ],
    "name:und_x_variant":[
        "Xenopo\u00falou",
        "Xen\u00f3poulon"
    ],
    "wof:name":"Xenopoulo",
    "wof:placetype":"locality"
},
  "geometry": {"coordinates":[20.72258,38.13633],"type":"Point"}
}