{
  "type": "Feature",
  "properties": {
    "gn:admin1_code":"ESYE21",
    "gn:admin2_code":"19.0",
    "gn:admin3_code":"9089",
    "gn:asciiname":"Chrysogiali",
    "gn:country_code":"GR",
    "gn:dem":11,
    "gn:feature_class":"P",
    "gn:feature_code":"PPL",
    "gn:name":"Chrysogi\u00e1li",
    "gn:population":0,
    "gn:timezone":"Europe/Athens",
    "iso:country":"GR",
    "name:ell_x_preferred":[
        "Chrysogi\u00e1li"
    ],
    "name:ell_x_variant":[
        "\u03a7\u03c1\u03c5\u03c3\u03bf\u03b3\u03b9\u03ac\u03bb\u03b9"
    ],
    "wof:name":"Chrysogiali",
    "wof:placetype":"locality"
},
  "geometry": {"coordinates":[20.3865,39.28708],"type":"Point"}
}