{
  "type": "Feature",
  "properties": {
    "gn:gn_country":"GR",
    "gn:gn_fcode":"PPL",
    "gn:gn_pop":63,
    "gn:population":32,
    "iso:country":"GR",
    "name:ell_x_preferred":[
        "\u0391\u03b3\u03ac\u03b8\u03b7"
    ],
    "name:ell_x_variant":[
        "\u0391\u03b3\u03b1\u03b8\u03ae"
    ],
    "name:unk_x_variant":[
        "Agathi"
    ],
    "qs_pg:aaroncc":"GR",
    "qs_pg:gn_country":"GR",
    "qs_pg:gn_fcode":"PPL",
    "qs_pg:gn_pop":63,
    "qs_pg:name":"Ag\u00e1thi",
    "qs_pg:photos_9r":0,
    "qs_pg:photos_sr":0,
    "qs_pg:pop_sr":1,
    "qs_pg:qs_pg_placetype":"locality",
    "wof:name":"Ag\u00e1thi",
    "wof:placetype":"locality",
    "wof:population":32
},
  "geometry": {"coordinates":[22.05889,41.00917],"type":"Point"}
}