{
  "type": "Feature",
  "properties": {
    "gn:admin1_code":"ESYE43",
    "gn:admin2_code":"45.0",
    "gn:admin3_code":"9306.0",
    "gn:asciiname":"Agios Georgios Methystis",
    "gn:country_code":"GR",
    "gn:dem":108,
    "gn:feature_class":"P",
    "gn:feature_code":"PPL",
    "gn:name":"\u00c1gios Ge\u00f3rgios Methyst\u00eds",
    "gn:population":117,
    "gn:timezone":"Europe/Athens",
    "iso:country":"GR",
    "name:ell_x_preferred":[
        "\u0386\u03b3\u03b9\u03bf\u03c2 \u0393\u03b5\u03ce\u03c1\u03b3\u03b9\u03bf\u03c2 \u039c\u03b5\u03b8\u03c5\u03c3\u03c4\u03ae\u03c2"
    ],
    "name:ell_x_variant":[
        "\u0386\u03b3\u03b9\u03bf\u03c2 \u0393\u03b5\u03ce\u03c1\u03b3\u03b9\u03bf\u03c2 \u03bf \u039c\u03b5\u03b8\u03c5\u03c3\u03c4\u03ae\u03c2"
    ],
    "name:eng_x_preferred":[
        "Agios Georgios Methystis"
    ],
    "wof:name":"Agios Georgios Methystis",
    "wof:placetype":"locality",
    "wof:population":117
},
  "geometry": {"coordinates":[25.04479,35.30329000000001],"type":"Point"}
}