{
  "type": "Feature",
  "properties": {
    "gn:admin1_code":"ESYE13",
    "gn:admin2_code":"11.0",
    "gn:admin3_code":"9066",
    "gn:asciiname":"Pylori",
    "gn:country_code":"GR",
    "gn:dem":659,
    "gn:feature_class":"P",
    "gn:feature_code":"PPL",
    "gn:name":"Pyl\u00f3ri",
    "gn:population":0,
    "gn:timezone":"Europe/Athens",
    "iso:country":"GR",
    "name:ell_x_preferred":[
        "Pyl\u00f3ri"
    ],
    "name:ell_x_variant":[
        "\u03a0\u03c5\u03bb\u03ce\u03c1\u03b9",
        "Pyl\u00f3rion",
        "\u03a0\u03c5\u03bb\u03ce\u03c1\u03b9\u03bf\u03bd"
    ],
    "name:und_x_variant":[
        "Pilor\u00ed",
        "Pil\u00f3rion"
    ],
    "wof:name":"Pylori",
    "wof:placetype":"locality"
},
  "geometry": {"coordinates":[21.38458,40.27019],"type":"Point"}
}