{
  "type": "Feature",
  "properties": {
    "gn:country":"GR",
    "gn:fcode":"PPL",
    "gn:population":934,
    "iso:country":"GR",
    "name:ara_x_preferred":[
        "\u0645\u064a\u062a\u064a\u0643\u0627\u0633\u060c \u0623\u064a\u062a\u0648\u0644\u064a\u0627 \u0643\u064a \u0623\u0643\u0627\u0631\u0646\u0627\u0646\u064a\u0627"
    ],
    "name:ara_x_variant":[
        "\u0645\u064a\u062a\u064a\u0643\u0627\u0633"
    ],
    "name:arz_x_preferred":[
        "\u0645\u064a\u062a\u064a\u0643\u0627\u0633"
    ],
    "name:ceb_x_preferred":[
        "M\u00fdtikas"
    ],
    "name:deu_x_preferred":[
        "Mytikas"
    ],
    "name:ell_x_preferred":[
        "\u039c\u03cd\u03c4\u03b9\u03ba\u03b1\u03c2"
    ],
    "name:ell_x_variant":[
        "\u039c\u03cd\u03c4\u03b9\u03ba\u03b1\u03c2 \u0391\u03b9\u03c4\u03c9\u03bb\u03bf\u03b1\u03ba\u03b1\u03c1\u03bd\u03b1\u03bd\u03af\u03b1\u03c2"
    ],
    "name:eng_x_preferred":[
        "Mytikas"
    ],
    "name:fra_x_preferred":[
        "M\u00fdtikas"
    ],
    "name:ita_x_preferred":[
        "Mytikas"
    ],
    "name:nld_x_preferred":[
        "Mytikas"
    ],
    "name:rus_x_preferred":[
        "\u041c\u0438\u0442\u0438\u043a\u0430\u0441"
    ],
    "name:swe_x_preferred":[
        "M\u00fdtikas"
    ],
    "name:und_x_variant":[
        "M\u00edtikas"
    ],
    "qs_pg:aaroncc":"GR",
    "qs_pg:gn_country":"GR",
    "qs_pg:gn_fcode":"PPL",
    "qs_pg:gn_pop":934,
    "qs_pg:name":"Mytikas",
    "qs_pg:name_adm0":"\u0395\u03bb\u03bb\u03ac\u03b4\u03b1",
    "qs_pg:name_adm1":"Peloponnese Western Greece and the Ionian Islands",
    "qs_pg:photos_9k":1,
    "qs_pg:photos_9r":1,
    "qs_pg:photos_all":9,
    "qs_pg:photos_sr":0,
    "qs_pg:pop_sr":2,
    "qs_pg:qs_pg_placetype":"locality",
    "qs_pg:qs_pg_placetype_gp":"Town",
    "qs_pg:woe_adm0":23424833,
    "woe:adm0_id":23424833,
    "woe:name_adm0":"\u0395\u03bb\u03bb\u03ac\u03b4\u03b1",
    "woe:name_adm1":"Peloponnese Western Greece and the Ionian Islands",
    "woe:placetype":"Town",
    "wof:name":"Mytikas",
    "wof:placetype":"locality",
    "wof:population":759
},
  "geometry": {"coordinates":[20.93333,38.66667],"type":"Point"}
}