{
  "type": "Feature",
  "properties": {
    "gn:admin1_code":"ESYE14",
    "gn:admin2_code":"21.0",
    "gn:admin3_code":"9102",
    "gn:asciiname":"Karkatzi",
    "gn:country_code":"GR",
    "gn:dem":76,
    "gn:feature_class":"P",
    "gn:feature_code":"PPL",
    "gn:name":"Karkatz\u00ed",
    "gn:population":0,
    "gn:timezone":"Europe/Athens",
    "iso:country":"GR",
    "name:und_x_variant":[
        "Karkatz\u00ed",
        "Karkaj\u00ed"
    ],
    "wof:name":"Karkatzi",
    "wof:placetype":"locality"
},
  "geometry": {"coordinates":[22.35,39.73333],"type":"Point"}
}