{
  "type": "Feature",
  "properties": {
    "gn:gn_country":"GR",
    "gn:gn_fcode":"PPLA",
    "gn:gn_pop":237,
    "gn:population":237,
    "iso:country":"GR",
    "name:afr_x_preferred":[
        "Karyes"
    ],
    "name:ara_x_preferred":[
        "\u0643\u0627\u0631\u064a\u0633"
    ],
    "name:bul_x_preferred":[
        "\u041a\u0430\u0440\u0435\u044f"
    ],
    "name:cat_x_preferred":[
        "Karyes"
    ],
    "name:ceb_x_preferred":[
        "Karyes"
    ],
    "name:ces_x_preferred":[
        "Kary\u00e9s"
    ],
    "name:deu_x_preferred":[
        "Karyes"
    ],
    "name:ell_x_preferred":[
        "\u039a\u03b1\u03c1\u03c5\u03ad\u03c2"
    ],
    "name:ell_x_variant":[
        "\u039a\u03b1\u03c1\u03c5\u03ad\u03c2 \u0391\u03b3\u03af\u03bf\u03c5 \u038c\u03c1\u03bf\u03c5\u03c2"
    ],
    "name:eng_x_preferred":[
        "Karyes"
    ],
    "name:eus_x_preferred":[
        "Karyes"
    ],
    "name:fin_x_preferred":[
        "Kary\u00e9s"
    ],
    "name:fra_x_preferred":[
        "Kary\u00e8s"
    ],
    "name:hrv_x_preferred":[
        "Kareja"
    ],
    "name:ita_x_preferred":[
        "Karyes"
    ],
    "name:jav_x_preferred":[
        "Karyes"
    ],
    "name:jpn_x_preferred":[
        "\u30ab\u30ea\u30a8\u30b9"
    ],
    "name:kat_x_preferred":[
        "\u10d9\u10d0\u10e0\u10d8\u10d4\u10e1\u10d8"
    ],
    "name:kor_x_preferred":[
        "\uce74\ub9ac\uc5d0\uc2a4"
    ],
    "name:nld_x_preferred":[
        "Karyes"
    ],
    "name:nno_x_preferred":[
        "Kary\u00e9s"
    ],
    "name:pol_x_preferred":[
        "Karies"
    ],
    "name:por_x_preferred":[
        "Karyes"
    ],
    "name:rus_x_preferred":[
        "\u041a\u0430\u0440\u044c\u0435"
    ],
    "name:slv_x_preferred":[
        "Karies"
    ],
    "name:spa_x_preferred":[
        "Kary\u00e9s"
    ],
    "name:srp_x_preferred":[
        "\u041a\u0430\u0440\u0435\u0458\u0430"
    ],
    "name:swe_x_preferred":[
        "Karyes"
    ],
    "name:tur_x_preferred":[
        "Karyes"
    ],
    "name:ukr_x_preferred":[
        "\u041a\u0430\u0440\u0456\u0435\u0441"
    ],
    "name:unk_x_variant":[
        "Karyaes"
    ],
    "name:war_x_preferred":[
        "Karyes"
    ],
    "name:zho_x_preferred":[
        "\u5361\u91cc\u57c3"
    ],
    "qs_pg:aaroncc":"GR",
    "qs_pg:gn_country":"GR",
    "qs_pg:gn_fcode":"PPLA",
    "qs_pg:gn_pop":237,
    "qs_pg:name":"Kariai",
    "qs_pg:name_adm0":"\u0395\u03bb\u03bb\u03ac\u03b4\u03b1",
    "qs_pg:name_adm1":"Mount Athos",
    "qs_pg:photos_9k":1,
    "qs_pg:photos_9r":1,
    "qs_pg:photos_all":9,
    "qs_pg:photos_sr":0,
    "qs_pg:pop_sr":2,
    "qs_pg:qs_pg_placetype":"locality",
    "qs_pg:qs_pg_placetype_gp":"Town",
    "qs_pg:woe_adm0":23424833,
    "woe:adm0_id":23424833,
    "woe:name_adm0":"\u0395\u03bb\u03bb\u03ac\u03b4\u03b1",
    "woe:name_adm1":"Mount Athos",
    "woe:placetype":"Town",
    "wof:name":"Kariai",
    "wof:placetype":"locality",
    "wof:population":237
},
  "geometry": {"coordinates":[24.24498,40.25715],"type":"Point"}
}