{
  "type": "Feature",
  "properties": {
    "gn:admin1_code":"ESYE23",
    "gn:admin2_code":"31.0",
    "gn:admin3_code":"9123",
    "gn:asciiname":"Gourgoutsaiika",
    "gn:cc2":"GR",
    "gn:country_code":"GR",
    "gn:dem":139,
    "gn:feature_class":"P",
    "gn:feature_code":"PPL",
    "gn:name":"Gourgoutsa\u00edika",
    "gn:population":0,
    "gn:timezone":"Europe/Athens",
    "iso:country":"GR",
    "name:und_x_variant":[
        "Gourgoulits\u00e9\u00efka",
        "Gourgoutsa\u00edika"
    ],
    "wof:name":"Gourgoutsaiika",
    "wof:placetype":"locality"
},
  "geometry": {"coordinates":[21.43351,38.52024],"type":"Point"}
}