{
  "type": "Feature",
  "properties": {
    "gn:admin1_code":"ESYE21",
    "gn:admin2_code":"20.0",
    "gn:admin3_code":"9074",
    "gn:asciiname":"Karyes",
    "gn:country_code":"GR",
    "gn:dem":641,
    "gn:feature_class":"P",
    "gn:feature_code":"PPL",
    "gn:name":"Kary\u00e9s",
    "gn:population":0,
    "gn:timezone":"Europe/Athens",
    "iso:country":"GR",
    "name:ell_x_preferred":[
        "Kary\u00e9s"
    ],
    "name:ell_x_variant":[
        "\u039a\u03b1\u03c1\u03c5\u03ad\u03c2"
    ],
    "name:und_x_variant":[
        "Kary\u00e1"
    ],
    "wof:name":"Karyes",
    "wof:placetype":"locality"
},
  "geometry": {"coordinates":[21.30931,39.22953],"type":"Point"}
}