{
  "type": "Feature",
  "properties": {
    "gn:admin1_code":"ESYE43",
    "gn:admin2_code":"46.0",
    "gn:admin3_code":"9310",
    "gn:asciiname":"Vrachasi",
    "gn:country_code":"GR",
    "gn:dem":373,
    "gn:feature_class":"P",
    "gn:feature_code":"PPL",
    "gn:name":"Vrach\u00e1si",
    "gn:population":311,
    "gn:timezone":"Europe/Athens",
    "iso:country":"GR",
    "name:cat_x_preferred":[
        "Vrakhassi"
    ],
    "name:ces_x_preferred":[
        "Vrachasi"
    ],
    "name:ell_x_preferred":[
        "\u0392\u03c1\u03b1\u03c7\u03ac\u03c3\u03b9"
    ],
    "name:ell_x_variant":[
        "\u039a\u03bf\u03b9\u03bd\u03cc\u03c4\u03b7\u03c4\u03b1 \u0392\u03c1\u03b1\u03c7\u03b1\u03c3\u03af\u03bf\u03c5"
    ],
    "name:eng_x_preferred":[
        "Vrachasi"
    ],
    "name:fin_x_preferred":[
        "Vrach\u00e1si"
    ],
    "name:ita_x_preferred":[
        "Vrachasi"
    ],
    "name:nno_x_preferred":[
        "Vrakh\u00e1si"
    ],
    "name:und_x_variant":[
        "Vrakh\u00e1sion"
    ],
    "wof:name":"Vrachasi",
    "wof:placetype":"locality",
    "wof:population":311
},
  "geometry": {"coordinates":[25.56407,35.27316],"type":"Point"}
}