{
  "type": "Feature",
  "properties": {
    "gn:admin1_code":"ESYE13",
    "gn:admin2_code":"11.0",
    "gn:admin3_code":"9069",
    "gn:asciiname":"Roditis",
    "gn:country_code":"GR",
    "gn:dem":392,
    "gn:feature_class":"P",
    "gn:feature_code":"PPL",
    "gn:name":"Rod\u00edtis",
    "gn:population":0,
    "gn:timezone":"Europe/Athens",
    "iso:country":"GR",
    "name:ell_x_preferred":[
        "Rod\u00edtis"
    ],
    "name:ell_x_variant":[
        "\u03a1\u03bf\u03b4\u03af\u03c4\u03b7\u03c2"
    ],
    "name:und_x_variant":[
        "Haj\u00ed-Omurl\u00fa",
        "Rodh\u00edtis"
    ],
    "wof:name":"Roditis",
    "wof:placetype":"locality"
},
  "geometry": {"coordinates":[21.93845,40.26823],"type":"Point"}
}