{
  "type": "Feature",
  "properties": {
    "gn:admin1_code":"ESYE22",
    "gn:admin2_code":"28.0",
    "gn:admin3_code":"9116",
    "gn:asciiname":"Neromylos",
    "gn:country_code":"GR",
    "gn:dem":12,
    "gn:feature_class":"P",
    "gn:feature_code":"PPL",
    "gn:name":"Ner\u00f3mylos",
    "gn:population":61,
    "gn:timezone":"Europe/Athens",
    "iso:country":"GR",
    "name:ell_x_preferred":[
        "\u039d\u03b5\u03c1\u03cc\u03bc\u03c5\u03bb\u03bf\u03c2"
    ],
    "name:eng_x_preferred":[
        "Neromylos"
    ],
    "name:und_x_variant":[
        "Neromilos"
    ],
    "wof:name":"Neromylos",
    "wof:placetype":"locality",
    "wof:population":61
},
  "geometry": {"coordinates":[20.83785,37.82697],"type":"Point"}
}