{
  "type": "Feature",
  "properties": {
    "gn:admin1_code":"ESYE43",
    "gn:admin2_code":"43.0",
    "gn:admin3_code":"9321",
    "gn:asciiname":"Tsagkariakos",
    "gn:country_code":"GR",
    "gn:dem":685,
    "gn:feature_class":"P",
    "gn:feature_code":"PPL",
    "gn:name":"Tsagkari\u00e1kos",
    "gn:population":0,
    "gn:timezone":"Europe/Athens",
    "iso:country":"GR",
    "name:ell_x_preferred":[
        "Tsagkari\u00e1kos"
    ],
    "name:ell_x_variant":[
        "\u03a4\u03c3\u03b1\u03b3\u03ba\u03b1\u03c1\u03b9\u03ac\u03ba\u03bf\u03c2"
    ],
    "name:und_x_variant":[
        "Zagari\u00e1ko",
        "Zangari\u00e1ko",
        "Tsangari\u00e1kos"
    ],
    "wof:name":"Tsagkariakos",
    "wof:placetype":"locality"
},
  "geometry": {"coordinates":[23.77807,35.31856],"type":"Point"}
}