{
  "type": "Feature",
  "properties": {
    "gn:admin1_code":"ESYE22",
    "gn:admin2_code":"27.0",
    "gn:admin3_code":"9120",
    "gn:asciiname":"Kontogenada",
    "gn:country_code":"GR",
    "gn:dem":241,
    "gn:feature_class":"P",
    "gn:feature_code":"PPL",
    "gn:name":"Kontogen\u00e1da",
    "gn:population":0,
    "gn:timezone":"Europe/Athens",
    "iso:country":"GR",
    "name:ell_x_preferred":[
        "Kontogen\u00e1da"
    ],
    "name:ell_x_variant":[
        "\u039a\u03bf\u03bd\u03c4\u03bf\u03b3\u03b5\u03bd\u03ac\u03b4\u03b1"
    ],
    "name:und_x_variant":[
        "Kondoyen\u00e1dha"
    ],
    "wof:name":"Kontogenada",
    "wof:placetype":"locality"
},
  "geometry": {"coordinates":[20.39608,38.25047],"type":"Point"}
}