{
  "type": "Feature",
  "properties": {
    "gn:gn_country":"GR",
    "gn:gn_fcode":"ADM3",
    "gn:gn_pop":12514,
    "gn:population":12514,
    "iso:country":"GR",
    "name:ell_x_preferred":[
        "\u03a0\u03ac\u03c1\u03bf\u03c5"
    ],
    "name:ell_x_variant":[
        "\u03a0\u03ac\u03c1\u03bf\u03c2"
    ],
    "qs_pg:aaroncc":"GR",
    "qs_pg:gn_country":"GR",
    "qs_pg:gn_fcode":"ADM3",
    "qs_pg:gn_pop":12514,
    "qs_pg:name":"Dimos Paros",
    "qs_pg:photos_9r":0,
    "qs_pg:photos_sr":0,
    "qs_pg:pop_sr":6,
    "qs_pg:qs_pg_placetype":"localadmin",
    "wof:name":"Dimos Paros",
    "wof:placetype":"localadmin",
    "wof:population":12514
},
  "geometry": {"coordinates":[25.19213,37.05929],"type":"Point"}
}