{
  "type": "Feature",
  "properties": {
    "gn:admin1_code":"ESYE41",
    "gn:admin2_code":"51.0",
    "gn:admin3_code":"9261",
    "gn:asciiname":"Ampelikon",
    "gn:cc2":"GR",
    "gn:country_code":"GR",
    "gn:dem":371,
    "gn:feature_class":"P",
    "gn:feature_code":"PPL",
    "gn:name":"Ampelik\u00f3n",
    "gn:population":0,
    "gn:timezone":"Europe/Athens",
    "iso:country":"GR",
    "name:ell_x_preferred":[
        "\u0391\u03bc\u03c0\u03b5\u03bb\u03b9\u03ba\u03cc"
    ],
    "name:ell_x_variant":[
        "\u0391\u03bc\u03c0\u03b5\u03bb\u03b9\u03ba\u03cc\u03bd"
    ],
    "name:eng_x_preferred":[
        "Ampeliko"
    ],
    "name:und_x_variant":[
        "Ambelik\u00f3",
        "Ambelik\u00f3n",
        "Ampelik\u00f3n"
    ],
    "wof:name":"Ampelikon",
    "wof:placetype":"locality"
},
  "geometry": {"coordinates":[26.31306,39.05737],"type":"Point"}
}