{
  "type": "Feature",
  "properties": {
    "gn:gn_country":"GR",
    "gn:gn_fcode":"PPL",
    "gn:gn_pop":63,
    "gn:population":20,
    "iso:country":"GR",
    "name:ell_x_preferred":[
        "\u039c\u03b1\u03c5\u03c1\u03bf\u03b2\u03bf\u03cd\u03bd\u03b9"
    ],
    "name:ell_x_variant":[
        "\u039c\u03b1\u03c5\u03c1\u03bf\u03b2\u03bf\u03cd\u03bd\u03b9\u03bf\u03bd"
    ],
    "name:eng_x_preferred":[
        "Mavrovouni"
    ],
    "name:unk_x_variant":[
        "Mavrovo\u00fani"
    ],
    "qs_pg:aaroncc":"GR",
    "qs_pg:gn_country":"GR",
    "qs_pg:gn_fcode":"PPL",
    "qs_pg:gn_pop":63,
    "qs_pg:name":"Mavrovo\u00fanion",
    "qs_pg:photos_9r":0,
    "qs_pg:photos_sr":0,
    "qs_pg:pop_sr":1,
    "qs_pg:qs_pg_placetype":"locality",
    "wof:name":"Mavrovo\u00fanion",
    "wof:placetype":"locality",
    "wof:population":20
},
  "geometry": {"coordinates":[20.61639,39.95],"type":"Point"}
}