{
  "type": "Feature",
  "properties": {
    "gn:country":"GR",
    "gn:fcode":"PPL",
    "gn:population":93,
    "iso:country":"GR",
    "name:ell_x_preferred":[
        "\u03a7\u03b1\u03ca\u03b4\u03b5\u03bc\u03ad\u03bd\u03b7"
    ],
    "name:und_x_variant":[
        "Tolp\u00edtsa"
    ],
    "qs_pg:aaroncc":"GR",
    "qs_pg:gn_country":"GR",
    "qs_pg:gn_fcode":"PPL",
    "qs_pg:gn_pop":93,
    "qs_pg:name":"Cha\u00efdem\u00e9ni",
    "qs_pg:photos_9r":0,
    "qs_pg:photos_sr":0,
    "qs_pg:pop_sr":1,
    "qs_pg:qs_pg_placetype":"locality",
    "wof:name":"Cha\u00efdem\u00e9ni",
    "wof:placetype":"locality",
    "wof:population":93
},
  "geometry": {"coordinates":[21.76778,39.61583],"type":"Point"}
}