{
  "type": "Feature",
  "properties": {
    "gn:population":2454,
    "iso:country":"GR",
    "name:bul_x_preferred":[
        "\u041f\u0435\u0440\u0438\u0441\u0442\u0430\u0441\u0438"
    ],
    "name:dut_x_preferred":[
        "Peristasi"
    ],
    "name:ell_x_preferred":[
        "\u03a0\u03b5\u03c1\u03af\u03c3\u03c4\u03b1\u03c3\u03b9\u03c2"
    ],
    "name:ell_x_variant":[
        "\u03a0\u03b5\u03c1\u03af\u03c3\u03c4\u03b1\u03c3\u03b7"
    ],
    "name:eng_x_preferred":[
        "Peristasi"
    ],
    "name:gre_x_preferred":[
        "\u03a0\u03b5\u03c1\u03af\u03c3\u03c4\u03b1\u03c3\u03b7 \u03a0\u03b9\u03b5\u03c1\u03af\u03b1\u03c2"
    ],
    "name:nno_x_preferred":[
        "Per\u00edstasi"
    ],
    "name:unk_x_variant":[
        "Per\u00edstasi"
    ],
    "qs:a0":"Greece",
    "qs:a1":"*\u039a\u0395\u039d\u03a4\u03a1\u0399\u039a\u0397 \u039c\u0391\u039a\u0395\u0394\u039f\u039d\u0399\u0391",
    "qs:a1_alt":"KENTRIKH MAKEDONIA",
    "qs:a1r":"0",
    "qs:a2_alt":"PIERIA",
    "qs:adm0":"Greece",
    "qs:la_lc":"*",
    "qs:level":"locality",
    "qs:loc":"\u03a0\u0395\u03a1\u0399\u03a3\u03a4\u0391\u03a3\u0399\u03a3",
    "qs:loc_alt":"PERISTASIS",
    "qs:pop":0,
    "qs:type":"buffered point",
    "wof:name":"\u03a0\u0395\u03a1\u0399\u03a3\u03a4\u0391\u03a3\u0399\u03a3",
    "wof:placetype":"locality",
    "wof:population":2454
},
  "geometry": {"coordinates":[22.544348,40.273739],"type":"Point"}
}