{
  "type": "Feature",
  "properties": {
    "gn:admin1_code":"ESYE43",
    "gn:admin2_code":"45.0",
    "gn:admin3_code":"9308",
    "gn:asciiname":"Kokkinos Pyrgos",
    "gn:country_code":"GR",
    "gn:dem":9,
    "gn:feature_class":"P",
    "gn:feature_code":"PPL",
    "gn:name":"K\u00f3kkinos P\u00fdrgos",
    "gn:population":426,
    "gn:timezone":"Europe/Athens",
    "iso:country":"GR",
    "name:ell_x_preferred":[
        "\u039a\u03cc\u03ba\u03ba\u03b9\u03bd\u03bf\u03c2 \u03a0\u03cd\u03c1\u03b3\u03bf\u03c2"
    ],
    "name:eng_x_preferred":[
        "Kokkinos Pyrgos"
    ],
    "name:und_x_variant":[
        "K\u00f3kkinos P\u00fdrgos",
        "K\u00f3kkinos P\u00edrgos"
    ],
    "wof:name":"Kokkinos Pyrgos",
    "wof:placetype":"locality",
    "wof:population":426
},
  "geometry": {"coordinates":[24.73899,35.08403],"type":"Point"}
}