{
  "type": "Feature",
  "properties": {
    "gn:admin1_code":"ESYE24",
    "gn:admin2_code":"32.0",
    "gn:admin3_code":"9165",
    "gn:asciiname":"Agios Konstantinos",
    "gn:country_code":"GR",
    "gn:dem":182,
    "gn:feature_class":"P",
    "gn:feature_code":"PPL",
    "gn:name":"\u00c1gios Konstant\u00ednos",
    "gn:population":0,
    "gn:timezone":"Europe/Athens",
    "iso:country":"GR",
    "name:ceb_x_preferred":[
        "Agios Konstantinos"
    ],
    "name:ell_x_preferred":[
        "\u00c1gios Konstant\u00ednos"
    ],
    "name:ell_x_variant":[
        "\u0386\u03b3\u03b9\u03bf\u03c2 \u039a\u03c9\u03bd\u03c3\u03c4\u03b1\u03bd\u03c4\u03af\u03bd\u03bf\u03c2"
    ],
    "name:fin_x_preferred":[
        "\u00c1gios Konstant\u00ednos"
    ],
    "name:ita_x_preferred":[
        "Agios Konstantinos"
    ],
    "name:rus_x_preferred":[
        "\u0410\u0439\u043e\u0441-\u041a\u043e\u043d\u0441\u0442\u0430\u043d\u0434\u0438\u043d\u043e\u0441"
    ],
    "name:swe_x_preferred":[
        "Agios Konstantinos"
    ],
    "name:und_x_variant":[
        "Sergo\u00fani",
        "\u00c1yios Konstand\u00ednos"
    ],
    "wof:name":"Agios Konstantinos",
    "wof:placetype":"locality"
},
  "geometry": {"coordinates":[22.39206,38.50142],"type":"Point"}
}