{
  "type": "Feature",
  "properties": {
    "gn:admin1_code":"ESYE24",
    "gn:admin2_code":"30.0",
    "gn:admin3_code":"9157",
    "gn:asciiname":"Aroniada",
    "gn:country_code":"GR",
    "gn:dem":471,
    "gn:feature_class":"P",
    "gn:feature_code":"PPL",
    "gn:name":"Aroni\u00e1da",
    "gn:population":1,
    "gn:timezone":"Europe/Athens",
    "iso:country":"GR",
    "name:ell_x_preferred":[
        "\u0391\u03c1\u03c9\u03bd\u03b9\u03ac\u03b4\u03b1"
    ],
    "wof:name":"Aroniada",
    "wof:placetype":"locality",
    "wof:population":1
},
  "geometry": {"coordinates":[21.6992,38.9541],"type":"Point"}
}