{
  "type": "Feature",
  "properties": {
    "gn:admin1_code":"ESYE24",
    "gn:admin2_code":"34.0",
    "gn:admin3_code":"9151",
    "gn:asciiname":"Panagia",
    "gn:country_code":"GR",
    "gn:dem":14,
    "gn:feature_class":"P",
    "gn:feature_code":"PPL",
    "gn:name":"Panag\u00eda",
    "gn:population":0,
    "gn:timezone":"Europe/Athens",
    "iso:country":"GR",
    "name:cat_x_preferred":[
        "Panagia"
    ],
    "name:deu_x_preferred":[
        "Panagia"
    ],
    "name:ell_x_preferred":[
        "Panag\u00eda"
    ],
    "name:ell_x_variant":[
        "\u03a0\u03b1\u03bd\u03b1\u03b3\u03af\u03b1"
    ],
    "name:ita_x_preferred":[
        "Panaghia"
    ],
    "name:jpn_x_preferred":[
        "\u30d1\u30ca\u30ae\u30a2"
    ],
    "name:rus_x_preferred":[
        "\u041f\u0430\u043d\u0430\u0433\u0438\u044f"
    ],
    "name:spa_x_preferred":[
        "Panagia"
    ],
    "name:und_x_variant":[
        "Panay\u00eda"
    ],
    "name:vie_x_preferred":[
        "Panagia"
    ],
    "wof:name":"Panagia",
    "wof:placetype":"locality"
},
  "geometry": {"coordinates":[24.26131,38.01736],"type":"Point"}
}