{
  "type": "Feature",
  "properties": {
    "gn:admin1_code":"ESYE14",
    "gn:admin2_code":"21.0",
    "gn:admin3_code":"9100",
    "gn:asciiname":"Rachoula",
    "gn:country_code":"GR",
    "gn:dem":119,
    "gn:feature_class":"P",
    "gn:feature_code":"PPL",
    "gn:name":"Racho\u00fala",
    "gn:population":472,
    "gn:timezone":"Europe/Athens",
    "iso:country":"GR",
    "name:ell_x_preferred":[
        "\u03a1\u03b1\u03c7\u03bf\u03cd\u03bb\u03b1"
    ],
    "name:eng_x_preferred":[
        "Rachoula"
    ],
    "name:und_x_variant":[
        "Thoma\u00edon",
        "Tursul\u00e1r",
        "Thoma\u1e2f",
        "Ner\u00e1\u00efdha",
        "Racho\u00fala"
    ],
    "wof:name":"Rachoula",
    "wof:placetype":"locality",
    "wof:population":472
},
  "geometry": {"coordinates":[22.29572000000001,39.60781],"type":"Point"}
}