{
  "type": "Feature",
  "properties": {
    "gn:admin1_code":"ESYE22",
    "gn:admin2_code":"25.0",
    "gn:admin3_code":"9119",
    "gn:asciiname":"Manesatika",
    "gn:country_code":"GR",
    "gn:dem":174,
    "gn:feature_class":"P",
    "gn:feature_code":"PPL",
    "gn:name":"Manes\u00e1tika",
    "gn:population":0,
    "gn:timezone":"Europe/Athens",
    "iso:country":"GR",
    "name:ell_x_preferred":[
        "Manes\u00e1tika"
    ],
    "name:ell_x_variant":[
        "\u039c\u03b1\u03bd\u03b5\u03c3\u03ac\u03c4\u03b9\u03ba\u03b1"
    ],
    "wof:name":"Manesatika",
    "wof:placetype":"locality"
},
  "geometry": {"coordinates":[20.14353,39.21783],"type":"Point"}
}