{
  "type": "Feature",
  "properties": {
    "gn:admin1_code":"ESYE12",
    "gn:admin2_code":"15.0",
    "gn:admin3_code":"9057",
    "gn:asciiname":"Mpoulamatsia",
    "gn:country_code":"GR",
    "gn:dem":49,
    "gn:feature_class":"P",
    "gn:feature_code":"PPL",
    "gn:name":"Mpoulam\u00e1tsia",
    "gn:population":1,
    "gn:timezone":"Europe/Athens",
    "iso:country":"GR",
    "name:ell_x_preferred":[
        "\u039c\u03c0\u03bf\u03c5\u03bb\u03b1\u03bc\u03ac\u03c4\u03c3\u03b9\u03b1"
    ],
    "name:eng_x_preferred":[
        "Mpoulamatsia"
    ],
    "wof:name":"Mpoulamatsia",
    "wof:placetype":"locality",
    "wof:population":1
},
  "geometry": {"coordinates":[23.42653,39.9693],"type":"Point"}
}