{
  "type": "Feature",
  "properties": {
    "gn:admin1_code":"ESYE13",
    "gn:admin2_code":"11.0",
    "gn:admin3_code":"9067",
    "gn:asciiname":"Olimbias",
    "gn:cc2":"GR",
    "gn:country_code":"GR",
    "gn:dem":665,
    "gn:feature_class":"P",
    "gn:feature_code":"PPL",
    "gn:name":"Olimbi\u00e1s",
    "gn:population":0,
    "gn:timezone":"Europe/Athens",
    "iso:country":"GR",
    "name:eng_x_preferred":[
        "Olympiada"
    ],
    "name:und_x_variant":[
        "Rak\u00edta",
        "Olimbi\u00e1s"
    ],
    "wof:name":"Olimbias",
    "wof:placetype":"locality"
},
  "geometry": {"coordinates":[21.60045,40.57049],"type":"Point"}
}