{
  "type": "Feature",
  "properties": {
    "gn:country":"GR",
    "gn:fcode":"PPL",
    "gn:population":515,
    "iso:country":"GR",
    "name:ara_x_preferred":[
        "\u062d\u062c\u0631 \u0628\u0631\u064a\u0641\u064a\u0632\u0627"
    ],
    "name:ceb_x_preferred":[
        "P\u00e9tra"
    ],
    "name:deu_x_preferred":[
        "Petra Prevezas"
    ],
    "name:ell_x_preferred":[
        "P\u00e9tra"
    ],
    "name:ell_x_variant":[
        "\u03a0\u03ad\u03c4\u03c1\u03b1",
        "\u03a0\u03ad\u03c4\u03c1\u03b1 \u03a0\u03c1\u03ad\u03b2\u03b5\u03b6\u03b1\u03c2"
    ],
    "name:eng_x_preferred":[
        "Petra Prevezas"
    ],
    "name:fra_x_preferred":[
        "Petra Prevezas"
    ],
    "name:fra_x_variant":[
        "P\u00e9tra"
    ],
    "name:gle_x_preferred":[
        "Petra"
    ],
    "name:ita_x_preferred":[
        "Petra Prevezas"
    ],
    "name:nld_x_preferred":[
        "Petra Prevezas"
    ],
    "name:rus_x_preferred":[
        "\u041f\u0435\u0442\u0440\u0430 \u041f\u0440\u0435\u0432\u0435\u0437\u044b"
    ],
    "name:spa_x_preferred":[
        "Petra Prevezas"
    ],
    "name:sqi_x_preferred":[
        "Petra"
    ],
    "name:swe_x_preferred":[
        "P\u00e9tra"
    ],
    "name:ukr_x_preferred":[
        "\u041f\u0435\u0442\u0440\u0430"
    ],
    "qs_pg:aaroncc":"GR",
    "qs_pg:gn_country":"GR",
    "qs_pg:gn_fcode":"PPL",
    "qs_pg:gn_pop":515,
    "qs_pg:name":"Petra",
    "qs_pg:name_adm0":"\u0395\u03bb\u03bb\u03ac\u03b4\u03b1",
    "qs_pg:name_adm1":"Epirus and Western Macedonia",
    "qs_pg:photos_9r":0,
    "qs_pg:photos_sr":0,
    "qs_pg:pop_sr":2,
    "qs_pg:qs_pg_placetype":"locality",
    "qs_pg:qs_pg_placetype_gp":"Town",
    "qs_pg:woe_adm0":23424833,
    "woe:adm0_id":23424833,
    "woe:name_adm0":"\u0395\u03bb\u03bb\u03ac\u03b4\u03b1",
    "woe:name_adm1":"Epirus and Western Macedonia",
    "woe:placetype":"Town",
    "wof:name":"Petra",
    "wof:placetype":"locality",
    "wof:population":515
},
  "geometry": {"coordinates":[20.81583,39.15694],"type":"Point"}
}