{
  "type": "Feature",
  "properties": {
    "gn:admin1_code":"ESYE42",
    "gn:admin2_code":"47.0",
    "gn:admin3_code":"9298",
    "gn:asciiname":"Mikro Chorio",
    "gn:country_code":"GR",
    "gn:dem":246,
    "gn:feature_class":"P",
    "gn:feature_code":"PPL",
    "gn:name":"Mikr\u00f3 Chor\u00edo",
    "gn:population":0,
    "gn:timezone":"Europe/Athens",
    "iso:country":"GR",
    "name:ell_x_preferred":[
        "Mikr\u00f3 Chor\u00edo"
    ],
    "name:ell_x_variant":[
        "\u039c\u03b9\u03ba\u03c1\u03cc \u03a7\u03c9\u03c1\u03af\u03bf",
        "\u039c\u03b9\u03ba\u03c1\u03cc\u03bd \u03a7\u03c9\u03c1\u03af\u03bf\u03bd"
    ],
    "name:und_x_variant":[
        "Mikr\u00f3n Khor\u00edon",
        "Microcorio",
        "Mikr\u00f3 Khori\u00f3",
        "Mikr\u00f3n Chor\u00edon"
    ],
    "wof:name":"Mikro Chorio",
    "wof:placetype":"locality"
},
  "geometry": {"coordinates":[27.37062,36.4231],"type":"Point"}
}