{
  "type": "Feature",
  "properties": {
    "gn:admin1_code":"ESYE25",
    "gn:admin2_code":"42.0",
    "gn:admin3_code":"9248",
    "gn:asciiname":"Mesa Chora",
    "gn:country_code":"GR",
    "gn:dem":139,
    "gn:feature_class":"P",
    "gn:feature_code":"PPL",
    "gn:name":"M\u00e9sa Ch\u00f3ra",
    "gn:population":25,
    "gn:timezone":"Europe/Athens",
    "iso:country":"GR",
    "name:ell_x_historical":[
        "\u039c\u03ad\u03c3\u03b1 \u039d\u03cd\u03bc\u03c6\u03b7"
    ],
    "name:ell_x_preferred":[
        "\u039c\u03ad\u03c3\u03b1 \u03a7\u03ce\u03c1\u03b1"
    ],
    "name:ell_x_variant":[
        "\u039c\u03ad\u03c3\u03b1 \u039d\u03cd\u03bc\u03c6\u03b7"
    ],
    "name:eng_x_preferred":[
        "Mesa Chora"
    ],
    "name:und_x_variant":[
        "Eso N\u00edmfi",
        "\u00c9so N\u00edfi",
        "M\u00e9sa Kh\u00f3ra"
    ],
    "wof:name":"Mesa Chora",
    "wof:placetype":"locality",
    "wof:population":25
},
  "geometry": {"coordinates":[22.46661,36.56257],"type":"Point"}
}