{
  "type": "Feature",
  "properties": {
    "gn:admin1_code":"ESYE41",
    "gn:admin2_code":"51.0",
    "gn:admin3_code":"9261",
    "gn:asciiname":"Tsafi",
    "gn:country_code":"GR",
    "gn:dem":13,
    "gn:feature_class":"P",
    "gn:feature_code":"PPL",
    "gn:name":"Ts\u00e1fi",
    "gn:population":9,
    "gn:timezone":"Europe/Athens",
    "iso:country":"GR",
    "name:ell_x_preferred":[
        "\u03a4\u03c3\u03ac\u03c6\u03b9"
    ],
    "wof:name":"Tsafi",
    "wof:placetype":"locality",
    "wof:population":9
},
  "geometry": {"coordinates":[26.49559,38.97743],"type":"Point"}
}