{
  "type": "Feature",
  "properties": {
    "gn:admin1_code":"ESYE25",
    "gn:admin2_code":"40.0",
    "gn:admin3_code":"9255",
    "gn:asciiname":"Strefi",
    "gn:country_code":"GR",
    "gn:dem":239,
    "gn:feature_class":"P",
    "gn:feature_code":"PPL",
    "gn:name":"Str\u00e9fi",
    "gn:population":0,
    "gn:timezone":"Europe/Athens",
    "iso:country":"GR",
    "name:ell_x_preferred":[
        "\u03a3\u03c4\u03c1\u03ad\u03c6\u03b9"
    ],
    "name:ell_x_variant":[
        "\u03a3\u03c4\u03c1\u03ad\u03c6\u03b9\u03bf\u03bd"
    ],
    "name:und_x_variant":[
        "Str\u00e9fi",
        "Str\u00e9fion"
    ],
    "wof:name":"Strefi",
    "wof:placetype":"locality"
},
  "geometry": {"coordinates":[21.88901,37.05351],"type":"Point"}
}