{
  "type": "Feature",
  "properties": {
    "gn:country":"GR",
    "gn:fcode":"PPL",
    "gn:population":1965,
    "iso:country":"GR",
    "name:ell_x_preferred":[
        "\u039a\u03b1\u03c1\u03c5\u03ce\u03c4\u03b9\u03c3\u03c3\u03b1"
    ],
    "name:und_x_variant":[
        "Kari\u00f3tissa"
    ],
    "qs_pg:aaroncc":"GR",
    "qs_pg:gn_country":"GR",
    "qs_pg:gn_fcode":"PPL",
    "qs_pg:gn_pop":1965,
    "qs_pg:name":"Kary\u00f3tissa",
    "qs_pg:photos_9r":0,
    "qs_pg:photos_sr":0,
    "qs_pg:pop_sr":3,
    "qs_pg:qs_pg_placetype":"locality",
    "wof:name":"Kary\u00f3tissa",
    "wof:placetype":"locality",
    "wof:population":1965
},
  "geometry": {"coordinates":[22.30528,40.76833],"type":"Point"}
}