{
  "type": "Feature",
  "properties": {
    "gn:admin1_code":"ESYE42",
    "gn:admin2_code":"49.0",
    "gn:admin3_code":"9301",
    "gn:asciiname":"Agios Romanos",
    "gn:country_code":"GR",
    "gn:dem":10,
    "gn:feature_class":"P",
    "gn:feature_code":"PPL",
    "gn:name":"Agios Romanos",
    "gn:population":0,
    "gn:timezone":"Europe/Athens",
    "iso:country":"GR",
    "wof:name":"Agios Romanos",
    "wof:placetype":"locality"
},
  "geometry": {"coordinates":[25.11286,37.57166],"type":"Point"}
}