{
  "type": "Feature",
  "properties": {
    "gn:admin1_code":"ESYE22",
    "gn:admin2_code":"28.0",
    "gn:admin3_code":"9116",
    "gn:asciiname":"Koiliomenos",
    "gn:country_code":"GR",
    "gn:dem":480,
    "gn:elevation":"480.0",
    "gn:feature_class":"P",
    "gn:feature_code":"PPL",
    "gn:name":"Koiliom\u00e9nos",
    "gn:population":391,
    "gn:timezone":"Europe/Athens",
    "iso:country":"GR",
    "name:ceb_x_preferred":[
        "Koiliom\u00e9nos"
    ],
    "name:ell_x_preferred":[
        "\u039a\u03bf\u03b9\u03bb\u03b9\u03c9\u03bc\u03ad\u03bd\u03bf"
    ],
    "name:ell_x_variant":[
        "\u039a\u03bf\u03b9\u03bb\u03b9\u03c9\u03bc\u03ad\u03bd\u03bf\u03c2",
        "\u0386\u03b3\u03b9\u03bf\u03c2 \u039d\u03b9\u03ba\u03cc\u03bb\u03b1\u03bf\u03c2",
        "\u039a\u03bf\u03b9\u03bb\u03b9\u03c9\u03bc\u03ad\u03bd\u03bf \u0396\u03b1\u03ba\u03cd\u03bd\u03b8\u03bf\u03c5"
    ],
    "name:eng_x_preferred":[
        "Koiliomenos"
    ],
    "name:rus_x_preferred":[
        "\u0410\u0433\u0438\u043e\u0441-\u041d\u0438\u043a\u043e\u043b\u0430\u043e\u0441"
    ],
    "name:swe_x_preferred":[
        "Koiliom\u00e9nos"
    ],
    "name:und_x_variant":[
        "\u00c1yios Nik\u00f3laos",
        "Koiliom\u00e9nos",
        "Koiliom\u00e9no",
        "\u00c1gios Nik\u00f3laos"
    ],
    "wof:name":"Koiliomenos",
    "wof:placetype":"locality",
    "wof:population":391
},
  "geometry": {"coordinates":[20.77369,37.74717],"type":"Point"}
}