{
  "type": "Feature",
  "properties": {
    "gn:admin1_code":"ESYE23",
    "gn:admin2_code":"38.0",
    "gn:admin3_code":"9130",
    "gn:asciiname":"Kato Potamia",
    "gn:country_code":"GR",
    "gn:dem":727,
    "gn:feature_class":"P",
    "gn:feature_code":"PPL",
    "gn:name":"K\u00e1to Potami\u00e1",
    "gn:population":0,
    "gn:timezone":"Europe/Athens",
    "iso:country":"GR",
    "name:ell_x_preferred":[
        "K\u00e1to Potami\u00e1"
    ],
    "name:ell_x_variant":[
        "\u039a\u03ac\u03c4\u03c9 \u03a0\u03bf\u03c4\u03b1\u03bc\u03b9\u03ac"
    ],
    "wof:name":"Kato Potamia",
    "wof:placetype":"locality"
},
  "geometry": {"coordinates":[22.23644,38.09981],"type":"Point"}
}