{
  "type": "Feature",
  "properties": {
    "gn:admin1_code":"ESYE23",
    "gn:admin2_code":"31.0",
    "gn:admin3_code":"9125",
    "gn:asciiname":"Ampeli",
    "gn:country_code":"GR",
    "gn:dem":655,
    "gn:feature_class":"P",
    "gn:feature_code":"PPL",
    "gn:name":"Amp\u00e9li",
    "gn:population":0,
    "gn:timezone":"Europe/Athens",
    "iso:country":"GR",
    "name:ell_x_preferred":[
        "Amp\u00e9li"
    ],
    "name:ell_x_variant":[
        "\u0391\u03bc\u03c0\u03ad\u03bb\u03b9",
        "Amp\u00e9lion",
        "\u0391\u03bc\u03c0\u03ad\u03bb\u03b9\u03bf\u03bd"
    ],
    "name:und_x_variant":[
        "Amb\u00e9li",
        "Amb\u00e9lion"
    ],
    "wof:name":"Ampeli",
    "wof:placetype":"locality"
},
  "geometry": {"coordinates":[21.43728,38.9765],"type":"Point"}
}