{
  "type": "Feature",
  "properties": {
    "gn:admin1_code":"ESYE43",
    "gn:admin2_code":"43.0",
    "gn:admin3_code":"9325",
    "gn:asciiname":"Skiadhi",
    "gn:country_code":"GR",
    "gn:dem":87,
    "gn:feature_class":"P",
    "gn:feature_code":"PPL",
    "gn:name":"Ski\u00e1dhi",
    "gn:population":0,
    "gn:timezone":"Europe/Athens",
    "iso:country":"GR",
    "wof:name":"Skiadhi",
    "wof:placetype":"locality"
},
  "geometry": {"coordinates":[24.05,35.51667],"type":"Point"}
}