{
  "type": "Feature",
  "properties": {
    "iso:country":"GR",
    "name:bul_x_preferred":[
        "\u041a\u0430\u0442\u043e \u041f\u0435\u0434\u0438\u043d\u0430"
    ],
    "name:dut_x_preferred":[
        "Kato Pedina"
    ],
    "name:eng_x_preferred":[
        "Kato Pedina"
    ],
    "name:gre_x_preferred":[
        "\u039a\u03ac\u03c4\u03c9 \u03a0\u03b5\u03b4\u03b9\u03bd\u03ac \u0399\u03c9\u03b1\u03bd\u03bd\u03af\u03bd\u03c9\u03bd"
    ],
    "qs_pg:aaroncc":"GR",
    "qs_pg:name":"Kato Pedhina",
    "qs_pg:name_adm0":"\u0395\u03bb\u03bb\u03ac\u03b4\u03b1",
    "qs_pg:name_adm1":"Epirus and Western Macedonia",
    "qs_pg:photos":9,
    "qs_pg:photos_1k":2,
    "qs_pg:photos_9k":1,
    "qs_pg:photos_9r":1,
    "qs_pg:photos_all":9,
    "qs_pg:photos_sr":1,
    "qs_pg:pop_sr":0,
    "qs_pg:qs_pg_placetype":"locality",
    "qs_pg:qs_pg_placetype_gp":"Town",
    "qs_pg:woe_adm0":23424833,
    "woe:adm0_id":23424833,
    "woe:name_adm0":"\u0395\u03bb\u03bb\u03ac\u03b4\u03b1",
    "woe:name_adm1":"Epirus and Western Macedonia",
    "woe:placetype":"Town",
    "wof:name":"Kato Pedhina",
    "wof:placetype":"locality"
},
  "geometry": {"coordinates":[20.679016,39.8803],"type":"Point"}
}