{
  "type": "Feature",
  "properties": {
    "iso:country":"GR",
    "name:arz_x_preferred":[
        "\u0643\u0627\u062a\u0648 \u067e\u064a\u062f\u064a\u0646\u0627"
    ],
    "name:bul_x_preferred":[
        "\u041a\u0430\u0442\u043e \u041f\u0435\u0434\u0438\u043d\u0430"
    ],
    "name:ell_x_preferred":[
        "\u039a\u03ac\u03c4\u03c9 \u03a0\u03b5\u03b4\u03b9\u03bd\u03ac \u0399\u03c9\u03b1\u03bd\u03bd\u03af\u03bd\u03c9\u03bd"
    ],
    "name:eng_x_preferred":[
        "Kato Pedina"
    ],
    "name:fra_x_preferred":[
        "K\u00e1to Pedin\u00e1"
    ],
    "name:mkd_x_preferred":[
        "\u0414\u043e\u043b\u043d\u0430 \u0421\u0442\u0443\u0434\u0435\u043d\u0430"
    ],
    "name:nld_x_preferred":[
        "Kato Pedina"
    ],
    "name:rus_x_preferred":[
        "\u041a\u0430\u0442\u043e-\u041f\u0435\u0434\u0438\u043d\u0430"
    ],
    "qs_pg:aaroncc":"GR",
    "qs_pg:name":"Kato Pedhina",
    "qs_pg:name_adm0":"\u0395\u03bb\u03bb\u03ac\u03b4\u03b1",
    "qs_pg:name_adm1":"Epirus and Western Macedonia",
    "qs_pg:photos":9,
    "qs_pg:photos_1k":2,
    "qs_pg:photos_9k":1,
    "qs_pg:photos_9r":1,
    "qs_pg:photos_all":9,
    "qs_pg:photos_sr":1,
    "qs_pg:pop_sr":0,
    "qs_pg:qs_pg_placetype":"locality",
    "qs_pg:qs_pg_placetype_gp":"Town",
    "qs_pg:woe_adm0":23424833,
    "woe:adm0_id":23424833,
    "woe:name_adm0":"\u0395\u03bb\u03bb\u03ac\u03b4\u03b1",
    "woe:name_adm1":"Epirus and Western Macedonia",
    "woe:placetype":"Town",
    "wof:name":"Kato Pedhina",
    "wof:placetype":"locality"
},
  "geometry": {"coordinates":[20.679016,39.8803],"type":"Point"}
}