{
  "type": "Feature",
  "properties": {
    "gn:admin1_code":"ESYE24",
    "gn:admin2_code":"30.0",
    "gn:admin3_code":"9157",
    "gn:asciiname":"Ayios Andreas",
    "gn:country_code":"GR",
    "gn:dem":986,
    "gn:feature_class":"P",
    "gn:feature_code":"PPL",
    "gn:name":"\u00c1yios Andr\u00e9as",
    "gn:population":12,
    "gn:timezone":"Europe/Athens",
    "iso:country":"GR",
    "name:ell_x_preferred":[
        "\u0386\u03b3\u03b9\u03bf\u03c2 \u0391\u03bd\u03b4\u03c1\u03ad\u03b1\u03c2"
    ],
    "name:eng_x_preferred":[
        "Agios Andreas"
    ],
    "name:und_x_variant":[
        "\u00c1yios Andhr\u00e9as",
        "\u00c1yios Andr\u00e9as"
    ],
    "wof:name":"Ayios Andreas",
    "wof:placetype":"locality",
    "wof:population":12
},
  "geometry": {"coordinates":[21.78876,38.87386],"type":"Point"}
}