{
  "type": "Feature",
  "properties": {
    "gn:country":"GR",
    "gn:fcode":"PPL",
    "gn:population":164,
    "iso:country":"GR",
    "name:ell_x_preferred":[
        "Ner\u00e1ida"
    ],
    "name:ell_x_variant":[
        "\u039d\u03b5\u03c1\u03ac\u03b9\u03b4\u03b1"
    ],
    "name:und_x_variant":[
        "Grevenos\u00e9li"
    ],
    "qs_pg:aaroncc":"GR",
    "qs_pg:gn_country":"GR",
    "qs_pg:gn_fcode":"PPL",
    "qs_pg:gn_pop":164,
    "qs_pg:name":"Neraida",
    "qs_pg:name_adm0":"\u0395\u03bb\u03bb\u03ac\u03b4\u03b1",
    "qs_pg:name_adm1":"Epirus and Western Macedonia",
    "qs_pg:photos_9r":0,
    "qs_pg:photos_sr":0,
    "qs_pg:pop_sr":1,
    "qs_pg:qs_pg_placetype":"locality",
    "qs_pg:qs_pg_placetype_gp":"Town",
    "qs_pg:woe_adm0":23424833,
    "woe:adm0_id":23424833,
    "woe:name_adm0":"\u0395\u03bb\u03bb\u03ac\u03b4\u03b1",
    "woe:name_adm1":"Epirus and Western Macedonia",
    "woe:placetype":"Town",
    "wof:name":"Neraida",
    "wof:placetype":"locality",
    "wof:population":164
},
  "geometry": {"coordinates":[21.22861,39.44889],"type":"Point"}
}