{
  "type": "Feature",
  "properties": {
    "gn:admin1_code":"ESYE43",
    "gn:admin2_code":"45.0",
    "gn:admin3_code":"9302",
    "gn:asciiname":"Paranimfoi",
    "gn:country_code":"GR",
    "gn:dem":510,
    "gn:feature_class":"P",
    "gn:feature_code":"PPL",
    "gn:name":"Par\u00e1nimfoi",
    "gn:population":0,
    "gn:timezone":"Europe/Athens",
    "iso:country":"GR",
    "wof:name":"Paranimfoi",
    "wof:placetype":"locality"
},
  "geometry": {"coordinates":[25.12968,34.97298],"type":"Point"}
}