{
  "type": "Feature",
  "properties": {
    "gn:admin1_code":"ESYE43",
    "gn:admin2_code":"44.0",
    "gn:admin3_code":"9318",
    "gn:asciiname":"Sfakaki",
    "gn:country_code":"GR",
    "gn:dem":5,
    "gn:feature_class":"P",
    "gn:feature_code":"PPL",
    "gn:name":"Sfak\u00e1ki",
    "gn:population":792,
    "gn:timezone":"Europe/Athens",
    "iso:country":"GR",
    "name:ell_x_preferred":[
        "\u03a3\u03c6\u03b1\u03ba\u03ac\u03ba\u03b9"
    ],
    "name:eng_x_preferred":[
        "Sfakaki"
    ],
    "name:und_x_variant":[
        "Sfak\u00e1ki"
    ],
    "wof:name":"Sfakaki",
    "wof:placetype":"locality",
    "wof:population":792
},
  "geometry": {"coordinates":[24.58257,35.38132],"type":"Point"}
}