{
  "type": "Feature",
  "properties": {
    "gn:population":1426,
    "iso:country":"GR",
    "name:ara_x_preferred":[
        "\u0646\u064a \u0643\u0627\u0631\u064a\u0627\u060c \u0643\u0627\u0641\u0627\u0644\u0627"
    ],
    "name:ara_x_variant":[
        "\u0646\u064a \u0643\u0627\u0631\u064a\u0627"
    ],
    "name:ceb_x_preferred":[
        "N\u00e9a Kary\u00e1"
    ],
    "name:ell_x_preferred":[
        "\u039d\u03ad\u03b1 \u039a\u03b1\u03c1\u03c5\u03ac"
    ],
    "name:ell_x_variant":[
        "\u039d\u03ad\u03b1 \u039a\u03b1\u03c1\u03c5\u03ac \u039a\u03b1\u03b2\u03ac\u03bb\u03b1\u03c2"
    ],
    "name:eng_x_preferred":[
        "Nea Karya"
    ],
    "name:swe_x_preferred":[
        "N\u00e9a Kary\u00e1"
    ],
    "name:unk_x_variant":[
        "N\u00e9a Kari\u00e1"
    ],
    "qs:a0":"Greece",
    "qs:a1":"*\u0391\u039d\u0391\u03a4\u039f\u039b\u0399\u039a\u0397 \u039c\u0391\u039a\u0395\u0394\u039f\u039d\u0399\u0391 \u039a\u0391\u0399 \u0398\u03a1\u0391\u039a\u0397",
    "qs:a1_alt":"ANATOLIKH MAKEDONIA KAI URAKH",
    "qs:a1r":"0",
    "qs:a2_alt":"KABALA",
    "qs:adm0":"Greece",
    "qs:la_lc":"*",
    "qs:level":"locality",
    "qs:loc":"\u039d\u0395\u0391 \u039a\u0391\u03a1\u03a5\u0391",
    "qs:loc_alt":"NEA KARYA",
    "qs:pop":0,
    "qs:type":"buffered point",
    "wof:name":"\u039d\u0395\u0391 \u039a\u0391\u03a1\u03a5\u0391",
    "wof:placetype":"locality",
    "wof:population":1426
},
  "geometry": {"coordinates":[24.706928,40.90588],"type":"Point"}
}