{
  "type": "Feature",
  "properties": {
    "gn:admin1_code":"ESYE43",
    "gn:admin2_code":"43.0",
    "gn:admin3_code":"9323",
    "gn:asciiname":"Pentariana",
    "gn:country_code":"GR",
    "gn:dem":253,
    "gn:feature_class":"P",
    "gn:feature_code":"PPL",
    "gn:name":"Pentarian\u00e1",
    "gn:population":0,
    "gn:timezone":"Europe/Athens",
    "iso:country":"GR",
    "name:ell_x_preferred":[
        "Pentarian\u00e1"
    ],
    "name:ell_x_variant":[
        "\u03a0\u03b5\u03bd\u03c4\u03b1\u03c1\u03b9\u03b1\u03bd\u03ac",
        "Pendarian\u00e1"
    ],
    "wof:name":"Pentariana",
    "wof:placetype":"locality"
},
  "geometry": {"coordinates":[23.81667,35.46667],"type":"Point"}
}