{
  "type": "Feature",
  "properties": {
    "gn:admin1_code":"ESYE25",
    "gn:admin2_code":"41.0",
    "gn:admin3_code":"9239",
    "gn:asciiname":"Tourkolekas",
    "gn:country_code":"GR",
    "gn:dem":765,
    "gn:feature_class":"P",
    "gn:feature_code":"PPL",
    "gn:name":"Tourkol\u00e9kas",
    "gn:population":0,
    "gn:timezone":"Europe/Athens",
    "iso:country":"GR",
    "name:ell_x_preferred":[
        "\u03a4\u03bf\u03c5\u03c1\u03ba\u03bf\u03bb\u03ad\u03ba\u03b1\u03c2"
    ],
    "name:ell_x_variant":[
        "\u03a4\u03bf\u03c5\u03c1\u03ba\u03bf\u03bb\u03ad\u03ba\u03b1\u03c2 \u0391\u03c1\u03ba\u03b1\u03b4\u03af\u03b1\u03c2"
    ],
    "name:ron_x_preferred":[
        "Tourkoleka"
    ],
    "name:und_x_variant":[
        "Tourkol\u00e9ka",
        "Tourkole\u00efka",
        "Tourkol\u00e9kas"
    ],
    "wof:name":"Tourkolekas",
    "wof:placetype":"locality"
},
  "geometry": {"coordinates":[22.11965,37.25262],"type":"Point"}
}