{
  "type": "Feature",
  "properties": {
    "gn:country":"GR",
    "gn:fcode":"PPLA",
    "gn:population":11351,
    "iso:country":"GR",
    "name:ara_x_preferred":[
        "\u0647\u0631\u0645\u0648\u0628\u0648\u0644\u064a\u0633"
    ],
    "name:bul_x_preferred":[
        "\u0415\u0440\u043c\u0443\u043f\u043e\u043b\u0438"
    ],
    "name:cat_x_preferred":[
        "Herm\u00fapolis"
    ],
    "name:ceb_x_preferred":[
        "Ermo\u00fapolis"
    ],
    "name:ces_x_preferred":[
        "Ermupoli"
    ],
    "name:dan_x_preferred":[
        "Ermoupoli"
    ],
    "name:deu_x_preferred":[
        "Ermoupoli"
    ],
    "name:ell_x_preferred":[
        "\u0395\u03c1\u03bc\u03bf\u03cd\u03c0\u03bf\u03bb\u03b9\u03c2"
    ],
    "name:ell_x_variant":[
        "\u0395\u03c1\u03bc\u03bf\u03cd\u03c0\u03bf\u03bb\u03b7"
    ],
    "name:eng_x_preferred":[
        "Ermoupolis"
    ],
    "name:epo_x_preferred":[
        "Ermupolis"
    ],
    "name:est_x_preferred":[
        "Ermo\u00fapoli"
    ],
    "name:eus_x_preferred":[
        "Ermoupoli"
    ],
    "name:fin_x_preferred":[
        "Ermo\u00fapoli"
    ],
    "name:fra_x_preferred":[
        "Ermo\u00fapoli"
    ],
    "name:hrv_x_preferred":[
        "Ermoupolis"
    ],
    "name:hun_x_preferred":[
        "Erm\u00fapoli"
    ],
    "name:hye_x_preferred":[
        "\u0537\u0580\u0574\u0578\u0582\u057a\u0578\u056c\u056b\u057d"
    ],
    "name:ind_x_preferred":[
        "Ermoupoli"
    ],
    "name:ita_x_preferred":[
        "Ermoupoli"
    ],
    "name:jpn_x_preferred":[
        "\u30a8\u30eb\u30e0\u30dd\u30ea"
    ],
    "name:kor_x_preferred":[
        "\uc5d0\ub974\ubb34\ud3f4\ub9ac"
    ],
    "name:lat_x_preferred":[
        "Hermupolis"
    ],
    "name:lit_x_preferred":[
        "Ermupolis"
    ],
    "name:nld_x_preferred":[
        "Ermoupoli"
    ],
    "name:nno_x_preferred":[
        "Ermo\u00fapoli"
    ],
    "name:nob_x_preferred":[
        "Ermoupoli"
    ],
    "name:pol_x_preferred":[
        "Ermupolis"
    ],
    "name:por_x_preferred":[
        "Herm\u00f3polis"
    ],
    "name:ron_x_preferred":[
        "Ermoupolis"
    ],
    "name:rus_x_preferred":[
        "\u042d\u0440\u043c\u0443\u043f\u043e\u043b\u0438\u0441"
    ],
    "name:slv_x_preferred":[
        "Ermoupolis"
    ],
    "name:spa_x_preferred":[
        "Erm\u00fapoli"
    ],
    "name:sqi_x_preferred":[
        "Hermupolis"
    ],
    "name:srp_x_preferred":[
        "\u0415\u0440\u043c\u0443\u043f\u043e\u043b\u0438"
    ],
    "name:swe_x_preferred":[
        "Ermoupoli"
    ],
    "name:tur_x_preferred":[
        "Hermupolis"
    ],
    "name:ukr_x_preferred":[
        "\u0415\u0440\u043c\u0443\u043f\u043e\u043b\u0456\u0441"
    ],
    "name:und_x_variant":[
        "S\u00edros"
    ],
    "name:urd_x_preferred":[
        "\u0627\u0631\u0645\u0624\u067e\u0648\u0644\u06cc"
    ],
    "name:war_x_preferred":[
        "Ermoupoli"
    ],
    "name:zho_x_preferred":[
        "\u57c3\u5c14\u7a46\u6ce2\u5229"
    ],
    "qs_pg:aaroncc":"GR",
    "qs_pg:gn_country":"GR",
    "qs_pg:gn_fcode":"PPLA",
    "qs_pg:gn_pop":11351,
    "qs_pg:name":"Ermo\u00fapolis",
    "qs_pg:photos_9r":0,
    "qs_pg:photos_sr":0,
    "qs_pg:pop_sr":6,
    "qs_pg:qs_pg_placetype":"locality",
    "wof:name":"Ermo\u00fapolis",
    "wof:placetype":"locality",
    "wof:population":11351
},
  "geometry": {"coordinates":[24.94248,37.44227],"type":"Point"}
}