{
  "type": "Feature",
  "properties": {
    "gn:admin1_code":"ESYE24",
    "gn:admin2_code":"29.0",
    "gn:admin3_code":"9160",
    "gn:asciiname":"Neokhorion",
    "gn:country_code":"GR",
    "gn:dem":1266,
    "gn:feature_class":"P",
    "gn:feature_code":"PPL",
    "gn:name":"Neokh\u00f3rion",
    "gn:population":197,
    "gn:timezone":"Europe/Athens",
    "iso:country":"GR",
    "name:ell_x_colloquial":[
        "\u039d\u03b5\u03c7\u03ce\u03c1\u03b9"
    ],
    "name:ell_x_preferred":[
        "\u039d\u03b5\u03bf\u03c7\u03ce\u03c1\u03b9"
    ],
    "name:ell_x_variant":[
        "\u039d\u03b5\u03bf\u03c7\u03ce\u03c1\u03b9 \u03a5\u03c0\u03ac\u03c4\u03b7\u03c2",
        "\u039d\u03b5\u03c7\u03ce\u03c1\u03b9",
        "\u039d\u03b5\u03bf\u03c7\u03ce\u03c1\u03b9\u03bf",
        "\u039d\u03b5\u03bf\u03c7\u03ce\u03c1\u03b9\u03bf\u03bd"
    ],
    "name:eng_x_preferred":[
        "Neochori"
    ],
    "name:und_x_variant":[
        "Neokh\u00f3ri",
        "Neokh\u00f3rion Ip\u00e1tis",
        "Neokh\u00f3ri Ip\u00e1tis",
        "Neokh\u00f3rion"
    ],
    "wof:name":"Neokhorion",
    "wof:placetype":"locality",
    "wof:population":197
},
  "geometry": {"coordinates":[22.19891,38.79818],"type":"Point"}
}