{
  "type": "Feature",
  "properties": {
    "gn:admin1_code":"ESYE24",
    "gn:admin2_code":"34.0",
    "gn:admin3_code":"9152",
    "gn:asciiname":"Tharounia",
    "gn:cc2":"GR",
    "gn:country_code":"GR",
    "gn:dem":399,
    "gn:feature_class":"P",
    "gn:feature_code":"PPL",
    "gn:name":"Tharo\u00fania",
    "gn:population":0,
    "gn:timezone":"Europe/Athens",
    "iso:country":"GR",
    "name:und_x_variant":[
        "Tharro\u00fania",
        "Tharo\u00fania"
    ],
    "wof:name":"Tharounia",
    "wof:placetype":"locality"
},
  "geometry": {"coordinates":[23.9756,38.51258],"type":"Point"}
}