{
  "type": "Feature",
  "properties": {
    "gn:population":1067,
    "iso:country":"GR",
    "name:ara_x_preferred":[
        "\u0623\u0644\u0641\u064a\u0648\u0633\u0627"
    ],
    "name:ceb_x_preferred":[
        "Alfio\u00fasa"
    ],
    "name:ell_x_preferred":[
        "\u0391\u03bb\u03c6\u03b5\u03b9\u03bf\u03cd\u03c3\u03b1 \u0397\u03bb\u03b5\u03af\u03b1\u03c2"
    ],
    "name:ell_x_variant":[
        "\u0391\u03bb\u03c6\u03b5\u03b9\u03bf\u03cd\u03c3\u03b1",
        "Alfeio\u00fasa"
    ],
    "name:eng_x_preferred":[
        "Alfeiousa"
    ],
    "name:nld_x_preferred":[
        "Alfeiousa"
    ],
    "name:swe_x_preferred":[
        "Alfio\u00fasa"
    ],
    "name:swe_x_variant":[
        "Mol\u00e1oi"
    ],
    "name:und_x_variant":[
        "Vol\u00e1ntza"
    ],
    "qs:a0":"Greece",
    "qs:a1":"*\u0394\u03a5\u03a4\u0399\u039a\u0397 \u0395\u039b\u039b\u0391\u0394\u0391",
    "qs:a1_alt":"DYTIKH ELLADA",
    "qs:a1r":"0",
    "qs:a2_alt":"HLEIA",
    "qs:adm0":"Greece",
    "qs:la_lc":"*",
    "qs:level":"locality",
    "qs:loc":"\u0391\u039b\u03a6\u0395\u0399\u039f\u03a5\u03a3\u0391",
    "qs:loc_alt":"ALFEIOYSA",
    "qs:pop":0,
    "qs:type":"buffered point",
    "wd:wordcount":102,
    "wof:name":"\u0391\u039b\u03a6\u0395\u0399\u039f\u03a5\u03a3\u0391",
    "wof:placetype":"locality",
    "wof:population":1067
},
  "geometry": {"coordinates":[21.540567,37.640594],"type":"Point"}
}