{
  "type": "Feature",
  "properties": {
    "gn:admin1_code":"ESYE43",
    "gn:admin2_code":"46.0",
    "gn:admin3_code":"9313",
    "gn:asciiname":"Palekastro",
    "gn:country_code":"GR",
    "gn:dem":37,
    "gn:feature_class":"P",
    "gn:feature_code":"PPL",
    "gn:name":"Palekastro",
    "gn:population":1094,
    "gn:timezone":"Europe/Athens",
    "iso:country":"GR",
    "name:ara_x_preferred":[
        "\u0628\u0627\u0644\u064a\u0643\u0627\u0633\u062a\u0631\u0648"
    ],
    "name:bul_x_preferred":[
        "\u041f\u0430\u043b\u0435\u043a\u0430\u0441\u0442\u0440\u043e"
    ],
    "name:cat_x_preferred":[
        "Pal\u00e9kastro"
    ],
    "name:ceb_x_preferred":[
        "Palekastro"
    ],
    "name:deu_x_preferred":[
        "Palekastro"
    ],
    "name:ell_x_preferred":[
        "\u03a0\u03b1\u03bb\u03b1\u03af\u03ba\u03b1\u03c3\u03c4\u03c1\u03bf\u03bd"
    ],
    "name:ell_x_variant":[
        "\u03a0\u03b1\u03bb\u03b1\u03af\u03ba\u03b1\u03c3\u03c4\u03c1\u03bf",
        "\u03a0\u03b1\u03bb\u03b1\u03b9\u03cc\u03ba\u03b1\u03c3\u03c4\u03c1\u03bf\u03bd",
        "\u03a0\u03b1\u03bb\u03b1\u03af\u03ba\u03b1\u03c3\u03c4\u03c1\u03bf \u039b\u03b1\u03c3\u03b9\u03b8\u03af\u03bf\u03c5"
    ],
    "name:eng_x_preferred":[
        "Palekastro"
    ],
    "name:fin_x_preferred":[
        "Pala\u00edkastro"
    ],
    "name:fra_x_preferred":[
        "Palekastro"
    ],
    "name:ita_x_preferred":[
        "Paleocastro"
    ],
    "name:nno_x_preferred":[
        "Pal\u00e9kastro"
    ],
    "name:por_x_preferred":[
        "Palaicastro"
    ],
    "name:rus_x_preferred":[
        "\u041f\u0430\u043b\u0435\u043a\u0430\u0441\u0442\u0440\u043e\u043d"
    ],
    "name:spa_x_preferred":[
        "Palaikastro"
    ],
    "name:swe_x_preferred":[
        "Palekastro"
    ],
    "name:und_x_variant":[
        "Palai\u00f3kastron",
        "Pala\u00edkastro",
        "Pal\u00e9kastro",
        "Palai\u00f3kastro",
        "Pala\u00edkastron"
    ],
    "wof:name":"Palekastro",
    "wof:placetype":"locality",
    "wof:population":1094
},
  "geometry": {"coordinates":[26.25429,35.19793],"type":"Point"}
}