{
  "type": "Feature",
  "properties": {
    "gn:admin1_code":"ESYE43",
    "gn:admin2_code":"46.0",
    "gn:admin3_code":"9313",
    "gn:asciiname":"Palekastro",
    "gn:country_code":"GR",
    "gn:dem":37,
    "gn:feature_class":"P",
    "gn:feature_code":"PPL",
    "gn:name":"Palekastro",
    "gn:population":1094,
    "gn:timezone":"Europe/Athens",
    "iso:country":"GR",
    "name:ell_x_preferred":[
        "\u03a0\u03b1\u03bb\u03b1\u03af\u03ba\u03b1\u03c3\u03c4\u03c1\u03bf\u03bd"
    ],
    "name:ell_x_variant":[
        "\u03a0\u03b1\u03bb\u03b1\u03af\u03ba\u03b1\u03c3\u03c4\u03c1\u03bf",
        "\u03a0\u03b1\u03bb\u03b1\u03b9\u03cc\u03ba\u03b1\u03c3\u03c4\u03c1\u03bf\u03bd"
    ],
    "name:eng_x_preferred":[
        "Palekastro"
    ],
    "name:und_x_variant":[
        "Palai\u00f3kastron",
        "Pala\u00edkastro",
        "Pal\u00e9kastro",
        "Palai\u00f3kastro",
        "Pala\u00edkastron"
    ],
    "wof:name":"Palekastro",
    "wof:placetype":"locality",
    "wof:population":1094
},
  "geometry": {"coordinates":[26.25429,35.19793],"type":"Point"}
}