{
  "type": "Feature",
  "properties": {
    "gn:population":1655,
    "iso:country":"GR",
    "name:dut_x_preferred":[
        "Perama"
    ],
    "name:eng_x_preferred":[
        "Perama"
    ],
    "name:eng_x_variant":[
        "P\u00e9rama"
    ],
    "name:fin_x_preferred":[
        "P\u00e9rama"
    ],
    "name:ger_x_preferred":[
        "Perama"
    ],
    "name:gre_x_preferred":[
        "\u03a0\u03ad\u03c1\u03b1\u03bc\u03b1 \u03a1\u03b5\u03b8\u03cd\u03bc\u03bd\u03b7\u03c2"
    ],
    "name:nno_x_preferred":[
        "P\u00e9rama i R\u00e9thymno"
    ],
    "name:por_x_preferred":[
        "Perama"
    ],
    "name:rus_x_preferred":[
        "\u041f\u0435\u0440\u0430\u043c\u0430"
    ],
    "name:swe_x_preferred":[
        "P\u00e9rama"
    ],
    "name:und_x_variant":[
        "\u03a0\u0395\u03a1\u0391\u039c\u0391"
    ],
    "name:unk_x_variant":[
        "P\u00e9rama"
    ],
    "qs:a0":"Greece",
    "qs:a1":"*\u039a\u03a1\u0397\u03a4\u0397",
    "qs:a1_alt":"KRHTH",
    "qs:a1r":"0",
    "qs:a2_alt":"XANIA",
    "qs:adm0":"Greece",
    "qs:la_lc":"*",
    "qs:level":"locality",
    "qs:loc":"\u03a0\u0395\u03a1\u0391\u039c\u0391",
    "qs:loc_alt":"PERAMA",
    "qs:pop":0,
    "qs:type":"buffered point",
    "wof:lang":[
        "eng"
    ],
    "wof:name":"\u03a0\u0395\u03a1\u0391\u039c\u0391",
    "wof:placetype":"locality",
    "wof:population":1655
},
  "geometry": {"coordinates":[24.70244,35.37149],"type":"Point"}
}