{
  "type": "Feature",
  "properties": {
    "gn:admin1_code":"ESYE43",
    "gn:admin2_code":"44.0",
    "gn:admin3_code":"9317",
    "gn:asciiname":"Faratsion",
    "gn:cc2":"GR",
    "gn:country_code":"GR",
    "gn:dem":294,
    "gn:feature_class":"P",
    "gn:feature_code":"PPL",
    "gn:name":"Far\u00e1tsion",
    "gn:population":0,
    "gn:timezone":"Europe/Athens",
    "iso:country":"GR",
    "name:und_x_variant":[
        "Far\u00e1tsi",
        "Far\u00e1tsion"
    ],
    "wof:name":"Faratsion",
    "wof:placetype":"locality"
},
  "geometry": {"coordinates":[24.8091,35.34033],"type":"Point"}
}