{
  "type": "Feature",
  "properties": {
    "gn:admin1_code":"ESYE25",
    "gn:asciiname":"Kolokithas",
    "gn:cc2":"GR",
    "gn:country_code":"GR",
    "gn:dem":92,
    "gn:feature_class":"P",
    "gn:feature_code":"PPL",
    "gn:name":"Kolokith\u00e1s",
    "gn:population":0,
    "gn:timezone":"Europe/Athens",
    "iso:country":"GR",
    "name:und_x_variant":[
        "Kolokithi\u00e1",
        "Kolokith\u00e1",
        "Kolokith\u00e1s"
    ],
    "wof:name":"Kolokithas",
    "wof:placetype":"locality"
},
  "geometry": {"coordinates":[21.42866,37.89206],"type":"Point"}
}