{
  "type": "Feature",
  "properties": {
    "gn:country":"GR",
    "gn:fcode":"PPL",
    "gn:population":155,
    "iso:country":"GR",
    "name:ell_x_preferred":[
        "\u039a\u03ac\u03c4\u03c9 \u0396\u03ac\u03bb\u03bf\u03b3\u03ba\u03bf"
    ],
    "name:ell_x_variant":[
        "\u039a\u03ac\u03c4\u03c9 \u0396\u03ac\u03bb\u03bf\u03b3\u03ba\u03bf\u03bd",
        "\u039a\u03ac\u03c4\u03c9 \u0396\u03ac\u03bb\u03bf\u03b3\u03b3\u03bf"
    ],
    "name:eng_x_preferred":[
        "Kato Zalongo"
    ],
    "name:und_x_variant":[
        "K\u00e1to Z\u00e1logko"
    ],
    "qs_pg:aaroncc":"GR",
    "qs_pg:gn_country":"GR",
    "qs_pg:gn_fcode":"PPL",
    "qs_pg:gn_pop":155,
    "qs_pg:name":"Ano Zalongon",
    "qs_pg:name_adm0":"\u0395\u03bb\u03bb\u03ac\u03b4\u03b1",
    "qs_pg:name_adm1":"Epirus and Western Macedonia",
    "qs_pg:photos_9r":0,
    "qs_pg:photos_sr":0,
    "qs_pg:pop_sr":1,
    "qs_pg:qs_pg_placetype":"locality",
    "qs_pg:qs_pg_placetype_gp":"Town",
    "qs_pg:woe_adm0":23424833,
    "woe:adm0_id":23424833,
    "woe:name_adm0":"\u0395\u03bb\u03bb\u03ac\u03b4\u03b1",
    "woe:name_adm1":"Epirus and Western Macedonia",
    "woe:placetype":"Town",
    "wof:name":"Ano Zalongon",
    "wof:placetype":"locality",
    "wof:population":98
},
  "geometry": {"coordinates":[20.53306,39.61639],"type":"Point"}
}