{
  "type": "Feature",
  "properties": {
    "gn:admin1_code":"ESYE23",
    "gn:admin2_code":"38.0",
    "gn:admin3_code":"9133",
    "gn:asciiname":"Goumenissa",
    "gn:country_code":"GR",
    "gn:dem":769,
    "gn:feature_class":"P",
    "gn:feature_code":"PPL",
    "gn:name":"Goum\u00e9nissa",
    "gn:population":0,
    "gn:timezone":"Europe/Athens",
    "iso:country":"GR",
    "name:ara_x_preferred":[
        "\u063a\u0648\u0645\u064a\u0646\u064a\u0633\u0627"
    ],
    "name:bul_x_preferred":[
        "\u0413\u0443\u043c\u0435\u043d\u0434\u0436\u0435"
    ],
    "name:ceb_x_preferred":[
        "Goum\u00e9nissa"
    ],
    "name:chu_x_preferred":[
        "\u0413\u0477\u043c\u0454\u043d\u0434\u0436\u0454"
    ],
    "name:ell_x_preferred":[
        "Goum\u00e9nissa"
    ],
    "name:ell_x_variant":[
        "\u0393\u03bf\u03c5\u03bc\u03ad\u03bd\u03b9\u03c3\u03c3\u03b1"
    ],
    "name:fin_x_preferred":[
        "Goum\u00e9nissa"
    ],
    "name:ita_x_preferred":[
        "Goumenissa"
    ],
    "name:mkd_x_preferred":[
        "\u0413\u0443\u043c\u0435\u043d\u045f\u0435"
    ],
    "name:nno_x_preferred":[
        "Goum\u00e9nissa"
    ],
    "name:rus_x_preferred":[
        "\u0413\u0443\u043c\u0435\u043d\u0438\u0441\u0430"
    ],
    "name:sqi_x_preferred":[
        "Gumenica"
    ],
    "name:swe_x_preferred":[
        "Goum\u00e9nissa"
    ],
    "name:und_x_variant":[
        "K\u00e1to Goumenitsa",
        "Vris\u00e1rion"
    ],
    "name:vep_x_preferred":[
        "Gumeniss"
    ],
    "wof:name":"Goumenissa",
    "wof:placetype":"locality"
},
  "geometry": {"coordinates":[22.03122,38.06111],"type":"Point"}
}