{
  "type": "Feature",
  "properties": {
    "gn:population":4978,
    "iso:country":"GR",
    "name:ara_x_preferred":[
        "\u0623\u062a\u0627\u0644\u0627\u0646\u062a\u064a"
    ],
    "name:bul_x_preferred":[
        "\u0410\u0442\u0430\u043b\u0430\u043d\u0442\u0438"
    ],
    "name:deu_x_preferred":[
        "Atalandi"
    ],
    "name:ell_x_preferred":[
        "\u0391\u03c4\u03b1\u03bb\u03ac\u03bd\u03c4\u03b7"
    ],
    "name:ell_x_variant":[
        "\u0391\u03c4\u03b1\u03bb\u03ac\u03bd\u03c4\u03b7 \u03a6\u03b8\u03b9\u03ce\u03c4\u03b9\u03b4\u03b1\u03c2"
    ],
    "name:eng_x_preferred":[
        "Atalanti"
    ],
    "name:fin_x_preferred":[
        "Atal\u00e1nti"
    ],
    "name:fra_x_preferred":[
        "Atal\u00e1nti"
    ],
    "name:ita_x_preferred":[
        "Atalanti"
    ],
    "name:jpn_x_preferred":[
        "\u30a2\u30bf\u30e9\u30f3\u30c6\u30a3"
    ],
    "name:lat_x_preferred":[
        "Atalanta"
    ],
    "name:nld_x_preferred":[
        "Atalanti"
    ],
    "name:nno_x_preferred":[
        "Atal\u00e1ndi"
    ],
    "name:ron_x_preferred":[
        "Atalanti"
    ],
    "name:srp_x_preferred":[
        "\u0410\u0442\u0430\u043b\u0430\u043d\u0442\u0438"
    ],
    "name:swe_x_preferred":[
        "Atal\u00e1nti"
    ],
    "name:unk_x_variant":[
        "Atal\u00e1ndi"
    ],
    "qs:a0":"Greece",
    "qs:a1":"*\u03a3\u03a4\u0395\u03a1\u0395\u0391 \u0395\u039b\u039b\u0391\u0394\u0391",
    "qs:a1_alt":"STEREA ELLADA",
    "qs:a1r":"0",
    "qs:a2_alt":"FUIVTIDA",
    "qs:adm0":"Greece",
    "qs:la_lc":"*",
    "qs:level":"locality",
    "qs:loc":"\u0391\u03a4\u0391\u039b\u0391\u039d\u03a4\u0397",
    "qs:loc_alt":"ATALANU",
    "qs:pop":0,
    "qs:type":"buffered point",
    "wd:wordcount":5508,
    "wof:name":"\u0391\u03a4\u0391\u039b\u0391\u039d\u03a4\u0397",
    "wof:placetype":"locality",
    "wof:population":4978
},
  "geometry": {"coordinates":[22.992983,38.654579],"type":"Point"}
}