{
  "type": "Feature",
  "properties": {
    "gn:country":"GR",
    "gn:fcode":"PPL",
    "gn:population":58,
    "iso:country":"GR",
    "name:ell_x_historical":[
        "\u0396\u03ad\u03bb\u03b5\u03b3\u03ba\u03c1\u03b1\u03b4"
    ],
    "name:ell_x_preferred":[
        "\u039c\u03b5\u03c3\u03cc\u03b2\u03c1\u03b1\u03c7\u03bf"
    ],
    "name:ell_x_variant":[
        "\u039c\u03b5\u03c3\u03cc\u03b2\u03c1\u03b1\u03c7\u03bf\u03bd",
        "\u0396\u03ad\u03bb\u03b5\u03b3\u03ba\u03c1\u03b1\u03b4"
    ],
    "name:eng_x_preferred":[
        "Mesovracho"
    ],
    "name:und_x_variant":[
        "Mes\u00f3vrakhon"
    ],
    "qs_pg:aaroncc":"GR",
    "qs_pg:gn_country":"GR",
    "qs_pg:gn_fcode":"PPL",
    "qs_pg:gn_pop":58,
    "qs_pg:name":"Mes\u00f3vrachon",
    "qs_pg:photos_9r":0,
    "qs_pg:photos_sr":0,
    "qs_pg:pop_sr":1,
    "qs_pg:qs_pg_placetype":"locality",
    "wof:name":"Mes\u00f3vrachon",
    "wof:placetype":"locality",
    "wof:population":6
},
  "geometry": {"coordinates":[20.98528,40.4625],"type":"Point"}
}