{
  "type": "Feature",
  "properties": {
    "gn:admin1_code":"ESYE24",
    "gn:admin2_code":"30.0",
    "gn:admin3_code":"9157",
    "gn:asciiname":"Krikellon",
    "gn:country_code":"GR",
    "gn:dem":1097,
    "gn:feature_class":"P",
    "gn:feature_code":"PPL",
    "gn:name":"Kr\u00edkellon",
    "gn:population":161,
    "gn:timezone":"Europe/Athens",
    "iso:country":"GR",
    "name:ell_x_preferred":[
        "\u039a\u03c1\u03af\u03ba\u03b5\u03bb\u03bb\u03bf"
    ],
    "name:eng_x_preferred":[
        "Krikello"
    ],
    "name:und_x_variant":[
        "Krikelu",
        "Kr\u00edkellon"
    ],
    "wof:name":"Krikellon",
    "wof:placetype":"locality",
    "wof:population":161
},
  "geometry": {"coordinates":[21.85245,38.79601],"type":"Point"}
}