{
  "type": "Feature",
  "properties": {
    "gn:admin1_code":"ESYE43",
    "gn:admin2_code":"43.0",
    "gn:admin3_code":"9325",
    "gn:asciiname":"Kampoi",
    "gn:country_code":"GR",
    "gn:dem":566,
    "gn:feature_class":"P",
    "gn:feature_code":"PPL",
    "gn:name":"K\u00e1mpoi",
    "gn:population":0,
    "gn:timezone":"Europe/Athens",
    "iso:country":"GR",
    "name:ara_x_preferred":[
        "\u0643\u0627\u0645\u0628\u064a"
    ],
    "name:ceb_x_preferred":[
        "Kamp\u00ed"
    ],
    "name:ell_x_preferred":[
        "K\u00e1mpoi"
    ],
    "name:ell_x_variant":[
        "\u039a\u03ac\u03bc\u03c0\u03bf\u03b9",
        "K\u00e1mboi"
    ],
    "name:fra_x_preferred":[
        "Kamboi"
    ],
    "wof:name":"Kampoi",
    "wof:placetype":"locality"
},
  "geometry": {"coordinates":[24.06887,35.41968],"type":"Point"}
}