{
  "type": "Feature",
  "properties": {
    "gn:admin1_code":"ESYE43",
    "gn:admin2_code":"43.0",
    "gn:admin3_code":"9323",
    "gn:asciiname":"Chrysavgi",
    "gn:country_code":"GR",
    "gn:dem":154,
    "gn:feature_class":"P",
    "gn:feature_code":"PPL",
    "gn:name":"Chrysavg\u00ed",
    "gn:population":0,
    "gn:timezone":"Europe/Athens",
    "iso:country":"GR",
    "name:bul_x_preferred":[
        "\u0425\u0440\u0438\u0441\u0430\u0432\u0433\u0438"
    ],
    "name:ell_x_preferred":[
        "Chrysavg\u00ed"
    ],
    "name:ell_x_variant":[
        "\u03a7\u03c1\u03c5\u03c3\u03b1\u03c5\u03b3\u03ae",
        "\u03a7\u03c1\u03c5\u03c3\u03b1\u03c5\u03b3\u03ae \u039a\u03bf\u03b6\u03ac\u03bd\u03b7\u03c2"
    ],
    "name:mkd_x_preferred":[
        "\u041c\u0438\u0440\u0430\u043b\u0438"
    ],
    "wof:name":"Chrysavgi",
    "wof:placetype":"locality"
},
  "geometry": {"coordinates":[23.80269,35.49272],"type":"Point"}
}