{
  "type": "Feature",
  "properties": {
    "gn:admin1_code":"ESYE11",
    "gn:admin2_code":"14.0",
    "gn:admin3_code":"9014",
    "gn:asciiname":"Pyrgochori",
    "gn:country_code":"GR",
    "gn:dem":158,
    "gn:feature_class":"P",
    "gn:feature_code":"PPL",
    "gn:name":"Pyrgoch\u00f3ri",
    "gn:population":140,
    "gn:timezone":"Europe/Athens",
    "iso:country":"GR",
    "name:ell_x_preferred":[
        "\u03a0\u03c5\u03c1\u03b3\u03bf\u03c7\u03ce\u03c1\u03b9"
    ],
    "name:ell_x_variant":[
        "Pyrgoch\u00f3ri",
        "Pirgokh\u00f3rion",
        "Pyrgoch\u00f3rion",
        "\u03a0\u03c5\u03c1\u03b3\u03bf\u03c7\u03ce\u03c1\u03b9\u03bf\u03bd"
    ],
    "name:eng_x_preferred":[
        "Pyrgochori"
    ],
    "wof:name":"Pyrgochori",
    "wof:placetype":"locality",
    "wof:population":140
},
  "geometry": {"coordinates":[24.15527,40.87138],"type":"Point"}
}