{
  "type": "Feature",
  "properties": {
    "gn:admin1_code":"ESYE25",
    "gn:admin2_code":"37.0",
    "gn:admin3_code":"9246",
    "gn:asciiname":"Thalero",
    "gn:country_code":"GR",
    "gn:dem":151,
    "gn:feature_class":"P",
    "gn:feature_code":"PPL",
    "gn:name":"Thaler\u00f3",
    "gn:population":162,
    "gn:timezone":"Europe/Athens",
    "iso:country":"GR",
    "name:ceb_x_preferred":[
        "Thaler\u00f3"
    ],
    "name:ell_x_preferred":[
        "\u0398\u03b1\u03bb\u03b5\u03c1\u03cc"
    ],
    "name:eng_x_preferred":[
        "Thalero"
    ],
    "name:swe_x_preferred":[
        "Thaler\u00f3"
    ],
    "name:und_x_variant":[
        "Thoter\u00f3n",
        "Tholer\u00f3n",
        "Thaler\u00f3n"
    ],
    "wof:name":"Thalero",
    "wof:placetype":"locality",
    "wof:population":162
},
  "geometry": {"coordinates":[22.66399,38.03677],"type":"Point"}
}