{
  "type": "Feature",
  "properties": {
    "gn:admin1_code":"ESYE42",
    "gn:admin2_code":"47.0",
    "gn:admin3_code":"9280",
    "gn:asciiname":"Amoopi",
    "gn:country_code":"GR",
    "gn:dem":70,
    "gn:feature_class":"P",
    "gn:feature_code":"PPL",
    "gn:name":"Amoopi",
    "gn:population":0,
    "gn:timezone":"Europe/Athens",
    "iso:country":"GR",
    "name:nor_x_preferred":[
        "Amopi"
    ],
    "name:und_x_variant":[
        "Amopi"
    ],
    "wof:name":"Amoopi",
    "wof:placetype":"locality"
},
  "geometry": {"coordinates":[27.18863,35.47493],"type":"Point"}
}