{
  "type": "Feature",
  "properties": {
    "gn:admin1_code":"ESYE43",
    "gn:admin2_code":"44.0",
    "gn:admin3_code":"9318",
    "gn:asciiname":"Roussounavli",
    "gn:country_code":"GR",
    "gn:dem":197,
    "gn:feature_class":"P",
    "gn:feature_code":"PPL",
    "gn:name":"Roussoun\u00e1vli",
    "gn:population":0,
    "gn:timezone":"Europe/Athens",
    "iso:country":"GR",
    "name:ell_x_preferred":[
        "Roussoun\u00e1vli"
    ],
    "name:ell_x_variant":[
        "\u03a1\u03bf\u03c5\u03c3\u03c3\u03bf\u03c5\u03bd\u03b1\u03cd\u03bb\u03b9"
    ],
    "wof:name":"Roussounavli",
    "wof:placetype":"locality"
},
  "geometry": {"coordinates":[24.63453,35.35489000000001],"type":"Point"}
}