{
  "type": "Feature",
  "properties": {
    "gn:admin1_code":"ESYE24",
    "gn:admin2_code":"32.0",
    "gn:admin3_code":"9166",
    "gn:asciiname":"Makrini",
    "gn:country_code":"GR",
    "gn:dem":681,
    "gn:feature_class":"P",
    "gn:feature_code":"PPL",
    "gn:name":"Makrin\u00ed",
    "gn:population":0,
    "gn:timezone":"Europe/Athens",
    "iso:country":"GR",
    "name:ell_x_preferred":[
        "\u039c\u03b1\u03ba\u03c1\u03b9\u03bd\u03ae"
    ],
    "name:und_x_variant":[
        "M\u00e1krisa",
        "M\u00e1krisi",
        "Makrin\u00ed"
    ],
    "wof:name":"Makrini",
    "wof:placetype":"locality"
},
  "geometry": {"coordinates":[22.12406,38.43303],"type":"Point"}
}