{
  "type": "Feature",
  "properties": {
    "gn:country":"GR",
    "gn:fcode":"PPL",
    "gn:population":408,
    "iso:country":"GR",
    "name:ell_x_preferred":[
        "\u039e\u03b7\u03c1\u03bf\u03c7\u03ce\u03c1\u03b9"
    ],
    "name:ell_x_variant":[
        "\u039e\u03b7\u03c1\u03bf\u03c7\u03ce\u03c1\u03b9\u03bf\u03bd"
    ],
    "name:und_x_variant":[
        "\u00c1no Xirokh\u00f3ri"
    ],
    "qs_pg:aaroncc":"GR",
    "qs_pg:gn_country":"GR",
    "qs_pg:gn_fcode":"PPL",
    "qs_pg:gn_pop":408,
    "qs_pg:name":"Xiroch\u00f3rion",
    "qs_pg:photos_9r":0,
    "qs_pg:photos_sr":0,
    "qs_pg:pop_sr":2,
    "qs_pg:qs_pg_placetype":"locality",
    "wof:name":"Xiroch\u00f3rion",
    "wof:placetype":"locality",
    "wof:population":408
},
  "geometry": {"coordinates":[21.65,37.51667],"type":"Point"}
}