{
  "type": "Feature",
  "properties": {
    "gn:admin1_code":"ESYE24",
    "gn:admin2_code":"34.0",
    "gn:admin3_code":"9152",
    "gn:asciiname":"Argyro",
    "gn:country_code":"GR",
    "gn:dem":226,
    "gn:feature_class":"P",
    "gn:feature_code":"PPL",
    "gn:name":"Argyr\u00f3",
    "gn:population":0,
    "gn:timezone":"Europe/Athens",
    "iso:country":"GR",
    "name:ell_x_preferred":[
        "Argyr\u00f3"
    ],
    "name:ell_x_variant":[
        "\u0391\u03c1\u03b3\u03c5\u03c1\u03cc",
        "Argyr\u00f3n",
        "\u0391\u03c1\u03b3\u03c5\u03c1\u03cc\u03bd"
    ],
    "name:und_x_variant":[
        "V\u00edrra",
        "V\u00edra"
    ],
    "wof:name":"Argyro",
    "wof:placetype":"locality"
},
  "geometry": {"coordinates":[24.14847,38.30894],"type":"Point"}
}