{
  "type": "Feature",
  "properties": {
    "gn:country":"GR",
    "gn:fcode":"PPL",
    "gn:population":73,
    "iso:country":"GR",
    "name:ell_x_historical":[
        "\u03a4\u03c3\u03b5\u03c1\u03b2\u03ac\u03c1\u03b9"
    ],
    "name:ell_x_preferred":[
        "\u0395\u03bb\u03b1\u03c6\u03cc\u03c4\u03bf\u03c0\u03bf\u03c2"
    ],
    "name:ell_x_variant":[
        "\u03a4\u03c3\u03b5\u03c1\u03b2\u03ac\u03c1\u03b9"
    ],
    "name:eng_x_preferred":[
        "Elafotopos"
    ],
    "name:und_x_variant":[
        "Tserv\u00e1ri"
    ],
    "qs_pg:aaroncc":"GR",
    "qs_pg:gn_country":"GR",
    "qs_pg:gn_fcode":"PPL",
    "qs_pg:gn_pop":73,
    "qs_pg:name":"Elafotopos",
    "qs_pg:name_adm0":"\u0395\u03bb\u03bb\u03ac\u03b4\u03b1",
    "qs_pg:name_adm1":"Epirus and Western Macedonia",
    "qs_pg:photos":9,
    "qs_pg:photos_1k":2,
    "qs_pg:photos_9k":1,
    "qs_pg:photos_9r":1,
    "qs_pg:photos_all":9,
    "qs_pg:photos_sr":1,
    "qs_pg:pop_sr":1,
    "qs_pg:qs_pg_placetype":"locality",
    "qs_pg:qs_pg_placetype_gp":"Town",
    "qs_pg:woe_adm0":23424833,
    "woe:adm0_id":23424833,
    "woe:name_adm0":"\u0395\u03bb\u03bb\u03ac\u03b4\u03b1",
    "woe:name_adm1":"Epirus and Western Macedonia",
    "woe:placetype":"Town",
    "wof:name":"Elafotopos",
    "wof:placetype":"locality",
    "wof:population":51
},
  "geometry": {"coordinates":[20.69,39.90028],"type":"Point"}
}