{
  "type": "Feature",
  "properties": {
    "gn:admin1_code":"ESYE21",
    "gn:admin2_code":"20.0",
    "gn:admin3_code":"9075",
    "gn:asciiname":"Livadi",
    "gn:country_code":"GR",
    "gn:dem":498,
    "gn:feature_class":"P",
    "gn:feature_code":"PPL",
    "gn:name":"Liv\u00e1di",
    "gn:population":0,
    "gn:timezone":"Europe/Athens",
    "iso:country":"GR",
    "name:ara_x_preferred":[
        "\u0644\u064a\u0641\u0627\u062f\u064a"
    ],
    "name:bul_x_preferred":[
        "\u041b\u0438\u0432\u0430\u0434\u0438"
    ],
    "name:ceb_x_preferred":[
        "Liv\u00e1di"
    ],
    "name:ell_x_preferred":[
        "\u039b\u03b9\u03b2\u03ac\u03b4\u03b9"
    ],
    "name:ell_x_variant":[
        "\u039b\u03b9\u03b2\u03ac\u03b4\u03b9\u03bf\u03bd",
        "\u039b\u03b9\u03b2\u03ac\u03b4\u03b9 \u039f\u03bb\u03cd\u03bc\u03c0\u03bf\u03c5"
    ],
    "name:fin_x_preferred":[
        "Liv\u00e1di"
    ],
    "name:ita_x_preferred":[
        "Livadi"
    ],
    "name:nno_x_preferred":[
        "Liv\u00e1di"
    ],
    "name:ron_x_preferred":[
        "Livadi"
    ],
    "name:und_x_variant":[
        "Liv\u00e1dhion",
        "Liv\u00e1dhi",
        "Liv\u00e1dion"
    ],
    "wof:name":"Livadi",
    "wof:placetype":"locality"
},
  "geometry": {"coordinates":[21.07236,39.38625],"type":"Point"}
}