{
  "type": "Feature",
  "properties": {
    "gn:gn_country":"GR",
    "gn:gn_fcode":"PPL",
    "gn:gn_pop":388,
    "gn:population":388,
    "iso:country":"GR",
    "name:ell_x_preferred":[
        "Lo\u00fatsa"
    ],
    "name:ell_x_variant":[
        "\u039b\u03bf\u03cd\u03c4\u03c3\u03b1"
    ],
    "qs_pg:aaroncc":"GR",
    "qs_pg:gn_country":"GR",
    "qs_pg:gn_fcode":"PPL",
    "qs_pg:gn_pop":388,
    "qs_pg:name":"Lo\u00fatsa",
    "qs_pg:photos_9r":0,
    "qs_pg:photos_sr":0,
    "qs_pg:pop_sr":2,
    "qs_pg:qs_pg_placetype":"locality",
    "wof:name":"Lo\u00fatsa",
    "wof:placetype":"locality",
    "wof:population":388
},
  "geometry": {"coordinates":[20.53194,39.1975],"type":"Point"}
}