{
  "type": "Feature",
  "properties": {
    "gn:gn_country":"GR",
    "gn:gn_fcode":"PPL",
    "gn:gn_pop":86,
    "gn:population":86,
    "iso:country":"GR",
    "name:ell_x_preferred":[
        "\u0391\u03b3\u03af\u03b1 \u039a\u03c5\u03c1\u03b9\u03b1\u03ba\u03ae"
    ],
    "name:ell_x_variant":[
        "\u0391\u03b3\u03af\u03b1 \u039a\u03c5\u03c1\u03b9\u03b1\u03ba\u03ae \u0391\u03c3\u03c4\u03c5\u03c0\u03ac\u03bb\u03b1\u03b9\u03b1\u03c2"
    ],
    "name:unk_x_variant":[
        "P\u00f3povon"
    ],
    "qs_pg:aaroncc":"GR",
    "qs_pg:gn_country":"GR",
    "qs_pg:gn_fcode":"PPL",
    "qs_pg:gn_pop":86,
    "qs_pg:name":"Agia Kyriaki",
    "qs_pg:name_adm0":"\u0395\u03bb\u03bb\u03ac\u03b4\u03b1",
    "qs_pg:name_adm1":"Epirus and Western Macedonia",
    "qs_pg:photos_9r":0,
    "qs_pg:photos_sr":0,
    "qs_pg:pop_sr":1,
    "qs_pg:qs_pg_placetype":"locality",
    "qs_pg:qs_pg_placetype_gp":"Town",
    "qs_pg:woe_adm0":23424833,
    "woe:adm0_id":23424833,
    "woe:name_adm0":"\u0395\u03bb\u03bb\u03ac\u03b4\u03b1",
    "woe:name_adm1":"Epirus and Western Macedonia",
    "woe:placetype":"Town",
    "wof:name":"Agia Kyriaki",
    "wof:placetype":"locality",
    "wof:population":86
},
  "geometry": {"coordinates":[20.57,39.48778],"type":"Point"}
}