{
  "type": "Feature",
  "properties": {
    "gn:admin1_code":"ESYE31",
    "gn:admin2_code":"406101.0",
    "gn:admin3_code":"9211",
    "gn:asciiname":"Dimitrani",
    "gn:country_code":"GR",
    "gn:dem":46,
    "gn:feature_class":"P",
    "gn:feature_code":"PPL",
    "gn:name":"Dimitr\u00e1ni",
    "gn:population":96,
    "gn:timezone":"Europe/Athens",
    "iso:country":"GR",
    "name:ell_x_historical":[
        "\u0394\u03b7\u03bc\u03b7\u03c4\u03c1\u03ac\u03bd\u03b7"
    ],
    "name:ell_x_preferred":[
        "\u0394\u03b7\u03bc\u03b7\u03c4\u03c1\u03ac\u03bd\u03b9"
    ],
    "name:ell_x_variant":[
        "\u0394\u03b7\u03bc\u03b7\u03c4\u03c1\u03ac\u03bd\u03b7"
    ],
    "name:eng_x_preferred":[
        "Dimitrani"
    ],
    "wof:name":"Dimitrani",
    "wof:placetype":"locality",
    "wof:population":96
},
  "geometry": {"coordinates":[23.49244,37.90439],"type":"Point"}
}