{
  "type": "Feature",
  "properties": {
    "gn:gn_country":"GR",
    "gn:gn_fcode":"PPL",
    "gn:gn_pop":5562,
    "gn:population":5562,
    "iso:country":"GR",
    "name:ara_x_preferred":[
        "\u0623\u0641\u0627\u0646\u062a\u0648"
    ],
    "name:ceb_x_preferred":[
        "Af\u00e1ntou"
    ],
    "name:ces_x_preferred":[
        "Afantou"
    ],
    "name:deu_x_preferred":[
        "Afandou"
    ],
    "name:ell_x_preferred":[
        "\u0391\u03c6\u03ac\u03bd\u03c4\u03bf\u03c5"
    ],
    "name:fin_x_preferred":[
        "Af\u00e1ntou"
    ],
    "name:fra_x_preferred":[
        "Af\u00e1ntou"
    ],
    "name:ita_x_preferred":[
        "Afando"
    ],
    "name:nno_x_preferred":[
        "Af\u00e1ndou"
    ],
    "name:pol_x_preferred":[
        "Afandu"
    ],
    "name:swe_x_preferred":[
        "Af\u00e1ntou"
    ],
    "name:unk_x_variant":[
        "Af\u00e1ndou"
    ],
    "qs_pg:aaroncc":"GR",
    "qs_pg:gn_country":"GR",
    "qs_pg:gn_fcode":"PPL",
    "qs_pg:gn_pop":5562,
    "qs_pg:name":"Afantou",
    "qs_pg:name_adm0":"\u0395\u03bb\u03bb\u03ac\u03b4\u03b1",
    "qs_pg:name_adm1":"Aegean",
    "qs_pg:photos":441,
    "qs_pg:photos_1k":89,
    "qs_pg:photos_9k":2,
    "qs_pg:photos_9r":5,
    "qs_pg:photos_all":441,
    "qs_pg:photos_sr":6,
    "qs_pg:pop_sr":5,
    "qs_pg:qs_pg_placetype":"locality",
    "qs_pg:qs_pg_placetype_gp":"Town",
    "qs_pg:woe_adm0":23424833,
    "woe:adm0_id":23424833,
    "woe:name_adm0":"\u0395\u03bb\u03bb\u03ac\u03b4\u03b1",
    "woe:name_adm1":"Aegean",
    "woe:placetype":"Town",
    "wof:name":"Afantou",
    "wof:placetype":"locality",
    "wof:population":5562
},
  "geometry": {"coordinates":[28.16225,36.29354],"type":"Point"}
}