{
  "type": "Feature",
  "properties": {
    "gn:admin1_code":"ESYE24",
    "gn:admin2_code":"29.0",
    "gn:admin3_code":"9162",
    "gn:asciiname":"Koureleika",
    "gn:country_code":"GR",
    "gn:dem":969,
    "gn:feature_class":"P",
    "gn:feature_code":"PPL",
    "gn:name":"Kourel\u00e9ika",
    "gn:population":32,
    "gn:timezone":"Europe/Athens",
    "iso:country":"GR",
    "name:ell_x_preferred":[
        "\u039a\u03bf\u03c5\u03c1\u03b5\u03bb\u03ad\u03b9\u03ba\u03b1"
    ],
    "name:eng_x_preferred":[
        "Koureleika"
    ],
    "wof:name":"Koureleika",
    "wof:placetype":"locality",
    "wof:population":32
},
  "geometry": {"coordinates":[21.95566,38.84211],"type":"Point"}
}