{
  "type": "Feature",
  "properties": {
    "gn:gn_country":"GR",
    "gn:gn_fcode":"PPL",
    "gn:gn_pop":695,
    "gn:population":695,
    "iso:country":"GR",
    "name:ara_x_preferred":[
        "\u0643\u0627\u0646\u0627\u0644\u064a\u0627"
    ],
    "name:ceb_x_preferred":[
        "Kan\u00e1lia"
    ],
    "name:ell_x_preferred":[
        "Kan\u00e1lia"
    ],
    "name:ell_x_variant":[
        "\u039a\u03b1\u03bd\u03ac\u03bb\u03b9\u03b1",
        "\u039a\u03b1\u03bd\u03ac\u03bb\u03b9\u03b1 \u039c\u03b1\u03b3\u03bd\u03b7\u03c3\u03af\u03b1\u03c2"
    ],
    "qs_pg:aaroncc":"GR",
    "qs_pg:gn_country":"GR",
    "qs_pg:gn_fcode":"PPL",
    "qs_pg:gn_pop":695,
    "qs_pg:name":"Kanalia",
    "qs_pg:name_adm0":"\u0395\u03bb\u03bb\u03ac\u03b4\u03b1",
    "qs_pg:name_adm1":"Thessaly and Continental Greece",
    "qs_pg:photos_9k":1,
    "qs_pg:photos_9r":1,
    "qs_pg:photos_all":4,
    "qs_pg:photos_sr":0,
    "qs_pg:pop_sr":2,
    "qs_pg:qs_pg_placetype":"locality",
    "qs_pg:qs_pg_placetype_gp":"Town",
    "qs_pg:woe_adm0":23424833,
    "woe:adm0_id":23424833,
    "woe:name_adm0":"\u0395\u03bb\u03bb\u03ac\u03b4\u03b1",
    "woe:name_adm1":"Thessaly and Continental Greece",
    "woe:placetype":"Town",
    "wof:name":"Kanalia",
    "wof:placetype":"locality",
    "wof:population":695
},
  "geometry": {"coordinates":[21.79889,39.39833],"type":"Point"}
}