{
  "type": "Feature",
  "properties": {
    "iso:country":"GR",
    "name:ara_x_preferred":[
        "\u0643\u0627\u0633\u062a\u0631\u0627\u0643\u064a\u0648\u0646\u060c \u062a\u0631\u064a\u0643\u0627\u0644\u0627"
    ],
    "name:ara_x_variant":[
        "\u0643\u0627\u0633\u062a\u0631\u0627\u0643\u064a\u0648\u0646"
    ],
    "name:ceb_x_preferred":[
        "Kastr\u00e1ki"
    ],
    "name:ell_x_preferred":[
        "\u039a\u03b1\u03c3\u03c4\u03c1\u03ac\u03ba\u03b9 \u03a4\u03c1\u03b9\u03ba\u03ac\u03bb\u03c9\u03bd"
    ],
    "name:eng_x_preferred":[
        "Kastraki"
    ],
    "name:fin_x_preferred":[
        "Kastr\u00e1ki"
    ],
    "name:nld_x_preferred":[
        "Kastraki"
    ],
    "name:pol_x_preferred":[
        "Kastraki"
    ],
    "name:swe_x_preferred":[
        "Kastr\u00e1ki"
    ],
    "name:ukr_x_preferred":[
        "\u041a\u0430\u0441\u0442\u0440\u0430\u043a\u0456"
    ],
    "qs_pg:aaroncc":"GR",
    "qs_pg:name":"Kastraki",
    "qs_pg:name_adm0":"\u0395\u03bb\u03bb\u03ac\u03b4\u03b1",
    "qs_pg:name_adm1":"Thessaly and Continental Greece",
    "qs_pg:photos":456,
    "qs_pg:photos_1k":92,
    "qs_pg:photos_9k":2,
    "qs_pg:photos_9r":5,
    "qs_pg:photos_all":456,
    "qs_pg:photos_sr":7,
    "qs_pg:pop_sr":0,
    "qs_pg:qs_pg_placetype":"locality",
    "qs_pg:qs_pg_placetype_gp":"Town",
    "qs_pg:woe_adm0":23424833,
    "woe:adm0_id":23424833,
    "woe:name_adm0":"\u0395\u03bb\u03bb\u03ac\u03b4\u03b1",
    "woe:name_adm1":"Thessaly and Continental Greece",
    "woe:placetype":"Town",
    "wof:name":"Kastraki",
    "wof:placetype":"locality"
},
  "geometry": {"coordinates":[21.6204715,39.715704],"type":"Point"}
}