{
  "type": "Feature",
  "properties": {
    "gn:country":"GR",
    "gn:fcode":"PPL",
    "gn:population":379,
    "iso:country":"GR",
    "name:ell_x_preferred":[
        "Monastir\u00e1ki"
    ],
    "name:ell_x_variant":[
        "\u039c\u03bf\u03bd\u03b1\u03c3\u03c4\u03b7\u03c1\u03ac\u03ba\u03b9",
        "Monastir\u00e1kion",
        "\u039c\u03bf\u03bd\u03b1\u03c3\u03c4\u03b7\u03c1\u03ac\u03ba\u03b9\u03bf\u03bd"
    ],
    "qs_pg:aaroncc":"GR",
    "qs_pg:gn_country":"GR",
    "qs_pg:gn_fcode":"PPL",
    "qs_pg:gn_pop":379,
    "qs_pg:name":"Monastirakion",
    "qs_pg:name_adm0":"\u0395\u03bb\u03bb\u03ac\u03b4\u03b1",
    "qs_pg:name_adm1":"Macedonia and Thrace",
    "qs_pg:photos_9k":1,
    "qs_pg:photos_9r":1,
    "qs_pg:photos_all":1,
    "qs_pg:photos_sr":0,
    "qs_pg:pop_sr":2,
    "qs_pg:qs_pg_placetype":"locality",
    "qs_pg:qs_pg_placetype_gp":"Town",
    "qs_pg:woe_adm0":23424833,
    "woe:adm0_id":23424833,
    "woe:name_adm0":"\u0395\u03bb\u03bb\u03ac\u03b4\u03b1",
    "woe:name_adm1":"Macedonia and Thrace",
    "woe:placetype":"Town",
    "wof:name":"Monastirakion",
    "wof:placetype":"locality",
    "wof:population":379
},
  "geometry": {"coordinates":[26.10389,40.85056],"type":"Point"}
}