{
  "type": "Feature",
  "properties": {
    "gn:admin1_code":"ESYE23",
    "gn:admin2_code":"31.0",
    "gn:admin3_code":"9127",
    "gn:asciiname":"Fragkoulaiika",
    "gn:country_code":"GR",
    "gn:dem":100,
    "gn:feature_class":"P",
    "gn:feature_code":"PPL",
    "gn:name":"Fragkoula\u00edika",
    "gn:population":0,
    "gn:timezone":"Europe/Athens",
    "iso:country":"GR",
    "name:ell_x_preferred":[
        "Fragkoula\u00edika"
    ],
    "name:ell_x_variant":[
        "\u03a6\u03c1\u03b1\u03b3\u03ba\u03bf\u03c5\u03bb\u03b1\u03af\u03b9\u03ba\u03b1"
    ],
    "name:und_x_variant":[
        "Frangouleika",
        "Franguol\u00e9\u00efka",
        "Frangoula\u00edika"
    ],
    "wof:name":"Fragkoulaiika",
    "wof:placetype":"locality"
},
  "geometry": {"coordinates":[21.37881,38.52047],"type":"Point"}
}