{
  "type": "Feature",
  "properties": {
    "gn:admin1_code":"ESYE22",
    "gn:admin2_code":"27.0",
    "gn:admin3_code":"9120",
    "gn:asciiname":"Kapandriti",
    "gn:country_code":"GR",
    "gn:dem":317,
    "gn:feature_class":"P",
    "gn:feature_code":"PPL",
    "gn:name":"Kapandr\u00edti",
    "gn:population":0,
    "gn:timezone":"Europe/Athens",
    "iso:country":"GR",
    "name:ell_x_preferred":[
        "Kapandr\u00edti"
    ],
    "name:ell_x_variant":[
        "\u039a\u03b1\u03c0\u03b1\u03bd\u03b4\u03c1\u03af\u03c4\u03b9",
        "\u039a\u03b1\u03c0\u03b1\u03bd\u03b4\u03c1\u03af\u03c4\u03b9\u03bf\u03bd"
    ],
    "name:und_x_variant":[
        "Kapandhr\u00edti",
        "Kapandr\u00edtion"
    ],
    "wof:name":"Kapandriti",
    "wof:placetype":"locality"
},
  "geometry": {"coordinates":[20.72647000000001,38.12667],"type":"Point"}
}