{
  "type": "Feature",
  "properties": {
    "gn:gn_country":"GR",
    "gn:gn_fcode":"ADM3",
    "gn:gn_pop":152,
    "gn:population":152,
    "iso:country":"GR",
    "name:ell_x_preferred":[
        "\u0394\u03ae\u03bc\u03bf\u03c2 \u0391\u03b3\u03b1\u03b8\u03bf\u03bd\u03b7\u03c3\u03af\u03bf\u03c5"
    ],
    "name:ell_x_variant":[
        "\u0391\u03b3\u03b1\u03b8\u03bf\u03bd\u03ae\u03c3\u03b9"
    ],
    "qs_pg:aaroncc":"GR",
    "qs_pg:gn_country":"GR",
    "qs_pg:gn_fcode":"ADM3",
    "qs_pg:gn_pop":152,
    "qs_pg:name":"Dimos Agathonisi",
    "qs_pg:photos_9r":0,
    "qs_pg:photos_sr":0,
    "qs_pg:pop_sr":1,
    "qs_pg:qs_pg_placetype":"localadmin",
    "wof:name":"Dimos Agathonisi",
    "wof:placetype":"localadmin",
    "wof:population":152
},
  "geometry": {"coordinates":[26.96804,37.46231],"type":"Point"}
}