{
  "type": "Feature",
  "properties": {
    "gn:admin1_code":"ESYE13",
    "gn:admin2_code":"10.0",
    "gn:admin3_code":"9061",
    "gn:asciiname":"Exarchos",
    "gn:country_code":"GR",
    "gn:dem":729,
    "gn:feature_class":"P",
    "gn:feature_code":"PPL",
    "gn:name":"\u00c9xarchos",
    "gn:population":0,
    "gn:timezone":"Europe/Athens",
    "iso:country":"GR",
    "name:bul_x_preferred":[
        "\u0415\u043a\u0441\u0430\u0440\u0445\u043e\u0441"
    ],
    "name:ell_x_preferred":[
        "\u00c9xarchos"
    ],
    "name:ell_x_variant":[
        "\u0388\u03be\u03b1\u03c1\u03c7\u03bf\u03c2"
    ],
    "name:und_x_variant":[
        "\u00c9xarkhos"
    ],
    "wof:name":"Exarchos",
    "wof:placetype":"locality"
},
  "geometry": {"coordinates":[21.63045,40.15911],"type":"Point"}
}