{
  "type": "Feature",
  "properties": {
    "gn:admin1_code":"ESYE13",
    "gn:admin2_code":"11.0",
    "gn:admin3_code":"9069",
    "gn:asciiname":"Tranovalto",
    "gn:country_code":"GR",
    "gn:dem":667,
    "gn:feature_class":"P",
    "gn:feature_code":"PPL",
    "gn:name":"Tran\u00f3valto",
    "gn:population":0,
    "gn:timezone":"Europe/Athens",
    "iso:country":"GR",
    "name:bul_x_preferred":[
        "\u0422\u0440\u0430\u043d\u043e\u0432\u0430\u043b\u0442\u043e"
    ],
    "name:ell_x_preferred":[
        "Tran\u00f3valto"
    ],
    "name:ell_x_variant":[
        "\u03a4\u03c1\u03b1\u03bd\u03cc\u03b2\u03b1\u03bb\u03c4\u03bf",
        "Tran\u00f3valton",
        "\u03a4\u03c1\u03b1\u03bd\u03cc\u03b2\u03b1\u03bb\u03c4\u03bf\u03bd"
    ],
    "name:nno_x_preferred":[
        "Tran\u00f3valto"
    ],
    "wof:name":"Tranovalto",
    "wof:placetype":"locality"
},
  "geometry": {"coordinates":[21.8664,40.05904],"type":"Point"}
}