{
  "type": "Feature",
  "properties": {
    "gn:admin1_code":"ESYE14",
    "gn:admin2_code":"21.0",
    "gn:admin3_code":"9101",
    "gn:asciiname":"Elia",
    "gn:country_code":"GR",
    "gn:dem":175,
    "gn:feature_class":"P",
    "gn:feature_code":"PPL",
    "gn:name":"Eli\u00e1",
    "gn:population":0,
    "gn:timezone":"Europe/Athens",
    "iso:country":"GR",
    "name:ell_x_preferred":[
        "\u0395\u03bb\u03b9\u03ac"
    ],
    "name:und_x_variant":[
        "Kichil\u00e9r",
        "Eli\u00e1",
        "Ela\u00eda"
    ],
    "wof:name":"Elia",
    "wof:placetype":"locality"
},
  "geometry": {"coordinates":[22.44164,39.85758],"type":"Point"}
}