{
  "type": "Feature",
  "properties": {
    "gn:admin1_code":"ESYE23",
    "gn:admin2_code":"31.0",
    "gn:admin3_code":"9128",
    "gn:asciiname":"Paliopyrgos",
    "gn:country_code":"GR",
    "gn:dem":734,
    "gn:feature_class":"P",
    "gn:feature_code":"PPL",
    "gn:name":"Pali\u00f3pyrgos",
    "gn:population":0,
    "gn:timezone":"Europe/Athens",
    "iso:country":"GR",
    "name:ell_x_preferred":[
        "\u03a0\u03b1\u03bb\u03b1\u03b9\u03cc\u03c0\u03c5\u03c1\u03b3\u03bf\u03c2"
    ],
    "name:ell_x_variant":[
        "Pali\u00f3pyrgos",
        "\u03a0\u03b1\u03bb\u03b9\u03cc\u03c0\u03c5\u03c1\u03b3\u03bf\u03c2"
    ],
    "name:und_x_variant":[
        "Velv\u00edtsaina",
        "Pali\u00f3pirgos",
        "Palai\u00f3pirgos"
    ],
    "wof:name":"Paliopyrgos",
    "wof:placetype":"locality"
},
  "geometry": {"coordinates":[21.84211,38.49856],"type":"Point"}
}