{
  "type": "Feature",
  "properties": {
    "gn:admin1_code":"ESYE12",
    "gn:admin2_code":"5.0",
    "gn:admin3_code":"9051",
    "gn:asciiname":"Sykia",
    "gn:country_code":"GR",
    "gn:dem":263,
    "gn:feature_class":"P",
    "gn:feature_code":"PPL",
    "gn:name":"Syki\u00e1",
    "gn:population":50,
    "gn:timezone":"Europe/Athens",
    "iso:country":"GR",
    "name:bul_x_preferred":[
        "\u0421\u043e\u043a\u043e\u043b"
    ],
    "name:bul_x_variant":[
        "\u0421\u0438\u043a\u0435\u0430",
        "\u0421\u0438\u043a\u0438\u044f"
    ],
    "name:ceb_x_preferred":[
        "Sykia"
    ],
    "name:ell_x_historical":[
        "\u03a3\u03bf\u03ba\u03cc\u03bb"
    ],
    "name:ell_x_preferred":[
        "\u03a3\u03c5\u03ba\u03b9\u03ac"
    ],
    "name:ell_x_variant":[
        "Syki\u00e1",
        "\u03a3\u03c5\u03ba\u03ad\u03b1",
        "\u03a3\u03bf\u03ba\u03cc\u03bb"
    ],
    "name:eng_x_preferred":[
        "Sykia"
    ],
    "name:mkd_x_preferred":[
        "\u0421\u043e\u043a\u043e\u043b"
    ],
    "name:swe_x_preferred":[
        "Sykia"
    ],
    "name:und_x_variant":[
        "Siki\u00e1",
        "Svik\u00e1",
        "Sok\u00f3l",
        "Sik\u00e9a"
    ],
    "wof:name":"Sykia",
    "wof:placetype":"locality",
    "wof:population":50
},
  "geometry": {"coordinates":[23.72588,41.0836],"type":"Point"}
}