{
  "type": "Feature",
  "properties": {
    "gn:gn_country":"GR",
    "gn:gn_fcode":"PPL",
    "gn:gn_pop":60,
    "gn:population":36,
    "iso:country":"GR",
    "name:ell_x_preferred":[
        "\u03a3\u03c0\u03b1\u03c1\u03c4\u03bf\u03cd\u03bd\u03c4\u03b1"
    ],
    "name:eng_x_preferred":[
        "Spartounda"
    ],
    "qs_pg:aaroncc":"GR",
    "qs_pg:gn_country":"GR",
    "qs_pg:gn_fcode":"PPL",
    "qs_pg:gn_pop":60,
    "qs_pg:name":"Spartounta",
    "qs_pg:name_adm0":"\u0395\u03bb\u03bb\u03ac\u03b4\u03b1",
    "qs_pg:name_adm1":"Aegean",
    "qs_pg:photos_9k":1,
    "qs_pg:photos_9r":2,
    "qs_pg:photos_all":28,
    "qs_pg:photos_sr":0,
    "qs_pg:pop_sr":1,
    "qs_pg:qs_pg_placetype":"locality",
    "qs_pg:qs_pg_placetype_gp":"Town",
    "qs_pg:woe_adm0":23424833,
    "woe:adm0_id":23424833,
    "woe:name_adm0":"\u0395\u03bb\u03bb\u03ac\u03b4\u03b1",
    "woe:name_adm1":"Aegean",
    "woe:placetype":"Town",
    "wof:name":"Spartounta",
    "wof:placetype":"locality",
    "wof:population":36
},
  "geometry": {"coordinates":[25.99303,38.54375],"type":"Point"}
}