{
  "type": "Feature",
  "properties": {
    "gn:admin1_code":"ESYE25",
    "gn:asciiname":"Agkistri",
    "gn:country_code":"GR",
    "gn:dem":183,
    "gn:feature_class":"P",
    "gn:feature_code":"PPL",
    "gn:name":"Agk\u00edstri",
    "gn:population":0,
    "gn:timezone":"Europe/Athens",
    "iso:country":"GR",
    "name:ell_x_preferred":[
        "\u0391\u03b3\u03ba\u03af\u03c3\u03c4\u03c1\u03b9"
    ],
    "name:eng_x_preferred":[
        "Angistri"
    ],
    "name:eng_x_variant":[
        "Agistri"
    ],
    "wof:name":"Agkistri",
    "wof:placetype":"locality"
},
  "geometry": {"coordinates":[23.3456,37.6917],"type":"Point"}
}