{
  "type": "Feature",
  "properties": {
    "gn:admin1_code":"ESYE42",
    "gn:admin2_code":"49.0",
    "gn:admin3_code":"9291",
    "gn:asciiname":"Rachoula",
    "gn:country_code":"GR",
    "gn:dem":211,
    "gn:feature_class":"P",
    "gn:feature_code":"PPL",
    "gn:name":"Racho\u00fala",
    "gn:population":10,
    "gn:timezone":"Europe/Athens",
    "iso:country":"GR",
    "name:ell_x_preferred":[
        "\u03a1\u03b1\u03c7\u03bf\u03cd\u03bb\u03b1"
    ],
    "name:eng_x_preferred":[
        "Rachoula"
    ],
    "wof:name":"Rachoula",
    "wof:placetype":"locality",
    "wof:population":10
},
  "geometry": {"coordinates":[25.80521,36.79358],"type":"Point"}
}