{
  "type": "Feature",
  "properties": {
    "gn:admin1_code":"ESYE23",
    "gn:admin2_code":"38.0",
    "gn:admin3_code":"9134",
    "gn:asciiname":"Perivola",
    "gn:country_code":"GR",
    "gn:dem":102,
    "gn:feature_class":"P",
    "gn:feature_code":"PPL",
    "gn:name":"Periv\u00f3la",
    "gn:population":0,
    "gn:timezone":"Europe/Athens",
    "iso:country":"GR",
    "name:ell_x_preferred":[
        "Periv\u00f3la"
    ],
    "name:ell_x_variant":[
        "\u03a0\u03b5\u03c1\u03b9\u03b2\u03cc\u03bb\u03b1"
    ],
    "wof:name":"Perivola",
    "wof:placetype":"locality"
},
  "geometry": {"coordinates":[21.77053,38.21114],"type":"Point"}
}