{
  "type": "Feature",
  "properties": {
    "gn:admin1_code":"ESYE13",
    "gn:admin2_code":"10.0",
    "gn:admin3_code":"9061",
    "gn:asciiname":"Mesolakkos",
    "gn:country_code":"GR",
    "gn:dem":615,
    "gn:feature_class":"P",
    "gn:feature_code":"PPL",
    "gn:name":"Mes\u00f3lakkos",
    "gn:population":0,
    "gn:timezone":"Europe/Athens",
    "iso:country":"GR",
    "name:bul_x_preferred":[
        "\u041c\u0435\u0441\u043e\u043b\u0430\u043a\u043e\u0441"
    ],
    "name:ell_x_preferred":[
        "\u039c\u03b5\u03c3\u03cc\u03bb\u03b1\u03ba\u03ba\u03bf\u03c2"
    ],
    "name:ell_x_variant":[
        "\u039c\u03b5\u03c3\u03cc\u03bb\u03b1\u03ba\u03ba\u03bf\u03c2 \u0393\u03c1\u03b5\u03b2\u03b5\u03bd\u03ce\u03bd"
    ],
    "name:mkd_x_preferred":[
        "\u0417\u0438\u0433\u043e\u0441\u0442"
    ],
    "name:und_x_variant":[
        "Zig\u00f3sti",
        "Mes\u00f3lakkos"
    ],
    "wof:name":"Mesolakkos",
    "wof:placetype":"locality"
},
  "geometry": {"coordinates":[21.51392,40.08543],"type":"Point"}
}