{
  "type": "Feature",
  "properties": {
    "gn:admin1_code":"ESYE43",
    "gn:admin2_code":"43.0",
    "gn:admin3_code":"9322",
    "gn:asciiname":"Marediana",
    "gn:country_code":"GR",
    "gn:dem":215,
    "gn:feature_class":"P",
    "gn:feature_code":"PPL",
    "gn:name":"Maredian\u00e1",
    "gn:population":35,
    "gn:timezone":"Europe/Athens",
    "iso:country":"GR",
    "name:ell_x_preferred":[
        "\u039c\u03b1\u03c1\u03b5\u03b4\u03b9\u03b1\u03bd\u03ac"
    ],
    "name:eng_x_preferred":[
        "Marediana"
    ],
    "name:und_x_variant":[
        "Maredhian\u00e1",
        "Maredian\u00e1"
    ],
    "wof:name":"Marediana",
    "wof:placetype":"locality",
    "wof:population":35
},
  "geometry": {"coordinates":[23.66765,35.46939000000001],"type":"Point"}
}