{
  "type": "Feature",
  "properties": {
    "iso:country":"GR",
    "qs:a0":"Greece",
    "qs:a1":"*\u0391\u039d\u0391\u03a4\u039f\u039b\u0399\u039a\u0397 \u039c\u0391\u039a\u0395\u0394\u039f\u039d\u0399\u0391 \u039a\u0391\u0399 \u0398\u03a1\u0391\u039a\u0397",
    "qs:a1_alt":"ANATOLIKH MAKEDONIA KAI URAKH",
    "qs:a1r":"0",
    "qs:a2_alt":"EBROS",
    "qs:adm0":"Greece",
    "qs:la_lc":"*",
    "qs:level":"locality",
    "qs:loc":"\u039d\u0395\u039f\u03a7\u03a9\u03a1\u0399\u039f\u039d",
    "qs:loc_alt":"NEOXVRION",
    "qs:pop":0,
    "qs:type":"buffered point",
    "wof:name":"\u039d\u0395\u039f\u03a7\u03a9\u03a1\u0399\u039f\u039d",
    "wof:placetype":"locality"
},
  "geometry": {"coordinates":[26.459063,41.510613],"type":"Point"}
}