{
  "type": "Feature",
  "properties": {
    "gn:admin1_code":"ESYE25",
    "gn:admin2_code":"42.0",
    "gn:admin3_code":"9252",
    "gn:asciiname":"Vergadhaiika",
    "gn:cc2":"GR",
    "gn:country_code":"GR",
    "gn:dem":545,
    "gn:feature_class":"P",
    "gn:feature_code":"PPL",
    "gn:name":"Vergadha\u00edika",
    "gn:population":0,
    "gn:timezone":"Europe/Athens",
    "iso:country":"GR",
    "name:ell_x_preferred":[
        "\u0392\u03b5\u03c1\u03b3\u03b1\u03b4\u03b1\u03af\u03b9\u03ba\u03b1"
    ],
    "name:ell_x_variant":[
        "\u0392\u03b5\u03c1\u03b3\u03b1\u03b4\u03b1\u0390\u03b9\u03ba\u03b1"
    ],
    "name:und_x_variant":[
        "Vergadh\u00e9\u00efka",
        "Vergadha\u00edika"
    ],
    "wof:name":"Vergadhaiika",
    "wof:placetype":"locality"
},
  "geometry": {"coordinates":[22.26238,37.22807],"type":"Point"}
}