{
  "type": "Feature",
  "properties": {
    "gn:gn_country":"GR",
    "gn:gn_fcode":"PPL",
    "gn:gn_pop":1904,
    "gn:population":1954,
    "iso:country":"GR",
    "name:ara_x_preferred":[
        "\u0643\u0627\u062a\u0648 \u0633\u0643\u0648\u0644\u0627\u0631\u064a\u0648\u0646\u060c \u062b\u064a\u0633\u0627\u0644\u0648\u0646\u064a\u0643\u064a"
    ],
    "name:bul_x_preferred":[
        "\u041a\u0430\u0442\u043e \u0421\u0445\u043e\u043b\u0430\u0440\u0438"
    ],
    "name:dut_x_preferred":[
        "Kato Scholari"
    ],
    "name:ell_x_preferred":[
        "\u039a\u03ac\u03c4\u03c9 \u03a3\u03c7\u03bf\u03bb\u03ac\u03c1\u03b9\u03bf\u03bd"
    ],
    "name:ell_x_variant":[
        "K\u00e1to Schol\u00e1ri",
        "\u039a\u03ac\u03c4\u03c9 \u03a3\u03c7\u03bf\u03bb\u03ac\u03c1\u03b9",
        "K\u00e1to Schol\u00e1rion"
    ],
    "name:eng_x_preferred":[
        "Kato Scholari"
    ],
    "name:gre_x_preferred":[
        "\u039a\u03ac\u03c4\u03c9 \u03a3\u03c7\u03bf\u03bb\u03ac\u03c1\u03b9 \u0398\u03b5\u03c3\u03c3\u03b1\u03bb\u03bf\u03bd\u03af\u03ba\u03b7\u03c2"
    ],
    "name:mac_x_preferred":[
        "\u0410\u0434\u0430\u043b\u0438"
    ],
    "name:swe_x_preferred":[
        "K\u00e1to Schol\u00e1ri"
    ],
    "name:unk_x_variant":[
        "Adal\u00ed"
    ],
    "qs_pg:aaroncc":"GR",
    "qs_pg:gn_country":"GR",
    "qs_pg:gn_fcode":"PPL",
    "qs_pg:gn_pop":1904,
    "qs_pg:name":"Kato Skholarion",
    "qs_pg:name_adm0":"\u0395\u03bb\u03bb\u03ac\u03b4\u03b1",
    "qs_pg:name_adm1":"Macedonia and Thrace",
    "qs_pg:photos_9r":0,
    "qs_pg:photos_sr":0,
    "qs_pg:pop_sr":3,
    "qs_pg:qs_pg_placetype":"locality",
    "qs_pg:qs_pg_placetype_gp":"Town",
    "qs_pg:woe_adm0":23424833,
    "woe:adm0_id":23424833,
    "woe:name_adm0":"\u0395\u03bb\u03bb\u03ac\u03b4\u03b1",
    "woe:name_adm1":"Macedonia and Thrace",
    "woe:placetype":"Town",
    "wof:name":"Kato Skholarion",
    "wof:placetype":"locality",
    "wof:population":1954
},
  "geometry": {"coordinates":[23.03333,40.43333],"type":"Point"}
}