{
  "type": "Feature",
  "properties": {
    "gn:admin1_code":"ESYE23",
    "gn:admin2_code":"38.0",
    "gn:admin3_code":"9133",
    "gn:asciiname":"Planitero",
    "gn:country_code":"GR",
    "gn:dem":679,
    "gn:feature_class":"P",
    "gn:feature_code":"PPL",
    "gn:name":"Planit\u00e9ro",
    "gn:population":0,
    "gn:timezone":"Europe/Athens",
    "iso:country":"GR",
    "name:ell_x_preferred":[
        "Planit\u00e9ro"
    ],
    "name:ell_x_variant":[
        "\u03a0\u03bb\u03b1\u03bd\u03b9\u03c4\u03ad\u03c1\u03bf",
        "Planit\u00e9ron",
        "\u03a0\u03bb\u03b1\u03bd\u03b9\u03c4\u03ad\u03c1\u03bf\u03bd"
    ],
    "wof:name":"Planitero",
    "wof:placetype":"locality"
},
  "geometry": {"coordinates":[22.16722,37.93647],"type":"Point"}
}