{
  "type": "Feature",
  "properties": {
    "gn:admin1_code":"ESYE43",
    "gn:admin2_code":"43.0",
    "gn:admin3_code":"9323",
    "gn:asciiname":"Pananiana",
    "gn:country_code":"GR",
    "gn:dem":446,
    "gn:feature_class":"P",
    "gn:feature_code":"PPL",
    "gn:name":"Pananian\u00e1",
    "gn:population":0,
    "gn:timezone":"Europe/Athens",
    "iso:country":"GR",
    "name:ell_x_preferred":[
        "\u03a0\u03b1\u03bd\u03b1\u03bd\u03b9\u03b1\u03bd\u03ac"
    ],
    "name:und_x_variant":[
        "Panay\u00eda",
        "Pananian\u00e1"
    ],
    "wof:name":"Pananiana",
    "wof:placetype":"locality"
},
  "geometry": {"coordinates":[23.7679,35.40691],"type":"Point"}
}