{
  "type": "Feature",
  "properties": {
    "gn:admin1_code":"ESYE31",
    "gn:admin2_code":"445406.0",
    "gn:admin3_code":"9221.0",
    "gn:asciiname":"Natso",
    "gn:country_code":"GR",
    "gn:dem":54,
    "gn:feature_class":"P",
    "gn:feature_code":"PPL",
    "gn:name":"N\u00e1tso",
    "gn:population":0,
    "gn:timezone":"Europe/Athens",
    "iso:country":"GR",
    "name:ell_x_preferred":[
        "N\u00e1tso"
    ],
    "name:ell_x_variant":[
        "\u039d\u03ac\u03c4\u03c3\u03bf"
    ],
    "wof:name":"Natso",
    "wof:placetype":"locality"
},
  "geometry": {"coordinates":[24.04388,37.85822],"type":"Point"}
}