{
  "type": "Feature",
  "properties": {
    "gn:admin1_code":"ESYE43",
    "gn:admin2_code":"45.0",
    "gn:admin3_code":"9303",
    "gn:asciiname":"Xeniakos",
    "gn:cc2":"GR",
    "gn:country_code":"GR",
    "gn:dem":483,
    "gn:feature_class":"P",
    "gn:feature_code":"PPL",
    "gn:name":"Xeni\u00e1kos",
    "gn:population":0,
    "gn:timezone":"Europe/Athens",
    "iso:country":"GR",
    "name:und_x_variant":[
        "X\u00e9niako",
        "Xeni\u00e1kos"
    ],
    "wof:name":"Xeniakos",
    "wof:placetype":"locality"
},
  "geometry": {"coordinates":[25.39979,35.09681],"type":"Point"}
}