{
  "type": "Feature",
  "properties": {
    "gn:admin1_code":"ESYE31",
    "gn:admin2_code":"445406.0",
    "gn:admin3_code":"9219",
    "gn:asciiname":"Myrteza",
    "gn:country_code":"GR",
    "gn:dem":154,
    "gn:feature_class":"P",
    "gn:feature_code":"PPL",
    "gn:name":"Myrt\u00e9za",
    "gn:population":164,
    "gn:timezone":"Europe/Athens",
    "iso:country":"GR",
    "name:ell_x_preferred":[
        "\u039c\u03c5\u03c1\u03c4\u03ad\u03b6\u03b1"
    ],
    "wof:name":"Myrteza",
    "wof:placetype":"locality",
    "wof:population":164
},
  "geometry": {"coordinates":[24.02817000000001,37.81867],"type":"Point"}
}