{
  "type": "Feature",
  "properties": {
    "gn:admin1_code":"ESYE11",
    "gn:admin2_code":"3.0",
    "gn:admin3_code":"9017",
    "gn:asciiname":"Peva Mahale",
    "gn:cc2":"GR",
    "gn:country_code":"GR",
    "gn:dem":435,
    "gn:feature_class":"P",
    "gn:feature_code":"PPL",
    "gn:name":"P\u00e9va Mahal\u00e9",
    "gn:population":0,
    "gn:timezone":"Europe/Athens",
    "iso:country":"GR",
    "name:und_x_variant":[
        "P\u00e9va Makhal\u00e9",
        "P\u00e9va Mahal\u00e9"
    ],
    "wof:name":"Peva Mahale",
    "wof:placetype":"locality"
},
  "geometry": {"coordinates":[24.96667,41.15],"type":"Point"}
}