{
  "type": "Feature",
  "properties": {
    "gn:country":"GR",
    "gn:fcode":"PPL",
    "gn:population":0,
    "iso:country":"GR",
    "name:bul_x_preferred":[
        "\u041a\u0430\u0432\u0443\u0441\u0438"
    ],
    "name:deu_x_preferred":[
        "Kavousi"
    ],
    "name:ell_x_preferred":[
        "\u039a\u03b1\u03b2\u03bf\u03cd\u03c3\u03b9"
    ],
    "name:ell_x_variant":[
        "\u039a\u03b1\u03b2\u03bf\u03cd\u03c3\u03b9 \u039b\u03b1\u03c3\u03b9\u03b8\u03af\u03bf\u03c5"
    ],
    "name:eng_x_preferred":[
        "Kavousi"
    ],
    "name:fas_x_preferred":[
        "\u06a9\u0627\u0648\u0633\u06cc"
    ],
    "name:fin_x_preferred":[
        "Kavo\u00fasi"
    ],
    "name:fra_x_preferred":[
        "Kavousi"
    ],
    "name:nld_x_preferred":[
        "Kavousi"
    ],
    "name:spa_x_preferred":[
        "Kavusi"
    ],
    "qs_pg:aaroncc":"GR",
    "qs_pg:gn_country":"GR",
    "qs_pg:gn_fcode":"PPL",
    "qs_pg:gn_pop":0,
    "qs_pg:name":"Kavousi",
    "qs_pg:name_adm0":"\u0395\u03bb\u03bb\u03ac\u03b4\u03b1",
    "qs_pg:name_adm1":"Crete",
    "qs_pg:photos":123,
    "qs_pg:photos_1k":25,
    "qs_pg:photos_9k":1,
    "qs_pg:photos_9r":3,
    "qs_pg:photos_all":123,
    "qs_pg:photos_sr":3,
    "qs_pg:pop_sr":0,
    "qs_pg:qs_pg_placetype":"locality",
    "qs_pg:qs_pg_placetype_gp":"Town",
    "qs_pg:woe_adm0":23424833,
    "woe:adm0_id":23424833,
    "woe:name_adm0":"\u0395\u03bb\u03bb\u03ac\u03b4\u03b1",
    "woe:name_adm1":"Crete",
    "woe:placetype":"Town",
    "wof:name":"Kavousi",
    "wof:placetype":"locality",
    "wof:population":559
},
  "geometry": {"coordinates":[25.85701,35.12599],"type":"Point"}
}