{
  "type": "Feature",
  "properties": {
    "gn:admin1_code":"ESYE25",
    "gn:admin2_code":"41.0",
    "gn:admin3_code":"9239",
    "gn:asciiname":"Neo Psathi",
    "gn:country_code":"GR",
    "gn:dem":421,
    "gn:feature_class":"P",
    "gn:feature_code":"PPL",
    "gn:name":"N\u00e9o Psath\u00ed",
    "gn:population":0,
    "gn:timezone":"Europe/Athens",
    "iso:country":"GR",
    "name:ell_x_preferred":[
        "N\u00e9o Psath\u00ed"
    ],
    "name:ell_x_variant":[
        "\u039d\u03ad\u03bf \u03a8\u03b1\u03b8\u03af"
    ],
    "name:und_x_variant":[
        "Ayi\u00e1spe\u00ef",
        "Psath\u00ed",
        "Psath\u00edon"
    ],
    "wof:name":"Neo Psathi",
    "wof:placetype":"locality"
},
  "geometry": {"coordinates":[22.1293,37.39626],"type":"Point"}
}