{
  "type": "Feature",
  "properties": {
    "gn:country":"GR",
    "gn:fcode":"PPL",
    "gn:population":875,
    "iso:country":"GR",
    "name:ara_x_preferred":[
        "\u0633\u064a\u0634\u0646\u060c \u0644\u0627\u0633\u064a\u062b\u064a"
    ],
    "name:ara_x_variant":[
        "\u0633\u064a\u0634\u0646"
    ],
    "name:arz_x_preferred":[
        "\u0633\u064a\u0633\u0649"
    ],
    "name:ceb_x_preferred":[
        "S\u00edsion"
    ],
    "name:deu_x_preferred":[
        "Sissi"
    ],
    "name:ell_x_preferred":[
        "\u03a3\u03af\u03c3\u03b9\u03bf\u03bd"
    ],
    "name:ell_x_variant":[
        "\u03a3\u03af\u03c3\u03b9",
        "\u03a3\u03af\u03c3\u03b9 \u039b\u03b1\u03c3\u03b9\u03b8\u03af\u03bf\u03c5"
    ],
    "name:eng_x_preferred":[
        "Sisi"
    ],
    "name:fin_x_preferred":[
        "S\u00edsi"
    ],
    "name:fra_x_preferred":[
        "Sisi"
    ],
    "name:fra_x_variant":[
        "S\u00edsi"
    ],
    "name:nld_x_preferred":[
        "Sisi"
    ],
    "name:por_x_preferred":[
        "Sisi"
    ],
    "name:spa_x_preferred":[
        "Sisi"
    ],
    "name:swe_x_preferred":[
        "S\u00edsion"
    ],
    "name:und_x_variant":[
        "K\u00e1to S\u00edsi"
    ],
    "qs_pg:aaroncc":"GR",
    "qs_pg:gn_country":"GR",
    "qs_pg:gn_fcode":"PPL",
    "qs_pg:gn_pop":875,
    "qs_pg:name":"Kato Sisi",
    "qs_pg:name_adm0":"\u0395\u03bb\u03bb\u03ac\u03b4\u03b1",
    "qs_pg:name_adm1":"Crete",
    "qs_pg:photos":95,
    "qs_pg:photos_1k":19,
    "qs_pg:photos_9k":1,
    "qs_pg:photos_9r":3,
    "qs_pg:photos_all":95,
    "qs_pg:photos_sr":3,
    "qs_pg:pop_sr":2,
    "qs_pg:qs_pg_placetype":"locality",
    "qs_pg:qs_pg_placetype_gp":"Town",
    "qs_pg:woe_adm0":23424833,
    "woe:adm0_id":23424833,
    "woe:name_adm0":"\u0395\u03bb\u03bb\u03ac\u03b4\u03b1",
    "woe:name_adm1":"Crete",
    "woe:placetype":"Town",
    "wof:name":"Kato Sisi",
    "wof:placetype":"locality",
    "wof:population":1003
},
  "geometry": {"coordinates":[25.52021,35.3077],"type":"Point"}
}