{
  "type": "Feature",
  "properties": {
    "gn:admin1_code":"ESYE23",
    "gn:admin2_code":"31.0",
    "gn:admin3_code":"9123",
    "gn:asciiname":"Ellinikon",
    "gn:country_code":"GR",
    "gn:dem":298,
    "gn:feature_class":"P",
    "gn:feature_code":"PPL",
    "gn:name":"Ellinik\u00f3n",
    "gn:population":62,
    "gn:timezone":"Europe/Athens",
    "iso:country":"GR",
    "name:ell_x_historical":[
        "\u0395\u03bb\u03bb\u03b7\u03bd\u03b9\u03ba\u03cc\u03c2"
    ],
    "name:ell_x_preferred":[
        "\u0395\u03bb\u03bb\u03b7\u03bd\u03b9\u03ba\u03cc"
    ],
    "name:ell_x_variant":[
        "\u0395\u03bb\u03bb\u03b7\u03bd\u03b9\u03ba\u03cc\u03c2",
        "\u0395\u03bb\u03bb\u03b7\u03bd\u03b9\u03ba\u03cc\u03bd"
    ],
    "name:eng_x_historical":[
        "Ellinikos"
    ],
    "name:eng_x_preferred":[
        "Ellinikos"
    ],
    "name:eng_x_variant":[
        "Ellinikon"
    ],
    "wof:name":"Ellinikon",
    "wof:placetype":"locality",
    "wof:population":62
},
  "geometry": {"coordinates":[21.47645,38.69378],"type":"Point"}
}