{
  "type": "Feature",
  "properties": {
    "gn:admin1_code":"ESYE21",
    "gn:admin2_code":"20.0",
    "gn:admin3_code":"9074",
    "gn:asciiname":"Karachristaiika",
    "gn:cc2":"GR",
    "gn:country_code":"GR",
    "gn:dem":510,
    "gn:feature_class":"P",
    "gn:feature_code":"PPL",
    "gn:name":"Karachrista\u00edika",
    "gn:population":0,
    "gn:timezone":"Europe/Athens",
    "iso:country":"GR",
    "name:und_x_variant":[
        "Karakhrista\u00edika",
        "Karachrista\u00edika"
    ],
    "wof:name":"Karachristaiika",
    "wof:placetype":"locality"
},
  "geometry": {"coordinates":[21.24056,39.14667],"type":"Point"}
}