{
  "type": "Feature",
  "properties": {
    "gn:population":1095,
    "iso:country":"GR",
    "name:ara_x_preferred":[
        "\u0643\u064a\u0628\u0631\u064a\u0646\u0648\u0633"
    ],
    "name:bul_x_preferred":[
        "\u0421\u0430\u0440\u044a\u0445\u0430\u0434\u044a\u0440"
    ],
    "name:ceb_x_preferred":[
        "Kypr\u00ednos"
    ],
    "name:ell_x_preferred":[
        "\u039a\u03c5\u03c0\u03c1\u03af\u03bd\u03bf\u03c2 \u0388\u03b2\u03c1\u03bf\u03c5"
    ],
    "name:ell_x_variant":[
        "\u039a\u03c5\u03c0\u03c1\u03af\u03bd\u03bf\u03c2",
        "Kypr\u00ednos"
    ],
    "name:eng_x_preferred":[
        "Kyprinos"
    ],
    "name:fin_x_preferred":[
        "Kypr\u00ednos"
    ],
    "name:fra_x_preferred":[
        "Kyprinos"
    ],
    "name:isl_x_preferred":[
        "Kyprinos"
    ],
    "name:ita_x_preferred":[
        "Kyprinos"
    ],
    "name:jpn_x_preferred":[
        "\u30ad\u30d7\u30ea\u30ce\u30b9"
    ],
    "name:nld_x_preferred":[
        "Kyprinos"
    ],
    "name:nno_x_preferred":[
        "Kypr\u00ednos"
    ],
    "name:swe_x_preferred":[
        "Kypr\u00ednos"
    ],
    "name:tur_x_preferred":[
        "Sar\u0131h\u0131d\u0131r"
    ],
    "name:und_x_variant":[
        "Kipr\u00ednos"
    ],
    "qs:a0":"Greece",
    "qs:a1":"*\u0391\u039d\u0391\u03a4\u039f\u039b\u0399\u039a\u0397 \u039c\u0391\u039a\u0395\u0394\u039f\u039d\u0399\u0391 \u039a\u0391\u0399 \u0398\u03a1\u0391\u039a\u0397",
    "qs:a1_alt":"ANATOLIKH MAKEDONIA KAI URAKH",
    "qs:a1r":"0",
    "qs:a2_alt":"EBROS",
    "qs:adm0":"Greece",
    "qs:la_lc":"*",
    "qs:level":"locality",
    "qs:loc":"\u039a\u03a5\u03a0\u03a1\u0399\u039d\u039f\u03a3",
    "qs:loc_alt":"KYPRINOS",
    "qs:pop":0,
    "qs:type":"buffered point",
    "wd:wordcount":777,
    "wof:name":"\u039a\u03a5\u03a0\u03a1\u0399\u039d\u039f\u03a3",
    "wof:placetype":"locality",
    "wof:population":1095
},
  "geometry": {"coordinates":[26.217682,41.576706],"type":"Point"}
}