{
  "type": "Feature",
  "properties": {
    "gn:admin1_code":"ESYE43",
    "gn:admin2_code":"45.0",
    "gn:admin3_code":"9305",
    "gn:asciiname":"Foinikia",
    "gn:cc2":"GR",
    "gn:country_code":"GR",
    "gn:dem":35,
    "gn:feature_class":"P",
    "gn:feature_code":"PPL",
    "gn:name":"Foiniki\u00e1",
    "gn:population":0,
    "gn:timezone":"Europe/Athens",
    "iso:country":"GR",
    "name:und_x_variant":[
        "Finoiki\u00e1",
        "Foiniki\u00e1"
    ],
    "wof:name":"Foinikia",
    "wof:placetype":"locality"
},
  "geometry": {"coordinates":[25.10633,35.28136],"type":"Point"}
}