{
  "type": "Feature",
  "properties": {
    "gn:admin1_code":"ESYE24",
    "gn:admin2_code":"34.0",
    "gn:admin3_code":"9151",
    "gn:asciiname":"Giannitsi",
    "gn:country_code":"GR",
    "gn:dem":295,
    "gn:feature_class":"P",
    "gn:feature_code":"PPL",
    "gn:name":"Giann\u00edtsi",
    "gn:population":0,
    "gn:timezone":"Europe/Athens",
    "iso:country":"GR",
    "name:ell_x_preferred":[
        "Giann\u00edtsi"
    ],
    "name:ell_x_variant":[
        "\u0393\u03b9\u03b1\u03bd\u03bd\u03af\u03c4\u03c3\u03b9",
        "Giann\u00edtsion",
        "\u0393\u03b9\u03b1\u03bd\u03bd\u03af\u03c4\u03c3\u03b9\u03bf\u03bd"
    ],
    "name:und_x_variant":[
        "Yiann\u00edtsi",
        "Yiann\u00edtsion"
    ],
    "wof:name":"Giannitsi",
    "wof:placetype":"locality"
},
  "geometry": {"coordinates":[24.39397,38.14406],"type":"Point"}
}