{
  "type": "Feature",
  "properties": {
    "gn:admin1_code":"ESYE14",
    "gn:admin2_code":"24.0",
    "gn:admin3_code":"9105",
    "gn:asciiname":"Mikrothives",
    "gn:country_code":"GR",
    "gn:dem":79,
    "gn:feature_class":"P",
    "gn:feature_code":"PPL",
    "gn:name":"Mikroth\u00edves",
    "gn:population":0,
    "gn:timezone":"Europe/Athens",
    "iso:country":"GR",
    "name:ell_x_preferred":[
        "Mikroth\u00edves"
    ],
    "name:ell_x_variant":[
        "\u039c\u03b9\u03ba\u03c1\u03bf\u03b8\u03ae\u03b2\u03b5\u03c2",
        "\u039c\u03b9\u03ba\u03c1\u03bf\u03b8\u03ae\u03b2\u03b1\u03b9"
    ],
    "name:und_x_variant":[
        "\u00c1kitsi",
        "Mikroth\u00edvai"
    ],
    "wof:name":"Mikrothives",
    "wof:placetype":"locality"
},
  "geometry": {"coordinates":[22.751,39.26322],"type":"Point"}
}