{
  "type": "Feature",
  "properties": {
    "gn:admin1_code":"ESYE11",
    "gn:admin2_code":"14.0",
    "gn:admin3_code":"9011",
    "gn:asciiname":"Skala Sotiros",
    "gn:country_code":"GR",
    "gn:dem":9,
    "gn:feature_class":"P",
    "gn:feature_code":"PPL",
    "gn:name":"Sk\u00e1la Sot\u00edros",
    "gn:population":376,
    "gn:timezone":"Europe/Athens",
    "iso:country":"GR",
    "name:ell_x_preferred":[
        "\u03a3\u03ba\u03ac\u03bb\u03b1 \u03a3\u03c9\u03c4\u03ae\u03c1\u03bf\u03c2"
    ],
    "name:ell_x_variant":[
        "Sk\u00e1la Sot\u00edros"
    ],
    "name:eng_x_preferred":[
        "Skala Sotiros"
    ],
    "wof:name":"Skala Sotiros",
    "wof:placetype":"locality",
    "wof:population":376
},
  "geometry": {"coordinates":[24.5483,40.7288],"type":"Point"}
}