{
  "type": "Feature",
  "properties": {
    "gn:admin1_code":"ESYE14",
    "gn:admin2_code":"23.0",
    "gn:admin3_code":"9095",
    "gn:asciiname":"Kalyvakia",
    "gn:country_code":"GR",
    "gn:dem":93,
    "gn:feature_class":"P",
    "gn:feature_code":"PPL",
    "gn:name":"Kalyv\u00e1kia",
    "gn:population":0,
    "gn:timezone":"Europe/Athens",
    "iso:country":"GR",
    "name:ell_x_preferred":[
        "Kalyv\u00e1kia"
    ],
    "name:ell_x_variant":[
        "\u039a\u03b1\u03bb\u03c5\u03b2\u03ac\u03ba\u03b9\u03b1"
    ],
    "name:und_x_variant":[
        "Kaliv\u00e1kia"
    ],
    "wof:name":"Kalyvakia",
    "wof:placetype":"locality"
},
  "geometry": {"coordinates":[22.07559,39.44595],"type":"Point"}
}