{
  "type": "Feature",
  "properties": {
    "gn:admin1_code":"ESYE25",
    "gn:admin2_code":"42.0",
    "gn:admin3_code":"9248",
    "gn:asciiname":"Mentourgiannika",
    "gn:country_code":"GR",
    "gn:dem":86,
    "gn:feature_class":"P",
    "gn:feature_code":"PPL",
    "gn:name":"Mentourgi\u00e1nnika",
    "gn:population":0,
    "gn:timezone":"Europe/Athens",
    "iso:country":"GR",
    "name:ell_x_preferred":[
        "Mentourgi\u00e1nnika"
    ],
    "name:ell_x_variant":[
        "\u039c\u03b5\u03bd\u03c4\u03bf\u03c5\u03c1\u03b3\u03b9\u03ac\u03bd\u03bd\u03b9\u03ba\u03b1"
    ],
    "name:und_x_variant":[
        "Meniouryi\u00e1nnika"
    ],
    "wof:name":"Mentourgiannika",
    "wof:placetype":"locality"
},
  "geometry": {"coordinates":[22.48125,36.70621],"type":"Point"}
}