{
  "type": "Feature",
  "properties": {
    "gn:admin1_code":"ESYE14",
    "gn:admin2_code":"23.0",
    "gn:admin3_code":"9096",
    "gn:asciiname":"Pyrgos",
    "gn:country_code":"GR",
    "gn:dem":102,
    "gn:feature_class":"P",
    "gn:feature_code":"PPL",
    "gn:name":"P\u00fdrgos",
    "gn:population":0,
    "gn:timezone":"Europe/Athens",
    "iso:country":"GR",
    "name:ell_x_preferred":[
        "\u03a0\u03cd\u03c1\u03b3\u03bf\u03c2"
    ],
    "name:ell_x_variant":[
        "P\u00fdrgos"
    ],
    "name:und_x_variant":[
        "P\u00edrgos Matarangas",
        "P\u00edrgos",
        "Pyrgos Kieriou"
    ],
    "wof:name":"Pyrgos",
    "wof:placetype":"locality"
},
  "geometry": {"coordinates":[22.07521,39.36857],"type":"Point"}
}