{
  "type": "Feature",
  "properties": {
    "gn:admin1_code":"ESYE24",
    "gn:admin2_code":"29.0",
    "gn:admin3_code":"9159",
    "gn:asciiname":"Petroto",
    "gn:country_code":"GR",
    "gn:dem":646,
    "gn:feature_class":"P",
    "gn:feature_code":"PPL",
    "gn:name":"Petrot\u00f3",
    "gn:population":386,
    "gn:timezone":"Europe/Athens",
    "iso:country":"GR",
    "name:ceb_x_preferred":[
        "Petroto"
    ],
    "name:ell_x_preferred":[
        "\u03a0\u03b5\u03c4\u03c1\u03c9\u03c4\u03cc"
    ],
    "name:ell_x_variant":[
        "\u03a0\u03b5\u03c4\u03c1\u03c9\u03c4\u03cc\u03bd"
    ],
    "name:eng_x_preferred":[
        "Petroto"
    ],
    "name:swe_x_preferred":[
        "Petroto"
    ],
    "name:und_x_variant":[
        "Chatm\u00e1s",
        "Tsatm\u00e1s",
        "Petrot\u00f3n"
    ],
    "wof:name":"Petroto",
    "wof:placetype":"locality",
    "wof:population":386
},
  "geometry": {"coordinates":[22.3896,39.18908],"type":"Point"}
}