{
  "type": "Feature",
  "properties": {
    "gn:admin1_code":"ESYE43",
    "gn:admin2_code":"44.0",
    "gn:admin3_code":"9318",
    "gn:asciiname":"Agios Andreas",
    "gn:country_code":"GR",
    "gn:dem":205,
    "gn:feature_class":"P",
    "gn:feature_code":"PPL",
    "gn:name":"\u00c1gios Andr\u00e9as",
    "gn:population":203,
    "gn:timezone":"Europe/Athens",
    "iso:country":"GR",
    "name:ell_x_preferred":[
        "\u0386\u03b3\u03b9\u03bf\u03c2 \u0391\u03bd\u03b4\u03c1\u03ad\u03b1\u03c2"
    ],
    "name:eng_x_preferred":[
        "Agios Andreas"
    ],
    "name:und_x_variant":[
        "\u00c1yios Andhreas",
        "\u00c1yios Andr\u00e9as",
        "\u00c1gios Andr\u00e9as"
    ],
    "wof:name":"Agios Andreas",
    "wof:placetype":"locality",
    "wof:population":203
},
  "geometry": {"coordinates":[24.41386,35.31789000000001],"type":"Point"}
}