{
  "type": "Feature",
  "properties": {
    "gn:admin1_code":"ESYE25",
    "gn:admin2_code":"41.0",
    "gn:admin3_code":"9239",
    "gn:asciiname":"Kyparissia",
    "gn:country_code":"GR",
    "gn:dem":398,
    "gn:feature_class":"P",
    "gn:feature_code":"PPL",
    "gn:name":"Kypar\u00edssia",
    "gn:population":0,
    "gn:timezone":"Europe/Athens",
    "iso:country":"GR",
    "name:ara_x_preferred":[
        "\u0643\u064a\u0628\u0627\u0631\u064a\u0633\u064a\u0627"
    ],
    "name:cat_x_preferred":[
        "Cipar\u00edssia"
    ],
    "name:ceb_x_preferred":[
        "Kypariss\u00eda"
    ],
    "name:deu_x_preferred":[
        "Kyparissia"
    ],
    "name:ell_x_preferred":[
        "Kypar\u00edssia"
    ],
    "name:ell_x_variant":[
        "\u039a\u03c5\u03c0\u03b1\u03c1\u03af\u03c3\u03c3\u03b9\u03b1",
        "\u039a\u03c5\u03c0\u03b1\u03c1\u03b9\u03c3\u03c3\u03af\u03b1"
    ],
    "name:fin_x_preferred":[
        "Kypariss\u00eda"
    ],
    "name:fra_x_preferred":[
        "Kyparissia"
    ],
    "name:ita_x_preferred":[
        "Kyparissia"
    ],
    "name:nld_x_preferred":[
        "Kyparissia"
    ],
    "name:nno_x_preferred":[
        "Kypariss\u00eda"
    ],
    "name:ron_x_preferred":[
        "Kyparissia"
    ],
    "name:rus_x_preferred":[
        "\u041a\u0438\u043f\u0430\u0440\u0438\u0441\u0438\u044f"
    ],
    "name:spa_x_preferred":[
        "Ciparisia"
    ],
    "name:srp_x_preferred":[
        "\u041a\u0438\u043f\u0430\u0440\u0438\u0441\u0438\u0458\u0430"
    ],
    "name:swe_x_preferred":[
        "Kyparissia"
    ],
    "name:und_x_variant":[
        "Kipar\u00edssia"
    ],
    "wof:name":"Kyparissia",
    "wof:placetype":"locality"
},
  "geometry": {"coordinates":[22.06556,37.44488],"type":"Point"}
}