{
  "type": "Feature",
  "properties": {
    "gn:admin1_code":"ESYE25",
    "gn:admin2_code":"41.0",
    "gn:admin3_code":"9239",
    "gn:asciiname":"Kyparissia",
    "gn:country_code":"GR",
    "gn:dem":398,
    "gn:feature_class":"P",
    "gn:feature_code":"PPL",
    "gn:name":"Kypar\u00edssia",
    "gn:population":0,
    "gn:timezone":"Europe/Athens",
    "iso:country":"GR",
    "name:ell_x_preferred":[
        "Kypar\u00edssia"
    ],
    "name:ell_x_variant":[
        "\u039a\u03c5\u03c0\u03b1\u03c1\u03af\u03c3\u03c3\u03b9\u03b1"
    ],
    "name:und_x_variant":[
        "Kipar\u00edssia"
    ],
    "wof:name":"Kyparissia",
    "wof:placetype":"locality"
},
  "geometry": {"coordinates":[22.06556,37.44488],"type":"Point"}
}