{
  "type": "Feature",
  "properties": {
    "gn:admin1_code":"ESYE23",
    "gn:admin2_code":"38.0",
    "gn:admin3_code":"9130",
    "gn:asciiname":"Mertidion",
    "gn:country_code":"GR",
    "gn:dem":283,
    "gn:feature_class":"P",
    "gn:feature_code":"PPL",
    "gn:name":"Mert\u00eddion",
    "gn:population":21,
    "gn:timezone":"Europe/Athens",
    "iso:country":"GR",
    "name:ell_x_preferred":[
        "\u039c\u03b5\u03c1\u03c4\u03af\u03b4\u03b9"
    ],
    "name:eng_x_preferred":[
        "Mertidi"
    ],
    "name:und_x_variant":[
        "Mert\u00eddhi",
        "Mert\u00eddhion"
    ],
    "wof:name":"Mertidion",
    "wof:placetype":"locality",
    "wof:population":21
},
  "geometry": {"coordinates":[22.006,38.2434],"type":"Point"}
}