{
  "type": "Feature",
  "properties": {
    "gn:admin1_code":"ESYE43",
    "gn:admin2_code":"44.0",
    "gn:admin3_code":"9317",
    "gn:asciiname":"Metokhia Kambou",
    "gn:cc2":"GR",
    "gn:country_code":"GR",
    "gn:dem":82,
    "gn:feature_class":"P",
    "gn:feature_code":"PPL",
    "gn:name":"Met\u00f3khia K\u00e1mbou",
    "gn:population":0,
    "gn:timezone":"Europe/Athens",
    "iso:country":"GR",
    "name:und_x_variant":[
        "K\u00e1mbou Met\u00f3khia",
        "Met\u00f3khia",
        "Met\u00f3khia K\u00e1mbou"
    ],
    "wof:name":"Metokhia Kambou",
    "wof:placetype":"locality"
},
  "geometry": {"coordinates":[24.68333,35.38333],"type":"Point"}
}