{
  "type": "Feature",
  "properties": {
    "gn:admin1_code":"ESYE12",
    "gn:admin2_code":"13.0",
    "gn:admin3_code":"9030",
    "gn:asciiname":"Troulos",
    "gn:cc2":"GR",
    "gn:country_code":"GR",
    "gn:dem":171,
    "gn:feature_class":"P",
    "gn:feature_code":"PPL",
    "gn:name":"Tro\u00falos",
    "gn:population":0,
    "gn:timezone":"Europe/Athens",
    "iso:country":"GR",
    "name:und_x_variant":[
        "Semsel\u00ed",
        "Tro\u00falos"
    ],
    "wof:name":"Troulos",
    "wof:placetype":"locality"
},
  "geometry": {"coordinates":[23.03333,40.45],"type":"Point"}
}