{
  "type": "Feature",
  "properties": {
    "gn:admin1_code":"ESYE31",
    "gn:admin2_code":"445406.0",
    "gn:admin3_code":"9224.0",
    "gn:asciiname":"Perivolakia",
    "gn:country_code":"GR",
    "gn:dem":85,
    "gn:feature_class":"P",
    "gn:feature_code":"PPL",
    "gn:name":"Perivol\u00e1kia",
    "gn:population":0,
    "gn:timezone":"Europe/Athens",
    "iso:country":"GR",
    "name:ell_x_preferred":[
        "Perivol\u00e1kia"
    ],
    "name:ell_x_variant":[
        "\u03a0\u03b5\u03c1\u03b9\u03b2\u03bf\u03bb\u03ac\u03ba\u03b9\u03b1"
    ],
    "wof:name":"Perivolakia",
    "wof:placetype":"locality"
},
  "geometry": {"coordinates":[23.99369,38.0083],"type":"Point"}
}