{
  "type": "Feature",
  "properties": {
    "gn:admin1_code":"ESYE21",
    "gn:admin2_code":"18.0",
    "gn:admin3_code":"9078",
    "gn:asciiname":"Agios Panteleimonas",
    "gn:cc2":"GR",
    "gn:country_code":"GR",
    "gn:dem":260,
    "gn:feature_class":"P",
    "gn:feature_code":"PPL",
    "gn:name":"\u00c1gios Pantele\u00edmonas",
    "gn:population":0,
    "gn:timezone":"Europe/Athens",
    "iso:country":"GR",
    "name:ron_x_preferred":[
        "Agios Panteleimonas"
    ],
    "name:und_x_variant":[
        "Virv\u00edtsa",
        "\u00c1gios Pantele\u00edmonas"
    ],
    "wof:name":"Agios Panteleimonas",
    "wof:placetype":"locality"
},
  "geometry": {"coordinates":[20.39861,39.43778],"type":"Point"}
}