{
  "type": "Feature",
  "properties": {
    "iso:country":"GR",
    "qs_pg:aaroncc":"GR",
    "qs_pg:name":"Vellou",
    "qs_pg:name_adm0":"\u0395\u03bb\u03bb\u03ac\u03b4\u03b1",
    "qs_pg:name_adm1":"Peloponnese Western Greece and the Ionian Islands",
    "qs_pg:photos":48,
    "qs_pg:photos_1k":10,
    "qs_pg:photos_9k":1,
    "qs_pg:photos_9r":2,
    "qs_pg:photos_all":48,
    "qs_pg:photos_sr":2,
    "qs_pg:pop_sr":0,
    "qs_pg:qs_pg_placetype":"locality",
    "qs_pg:qs_pg_placetype_gp":"Town",
    "qs_pg:woe_adm0":23424833,
    "woe:adm0_id":23424833,
    "woe:name_adm0":"\u0395\u03bb\u03bb\u03ac\u03b4\u03b1",
    "woe:name_adm1":"Peloponnese Western Greece and the Ionian Islands",
    "woe:placetype":"Town",
    "wof:name":"Vellou",
    "wof:placetype":"locality"
},
  "geometry": {"coordinates":[22.778091,37.972146],"type":"Point"}
}