{
  "type": "Feature",
  "properties": {
    "gn:country":"GR",
    "gn:fcode":"ADM3",
    "gn:population":18259,
    "iso:country":"GR",
    "name:ell_x_preferred":[
        "\u0391\u03c1\u03c1\u03b9\u03b1\u03bd\u03ce\u03bd"
    ],
    "qs_pg:aaroncc":"GR",
    "qs_pg:gn_country":"GR",
    "qs_pg:gn_fcode":"ADM3",
    "qs_pg:gn_pop":18259,
    "qs_pg:name":"Dimos Arriana",
    "qs_pg:photos_9r":0,
    "qs_pg:photos_sr":0,
    "qs_pg:pop_sr":6,
    "qs_pg:qs_pg_placetype":"localadmin",
    "wof:name":"Dimos Arriana",
    "wof:placetype":"localadmin",
    "wof:population":18259
},
  "geometry": {"coordinates":[25.72812,41.1934],"type":"Point"}
}