{
  "type": "Feature",
  "properties": {
    "gn:country":"GR",
    "gn:fcode":"PPL",
    "gn:population":1008,
    "iso:country":"GR",
    "name:ara_x_preferred":[
        "\u0643\u0648\u0631\u0645\u064a\u0633\u062a\u0627"
    ],
    "name:arz_x_preferred":[
        "\u0643\u0648\u0631\u0645\u064a\u0633\u062a\u0627"
    ],
    "name:bul_x_preferred":[
        "\u041a\u043e\u0440\u043c\u0438\u0449\u0430"
    ],
    "name:ceb_x_preferred":[
        "Korm\u00edsta"
    ],
    "name:ell_x_preferred":[
        "\u039a\u03bf\u03c1\u03bc\u03af\u03c3\u03c4\u03b1"
    ],
    "name:ell_x_variant":[
        "\u039a\u03bf\u03c1\u03bc\u03af\u03c3\u03c4\u03b1 \u03a3\u03b5\u03c1\u03c1\u03ce\u03bd"
    ],
    "name:eng_x_preferred":[
        "Kormista"
    ],
    "name:fin_x_preferred":[
        "Korm\u00edsta"
    ],
    "name:fra_x_preferred":[
        "Korm\u00edsta"
    ],
    "name:ita_x_preferred":[
        "Kormista"
    ],
    "name:jpn_x_preferred":[
        "\u30b3\u30eb\u30df\u30b9\u30bf"
    ],
    "name:mkd_x_preferred":[
        "\u041a\u043e\u0440\u043c\u0438\u0448\u0442\u0430"
    ],
    "name:nld_x_preferred":[
        "Kormista"
    ],
    "name:nno_x_preferred":[
        "Korm\u00edsta"
    ],
    "name:rus_x_preferred":[
        "\u041a\u043e\u0440\u043c\u0438\u0441\u0442\u0430"
    ],
    "name:swe_x_preferred":[
        "Korm\u00edsta"
    ],
    "qs_pg:aaroncc":"GR",
    "qs_pg:gn_country":"GR",
    "qs_pg:gn_fcode":"PPL",
    "qs_pg:gn_pop":1008,
    "qs_pg:name":"Kormista",
    "qs_pg:name_adm0":"\u0395\u03bb\u03bb\u03ac\u03b4\u03b1",
    "qs_pg:name_adm1":"Macedonia and Thrace",
    "qs_pg:photos_9r":0,
    "qs_pg:photos_sr":0,
    "qs_pg:pop_sr":3,
    "qs_pg:qs_pg_placetype":"locality",
    "qs_pg:qs_pg_placetype_gp":"Town",
    "qs_pg:woe_adm0":23424833,
    "woe:adm0_id":23424833,
    "woe:name_adm0":"\u0395\u03bb\u03bb\u03ac\u03b4\u03b1",
    "woe:name_adm1":"Macedonia and Thrace",
    "woe:placetype":"Town",
    "wof:name":"Kormista",
    "wof:placetype":"locality",
    "wof:population":555
},
  "geometry": {"coordinates":[24.05,40.98333],"type":"Point"}
}