{
  "type": "Feature",
  "properties": {
    "gn:population":5403,
    "iso:country":"GR",
    "name:ara_x_preferred":[
        "\u0641\u064a\u0631\u0633"
    ],
    "name:arz_x_preferred":[
        "\u0641\u064a\u0631\u0633"
    ],
    "name:ast_x_preferred":[
        "Feres"
    ],
    "name:bul_x_preferred":[
        "\u0424\u0435\u0440\u0435"
    ],
    "name:cat_x_preferred":[
        "Feres"
    ],
    "name:ceb_x_preferred":[
        "F\u00e9res"
    ],
    "name:deu_x_preferred":[
        "Feres"
    ],
    "name:ell_x_preferred":[
        "\u0394\u03ae\u03bc\u03bf\u03c2 \u0391\u03bb\u03b5\u03be\u03b1\u03bd\u03b4\u03c1\u03bf\u03cd\u03c0\u03bf\u03bb\u03b7\u03c2#\u0395\u03bd\u03cc\u03c4\u03b7\u03c4\u03b1 \u03a6\u03b5\u03c1\u03ce\u03bd"
    ],
    "name:ell_x_variant":[
        "\u03a6\u03ad\u03c1\u03b1\u03b9",
        "\u03a6\u03ad\u03c1\u03b5\u03c2",
        "\u03a6\u03ad\u03c1\u03b5\u03c2 \u0388\u03b2\u03c1\u03bf\u03c5"
    ],
    "name:eng_x_preferred":[
        "Feres"
    ],
    "name:fas_x_preferred":[
        "\u0641\u0631\u06cc\u0633"
    ],
    "name:fin_x_preferred":[
        "F\u00e9res"
    ],
    "name:fra_x_preferred":[
        "Ph\u00e8res"
    ],
    "name:fra_x_variant":[
        "Feres"
    ],
    "name:ita_x_preferred":[
        "Feres"
    ],
    "name:jpn_x_preferred":[
        "\u30d5\u30a7\u30ec\u30b9"
    ],
    "name:nld_x_preferred":[
        "Feres"
    ],
    "name:nno_x_preferred":[
        "F\u00e9res i \u00c9vros"
    ],
    "name:por_x_preferred":[
        "Feres"
    ],
    "name:ron_x_preferred":[
        "Feres"
    ],
    "name:rus_x_preferred":[
        "\u0424\u0435\u0440\u0435"
    ],
    "name:spa_x_preferred":[
        "Feres"
    ],
    "name:swe_x_preferred":[
        "F\u00e9res"
    ],
    "name:tur_x_preferred":[
        "Ferecik"
    ],
    "name:und_x_variant":[
        "Pherrai"
    ],
    "name:zho_x_preferred":[
        "\u8d39\u96f7\u65af"
    ],
    "qs:a0":"Greece",
    "qs:a1":"*\u0391\u039d\u0391\u03a4\u039f\u039b\u0399\u039a\u0397 \u039c\u0391\u039a\u0395\u0394\u039f\u039d\u0399\u0391 \u039a\u0391\u0399 \u0398\u03a1\u0391\u039a\u0397",
    "qs:a1_alt":"ANATOLIKH MAKEDONIA KAI URAKH",
    "qs:a1r":"0",
    "qs:a2_alt":"EBROS",
    "qs:adm0":"Greece",
    "qs:la_lc":"*",
    "qs:level":"locality",
    "qs:loc":"\u03a6\u0395\u03a1\u0391\u0399",
    "qs:loc_alt":"FERAI",
    "qs:pop":0,
    "qs:type":"buffered point",
    "wd:wordcount":331,
    "wof:name":"\u03a6\u0395\u03a1\u0391\u0399",
    "wof:placetype":"locality",
    "wof:population":5403
},
  "geometry": {"coordinates":[26.17399,40.893318],"type":"Point"}
}