{
  "type": "Feature",
  "properties": {
    "gn:admin1_code":"ESYE25",
    "gn:admin2_code":"42.0",
    "gn:admin3_code":"9248",
    "gn:asciiname":"Kokkina Louria",
    "gn:country_code":"GR",
    "gn:dem":384,
    "gn:feature_class":"P",
    "gn:feature_code":"PPL",
    "gn:name":"K\u00f3kkina Louri\u00e1",
    "gn:population":0,
    "gn:timezone":"Europe/Athens",
    "iso:country":"GR",
    "name:ell_x_preferred":[
        "K\u00f3kkina Louri\u00e1"
    ],
    "name:ell_x_variant":[
        "\u039a\u03cc\u03ba\u03ba\u03b9\u03bd\u03b1 \u039b\u03bf\u03c5\u03c1\u03b9\u03ac"
    ],
    "wof:name":"Kokkina Louria",
    "wof:placetype":"locality"
},
  "geometry": {"coordinates":[22.44834,36.82242],"type":"Point"}
}