{
  "type": "Feature",
  "properties": {
    "gn:admin1_code":"ESYE43",
    "gn:admin2_code":"45.0",
    "gn:admin3_code":"9302",
    "gn:asciiname":"Tefeli",
    "gn:country_code":"GR",
    "gn:dem":357,
    "gn:feature_class":"P",
    "gn:feature_code":"PPL",
    "gn:name":"Tef\u00e9li",
    "gn:population":0,
    "gn:timezone":"Europe/Athens",
    "iso:country":"GR",
    "name:ell_x_preferred":[
        "\u03a4\u03b5\u03c6\u03ad\u03bb\u03b9"
    ],
    "name:ell_x_variant":[
        "\u03a4\u03b5\u03c6\u03ad\u03bb\u03b9\u03bf\u03bd"
    ],
    "name:und_x_variant":[
        "Tef\u00e9li",
        "Tef\u00e9lion"
    ],
    "wof:name":"Tefeli",
    "wof:placetype":"locality"
},
  "geometry": {"coordinates":[25.16268,35.09214],"type":"Point"}
}