{
  "type": "Feature",
  "properties": {
    "gn:admin1_code":"ESYE23",
    "gn:admin2_code":"38.0",
    "gn:admin3_code":"9130",
    "gn:asciiname":"Mandiles",
    "gn:country_code":"GR",
    "gn:dem":296,
    "gn:feature_class":"P",
    "gn:feature_code":"PPL",
    "gn:name":"M\u00e1ndiles",
    "gn:population":0,
    "gn:timezone":"Europe/Athens",
    "iso:country":"GR",
    "name:ell_x_preferred":[
        "\u039c\u03ac\u03bd\u03b4\u03b9\u03bb\u03b5\u03c2"
    ],
    "name:und_x_variant":[
        "Mandhil\u00e1s",
        "M\u00e1ndiles"
    ],
    "wof:name":"Mandiles",
    "wof:placetype":"locality"
},
  "geometry": {"coordinates":[22.19114,38.15042],"type":"Point"}
}