{
  "type": "Feature",
  "properties": {
    "gn:admin1_code":"ESYE23",
    "gn:admin2_code":"39.0",
    "gn:admin3_code":"9139",
    "gn:asciiname":"Latas",
    "gn:country_code":"GR",
    "gn:dem":156,
    "gn:feature_class":"P",
    "gn:feature_code":"PPL",
    "gn:name":"L\u00e1tas",
    "gn:population":0,
    "gn:timezone":"Europe/Athens",
    "iso:country":"GR",
    "name:ell_x_preferred":[
        "\u039b\u03ac\u03c4\u03b1\u03c2"
    ],
    "name:und_x_variant":[
        "L\u00e1ta",
        "L\u00e1tas"
    ],
    "wof:name":"Latas",
    "wof:placetype":"locality"
},
  "geometry": {"coordinates":[21.546,37.87742],"type":"Point"}
}