{
  "type": "Feature",
  "properties": {
    "gn:admin1_code":"ESYE24",
    "gn:admin2_code":"30.0",
    "gn:admin3_code":"9157",
    "gn:asciiname":"Vrysoula",
    "gn:country_code":"GR",
    "gn:dem":686,
    "gn:feature_class":"P",
    "gn:feature_code":"PPL",
    "gn:name":"Vryso\u00fala",
    "gn:population":14,
    "gn:timezone":"Europe/Athens",
    "iso:country":"GR",
    "name:ell_x_historical":[
        "\u0391\u03bc\u03c0\u03ad\u03bb\u03b9\u03b1"
    ],
    "name:ell_x_preferred":[
        "\u0392\u03c1\u03c5\u03c3\u03bf\u03cd\u03bb\u03b1"
    ],
    "name:ell_x_variant":[
        "\u0391\u03bc\u03c0\u03ad\u03bb\u03b9\u03b1"
    ],
    "name:eng_x_historical":[
        "Ampelia"
    ],
    "name:eng_x_preferred":[
        "Vrysoula"
    ],
    "name:eng_x_variant":[
        "Ampelia"
    ],
    "wof:name":"Vrysoula",
    "wof:placetype":"locality",
    "wof:population":14
},
  "geometry": {"coordinates":[21.64307,38.79013],"type":"Point"}
}