{
  "type": "Feature",
  "properties": {
    "iso:country":"GR",
    "name:ell_x_preferred":[
        "\u0394\u03ae\u03bc\u03bf\u03c2 \u0391\u03c1\u03ba\u03b1\u03b4\u03af\u03bf\u03c5"
    ],
    "name:fin_x_preferred":[
        "Ark\u00e1di"
    ],
    "name:fra_x_preferred":[
        "Ark\u00e1di"
    ],
    "name:nno_x_preferred":[
        "Ark\u00e1di"
    ],
    "name:por_x_preferred":[
        "Arc\u00e1di"
    ],
    "name:ron_x_preferred":[
        "Arkadi"
    ],
    "qs_pg:aaroncc":"GR",
    "qs_pg:name":"Arkadi",
    "qs_pg:name_adm0":"\u0395\u03bb\u03bb\u03ac\u03b4\u03b1",
    "qs_pg:name_adm1":"Crete",
    "qs_pg:photos":33,
    "qs_pg:photos_1k":7,
    "qs_pg:photos_9k":1,
    "qs_pg:photos_9r":2,
    "qs_pg:photos_all":33,
    "qs_pg:photos_sr":2,
    "qs_pg:pop_sr":0,
    "qs_pg:qs_pg_placetype":"locality",
    "qs_pg:qs_pg_placetype_gp":"Town",
    "qs_pg:woe_adm0":23424833,
    "woe:adm0_id":23424833,
    "woe:name_adm0":"\u0395\u03bb\u03bb\u03ac\u03b4\u03b1",
    "woe:name_adm1":"Crete",
    "woe:placetype":"Town",
    "wof:name":"Arkadi",
    "wof:placetype":"locality"
},
  "geometry": {"coordinates":[25.096809,35.14492],"type":"Point"}
}