{
  "type": "Feature",
  "properties": {
    "gn:admin1_code":"ESYE24",
    "gn:admin2_code":"32.0",
    "gn:admin3_code":"9166",
    "gn:asciiname":"Kallithea",
    "gn:country_code":"GR",
    "gn:dem":764,
    "gn:feature_class":"P",
    "gn:feature_code":"PPL",
    "gn:name":"Kallith\u00e9a",
    "gn:population":0,
    "gn:timezone":"Europe/Athens",
    "iso:country":"GR",
    "name:ell_x_preferred":[
        "Kallith\u00e9a"
    ],
    "name:ell_x_variant":[
        "\u039a\u03b1\u03bb\u03bb\u03b9\u03b8\u03ad\u03b1"
    ],
    "wof:name":"Kallithea",
    "wof:placetype":"locality"
},
  "geometry": {"coordinates":[22.14092,38.39108],"type":"Point"}
}