{
  "type": "Feature",
  "properties": {
    "gn:country":"GR",
    "gn:fcode":"PPL",
    "gn:population":569,
    "iso:country":"GR",
    "name:cat_x_preferred":[
        "Vamos"
    ],
    "name:ceb_x_preferred":[
        "V\u00e1mos"
    ],
    "name:deu_x_preferred":[
        "Vamos"
    ],
    "name:ell_x_preferred":[
        "\u0392\u03ac\u03bc\u03bf\u03c2"
    ],
    "name:ell_x_variant":[
        "\u0394\u03ae\u03bc\u03bf\u03c2 \u0392\u03ac\u03bc\u03bf\u03c5"
    ],
    "name:fin_x_preferred":[
        "V\u00e1mos"
    ],
    "name:fra_x_preferred":[
        "V\u00e1mos"
    ],
    "name:ita_x_preferred":[
        "Vamos"
    ],
    "name:nld_x_preferred":[
        "Vamos"
    ],
    "name:nno_x_preferred":[
        "V\u00e1mos"
    ],
    "name:por_x_preferred":[
        "V\u00e1mos"
    ],
    "name:swe_x_preferred":[
        "V\u00e1mos"
    ],
    "qs_pg:aaroncc":"GR",
    "qs_pg:gn_country":"GR",
    "qs_pg:gn_fcode":"PPL",
    "qs_pg:gn_pop":569,
    "qs_pg:name":"Vamos",
    "qs_pg:name_adm0":"\u0395\u03bb\u03bb\u03ac\u03b4\u03b1",
    "qs_pg:name_adm1":"Crete",
    "qs_pg:photos":256,
    "qs_pg:photos_1k":52,
    "qs_pg:photos_9k":1,
    "qs_pg:photos_9r":4,
    "qs_pg:photos_all":256,
    "qs_pg:photos_sr":5,
    "qs_pg:pop_sr":2,
    "qs_pg:qs_pg_placetype":"locality",
    "qs_pg:qs_pg_placetype_gp":"Town",
    "qs_pg:woe_adm0":23424833,
    "woe:adm0_id":23424833,
    "woe:name_adm0":"\u0395\u03bb\u03bb\u03ac\u03b4\u03b1",
    "woe:name_adm1":"Crete",
    "woe:placetype":"Town",
    "wof:name":"Vamos",
    "wof:placetype":"locality",
    "wof:population":569
},
  "geometry": {"coordinates":[24.19806,35.40694],"type":"Point"}
}