{
  "type": "Feature",
  "properties": {
    "gn:admin1_code":"ESYE43",
    "gn:admin2_code":"45.0",
    "gn:admin3_code":"9302",
    "gn:asciiname":"Ethia",
    "gn:country_code":"GR",
    "gn:dem":737,
    "gn:feature_class":"P",
    "gn:feature_code":"PPL",
    "gn:name":"Ethi\u00e1",
    "gn:population":0,
    "gn:timezone":"Europe/Athens",
    "iso:country":"GR",
    "wof:name":"Ethia",
    "wof:placetype":"locality"
},
  "geometry": {"coordinates":[25.19374,34.98863],"type":"Point"}
}