{
  "type": "Feature",
  "properties": {
    "gn:admin1_code":"ESYE22",
    "gn:admin2_code":"26.0",
    "gn:admin3_code":"9121",
    "gn:asciiname":"Spanokhorion",
    "gn:country_code":"GR",
    "gn:dem":432,
    "gn:feature_class":"P",
    "gn:feature_code":"PPL",
    "gn:name":"Spanokh\u00f3rion",
    "gn:population":161,
    "gn:timezone":"Europe/Athens",
    "iso:country":"GR",
    "name:ell_x_preferred":[
        "\u03a3\u03c0\u03b1\u03bd\u03bf\u03c7\u03ce\u03c1\u03b9"
    ],
    "name:eng_x_preferred":[
        "Spanochori"
    ],
    "name:und_x_variant":[
        "Spanokh\u00f3ri",
        "Spanokh\u00f3rion"
    ],
    "wof:name":"Spanokhorion",
    "wof:placetype":"locality",
    "wof:population":161
},
  "geometry": {"coordinates":[20.67121,38.78239],"type":"Point"}
}