{
  "type": "Feature",
  "properties": {
    "gn:admin1_code":"ESYE24",
    "gn:admin2_code":"29.0",
    "gn:admin3_code":"9159",
    "gn:asciiname":"Yeraklion",
    "gn:country_code":"GR",
    "gn:dem":356,
    "gn:feature_class":"P",
    "gn:feature_code":"PPL",
    "gn:name":"Yerakl\u00edon",
    "gn:population":24,
    "gn:timezone":"Europe/Athens",
    "iso:country":"GR",
    "name:ell_x_preferred":[
        "\u0393\u03b5\u03c1\u03b1\u03ba\u03bb\u03af"
    ],
    "name:ell_x_variant":[
        "\u0393\u03b5\u03c1\u03b1\u03ba\u03bb\u03af\u03bf\u03bd",
        "\u0393\u03b5\u03c1\u03b1\u03ba\u03bb\u03af\u03bf"
    ],
    "name:eng_x_preferred":[
        "Gerakli"
    ],
    "name:und_x_variant":[
        "Yarakl\u00ed",
        "Yerakl\u00ed",
        "Yerakl\u00edon"
    ],
    "wof:name":"Yeraklion",
    "wof:placetype":"locality",
    "wof:population":24
},
  "geometry": {"coordinates":[22.36932,39.1471],"type":"Point"}
}