{
  "type": "Feature",
  "properties": {
    "gn:admin1_code":"ESYE25",
    "gn:admin2_code":"40.0",
    "gn:admin3_code":"9255",
    "gn:asciiname":"Manesis",
    "gn:country_code":"GR",
    "gn:dem":209,
    "gn:feature_class":"P",
    "gn:feature_code":"PPL",
    "gn:name":"M\u00e1nesis",
    "gn:population":0,
    "gn:timezone":"Europe/Athens",
    "iso:country":"GR",
    "name:ell_x_preferred":[
        "\u039c\u03ac\u03bd\u03b5\u03c3\u03b7\u03c2"
    ],
    "name:und_x_variant":[
        "M\u00e1nesi",
        "M\u00e1nesis"
    ],
    "wof:name":"Manesis",
    "wof:placetype":"locality"
},
  "geometry": {"coordinates":[21.89774,37.0855],"type":"Point"}
}