{
  "type": "Feature",
  "properties": {
    "gn:country":"GR",
    "gn:fcode":"PPL",
    "gn:population":197,
    "iso:country":"GR",
    "name:ell_x_preferred":[
        "\u039a\u03bf\u03c1\u03c5\u03b4\u03b1\u03bb\u03bb\u03cc\u03c2"
    ],
    "name:und_x_variant":[
        "Koridhall\u00f3s"
    ],
    "qs_pg:aaroncc":"GR",
    "qs_pg:gn_country":"GR",
    "qs_pg:gn_fcode":"PPL",
    "qs_pg:gn_pop":197,
    "qs_pg:name":"Korydall\u00f3s",
    "qs_pg:photos_9r":0,
    "qs_pg:photos_sr":0,
    "qs_pg:pop_sr":1,
    "qs_pg:qs_pg_placetype":"locality",
    "wof:name":"Korydall\u00f3s",
    "wof:placetype":"locality",
    "wof:population":197
},
  "geometry": {"coordinates":[21.34167,39.80917],"type":"Point"}
}