{
  "type": "Feature",
  "properties": {
    "gn:admin1_code":"ESYE42",
    "gn:asciiname":"Azolimnos",
    "gn:country_code":"GR",
    "gn:dem":24,
    "gn:feature_class":"P",
    "gn:feature_code":"PPL",
    "gn:name":"Az\u00f3limnos",
    "gn:population":0,
    "gn:timezone":"Europe/Athens",
    "iso:country":"GR",
    "name:ell_x_preferred":[
        "Az\u00f3limnos"
    ],
    "name:ell_x_variant":[
        "\u0391\u03b6\u03cc\u03bb\u03b9\u03bc\u03bd\u03bf\u03c2"
    ],
    "wof:name":"Azolimnos",
    "wof:placetype":"locality"
},
  "geometry": {"coordinates":[24.96108,37.41015],"type":"Point"}
}