{
  "type": "Feature",
  "properties": {
    "gn:admin1_code":"ESYE25",
    "gn:admin2_code":"37.0",
    "gn:admin3_code":"9242",
    "gn:asciiname":"Sataiika",
    "gn:country_code":"GR",
    "gn:dem":61,
    "gn:feature_class":"P",
    "gn:feature_code":"PPL",
    "gn:name":"Sata\u00edika",
    "gn:population":107,
    "gn:timezone":"Europe/Athens",
    "iso:country":"GR",
    "name:ell_x_preferred":[
        "\u03a3\u03b1\u03c4\u03b1\u03af\u03b9\u03ba\u03b1"
    ],
    "name:eng_x_preferred":[
        "Sataiika"
    ],
    "wof:name":"Sataiika",
    "wof:placetype":"locality",
    "wof:population":107
},
  "geometry": {"coordinates":[22.74584,37.96629],"type":"Point"}
}