{
  "type": "Feature",
  "properties": {
    "gn:admin1_code":"ESYE42",
    "gn:admin2_code":"49.0",
    "gn:admin3_code":"9282",
    "gn:asciiname":"Mavrampeli",
    "gn:country_code":"GR",
    "gn:dem":155,
    "gn:feature_class":"P",
    "gn:feature_code":"PPL",
    "gn:name":"Mavramp\u00e9li",
    "gn:population":0,
    "gn:timezone":"Europe/Athens",
    "iso:country":"GR",
    "name:ell_x_preferred":[
        "Mavramp\u00e9li"
    ],
    "name:ell_x_variant":[
        "\u039c\u03b1\u03c5\u03c1\u03b1\u03bc\u03c0\u03ad\u03bb\u03b9",
        "Mavramp\u00e9lion",
        "\u039c\u03b1\u03c5\u03c1\u03b1\u03bc\u03c0\u03ad\u03bb\u03b9\u03bf\u03bd"
    ],
    "name:und_x_variant":[
        "Mavramb\u00e9li",
        "Mavramb\u00e9lion"
    ],
    "wof:name":"Mavrampeli",
    "wof:placetype":"locality"
},
  "geometry": {"coordinates":[24.29578,37.63305],"type":"Point"}
}