{
  "type": "Feature",
  "properties": {
    "gn:country":"GR",
    "gn:fcode":"PPL",
    "gn:population":117,
    "iso:country":"GR",
    "name:ell_x_preferred":[
        "\u039a\u03bf\u03c1\u03af\u03c4\u03b9\u03b1\u03bd\u03b7"
    ],
    "name:eng_x_preferred":[
        "Koritiani"
    ],
    "name:und_x_variant":[
        "Kor\u00edtiani"
    ],
    "qs_pg:aaroncc":"GR",
    "qs_pg:gn_country":"GR",
    "qs_pg:gn_fcode":"PPL",
    "qs_pg:gn_pop":117,
    "qs_pg:name":"Koritiani",
    "qs_pg:name_adm0":"\u0395\u03bb\u03bb\u03ac\u03b4\u03b1",
    "qs_pg:name_adm1":"Epirus and Western Macedonia",
    "qs_pg:photos_9r":0,
    "qs_pg:photos_sr":0,
    "qs_pg:pop_sr":1,
    "qs_pg:qs_pg_placetype":"locality",
    "qs_pg:qs_pg_placetype_gp":"Town",
    "qs_pg:woe_adm0":23424833,
    "woe:adm0_id":23424833,
    "woe:name_adm0":"\u0395\u03bb\u03bb\u03ac\u03b4\u03b1",
    "woe:name_adm1":"Epirus and Western Macedonia",
    "woe:placetype":"Town",
    "wof:name":"Koritiani",
    "wof:placetype":"locality",
    "wof:population":59
},
  "geometry": {"coordinates":[20.94778,39.49444],"type":"Point"}
}