{
  "type": "Feature",
  "properties": {
    "gn:admin1_code":"ESYE23",
    "gn:admin2_code":"31.0",
    "gn:admin3_code":"9125",
    "gn:asciiname":"Bletsi",
    "gn:country_code":"GR",
    "gn:dem":507,
    "gn:feature_class":"P",
    "gn:feature_code":"PPL",
    "gn:name":"Bl\u00e9tsi",
    "gn:population":0,
    "gn:timezone":"Europe/Athens",
    "iso:country":"GR",
    "name:ell_x_preferred":[
        "Bl\u00e9tsi"
    ],
    "name:ell_x_variant":[
        "\u039c\u03c0\u03bb\u03ad\u03c4\u03c3\u03b9"
    ],
    "wof:name":"Bletsi",
    "wof:placetype":"locality"
},
  "geometry": {"coordinates":[21.40247,39.06286],"type":"Point"}
}