{
  "type": "Feature",
  "properties": {
    "gn:admin1_code":"ESYE43",
    "gn:admin2_code":"43.0",
    "gn:admin3_code":"9323",
    "gn:asciiname":"Petres",
    "gn:country_code":"GR",
    "gn:dem":140,
    "gn:feature_class":"P",
    "gn:feature_code":"PPL",
    "gn:name":"Petr\u00e9s",
    "gn:population":0,
    "gn:timezone":"Europe/Athens",
    "iso:country":"GR",
    "name:ell_x_preferred":[
        "Petr\u00e9s"
    ],
    "name:ell_x_variant":[
        "\u03a0\u03b5\u03c4\u03c1\u03ad\u03c2"
    ],
    "wof:name":"Petres",
    "wof:placetype":"locality"
},
  "geometry": {"coordinates":[23.81117,35.47277000000001],"type":"Point"}
}