{
  "type": "Feature",
  "properties": {
    "gn:admin1_code":"ESYE25",
    "gn:admin2_code":"37.0",
    "gn:admin3_code":"9247",
    "gn:asciiname":"Karterion",
    "gn:country_code":"GR",
    "gn:dem":632,
    "gn:feature_class":"P",
    "gn:feature_code":"PPL",
    "gn:name":"Kart\u00e9rion",
    "gn:population":96,
    "gn:timezone":"Europe/Athens",
    "iso:country":"GR",
    "name:ell_x_preferred":[
        "\u039a\u03b1\u03c1\u03c4\u03ad\u03c1\u03b9"
    ],
    "name:eng_x_preferred":[
        "Karteri"
    ],
    "name:und_x_variant":[
        "Kart\u00e9ri",
        "Kart\u00e9rion"
    ],
    "wof:name":"Karterion",
    "wof:placetype":"locality",
    "wof:population":96
},
  "geometry": {"coordinates":[22.40803,37.8451],"type":"Point"}
}