{
  "type": "Feature",
  "properties": {
    "gn:admin1_code":"ESYE14",
    "gn:admin2_code":"21.0",
    "gn:admin3_code":"9103",
    "gn:asciiname":"Ampelia",
    "gn:country_code":"GR",
    "gn:dem":211,
    "gn:feature_class":"P",
    "gn:feature_code":"PPL",
    "gn:name":"Ampeli\u00e1",
    "gn:population":0,
    "gn:timezone":"Europe/Athens",
    "iso:country":"GR",
    "name:ell_x_preferred":[
        "Ampeli\u00e1"
    ],
    "name:ell_x_variant":[
        "\u0391\u03bc\u03c0\u03b5\u03bb\u03b9\u03ac"
    ],
    "name:und_x_variant":[
        "K\u00e1to Derekl\u00ed",
        "Ambel\u00eda"
    ],
    "wof:name":"Ampelia",
    "wof:placetype":"locality"
},
  "geometry": {"coordinates":[22.49339,39.30958],"type":"Point"}
}