{
  "type": "Feature",
  "properties": {
    "gn:population":1294,
    "iso:country":"GR",
    "name:ell_x_preferred":[
        "\u0394\u03b9\u03b1\u03b2\u03b1\u03c4\u03cc\u03c2"
    ],
    "name:und_x_variant":[
        "Dhiavat\u00f3s"
    ],
    "qs:a0":"Greece",
    "qs:a1":"*\u039a\u0395\u039d\u03a4\u03a1\u0399\u039a\u0397 \u039c\u0391\u039a\u0395\u0394\u039f\u039d\u0399\u0391",
    "qs:a1_alt":"KENTRIKH MAKEDONIA",
    "qs:a1r":"0",
    "qs:a2_alt":"HMAUIA",
    "qs:adm0":"Greece",
    "qs:la_lc":"*",
    "qs:level":"locality",
    "qs:loc":"\u0394\u0399\u0391\u0392\u0391\u03a4\u039f\u03a3",
    "qs:loc_alt":"DIABATOS",
    "qs:pop":0,
    "qs:type":"buffered point",
    "wof:name":"\u0394\u0399\u0391\u0392\u0391\u03a4\u039f\u03a3",
    "wof:placetype":"locality",
    "wof:population":1294
},
  "geometry": {"coordinates":[22.268816,40.544956],"type":"Point"}
}