{
  "type": "Feature",
  "properties": {
    "gn:admin1_code":"ESYE14",
    "gn:admin2_code":"21.0",
    "gn:admin3_code":"9098",
    "gn:asciiname":"Kefalovryso",
    "gn:country_code":"GR",
    "gn:dem":261,
    "gn:feature_class":"P",
    "gn:feature_code":"PPL",
    "gn:name":"Kefal\u00f3vryso",
    "gn:population":0,
    "gn:timezone":"Europe/Athens",
    "iso:country":"GR",
    "name:ell_x_preferred":[
        "\u039a\u03b5\u03c6\u03b1\u03bb\u03cc\u03b2\u03c1\u03c5\u03c3\u03bf\u03bd"
    ],
    "name:ell_x_variant":[
        "Kefal\u00f3vryso",
        "\u039a\u03b5\u03c6\u03b1\u03bb\u03cc\u03b2\u03c1\u03c5\u03c3\u03bf",
        "Kefal\u00f3vryson"
    ],
    "name:und_x_variant":[
        "Kefal\u00f3vriso",
        "Kefal\u00f3vrison"
    ],
    "wof:name":"Kefalovryso",
    "wof:placetype":"locality"
},
  "geometry": {"coordinates":[22.07239,39.89131],"type":"Point"}
}