{
  "type": "Feature",
  "properties": {
    "gn:admin1_code":"ESYE23",
    "gn:admin2_code":"38.0",
    "gn:admin3_code":"9131",
    "gn:asciiname":"Psili Rachi",
    "gn:country_code":"GR",
    "gn:dem":35,
    "gn:feature_class":"P",
    "gn:feature_code":"PPL",
    "gn:name":"Psil\u00ed R\u00e1chi",
    "gn:population":0,
    "gn:timezone":"Europe/Athens",
    "iso:country":"GR",
    "name:ell_x_preferred":[
        "Psil\u00ed R\u00e1chi"
    ],
    "name:ell_x_variant":[
        "\u03a8\u03b7\u03bb\u03ae \u03a1\u03ac\u03c7\u03b7"
    ],
    "name:und_x_variant":[
        "Ipsil\u00ed R\u00e1khi"
    ],
    "wof:name":"Psili Rachi",
    "wof:placetype":"locality"
},
  "geometry": {"coordinates":[21.57853,38.11636],"type":"Point"}
}