{
  "type": "Feature",
  "properties": {
    "gn:admin1_code":"ESYE42",
    "gn:admin2_code":"49.0",
    "gn:admin3_code":"9292",
    "gn:asciiname":"Schoinoussa",
    "gn:country_code":"GR",
    "gn:dem":72,
    "gn:feature_class":"P",
    "gn:feature_code":"PPL",
    "gn:name":"Schoino\u00fassa",
    "gn:population":211,
    "gn:timezone":"Europe/Athens",
    "iso:country":"GR",
    "name:ell_x_preferred":[
        "\u03a3\u03c7\u03bf\u03b9\u03bd\u03bf\u03cd\u03c3\u03b1"
    ],
    "name:ell_x_variant":[
        "\u03a3\u03c7\u03bf\u03b9\u03bd\u03bf\u03cd\u03c3\u03c3\u03b1",
        "\u03a7\u03ce\u03c1\u03b1 \u03a3\u03c7\u03bf\u03b9\u03bd\u03bf\u03cd\u03c3\u03c3\u03b1\u03c2",
        "\u03a7\u03ce\u03c1\u03b1",
        "\u03a7\u03ce\u03c1\u03b1 \u03a3\u03c7\u03bf\u03b9\u03bd\u03bf\u03cd\u03c3\u03b1\u03c2"
    ],
    "name:eng_x_preferred":[
        "Schinoussa"
    ],
    "name:und_x_variant":[
        "Echinosa",
        "Panay\u00eda",
        "Skhoino\u00fasa",
        "Skhoino\u00fassa",
        "Schoino\u00fassa"
    ],
    "wof:name":"Schoinoussa",
    "wof:placetype":"locality",
    "wof:population":211
},
  "geometry": {"coordinates":[25.51867,36.86982],"type":"Point"}
}