{
  "type": "Feature",
  "properties": {
    "gn:country":"GR",
    "gn:fcode":"PPL",
    "gn:population":196,
    "iso:country":"GR",
    "name:ell_x_preferred":[
        "\u039c\u03b5\u03b3\u03ac\u03bb\u03b7 \u0393\u03cc\u03c4\u03b9\u03c3\u03c4\u03b1"
    ],
    "name:eng_x_preferred":[
        "Megali Gotista"
    ],
    "name:und_x_variant":[
        "Meg\u00e1li G\u00f3tista"
    ],
    "qs_pg:aaroncc":"GR",
    "qs_pg:gn_country":"GR",
    "qs_pg:gn_fcode":"PPL",
    "qs_pg:gn_pop":196,
    "qs_pg:name":"Megali Gotista",
    "qs_pg:name_adm0":"\u0395\u03bb\u03bb\u03ac\u03b4\u03b1",
    "qs_pg:name_adm1":"Epirus and Western Macedonia",
    "qs_pg:photos_9r":0,
    "qs_pg:photos_sr":0,
    "qs_pg:pop_sr":1,
    "qs_pg:qs_pg_placetype":"locality",
    "qs_pg:qs_pg_placetype_gp":"Town",
    "qs_pg:woe_adm0":23424833,
    "woe:adm0_id":23424833,
    "woe:name_adm0":"\u0395\u03bb\u03bb\u03ac\u03b4\u03b1",
    "woe:name_adm1":"Epirus and Western Macedonia",
    "woe:placetype":"Town",
    "wof:name":"Megali Gotista",
    "wof:placetype":"locality",
    "wof:population":166
},
  "geometry": {"coordinates":[21.0425,39.68444],"type":"Point"}
}