{
  "type": "Feature",
  "properties": {
    "gn:admin1_code":"ESYE21",
    "gn:admin2_code":"17.0",
    "gn:admin3_code":"9086",
    "gn:asciiname":"Kerasia",
    "gn:country_code":"GR",
    "gn:dem":809,
    "gn:feature_class":"P",
    "gn:feature_code":"PPL",
    "gn:name":"Kerasi\u00e1",
    "gn:population":6,
    "gn:timezone":"Europe/Athens",
    "iso:country":"GR",
    "name:ell_x_historical":[
        "\u0399\u03c4\u03ad\u03b1"
    ],
    "name:ell_x_preferred":[
        "\u039a\u03b5\u03c1\u03b1\u03c3\u03b9\u03ac"
    ],
    "name:ell_x_variant":[
        "\u0399\u03c4\u03ad\u03b1"
    ],
    "name:eng_x_preferred":[
        "Kerasia"
    ],
    "name:und_x_variant":[
        "It\u00e9a",
        "Kerasi\u00e1"
    ],
    "wof:name":"Kerasia",
    "wof:placetype":"locality",
    "wof:population":6
},
  "geometry": {"coordinates":[21.05525,39.71655],"type":"Point"}
}