{
  "type": "Feature",
  "properties": {
    "gn:admin1_code":"ESYE25",
    "gn:admin2_code":"37.0",
    "gn:admin3_code":"9246",
    "gn:asciiname":"Kristallopiyi",
    "gn:cc2":"GR",
    "gn:country_code":"GR",
    "gn:dem":851,
    "gn:feature_class":"P",
    "gn:feature_code":"PPL",
    "gn:name":"Kristallopiy\u00ed",
    "gn:population":0,
    "gn:timezone":"Europe/Athens",
    "iso:country":"GR",
    "name:ell_x_preferred":[
        "\u039a\u03c1\u03c5\u03c3\u03c4\u03b1\u03bb\u03bb\u03bf\u03c0\u03b7\u03b3\u03ae"
    ],
    "name:und_x_variant":[
        "Tourtoura\u00edika",
        "Tourtour\u00e9\u00efka",
        "Kristallopiy\u00ed"
    ],
    "wof:name":"Kristallopiyi",
    "wof:placetype":"locality"
},
  "geometry": {"coordinates":[22.44915,38.05008],"type":"Point"}
}