{
  "type": "Feature",
  "properties": {
    "gn:admin1_code":"ESYE14",
    "gn:admin2_code":"21.0",
    "gn:admin3_code":"9099",
    "gn:asciiname":"Krya Vrysi",
    "gn:country_code":"GR",
    "gn:dem":115,
    "gn:feature_class":"P",
    "gn:feature_code":"PPL",
    "gn:name":"Kr\u00fda Vr\u00fdsi",
    "gn:population":0,
    "gn:timezone":"Europe/Athens",
    "iso:country":"GR",
    "name:bul_x_preferred":[
        "\u041a\u0440\u0438\u044f \u0412\u0440\u0438\u0441\u0438"
    ],
    "name:ell_x_preferred":[
        "Kr\u00fda Vr\u00fdsi"
    ],
    "name:ell_x_variant":[
        "\u039a\u03c1\u03cd\u03b1 \u0392\u03c1\u03cd\u03c3\u03b7"
    ],
    "name:und_x_variant":[
        "Chabasl\u00e1r"
    ],
    "wof:name":"Krya Vrysi",
    "wof:placetype":"locality"
},
  "geometry": {"coordinates":[22.26928,39.51858],"type":"Point"}
}