{
  "type": "Feature",
  "properties": {
    "gn:admin1_code":"ESYE43",
    "gn:admin2_code":"45.0",
    "gn:admin3_code":"9304",
    "gn:asciiname":"Miamou",
    "gn:country_code":"GR",
    "gn:dem":477,
    "gn:feature_class":"P",
    "gn:feature_code":"PPL",
    "gn:name":"Miamo\u00fa",
    "gn:population":0,
    "gn:timezone":"Europe/Athens",
    "iso:country":"GR",
    "name:und_x_variant":[
        "Miamo\u00fa"
    ],
    "wof:name":"Miamou",
    "wof:placetype":"locality"
},
  "geometry": {"coordinates":[24.9369,34.9722],"type":"Point"}
}