{
  "type": "Feature",
  "properties": {
    "gn:admin1_code":"ESYE22",
    "gn:admin2_code":"27.0",
    "gn:admin3_code":"9120",
    "gn:asciiname":"Karousa",
    "gn:country_code":"GR",
    "gn:dem":81,
    "gn:feature_class":"P",
    "gn:feature_code":"PPL",
    "gn:name":"Karo\u00fasa",
    "gn:population":0,
    "gn:timezone":"Europe/Athens",
    "iso:country":"GR",
    "name:ell_x_preferred":[
        "Karo\u00fasa"
    ],
    "name:ell_x_variant":[
        "\u039a\u03b1\u03c1\u03bf\u03cd\u03c3\u03b1"
    ],
    "name:und_x_variant":[
        "Karo\u00fassa"
    ],
    "wof:name":"Karousa",
    "wof:placetype":"locality"
},
  "geometry": {"coordinates":[20.74711,38.12692],"type":"Point"}
}