{
  "type": "Feature",
  "properties": {
    "gn:admin1_code":"ESYE23",
    "gn:admin2_code":"39.0",
    "gn:admin3_code":"9141.0",
    "gn:asciiname":"Kato Kavouri",
    "gn:country_code":"GR",
    "gn:dem":3,
    "gn:feature_class":"P",
    "gn:feature_code":"PPL",
    "gn:name":"Kato Kavouri",
    "gn:population":0,
    "gn:timezone":"Europe/Athens",
    "iso:country":"GR",
    "name:ell_x_preferred":[
        "\u039a\u03ac\u03c4\u03c9 \u039a\u03b1\u03b2\u03bf\u03cd\u03c1\u03b9"
    ],
    "wof:name":"Kato Kavouri",
    "wof:placetype":"locality"
},
  "geometry": {"coordinates":[21.3448,37.66453],"type":"Point"}
}