{
  "type": "Feature",
  "properties": {
    "gn:admin1_code":"ESYE22",
    "gn:admin2_code":"27.0",
    "gn:admin3_code":"9120",
    "gn:asciiname":"Makriotika",
    "gn:country_code":"GR",
    "gn:dem":224,
    "gn:feature_class":"P",
    "gn:feature_code":"PPL",
    "gn:name":"Makri\u00f3tika",
    "gn:population":0,
    "gn:timezone":"Europe/Athens",
    "iso:country":"GR",
    "name:ell_x_preferred":[
        "Makri\u00f3tika"
    ],
    "name:ell_x_variant":[
        "\u039c\u03b1\u03ba\u03c1\u03b9\u03ce\u03c4\u03b9\u03ba\u03b1"
    ],
    "wof:name":"Makriotika",
    "wof:placetype":"locality"
},
  "geometry": {"coordinates":[20.55583,38.30911],"type":"Point"}
}