{
  "type": "Feature",
  "properties": {
    "gn:admin1_code":"ESYE41",
    "gn:admin2_code":"48.0",
    "gn:admin3_code":"9264",
    "gn:asciiname":"Potami Mesokampou",
    "gn:country_code":"GR",
    "gn:dem":6,
    "gn:feature_class":"P",
    "gn:feature_code":"PPL",
    "gn:name":"Pot\u00e1mi Mesok\u00e1mpou",
    "gn:population":40,
    "gn:timezone":"Europe/Athens",
    "iso:country":"GR",
    "name:ell_x_preferred":[
        "\u03a0\u03bf\u03c4\u03ac\u03bc\u03b9 \u039c\u03b5\u03c3\u03bf\u03ba\u03ac\u03bc\u03c0\u03bf\u03c5"
    ],
    "name:eng_x_preferred":[
        "Potami Mesokampou"
    ],
    "wof:name":"Potami Mesokampou",
    "wof:placetype":"locality",
    "wof:population":40
},
  "geometry": {"coordinates":[26.97092,37.70574000000001],"type":"Point"}
}