{
  "type": "Feature",
  "properties": {
    "gn:country":"GR",
    "gn:fcode":"PPL",
    "gn:population":556,
    "iso:country":"GR",
    "name:ell_x_preferred":[
        "Kall\u00edpoli"
    ],
    "name:ell_x_variant":[
        "\u039a\u03b1\u03bb\u03bb\u03af\u03c0\u03bf\u03bb\u03b7",
        "\u039a\u03b1\u03bb\u03bb\u03af\u03c0\u03bf\u03bb\u03b9\u03c2"
    ],
    "name:und_x_variant":[
        "Kar\u00e1mpsa"
    ],
    "qs_pg:aaroncc":"GR",
    "qs_pg:gn_country":"GR",
    "qs_pg:gn_fcode":"PPL",
    "qs_pg:gn_pop":556,
    "qs_pg:name":"Kallipolis",
    "qs_pg:name_adm0":"\u0395\u03bb\u03bb\u03ac\u03b4\u03b1",
    "qs_pg:name_adm1":"Macedonia and Thrace",
    "qs_pg:photos_9r":0,
    "qs_pg:photos_sr":0,
    "qs_pg:pop_sr":2,
    "qs_pg:qs_pg_placetype":"locality",
    "qs_pg:qs_pg_placetype_gp":"Town",
    "qs_pg:woe_adm0":23424833,
    "woe:adm0_id":23424833,
    "woe:name_adm0":"\u0395\u03bb\u03bb\u03ac\u03b4\u03b1",
    "woe:name_adm1":"Macedonia and Thrace",
    "woe:placetype":"Town",
    "wof:name":"Kallipolis",
    "wof:placetype":"locality",
    "wof:population":556
},
  "geometry": {"coordinates":[22.22417,40.78972],"type":"Point"}
}