{
  "type": "Feature",
  "properties": {
    "gn:admin1_code":"ESYE23",
    "gn:admin2_code":"39.0",
    "gn:admin3_code":"9141",
    "gn:asciiname":"Karya",
    "gn:country_code":"GR",
    "gn:dem":412,
    "gn:feature_class":"P",
    "gn:feature_code":"PPL",
    "gn:name":"Kary\u00e1",
    "gn:population":0,
    "gn:timezone":"Europe/Athens",
    "iso:country":"GR",
    "name:ell_x_preferred":[
        "Kary\u00e1"
    ],
    "name:ell_x_variant":[
        "\u039a\u03b1\u03c1\u03c5\u03ac"
    ],
    "name:fin_x_preferred":[
        "Kary\u00e1"
    ],
    "name:nld_x_preferred":[
        "Karya"
    ],
    "name:slk_x_preferred":[
        "Karya"
    ],
    "name:und_x_variant":[
        "Kari\u00e1"
    ],
    "wof:name":"Karya",
    "wof:placetype":"locality"
},
  "geometry": {"coordinates":[21.62289,37.79956],"type":"Point"}
}