{
  "type": "Feature",
  "properties": {
    "gn:admin1_code":"ESYE23",
    "gn:admin2_code":"38.0",
    "gn:admin3_code":"9133",
    "gn:asciiname":"Menychtaiika",
    "gn:country_code":"GR",
    "gn:dem":685,
    "gn:feature_class":"P",
    "gn:feature_code":"PPL",
    "gn:name":"Menychta\u00edika",
    "gn:population":0,
    "gn:timezone":"Europe/Athens",
    "iso:country":"GR",
    "name:ell_x_preferred":[
        "Menychta\u00edika"
    ],
    "name:ell_x_variant":[
        "\u039c\u03b5\u03bd\u03c5\u03c7\u03c4\u03b1\u03af\u03b9\u03ba\u03b1"
    ],
    "name:und_x_variant":[
        "Sougl\u00e9\u00efka",
        "Menikhta\u00edika"
    ],
    "wof:name":"Menychtaiika",
    "wof:placetype":"locality"
},
  "geometry": {"coordinates":[21.92117,38.03944],"type":"Point"}
}