{
  "type": "Feature",
  "properties": {
    "gn:admin1_code":"ESYE25",
    "gn:admin2_code":"40.0",
    "gn:admin3_code":"9258",
    "gn:asciiname":"Elaia",
    "gn:cc2":"GR",
    "gn:country_code":"GR",
    "gn:dem":16,
    "gn:feature_class":"P",
    "gn:feature_code":"PPL",
    "gn:name":"Ela\u00eda",
    "gn:population":0,
    "gn:timezone":"Europe/Athens",
    "iso:country":"GR",
    "name:und_x_variant":[
        "Bo\u00fazi",
        "Bo\u00fazion",
        "Ela\u00eda"
    ],
    "wof:name":"Elaia",
    "wof:placetype":"locality"
},
  "geometry": {"coordinates":[21.6907,37.37534],"type":"Point"}
}