{
  "type": "Feature",
  "properties": {
    "iso:country":"GR",
    "qs_pg:aaroncc":"GR",
    "qs_pg:name":"Papiana",
    "qs_pg:name_adm0":"\u0395\u03bb\u03bb\u03ac\u03b4\u03b1",
    "qs_pg:name_adm1":"Aegean",
    "qs_pg:photos":20,
    "qs_pg:photos_1k":4,
    "qs_pg:photos_9k":1,
    "qs_pg:photos_9r":1,
    "qs_pg:photos_all":20,
    "qs_pg:photos_sr":1,
    "qs_pg:pop_sr":0,
    "qs_pg:qs_pg_placetype":"locality",
    "qs_pg:qs_pg_placetype_gp":"Town",
    "qs_pg:woe_adm0":23424833,
    "woe:adm0_id":23424833,
    "woe:name_adm0":"\u0395\u03bb\u03bb\u03ac\u03b4\u03b1",
    "woe:name_adm1":"Aegean",
    "woe:placetype":"Town",
    "wof:name":"Papiana",
    "wof:placetype":"locality"
},
  "geometry": {"coordinates":[26.2232775,39.2131205],"type":"Point"}
}