{
  "type": "Feature",
  "properties": {
    "gn:admin1_code":"ESYE11",
    "gn:admin2_code":"4.0",
    "gn:admin3_code":"9004",
    "gn:asciiname":"Myrovlitis",
    "gn:country_code":"GR",
    "gn:dem":244,
    "gn:feature_class":"P",
    "gn:feature_code":"PPL",
    "gn:name":"Myrovl\u00edtis",
    "gn:population":0,
    "gn:timezone":"Europe/Athens",
    "iso:country":"GR",
    "name:ell_x_preferred":[
        "Myrovl\u00edtis"
    ],
    "name:ell_x_variant":[
        "\u039c\u03c5\u03c1\u03bf\u03b2\u03bb\u03ae\u03c4\u03b7\u03c2"
    ],
    "name:und_x_variant":[
        "Burazanl\u00ed",
        "Mirovl\u00edtis"
    ],
    "wof:name":"Myrovlitis",
    "wof:placetype":"locality"
},
  "geometry": {"coordinates":[24.3161,41.16742],"type":"Point"}
}