{
  "type": "Feature",
  "properties": {
    "gn:admin1_code":"ESYE12",
    "gn:admin2_code":"15.0",
    "gn:admin3_code":"9060",
    "gn:asciiname":"Azapiko",
    "gn:country_code":"GR",
    "gn:dem":14,
    "gn:feature_class":"P",
    "gn:feature_code":"PPL",
    "gn:name":"Az\u00e1piko",
    "gn:population":5,
    "gn:timezone":"Europe/Athens",
    "iso:country":"GR",
    "name:ell_x_preferred":[
        "\u0391\u03b6\u03ac\u03c0\u03b9\u03ba\u03bf"
    ],
    "name:eng_x_preferred":[
        "Azapiko"
    ],
    "wof:name":"Azapiko",
    "wof:placetype":"locality",
    "wof:population":5
},
  "geometry": {"coordinates":[23.85947,40.02216],"type":"Point"}
}