{
  "type": "Feature",
  "properties": {
    "gn:admin1_code":"ESYE43",
    "gn:admin2_code":"44.0",
    "gn:admin3_code":"9317",
    "gn:asciiname":"Keramota",
    "gn:cc2":"GR",
    "gn:country_code":"GR",
    "gn:dem":356,
    "gn:feature_class":"P",
    "gn:feature_code":"PPL",
    "gn:name":"Keramot\u00e1",
    "gn:population":0,
    "gn:timezone":"Europe/Athens",
    "iso:country":"GR",
    "name:und_x_variant":[
        "Keramidhi\u00e1",
        "Keramot\u00e1"
    ],
    "wof:name":"Keramota",
    "wof:placetype":"locality"
},
  "geometry": {"coordinates":[24.7419,35.33095],"type":"Point"}
}