{
  "type": "Feature",
  "properties": {
    "gn:admin1_code":"ESYE23",
    "gn:admin2_code":"31.0",
    "gn:admin3_code":"9128",
    "gn:asciiname":"Xiropigado",
    "gn:country_code":"GR",
    "gn:dem":22,
    "gn:feature_class":"P",
    "gn:feature_code":"PPL",
    "gn:name":"Xirop\u00edgado",
    "gn:population":0,
    "gn:timezone":"Europe/Athens",
    "iso:country":"GR",
    "name:ell_x_preferred":[
        "Xirop\u00edgado"
    ],
    "name:ell_x_variant":[
        "\u039e\u03b7\u03c1\u03bf\u03c0\u03ae\u03b3\u03b1\u03b4\u03bf",
        "Xirop\u00edgadon",
        "\u039e\u03b7\u03c1\u03bf\u03c0\u03ae\u03b3\u03b1\u03b4\u03bf\u03bd"
    ],
    "name:und_x_variant":[
        "Xiropigadho",
        "Xirop\u00edgadhon"
    ],
    "wof:name":"Xiropigado",
    "wof:placetype":"locality"
},
  "geometry": {"coordinates":[21.8588,38.40262],"type":"Point"}
}