{
  "type": "Feature",
  "properties": {
    "gn:gn_country":"GR",
    "gn:gn_fcode":"PPL",
    "gn:gn_pop":57,
    "gn:population":28,
    "iso:country":"GR",
    "name:ell_x_preferred":[
        "\u039a\u03b1\u03c1\u03b2\u03b1\u03c3\u03b1\u03c1\u03ac\u03c2"
    ],
    "name:eng_x_preferred":[
        "Karvasaras"
    ],
    "name:unk_x_variant":[
        "Karvasar\u00e1s"
    ],
    "qs_pg:aaroncc":"GR",
    "qs_pg:gn_country":"GR",
    "qs_pg:gn_fcode":"PPL",
    "qs_pg:gn_pop":57,
    "qs_pg:name":"Karvasaras",
    "qs_pg:name_adm0":"\u0395\u03bb\u03bb\u03ac\u03b4\u03b1",
    "qs_pg:name_adm1":"Thessaly and Continental Greece",
    "qs_pg:photos_9r":0,
    "qs_pg:photos_sr":0,
    "qs_pg:pop_sr":1,
    "qs_pg:qs_pg_placetype":"locality",
    "qs_pg:qs_pg_placetype_gp":"Town",
    "qs_pg:woe_adm0":23424833,
    "woe:adm0_id":23424833,
    "woe:name_adm0":"\u0395\u03bb\u03bb\u03ac\u03b4\u03b1",
    "woe:name_adm1":"Thessaly and Continental Greece",
    "woe:placetype":"Town",
    "wof:name":"Karvasaras",
    "wof:placetype":"locality",
    "wof:population":28
},
  "geometry": {"coordinates":[21.66222,39.25194],"type":"Point"}
}