{
  "type": "Feature",
  "properties": {
    "gn:gn_country":"GR",
    "gn:gn_fcode":"PPL",
    "gn:gn_pop":394,
    "gn:population":295,
    "iso:country":"GR",
    "name:ceb_x_preferred":[
        "Boukaris"
    ],
    "name:deu_x_preferred":[
        "Boukaris"
    ],
    "name:ell_x_preferred":[
        "\u039a\u03bf\u03c5\u03c3\u03c0\u03ac\u03b4\u03b5\u03c2"
    ],
    "name:ell_x_variant":[
        "\u039c\u03c0\u03bf\u03cd\u03ba\u03b1\u03c1\u03b7\u03c2 \u039a\u03ad\u03c1\u03ba\u03c5\u03c1\u03b1\u03c2"
    ],
    "name:eng_x_preferred":[
        "Kouspades"
    ],
    "name:eng_x_variant":[
        "Boukaris"
    ],
    "name:nld_x_preferred":[
        "Kouspades"
    ],
    "name:nld_x_variant":[
        "Boukaris"
    ],
    "name:swe_x_preferred":[
        "Kousp\u00e1des"
    ],
    "name:swe_x_variant":[
        "Boukaris"
    ],
    "name:unk_x_variant":[
        "Kousp\u00e1dhes"
    ],
    "qs_pg:aaroncc":"GR",
    "qs_pg:gn_country":"GR",
    "qs_pg:gn_fcode":"PPL",
    "qs_pg:gn_pop":394,
    "qs_pg:name":"Kousp\u00e1des",
    "qs_pg:photos_9r":0,
    "qs_pg:photos_sr":0,
    "qs_pg:pop_sr":2,
    "qs_pg:qs_pg_placetype":"locality",
    "wof:name":"Kousp\u00e1des",
    "wof:placetype":"locality",
    "wof:population":295
},
  "geometry": {"coordinates":[19.9775,39.45444],"type":"Point"}
}