{
  "type": "Feature",
  "properties": {
    "gn:admin1_code":"ESYE43",
    "gn:admin2_code":"45.0",
    "gn:admin3_code":"9307",
    "gn:asciiname":"Lagouta",
    "gn:country_code":"GR",
    "gn:dem":244,
    "gn:feature_class":"P",
    "gn:feature_code":"PPL",
    "gn:name":"Lago\u00fata",
    "gn:population":0,
    "gn:timezone":"Europe/Athens",
    "iso:country":"GR",
    "name:ell_x_preferred":[
        "Lago\u00fata"
    ],
    "name:ell_x_variant":[
        "\u039b\u03b1\u03b3\u03bf\u03cd\u03c4\u03b1"
    ],
    "wof:name":"Lagouta",
    "wof:placetype":"locality"
},
  "geometry": {"coordinates":[25.29728,35.0675],"type":"Point"}
}