{
  "type": "Feature",
  "properties": {
    "gn:population":2234,
    "iso:country":"GR",
    "name:ara_x_preferred":[
        "\u0643\u0627\u062a\u0648\u0646\u0627\u060c \u0623\u064a\u062a\u0648\u0644\u064a\u0627 \u0643\u064a \u0623\u0643\u0627\u0631\u0646\u0627\u0646\u064a\u0627"
    ],
    "name:ara_x_variant":[
        "\u0643\u0627\u062a\u0648\u0646\u0627"
    ],
    "name:ceb_x_preferred":[
        "Kato\u00fana"
    ],
    "name:ell_x_preferred":[
        "\u039a\u03b1\u03c4\u03bf\u03cd\u03bd\u03b1"
    ],
    "name:ell_x_variant":[
        "\u039a\u03b1\u03c4\u03bf\u03cd\u03bd\u03b1 \u0391\u03b9\u03c4\u03c9\u03bb\u03bf\u03b1\u03ba\u03b1\u03c1\u03bd\u03b1\u03bd\u03af\u03b1\u03c2"
    ],
    "name:eng_x_preferred":[
        "Katouna"
    ],
    "name:nld_x_preferred":[
        "Katouna"
    ],
    "name:nno_x_preferred":[
        "Kato\u00fana"
    ],
    "name:ron_x_preferred":[
        "Katouna"
    ],
    "name:swe_x_preferred":[
        "Kato\u00fana"
    ],
    "qs:a0":"Greece",
    "qs:a1":"*\u0394\u03a5\u03a4\u0399\u039a\u0397 \u0395\u039b\u039b\u0391\u0394\u0391",
    "qs:a1_alt":"DYTIKH ELLADA",
    "qs:a1r":"0",
    "qs:a2_alt":"AITVLIA KAI AKARNANIA",
    "qs:adm0":"Greece",
    "qs:la_lc":"*",
    "qs:level":"locality",
    "qs:loc":"\u039a\u0391\u03a4\u039f\u03a5\u039d\u0391",
    "qs:loc_alt":"KATOYNA",
    "qs:pop":0,
    "qs:type":"buffered point",
    "wof:name":"\u039a\u0391\u03a4\u039f\u03a5\u039d\u0391",
    "wof:placetype":"locality",
    "wof:population":2234
},
  "geometry": {"coordinates":[21.117119,38.785702],"type":"Point"}
}