{
  "type": "Feature",
  "properties": {
    "gn:population":2099,
    "iso:country":"GR",
    "name:ara_x_preferred":[
        "\u0645\u064a\u0633\u0648\u0628\u0648\u062a\u0627\u0645\u064a\u0627"
    ],
    "name:bul_x_historical":[
        "\u0427\u0435\u0442\u0438\u0440\u043e\u043a"
    ],
    "name:bul_x_preferred":[
        "\u0427\u0435\u0442\u0438\u0440\u043e\u043a"
    ],
    "name:bul_x_variant":[
        "\u041c\u0435\u0441\u043e\u043f\u043e\u0442\u0430\u043c\u0438\u044f"
    ],
    "name:ceb_x_preferred":[
        "Mesopotam\u00eda"
    ],
    "name:ell_x_historical":[
        "\u03a4\u03c3\u03b5\u03c4\u03b9\u03c1\u03ac\u03ba\u03b7",
        "\u03a4\u03c3\u03b5\u03c4\u03b5\u03c1\u03ac\u03ba\u03b7",
        "\u03a4\u03c3\u03b5\u03c4\u03b9\u03c1\u03cc\u03ba\u03b9"
    ],
    "name:ell_x_preferred":[
        "\u039c\u03b5\u03c3\u03bf\u03c0\u03bf\u03c4\u03b1\u03bc\u03af\u03b1 \u039a\u03b1\u03c3\u03c4\u03bf\u03c1\u03b9\u03ac\u03c2"
    ],
    "name:ell_x_variant":[
        "\u039c\u03b5\u03c3\u03bf\u03c0\u03bf\u03c4\u03b1\u03bc\u03b9\u03ac",
        "\u039c\u03b5\u03c3\u03bf\u03c0\u03bf\u03c4\u03b1\u03bc\u03af\u03b1",
        "\u03a4\u03c3\u03b5\u03c4\u03b9\u03c1\u03ac\u03ba\u03b7",
        "\u03a4\u03c3\u03b5\u03c4\u03b5\u03c1\u03ac\u03ba\u03b7",
        "\u03a4\u03c3\u03b5\u03c4\u03b9\u03c1\u03cc\u03ba\u03b9"
    ],
    "name:eng_x_preferred":[
        "Mesopotamia"
    ],
    "name:fin_x_preferred":[
        "Mesopotam\u00eda"
    ],
    "name:ita_x_preferred":[
        "Mesopotamia"
    ],
    "name:mkd_x_historical":[
        "\u0427\u0435\u0442\u0438\u0440\u043e\u043a"
    ],
    "name:mkd_x_preferred":[
        "\u0427\u0435\u0442\u0438\u0440\u043e\u043a"
    ],
    "name:mkd_x_variant":[
        "\u041c\u0435\u0441\u043e\u043f\u043e\u0442\u0430\u043c\u0438\u0458\u0430"
    ],
    "name:nld_x_preferred":[
        "Mesopotamia"
    ],
    "name:nno_x_preferred":[
        "Mesopotami\u00e1 i Kastori\u00e1"
    ],
    "name:ron_x_preferred":[
        "Mesopotamia"
    ],
    "name:rus_x_preferred":[
        "\u041c\u0435\u0441\u043e\u043f\u043e\u0442\u0430\u043c\u044c\u044f"
    ],
    "name:sqi_x_historical":[
        "\u00c7etiroku"
    ],
    "name:sqi_x_preferred":[
        "\u00c7etiroku"
    ],
    "name:sqi_x_variant":[
        "Mesopotami\u00e1"
    ],
    "name:swe_x_preferred":[
        "Mesopotam\u00eda"
    ],
    "name:unk_x_variant":[
        "Tseter\u00e1ki"
    ],
    "qs:a0":"Greece",
    "qs:a1":"*\u0394\u03a5\u03a4\u0399\u039a\u0397 \u039c\u0391\u039a\u0395\u0394\u039f\u039d\u0399\u0391",
    "qs:a1_alt":"DYTIKH MAKEDONIA",
    "qs:a1r":"0",
    "qs:a2_alt":"KASTORIA",
    "qs:adm0":"Greece",
    "qs:la_lc":"*",
    "qs:level":"locality",
    "qs:loc":"\u039c\u0395\u03a3\u039f\u03a0\u039f\u03a4\u0391\u039c\u0399\u0391",
    "qs:loc_alt":"MESOPOTAMIA",
    "qs:pop":0,
    "qs:type":"buffered point",
    "wd:wordcount":308,
    "wof:name":"\u039c\u0395\u03a3\u039f\u03a0\u039f\u03a4\u0391\u039c\u0399\u0391",
    "wof:placetype":"locality",
    "wof:population":2099
},
  "geometry": {"coordinates":[21.158331,40.504425],"type":"Point"}
}