{
  "type": "Feature",
  "properties": {
    "gn:admin1_code":"ESYE21",
    "gn:admin2_code":"18.0",
    "gn:admin3_code":"9079",
    "gn:asciiname":"Ano Palaiokklisi",
    "gn:country_code":"GR",
    "gn:dem":179,
    "gn:feature_class":"P",
    "gn:feature_code":"PPL",
    "gn:name":"\u00c1no Palaiokkl\u00edsi",
    "gn:population":0,
    "gn:timezone":"Europe/Athens",
    "iso:country":"GR",
    "name:ell_x_preferred":[
        "\u00c1no Palaiokkl\u00edsi"
    ],
    "name:ell_x_variant":[
        "\u0386\u03bd\u03c9 \u03a0\u03b1\u03bb\u03b1\u03b9\u03bf\u03ba\u03ba\u03bb\u03ae\u03c3\u03b9",
        "\u00c1no Palaiokkl\u00edsion",
        "\u0386\u03bd\u03c9 \u03a0\u03b1\u03bb\u03b1\u03b9\u03bf\u03ba\u03ba\u03bb\u03ae\u03c3\u03b9\u03bf\u03bd"
    ],
    "wof:name":"Ano Palaiokklisi",
    "wof:placetype":"locality"
},
  "geometry": {"coordinates":[20.41619,39.58208],"type":"Point"}
}