{
  "type": "Feature",
  "properties": {
    "gn:gn_country":"GR",
    "gn:gn_fcode":"PPL",
    "gn:gn_pop":214,
    "gn:population":214,
    "iso:country":"GR",
    "name:ceb_x_preferred":[
        "Neoch\u00f3ri"
    ],
    "name:deu_x_preferred":[
        "Neochori"
    ],
    "name:ell_x_preferred":[
        "\u039d\u03b5\u03bf\u03c7\u03ce\u03c1\u03b9"
    ],
    "name:ell_x_variant":[
        "\u039d\u03b5\u03bf\u03c7\u03ce\u03c1\u03b9\u03bf\u03bd",
        "\u039d\u03b5\u03bf\u03c7\u03ce\u03c1\u03b9 \u0398\u03b5\u03c3\u03c0\u03c1\u03c9\u03c4\u03af\u03b1\u03c2"
    ],
    "name:eng_x_preferred":[
        "Neochori"
    ],
    "name:sqi_x_preferred":[
        "Njihori"
    ],
    "name:swe_x_preferred":[
        "Neoch\u00f3ri"
    ],
    "name:unk_x_variant":[
        "Neoch\u00f3ri"
    ],
    "qs_pg:aaroncc":"GR",
    "qs_pg:gn_country":"GR",
    "qs_pg:gn_fcode":"PPL",
    "qs_pg:gn_pop":214,
    "qs_pg:name":"Neoch\u00f3rion",
    "qs_pg:photos_9r":0,
    "qs_pg:photos_sr":0,
    "qs_pg:pop_sr":2,
    "qs_pg:qs_pg_placetype":"locality",
    "wof:name":"Neoch\u00f3rion",
    "wof:placetype":"locality",
    "wof:population":214
},
  "geometry": {"coordinates":[20.43833,39.51],"type":"Point"}
}