{
  "type": "Feature",
  "properties": {
    "gn:country":"GR",
    "gn:fcode":"ADM3",
    "gn:population":1011,
    "iso:country":"GR",
    "name:ell_x_preferred":[
        "\u0391\u03bd\u03c4\u03b9\u03c0\u03ac\u03c1\u03bf\u03c5"
    ],
    "qs_pg:aaroncc":"GR",
    "qs_pg:gn_country":"GR",
    "qs_pg:gn_fcode":"ADM3",
    "qs_pg:gn_pop":1011,
    "qs_pg:name":"Dimos Antiparos",
    "qs_pg:photos_9r":0,
    "qs_pg:photos_sr":0,
    "qs_pg:pop_sr":3,
    "qs_pg:qs_pg_placetype":"localadmin",
    "wof:name":"Dimos Antiparos",
    "wof:placetype":"localadmin",
    "wof:population":1011
},
  "geometry": {"coordinates":[25.04229,36.99256],"type":"Point"}
}