{
  "type": "Feature",
  "properties": {
    "gn:admin1_code":"ESYE14",
    "gn:admin2_code":"21.0",
    "gn:admin3_code":"9097.0",
    "gn:asciiname":"Alexandrini",
    "gn:country_code":"GR",
    "gn:dem":2,
    "gn:feature_class":"P",
    "gn:feature_code":"PPL",
    "gn:name":"Alexandrini",
    "gn:population":0,
    "gn:timezone":"Europe/Athens",
    "iso:country":"GR",
    "name:ell_x_preferred":[
        "\u0391\u03bb\u03b5\u03be\u03b1\u03bd\u03b4\u03c1\u03b9\u03bd\u03ae"
    ],
    "wof:name":"Alexandrini",
    "wof:placetype":"locality"
},
  "geometry": {"coordinates":[22.7193,39.89492],"type":"Point"}
}