{
  "type": "Feature",
  "properties": {
    "gn:admin1_code":"ESYE42",
    "gn:admin2_code":"49.0",
    "gn:admin3_code":"9268",
    "gn:asciiname":"Lamyra",
    "gn:country_code":"GR",
    "gn:dem":162,
    "gn:feature_class":"P",
    "gn:feature_code":"PPL",
    "gn:name":"L\u00e1myra",
    "gn:population":0,
    "gn:timezone":"Europe/Athens",
    "iso:country":"GR",
    "name:ell_x_preferred":[
        "L\u00e1myra"
    ],
    "name:ell_x_variant":[
        "\u039b\u03ac\u03bc\u03c5\u03c1\u03b1"
    ],
    "name:und_x_variant":[
        "L\u00e1mira"
    ],
    "wof:name":"Lamyra",
    "wof:placetype":"locality"
},
  "geometry": {"coordinates":[24.91331,37.83154],"type":"Point"}
}