{
  "type": "Feature",
  "properties": {
    "gn:admin1_code":"ESYE31",
    "gn:admin2_code":"406101.0",
    "gn:admin3_code":"9209",
    "gn:asciiname":"Karvounadhes",
    "gn:country_code":"GR",
    "gn:dem":327,
    "gn:feature_class":"P",
    "gn:feature_code":"PPL",
    "gn:name":"Karvoun\u00e1dhes",
    "gn:population":119,
    "gn:timezone":"Europe/Athens",
    "iso:country":"GR",
    "name:ell_x_preferred":[
        "\u039a\u03b1\u03c1\u03b2\u03bf\u03c5\u03bd\u03ac\u03b4\u03b5\u03c2"
    ],
    "name:eng_x_preferred":[
        "Karvounades"
    ],
    "wof:name":"Karvounadhes",
    "wof:placetype":"locality",
    "wof:population":119
},
  "geometry": {"coordinates":[22.9749,36.2051],"type":"Point"}
}