{
  "type": "Feature",
  "properties": {
    "gn:admin1_code":"ESYE11",
    "gn:admin2_code":"2.0",
    "gn:admin3_code":"9021",
    "gn:asciiname":"Porpi",
    "gn:country_code":"GR",
    "gn:dem":32,
    "gn:feature_class":"P",
    "gn:feature_code":"PPL",
    "gn:name":"P\u00f3rpi",
    "gn:population":0,
    "gn:timezone":"Europe/Athens",
    "iso:country":"GR",
    "name:ell_x_preferred":[
        "P\u00f3rpi"
    ],
    "name:ell_x_variant":[
        "\u03a0\u03cc\u03c1\u03c0\u03b7"
    ],
    "wof:name":"Porpi",
    "wof:placetype":"locality"
},
  "geometry": {"coordinates":[25.23882,41.01863],"type":"Point"}
}