{
  "type": "Feature",
  "properties": {
    "gn:admin1_code":"ESYE23",
    "gn:admin2_code":"38.0",
    "gn:admin3_code":"9132",
    "gn:asciiname":"Trousaki",
    "gn:country_code":"GR",
    "gn:dem":465,
    "gn:feature_class":"P",
    "gn:feature_code":"PPL",
    "gn:name":"Trous\u00e1ki",
    "gn:population":0,
    "gn:timezone":"Europe/Athens",
    "iso:country":"GR",
    "name:ell_x_preferred":[
        "\u03a4\u03c1\u03bf\u03c5\u03c3\u03ac\u03ba\u03b9"
    ],
    "name:ell_x_variant":[
        "\u03a4\u03c1\u03bf\u03c5\u03c3\u03ac\u03ba\u03b9\u03bf\u03bd"
    ],
    "name:und_x_variant":[
        "Trous\u00e1ki",
        "Trous\u00e1kion"
    ],
    "wof:name":"Trousaki",
    "wof:placetype":"locality"
},
  "geometry": {"coordinates":[21.76794,38.04436],"type":"Point"}
}