{
  "type": "Feature",
  "properties": {
    "iso:country":"GR",
    "qs:a0":"Greece",
    "qs:a1":"*\u0391\u039d\u0391\u03a4\u039f\u039b\u0399\u039a\u0397 \u039c\u0391\u039a\u0395\u0394\u039f\u039d\u0399\u0391 \u039a\u0391\u0399 \u0398\u03a1\u0391\u039a\u0397",
    "qs:a1_alt":"ANATOLIKH MAKEDONIA KAI URAKH",
    "qs:a1r":"0",
    "qs:a2_alt":"KABALA",
    "qs:adm0":"Greece",
    "qs:la_lc":"*",
    "qs:level":"locality",
    "qs:loc":"\u0391\u039c\u03a5\u0393\u0394\u0391\u039b\u0395\u03a9\u039d",
    "qs:loc_alt":"AMYGDALEVN",
    "qs:pop":0,
    "qs:type":"buffered point",
    "wof:name":"\u0391\u039c\u03a5\u0393\u0394\u0391\u039b\u0395\u03a9\u039d",
    "wof:placetype":"locality"
},
  "geometry": {"coordinates":[24.360105,40.962478],"type":"Point"}
}