{
  "type": "Feature",
  "properties": {
    "gn:admin1_code":"ESYE43",
    "gn:admin2_code":"45.0",
    "gn:admin3_code":"9302",
    "gn:asciiname":"Damania",
    "gn:country_code":"GR",
    "gn:dem":425,
    "gn:feature_class":"P",
    "gn:feature_code":"PPL",
    "gn:name":"Dam\u00e1nia",
    "gn:population":0,
    "gn:timezone":"Europe/Athens",
    "iso:country":"GR",
    "name:ell_x_preferred":[
        "Dam\u00e1nia"
    ],
    "name:ell_x_variant":[
        "\u0394\u03b1\u03bc\u03ac\u03bd\u03b9\u03b1",
        "Dham\u00e1nia"
    ],
    "wof:name":"Damania",
    "wof:placetype":"locality"
},
  "geometry": {"coordinates":[25.11505,35.13406],"type":"Point"}
}