{
  "type": "Feature",
  "properties": {
    "gn:admin1_code":"ESYE23",
    "gn:admin2_code":"31.0",
    "gn:admin3_code":"9123",
    "gn:asciiname":"Lendini",
    "gn:country_code":"GR",
    "gn:dem":151,
    "gn:feature_class":"P",
    "gn:feature_code":"PPL",
    "gn:name":"Lend\u00edni",
    "gn:population":7,
    "gn:timezone":"Europe/Athens",
    "iso:country":"GR",
    "name:ell_x_preferred":[
        "\u039b\u03b5\u03bd\u03c4\u03af\u03bd\u03b7"
    ],
    "name:eng_x_preferred":[
        "Lentini"
    ],
    "wof:name":"Lendini",
    "wof:placetype":"locality",
    "wof:population":7
},
  "geometry": {"coordinates":[21.37718,38.7936],"type":"Point"}
}