{
  "type": "Feature",
  "properties": {
    "gn:admin1_code":"ESYE23",
    "gn:admin2_code":"38.0",
    "gn:admin3_code":"9133",
    "gn:asciiname":"Korfes",
    "gn:country_code":"GR",
    "gn:dem":879,
    "gn:feature_class":"P",
    "gn:feature_code":"PPL",
    "gn:name":"Korf\u00e9s",
    "gn:population":0,
    "gn:timezone":"Europe/Athens",
    "iso:country":"GR",
    "name:ell_x_preferred":[
        "\u039a\u03bf\u03c1\u03c6\u03ad\u03c2"
    ],
    "name:ell_x_variant":[
        "\u039a\u03bf\u03c1\u03c6\u03b1\u03af"
    ],
    "name:und_x_variant":[
        "Kir\u00edtsova",
        "Korf\u00e9s",
        "Korfa\u00ed"
    ],
    "wof:name":"Korfes",
    "wof:placetype":"locality"
},
  "geometry": {"coordinates":[22.03094,38.08725],"type":"Point"}
}