{
  "type": "Feature",
  "properties": {
    "gn:admin1_code":"ESYE42",
    "gn:admin2_code":"49.0",
    "gn:admin3_code":"9301",
    "gn:asciiname":"Triantaros",
    "gn:country_code":"GR",
    "gn:dem":329,
    "gn:feature_class":"P",
    "gn:feature_code":"PPL",
    "gn:name":"Triant\u00e1ros",
    "gn:population":0,
    "gn:timezone":"Europe/Athens",
    "iso:country":"GR",
    "name:und_x_variant":[
        "Triant\u00e1ros",
        "\u03a4\u03c1\u03b9\u03b1\u03bd\u03c4\u03ac\u03c1\u03bf\u03c2"
    ],
    "wof:name":"Triantaros",
    "wof:placetype":"locality"
},
  "geometry": {"coordinates":[25.19303,37.55982],"type":"Point"}
}