{
  "type": "Feature",
  "properties": {
    "gn:admin1_code":"ESYE12",
    "gn:admin2_code":"5.0",
    "gn:admin3_code":"9050",
    "gn:asciiname":"Sitochori",
    "gn:country_code":"GR",
    "gn:dem":88,
    "gn:feature_class":"P",
    "gn:feature_code":"PPL",
    "gn:name":"Sitoch\u00f3ri",
    "gn:population":531,
    "gn:timezone":"Europe/Athens",
    "iso:country":"GR",
    "name:deu_x_preferred":[
        "Sitochori"
    ],
    "name:ell_x_preferred":[
        "\u03a3\u03b9\u03c4\u03bf\u03c7\u03ce\u03c1\u03b9"
    ],
    "name:ell_x_variant":[
        "Sitoch\u00f3ri",
        "Sitoch\u00f3rion",
        "\u03a3\u03b9\u03c4\u03bf\u03c7\u03ce\u03c1\u03b9\u03bf\u03bd"
    ],
    "name:eng_x_preferred":[
        "Sitochori"
    ],
    "name:und_x_variant":[
        "Sitokh\u00f3ri",
        "Ts\u00edntzos",
        "Sitokh\u00f3rion"
    ],
    "wof:name":"Sitochori",
    "wof:placetype":"locality",
    "wof:population":531
},
  "geometry": {"coordinates":[23.61858,40.88172],"type":"Point"}
}