{
  "type": "Feature",
  "properties": {
    "gn:admin1_code":"ESYE24",
    "gn:admin2_code":"34.0",
    "gn:admin3_code":"9152",
    "gn:asciiname":"Lofiskos",
    "gn:cc2":"GR",
    "gn:country_code":"GR",
    "gn:dem":100,
    "gn:feature_class":"P",
    "gn:feature_code":"PPL",
    "gn:name":"Lof\u00edskos",
    "gn:population":0,
    "gn:timezone":"Europe/Athens",
    "iso:country":"GR",
    "name:und_x_variant":[
        "Bo\u00fazi",
        "Vo\u00fazion",
        "Vo\u00fazi",
        "Lof\u00edskos"
    ],
    "wof:name":"Lofiskos",
    "wof:placetype":"locality"
},
  "geometry": {"coordinates":[24.1139,38.48385],"type":"Point"}
}