{
  "type": "Feature",
  "properties": {
    "gn:admin1_code":"ESYE11",
    "gn:admin2_code":"3.0",
    "gn:admin3_code":"9018",
    "gn:asciiname":"Palaio Olvio",
    "gn:country_code":"GR",
    "gn:dem":23,
    "gn:feature_class":"P",
    "gn:feature_code":"PPL",
    "gn:name":"Palai\u00f3 \u00d3lvio",
    "gn:population":0,
    "gn:timezone":"Europe/Athens",
    "iso:country":"GR",
    "name:ell_x_preferred":[
        "Palai\u00f3 \u00d3lvio"
    ],
    "name:ell_x_variant":[
        "\u03a0\u03b1\u03bb\u03b1\u03b9\u03cc \u038c\u03bb\u03b2\u03b9\u03bf",
        "\u03a0\u03b1\u03bb\u03b1\u03b9\u03cc\u03bd \u038c\u03bb\u03b2\u03b9\u03bf\u03bd"
    ],
    "name:und_x_variant":[
        "\u00d3lvion",
        "Palai\u00f3n \u00d3lvion"
    ],
    "wof:name":"Palaio Olvio",
    "wof:placetype":"locality"
},
  "geometry": {"coordinates":[24.80659,41.01613],"type":"Point"}
}