{
  "type": "Feature",
  "properties": {
    "gn:country":"GR",
    "gn:fcode":"PPL",
    "gn:population":61,
    "iso:country":"GR",
    "name:ell_x_preferred":[
        "\u03a0\u03b1\u03bb\u03b1\u03bc\u03c0\u03ac\u03c2"
    ],
    "name:und_x_variant":[
        "Palamb\u00e1"
    ],
    "qs_pg:aaroncc":"GR",
    "qs_pg:gn_country":"GR",
    "qs_pg:gn_fcode":"PPL",
    "qs_pg:gn_pop":61,
    "qs_pg:name":"Palamp\u00e1s",
    "qs_pg:photos_9r":0,
    "qs_pg:photos_sr":0,
    "qs_pg:pop_sr":1,
    "qs_pg:qs_pg_placetype":"locality",
    "wof:name":"Palamp\u00e1s",
    "wof:placetype":"locality",
    "wof:population":61
},
  "geometry": {"coordinates":[20.27889,39.69528],"type":"Point"}
}