{
  "type": "Feature",
  "properties": {
    "gn:admin1_code":"ESYE25",
    "gn:admin2_code":"41.0",
    "gn:admin3_code":"9239",
    "gn:asciiname":"Tripotamo",
    "gn:country_code":"GR",
    "gn:dem":409,
    "gn:feature_class":"P",
    "gn:feature_code":"PPL",
    "gn:name":"Trip\u00f3tamo",
    "gn:population":0,
    "gn:timezone":"Europe/Athens",
    "iso:country":"GR",
    "name:ell_x_preferred":[
        "Trip\u00f3tamo"
    ],
    "name:ell_x_variant":[
        "\u03a4\u03c1\u03b9\u03c0\u03cc\u03c4\u03b1\u03bc\u03bf",
        "\u03a4\u03c1\u03b9\u03c0\u03cc\u03c4\u03b1\u03bc\u03bf\u03bd"
    ],
    "name:und_x_variant":[
        "Ded\u00e9be\u00ef",
        "Trip\u00f3tamon"
    ],
    "wof:name":"Tripotamo",
    "wof:placetype":"locality"
},
  "geometry": {"coordinates":[22.09959,37.36244],"type":"Point"}
}