{
  "type": "Feature",
  "properties": {
    "gn:country":"GR",
    "gn:fcode":"PPL",
    "gn:population":0,
    "iso:country":"GR",
    "name:bre_x_preferred":[
        "Stimfalos"
    ],
    "name:ceb_x_preferred":[
        "Stymfal\u00eda"
    ],
    "name:deu_x_preferred":[
        "Stymfalia"
    ],
    "name:ell_x_historical":[
        "\u039c\u03ac\u03c4\u03c3\u03b9\u03b6\u03b1"
    ],
    "name:ell_x_preferred":[
        "\u03a3\u03c4\u03c5\u03bc\u03c6\u03b1\u03bb\u03af\u03b1"
    ],
    "name:ell_x_variant":[
        "\u039c\u03ac\u03c4\u03c3\u03b9\u03b6\u03b1",
        "\u0394\u03ae\u03bc\u03bf\u03c2 \u03a3\u03c4\u03c5\u03bc\u03c6\u03b1\u03bb\u03af\u03b1\u03c2"
    ],
    "name:eng_x_preferred":[
        "Stymfalia"
    ],
    "name:eng_x_variant":[
        "Stymphalia"
    ],
    "name:fin_x_preferred":[
        "Stymfal\u00eda"
    ],
    "name:fra_x_preferred":[
        "Stymphale"
    ],
    "name:gle_x_preferred":[
        "Stiomfalas"
    ],
    "name:ita_x_preferred":[
        "Stymfalia"
    ],
    "name:jpn_x_preferred":[
        "\u30b9\u30c6\u30e5\u30e0\u30d1\u30fc\u30ed\u30b9"
    ],
    "name:nld_x_preferred":[
        "Stymfalia"
    ],
    "name:nno_x_preferred":[
        "Stymfal\u00eda"
    ],
    "name:ron_x_preferred":[
        "Stymfalia"
    ],
    "name:rus_x_preferred":[
        "\u0421\u0442\u0438\u043c\u0444\u0430\u043b\u0438\u044f"
    ],
    "name:spa_x_preferred":[
        "Stimfal\u00eda"
    ],
    "name:swe_x_preferred":[
        "Stymfal\u00eda"
    ],
    "name:und_x_variant":[
        "B\u00e1tziza"
    ],
    "qs_pg:aaroncc":"GR",
    "qs_pg:gn_country":"GR",
    "qs_pg:gn_fcode":"PPL",
    "qs_pg:gn_pop":0,
    "qs_pg:name":"Stymfalia",
    "qs_pg:name_adm0":"\u0395\u03bb\u03bb\u03ac\u03b4\u03b1",
    "qs_pg:name_adm1":"Peloponnese Western Greece and the Ionian Islands",
    "qs_pg:photos_9k":1,
    "qs_pg:photos_9r":4,
    "qs_pg:photos_all":197,
    "qs_pg:photos_sr":0,
    "qs_pg:pop_sr":0,
    "qs_pg:qs_pg_placetype":"locality",
    "qs_pg:qs_pg_placetype_gp":"Town",
    "qs_pg:woe_adm0":23424833,
    "woe:adm0_id":23424833,
    "woe:name_adm0":"\u0395\u03bb\u03bb\u03ac\u03b4\u03b1",
    "woe:name_adm1":"Peloponnese Western Greece and the Ionian Islands",
    "woe:placetype":"Town",
    "wof:name":"Stymfalia",
    "wof:placetype":"locality",
    "wof:population":151
},
  "geometry": {"coordinates":[22.46667,37.88333],"type":"Point"}
}