{
  "type": "Feature",
  "properties": {
    "gn:admin1_code":"ESYE43",
    "gn:admin2_code":"43.0",
    "gn:admin3_code":"9323",
    "gn:asciiname":"Kalami",
    "gn:country_code":"GR",
    "gn:dem":337,
    "gn:feature_class":"P",
    "gn:feature_code":"PPL",
    "gn:name":"Kal\u00e1mi",
    "gn:population":0,
    "gn:timezone":"Europe/Athens",
    "iso:country":"GR",
    "name:ell_x_preferred":[
        "Kal\u00e1mi"
    ],
    "name:ell_x_variant":[
        "\u039a\u03b1\u03bb\u03ac\u03bc\u03b9"
    ],
    "wof:name":"Kalami",
    "wof:placetype":"locality"
},
  "geometry": {"coordinates":[23.74426,35.43118],"type":"Point"}
}