{
  "type": "Feature",
  "properties": {
    "gn:admin1_code":"ESYE25",
    "gn:admin2_code":"40.0",
    "gn:admin3_code":"9255",
    "gn:asciiname":"Kastania",
    "gn:country_code":"GR",
    "gn:dem":292,
    "gn:feature_class":"P",
    "gn:feature_code":"PPL",
    "gn:name":"Kast\u00e1nia",
    "gn:population":0,
    "gn:timezone":"Europe/Athens",
    "iso:country":"GR",
    "name:bul_x_preferred":[
        "\u041a\u0430\u0441\u0442\u0430\u043d\u0438\u044f"
    ],
    "name:ceb_x_preferred":[
        "Kastania"
    ],
    "name:ell_x_preferred":[
        "Kast\u00e1nia"
    ],
    "name:ell_x_variant":[
        "\u039a\u03b1\u03c3\u03c4\u03ac\u03bd\u03b9\u03b1"
    ],
    "name:mkd_x_preferred":[
        "\u041a\u0430\u0441\u0442\u0430\u043d\u0438\u0458\u0430"
    ],
    "name:swe_x_preferred":[
        "Kastania"
    ],
    "wof:name":"Kastania",
    "wof:placetype":"locality"
},
  "geometry": {"coordinates":[21.88583,36.9597],"type":"Point"}
}