{
  "type": "Feature",
  "properties": {
    "gn:admin1_code":"ESYE43",
    "gn:admin2_code":"43.0",
    "gn:admin3_code":"9325",
    "gn:asciiname":"Alonaki",
    "gn:country_code":"GR",
    "gn:dem":446,
    "gn:feature_class":"P",
    "gn:feature_code":"PPL",
    "gn:name":"Alon\u00e1ki",
    "gn:population":0,
    "gn:timezone":"Europe/Athens",
    "iso:country":"GR",
    "name:ell_x_preferred":[
        "\u0391\u03bb\u03c9\u03bd\u03ac\u03ba\u03b9"
    ],
    "name:ell_x_variant":[
        "\u0391\u03bb\u03c9\u03bd\u03ac\u03ba\u03b9\u03bf\u03bd"
    ],
    "name:und_x_variant":[
        "Alon\u00e1ki",
        "Alon\u00e1kion"
    ],
    "wof:name":"Alonaki",
    "wof:placetype":"locality"
},
  "geometry": {"coordinates":[24.03353,35.41050999999999],"type":"Point"}
}