{
  "type": "Feature",
  "properties": {
    "gn:country":"GR",
    "gn:fcode":"PPLA3",
    "gn:population":0,
    "iso:country":"GR",
    "name:ell_x_preferred":[
        "\u039c\u03b5\u03c4\u03b1\u03bc\u03cc\u03c1\u03c6\u03c9\u03c3\u03b7 \u03a4\u03c1\u03bf\u03b9\u03b6\u03ae\u03bd\u03bf\u03c2"
    ],
    "name:eng_x_preferred":[
        "Metamorfosi Troizinos"
    ],
    "name:und_x_variant":[
        "Valari\u00f3n"
    ],
    "qs_pg:aaroncc":"GR",
    "qs_pg:gn_country":"GR",
    "qs_pg:gn_fcode":"PPLA3",
    "qs_pg:gn_pop":0,
    "qs_pg:name":"Metam\u00f3rfosi",
    "qs_pg:photos_9r":0,
    "qs_pg:photos_sr":0,
    "qs_pg:pop_sr":0,
    "qs_pg:qs_pg_placetype":"locality",
    "wof:name":"Metam\u00f3rfosi",
    "wof:placetype":"locality",
    "wof:population":75
},
  "geometry": {"coordinates":[23.35,37.53333],"type":"Point"}
}