{
  "type": "Feature",
  "properties": {
    "gn:country":"GR",
    "gn:fcode":"PPL",
    "gn:population":93,
    "iso:country":"GR",
    "name:ell_x_preferred":[
        "\u03a0\u03b5\u03c1\u03b4\u03b9\u03ba\u03cc\u03c1\u03b1\u03c7\u03b7"
    ],
    "name:ell_x_variant":[
        "\u03a0\u03b5\u03c1\u03b4\u03b9\u03ba\u03bf\u03c1\u03c1\u03ac\u03c7\u03b7"
    ],
    "name:eng_x_preferred":[
        "Perdikorrachi"
    ],
    "name:und_x_variant":[
        "Kat\u00eddhi"
    ],
    "qs_pg:aaroncc":"GR",
    "qs_pg:gn_country":"GR",
    "qs_pg:gn_fcode":"PPL",
    "qs_pg:gn_pop":93,
    "qs_pg:name":"Perdikorr\u00e1chi",
    "qs_pg:photos_9r":0,
    "qs_pg:photos_sr":0,
    "qs_pg:pop_sr":1,
    "qs_pg:qs_pg_placetype":"locality",
    "wof:name":"Perdikorr\u00e1chi",
    "wof:placetype":"locality",
    "wof:population":96
},
  "geometry": {"coordinates":[21.76861,39.59194],"type":"Point"}
}