{
  "type": "Feature",
  "properties": {
    "gn:admin1_code":"ESYE21",
    "gn:admin2_code":"17.0",
    "gn:admin3_code":"9081",
    "gn:asciiname":"Agia Paraskevi Melias",
    "gn:country_code":"GR",
    "gn:dem":336,
    "gn:feature_class":"P",
    "gn:feature_code":"PPL",
    "gn:name":"Ag\u00eda Paraskev\u00ed Meli\u00e1s",
    "gn:population":12,
    "gn:timezone":"Europe/Athens",
    "iso:country":"GR",
    "name:ell_x_preferred":[
        "\u0391\u03b3\u03af\u03b1 \u03a0\u03b1\u03c1\u03b1\u03c3\u03ba\u03b5\u03c5\u03ae \u039c\u03b5\u03bb\u03b9\u03ac\u03c2"
    ],
    "name:eng_x_preferred":[
        "Agia Paraskevi Melias"
    ],
    "name:und_x_variant":[
        "Stratige\u00edon"
    ],
    "wof:name":"Agia Paraskevi Melias",
    "wof:placetype":"locality",
    "wof:population":12
},
  "geometry": {"coordinates":[20.85889,39.45389],"type":"Point"}
}