{
  "type": "Feature",
  "properties": {
    "gn:country":"GR",
    "gn:fcode":"PPL",
    "gn:population":331,
    "iso:country":"GR",
    "name:ell_x_preferred":[
        "\u0391\u03c1\u03b3\u03c5\u03c1\u03cc\u03c4\u03bf\u03c0\u03bf\u03c2"
    ],
    "name:und_x_variant":[
        "Aryir\u00f3topos"
    ],
    "qs_pg:aaroncc":"GR",
    "qs_pg:gn_country":"GR",
    "qs_pg:gn_fcode":"PPL",
    "qs_pg:gn_pop":331,
    "qs_pg:name":"Argyr\u00f3topos",
    "qs_pg:photos_9r":0,
    "qs_pg:photos_sr":0,
    "qs_pg:pop_sr":2,
    "qs_pg:qs_pg_placetype":"locality",
    "wof:name":"Argyr\u00f3topos",
    "wof:placetype":"locality",
    "wof:population":331
},
  "geometry": {"coordinates":[20.31417,39.41722],"type":"Point"}
}