{
  "type": "Feature",
  "properties": {
    "gn:admin1_code":"ESYE25",
    "gn:admin2_code":"41.0",
    "gn:admin3_code":"9238",
    "gn:asciiname":"Nymfasia",
    "gn:country_code":"GR",
    "gn:dem":926,
    "gn:feature_class":"P",
    "gn:feature_code":"PPL",
    "gn:name":"Nymfas\u00eda",
    "gn:population":0,
    "gn:timezone":"Europe/Athens",
    "iso:country":"GR",
    "name:ell_x_preferred":[
        "Nymfas\u00eda"
    ],
    "name:ell_x_variant":[
        "\u039d\u03c5\u03bc\u03c6\u03b1\u03c3\u03af\u03b1",
        "\u039d\u03c5\u03bc\u03c6\u03b1\u03c3\u03af\u03b1 \u0391\u03c1\u03ba\u03b1\u03b4\u03af\u03b1\u03c2"
    ],
    "name:ron_x_preferred":[
        "Nymfasia"
    ],
    "name:und_x_variant":[
        "Granitsa",
        "Nimfas\u00eda"
    ],
    "wof:name":"Nymfasia",
    "wof:placetype":"locality"
},
  "geometry": {"coordinates":[22.1845,37.69166],"type":"Point"}
}