{
  "type": "Feature",
  "properties": {
    "gn:country":"GR",
    "gn:fcode":"PPL",
    "gn:population":140,
    "iso:country":"GR",
    "name:ell_x_preferred":[
        "\u03a7\u03b1\u03bc\u03b7\u03bb\u03cc"
    ],
    "name:ell_x_variant":[
        "\u03a7\u03b1\u03bc\u03b7\u03bb\u03cc\u03bd"
    ],
    "name:und_x_variant":[
        "Alch\u00e1k"
    ],
    "qs_pg:aaroncc":"GR",
    "qs_pg:gn_country":"GR",
    "qs_pg:gn_fcode":"PPL",
    "qs_pg:gn_pop":140,
    "qs_pg:name":"Chamil\u00f3n",
    "qs_pg:photos_9r":0,
    "qs_pg:photos_sr":0,
    "qs_pg:pop_sr":1,
    "qs_pg:qs_pg_placetype":"locality",
    "wof:name":"Chamil\u00f3n",
    "wof:placetype":"locality",
    "wof:population":140
},
  "geometry": {"coordinates":[22.47556,41.10111],"type":"Point"}
}