{
  "type": "Feature",
  "properties": {
    "gn:admin1_code":"ESYE25",
    "gn:admin2_code":"41.0",
    "gn:admin3_code":"9237",
    "gn:asciiname":"Louloudia",
    "gn:country_code":"GR",
    "gn:dem":314,
    "gn:feature_class":"P",
    "gn:feature_code":"PPL",
    "gn:name":"Loulo\u00fadia",
    "gn:population":0,
    "gn:timezone":"Europe/Athens",
    "iso:country":"GR",
    "name:ell_x_preferred":[
        "Loulo\u00fadia"
    ],
    "name:ell_x_variant":[
        "\u039b\u03bf\u03c5\u03bb\u03bf\u03cd\u03b4\u03b9\u03b1"
    ],
    "name:und_x_variant":[
        "Tsimo\u00fari Kh\u00e1ni"
    ],
    "wof:name":"Louloudia",
    "wof:placetype":"locality"
},
  "geometry": {"coordinates":[22.61107,37.43261],"type":"Point"}
}