{
  "type": "Feature",
  "properties": {
    "gn:country":"GR",
    "gn:fcode":"PPL",
    "gn:population":1191,
    "iso:country":"GR",
    "name:ell_x_preferred":[
        "\u039c\u03b5\u03b3\u03ac\u03bb\u03b7 \u03a7\u03ce\u03c1\u03b1"
    ],
    "name:eng_x_preferred":[
        "Megali Chora"
    ],
    "name:und_x_variant":[
        "Zap\u00e1ndion"
    ],
    "qs_pg:aaroncc":"GR",
    "qs_pg:gn_country":"GR",
    "qs_pg:gn_fcode":"PPL",
    "qs_pg:gn_pop":1191,
    "qs_pg:name":"Meg\u00e1li Kh\u00f3ra",
    "qs_pg:photos_9r":0,
    "qs_pg:photos_sr":0,
    "qs_pg:pop_sr":3,
    "qs_pg:qs_pg_placetype":"locality",
    "wof:name":"Meg\u00e1li Kh\u00f3ra",
    "wof:placetype":"locality",
    "wof:population":1408
},
  "geometry": {"coordinates":[21.36667,38.63333],"type":"Point"}
}