{
  "type": "Feature",
  "properties": {
    "gn:admin1_code":"ESYE13",
    "gn:admin2_code":"8.0",
    "gn:admin3_code":"9072",
    "gn:asciiname":"Ethniko",
    "gn:country_code":"GR",
    "gn:dem":677,
    "gn:feature_class":"P",
    "gn:feature_code":"PPL",
    "gn:name":"Ethnik\u00f3",
    "gn:population":58,
    "gn:timezone":"Europe/Athens",
    "iso:country":"GR",
    "name:ell_x_preferred":[
        "\u0395\u03b8\u03bd\u03b9\u03ba\u03cc"
    ],
    "name:ell_x_variant":[
        "\u0395\u03b8\u03bd\u03b9\u03ba\u03cc\u03bd"
    ],
    "name:eng_x_preferred":[
        "Ethniko"
    ],
    "name:mkd_x_preferred":[
        "\u041e\u043f\u0441\u0438\u0440\u0435\u043d\u043e"
    ],
    "name:und_x_variant":[
        "Ops\u00edrina",
        "Ethnik\u00f3n",
        "Ethnik\u00f3"
    ],
    "wof:name":"Ethniko",
    "wof:placetype":"locality",
    "wof:population":58
},
  "geometry": {"coordinates":[21.35506,40.87054000000001],"type":"Point"}
}