{
  "type": "Feature",
  "properties": {
    "gn:admin1_code":"ESYE25",
    "gn:admin2_code":"36.0",
    "gn:admin3_code":"9234",
    "gn:asciiname":"Dimosia",
    "gn:country_code":"GR",
    "gn:dem":402,
    "gn:feature_class":"P",
    "gn:feature_code":"PPL",
    "gn:name":"Dimosi\u00e1",
    "gn:population":28,
    "gn:timezone":"Europe/Athens",
    "iso:country":"GR",
    "name:ell_x_preferred":[
        "\u0394\u03b7\u03bc\u03bf\u03c3\u03b9\u03ac"
    ],
    "name:eng_x_preferred":[
        "Dimosia"
    ],
    "wof:name":"Dimosia",
    "wof:placetype":"locality",
    "wof:population":28
},
  "geometry": {"coordinates":[23.10772,37.59333],"type":"Point"}
}