{
  "type": "Feature",
  "properties": {
    "gn:admin1_code":"ESYE24",
    "gn:admin2_code":"30.0",
    "gn:admin3_code":"9156",
    "gn:asciiname":"Politia",
    "gn:country_code":"GR",
    "gn:dem":472,
    "gn:feature_class":"P",
    "gn:feature_code":"PPL",
    "gn:name":"Pol\u00edtia",
    "gn:population":0,
    "gn:timezone":"Europe/Athens",
    "iso:country":"GR",
    "name:ell_x_preferred":[
        "Pol\u00edtia"
    ],
    "name:ell_x_variant":[
        "\u03a0\u03bf\u03bb\u03af\u03c4\u03b9\u03b1"
    ],
    "wof:name":"Politia",
    "wof:placetype":"locality"
},
  "geometry": {"coordinates":[21.49833,39.08281],"type":"Point"}
}