{
  "type": "Feature",
  "properties": {
    "gn:admin1_code":"ESYE42",
    "gn:admin2_code":"49.0",
    "gn:admin3_code":"9288",
    "gn:asciiname":"Galani",
    "gn:country_code":"GR",
    "gn:dem":182,
    "gn:feature_class":"P",
    "gn:feature_code":"PPL",
    "gn:name":"Galan\u00ed",
    "gn:population":59,
    "gn:timezone":"Europe/Athens",
    "iso:country":"GR",
    "name:ell_x_preferred":[
        "\u0393\u03b1\u03bb\u03b1\u03bd\u03ae"
    ],
    "name:eng_x_preferred":[
        "Galani"
    ],
    "wof:name":"Galani",
    "wof:placetype":"locality",
    "wof:population":59
},
  "geometry": {"coordinates":[24.49398,37.19089],"type":"Point"}
}