{
  "type": "Feature",
  "properties": {
    "gn:population":2706,
    "iso:country":"GR",
    "name:ell_x_preferred":[
        "\u0396\u03b7\u03c0\u03ac\u03c1\u03b9\u03bf\u03bd"
    ],
    "name:ell_x_variant":[
        "\u0396\u03b9\u03c0\u03ac\u03c1\u03b9",
        "\u0396\u03b9\u03c0\u03ac\u03c1\u03b9\u03bf\u03bd"
    ],
    "name:unk_x_variant":[
        "Zip\u00e1ri"
    ],
    "qs:a0":"Greece",
    "qs:a1":"*\u039d\u039f\u03a4\u0399\u039f \u0391\u0399\u0393\u0391\u0399\u039f",
    "qs:a1_alt":"NOTIO AIGAIO",
    "qs:a1r":"0",
    "qs:a2_alt":"DVDEKANHSOS",
    "qs:adm0":"Greece",
    "qs:la_lc":"*",
    "qs:level":"locality",
    "qs:loc":"\u0396\u0397\u03a0\u0391\u03a1\u0399\u039f\u039d",
    "qs:loc_alt":"ZHPARION",
    "qs:pop":0,
    "qs:type":"buffered point",
    "wof:name":"\u0396\u0397\u03a0\u0391\u03a1\u0399\u039f\u039d",
    "wof:placetype":"locality",
    "wof:population":2706
},
  "geometry": {"coordinates":[27.207077,36.875889],"type":"Point"}
}