{
  "type": "Feature",
  "properties": {
    "gn:gn_country":"GR",
    "gn:gn_fcode":"PPL",
    "gn:gn_pop":5838,
    "gn:population":5838,
    "iso:country":"GR",
    "name:ara_x_preferred":[
        "\u0623\u0648\u0641\u0631\u064a\u0627\u060c \u0623\u0647\u064a\u0627"
    ],
    "name:ara_x_variant":[
        "\u0623\u0648\u0641\u0631\u064a\u0627"
    ],
    "name:ceb_x_preferred":[
        "Ovri\u00e1"
    ],
    "name:ell_x_preferred":[
        "\u039f\u03b2\u03c1\u03c5\u03ac"
    ],
    "name:ell_x_variant":[
        "\u039f\u03b2\u03c1\u03c5\u03ac \u0391\u03c7\u03b1\u0390\u03b1\u03c2"
    ],
    "name:eng_x_preferred":[
        "Ovrya"
    ],
    "name:jpn_x_preferred":[
        "\u30aa\u30f4\u30ea\u30a2"
    ],
    "name:nld_x_preferred":[
        "Ovrya"
    ],
    "name:nno_x_preferred":[
        "Ovry\u00e1"
    ],
    "name:ron_x_preferred":[
        "Ovrya"
    ],
    "name:swe_x_preferred":[
        "Ovri\u00e1"
    ],
    "name:unk_x_variant":[
        "Ovri\u00e1"
    ],
    "qs_pg:aaroncc":"GR",
    "qs_pg:gn_country":"GR",
    "qs_pg:gn_fcode":"PPL",
    "qs_pg:gn_pop":5838,
    "qs_pg:name":"Ovria",
    "qs_pg:name_adm0":"\u0395\u03bb\u03bb\u03ac\u03b4\u03b1",
    "qs_pg:name_adm1":"Peloponnese Western Greece and the Ionian Islands",
    "qs_pg:photos_9r":0,
    "qs_pg:photos_sr":0,
    "qs_pg:pop_sr":5,
    "qs_pg:qs_pg_placetype":"locality",
    "qs_pg:qs_pg_placetype_gp":"Town",
    "qs_pg:woe_adm0":23424833,
    "woe:adm0_id":23424833,
    "woe:name_adm0":"\u0395\u03bb\u03bb\u03ac\u03b4\u03b1",
    "woe:name_adm1":"Peloponnese Western Greece and the Ionian Islands",
    "woe:placetype":"Town",
    "wof:name":"Ovria",
    "wof:placetype":"locality",
    "wof:population":5838
},
  "geometry": {"coordinates":[21.71667,38.18333],"type":"Point"}
}