{
  "type": "Feature",
  "properties": {
    "gn:gn_country":"GR",
    "gn:gn_fcode":"PPL",
    "gn:gn_pop":953,
    "gn:population":953,
    "iso:country":"GR",
    "name:ell_x_preferred":[
        "\u03a0\u03cc\u03bc\u03c0\u03b9\u03b1"
    ],
    "name:ell_x_variant":[
        "P\u00f3mpia"
    ],
    "name:unk_x_variant":[
        "B\u00f3mbia"
    ],
    "qs_pg:aaroncc":"GR",
    "qs_pg:gn_country":"GR",
    "qs_pg:gn_fcode":"PPL",
    "qs_pg:gn_pop":953,
    "qs_pg:name":"Pombia",
    "qs_pg:name_adm0":"\u0395\u03bb\u03bb\u03ac\u03b4\u03b1",
    "qs_pg:name_adm1":"Crete",
    "qs_pg:photos":10,
    "qs_pg:photos_1k":2,
    "qs_pg:photos_9k":1,
    "qs_pg:photos_9r":1,
    "qs_pg:photos_all":10,
    "qs_pg:photos_sr":1,
    "qs_pg:pop_sr":2,
    "qs_pg:qs_pg_placetype":"locality",
    "qs_pg:qs_pg_placetype_gp":"Town",
    "qs_pg:woe_adm0":23424833,
    "woe:adm0_id":23424833,
    "woe:name_adm0":"\u0395\u03bb\u03bb\u03ac\u03b4\u03b1",
    "woe:name_adm1":"Crete",
    "woe:placetype":"Town",
    "wof:name":"Pombia",
    "wof:placetype":"locality",
    "wof:population":953
},
  "geometry": {"coordinates":[24.87069,35.01021],"type":"Point"}
}