{
  "type": "Feature",
  "properties": {
    "gn:country":"GR",
    "gn:fcode":"PPL",
    "gn:population":953,
    "iso:country":"GR",
    "name:azb_x_preferred":[
        "\u067e\u0648\u0645\u0628\u06cc\u0627"
    ],
    "name:bar_x_preferred":[
        "Pombia"
    ],
    "name:bel_x_preferred":[
        "\u041f\u043e\u043c\u0431\u0456\u044f"
    ],
    "name:bul_x_preferred":[
        "\u041f\u043e\u043c\u0431\u0438\u044f"
    ],
    "name:cat_x_preferred":[
        "Pombia"
    ],
    "name:ceb_x_preferred":[
        "Pombia"
    ],
    "name:deu_x_preferred":[
        "Pombia"
    ],
    "name:ell_x_preferred":[
        "\u03a0\u03cc\u03bc\u03c0\u03b9\u03b1"
    ],
    "name:ell_x_variant":[
        "P\u00f3mpia"
    ],
    "name:epo_x_preferred":[
        "Pombia"
    ],
    "name:eus_x_preferred":[
        "Pombia"
    ],
    "name:fas_x_preferred":[
        "\u067e\u0648\u0645\u0628\u06cc\u0627"
    ],
    "name:fra_x_preferred":[
        "Pombia"
    ],
    "name:hun_x_preferred":[
        "Pombia"
    ],
    "name:hye_x_preferred":[
        "\u054a\u0578\u0574\u0562\u056b\u0561"
    ],
    "name:ind_x_preferred":[
        "Pombia"
    ],
    "name:ita_x_preferred":[
        "Pombia"
    ],
    "name:jpn_x_preferred":[
        "\u30dd\u30f3\u30d3\u30a2"
    ],
    "name:kaz_x_preferred":[
        "\u041f\u043e\u043c\u0431\u0438\u044f"
    ],
    "name:lat_x_preferred":[
        "Plumbia"
    ],
    "name:lmo_x_preferred":[
        "Pumbia"
    ],
    "name:msa_x_preferred":[
        "Pombia"
    ],
    "name:nap_x_preferred":[
        "Pombia"
    ],
    "name:nld_x_preferred":[
        "Pombia"
    ],
    "name:pms_x_preferred":[
        "Pombia"
    ],
    "name:pol_x_preferred":[
        "Pombia"
    ],
    "name:por_x_preferred":[
        "Pombia"
    ],
    "name:ron_x_preferred":[
        "Pombia"
    ],
    "name:rus_x_preferred":[
        "\u041f\u043e\u043c\u0431\u0438\u044f"
    ],
    "name:scn_x_preferred":[
        "Pombia"
    ],
    "name:spa_x_preferred":[
        "Pombia"
    ],
    "name:srp_x_preferred":[
        "\u041f\u043e\u043c\u0431\u0438\u0458\u0430"
    ],
    "name:tgl_x_preferred":[
        "Pombia"
    ],
    "name:ukr_x_preferred":[
        "\u041f\u043e\u043c\u0431\u0456\u044f"
    ],
    "name:und_x_variant":[
        "B\u00f3mbia"
    ],
    "name:uzb_x_preferred":[
        "Pombia"
    ],
    "name:vie_x_preferred":[
        "Pombia"
    ],
    "name:vol_x_preferred":[
        "Pombia"
    ],
    "name:war_x_preferred":[
        "Pombia"
    ],
    "name:zho_x_preferred":[
        "\u84ec\u6bd4\u4e9a"
    ],
    "qs_pg:aaroncc":"GR",
    "qs_pg:gn_country":"GR",
    "qs_pg:gn_fcode":"PPL",
    "qs_pg:gn_pop":953,
    "qs_pg:name":"Pombia",
    "qs_pg:name_adm0":"\u0395\u03bb\u03bb\u03ac\u03b4\u03b1",
    "qs_pg:name_adm1":"Crete",
    "qs_pg:photos":10,
    "qs_pg:photos_1k":2,
    "qs_pg:photos_9k":1,
    "qs_pg:photos_9r":1,
    "qs_pg:photos_all":10,
    "qs_pg:photos_sr":1,
    "qs_pg:pop_sr":2,
    "qs_pg:qs_pg_placetype":"locality",
    "qs_pg:qs_pg_placetype_gp":"Town",
    "qs_pg:woe_adm0":23424833,
    "woe:adm0_id":23424833,
    "woe:name_adm0":"\u0395\u03bb\u03bb\u03ac\u03b4\u03b1",
    "woe:name_adm1":"Crete",
    "woe:placetype":"Town",
    "wof:name":"Pombia",
    "wof:placetype":"locality",
    "wof:population":953
},
  "geometry": {"coordinates":[24.87069,35.01021],"type":"Point"}
}