{
  "type": "Feature",
  "properties": {
    "gn:admin1_code":"ESYE43",
    "gn:admin2_code":"44.0",
    "gn:admin3_code":"9317",
    "gn:asciiname":"Argoulion",
    "gn:cc2":"GR",
    "gn:country_code":"GR",
    "gn:dem":423,
    "gn:feature_class":"P",
    "gn:feature_code":"PPL",
    "gn:name":"Argouli\u00f3n",
    "gn:population":0,
    "gn:timezone":"Europe/Athens",
    "iso:country":"GR",
    "name:und_x_variant":[
        "Argouli\u00f3",
        "Argouli\u00f3n"
    ],
    "wof:name":"Argoulion",
    "wof:placetype":"locality"
},
  "geometry": {"coordinates":[24.75786,35.32759],"type":"Point"}
}