{
  "type": "Feature",
  "properties": {
    "gn:admin1_code":"ESYE14",
    "gn:admin2_code":"24.0",
    "gn:admin3_code":"9111",
    "gn:asciiname":"Kaloyiros",
    "gn:country_code":"GR",
    "gn:dem":125,
    "gn:feature_class":"P",
    "gn:feature_code":"PPL",
    "gn:name":"Kal\u00f3yiros",
    "gn:population":0,
    "gn:timezone":"Europe/Athens",
    "iso:country":"GR",
    "wof:name":"Kaloyiros",
    "wof:placetype":"locality"
},
  "geometry": {"coordinates":[23.68828,39.15625],"type":"Point"}
}