{
  "type": "Feature",
  "properties": {
    "gn:gn_country":"GR",
    "gn:gn_fcode":"PPL",
    "gn:gn_pop":126,
    "gn:population":126,
    "iso:country":"GR",
    "name:ell_x_preferred":[
        "\u039b\u03b5\u03bf\u03bd\u03c4\u03af\u03c4\u03bf"
    ],
    "name:ell_x_variant":[
        "\u039b\u03b5\u03bf\u03bd\u03c4\u03af\u03c4\u03bf\u03bd"
    ],
    "name:unk_x_variant":[
        "Leond\u00edti"
    ],
    "qs_pg:aaroncc":"GR",
    "qs_pg:gn_country":"GR",
    "qs_pg:gn_fcode":"PPL",
    "qs_pg:gn_pop":126,
    "qs_pg:name":"Leont\u00edton",
    "qs_pg:photos_9r":0,
    "qs_pg:photos_sr":0,
    "qs_pg:pop_sr":1,
    "qs_pg:qs_pg_placetype":"locality",
    "wof:name":"Leont\u00edton",
    "wof:placetype":"locality",
    "wof:population":126
},
  "geometry": {"coordinates":[21.53444,39.26389],"type":"Point"}
}