{
  "type": "Feature",
  "properties": {
    "gn:admin1_code":"ESYE43",
    "gn:admin2_code":"43.0",
    "gn:admin3_code":"9323",
    "gn:asciiname":"Sinoikismos Garoufaliana",
    "gn:country_code":"GR",
    "gn:dem":379,
    "gn:feature_class":"P",
    "gn:feature_code":"PPL",
    "gn:name":"Sinoikism\u00f3s Garoufalian\u00e1",
    "gn:population":0,
    "gn:timezone":"Europe/Athens",
    "iso:country":"GR",
    "wof:name":"Sinoikismos Garoufaliana",
    "wof:placetype":"locality"
},
  "geometry": {"coordinates":[23.85,35.43333],"type":"Point"}
}