{
  "type": "Feature",
  "properties": {
    "gn:country":"GR",
    "gn:fcode":"ADM3",
    "gn:population":31644,
    "iso:country":"GR",
    "name:ell_x_preferred":[
        "\u03a0\u03b1\u03b3\u03b3\u03b1\u03af\u03bf\u03c5"
    ],
    "qs_pg:aaroncc":"GR",
    "qs_pg:gn_country":"GR",
    "qs_pg:gn_fcode":"ADM3",
    "qs_pg:gn_pop":31644,
    "qs_pg:name":"Dimos Pangaio",
    "qs_pg:photos_9r":0,
    "qs_pg:photos_sr":0,
    "qs_pg:pop_sr":7,
    "qs_pg:qs_pg_placetype":"localadmin",
    "wof:name":"Dimos Pangaio",
    "wof:placetype":"localadmin",
    "wof:population":31644
},
  "geometry": {"coordinates":[24.13387,40.85151],"type":"Point"}
}