{
  "type": "Feature",
  "properties": {
    "gn:admin1_code":"ESYE12",
    "gn:admin2_code":"15.0",
    "gn:admin3_code":"9058",
    "gn:asciiname":"Rodokipos",
    "gn:country_code":"GR",
    "gn:dem":164,
    "gn:feature_class":"P",
    "gn:feature_code":"PPL",
    "gn:name":"Rod\u00f3kipos",
    "gn:population":61,
    "gn:timezone":"Europe/Athens",
    "iso:country":"GR",
    "name:ell_x_preferred":[
        "\u03a1\u03bf\u03b4\u03cc\u03ba\u03b7\u03c0\u03bf\u03c2"
    ],
    "name:ell_x_variant":[
        "Rod\u00f3kipos"
    ],
    "name:eng_x_preferred":[
        "Rodokipos"
    ],
    "name:und_x_variant":[
        "Senel\u00ed",
        "Radh\u00f3klpos",
        "Radh\u00f3kipos",
        "Rodh\u00f3kipos"
    ],
    "wof:name":"Rodokipos",
    "wof:placetype":"locality",
    "wof:population":61
},
  "geometry": {"coordinates":[23.13196,40.35562],"type":"Point"}
}