{
  "type": "Feature",
  "properties": {
    "gn:admin1_code":"ESYE24",
    "gn:admin2_code":"29.0",
    "gn:admin3_code":"9160",
    "gn:asciiname":"Kompotades",
    "gn:country_code":"GR",
    "gn:dem":43,
    "gn:feature_class":"P",
    "gn:feature_code":"PPL",
    "gn:name":"Kompot\u00e1des",
    "gn:population":539,
    "gn:timezone":"Europe/Athens",
    "iso:country":"GR",
    "name:ell_x_preferred":[
        "\u039a\u03bf\u03bc\u03c0\u03bf\u03c4\u03ac\u03b4\u03b5\u03c2"
    ],
    "name:ell_x_variant":[
        "Kompot\u00e1des"
    ],
    "name:eng_x_preferred":[
        "Kompotades"
    ],
    "name:und_x_variant":[
        "Kombot\u00e1dhes"
    ],
    "wof:name":"Kompotades",
    "wof:placetype":"locality",
    "wof:population":539
},
  "geometry": {"coordinates":[22.34795,38.86756],"type":"Point"}
}