{
  "type": "Feature",
  "properties": {
    "gn:admin1_code":"ESYE21",
    "gn:admin2_code":"18.0",
    "gn:admin3_code":"9077",
    "gn:asciiname":"Bentelenion",
    "gn:cc2":"GR",
    "gn:country_code":"GR",
    "gn:dem":451,
    "gn:feature_class":"P",
    "gn:feature_code":"PPL",
    "gn:name":"Bentel\u00e9nion",
    "gn:population":0,
    "gn:timezone":"Europe/Athens",
    "iso:country":"GR",
    "name:und_x_variant":[
        "Bendel\u00e9nion"
    ],
    "wof:name":"Bentelenion",
    "wof:placetype":"locality"
},
  "geometry": {"coordinates":[20.36083,39.49694],"type":"Point"}
}