{
  "type": "Feature",
  "properties": {
    "gn:country":"GR",
    "gn:fcode":"PPL",
    "gn:population":23,
    "iso:country":"GR",
    "name:ell_x_preferred":[
        "\u0393\u03b5\u03c1\u03b1\u03ba\u03ac\u03c1\u03b9"
    ],
    "name:ell_x_variant":[
        "\u0393\u03b5\u03c1\u03b1\u03ba\u03ac\u03c1\u03b9\u03bf\u03bd",
        "\u0393\u03b9\u03b1\u03c1\u03b1\u03ba\u03ac\u03c1\u03b9"
    ],
    "name:eng_x_preferred":[
        "Giarakari"
    ],
    "name:und_x_variant":[
        "Yer\u00e1kion"
    ],
    "qs_pg:aaroncc":"GR",
    "qs_pg:gn_country":"GR",
    "qs_pg:gn_fcode":"PPL",
    "qs_pg:gn_pop":23,
    "qs_pg:name":"Giarak\u00e1rion",
    "qs_pg:photos_9r":0,
    "qs_pg:photos_sr":0,
    "qs_pg:pop_sr":1,
    "qs_pg:qs_pg_placetype":"locality",
    "wof:name":"Giarak\u00e1rion",
    "wof:placetype":"locality",
    "wof:population":10
},
  "geometry": {"coordinates":[21.105,39.74694],"type":"Point"}
}