{
  "type": "Feature",
  "properties": {
    "gn:admin1_code":"ESYE43",
    "gn:admin2_code":"46.0",
    "gn:admin3_code":"9312",
    "gn:asciiname":"Magoulas",
    "gn:cc2":"GR",
    "gn:country_code":"GR",
    "gn:dem":871,
    "gn:feature_class":"P",
    "gn:feature_code":"PPL",
    "gn:name":"Magoul\u00e1s",
    "gn:population":0,
    "gn:timezone":"Europe/Athens",
    "iso:country":"GR",
    "name:und_x_variant":[
        "Magoul\u00e1",
        "Magoul\u00e1s"
    ],
    "wof:name":"Magoulas",
    "wof:placetype":"locality"
},
  "geometry": {"coordinates":[25.4579,35.15978],"type":"Point"}
}