{
  "type": "Feature",
  "properties": {
    "gn:admin1_code":"ESYE43",
    "gn:admin2_code":"45.0",
    "gn:admin3_code":"9303",
    "gn:asciiname":"Kefalovrisi",
    "gn:country_code":"GR",
    "gn:dem":757,
    "gn:feature_class":"P",
    "gn:feature_code":"PPL",
    "gn:name":"Kefalovr\u00edsi",
    "gn:population":0,
    "gn:timezone":"Europe/Athens",
    "iso:country":"GR",
    "wof:name":"Kefalovrisi",
    "wof:placetype":"locality"
},
  "geometry": {"coordinates":[25.45532,35.04405],"type":"Point"}
}