{
  "type": "Feature",
  "properties": {
    "gn:admin1_code":"ESYE42",
    "gn:admin2_code":"49.0",
    "gn:admin3_code":"9300",
    "gn:asciiname":"Ano Manna",
    "gn:country_code":"GR",
    "gn:dem":52,
    "gn:feature_class":"P",
    "gn:feature_code":"PPL",
    "gn:name":"\u00c1no M\u00e1nna",
    "gn:population":0,
    "gn:timezone":"Europe/Athens",
    "iso:country":"GR",
    "name:ell_x_preferred":[
        "\u00c1no M\u00e1nna"
    ],
    "name:ell_x_variant":[
        "\u0386\u03bd\u03c9 \u039c\u03ac\u03bd\u03bd\u03b1"
    ],
    "name:und_x_variant":[
        "Fir\u00f3kambos"
    ],
    "wof:name":"Ano Manna",
    "wof:placetype":"locality"
},
  "geometry": {"coordinates":[24.93711,37.41658],"type":"Point"}
}