{
  "type": "Feature",
  "properties": {
    "gn:country":"GR",
    "gn:fcode":"PPL",
    "gn:population":672,
    "iso:country":"GR",
    "name:ceb_x_preferred":[
        "Peroul\u00e1des"
    ],
    "name:ell_x_preferred":[
        "\u03a0\u03b5\u03c1\u03bf\u03c5\u03bb\u03ac\u03b4\u03b5\u03c2"
    ],
    "name:ell_x_variant":[
        "\u03a0\u03b5\u03c1\u03bf\u03c5\u03bb\u03ac\u03b4\u03b5\u03c2 \u039a\u03ad\u03c1\u03ba\u03c5\u03c1\u03b1\u03c2"
    ],
    "name:eng_x_preferred":[
        "Peroulades"
    ],
    "name:nld_x_preferred":[
        "Peroulades"
    ],
    "name:swe_x_preferred":[
        "Peroul\u00e1des"
    ],
    "name:und_x_variant":[
        "Peroul\u00e1dhes"
    ],
    "qs_pg:aaroncc":"GR",
    "qs_pg:gn_country":"GR",
    "qs_pg:gn_fcode":"PPL",
    "qs_pg:gn_pop":672,
    "qs_pg:name":"Perouladhes",
    "qs_pg:name_adm0":"\u0395\u03bb\u03bb\u03ac\u03b4\u03b1",
    "qs_pg:name_adm1":"Peloponnese Western Greece and the Ionian Islands",
    "qs_pg:photos":200,
    "qs_pg:photos_1k":41,
    "qs_pg:photos_9k":1,
    "qs_pg:photos_9r":4,
    "qs_pg:photos_all":200,
    "qs_pg:photos_sr":4,
    "qs_pg:pop_sr":2,
    "qs_pg:qs_pg_placetype":"locality",
    "qs_pg:qs_pg_placetype_gp":"Town",
    "qs_pg:woe_adm0":23424833,
    "woe:adm0_id":23424833,
    "woe:name_adm0":"\u0395\u03bb\u03bb\u03ac\u03b4\u03b1",
    "woe:name_adm1":"Peloponnese Western Greece and the Ionian Islands",
    "woe:placetype":"Town",
    "wof:name":"Perouladhes",
    "wof:placetype":"locality",
    "wof:population":673
},
  "geometry": {"coordinates":[19.67167,39.78667],"type":"Point"}
}