{
  "type": "Feature",
  "properties": {
    "gn:admin1_code":"ESYE12",
    "gn:admin2_code":"13.0",
    "gn:admin3_code":"9034",
    "gn:asciiname":"Toumpa",
    "gn:country_code":"GR",
    "gn:dem":75,
    "gn:feature_class":"P",
    "gn:feature_code":"PPL",
    "gn:name":"To\u00fampa",
    "gn:population":0,
    "gn:timezone":"Europe/Athens",
    "iso:country":"GR",
    "name:ell_x_preferred":[
        "To\u00fampa"
    ],
    "name:ell_x_variant":[
        "\u03a4\u03bf\u03cd\u03bc\u03c0\u03b1",
        "To\u00famba"
    ],
    "wof:name":"Toumpa",
    "wof:placetype":"locality"
},
  "geometry": {"coordinates":[23.08333,40.68333],"type":"Point"}
}