{
  "type": "Feature",
  "properties": {
    "gn:admin1_code":"ESYE13",
    "gn:admin2_code":"11.0",
    "gn:admin3_code":"9066",
    "gn:asciiname":"Dilofo",
    "gn:country_code":"GR",
    "gn:dem":953,
    "gn:feature_class":"P",
    "gn:feature_code":"PPL",
    "gn:name":"D\u00edlofo",
    "gn:population":0,
    "gn:timezone":"Europe/Athens",
    "iso:country":"GR",
    "name:bul_x_preferred":[
        "\u0414\u0438\u043b\u043e\u0444\u043e"
    ],
    "name:ell_x_preferred":[
        "D\u00edlofo"
    ],
    "name:ell_x_variant":[
        "\u0394\u03af\u03bb\u03bf\u03c6\u03bf",
        "D\u00edlofon",
        "\u0394\u03af\u03bb\u03bf\u03c6\u03bf\u03bd"
    ],
    "name:und_x_variant":[
        "Vrakhoplayi\u00e1",
        "Lib\u00f3khovon",
        "Dh\u00edlofon"
    ],
    "wof:name":"Dilofo",
    "wof:placetype":"locality"
},
  "geometry": {"coordinates":[21.16481,40.17032],"type":"Point"}
}