{
  "type": "Feature",
  "properties": {
    "gn:admin1_code":"ESYE25",
    "gn:admin2_code":"40.0",
    "gn:admin3_code":"9254",
    "gn:asciiname":"Artemisia",
    "gn:country_code":"GR",
    "gn:dem":704,
    "gn:feature_class":"P",
    "gn:feature_code":"PPL",
    "gn:name":"Artemis\u00eda",
    "gn:population":0,
    "gn:timezone":"Europe/Athens",
    "iso:country":"GR",
    "name:ell_x_preferred":[
        "\u0391\u03c1\u03c4\u03b5\u03bc\u03b9\u03c3\u03af\u03b1"
    ],
    "name:und_x_variant":[
        "Stern\u00edtsa",
        "Tsern\u00edtsa",
        "Artemis\u00eda"
    ],
    "wof:name":"Artemisia",
    "wof:placetype":"locality"
},
  "geometry": {"coordinates":[22.22996,37.09932],"type":"Point"}
}