{
  "type": "Feature",
  "properties": {
    "gn:admin1_code":"ESYE25",
    "gn:admin2_code":"41.0",
    "gn:admin3_code":"9238",
    "gn:asciiname":"Elati",
    "gn:country_code":"GR",
    "gn:dem":1195,
    "gn:feature_class":"P",
    "gn:feature_code":"PPL",
    "gn:name":"El\u00e1ti",
    "gn:population":0,
    "gn:timezone":"Europe/Athens",
    "iso:country":"GR",
    "name:ceb_x_preferred":[
        "Elati"
    ],
    "name:deu_x_preferred":[
        "Elati"
    ],
    "name:ell_x_preferred":[
        "El\u00e1ti"
    ],
    "name:ell_x_variant":[
        "\u0395\u03bb\u03ac\u03c4\u03b7"
    ],
    "name:spa_x_preferred":[
        "Elati"
    ],
    "name:swe_x_preferred":[
        "Elati"
    ],
    "name:und_x_variant":[
        "Gortseniko\u00fa",
        "Gorzen\u00edkou",
        "Dh\u00edrrevma"
    ],
    "wof:name":"Elati",
    "wof:placetype":"locality"
},
  "geometry": {"coordinates":[22.1487,37.62674000000001],"type":"Point"}
}