{
  "type": "Feature",
  "properties": {
    "gn:admin1_code":"ESYE25",
    "gn:admin2_code":"40.0",
    "gn:admin3_code":"9257",
    "gn:asciiname":"Velanidhia",
    "gn:cc2":"GR",
    "gn:country_code":"GR",
    "gn:dem":353,
    "gn:feature_class":"P",
    "gn:feature_code":"PPL",
    "gn:name":"Velanidhi\u00e1",
    "gn:population":0,
    "gn:timezone":"Europe/Athens",
    "iso:country":"GR",
    "name:und_x_variant":[
        "Fourtz\u00ed",
        "Velanidhi\u00e9s",
        "Velanidhi\u00e1"
    ],
    "wof:name":"Velanidhia",
    "wof:placetype":"locality"
},
  "geometry": {"coordinates":[21.79299,36.99052],"type":"Point"}
}