{
  "type": "Feature",
  "properties": {
    "gn:country":"GR",
    "gn:fcode":"PPL",
    "gn:population":20,
    "iso:country":"GR",
    "name:ell_x_preferred":[
        "Palai\u00f3dentros"
    ],
    "name:ell_x_variant":[
        "\u03a0\u03b1\u03bb\u03b1\u03b9\u03cc\u03b4\u03b5\u03bd\u03c4\u03c1\u03bf\u03c2"
    ],
    "qs_pg:aaroncc":"GR",
    "qs_pg:gn_country":"GR",
    "qs_pg:gn_fcode":"PPL",
    "qs_pg:gn_pop":20,
    "qs_pg:name":"Palai\u00f3dendros",
    "qs_pg:photos_9r":0,
    "qs_pg:photos_sr":0,
    "qs_pg:pop_sr":1,
    "qs_pg:qs_pg_placetype":"locality",
    "wof:name":"Palai\u00f3dendros",
    "wof:placetype":"locality",
    "wof:population":20
},
  "geometry": {"coordinates":[21.43111,39.30806],"type":"Point"}
}