{
  "type": "Feature",
  "properties": {
    "gn:admin1_code":"ESYE25",
    "gn:admin2_code":"40.0",
    "gn:admin3_code":"9258",
    "gn:asciiname":"Christianou",
    "gn:country_code":"GR",
    "gn:dem":408,
    "gn:feature_class":"P",
    "gn:feature_code":"PPL",
    "gn:name":"Christiano\u00fa",
    "gn:population":0,
    "gn:timezone":"Europe/Athens",
    "iso:country":"GR",
    "name:ell_x_preferred":[
        "Christiano\u00fa"
    ],
    "name:ell_x_variant":[
        "\u03a7\u03c1\u03b9\u03c3\u03c4\u03b9\u03b1\u03bd\u03bf\u03cd"
    ],
    "name:und_x_variant":[
        "Khristi\u00e1noi",
        "Khristian\u00f3n"
    ],
    "wof:name":"Christianou",
    "wof:placetype":"locality"
},
  "geometry": {"coordinates":[21.68497,37.14087],"type":"Point"}
}