{
  "type": "Feature",
  "properties": {
    "gn:admin1_code":"ESYE12",
    "gn:admin2_code":"5.0",
    "gn:admin3_code":"9053",
    "gn:asciiname":"Myrkinos",
    "gn:country_code":"GR",
    "gn:dem":17,
    "gn:feature_class":"P",
    "gn:feature_code":"PPL",
    "gn:name":"M\u00fdrkinos",
    "gn:population":199,
    "gn:timezone":"Europe/Athens",
    "iso:country":"GR",
    "name:bul_x_preferred":[
        "\u041c\u0438\u0440\u043a\u0438\u043d\u043e\u0441"
    ],
    "name:ell_x_historical":[
        "\u0394\u03bf\u03be\u03cc\u03bc\u03c0\u03bf\u03c5\u03c2"
    ],
    "name:ell_x_preferred":[
        "\u039c\u03cd\u03c1\u03ba\u03b9\u03bd\u03bf\u03c2"
    ],
    "name:ell_x_variant":[
        "\u0394\u03bf\u03be\u03cc\u03bc\u03c0\u03bf\u03c2",
        "\u0394\u03bf\u03be\u03cc\u03bc\u03c0\u03bf\u03c5\u03c2"
    ],
    "name:eng_x_preferred":[
        "Myrkinos"
    ],
    "name:pol_x_preferred":[
        "Myrkinos"
    ],
    "name:spa_x_preferred":[
        "Mircino"
    ],
    "name:und_x_variant":[
        "M\u00fdrkinos",
        "M\u00edrkinos"
    ],
    "wof:name":"Myrkinos",
    "wof:placetype":"locality",
    "wof:population":199
},
  "geometry": {"coordinates":[23.81998,40.90129],"type":"Point"}
}