{
  "type": "Feature",
  "properties": {
    "gn:admin1_code":"ESYE42",
    "gn:admin2_code":"47.0",
    "gn:admin3_code":"9285",
    "gn:asciiname":"Avlaki",
    "gn:country_code":"GR",
    "gn:dem":11,
    "gn:feature_class":"P",
    "gn:feature_code":"PPL",
    "gn:name":"Avl\u00e1ki",
    "gn:population":0,
    "gn:timezone":"Europe/Athens",
    "iso:country":"GR",
    "name:ell_x_preferred":[
        "Avl\u00e1ki"
    ],
    "name:ell_x_variant":[
        "\u0391\u03c5\u03bb\u03ac\u03ba\u03b9",
        "Avl\u00e1kion",
        "\u0391\u03c5\u03bb\u03ac\u03ba\u03b9\u03bf\u03bd"
    ],
    "wof:name":"Avlaki",
    "wof:placetype":"locality"
},
  "geometry": {"coordinates":[27.17587,36.55843],"type":"Point"}
}