{
  "type": "Feature",
  "properties": {
    "gn:admin1_code":"ESYE23",
    "gn:admin2_code":"38.0",
    "gn:admin3_code":"9133.0",
    "gn:asciiname":"Kato Drymos",
    "gn:country_code":"GR",
    "gn:dem":567,
    "gn:feature_class":"P",
    "gn:feature_code":"PPL",
    "gn:name":"Kato Drym\u00f3s",
    "gn:population":0,
    "gn:timezone":"Europe/Athens",
    "iso:country":"GR",
    "name:ell_x_preferred":[
        "\u039a\u03ac\u03c4\u03c9 \u0394\u03c1\u03c5\u03bc\u03cc\u03c2"
    ],
    "name:eng_x_preferred":[
        "Kato Drim\u00f3s"
    ],
    "name:eng_x_variant":[
        "Kato Drimos"
    ],
    "wof:name":"Kato Drymos",
    "wof:placetype":"locality"
},
  "geometry": {"coordinates":[22.07411,37.88885],"type":"Point"}
}