{
  "type": "Feature",
  "properties": {
    "gn:admin1_code":"ESYE25",
    "gn:admin2_code":"42.0",
    "gn:admin3_code":"9248",
    "gn:asciiname":"Aofaloti",
    "gn:cc2":"GR",
    "gn:country_code":"GR",
    "gn:dem":171,
    "gn:feature_class":"P",
    "gn:feature_code":"PPL",
    "gn:name":"Aofalot\u00ed",
    "gn:population":0,
    "gn:timezone":"Europe/Athens",
    "iso:country":"GR",
    "name:und_x_variant":[
        "Afalot\u00ed",
        "Aofalot\u00ed"
    ],
    "wof:name":"Aofaloti",
    "wof:placetype":"locality"
},
  "geometry": {"coordinates":[22.40571,36.57608],"type":"Point"}
}