{
  "type": "Feature",
  "properties": {
    "iso:country":"GR",
    "name:arm_x_preferred":[
        "\u0531\u0580\u0565\u0578\u057a\u0578\u056c\u056b\u057d"
    ],
    "name:bul_x_preferred":[
        "\u0410\u0440\u0435\u043e\u043f\u043e\u043b\u0438"
    ],
    "name:dut_x_preferred":[
        "Areopoli"
    ],
    "name:eng_x_preferred":[
        "Areopoli"
    ],
    "name:est_x_preferred":[
        "Are\u00f3poli"
    ],
    "name:fin_x_preferred":[
        "Are\u00f3poli"
    ],
    "name:fre_x_preferred":[
        "Are\u00f3poli"
    ],
    "name:ger_x_preferred":[
        "Areopoli"
    ],
    "name:gre_x_preferred":[
        "\u0391\u03c1\u03b5\u03cc\u03c0\u03bf\u03bb\u03b7 \u039b\u03b1\u03ba\u03c9\u03bd\u03af\u03b1\u03c2"
    ],
    "name:gsw_x_preferred":[
        "Areopoli"
    ],
    "name:heb_x_preferred":[
        "\u05d0\u05e8\u05d0\u05d5\u05e4\u05d5\u05dc\u05d9"
    ],
    "name:lat_x_preferred":[
        "Areopolis"
    ],
    "name:nno_x_preferred":[
        "Are\u00f3poli"
    ],
    "name:rum_x_preferred":[
        "Areopoli"
    ],
    "name:rus_x_preferred":[
        "\u0410\u0440\u0435\u043e\u043f\u043e\u043b\u0438\u0441"
    ],
    "name:swe_x_preferred":[
        "Are\u00f3poli"
    ],
    "name:ukr_x_preferred":[
        "\u0410\u0440\u0435\u043e\u043f\u043e\u043b\u0456"
    ],
    "name:wel_x_preferred":[
        "Areopoli"
    ],
    "qs_pg:aaroncc":"GR",
    "qs_pg:name":"Areopolis",
    "qs_pg:name_adm0":"\u0395\u03bb\u03bb\u03ac\u03b4\u03b1",
    "qs_pg:name_adm1":"Peloponnese Western Greece and the Ionian Islands",
    "qs_pg:photos":77,
    "qs_pg:photos_1k":16,
    "qs_pg:photos_9k":1,
    "qs_pg:photos_9r":3,
    "qs_pg:photos_all":77,
    "qs_pg:photos_sr":3,
    "qs_pg:pop_sr":0,
    "qs_pg:qs_pg_placetype":"locality",
    "qs_pg:qs_pg_placetype_gp":"Town",
    "qs_pg:woe_adm0":23424833,
    "woe:adm0_id":23424833,
    "woe:name_adm0":"\u0395\u03bb\u03bb\u03ac\u03b4\u03b1",
    "woe:name_adm1":"Peloponnese Western Greece and the Ionian Islands",
    "woe:placetype":"Town",
    "wof:name":"Areopolis",
    "wof:placetype":"locality"
},
  "geometry": {"coordinates":[22.377522,36.679969],"type":"Point"}
}