{
  "type": "Feature",
  "properties": {
    "gn:admin1_code":"ESYE43",
    "gn:admin2_code":"46.0",
    "gn:admin3_code":"9313",
    "gn:asciiname":"Krionerion",
    "gn:cc2":"GR",
    "gn:country_code":"GR",
    "gn:dem":649,
    "gn:feature_class":"P",
    "gn:feature_code":"PPL",
    "gn:name":"Krion\u00e9rion",
    "gn:population":0,
    "gn:timezone":"Europe/Athens",
    "iso:country":"GR",
    "name:und_x_variant":[
        "Misirio\u00fa",
        "Misiryio\u00fa",
        "Krion\u00e9rion"
    ],
    "wof:name":"Krionerion",
    "wof:placetype":"locality"
},
  "geometry": {"coordinates":[26.16338,35.16076],"type":"Point"}
}