{
  "type": "Feature",
  "properties": {
    "gn:admin1_code":"ESYE21",
    "gn:admin2_code":"19.0",
    "gn:admin3_code":"9088",
    "gn:asciiname":"Kato Chalasmata",
    "gn:cc2":"GR",
    "gn:country_code":"GR",
    "gn:dem":225,
    "gn:feature_class":"P",
    "gn:feature_code":"PPL",
    "gn:name":"K\u00e1to Chal\u00e1smata",
    "gn:population":0,
    "gn:timezone":"Europe/Athens",
    "iso:country":"GR",
    "name:und_x_variant":[
        "K\u00e1to Khal\u00e1smata"
    ],
    "wof:name":"Kato Chalasmata",
    "wof:placetype":"locality"
},
  "geometry": {"coordinates":[20.78056,39.33056],"type":"Point"}
}