{
  "type": "Feature",
  "properties": {
    "gn:admin1_code":"ESYE13",
    "gn:admin2_code":"10.0",
    "gn:admin3_code":"9061",
    "gn:asciiname":"Kyparissi",
    "gn:country_code":"GR",
    "gn:dem":939,
    "gn:feature_class":"P",
    "gn:feature_code":"PPL",
    "gn:name":"Kypar\u00edssi",
    "gn:population":0,
    "gn:timezone":"Europe/Athens",
    "iso:country":"GR",
    "name:ell_x_preferred":[
        "Kypar\u00edssi"
    ],
    "name:ell_x_variant":[
        "\u039a\u03c5\u03c0\u03b1\u03c1\u03af\u03c3\u03c3\u03b9",
        "Kypar\u00edssion",
        "\u039a\u03c5\u03c0\u03b1\u03c1\u03af\u03c3\u03c3\u03b9\u03bf\u03bd"
    ],
    "name:und_x_variant":[
        "Kipar\u00edssi",
        "Kipar\u00edssion"
    ],
    "wof:name":"Kyparissi",
    "wof:placetype":"locality"
},
  "geometry": {"coordinates":[21.22758,40.13723],"type":"Point"}
}