{
  "type": "Feature",
  "properties": {
    "gn:admin1_code":"ESYE25",
    "gn:admin2_code":"40.0",
    "gn:admin3_code":"9258",
    "gn:asciiname":"Sellas",
    "gn:country_code":"GR",
    "gn:dem":508,
    "gn:feature_class":"P",
    "gn:feature_code":"PPL",
    "gn:name":"Sell\u00e1s",
    "gn:population":0,
    "gn:timezone":"Europe/Athens",
    "iso:country":"GR",
    "name:ell_x_preferred":[
        "\u03a3\u03b5\u03bb\u03bb\u03ac\u03c2"
    ],
    "name:und_x_variant":[
        "S\u00e9la",
        "Sell\u00e1s"
    ],
    "wof:name":"Sellas",
    "wof:placetype":"locality"
},
  "geometry": {"coordinates":[21.78526,37.2085],"type":"Point"}
}