{
  "type": "Feature",
  "properties": {
    "gn:admin1_code":"ESYE13",
    "gn:admin2_code":"11.0",
    "gn:admin3_code":"9066",
    "gn:asciiname":"Kaloneri",
    "gn:country_code":"GR",
    "gn:dem":625,
    "gn:feature_class":"P",
    "gn:feature_code":"PPL",
    "gn:name":"Kalon\u00e9ri",
    "gn:population":0,
    "gn:timezone":"Europe/Athens",
    "iso:country":"GR",
    "name:bul_x_preferred":[
        "\u041a\u0430\u043b\u043e\u043d\u0435\u0440\u0438"
    ],
    "name:ell_x_preferred":[
        "\u039a\u03b1\u03bb\u03bf\u03bd\u03ad\u03c1\u03b9"
    ],
    "name:ell_x_variant":[
        "\u039a\u03b1\u03bb\u03bf\u03bd\u03ad\u03c1\u03b9\u03bf\u03bd",
        "\u039a\u03b1\u03bb\u03bf\u03bd\u03ad\u03c1\u03b9 \u039a\u03bf\u03b6\u03ac\u03bd\u03b7\u03c2"
    ],
    "name:mkd_x_preferred":[
        "\u0412\u0440\u0430\u043d\u0438\u0448\u0442\u0430"
    ],
    "name:nno_x_preferred":[
        "Kalon\u00e9ri"
    ],
    "name:und_x_variant":[
        "Vrong\u00edsta",
        "Kalon\u00e9ri",
        "Kalon\u00e9rion"
    ],
    "wof:name":"Kaloneri",
    "wof:placetype":"locality"
},
  "geometry": {"coordinates":[21.49144,40.28932],"type":"Point"}
}