{
  "type": "Feature",
  "properties": {
    "gn:admin1_code":"ESYE13",
    "gn:admin2_code":"11.0",
    "gn:admin3_code":"9066",
    "gn:asciiname":"Kaloneri",
    "gn:country_code":"GR",
    "gn:dem":625,
    "gn:feature_class":"P",
    "gn:feature_code":"PPL",
    "gn:name":"Kalon\u00e9ri",
    "gn:population":0,
    "gn:timezone":"Europe/Athens",
    "iso:country":"GR",
    "name:ell_x_preferred":[
        "\u039a\u03b1\u03bb\u03bf\u03bd\u03ad\u03c1\u03b9"
    ],
    "name:ell_x_variant":[
        "\u039a\u03b1\u03bb\u03bf\u03bd\u03ad\u03c1\u03b9\u03bf\u03bd"
    ],
    "name:und_x_variant":[
        "Vrong\u00edsta",
        "Kalon\u00e9ri",
        "Kalon\u00e9rion"
    ],
    "wof:name":"Kaloneri",
    "wof:placetype":"locality"
},
  "geometry": {"coordinates":[21.49144,40.28932],"type":"Point"}
}