{
  "type": "Feature",
  "properties": {
    "gn:admin1_code":"ESYE12",
    "gn:admin2_code":"15.0",
    "gn:admin3_code":"9059",
    "gn:asciiname":"Agia Anastasia",
    "gn:country_code":"GR",
    "gn:dem":130,
    "gn:feature_class":"P",
    "gn:feature_code":"PPL",
    "gn:name":"Ag\u00eda Anastas\u00eda",
    "gn:population":118,
    "gn:timezone":"Europe/Athens",
    "iso:country":"GR",
    "name:ell_x_preferred":[
        "\u0391\u03b3\u03af\u03b1 \u0391\u03bd\u03b1\u03c3\u03c4\u03b1\u03c3\u03af\u03b1"
    ],
    "name:eng_x_preferred":[
        "Agia Anastasia"
    ],
    "wof:name":"Agia Anastasia",
    "wof:placetype":"locality",
    "wof:population":118
},
  "geometry": {"coordinates":[23.18656,40.47581],"type":"Point"}
}