{
  "type": "Feature",
  "properties": {
    "gn:admin1_code":"ESYE42",
    "gn:admin2_code":"49.0",
    "gn:admin3_code":"9300",
    "gn:asciiname":"Kouroupi",
    "gn:country_code":"GR",
    "gn:dem":62,
    "gn:feature_class":"P",
    "gn:feature_code":"PPL",
    "gn:name":"Kouro\u00fapi",
    "gn:population":0,
    "gn:timezone":"Europe/Athens",
    "iso:country":"GR",
    "wof:name":"Kouroupi",
    "wof:placetype":"locality"
},
  "geometry": {"coordinates":[24.95,37.41667],"type":"Point"}
}