{
  "type": "Feature",
  "properties": {
    "gn:admin1_code":"ESYE23",
    "gn:admin2_code":"38.0",
    "gn:admin3_code":"9130",
    "gn:asciiname":"Oikonomaiika",
    "gn:country_code":"GR",
    "gn:dem":208,
    "gn:feature_class":"P",
    "gn:feature_code":"PPL",
    "gn:name":"Oikonoma\u00edika",
    "gn:population":0,
    "gn:timezone":"Europe/Athens",
    "iso:country":"GR",
    "wof:name":"Oikonomaiika",
    "wof:placetype":"locality"
},
  "geometry": {"coordinates":[22.36583,38.13346],"type":"Point"}
}