{
  "type": "Feature",
  "properties": {
    "gn:admin1_code":"ESYE13",
    "gn:admin2_code":"11.0",
    "gn:admin3_code":"9066",
    "gn:asciiname":"Chrysavgi",
    "gn:country_code":"GR",
    "gn:dem":822,
    "gn:feature_class":"P",
    "gn:feature_code":"PPL",
    "gn:name":"Chrysavg\u00ed",
    "gn:population":0,
    "gn:timezone":"Europe/Athens",
    "iso:country":"GR",
    "name:ell_x_preferred":[
        "Chrysavg\u00ed"
    ],
    "name:ell_x_variant":[
        "\u03a7\u03c1\u03c5\u03c3\u03b1\u03c5\u03b3\u03ae"
    ],
    "name:und_x_variant":[
        "Khrisavy\u00ed"
    ],
    "wof:name":"Chrysavgi",
    "wof:placetype":"locality"
},
  "geometry": {"coordinates":[21.22117,40.16855],"type":"Point"}
}