{
  "type": "Feature",
  "properties": {
    "gn:admin1_code":"ESYE42",
    "gn:admin2_code":"49.0",
    "gn:admin3_code":"9290.0",
    "gn:asciiname":"Skalado",
    "gn:country_code":"GR",
    "gn:dem":113,
    "gn:feature_class":"P",
    "gn:feature_code":"PPLL",
    "gn:name":"Skal\u00e1do",
    "gn:population":0,
    "gn:timezone":"Europe/Athens",
    "iso:country":"GR",
    "name:ell_x_preferred":[
        "\u03a3\u03ba\u03b1\u03bb\u03ac\u03b4\u03bf"
    ],
    "name:eng_x_preferred":[
        "Skalado"
    ],
    "wof:name":"Skalado",
    "wof:placetype":"locality"
},
  "geometry": {"coordinates":[25.34218,37.43053],"type":"Point"}
}