{
  "type": "Feature",
  "properties": {
    "gn:gn_country":"GR",
    "gn:gn_fcode":"PPL",
    "gn:gn_pop":222,
    "gn:population":222,
    "iso:country":"GR",
    "name:ell_x_preferred":[
        "\u03a3\u03ba\u03ac\u03bd\u03b4\u03b1\u03bb\u03bf"
    ],
    "name:ell_x_variant":[
        "\u03a3\u03ba\u03ac\u03bd\u03b4\u03b1\u03bb\u03bf\u03bd"
    ],
    "name:unk_x_variant":[
        "Sk\u00e1ndhalon"
    ],
    "qs_pg:aaroncc":"GR",
    "qs_pg:gn_country":"GR",
    "qs_pg:gn_fcode":"PPL",
    "qs_pg:gn_pop":222,
    "qs_pg:name":"Skandhalon",
    "qs_pg:name_adm0":"\u0395\u03bb\u03bb\u03ac\u03b4\u03b1",
    "qs_pg:name_adm1":"Epirus and Western Macedonia",
    "qs_pg:photos_9r":0,
    "qs_pg:photos_sr":0,
    "qs_pg:pop_sr":2,
    "qs_pg:qs_pg_placetype":"locality",
    "qs_pg:qs_pg_placetype_gp":"Town",
    "qs_pg:woe_adm0":23424833,
    "woe:adm0_id":23424833,
    "woe:name_adm0":"\u0395\u03bb\u03bb\u03ac\u03b4\u03b1",
    "woe:name_adm1":"Epirus and Western Macedonia",
    "woe:placetype":"Town",
    "wof:name":"Skandhalon",
    "wof:placetype":"locality",
    "wof:population":222
},
  "geometry": {"coordinates":[20.53639,39.36333],"type":"Point"}
}