{
  "type": "Feature",
  "properties": {
    "gn:admin1_code":"ESYE42",
    "gn:admin2_code":"49.0",
    "gn:admin3_code":"9268",
    "gn:asciiname":"Aipatia",
    "gn:country_code":"GR",
    "gn:dem":84,
    "gn:feature_class":"P",
    "gn:feature_code":"PPL",
    "gn:name":"A\u00efp\u00e1tia",
    "gn:population":0,
    "gn:timezone":"Europe/Athens",
    "iso:country":"GR",
    "name:ell_x_preferred":[
        "A\u00efp\u00e1tia"
    ],
    "name:ell_x_variant":[
        "\u0391\u03ca\u03c0\u03ac\u03c4\u03b9\u03b1"
    ],
    "wof:name":"Aipatia",
    "wof:placetype":"locality"
},
  "geometry": {"coordinates":[24.92269,37.75274],"type":"Point"}
}