{
  "type": "Feature",
  "properties": {
    "gn:admin1_code":"ESYE43",
    "gn:admin2_code":"43.0",
    "gn:admin3_code":"9323",
    "gn:asciiname":"Loutraki",
    "gn:country_code":"GR",
    "gn:dem":65,
    "gn:feature_class":"P",
    "gn:feature_code":"PPL",
    "gn:name":"Loutr\u00e1ki",
    "gn:population":0,
    "gn:timezone":"Europe/Athens",
    "iso:country":"GR",
    "name:ara_x_preferred":[
        "\u0644\u0648\u062a\u0631\u0627\u0643\u064a"
    ],
    "name:ceb_x_preferred":[
        "Loutr\u00e1ki"
    ],
    "name:ces_x_preferred":[
        "Loutraki"
    ],
    "name:deu_x_preferred":[
        "Loutraki"
    ],
    "name:ell_x_preferred":[
        "\u039b\u03bf\u03c5\u03c4\u03c1\u03ac\u03ba\u03b9"
    ],
    "name:ell_x_variant":[
        "\u039b\u03bf\u03c5\u03c4\u03c1\u03ac\u03ba\u03b9\u03bf\u03bd"
    ],
    "name:fin_x_preferred":[
        "Loutr\u00e1ki"
    ],
    "name:fra_x_preferred":[
        "Loutr\u00e1ki"
    ],
    "name:ita_x_preferred":[
        "Loutraki"
    ],
    "name:nno_x_preferred":[
        "Loutr\u00e1ki"
    ],
    "name:nor_x_preferred":[
        "Loutraki"
    ],
    "name:pol_x_preferred":[
        "Lutraki"
    ],
    "name:ron_x_preferred":[
        "Loutraki"
    ],
    "name:rus_x_preferred":[
        "\u041b\u0443\u0442\u0440\u0430\u043a\u0438"
    ],
    "name:sqi_x_preferred":[
        "Llutraqi"
    ],
    "name:swe_x_preferred":[
        "Loutr\u00e1ki"
    ],
    "name:ukr_x_preferred":[
        "\u041b\u0443\u0442\u0440\u0430\u043a\u0456"
    ],
    "name:und_x_variant":[
        "Loutr\u00e1ki",
        "Loutr\u00e1kion"
    ],
    "name:urd_x_preferred":[
        "\u0644\u0624\u062a\u0631\u0627\u06a9\u06cc"
    ],
    "wof:name":"Loutraki",
    "wof:placetype":"locality"
},
  "geometry": {"coordinates":[23.86923,35.49019000000001],"type":"Point"}
}