{
  "type": "Feature",
  "properties": {
    "gn:admin1_code":"ESYE14",
    "gn:admin2_code":"23.0",
    "gn:admin3_code":"9092",
    "gn:asciiname":"Krya Vrysi",
    "gn:country_code":"GR",
    "gn:dem":127,
    "gn:feature_class":"P",
    "gn:feature_code":"PPL",
    "gn:name":"Kr\u00fda Vr\u00fdsi",
    "gn:population":541,
    "gn:timezone":"Europe/Athens",
    "iso:country":"GR",
    "name:ell_x_preferred":[
        "\u039a\u03c1\u03cd\u03b1 \u0392\u03c1\u03cd\u03c3\u03b7"
    ],
    "name:und_x_variant":[
        "Kr\u00eda Vr\u00edsi",
        "Kr\u00fda Vr\u00fdsi"
    ],
    "wof:name":"Krya Vrysi",
    "wof:placetype":"locality",
    "wof:population":541
},
  "geometry": {"coordinates":[21.87367,39.32352],"type":"Point"}
}