{
  "type": "Feature",
  "properties": {
    "gn:admin1_code":"ESYE24",
    "gn:admin2_code":"33.0",
    "gn:admin3_code":"9147",
    "gn:asciiname":"Kokkini",
    "gn:country_code":"GR",
    "gn:dem":252,
    "gn:feature_class":"P",
    "gn:feature_code":"PPL",
    "gn:name":"Kokk\u00edni",
    "gn:population":0,
    "gn:timezone":"Europe/Athens",
    "iso:country":"GR",
    "name:ell_x_preferred":[
        "\u039a\u03bf\u03ba\u03ba\u03af\u03bd\u03b9"
    ],
    "name:ell_x_variant":[
        "\u039a\u03bf\u03ba\u03ba\u03af\u03bd\u03b9\u03bf\u03bd"
    ],
    "name:und_x_variant":[
        "Kokk\u00ednis",
        "Kokk\u00edni",
        "Kokk\u00ednion"
    ],
    "wof:name":"Kokkini",
    "wof:placetype":"locality"
},
  "geometry": {"coordinates":[23.52528,38.14658],"type":"Point"}
}