{
  "type": "Feature",
  "properties": {
    "gn:admin1_code":"ESYE25",
    "gn:admin2_code":"41.0",
    "gn:admin3_code":"9241",
    "gn:asciiname":"Elaiochori",
    "gn:country_code":"GR",
    "gn:dem":527,
    "gn:feature_class":"P",
    "gn:feature_code":"PPL",
    "gn:name":"Elaioch\u00f3ri",
    "gn:population":0,
    "gn:timezone":"Europe/Athens",
    "iso:country":"GR",
    "name:ell_x_preferred":[
        "Elaioch\u00f3ri"
    ],
    "name:ell_x_variant":[
        "\u0395\u03bb\u03b1\u03b9\u03bf\u03c7\u03ce\u03c1\u03b9",
        "Elaioch\u00f3rion",
        "\u0395\u03bb\u03b1\u03b9\u03bf\u03c7\u03ce\u03c1\u03b9\u03bf\u03bd"
    ],
    "name:sco_x_preferred":[
        "Elaiochori"
    ],
    "name:und_x_variant":[
        "Masil\u00edna",
        "M\u00e1sklina",
        "Elaiokh\u00f3rion"
    ],
    "wof:name":"Elaiochori",
    "wof:placetype":"locality"
},
  "geometry": {"coordinates":[22.5692,37.45607],"type":"Point"}
}