{
  "type": "Feature",
  "properties": {
    "gn:admin1_code":"ESYE23",
    "gn:admin2_code":"39.0",
    "gn:admin3_code":"9140",
    "gn:asciiname":"Glyfa",
    "gn:country_code":"GR",
    "gn:dem":38,
    "gn:feature_class":"P",
    "gn:feature_code":"PPL",
    "gn:name":"Gl\u00fdfa",
    "gn:population":0,
    "gn:timezone":"Europe/Athens",
    "iso:country":"GR",
    "name:ell_x_preferred":[
        "\u0393\u03bb\u03cd\u03c6\u03b1"
    ],
    "name:eng_x_preferred":[
        "Gl\u00fdfa"
    ],
    "name:und_x_variant":[
        "Gl\u00edfa"
    ],
    "wof:name":"Glyfa",
    "wof:placetype":"locality"
},
  "geometry": {"coordinates":[21.14447,37.84225],"type":"Point"}
}