{
  "type": "Feature",
  "properties": {
    "gn:gn_country":"GR",
    "gn:gn_fcode":"PPLA3",
    "gn:gn_pop":5719,
    "gn:population":5719,
    "iso:country":"GR",
    "name:ell_x_preferred":[
        "\u03a0\u03b1\u03bb\u03b1\u03bc\u03ac\u03c2"
    ],
    "name:ell_x_variant":[
        "\u03a0\u03b1\u03bb\u03b1\u03bc\u03ac\u03c2 \u039a\u03b1\u03c1\u03b4\u03af\u03c4\u03c3\u03b1\u03c2"
    ],
    "name:eng_x_preferred":[
        "Palamas Karditsa"
    ],
    "name:nld_x_preferred":[
        "Palamas"
    ],
    "name:pol_x_preferred":[
        "Palamas"
    ],
    "name:swe_x_preferred":[
        "Palam\u00e1s"
    ],
    "qs_pg:aaroncc":"GR",
    "qs_pg:gn_country":"GR",
    "qs_pg:gn_fcode":"PPLA3",
    "qs_pg:gn_pop":5719,
    "qs_pg:name":"Palam\u00e1s",
    "qs_pg:photos_9r":0,
    "qs_pg:photos_sr":0,
    "qs_pg:pop_sr":5,
    "qs_pg:qs_pg_placetype":"locality",
    "wof:name":"Palam\u00e1s",
    "wof:placetype":"locality",
    "wof:population":5719
},
  "geometry": {"coordinates":[22.08333,39.46667],"type":"Point"}
}