{
  "type": "Feature",
  "properties": {
    "gn:admin1_code":"ESYE25",
    "gn:admin2_code":"41.0",
    "gn:admin3_code":"9238",
    "gn:asciiname":"Rizospilia",
    "gn:cc2":"GR",
    "gn:country_code":"GR",
    "gn:dem":403,
    "gn:feature_class":"P",
    "gn:feature_code":"PPL",
    "gn:name":"Rizospili\u00e1",
    "gn:population":0,
    "gn:timezone":"Europe/Athens",
    "iso:country":"GR",
    "name:ron_x_preferred":[
        "Rizospilia"
    ],
    "name:und_x_variant":[
        "\u00c1no Stro\u00faza",
        "Stro\u00faza",
        "Rizospili\u00e1"
    ],
    "wof:name":"Rizospilia",
    "wof:placetype":"locality"
},
  "geometry": {"coordinates":[21.95223,37.56673],"type":"Point"}
}