{
  "type": "Feature",
  "properties": {
    "gn:admin1_code":"ESYE43",
    "gn:admin2_code":"43.0",
    "gn:admin3_code":"9319",
    "gn:asciiname":"Metamorfosi",
    "gn:country_code":"GR",
    "gn:dem":40,
    "gn:feature_class":"P",
    "gn:feature_code":"PPL",
    "gn:name":"Metam\u00f3rfosi",
    "gn:population":0,
    "gn:timezone":"Europe/Athens",
    "iso:country":"GR",
    "name:ara_x_preferred":[
        "\u0645\u064a\u062a\u0627\u0645\u0648\u0631\u0641\u0648\u0633\u064a"
    ],
    "name:ceb_x_preferred":[
        "Metam\u00f3rfosi"
    ],
    "name:deu_x_preferred":[
        "Metamorfosi"
    ],
    "name:ell_x_preferred":[
        "\u039c\u03b5\u03c4\u03b1\u03bc\u03cc\u03c1\u03c6\u03c9\u03c3\u03b7"
    ],
    "name:ell_x_variant":[
        "Metam\u00f3rfosi",
        "\u039c\u03b5\u03c4\u03b1\u03bc\u03cc\u03c1\u03c6\u03c9\u03c3\u03b7 \u0391\u03c4\u03c4\u03b9\u03ba\u03ae\u03c2"
    ],
    "name:fas_x_preferred":[
        "\u0645\u062a\u0627\u0645\u0648\u0631\u0641\u0648\u0633\u06cc"
    ],
    "name:fin_x_preferred":[
        "Metam\u00f3rfosi"
    ],
    "name:fra_x_preferred":[
        "Metam\u00f3rfosi"
    ],
    "name:ita_x_preferred":[
        "Metamorfosi"
    ],
    "name:nld_x_preferred":[
        "Metamorfosi"
    ],
    "name:nno_x_preferred":[
        "Metam\u00f3rfosi"
    ],
    "name:pol_x_preferred":[
        "Metamorfosi"
    ],
    "name:ron_x_preferred":[
        "Metamorfosis"
    ],
    "name:rus_x_preferred":[
        "\u041c\u0435\u0442\u0430\u043c\u043e\u0440\u0444\u043e\u0441\u0438\u0441"
    ],
    "name:sco_x_preferred":[
        "Metamorfosi"
    ],
    "name:srp_x_preferred":[
        "\u041c\u0435\u0442\u0430\u043c\u043e\u0440\u0444\u043e\u0441\u0438"
    ],
    "name:swe_x_preferred":[
        "Metam\u00f3rfosi"
    ],
    "name:tur_x_preferred":[
        "Metamorfosi"
    ],
    "name:ukr_x_preferred":[
        "\u041c\u0435\u0442\u0430\u043c\u043e\u0440\u0444\u043e\u0441\u0456"
    ],
    "name:urd_x_preferred":[
        "\u0645\u06cc\u062a\u0627\u0645\u0648\u0631\u0641\u0648\u0633\u06cc"
    ],
    "name:vie_x_preferred":[
        "Metamorfossi"
    ],
    "wof:name":"Metamorfosi",
    "wof:placetype":"locality"
},
  "geometry": {"coordinates":[24.30734,35.34171],"type":"Point"}
}