{
  "type": "Feature",
  "properties": {
    "gn:admin1_code":"ESYE22",
    "gn:admin2_code":"27.0",
    "gn:asciiname":"Karavados",
    "gn:country_code":"GR",
    "gn:dem":7,
    "gn:feature_class":"P",
    "gn:feature_code":"PPL",
    "gn:name":"Karavados",
    "gn:population":0,
    "gn:timezone":"Europe/Athens",
    "iso:country":"GR",
    "wof:name":"Karavados",
    "wof:placetype":"locality"
},
  "geometry": {"coordinates":[20.60016,38.11596],"type":"Point"}
}