{
  "type": "Feature",
  "properties": {
    "gn:country":"GR",
    "iso:country":"GR",
    "name:cat_x_preferred":[
        "Ni\u014d"
    ],
    "name:ces_x_preferred":[
        "Ni\u00f3"
    ],
    "name:epo_x_preferred":[
        "Nioo"
    ],
    "name:eus_x_preferred":[
        "Nio"
    ],
    "name:fra_x_preferred":[
        "Ni\u014d"
    ],
    "name:hun_x_preferred":[
        "Nio"
    ],
    "name:ita_x_preferred":[
        "Nio"
    ],
    "name:jpn_x_preferred":[
        "\u91d1\u525b\u529b\u58eb"
    ],
    "name:kor_x_preferred":[
        "\uae08\uac15\uc5ed\uc0ac"
    ],
    "name:pol_x_preferred":[
        "Ni\u014d"
    ],
    "name:ron_x_preferred":[
        "Ni\u014d"
    ],
    "name:spa_x_preferred":[
        "Ni\u014d"
    ],
    "name:zho_x_preferred":[
        "\u91d1\u525b\u529b\u58eb"
    ],
    "qs_pg:aaroncc":"GR",
    "qs_pg:gn_country":"GR",
    "qs_pg:name":"Nio",
    "qs_pg:name_adm0":"\u0395\u03bb\u03bb\u03ac\u03b4\u03b1",
    "qs_pg:name_adm1":"Aegean",
    "qs_pg:photos":1236,
    "qs_pg:photos_1k":250,
    "qs_pg:photos_9k":5,
    "qs_pg:photos_9r":7,
    "qs_pg:photos_all":1236,
    "qs_pg:photos_sr":11,
    "qs_pg:pop_sr":0,
    "qs_pg:qs_pg_placetype":"locality",
    "qs_pg:qs_pg_placetype_gp":"Town",
    "qs_pg:woe_adm0":23424833,
    "woe:adm0_id":23424833,
    "woe:name_adm0":"\u0395\u03bb\u03bb\u03ac\u03b4\u03b1",
    "woe:name_adm1":"Aegean",
    "woe:placetype":"Town",
    "wof:name":"Nio",
    "wof:placetype":"locality"
},
  "geometry": {"coordinates":[25.276107,36.72375],"type":"Point"}
}