{
  "type": "Feature",
  "properties": {
    "gn:admin1_code":"ESYE25",
    "gn:admin2_code":"42.0",
    "gn:admin3_code":"9251",
    "gn:asciiname":"Kato Kastania",
    "gn:country_code":"GR",
    "gn:dem":248,
    "gn:feature_class":"P",
    "gn:feature_code":"PPL",
    "gn:name":"K\u00e1to Kastani\u00e1",
    "gn:population":0,
    "gn:timezone":"Europe/Athens",
    "iso:country":"GR",
    "name:ell_x_preferred":[
        "\u039a\u03ac\u03c4\u03c9 \u039a\u03b1\u03c3\u03c4\u03b1\u03bd\u03b9\u03ac"
    ],
    "name:ell_x_variant":[
        "\u039a\u03ac\u03c4\u03c9 \u039a\u03b1\u03c3\u03c4\u03b1\u03bd\u03ad\u03b1"
    ],
    "name:und_x_variant":[
        "K\u00e1to Kastani\u00e1",
        "K\u00e1to Kastan\u00e9a"
    ],
    "wof:name":"Kato Kastania",
    "wof:placetype":"locality"
},
  "geometry": {"coordinates":[23.11618,36.52866],"type":"Point"}
}