{
  "type": "Feature",
  "properties": {
    "gn:admin1_code":"ESYE24",
    "gn:admin2_code":"32.0",
    "gn:admin3_code":"9166",
    "gn:asciiname":"Erateini",
    "gn:country_code":"GR",
    "gn:dem":10,
    "gn:feature_class":"P",
    "gn:feature_code":"PPL",
    "gn:name":"Eratein\u00ed",
    "gn:population":0,
    "gn:timezone":"Europe/Athens",
    "iso:country":"GR",
    "name:ell_x_preferred":[
        "Eratein\u00ed"
    ],
    "name:ell_x_variant":[
        "\u0395\u03c1\u03b1\u03c4\u03b5\u03b9\u03bd\u03ae"
    ],
    "name:und_x_variant":[
        "Eratin\u00ed"
    ],
    "wof:name":"Erateini",
    "wof:placetype":"locality"
},
  "geometry": {"coordinates":[22.2283,38.36179],"type":"Point"}
}