{
  "type": "Feature",
  "properties": {
    "gn:admin1_code":"ESYE11",
    "gn:admin2_code":"3.0",
    "gn:admin3_code":"9016",
    "gn:asciiname":"Diaforo",
    "gn:country_code":"GR",
    "gn:dem":441,
    "gn:feature_class":"P",
    "gn:feature_code":"PPL",
    "gn:name":"Di\u00e1foro",
    "gn:population":0,
    "gn:timezone":"Europe/Athens",
    "iso:country":"GR",
    "name:ell_x_preferred":[
        "Di\u00e1foro"
    ],
    "name:ell_x_variant":[
        "\u0394\u03b9\u03ac\u03c6\u03bf\u03c1\u03bf"
    ],
    "name:und_x_variant":[
        "B\u00e1ra Males\u00ed"
    ],
    "wof:name":"Diaforo",
    "wof:placetype":"locality"
},
  "geometry": {"coordinates":[24.90183,41.17709],"type":"Point"}
}