{
  "type": "Feature",
  "properties": {
    "gn:admin1_code":"ESYE24",
    "gn:admin2_code":"30.0",
    "gn:admin3_code":"9157",
    "gn:asciiname":"Neo Dermati",
    "gn:country_code":"GR",
    "gn:dem":702,
    "gn:feature_class":"P",
    "gn:feature_code":"PPL",
    "gn:name":"N\u00e9o Derm\u00e1ti",
    "gn:population":30,
    "gn:timezone":"Europe/Athens",
    "iso:country":"GR",
    "name:ell_x_preferred":[
        "\u039d\u03ad\u03bf \u0394\u03b5\u03c1\u03bc\u03ac\u03c4\u03b9"
    ],
    "wof:name":"Neo Dermati",
    "wof:placetype":"locality",
    "wof:population":30
},
  "geometry": {"coordinates":[21.73645,38.84541],"type":"Point"}
}