{
  "type": "Feature",
  "properties": {
    "gn:admin1_code":"ESYE25",
    "gn:admin2_code":"42.0",
    "gn:admin3_code":"9252",
    "gn:asciiname":"Arna",
    "gn:country_code":"GR",
    "gn:dem":767,
    "gn:feature_class":"P",
    "gn:feature_code":"PPL",
    "gn:name":"\u00c1rna",
    "gn:population":0,
    "gn:timezone":"Europe/Athens",
    "iso:country":"GR",
    "name:ell_x_preferred":[
        "\u0386\u03c1\u03bd\u03b1"
    ],
    "name:ell_x_variant":[
        "\u0391\u03c1\u03bd\u03b1"
    ],
    "name:ron_x_preferred":[
        "Arna"
    ],
    "name:und_x_variant":[
        "\u00c1rna"
    ],
    "wof:name":"Arna",
    "wof:placetype":"locality"
},
  "geometry": {"coordinates":[22.41486,36.87787],"type":"Point"}
}