{
  "type": "Feature",
  "properties": {
    "gn:admin1_code":"ESYE43",
    "gn:admin2_code":"43.0",
    "gn:admin3_code":"9323",
    "gn:asciiname":"Sembrono",
    "gn:cc2":"GR",
    "gn:country_code":"GR",
    "gn:dem":583,
    "gn:feature_class":"P",
    "gn:feature_code":"PPL",
    "gn:name":"S\u00e9mbrono",
    "gn:population":0,
    "gn:timezone":"Europe/Athens",
    "iso:country":"GR",
    "name:und_x_variant":[
        "S\u00e9mprono",
        "S\u00e9mbrono"
    ],
    "wof:name":"Sembrono",
    "wof:placetype":"locality"
},
  "geometry": {"coordinates":[23.81667,35.38333],"type":"Point"}
}