{
  "type": "Feature",
  "properties": {
    "gn:admin1_code":"ESYE24",
    "gn:admin2_code":"34.0",
    "gn:admin3_code":"9150",
    "gn:asciiname":"Agios Ioannis",
    "gn:country_code":"GR",
    "gn:dem":111,
    "gn:feature_class":"P",
    "gn:feature_code":"PPL",
    "gn:name":"\u00c1gios Io\u00e1nnis",
    "gn:population":0,
    "gn:timezone":"Europe/Athens",
    "iso:country":"GR",
    "name:ell_x_preferred":[
        "\u00c1gios Io\u00e1nnis"
    ],
    "name:ell_x_variant":[
        "\u0386\u03b3\u03b9\u03bf\u03c2 \u0399\u03c9\u03ac\u03bd\u03bd\u03b7\u03c2"
    ],
    "name:und_x_variant":[
        "\u00c1yios Io\u00e1nnis"
    ],
    "wof:name":"Agios Ioannis",
    "wof:placetype":"locality"
},
  "geometry": {"coordinates":[23.11511,38.91475],"type":"Point"}
}