{
  "type": "Feature",
  "properties": {
    "gn:admin1_code":"ESYE42",
    "gn:admin2_code":"47.0",
    "gn:admin3_code":"9278",
    "gn:asciiname":"Partheni",
    "gn:country_code":"GR",
    "gn:dem":10,
    "gn:feature_class":"P",
    "gn:feature_code":"PPL",
    "gn:name":"Parth\u00e9ni",
    "gn:population":0,
    "gn:timezone":"Europe/Athens",
    "iso:country":"GR",
    "name:ell_x_preferred":[
        "\u03a0\u03b1\u03c1\u03b8\u03ad\u03bd\u03b9"
    ],
    "name:ell_x_variant":[
        "\u03a0\u03b1\u03c1\u03b8\u03ad\u03bd\u03b9\u03bf\u03bd"
    ],
    "name:und_x_variant":[
        "Parth\u00e9ni",
        "Parteni",
        "Parth\u00e9nion"
    ],
    "wof:name":"Partheni",
    "wof:placetype":"locality"
},
  "geometry": {"coordinates":[26.80828,37.18858],"type":"Point"}
}