{
  "type": "Feature",
  "properties": {
    "gn:admin1_code":"ESYE23",
    "gn:admin2_code":"39.0",
    "gn:admin3_code":"9141.0",
    "gn:asciiname":"Paralia",
    "gn:country_code":"GR",
    "gn:dem":1,
    "gn:feature_class":"P",
    "gn:feature_code":"PPL",
    "gn:name":"Paralia",
    "gn:population":0,
    "gn:timezone":"Europe/Athens",
    "iso:country":"GR",
    "name:bul_x_preferred":[
        "\u041f\u0430\u0440\u0430\u043b\u0438\u044f"
    ],
    "name:ceb_x_preferred":[
        "Paralia"
    ],
    "name:deu_x_preferred":[
        "Paralia"
    ],
    "name:fin_x_preferred":[
        "Paralia"
    ],
    "name:ita_x_preferred":[
        "Paralia"
    ],
    "name:pol_x_preferred":[
        "Paralia"
    ],
    "name:srp_x_preferred":[
        "\u041f\u0430\u0440\u0430\u043b\u0438\u0458\u0430"
    ],
    "name:swe_x_preferred":[
        "Paralia"
    ],
    "wof:name":"Paralia",
    "wof:placetype":"locality"
},
  "geometry": {"coordinates":[21.46424,37.60734],"type":"Point"}
}