{
  "type": "Feature",
  "properties": {
    "gn:admin1_code":"ESYE13",
    "gn:admin2_code":"9.0",
    "gn:admin3_code":"9065",
    "gn:asciiname":"Nostimo",
    "gn:country_code":"GR",
    "gn:dem":915,
    "gn:feature_class":"P",
    "gn:feature_code":"PPL",
    "gn:name":"N\u00f3stimo",
    "gn:population":108,
    "gn:timezone":"Europe/Athens",
    "iso:country":"GR",
    "name:bul_x_historical":[
        "\u041d\u0435\u0441\u0442\u0438\u043c\u0435"
    ],
    "name:bul_x_preferred":[
        "\u041d\u0435\u0441\u0442\u0438\u043c\u0435"
    ],
    "name:bul_x_variant":[
        "\u041d\u043e\u0441\u0442\u0438\u043c\u043e"
    ],
    "name:ell_x_historical":[
        "\u039d\u03b9\u03c3\u03c4\u03ae\u03bc\u03b9\u03bf\u03bd",
        "\u039a\u03bf\u03c5\u03c6\u03bf\u03be\u03c5\u03bb\u03b9\u03ac"
    ],
    "name:ell_x_preferred":[
        "\u039d\u03cc\u03c3\u03c4\u03b9\u03bc\u03bf"
    ],
    "name:ell_x_variant":[
        "\u039d\u03cc\u03c3\u03c4\u03b9\u03bc\u03bf\u03bd",
        "\u039d\u03b9\u03c3\u03c4\u03ae\u03bc\u03b9\u03bf\u03bd",
        "\u039a\u03bf\u03c5\u03c6\u03bf\u03be\u03c5\u03bb\u03b9\u03ac"
    ],
    "name:eng_x_preferred":[
        "Nostimo"
    ],
    "name:und_x_variant":[
        "Nist\u00edmion",
        "Koufoxili\u00e1",
        "N\u00f3stimon",
        "N\u00f3stimo"
    ],
    "wof:name":"Nostimo",
    "wof:placetype":"locality",
    "wof:population":108
},
  "geometry": {"coordinates":[21.20464,40.38752],"type":"Point"}
}