{
  "type": "Feature",
  "properties": {
    "gn:admin1_code":"ESYE11",
    "gn:admin2_code":"3.0",
    "gn:admin3_code":"9018",
    "gn:asciiname":"Kremasti",
    "gn:country_code":"GR",
    "gn:dem":24,
    "gn:feature_class":"P",
    "gn:feature_code":"PPL",
    "gn:name":"Kremast\u00ed",
    "gn:population":0,
    "gn:timezone":"Europe/Athens",
    "iso:country":"GR",
    "name:ell_x_preferred":[
        "Kremast\u00ed"
    ],
    "name:ell_x_variant":[
        "\u039a\u03c1\u03b5\u03bc\u03b1\u03c3\u03c4\u03ae"
    ],
    "wof:name":"Kremasti",
    "wof:placetype":"locality"
},
  "geometry": {"coordinates":[24.76634,41.01543],"type":"Point"}
}