{
  "type": "Feature",
  "properties": {
    "gn:admin1_code":"ESYE11",
    "gn:admin2_code":"3.0",
    "gn:admin3_code":"9018",
    "gn:asciiname":"Kremasti",
    "gn:country_code":"GR",
    "gn:dem":24,
    "gn:feature_class":"P",
    "gn:feature_code":"PPL",
    "gn:name":"Kremast\u00ed",
    "gn:population":0,
    "gn:timezone":"Europe/Athens",
    "iso:country":"GR",
    "name:ara_x_preferred":[
        "\u0643\u0631\u064a\u0645\u0627\u0633\u062a\u064a"
    ],
    "name:ceb_x_preferred":[
        "Kremast\u00ed"
    ],
    "name:ell_x_preferred":[
        "Kremast\u00ed"
    ],
    "name:ell_x_variant":[
        "\u039a\u03c1\u03b5\u03bc\u03b1\u03c3\u03c4\u03ae",
        "\u039a\u03c1\u03b5\u03bc\u03b1\u03c3\u03c4\u03ae \u03a1\u03cc\u03b4\u03bf\u03c5"
    ],
    "name:fin_x_preferred":[
        "Kremast\u00ed"
    ],
    "name:nno_x_preferred":[
        "Kremast\u00ed"
    ],
    "name:rus_x_preferred":[
        "\u041a\u0440\u0435\u043c\u0430\u0441\u0442\u0438"
    ],
    "name:swe_x_preferred":[
        "Kremast\u00ed"
    ],
    "wof:name":"Kremasti",
    "wof:placetype":"locality"
},
  "geometry": {"coordinates":[24.76634,41.01543],"type":"Point"}
}