{
  "type": "Feature",
  "properties": {
    "gn:admin1_code":"ESYE43",
    "gn:admin2_code":"45.0",
    "gn:admin3_code":"9303",
    "gn:asciiname":"Keratokambos",
    "gn:country_code":"GR",
    "gn:dem":6,
    "gn:feature_class":"P",
    "gn:feature_code":"PPL",
    "gn:name":"Kerat\u00f3kambos",
    "gn:population":0,
    "gn:timezone":"Europe/Athens",
    "iso:country":"GR",
    "wof:name":"Keratokambos",
    "wof:placetype":"locality"
},
  "geometry": {"coordinates":[25.37827,34.99905],"type":"Point"}
}