{
  "type": "Feature",
  "properties": {
    "gn:admin1_code":"ESYE43",
    "gn:admin2_code":"45.0",
    "gn:admin3_code":"9307",
    "gn:asciiname":"Galatas",
    "gn:country_code":"GR",
    "gn:dem":384,
    "gn:feature_class":"P",
    "gn:feature_code":"PPL",
    "gn:name":"Galat\u00e1s",
    "gn:population":0,
    "gn:timezone":"Europe/Athens",
    "iso:country":"GR",
    "name:ell_x_preferred":[
        "\u0393\u03b1\u03bb\u03b1\u03c4\u03ac\u03c2"
    ],
    "name:und_x_variant":[
        "Galat\u00e1",
        "Galat\u00e1s"
    ],
    "wof:name":"Galatas",
    "wof:placetype":"locality"
},
  "geometry": {"coordinates":[25.24738,35.18208],"type":"Point"}
}