{
  "type": "Feature",
  "properties": {
    "gn:country":"GR",
    "gn:fcode":"PPL",
    "gn:population":58,
    "iso:country":"GR",
    "name:ell_x_preferred":[
        "\u0392\u03c1\u03b1\u03b3\u03b3\u03b9\u03b1\u03bd\u03ac"
    ],
    "name:und_x_variant":[
        "Meg\u00e1la Vray\u00e9na"
    ],
    "qs_pg:aaroncc":"GR",
    "qs_pg:gn_country":"GR",
    "qs_pg:gn_fcode":"PPL",
    "qs_pg:gn_pop":58,
    "qs_pg:name":"Vrangiana",
    "qs_pg:name_adm0":"\u0395\u03bb\u03bb\u03ac\u03b4\u03b1",
    "qs_pg:name_adm1":"Thessaly and Continental Greece",
    "qs_pg:photos_9r":0,
    "qs_pg:photos_sr":0,
    "qs_pg:pop_sr":1,
    "qs_pg:qs_pg_placetype":"locality",
    "qs_pg:qs_pg_placetype_gp":"Town",
    "qs_pg:woe_adm0":23424833,
    "woe:adm0_id":23424833,
    "woe:name_adm0":"\u0395\u03bb\u03bb\u03ac\u03b4\u03b1",
    "woe:name_adm1":"Thessaly and Continental Greece",
    "woe:placetype":"Town",
    "wof:name":"Vrangiana",
    "wof:placetype":"locality",
    "wof:population":58
},
  "geometry": {"coordinates":[21.64528,39.20806],"type":"Point"}
}