{
  "type": "Feature",
  "properties": {
    "gn:admin1_code":"ESYE24",
    "gn:admin2_code":"29.0",
    "gn:admin3_code":"9162",
    "gn:asciiname":"Loutra Platistomou",
    "gn:country_code":"GR",
    "gn:dem":252,
    "gn:feature_class":"P",
    "gn:feature_code":"PPL",
    "gn:name":"Loutr\u00e1 Platist\u00f3mou",
    "gn:population":7,
    "gn:timezone":"Europe/Athens",
    "iso:country":"GR",
    "name:ell_x_preferred":[
        "\u039b\u03bf\u03c5\u03c4\u03c1\u03ac \u03a0\u03bb\u03b1\u03c4\u03c5\u03c3\u03c4\u03cc\u03bc\u03bf\u03c5"
    ],
    "name:eng_x_preferred":[
        "Loutra Platystomou"
    ],
    "wof:name":"Loutra Platistomou",
    "wof:placetype":"locality",
    "wof:population":7
},
  "geometry": {"coordinates":[22.10042,38.97079],"type":"Point"}
}