{
  "type": "Feature",
  "properties": {
    "gn:population":1556,
    "iso:country":"GR",
    "name:ara_x_preferred":[
        "\u0623\u0631\u0646\u064a\u0633\u0627"
    ],
    "name:bul_x_preferred":[
        "\u041e\u0441\u0442\u0440\u043e\u0432\u043e"
    ],
    "name:ceb_x_preferred":[
        "\u00c1rnissa"
    ],
    "name:ell_x_preferred":[
        "\u0386\u03c1\u03bd\u03b9\u03c3\u03c3\u03b1 \u03a0\u03ad\u03bb\u03bb\u03b1\u03c2"
    ],
    "name:ell_x_variant":[
        "\u0386\u03c1\u03bd\u03b9\u03c3\u03c3\u03b1"
    ],
    "name:eng_x_preferred":[
        "Arnissa"
    ],
    "name:mkd_x_preferred":[
        "\u041e\u0441\u0442\u0440\u043e\u0432\u043e"
    ],
    "name:nld_x_preferred":[
        "Arnissa"
    ],
    "name:nno_x_preferred":[
        "\u00c1rnissa"
    ],
    "name:ota_x_preferred":[
        "\u0627\u0648\u0633\u062a\u0631\u0648\u0648\u0647"
    ],
    "name:por_x_preferred":[
        "Arnissa"
    ],
    "name:rus_x_preferred":[
        "\u0410\u0440\u043d\u0438\u0441\u0430"
    ],
    "name:swe_x_preferred":[
        "\u00c1rnissa"
    ],
    "name:und_x_variant":[
        "\u00d3strovon"
    ],
    "qs:a0":"Greece",
    "qs:a1":"*\u039a\u0395\u039d\u03a4\u03a1\u0399\u039a\u0397 \u039c\u0391\u039a\u0395\u0394\u039f\u039d\u0399\u0391",
    "qs:a1_alt":"KENTRIKH MAKEDONIA",
    "qs:a1r":"0",
    "qs:a2_alt":"PELLA",
    "qs:adm0":"Greece",
    "qs:la_lc":"*",
    "qs:level":"locality",
    "qs:loc":"\u0391\u03a1\u039d\u0399\u03a3\u03a3\u0391",
    "qs:loc_alt":"ARNISSA",
    "qs:pop":0,
    "qs:type":"buffered point",
    "wd:population":1411,
    "wd:wordcount":73,
    "wof:name":"\u0391\u03a1\u039d\u0399\u03a3\u03a3\u0391",
    "wof:placetype":"locality",
    "wof:population":1411
},
  "geometry": {"coordinates":[21.836359,40.796276],"type":"Point"}
}