{
  "type": "Feature",
  "properties": {
    "gn:gn_country":"GR",
    "gn:gn_fcode":"PPL",
    "gn:gn_pop":753,
    "gn:population":1563,
    "iso:country":"GR",
    "name:ell_x_preferred":[
        "\u03a3\u03c4\u03b1\u03c5\u03c1\u03ac\u03ba\u03b9"
    ],
    "name:ell_x_variant":[
        "\u03a3\u03c4\u03b1\u03c5\u03c1\u03ac\u03ba\u03b9\u03bf\u03bd"
    ],
    "name:eng_x_preferred":[
        "Stavraki"
    ],
    "name:unk_x_variant":[
        "Stavr\u00e1ki"
    ],
    "qs_pg:aaroncc":"GR",
    "qs_pg:gn_country":"GR",
    "qs_pg:gn_fcode":"PPL",
    "qs_pg:gn_pop":753,
    "qs_pg:name":"Stavr\u00e1kion",
    "qs_pg:photos_9r":0,
    "qs_pg:photos_sr":0,
    "qs_pg:pop_sr":2,
    "qs_pg:qs_pg_placetype":"locality",
    "wof:name":"Stavr\u00e1kion",
    "wof:placetype":"locality",
    "wof:population":1563
},
  "geometry": {"coordinates":[20.8175,39.65583],"type":"Point"}
}