{
  "type": "Feature",
  "properties": {
    "gn:population":1679,
    "iso:country":"GR",
    "name:ell_x_preferred":[
        "\u03a3\u03bf\u03c6\u03b9\u03ba\u03cc\u03bd"
    ],
    "name:ell_x_variant":[
        "\u03a3\u03bf\u03c6\u03b9\u03ba\u03cc"
    ],
    "name:eng_x_preferred":[
        "Sofiko"
    ],
    "name:unk_x_variant":[
        "Sophiko"
    ],
    "qs:a0":"Greece",
    "qs:a1":"*\u03a0\u0395\u039b\u039f\u03a0\u039f\u039d\u039d\u0397\u03a3\u039f\u03a3",
    "qs:a1_alt":"PELOPONNHSOS",
    "qs:a1r":"0",
    "qs:a2_alt":"KORINUIA",
    "qs:adm0":"Greece",
    "qs:la_lc":"*",
    "qs:level":"locality",
    "qs:loc":"\u03a3\u039f\u03a6\u0399\u039a\u039f\u039d",
    "qs:loc_alt":"SOFIKON",
    "qs:pop":0,
    "qs:type":"buffered point",
    "wof:name":"\u03a3\u039f\u03a6\u0399\u039a\u039f\u039d",
    "wof:placetype":"locality",
    "wof:population":1679
},
  "geometry": {"coordinates":[23.053838,37.792439],"type":"Point"}
}