{
  "type": "Feature",
  "properties": {
    "gn:admin1_code":"ESYE25",
    "gn:admin2_code":"41.0",
    "gn:admin3_code":"9239",
    "gn:asciiname":"Kampochori",
    "gn:country_code":"GR",
    "gn:dem":478,
    "gn:feature_class":"P",
    "gn:feature_code":"PPL",
    "gn:name":"Kampoch\u00f3ri",
    "gn:population":0,
    "gn:timezone":"Europe/Athens",
    "iso:country":"GR",
    "name:ell_x_preferred":[
        "Kampoch\u00f3ri"
    ],
    "name:ell_x_variant":[
        "\u039a\u03b1\u03bc\u03c0\u03bf\u03c7\u03ce\u03c1\u03b9",
        "Kampoch\u00f3rion",
        "\u039a\u03b1\u03bc\u03c0\u03bf\u03c7\u03ce\u03c1\u03b9\u03bf\u03bd"
    ],
    "name:und_x_variant":[
        "Mendz\u00edni",
        "Kambokh\u00f3rion"
    ],
    "wof:name":"Kampochori",
    "wof:placetype":"locality"
},
  "geometry": {"coordinates":[22.15868,37.26574],"type":"Point"}
}