{
  "type": "Feature",
  "properties": {
    "gn:admin1_code":"ESYE31",
    "gn:admin2_code":"406101.0",
    "gn:admin3_code":"9214",
    "gn:asciiname":"Agios Konstantinos Ydras",
    "gn:country_code":"GR",
    "gn:dem":64,
    "gn:feature_class":"P",
    "gn:feature_code":"PPL",
    "gn:name":"\u00c1gios Konstant\u00ednos Ydras",
    "gn:population":1,
    "gn:timezone":"Europe/Athens",
    "iso:country":"GR",
    "name:ell_x_historical":[
        "\u0386\u03b3\u03b9\u03bf\u03c2 \u03a0\u03ad\u03c4\u03c1\u03bf\u03c2",
        "\u0386\u03b3\u03b9\u03bf\u03b9 \u03a0\u03ad\u03c4\u03c1\u03bf\u03c2 \u03ba\u03b1\u03b9 \u03a0\u03b1\u03cd\u03bb\u03bf\u03c2"
    ],
    "name:ell_x_preferred":[
        "\u0386\u03b3\u03b9\u03bf\u03c2 \u039a\u03c9\u03bd\u03c3\u03c4\u03b1\u03bd\u03c4\u03af\u03bd\u03bf\u03c2 \u038e\u03b4\u03c1\u03b1\u03c2"
    ],
    "name:ell_x_variant":[
        "\u0386\u03b3\u03b9\u03bf\u03c2 \u03a0\u03ad\u03c4\u03c1\u03bf\u03c2",
        "\u0386\u03b3\u03b9\u03bf\u03b9 \u03a0\u03ad\u03c4\u03c1\u03bf\u03c2 \u03ba\u03b1\u03b9 \u03a0\u03b1\u03cd\u03bb\u03bf\u03c2"
    ],
    "name:eng_x_preferred":[
        "Agios Konstantinos Ydras"
    ],
    "name:und_x_variant":[
        "\u00c1yios P\u00e9tros"
    ],
    "wof:name":"Agios Konstantinos Ydras",
    "wof:placetype":"locality",
    "wof:population":1
},
  "geometry": {"coordinates":[23.50106,37.33045],"type":"Point"}
}