{
  "type": "Feature",
  "properties": {
    "gn:admin1_code":"ESYE23",
    "gn:admin2_code":"31.0",
    "gn:admin3_code":"9123",
    "gn:asciiname":"Makrinou",
    "gn:country_code":"GR",
    "gn:dem":374,
    "gn:feature_class":"P",
    "gn:feature_code":"PPL",
    "gn:name":"Makrino\u00fa",
    "gn:population":131,
    "gn:timezone":"Europe/Athens",
    "iso:country":"GR",
    "name:ceb_x_preferred":[
        "Makrino\u00fa"
    ],
    "name:ell_x_preferred":[
        "\u039c\u03b1\u03ba\u03c1\u03b9\u03bd\u03bf\u03cd"
    ],
    "name:ell_x_variant":[
        "\u0386\u03bd\u03c9 \u039c\u03b1\u03ba\u03c1\u03b9\u03bd\u03bf\u03cd"
    ],
    "name:eng_x_preferred":[
        "Makrinou"
    ],
    "name:ron_x_preferred":[
        "Makrinou"
    ],
    "name:swe_x_preferred":[
        "Makrino\u00fa"
    ],
    "name:und_x_variant":[
        "\u00c1no Makrino\u00fa",
        "Makrin\u00f3n"
    ],
    "wof:name":"Makrinou",
    "wof:placetype":"locality",
    "wof:population":131
},
  "geometry": {"coordinates":[21.61528,38.47447],"type":"Point"}
}