{
  "type": "Feature",
  "properties": {
    "gn:admin1_code":"ESYE25",
    "gn:admin2_code":"36.0",
    "gn:admin3_code":"9235.0",
    "gn:asciiname":"Vlachopoulaiika",
    "gn:country_code":"GR",
    "gn:dem":26,
    "gn:feature_class":"P",
    "gn:feature_code":"PPL",
    "gn:name":"Vlachopoula\u00edika",
    "gn:population":0,
    "gn:timezone":"Europe/Athens",
    "iso:country":"GR",
    "name:ell_x_preferred":[
        "Vlachopoula\u00edika"
    ],
    "name:ell_x_variant":[
        "\u0392\u03bb\u03b1\u03c7\u03bf\u03c0\u03bf\u03c5\u03bb\u03b1\u03af\u03b9\u03ba\u03b1"
    ],
    "wof:name":"Vlachopoulaiika",
    "wof:placetype":"locality"
},
  "geometry": {"coordinates":[23.15443,37.42119],"type":"Point"}
}