{
  "type": "Feature",
  "properties": {
    "gn:admin1_code":"ESYE12",
    "gn:admin2_code":"15.0",
    "gn:admin3_code":"9058",
    "gn:asciiname":"Nea Irakleia",
    "gn:country_code":"GR",
    "gn:dem":17,
    "gn:feature_class":"P",
    "gn:feature_code":"PPL",
    "gn:name":"N\u00e9a Ir\u00e1kleia",
    "gn:population":832,
    "gn:timezone":"Europe/Athens",
    "iso:country":"GR",
    "name:ell_x_preferred":[
        "\u039d\u03ad\u03b1 \u0397\u03c1\u03ac\u03ba\u03bb\u03b5\u03b9\u03b1"
    ],
    "name:ell_x_variant":[
        "N\u00e9a Ir\u00e1kleia"
    ],
    "name:eng_x_preferred":[
        "Nea Irakleia"
    ],
    "name:und_x_variant":[
        "Ir\u00e1klta",
        "Ir\u00e1klia",
        "N\u00e9a Ir\u00e1klia"
    ],
    "wof:name":"Nea Irakleia",
    "wof:placetype":"locality",
    "wof:population":832
},
  "geometry": {"coordinates":[23.0155,40.34772],"type":"Point"}
}