{
  "type": "Feature",
  "properties": {
    "gn:admin1_code":"ESYE22",
    "gn:admin2_code":"26.0",
    "gn:admin3_code":"9121",
    "gn:asciiname":"Alatron",
    "gn:country_code":"GR",
    "gn:dem":540,
    "gn:feature_class":"P",
    "gn:feature_code":"PPL",
    "gn:name":"\u00c1latron",
    "gn:population":17,
    "gn:timezone":"Europe/Athens",
    "iso:country":"GR",
    "name:ell_x_preferred":[
        "\u0386\u03bb\u03b1\u03c4\u03c1\u03bf"
    ],
    "name:eng_x_preferred":[
        "Alatro"
    ],
    "name:und_x_variant":[
        "\u00c1latro",
        "Alatr\u00e1",
        "\u00c1latron",
        "Alatro"
    ],
    "wof:name":"Alatron",
    "wof:placetype":"locality",
    "wof:population":17
},
  "geometry": {"coordinates":[20.65975,38.68414],"type":"Point"}
}