{
  "type": "Feature",
  "properties": {
    "gn:admin1_code":"ESYE23",
    "gn:admin2_code":"38.0",
    "gn:admin3_code":"9130",
    "gn:asciiname":"Pyrgos",
    "gn:country_code":"GR",
    "gn:dem":674,
    "gn:feature_class":"P",
    "gn:feature_code":"PPL",
    "gn:name":"P\u00fdrgos",
    "gn:population":0,
    "gn:timezone":"Europe/Athens",
    "iso:country":"GR",
    "name:bul_x_preferred":[
        "\u041f\u0438\u0440\u0433\u043e\u0441"
    ],
    "name:ceb_x_preferred":[
        "Pyrgos"
    ],
    "name:deu_x_preferred":[
        "Pyrgos"
    ],
    "name:ell_x_preferred":[
        "P\u00fdrgos"
    ],
    "name:ell_x_variant":[
        "\u03a0\u03cd\u03c1\u03b3\u03bf\u03c2"
    ],
    "name:fin_x_preferred":[
        "P\u00fdrgos"
    ],
    "name:fra_x_preferred":[
        "Pyrgos"
    ],
    "name:kor_x_preferred":[
        "\ud53c\ub974\uace0\uc2a4"
    ],
    "name:nld_x_preferred":[
        "Pyrgos"
    ],
    "name:rus_x_preferred":[
        "\u041f\u0438\u0440\u0433\u043e\u0441"
    ],
    "name:swe_x_preferred":[
        "Pyrgos"
    ],
    "name:ukr_x_preferred":[
        "\u041f\u0456\u0440\u0433\u043e\u0441"
    ],
    "name:und_x_variant":[
        "P\u00edrgos"
    ],
    "name:vie_x_preferred":[
        "Pyrgos"
    ],
    "wof:name":"Pyrgos",
    "wof:placetype":"locality"
},
  "geometry": {"coordinates":[22.28661,38.11953],"type":"Point"}
}