{
  "type": "Feature",
  "properties": {
    "gn:admin1_code":"ESYE25",
    "gn:admin2_code":"40.0",
    "gn:admin3_code":"9255",
    "gn:asciiname":"Gamvria",
    "gn:country_code":"GR",
    "gn:dem":596,
    "gn:feature_class":"P",
    "gn:feature_code":"PPL",
    "gn:name":"Gamvri\u00e1",
    "gn:population":0,
    "gn:timezone":"Europe/Athens",
    "iso:country":"GR",
    "name:ell_x_preferred":[
        "\u0393\u03b1\u03bc\u03b2\u03c1\u03b9\u03ac"
    ],
    "name:und_x_variant":[
        "Gamoria",
        "Gambri\u00e1",
        "Gamvri\u00e1"
    ],
    "wof:name":"Gamvria",
    "wof:placetype":"locality"
},
  "geometry": {"coordinates":[21.86222,36.91918],"type":"Point"}
}