{
  "type": "Feature",
  "properties": {
    "gn:admin1_code":"ESYE23",
    "gn:admin2_code":"38.0",
    "gn:admin3_code":"9131",
    "gn:asciiname":"Poimenochori",
    "gn:country_code":"GR",
    "gn:dem":85,
    "gn:feature_class":"P",
    "gn:feature_code":"PPL",
    "gn:name":"Poimenoch\u00f3ri",
    "gn:population":0,
    "gn:timezone":"Europe/Athens",
    "iso:country":"GR",
    "name:ell_x_preferred":[
        "Poimenoch\u00f3ri"
    ],
    "name:ell_x_variant":[
        "\u03a0\u03bf\u03b9\u03bc\u03b5\u03bd\u03bf\u03c7\u03ce\u03c1\u03b9"
    ],
    "name:und_x_variant":[
        "Boudhour\u00e9\u00efka",
        "Boundoura\u00edika"
    ],
    "wof:name":"Poimenochori",
    "wof:placetype":"locality"
},
  "geometry": {"coordinates":[21.62736,38.09075],"type":"Point"}
}