{
  "type": "Feature",
  "properties": {
    "gn:admin1_code":"ESYE43",
    "gn:admin2_code":"43.0",
    "gn:admin3_code":"9321",
    "gn:asciiname":"Agios Efstratios",
    "gn:country_code":"GR",
    "gn:dem":395,
    "gn:feature_class":"P",
    "gn:feature_code":"PPL",
    "gn:name":"\u00c1gios Efstr\u00e1tios",
    "gn:population":0,
    "gn:timezone":"Europe/Athens",
    "iso:country":"GR",
    "name:ell_x_preferred":[
        "\u00c1gios Efstr\u00e1tios"
    ],
    "name:ell_x_variant":[
        "\u0386\u03b3\u03b9\u03bf\u03c2 \u0395\u03c5\u03c3\u03c4\u03c1\u03ac\u03c4\u03b9\u03bf\u03c2",
        "\u00c1yios Evstr\u00e1tios"
    ],
    "wof:name":"Agios Efstratios",
    "wof:placetype":"locality"
},
  "geometry": {"coordinates":[23.71093,35.34283],"type":"Point"}
}