{
  "type": "Feature",
  "properties": {
    "gn:admin1_code":"ESYE11",
    "gn:admin2_code":"3.0",
    "gn:admin3_code":"9016",
    "gn:asciiname":"Kalotycho",
    "gn:country_code":"GR",
    "gn:dem":488,
    "gn:feature_class":"P",
    "gn:feature_code":"PPL",
    "gn:name":"Kal\u00f3tycho",
    "gn:population":0,
    "gn:timezone":"Europe/Athens",
    "iso:country":"GR",
    "name:ell_x_preferred":[
        "Kal\u00f3tycho"
    ],
    "name:ell_x_variant":[
        "\u039a\u03b1\u03bb\u03cc\u03c4\u03c5\u03c7\u03bf",
        "Kal\u00f3tikhon",
        "Kal\u00f3tychon",
        "\u039a\u03b1\u03bb\u03cc\u03c4\u03c5\u03c7\u03bf\u03bd"
    ],
    "wof:name":"Kalotycho",
    "wof:placetype":"locality"
},
  "geometry": {"coordinates":[25.18375,41.28769000000001],"type":"Point"}
}