{
  "type": "Feature",
  "properties": {
    "gn:admin1_code":"ESYE23",
    "gn:admin2_code":"38.0",
    "gn:admin3_code":"9131",
    "gn:asciiname":"Flokas",
    "gn:country_code":"GR",
    "gn:dem":398,
    "gn:feature_class":"P",
    "gn:feature_code":"PPL",
    "gn:name":"Fl\u00f3kas",
    "gn:population":0,
    "gn:timezone":"Europe/Athens",
    "iso:country":"GR",
    "name:ell_x_preferred":[
        "\u03a6\u03bb\u03cc\u03ba\u03b1\u03c2"
    ],
    "name:und_x_variant":[
        "Fioka",
        "Fl\u00f3ka",
        "Fl\u00f3kas"
    ],
    "wof:name":"Flokas",
    "wof:placetype":"locality"
},
  "geometry": {"coordinates":[21.6375,38.02908],"type":"Point"}
}