{
  "type": "Feature",
  "properties": {
    "iso:country":"GR",
    "name:deu_x_preferred":[
        "Vai"
    ],
    "name:fra_x_preferred":[
        "Vai"
    ],
    "name:hun_x_preferred":[
        "Vai"
    ],
    "name:pol_x_preferred":[
        "Vai"
    ],
    "name:rus_x_preferred":[
        "\u0412\u0430\u0438"
    ],
    "name:slk_x_preferred":[
        "Vai"
    ],
    "qs_pg:aaroncc":"GR",
    "qs_pg:name":"Vai",
    "qs_pg:name_adm0":"\u0395\u03bb\u03bb\u03ac\u03b4\u03b1",
    "qs_pg:name_adm1":"Crete",
    "qs_pg:photos":120,
    "qs_pg:photos_1k":24,
    "qs_pg:photos_9k":1,
    "qs_pg:photos_9r":3,
    "qs_pg:photos_all":120,
    "qs_pg:photos_sr":3,
    "qs_pg:pop_sr":0,
    "qs_pg:qs_pg_placetype":"locality",
    "qs_pg:qs_pg_placetype_gp":"Town",
    "qs_pg:woe_adm0":23424833,
    "woe:adm0_id":23424833,
    "woe:name_adm0":"\u0395\u03bb\u03bb\u03ac\u03b4\u03b1",
    "woe:name_adm1":"Crete",
    "woe:placetype":"Town",
    "wof:name":"Vai",
    "wof:placetype":"locality"
},
  "geometry": {"coordinates":[26.264533,35.253846],"type":"Point"}
}