{
  "type": "Feature",
  "properties": {
    "iso:country":"GR",
    "name:ara_x_preferred":[
        "\u0644\u0627\u0631\u062f\u0648\u0633\u060c \u062f\u0648\u062f\u064a\u0643\u0627\u0646\u064a\u0633\u0648\u0633"
    ],
    "name:dut_x_preferred":[
        "Lardos"
    ],
    "name:eng_x_preferred":[
        "Lardos"
    ],
    "name:fin_x_preferred":[
        "L\u00e1rdos"
    ],
    "name:ger_x_preferred":[
        "Lardos"
    ],
    "name:gre_x_preferred":[
        "\u039b\u03ac\u03c1\u03b4\u03bf\u03c2 \u03a1\u03cc\u03b4\u03bf\u03c5"
    ],
    "name:swe_x_preferred":[
        "Lardos"
    ],
    "qs_pg:aaroncc":"GR",
    "qs_pg:name":"Lardhos",
    "qs_pg:name_adm0":"\u0395\u03bb\u03bb\u03ac\u03b4\u03b1",
    "qs_pg:name_adm1":"Aegean",
    "qs_pg:photos":329,
    "qs_pg:photos_1k":67,
    "qs_pg:photos_9k":1,
    "qs_pg:photos_9r":5,
    "qs_pg:photos_all":329,
    "qs_pg:photos_sr":5,
    "qs_pg:pop_sr":0,
    "qs_pg:qs_pg_placetype":"locality",
    "qs_pg:qs_pg_placetype_gp":"Town",
    "qs_pg:woe_adm0":23424833,
    "woe:adm0_id":23424833,
    "woe:name_adm0":"\u0395\u03bb\u03bb\u03ac\u03b4\u03b1",
    "woe:name_adm1":"Aegean",
    "woe:placetype":"Town",
    "wof:name":"Lardhos",
    "wof:placetype":"locality"
},
  "geometry": {"coordinates":[28.01928,36.077199],"type":"Point"}
}