{
  "type": "Feature",
  "properties": {
    "gn:admin1_code":"ESYE25",
    "gn:admin2_code":"42.0",
    "gn:admin3_code":"9248",
    "gn:asciiname":"Sidirokastro",
    "gn:country_code":"GR",
    "gn:dem":529,
    "gn:feature_class":"P",
    "gn:feature_code":"PPL",
    "gn:name":"Sidir\u00f3kastro",
    "gn:population":0,
    "gn:timezone":"Europe/Athens",
    "iso:country":"GR",
    "name:ara_x_preferred":[
        "\u0633\u064a\u062f\u064a\u0631\u0648\u0643\u0627\u0633\u062a\u0631\u0648"
    ],
    "name:bul_x_preferred":[
        "\u0412\u0430\u043b\u043e\u0432\u0438\u0449\u0430"
    ],
    "name:ceb_x_preferred":[
        "Sidir\u00f3kastro"
    ],
    "name:chu_x_preferred":[
        "\u0412\u0430\u043b\u043e\u0432\u0438\u0449\u0454"
    ],
    "name:deu_x_preferred":[
        "Sidirokastro"
    ],
    "name:ell_x_preferred":[
        "Sidir\u00f3kastro"
    ],
    "name:ell_x_variant":[
        "\u03a3\u03b9\u03b4\u03b7\u03c1\u03cc\u03ba\u03b1\u03c3\u03c4\u03c1\u03bf",
        "Sidir\u00f3kastron",
        "\u03a3\u03b9\u03b4\u03b7\u03c1\u03cc\u03ba\u03b1\u03c3\u03c4\u03c1\u03bf\u03bd",
        "\u03a3\u03b9\u03b4\u03b7\u03c1\u03cc\u03ba\u03b1\u03c3\u03c4\u03c1\u03bf \u03a3\u03b5\u03c1\u03c1\u03ce\u03bd"
    ],
    "name:epo_x_preferred":[
        "Sidirokastro"
    ],
    "name:fin_x_preferred":[
        "Sidir\u00f3kastro"
    ],
    "name:fra_x_preferred":[
        "Sidir\u00f3kastro"
    ],
    "name:ita_x_preferred":[
        "Sidirokastro"
    ],
    "name:mkd_x_preferred":[
        "\u0412\u0430\u043b\u043e\u0432\u0438\u0448\u0442\u0430"
    ],
    "name:nno_x_preferred":[
        "Sidir\u00f3kastro"
    ],
    "name:spa_x_preferred":[
        "Sidir\u00f3kastro"
    ],
    "name:sqi_x_preferred":[
        "Demirhisari"
    ],
    "name:srp_x_preferred":[
        "\u0412\u0430\u043b\u043e\u0432\u0438\u0448\u0442\u0435"
    ],
    "name:swe_x_preferred":[
        "Sidir\u00f3kastro"
    ],
    "name:tur_x_preferred":[
        "Sidirokastro"
    ],
    "name:und_x_variant":[
        "Sidhir\u00f3kastron"
    ],
    "wof:name":"Sidirokastro",
    "wof:placetype":"locality"
},
  "geometry": {"coordinates":[22.42212,36.77078],"type":"Point"}
}