{
  "type": "Feature",
  "properties": {
    "gn:gn_country":"GR",
    "gn:gn_fcode":"PPL",
    "gn:gn_pop":684,
    "gn:population":684,
    "iso:country":"GR",
    "name:ell_x_preferred":[
        "\u039c\u03ac\u03bd\u03b4\u03c1\u03b5\u03c2"
    ],
    "name:ell_x_variant":[
        "\u039c\u03ac\u03bd\u03b4\u03c1\u03b1\u03b9"
    ],
    "name:unk_x_variant":[
        "Ab\u00e1r K\u00f3\u00ef"
    ],
    "qs_pg:aaroncc":"GR",
    "qs_pg:gn_country":"GR",
    "qs_pg:gn_fcode":"PPL",
    "qs_pg:gn_pop":684,
    "qs_pg:name":"M\u00e1ndrai",
    "qs_pg:photos_9r":0,
    "qs_pg:photos_sr":0,
    "qs_pg:pop_sr":2,
    "qs_pg:qs_pg_placetype":"locality",
    "wof:name":"M\u00e1ndrai",
    "wof:placetype":"locality",
    "wof:population":684
},
  "geometry": {"coordinates":[22.90472,40.86806],"type":"Point"}
}