{
  "type": "Feature",
  "properties": {
    "gn:admin1_code":"ESYE42",
    "gn:admin2_code":"49.0",
    "gn:admin3_code":"9270",
    "gn:asciiname":"Kontochori",
    "gn:country_code":"GR",
    "gn:dem":199,
    "gn:feature_class":"P",
    "gn:feature_code":"PPL",
    "gn:name":"Kontoch\u00f3ri",
    "gn:population":0,
    "gn:timezone":"Europe/Athens",
    "iso:country":"GR",
    "name:und_x_variant":[
        "Kontoch\u00f3ri",
        "\u039a\u03bf\u03bd\u03c4\u03bf\u03c7\u03ce\u03c1\u03b9",
        "Kodochori"
    ],
    "wof:name":"Kontochori",
    "wof:placetype":"locality"
},
  "geometry": {"coordinates":[25.43324,36.42447],"type":"Point"}
}