{
  "type": "Feature",
  "properties": {
    "gn:admin1_code":"ESYE24",
    "gn:admin2_code":"29.0",
    "gn:admin3_code":"9160",
    "gn:asciiname":"Vasilika",
    "gn:country_code":"GR",
    "gn:dem":126,
    "gn:feature_class":"P",
    "gn:feature_code":"PPL",
    "gn:name":"Vasilik\u00e1",
    "gn:population":182,
    "gn:timezone":"Europe/Athens",
    "iso:country":"GR",
    "name:ell_x_preferred":[
        "\u0392\u03b1\u03c3\u03b9\u03bb\u03b9\u03ba\u03ac"
    ],
    "name:eng_x_preferred":[
        "Vasilika"
    ],
    "wof:name":"Vasilika",
    "wof:placetype":"locality",
    "wof:population":182
},
  "geometry": {"coordinates":[22.21178,38.89584],"type":"Point"}
}