{
  "type": "Feature",
  "properties": {
    "gn:gn_country":"GR",
    "gn:gn_fcode":"PPL",
    "gn:gn_pop":560,
    "gn:population":560,
    "iso:country":"GR",
    "name:ell_x_preferred":[
        "\u03a6\u03bb\u03b1\u03bc\u03bf\u03cd\u03bb\u03b9"
    ],
    "name:ell_x_variant":[
        "\u03a6\u03bb\u03b1\u03bc\u03bf\u03cd\u03bb\u03b9\u03bf\u03bd"
    ],
    "name:unk_x_variant":[
        "Flamo\u00farion"
    ],
    "qs_pg:aaroncc":"GR",
    "qs_pg:gn_country":"GR",
    "qs_pg:gn_fcode":"PPL",
    "qs_pg:gn_pop":560,
    "qs_pg:name":"Flamo\u00falion",
    "qs_pg:photos_9r":0,
    "qs_pg:photos_sr":0,
    "qs_pg:pop_sr":2,
    "qs_pg:qs_pg_placetype":"locality",
    "wof:name":"Flamo\u00falion",
    "wof:placetype":"locality",
    "wof:population":560
},
  "geometry": {"coordinates":[21.765,39.52611],"type":"Point"}
}