{
  "type": "Feature",
  "properties": {
    "gn:admin1_code":"ESYE42",
    "gn:admin2_code":"49.0",
    "gn:admin3_code":"9292.0",
    "gn:asciiname":"Charavgi",
    "gn:country_code":"GR",
    "gn:dem":150,
    "gn:feature_class":"P",
    "gn:feature_code":"PPL",
    "gn:name":"Charavg\u00ed",
    "gn:population":2,
    "gn:timezone":"Europe/Athens",
    "iso:country":"GR",
    "name:ell_x_preferred":[
        "\u03a7\u03b1\u03c1\u03b1\u03c5\u03b3\u03ae"
    ],
    "name:eng_x_preferred":[
        "Charavgi"
    ],
    "wof:name":"Charavgi",
    "wof:placetype":"locality",
    "wof:population":2
},
  "geometry": {"coordinates":[25.81325,37.09748],"type":"Point"}
}