{
  "type": "Feature",
  "properties": {
    "gn:gn_country":"GR",
    "gn:gn_fcode":"PPL",
    "gn:gn_pop":304,
    "gn:population":261,
    "iso:country":"GR",
    "name:bul_x_preferred":[
        "\u0426\u0435\u043f\u0435\u043b\u043e\u0432\u043e"
    ],
    "name:ell_x_preferred":[
        "\u03a4\u03c3\u03b5\u03c0\u03ad\u03bb\u03bf\u03b2\u03bf"
    ],
    "name:ell_x_variant":[
        "\u03a4\u03c3\u03b5\u03c0\u03ad\u03bb\u03bf\u03b2\u03bf\u03bd",
        "\u03a4\u03c3\u03b5\u03c0\u03ad\u03bb\u03bf\u03b2\u03bf \u0399\u03c9\u03b1\u03bd\u03bd\u03af\u03bd\u03c9\u03bd"
    ],
    "name:eng_x_preferred":[
        "Tsepelovo"
    ],
    "name:nld_x_preferred":[
        "Tsepelovo"
    ],
    "name:nno_x_preferred":[
        "Tsep\u00e9lovo"
    ],
    "name:swe_x_preferred":[
        "Tsep\u00e9lovo"
    ],
    "name:unk_x_variant":[
        "Tsep\u00e9lovo"
    ],
    "qs_pg:aaroncc":"GR",
    "qs_pg:gn_country":"GR",
    "qs_pg:gn_fcode":"PPL",
    "qs_pg:gn_pop":304,
    "qs_pg:name":"Tsepelovon",
    "qs_pg:name_adm0":"\u0395\u03bb\u03bb\u03ac\u03b4\u03b1",
    "qs_pg:name_adm1":"Epirus and Western Macedonia",
    "qs_pg:photos":9,
    "qs_pg:photos_1k":2,
    "qs_pg:photos_9k":1,
    "qs_pg:photos_9r":1,
    "qs_pg:photos_all":9,
    "qs_pg:photos_sr":1,
    "qs_pg:pop_sr":2,
    "qs_pg:qs_pg_placetype":"locality",
    "qs_pg:qs_pg_placetype_gp":"Town",
    "qs_pg:woe_adm0":23424833,
    "woe:adm0_id":23424833,
    "woe:name_adm0":"\u0395\u03bb\u03bb\u03ac\u03b4\u03b1",
    "woe:name_adm1":"Epirus and Western Macedonia",
    "woe:placetype":"Town",
    "wof:name":"Tsepelovon",
    "wof:placetype":"locality",
    "wof:population":261
},
  "geometry": {"coordinates":[20.82028,39.90611],"type":"Point"}
}