{
  "type": "Feature",
  "properties": {
    "gn:gn_country":"GR",
    "gn:gn_fcode":"PPL",
    "gn:gn_pop":0,
    "gn:population":349,
    "iso:country":"GR",
    "name:ell_x_preferred":[
        "\u03a3\u03ba\u03ac\u03bb\u03b1 \u0395\u03c1\u03b5\u03c3\u03bf\u03cd"
    ],
    "name:ell_x_variant":[
        "\u0393\u03c5\u03b1\u03bb\u03cc\u03c2",
        "\u03a3\u03ba\u03ac\u03bb\u03b1 \u0395\u03c1\u03b5\u03c3\u03bf\u03cd \u039b\u03ad\u03c3\u03b2\u03bf\u03c5"
    ],
    "name:eng_x_preferred":[
        "Skala Eresou"
    ],
    "name:fin_x_preferred":[
        "Sk\u00e1la Ereso\u00fa"
    ],
    "name:lat_x_preferred":[
        "Scala Eresi"
    ],
    "name:nld_x_preferred":[
        "Skala Eresou"
    ],
    "name:rus_x_preferred":[
        "\u0421\u043a\u0430\u043b\u0430-\u042d\u0440\u0435\u0441\u0443"
    ],
    "name:swe_x_preferred":[
        "Sk\u00e1la Ereso\u00fa"
    ],
    "name:unk_x_variant":[
        "Sk\u00e1la Eresso\u00fa"
    ],
    "qs_pg:aaroncc":"GR",
    "qs_pg:gn_country":"GR",
    "qs_pg:gn_fcode":"PPL",
    "qs_pg:gn_pop":0,
    "qs_pg:name":"Skala Eresou",
    "qs_pg:name_adm0":"\u0395\u03bb\u03bb\u03ac\u03b4\u03b1",
    "qs_pg:name_adm1":"Aegean",
    "qs_pg:photos":291,
    "qs_pg:photos_1k":59,
    "qs_pg:photos_9k":1,
    "qs_pg:photos_9r":4,
    "qs_pg:photos_all":291,
    "qs_pg:photos_sr":5,
    "qs_pg:pop_sr":0,
    "qs_pg:qs_pg_placetype":"locality",
    "qs_pg:qs_pg_placetype_gp":"Town",
    "qs_pg:woe_adm0":23424833,
    "woe:adm0_id":23424833,
    "woe:name_adm0":"\u0395\u03bb\u03bb\u03ac\u03b4\u03b1",
    "woe:name_adm1":"Aegean",
    "woe:placetype":"Town",
    "wof:name":"Skala Eresou",
    "wof:placetype":"locality",
    "wof:population":349
},
  "geometry": {"coordinates":[25.93333,39.13333],"type":"Point"}
}