{
  "type": "Feature",
  "properties": {
    "gn:admin1_code":"ESYE23",
    "gn:admin2_code":"38.0",
    "gn:admin3_code":"9130",
    "gn:asciiname":"Krathion",
    "gn:country_code":"GR",
    "gn:dem":5,
    "gn:feature_class":"P",
    "gn:feature_code":"PPL",
    "gn:name":"Kr\u00e1thion",
    "gn:population":0,
    "gn:timezone":"Europe/Athens",
    "iso:country":"GR",
    "name:ell_x_historical":[
        "\u03a0\u03b1\u03c1\u03b1\u03bb\u03af\u03b1 \u0391\u03ba\u03c1\u03ac\u03c4\u03b1\u03c2"
    ],
    "name:ell_x_preferred":[
        "\u039a\u03c1\u03ac\u03b8\u03b9"
    ],
    "name:ell_x_variant":[
        "\u03a0\u03b1\u03c1\u03b1\u03bb\u03af\u03b1 \u0391\u03ba\u03c1\u03ac\u03c4\u03b1\u03c2",
        "\u039a\u03c1\u03ac\u03b8\u03b9\u03bf\u03bd"
    ],
    "name:eng_x_historical":[
        "Paralia Akratas"
    ],
    "name:eng_x_preferred":[
        "Krathi"
    ],
    "name:eng_x_variant":[
        "Paralia Akratas"
    ],
    "name:und_x_variant":[
        "Paral\u00eda Akr\u00e1tas"
    ],
    "wof:name":"Krathion",
    "wof:placetype":"locality"
},
  "geometry": {"coordinates":[22.34344,38.16054000000001],"type":"Point"}
}