{
  "type": "Feature",
  "properties": {
    "gn:admin1_code":"ESYE25",
    "gn:admin2_code":"40.0",
    "gn:admin3_code":"9253",
    "gn:asciiname":"Krya Vrysi",
    "gn:country_code":"GR",
    "gn:dem":1095,
    "gn:feature_class":"P",
    "gn:feature_code":"PPL",
    "gn:name":"Krya Vrysi",
    "gn:population":8,
    "gn:timezone":"Europe/Athens",
    "iso:country":"GR",
    "name:ell_x_preferred":[
        "\u039a\u03c1\u03cd\u03b1 \u0392\u03c1\u03cd\u03c3\u03b7"
    ],
    "name:eng_x_preferred":[
        "Krya Vrysi"
    ],
    "name:und_x_variant":[
        "Kr\u00eda Vr\u00edsi"
    ],
    "wof:name":"Krya Vrysi",
    "wof:placetype":"locality",
    "wof:population":8
},
  "geometry": {"coordinates":[22.26651,37.0095],"type":"Point"}
}