{
  "type": "Feature",
  "properties": {
    "gn:country":"GR",
    "gn:fcode":"PPL",
    "gn:population":898,
    "iso:country":"GR",
    "name:ara_x_preferred":[
        "\u0623\u0648\u064a\u0646\u0648\u064a"
    ],
    "name:ceb_x_preferred":[
        "Oin\u00f3i"
    ],
    "name:ell_x_historical":[
        "\u039c\u03ac\u03b6\u03b9"
    ],
    "name:ell_x_preferred":[
        "\u039f\u03b9\u03bd\u03cc\u03b7"
    ],
    "name:ell_x_variant":[
        "\u039c\u03ac\u03b6\u03b9",
        "\u039f\u03b9\u03bd\u03cc\u03b7 \u0391\u03c4\u03c4\u03b9\u03ba\u03ae\u03c2"
    ],
    "name:eng_x_preferred":[
        "Oinoi"
    ],
    "name:fin_x_preferred":[
        "Oin\u00f3i"
    ],
    "name:fra_x_preferred":[
        "Oinoi"
    ],
    "name:ita_x_preferred":[
        "Oinoi"
    ],
    "name:nno_x_preferred":[
        "In\u00f3i"
    ],
    "name:ukr_x_preferred":[
        "\u0415\u043d\u043e\u044f"
    ],
    "name:und_x_variant":[
        "M\u00e1zi"
    ],
    "qs_pg:aaroncc":"GR",
    "qs_pg:gn_country":"GR",
    "qs_pg:gn_fcode":"PPL",
    "qs_pg:gn_pop":898,
    "qs_pg:name":"Oinoi",
    "qs_pg:name_adm0":"\u0395\u03bb\u03bb\u03ac\u03b4\u03b1",
    "qs_pg:name_adm1":"Attica",
    "qs_pg:photos_9k":1,
    "qs_pg:photos_9r":1,
    "qs_pg:photos_all":5,
    "qs_pg:photos_sr":0,
    "qs_pg:pop_sr":2,
    "qs_pg:qs_pg_placetype":"locality",
    "qs_pg:qs_pg_placetype_gp":"Town",
    "qs_pg:woe_adm0":23424833,
    "woe:adm0_id":23424833,
    "woe:name_adm0":"\u0395\u03bb\u03bb\u03ac\u03b4\u03b1",
    "woe:name_adm1":"Attica",
    "woe:placetype":"Town",
    "wof:name":"Oinoi",
    "wof:placetype":"locality",
    "wof:population":382
},
  "geometry": {"coordinates":[23.41667,38.16667],"type":"Point"}
}