{
  "type": "Feature",
  "properties": {
    "gn:country":"GR",
    "gn:fcode":"PPL",
    "gn:population":100,
    "iso:country":"GR",
    "name:ell_x_preferred":[
        "\u03a3\u03cd\u03b2\u03bf\u03c4\u03b1"
    ],
    "name:ell_x_variant":[
        "S\u00fdvota"
    ],
    "name:eng_x_preferred":[
        "Syvota"
    ],
    "name:rus_x_preferred":[
        "\u0421\u0438\u0432\u043e\u0442\u0430"
    ],
    "name:und_x_variant":[
        "S\u00edvota"
    ],
    "qs_pg:aaroncc":"GR",
    "qs_pg:gn_country":"GR",
    "qs_pg:gn_fcode":"PPL",
    "qs_pg:gn_pop":100,
    "qs_pg:name":"Sivota",
    "qs_pg:name_adm0":"\u0395\u03bb\u03bb\u03ac\u03b4\u03b1",
    "qs_pg:name_adm1":"Peloponnese Western Greece and the Ionian Islands",
    "qs_pg:photos":230,
    "qs_pg:photos_1k":47,
    "qs_pg:photos_9k":1,
    "qs_pg:photos_9r":4,
    "qs_pg:photos_all":230,
    "qs_pg:photos_sr":4,
    "qs_pg:pop_sr":1,
    "qs_pg:qs_pg_placetype":"locality",
    "qs_pg:qs_pg_placetype_gp":"Town",
    "qs_pg:woe_adm0":23424833,
    "woe:adm0_id":23424833,
    "woe:name_adm0":"\u0395\u03bb\u03bb\u03ac\u03b4\u03b1",
    "woe:name_adm1":"Peloponnese Western Greece and the Ionian Islands",
    "woe:placetype":"Town",
    "wof:name":"Sivota",
    "wof:placetype":"locality",
    "wof:population":100
},
  "geometry": {"coordinates":[20.68333,38.61667],"type":"Point"}
}