{
  "type": "Feature",
  "properties": {
    "gn:country":"GR",
    "gn:fcode":"PPL",
    "gn:population":2560,
    "iso:country":"GR",
    "name:bul_x_preferred":[
        "\u041a\u0435\u0448\u0438\u0448\u043b\u044a\u043a"
    ],
    "name:bul_x_variant":[
        "\u041d\u0435\u043e\u0441 \u0421\u043a\u043e\u043f\u043e\u0441"
    ],
    "name:ell_x_preferred":[
        "\u039d\u03ad\u03bf\u03c2 \u03a3\u03ba\u03bf\u03c0\u03cc\u03c2"
    ],
    "name:ell_x_variant":[
        "\u039d\u03b5\u03cc\u03c2 \u03a3\u03ba\u03bf\u03c0\u03cc\u03c2"
    ],
    "name:eng_x_preferred":[
        "Neos Skopos"
    ],
    "name:nno_x_preferred":[
        "N\u00e9os Skop\u00f3s"
    ],
    "name:und_x_variant":[
        "Toumb\u00edsta"
    ],
    "qs_pg:aaroncc":"GR",
    "qs_pg:gn_country":"GR",
    "qs_pg:gn_fcode":"PPL",
    "qs_pg:gn_pop":2560,
    "qs_pg:name":"Neos Skopos",
    "qs_pg:name_adm0":"\u0395\u03bb\u03bb\u03ac\u03b4\u03b1",
    "qs_pg:name_adm1":"Macedonia and Thrace",
    "qs_pg:photos_9r":0,
    "qs_pg:photos_sr":0,
    "qs_pg:pop_sr":4,
    "qs_pg:qs_pg_placetype":"locality",
    "qs_pg:qs_pg_placetype_gp":"Town",
    "qs_pg:woe_adm0":23424833,
    "woe:adm0_id":23424833,
    "woe:name_adm0":"\u0395\u03bb\u03bb\u03ac\u03b4\u03b1",
    "woe:name_adm1":"Macedonia and Thrace",
    "woe:placetype":"Town",
    "wof:name":"Neos Skopos",
    "wof:placetype":"locality",
    "wof:population":1934
},
  "geometry": {"coordinates":[23.61667,41.01667],"type":"Point"}
}