{
  "type": "Feature",
  "properties": {
    "gn:admin1_code":"ESYE11",
    "gn:admin2_code":"1.0",
    "gn:admin3_code":"9006",
    "gn:asciiname":"Apalos",
    "gn:country_code":"GR",
    "gn:dem":9,
    "gn:feature_class":"P",
    "gn:feature_code":"PPL",
    "gn:name":"Apal\u00f3s",
    "gn:population":0,
    "gn:timezone":"Europe/Athens",
    "iso:country":"GR",
    "name:ell_x_preferred":[
        "\u0391\u03c0\u03b1\u03bb\u03cc\u03c2"
    ],
    "name:und_x_variant":[
        "Ombal\u00e1r",
        "Apal\u00f3s"
    ],
    "wof:name":"Apalos",
    "wof:placetype":"locality"
},
  "geometry": {"coordinates":[25.93505,40.85759],"type":"Point"}
}