{
  "type": "Feature",
  "properties": {
    "gn:admin1_code":"ESYE11",
    "gn:admin2_code":"1.0",
    "gn:admin3_code":"9006",
    "gn:asciiname":"Mesimvria",
    "gn:country_code":"GR",
    "gn:dem":57,
    "gn:feature_class":"P",
    "gn:feature_code":"PPL",
    "gn:name":"Mesimvr\u00eda",
    "gn:population":0,
    "gn:timezone":"Europe/Athens",
    "iso:country":"GR",
    "name:ell_x_preferred":[
        "Mesimvr\u00eda"
    ],
    "name:ell_x_variant":[
        "\u039c\u03b5\u03c3\u03b7\u03bc\u03b2\u03c1\u03af\u03b1"
    ],
    "wof:name":"Mesimvria",
    "wof:placetype":"locality"
},
  "geometry": {"coordinates":[25.67652,40.86764],"type":"Point"}
}