{
  "type": "Feature",
  "properties": {
    "gn:gn_country":"GR",
    "gn:gn_fcode":"PPL",
    "gn:gn_pop":504,
    "gn:population":504,
    "iso:country":"GR",
    "name:ell_x_preferred":[
        "\u039d\u03ad\u03b1 \u03a4\u03c1\u03b1\u03c0\u03b5\u03b6\u03bf\u03cd\u03bd\u03c4\u03b1"
    ],
    "name:unk_x_variant":[
        "Agios Ioanis Ofis"
    ],
    "qs_pg:aaroncc":"GR",
    "qs_pg:gn_country":"GR",
    "qs_pg:gn_fcode":"PPL",
    "qs_pg:gn_pop":504,
    "qs_pg:name":"N\u00e9a Trapezo\u00fas",
    "qs_pg:photos_9r":0,
    "qs_pg:photos_sr":0,
    "qs_pg:pop_sr":2,
    "qs_pg:qs_pg_placetype":"locality",
    "wof:name":"N\u00e9a Trapezo\u00fas",
    "wof:placetype":"locality",
    "wof:population":504
},
  "geometry": {"coordinates":[22.52556,40.33472],"type":"Point"}
}