{
  "type": "Feature",
  "properties": {
    "gn:admin1_code":"ESYE23",
    "gn:admin2_code":"38.0",
    "gn:admin3_code":"9133.0",
    "gn:asciiname":"Ano Psofida",
    "gn:country_code":"GR",
    "gn:dem":592,
    "gn:feature_class":"P",
    "gn:feature_code":"PPL",
    "gn:name":"Ano Psofida",
    "gn:population":0,
    "gn:timezone":"Europe/Athens",
    "iso:country":"GR",
    "name:ell_x_historical":[
        "\u0386\u03bd\u03c9 \u03a8\u03c9\u03c6\u03af\u03c2"
    ],
    "name:ell_x_preferred":[
        "\u0386\u03bd\u03c9 \u03a8\u03c9\u03c6\u03af\u03b4\u03b1"
    ],
    "name:ell_x_variant":[
        "\u0386\u03bd\u03c9 \u03a8\u03c9\u03c6\u03af\u03c2"
    ],
    "wof:name":"Ano Psofida",
    "wof:placetype":"locality"
},
  "geometry": {"coordinates":[21.88996,37.87595],"type":"Point"}
}