{
  "type": "Feature",
  "properties": {
    "gn:admin1_code":"ESYE25",
    "gn:admin2_code":"37.0",
    "gn:admin3_code":"9243",
    "gn:asciiname":"Ayia Paraskevi",
    "gn:country_code":"GR",
    "gn:dem":64,
    "gn:feature_class":"P",
    "gn:feature_code":"PPL",
    "gn:name":"Ay\u00eda Paraskev\u00ed",
    "gn:population":68,
    "gn:timezone":"Europe/Athens",
    "iso:country":"GR",
    "name:ell_x_preferred":[
        "\u0391\u03b3\u03af\u03b1 \u03a0\u03b1\u03c1\u03b1\u03c3\u03ba\u03b5\u03c5\u03ae"
    ],
    "name:eng_x_preferred":[
        "Agia Paraskevi"
    ],
    "name:und_x_variant":[
        "Ayia Paraskevi"
    ],
    "wof:name":"Ayia Paraskevi",
    "wof:placetype":"locality",
    "wof:population":68
},
  "geometry": {"coordinates":[22.97587,37.87811],"type":"Point"}
}