{
  "type": "Feature",
  "properties": {
    "gn:gn_country":"GR",
    "gn:gn_fcode":"PPL",
    "gn:gn_pop":191,
    "gn:population":191,
    "iso:country":"GR",
    "name:ell_x_preferred":[
        "P\u00e9tra"
    ],
    "name:ell_x_variant":[
        "\u03a0\u03ad\u03c4\u03c1\u03b1"
    ],
    "qs_pg:aaroncc":"GR",
    "qs_pg:gn_country":"GR",
    "qs_pg:gn_fcode":"PPL",
    "qs_pg:gn_pop":191,
    "qs_pg:name":"P\u00e9tra",
    "qs_pg:photos_9r":0,
    "qs_pg:photos_sr":0,
    "qs_pg:pop_sr":1,
    "qs_pg:qs_pg_placetype":"locality",
    "wof:name":"P\u00e9tra",
    "wof:placetype":"locality",
    "wof:population":191
},
  "geometry": {"coordinates":[21.2575,39.13194],"type":"Point"}
}