{
  "type": "Feature",
  "properties": {
    "gn:admin1_code":"ESYE13",
    "gn:admin2_code":"11.0",
    "gn:admin3_code":"9067",
    "gn:asciiname":"Kryovrysi",
    "gn:country_code":"GR",
    "gn:dem":698,
    "gn:feature_class":"P",
    "gn:feature_code":"PPL",
    "gn:name":"Kry\u00f3vrysi",
    "gn:population":0,
    "gn:timezone":"Europe/Athens",
    "iso:country":"GR",
    "name:ell_x_preferred":[
        "Kry\u00f3vrysi"
    ],
    "name:ell_x_variant":[
        "\u039a\u03c1\u03c5\u03cc\u03b2\u03c1\u03c5\u03c3\u03b7"
    ],
    "name:und_x_variant":[
        "Rad\u00fanista",
        "Kri\u00f3vrisi"
    ],
    "wof:name":"Kryovrysi",
    "wof:placetype":"locality"
},
  "geometry": {"coordinates":[21.59717,40.48437],"type":"Point"}
}