{
  "type": "Feature",
  "properties": {
    "gn:population":1412,
    "iso:country":"GR",
    "name:ara_x_preferred":[
        "\u0623\u0631\u062a\u064a\u0633\u064a\u0627\u0646\u0648\u0646\u060c \u0643\u0627\u0631\u062f\u064a\u062a\u0633\u0627"
    ],
    "name:ara_x_variant":[
        "\u0623\u0631\u062a\u064a\u0633\u064a\u0627\u0646\u0648\u0646"
    ],
    "name:arz_x_preferred":[
        "\u0627\u0631\u062a\u064a\u0633\u064a\u0627\u0646\u0648"
    ],
    "name:bul_x_preferred":[
        "\u0410\u0440\u0442\u0435\u0441\u0438\u0430\u043d\u043e"
    ],
    "name:ceb_x_preferred":[
        "Artesian\u00f3"
    ],
    "name:ell_x_preferred":[
        "\u0391\u03c1\u03c4\u03b5\u03c3\u03b9\u03b1\u03bd\u03cc\u03bd"
    ],
    "name:ell_x_variant":[
        "\u0391\u03c1\u03c4\u03b5\u03c3\u03b9\u03b1\u03bd\u03cc",
        "\u0391\u03c1\u03c4\u03b5\u03c3\u03b9\u03b1\u03bd\u03cc \u039a\u03b1\u03c1\u03b4\u03af\u03c4\u03c3\u03b1\u03c2"
    ],
    "name:eng_x_preferred":[
        "Artesiano"
    ],
    "name:rus_x_preferred":[
        "\u0410\u0440\u0442\u0435\u0441\u0438\u0430\u043d\u043e\u043d"
    ],
    "name:swe_x_preferred":[
        "Artesian\u00f3"
    ],
    "name:und_x_variant":[
        "Pits\u00e1ri"
    ],
    "qs:a0":"Greece",
    "qs:a1":"*\u0398\u0395\u03a3\u03a3\u0391\u039b\u0399\u0391",
    "qs:a1_alt":"UESSALIA",
    "qs:a1r":"0",
    "qs:a2_alt":"KARDITSA",
    "qs:adm0":"Greece",
    "qs:la_lc":"*",
    "qs:level":"locality",
    "qs:loc":"\u0391\u03a1\u03a4\u0395\u03a3\u0399\u0391\u039d\u039f\u039d",
    "qs:loc_alt":"ARTESIANON",
    "qs:pop":0,
    "qs:type":"buffered point",
    "wof:name":"\u0391\u03a1\u03a4\u0395\u03a3\u0399\u0391\u039d\u039f\u039d",
    "wof:placetype":"locality",
    "wof:population":1412
},
  "geometry": {"coordinates":[21.896097,39.402984],"type":"Point"}
}