{
  "type": "Feature",
  "properties": {
    "gn:admin1_code":"ESYE23",
    "gn:admin2_code":"38.0",
    "gn:admin3_code":"9133",
    "gn:asciiname":"Vrachni",
    "gn:country_code":"GR",
    "gn:dem":1102,
    "gn:feature_class":"P",
    "gn:feature_code":"PPL",
    "gn:name":"Vrachn\u00ed",
    "gn:population":0,
    "gn:timezone":"Europe/Athens",
    "iso:country":"GR",
    "name:ell_x_preferred":[
        "Vrachn\u00ed"
    ],
    "name:ell_x_variant":[
        "\u0392\u03c1\u03b1\u03c7\u03bd\u03af",
        "Vrachn\u00edon",
        "\u0392\u03c1\u03b1\u03c7\u03bd\u03af\u03bf\u03bd"
    ],
    "name:und_x_variant":[
        "Vrakhn\u00ed",
        "Vrakn\u00edon"
    ],
    "wof:name":"Vrachni",
    "wof:placetype":"locality"
},
  "geometry": {"coordinates":[22.17328,38.03697],"type":"Point"}
}