{
  "type": "Feature",
  "properties": {
    "gn:country":"GR",
    "gn:fcode":"PPL",
    "gn:population":1528,
    "iso:country":"GR",
    "name:ara_x_preferred":[
        "\u063a\u0631\u064a\u0632\u0627\u0646\u0648"
    ],
    "name:bul_x_preferred":[
        "\u0413\u0440\u0438\u0437\u0430\u043d\u043e"
    ],
    "name:ceb_x_preferred":[
        "Griz\u00e1no"
    ],
    "name:ell_x_preferred":[
        "Griz\u00e1no"
    ],
    "name:ell_x_variant":[
        "\u0393\u03c1\u03b9\u03b6\u03ac\u03bd\u03bf",
        "\u0393\u03c1\u03b9\u03b6\u03ac\u03bd\u03bf\u03bd",
        "\u0393\u03c1\u03b9\u03b6\u03ac\u03bd\u03bf \u03a4\u03c1\u03b9\u03ba\u03ac\u03bb\u03c9\u03bd"
    ],
    "name:eng_x_preferred":[
        "Grizano"
    ],
    "name:swe_x_preferred":[
        "Griz\u00e1no"
    ],
    "name:und_x_variant":[
        "Gr\u00edtzanon"
    ],
    "qs_pg:aaroncc":"GR",
    "qs_pg:gn_country":"GR",
    "qs_pg:gn_fcode":"PPL",
    "qs_pg:gn_pop":1528,
    "qs_pg:name":"Grizanon",
    "qs_pg:name_adm0":"\u0395\u03bb\u03bb\u03ac\u03b4\u03b1",
    "qs_pg:name_adm1":"Thessaly and Continental Greece",
    "qs_pg:photos_9r":0,
    "qs_pg:photos_sr":0,
    "qs_pg:pop_sr":3,
    "qs_pg:qs_pg_placetype":"locality",
    "qs_pg:qs_pg_placetype_gp":"Town",
    "qs_pg:woe_adm0":23424833,
    "woe:adm0_id":23424833,
    "woe:name_adm0":"\u0395\u03bb\u03bb\u03ac\u03b4\u03b1",
    "woe:name_adm1":"Thessaly and Continental Greece",
    "woe:placetype":"Town",
    "wof:name":"Grizanon",
    "wof:placetype":"locality",
    "wof:population":1528
},
  "geometry": {"coordinates":[22.05,39.63333],"type":"Point"}
}