{
  "type": "Feature",
  "properties": {
    "gn:gn_country":"GR",
    "gn:gn_fcode":"PPL",
    "gn:gn_pop":0,
    "iso:country":"GR",
    "name:ell_x_preferred":[
        "\u0395\u03c0\u03b9\u03c3\u03ba\u03bf\u03c0\u03ae \u0393\u03c9\u03bd\u03b9\u03ac\u03c2 \u0398\u03ae\u03c1\u03b1\u03c2"
    ],
    "name:eng_x_preferred":[
        "Episkopi Gonias"
    ],
    "name:fin_x_preferred":[
        "Episkop\u00ed Goni\u00e1s"
    ],
    "name:rus_x_preferred":[
        "\u042d\u043f\u0438\u0441\u043a\u043e\u043f\u0438-\u0413\u043e\u043d\u044c\u044f\u0441"
    ],
    "name:unk_x_variant":[
        "M\u00e9sa Goni\u00e1"
    ],
    "qs_pg:aaroncc":"GR",
    "qs_pg:gn_country":"GR",
    "qs_pg:gn_fcode":"PPL",
    "qs_pg:gn_pop":0,
    "qs_pg:name":"Episkopi Gonias",
    "qs_pg:name_adm0":"\u0395\u03bb\u03bb\u03ac\u03b4\u03b1",
    "qs_pg:name_adm1":"Aegean",
    "qs_pg:photos":72,
    "qs_pg:photos_1k":15,
    "qs_pg:photos_9k":1,
    "qs_pg:photos_9r":2,
    "qs_pg:photos_all":72,
    "qs_pg:photos_sr":2,
    "qs_pg:pop_sr":0,
    "qs_pg:qs_pg_placetype":"locality",
    "qs_pg:qs_pg_placetype_gp":"Town",
    "qs_pg:woe_adm0":23424833,
    "woe:adm0_id":23424833,
    "woe:name_adm0":"\u0395\u03bb\u03bb\u03ac\u03b4\u03b1",
    "woe:name_adm1":"Aegean",
    "woe:placetype":"Town",
    "wof:name":"Episkopi Gonias",
    "wof:placetype":"locality"
},
  "geometry": {"coordinates":[25.45878,36.38353],"type":"Point"}
}