{
  "type": "Feature",
  "properties": {
    "gn:admin1_code":"ESYE22",
    "gn:admin2_code":"28.0",
    "gn:admin3_code":"9116",
    "gn:asciiname":"Alonia",
    "gn:country_code":"GR",
    "gn:dem":16,
    "gn:feature_class":"P",
    "gn:feature_code":"PPL",
    "gn:name":"Al\u00f3nia",
    "gn:population":526,
    "gn:timezone":"Europe/Athens",
    "iso:country":"GR",
    "name:ell_x_preferred":[
        "\u0391\u03bb\u03ce\u03bd\u03b9\u03b1"
    ],
    "name:eng_x_preferred":[
        "Alonia"
    ],
    "wof:name":"Alonia",
    "wof:placetype":"locality",
    "wof:population":526
},
  "geometry": {"coordinates":[20.79854,37.8265],"type":"Point"}
}