{
  "type": "Feature",
  "properties": {
    "gn:admin1_code":"ESYE25",
    "gn:admin2_code":"42.0",
    "gn:admin3_code":"9252",
    "gn:asciiname":"Zaganon",
    "gn:country_code":"GR",
    "gn:dem":168,
    "gn:feature_class":"P",
    "gn:feature_code":"PPL",
    "gn:name":"Zag\u00e1non",
    "gn:population":0,
    "gn:timezone":"Europe/Athens",
    "iso:country":"GR",
    "name:ell_x_preferred":[
        "\u0396\u03b1\u03b3\u03ac\u03bd\u03bf"
    ],
    "wof:name":"Zaganon",
    "wof:placetype":"locality"
},
  "geometry": {"coordinates":[22.46723,37.04069000000001],"type":"Point"}
}