{
  "type": "Feature",
  "properties": {
    "gn:admin1_code":"ESYE24",
    "gn:admin2_code":"34.0",
    "gn:admin3_code":"9150",
    "gn:asciiname":"Agios Georgios Gialtron",
    "gn:country_code":"GR",
    "gn:dem":2,
    "gn:feature_class":"P",
    "gn:feature_code":"PPL",
    "gn:name":"\u00c1gios Ge\u00f3rgios Gi\u00e1ltron",
    "gn:population":24,
    "gn:timezone":"Europe/Athens",
    "iso:country":"GR",
    "name:ell_x_preferred":[
        "\u0386\u03b3\u03b9\u03bf\u03c2 \u0393\u03b5\u03ce\u03c1\u03b3\u03b9\u03bf\u03c2 \u0393\u03b9\u03ac\u03bb\u03c4\u03c1\u03c9\u03bd"
    ],
    "name:eng_x_preferred":[
        "Agios Georgios Gialtron"
    ],
    "wof:name":"Agios Georgios Gialtron",
    "wof:placetype":"locality",
    "wof:population":24
},
  "geometry": {"coordinates":[22.9766,38.87117],"type":"Point"}
}