{
  "type": "Feature",
  "properties": {
    "gn:admin1_code":"ESYE23",
    "gn:admin2_code":"39.0",
    "gn:admin3_code":"9137",
    "gn:asciiname":"Nemouta",
    "gn:country_code":"GR",
    "gn:dem":570,
    "gn:feature_class":"P",
    "gn:feature_code":"PPL",
    "gn:name":"Nemo\u00fata",
    "gn:population":0,
    "gn:timezone":"Europe/Athens",
    "iso:country":"GR",
    "name:ell_x_preferred":[
        "\u039d\u03b5\u03bc\u03bf\u03cd\u03c4\u03b1"
    ],
    "name:und_x_variant":[
        "Demo\u00fata",
        "Nemo\u00fata"
    ],
    "wof:name":"Nemouta",
    "wof:placetype":"locality"
},
  "geometry": {"coordinates":[21.79189,37.70094],"type":"Point"}
}