{
  "type": "Feature",
  "properties": {
    "gn:admin1_code":"ESYE24",
    "gn:admin2_code":"30.0",
    "gn:admin3_code":"9157",
    "gn:asciiname":"Sella",
    "gn:country_code":"GR",
    "gn:dem":1039,
    "gn:elevation":"1100.0",
    "gn:feature_class":"P",
    "gn:feature_code":"PPL",
    "gn:name":"Sell\u00e1",
    "gn:population":101,
    "gn:timezone":"Europe/Athens",
    "iso:country":"GR",
    "name:arg_x_preferred":[
        "Sella"
    ],
    "name:cat_x_preferred":[
        "Sella"
    ],
    "name:ceb_x_preferred":[
        "Sella"
    ],
    "name:deu_x_preferred":[
        "Sella"
    ],
    "name:ell_x_preferred":[
        "\u03a3\u03b5\u03bb\u03bb\u03ac"
    ],
    "name:eus_x_preferred":[
        "Sella"
    ],
    "name:fra_x_preferred":[
        "Sella"
    ],
    "name:glg_x_preferred":[
        "Sella"
    ],
    "name:ita_x_preferred":[
        "Sella"
    ],
    "name:nld_x_preferred":[
        "Sella"
    ],
    "name:por_x_preferred":[
        "Sella"
    ],
    "name:rus_x_preferred":[
        "\u0421\u0435\u043b\u043b\u0430"
    ],
    "name:spa_x_preferred":[
        "Sella"
    ],
    "name:srp_x_preferred":[
        "Sella"
    ],
    "name:swe_x_preferred":[
        "Sella"
    ],
    "name:und_x_variant":[
        "Sel\u00e1",
        "Sell\u00e1"
    ],
    "wof:name":"Sella",
    "wof:placetype":"locality",
    "wof:population":101
},
  "geometry": {"coordinates":[21.6821,38.87112],"type":"Point"}
}