{
  "type": "Feature",
  "properties": {
    "gn:admin1_code":"ESYE21",
    "gn:admin2_code":"20.0",
    "gn:admin3_code":"9075",
    "gn:asciiname":"Logarou",
    "gn:country_code":"GR",
    "gn:dem":801,
    "gn:feature_class":"P",
    "gn:feature_code":"PPL",
    "gn:name":"Logaro\u00fa",
    "gn:population":0,
    "gn:timezone":"Europe/Athens",
    "iso:country":"GR",
    "name:ell_x_preferred":[
        "Logaro\u00fa"
    ],
    "name:ell_x_variant":[
        "\u039b\u03bf\u03b3\u03b1\u03c1\u03bf\u03cd"
    ],
    "wof:name":"Logarou",
    "wof:placetype":"locality"
},
  "geometry": {"coordinates":[21.273,39.36133],"type":"Point"}
}