{
  "type": "Feature",
  "properties": {
    "gn:admin1_code":"ESYE25",
    "gn:admin2_code":"41.0",
    "gn:admin3_code":"9241",
    "gn:asciiname":"Kapsas",
    "gn:cc2":"GR",
    "gn:country_code":"GR",
    "gn:dem":695,
    "gn:feature_class":"P",
    "gn:feature_code":"PPL",
    "gn:name":"K\u00e1psas",
    "gn:population":0,
    "gn:timezone":"Europe/Athens",
    "iso:country":"GR",
    "name:ell_x_preferred":[
        "\u039a\u03ac\u03c8\u03b9\u03b1 \u0391\u03c1\u03ba\u03b1\u03b4\u03af\u03b1\u03c2"
    ],
    "name:ron_x_preferred":[
        "Kapsas"
    ],
    "name:und_x_variant":[
        "K\u00e1psia",
        "K\u00e1psas"
    ],
    "wof:name":"Kapsas",
    "wof:placetype":"locality"
},
  "geometry": {"coordinates":[22.34508,37.61546],"type":"Point"}
}