{
  "type": "Feature",
  "properties": {
    "iso:country":"GR",
    "name:ell_x_preferred":[
        "Kalythi\u00e9s"
    ],
    "name:ell_x_variant":[
        "\u039a\u03b1\u03bb\u03c5\u03b8\u03b9\u03ad\u03c2"
    ],
    "name:und_x_variant":[
        "Kalythia\u00ed"
    ],
    "qs:a0":"Greece",
    "qs:a1":"*\u039d\u039f\u03a4\u0399\u039f \u0391\u0399\u0393\u0391\u0399\u039f",
    "qs:a1_alt":"NOTIO AIGAIO",
    "qs:a1r":"0",
    "qs:a2_alt":"DVDEKANHSOS",
    "qs:adm0":"Greece",
    "qs:la_lc":"*",
    "qs:level":"locality",
    "qs:loc":"\u039a\u0391\u039b\u03a5\u0398\u0399\u0391\u0399",
    "qs:loc_alt":"KALYUIAI",
    "qs:pop":0,
    "qs:type":"buffered point",
    "wof:name":"\u039a\u0391\u039b\u03a5\u0398\u0399\u0391\u0399",
    "wof:placetype":"locality"
},
  "geometry": {"coordinates":[28.179716,36.331074],"type":"Point"}
}