{
  "type": "Feature",
  "properties": {
    "gn:gn_country":"GR",
    "gn:gn_fcode":"PPL",
    "gn:gn_pop":0,
    "iso:country":"GR",
    "name:cat_x_preferred":[
        "Lendas"
    ],
    "name:ces_x_preferred":[
        "Lentas"
    ],
    "name:deu_x_preferred":[
        "Lendas"
    ],
    "name:ell_x_preferred":[
        "\u039b\u03ad\u03bd\u03c4\u03b1\u03c2 \u0397\u03c1\u03b1\u03ba\u03bb\u03b5\u03af\u03bf\u03c5"
    ],
    "name:eng_x_preferred":[
        "Lentas"
    ],
    "name:nld_x_preferred":[
        "Lendas"
    ],
    "name:por_x_preferred":[
        "Lentas"
    ],
    "name:unk_x_variant":[
        "Metokhi L\u00e9ndas"
    ],
    "qs_pg:aaroncc":"GR",
    "qs_pg:gn_country":"GR",
    "qs_pg:gn_fcode":"PPL",
    "qs_pg:gn_pop":0,
    "qs_pg:name":"Metokhi Lendas",
    "qs_pg:name_adm0":"\u0395\u03bb\u03bb\u03ac\u03b4\u03b1",
    "qs_pg:name_adm1":"Crete",
    "qs_pg:photos":35,
    "qs_pg:photos_1k":7,
    "qs_pg:photos_9k":1,
    "qs_pg:photos_9r":2,
    "qs_pg:photos_all":35,
    "qs_pg:photos_sr":2,
    "qs_pg:pop_sr":0,
    "qs_pg:qs_pg_placetype":"locality",
    "qs_pg:qs_pg_placetype_gp":"Town",
    "qs_pg:woe_adm0":23424833,
    "woe:adm0_id":23424833,
    "woe:name_adm0":"\u0395\u03bb\u03bb\u03ac\u03b4\u03b1",
    "woe:name_adm1":"Crete",
    "woe:placetype":"Town",
    "wof:name":"Metokhi Lendas",
    "wof:placetype":"locality"
},
  "geometry": {"coordinates":[24.92345,34.93036],"type":"Point"}
}