{
  "type": "Feature",
  "properties": {
    "gn:population":5323,
    "iso:country":"GR",
    "name:ara_x_preferred":[
        "\u0641\u0631\u0648\u0646\u062a\u0627\u062f\u0648\u0633"
    ],
    "name:arz_x_preferred":[
        "\u0641\u0631\u0648\u0646\u062a\u0627\u062f\u0648\u0633"
    ],
    "name:ast_x_preferred":[
        "Vrontados"
    ],
    "name:bul_x_preferred":[
        "\u0412\u0440\u043e\u043d\u0442\u0430\u0434\u043e\u0441"
    ],
    "name:ceb_x_preferred":[
        "Vront\u00e1dos"
    ],
    "name:ell_x_preferred":[
        "\u0392\u03c1\u03bf\u03bd\u03c4\u03ac\u03b4\u03bf\u03c2"
    ],
    "name:ell_x_variant":[
        "\u0392\u03c1\u03bf\u03bd\u03c4\u03ac\u03b4\u03bf\u03c2 \u03a7\u03af\u03bf\u03c5"
    ],
    "name:eng_x_preferred":[
        "Vrontados"
    ],
    "name:fas_x_preferred":[
        "\u0641\u0631\u0648\u0646\u062a\u0627\u062f\u0648\u0633"
    ],
    "name:fin_x_preferred":[
        "Vront\u00e1dos"
    ],
    "name:nld_x_preferred":[
        "Vrontados"
    ],
    "name:nno_x_preferred":[
        "Vrond\u00e1dos"
    ],
    "name:pol_x_preferred":[
        "Vrontados"
    ],
    "name:rus_x_preferred":[
        "\u0412\u0440\u043e\u043d\u0434\u0430\u0434\u043e\u0441"
    ],
    "name:swe_x_preferred":[
        "Vront\u00e1dos"
    ],
    "name:ukr_x_preferred":[
        "\u0412\u0440\u043e\u043d\u0442\u0430\u0434\u043e\u0441"
    ],
    "name:und_x_variant":[
        "Vrondh\u00e1des"
    ],
    "qs:a0":"Greece",
    "qs:a1":"*\u0392\u039f\u03a1\u0395\u0399\u039f \u0391\u0399\u0393\u0391\u0399\u039f",
    "qs:a1_alt":"BOREIO AIGAIO",
    "qs:a1r":"0",
    "qs:a2_alt":"XIOS",
    "qs:adm0":"Greece",
    "qs:la_lc":"*",
    "qs:level":"locality",
    "qs:loc":"\u0392\u03a1\u039f\u039d\u03a4\u0391\u0394\u039f\u03a3",
    "qs:loc_alt":"BRONTADOS",
    "qs:pop":0,
    "qs:type":"buffered point",
    "wd:wordcount":301,
    "wof:name":"\u0392\u03a1\u039f\u039d\u03a4\u0391\u0394\u039f\u03a3",
    "wof:placetype":"locality",
    "wof:population":5323
},
  "geometry": {"coordinates":[26.130319,38.408589],"type":"Point"}
}