{
  "type": "Feature",
  "properties": {
    "gn:gn_country":"GR",
    "gn:gn_fcode":"PPL",
    "gn:gn_pop":906,
    "gn:population":950,
    "iso:country":"GR",
    "name:ell_x_preferred":[
        "\u03a7\u03b1\u03bb\u03ba\u03b5\u03b9\u03cc"
    ],
    "name:ell_x_variant":[
        "\u03a7\u03b1\u03bb\u03ba\u03b5\u03b9\u03cc\u03c2"
    ],
    "name:eng_x_preferred":[
        "Chalkios"
    ],
    "name:unk_x_variant":[
        "Khalki\u00f3s"
    ],
    "qs_pg:aaroncc":"GR",
    "qs_pg:gn_country":"GR",
    "qs_pg:gn_fcode":"PPL",
    "qs_pg:gn_pop":906,
    "qs_pg:name":"Chalkei\u00f3n",
    "qs_pg:photos_9r":0,
    "qs_pg:photos_sr":0,
    "qs_pg:pop_sr":2,
    "qs_pg:qs_pg_placetype":"locality",
    "wof:name":"Chalkei\u00f3n",
    "wof:placetype":"locality",
    "wof:population":950
},
  "geometry": {"coordinates":[26.09845,38.33335],"type":"Point"}
}