{
  "type": "Feature",
  "properties": {
    "gn:gn_country":"GR",
    "gn:gn_fcode":"PPLA3",
    "gn:gn_pop":0,
    "gn:population":3671,
    "iso:country":"GR",
    "name:ara_x_preferred":[
        "\u0623\u0645\u064a\u0646\u062a\u0627\u064a\u0648"
    ],
    "name:bul_x_preferred":[
        "\u0410\u043c\u0300\u0438\u043d\u0434\u0435\u043e"
    ],
    "name:bul_x_variant":[
        "\u0421\u0443\u0440\u043e\u0432\u0438\u0447\u0435\u0432\u043e"
    ],
    "name:ceb_x_preferred":[
        "Am\u00fdntaio"
    ],
    "name:deu_x_preferred":[
        "Amyndeo"
    ],
    "name:ell_x_historical":[
        "\u03a3\u03cc\u03c1\u03bf\u03b2\u03b9\u03c4\u03c2",
        "\u03a3\u03bf\u03cd\u03c1\u03bf\u03b2\u03b9\u03c4\u03c2",
        "\u03a3\u03bf\u03c5\u03c1\u03bf\u03b2\u03af\u03c4\u03c3\u03b5\u03b2\u03bf",
        "\u03a3\u03c5\u03c1\u03bf\u03b2\u03af\u03c4\u03c3\u03b5\u03b2\u03bf"
    ],
    "name:ell_x_preferred":[
        "\u0391\u03bc\u03cd\u03bd\u03c4\u03b1\u03b9\u03bf"
    ],
    "name:ell_x_variant":[
        "\u03a3\u03cc\u03c1\u03bf\u03b2\u03b9\u03c4\u03c2",
        "\u03a3\u03bf\u03cd\u03c1\u03bf\u03b2\u03b9\u03c4\u03c2",
        "\u03a3\u03bf\u03c5\u03c1\u03bf\u03b2\u03af\u03c4\u03c3\u03b5\u03b2\u03bf",
        "\u03a3\u03c5\u03c1\u03bf\u03b2\u03af\u03c4\u03c3\u03b5\u03b2\u03bf"
    ],
    "name:eng_x_preferred":[
        "Amyntaio"
    ],
    "name:fin_x_preferred":[
        "Am\u00fdntaio"
    ],
    "name:fra_x_preferred":[
        "Am\u00fdntaio"
    ],
    "name:hye_x_preferred":[
        "\u0531\u0574\u056b\u0576\u0564\u0565\u0578\u0576"
    ],
    "name:ita_x_preferred":[
        "Amyntaio"
    ],
    "name:mkd_x_preferred":[
        "\u0421\u0443\u0440\u043e\u0432\u0438\u0447\u0435\u0432\u043e"
    ],
    "name:nld_x_preferred":[
        "Amyntaio"
    ],
    "name:nno_x_preferred":[
        "Am\u00fdndeo"
    ],
    "name:pol_x_preferred":[
        "Amindeo"
    ],
    "name:rus_x_preferred":[
        "\u0410\u043c\u0438\u043d\u0434\u0435\u043e"
    ],
    "name:rus_x_variant":[
        "\u0410\u043c\u0438\u043d\u0434\u0435\u043e\u043d"
    ],
    "name:spa_x_preferred":[
        "Amindeo"
    ],
    "name:sqi_x_preferred":[
        "Sorovi\u00e7i"
    ],
    "name:srp_x_preferred":[
        "\u0421\u0443\u0440\u043e\u0432\u0438\u0447\u0435\u0432\u043e"
    ],
    "name:swe_x_preferred":[
        "Am\u00fdntaio"
    ],
    "name:tur_x_preferred":[
        "Sorovi\u00e7"
    ],
    "name:unk_x_variant":[
        "S\u00f3rovits"
    ],
    "name:vie_x_preferred":[
        "Amynteo"
    ],
    "qs_pg:aaroncc":"GR",
    "qs_pg:gn_country":"GR",
    "qs_pg:gn_fcode":"PPLA3",
    "qs_pg:gn_pop":0,
    "qs_pg:name":"Amyntaio",
    "qs_pg:name_adm0":"\u0395\u03bb\u03bb\u03ac\u03b4\u03b1",
    "qs_pg:name_adm1":"Epirus and Western Macedonia",
    "qs_pg:photos_9k":1,
    "qs_pg:photos_9r":4,
    "qs_pg:photos_all":251,
    "qs_pg:photos_sr":0,
    "qs_pg:pop_sr":7,
    "qs_pg:qs_pg_placetype":"localadmin",
    "qs_pg:qs_pg_placetype_gp":"LocalAdmin",
    "qs_pg:woe_adm0":23424833,
    "woe:adm0_id":23424833,
    "woe:name_adm0":"\u0395\u03bb\u03bb\u03ac\u03b4\u03b1",
    "woe:name_adm1":"Epirus and Western Macedonia",
    "woe:placetype":"LocalAdmin",
    "wof:name":"Amyntaio",
    "wof:placetype":"localadmin",
    "wof:population":3671
},
  "geometry": {"coordinates":[21.68333,40.68333],"type":"Point"}
}