{
  "type": "Feature",
  "properties": {
    "gn:admin1_code":"ESYE22",
    "gn:admin2_code":"28.0",
    "gn:admin3_code":"9116",
    "gn:asciiname":"Agioi Pantes",
    "gn:country_code":"GR",
    "gn:dem":102,
    "gn:feature_class":"P",
    "gn:feature_code":"PPL",
    "gn:name":"Agioi P\u00e1ntes",
    "gn:population":339,
    "gn:timezone":"Europe/Athens",
    "iso:country":"GR",
    "name:ell_x_historical":[
        "\u039c\u03b9\u03ba\u03c1\u03cc \u0393\u03b1\u03bb\u03b1\u03c1\u03cc",
        "\u039c\u03b9\u03ba\u03c1\u03cc \u0393\u03b1\u03bb\u03b1\u03c1\u03cc\u03bd"
    ],
    "name:ell_x_preferred":[
        "\u0386\u03b3\u03b9\u03bf\u03b9 \u03a0\u03ac\u03bd\u03c4\u03b5\u03c2"
    ],
    "name:ell_x_variant":[
        "\u039c\u03b9\u03ba\u03c1\u03cc \u0393\u03b1\u03bb\u03b1\u03c1\u03cc",
        "\u039c\u03b9\u03ba\u03c1\u03cc \u0393\u03b1\u03bb\u03b1\u03c1\u03cc\u03bd",
        "\u0386\u03b3\u03b9\u03bf\u03b9 \u03a0\u03ac\u03bd\u03c4\u03b5\u03c2 \u0396\u03b1\u03ba\u03cd\u03bd\u03b8\u03bf\u03c5"
    ],
    "name:eng_x_historical":[
        "Mikron Galaron"
    ],
    "name:eng_x_preferred":[
        "Mikron Galaron"
    ],
    "name:eng_x_variant":[
        "Agioi Pantes"
    ],
    "name:und_x_variant":[
        "Galar\u00f3n",
        "Galar\u00f3s",
        "Mikr\u00f3n Gal\u00e1ron",
        "Ayioi Pantes"
    ],
    "wof:name":"Agioi Pantes",
    "wof:placetype":"locality",
    "wof:population":339
},
  "geometry": {"coordinates":[20.78609,37.78123],"type":"Point"}
}