{
  "type": "Feature",
  "properties": {
    "gn:admin1_code":"ESYE43",
    "gn:admin2_code":"43.0",
    "gn:admin3_code":"9322",
    "gn:asciiname":"Fournados",
    "gn:country_code":"GR",
    "gn:dem":116,
    "gn:feature_class":"P",
    "gn:feature_code":"PPL",
    "gn:name":"Fourn\u00e1dos",
    "gn:population":20,
    "gn:timezone":"Europe/Athens",
    "iso:country":"GR",
    "name:ell_x_preferred":[
        "\u03a6\u03bf\u03c5\u03c1\u03bd\u03ac\u03b4\u03bf\u03c2"
    ],
    "name:eng_x_preferred":[
        "Fournados"
    ],
    "name:und_x_variant":[
        "Fourn\u00e1dho",
        "Fourn\u00e1dhos",
        "Fourn\u00e1dos"
    ],
    "wof:name":"Fournados",
    "wof:placetype":"locality",
    "wof:population":20
},
  "geometry": {"coordinates":[23.61876,35.49598],"type":"Point"}
}