{
  "type": "Feature",
  "properties": {
    "gn:admin1_code":"ESYE25",
    "gn:admin2_code":"40.0",
    "gn:admin3_code":"9257",
    "gn:asciiname":"Soulinari",
    "gn:country_code":"GR",
    "gn:dem":340,
    "gn:feature_class":"P",
    "gn:feature_code":"PPL",
    "gn:name":"Soulin\u00e1ri",
    "gn:population":0,
    "gn:timezone":"Europe/Athens",
    "iso:country":"GR",
    "name:ell_x_preferred":[
        "Soulin\u00e1ri"
    ],
    "name:ell_x_variant":[
        "\u03a3\u03bf\u03c5\u03bb\u03b9\u03bd\u03ac\u03c1\u03b9",
        "\u03a3\u03bf\u03c5\u03bb\u03b9\u03bd\u03ac\u03c1\u03b9\u03bf\u03bd"
    ],
    "name:und_x_variant":[
        "Solin\u00e1rion",
        "Soulin\u00e1rion"
    ],
    "wof:name":"Soulinari",
    "wof:placetype":"locality"
},
  "geometry": {"coordinates":[21.80652000000001,36.96974],"type":"Point"}
}