{
  "type": "Feature",
  "properties": {
    "gn:admin1_code":"ESYE25",
    "gn:admin2_code":"40.0",
    "gn:admin3_code":"9254",
    "gn:asciiname":"Poliani",
    "gn:country_code":"GR",
    "gn:dem":648,
    "gn:feature_class":"P",
    "gn:feature_code":"PPL",
    "gn:name":"Polian\u00ed",
    "gn:population":0,
    "gn:timezone":"Europe/Athens",
    "iso:country":"GR",
    "name:ell_x_preferred":[
        "Polian\u00ed"
    ],
    "name:ell_x_variant":[
        "\u03a0\u03bf\u03bb\u03b9\u03b1\u03bd\u03ae"
    ],
    "name:und_x_variant":[
        "Poulian\u00ed",
        "Poli\u00e1na"
    ],
    "wof:name":"Poliani",
    "wof:placetype":"locality"
},
  "geometry": {"coordinates":[22.1391,37.15706],"type":"Point"}
}