{
  "type": "Feature",
  "properties": {
    "gn:admin1_code":"ESYE41",
    "gn:admin2_code":"51.0",
    "gn:admin3_code":"9263",
    "gn:asciiname":"Plaka",
    "gn:country_code":"GR",
    "gn:dem":23,
    "gn:feature_class":"P",
    "gn:feature_code":"PPL",
    "gn:name":"Pl\u00e1ka",
    "gn:population":0,
    "gn:timezone":"Europe/Athens",
    "iso:country":"GR",
    "name:ell_x_preferred":[
        "\u03a0\u03bb\u03ac\u03ba\u03b1"
    ],
    "name:ell_x_variant":[
        "\u03a0\u03bb\u03ac\u03ba\u03b1 \u039b\u03ae\u03bc\u03bd\u03bf\u03c5"
    ],
    "name:eng_x_preferred":[
        "Plaka"
    ],
    "wof:name":"Plaka",
    "wof:placetype":"locality"
},
  "geometry": {"coordinates":[25.4264,40.00425],"type":"Point"}
}