{
  "type": "Feature",
  "properties": {
    "gn:gn_country":"GR",
    "gn:gn_fcode":"ADM3",
    "gn:gn_pop":17864,
    "gn:population":17864,
    "iso:country":"GR",
    "name:ell_x_preferred":[
        "\u03a0\u03bb\u03b1\u03c4\u03b1\u03bd\u03b9\u03ac"
    ],
    "name:ell_x_variant":[
        "\u03a0\u03bb\u03b1\u03c4\u03b1\u03bd\u03b9\u03ac\u03c2"
    ],
    "qs_pg:aaroncc":"GR",
    "qs_pg:gn_country":"GR",
    "qs_pg:gn_fcode":"ADM3",
    "qs_pg:gn_pop":17864,
    "qs_pg:name":"Platanias",
    "qs_pg:name_adm0":"\u0395\u03bb\u03bb\u03ac\u03b4\u03b1",
    "qs_pg:name_adm1":"Crete",
    "qs_pg:photos_9k":12,
    "qs_pg:photos_9r":10,
    "qs_pg:photos_all":2701,
    "qs_pg:photos_sr":0,
    "qs_pg:pop_sr":6,
    "qs_pg:qs_pg_placetype":"localadmin",
    "qs_pg:qs_pg_placetype_gp":"LocalAdmin",
    "qs_pg:woe_adm0":23424833,
    "woe:adm0_id":23424833,
    "woe:name_adm0":"\u0395\u03bb\u03bb\u03ac\u03b4\u03b1",
    "woe:name_adm1":"Crete",
    "woe:placetype":"LocalAdmin",
    "wof:name":"Platanias",
    "wof:placetype":"localadmin",
    "wof:population":17864
},
  "geometry": {"coordinates":[23.90659,35.51369],"type":"Point"}
}