{
  "type": "Feature",
  "properties": {
    "gn:admin1_code":"ESYE25",
    "gn:admin2_code":"42.0",
    "gn:admin3_code":"9250",
    "gn:asciiname":"Karitsa",
    "gn:country_code":"GR",
    "gn:dem":678,
    "gn:feature_class":"P",
    "gn:feature_code":"PPL",
    "gn:name":"Kar\u00edtsa",
    "gn:population":0,
    "gn:timezone":"Europe/Athens",
    "iso:country":"GR",
    "name:ceb_x_preferred":[
        "Karitsa"
    ],
    "name:ell_x_preferred":[
        "Kar\u00edtsa"
    ],
    "name:ell_x_variant":[
        "\u039a\u03b1\u03c1\u03af\u03c4\u03c3\u03b1"
    ],
    "name:est_x_preferred":[
        "Karitsa"
    ],
    "name:pol_x_preferred":[
        "Karitsa"
    ],
    "name:sco_x_preferred":[
        "Karitsa"
    ],
    "name:swe_x_preferred":[
        "Karitsa"
    ],
    "name:vol_x_preferred":[
        "Karitsa"
    ],
    "wof:name":"Karitsa",
    "wof:placetype":"locality"
},
  "geometry": {"coordinates":[22.77645,37.00854],"type":"Point"}
}