{
  "type": "Feature",
  "properties": {
    "gn:admin1_code":"ESYE41",
    "gn:admin2_code":"51.0",
    "gn:admin3_code":"9263",
    "gn:asciiname":"Ayia Irini",
    "gn:cc2":"GR",
    "gn:country_code":"GR",
    "gn:dem":61,
    "gn:feature_class":"P",
    "gn:feature_code":"PPL",
    "gn:name":"Ay\u00eda Ir\u00edni",
    "gn:population":0,
    "gn:timezone":"Europe/Athens",
    "iso:country":"GR",
    "name:und_x_variant":[
        "Kondovr\u00e1kion",
        "Kondovr\u00e1ki",
        "Ay\u00eda Ir\u00edni"
    ],
    "wof:name":"Ayia Irini",
    "wof:placetype":"locality"
},
  "geometry": {"coordinates":[25.18882,39.94131],"type":"Point"}
}