{
  "type": "Feature",
  "properties": {
    "gn:admin1_code":"ESYE42",
    "gn:admin2_code":"47.0",
    "gn:admin3_code":"9296",
    "gn:asciiname":"Lachania",
    "gn:country_code":"GR",
    "gn:dem":49,
    "gn:feature_class":"P",
    "gn:feature_code":"PPL",
    "gn:name":"Lachani\u00e1",
    "gn:population":0,
    "gn:timezone":"Europe/Athens",
    "iso:country":"GR",
    "name:und_x_variant":[
        "Lakania",
        "Lacania",
        "Lakhani\u00e1",
        "Lachani\u00e1",
        "\u039b\u03b1\u03c7\u03b1\u03bd\u03b9\u03ac"
    ],
    "wof:name":"Lachania",
    "wof:placetype":"locality"
},
  "geometry": {"coordinates":[27.85182,35.96680999999999],"type":"Point"}
}