{
  "type": "Feature",
  "properties": {
    "gn:admin1_code":"ESYE24",
    "gn:admin2_code":"29.0",
    "gn:admin3_code":"9159",
    "gn:asciiname":"Kariai",
    "gn:country_code":"GR",
    "gn:dem":414,
    "gn:feature_class":"P",
    "gn:feature_code":"PPL",
    "gn:name":"Karia\u00ed",
    "gn:population":123,
    "gn:timezone":"Europe/Athens",
    "iso:country":"GR",
    "name:ell_x_preferred":[
        "\u039a\u03b1\u03c1\u03c5\u03ad\u03c2"
    ],
    "name:eng_x_preferred":[
        "Karyes"
    ],
    "name:und_x_variant":[
        "Al\u00edfaka",
        "Kari\u00e9s",
        "Karia\u00ed"
    ],
    "wof:name":"Kariai",
    "wof:placetype":"locality",
    "wof:population":123
},
  "geometry": {"coordinates":[22.42473,39.08141],"type":"Point"}
}