{
  "type": "Feature",
  "properties": {
    "gn:admin1_code":"ESYE25",
    "gn:admin2_code":"36.0",
    "gn:admin3_code":"9236",
    "gn:asciiname":"Panaritis",
    "gn:country_code":"GR",
    "gn:dem":46,
    "gn:feature_class":"P",
    "gn:feature_code":"PPL",
    "gn:name":"Panar\u00edtis",
    "gn:population":563,
    "gn:timezone":"Europe/Athens",
    "iso:country":"GR",
    "name:ell_x_preferred":[
        "\u03a0\u03b1\u03bd\u03b1\u03c1\u03af\u03c4\u03b7\u03c2"
    ],
    "name:eng_x_preferred":[
        "Panaritis"
    ],
    "name:und_x_variant":[
        "Panar\u00edti",
        "Panar\u00edtis"
    ],
    "wof:name":"Panaritis",
    "wof:placetype":"locality",
    "wof:population":563
},
  "geometry": {"coordinates":[22.8235,37.63102],"type":"Point"}
}