{
  "type": "Feature",
  "properties": {
    "gn:gn_country":"GR",
    "gn:gn_fcode":"PPL",
    "gn:gn_pop":253,
    "gn:population":253,
    "iso:country":"GR",
    "name:ell_x_preferred":[
        "N\u00e9o Arg\u00fdri"
    ],
    "name:ell_x_variant":[
        "\u039d\u03ad\u03bf \u0391\u03c1\u03b3\u03cd\u03c1\u03b9",
        "\u039d\u03ad\u03bf\u03bd \u0391\u03c1\u03b3\u03cd\u03c1\u03b9\u03bf\u03bd"
    ],
    "name:unk_x_variant":[
        "N\u00e9on Ary\u00edrion"
    ],
    "qs_pg:aaroncc":"GR",
    "qs_pg:gn_country":"GR",
    "qs_pg:gn_fcode":"PPL",
    "qs_pg:gn_pop":253,
    "qs_pg:name":"N\u00e9on Arg\u00fdrion",
    "qs_pg:photos_9r":0,
    "qs_pg:photos_sr":0,
    "qs_pg:pop_sr":2,
    "qs_pg:qs_pg_placetype":"locality",
    "wof:name":"N\u00e9on Arg\u00fdrion",
    "wof:placetype":"locality",
    "wof:population":253
},
  "geometry": {"coordinates":[21.40222,39.15139],"type":"Point"}
}