{
  "type": "Feature",
  "properties": {
    "gn:admin1_code":"ESYE24",
    "gn:admin2_code":"30.0",
    "gn:admin3_code":"9156",
    "gn:asciiname":"Vlachopoula",
    "gn:country_code":"GR",
    "gn:dem":1236,
    "gn:feature_class":"P",
    "gn:feature_code":"PPL",
    "gn:name":"Vlachopo\u00fala",
    "gn:population":0,
    "gn:timezone":"Europe/Athens",
    "iso:country":"GR",
    "name:ell_x_preferred":[
        "Vlachopo\u00fala"
    ],
    "name:ell_x_variant":[
        "\u0392\u03bb\u03b1\u03c7\u03bf\u03c0\u03bf\u03cd\u03bb\u03b1"
    ],
    "wof:name":"Vlachopoula",
    "wof:placetype":"locality"
},
  "geometry": {"coordinates":[21.56817,39.13753],"type":"Point"}
}