{
  "type": "Feature",
  "properties": {
    "gn:gn_country":"GR",
    "gn:gn_fcode":"PPL",
    "gn:gn_pop":18,
    "gn:population":18,
    "iso:country":"GR",
    "name:ell_x_preferred":[
        "Trip\u00f3tamos"
    ],
    "name:ell_x_variant":[
        "\u03a4\u03c1\u03b9\u03c0\u03cc\u03c4\u03b1\u03bc\u03bf\u03c2"
    ],
    "qs_pg:aaroncc":"GR",
    "qs_pg:gn_country":"GR",
    "qs_pg:gn_fcode":"PPL",
    "qs_pg:gn_pop":18,
    "qs_pg:name":"Tripotamos",
    "qs_pg:name_adm0":"\u0395\u03bb\u03bb\u03ac\u03b4\u03b1",
    "qs_pg:name_adm1":"Macedonia and Thrace",
    "qs_pg:photos_9r":0,
    "qs_pg:photos_sr":0,
    "qs_pg:pop_sr":1,
    "qs_pg:qs_pg_placetype":"locality",
    "qs_pg:qs_pg_placetype_gp":"Town",
    "qs_pg:woe_adm0":23424833,
    "woe:adm0_id":23424833,
    "woe:name_adm0":"\u0395\u03bb\u03bb\u03ac\u03b4\u03b1",
    "woe:name_adm1":"Macedonia and Thrace",
    "woe:placetype":"Town",
    "wof:name":"Tripotamos",
    "wof:placetype":"locality",
    "wof:population":18
},
  "geometry": {"coordinates":[22.925,41.17472],"type":"Point"}
}