{
  "type": "Feature",
  "properties": {
    "gn:admin1_code":"ESYE11",
    "gn:admin2_code":"3.0",
    "gn:admin3_code":"9017",
    "gn:asciiname":"Stavrochori",
    "gn:country_code":"GR",
    "gn:dem":151,
    "gn:feature_class":"P",
    "gn:feature_code":"PPL",
    "gn:name":"Stavroch\u00f3ri",
    "gn:population":0,
    "gn:timezone":"Europe/Athens",
    "iso:country":"GR",
    "name:ell_x_preferred":[
        "Stavroch\u00f3ri"
    ],
    "name:ell_x_variant":[
        "\u03a3\u03c4\u03b1\u03c5\u03c1\u03bf\u03c7\u03ce\u03c1\u03b9",
        "Stavrokh\u00f3rion",
        "Stavroch\u00f3rion",
        "\u03a3\u03c4\u03b1\u03c5\u03c1\u03bf\u03c7\u03ce\u03c1\u03b9\u03bf\u03bd"
    ],
    "wof:name":"Stavrochori",
    "wof:placetype":"locality"
},
  "geometry": {"coordinates":[24.60081,41.24119],"type":"Point"}
}