{
  "type": "Feature",
  "properties": {
    "gn:admin1_code":"ESYE43",
    "gn:admin2_code":"44.0",
    "gn:admin3_code":"9318",
    "gn:asciiname":"Bezeriana Metochia",
    "gn:country_code":"GR",
    "gn:dem":170,
    "gn:feature_class":"P",
    "gn:feature_code":"PPL",
    "gn:name":"Bezerian\u00e1 Met\u00f3chia",
    "gn:population":0,
    "gn:timezone":"Europe/Athens",
    "iso:country":"GR",
    "name:ell_x_preferred":[
        "Bezerian\u00e1 Met\u00f3chia"
    ],
    "name:ell_x_variant":[
        "\u039c\u03c0\u03b5\u03b6\u03b5\u03c1\u03b9\u03b1\u03bd\u03ac \u039c\u03b5\u03c4\u03cc\u03c7\u03b9\u03b1"
    ],
    "wof:name":"Bezeriana Metochia",
    "wof:placetype":"locality"
},
  "geometry": {"coordinates":[24.39982,35.34392000000001],"type":"Point"}
}