{
  "type": "Feature",
  "properties": {
    "gn:admin1_code":"ESYE41",
    "gn:asciiname":"Ploumari",
    "gn:country_code":"GR",
    "gn:dem":414,
    "gn:feature_class":"P",
    "gn:feature_code":"PPL",
    "gn:name":"Plo\u00famari",
    "gn:population":0,
    "gn:timezone":"Europe/Athens",
    "iso:country":"GR",
    "name:ell_x_preferred":[
        "Plo\u00famari"
    ],
    "name:ell_x_variant":[
        "\u03a0\u03bb\u03bf\u03cd\u03bc\u03b1\u03c1\u03b9"
    ],
    "wof:name":"Ploumari",
    "wof:placetype":"locality"
},
  "geometry": {"coordinates":[26.26129,37.64059],"type":"Point"}
}