{
  "type": "Feature",
  "properties": {
    "gn:admin1_code":"ESYE21",
    "gn:admin2_code":"18.0",
    "gn:admin3_code":"9079",
    "gn:asciiname":"Ragio",
    "gn:country_code":"GR",
    "gn:dem":40,
    "gn:feature_class":"P",
    "gn:feature_code":"PPL",
    "gn:name":"R\u00e1gio",
    "gn:population":0,
    "gn:timezone":"Europe/Athens",
    "iso:country":"GR",
    "name:ell_x_preferred":[
        "R\u00e1gio"
    ],
    "name:ell_x_variant":[
        "\u03a1\u03ac\u03b3\u03b9\u03bf"
    ],
    "wof:name":"Ragio",
    "wof:placetype":"locality"
},
  "geometry": {"coordinates":[20.24522,39.57725],"type":"Point"}
}