{
  "type": "Feature",
  "properties": {
    "gn:country":"GR",
    "gn:fcode":"PPL",
    "gn:population":576,
    "iso:country":"GR",
    "name:ell_x_historical":[
        "\u03a4\u03c3\u03ac\u03ba\u03c9\u03bd \u03a4\u03c3\u03b9\u03c6\u03bb\u03af\u03ba"
    ],
    "name:ell_x_preferred":[
        "\u03a7\u03c1\u03cd\u03c3\u03b1"
    ],
    "name:ell_x_variant":[
        "\u03a4\u03c3\u03ac\u03ba\u03c9\u03bd \u03a4\u03c3\u03b9\u03c6\u03bb\u03af\u03ba"
    ],
    "name:eng_x_preferred":[
        "Chrysa"
    ],
    "name:nld_x_preferred":[
        "Chrysa"
    ],
    "name:und_x_variant":[
        "Khr\u00edsa"
    ],
    "qs_pg:aaroncc":"GR",
    "qs_pg:gn_country":"GR",
    "qs_pg:gn_fcode":"PPL",
    "qs_pg:gn_pop":576,
    "qs_pg:name":"Chr\u00fdsa",
    "qs_pg:photos_9r":0,
    "qs_pg:photos_sr":0,
    "qs_pg:pop_sr":2,
    "qs_pg:qs_pg_placetype":"locality",
    "wof:name":"Chr\u00fdsa",
    "wof:placetype":"locality",
    "wof:population":576
},
  "geometry": {"coordinates":[22.04167,40.95333],"type":"Point"}
}