{
  "type": "Feature",
  "properties": {
    "gn:admin1_code":"ESYE11",
    "gn:admin2_code":"4.0",
    "gn:admin3_code":"9003",
    "gn:asciiname":"Achladia",
    "gn:country_code":"GR",
    "gn:dem":591,
    "gn:feature_class":"P",
    "gn:feature_code":"PPL",
    "gn:name":"Achladi\u00e1",
    "gn:population":0,
    "gn:timezone":"Europe/Athens",
    "iso:country":"GR",
    "name:bul_x_preferred":[
        "\u0411\u043b\u0430\u0442\u0447\u0435\u043d"
    ],
    "name:ell_x_preferred":[
        "Achladi\u00e1"
    ],
    "name:ell_x_variant":[
        "\u0391\u03c7\u03bb\u03b1\u03b4\u03b9\u03ac"
    ],
    "name:und_x_variant":[
        "Bl\u00e1tsen",
        "Akhladhi\u00e1s",
        "Akhladhi\u00e1",
        "Akhladh\u00e9a"
    ],
    "wof:name":"Achladia",
    "wof:placetype":"locality"
},
  "geometry": {"coordinates":[24.01045,41.39755],"type":"Point"}
}