{
  "type": "Feature",
  "properties": {
    "gn:admin1_code":"ESYE25",
    "gn:admin2_code":"42.0",
    "gn:admin3_code":"9248",
    "gn:asciiname":"Lakkos",
    "gn:country_code":"GR",
    "gn:dem":125,
    "gn:feature_class":"P",
    "gn:feature_code":"PPL",
    "gn:name":"L\u00e1kkos",
    "gn:population":40,
    "gn:timezone":"Europe/Athens",
    "iso:country":"GR",
    "name:ell_x_preferred":[
        "\u039b\u03ac\u03ba\u03ba\u03bf\u03c2"
    ],
    "name:eng_x_preferred":[
        "Lakkos"
    ],
    "name:spa_x_preferred":[
        "Lakkos"
    ],
    "wof:name":"Lakkos",
    "wof:placetype":"locality",
    "wof:population":40
},
  "geometry": {"coordinates":[22.40526,36.55598],"type":"Point"}
}