{
  "type": "Feature",
  "properties": {
    "gn:country":"GR",
    "gn:fcode":"PPL",
    "gn:population":1529,
    "iso:country":"GR",
    "name:arz_x_preferred":[
        "\u0633\u062a\u0627\u06a4\u0631\u0648\u0633 \u06a4\u064a\u0631\u064a\u0627\u0633"
    ],
    "name:bul_x_preferred":[
        "\u0421\u0442\u0430\u0432\u0440\u043e\u0441"
    ],
    "name:ceb_x_preferred":[
        "Stavr\u00f3s"
    ],
    "name:deu_x_preferred":[
        "stavros verias"
    ],
    "name:ell_x_preferred":[
        "Stavr\u00f3s"
    ],
    "name:ell_x_variant":[
        "\u03a3\u03c4\u03b1\u03c5\u03c1\u03cc\u03c2",
        "\u03a3\u03c4\u03b1\u03c5\u03c1\u03cc\u03c2 \u0397\u03bc\u03b1\u03b8\u03af\u03b1\u03c2"
    ],
    "name:eng_x_preferred":[
        "stavros verias"
    ],
    "name:eng_x_variant":[
        "Stavros"
    ],
    "name:fra_x_preferred":[
        "Stavr\u00f3s"
    ],
    "name:mkd_x_preferred":[
        "\u0421\u0442\u0430\u0432\u0440\u043e\u0441"
    ],
    "name:nld_x_preferred":[
        "stavros verias"
    ],
    "name:rus_x_preferred":[
        "\u0421\u0442\u0430\u0432\u0440\u043e\u0441"
    ],
    "name:swe_x_preferred":[
        "Stavr\u00f3s"
    ],
    "qs_pg:aaroncc":"GR",
    "qs_pg:gn_country":"GR",
    "qs_pg:gn_fcode":"PPL",
    "qs_pg:gn_pop":1529,
    "qs_pg:name":"Stavros",
    "qs_pg:name_adm0":"\u0395\u03bb\u03bb\u03ac\u03b4\u03b1",
    "qs_pg:name_adm1":"Macedonia and Thrace",
    "qs_pg:photos_9k":1,
    "qs_pg:photos_9r":1,
    "qs_pg:photos_all":1,
    "qs_pg:photos_sr":0,
    "qs_pg:pop_sr":3,
    "qs_pg:qs_pg_placetype":"locality",
    "qs_pg:qs_pg_placetype_gp":"Town",
    "qs_pg:woe_adm0":23424833,
    "woe:adm0_id":23424833,
    "woe:name_adm0":"\u0395\u03bb\u03bb\u03ac\u03b4\u03b1",
    "woe:name_adm1":"Macedonia and Thrace",
    "woe:placetype":"Town",
    "wof:name":"Stavros",
    "wof:placetype":"locality",
    "wof:population":1529
},
  "geometry": {"coordinates":[22.30861,40.58889],"type":"Point"}
}