{
  "type": "Feature",
  "properties": {
    "gn:admin1_code":"ESYE24",
    "gn:admin2_code":"29.0",
    "gn:admin3_code":"9160",
    "gn:asciiname":"Thermopilai",
    "gn:country_code":"GR",
    "gn:dem":27,
    "gn:feature_class":"P",
    "gn:feature_code":"PPL",
    "gn:name":"Thermop\u00edlai",
    "gn:population":295,
    "gn:timezone":"Europe/Athens",
    "iso:country":"GR",
    "name:bul_x_preferred":[
        "\u0422\u0435\u0440\u043c\u043e\u043f\u0438\u043b\u0438"
    ],
    "name:deu_x_preferred":[
        "Thermopylen"
    ],
    "name:ell_x_historical":[
        "\u0394\u03c1\u03b1\u03ba\u03bf\u03c3\u03c0\u03b7\u03bb\u03b9\u03ac"
    ],
    "name:ell_x_preferred":[
        "\u0398\u03b5\u03c1\u03bc\u03bf\u03c0\u03cd\u03bb\u03b5\u03c2"
    ],
    "name:ell_x_variant":[
        "\u0398\u03b5\u03c1\u03bc\u03bf\u03c0\u03cd\u03bb\u03b1\u03b9",
        "\u0394\u03c1\u03b1\u03ba\u03bf\u03c3\u03c0\u03b7\u03bb\u03b9\u03ac"
    ],
    "name:eng_x_preferred":[
        "Thermopylae"
    ],
    "name:fra_x_preferred":[
        "Thermopyles"
    ],
    "name:grc_x_preferred":[
        "\u0398\u03b5\u03c1\u03bc\u03bf\u03c0\u03cd\u03bb\u03b1\u03b9"
    ],
    "name:ita_x_preferred":[
        "Termopili"
    ],
    "name:ron_x_preferred":[
        "Termopile"
    ],
    "name:rus_x_preferred":[
        "\u0424\u0435\u0440\u043c\u043e\u043f\u0438\u0301\u043b\u044b"
    ],
    "name:und_x_variant":[
        "Dhrakospili\u00e1",
        "Kalivai Dhrakospili\u00e1s",
        "Kal\u00edvia",
        "Thermop\u00edlai",
        "Thermopyles",
        "Thermopiles"
    ],
    "wof:name":"Thermopilai",
    "wof:placetype":"locality",
    "wof:population":295
},
  "geometry": {"coordinates":[22.5453,38.79945],"type":"Point"}
}