{
  "type": "Feature",
  "properties": {
    "gn:admin1_code":"ESYE11",
    "gn:admin2_code":"2.0",
    "gn:admin3_code":"9021",
    "gn:asciiname":"Nea Kallisti",
    "gn:country_code":"GR",
    "gn:dem":14,
    "gn:feature_class":"P",
    "gn:feature_code":"PPL",
    "gn:name":"N\u00e9a Kall\u00edsti",
    "gn:population":0,
    "gn:timezone":"Europe/Athens",
    "iso:country":"GR",
    "name:ell_x_preferred":[
        "\u039d\u03ad\u03b1 \u039a\u03b1\u03bb\u03bb\u03af\u03c3\u03c4\u03b7"
    ],
    "name:ell_x_variant":[
        "Kall\u00edsti"
    ],
    "name:und_x_variant":[
        "N\u00e9a Kall\u00edsti"
    ],
    "wof:name":"Nea Kallisti",
    "wof:placetype":"locality"
},
  "geometry": {"coordinates":[25.2133,41.03624],"type":"Point"}
}