{
  "type": "Feature",
  "properties": {
    "gn:admin1_code":"ESYE24",
    "gn:admin2_code":"29.0",
    "gn:admin3_code":"9163",
    "gn:asciiname":"Renginion",
    "gn:country_code":"GR",
    "gn:dem":179,
    "gn:feature_class":"P",
    "gn:feature_code":"PPL",
    "gn:name":"Reng\u00ednion",
    "gn:population":577,
    "gn:timezone":"Europe/Athens",
    "iso:country":"GR",
    "name:ell_x_preferred":[
        "\u03a1\u03b5\u03b3\u03ba\u03af\u03bd\u03b9"
    ],
    "name:ell_x_variant":[
        "\u03a1\u03b5\u03b3\u03ba\u03af\u03bd\u03b9\u03bf\u03bd"
    ],
    "name:eng_x_preferred":[
        "Regkini"
    ],
    "name:und_x_variant":[
        "Riy\u00edni",
        "Rig\u00edni",
        "Reng\u00ednion"
    ],
    "wof:name":"Renginion",
    "wof:placetype":"locality",
    "wof:population":577
},
  "geometry": {"coordinates":[22.71001,38.71957],"type":"Point"}
}