{
  "type": "Feature",
  "properties": {
    "gn:admin1_code":"ESYE13",
    "gn:admin2_code":"11.0",
    "gn:admin3_code":"9067",
    "gn:asciiname":"Komanos",
    "gn:country_code":"GR",
    "gn:dem":658,
    "gn:feature_class":"P",
    "gn:feature_code":"PPL",
    "gn:name":"K\u00f3manos",
    "gn:population":0,
    "gn:timezone":"Europe/Athens",
    "iso:country":"GR",
    "name:bul_x_preferred":[
        "\u041a\u043e\u043c\u0430\u043d"
    ],
    "name:ell_x_preferred":[
        "\u039a\u03cc\u03bc\u03b1\u03bd\u03bf\u03c2"
    ],
    "name:mkd_x_preferred":[
        "\u041a\u043e\u043c\u0430\u043d"
    ],
    "name:und_x_variant":[
        "K\u00f3manos"
    ],
    "wof:name":"Komanos",
    "wof:placetype":"locality"
},
  "geometry": {"coordinates":[21.76322,40.45525],"type":"Point"}
}