{
  "type": "Feature",
  "properties": {
    "gn:gn_country":"GR",
    "gn:gn_fcode":"PPL",
    "gn:gn_pop":63,
    "gn:population":39,
    "iso:country":"GR",
    "name:ell_x_preferred":[
        "\u0392\u03bf\u03c5\u03c4\u03b1\u03bd\u03c3\u03b1\u03af\u03bf\u03b9"
    ],
    "name:eng_x_preferred":[
        "Voutansaioi"
    ],
    "qs_pg:aaroncc":"GR",
    "qs_pg:gn_country":"GR",
    "qs_pg:gn_fcode":"PPL",
    "qs_pg:gn_pop":63,
    "qs_pg:name":"Voutansa\u00edoi",
    "qs_pg:photos_9r":0,
    "qs_pg:photos_sr":0,
    "qs_pg:pop_sr":1,
    "qs_pg:qs_pg_placetype":"locality",
    "wof:name":"Voutansa\u00edoi",
    "wof:placetype":"locality",
    "wof:population":39
},
  "geometry": {"coordinates":[21.00694,39.72778],"type":"Point"}
}