{
  "type": "Feature",
  "properties": {
    "gn:admin1_code":"ESYE21",
    "gn:admin2_code":"18.0",
    "gn:admin3_code":"9077",
    "gn:asciiname":"Koletsation",
    "gn:cc2":"GR",
    "gn:country_code":"GR",
    "gn:dem":451,
    "gn:feature_class":"P",
    "gn:feature_code":"PPL",
    "gn:name":"Kolets\u00e1tion",
    "gn:population":0,
    "gn:timezone":"Europe/Athens",
    "iso:country":"GR",
    "name:und_x_variant":[
        "Katlts\u00e1ti",
        "Kolets\u00e1tion"
    ],
    "wof:name":"Koletsation",
    "wof:placetype":"locality"
},
  "geometry": {"coordinates":[20.39889,39.48611],"type":"Point"}
}