{
  "type": "Feature",
  "properties": {
    "gn:admin1_code":"ESYE24",
    "gn:admin2_code":"34.0",
    "gn:admin3_code":"9152",
    "gn:asciiname":"Mirtea",
    "gn:cc2":"GR",
    "gn:country_code":"GR",
    "gn:dem":40,
    "gn:feature_class":"P",
    "gn:feature_code":"PPL",
    "gn:name":"Mirt\u00e9a",
    "gn:population":0,
    "gn:timezone":"Europe/Athens",
    "iso:country":"GR",
    "name:und_x_variant":[
        "Mourt\u00e1ra",
        "Mourtarion",
        "Mirt\u00e9a"
    ],
    "wof:name":"Mirtea",
    "wof:placetype":"locality"
},
  "geometry": {"coordinates":[24.12979,38.53255],"type":"Point"}
}