{
  "type": "Feature",
  "properties": {
    "gn:admin1_code":"ESYE25",
    "gn:admin2_code":"40.0",
    "gn:admin3_code":"9257",
    "gn:asciiname":"Methoni",
    "gn:country_code":"GR",
    "gn:dem":20,
    "gn:feature_class":"P",
    "gn:feature_code":"PPL",
    "gn:name":"Meth\u00f3ni",
    "gn:population":1165,
    "gn:timezone":"Europe/Athens",
    "iso:country":"GR",
    "name:ara_x_preferred":[
        "\u0645\u064a\u062b\u0648\u0646\u064a"
    ],
    "name:cat_x_preferred":[
        "Mod\u00f3"
    ],
    "name:cat_x_variant":[
        "Modona"
    ],
    "name:ceb_x_preferred":[
        "Meth\u00f3ni"
    ],
    "name:deu_x_preferred":[
        "Methoni"
    ],
    "name:ell_x_preferred":[
        "\u039c\u03b5\u03b8\u03ce\u03bd\u03b7"
    ],
    "name:ell_x_variant":[
        "\u039c\u03b5\u03b8\u03ce\u03bd\u03b7 \u039c\u03b5\u03c3\u03c3\u03b7\u03bd\u03af\u03b1\u03c2"
    ],
    "name:fas_x_preferred":[
        "\u0645\u062b\u0648\u0646\u06cc"
    ],
    "name:fin_x_preferred":[
        "Meth\u00f3ni"
    ],
    "name:fra_x_preferred":[
        "Modon"
    ],
    "name:glg_x_preferred":[
        "Modon"
    ],
    "name:hye_x_preferred":[
        "\u0544\u0565\u0569\u0578\u0576\u056b"
    ],
    "name:ita_x_preferred":[
        "Modone"
    ],
    "name:nld_x_preferred":[
        "Methone"
    ],
    "name:nno_x_preferred":[
        "Meth\u00f3ni"
    ],
    "name:pol_x_preferred":[
        "Metoni"
    ],
    "name:por_x_preferred":[
        "Modon"
    ],
    "name:ron_x_preferred":[
        "Methoni"
    ],
    "name:rus_x_preferred":[
        "\u041c\u0435\u0442\u043e\u043d\u0438"
    ],
    "name:spa_x_preferred":[
        "Modona"
    ],
    "name:swe_x_preferred":[
        "Methone"
    ],
    "name:tur_x_preferred":[
        "Methone"
    ],
    "name:vec_x_preferred":[
        "Modon"
    ],
    "wof:name":"Methoni",
    "wof:placetype":"locality",
    "wof:population":1165
},
  "geometry": {"coordinates":[21.70486,36.81973],"type":"Point"}
}