{
  "type": "Feature",
  "properties": {
    "gn:admin1_code":"ESYE25",
    "gn:admin2_code":"40.0",
    "gn:admin3_code":"9257",
    "gn:asciiname":"Methoni",
    "gn:country_code":"GR",
    "gn:dem":20,
    "gn:feature_class":"P",
    "gn:feature_code":"PPL",
    "gn:name":"Meth\u00f3ni",
    "gn:population":1165,
    "gn:timezone":"Europe/Athens",
    "iso:country":"GR",
    "name:cat_x_preferred":[
        "Mod\u00f3"
    ],
    "name:ell_x_preferred":[
        "\u039c\u03b5\u03b8\u03ce\u03bd\u03b7"
    ],
    "wof:name":"Methoni",
    "wof:placetype":"locality",
    "wof:population":1165
},
  "geometry": {"coordinates":[21.70486,36.81973],"type":"Point"}
}