{
  "type": "Feature",
  "properties": {
    "gn:admin1_code":"ESYE25",
    "gn:admin2_code":"40.0",
    "gn:admin3_code":"9258.0",
    "gn:asciiname":"Merolithi",
    "gn:country_code":"GR",
    "gn:dem":6,
    "gn:feature_class":"P",
    "gn:feature_code":"PPL",
    "gn:name":"Merolithi",
    "gn:population":0,
    "gn:timezone":"Europe/Athens",
    "iso:country":"GR",
    "name:ell_x_preferred":[
        "\u039c\u03b5\u03c1\u03bf\u03bb\u03af\u03b8\u03b9"
    ],
    "wof:name":"Merolithi",
    "wof:placetype":"locality"
},
  "geometry": {"coordinates":[21.57856,37.19185],"type":"Point"}
}