{
  "type": "Feature",
  "properties": {
    "gn:admin1_code":"ESYE23",
    "gn:admin2_code":"39.0",
    "gn:admin3_code":"9136",
    "gn:asciiname":"Barakitika",
    "gn:country_code":"GR",
    "gn:dem":210,
    "gn:feature_class":"P",
    "gn:feature_code":"PPL",
    "gn:name":"Barak\u00edtika",
    "gn:population":0,
    "gn:timezone":"Europe/Athens",
    "iso:country":"GR",
    "name:ell_x_preferred":[
        "Barak\u00edtika"
    ],
    "name:ell_x_variant":[
        "\u039c\u03c0\u03b1\u03c1\u03b1\u03ba\u03af\u03c4\u03b9\u03ba\u03b1"
    ],
    "wof:name":"Barakitika",
    "wof:placetype":"locality"
},
  "geometry": {"coordinates":[21.79103,37.55458],"type":"Point"}
}