{
  "type": "Feature",
  "properties": {
    "gn:admin1_code":"ESYE12",
    "gn:admin2_code":"15.0",
    "gn:admin3_code":"9059",
    "gn:asciiname":"Doumpia",
    "gn:country_code":"GR",
    "gn:dem":329,
    "gn:feature_class":"P",
    "gn:feature_code":"PPL",
    "gn:name":"Doumpi\u00e1",
    "gn:population":451,
    "gn:timezone":"Europe/Athens",
    "iso:country":"GR",
    "name:bul_x_preferred":[
        "\u0414\u0443\u043c\u0431\u0438\u044f"
    ],
    "name:ell_x_preferred":[
        "\u0394\u03bf\u03c5\u03bc\u03c0\u03b9\u03ac"
    ],
    "name:eng_x_preferred":[
        "Doumpia"
    ],
    "wof:name":"Doumpia",
    "wof:placetype":"locality",
    "wof:population":451
},
  "geometry": {"coordinates":[23.35058,40.51262],"type":"Point"}
}