{
  "type": "Feature",
  "properties": {
    "gn:admin1_code":"ESYE25",
    "gn:admin2_code":"42.0",
    "gn:admin3_code":"9248",
    "gn:asciiname":"Archia",
    "gn:country_code":"GR",
    "gn:dem":99,
    "gn:feature_class":"P",
    "gn:feature_code":"PPL",
    "gn:name":"Archi\u00e1",
    "gn:population":3,
    "gn:timezone":"Europe/Athens",
    "iso:country":"GR",
    "name:ell_x_preferred":[
        "\u0391\u03c1\u03c7\u03b9\u03ac"
    ],
    "name:eng_x_preferred":[
        "Archia"
    ],
    "wof:name":"Archia",
    "wof:placetype":"locality",
    "wof:population":3
},
  "geometry": {"coordinates":[22.3992,36.50436],"type":"Point"}
}