{
  "type": "Feature",
  "properties": {
    "gn:gn_country":"GR",
    "gn:gn_fcode":"PPL",
    "gn:gn_pop":0,
    "iso:country":"GR",
    "name:cat_x_preferred":[
        "Zakros"
    ],
    "name:ces_x_preferred":[
        "Kat\u00f3 Zakros"
    ],
    "name:deu_x_preferred":[
        "Palast von Zakros"
    ],
    "name:ell_x_preferred":[
        "\u0396\u03ac\u03ba\u03c1\u03bf\u03c2 \u039b\u03b1\u03c3\u03b9\u03b8\u03af\u03bf\u03c5"
    ],
    "name:eng_x_preferred":[
        "Zakros"
    ],
    "name:epo_x_preferred":[
        "Zakro"
    ],
    "name:fas_x_preferred":[
        "\u0632\u0627\u06a9\u0631\u0633"
    ],
    "name:fin_x_preferred":[
        "K\u00e1to Z\u00e1kros"
    ],
    "name:fra_x_preferred":[
        "Zakros"
    ],
    "name:ita_x_preferred":[
        "Zakros"
    ],
    "name:jpn_x_preferred":[
        "\u30b6\u30af\u30ed\u30b9"
    ],
    "name:lat_x_preferred":[
        "Zacrus"
    ],
    "name:nld_x_preferred":[
        "Zakros"
    ],
    "name:nob_x_preferred":[
        "Zakros"
    ],
    "name:oci_x_preferred":[
        "Zakros"
    ],
    "name:pol_x_preferred":[
        "Kato Zakros"
    ],
    "name:por_x_preferred":[
        "Zakros"
    ],
    "name:rus_x_preferred":[
        "\u0417\u0430\u043a\u0440\u043e\u0441"
    ],
    "name:slk_x_preferred":[
        "Kato Zakros"
    ],
    "name:spa_x_preferred":[
        "Zakros"
    ],
    "name:ukr_x_preferred":[
        "\u0417\u0430\u043a\u0440\u043e\u0441"
    ],
    "name:unk_x_variant":[
        "Ep\u00e1no Z\u00e1kros"
    ],
    "name:zho_x_preferred":[
        "\u624e\u514b\u7f85\u65af"
    ],
    "qs_pg:aaroncc":"GR",
    "qs_pg:gn_country":"GR",
    "qs_pg:gn_fcode":"PPL",
    "qs_pg:gn_pop":0,
    "qs_pg:name":"Apano Zakro",
    "qs_pg:name_adm0":"\u0395\u03bb\u03bb\u03ac\u03b4\u03b1",
    "qs_pg:name_adm1":"Crete",
    "qs_pg:photos":127,
    "qs_pg:photos_1k":26,
    "qs_pg:photos_9k":1,
    "qs_pg:photos_9r":3,
    "qs_pg:photos_all":127,
    "qs_pg:photos_sr":3,
    "qs_pg:pop_sr":0,
    "qs_pg:qs_pg_placetype":"locality",
    "qs_pg:qs_pg_placetype_gp":"Town",
    "qs_pg:woe_adm0":23424833,
    "woe:adm0_id":23424833,
    "woe:name_adm0":"\u0395\u03bb\u03bb\u03ac\u03b4\u03b1",
    "woe:name_adm1":"Crete",
    "woe:placetype":"Town",
    "wof:name":"Apano Zakro",
    "wof:placetype":"locality"
},
  "geometry": {"coordinates":[26.21724,35.11373],"type":"Point"}
}