{
  "type": "Feature",
  "properties": {
    "gn:admin1_code":"ESYE25",
    "gn:admin2_code":"40.0",
    "gn:admin3_code":"9253",
    "gn:asciiname":"Charavgi",
    "gn:country_code":"GR",
    "gn:dem":401,
    "gn:feature_class":"P",
    "gn:feature_code":"PPL",
    "gn:name":"Charavg\u00ed",
    "gn:population":48,
    "gn:timezone":"Europe/Athens",
    "iso:country":"GR",
    "name:ell_x_preferred":[
        "\u03a7\u03b1\u03c1\u03b1\u03c5\u03b3\u03ae"
    ],
    "name:eng_x_preferred":[
        "Charavgi"
    ],
    "name:und_x_variant":[
        "Trik\u00f3tsova",
        "Kharavy\u00ed"
    ],
    "wof:name":"Charavgi",
    "wof:placetype":"locality",
    "wof:population":48
},
  "geometry": {"coordinates":[22.18019,36.9778],"type":"Point"}
}