{
  "type": "Feature",
  "properties": {
    "gn:admin1_code":"ESYE23",
    "gn:admin2_code":"31.0",
    "gn:admin3_code":"9123",
    "gn:asciiname":"Xirakia",
    "gn:country_code":"GR",
    "gn:dem":434,
    "gn:feature_class":"P",
    "gn:feature_code":"PPL",
    "gn:name":"Xir\u00e1kia",
    "gn:population":29,
    "gn:timezone":"Europe/Athens",
    "iso:country":"GR",
    "name:ell_x_preferred":[
        "\u039e\u03b7\u03c1\u03ac\u03ba\u03b9\u03b1"
    ],
    "name:eng_x_preferred":[
        "Xirakia"
    ],
    "name:und_x_variant":[
        "Ksirakia"
    ],
    "wof:name":"Xirakia",
    "wof:placetype":"locality",
    "wof:population":29
},
  "geometry": {"coordinates":[21.5214,38.71647],"type":"Point"}
}