{
  "type": "Feature",
  "properties": {
    "gn:admin1_code":"ESYE25",
    "gn:admin2_code":"40.0",
    "gn:admin3_code":"9256",
    "gn:asciiname":"Oichalia",
    "gn:country_code":"GR",
    "gn:dem":90,
    "gn:feature_class":"P",
    "gn:feature_code":"PPL",
    "gn:name":"Oichal\u00eda",
    "gn:population":0,
    "gn:timezone":"Europe/Athens",
    "iso:country":"GR",
    "name:ceb_x_preferred":[
        "Oichalia"
    ],
    "name:deu_x_preferred":[
        "Oichalia"
    ],
    "name:ell_x_preferred":[
        "\u039f\u03b9\u03c7\u03b1\u03bb\u03af\u03b1"
    ],
    "name:ell_x_variant":[
        "Oichal\u00eda"
    ],
    "name:ita_x_preferred":[
        "Oichalia"
    ],
    "name:swe_x_preferred":[
        "Oichalia"
    ],
    "name:und_x_variant":[
        "Alichelep\u00ed",
        "Al\u00ed Tselep\u00ed",
        "Oikhal\u00eda"
    ],
    "wof:name":"Oichalia",
    "wof:placetype":"locality"
},
  "geometry": {"coordinates":[21.99847,37.25417],"type":"Point"}
}