{
  "type": "Feature",
  "properties": {
    "gn:admin1_code":"ESYE23",
    "gn:admin2_code":"38.0",
    "gn:admin3_code":"9130",
    "gn:asciiname":"Sinania",
    "gn:country_code":"GR",
    "gn:dem":366,
    "gn:feature_class":"P",
    "gn:feature_code":"PPL",
    "gn:name":"Sinani\u00e1",
    "gn:population":0,
    "gn:timezone":"Europe/Athens",
    "iso:country":"GR",
    "name:und_x_variant":[
        "Sinani\u00e1"
    ],
    "wof:name":"Sinania",
    "wof:placetype":"locality"
},
  "geometry": {"coordinates":[21.99157,38.26288],"type":"Point"}
}