{
  "type": "Feature",
  "properties": {
    "gn:country":"GR",
    "gn:fcode":"PPL",
    "gn:population":14,
    "iso:country":"GR",
    "name:ell_x_preferred":[
        "\u039d\u03b1\u03b3\u03cc\u03c2"
    ],
    "name:eng_x_preferred":[
        "Naghos"
    ],
    "name:eng_x_variant":[
        "Nagos"
    ],
    "name:rus_x_preferred":[
        "\u041d\u0430\u0433\u043e\u0441"
    ],
    "qs_pg:aaroncc":"GR",
    "qs_pg:gn_country":"GR",
    "qs_pg:gn_fcode":"PPL",
    "qs_pg:gn_pop":14,
    "qs_pg:name":"Nagos",
    "qs_pg:name_adm0":"\u0395\u03bb\u03bb\u03ac\u03b4\u03b1",
    "qs_pg:name_adm1":"Aegean",
    "qs_pg:photos_9k":1,
    "qs_pg:photos_9r":1,
    "qs_pg:photos_all":14,
    "qs_pg:photos_sr":0,
    "qs_pg:pop_sr":1,
    "qs_pg:qs_pg_placetype":"locality",
    "qs_pg:qs_pg_placetype_gp":"Town",
    "qs_pg:woe_adm0":23424833,
    "woe:adm0_id":23424833,
    "woe:name_adm0":"\u0395\u03bb\u03bb\u03ac\u03b4\u03b1",
    "woe:name_adm1":"Aegean",
    "woe:placetype":"Town",
    "wof:name":"Nagos",
    "wof:placetype":"locality",
    "wof:population":14
},
  "geometry": {"coordinates":[26.08333,38.55823],"type":"Point"}
}