{
  "type": "Feature",
  "properties": {
    "gn:country":"GR",
    "gn:fcode":"PPL",
    "gn:population":2314,
    "iso:country":"GR",
    "name:ara_x_preferred":[
        "\u0625\u0641\u0631\u0648\u0628\u0648\u0633"
    ],
    "name:bul_x_preferred":[
        "\u0410\u0448\u0438\u043a\u043b\u0430\u0440"
    ],
    "name:ceb_x_preferred":[
        "Evrop\u00f3s"
    ],
    "name:ell_x_preferred":[
        "\u0395\u03c5\u03c1\u03c9\u03c0\u03cc\u03c2"
    ],
    "name:eng_x_preferred":[
        "Evropos"
    ],
    "name:fin_x_preferred":[
        "Evrop\u00f3s"
    ],
    "name:fra_x_preferred":[
        "Evropos"
    ],
    "name:fra_x_variant":[
        "Europos"
    ],
    "name:ita_x_preferred":[
        "Evropos"
    ],
    "name:jpn_x_preferred":[
        "\u30a8\u30f4\u30ed\u30dd\u30b9"
    ],
    "name:mkd_x_preferred":[
        "\u0410\u0448\u0438\u043a\u043b\u0430\u0440"
    ],
    "name:nld_x_preferred":[
        "Evropos"
    ],
    "name:nno_x_preferred":[
        "Evrop\u00f3s"
    ],
    "name:rus_x_preferred":[
        "\u042d\u0432\u0440\u043e\u043f\u043e\u0441"
    ],
    "name:swe_x_preferred":[
        "Evrop\u00f3s"
    ],
    "name:und_x_variant":[
        "Asikl\u00e1r"
    ],
    "qs_pg:aaroncc":"GR",
    "qs_pg:gn_country":"GR",
    "qs_pg:gn_fcode":"PPL",
    "qs_pg:gn_pop":2314,
    "qs_pg:name":"Evropos",
    "qs_pg:name_adm0":"\u0395\u03bb\u03bb\u03ac\u03b4\u03b1",
    "qs_pg:name_adm1":"Macedonia and Thrace",
    "qs_pg:photos_9k":1,
    "qs_pg:photos_9r":1,
    "qs_pg:photos_all":1,
    "qs_pg:photos_sr":0,
    "qs_pg:pop_sr":4,
    "qs_pg:qs_pg_placetype":"locality",
    "qs_pg:qs_pg_placetype_gp":"Town",
    "qs_pg:woe_adm0":23424833,
    "woe:adm0_id":23424833,
    "woe:name_adm0":"\u0395\u03bb\u03bb\u03ac\u03b4\u03b1",
    "woe:name_adm1":"Macedonia and Thrace",
    "woe:placetype":"Town",
    "wof:name":"Evropos",
    "wof:placetype":"locality",
    "wof:population":2314
},
  "geometry": {"coordinates":[22.54472,40.89444],"type":"Point"}
}