{
  "type": "Feature",
  "properties": {
    "gn:gn_country":"GR",
    "gn:gn_fcode":"PPL",
    "gn:gn_pop":1308,
    "gn:population":1992,
    "iso:country":"GR",
    "name:ell_x_historical":[
        "\u039a\u03b1\u03ca\u03c3\u03bb\u03ac\u03c1",
        "\u039c\u03c0\u03b1\u03ca\u03c3\u03bb\u03ac\u03c1"
    ],
    "name:ell_x_preferred":[
        "\u03a4\u03b5\u03c1\u03c8\u03b9\u03b8\u03ad\u03b1"
    ],
    "name:ell_x_variant":[
        "\u039a\u03b1\u03ca\u03c3\u03bb\u03ac\u03c1",
        "\u039c\u03c0\u03b1\u03ca\u03c3\u03bb\u03ac\u03c1"
    ],
    "name:eng_x_preferred":[
        "Terpsithea"
    ],
    "name:unk_x_variant":[
        "Ka\u00efsl\u00e1r"
    ],
    "qs_pg:aaroncc":"GR",
    "qs_pg:gn_country":"GR",
    "qs_pg:gn_fcode":"PPL",
    "qs_pg:gn_pop":1308,
    "qs_pg:name":"Terpsithea",
    "qs_pg:name_adm0":"\u0395\u03bb\u03bb\u03ac\u03b4\u03b1",
    "qs_pg:name_adm1":"Thessaly and Continental Greece",
    "qs_pg:photos_9k":1,
    "qs_pg:photos_9r":1,
    "qs_pg:photos_all":2,
    "qs_pg:photos_sr":0,
    "qs_pg:pop_sr":3,
    "qs_pg:qs_pg_placetype":"locality",
    "qs_pg:qs_pg_placetype_gp":"Town",
    "qs_pg:woe_adm0":23424833,
    "woe:adm0_id":23424833,
    "woe:name_adm0":"\u0395\u03bb\u03bb\u03ac\u03b4\u03b1",
    "woe:name_adm1":"Thessaly and Continental Greece",
    "woe:placetype":"Town",
    "wof:name":"Terpsithea",
    "wof:placetype":"locality",
    "wof:population":1992
},
  "geometry": {"coordinates":[22.36667,39.61667],"type":"Point"}
}