{
  "type": "Feature",
  "properties": {
    "gn:gn_country":"GR",
    "gn:gn_fcode":"PPL",
    "gn:gn_pop":860,
    "gn:population":860,
    "iso:country":"GR",
    "name:ara_x_preferred":[
        "\u0641\u0631\u064a\u0646\u0627\u060c \u0625\u0644\u064a\u0627"
    ],
    "name:ara_x_variant":[
        "\u0641\u0631\u064a\u0646\u0627"
    ],
    "name:ceb_x_preferred":[
        "Vr\u00edna"
    ],
    "name:ell_x_preferred":[
        "\u0392\u03c1\u03af\u03bd\u03b1"
    ],
    "name:ell_x_variant":[
        "\u0392\u03c1\u03af\u03bd\u03b1 \u0397\u03bb\u03b5\u03af\u03b1\u03c2"
    ],
    "name:eng_x_preferred":[
        "Vrina"
    ],
    "name:swe_x_preferred":[
        "Vr\u00edna"
    ],
    "name:unk_x_variant":[
        "Vr\u00edna"
    ],
    "qs_pg:aaroncc":"GR",
    "qs_pg:gn_country":"GR",
    "qs_pg:gn_fcode":"PPL",
    "qs_pg:gn_pop":860,
    "qs_pg:name":"Vrina",
    "qs_pg:name_adm0":"\u0395\u03bb\u03bb\u03ac\u03b4\u03b1",
    "qs_pg:name_adm1":"Peloponnese Western Greece and the Ionian Islands",
    "qs_pg:photos_9r":0,
    "qs_pg:photos_sr":0,
    "qs_pg:pop_sr":2,
    "qs_pg:qs_pg_placetype":"locality",
    "qs_pg:qs_pg_placetype_gp":"Town",
    "qs_pg:woe_adm0":23424833,
    "woe:adm0_id":23424833,
    "woe:name_adm0":"\u0395\u03bb\u03bb\u03ac\u03b4\u03b1",
    "woe:name_adm1":"Peloponnese Western Greece and the Ionian Islands",
    "woe:placetype":"Town",
    "wof:name":"Vrina",
    "wof:placetype":"locality",
    "wof:population":860
},
  "geometry": {"coordinates":[21.63333,37.56667],"type":"Point"}
}