{
  "type": "Feature",
  "properties": {
    "gn:population":1772,
    "iso:country":"GR",
    "name:ara_x_preferred":[
        "\u0641\u064a\u0644\u0648\u062a\u0627\u0633"
    ],
    "name:bul_x_preferred":[
        "\u0427\u0430\u043b\u0434\u0436\u0438\u0435\u0432\u043e"
    ],
    "name:ceb_x_preferred":[
        "Fil\u00f3tas"
    ],
    "name:ell_x_historical":[
        "\u03a4\u03c3\u03b1\u03bb\u03c4\u03b6\u03b9\u03bb\u03ac\u03c1"
    ],
    "name:ell_x_preferred":[
        "\u0394\u03ae\u03bc\u03bf\u03c2 \u03a6\u03b9\u03bb\u03ce\u03c4\u03b1"
    ],
    "name:ell_x_variant":[
        "\u03a6\u03b9\u03bb\u03ce\u03c4\u03b1\u03c2",
        "\u03a4\u03c3\u03b1\u03bb\u03c4\u03b6\u03b9\u03bb\u03ac\u03c1"
    ],
    "name:eng_x_preferred":[
        "Filotas"
    ],
    "name:fin_x_preferred":[
        "Fil\u00f3tas"
    ],
    "name:ita_x_preferred":[
        "Filotas"
    ],
    "name:nld_x_preferred":[
        "Filotas"
    ],
    "name:nno_x_preferred":[
        "Fil\u00f3tas"
    ],
    "name:ron_x_preferred":[
        "Filotas"
    ],
    "name:swe_x_preferred":[
        "Fil\u00f3tas"
    ],
    "name:unk_x_variant":[
        "Chaljil\u00e1r"
    ],
    "qs:a0":"Greece",
    "qs:a1":"*\u0394\u03a5\u03a4\u0399\u039a\u0397 \u039c\u0391\u039a\u0395\u0394\u039f\u039d\u0399\u0391",
    "qs:a1_alt":"DYTIKH MAKEDONIA",
    "qs:a1r":"0",
    "qs:a2_alt":"FLVRINA",
    "qs:adm0":"Greece",
    "qs:la_lc":"*",
    "qs:level":"locality",
    "qs:loc":"\u03a6\u0399\u039b\u03a9\u03a4\u0391\u03a3",
    "qs:loc_alt":"FILVTAS",
    "qs:pop":0,
    "qs:type":"buffered point",
    "wd:wordcount":69,
    "wof:name":"\u03a6\u0399\u039b\u03a9\u03a4\u0391\u03a3",
    "wof:placetype":"locality",
    "wof:population":1772
},
  "geometry": {"coordinates":[21.707587,40.624375],"type":"Point"}
}