{
  "type": "Feature",
  "properties": {
    "gn:country":"GR",
    "gn:fcode":"PPL",
    "gn:population":365,
    "iso:country":"GR",
    "name:ceb_x_preferred":[
        "Klimati\u00e1"
    ],
    "name:deu_x_preferred":[
        "Klimatia"
    ],
    "name:ell_x_preferred":[
        "\u039a\u03bb\u03b7\u03bc\u03b1\u03c4\u03b9\u03ac"
    ],
    "name:ell_x_variant":[
        "\u039a\u03bb\u03b7\u03bc\u03b1\u03c4\u03b9\u03ac \u039a\u03ad\u03c1\u03ba\u03c5\u03c1\u03b1\u03c2"
    ],
    "name:eng_x_preferred":[
        "Klimatia"
    ],
    "name:nld_x_preferred":[
        "Klimatia"
    ],
    "name:swe_x_preferred":[
        "Klimati\u00e1"
    ],
    "qs_pg:aaroncc":"GR",
    "qs_pg:gn_country":"GR",
    "qs_pg:gn_fcode":"PPL",
    "qs_pg:gn_pop":365,
    "qs_pg:name":"Klimatia",
    "qs_pg:name_adm0":"\u0395\u03bb\u03bb\u03ac\u03b4\u03b1",
    "qs_pg:name_adm1":"Peloponnese Western Greece and the Ionian Islands",
    "qs_pg:photos_9r":0,
    "qs_pg:photos_sr":0,
    "qs_pg:pop_sr":2,
    "qs_pg:qs_pg_placetype":"locality",
    "qs_pg:qs_pg_placetype_gp":"Town",
    "qs_pg:woe_adm0":23424833,
    "woe:adm0_id":23424833,
    "woe:name_adm0":"\u0395\u03bb\u03bb\u03ac\u03b4\u03b1",
    "woe:name_adm1":"Peloponnese Western Greece and the Ionian Islands",
    "woe:placetype":"Town",
    "wof:name":"Klimatia",
    "wof:placetype":"locality",
    "wof:population":229
},
  "geometry": {"coordinates":[19.7825,39.73917],"type":"Point"}
}