{
  "type": "Feature",
  "properties": {
    "gn:gn_country":"GR",
    "gn:gn_fcode":"PPL",
    "gn:gn_pop":183,
    "gn:population":183,
    "iso:country":"GR",
    "name:ell_x_preferred":[
        "\u039b\u03b1\u03b3\u03ba\u03b1\u03b4\u03b9\u03ac"
    ],
    "name:unk_x_variant":[
        "Langadhi\u00e1"
    ],
    "qs_pg:aaroncc":"GR",
    "qs_pg:gn_country":"GR",
    "qs_pg:gn_fcode":"PPL",
    "qs_pg:gn_pop":183,
    "qs_pg:name":"Lagkadi\u00e1",
    "qs_pg:photos_9r":0,
    "qs_pg:photos_sr":0,
    "qs_pg:pop_sr":1,
    "qs_pg:qs_pg_placetype":"locality",
    "wof:name":"Lagkadi\u00e1",
    "wof:placetype":"locality",
    "wof:population":183
},
  "geometry": {"coordinates":[21.82222,39.65389],"type":"Point"}
}