{
  "type": "Feature",
  "properties": {
    "gn:admin1_code":"ESYE42",
    "gn:admin2_code":"49.0",
    "gn:admin3_code":"9282",
    "gn:asciiname":"Kato Meria",
    "gn:country_code":"GR",
    "gn:dem":393,
    "gn:feature_class":"P",
    "gn:feature_code":"PPL",
    "gn:name":"K\u00e1to Meri\u00e1",
    "gn:population":0,
    "gn:timezone":"Europe/Athens",
    "iso:country":"GR",
    "name:ell_x_preferred":[
        "K\u00e1to Meri\u00e1"
    ],
    "name:ell_x_variant":[
        "\u039a\u03ac\u03c4\u03c9 \u039c\u03b5\u03c1\u03b9\u03ac"
    ],
    "wof:name":"Kato Meria",
    "wof:placetype":"locality"
},
  "geometry": {"coordinates":[24.31902,37.58662],"type":"Point"}
}