{
  "type": "Feature",
  "properties": {
    "gn:admin1_code":"ESYE14",
    "gn:admin2_code":"24.0",
    "gn:admin3_code":"9105",
    "gn:asciiname":"Katichori",
    "gn:country_code":"GR",
    "gn:dem":520,
    "gn:feature_class":"P",
    "gn:feature_code":"PPL",
    "gn:name":"Katich\u00f3ri",
    "gn:population":0,
    "gn:timezone":"Europe/Athens",
    "iso:country":"GR",
    "name:ell_x_preferred":[
        "\u039a\u03b1\u03c4\u03b7\u03c7\u03ce\u03c1\u03b9"
    ],
    "name:ell_x_variant":[
        "\u039a\u03b1\u03c4\u03b7\u03c7\u03ce\u03c1\u03b9\u03bf\u03bd",
        "\u039a\u03b1\u03c4\u03c9\u03c7\u03ce\u03c1\u03b9",
        "\u039a\u03b1\u03c4\u03c9\u03c7\u03ce\u03c1\u03b9\u03bf\u03bd"
    ],
    "name:und_x_variant":[
        "Katik\u00f3ri",
        "Katokh\u00f3rion",
        "Katich\u00f3ri",
        "Katich\u00f3rion"
    ],
    "wof:name":"Katichori",
    "wof:placetype":"locality"
},
  "geometry": {"coordinates":[22.99636,39.38239],"type":"Point"}
}