{
  "type": "Feature",
  "properties": {
    "gn:admin1_code":"ESYE43",
    "gn:admin2_code":"43.0",
    "gn:admin3_code":"9324",
    "gn:asciiname":"Askyfou",
    "gn:country_code":"GR",
    "gn:dem":682,
    "gn:feature_class":"P",
    "gn:feature_code":"PPLS",
    "gn:name":"Ask\u00fdfou",
    "gn:population":0,
    "gn:timezone":"Europe/Athens",
    "iso:country":"GR",
    "name:ell_x_preferred":[
        "\u0391\u03c3\u03ba\u03cd\u03c6\u03bf\u03c5"
    ],
    "name:eng_x_preferred":[
        "Askyfou"
    ],
    "name:und_x_variant":[
        "Ask\u00fdfou",
        "Ask\u00edfou"
    ],
    "wof:name":"Askyfou",
    "wof:placetype":"locality"
},
  "geometry": {"coordinates":[24.18443,35.29201],"type":"Point"}
}