{
  "type": "Feature",
  "properties": {
    "gn:admin1_code":"ESYE42",
    "gn:admin2_code":"49.0",
    "gn:admin3_code":"9268.0",
    "gn:asciiname":"Aladino",
    "gn:country_code":"GR",
    "gn:dem":140,
    "gn:feature_class":"P",
    "gn:feature_code":"PPL",
    "gn:name":"Aladino",
    "gn:population":0,
    "gn:timezone":"Europe/Athens",
    "iso:country":"GR",
    "name:ell_x_historical":[
        "\u0391\u03bb\u03b1\u03b4\u03b9\u03bd\u03cc\u03bd"
    ],
    "name:ell_x_preferred":[
        "\u0391\u03bb\u03b1\u03b4\u03b9\u03bd\u03cc"
    ],
    "name:ell_x_variant":[
        "\u0391\u03bb\u03b1\u03b4\u03b9\u03bd\u03cc\u03bd"
    ],
    "wof:name":"Aladino",
    "wof:placetype":"locality"
},
  "geometry": {"coordinates":[24.89742,37.81176],"type":"Point"}
}