{
  "type": "Feature",
  "properties": {
    "gn:admin1_code":"ESYE12",
    "gn:admin2_code":"15.0",
    "gn:admin3_code":"9059",
    "gn:asciiname":"Riza",
    "gn:country_code":"GR",
    "gn:dem":363,
    "gn:feature_class":"P",
    "gn:feature_code":"PPL",
    "gn:name":"Riz\u00e1",
    "gn:population":487,
    "gn:timezone":"Europe/Athens",
    "iso:country":"GR",
    "name:bel_x_preferred":[
        "\u0410\u0431\u043a\u043b\u0430\u0434 \u0456\u043a\u043e\u043d\u044b"
    ],
    "name:ell_x_historical":[
        "\u03a3\u03b9\u03c0\u03bf\u03c4\u03bd\u03af\u03ba\u03b9\u03b1"
    ],
    "name:ell_x_preferred":[
        "\u03a1\u03b9\u03b6\u03ac"
    ],
    "name:ell_x_variant":[
        "\u03a3\u03b9\u03c0\u03bf\u03c4\u03bd\u03af\u03ba\u03b9\u03b1"
    ],
    "name:eng_x_preferred":[
        "Riza"
    ],
    "name:fin_x_preferred":[
        "Riisa"
    ],
    "name:hrv_x_preferred":[
        "Riza"
    ],
    "name:ita_x_preferred":[
        "Riza"
    ],
    "name:jpn_x_preferred":[
        "\u30ea\u30b6"
    ],
    "name:pol_x_preferred":[
        "Ryza"
    ],
    "name:rus_x_preferred":[
        "\u041e\u043a\u043b\u0430\u0434 \u0438\u043a\u043e\u043d\u044b"
    ],
    "name:ukr_x_preferred":[
        "\u0428\u0430\u0442\u0438 \u0456\u043a\u043e\u043d\u0438"
    ],
    "name:und_x_variant":[
        "Sepotn\u00edkia",
        "Riz\u00e1"
    ],
    "wof:name":"Riza",
    "wof:placetype":"locality",
    "wof:population":487
},
  "geometry": {"coordinates":[23.44294,40.50545],"type":"Point"}
}