{
  "type": "Feature",
  "properties": {
    "gn:admin1_code":"ESYE12",
    "gn:admin2_code":"15.0",
    "gn:admin3_code":"9059",
    "gn:asciiname":"Riza",
    "gn:country_code":"GR",
    "gn:dem":363,
    "gn:feature_class":"P",
    "gn:feature_code":"PPL",
    "gn:name":"Riz\u00e1",
    "gn:population":487,
    "gn:timezone":"Europe/Athens",
    "iso:country":"GR",
    "name:ell_x_historical":[
        "\u03a3\u03b9\u03c0\u03bf\u03c4\u03bd\u03af\u03ba\u03b9\u03b1"
    ],
    "name:ell_x_preferred":[
        "\u03a1\u03b9\u03b6\u03ac"
    ],
    "name:ell_x_variant":[
        "\u03a3\u03b9\u03c0\u03bf\u03c4\u03bd\u03af\u03ba\u03b9\u03b1"
    ],
    "name:eng_x_preferred":[
        "Riza"
    ],
    "name:und_x_variant":[
        "Sepotn\u00edkia",
        "Riz\u00e1"
    ],
    "wof:name":"Riza",
    "wof:placetype":"locality",
    "wof:population":487
},
  "geometry": {"coordinates":[23.44294,40.50545],"type":"Point"}
}