{
  "type": "Feature",
  "properties": {
    "gn:country":"GR",
    "gn:fcode":"PPL",
    "gn:population":985,
    "iso:country":"GR",
    "name:ara_x_preferred":[
        "\u0644\u0648\u062a\u0631\u0648\u0633\u060c \u0625\u0641\u0631\u0648\u0633"
    ],
    "name:ara_x_variant":[
        "\u0644\u0648\u062a\u0631\u0648\u0633"
    ],
    "name:arz_x_preferred":[
        "\u0644\u0648\u062a\u0631\u0648\u0633"
    ],
    "name:bul_x_preferred":[
        "\u041b\u044a\u0434\u0436\u0430\u043a\u044c\u043e\u0439"
    ],
    "name:ceb_x_preferred":[
        "Loutr\u00f3s"
    ],
    "name:ell_x_preferred":[
        "\u039b\u03bf\u03c5\u03c4\u03c1\u03cc\u03c2"
    ],
    "name:ell_x_variant":[
        "\u039b\u03bf\u03c5\u03c4\u03c1\u03cc\u03c2 \u0388\u03b2\u03c1\u03bf\u03c5"
    ],
    "name:eng_x_preferred":[
        "Loutros"
    ],
    "name:mkd_x_preferred":[
        "\u041b\u0430\u045f\u0430\u045c\u043e\u0458"
    ],
    "name:nld_x_preferred":[
        "Loutros"
    ],
    "name:por_x_preferred":[
        "Lutr\u00f3s"
    ],
    "name:swe_x_preferred":[
        "Loutr\u00f3s"
    ],
    "name:tur_x_preferred":[
        "Ulucabeyk\u00f6y"
    ],
    "name:und_x_variant":[
        "Ilitr\u00e1"
    ],
    "qs_pg:aaroncc":"GR",
    "qs_pg:gn_country":"GR",
    "qs_pg:gn_fcode":"PPL",
    "qs_pg:gn_pop":985,
    "qs_pg:name":"Loutros",
    "qs_pg:name_adm0":"\u0395\u03bb\u03bb\u03ac\u03b4\u03b1",
    "qs_pg:name_adm1":"Macedonia and Thrace",
    "qs_pg:photos_9k":1,
    "qs_pg:photos_9r":1,
    "qs_pg:photos_all":7,
    "qs_pg:photos_sr":0,
    "qs_pg:pop_sr":2,
    "qs_pg:qs_pg_placetype":"locality",
    "qs_pg:qs_pg_placetype_gp":"Town",
    "qs_pg:woe_adm0":23424833,
    "woe:adm0_id":23424833,
    "woe:name_adm0":"\u0395\u03bb\u03bb\u03ac\u03b4\u03b1",
    "woe:name_adm1":"Macedonia and Thrace",
    "woe:placetype":"Town",
    "wof:name":"Loutros",
    "wof:placetype":"locality",
    "wof:population":985
},
  "geometry": {"coordinates":[26.04361,40.87917],"type":"Point"}
}