{
  "type": "Feature",
  "properties": {
    "gn:admin1_code":"ESYE23",
    "gn:admin2_code":"31.0",
    "gn:admin3_code":"9128",
    "gn:asciiname":"Achladokastro",
    "gn:country_code":"GR",
    "gn:dem":747,
    "gn:feature_class":"P",
    "gn:feature_code":"PPL",
    "gn:name":"Achlad\u00f3kastro",
    "gn:population":0,
    "gn:timezone":"Europe/Athens",
    "iso:country":"GR",
    "name:ell_x_preferred":[
        "Achlad\u00f3kastro"
    ],
    "name:ell_x_variant":[
        "\u0391\u03c7\u03bb\u03b1\u03b4\u03cc\u03ba\u03b1\u03c3\u03c4\u03c1\u03bf",
        "Achlad\u00f3kastron",
        "\u0391\u03c7\u03bb\u03b1\u03b4\u03cc\u03ba\u03b1\u03c3\u03c4\u03c1\u03bf\u03bd"
    ],
    "name:und_x_variant":[
        "Artot\u00edva",
        "Akhadh\u00f3kastron",
        "Akhladh\u00f3kastron"
    ],
    "wof:name":"Achladokastro",
    "wof:placetype":"locality"
},
  "geometry": {"coordinates":[21.75011,38.58144],"type":"Point"}
}