{
  "type": "Feature",
  "properties": {
    "gn:admin1_code":"ESYE24",
    "gn:admin2_code":"34.0",
    "gn:admin3_code":"9152",
    "gn:asciiname":"Orion",
    "gn:country_code":"GR",
    "gn:dem":35,
    "gn:feature_class":"P",
    "gn:feature_code":"PPL",
    "gn:name":"\u00d3rion",
    "gn:population":0,
    "gn:timezone":"Europe/Athens",
    "iso:country":"GR",
    "wof:name":"Orion",
    "wof:placetype":"locality"
},
  "geometry": {"coordinates":[24.11888,38.53596],"type":"Point"}
}