{
  "type": "Feature",
  "properties": {
    "gn:admin1_code":"ESYE23",
    "gn:admin2_code":"39.0",
    "gn:admin3_code":"9138",
    "gn:asciiname":"Faskomilia",
    "gn:cc2":"GR",
    "gn:country_code":"GR",
    "gn:dem":400,
    "gn:feature_class":"P",
    "gn:feature_code":"PPL",
    "gn:name":"Faskomili\u00e1",
    "gn:population":0,
    "gn:timezone":"Europe/Athens",
    "iso:country":"GR",
    "name:und_x_variant":[
        "Moundr\u00e1",
        "Moutr\u00e1",
        "Faskomili\u00e1"
    ],
    "wof:name":"Faskomilia",
    "wof:placetype":"locality"
},
  "geometry": {"coordinates":[21.75344,37.43963],"type":"Point"}
}