{
  "type": "Feature",
  "properties": {
    "gn:admin1_code":"ESYE25",
    "gn:admin2_code":"40.0",
    "gn:admin3_code":"9253",
    "gn:asciiname":"Kalivai",
    "gn:cc2":"GR",
    "gn:country_code":"GR",
    "gn:dem":222,
    "gn:feature_class":"P",
    "gn:feature_code":"PPL",
    "gn:name":"Kal\u00edvai",
    "gn:population":0,
    "gn:timezone":"Europe/Athens",
    "iso:country":"GR",
    "name:und_x_variant":[
        "Kal\u00edves"
    ],
    "wof:name":"Kalivai",
    "wof:placetype":"locality"
},
  "geometry": {"coordinates":[22.24517,36.90365],"type":"Point"}
}