{
  "type": "Feature",
  "properties": {
    "gn:admin1_code":"ESYE25",
    "gn:admin2_code":"41.0",
    "gn:admin3_code":"9237",
    "gn:asciiname":"Oreini Meligou",
    "gn:country_code":"GR",
    "gn:dem":620,
    "gn:feature_class":"P",
    "gn:feature_code":"PPL",
    "gn:name":"Orein\u00ed Meligo\u00fa",
    "gn:population":0,
    "gn:timezone":"Europe/Athens",
    "iso:country":"GR",
    "name:ell_x_preferred":[
        "Orein\u00ed Meligo\u00fa"
    ],
    "name:ell_x_variant":[
        "\u039f\u03c1\u03b5\u03b9\u03bd\u03ae \u039c\u03b5\u03bb\u03b9\u03b3\u03bf\u03cd"
    ],
    "name:und_x_variant":[
        "Meligo\u00fa",
        "Orin\u00ed Meligo\u00fa"
    ],
    "wof:name":"Oreini Meligou",
    "wof:placetype":"locality"
},
  "geometry": {"coordinates":[22.65753,37.35871],"type":"Point"}
}