{
  "type": "Feature",
  "properties": {
    "gn:admin1_code":"ESYE23",
    "gn:admin2_code":"39.0",
    "gn:admin3_code":"9138",
    "gn:asciiname":"Arini",
    "gn:country_code":"GR",
    "gn:dem":204,
    "gn:feature_class":"P",
    "gn:feature_code":"PPL",
    "gn:name":"Ar\u00edni",
    "gn:population":0,
    "gn:timezone":"Europe/Athens",
    "iso:country":"GR",
    "name:ceb_x_preferred":[
        "Arini"
    ],
    "name:deu_x_preferred":[
        "Arini"
    ],
    "name:ell_x_preferred":[
        "Ar\u00edni"
    ],
    "name:ell_x_variant":[
        "\u0391\u03c1\u03ae\u03bd\u03b7"
    ],
    "name:epo_x_preferred":[
        "Arini"
    ],
    "name:hun_x_preferred":[
        "Arini"
    ],
    "name:ron_x_preferred":[
        "Arini"
    ],
    "name:swe_x_preferred":[
        "Arini"
    ],
    "wof:name":"Arini",
    "wof:placetype":"locality"
},
  "geometry": {"coordinates":[21.69936,37.49958],"type":"Point"}
}