{
  "type": "Feature",
  "properties": {
    "gn:gn_country":"GR",
    "gn:gn_fcode":"PPL",
    "gn:gn_pop":854,
    "gn:population":854,
    "iso:country":"GR",
    "name:bul_x_preferred":[
        "\u0412\u043b\u0430\u0434\u043e\u0432\u043e"
    ],
    "name:cat_x_preferred":[
        "Agras"
    ],
    "name:dut_x_preferred":[
        "Agras"
    ],
    "name:ell_x_preferred":[
        "\u0386\u03b3\u03c1\u03b1\u03c2"
    ],
    "name:eng_x_preferred":[
        "Agras"
    ],
    "name:ger_x_preferred":[
        "Agras"
    ],
    "name:glg_x_preferred":[
        "Agras"
    ],
    "name:mac_x_preferred":[
        "\u0412\u043b\u0430\u0434\u043e\u0432\u043e"
    ],
    "name:spa_x_preferred":[
        "Agras"
    ],
    "name:unk_x_variant":[
        "Vl\u00e1dovon"
    ],
    "qs_pg:aaroncc":"GR",
    "qs_pg:gn_country":"GR",
    "qs_pg:gn_fcode":"PPL",
    "qs_pg:gn_pop":854,
    "qs_pg:name":"Agras",
    "qs_pg:name_adm0":"\u0395\u03bb\u03bb\u03ac\u03b4\u03b1",
    "qs_pg:name_adm1":"Macedonia and Thrace",
    "qs_pg:photos_9k":1,
    "qs_pg:photos_9r":1,
    "qs_pg:photos_all":21,
    "qs_pg:photos_sr":0,
    "qs_pg:pop_sr":2,
    "qs_pg:qs_pg_placetype":"locality",
    "qs_pg:qs_pg_placetype_gp":"Town",
    "qs_pg:woe_adm0":23424833,
    "woe:adm0_id":23424833,
    "woe:name_adm0":"\u0395\u03bb\u03bb\u03ac\u03b4\u03b1",
    "woe:name_adm1":"Macedonia and Thrace",
    "woe:placetype":"Town",
    "wof:name":"Agras",
    "wof:placetype":"locality",
    "wof:population":854
},
  "geometry": {"coordinates":[22.00056,40.805],"type":"Point"}
}