{
  "type": "Feature",
  "properties": {
    "gn:gn_country":"GR",
    "gn:gn_fcode":"PPL",
    "gn:gn_pop":0,
    "iso:country":"GR",
    "name:deu_x_preferred":[
        "Piso Livadi"
    ],
    "name:ell_x_preferred":[
        "\u03a0\u03af\u03c3\u03c9 \u039b\u03b9\u03b2\u03ac\u03b4\u03b9 \u03a0\u03ac\u03c1\u03bf\u03c5"
    ],
    "name:eng_x_preferred":[
        "Piso Livadi"
    ],
    "name:nld_x_preferred":[
        "Piso Livadi"
    ],
    "qs_pg:aaroncc":"GR",
    "qs_pg:gn_country":"GR",
    "qs_pg:gn_fcode":"PPL",
    "qs_pg:gn_pop":0,
    "qs_pg:name":"Piso Livadi",
    "qs_pg:name_adm0":"\u0395\u03bb\u03bb\u03ac\u03b4\u03b1",
    "qs_pg:name_adm1":"Aegean",
    "qs_pg:photos":384,
    "qs_pg:photos_1k":78,
    "qs_pg:photos_9k":2,
    "qs_pg:photos_9r":5,
    "qs_pg:photos_all":384,
    "qs_pg:photos_sr":6,
    "qs_pg:pop_sr":0,
    "qs_pg:qs_pg_placetype":"locality",
    "qs_pg:qs_pg_placetype_gp":"Town",
    "qs_pg:woe_adm0":23424833,
    "woe:adm0_id":23424833,
    "woe:name_adm0":"\u0395\u03bb\u03bb\u03ac\u03b4\u03b1",
    "woe:name_adm1":"Aegean",
    "woe:placetype":"Town",
    "wof:name":"Piso Livadi",
    "wof:placetype":"locality"
},
  "geometry": {"coordinates":[25.25984,37.03699],"type":"Point"}
}