{
  "type": "Feature",
  "properties": {
    "gn:admin1_code":"ESYE42",
    "gn:admin2_code":"49.0",
    "gn:admin3_code":"9287",
    "gn:asciiname":"Ralakion Chalakos",
    "gn:country_code":"GR",
    "gn:dem":165,
    "gn:feature_class":"P",
    "gn:feature_code":"PPL",
    "gn:name":"Ral\u00e1kion Ch\u00e1lakos",
    "gn:population":0,
    "gn:timezone":"Europe/Athens",
    "iso:country":"GR",
    "name:ell_x_preferred":[
        "\u03a1\u03b1\u03bb\u03ac\u03ba\u03b9 \u03a7\u03ac\u03bb\u03b1\u03ba\u03b1"
    ],
    "name:ell_x_variant":[
        "\u03a1\u03b1\u03bb\u03ac\u03ba\u03b9",
        "\u03a1\u03b1\u03bb\u03ac\u03ba\u03b9\u03bf\u03bd",
        "\u03a1\u03b1\u03bb\u03ac\u03ba\u03b9\u03bf",
        "\u03a1\u03b1\u03bb\u03ac\u03ba\u03b9\u03bf\u03bd \u03a7\u03ac\u03bb\u03b1\u03ba\u03bf\u03c2"
    ],
    "name:eng_x_preferred":[
        "Ralaki Chalaka"
    ],
    "name:eng_x_variant":[
        "Ralaki"
    ],
    "wof:name":"Ralakion Chalakos",
    "wof:placetype":"locality"
},
  "geometry": {"coordinates":[24.36748,36.69763],"type":"Point"}
}