{
  "type": "Feature",
  "properties": {
    "gn:admin1_code":"ESYE25",
    "gn:admin2_code":"41.0",
    "gn:admin3_code":"9238",
    "gn:asciiname":"Kokkinorachi",
    "gn:country_code":"GR",
    "gn:dem":655,
    "gn:feature_class":"P",
    "gn:feature_code":"PPL",
    "gn:name":"Kokkin\u00f3rachi",
    "gn:population":0,
    "gn:timezone":"Europe/Athens",
    "iso:country":"GR",
    "name:ell_x_preferred":[
        "Kokkin\u00f3rachi"
    ],
    "name:ell_x_variant":[
        "\u039a\u03bf\u03ba\u03ba\u03b9\u03bd\u03cc\u03c1\u03b1\u03c7\u03b7"
    ],
    "name:und_x_variant":[
        "Kokkinor\u00e1khi",
        "Kokkin\u00f3rrakhi"
    ],
    "wof:name":"Kokkinorachi",
    "wof:placetype":"locality"
},
  "geometry": {"coordinates":[21.93874,37.6614],"type":"Point"}
}