{
  "type": "Feature",
  "properties": {
    "gn:admin1_code":"ESYE42",
    "gn:admin2_code":"49.0",
    "gn:admin3_code":"9270",
    "gn:asciiname":"Potamos",
    "gn:country_code":"GR",
    "gn:dem":67,
    "gn:feature_class":"P",
    "gn:feature_code":"PPL",
    "gn:name":"Potam\u00f3s",
    "gn:population":113,
    "gn:timezone":"Europe/Athens",
    "iso:country":"GR",
    "name:ell_x_preferred":[
        "\u03a0\u03bf\u03c4\u03b1\u03bc\u03cc\u03c2"
    ],
    "name:eng_x_preferred":[
        "Potamos"
    ],
    "name:und_x_variant":[
        "Potam\u00f3s"
    ],
    "wof:name":"Potamos",
    "wof:placetype":"locality",
    "wof:population":113
},
  "geometry": {"coordinates":[25.33881,36.43724],"type":"Point"}
}