{
  "type": "Feature",
  "properties": {
    "gn:admin1_code":"ESYE12",
    "gn:admin2_code":"13.0",
    "gn:admin3_code":"9027",
    "gn:asciiname":"Modi",
    "gn:country_code":"GR",
    "gn:dem":128,
    "gn:feature_class":"P",
    "gn:feature_code":"PPL",
    "gn:name":"M\u00f3di",
    "gn:population":0,
    "gn:timezone":"Europe/Athens",
    "iso:country":"GR",
    "name:ceb_x_preferred":[
        "Modi"
    ],
    "name:deu_x_preferred":[
        "Modi"
    ],
    "name:ell_x_preferred":[
        "M\u00f3di"
    ],
    "name:ell_x_variant":[
        "\u039c\u03cc\u03b4\u03b9",
        "M\u00f3dion",
        "\u039c\u03cc\u03b4\u03b9\u03bf\u03bd"
    ],
    "name:fin_x_preferred":[
        "Modi"
    ],
    "name:fra_x_preferred":[
        "Modi"
    ],
    "name:jpn_x_preferred":[
        "\u30e2\u30fc\u30b8"
    ],
    "name:nld_x_preferred":[
        "Modi"
    ],
    "name:pol_x_preferred":[
        "Modi"
    ],
    "name:rus_x_preferred":[
        "\u041c\u043e\u0434\u0438"
    ],
    "name:swe_x_preferred":[
        "Modi"
    ],
    "name:und_x_variant":[
        "M\u00f3dhi",
        "M\u00f3dhion"
    ],
    "wof:name":"Modi",
    "wof:placetype":"locality"
},
  "geometry": {"coordinates":[23.61045,40.62606],"type":"Point"}
}