{
  "type": "Feature",
  "properties": {
    "gn:admin1_code":"ESYE43",
    "gn:admin2_code":"43.0",
    "gn:admin3_code":"9322",
    "gn:asciiname":"Maneriana",
    "gn:country_code":"GR",
    "gn:dem":433,
    "gn:feature_class":"P",
    "gn:feature_code":"PPL",
    "gn:name":"Manerian\u00e1",
    "gn:population":13,
    "gn:timezone":"Europe/Athens",
    "iso:country":"GR",
    "name:ell_x_preferred":[
        "\u039c\u03b1\u03bd\u03b5\u03c1\u03b9\u03b1\u03bd\u03ac"
    ],
    "name:eng_x_preferred":[
        "Maneriana"
    ],
    "name:und_x_variant":[
        "Manerian\u00e1"
    ],
    "wof:name":"Maneriana",
    "wof:placetype":"locality",
    "wof:population":13
},
  "geometry": {"coordinates":[23.71585,35.40391],"type":"Point"}
}