{
  "type": "Feature",
  "properties": {
    "gn:admin1_code":"ESYE24",
    "gn:admin2_code":"29.0",
    "gn:admin3_code":"9162",
    "gn:asciiname":"Dhilofon",
    "gn:country_code":"GR",
    "gn:dem":748,
    "gn:feature_class":"P",
    "gn:feature_code":"PPL",
    "gn:name":"Dh\u00edlofon",
    "gn:population":67,
    "gn:timezone":"Europe/Athens",
    "iso:country":"GR",
    "name:ell_x_preferred":[
        "\u0394\u03af\u03bb\u03bf\u03c6\u03bf"
    ],
    "name:ell_x_variant":[
        "\u0394\u03af\u03bb\u03bf\u03c6\u03bf\u03bd"
    ],
    "name:eng_x_preferred":[
        "Dilofo"
    ],
    "name:und_x_variant":[
        "Bro\u00fafliani",
        "Dh\u00edlofon"
    ],
    "wof:name":"Dhilofon",
    "wof:placetype":"locality",
    "wof:population":67
},
  "geometry": {"coordinates":[22.1281,38.86066],"type":"Point"}
}