{
  "type": "Feature",
  "properties": {
    "gn:admin1_code":"ESYE11",
    "gn:admin2_code":"4.0",
    "gn:admin3_code":"9003",
    "gn:asciiname":"Granitis",
    "gn:country_code":"GR",
    "gn:dem":810,
    "gn:feature_class":"P",
    "gn:feature_code":"PPL",
    "gn:name":"Gran\u00edtis",
    "gn:population":0,
    "gn:timezone":"Europe/Athens",
    "iso:country":"GR",
    "name:ell_x_preferred":[
        "\u0393\u03c1\u03b1\u03bd\u03af\u03c4\u03b7\u03c2"
    ],
    "name:und_x_variant":[
        "Gurej\u00edk",
        "Gran\u00edtis"
    ],
    "wof:name":"Granitis",
    "wof:placetype":"locality"
},
  "geometry": {"coordinates":[23.92978,41.28971],"type":"Point"}
}