{
  "type": "Feature",
  "properties": {
    "gn:country":"GR",
    "gn:fcode":"PPL",
    "gn:population":0,
    "iso:country":"GR",
    "name:bul_x_preferred":[
        "\u041d\u0435\u0433\u043e\u0447\u0430\u043d\u0438"
    ],
    "name:ceb_x_preferred":[
        "N\u00edki"
    ],
    "name:ell_x_historical":[
        "\u039d\u03b5\u03b3\u03ba\u03bf\u03c4\u03c3\u03ac\u03bd\u03b7",
        "\u039d\u03b5\u03b3\u03bf\u03c4\u03c3\u03ac\u03bd\u03b7"
    ],
    "name:ell_x_preferred":[
        "\u039d\u03af\u03ba\u03b7"
    ],
    "name:ell_x_variant":[
        "\u039d\u03b5\u03b3\u03ba\u03bf\u03c4\u03c3\u03ac\u03bd\u03b7",
        "\u039d\u03b5\u03b3\u03bf\u03c4\u03c3\u03ac\u03bd\u03b7",
        "\u039d\u03af\u03ba\u03b7 \u03a6\u03bb\u03ce\u03c1\u03b9\u03bd\u03b1\u03c2"
    ],
    "name:eng_x_historical":[
        "Negotsani",
        "Negkotsani"
    ],
    "name:eng_x_preferred":[
        "Niki"
    ],
    "name:eng_x_variant":[
        "Negotsani",
        "Negkotsani"
    ],
    "name:fin_x_preferred":[
        "N\u00edki"
    ],
    "name:jpn_x_preferred":[
        "\u30cb\u30ad"
    ],
    "name:mkd_x_preferred":[
        "\u041d\u0435\u0433\u043e\u0447\u0430\u043d\u0438"
    ],
    "name:nld_x_preferred":[
        "Niki"
    ],
    "name:sqi_x_preferred":[
        "Nego\u00e7ani"
    ],
    "name:srp_x_preferred":[
        "\u041d\u0435\u0433\u043e\u0447\u0430\u043d\u0438"
    ],
    "name:swe_x_preferred":[
        "N\u00edki"
    ],
    "name:und_x_variant":[
        "Negots\u00e1ni"
    ],
    "qs_pg:aaroncc":"GR",
    "qs_pg:gn_country":"GR",
    "qs_pg:gn_fcode":"PPL",
    "qs_pg:gn_pop":0,
    "qs_pg:name":"Niki",
    "qs_pg:name_adm0":"\u0395\u03bb\u03bb\u03ac\u03b4\u03b1",
    "qs_pg:name_adm1":"Epirus and Western Macedonia",
    "qs_pg:photos_9k":1,
    "qs_pg:photos_9r":1,
    "qs_pg:photos_all":1,
    "qs_pg:photos_sr":0,
    "qs_pg:pop_sr":0,
    "qs_pg:qs_pg_placetype":"locality",
    "qs_pg:qs_pg_placetype_gp":"Town",
    "qs_pg:woe_adm0":23424833,
    "woe:adm0_id":23424833,
    "woe:name_adm0":"\u0395\u03bb\u03bb\u03ac\u03b4\u03b1",
    "woe:name_adm1":"Epirus and Western Macedonia",
    "woe:placetype":"Town",
    "wof:name":"Niki",
    "wof:placetype":"locality",
    "wof:population":273
},
  "geometry": {"coordinates":[21.41667,40.91667],"type":"Point"}
}