{
  "type": "Feature",
  "properties": {
    "gn:admin1_code":"ESYE31",
    "gn:admin2_code":"445406.0",
    "gn:admin3_code":"9220",
    "gn:asciiname":"Avra",
    "gn:country_code":"GR",
    "gn:dem":53,
    "gn:feature_class":"P",
    "gn:feature_code":"PPL",
    "gn:name":"\u00c1vra",
    "gn:population":191,
    "gn:timezone":"Europe/Athens",
    "iso:country":"GR",
    "name:ell_x_preferred":[
        "Avra"
    ],
    "name:eng_x_preferred":[
        "\u0391\u03cd\u03c1\u03b1"
    ],
    "wof:name":"Avra",
    "wof:placetype":"locality",
    "wof:population":191
},
  "geometry": {"coordinates":[24.03216,38.18048],"type":"Point"}
}