{
  "type": "Feature",
  "properties": {
    "gn:admin1_code":"ESYE43",
    "gn:admin2_code":"45.0",
    "gn:admin3_code":"9307",
    "gn:asciiname":"Kastamonitsa",
    "gn:cc2":"GR",
    "gn:country_code":"GR",
    "gn:dem":519,
    "gn:feature_class":"P",
    "gn:feature_code":"PPL",
    "gn:name":"Kastamon\u00edtsa",
    "gn:population":0,
    "gn:timezone":"Europe/Athens",
    "iso:country":"GR",
    "name:und_x_variant":[
        "Kostam\u00f3nitsa",
        "Kastamon\u00edtsa"
    ],
    "wof:name":"Kastamonitsa",
    "wof:placetype":"locality"
},
  "geometry": {"coordinates":[25.37782,35.19260999999999],"type":"Point"}
}