{
  "type": "Feature",
  "properties": {
    "gn:admin1_code":"ESYE23",
    "gn:admin2_code":"31.0",
    "gn:admin3_code":"9128",
    "gn:asciiname":"Paliogali",
    "gn:country_code":"GR",
    "gn:dem":479,
    "gn:feature_class":"P",
    "gn:feature_code":"PPL",
    "gn:name":"Pali\u00f3gali",
    "gn:population":0,
    "gn:timezone":"Europe/Athens",
    "iso:country":"GR",
    "name:ell_x_preferred":[
        "Pali\u00f3gali"
    ],
    "name:ell_x_variant":[
        "\u03a0\u03b1\u03bb\u03b9\u03cc\u03b3\u03b1\u03bb\u03b7"
    ],
    "name:und_x_variant":[
        "Palai\u00f3goli"
    ],
    "wof:name":"Paliogali",
    "wof:placetype":"locality"
},
  "geometry": {"coordinates":[21.76667,38.43333],"type":"Point"}
}