{
  "type": "Feature",
  "properties": {
    "gn:admin1_code":"ESYE23",
    "gn:admin2_code":"38.0",
    "gn:admin3_code":"9133",
    "gn:asciiname":"Krinofyta",
    "gn:country_code":"GR",
    "gn:dem":666,
    "gn:feature_class":"P",
    "gn:feature_code":"PPL",
    "gn:name":"Krin\u00f3fyta",
    "gn:population":0,
    "gn:timezone":"Europe/Athens",
    "iso:country":"GR",
    "name:ell_x_preferred":[
        "Krin\u00f3fyta"
    ],
    "name:ell_x_variant":[
        "\u039a\u03c1\u03b9\u03bd\u03cc\u03c6\u03c5\u03c4\u03b1"
    ],
    "name:und_x_variant":[
        "Krin\u00f3fita"
    ],
    "wof:name":"Krinofyta",
    "wof:placetype":"locality"
},
  "geometry": {"coordinates":[22.16931,37.87153],"type":"Point"}
}