{
  "type": "Feature",
  "properties": {
    "gn:admin1_code":"ESYE23",
    "gn:admin2_code":"31.0",
    "gn:admin3_code":"9126",
    "gn:asciiname":"Ampelia",
    "gn:country_code":"GR",
    "gn:dem":695,
    "gn:feature_class":"P",
    "gn:feature_code":"PPL",
    "gn:name":"Amp\u00e9lia",
    "gn:population":0,
    "gn:timezone":"Europe/Athens",
    "iso:country":"GR",
    "name:ell_x_preferred":[
        "Amp\u00e9lia"
    ],
    "name:ell_x_variant":[
        "\u0391\u03bc\u03c0\u03ad\u03bb\u03b9\u03b1"
    ],
    "name:und_x_variant":[
        "Amb\u00e1lia",
        "Amb\u00e9lia"
    ],
    "wof:name":"Ampelia",
    "wof:placetype":"locality"
},
  "geometry": {"coordinates":[21.72833,38.66694],"type":"Point"}
}