{
  "type": "Feature",
  "properties": {
    "gn:gn_country":"GR",
    "gn:gn_fcode":"PPLA3",
    "gn:gn_pop":5828,
    "gn:population":5828,
    "iso:country":"GR",
    "name:ara_x_preferred":[
        "\u0628\u0633\u0627\u0643\u0646\u0627\u060c \u0625\u0641\u0641\u0648\u064a\u0627"
    ],
    "name:ara_x_variant":[
        "\u0628\u0633\u0627\u0643\u0646\u0627"
    ],
    "name:ceb_x_preferred":[
        "Psachn\u00e1"
    ],
    "name:ell_x_preferred":[
        "\u03a8\u03b1\u03c7\u03bd\u03ac"
    ],
    "name:ell_x_variant":[
        "Psachn\u00e1",
        "\u03a8\u03b1\u03c7\u03bd\u03ac \u0395\u03cd\u03b2\u03bf\u03b9\u03b1\u03c2"
    ],
    "name:eng_x_preferred":[
        "Psachna"
    ],
    "name:fin_x_preferred":[
        "Psachn\u00e1"
    ],
    "name:fra_x_preferred":[
        "Psachna"
    ],
    "name:nld_x_preferred":[
        "Psachna"
    ],
    "name:nno_x_preferred":[
        "Psakhn\u00e1"
    ],
    "name:rus_x_preferred":[
        "\u041f\u0441\u0430\u0445\u043d\u0430"
    ],
    "name:swe_x_preferred":[
        "Psachn\u00e1"
    ],
    "name:unk_x_variant":[
        "Psakhn\u00e1"
    ],
    "qs_pg:aaroncc":"GR",
    "qs_pg:gn_country":"GR",
    "qs_pg:gn_fcode":"PPLA3",
    "qs_pg:gn_pop":5828,
    "qs_pg:name":"Psachn\u00e1",
    "qs_pg:photos_9r":0,
    "qs_pg:photos_sr":0,
    "qs_pg:pop_sr":5,
    "qs_pg:qs_pg_placetype":"locality",
    "wof:name":"Psachn\u00e1",
    "wof:placetype":"locality",
    "wof:population":5828
},
  "geometry": {"coordinates":[23.63333,38.58333],"type":"Point"}
}