{
  "type": "Feature",
  "properties": {
    "gn:admin1_code":"ESYE43",
    "gn:admin2_code":"46.0",
    "gn:admin3_code":"9313",
    "gn:asciiname":"Sklavoi",
    "gn:country_code":"GR",
    "gn:dem":389,
    "gn:feature_class":"P",
    "gn:feature_code":"PPL",
    "gn:name":"Skl\u00e1voi",
    "gn:population":0,
    "gn:timezone":"Europe/Athens",
    "iso:country":"GR",
    "name:ell_x_preferred":[
        "\u03a3\u03ba\u03bb\u03ac\u03b2\u03bf\u03b9"
    ],
    "name:und_x_variant":[
        "Skl\u00e1vi",
        "Skl\u00e1voi"
    ],
    "wof:name":"Sklavoi",
    "wof:placetype":"locality"
},
  "geometry": {"coordinates":[26.07681,35.10223],"type":"Point"}
}