{
  "type": "Feature",
  "properties": {
    "gn:country":"GR",
    "gn:fcode":"PPL",
    "gn:population":604,
    "iso:country":"GR",
    "name:ell_x_historical":[
        "\u039b\u03bf\u03b6\u03ad\u03c4\u03c3\u03b9"
    ],
    "name:ell_x_preferred":[
        "\u0395\u03bb\u03bb\u03b7\u03bd\u03b9\u03ba\u03cc"
    ],
    "name:ell_x_variant":[
        "\u0395\u03bb\u03bb\u03b7\u03bd\u03b9\u03ba\u03cc\u03bd",
        "\u039b\u03bf\u03b6\u03ad\u03c4\u03c3\u03b9"
    ],
    "name:eng_x_preferred":[
        "Elliniko"
    ],
    "name:und_x_variant":[
        "Loz\u00e9tsi"
    ],
    "qs_pg:aaroncc":"GR",
    "qs_pg:gn_country":"GR",
    "qs_pg:gn_fcode":"PPL",
    "qs_pg:gn_pop":604,
    "qs_pg:name":"Ellinik\u00f3n",
    "qs_pg:photos_9r":0,
    "qs_pg:photos_sr":0,
    "qs_pg:pop_sr":2,
    "qs_pg:qs_pg_placetype":"locality",
    "wof:name":"Ellinik\u00f3n",
    "wof:placetype":"locality",
    "wof:population":443
},
  "geometry": {"coordinates":[20.95417,39.54917],"type":"Point"}
}