{
  "type": "Feature",
  "properties": {
    "gn:admin1_code":"ESYE43",
    "gn:admin2_code":"43.0",
    "gn:admin3_code":"9323",
    "gn:asciiname":"Rodopos",
    "gn:country_code":"GR",
    "gn:dem":247,
    "gn:feature_class":"P",
    "gn:feature_code":"PPL",
    "gn:name":"Rodop\u00f3s",
    "gn:population":0,
    "gn:timezone":"Europe/Athens",
    "iso:country":"GR",
    "name:ell_x_preferred":[
        "Rodop\u00f3s"
    ],
    "name:ell_x_variant":[
        "\u03a1\u03bf\u03b4\u03c9\u03c0\u03cc\u03c2",
        "Rodopo\u00fa",
        "\u03a1\u03bf\u03b4\u03c9\u03c0\u03bf\u03cd"
    ],
    "name:und_x_variant":[
        "Rodhopo\u00fa",
        "Rodhop\u00f3s"
    ],
    "wof:name":"Rodopos",
    "wof:placetype":"locality"
},
  "geometry": {"coordinates":[23.7548,35.56227],"type":"Point"}
}