{
  "type": "Feature",
  "properties": {
    "gn:population":1037,
    "iso:country":"GR",
    "name:ell_x_preferred":[
        "\u03a0\u03ad\u03c0\u03bb\u03bf\u03c2"
    ],
    "name:und_x_variant":[
        "P\u00e9plos"
    ],
    "qs:a0":"Greece",
    "qs:a1":"*\u0391\u039d\u0391\u03a4\u039f\u039b\u0399\u039a\u0397 \u039c\u0391\u039a\u0395\u0394\u039f\u039d\u0399\u0391 \u039a\u0391\u0399 \u0398\u03a1\u0391\u039a\u0397",
    "qs:a1_alt":"ANATOLIKH MAKEDONIA KAI URAKH",
    "qs:a1r":"0",
    "qs:a2_alt":"EBROS",
    "qs:adm0":"Greece",
    "qs:la_lc":"*",
    "qs:level":"locality",
    "qs:loc":"\u03a0\u0395\u03a0\u039b\u039f\u03a3",
    "qs:loc_alt":"PEPLOS",
    "qs:pop":0,
    "qs:type":"buffered point",
    "wof:name":"\u03a0\u0395\u03a0\u039b\u039f\u03a3",
    "wof:placetype":"locality",
    "wof:population":1037
},
  "geometry": {"coordinates":[26.265989,40.956913],"type":"Point"}
}