{
  "type": "Feature",
  "properties": {
    "gn:population":1459,
    "iso:country":"GR",
    "name:ell_x_preferred":[
        "\u0386\u03bd\u03c9 \u039c\u03b5\u03c1\u03ac"
    ],
    "name:eng_x_preferred":[
        "Ano Mera"
    ],
    "name:und_x_variant":[
        "\u00c1no Mer\u00e1"
    ],
    "qs:a0":"Greece",
    "qs:a1":"*\u039d\u039f\u03a4\u0399\u039f \u0391\u0399\u0393\u0391\u0399\u039f",
    "qs:a1_alt":"NOTIO AIGAIO",
    "qs:a1r":"0",
    "qs:a2_alt":"KYKLADES",
    "qs:adm0":"Greece",
    "qs:la_lc":"*",
    "qs:level":"locality",
    "qs:loc":"\u0391\u039d\u03a9 \u039c\u0395\u03a1\u0391",
    "qs:loc_alt":"ANV MERA",
    "qs:pop":0,
    "qs:type":"buffered point",
    "wof:name":"\u0391\u039d\u03a9 \u039c\u0395\u03a1\u0391",
    "wof:placetype":"locality",
    "wof:population":1459
},
  "geometry": {"coordinates":[25.397115,37.447632],"type":"Point"}
}