{
  "type": "Feature",
  "properties": {
    "gn:admin1_code":"ESYE21",
    "gn:admin2_code":"19.0",
    "gn:admin3_code":"9089",
    "gn:asciiname":"Lichnos",
    "gn:country_code":"GR",
    "gn:dem":38,
    "gn:feature_class":"P",
    "gn:feature_code":"PPL",
    "gn:name":"Lichnos",
    "gn:population":0,
    "gn:timezone":"Europe/Athens",
    "iso:country":"GR",
    "wof:name":"Lichnos",
    "wof:placetype":"locality"
},
  "geometry": {"coordinates":[20.43517,39.28303],"type":"Point"}
}