{
  "type": "Feature",
  "properties": {
    "gn:gn_country":"GR",
    "gn:gn_fcode":"PPL",
    "gn:gn_pop":43,
    "gn:population":43,
    "iso:country":"GR",
    "name:ell_x_preferred":[
        "\u039a\u03b1\u03c1\u03c5\u03ac"
    ],
    "name:unk_x_variant":[
        "Kari\u00e1"
    ],
    "qs_pg:aaroncc":"GR",
    "qs_pg:gn_country":"GR",
    "qs_pg:gn_fcode":"PPL",
    "qs_pg:gn_pop":43,
    "qs_pg:name":"Kary\u00e1",
    "qs_pg:photos_9r":0,
    "qs_pg:photos_sr":0,
    "qs_pg:pop_sr":1,
    "qs_pg:qs_pg_placetype":"locality",
    "wof:name":"Kary\u00e1",
    "wof:placetype":"locality",
    "wof:population":43
},
  "geometry": {"coordinates":[20.58333,38.36667],"type":"Point"}
}