{
  "type": "Feature",
  "properties": {
    "gn:admin1_code":"ESYE43",
    "gn:admin2_code":"43.0",
    "gn:admin3_code":"9321",
    "gn:asciiname":"Azogyres",
    "gn:country_code":"GR",
    "gn:dem":376,
    "gn:feature_class":"P",
    "gn:feature_code":"PPL",
    "gn:name":"Azogyr\u00e9s",
    "gn:population":0,
    "gn:timezone":"Europe/Athens",
    "iso:country":"GR",
    "name:ell_x_preferred":[
        "Azogyr\u00e9s"
    ],
    "name:ell_x_variant":[
        "\u0391\u03b6\u03bf\u03b3\u03c5\u03c1\u03ad\u03c2",
        "Azoyir\u00e9s"
    ],
    "wof:name":"Azogyres",
    "wof:placetype":"locality"
},
  "geometry": {"coordinates":[23.72154,35.27151],"type":"Point"}
}