{
  "type": "Feature",
  "properties": {
    "gn:admin1_code":"ESYE25",
    "gn:admin2_code":"36.0",
    "gn:admin3_code":"9233",
    "gn:asciiname":"Timenion",
    "gn:country_code":"GR",
    "gn:dem":3,
    "gn:feature_class":"P",
    "gn:feature_code":"PPL",
    "gn:name":"Tim\u00e9nion",
    "gn:population":73,
    "gn:timezone":"Europe/Athens",
    "iso:country":"GR",
    "name:ell_x_preferred":[
        "\u03a4\u03b7\u03bc\u03ad\u03bd\u03b9"
    ],
    "name:ell_x_variant":[
        "\u03a4\u03b7\u03bc\u03ad\u03bd\u03b9\u03bf\u03bd",
        "\u03a4\u03b7\u03bc\u03ad\u03bd\u03b9\u03bf"
    ],
    "name:eng_x_preferred":[
        "Timenio"
    ],
    "wof:name":"Timenion",
    "wof:placetype":"locality",
    "wof:population":73
},
  "geometry": {"coordinates":[22.7317,37.5778],"type":"Point"}
}