{
  "type": "Feature",
  "properties": {
    "gn:admin1_code":"ESYE23",
    "gn:admin2_code":"31.0",
    "gn:admin3_code":"9128",
    "gn:asciiname":"Nikaiika",
    "gn:country_code":"GR",
    "gn:dem":688,
    "gn:feature_class":"P",
    "gn:feature_code":"PPL",
    "gn:name":"Nika\u00edika",
    "gn:population":0,
    "gn:timezone":"Europe/Athens",
    "iso:country":"GR",
    "name:ell_x_preferred":[
        "\u039d\u03b9\u03ba\u03b1\u03af\u03b9\u03ba\u03b1"
    ],
    "name:und_x_variant":[
        "Nik\u00e9\u00efka",
        "Nika\u00edika"
    ],
    "wof:name":"Nikaiika",
    "wof:placetype":"locality"
},
  "geometry": {"coordinates":[21.82622000000001,38.44422],"type":"Point"}
}