{
  "type": "Feature",
  "properties": {
    "gn:admin1_code":"ESYE23",
    "gn:admin2_code":"38.0",
    "gn:admin3_code":"9130",
    "gn:asciiname":"Alsos",
    "gn:country_code":"GR",
    "gn:dem":338,
    "gn:feature_class":"P",
    "gn:feature_code":"PPL",
    "gn:name":"\u00c1lsos",
    "gn:population":123,
    "gn:timezone":"Europe/Athens",
    "iso:country":"GR",
    "name:ell_x_preferred":[
        "\u0386\u03bb\u03c3\u03bf\u03c2"
    ],
    "name:eng_x_preferred":[
        "Alsos"
    ],
    "name:und_x_variant":[
        "Rog\u00f3zena",
        "Arag\u00f3zena",
        "\u00c1lsos"
    ],
    "wof:name":"Alsos",
    "wof:placetype":"locality",
    "wof:population":123
},
  "geometry": {"coordinates":[21.98167,38.2467],"type":"Point"}
}