{
  "type": "Feature",
  "properties": {
    "gn:population":965,
    "iso:country":"GR",
    "name:ell_x_preferred":[
        "\u039a\u03b1\u03bb\u03cd\u03b2\u03b9\u03b1"
    ],
    "name:eng_x_preferred":[
        "Kalyvia"
    ],
    "name:und_x_variant":[
        "Kal\u00edvia"
    ],
    "qs:a0":"Greece",
    "qs:a1":"*\u0394\u03a5\u03a4\u0399\u039a\u0397 \u0395\u039b\u039b\u0391\u0394\u0391",
    "qs:a1_alt":"DYTIKH ELLADA",
    "qs:a1r":"0",
    "qs:a2_alt":"AITVLIA KAI AKARNANIA",
    "qs:adm0":"Greece",
    "qs:la_lc":"*",
    "qs:level":"locality",
    "qs:loc":"\u039a\u0391\u039b\u03a5\u0392\u0399\u0391",
    "qs:loc_alt":"KALYBIA",
    "qs:pop":0,
    "qs:type":"buffered point",
    "wof:name":"\u039a\u0391\u039b\u03a5\u0392\u0399\u0391",
    "wof:placetype":"locality",
    "wof:population":965
},
  "geometry": {"coordinates":[21.293743,38.617523],"type":"Point"}
}