{
  "type": "Feature",
  "properties": {
    "gn:admin1_code":"ESYE31",
    "gn:admin2_code":"406101.0",
    "gn:admin3_code":"9209",
    "gn:asciiname":"Moni Myrtidion",
    "gn:country_code":"GR",
    "gn:dem":113,
    "gn:feature_class":"P",
    "gn:feature_code":"PPLR",
    "gn:name":"Mon\u00ed Myrtid\u00edon",
    "gn:population":1,
    "gn:timezone":"Europe/Athens",
    "iso:country":"GR",
    "wof:name":"Moni Myrtidion",
    "wof:placetype":"locality",
    "wof:population":1
},
  "geometry": {"coordinates":[22.92467000000001,36.19983],"type":"Point"}
}