{
  "type": "Feature",
  "properties": {
    "gn:gn_country":"GR",
    "gn:gn_fcode":"ADM3",
    "gn:gn_pop":5114,
    "gn:population":5114,
    "iso:country":"GR",
    "name:ell_x_preferred":[
        "\u03a0\u03b1\u03c1\u03b1\u03bd\u03b5\u03c3\u03c4\u03af\u03bf\u03c5"
    ],
    "qs_pg:aaroncc":"GR",
    "qs_pg:gn_country":"GR",
    "qs_pg:gn_fcode":"ADM3",
    "qs_pg:gn_pop":5114,
    "qs_pg:name":"Dimos Paranesti",
    "qs_pg:photos_9r":0,
    "qs_pg:photos_sr":0,
    "qs_pg:pop_sr":5,
    "qs_pg:qs_pg_placetype":"localadmin",
    "wof:name":"Dimos Paranesti",
    "wof:placetype":"localadmin",
    "wof:population":5114
},
  "geometry": {"coordinates":[24.47526,41.34117],"type":"Point"}
}