{
  "type": "Feature",
  "properties": {
    "gn:admin1_code":"ESYE21",
    "gn:admin2_code":"20.0",
    "gn:admin3_code":"9075",
    "gn:asciiname":"Miliana",
    "gn:country_code":"GR",
    "gn:dem":130,
    "gn:feature_class":"P",
    "gn:feature_code":"PPL",
    "gn:name":"Milian\u00e1",
    "gn:population":0,
    "gn:timezone":"Europe/Athens",
    "iso:country":"GR",
    "name:ara_x_preferred":[
        "\u0645\u0644\u064a\u0627\u0646\u0629"
    ],
    "name:cat_x_preferred":[
        "Mliana"
    ],
    "name:deu_x_preferred":[
        "Miliana"
    ],
    "name:eus_x_preferred":[
        "Miliana"
    ],
    "name:fas_x_preferred":[
        "\u0645\u0644\u06cc\u0627\u0646\u0647"
    ],
    "name:fra_x_preferred":[
        "Miliana"
    ],
    "name:ita_x_preferred":[
        "Miliana"
    ],
    "name:kab_x_preferred":[
        "Tamelyant"
    ],
    "name:msa_x_preferred":[
        "Miliana"
    ],
    "name:pol_x_preferred":[
        "Miljana"
    ],
    "name:por_x_preferred":[
        "Miliana"
    ],
    "name:ron_x_preferred":[
        "Miliana"
    ],
    "name:slv_x_preferred":[
        "Miliana"
    ],
    "name:spa_x_preferred":[
        "Miliana"
    ],
    "name:vie_x_preferred":[
        "Miliana"
    ],
    "name:zho_x_preferred":[
        "\u7c73\u5229\u4e9e\u7d0d"
    ],
    "wof:name":"Miliana",
    "wof:placetype":"locality"
},
  "geometry": {"coordinates":[21.03056,39.255],"type":"Point"}
}