{
  "type": "Feature",
  "properties": {
    "gn:admin1_code":"ESYE22",
    "gn:admin2_code":"25.0",
    "gn:admin3_code":"9118",
    "gn:asciiname":"Vrachleri",
    "gn:country_code":"GR",
    "gn:dem":166,
    "gn:feature_class":"P",
    "gn:feature_code":"PPL",
    "gn:name":"Vrachler\u00ed",
    "gn:population":19,
    "gn:timezone":"Europe/Athens",
    "iso:country":"GR",
    "name:ell_x_preferred":[
        "\u0392\u03c1\u03b1\u03c7\u03bb\u03b5\u03c1\u03ae"
    ],
    "name:eng_x_preferred":[
        "Vrachleri"
    ],
    "wof:name":"Vrachleri",
    "wof:placetype":"locality",
    "wof:population":19
},
  "geometry": {"coordinates":[19.83607,39.78255],"type":"Point"}
}