{
  "type": "Feature",
  "properties": {
    "gn:gn_country":"GR",
    "gn:gn_fcode":"PPL",
    "gn:gn_pop":135,
    "gn:population":73,
    "iso:country":"GR",
    "name:ell_x_preferred":[
        "\u039c\u03b9\u03ba\u03c1\u03ae \u0393\u03cc\u03c4\u03b9\u03c3\u03c4\u03b1"
    ],
    "name:ell_x_variant":[
        "\u039c\u03b9\u03ba\u03c1\u03ac \u0393\u03cc\u03c4\u03b9\u03c3\u03c4\u03b1"
    ],
    "name:eng_x_preferred":[
        "Mikri Gotista"
    ],
    "name:unk_x_variant":[
        "Mikr\u00ed G\u00f3tista"
    ],
    "qs_pg:aaroncc":"GR",
    "qs_pg:gn_country":"GR",
    "qs_pg:gn_fcode":"PPL",
    "qs_pg:gn_pop":135,
    "qs_pg:name":"Mikra Gotista",
    "qs_pg:name_adm0":"\u0395\u03bb\u03bb\u03ac\u03b4\u03b1",
    "qs_pg:name_adm1":"Epirus and Western Macedonia",
    "qs_pg:photos_9r":0,
    "qs_pg:photos_sr":0,
    "qs_pg:pop_sr":1,
    "qs_pg:qs_pg_placetype":"locality",
    "qs_pg:qs_pg_placetype_gp":"Town",
    "qs_pg:woe_adm0":23424833,
    "woe:adm0_id":23424833,
    "woe:name_adm0":"\u0395\u03bb\u03bb\u03ac\u03b4\u03b1",
    "woe:name_adm1":"Epirus and Western Macedonia",
    "woe:placetype":"Town",
    "wof:name":"Mikra Gotista",
    "wof:placetype":"locality",
    "wof:population":73
},
  "geometry": {"coordinates":[21.03833,39.69139],"type":"Point"}
}