{
  "type": "Feature",
  "properties": {
    "gn:population":3368,
    "iso:country":"GR",
    "name:ara_x_preferred":[
        "\u0623\u0643\u0633\u064a\u0648\u0628\u0648\u0644\u064a"
    ],
    "name:bul_x_preferred":[
        "\u0411\u043e\u0439\u043c\u0438\u0446\u0430"
    ],
    "name:ell_x_preferred":[
        "\u0391\u03be\u03b9\u03bf\u03cd\u03c0\u03bf\u03bb\u03b7"
    ],
    "name:ell_x_variant":[
        "\u0391\u03be\u03b9\u03bf\u03cd\u03c0\u03bf\u03bb\u03b9\u03c2"
    ],
    "name:eng_x_preferred":[
        "Axioupoli"
    ],
    "name:ita_x_preferred":[
        "Axioupoli"
    ],
    "name:jpn_x_preferred":[
        "\u30a2\u30af\u30b7\u30a6\u30dd\u30ea"
    ],
    "name:mkd_x_preferred":[
        "\u0411\u043e\u0458\u043c\u0438\u0446\u0430"
    ],
    "name:nld_x_preferred":[
        "Axioupoli"
    ],
    "name:nno_x_preferred":[
        "Axio\u00fapoli"
    ],
    "name:spa_x_preferred":[
        "Axio\u00fapoli"
    ],
    "name:swe_x_preferred":[
        "Axio\u00fapoli"
    ],
    "name:unk_x_variant":[
        "B\u00f3\u00ebmitsa"
    ],
    "qs:a0":"Greece",
    "qs:a1":"*\u039a\u0395\u039d\u03a4\u03a1\u0399\u039a\u0397 \u039c\u0391\u039a\u0395\u0394\u039f\u039d\u0399\u0391",
    "qs:a1_alt":"KENTRIKH MAKEDONIA",
    "qs:a1r":"0",
    "qs:a2_alt":"KILKIS",
    "qs:adm0":"Greece",
    "qs:la_lc":"*",
    "qs:level":"locality",
    "qs:loc":"\u0391\u039e\u0399\u039f\u03a5\u03a0\u039f\u039b\u0397",
    "qs:loc_alt":"AJIOYPOLH",
    "qs:pop":0,
    "qs:type":"buffered point",
    "wd:population":2897,
    "wd:wordcount":1249,
    "wof:name":"\u0391\u039e\u0399\u039f\u03a5\u03a0\u039f\u039b\u0397",
    "wof:placetype":"locality",
    "wof:population":2897
},
  "geometry": {"coordinates":[22.53994,40.984585],"type":"Point"}
}