{
  "type": "Feature",
  "properties": {
    "gn:admin1_code":"ESYE22",
    "gn:admin2_code":"27.0",
    "gn:admin3_code":"9120",
    "gn:asciiname":"Drapanitika",
    "gn:country_code":"GR",
    "gn:dem":264,
    "gn:feature_class":"P",
    "gn:feature_code":"PPL",
    "gn:name":"Drapan\u00edtika",
    "gn:population":0,
    "gn:timezone":"Europe/Athens",
    "iso:country":"GR",
    "name:ell_x_preferred":[
        "Drapan\u00edtika"
    ],
    "name:ell_x_variant":[
        "\u0394\u03c1\u03b1\u03c0\u03b1\u03bd\u03af\u03c4\u03b9\u03ba\u03b1"
    ],
    "name:und_x_variant":[
        "Dhrapan\u00edtika"
    ],
    "wof:name":"Drapanitika",
    "wof:placetype":"locality"
},
  "geometry": {"coordinates":[20.55203,38.40131],"type":"Point"}
}