{
  "type": "Feature",
  "properties": {
    "gn:admin1_code":"ESYE31",
    "gn:admin2_code":"406101.0",
    "gn:admin3_code":"9205",
    "gn:asciiname":"Gouva Vavoula",
    "gn:country_code":"GR",
    "gn:dem":14,
    "gn:feature_class":"P",
    "gn:feature_code":"PPLL",
    "gn:name":"Go\u00fava V\u00e1voula",
    "gn:population":0,
    "gn:timezone":"Europe/Athens",
    "iso:country":"GR",
    "name:ell_x_preferred":[
        "\u0393\u03bf\u03cd\u03b2\u03b1 \u0392\u03ac\u03b2\u03bf\u03c5\u03bb\u03b1"
    ],
    "name:ell_x_variant":[
        "\u0392\u03ac\u03b2\u03bf\u03c5\u03bb\u03b1\u03c2",
        "\u0392\u03ac\u03b2\u03bf\u03c5\u03bb\u03b1",
        "\u0393\u03bf\u03cd\u03b2\u03b1 \u03c4\u03bf\u03c5 \u0392\u03ac\u03b2\u03bf\u03c5\u03bb\u03b1",
        "\u039b\u03ac\u03ba\u03ba\u03b1 \u0392\u03ac\u03b2\u03bf\u03c5\u03bb\u03b1",
        "\u039b\u03ac\u03ba\u03ba\u03b1 \u039c\u03b5\u03bb\u03b9\u03ac \u0395\u03c6\u03ad\u03bd\u03c4\u03b7"
    ],
    "name:eng_x_preferred":[
        "Gouva Vavoula"
    ],
    "wof:name":"Gouva Vavoula",
    "wof:placetype":"locality"
},
  "geometry": {"coordinates":[23.65117,37.94743],"type":"Point"}
}