{
  "type": "Feature",
  "properties": {
    "gn:admin1_code":"ESYE13",
    "gn:admin2_code":"8.0",
    "gn:admin3_code":"9072",
    "gn:asciiname":"Ano Achlada",
    "gn:country_code":"GR",
    "gn:dem":735,
    "gn:feature_class":"P",
    "gn:feature_code":"PPL",
    "gn:name":"\u00c1no Achl\u00e1da",
    "gn:population":102,
    "gn:timezone":"Europe/Athens",
    "iso:country":"GR",
    "name:ell_x_preferred":[
        "\u0386\u03bd\u03c9 \u0391\u03c7\u03bb\u03ac\u03b4\u03b1"
    ],
    "name:eng_x_preferred":[
        "Ano Achlada"
    ],
    "wof:name":"Ano Achlada",
    "wof:placetype":"locality",
    "wof:population":102
},
  "geometry": {"coordinates":[21.623,40.86446],"type":"Point"}
}