{
  "type": "Feature",
  "properties": {
    "gn:admin1_code":"ESYE23",
    "gn:admin2_code":"31.0",
    "gn:admin3_code":"9123",
    "gn:asciiname":"Kourtelaiika",
    "gn:country_code":"GR",
    "gn:dem":201,
    "gn:feature_class":"P",
    "gn:feature_code":"PPL",
    "gn:name":"Kourtela\u00edika",
    "gn:population":33,
    "gn:timezone":"Europe/Athens",
    "iso:country":"GR",
    "name:ell_x_preferred":[
        "\u039a\u03bf\u03c5\u03c1\u03c4\u03b5\u03bb\u03b1\u03af\u03b9\u03ba\u03b1"
    ],
    "name:eng_x_preferred":[
        "Kourtelaiika"
    ],
    "name:und_x_variant":[
        "Kourtel\u00e9ika",
        "Kourtela\u00edika",
        "Kourtelaiika"
    ],
    "wof:name":"Kourtelaiika",
    "wof:placetype":"locality",
    "wof:population":33
},
  "geometry": {"coordinates":[21.55663,38.49737],"type":"Point"}
}