{
  "type": "Feature",
  "properties": {
    "gn:admin1_code":"ESYE23",
    "gn:admin2_code":"38.0",
    "gn:admin3_code":"9133.0",
    "gn:asciiname":"Agioi Theodoroi",
    "gn:country_code":"GR",
    "gn:dem":665,
    "gn:feature_class":"P",
    "gn:feature_code":"PPL",
    "gn:name":"\u00c1gioi The\u00f3doroi",
    "gn:population":0,
    "gn:timezone":"Europe/Athens",
    "iso:country":"GR",
    "name:ara_x_preferred":[
        "\u0623\u063a\u064a\u0648\u064a \u062b\u064a\u0648\u062f\u0648\u0631\u0648\u064a"
    ],
    "name:ceb_x_preferred":[
        "\u00c1gioi The\u00f3doroi"
    ],
    "name:deu_x_preferred":[
        "Agii Theodori"
    ],
    "name:ell_x_preferred":[
        "\u0386\u03b3\u03b9\u03bf\u03b9 \u0398\u03b5\u03cc\u03b4\u03c9\u03c1\u03bf\u03b9 \u039a\u03bf\u03c1\u03b9\u03bd\u03b8\u03af\u03b1\u03c2"
    ],
    "name:fin_x_preferred":[
        "\u00c1gioi The\u00f3doroi"
    ],
    "name:ita_x_preferred":[
        "Agioi Theodoroi"
    ],
    "name:nno_x_preferred":[
        "\u00c1ji The\u00f3dori"
    ],
    "name:ron_x_preferred":[
        "Agioi Theodoroi"
    ],
    "name:rus_x_preferred":[
        "\u0410\u0439\u0438-\u0422\u0435\u043e\u0434\u043e\u0440\u0438"
    ],
    "name:sqi_x_preferred":[
        "Sindodhori"
    ],
    "wof:name":"Agioi Theodoroi",
    "wof:placetype":"locality"
},
  "geometry": {"coordinates":[22.0878,37.85805],"type":"Point"}
}