{
  "type": "Feature",
  "properties": {
    "gn:admin1_code":"ESYE23",
    "gn:admin2_code":"38.0",
    "gn:admin3_code":"9133.0",
    "gn:asciiname":"Agioi Theodoroi",
    "gn:country_code":"GR",
    "gn:dem":665,
    "gn:feature_class":"P",
    "gn:feature_code":"PPL",
    "gn:name":"\u00c1gioi The\u00f3doroi",
    "gn:population":0,
    "gn:timezone":"Europe/Athens",
    "iso:country":"GR",
    "wof:name":"Agioi Theodoroi",
    "wof:placetype":"locality"
},
  "geometry": {"coordinates":[22.0878,37.85805],"type":"Point"}
}