{
  "type": "Feature",
  "properties": {
    "gn:admin1_code":"ESYE41",
    "gn:asciiname":"Kosoikia",
    "gn:country_code":"GR",
    "gn:dem":362,
    "gn:feature_class":"P",
    "gn:feature_code":"PPL",
    "gn:name":"Koso\u00edkia",
    "gn:population":0,
    "gn:timezone":"Europe/Athens",
    "iso:country":"GR",
    "name:ell_x_preferred":[
        "Koso\u00edkia"
    ],
    "name:ell_x_variant":[
        "\u039a\u03bf\u03c3\u03bf\u03af\u03ba\u03b9\u03b1"
    ],
    "wof:name":"Kosoikia",
    "wof:placetype":"locality"
},
  "geometry": {"coordinates":[26.16249,37.5889],"type":"Point"}
}