{
  "type": "Feature",
  "properties": {
    "gn:admin1_code":"ESYE22",
    "gn:admin2_code":"27.0",
    "gn:admin3_code":"9120",
    "gn:asciiname":"Koutroukois",
    "gn:country_code":"GR",
    "gn:dem":306,
    "gn:feature_class":"P",
    "gn:feature_code":"PPL",
    "gn:name":"Koutrouk\u00f3is",
    "gn:population":0,
    "gn:timezone":"Europe/Athens",
    "iso:country":"GR",
    "name:ell_x_preferred":[
        "Koutrouk\u00f3is"
    ],
    "name:ell_x_variant":[
        "\u039a\u03bf\u03c5\u03c4\u03c1\u03bf\u03c5\u03ba\u03cc\u03b7\u03c2"
    ],
    "wof:name":"Koutroukois",
    "wof:placetype":"locality"
},
  "geometry": {"coordinates":[20.77211,38.09119000000001],"type":"Point"}
}