{
  "type": "Feature",
  "properties": {
    "gn:admin1_code":"ESYE25",
    "gn:admin2_code":"41.0",
    "gn:admin3_code":"9240",
    "gn:asciiname":"Fylatika",
    "gn:country_code":"GR",
    "gn:dem":879,
    "gn:feature_class":"P",
    "gn:feature_code":"PPL",
    "gn:name":"Fyl\u00e1tika",
    "gn:population":0,
    "gn:timezone":"Europe/Athens",
    "iso:country":"GR",
    "name:ell_x_preferred":[
        "Fyl\u00e1tika"
    ],
    "name:ell_x_variant":[
        "\u03a6\u03c5\u03bb\u03ac\u03c4\u03b9\u03ba\u03b1"
    ],
    "name:und_x_variant":[
        "Fil\u00e1",
        "Fil\u00e1tika"
    ],
    "wof:name":"Fylatika",
    "wof:placetype":"locality"
},
  "geometry": {"coordinates":[22.77714,37.06776],"type":"Point"}
}