{
  "type": "Feature",
  "properties": {
    "gn:admin1_code":"ESYE25",
    "gn:admin2_code":"41.0",
    "gn:admin3_code":"9238",
    "gn:asciiname":"Syriamakos",
    "gn:country_code":"GR",
    "gn:dem":434,
    "gn:feature_class":"P",
    "gn:feature_code":"PPL",
    "gn:name":"Syriam\u00e1kos",
    "gn:population":0,
    "gn:timezone":"Europe/Athens",
    "iso:country":"GR",
    "name:ell_x_preferred":[
        "Syriam\u00e1kos"
    ],
    "name:ell_x_variant":[
        "\u03a3\u03c5\u03c1\u03b9\u03b1\u03bc\u03ac\u03ba\u03bf\u03c2"
    ],
    "name:und_x_variant":[
        "Siriam\u00e1kou",
        "\u00c1yios Nik\u00f3laos"
    ],
    "wof:name":"Syriamakos",
    "wof:placetype":"locality"
},
  "geometry": {"coordinates":[22.00797,37.75438],"type":"Point"}
}