{
  "type": "Feature",
  "properties": {
    "gn:admin1_code":"ESYE21",
    "gn:admin2_code":"19.0",
    "gn:admin3_code":"9088",
    "gn:asciiname":"Drymonas",
    "gn:country_code":"GR",
    "gn:dem":158,
    "gn:feature_class":"P",
    "gn:feature_code":"PPL",
    "gn:name":"Drym\u00f3nas",
    "gn:population":0,
    "gn:timezone":"Europe/Athens",
    "iso:country":"GR",
    "name:ell_x_preferred":[
        "Drym\u00f3nas"
    ],
    "name:ell_x_variant":[
        "\u0394\u03c1\u03c5\u03bc\u03ce\u03bd\u03b1\u03c2",
        "Drym\u00f3n",
        "\u0394\u03c1\u03c5\u03bc\u03ce\u03bd"
    ],
    "wof:name":"Drymonas",
    "wof:placetype":"locality"
},
  "geometry": {"coordinates":[20.88925,39.31119],"type":"Point"}
}