{
  "type": "Feature",
  "properties": {
    "gn:admin1_code":"ESYE43",
    "gn:admin2_code":"46.0",
    "gn:admin3_code":"9311",
    "gn:asciiname":"Karydi",
    "gn:country_code":"GR",
    "gn:dem":713,
    "gn:feature_class":"P",
    "gn:feature_code":"PPL",
    "gn:name":"Kar\u00fddi",
    "gn:population":20,
    "gn:timezone":"Europe/Athens",
    "iso:country":"GR",
    "name:ell_x_preferred":[
        "\u039a\u03b1\u03c1\u03cd\u03b4\u03b9"
    ],
    "name:ell_x_variant":[
        "\u039a\u03b1\u03c1\u03cd\u03b4\u03b9\u03bf\u03bd"
    ],
    "name:eng_x_preferred":[
        "Karydi"
    ],
    "name:und_x_variant":[
        "Kar\u00eddhi",
        "Kar\u00eddhion",
        "Kar\u00fddi",
        "Kar\u00fddion"
    ],
    "wof:name":"Karydi",
    "wof:placetype":"locality",
    "wof:population":20
},
  "geometry": {"coordinates":[25.55827,35.04289],"type":"Point"}
}