{
  "type": "Feature",
  "properties": {
    "gn:gn_country":"GR",
    "gn:gn_fcode":"PPL",
    "gn:gn_pop":84,
    "gn:population":84,
    "iso:country":"GR",
    "name:dut_x_preferred":[
        "Tembi"
    ],
    "name:ell_x_preferred":[
        "\u03a4\u03ad\u03bc\u03c0\u03b7"
    ],
    "name:eng_x_preferred":[
        "Tembi"
    ],
    "name:gre_x_preferred":[
        "\u03a4\u03ad\u03bc\u03c0\u03b7 \u039b\u03ac\u03c1\u03b9\u03c3\u03b1\u03c2"
    ],
    "name:pol_x_preferred":[
        "Tembi"
    ],
    "name:unk_x_variant":[
        "Bab\u00e1"
    ],
    "qs_pg:aaroncc":"GR",
    "qs_pg:gn_country":"GR",
    "qs_pg:gn_fcode":"PPL",
    "qs_pg:gn_pop":84,
    "qs_pg:name":"T\u00e9mpi",
    "qs_pg:photos_9r":0,
    "qs_pg:photos_sr":0,
    "qs_pg:pop_sr":1,
    "qs_pg:qs_pg_placetype":"locality",
    "wof:name":"T\u00e9mpi",
    "wof:placetype":"locality",
    "wof:population":84
},
  "geometry": {"coordinates":[22.53056,39.85944],"type":"Point"}
}