{
  "type": "Feature",
  "properties": {
    "gn:admin1_code":"ESYE42",
    "gn:admin2_code":"49.0",
    "gn:admin3_code":"9282",
    "gn:asciiname":"Pera Meria",
    "gn:country_code":"GR",
    "gn:dem":438,
    "gn:feature_class":"P",
    "gn:feature_code":"PPL",
    "gn:name":"P\u00e9ra Meri\u00e1",
    "gn:population":0,
    "gn:timezone":"Europe/Athens",
    "iso:country":"GR",
    "name:ell_x_preferred":[
        "P\u00e9ra Meri\u00e1"
    ],
    "name:ell_x_variant":[
        "\u03a0\u03ad\u03c1\u03b1 \u039c\u03b5\u03c1\u03b9\u03ac"
    ],
    "wof:name":"Pera Meria",
    "wof:placetype":"locality"
},
  "geometry": {"coordinates":[24.37187,37.63301],"type":"Point"}
}