{
  "type": "Feature",
  "properties": {
    "iso:country":"GR",
    "qs:a0":"Greece",
    "qs:a1":"*\u039d\u039f\u03a4\u0399\u039f \u0391\u0399\u0393\u0391\u0399\u039f",
    "qs:a1_alt":"NOTIO AIGAIO",
    "qs:a1r":"0",
    "qs:a2_alt":"DVDEKANHSOS",
    "qs:adm0":"Greece",
    "qs:la_lc":"*",
    "qs:level":"locality",
    "qs:loc":"\u03a6\u0391\u039b\u0397\u03a1\u0391\u039a\u0399\u039f\u039d",
    "qs:loc_alt":"FALHRAKION",
    "qs:pop":0,
    "qs:type":"buffered point",
    "wof:name":"\u03a6\u0391\u039b\u0397\u03a1\u0391\u039a\u0399\u039f\u039d",
    "wof:placetype":"locality"
},
  "geometry": {"coordinates":[28.203676,36.339543],"type":"Point"}
}