{
  "type": "Feature",
  "properties": {
    "gn:admin1_code":"ESYE24",
    "gn:admin2_code":"33.0",
    "gn:admin3_code":"9145",
    "gn:asciiname":"Koroneia",
    "gn:country_code":"GR",
    "gn:dem":460,
    "gn:feature_class":"P",
    "gn:feature_code":"PPL",
    "gn:name":"Kor\u00f3neia",
    "gn:population":0,
    "gn:timezone":"Europe/Athens",
    "iso:country":"GR",
    "name:und_x_variant":[
        "Koutoumoul\u00e1",
        "Kor\u00f3nia",
        "Kor\u00f3neia",
        "\u039a\u03bf\u03c1\u03ce\u03bd\u03b5\u03b9\u03b1"
    ],
    "wof:name":"Koroneia",
    "wof:placetype":"locality"
},
  "geometry": {"coordinates":[22.96004,38.35925],"type":"Point"}
}