{
  "type": "Feature",
  "properties": {
    "gn:admin1_code":"ESYE24",
    "gn:admin2_code":"33.0",
    "gn:admin3_code":"9145",
    "gn:asciiname":"Koroneia",
    "gn:country_code":"GR",
    "gn:dem":460,
    "gn:feature_class":"P",
    "gn:feature_code":"PPL",
    "gn:name":"Kor\u00f3neia",
    "gn:population":0,
    "gn:timezone":"Europe/Athens",
    "iso:country":"GR",
    "name:cat_x_preferred":[
        "Coronea"
    ],
    "name:ceb_x_preferred":[
        "Kor\u00f3neia"
    ],
    "name:deu_x_preferred":[
        "Koroneia"
    ],
    "name:ell_x_preferred":[
        "\u039a\u03bf\u03c1\u03ce\u03bd\u03b5\u03b9\u03b1 \u0392\u03bf\u03b9\u03c9\u03c4\u03af\u03b1\u03c2"
    ],
    "name:eus_x_preferred":[
        "Koronea"
    ],
    "name:fin_x_preferred":[
        "Kor\u00f3neia"
    ],
    "name:fra_x_preferred":[
        "Coron\u00e9e"
    ],
    "name:ita_x_preferred":[
        "Koroneia"
    ],
    "name:jpn_x_preferred":[
        "\u30b3\u30ed\u30cd\u30a4\u30a2"
    ],
    "name:kor_x_preferred":[
        "\ucf54\ub85c\ub124\uc774\uc544"
    ],
    "name:lat_x_preferred":[
        "Coronea"
    ],
    "name:nld_x_preferred":[
        "Koroneia"
    ],
    "name:por_x_preferred":[
        "Coroneia"
    ],
    "name:rus_x_preferred":[
        "\u041a\u043e\u0440\u043e\u043d\u0438\u044f"
    ],
    "name:spa_x_preferred":[
        "Coronea"
    ],
    "name:swe_x_preferred":[
        "Koroneia"
    ],
    "name:und_x_variant":[
        "Koutoumoul\u00e1",
        "Kor\u00f3nia",
        "\u039a\u03bf\u03c1\u03ce\u03bd\u03b5\u03b9\u03b1"
    ],
    "wof:name":"Koroneia",
    "wof:placetype":"locality"
},
  "geometry": {"coordinates":[22.96004,38.35925],"type":"Point"}
}