{
  "type": "Feature",
  "properties": {
    "gn:country":"GR",
    "gn:fcode":"PPL",
    "gn:population":965,
    "iso:country":"GR",
    "name:ceb_x_preferred":[
        "\u00c9xarkhos"
    ],
    "name:deu_x_preferred":[
        "Exarchos"
    ],
    "name:ell_x_preferred":[
        "\u0388\u03be\u03b1\u03c1\u03c7\u03bf\u03c2"
    ],
    "name:ell_x_variant":[
        "\u0388\u03be\u03b1\u03c1\u03c7\u03bf\u03c2 \u03a6\u03b8\u03b9\u03ce\u03c4\u03b9\u03b4\u03b1\u03c2"
    ],
    "name:eng_x_preferred":[
        "Exarchos"
    ],
    "name:nld_x_preferred":[
        "Exarchos"
    ],
    "name:swe_x_preferred":[
        "\u00c9xarkhos"
    ],
    "qs_pg:aaroncc":"GR",
    "qs_pg:gn_country":"GR",
    "qs_pg:gn_fcode":"PPL",
    "qs_pg:gn_pop":965,
    "qs_pg:name":"Exarkhos",
    "qs_pg:name_adm0":"\u0395\u03bb\u03bb\u03ac\u03b4\u03b1",
    "qs_pg:name_adm1":"Thessaly and Continental Greece",
    "qs_pg:photos_9k":1,
    "qs_pg:photos_9r":1,
    "qs_pg:photos_all":1,
    "qs_pg:photos_sr":0,
    "qs_pg:pop_sr":2,
    "qs_pg:qs_pg_placetype":"locality",
    "qs_pg:qs_pg_placetype_gp":"Town",
    "qs_pg:woe_adm0":23424833,
    "woe:adm0_id":23424833,
    "woe:name_adm0":"\u0395\u03bb\u03bb\u03ac\u03b4\u03b1",
    "woe:name_adm1":"Thessaly and Continental Greece",
    "woe:placetype":"Town",
    "wof:name":"Exarkhos",
    "wof:placetype":"locality",
    "wof:population":699
},
  "geometry": {"coordinates":[22.95,38.58333],"type":"Point"}
}