{
  "type": "Feature",
  "properties": {
    "gn:admin1_code":"ESYE22",
    "gn:admin2_code":"28.0",
    "gn:admin3_code":"9116",
    "gn:asciiname":"Kato Yerakarion",
    "gn:country_code":"GR",
    "gn:dem":45,
    "gn:feature_class":"P",
    "gn:feature_code":"PPL",
    "gn:name":"K\u00e1to Yerakar\u00edon",
    "gn:population":347,
    "gn:timezone":"Europe/Athens",
    "iso:country":"GR",
    "name:ell_x_preferred":[
        "\u039a\u03ac\u03c4\u03c9 \u0393\u03b5\u03c1\u03b1\u03ba\u03ac\u03c1\u03b9"
    ],
    "name:eng_x_preferred":[
        "Kato Gerakari"
    ],
    "name:und_x_variant":[
        "K\u00e1to Yerak\u00e1ri",
        "K\u00e1to Yerakar\u00edon",
        "Kato Yerakari"
    ],
    "wof:name":"Kato Yerakarion",
    "wof:placetype":"locality",
    "wof:population":347
},
  "geometry": {"coordinates":[20.80931,37.81141],"type":"Point"}
}