{
  "type": "Feature",
  "properties": {
    "gn:admin1_code":"ESYE22",
    "gn:admin2_code":"27.0",
    "gn:admin3_code":"9117",
    "gn:asciiname":"Kalyvia",
    "gn:country_code":"GR",
    "gn:dem":118,
    "gn:feature_class":"P",
    "gn:feature_code":"PPL",
    "gn:name":"Kal\u00fdvia",
    "gn:population":0,
    "gn:timezone":"Europe/Athens",
    "iso:country":"GR",
    "name:ell_x_preferred":[
        "Kal\u00fdvia"
    ],
    "name:ell_x_variant":[
        "\u039a\u03b1\u03bb\u03cd\u03b2\u03b9\u03b1"
    ],
    "name:und_x_variant":[
        "Kal\u00edvia"
    ],
    "wof:name":"Kalyvia",
    "wof:placetype":"locality"
},
  "geometry": {"coordinates":[20.64178,38.44814],"type":"Point"}
}