{
  "type": "Feature",
  "properties": {
    "gn:gn_country":"GR",
    "gn:gn_fcode":"PPL",
    "gn:gn_pop":102,
    "gn:population":102,
    "iso:country":"GR",
    "name:dut_x_preferred":[
        "Trygona"
    ],
    "name:ell_x_preferred":[
        "\u03a4\u03c1\u03c5\u03b3\u03ce\u03bd\u03b1"
    ],
    "name:eng_x_preferred":[
        "Trygona"
    ],
    "name:gre_x_preferred":[
        "\u03a4\u03c1\u03c5\u03b3\u03cc\u03bd\u03b1 \u039a\u03b1\u03c1\u03b4\u03af\u03c4\u03c3\u03b1\u03c2"
    ],
    "name:rum_x_preferred":[
        "Trygona"
    ],
    "name:swe_x_preferred":[
        "Tryg\u00f3na"
    ],
    "name:unk_x_variant":[
        "Trig\u00f3na"
    ],
    "qs_pg:aaroncc":"GR",
    "qs_pg:gn_country":"GR",
    "qs_pg:gn_fcode":"PPL",
    "qs_pg:gn_pop":102,
    "qs_pg:name":"Tryg\u00f3na",
    "qs_pg:photos_9r":0,
    "qs_pg:photos_sr":0,
    "qs_pg:pop_sr":1,
    "qs_pg:qs_pg_placetype":"locality",
    "wof:name":"Tryg\u00f3na",
    "wof:placetype":"locality",
    "wof:population":102
},
  "geometry": {"coordinates":[21.62694,39.40139],"type":"Point"}
}