{
  "type": "Feature",
  "properties": {
    "gn:admin1_code":"ESYE31",
    "gn:admin2_code":"445406.0",
    "gn:admin3_code":"9227",
    "gn:asciiname":"Agia Triada",
    "gn:country_code":"GR",
    "gn:dem":559,
    "gn:feature_class":"P",
    "gn:feature_code":"PPL",
    "gn:name":"Ag\u00eda Tri\u00e1da",
    "gn:population":959,
    "gn:timezone":"Europe/Athens",
    "iso:country":"GR",
    "name:ell_x_historical":[
        "\u0399\u03c0\u03c0\u03bf\u03ba\u03c1\u03ac\u03c4\u03b5\u03b9\u03bf\u03c2 \u03a0\u03bf\u03bb\u03b9\u03c4\u03b5\u03af\u03b1",
        "\u0394\u03b9\u03b5\u03b8\u03bd\u03ae\u03c2 \u0399\u03c0\u03c0\u03bf\u03ba\u03c1\u03ac\u03c4\u03b5\u03b9\u03bf\u03c2 \u03a0\u03bf\u03bb\u03b9\u03c4\u03b5\u03af\u03b1 \u03a3\u03a5\u039d.\u03a0.\u0395."
    ],
    "name:ell_x_preferred":[
        "\u0391\u03b3\u03af\u03b1 \u03a4\u03c1\u03b9\u03ac\u03b4\u03b1 \u0391\u03c6\u03b9\u03b4\u03bd\u03ce\u03bd"
    ],
    "name:ell_x_variant":[
        "\u0399\u03c0\u03c0\u03bf\u03ba\u03c1\u03ac\u03c4\u03b5\u03b9\u03bf\u03c2 \u03a0\u03bf\u03bb\u03b9\u03c4\u03b5\u03af\u03b1",
        "\u0394\u03b9\u03b5\u03b8\u03bd\u03ae\u03c2 \u0399\u03c0\u03c0\u03bf\u03ba\u03c1\u03ac\u03c4\u03b5\u03b9\u03bf\u03c2 \u03a0\u03bf\u03bb\u03b9\u03c4\u03b5\u03af\u03b1 \u03a3\u03a5\u039d.\u03a0.\u0395."
    ],
    "name:eng_x_historical":[
        "Ippokrateios Politeia"
    ],
    "name:eng_x_preferred":[
        "Agia Triada Afidnon"
    ],
    "name:eng_x_variant":[
        "Ippokrateios Politeia"
    ],
    "name:und_x_variant":[
        "Ayia Triada Afidnon",
        "Aghia Triada Afidnon"
    ],
    "wof:name":"Agia Triada",
    "wof:placetype":"locality",
    "wof:population":959
},
  "geometry": {"coordinates":[23.80308,38.20345],"type":"Point"}
}