{
  "type": "Feature",
  "properties": {
    "gn:admin1_code":"ESYE11",
    "gn:admin2_code":"4.0",
    "gn:admin3_code":"9002",
    "gn:asciiname":"Kallikarpo",
    "gn:country_code":"GR",
    "gn:dem":658,
    "gn:feature_class":"P",
    "gn:feature_code":"PPL",
    "gn:name":"Kall\u00edkarpo",
    "gn:population":0,
    "gn:timezone":"Europe/Athens",
    "iso:country":"GR",
    "name:bul_x_preferred":[
        "\u041b\u043e\u0432\u0447\u0438\u0449\u0430"
    ],
    "name:ell_x_preferred":[
        "Kall\u00edkarpo"
    ],
    "name:ell_x_variant":[
        "\u039a\u03b1\u03bb\u03bb\u03af\u03ba\u03b1\u03c1\u03c0\u03bf",
        "\u039a\u03b1\u03bb\u03bb\u03af\u03ba\u03b1\u03c1\u03c0\u03bf\u03bd"
    ],
    "name:und_x_variant":[
        "Loft\u00edsta",
        "Kall\u00edkarpon"
    ],
    "wof:name":"Kallikarpo",
    "wof:placetype":"locality"
},
  "geometry": {"coordinates":[24.21831,41.39825],"type":"Point"}
}