{
  "type": "Feature",
  "properties": {
    "gn:admin1_code":"ESYE21",
    "gn:admin2_code":"20.0",
    "gn:admin3_code":"9074",
    "gn:asciiname":"Alonia",
    "gn:country_code":"GR",
    "gn:dem":659,
    "gn:feature_class":"P",
    "gn:feature_code":"PPL",
    "gn:name":"Al\u00f3nia",
    "gn:population":0,
    "gn:timezone":"Europe/Athens",
    "iso:country":"GR",
    "name:ceb_x_preferred":[
        "Alonia"
    ],
    "name:ell_x_preferred":[
        "\u0391\u03bb\u03ce\u03bd\u03b9\u03b1"
    ],
    "name:swe_x_preferred":[
        "Alonia"
    ],
    "name:und_x_variant":[
        "Vr\u00e9sta",
        "Vrest\u00f3n",
        "Al\u00f3nia"
    ],
    "wof:name":"Alonia",
    "wof:placetype":"locality"
},
  "geometry": {"coordinates":[21.32181,39.25828],"type":"Point"}
}