{
  "type": "Feature",
  "properties": {
    "gn:admin1_code":"ESYE21",
    "gn:admin2_code":"20.0",
    "gn:admin3_code":"9073",
    "gn:asciiname":"Fraxos",
    "gn:country_code":"GR",
    "gn:dem":383,
    "gn:feature_class":"P",
    "gn:feature_code":"PPL",
    "gn:name":"Fr\u00e1xos",
    "gn:population":9,
    "gn:timezone":"Europe/Athens",
    "iso:country":"GR",
    "name:ell_x_preferred":[
        "\u03a6\u03c1\u03ac\u03be\u03bf\u03c2"
    ],
    "name:eng_x_preferred":[
        "Fraxos"
    ],
    "name:und_x_variant":[
        "Fr\u00e1xos"
    ],
    "wof:name":"Fraxos",
    "wof:placetype":"locality",
    "wof:population":9
},
  "geometry": {"coordinates":[21.04,39.3825],"type":"Point"}
}