{
  "type": "Feature",
  "properties": {
    "gn:population":1018,
    "iso:country":"GR",
    "name:ara_x_preferred":[
        "\u063a\u0627\u0641\u0627\u0644\u0648"
    ],
    "name:ell_x_preferred":[
        "\u0393\u03b1\u03b2\u03b1\u03bb\u03bf\u03cd"
    ],
    "name:ell_x_variant":[
        "\u0393\u03b1\u03b2\u03b1\u03bb\u03bf\u03cd \u0391\u03b9\u03c4\u03c9\u03bb\u03bf\u03b1\u03ba\u03b1\u03c1\u03bd\u03b1\u03bd\u03af\u03b1\u03c2"
    ],
    "name:eng_x_preferred":[
        "Gavalou"
    ],
    "name:nld_x_preferred":[
        "Gavalou"
    ],
    "name:nno_x_preferred":[
        "Gavalo\u00fa"
    ],
    "name:ron_x_preferred":[
        "Gavalou"
    ],
    "name:swe_x_preferred":[
        "Gavalo\u00fa"
    ],
    "name:unk_x_variant":[
        "Gavalu"
    ],
    "qs:a0":"Greece",
    "qs:a1":"*\u0394\u03a5\u03a4\u0399\u039a\u0397 \u0395\u039b\u039b\u0391\u0394\u0391",
    "qs:a1_alt":"DYTIKH ELLADA",
    "qs:a1r":"0",
    "qs:a2_alt":"AITVLIA KAI AKARNANIA",
    "qs:adm0":"Greece",
    "qs:la_lc":"*",
    "qs:level":"locality",
    "qs:loc":"\u0393\u0391\u0392\u0391\u039b\u039f\u03a5",
    "qs:loc_alt":"GABALOY",
    "qs:pop":0,
    "qs:type":"buffered point",
    "wd:wordcount":301,
    "wof:name":"\u0393\u0391\u0392\u0391\u039b\u039f\u03a5",
    "wof:placetype":"locality",
    "wof:population":1018
},
  "geometry": {"coordinates":[21.535153,38.528198],"type":"Point"}
}