{
  "type": "Feature",
  "properties": {
    "gn:admin1_code":"ESYE23",
    "gn:admin2_code":"31.0",
    "gn:admin3_code":"9123",
    "gn:asciiname":"Pendakorfon",
    "gn:country_code":"GR",
    "gn:dem":727,
    "gn:feature_class":"P",
    "gn:feature_code":"PPL",
    "gn:name":"Pend\u00e1korfon",
    "gn:population":210,
    "gn:timezone":"Europe/Athens",
    "iso:country":"GR",
    "name:ell_x_historical":[
        "\u0391\u03c1\u03ac\u03c7\u03c9\u03b2\u03b1"
    ],
    "name:ell_x_preferred":[
        "\u03a0\u03b5\u03bd\u03c4\u03ac\u03ba\u03bf\u03c1\u03c6\u03bf"
    ],
    "name:ell_x_variant":[
        "\u03a0\u03b5\u03bd\u03c4\u03ac\u03ba\u03bf\u03c1\u03c6\u03bf\u03bd",
        "\u0391\u03c1\u03ac\u03c7\u03c9\u03b2\u03b1"
    ],
    "name:eng_x_preferred":[
        "Pentakorfo"
    ],
    "name:und_x_variant":[
        "Arakhova",
        "Pend\u00e1korfon"
    ],
    "wof:name":"Pendakorfon",
    "wof:placetype":"locality",
    "wof:population":210
},
  "geometry": {"coordinates":[21.53243,38.78139],"type":"Point"}
}