{
  "type": "Feature",
  "properties": {
    "gn:admin1_code":"ESYE12",
    "gn:admin2_code":"6.0",
    "gn:admin3_code":"9040",
    "gn:asciiname":"Eptalofos",
    "gn:country_code":"GR",
    "gn:dem":452,
    "gn:feature_class":"P",
    "gn:feature_code":"PPL",
    "gn:name":"Ept\u00e1lofos",
    "gn:population":0,
    "gn:timezone":"Europe/Athens",
    "iso:country":"GR",
    "name:ell_x_preferred":[
        "\u0395\u03c0\u03c4\u03ac\u03bb\u03bf\u03c6\u03bf\u03c2"
    ],
    "name:und_x_variant":[
        "Sevedekl\u00ed",
        "Chernal\u00e1k",
        "Ept\u00e1lofos"
    ],
    "wof:name":"Eptalofos",
    "wof:placetype":"locality"
},
  "geometry": {"coordinates":[23.01342,41.01041],"type":"Point"}
}