{
  "type": "Feature",
  "properties": {
    "gn:admin1_code":"ESYE13",
    "gn:admin2_code":"9.0",
    "gn:admin3_code":"9063",
    "gn:asciiname":"Dendrochori",
    "gn:country_code":"GR",
    "gn:dem":950,
    "gn:feature_class":"P",
    "gn:feature_code":"PPL",
    "gn:name":"Dendroch\u00f3ri",
    "gn:population":266,
    "gn:timezone":"Europe/Athens",
    "iso:country":"GR",
    "name:bul_x_preferred":[
        "\u0414\u044a\u043c\u0431\u0435\u043d\u0438"
    ],
    "name:ceb_x_preferred":[
        "Dendroch\u00f3ri"
    ],
    "name:ell_x_historical":[
        "\u039d\u03c4\u03cd\u03bc\u03c0\u03b5\u03bd\u03b7",
        "\u0394\u03cd\u03bc\u03c0\u03b5\u03bd\u03b9",
        "\u039d\u03c4\u03ad\u03bc\u03c0\u03b5\u03bd\u03b9"
    ],
    "name:ell_x_preferred":[
        "\u0394\u03b5\u03bd\u03b4\u03c1\u03bf\u03c7\u03ce\u03c1\u03b9"
    ],
    "name:ell_x_variant":[
        "\u0394\u03b5\u03bd\u03b4\u03c1\u03bf\u03c7\u03ce\u03c1\u03b9\u03bf\u03bd",
        "\u039d\u03c4\u03cd\u03bc\u03c0\u03b5\u03bd\u03b7",
        "\u0394\u03cd\u03bc\u03c0\u03b5\u03bd\u03b9",
        "\u039d\u03c4\u03ad\u03bc\u03c0\u03b5\u03bd\u03b9",
        "\u0394\u03b5\u03bd\u03b4\u03c1\u03bf\u03c7\u03ce\u03c1\u03b9 \u039a\u03b1\u03c3\u03c4\u03bf\u03c1\u03b9\u03ac\u03c2"
    ],
    "name:eng_x_preferred":[
        "Dendrochori"
    ],
    "name:mkd_x_preferred":[
        "\u0414\u2019\u043c\u0431\u0435\u043d\u0438"
    ],
    "name:und_x_variant":[
        "D\u00e9beni",
        "Dhendrokh\u00f3ri",
        "Dhendrokh\u00f3rion",
        "Dendroch\u00f3ri",
        "Dendroch\u00f3rion"
    ],
    "wof:name":"Dendrochori",
    "wof:placetype":"locality",
    "wof:population":266
},
  "geometry": {"coordinates":[21.14595,40.58108],"type":"Point"}
}