{
  "type": "Feature",
  "properties": {
    "gn:admin1_code":"ESYE43",
    "gn:admin2_code":"43.0",
    "gn:admin3_code":"9322",
    "gn:asciiname":"Rogdia",
    "gn:country_code":"GR",
    "gn:dem":612,
    "gn:feature_class":"P",
    "gn:feature_code":"PPL",
    "gn:name":"Rogdi\u00e1",
    "gn:population":60,
    "gn:timezone":"Europe/Athens",
    "iso:country":"GR",
    "name:ell_x_preferred":[
        "\u03a1\u03bf\u03b3\u03b4\u03b9\u03ac"
    ],
    "name:eng_x_preferred":[
        "Rogdia"
    ],
    "name:und_x_variant":[
        "Rogdi\u00e1",
        "Rogdhi\u00e1"
    ],
    "wof:name":"Rogdia",
    "wof:placetype":"locality",
    "wof:population":60
},
  "geometry": {"coordinates":[23.63848,35.38179],"type":"Point"}
}