{
  "type": "Feature",
  "properties": {
    "gn:admin1_code":"ESYE43",
    "gn:admin2_code":"46.0",
    "gn:admin3_code":"9310",
    "gn:asciiname":"Skinias",
    "gn:country_code":"GR",
    "gn:dem":231,
    "gn:feature_class":"P",
    "gn:feature_code":"PPL",
    "gn:name":"Skini\u00e1s",
    "gn:population":48,
    "gn:timezone":"Europe/Athens",
    "iso:country":"GR",
    "name:ell_x_preferred":[
        "\u03a3\u03ba\u03b9\u03bd\u03b9\u03ac\u03c2"
    ],
    "name:eng_x_preferred":[
        "Skinias"
    ],
    "name:und_x_variant":[
        "Skoini\u00e1",
        "Skin\u00e1s",
        "Skini\u00e1s"
    ],
    "wof:name":"Skinias",
    "wof:placetype":"locality",
    "wof:population":48
},
  "geometry": {"coordinates":[25.69321,35.31952000000001],"type":"Point"}
}