{
  "type": "Feature",
  "properties": {
    "gn:gn_country":"GR",
    "gn:gn_fcode":"PPL",
    "gn:gn_pop":0,
    "iso:country":"GR",
    "name:afr_x_preferred":[
        "Dafni"
    ],
    "name:bul_x_preferred":[
        "\u0414\u0430\u0444\u043d\u0438"
    ],
    "name:cat_x_preferred":[
        "Dafni"
    ],
    "name:dut_x_preferred":[
        "Dafni"
    ],
    "name:eng_x_preferred":[
        "Dafni"
    ],
    "name:fin_x_preferred":[
        "D\u00e1fni"
    ],
    "name:fre_x_preferred":[
        "Dafni"
    ],
    "name:geo_x_preferred":[
        "\u10d3\u10d0\u10e4\u10dc\u10d8"
    ],
    "name:gre_x_preferred":[
        "\u0394\u03ac\u03c6\u03bd\u03b7 \u0391\u03b3\u03af\u03bf\u03c5 \u038c\u03c1\u03bf\u03c5\u03c2"
    ],
    "name:ita_x_preferred":[
        "Dafni"
    ],
    "name:rum_x_preferred":[
        "Dafni"
    ],
    "name:rus_x_preferred":[
        "\u0414\u0430\u0444\u043d\u0438"
    ],
    "name:spa_x_preferred":[
        "Dafni"
    ],
    "name:ukr_x_preferred":[
        "\u0414\u0430\u0444\u043d\u0456"
    ],
    "name:unk_x_variant":[
        "Dh\u00e1fni"
    ],
    "qs_pg:aaroncc":"GR",
    "qs_pg:gn_country":"GR",
    "qs_pg:gn_fcode":"PPL",
    "qs_pg:gn_pop":0,
    "qs_pg:name":"Dhafni",
    "qs_pg:name_adm0":"\u0395\u03bb\u03bb\u03ac\u03b4\u03b1",
    "qs_pg:name_adm1":"Mount Athos",
    "qs_pg:photos":137,
    "qs_pg:photos_1k":28,
    "qs_pg:photos_9k":1,
    "qs_pg:photos_9r":3,
    "qs_pg:photos_all":137,
    "qs_pg:photos_sr":3,
    "qs_pg:pop_sr":0,
    "qs_pg:qs_pg_placetype":"locality",
    "qs_pg:qs_pg_placetype_gp":"Town",
    "qs_pg:woe_adm0":23424833,
    "woe:adm0_id":23424833,
    "woe:name_adm0":"\u0395\u03bb\u03bb\u03ac\u03b4\u03b1",
    "woe:name_adm1":"Mount Athos",
    "woe:placetype":"Town",
    "wof:name":"Dhafni",
    "wof:placetype":"locality"
},
  "geometry": {"coordinates":[24.22245,40.21395],"type":"Point"}
}