{
  "type": "Feature",
  "properties": {
    "gn:admin1_code":"ESYE23",
    "gn:admin2_code":"39.0",
    "gn:admin3_code":"9139",
    "gn:asciiname":"Mazaraki",
    "gn:country_code":"GR",
    "gn:dem":304,
    "gn:feature_class":"P",
    "gn:feature_code":"PPL",
    "gn:name":"Mazar\u00e1ki",
    "gn:population":0,
    "gn:timezone":"Europe/Athens",
    "iso:country":"GR",
    "name:ell_x_preferred":[
        "\u039c\u03b1\u03b6\u03b1\u03c1\u03ac\u03ba\u03b9"
    ],
    "name:ell_x_variant":[
        "\u039c\u03b1\u03b6\u03b1\u03c1\u03ac\u03ba\u03b9\u03bf\u03bd"
    ],
    "name:und_x_variant":[
        "Mazar\u00e1ki",
        "Mazar\u00e1kion"
    ],
    "wof:name":"Mazaraki",
    "wof:placetype":"locality"
},
  "geometry": {"coordinates":[21.58797,37.87953],"type":"Point"}
}