{
  "type": "Feature",
  "properties": {
    "gn:gn_country":"GR",
    "gn:gn_fcode":"PPL",
    "gn:gn_pop":1500,
    "gn:population":1500,
    "iso:country":"GR",
    "name:ara_x_preferred":[
        "\u0643\u0648\u0628\u0627\u0646\u0627\u0643\u064a\u060c \u0645\u064a\u0633\u064a\u0646\u064a\u0627"
    ],
    "name:ell_x_preferred":[
        "Kopan\u00e1ki"
    ],
    "name:ell_x_variant":[
        "\u039a\u03bf\u03c0\u03b1\u03bd\u03ac\u03ba\u03b9",
        "Kopan\u00e1kion",
        "\u039a\u03bf\u03c0\u03b1\u03bd\u03ac\u03ba\u03b9\u03bf\u03bd",
        "\u039a\u03bf\u03c0\u03b1\u03bd\u03ac\u03ba\u03b9 \u039c\u03b5\u03c3\u03c3\u03b7\u03bd\u03af\u03b1\u03c2"
    ],
    "name:eng_x_preferred":[
        "Kopanaki"
    ],
    "name:nno_x_preferred":[
        "Kopan\u00e1ki"
    ],
    "name:unk_x_variant":[
        "Ep\u00e1no Kopan\u00e1ki"
    ],
    "qs_pg:aaroncc":"GR",
    "qs_pg:gn_country":"GR",
    "qs_pg:gn_fcode":"PPL",
    "qs_pg:gn_pop":1500,
    "qs_pg:name":"\u00c1no Kopan\u00e1kion",
    "qs_pg:photos_9r":0,
    "qs_pg:photos_sr":0,
    "qs_pg:pop_sr":3,
    "qs_pg:qs_pg_placetype":"locality",
    "wof:name":"\u00c1no Kopan\u00e1kion",
    "wof:placetype":"locality",
    "wof:population":1500
},
  "geometry": {"coordinates":[21.81667,37.28333],"type":"Point"}
}