{
  "type": "Feature",
  "properties": {
    "gn:admin1_code":"ESYE25",
    "gn:admin2_code":"36.0",
    "gn:admin3_code":"9234",
    "gn:asciiname":"Stamataiika",
    "gn:country_code":"GR",
    "gn:dem":453,
    "gn:feature_class":"P",
    "gn:feature_code":"PPL",
    "gn:name":"Stamata\u00edika",
    "gn:population":5,
    "gn:timezone":"Europe/Athens",
    "iso:country":"GR",
    "name:ell_x_preferred":[
        "\u03a3\u03c4\u03b1\u03bc\u03b1\u03c4\u03b1\u03af\u03b9\u03ba\u03b1"
    ],
    "name:eng_x_preferred":[
        "Stamataiika"
    ],
    "name:und_x_variant":[
        "Stamat\u00e9\u00efka",
        "Stamata\u00edika"
    ],
    "wof:name":"Stamataiika",
    "wof:placetype":"locality",
    "wof:population":5
},
  "geometry": {"coordinates":[22.9848,37.61954],"type":"Point"}
}