{
  "type": "Feature",
  "properties": {
    "gn:admin1_code":"ESYE24",
    "gn:admin2_code":"34.0",
    "gn:admin3_code":"9151",
    "gn:asciiname":"Katsaroni",
    "gn:country_code":"GR",
    "gn:dem":285,
    "gn:feature_class":"P",
    "gn:feature_code":"PPL",
    "gn:name":"Katsar\u00f3ni",
    "gn:population":0,
    "gn:timezone":"Europe/Athens",
    "iso:country":"GR",
    "name:ell_x_preferred":[
        "\u039a\u03b1\u03c4\u03c3\u03b1\u03c1\u03ce\u03bd\u03b9"
    ],
    "name:ell_x_variant":[
        "\u039a\u03b1\u03c4\u03c3\u03b1\u03c1\u03ce\u03bd\u03b9\u03bf\u03bd"
    ],
    "name:und_x_variant":[
        "Mam\u00e1lia",
        "Katsar\u00f3ni",
        "Katsar\u00f3nion"
    ],
    "wof:name":"Katsaroni",
    "wof:placetype":"locality"
},
  "geometry": {"coordinates":[24.37836,38.05758],"type":"Point"}
}