{
  "type": "Feature",
  "properties": {
    "gn:gn_country":"GR",
    "gn:gn_fcode":"PPL",
    "gn:gn_pop":813,
    "gn:population":642,
    "iso:country":"GR",
    "name:ell_x_preferred":[
        "\u039d\u03cd\u03bc\u03c6\u03b5\u03c2"
    ],
    "name:ell_x_variant":[
        "N\u00fdmfes",
        "\u039d\u03cd\u03bc\u03c6\u03b1\u03b9"
    ],
    "name:eng_x_preferred":[
        "Nymphes"
    ],
    "name:unk_x_variant":[
        "N\u00edmfai"
    ],
    "qs_pg:aaroncc":"GR",
    "qs_pg:gn_country":"GR",
    "qs_pg:gn_fcode":"PPL",
    "qs_pg:gn_pop":813,
    "qs_pg:name":"N\u00fdmfai",
    "qs_pg:photos_9r":0,
    "qs_pg:photos_sr":0,
    "qs_pg:pop_sr":2,
    "qs_pg:qs_pg_placetype":"locality",
    "wof:name":"N\u00fdmfai",
    "wof:placetype":"locality",
    "wof:population":642
},
  "geometry": {"coordinates":[19.78222,39.75333],"type":"Point"}
}