{
  "type": "Feature",
  "properties": {
    "gn:admin1_code":"ESYE24",
    "gn:admin2_code":"29.0",
    "gn:admin3_code":"9162",
    "gn:asciiname":"Mavrilon",
    "gn:country_code":"GR",
    "gn:dem":880,
    "gn:feature_class":"P",
    "gn:feature_code":"PPL",
    "gn:name":"Mavr\u00edlon",
    "gn:population":146,
    "gn:timezone":"Europe/Athens",
    "iso:country":"GR",
    "name:ell_x_preferred":[
        "\u039c\u03b1\u03c5\u03c1\u03af\u03bb\u03bf"
    ],
    "name:ell_x_variant":[
        "\u039c\u03b1\u03c5\u03c1\u03af\u03bb\u03bf\u03bd"
    ],
    "name:eng_x_preferred":[
        "Mavrilo"
    ],
    "name:und_x_variant":[
        "Mavr\u00edllon",
        "Mavr\u00edlon"
    ],
    "wof:name":"Mavrilon",
    "wof:placetype":"locality",
    "wof:population":146
},
  "geometry": {"coordinates":[21.88047000000001,38.94693],"type":"Point"}
}