{
  "type": "Feature",
  "properties": {
    "gn:admin1_code":"ESYE43",
    "gn:admin2_code":"43.0",
    "gn:admin3_code":"9323",
    "gn:asciiname":"Koumares",
    "gn:country_code":"GR",
    "gn:dem":157,
    "gn:feature_class":"P",
    "gn:feature_code":"PPL",
    "gn:name":"Koumar\u00e9s",
    "gn:population":0,
    "gn:timezone":"Europe/Athens",
    "iso:country":"GR",
    "name:ell_x_preferred":[
        "Koumar\u00e9s"
    ],
    "name:ell_x_variant":[
        "\u039a\u03bf\u03c5\u03bc\u03b1\u03c1\u03ad\u03c2"
    ],
    "wof:name":"Koumares",
    "wof:placetype":"locality"
},
  "geometry": {"coordinates":[23.78083,35.46984000000001],"type":"Point"}
}