{
  "type": "Feature",
  "properties": {
    "gn:admin1_code":"ESYE25",
    "gn:admin2_code":"42.0",
    "gn:admin3_code":"9252",
    "gn:asciiname":"Levkokhoma",
    "gn:cc2":"GR",
    "gn:country_code":"GR",
    "gn:dem":158,
    "gn:feature_class":"P",
    "gn:feature_code":"PPL",
    "gn:name":"Levk\u00f3khoma",
    "gn:population":0,
    "gn:timezone":"Europe/Athens",
    "iso:country":"GR",
    "name:ell_x_preferred":[
        "\u039b\u03b5\u03c5\u03ba\u03cc\u03c7\u03c9\u03bc\u03b1"
    ],
    "name:und_x_variant":[
        "Kar\u00e1spa\u00ef",
        "Levk\u00f3khoma"
    ],
    "wof:name":"Levkokhoma",
    "wof:placetype":"locality"
},
  "geometry": {"coordinates":[22.51223,36.97746],"type":"Point"}
}