{
  "type": "Feature",
  "properties": {
    "gn:admin1_code":"ESYE43",
    "gn:admin2_code":"45.0",
    "gn:admin3_code":"9308.0",
    "gn:asciiname":"Ellinas",
    "gn:country_code":"GR",
    "gn:dem":85,
    "gn:feature_class":"P",
    "gn:feature_code":"PPL",
    "gn:name":"\u00c9llinas",
    "gn:population":15,
    "gn:timezone":"Europe/Athens",
    "iso:country":"GR",
    "name:ell_x_preferred":[
        "\u0388\u03bb\u03bb\u03b7\u03bd\u03b1\u03c2"
    ],
    "name:eng_x_preferred":[
        "Ellinas"
    ],
    "wof:name":"Ellinas",
    "wof:placetype":"locality",
    "wof:population":15
},
  "geometry": {"coordinates":[24.75763,35.10574],"type":"Point"}
}