{
  "type": "Feature",
  "properties": {
    "gn:admin1_code":"ESYE31",
    "gn:admin2_code":"445406.0",
    "gn:admin3_code":"9227",
    "gn:asciiname":"Pontioi",
    "gn:country_code":"GR",
    "gn:dem":71,
    "gn:feature_class":"P",
    "gn:feature_code":"PPL",
    "gn:name":"P\u00f3ntioi",
    "gn:population":308,
    "gn:timezone":"Europe/Athens",
    "iso:country":"GR",
    "name:ell_x_preferred":[
        "\u03a0\u03cc\u03bd\u03c4\u03b9\u03bf\u03b9"
    ],
    "wof:name":"Pontioi",
    "wof:placetype":"locality",
    "wof:population":308
},
  "geometry": {"coordinates":[23.79501,38.30388],"type":"Point"}
}