{
  "type": "Feature",
  "properties": {
    "gn:admin1_code":"ESYE23",
    "gn:admin2_code":"31.0",
    "gn:admin3_code":"9128",
    "gn:asciiname":"Kakaiika",
    "gn:country_code":"GR",
    "gn:dem":44,
    "gn:feature_class":"P",
    "gn:feature_code":"PPL",
    "gn:name":"Kaka\u00edika",
    "gn:population":0,
    "gn:timezone":"Europe/Athens",
    "iso:country":"GR",
    "name:ell_x_preferred":[
        "Kaka\u00edika"
    ],
    "name:ell_x_variant":[
        "\u039a\u03b1\u03ba\u03b1\u03af\u03b9\u03ba\u03b1"
    ],
    "wof:name":"Kakaiika",
    "wof:placetype":"locality"
},
  "geometry": {"coordinates":[21.64058,38.37297],"type":"Point"}
}