{
  "type": "Feature",
  "properties": {
    "gn:admin1_code":"ESYE23",
    "gn:admin2_code":"31.0",
    "gn:admin3_code":"9125",
    "gn:asciiname":"Ftelia",
    "gn:country_code":"GR",
    "gn:dem":343,
    "gn:feature_class":"P",
    "gn:feature_code":"PPL",
    "gn:name":"Fteli\u00e1",
    "gn:population":0,
    "gn:timezone":"Europe/Athens",
    "iso:country":"GR",
    "name:deu_x_preferred":[
        "Ftelia"
    ],
    "name:ell_x_preferred":[
        "Fteli\u00e1"
    ],
    "name:ell_x_variant":[
        "\u03a6\u03c4\u03b5\u03bb\u03b9\u03ac"
    ],
    "name:fin_x_preferred":[
        "Fteli\u00e1"
    ],
    "name:lat_x_preferred":[
        "Phthelia"
    ],
    "wof:name":"Ftelia",
    "wof:placetype":"locality"
},
  "geometry": {"coordinates":[21.30297,39.03694],"type":"Point"}
}