{
  "type": "Feature",
  "properties": {
    "gn:country":"GR",
    "gn:fcode":"PPL",
    "gn:population":0,
    "iso:country":"GR",
    "name:ell_x_preferred":[
        "\u039a\u03b1\u03bb\u03bb\u03af\u03b4\u03c1\u03bf\u03bc\u03bf"
    ],
    "name:ell_x_variant":[
        "\u039a\u03b1\u03bb\u03bb\u03af\u03b4\u03c1\u03bf\u03bc\u03bf\u03bd"
    ],
    "name:eng_x_preferred":[
        "Kallidromo"
    ],
    "name:und_x_variant":[
        "Retz\u00e9ri"
    ],
    "qs_pg:aaroncc":"GR",
    "qs_pg:gn_country":"GR",
    "qs_pg:gn_fcode":"PPL",
    "qs_pg:gn_pop":0,
    "qs_pg:name":"Kallidhromon",
    "qs_pg:name_adm0":"\u0395\u03bb\u03bb\u03ac\u03b4\u03b1",
    "qs_pg:name_adm1":"Thessaly and Continental Greece",
    "qs_pg:photos":4,
    "qs_pg:photos_1k":1,
    "qs_pg:photos_9k":1,
    "qs_pg:photos_9r":1,
    "qs_pg:photos_all":4,
    "qs_pg:photos_sr":1,
    "qs_pg:pop_sr":0,
    "qs_pg:qs_pg_placetype":"locality",
    "qs_pg:qs_pg_placetype_gp":"Town",
    "qs_pg:woe_adm0":23424833,
    "woe:adm0_id":23424833,
    "woe:name_adm0":"\u0395\u03bb\u03bb\u03ac\u03b4\u03b1",
    "woe:name_adm1":"Thessaly and Continental Greece",
    "woe:placetype":"Town",
    "wof:name":"Kallidhromon",
    "wof:placetype":"locality",
    "wof:population":168
},
  "geometry": {"coordinates":[22.66667,38.73333],"type":"Point"}
}