{
  "type": "Feature",
  "properties": {
    "gn:admin1_code":"ESYE22",
    "gn:admin2_code":"25.0",
    "gn:admin3_code":"9119",
    "gn:asciiname":"Vasilatika",
    "gn:country_code":"GR",
    "gn:dem":98,
    "gn:feature_class":"P",
    "gn:feature_code":"PPL",
    "gn:name":"Vasil\u00e1tika",
    "gn:population":0,
    "gn:timezone":"Europe/Athens",
    "iso:country":"GR",
    "name:ell_x_preferred":[
        "Vasil\u00e1tika"
    ],
    "name:ell_x_variant":[
        "\u0392\u03b1\u03c3\u03b9\u03bb\u03ac\u03c4\u03b9\u03ba\u03b1"
    ],
    "wof:name":"Vasilatika",
    "wof:placetype":"locality"
},
  "geometry": {"coordinates":[20.13222,39.22305],"type":"Point"}
}