{
  "type": "Feature",
  "properties": {
    "gn:admin1_code":"ESYE43",
    "gn:admin2_code":"46.0",
    "gn:admin3_code":"9313",
    "gn:asciiname":"Kalo Chorio",
    "gn:country_code":"GR",
    "gn:dem":554,
    "gn:feature_class":"P",
    "gn:feature_code":"PPL",
    "gn:name":"Kal\u00f3 Chori\u00f3",
    "gn:population":0,
    "gn:timezone":"Europe/Athens",
    "iso:country":"GR",
    "name:ceb_x_preferred":[
        "Kalo Chorio"
    ],
    "name:deu_x_preferred":[
        "Kalo Chorio"
    ],
    "name:ell_x_preferred":[
        "Kal\u00f3 Chori\u00f3"
    ],
    "name:ell_x_variant":[
        "\u039a\u03b1\u03bb\u03cc \u03a7\u03c9\u03c1\u03b9\u03cc",
        "Kal\u00f3n Chor\u00edon",
        "\u039a\u03b1\u03bb\u03cc\u03bd \u03a7\u03c9\u03c1\u03af\u03bf\u03bd"
    ],
    "name:fra_x_preferred":[
        "Kal\u00f3 Chori\u00f3"
    ],
    "name:pol_x_preferred":[
        "Kalo Chorio"
    ],
    "name:swe_x_preferred":[
        "Kalo Chorio"
    ],
    "name:und_x_variant":[
        "Kal\u00f3 Khori\u00f3",
        "Kal\u00f3n Khor\u00edon"
    ],
    "wof:name":"Kalo Chorio",
    "wof:placetype":"locality"
},
  "geometry": {"coordinates":[26.15689,35.04464],"type":"Point"}
}