{
  "type": "Feature",
  "properties": {
    "gn:admin1_code":"ESYE23",
    "gn:admin2_code":"38.0",
    "gn:admin3_code":"9131",
    "gn:asciiname":"Spata",
    "gn:country_code":"GR",
    "gn:dem":230,
    "gn:feature_class":"P",
    "gn:feature_code":"PPL",
    "gn:name":"Sp\u00e1ta",
    "gn:population":0,
    "gn:timezone":"Europe/Athens",
    "iso:country":"GR",
    "name:ara_x_preferred":[
        "\u0633\u0628\u0627\u062a\u0627"
    ],
    "name:ceb_x_preferred":[
        "Sp\u00e1ta"
    ],
    "name:ell_x_preferred":[
        "Sp\u00e1ta"
    ],
    "name:ell_x_variant":[
        "\u03a3\u03c0\u03ac\u03c4\u03b1"
    ],
    "name:fin_x_preferred":[
        "Sp\u00e1ta"
    ],
    "name:fra_x_preferred":[
        "Sp\u00e1ta"
    ],
    "name:hye_x_preferred":[
        "\u054d\u057a\u0561\u057f\u0561"
    ],
    "name:ita_x_preferred":[
        "Spata"
    ],
    "name:mya_x_preferred":[
        "\u1005\u1015\u102b\u1038\u1010\u102c\u1038"
    ],
    "name:nno_x_preferred":[
        "Sp\u00e1ta"
    ],
    "name:pol_x_preferred":[
        "Spata"
    ],
    "name:ron_x_preferred":[
        "Spata"
    ],
    "name:rus_x_preferred":[
        "\u0421\u043f\u0430\u0442\u0430"
    ],
    "name:sqi_x_preferred":[
        "Shpatanji"
    ],
    "name:swe_x_preferred":[
        "Sp\u00e1ta"
    ],
    "name:tur_x_preferred":[
        "Spata"
    ],
    "wof:name":"Spata",
    "wof:placetype":"locality"
},
  "geometry": {"coordinates":[21.48889,38.00558],"type":"Point"}
}