{
  "type": "Feature",
  "properties": {
    "gn:admin1_code":"ESYE23",
    "gn:admin2_code":"38.0",
    "gn:admin3_code":"9131",
    "gn:asciiname":"Spata",
    "gn:country_code":"GR",
    "gn:dem":230,
    "gn:feature_class":"P",
    "gn:feature_code":"PPL",
    "gn:name":"Sp\u00e1ta",
    "gn:population":0,
    "gn:timezone":"Europe/Athens",
    "iso:country":"GR",
    "name:ell_x_preferred":[
        "Sp\u00e1ta"
    ],
    "name:ell_x_variant":[
        "\u03a3\u03c0\u03ac\u03c4\u03b1"
    ],
    "wof:name":"Spata",
    "wof:placetype":"locality"
},
  "geometry": {"coordinates":[21.48889,38.00558],"type":"Point"}
}