{
  "type": "Feature",
  "properties": {
    "gn:country":"GR",
    "gn:fcode":"PPL",
    "gn:population":81,
    "iso:country":"GR",
    "qs_pg:aaroncc":"GR",
    "qs_pg:gn_country":"GR",
    "qs_pg:gn_fcode":"PPL",
    "qs_pg:gn_pop":81,
    "qs_pg:name":"Than\u00e1sia",
    "qs_pg:photos_9r":0,
    "qs_pg:photos_sr":0,
    "qs_pg:pop_sr":1,
    "qs_pg:qs_pg_placetype":"locality",
    "wof:name":"Than\u00e1sia",
    "wof:placetype":"locality",
    "wof:population":81
},
  "geometry": {"coordinates":[21.14778,39.32611],"type":"Point"}
}