{
  "type": "Feature",
  "properties": {
    "gn:country":"GR",
    "gn:fcode":"PPL",
    "gn:population":211,
    "iso:country":"GR",
    "name:arz_x_preferred":[
        "\u0627\u0631\u062a\u0648\u067e\u0648\u0644\u0627"
    ],
    "name:ceb_x_preferred":[
        "Artopo\u00fala"
    ],
    "name:ell_x_preferred":[
        "\u0391\u03c1\u03c4\u03bf\u03c0\u03bf\u03cd\u03bb\u03b1"
    ],
    "name:ell_x_variant":[
        "\u0391\u03c1\u03c4\u03bf\u03c0\u03bf\u03cd\u03bb\u03b1 \u0399\u03c9\u03b1\u03bd\u03bd\u03af\u03bd\u03c9\u03bd"
    ],
    "name:eng_x_preferred":[
        "Artopoula"
    ],
    "name:mkd_x_preferred":[
        "\u0415\u043b\u0435\u0437\u043d\u0430"
    ],
    "name:nld_x_preferred":[
        "Artopoula"
    ],
    "name:swe_x_preferred":[
        "Artopo\u00fala"
    ],
    "name:und_x_variant":[
        "\u00c9lezna"
    ],
    "qs_pg:aaroncc":"GR",
    "qs_pg:gn_country":"GR",
    "qs_pg:gn_fcode":"PPL",
    "qs_pg:gn_pop":211,
    "qs_pg:name":"Artopoula",
    "qs_pg:name_adm0":"\u0395\u03bb\u03bb\u03ac\u03b4\u03b1",
    "qs_pg:name_adm1":"Epirus and Western Macedonia",
    "qs_pg:photos_9r":0,
    "qs_pg:photos_sr":0,
    "qs_pg:pop_sr":2,
    "qs_pg:qs_pg_placetype":"locality",
    "qs_pg:qs_pg_placetype_gp":"Town",
    "qs_pg:woe_adm0":23424833,
    "woe:adm0_id":23424833,
    "woe:name_adm0":"\u0395\u03bb\u03bb\u03ac\u03b4\u03b1",
    "woe:name_adm1":"Epirus and Western Macedonia",
    "woe:placetype":"Town",
    "wof:name":"Artopoula",
    "wof:placetype":"locality",
    "wof:population":123
},
  "geometry": {"coordinates":[20.68667,39.495],"type":"Point"}
}