{
  "type": "Feature",
  "properties": {
    "gn:admin1_code":"ESYE31",
    "gn:admin2_code":"406101.0",
    "gn:admin3_code":"9211.0",
    "gn:asciiname":"Iliakti",
    "gn:country_code":"GR",
    "gn:dem":25,
    "gn:feature_class":"P",
    "gn:feature_code":"PPL",
    "gn:name":"Iliakt\u00ed",
    "gn:population":0,
    "gn:timezone":"Europe/Athens",
    "iso:country":"GR",
    "name:ell_x_preferred":[
        "Iliakt\u00ed"
    ],
    "name:ell_x_variant":[
        "\u0397\u03bb\u03b9\u03b1\u03ba\u03c4\u03ae"
    ],
    "wof:name":"Iliakti",
    "wof:placetype":"locality"
},
  "geometry": {"coordinates":[23.42917000000001,37.95706],"type":"Point"}
}