{
  "type": "Feature",
  "properties": {
    "gn:admin1_code":"ESYE14",
    "gn:admin2_code":"23.0",
    "gn:admin3_code":"9095",
    "gn:asciiname":"Gorgovites",
    "gn:country_code":"GR",
    "gn:dem":96,
    "gn:feature_class":"P",
    "gn:feature_code":"PPL",
    "gn:name":"Gorgov\u00edtes",
    "gn:population":0,
    "gn:timezone":"Europe/Athens",
    "iso:country":"GR",
    "name:ell_x_preferred":[
        "Gorgov\u00edtes"
    ],
    "name:ell_x_variant":[
        "\u0393\u03bf\u03c1\u03b3\u03bf\u03b2\u03af\u03c4\u03b5\u03c2",
        "\u0393\u03bf\u03c1\u03b3\u03bf\u03b2\u03af\u03c4\u03b1\u03b9"
    ],
    "name:und_x_variant":[
        "Gourgov\u00edtes",
        "Gorgov\u00edtai"
    ],
    "wof:name":"Gorgovites",
    "wof:placetype":"locality"
},
  "geometry": {"coordinates":[22.0143,39.40169],"type":"Point"}
}