{
  "type": "Feature",
  "properties": {
    "gn:admin1_code":"ESYE31",
    "gn:admin2_code":"445407.0",
    "gn:admin3_code":"9230",
    "gn:asciiname":"Nea Zoi",
    "gn:country_code":"GR",
    "gn:dem":138,
    "gn:feature_class":"P",
    "gn:feature_code":"PPL",
    "gn:name":"N\u00e9a Zo\u00ed",
    "gn:population":518,
    "gn:timezone":"Europe/Athens",
    "iso:country":"GR",
    "name:ell_x_preferred":[
        "\u039d\u03ad\u03b1 \u0396\u03c9\u03ae"
    ],
    "name:eng_x_preferred":[
        "Nea Zoi"
    ],
    "wof:name":"Nea Zoi",
    "wof:placetype":"locality",
    "wof:population":518
},
  "geometry": {"coordinates":[23.48413,38.08343],"type":"Point"}
}