{
  "type": "Feature",
  "properties": {
    "gn:admin1_code":"ESYE25",
    "gn:admin2_code":"40.0",
    "gn:admin3_code":"9257",
    "gn:asciiname":"Kallithea",
    "gn:country_code":"GR",
    "gn:dem":231,
    "gn:feature_class":"P",
    "gn:feature_code":"PPL",
    "gn:name":"Kallith\u00e9a",
    "gn:population":0,
    "gn:timezone":"Europe/Athens",
    "iso:country":"GR",
    "name:ell_x_preferred":[
        "\u039a\u03b1\u03bb\u03bb\u03b9\u03b8\u03ad\u03b1"
    ],
    "name:und_x_variant":[
        "Pil\u00edas",
        "Kallith\u00e9a Pil\u00edas",
        "Memer\u00edzi",
        "Kallith\u00e9a"
    ],
    "wof:name":"Kallithea",
    "wof:placetype":"locality"
},
  "geometry": {"coordinates":[21.7878,36.88001],"type":"Point"}
}