{
  "type": "Feature",
  "properties": {
    "gn:admin1_code":"ESYE25",
    "gn:admin2_code":"40.0",
    "gn:admin3_code":"9257",
    "gn:asciiname":"Kallithea",
    "gn:country_code":"GR",
    "gn:dem":231,
    "gn:feature_class":"P",
    "gn:feature_code":"PPL",
    "gn:name":"Kallith\u00e9a",
    "gn:population":0,
    "gn:timezone":"Europe/Athens",
    "iso:country":"GR",
    "name:ara_x_preferred":[
        "\u0643\u0627\u0644\u064a\u062b\u064a\u0627"
    ],
    "name:bul_x_preferred":[
        "\u041a\u0430\u043b\u0438\u0442\u0435\u0430"
    ],
    "name:cat_x_preferred":[
        "Kal\u00b7lithea"
    ],
    "name:ceb_x_preferred":[
        "Kallith\u00e9a"
    ],
    "name:ces_x_preferred":[
        "Kallithea"
    ],
    "name:deu_x_preferred":[
        "Kallithea"
    ],
    "name:ell_x_preferred":[
        "\u039a\u03b1\u03bb\u03bb\u03b9\u03b8\u03ad\u03b1"
    ],
    "name:ell_x_variant":[
        "\u039a\u03b1\u03bb\u03bb\u03b9\u03b8\u03ad\u03b1 \u0391\u03c4\u03c4\u03b9\u03ba\u03ae\u03c2"
    ],
    "name:fas_x_preferred":[
        "\u06a9\u0627\u0644\u06cc\u062a\u0647\u200c\u0622"
    ],
    "name:fin_x_preferred":[
        "Kallith\u00e9a"
    ],
    "name:fra_x_preferred":[
        "Kallith\u00e9a"
    ],
    "name:glv_x_preferred":[
        "Kallithea"
    ],
    "name:hun_x_preferred":[
        "Kalith\u00e9a"
    ],
    "name:ita_x_preferred":[
        "Kallithea"
    ],
    "name:jpn_x_preferred":[
        "\u30ab\u30ea\u30c6\u30a2"
    ],
    "name:kor_x_preferred":[
        "\uce7c\ub9ac\ud14c\uc544"
    ],
    "name:lit_x_preferred":[
        "Kalit\u0117ja"
    ],
    "name:nld_x_preferred":[
        "Kallithea"
    ],
    "name:nno_x_preferred":[
        "Kallith\u00e9a"
    ],
    "name:pol_x_preferred":[
        "Kalitea"
    ],
    "name:por_x_preferred":[
        "Caliteia"
    ],
    "name:ron_x_preferred":[
        "Kallithea"
    ],
    "name:rus_x_preferred":[
        "\u041a\u0430\u043b\u0438\u0442\u0435\u044f"
    ],
    "name:slk_x_preferred":[
        "Kallithea"
    ],
    "name:spa_x_preferred":[
        "Kallithea"
    ],
    "name:srp_x_preferred":[
        "\u041a\u0430\u043b\u0438\u0442\u0435\u0430"
    ],
    "name:swe_x_preferred":[
        "Kallithea"
    ],
    "name:tur_x_preferred":[
        "Kallithea"
    ],
    "name:ukr_x_preferred":[
        "\u041a\u0430\u043b\u043b\u0456\u0442\u0435\u044f"
    ],
    "name:und_x_variant":[
        "Pil\u00edas",
        "Kallith\u00e9a Pil\u00edas",
        "Memer\u00edzi",
        "Kallith\u00e9a"
    ],
    "name:urd_x_preferred":[
        "\u06a9\u0627\u0644\u06cc\u062a\u06be\u06cc\u0627"
    ],
    "name:vie_x_preferred":[
        "Kallithea"
    ],
    "name:vol_x_preferred":[
        "Kallithea"
    ],
    "name:war_x_preferred":[
        "Kallithea"
    ],
    "name:zho_x_preferred":[
        "\u5361\u5229\u5730\u4e9e"
    ],
    "wof:name":"Kallithea",
    "wof:placetype":"locality"
},
  "geometry": {"coordinates":[21.7878,36.88001],"type":"Point"}
}