{
  "type": "Feature",
  "properties": {
    "gn:admin1_code":"ESYE23",
    "gn:admin2_code":"31.0",
    "gn:admin3_code":"9126",
    "gn:asciiname":"Kaloudi",
    "gn:country_code":"GR",
    "gn:dem":377,
    "gn:feature_class":"P",
    "gn:feature_code":"PPL",
    "gn:name":"Kalo\u00fadi",
    "gn:population":0,
    "gn:timezone":"Europe/Athens",
    "iso:country":"GR",
    "name:ell_x_preferred":[
        "Kalo\u00fadi"
    ],
    "name:ell_x_variant":[
        "\u039a\u03b1\u03bb\u03bf\u03cd\u03b4\u03b9",
        "Kalo\u00fadion",
        "\u039a\u03b1\u03bb\u03bf\u03cd\u03b4\u03b9\u03bf\u03bd"
    ],
    "name:und_x_variant":[
        "Kalo\u00fadhira",
        "Kalo\u00fadhion"
    ],
    "wof:name":"Kaloudi",
    "wof:placetype":"locality"
},
  "geometry": {"coordinates":[21.67383,38.49256],"type":"Point"}
}