{
  "type": "Feature",
  "properties": {
    "gn:population":7885,
    "iso:country":"GR",
    "name:ara_x_preferred":[
        "\u063a\u064a\u0627\u0646\u0648\u0644\u064a"
    ],
    "name:ceb_x_preferred":[
        "Gi\u00e1nnouli"
    ],
    "name:ell_x_preferred":[
        "\u0394\u03ae\u03bc\u03bf\u03c2 \u0393\u03b9\u03ac\u03bd\u03bd\u03bf\u03c5\u03bb\u03b7\u03c2"
    ],
    "name:ell_x_variant":[
        "\u0393\u03b9\u03ac\u03bd\u03bd\u03bf\u03c5\u03bb\u03b7",
        "\u0393\u03b9\u03ac\u03bd\u03bd\u03bf\u03c5\u03bb\u03b7 \u039b\u03ac\u03c1\u03b9\u03c3\u03b1\u03c2"
    ],
    "name:eng_x_preferred":[
        "Giannouli"
    ],
    "name:fin_x_preferred":[
        "Gi\u00e1nnouli"
    ],
    "name:fra_x_preferred":[
        "Giannouli"
    ],
    "name:ita_x_preferred":[
        "Giannouli"
    ],
    "name:jpn_x_preferred":[
        "\u30e4\u30f3\u30cc\u30ea"
    ],
    "name:nld_x_preferred":[
        "Giannouli"
    ],
    "name:nno_x_preferred":[
        "J\u00e1nnouli"
    ],
    "name:rus_x_preferred":[
        "\u042f\u043d\u0443\u043b\u0438"
    ],
    "name:swe_x_preferred":[
        "Gi\u00e1nnouli"
    ],
    "name:unk_x_variant":[
        "Yi\u00e1nnouli"
    ],
    "qs:a0":"Greece",
    "qs:a1":"*\u0398\u0395\u03a3\u03a3\u0391\u039b\u0399\u0391",
    "qs:a1_alt":"UESSALIA",
    "qs:a1r":"0",
    "qs:a2_alt":"LARISA",
    "qs:adm0":"Greece",
    "qs:la_lc":"*",
    "qs:level":"locality",
    "qs:loc":"\u0393\u0399\u0391\u039d\u039d\u039f\u03a5\u039b\u0397",
    "qs:loc_alt":"GIANNOYLH",
    "qs:pop":0,
    "qs:type":"buffered point",
    "wd:wordcount":46,
    "wof:name":"\u0393\u0399\u0391\u039d\u039d\u039f\u03a5\u039b\u0397",
    "wof:placetype":"locality",
    "wof:population":7885
},
  "geometry": {"coordinates":[22.395632,39.666287],"type":"Point"}
}