{
  "type": "Feature",
  "properties": {
    "gn:admin1_code":"ESYE25",
    "gn:admin2_code":"40.0",
    "gn:admin3_code":"9258",
    "gn:asciiname":"Lykoudesi",
    "gn:country_code":"GR",
    "gn:dem":590,
    "gn:feature_class":"P",
    "gn:feature_code":"PPL",
    "gn:name":"Lykoud\u00e9si",
    "gn:population":0,
    "gn:timezone":"Europe/Athens",
    "iso:country":"GR",
    "name:ell_x_preferred":[
        "Lykoud\u00e9si"
    ],
    "name:ell_x_variant":[
        "\u039b\u03c5\u03ba\u03bf\u03c5\u03b4\u03ad\u03c3\u03b9",
        "Lykoud\u00e9sion",
        "\u039b\u03c5\u03ba\u03bf\u03c5\u03b4\u03ad\u03c3\u03b9\u03bf\u03bd"
    ],
    "name:und_x_variant":[
        "Likho\u00fadhesi",
        "Lik\u00f3dhesi",
        "Likoudh\u00e9sion"
    ],
    "wof:name":"Lykoudesi",
    "wof:placetype":"locality"
},
  "geometry": {"coordinates":[21.78229,37.17461],"type":"Point"}
}