{
  "type": "Feature",
  "properties": {
    "gn:gn_country":"GR",
    "gn:gn_fcode":"PPL",
    "gn:gn_pop":100,
    "gn:population":100,
    "iso:country":"GR",
    "name:dut_x_preferred":[
        "Athamania"
    ],
    "name:ell_x_preferred":[
        "\u0391\u03b8\u03b1\u03bc\u03b1\u03bd\u03af\u03b1"
    ],
    "name:eng_x_preferred":[
        "Athamania"
    ],
    "name:gre_x_preferred":[
        "\u0391\u03b8\u03b1\u03bc\u03b1\u03bd\u03af\u03b1 \u03a4\u03c1\u03b9\u03ba\u03ac\u03bb\u03c9\u03bd"
    ],
    "name:unk_x_variant":[
        "M\u00e9ga Lith\u00e1rion"
    ],
    "qs_pg:aaroncc":"GR",
    "qs_pg:gn_country":"GR",
    "qs_pg:gn_fcode":"PPL",
    "qs_pg:gn_pop":100,
    "qs_pg:name":"Athamania",
    "qs_pg:name_adm0":"\u0395\u03bb\u03bb\u03ac\u03b4\u03b1",
    "qs_pg:name_adm1":"Thessaly and Continental Greece",
    "qs_pg:photos_9k":1,
    "qs_pg:photos_9r":1,
    "qs_pg:photos_all":1,
    "qs_pg:photos_sr":0,
    "qs_pg:pop_sr":1,
    "qs_pg:qs_pg_placetype":"locality",
    "qs_pg:qs_pg_placetype_gp":"Town",
    "qs_pg:woe_adm0":23424833,
    "woe:adm0_id":23424833,
    "woe:name_adm0":"\u0395\u03bb\u03bb\u03ac\u03b4\u03b1",
    "woe:name_adm1":"Thessaly and Continental Greece",
    "woe:placetype":"Town",
    "wof:name":"Athamania",
    "wof:placetype":"locality",
    "wof:population":100
},
  "geometry": {"coordinates":[21.25028,39.52722],"type":"Point"}
}