{
  "type": "Feature",
  "properties": {
    "gn:admin1_code":"ESYE14",
    "gn:admin2_code":"23.0",
    "gn:admin3_code":"9096",
    "gn:asciiname":"Agia Paraskevi",
    "gn:country_code":"GR",
    "gn:dem":117,
    "gn:feature_class":"P",
    "gn:feature_code":"PPL",
    "gn:name":"Ag\u00eda Paraskev\u00ed",
    "gn:population":0,
    "gn:timezone":"Europe/Athens",
    "iso:country":"GR",
    "name:ell_x_preferred":[
        "Ag\u00eda Paraskev\u00ed"
    ],
    "name:ell_x_variant":[
        "\u0391\u03b3\u03af\u03b1 \u03a0\u03b1\u03c1\u03b1\u03c3\u03ba\u03b5\u03c5\u03ae"
    ],
    "name:und_x_variant":[
        "Kazn\u00e9sion Mago\u00falas",
        "Karn\u00e9si",
        "Ay\u00eda Paraskev\u00ed"
    ],
    "wof:name":"Agia Paraskevi",
    "wof:placetype":"locality"
},
  "geometry": {"coordinates":[22.04302,39.30571],"type":"Point"}
}