{
  "type": "Feature",
  "properties": {
    "gn:gn_country":"GR",
    "gn:gn_fcode":"PPL",
    "gn:gn_pop":68,
    "gn:population":41,
    "iso:country":"GR",
    "name:bul_x_preferred":[
        "\u041a\u0430\u0442\u043e \u041f\u0435\u0434\u0438\u043d\u0430"
    ],
    "name:dut_x_preferred":[
        "Kato Pedina"
    ],
    "name:ell_x_historical":[
        "\u039a\u03ac\u03c4\u03c9 \u03a3\u03bf\u03c5\u03b4\u03b5\u03bd\u03ac"
    ],
    "name:ell_x_preferred":[
        "\u039a\u03ac\u03c4\u03c9 \u03a0\u03b5\u03b4\u03b9\u03bd\u03ac"
    ],
    "name:ell_x_variant":[
        "\u039a\u03ac\u03c4\u03c9 \u03a3\u03bf\u03c5\u03b4\u03b5\u03bd\u03ac"
    ],
    "name:eng_x_preferred":[
        "Kato Pedina"
    ],
    "name:gre_x_preferred":[
        "\u039a\u03ac\u03c4\u03c9 \u03a0\u03b5\u03b4\u03b9\u03bd\u03ac \u0399\u03c9\u03b1\u03bd\u03bd\u03af\u03bd\u03c9\u03bd"
    ],
    "name:unk_x_variant":[
        "K\u00e1to Pedhin\u00e1"
    ],
    "qs_pg:aaroncc":"GR",
    "qs_pg:gn_country":"GR",
    "qs_pg:gn_fcode":"PPL",
    "qs_pg:gn_pop":68,
    "qs_pg:name":"K\u00e1to Pedin\u00e1",
    "qs_pg:photos_9r":0,
    "qs_pg:photos_sr":0,
    "qs_pg:pop_sr":1,
    "qs_pg:qs_pg_placetype":"locality",
    "wof:name":"K\u00e1to Pedin\u00e1",
    "wof:placetype":"locality",
    "wof:population":41
},
  "geometry": {"coordinates":[20.67694,39.87917],"type":"Point"}
}