{
  "type": "Feature",
  "properties": {
    "gn:admin1_code":"ESYE43",
    "gn:admin2_code":"45.0",
    "gn:admin3_code":"9308",
    "gn:asciiname":"Kastelli",
    "gn:country_code":"GR",
    "gn:dem":166,
    "gn:feature_class":"P",
    "gn:feature_code":"PPL",
    "gn:name":"Kast\u00e9lli",
    "gn:population":0,
    "gn:timezone":"Europe/Athens",
    "iso:country":"GR",
    "name:ell_x_preferred":[
        "Kast\u00e9lli"
    ],
    "name:ell_x_variant":[
        "\u039a\u03b1\u03c3\u03c4\u03ad\u03bb\u03bb\u03b9",
        "Kast\u00e9llion",
        "\u039a\u03b1\u03c3\u03c4\u03ad\u03bb\u03bb\u03b9\u03bf\u03bd"
    ],
    "wof:name":"Kastelli",
    "wof:placetype":"locality"
},
  "geometry": {"coordinates":[24.91812,35.05945],"type":"Point"}
}