{
  "type": "Feature",
  "properties": {
    "gn:admin1_code":"ESYE14",
    "gn:admin2_code":"21.0",
    "gn:admin3_code":"9099",
    "gn:asciiname":"Niki",
    "gn:country_code":"GR",
    "gn:dem":54,
    "gn:feature_class":"P",
    "gn:feature_code":"PPL",
    "gn:name":"N\u00edki",
    "gn:population":0,
    "gn:timezone":"Europe/Athens",
    "iso:country":"GR",
    "name:ceb_x_preferred":[
        "Niki"
    ],
    "name:deu_x_preferred":[
        "Niki"
    ],
    "name:ell_x_preferred":[
        "\u039d\u03af\u03ba\u03b7"
    ],
    "name:fra_x_preferred":[
        "Niki"
    ],
    "name:ita_x_preferred":[
        "Niki"
    ],
    "name:nld_x_preferred":[
        "Niki"
    ],
    "name:swe_x_preferred":[
        "Niki"
    ],
    "name:ukr_x_preferred":[
        "\u041d\u0456\u043a\u0456"
    ],
    "name:und_x_variant":[
        "Hajop\u00e1sion",
        "Haj\u00f3basi",
        "N\u00edki"
    ],
    "name:urd_x_preferred":[
        "\u0646\u06a9\u06cc"
    ],
    "name:vie_x_preferred":[
        "Niki"
    ],
    "wof:name":"Niki",
    "wof:placetype":"locality"
},
  "geometry": {"coordinates":[22.68642,39.51781],"type":"Point"}
}