{
  "type": "Feature",
  "properties": {
    "gn:country":"GR",
    "gn:fcode":"PPL",
    "gn:population":274,
    "iso:country":"GR",
    "name:ell_x_preferred":[
        "Pagkr\u00e1ti"
    ],
    "name:ell_x_variant":[
        "\u03a0\u03b1\u03b3\u03ba\u03c1\u03ac\u03c4\u03b9"
    ],
    "name:und_x_variant":[
        "Pangr\u00e1ti"
    ],
    "qs_pg:aaroncc":"GR",
    "qs_pg:gn_country":"GR",
    "qs_pg:gn_fcode":"PPL",
    "qs_pg:gn_pop":274,
    "qs_pg:name":"Pagkr\u00e1tai",
    "qs_pg:photos_9r":0,
    "qs_pg:photos_sr":0,
    "qs_pg:pop_sr":2,
    "qs_pg:qs_pg_placetype":"locality",
    "wof:name":"Pagkr\u00e1tai",
    "wof:placetype":"locality",
    "wof:population":274
},
  "geometry": {"coordinates":[20.47111,39.43278],"type":"Point"}
}