{
  "type": "Feature",
  "properties": {
    "gn:admin1_code":"ESYE24",
    "gn:admin2_code":"34.0",
    "gn:admin3_code":"9152",
    "gn:asciiname":"Perivolia",
    "gn:country_code":"GR",
    "gn:dem":93,
    "gn:feature_class":"P",
    "gn:feature_code":"PPL",
    "gn:name":"Periv\u00f3lia",
    "gn:population":0,
    "gn:timezone":"Europe/Athens",
    "iso:country":"GR",
    "name:ceb_x_preferred":[
        "Perivolia"
    ],
    "name:deu_x_preferred":[
        "Perivolia"
    ],
    "name:ell_x_preferred":[
        "Periv\u00f3lia"
    ],
    "name:ell_x_variant":[
        "\u03a0\u03b5\u03c1\u03b9\u03b2\u03cc\u03bb\u03b9\u03b1"
    ],
    "name:swe_x_preferred":[
        "Perivolia"
    ],
    "wof:name":"Perivolia",
    "wof:placetype":"locality"
},
  "geometry": {"coordinates":[24.13447,38.45072],"type":"Point"}
}