{
  "type": "Feature",
  "properties": {
    "gn:admin1_code":"ESYE13",
    "gn:admin2_code":"9.0",
    "gn:admin3_code":"9063",
    "gn:asciiname":"Stavropotamos",
    "gn:country_code":"GR",
    "gn:dem":704,
    "gn:feature_class":"P",
    "gn:feature_code":"PPL",
    "gn:name":"Stavrop\u00f3tamos",
    "gn:population":173,
    "gn:timezone":"Europe/Athens",
    "iso:country":"GR",
    "name:ell_x_preferred":[
        "\u03a3\u03c4\u03b1\u03c5\u03c1\u03bf\u03c0\u03cc\u03c4\u03b1\u03bc\u03bf\u03c2"
    ],
    "name:eng_x_preferred":[
        "Stavropotamos"
    ],
    "name:und_x_variant":[
        "Makrokh\u00f3ri",
        "Bob\u00f3ki",
        "Stavrop\u00f3tamos"
    ],
    "wof:name":"Stavropotamos",
    "wof:placetype":"locality",
    "wof:population":173
},
  "geometry": {"coordinates":[21.39316,40.54523],"type":"Point"}
}