{
  "type": "Feature",
  "properties": {
    "gn:admin1_code":"ESYE23",
    "gn:admin2_code":"39.0",
    "gn:admin3_code":"9136",
    "gn:asciiname":"Dhafnoula",
    "gn:country_code":"GR",
    "gn:dem":174,
    "gn:feature_class":"P",
    "gn:feature_code":"PPL",
    "gn:name":"Dhafno\u00fala",
    "gn:population":127,
    "gn:timezone":"Europe/Athens",
    "iso:country":"GR",
    "name:ell_x_preferred":[
        "\u0394\u03b1\u03c6\u03bd\u03bf\u03cd\u03bb\u03b1"
    ],
    "name:eng_x_preferred":[
        "Dafnoula"
    ],
    "name:und_x_variant":[
        "B\u00e1rji",
        "Dhafno\u00fala"
    ],
    "wof:name":"Dhafnoula",
    "wof:placetype":"locality",
    "wof:population":127
},
  "geometry": {"coordinates":[21.86687,37.59065],"type":"Point"}
}