{
  "type": "Feature",
  "properties": {
    "gn:admin1_code":"ESYE43",
    "gn:admin2_code":"45.0",
    "gn:admin3_code":"9305",
    "gn:asciiname":"Kaminia",
    "gn:country_code":"GR",
    "gn:dem":19,
    "gn:elevation":"25.0",
    "gn:feature_class":"P",
    "gn:feature_code":"PPL",
    "gn:name":"Kaminia",
    "gn:population":0,
    "gn:timezone":"Europe/Athens",
    "iso:country":"GR",
    "name:ceb_x_preferred":[
        "Kaminia"
    ],
    "name:ell_x_preferred":[
        "\u039a\u03b1\u03bc\u03af\u03bd\u03b9\u03b1"
    ],
    "name:swe_x_preferred":[
        "Kaminia"
    ],
    "wof:name":"Kaminia",
    "wof:placetype":"locality"
},
  "geometry": {"coordinates":[25.11305,35.33633],"type":"Point"}
}