{
  "type": "Feature",
  "properties": {
    "gn:admin1_code":"ESYE14",
    "gn:admin2_code":"21.0",
    "gn:admin3_code":"9103",
    "gn:asciiname":"Agios Charalampos",
    "gn:country_code":"GR",
    "gn:dem":307,
    "gn:feature_class":"P",
    "gn:feature_code":"PPL",
    "gn:name":"\u00c1gios Char\u00e1lampos",
    "gn:population":0,
    "gn:timezone":"Europe/Athens",
    "iso:country":"GR",
    "name:ell_x_preferred":[
        "\u00c1gios Char\u00e1lampos"
    ],
    "name:ell_x_variant":[
        "\u0386\u03b3\u03b9\u03bf\u03c2 \u03a7\u03b1\u03c1\u03ac\u03bb\u03b1\u03bc\u03c0\u03bf\u03c2"
    ],
    "wof:name":"Agios Charalampos",
    "wof:placetype":"locality"
},
  "geometry": {"coordinates":[22.61054,39.28831],"type":"Point"}
}