{
  "type": "Feature",
  "properties": {
    "gn:admin1_code":"ESYE23",
    "gn:admin2_code":"39.0",
    "gn:admin3_code":"9141",
    "gn:asciiname":"Ampelonas",
    "gn:country_code":"GR",
    "gn:dem":110,
    "gn:feature_class":"P",
    "gn:feature_code":"PPL",
    "gn:name":"Ampel\u00f3nas",
    "gn:population":0,
    "gn:timezone":"Europe/Athens",
    "iso:country":"GR",
    "name:ell_x_preferred":[
        "Ampel\u00f3nas"
    ],
    "name:ell_x_variant":[
        "\u0391\u03bc\u03c0\u03b5\u03bb\u03ce\u03bd\u03b1\u03c2"
    ],
    "name:und_x_variant":[
        "R\u00f3mesi",
        "Rom\u00e9sion"
    ],
    "wof:name":"Ampelonas",
    "wof:placetype":"locality"
},
  "geometry": {"coordinates":[21.46419,37.72861],"type":"Point"}
}