{
  "type": "Feature",
  "properties": {
    "gn:admin1_code":"ESYE23",
    "gn:admin2_code":"39.0",
    "gn:admin3_code":"9141",
    "gn:asciiname":"Ampelonas",
    "gn:country_code":"GR",
    "gn:dem":110,
    "gn:feature_class":"P",
    "gn:feature_code":"PPL",
    "gn:name":"Ampel\u00f3nas",
    "gn:population":0,
    "gn:timezone":"Europe/Athens",
    "iso:country":"GR",
    "name:ara_x_preferred":[
        "\u0623\u0645\u0628\u064a\u0644\u0648\u0646\u0627\u0633"
    ],
    "name:bul_x_preferred":[
        "\u0410\u043c\u0431\u0435\u043b\u043e\u043d\u0430\u0441"
    ],
    "name:ceb_x_preferred":[
        "Ampel\u00f3na"
    ],
    "name:deu_x_preferred":[
        "Ambelonas"
    ],
    "name:ell_x_preferred":[
        "Ampel\u00f3nas"
    ],
    "name:ell_x_variant":[
        "\u0391\u03bc\u03c0\u03b5\u03bb\u03ce\u03bd\u03b1\u03c2",
        "\u0391\u03bc\u03c0\u03b5\u03bb\u03ce\u03bd\u03b1\u03c2 \u039b\u03ac\u03c1\u03b9\u03c3\u03b1\u03c2"
    ],
    "name:fin_x_preferred":[
        "Ampel\u00f3nas"
    ],
    "name:ita_x_preferred":[
        "Ampelonas"
    ],
    "name:nno_x_preferred":[
        "Ambel\u00f3nas"
    ],
    "name:swe_x_preferred":[
        "Ampel\u00f3na"
    ],
    "name:und_x_variant":[
        "R\u00f3mesi",
        "Rom\u00e9sion"
    ],
    "wof:name":"Ampelonas",
    "wof:placetype":"locality"
},
  "geometry": {"coordinates":[21.46419,37.72861],"type":"Point"}
}