{
  "type": "Feature",
  "properties": {
    "gn:admin1_code":"ESYE12",
    "gn:admin2_code":"5.0",
    "gn:admin3_code":"9049",
    "gn:asciiname":"Krinida",
    "gn:country_code":"GR",
    "gn:dem":155,
    "gn:feature_class":"P",
    "gn:feature_code":"PPL",
    "gn:name":"Krin\u00edda",
    "gn:population":573,
    "gn:timezone":"Europe/Athens",
    "iso:country":"GR",
    "name:bul_x_historical":[
        "\u0412\u0438\u0442\u0430\u0447\u0438\u0449\u0430"
    ],
    "name:bul_x_preferred":[
        "\u041a\u0440\u0438\u043d\u0438\u0434\u0430"
    ],
    "name:bul_x_variant":[
        "\u0412\u0438\u0442\u0430\u0447\u0438\u0449\u0430"
    ],
    "name:ceb_x_preferred":[
        "Krin\u00edda"
    ],
    "name:ell_x_historical":[
        "\u0392\u03b9\u03c4\u03ac\u03c3\u03c4\u03b1"
    ],
    "name:ell_x_preferred":[
        "\u039a\u03c1\u03b7\u03bd\u03af\u03b4\u03b1"
    ],
    "name:ell_x_variant":[
        "Krin\u00edda",
        "\u039a\u03c1\u03b7\u03bd\u03af\u03c2",
        "\u0392\u03b9\u03c4\u03ac\u03c3\u03c4\u03b1",
        "\u039a\u03c1\u03b7\u03bd\u03af\u03b4\u03b1 \u03a3\u03b5\u03c1\u03c1\u03ce\u03bd"
    ],
    "name:eng_x_historical":[
        "Vitasta"
    ],
    "name:eng_x_preferred":[
        "Krinida"
    ],
    "name:eng_x_variant":[
        "Vitasta"
    ],
    "name:mkd_x_historical":[
        "\u0412\u0438\u0442\u0430\u0447\u0438\u0448\u0442\u0430"
    ],
    "name:mkd_x_preferred":[
        "\u0412\u0438\u0442\u0430\u0447\u0438\u0448\u0442\u0430"
    ],
    "name:swe_x_preferred":[
        "Krin\u00edda"
    ],
    "name:und_x_variant":[
        "Vit\u00e1sta"
    ],
    "wof:name":"Krinida",
    "wof:placetype":"locality",
    "wof:population":573
},
  "geometry": {"coordinates":[23.98408,40.99473],"type":"Point"}
}