{
  "type": "Feature",
  "properties": {
    "gn:gn_country":"GR",
    "gn:gn_fcode":"PPL",
    "gn:gn_pop":1595,
    "gn:population":1595,
    "iso:country":"GR",
    "name:ell_x_preferred":[
        "N\u00e9a P\u00e9lla"
    ],
    "name:ell_x_variant":[
        "\u039d\u03ad\u03b1 \u03a0\u03ad\u03bb\u03bb\u03b1"
    ],
    "qs_pg:aaroncc":"GR",
    "qs_pg:gn_country":"GR",
    "qs_pg:gn_fcode":"PPL",
    "qs_pg:gn_pop":1595,
    "qs_pg:name":"Nea Pella",
    "qs_pg:name_adm0":"\u0395\u03bb\u03bb\u03ac\u03b4\u03b1",
    "qs_pg:name_adm1":"Macedonia and Thrace",
    "qs_pg:photos_9k":1,
    "qs_pg:photos_9r":2,
    "qs_pg:photos_all":29,
    "qs_pg:photos_sr":0,
    "qs_pg:pop_sr":3,
    "qs_pg:qs_pg_placetype":"locality",
    "qs_pg:qs_pg_placetype_gp":"Town",
    "qs_pg:woe_adm0":23424833,
    "woe:adm0_id":23424833,
    "woe:name_adm0":"\u0395\u03bb\u03bb\u03ac\u03b4\u03b1",
    "woe:name_adm1":"Macedonia and Thrace",
    "woe:placetype":"Town",
    "wof:name":"Nea Pella",
    "wof:placetype":"locality",
    "wof:population":1595
},
  "geometry": {"coordinates":[22.48556,40.76611],"type":"Point"}
}