{
  "type": "Feature",
  "properties": {
    "gn:gn_country":"GR",
    "gn:gn_fcode":"PPL",
    "gn:gn_pop":247,
    "gn:population":247,
    "iso:country":"GR",
    "name:ceb_x_preferred":[
        "Aetos"
    ],
    "name:deu_x_preferred":[
        "Aetos"
    ],
    "name:ell_x_preferred":[
        "Aet\u00f3s"
    ],
    "name:ell_x_variant":[
        "\u0391\u03b5\u03c4\u03cc\u03c2"
    ],
    "name:fin_x_preferred":[
        "Aetos"
    ],
    "name:ita_x_preferred":[
        "Aetos"
    ],
    "name:nld_x_preferred":[
        "Aetos"
    ],
    "name:swe_x_preferred":[
        "Aetos"
    ],
    "name:unk_x_variant":[
        "Pits\u00e1rion"
    ],
    "qs_pg:aaroncc":"GR",
    "qs_pg:gn_country":"GR",
    "qs_pg:gn_fcode":"PPL",
    "qs_pg:gn_pop":247,
    "qs_pg:name":"Aetos",
    "qs_pg:name_adm0":"\u0395\u03bb\u03bb\u03ac\u03b4\u03b1",
    "qs_pg:name_adm1":"Epirus and Western Macedonia",
    "qs_pg:photos_9r":0,
    "qs_pg:photos_sr":0,
    "qs_pg:pop_sr":2,
    "qs_pg:qs_pg_placetype":"locality",
    "qs_pg:qs_pg_placetype_gp":"Town",
    "qs_pg:woe_adm0":23424833,
    "woe:adm0_id":23424833,
    "woe:name_adm0":"\u0395\u03bb\u03bb\u03ac\u03b4\u03b1",
    "woe:name_adm1":"Epirus and Western Macedonia",
    "woe:placetype":"Town",
    "wof:name":"Aetos",
    "wof:placetype":"locality",
    "wof:population":247
},
  "geometry": {"coordinates":[20.39667,39.58],"type":"Point"}
}