{
  "type": "Feature",
  "properties": {
    "gn:admin1_code":"ESYE41",
    "gn:admin2_code":"48.0",
    "gn:admin3_code":"9264",
    "gn:asciiname":"Agios Nikolaos",
    "gn:country_code":"GR",
    "gn:dem":26,
    "gn:feature_class":"P",
    "gn:feature_code":"PPL",
    "gn:name":"\u00c1gios Nik\u00f3laos",
    "gn:population":26,
    "gn:timezone":"Europe/Athens",
    "iso:country":"GR",
    "name:bul_x_preferred":[
        "\u0410\u0433\u0438\u043e\u0441 \u041d\u0438\u043a\u043e\u043b\u0430\u043e\u0441"
    ],
    "name:ceb_x_preferred":[
        "Agios Nikolaos"
    ],
    "name:deu_x_preferred":[
        "Agios Nikolaos"
    ],
    "name:ell_x_preferred":[
        "\u0386\u03b3\u03b9\u03bf\u03c2 \u039d\u03b9\u03ba\u03cc\u03bb\u03b1\u03bf\u03c2"
    ],
    "name:eng_x_preferred":[
        "Agios Nikolaos"
    ],
    "name:fra_x_preferred":[
        "Agios Nikolaos"
    ],
    "name:hrv_x_preferred":[
        "Agios Nikolaos"
    ],
    "name:hye_x_preferred":[
        "\u0531\u0575\u0578\u057d \u0546\u056b\u056f\u0578\u056c\u0561\u0578\u057d"
    ],
    "name:pol_x_preferred":[
        "Ajos Nikolaos"
    ],
    "name:rus_x_preferred":[
        "\u0410\u0439\u043e\u0441-\u041d\u0438\u043a\u043e\u043b\u0430\u043e\u0441"
    ],
    "name:spa_x_preferred":[
        "\u00c1gios Nikolaos"
    ],
    "name:swe_x_preferred":[
        "Agios Nikolaos"
    ],
    "name:ukr_x_preferred":[
        "\u0410\u0439\u043e\u0441-\u041d\u0456\u043a\u043e\u043b\u0430\u043e\u0441"
    ],
    "wof:name":"Agios Nikolaos",
    "wof:placetype":"locality",
    "wof:population":26
},
  "geometry": {"coordinates":[26.74128,37.81207],"type":"Point"}
}