{
  "type": "Feature",
  "properties": {
    "gn:gn_country":"GR",
    "gn:gn_fcode":"ADM3",
    "gn:gn_pop":994,
    "gn:population":994,
    "iso:country":"GR",
    "name:ell_x_preferred":[
        "\u039c\u03b5\u03b3\u03b1\u03bd\u03b7\u03c3\u03af\u03bf\u03c5"
    ],
    "qs_pg:aaroncc":"GR",
    "qs_pg:gn_country":"GR",
    "qs_pg:gn_fcode":"ADM3",
    "qs_pg:gn_pop":994,
    "qs_pg:name":"Dimos Meganisi",
    "qs_pg:photos_9r":0,
    "qs_pg:photos_sr":0,
    "qs_pg:pop_sr":2,
    "qs_pg:qs_pg_placetype":"localadmin",
    "wof:name":"Dimos Meganisi",
    "wof:placetype":"localadmin",
    "wof:population":994
},
  "geometry": {"coordinates":[20.76712,38.64827],"type":"Point"}
}