{
  "type": "Feature",
  "properties": {
    "gn:admin1_code":"ESYE43",
    "gn:admin2_code":"44.0",
    "gn:admin3_code":"9318",
    "gn:asciiname":"Monopari",
    "gn:country_code":"GR",
    "gn:dem":372,
    "gn:feature_class":"P",
    "gn:feature_code":"PPL",
    "gn:name":"Monop\u00e1ri",
    "gn:population":30,
    "gn:timezone":"Europe/Athens",
    "iso:country":"GR",
    "name:ell_x_preferred":[
        "\u039c\u03bf\u03bd\u03bf\u03c0\u03ac\u03c1\u03b9"
    ],
    "name:ell_x_variant":[
        "\u039c\u03bf\u03bd\u03bf\u03c0\u03ac\u03c1\u03b9\u03bf\u03bd"
    ],
    "name:eng_x_preferred":[
        "Monopari"
    ],
    "name:und_x_variant":[
        "Monop\u00e1ri",
        "Monop\u00e1rion"
    ],
    "wof:name":"Monopari",
    "wof:placetype":"locality",
    "wof:population":30
},
  "geometry": {"coordinates":[24.42269,35.29537],"type":"Point"}
}