{
  "type": "Feature",
  "properties": {
    "gn:admin1_code":"ESYE42",
    "gn:admin2_code":"49.0",
    "gn:admin3_code":"9301",
    "gn:asciiname":"Kionia",
    "gn:country_code":"GR",
    "gn:dem":11,
    "gn:feature_class":"P",
    "gn:feature_code":"PPL",
    "gn:name":"Ki\u00f3nia",
    "gn:population":0,
    "gn:timezone":"Europe/Athens",
    "iso:country":"GR",
    "name:und_x_variant":[
        "Ki\u00f3nia",
        "\u039a\u03b9\u03cc\u03bd\u03b9\u03b1"
    ],
    "wof:name":"Kionia",
    "wof:placetype":"locality"
},
  "geometry": {"coordinates":[25.14019,37.55394],"type":"Point"}
}