{
  "type": "Feature",
  "properties": {
    "gn:admin1_code":"ESYE43",
    "gn:admin2_code":"44.0",
    "gn:admin3_code":"9316",
    "gn:asciiname":"Metochi",
    "gn:country_code":"GR",
    "gn:dem":807,
    "gn:feature_class":"P",
    "gn:feature_code":"PPL",
    "gn:name":"Met\u00f3chi",
    "gn:population":0,
    "gn:timezone":"Europe/Athens",
    "iso:country":"GR",
    "name:ceb_x_preferred":[
        "Metochi"
    ],
    "name:ell_x_preferred":[
        "Met\u00f3chi"
    ],
    "name:ell_x_variant":[
        "\u039c\u03b5\u03c4\u03cc\u03c7\u03b9",
        "Met\u00f3khi"
    ],
    "name:swe_x_preferred":[
        "Metochi"
    ],
    "wof:name":"Metochi",
    "wof:placetype":"locality"
},
  "geometry": {"coordinates":[24.88333,35.28333],"type":"Point"}
}