{
  "type": "Feature",
  "properties": {
    "gn:admin1_code":"ESYE23",
    "gn:admin2_code":"38.0",
    "gn:admin3_code":"9131",
    "gn:asciiname":"Agios Nikolaos Kralis",
    "gn:country_code":"GR",
    "gn:dem":69,
    "gn:feature_class":"P",
    "gn:feature_code":"PPL",
    "gn:name":"\u00c1gios Nik\u00f3laos Kr\u00e1lis",
    "gn:population":0,
    "gn:timezone":"Europe/Athens",
    "iso:country":"GR",
    "name:ell_x_preferred":[
        "\u00c1gios Nik\u00f3laos Kr\u00e1lis"
    ],
    "name:ell_x_variant":[
        "\u0386\u03b3\u03b9\u03bf\u03c2 \u039d\u03b9\u03ba\u03cc\u03bb\u03b1\u03bf\u03c2 \u039a\u03c1\u03ac\u03bb\u03b7\u03c2"
    ],
    "name:und_x_variant":[
        "Kr\u00e1lion",
        "Kr\u00e1lli",
        "\u00c1yios Nik\u00f3laos"
    ],
    "wof:name":"Agios Nikolaos Kralis",
    "wof:placetype":"locality"
},
  "geometry": {"coordinates":[21.62203,38.10186],"type":"Point"}
}