{
  "type": "Feature",
  "properties": {
    "gn:admin1_code":"ESYE23",
    "gn:admin2_code":"31.0",
    "gn:admin3_code":"9123",
    "gn:asciiname":"Kyparissos",
    "gn:country_code":"GR",
    "gn:dem":509,
    "gn:feature_class":"P",
    "gn:feature_code":"PPL",
    "gn:name":"Kyp\u00e1rissos",
    "gn:population":268,
    "gn:timezone":"Europe/Athens",
    "iso:country":"GR",
    "name:ell_x_preferred":[
        "\u039a\u03c5\u03c0\u03ac\u03c1\u03b9\u03c3\u03c3\u03bf\u03c2"
    ],
    "name:ell_x_variant":[
        "Kyp\u00e1rissos"
    ],
    "name:eng_x_preferred":[
        "Kyparissos"
    ],
    "name:und_x_variant":[
        "T\u00e9rova",
        "Kip\u00e1rissos"
    ],
    "wof:name":"Kyparissos",
    "wof:placetype":"locality",
    "wof:population":268
},
  "geometry": {"coordinates":[21.48239,38.76775],"type":"Point"}
}