{
  "type": "Feature",
  "properties": {
    "gn:population":1159,
    "iso:country":"GR",
    "name:ara_x_preferred":[
        "\u0646\u064a\u0648\u0646 \u0645\u0648\u0646\u0627\u0633\u062a\u064a\u0631\u064a\u0648\u0646\u060c \u0641\u062b\u064a\u0648\u062a\u064a\u0633"
    ],
    "name:ara_x_variant":[
        "\u0646\u064a\u0648\u0646 \u0645\u0648\u0646\u0627\u0633\u062a\u064a\u0631\u064a\u0648\u0646"
    ],
    "name:arz_x_preferred":[
        "\u0646\u064a\u0648 \u0645\u0648\u0646\u0627\u0633\u062a\u064a\u0631\u0649 \u0641\u062b\u064a\u0648\u062a\u064a\u062f\u0627\u0633"
    ],
    "name:ceb_x_preferred":[
        "N\u00e9on Monast\u00edrion"
    ],
    "name:ell_x_preferred":[
        "\u039d\u03ad\u03bf\u03bd \u039c\u03bf\u03bd\u03b1\u03c3\u03c4\u03ae\u03c1\u03b9\u03bf\u03bd"
    ],
    "name:ell_x_variant":[
        "\u039d\u03ad\u03bf \u039c\u03bf\u03bd\u03b1\u03c3\u03c4\u03ae\u03c1\u03b9\u03bf",
        "\u039d\u03ad\u03bf \u039c\u03bf\u03bd\u03b1\u03c3\u03c4\u03ae\u03c1\u03b9",
        "\u039d\u03ad\u03bf \u039c\u03bf\u03bd\u03b1\u03c3\u03c4\u03ae\u03c1\u03b9 \u03a6\u03b8\u03b9\u03ce\u03c4\u03b9\u03b4\u03b1\u03c2"
    ],
    "name:eng_x_preferred":[
        "Neo Monastiri"
    ],
    "name:eng_x_variant":[
        "Neo Monastiri Fthiotidas"
    ],
    "name:nno_x_preferred":[
        "N\u00e9o Monast\u00edri"
    ],
    "name:swe_x_preferred":[
        "N\u00e9on Monast\u00edrion"
    ],
    "name:und_x_variant":[
        "Ts\u00f3mba"
    ],
    "qs:a0":"Greece",
    "qs:a1":"*\u03a3\u03a4\u0395\u03a1\u0395\u0391 \u0395\u039b\u039b\u0391\u0394\u0391",
    "qs:a1_alt":"STEREA ELLADA",
    "qs:a1r":"0",
    "qs:a2_alt":"FUIVTIDA",
    "qs:adm0":"Greece",
    "qs:la_lc":"*",
    "qs:level":"locality",
    "qs:loc":"\u039d\u0395\u039f\u039d \u039c\u039f\u039d\u0391\u03a3\u03a4\u0397\u03a1\u0399\u039f\u039d",
    "qs:loc_alt":"NEON MONASURION",
    "qs:pop":0,
    "qs:type":"buffered point",
    "wof:name":"\u039d\u0395\u039f\u039d \u039c\u039f\u039d\u0391\u03a3\u03a4\u0397\u03a1\u0399\u039f\u039d",
    "wof:placetype":"locality",
    "wof:population":1159
},
  "geometry": {"coordinates":[22.275751,39.243423],"type":"Point"}
}