{
  "type": "Feature",
  "properties": {
    "gn:admin1_code":"ESYE25",
    "gn:admin2_code":"36.0",
    "gn:admin3_code":"9234",
    "gn:asciiname":"Asklipeiio Epidavrou",
    "gn:country_code":"GR",
    "gn:dem":313,
    "gn:feature_class":"P",
    "gn:feature_code":"PPL",
    "gn:name":"Asklipe\u00edio Epid\u00e1vrou",
    "gn:population":19,
    "gn:timezone":"Europe/Athens",
    "iso:country":"GR",
    "name:ell_x_preferred":[
        "\u0391\u03c3\u03ba\u03bb\u03b7\u03c0\u03b9\u03b5\u03af\u03bf \u0395\u03c0\u03b9\u03b4\u03b1\u03cd\u03c1\u03bf\u03c5"
    ],
    "wof:name":"Asklipeiio Epidavrou",
    "wof:placetype":"locality",
    "wof:population":19
},
  "geometry": {"coordinates":[23.02932,37.60014],"type":"Point"}
}