{
  "type": "Feature",
  "properties": {
    "gn:country":"GR",
    "gn:fcode":"PPL",
    "gn:population":229,
    "iso:country":"GR",
    "name:ell_x_preferred":[
        "\u0391\u03bc\u03c0\u03b5\u03bb\u03b5\u03af\u03b1"
    ],
    "name:eng_x_preferred":[
        "Ampeleia"
    ],
    "name:und_x_variant":[
        "Ambel\u00eda"
    ],
    "qs_pg:aaroncc":"GR",
    "qs_pg:gn_country":"GR",
    "qs_pg:gn_fcode":"PPL",
    "qs_pg:gn_pop":229,
    "qs_pg:name":"Ampele\u00eda",
    "qs_pg:photos_9r":0,
    "qs_pg:photos_sr":0,
    "qs_pg:pop_sr":2,
    "qs_pg:qs_pg_placetype":"locality",
    "wof:name":"Ampele\u00eda",
    "wof:placetype":"locality",
    "wof:population":339
},
  "geometry": {"coordinates":[20.83361,39.56556],"type":"Point"}
}