{
  "type": "Feature",
  "properties": {
    "gn:country":"GR",
    "gn:fcode":"PPL",
    "gn:population":315,
    "iso:country":"GR",
    "name:ell_x_preferred":[
        "Dafno\u00fala"
    ],
    "name:ell_x_variant":[
        "\u0394\u03b1\u03c6\u03bd\u03bf\u03cd\u03bb\u03b1"
    ],
    "qs_pg:aaroncc":"GR",
    "qs_pg:gn_country":"GR",
    "qs_pg:gn_fcode":"PPL",
    "qs_pg:gn_pop":315,
    "qs_pg:name":"Dafnoula",
    "qs_pg:name_adm0":"\u0395\u03bb\u03bb\u03ac\u03b4\u03b1",
    "qs_pg:name_adm1":"Epirus and Western Macedonia",
    "qs_pg:photos_9r":0,
    "qs_pg:photos_sr":0,
    "qs_pg:pop_sr":2,
    "qs_pg:qs_pg_placetype":"locality",
    "qs_pg:qs_pg_placetype_gp":"Town",
    "qs_pg:woe_adm0":23424833,
    "woe:adm0_id":23424833,
    "woe:name_adm0":"\u0395\u03bb\u03bb\u03ac\u03b4\u03b1",
    "woe:name_adm1":"Epirus and Western Macedonia",
    "woe:placetype":"Town",
    "wof:name":"Dafnoula",
    "wof:placetype":"locality",
    "wof:population":315
},
  "geometry": {"coordinates":[20.5325,39.42611],"type":"Point"}
}