{
  "type": "Feature",
  "properties": {
    "gn:admin1_code":"ESYE24",
    "gn:admin2_code":"32.0",
    "gn:admin3_code":"9166",
    "gn:asciiname":"Pentagioi",
    "gn:country_code":"GR",
    "gn:dem":920,
    "gn:feature_class":"P",
    "gn:feature_code":"PPL",
    "gn:name":"Pentagio\u00ed",
    "gn:population":0,
    "gn:timezone":"Europe/Athens",
    "iso:country":"GR",
    "name:ell_x_preferred":[
        "Pentagio\u00ed"
    ],
    "name:ell_x_variant":[
        "\u03a0\u03b5\u03bd\u03c4\u03b1\u03b3\u03b9\u03bf\u03af"
    ],
    "name:und_x_variant":[
        "Pentaai",
        "Pendayio\u00ed"
    ],
    "wof:name":"Pentagioi",
    "wof:placetype":"locality"
},
  "geometry": {"coordinates":[22.05338,38.59194],"type":"Point"}
}