{
  "type": "Feature",
  "properties": {
    "gn:admin1_code":"ESYE14",
    "gn:admin2_code":"21.0",
    "gn:admin3_code":"9101",
    "gn:asciiname":"Koukousouli",
    "gn:country_code":"GR",
    "gn:dem":104,
    "gn:feature_class":"P",
    "gn:feature_code":"PPL",
    "gn:name":"Koukouso\u00fali",
    "gn:population":0,
    "gn:timezone":"Europe/Athens",
    "iso:country":"GR",
    "name:ell_x_preferred":[
        "Koukouso\u00fali"
    ],
    "name:ell_x_variant":[
        "\u039a\u03bf\u03c5\u03ba\u03bf\u03c5\u03c3\u03bf\u03cd\u03bb\u03b9"
    ],
    "wof:name":"Koukousouli",
    "wof:placetype":"locality"
},
  "geometry": {"coordinates":[22.52333,39.76467],"type":"Point"}
}