{
  "type": "Feature",
  "properties": {
    "gn:admin1_code":"ESYE25",
    "gn:admin2_code":"37.0",
    "gn:admin3_code":"9242",
    "gn:asciiname":"Poullitsa",
    "gn:country_code":"GR",
    "gn:dem":29,
    "gn:feature_class":"P",
    "gn:feature_code":"PPL",
    "gn:name":"Poull\u00edtsa",
    "gn:population":696,
    "gn:timezone":"Europe/Athens",
    "iso:country":"GR",
    "name:ell_x_preferred":[
        "\u03a0\u03bf\u03c5\u03bb\u03bb\u03af\u03c4\u03c3\u03b1"
    ],
    "name:eng_x_preferred":[
        "Poullitsa"
    ],
    "name:und_x_variant":[
        "Poul\u00edtsa",
        "Poull\u00edtsa"
    ],
    "wof:name":"Poullitsa",
    "wof:placetype":"locality",
    "wof:population":696
},
  "geometry": {"coordinates":[22.77131,37.95899],"type":"Point"}
}