{
  "type": "Feature",
  "properties": {
    "gn:admin1_code":"ESYE25",
    "gn:admin2_code":"37.0",
    "gn:admin3_code":"9244",
    "gn:asciiname":"Paradeisos",
    "gn:country_code":"GR",
    "gn:dem":54,
    "gn:feature_class":"P",
    "gn:feature_code":"PPL",
    "gn:name":"Par\u00e1deisos",
    "gn:population":78,
    "gn:timezone":"Europe/Athens",
    "iso:country":"GR",
    "name:ell_x_preferred":[
        "\u03a0\u03b1\u03c1\u03ac\u03b4\u03b5\u03b9\u03c3\u03bf\u03c2"
    ],
    "name:eng_x_preferred":[
        "Paradeisos"
    ],
    "wof:name":"Paradeisos",
    "wof:placetype":"locality",
    "wof:population":78
},
  "geometry": {"coordinates":[23.00891,37.92462],"type":"Point"}
}