{
  "type": "Feature",
  "properties": {
    "gn:admin1_code":"ESYE43",
    "gn:admin2_code":"45.0",
    "gn:admin3_code":"9309",
    "gn:asciiname":"Piskopiano",
    "gn:country_code":"GR",
    "gn:dem":85,
    "gn:feature_class":"P",
    "gn:feature_code":"PPL",
    "gn:name":"Piskopian\u00f3",
    "gn:population":286,
    "gn:timezone":"Europe/Athens",
    "iso:country":"GR",
    "name:ell_x_preferred":[
        "\u03a0\u03b9\u03c3\u03ba\u03bf\u03c0\u03b9\u03b1\u03bd\u03cc"
    ],
    "name:eng_x_preferred":[
        "Piskopiano"
    ],
    "name:und_x_variant":[
        "Episkopian\u00f3",
        "Piskopian\u00f3",
        "Piskopian\u00f3n"
    ],
    "wof:name":"Piskopiano",
    "wof:placetype":"locality",
    "wof:population":286
},
  "geometry": {"coordinates":[25.38474,35.30822],"type":"Point"}
}