{
  "type": "Feature",
  "properties": {
    "gn:admin1_code":"ESYE43",
    "gn:admin2_code":"45.0",
    "gn:admin3_code":"9303",
    "gn:asciiname":"Kato Simi",
    "gn:country_code":"GR",
    "gn:dem":775,
    "gn:feature_class":"P",
    "gn:feature_code":"PPL",
    "gn:name":"Kato Simi",
    "gn:population":0,
    "gn:timezone":"Europe/Athens",
    "iso:country":"GR",
    "name:cat_x_preferred":[
        "Kato Simi"
    ],
    "name:ell_x_preferred":[
        "\u039a\u03ac\u03c4\u03c9 \u03a3\u03cd\u03bc\u03b7"
    ],
    "name:ell_x_variant":[
        "\u039a\u03ac\u03c4\u03c9 \u03a3\u03cd\u03bc\u03b7 \u0397\u03c1\u03b1\u03ba\u03bb\u03b5\u03af\u03bf\u03c5"
    ],
    "name:spa_x_preferred":[
        "Kato Simi"
    ],
    "wof:name":"Kato Simi",
    "wof:placetype":"locality"
},
  "geometry": {"coordinates":[25.4888,35.04686],"type":"Point"}
}