{
  "type": "Feature",
  "properties": {
    "gn:admin1_code":"ESYE24",
    "gn:admin2_code":"30.0",
    "gn:admin3_code":"9157",
    "gn:asciiname":"Katavothra",
    "gn:country_code":"GR",
    "gn:dem":723,
    "gn:feature_class":"P",
    "gn:feature_code":"PPL",
    "gn:name":"Katav\u00f3thra",
    "gn:population":64,
    "gn:timezone":"Europe/Athens",
    "iso:country":"GR",
    "name:ceb_x_preferred":[
        "Katav\u00f3thra"
    ],
    "name:ell_x_preferred":[
        "\u039a\u03b1\u03c4\u03b1\u03b2\u03cc\u03b8\u03c1\u03b1"
    ],
    "name:ell_x_variant":[
        "\u039a\u03b1\u03c4\u03b1\u03b2\u03cc\u03b8\u03c1\u03b1 \u0398\u03b5\u03c3\u03c0\u03c1\u03c9\u03c4\u03af\u03b1\u03c2"
    ],
    "name:sqi_x_preferred":[
        "Luarati"
    ],
    "name:und_x_variant":[
        "Sindhendhron",
        "Katav\u00f3thra"
    ],
    "wof:name":"Katavothra",
    "wof:placetype":"locality",
    "wof:population":64
},
  "geometry": {"coordinates":[21.59062,38.77008],"type":"Point"}
}