{
  "type": "Feature",
  "properties": {
    "gn:gn_country":"GR",
    "gn:gn_fcode":"ADM3",
    "gn:gn_pop":20139,
    "gn:population":20139,
    "iso:country":"GR",
    "name:ell_x_preferred":[
        "\u0391\u03bb\u03bc\u03c5\u03c1\u03bf\u03cd"
    ],
    "qs_pg:aaroncc":"GR",
    "qs_pg:gn_country":"GR",
    "qs_pg:gn_fcode":"ADM3",
    "qs_pg:gn_pop":20139,
    "qs_pg:name":"Dimos Almyros",
    "qs_pg:photos_9r":0,
    "qs_pg:photos_sr":0,
    "qs_pg:pop_sr":7,
    "qs_pg:qs_pg_placetype":"localadmin",
    "wof:name":"Dimos Almyros",
    "wof:placetype":"localadmin",
    "wof:population":20139
},
  "geometry": {"coordinates":[22.74229,39.11658],"type":"Point"}
}