{
  "type": "Feature",
  "properties": {
    "gn:country":"GR",
    "gn:fcode":"PPL",
    "gn:population":73,
    "iso:country":"GR",
    "name:bul_x_preferred":[
        "\u0410\u0432\u0433\u0438"
    ],
    "name:ell_x_preferred":[
        "\u0391\u03c5\u03b3\u03ae"
    ],
    "name:ell_x_variant":[
        "\u0391\u03c5\u03b3\u03ae \u039a\u03bf\u03b6\u03ac\u03bd\u03b7\u03c2"
    ],
    "name:eng_x_preferred":[
        "Avgi"
    ],
    "name:mkd_x_preferred":[
        "\u0418\u0434\u0435\u043b\u043e\u0432\u0430"
    ],
    "name:nld_x_preferred":[
        "Avgi"
    ],
    "name:rus_x_preferred":[
        "\u0410\u0432\u044c\u0438"
    ],
    "name:und_x_variant":[
        "Id\u00e9lova"
    ],
    "qs_pg:aaroncc":"GR",
    "qs_pg:gn_country":"GR",
    "qs_pg:gn_fcode":"PPL",
    "qs_pg:gn_pop":73,
    "qs_pg:name":"Avg\u00ed",
    "qs_pg:photos_9r":0,
    "qs_pg:photos_sr":0,
    "qs_pg:pop_sr":1,
    "qs_pg:qs_pg_placetype":"locality",
    "wof:name":"Avg\u00ed",
    "wof:placetype":"locality",
    "wof:population":73
},
  "geometry": {"coordinates":[22.04139,40.34417],"type":"Point"}
}