{
  "type": "Feature",
  "properties": {
    "gn:admin1_code":"ESYE22",
    "gn:admin2_code":"28.0",
    "gn:admin3_code":"9116",
    "gn:asciiname":"Kalliteros",
    "gn:country_code":"GR",
    "gn:dem":16,
    "gn:feature_class":"P",
    "gn:feature_code":"PPL",
    "gn:name":"Kallit\u00e9ros",
    "gn:population":627,
    "gn:timezone":"Europe/Athens",
    "iso:country":"GR",
    "name:ell_x_preferred":[
        "\u039a\u03b1\u03bb\u03bb\u03b9\u03c4\u03ad\u03c1\u03bf\u03c2"
    ],
    "name:eng_x_preferred":[
        "Kalliteros"
    ],
    "wof:name":"Kalliteros",
    "wof:placetype":"locality",
    "wof:population":627
},
  "geometry": {"coordinates":[20.90072,37.75792],"type":"Point"}
}