{
  "type": "Feature",
  "properties": {
    "gn:admin1_code":"ESYE43",
    "gn:admin2_code":"44.0",
    "gn:admin3_code":"9318",
    "gn:asciiname":"Petres",
    "gn:country_code":"GR",
    "gn:dem":9,
    "gn:feature_class":"P",
    "gn:feature_code":"PPL",
    "gn:name":"Petr\u00e9s",
    "gn:population":62,
    "gn:timezone":"Europe/Athens",
    "iso:country":"GR",
    "name:ell_x_preferred":[
        "\u03a0\u03b5\u03c4\u03c1\u03ad\u03c2"
    ],
    "name:ell_x_variant":[
        "\u03a0\u03b5\u03c4\u03c1\u03ad\u03c2 \u03a1\u03b5\u03b8\u03cd\u03bc\u03bd\u03b7\u03c2"
    ],
    "name:eng_x_preferred":[
        "Petres"
    ],
    "name:und_x_variant":[
        "Petr\u00e9s"
    ],
    "wof:name":"Petres",
    "wof:placetype":"locality",
    "wof:population":62
},
  "geometry": {"coordinates":[24.36683,35.35491],"type":"Point"}
}