{
  "type": "Feature",
  "properties": {
    "gn:admin1_code":"ESYE25",
    "gn:admin2_code":"41.0",
    "gn:admin3_code":"9241",
    "gn:asciiname":"Strigkos",
    "gn:country_code":"GR",
    "gn:dem":663,
    "gn:feature_class":"P",
    "gn:feature_code":"PPL",
    "gn:name":"Str\u00edgkos",
    "gn:population":0,
    "gn:timezone":"Europe/Athens",
    "iso:country":"GR",
    "name:ell_x_preferred":[
        "Str\u00edgkos"
    ],
    "name:ell_x_variant":[
        "\u03a3\u03c4\u03c1\u03af\u03b3\u03ba\u03bf\u03c2"
    ],
    "name:und_x_variant":[
        "Str\u00edngon",
        "Str\u00edngos"
    ],
    "wof:name":"Strigkos",
    "wof:placetype":"locality"
},
  "geometry": {"coordinates":[22.39767,37.45218],"type":"Point"}
}