{
  "type": "Feature",
  "properties": {
    "gn:admin1_code":"ESYE25",
    "gn:admin2_code":"42.0",
    "gn:admin3_code":"9248",
    "gn:asciiname":"Kokkala",
    "gn:country_code":"GR",
    "gn:dem":14,
    "gn:feature_class":"P",
    "gn:feature_code":"PPL",
    "gn:name":"Kokk\u00e1la",
    "gn:population":238,
    "gn:timezone":"Europe/Athens",
    "iso:country":"GR",
    "name:ceb_x_preferred":[
        "Kokkala"
    ],
    "name:ell_x_preferred":[
        "\u039a\u03bf\u03ba\u03ba\u03ac\u03bb\u03b1"
    ],
    "name:eng_x_preferred":[
        "Kokkala"
    ],
    "name:swe_x_preferred":[
        "Kokkala"
    ],
    "wof:name":"Kokkala",
    "wof:placetype":"locality",
    "wof:population":238
},
  "geometry": {"coordinates":[22.47105,36.52694],"type":"Point"}
}