{
  "type": "Feature",
  "properties": {
    "gn:admin1_code":"ESYE23",
    "gn:admin2_code":"31.0",
    "gn:admin3_code":"9128",
    "gn:asciiname":"Lefka",
    "gn:country_code":"GR",
    "gn:dem":33,
    "gn:feature_class":"P",
    "gn:feature_code":"PPL",
    "gn:name":"L\u00e9fka",
    "gn:population":0,
    "gn:timezone":"Europe/Athens",
    "iso:country":"GR",
    "name:ceb_x_preferred":[
        "L\u00e9fka"
    ],
    "name:deu_x_preferred":[
        "Lefgios/Lefke"
    ],
    "name:ell_x_preferred":[
        "L\u00e9fka"
    ],
    "name:ell_x_variant":[
        "\u039b\u03b5\u03cd\u03ba\u03b1",
        "\u039b\u03ad\u03c6\u03ba\u03b5"
    ],
    "name:fas_x_preferred":[
        "\u0644\u0641\u06a9\u0627"
    ],
    "name:fin_x_preferred":[
        "L\u00e9fka"
    ],
    "name:fra_x_preferred":[
        "Lefke"
    ],
    "name:ita_x_preferred":[
        "Leuka"
    ],
    "name:kaa_x_preferred":[
        "Lefke"
    ],
    "name:nld_x_preferred":[
        "Lefke"
    ],
    "name:nno_x_preferred":[
        "L\u00e9vka"
    ],
    "name:nor_x_preferred":[
        "Lefka"
    ],
    "name:pol_x_preferred":[
        "Lefka"
    ],
    "name:rus_x_preferred":[
        "\u041b\u0435\u0444\u043a\u0430"
    ],
    "name:spa_x_preferred":[
        "Lefka"
    ],
    "name:swe_x_preferred":[
        "Lefka"
    ],
    "name:tur_x_preferred":[
        "Lefke"
    ],
    "name:und_x_variant":[
        "Elaiost\u00e1sion"
    ],
    "name:urd_x_preferred":[
        "\u0644\u06cc\u0641\u06a9\u0627"
    ],
    "wof:name":"Lefka",
    "wof:placetype":"locality"
},
  "geometry": {"coordinates":[21.80544,38.39656],"type":"Point"}
}