{
  "type": "Feature",
  "properties": {
    "gn:admin1_code":"ESYE23",
    "gn:admin2_code":"31.0",
    "gn:admin3_code":"9128",
    "gn:asciiname":"Lefka",
    "gn:country_code":"GR",
    "gn:dem":33,
    "gn:feature_class":"P",
    "gn:feature_code":"PPL",
    "gn:name":"L\u00e9fka",
    "gn:population":0,
    "gn:timezone":"Europe/Athens",
    "iso:country":"GR",
    "name:ell_x_preferred":[
        "L\u00e9fka"
    ],
    "name:ell_x_variant":[
        "\u039b\u03b5\u03cd\u03ba\u03b1"
    ],
    "name:und_x_variant":[
        "Elaiost\u00e1sion"
    ],
    "wof:name":"Lefka",
    "wof:placetype":"locality"
},
  "geometry": {"coordinates":[21.80544,38.39656],"type":"Point"}
}