{
  "type": "Feature",
  "properties": {
    "gn:admin1_code":"ESYE14",
    "gn:admin2_code":"23.0",
    "gn:admin3_code":"9096",
    "gn:asciiname":"Gavrakia",
    "gn:country_code":"GR",
    "gn:dem":234,
    "gn:feature_class":"P",
    "gn:feature_code":"PPL",
    "gn:name":"Gavr\u00e1kia",
    "gn:population":216,
    "gn:timezone":"Europe/Athens",
    "iso:country":"GR",
    "name:ell_x_preferred":[
        "\u0393\u03b1\u03b2\u03c1\u03ac\u03ba\u03b9\u03b1"
    ],
    "name:eng_x_preferred":[
        "Gavrakia"
    ],
    "name:und_x_variant":[
        "Masl\u00ed",
        "Gavr\u00e1kia"
    ],
    "wof:name":"Gavrakia",
    "wof:placetype":"locality",
    "wof:population":216
},
  "geometry": {"coordinates":[22.17539,39.16161],"type":"Point"}
}