{
  "type": "Feature",
  "properties": {
    "gn:admin1_code":"ESYE43",
    "gn:admin2_code":"44.0",
    "gn:admin3_code":"9317",
    "gn:asciiname":"Ano Tripado",
    "gn:country_code":"GR",
    "gn:dem":349,
    "gn:feature_class":"P",
    "gn:feature_code":"PPL",
    "gn:name":"\u00c1no Trip\u00e1do",
    "gn:population":0,
    "gn:timezone":"Europe/Athens",
    "iso:country":"GR",
    "name:ell_x_preferred":[
        "\u00c1no Trip\u00e1do"
    ],
    "name:ell_x_variant":[
        "\u0386\u03bd\u03c9 \u03a4\u03c1\u03b9\u03c0\u03ac\u03b4\u03bf",
        "\u00c1no Trip\u00e1don",
        "\u0386\u03bd\u03c9 \u03a4\u03c1\u03b9\u03c0\u03ac\u03b4\u03bf\u03bd"
    ],
    "name:und_x_variant":[
        "Trip\u00f3dho Ano",
        "\u00c1no Trip\u00f3dho",
        "\u00c1no Trip\u00f3dhon"
    ],
    "wof:name":"Ano Tripado",
    "wof:placetype":"locality"
},
  "geometry": {"coordinates":[24.68849,35.32637000000001],"type":"Point"}
}