{
  "type": "Feature",
  "properties": {
    "gn:admin1_code":"ESYE24",
    "gn:admin2_code":"34.0",
    "gn:admin3_code":"9151",
    "gn:asciiname":"Kapsala",
    "gn:country_code":"GR",
    "gn:dem":165,
    "gn:feature_class":"P",
    "gn:feature_code":"PPL",
    "gn:name":"K\u00e1psala",
    "gn:population":0,
    "gn:timezone":"Europe/Athens",
    "iso:country":"GR",
    "name:ell_x_preferred":[
        "\u039a\u03ac\u03c8\u03b1\u03bb\u03b1"
    ],
    "name:und_x_variant":[
        "Kaps\u00e1ni",
        "K\u00e1psala"
    ],
    "wof:name":"Kapsala",
    "wof:placetype":"locality"
},
  "geometry": {"coordinates":[24.24778,38.14189],"type":"Point"}
}