{
  "type": "Feature",
  "properties": {
    "gn:admin1_code":"ESYE23",
    "gn:admin2_code":"38.0",
    "gn:admin3_code":"9134",
    "gn:asciiname":"Nezeritika",
    "gn:country_code":"GR",
    "gn:dem":85,
    "gn:feature_class":"P",
    "gn:feature_code":"PPL",
    "gn:name":"Nezer\u00edtika",
    "gn:population":0,
    "gn:timezone":"Europe/Athens",
    "iso:country":"GR",
    "name:ell_x_preferred":[
        "\u039d\u03b5\u03b6\u03b5\u03c1\u03af\u03c4\u03b9\u03ba\u03b1"
    ],
    "name:und_x_variant":[
        "Neser\u00edtika",
        "Nezer\u00edtika"
    ],
    "wof:name":"Nezeritika",
    "wof:placetype":"locality"
},
  "geometry": {"coordinates":[21.702,38.16678],"type":"Point"}
}