{
  "type": "Feature",
  "properties": {
    "gn:admin1_code":"ESYE31",
    "gn:admin2_code":"445406.0",
    "gn:admin3_code":"9220",
    "gn:asciiname":"Vothon",
    "gn:country_code":"GR",
    "gn:dem":282,
    "gn:feature_class":"P",
    "gn:feature_code":"PPL",
    "gn:name":"V\u00f3thon",
    "gn:population":177,
    "gn:timezone":"Europe/Athens",
    "iso:country":"GR",
    "name:ell_x_historical":[
        "\u039a\u03b1\u03bb\u03ad\u03bd\u03c4\u03b6\u03b9"
    ],
    "name:ell_x_preferred":[
        "\u0392\u03cc\u03b8\u03c9\u03bd\u03b1\u03c2"
    ],
    "name:ell_x_variant":[
        "\u039a\u03b1\u03bb\u03ad\u03bd\u03c4\u03b6\u03b9"
    ],
    "name:eng_x_preferred":[
        "Vothonas"
    ],
    "name:und_x_variant":[
        "Kal\u00e9nji",
        "V\u00f3thonas",
        "Kal\u00e9ndzi",
        "V\u00f3thon"
    ],
    "wof:name":"Vothon",
    "wof:placetype":"locality",
    "wof:population":177
},
  "geometry": {"coordinates":[23.91955,38.17721],"type":"Point"}
}