{
  "type": "Feature",
  "properties": {
    "gn:admin1_code":"ESYE11",
    "gn:admin2_code":"14.0",
    "gn:admin3_code":"9011",
    "gn:asciiname":"Koinyra",
    "gn:country_code":"GR",
    "gn:dem":21,
    "gn:feature_class":"P",
    "gn:feature_code":"PPL",
    "gn:name":"Ko\u00ednyra",
    "gn:population":105,
    "gn:timezone":"Europe/Athens",
    "iso:country":"GR",
    "name:ell_x_preferred":[
        "\u039a\u03bf\u03af\u03bd\u03c5\u03c1\u03b1"
    ],
    "name:ell_x_variant":[
        "Ko\u00ednyra"
    ],
    "name:eng_x_preferred":[
        "Koinyra"
    ],
    "name:und_x_variant":[
        "K\u00ednira",
        "Ko\u00ednira"
    ],
    "wof:name":"Koinyra",
    "wof:placetype":"locality",
    "wof:population":105
},
  "geometry": {"coordinates":[24.7619,40.66564],"type":"Point"}
}