{
  "type": "Feature",
  "properties": {
    "gn:population":1113,
    "iso:country":"GR",
    "name:bul_x_preferred":[
        "\u0410\u043a\u0440\u0438\u043d\u0438"
    ],
    "name:ceb_x_preferred":[
        "Akrin\u00ed"
    ],
    "name:ell_x_preferred":[
        "\u0391\u03ba\u03c1\u03b9\u03bd\u03ae"
    ],
    "name:ell_x_variant":[
        "\u0391\u03ba\u03c1\u03b9\u03bd\u03ae \u039a\u03bf\u03b6\u03ac\u03bd\u03b7\u03c2"
    ],
    "name:eng_x_preferred":[
        "Akrini"
    ],
    "name:mkd_x_preferred":[
        "\u0418\u043d\u0435\u0432\u043e"
    ],
    "name:nld_x_preferred":[
        "Akrini"
    ],
    "name:srp_x_preferred":[
        "\u0410\u043a\u0440\u0438\u043d\u0438"
    ],
    "name:swe_x_preferred":[
        "Akrin\u00ed"
    ],
    "name:und_x_variant":[
        "Ine\u00f3va"
    ],
    "qs:a0":"Greece",
    "qs:a1":"*\u0394\u03a5\u03a4\u0399\u039a\u0397 \u039c\u0391\u039a\u0395\u0394\u039f\u039d\u0399\u0391",
    "qs:a1_alt":"DYTIKH MAKEDONIA",
    "qs:a1r":"0",
    "qs:a2_alt":"KOZANH",
    "qs:adm0":"Greece",
    "qs:la_lc":"*",
    "qs:level":"locality",
    "qs:loc":"\u0391\u039a\u03a1\u0399\u039d\u0397",
    "qs:loc_alt":"AKRINH",
    "qs:pop":0,
    "qs:type":"buffered point",
    "wof:name":"\u0391\u039a\u03a1\u0399\u039d\u0397",
    "wof:placetype":"locality",
    "wof:population":1113
},
  "geometry": {"coordinates":[21.907528,40.435341],"type":"Point"}
}