{
  "type": "Feature",
  "properties": {
    "gn:admin1_code":"ESYE41",
    "gn:admin2_code":"51.0",
    "gn:admin3_code":"9261",
    "gn:asciiname":"Ntipion",
    "gn:cc2":"GR",
    "gn:country_code":"GR",
    "gn:dem":4,
    "gn:feature_class":"P",
    "gn:feature_code":"PPL",
    "gn:name":"Nt\u00edpion",
    "gn:population":0,
    "gn:timezone":"Europe/Athens",
    "iso:country":"GR",
    "name:ell_x_preferred":[
        "\u039d\u03c4\u03af\u03c0\u03b9"
    ],
    "name:eng_x_preferred":[
        "Ntipi"
    ],
    "name:und_x_variant":[
        "D\u00edpion",
        "Nt\u00edpion"
    ],
    "wof:name":"Ntipion",
    "wof:placetype":"locality"
},
  "geometry": {"coordinates":[26.43873,39.11093],"type":"Point"}
}