{
  "type": "Feature",
  "properties": {
    "gn:admin1_code":"ESYE22",
    "gn:admin2_code":"26.0",
    "gn:admin3_code":"9121",
    "gn:asciiname":"Lefkas Egremni",
    "gn:country_code":"GR",
    "gn:dem":258,
    "gn:feature_class":"P",
    "gn:feature_code":"PPL",
    "gn:name":"Lefkas Egremni",
    "gn:population":0,
    "gn:timezone":"Europe/Athens",
    "iso:country":"GR",
    "wof:name":"Lefkas Egremni",
    "wof:placetype":"locality"
},
  "geometry": {"coordinates":[20.56326,38.64202],"type":"Point"}
}