{
  "type": "Feature",
  "properties": {
    "gn:admin1_code":"ESYE43",
    "gn:admin2_code":"43.0",
    "gn:admin3_code":"9323",
    "gn:asciiname":"Panethimos",
    "gn:country_code":"GR",
    "gn:dem":261,
    "gn:feature_class":"P",
    "gn:feature_code":"PPL",
    "gn:name":"Pan\u00e9thimos",
    "gn:population":0,
    "gn:timezone":"Europe/Athens",
    "iso:country":"GR",
    "name:ell_x_preferred":[
        "\u03a0\u03b1\u03bd\u03ad\u03b8\u03b7\u03bc\u03bf\u03c2"
    ],
    "name:ell_x_variant":[
        "\u03a0\u03b1\u03bd\u03ad\u03b8\u03b7\u03bc\u03bf\u03bd"
    ],
    "name:und_x_variant":[
        "Pan\u00e9thimon",
        "Pan\u00e9thimos"
    ],
    "wof:name":"Panethimos",
    "wof:placetype":"locality"
},
  "geometry": {"coordinates":[23.74607,35.44944],"type":"Point"}
}