{
  "type": "Feature",
  "properties": {
    "gn:country":"GR",
    "gn:fcode":"PPL",
    "gn:population":7030,
    "iso:country":"GR",
    "name:ara_x_preferred":[
        "\u063a\u064a\u0627\u0646\u0648\u0644\u064a"
    ],
    "name:ceb_x_preferred":[
        "Gi\u00e1nnouli"
    ],
    "name:ell_x_preferred":[
        "\u0393\u03b9\u03ac\u03bd\u03bd\u03bf\u03c5\u03bb\u03b7"
    ],
    "name:ell_x_variant":[
        "\u0393\u03b9\u03ac\u03bd\u03bd\u03bf\u03c5\u03bb\u03b7 \u039b\u03ac\u03c1\u03b9\u03c3\u03b1\u03c2"
    ],
    "name:eng_x_preferred":[
        "Giannouli"
    ],
    "name:fin_x_preferred":[
        "Gi\u00e1nnouli"
    ],
    "name:fra_x_preferred":[
        "Giannouli"
    ],
    "name:ita_x_preferred":[
        "Giannouli"
    ],
    "name:jpn_x_preferred":[
        "\u30e4\u30f3\u30cc\u30ea"
    ],
    "name:nld_x_preferred":[
        "Giannouli"
    ],
    "name:nno_x_preferred":[
        "J\u00e1nnouli"
    ],
    "name:rus_x_preferred":[
        "\u042f\u043d\u0443\u043b\u0438"
    ],
    "name:swe_x_preferred":[
        "Gi\u00e1nnouli"
    ],
    "name:und_x_variant":[
        "Yi\u00e1nnouli"
    ],
    "qs_pg:aaroncc":"GR",
    "qs_pg:gn_country":"GR",
    "qs_pg:gn_fcode":"PPL",
    "qs_pg:gn_pop":7030,
    "qs_pg:name":"Yiannouli",
    "qs_pg:name_adm0":"\u0395\u03bb\u03bb\u03ac\u03b4\u03b1",
    "qs_pg:name_adm1":"Thessaly and Continental Greece",
    "qs_pg:photos_9k":1,
    "qs_pg:photos_9r":1,
    "qs_pg:photos_all":8,
    "qs_pg:photos_sr":0,
    "qs_pg:pop_sr":5,
    "qs_pg:qs_pg_placetype":"locality",
    "qs_pg:qs_pg_placetype_gp":"Town",
    "qs_pg:woe_adm0":23424833,
    "woe:adm0_id":23424833,
    "woe:name_adm0":"\u0395\u03bb\u03bb\u03ac\u03b4\u03b1",
    "woe:name_adm1":"Thessaly and Continental Greece",
    "woe:placetype":"Town",
    "wof:name":"Yiannouli",
    "wof:placetype":"locality",
    "wof:population":7885
},
  "geometry": {"coordinates":[22.38333,39.66667],"type":"Point"}
}