{
  "type": "Feature",
  "properties": {
    "gn:admin1_code":"ESYE42",
    "gn:admin2_code":"49.0",
    "gn:admin3_code":"9282",
    "gn:asciiname":"Kokka",
    "gn:country_code":"GR",
    "gn:dem":39,
    "gn:feature_class":"P",
    "gn:feature_code":"PPL",
    "gn:name":"K\u00f3kka",
    "gn:population":0,
    "gn:timezone":"Europe/Athens",
    "iso:country":"GR",
    "name:por_x_preferred":[
        "Kokka"
    ],
    "wof:name":"Kokka",
    "wof:placetype":"locality"
},
  "geometry": {"coordinates":[24.32229,37.66461],"type":"Point"}
}