{
  "type": "Feature",
  "properties": {
    "gn:admin1_code":"ESYE24",
    "gn:admin2_code":"30.0",
    "gn:admin3_code":"9156",
    "gn:asciiname":"Paliolakka",
    "gn:country_code":"GR",
    "gn:dem":1149,
    "gn:feature_class":"P",
    "gn:feature_code":"PPL",
    "gn:name":"Pali\u00f3lakka",
    "gn:population":0,
    "gn:timezone":"Europe/Athens",
    "iso:country":"GR",
    "name:ell_x_preferred":[
        "\u03a0\u03b1\u03bb\u03b9\u03cc\u03bb\u03b1\u03ba\u03ba\u03b1"
    ],
    "name:und_x_variant":[
        "Kalambal\u00edki",
        "Pali\u00f3lakka",
        "Kalabaliki",
        "Palai\u00f3lakka"
    ],
    "wof:name":"Paliolakka",
    "wof:placetype":"locality"
},
  "geometry": {"coordinates":[21.69472,39.17133],"type":"Point"}
}