{
  "type": "Feature",
  "properties": {
    "gn:admin1_code":"ESYE31",
    "gn:admin2_code":"406101.0",
    "gn:admin3_code":"9210",
    "gn:asciiname":"Agios Nektarios Porou",
    "gn:country_code":"GR",
    "gn:dem":151,
    "gn:feature_class":"P",
    "gn:feature_code":"PPL",
    "gn:name":"\u00c1gios Nekt\u00e1rios P\u00f3rou",
    "gn:population":101,
    "gn:timezone":"Europe/Athens",
    "iso:country":"GR",
    "name:ell_x_preferred":[
        "\u0386\u03b3\u03b9\u03bf\u03c2 \u039d\u03b5\u03ba\u03c4\u03ac\u03c1\u03b9\u03bf\u03c2 \u03a0\u03cc\u03c1\u03bf\u03c5"
    ],
    "name:ell_x_variant":[
        "\u0386\u03b3\u03b9\u03bf\u03c2 \u039d\u03b5\u03ba\u03c4\u03ac\u03c1\u03b9\u03bf\u03c2"
    ],
    "wof:name":"Agios Nektarios Porou",
    "wof:placetype":"locality",
    "wof:population":101
},
  "geometry": {"coordinates":[23.47116,37.52339],"type":"Point"}
}