{
  "type": "Feature",
  "properties": {
    "gn:admin1_code":"ESYE25",
    "gn:admin2_code":"40.0",
    "gn:admin3_code":"9256",
    "gn:asciiname":"Meropi",
    "gn:country_code":"GR",
    "gn:dem":85,
    "gn:feature_class":"P",
    "gn:feature_code":"PPL",
    "gn:name":"Mer\u00f3pi",
    "gn:population":0,
    "gn:timezone":"Europe/Athens",
    "iso:country":"GR",
    "name:ell_x_preferred":[
        "\u039c\u03b5\u03c1\u03cc\u03c0\u03b7"
    ],
    "name:por_x_preferred":[
        "Allagi"
    ],
    "name:ron_x_preferred":[
        "Allagi"
    ],
    "name:und_x_variant":[
        "Mer\u00f3pi"
    ],
    "wof:name":"Meropi",
    "wof:placetype":"locality"
},
  "geometry": {"coordinates":[22.0032,37.24192],"type":"Point"}
}