{
  "type": "Feature",
  "properties": {
    "gn:admin1_code":"ESYE23",
    "gn:admin2_code":"38.0",
    "gn:admin3_code":"9130",
    "gn:asciiname":"Ano Ziria",
    "gn:country_code":"GR",
    "gn:dem":511,
    "gn:feature_class":"P",
    "gn:feature_code":"PPL",
    "gn:name":"\u00c1no Z\u00edria",
    "gn:population":0,
    "gn:timezone":"Europe/Athens",
    "iso:country":"GR",
    "name:ell_x_preferred":[
        "\u00c1no Z\u00edria"
    ],
    "name:ell_x_variant":[
        "\u0386\u03bd\u03c9 \u0396\u03ae\u03c1\u03b9\u03b1"
    ],
    "wof:name":"Ano Ziria",
    "wof:placetype":"locality"
},
  "geometry": {"coordinates":[21.94728,38.30497],"type":"Point"}
}