{
  "type": "Feature",
  "properties": {
    "iso:country":"GR",
    "qs:a0":"Greece",
    "qs:a1":"*\u03a0\u0395\u039b\u039f\u03a0\u039f\u039d\u039d\u0397\u03a3\u039f\u03a3",
    "qs:a1_alt":"PELOPONNHSOS",
    "qs:a1r":"0",
    "qs:a2_alt":"ARGOLIDA",
    "qs:adm0":"Greece",
    "qs:la_lc":"*",
    "qs:level":"locality",
    "qs:loc":"\u0391\u0393\u0399\u0391 \u03a4\u03a1\u0399\u0391\u0394\u0391",
    "qs:loc_alt":"AGIA TRIADA",
    "qs:pop":0,
    "qs:type":"buffered point",
    "wof:name":"\u0391\u0393\u0399\u0391 \u03a4\u03a1\u0399\u0391\u0394\u0391",
    "wof:placetype":"locality"
},
  "geometry": {"coordinates":[22.80669,37.638283],"type":"Point"}
}