{
  "type": "Feature",
  "properties": {
    "gn:gn_country":"GR",
    "gn:gn_fcode":"ADM3",
    "gn:gn_pop":42127,
    "gn:population":48399,
    "iso:country":"GR",
    "name:ell_x_preferred":[
        "\u0392\u03ac\u03c1\u03b7\u03c2 - \u0392\u03bf\u03cd\u03bb\u03b1\u03c2 - \u0392\u03bf\u03c5\u03bb\u03b9\u03b1\u03b3\u03bc\u03ad\u03bd\u03b7\u03c2"
    ],
    "qs_pg:aaroncc":"GR",
    "qs_pg:gn_country":"GR",
    "qs_pg:gn_fcode":"ADM3",
    "qs_pg:gn_pop":42127,
    "qs_pg:name":"Vari-Voula-Vouliagmeni",
    "qs_pg:name_adm0":"\u0395\u03bb\u03bb\u03ac\u03b4\u03b1",
    "qs_pg:name_adm1":"Attica",
    "qs_pg:photos_9k":4,
    "qs_pg:photos_9r":6,
    "qs_pg:photos_all":980,
    "qs_pg:photos_sr":0,
    "qs_pg:pop_sr":7,
    "qs_pg:qs_pg_placetype":"localadmin",
    "qs_pg:qs_pg_placetype_gp":"LocalAdmin",
    "qs_pg:woe_adm0":23424833,
    "woe:adm0_id":23424833,
    "woe:name_adm0":"\u0395\u03bb\u03bb\u03ac\u03b4\u03b1",
    "woe:name_adm1":"Attica",
    "woe:placetype":"LocalAdmin",
    "wof:name":"Vari-Voula-Vouliagmeni",
    "wof:placetype":"localadmin",
    "wof:population":48399
},
  "geometry": {"coordinates":[23.79225,37.83333],"type":"Point"}
}