{
  "type": "Feature",
  "properties": {
    "gn:admin1_code":"ESYE23",
    "gn:admin2_code":"39.0",
    "gn:admin3_code":"9141",
    "gn:asciiname":"Rozaiika",
    "gn:country_code":"GR",
    "gn:dem":213,
    "gn:feature_class":"P",
    "gn:feature_code":"PPL",
    "gn:name":"Roza\u00edika",
    "gn:population":0,
    "gn:timezone":"Europe/Athens",
    "iso:country":"GR",
    "name:ell_x_preferred":[
        "\u03a1\u03bf\u03b6\u03b1\u03af\u03b9\u03ba\u03b1"
    ],
    "name:und_x_variant":[
        "Roze\u00efka",
        "Roza\u00edika"
    ],
    "wof:name":"Rozaiika",
    "wof:placetype":"locality"
},
  "geometry": {"coordinates":[21.49321,37.72636],"type":"Point"}
}