{
  "type": "Feature",
  "properties": {
    "gn:country":"GR",
    "gn:fcode":"PPL",
    "gn:population":96,
    "iso:country":"GR",
    "name:ell_x_preferred":[
        "\u0395\u03bc\u03c0\u03bf\u03c1\u03b5\u03b9\u03cc\u03c2"
    ],
    "name:ell_x_variant":[
        "\u0395\u03bc\u03c0\u03bf\u03c1\u03b5\u03b9\u03cc",
        "\u0395\u03bc\u03c0\u03bf\u03c1\u03b9\u03cc"
    ],
    "name:eng_x_preferred":[
        "Emporeios"
    ],
    "name:und_x_variant":[
        "Chori\u00f3 Emporei\u00f3s"
    ],
    "qs_pg:aaroncc":"GR",
    "qs_pg:gn_country":"GR",
    "qs_pg:gn_fcode":"PPL",
    "qs_pg:gn_pop":96,
    "qs_pg:name":"Emporei\u00f3s",
    "qs_pg:photos_9r":0,
    "qs_pg:photos_sr":0,
    "qs_pg:pop_sr":1,
    "qs_pg:qs_pg_placetype":"locality",
    "wof:name":"Emporei\u00f3s",
    "wof:placetype":"locality",
    "wof:population":47
},
  "geometry": {"coordinates":[26.02877,38.18825],"type":"Point"}
}