{
  "type": "Feature",
  "properties": {
    "gn:admin1_code":"ESYE43",
    "gn:admin2_code":"45.0",
    "gn:admin3_code":"9306",
    "gn:asciiname":"Thiseas",
    "gn:country_code":"GR",
    "gn:dem":148,
    "gn:elevation":"129.0",
    "gn:feature_class":"P",
    "gn:feature_code":"PPLL",
    "gn:name":"Thiseas",
    "gn:population":0,
    "gn:timezone":"Europe/Athens",
    "iso:country":"GR",
    "wof:name":"Thiseas",
    "wof:placetype":"locality"
},
  "geometry": {"coordinates":[25.04252,35.39332],"type":"Point"}
}