{
  "type": "Feature",
  "properties": {
    "gn:gn_country":"GR",
    "gn:gn_fcode":"PPL",
    "gn:gn_pop":0,
    "gn:population":566,
    "iso:country":"GR",
    "name:ell_x_preferred":[
        "\u039a\u03bf\u03c5\u03c4\u03c3\u03bf\u03c5\u03bd\u03ac\u03c1\u03b9"
    ],
    "name:eng_x_preferred":[
        "Koutsounari"
    ],
    "name:gre_x_preferred":[
        "\u039a\u03bf\u03c5\u03c4\u03c3\u03bf\u03c5\u03bd\u03ac\u03c1\u03b9 \u039b\u03b1\u03c3\u03b9\u03b8\u03af\u03bf\u03c5"
    ],
    "name:unk_x_variant":[
        "Koutsoun\u00e1ri"
    ],
    "qs_pg:aaroncc":"GR",
    "qs_pg:gn_country":"GR",
    "qs_pg:gn_fcode":"PPL",
    "qs_pg:gn_pop":0,
    "qs_pg:name":"Koutsounari",
    "qs_pg:name_adm0":"\u0395\u03bb\u03bb\u03ac\u03b4\u03b1",
    "qs_pg:name_adm1":"Crete",
    "qs_pg:photos":176,
    "qs_pg:photos_1k":36,
    "qs_pg:photos_9k":1,
    "qs_pg:photos_9r":4,
    "qs_pg:photos_all":176,
    "qs_pg:photos_sr":4,
    "qs_pg:pop_sr":0,
    "qs_pg:qs_pg_placetype":"locality",
    "qs_pg:qs_pg_placetype_gp":"Town",
    "qs_pg:woe_adm0":23424833,
    "woe:adm0_id":23424833,
    "woe:name_adm0":"\u0395\u03bb\u03bb\u03ac\u03b4\u03b1",
    "woe:name_adm1":"Crete",
    "woe:placetype":"Town",
    "wof:name":"Koutsounari",
    "wof:placetype":"locality",
    "wof:population":566
},
  "geometry": {"coordinates":[25.83333,35.01667],"type":"Point"}
}