{
  "type": "Feature",
  "properties": {
    "gn:gn_country":"GR",
    "gn:gn_fcode":"PPL",
    "gn:gn_pop":987,
    "gn:population":987,
    "iso:country":"GR",
    "name:ara_x_preferred":[
        "\u063a\u0644\u0648\u0633\u0627\u060c \u0645\u0627\u063a\u0646\u064a\u0633\u064a\u0627"
    ],
    "name:ell_x_preferred":[
        "\u0393\u03bb\u03ce\u03c3\u03c3\u03b1"
    ],
    "name:ell_x_variant":[
        "\u0393\u03bb\u03ce\u03c3\u03c3\u03b1 \u03a3\u03ba\u03bf\u03c0\u03ad\u03bb\u03bf\u03c5"
    ],
    "name:eng_x_preferred":[
        "Glossa"
    ],
    "name:nld_x_preferred":[
        "Glossa"
    ],
    "name:swe_x_preferred":[
        "Gl\u00f3ssa"
    ],
    "name:unk_x_variant":[
        "Plat\u00e1nia"
    ],
    "qs_pg:aaroncc":"GR",
    "qs_pg:gn_country":"GR",
    "qs_pg:gn_fcode":"PPL",
    "qs_pg:gn_pop":987,
    "qs_pg:name":"Glossa",
    "qs_pg:name_adm0":"\u0395\u03bb\u03bb\u03ac\u03b4\u03b1",
    "qs_pg:name_adm1":"Thessaly and Continental Greece",
    "qs_pg:photos":368,
    "qs_pg:photos_1k":75,
    "qs_pg:photos_9k":2,
    "qs_pg:photos_9r":5,
    "qs_pg:photos_all":368,
    "qs_pg:photos_sr":6,
    "qs_pg:pop_sr":2,
    "qs_pg:qs_pg_placetype":"locality",
    "qs_pg:qs_pg_placetype_gp":"Town",
    "qs_pg:woe_adm0":23424833,
    "woe:adm0_id":23424833,
    "woe:name_adm0":"\u0395\u03bb\u03bb\u03ac\u03b4\u03b1",
    "woe:name_adm1":"Thessaly and Continental Greece",
    "woe:placetype":"Town",
    "wof:name":"Glossa",
    "wof:placetype":"locality",
    "wof:population":987
},
  "geometry": {"coordinates":[23.61667,39.16667],"type":"Point"}
}