{
  "type": "Feature",
  "properties": {
    "gn:admin1_code":"ESYE24",
    "gn:admin2_code":"34.0",
    "gn:admin3_code":"9151",
    "gn:asciiname":"Rizovouni",
    "gn:country_code":"GR",
    "gn:dem":257,
    "gn:feature_class":"P",
    "gn:feature_code":"PPL",
    "gn:name":"Rizovo\u00fani",
    "gn:population":0,
    "gn:timezone":"Europe/Athens",
    "iso:country":"GR",
    "name:ell_x_preferred":[
        "Rizovo\u00fani"
    ],
    "name:ell_x_variant":[
        "\u03a1\u03b9\u03b6\u03bf\u03b2\u03bf\u03cd\u03bd\u03b9",
        "\u03a1\u03b9\u03b6\u03bf\u03b2\u03bf\u03cd\u03bd\u03b9\u03bf\u03bd"
    ],
    "name:und_x_variant":[
        "Bayi\u00e1tion",
        "Boyi\u00e1ti",
        "Rizovo\u00fanion"
    ],
    "wof:name":"Rizovouni",
    "wof:placetype":"locality"
},
  "geometry": {"coordinates":[24.31222,38.12847],"type":"Point"}
}