{
  "type": "Feature",
  "properties": {
    "gn:gn_country":"GR",
    "iso:country":"GR",
    "name:bul_x_preferred":[
        "\u041f\u0430\u043b\u044e\u0440\u0438"
    ],
    "name:ceb_x_preferred":[
        "Palio\u00fari"
    ],
    "name:ell_x_preferred":[
        "\u03a0\u03b1\u03bb\u03b9\u03bf\u03cd\u03c1\u03b9 \u03a7\u03b1\u03bb\u03ba\u03b9\u03b4\u03b9\u03ba\u03ae\u03c2"
    ],
    "name:eng_x_preferred":[
        "Paliouri"
    ],
    "name:nld_x_preferred":[
        "Paliouri"
    ],
    "name:swe_x_preferred":[
        "Palio\u00fari"
    ],
    "qs_pg:aaroncc":"GR",
    "qs_pg:gn_country":"GR",
    "qs_pg:name":"Paliouri",
    "qs_pg:name_adm0":"\u0395\u03bb\u03bb\u03ac\u03b4\u03b1",
    "qs_pg:name_adm1":"Macedonia and Thrace",
    "qs_pg:photos":174,
    "qs_pg:photos_1k":35,
    "qs_pg:photos_9k":1,
    "qs_pg:photos_9r":4,
    "qs_pg:photos_all":174,
    "qs_pg:photos_sr":4,
    "qs_pg:pop_sr":0,
    "qs_pg:qs_pg_placetype":"locality",
    "qs_pg:qs_pg_placetype_gp":"Town",
    "qs_pg:woe_adm0":23424833,
    "woe:adm0_id":23424833,
    "woe:name_adm0":"\u0395\u03bb\u03bb\u03ac\u03b4\u03b1",
    "woe:name_adm1":"Macedonia and Thrace",
    "woe:placetype":"Town",
    "wof:name":"Paliouri",
    "wof:placetype":"locality"
},
  "geometry": {"coordinates":[23.723173,39.913916],"type":"Point"}
}