{
  "type": "Feature",
  "properties": {
    "gn:admin1_code":"ESYE13",
    "gn:admin2_code":"9.0",
    "gn:admin3_code":"9065",
    "gn:asciiname":"Ammos",
    "gn:country_code":"GR",
    "gn:dem":638,
    "gn:feature_class":"P",
    "gn:feature_code":"PPLL",
    "gn:name":"\u00c1mmos",
    "gn:population":0,
    "gn:timezone":"Europe/Athens",
    "iso:country":"GR",
    "name:ell_x_preferred":[
        "\u0386\u03bc\u03bc\u03bf\u03c2"
    ],
    "name:eng_x_preferred":[
        "Ammos"
    ],
    "wof:name":"Ammos",
    "wof:placetype":"locality"
},
  "geometry": {"coordinates":[21.31468,40.47317],"type":"Point"}
}