{
  "type": "Feature",
  "properties": {
    "gn:admin1_code":"ESYE43",
    "gn:admin2_code":"44.0",
    "gn:admin3_code":"9315",
    "gn:asciiname":"Smiles",
    "gn:country_code":"GR",
    "gn:dem":497,
    "gn:feature_class":"P",
    "gn:feature_code":"PPL",
    "gn:name":"Smil\u00e9s",
    "gn:population":0,
    "gn:timezone":"Europe/Athens",
    "iso:country":"GR",
    "name:ell_x_preferred":[
        "Smil\u00e9s"
    ],
    "name:ell_x_variant":[
        "\u03a3\u03bc\u03b9\u03bb\u03ad\u03c2"
    ],
    "wof:name":"Smiles",
    "wof:placetype":"locality"
},
  "geometry": {"coordinates":[24.63994,35.20811],"type":"Point"}
}