{
  "type": "Feature",
  "properties": {
    "gn:admin1_code":"ESYE23",
    "gn:admin2_code":"31.0",
    "gn:admin3_code":"9125",
    "gn:asciiname":"Triklino",
    "gn:country_code":"GR",
    "gn:dem":568,
    "gn:feature_class":"P",
    "gn:feature_code":"PPL",
    "gn:name":"Tr\u00edklino",
    "gn:population":0,
    "gn:timezone":"Europe/Athens",
    "iso:country":"GR",
    "name:deu_x_preferred":[
        "Triklino"
    ],
    "name:ell_x_preferred":[
        "Tr\u00edklino"
    ],
    "name:ell_x_variant":[
        "\u03a4\u03c1\u03af\u03ba\u03bb\u03b9\u03bd\u03bf",
        "\u03a4\u03c1\u03af\u03ba\u03bb\u03b9\u03bd\u03bf\u03bd",
        "\u03a4\u03c1\u03af\u03ba\u03bb\u03b9\u03bd\u03bf \u0391\u03b9\u03c4\u03c9\u03bb\u03bf\u03b1\u03ba\u03b1\u03c1\u03bd\u03b1\u03bd\u03af\u03b1\u03c2"
    ],
    "name:ron_x_preferred":[
        "Triklino"
    ],
    "name:und_x_variant":[
        "Priantza",
        "Tr\u00edklinos",
        "Tr\u00edklinon"
    ],
    "wof:name":"Triklino",
    "wof:placetype":"locality"
},
  "geometry": {"coordinates":[21.445,38.97342],"type":"Point"}
}