{
  "type": "Feature",
  "properties": {
    "gn:gn_country":"GR",
    "gn:gn_fcode":"PPL",
    "gn:gn_pop":4144,
    "gn:population":4144,
    "iso:country":"GR",
    "name:ara_x_preferred":[
        "\u0646\u064a \u0645\u0627\u063a\u0646\u064a\u0633\u064a\u0627\u060c \u062b\u064a\u0633\u0627\u0644\u0648\u0646\u064a\u0643\u064a"
    ],
    "name:bul_x_preferred":[
        "\u0410\u0440\u0430\u043f\u043b\u0438"
    ],
    "name:dut_x_preferred":[
        "Nea Magnisia"
    ],
    "name:ell_x_preferred":[
        "\u039d\u03ad\u03b1 \u039c\u03b1\u03b3\u03bd\u03b7\u03c3\u03af\u03b1"
    ],
    "name:ell_x_variant":[
        "\u039d\u03b5\u03ac \u039c\u03b1\u03b3\u03bd\u03b7\u03c3\u03af\u03b1"
    ],
    "name:eng_x_preferred":[
        "Nea Magnisia"
    ],
    "name:gre_x_preferred":[
        "\u039d\u03ad\u03b1 \u039c\u03b1\u03b3\u03bd\u03b7\u03c3\u03af\u03b1 \u0398\u03b5\u03c3\u03c3\u03b1\u03bb\u03bf\u03bd\u03af\u03ba\u03b7\u03c2"
    ],
    "name:nno_x_preferred":[
        "N\u00e9a Magnis\u00eda"
    ],
    "name:swe_x_preferred":[
        "N\u00e9a Magnis\u00eda"
    ],
    "name:unk_x_variant":[
        "Arapl\u00ed"
    ],
    "qs_pg:aaroncc":"GR",
    "qs_pg:gn_country":"GR",
    "qs_pg:gn_fcode":"PPL",
    "qs_pg:gn_pop":4144,
    "qs_pg:name":"Nea Magnisia",
    "qs_pg:name_adm0":"\u0395\u03bb\u03bb\u03ac\u03b4\u03b1",
    "qs_pg:name_adm1":"Macedonia and Thrace",
    "qs_pg:photos_9r":0,
    "qs_pg:photos_sr":0,
    "qs_pg:pop_sr":4,
    "qs_pg:qs_pg_placetype":"locality",
    "qs_pg:qs_pg_placetype_gp":"Town",
    "qs_pg:woe_adm0":23424833,
    "woe:adm0_id":23424833,
    "woe:name_adm0":"\u0395\u03bb\u03bb\u03ac\u03b4\u03b1",
    "woe:name_adm1":"Macedonia and Thrace",
    "woe:placetype":"Town",
    "wof:name":"Nea Magnisia",
    "wof:placetype":"locality",
    "wof:population":4144
},
  "geometry": {"coordinates":[22.84694,40.6875],"type":"Point"}
}