{
  "type": "Feature",
  "properties": {
    "gn:admin1_code":"ESYE23",
    "gn:admin2_code":"31.0",
    "gn:admin3_code":"9123",
    "gn:asciiname":"Ayia Trias Makrinous",
    "gn:country_code":"GR",
    "gn:dem":162,
    "gn:feature_class":"P",
    "gn:feature_code":"PPL",
    "gn:name":"Ay\u00eda Tri\u00e1s Makrino\u00fas",
    "gn:population":44,
    "gn:timezone":"Europe/Athens",
    "iso:country":"GR",
    "name:ell_x_historical":[
        "\u039a\u03ac\u03c4\u03c9 \u039c\u03c0\u03b5\u03c1\u03bc\u03c0\u03ac\u03c4\u03b7"
    ],
    "name:ell_x_preferred":[
        "\u0391\u03b3\u03af\u03b1 \u03a4\u03c1\u03b9\u03ac\u03b4\u03b1 \u039c\u03b1\u03ba\u03c1\u03b9\u03bd\u03bf\u03cd\u03c2"
    ],
    "name:ell_x_variant":[
        "\u039a\u03ac\u03c4\u03c9 \u039c\u03c0\u03b5\u03c1\u03bc\u03c0\u03ac\u03c4\u03b7"
    ],
    "name:eng_x_historical":[
        "Kato Berbati"
    ],
    "name:eng_x_preferred":[
        "Agia Triada Makrinous"
    ],
    "name:eng_x_variant":[
        "Kato Berbati"
    ],
    "name:und_x_variant":[
        "Kato Mpermpati",
        "Ay\u00eda Tri\u00e1da Makrino\u00fas"
    ],
    "wof:name":"Ayia Trias Makrinous",
    "wof:placetype":"locality",
    "wof:population":44
},
  "geometry": {"coordinates":[21.62674,38.43848],"type":"Point"}
}