{
  "type": "Feature",
  "properties": {
    "gn:admin1_code":"ESYE41",
    "gn:asciiname":"Mavrato",
    "gn:country_code":"GR",
    "gn:dem":455,
    "gn:feature_class":"P",
    "gn:feature_code":"PPL",
    "gn:name":"Mavr\u00e1to",
    "gn:population":0,
    "gn:timezone":"Europe/Athens",
    "iso:country":"GR",
    "name:ell_x_preferred":[
        "Mavr\u00e1to"
    ],
    "name:ell_x_variant":[
        "\u039c\u03b1\u03c5\u03c1\u03ac\u03c4\u03bf"
    ],
    "wof:name":"Mavrato",
    "wof:placetype":"locality"
},
  "geometry": {"coordinates":[26.28431,37.63357],"type":"Point"}
}