{
  "type": "Feature",
  "properties": {
    "iso:country":"GR",
    "name:ara_x_preferred":[
        "\u0628\u064a\u062a\u0627\u0644\u064a\u062f\u064a"
    ],
    "name:bre_x_preferred":[
        "Petalidi"
    ],
    "name:cos_x_preferred":[
        "Petalidi"
    ],
    "name:dan_x_preferred":[
        "Petalidi"
    ],
    "name:deu_x_preferred":[
        "Petalidi"
    ],
    "name:ell_x_preferred":[
        "Petal\u00eddi"
    ],
    "name:ell_x_variant":[
        "\u03a0\u03b5\u03c4\u03b1\u03bb\u03af\u03b4\u03b9",
        "Petal\u00eddion",
        "\u03a0\u03b5\u03c4\u03b1\u03bb\u03af\u03b4\u03b9\u03bf\u03bd",
        "\u03a0\u03b5\u03c4\u03b1\u03bb\u03af\u03b4\u03b9 \u039c\u03b5\u03c3\u03c3\u03b7\u03bd\u03af\u03b1\u03c2"
    ],
    "name:eng_x_preferred":[
        "Petalidi"
    ],
    "name:fin_x_preferred":[
        "Petal\u00eddi"
    ],
    "name:fra_x_preferred":[
        "Petalidi"
    ],
    "name:ind_x_preferred":[
        "Petalidi"
    ],
    "name:ita_x_preferred":[
        "Petalidi"
    ],
    "name:jpn_x_preferred":[
        "\u30da\u30bf\u30ea\u30c7\u30a3"
    ],
    "name:nds_x_preferred":[
        "Petalidi"
    ],
    "name:nld_x_preferred":[
        "Petalidi"
    ],
    "name:nno_x_preferred":[
        "Petal\u00eddi"
    ],
    "name:por_x_preferred":[
        "Petalidi"
    ],
    "name:ron_x_preferred":[
        "Petalidi"
    ],
    "name:rus_x_preferred":[
        "\u041f\u0435\u0442\u0430\u043b\u0438\u0434\u0438"
    ],
    "name:spa_x_preferred":[
        "Petalidi"
    ],
    "name:sqi_x_preferred":[
        "Petalidi"
    ],
    "name:swe_x_preferred":[
        "Petalidi"
    ],
    "name:tah_x_preferred":[
        "Petalidi"
    ],
    "name:und_x_variant":[
        "Petal\u00eddhi"
    ],
    "qs:a0":"Greece",
    "qs:a1":"*\u03a0\u0395\u039b\u039f\u03a0\u039f\u039d\u039d\u0397\u03a3\u039f\u03a3",
    "qs:a1_alt":"PELOPONNHSOS",
    "qs:a1r":"0",
    "qs:a2_alt":"MESSHNIA",
    "qs:adm0":"Greece",
    "qs:la_lc":"*",
    "qs:level":"locality",
    "qs:loc":"\u03a0\u0395\u03a4\u0391\u039b\u0399\u0394\u0399\u039f\u039d",
    "qs:loc_alt":"PETALIDION",
    "qs:pop":0,
    "qs:type":"buffered point",
    "wd:wordcount":150,
    "wof:name":"\u03a0\u0395\u03a4\u0391\u039b\u0399\u0394\u0399\u039f\u039d",
    "wof:placetype":"locality"
},
  "geometry": {"coordinates":[21.927961,36.959343],"type":"Point"}
}