{
  "type": "Feature",
  "properties": {
    "gn:admin1_code":"ESYE22",
    "gn:admin2_code":"27.0",
    "gn:admin3_code":"9120",
    "gn:asciiname":"Razata",
    "gn:country_code":"GR",
    "gn:dem":164,
    "gn:feature_class":"P",
    "gn:feature_code":"PPL",
    "gn:name":"Raz\u00e1ta",
    "gn:population":0,
    "gn:timezone":"Europe/Athens",
    "iso:country":"GR",
    "name:ell_x_preferred":[
        "\u03a1\u03b1\u03b6\u03ac\u03c4\u03b1"
    ],
    "name:und_x_variant":[
        "Raz\u00e1ta"
    ],
    "wof:name":"Razata",
    "wof:placetype":"locality"
},
  "geometry": {"coordinates":[20.52425,38.18639],"type":"Point"}
}