{
  "type": "Feature",
  "properties": {
    "gn:admin1_code":"ESYE23",
    "gn:admin2_code":"31.0",
    "gn:admin3_code":"9124",
    "gn:asciiname":"Ayia Varvara",
    "gn:country_code":"GR",
    "gn:dem":26,
    "gn:feature_class":"P",
    "gn:feature_code":"PPL",
    "gn:name":"Ay\u00eda Varv\u00e1ra",
    "gn:population":0,
    "gn:timezone":"Europe/Athens",
    "iso:country":"GR",
    "wof:name":"Ayia Varvara",
    "wof:placetype":"locality"
},
  "geometry": {"coordinates":[20.74658,38.8356],"type":"Point"}
}