{
  "type": "Feature",
  "properties": {
    "gn:admin1_code":"ESYE23",
    "gn:admin2_code":"39.0",
    "gn:admin3_code":"9141",
    "gn:asciiname":"Korakochori",
    "gn:country_code":"GR",
    "gn:dem":37,
    "gn:feature_class":"P",
    "gn:feature_code":"PPL",
    "gn:name":"Korakoch\u00f3ri",
    "gn:population":0,
    "gn:timezone":"Europe/Athens",
    "iso:country":"GR",
    "name:ell_x_preferred":[
        "Korakoch\u00f3ri"
    ],
    "name:ell_x_variant":[
        "\u039a\u03bf\u03c1\u03b1\u03ba\u03bf\u03c7\u03ce\u03c1\u03b9",
        "Korakoch\u00f3rion",
        "\u039a\u03bf\u03c1\u03b1\u03ba\u03bf\u03c7\u03ce\u03c1\u03b9\u03bf\u03bd",
        "\u039a\u03bf\u03c1\u03b1\u03ba\u03bf\u03c7\u03ce\u03c1\u03b9 \u0397\u03bb\u03b5\u03af\u03b1\u03c2"
    ],
    "name:und_x_variant":[
        "Korakokh\u00f3ri",
        "Korakokh\u00f3rion"
    ],
    "wof:name":"Korakochori",
    "wof:placetype":"locality"
},
  "geometry": {"coordinates":[21.31478,37.67514],"type":"Point"}
}