{
  "type": "Feature",
  "properties": {
    "gn:admin1_code":"ESYE23",
    "gn:admin2_code":"31.0",
    "gn:admin3_code":"9125",
    "gn:asciiname":"Monopolion",
    "gn:country_code":"GR",
    "gn:dem":393,
    "gn:feature_class":"P",
    "gn:feature_code":"PPL",
    "gn:name":"Monop\u00f3lion",
    "gn:population":0,
    "gn:timezone":"Europe/Athens",
    "iso:country":"GR",
    "wof:name":"Monopolion",
    "wof:placetype":"locality"
},
  "geometry": {"coordinates":[21.48333,38.96667],"type":"Point"}
}