{
  "type": "Feature",
  "properties": {
    "gn:country":"GR",
    "gn:fcode":"PPL",
    "gn:population":759,
    "iso:country":"GR",
    "name:bul_x_preferred":[
        "\u0410\u0440\u0435\u043e\u043f\u043e\u043b\u0438"
    ],
    "name:ceb_x_preferred":[
        "Are\u00f3poli"
    ],
    "name:cym_x_preferred":[
        "Areopoli"
    ],
    "name:deu_x_preferred":[
        "Areopoli"
    ],
    "name:ell_x_historical":[
        "\u03a4\u03c3\u03af\u03bc\u03bf\u03b2\u03b1",
        "\u03a4\u03b6\u03af\u03bc\u03bf\u03b2\u03b1"
    ],
    "name:ell_x_preferred":[
        "\u0391\u03c1\u03b5\u03cc\u03c0\u03bf\u03bb\u03b7"
    ],
    "name:ell_x_variant":[
        "\u03a4\u03c3\u03af\u03bc\u03bf\u03b2\u03b1",
        "\u03a4\u03b6\u03af\u03bc\u03bf\u03b2\u03b1",
        "\u0391\u03c1\u03b5\u03cc\u03c0\u03bf\u03bb\u03b7 \u039b\u03b1\u03ba\u03c9\u03bd\u03af\u03b1\u03c2"
    ],
    "name:eng_x_preferred":[
        "Areopolis"
    ],
    "name:eng_x_variant":[
        "Areopoli"
    ],
    "name:est_x_preferred":[
        "Are\u00f3poli"
    ],
    "name:fin_x_preferred":[
        "Are\u00f3poli"
    ],
    "name:fra_x_preferred":[
        "Are\u00f3poli"
    ],
    "name:gsw_x_preferred":[
        "Areopoli"
    ],
    "name:heb_x_preferred":[
        "\u05d0\u05e8\u05d0\u05d5\u05e4\u05d5\u05dc\u05d9"
    ],
    "name:hye_x_preferred":[
        "\u0531\u0580\u0565\u0578\u057a\u0578\u056c\u056b\u057d"
    ],
    "name:ita_x_preferred":[
        "Areopoli"
    ],
    "name:lat_x_preferred":[
        "Areopolis"
    ],
    "name:nld_x_preferred":[
        "Areopoli"
    ],
    "name:nno_x_preferred":[
        "Are\u00f3poli"
    ],
    "name:ron_x_preferred":[
        "Areopoli"
    ],
    "name:rus_x_preferred":[
        "\u0410\u0440\u0435\u043e\u043f\u043e\u043b\u0438\u0441"
    ],
    "name:swe_x_preferred":[
        "Are\u00f3poli"
    ],
    "name:ukr_x_preferred":[
        "\u0410\u0440\u0435\u043e\u043f\u043e\u043b\u0456"
    ],
    "name:und_x_variant":[
        "Ts\u00edmova"
    ],
    "qs_pg:aaroncc":"GR",
    "qs_pg:gn_country":"GR",
    "qs_pg:gn_fcode":"PPL",
    "qs_pg:gn_pop":759,
    "qs_pg:name":"Areopoli",
    "qs_pg:name_adm0":"\u0395\u03bb\u03bb\u03ac\u03b4\u03b1",
    "qs_pg:name_adm1":"Peloponnese Western Greece and the Ionian Islands",
    "qs_pg:photos":290,
    "qs_pg:photos_1k":59,
    "qs_pg:photos_9k":1,
    "qs_pg:photos_9r":4,
    "qs_pg:photos_all":290,
    "qs_pg:photos_sr":5,
    "qs_pg:pop_sr":2,
    "qs_pg:qs_pg_placetype":"locality",
    "qs_pg:qs_pg_placetype_gp":"Town",
    "qs_pg:woe_adm0":23424833,
    "woe:adm0_id":23424833,
    "woe:name_adm0":"\u0395\u03bb\u03bb\u03ac\u03b4\u03b1",
    "woe:name_adm1":"Peloponnese Western Greece and the Ionian Islands",
    "woe:placetype":"Town",
    "wof:name":"Areopoli",
    "wof:placetype":"locality",
    "wof:population":888
},
  "geometry": {"coordinates":[22.3825,36.66389],"type":"Point"}
}