{
  "type": "Feature",
  "properties": {
    "gn:admin1_code":"ESYE43",
    "gn:admin2_code":"44.0",
    "gn:admin3_code":"9315",
    "gn:asciiname":"Meronas",
    "gn:country_code":"GR",
    "gn:dem":608,
    "gn:feature_class":"P",
    "gn:feature_code":"PPL",
    "gn:name":"M\u00e9ronas",
    "gn:population":0,
    "gn:timezone":"Europe/Athens",
    "iso:country":"GR",
    "wof:name":"Meronas",
    "wof:placetype":"locality"
},
  "geometry": {"coordinates":[24.62929,35.23397999999999],"type":"Point"}
}