{
  "type": "Feature",
  "properties": {
    "gn:admin1_code":"ESYE13",
    "gn:admin2_code":"10.0",
    "gn:admin3_code":"9061",
    "gn:asciiname":"KONTA EISAI",
    "gn:country_code":"GR",
    "gn:dem":1385,
    "gn:elevation":"1400.0",
    "gn:feature_class":"P",
    "gn:feature_code":"PPL",
    "gn:name":"KONTA EISAI",
    "gn:population":0,
    "gn:timezone":"Europe/Athens",
    "iso:country":"GR",
    "wof:name":"KONTA EISAI",
    "wof:placetype":"locality"
},
  "geometry": {"coordinates":[21.13242,39.94143],"type":"Point"}
}