{
  "type": "Feature",
  "properties": {
    "gn:admin1_code":"ESYE24",
    "gn:admin2_code":"30.0",
    "gn:admin3_code":"9157",
    "gn:asciiname":"Ayios Kharalambos",
    "gn:country_code":"GR",
    "gn:dem":893,
    "gn:feature_class":"P",
    "gn:feature_code":"PPL",
    "gn:name":"\u00c1yios Khar\u00e1lambos",
    "gn:population":60,
    "gn:timezone":"Europe/Athens",
    "iso:country":"GR",
    "name:ell_x_preferred":[
        "\u0386\u03b3\u03b9\u03bf\u03c2 \u03a7\u03b1\u03c1\u03ac\u03bb\u03b1\u03bc\u03c0\u03bf\u03c2"
    ],
    "name:eng_x_preferred":[
        "Agios Charalampos"
    ],
    "name:und_x_variant":[
        "Eloga",
        "\u00c1yios Khar\u00e1lambos"
    ],
    "wof:name":"Ayios Kharalambos",
    "wof:placetype":"locality",
    "wof:population":60
},
  "geometry": {"coordinates":[21.84576,38.99354],"type":"Point"}
}