{
  "type": "Feature",
  "properties": {
    "gn:gn_country":"GR",
    "gn:gn_fcode":"PPL",
    "gn:gn_pop":0,
    "iso:country":"GR",
    "name:ara_x_preferred":[
        "\u0623\u064a\u062f\u064a\u0628\u0633\u0648\u0633\u060c \u0625\u0641\u0641\u0648\u064a\u0627"
    ],
    "name:dut_x_preferred":[
        "Aidipsos"
    ],
    "name:eng_x_preferred":[
        "Aidipsos"
    ],
    "name:fre_x_preferred":[
        "Edipsos"
    ],
    "name:ger_x_preferred":[
        "Edipsos"
    ],
    "name:gre_x_preferred":[
        "\u0391\u03b9\u03b4\u03b7\u03c8\u03cc\u03c2 \u0395\u03cd\u03b2\u03bf\u03b9\u03b1\u03c2"
    ],
    "name:ita_x_preferred":[
        "Aidipsos"
    ],
    "name:jpn_x_preferred":[
        "\u30a8\u30c7\u30a3\u30d7\u30bd\u30b9"
    ],
    "name:lat_x_preferred":[
        "Aedepsus"
    ],
    "name:nno_x_preferred":[
        "Edips\u00f3s"
    ],
    "name:rus_x_preferred":[
        "\u042d\u0434\u0438\u043f\u0441\u043e\u0441"
    ],
    "name:spa_x_preferred":[
        "Edepso"
    ],
    "name:swe_x_preferred":[
        "Aidips\u00f3s"
    ],
    "name:ukr_x_preferred":[
        "\u0415\u0434\u0456\u043f\u0441\u043e\u0441"
    ],
    "qs_pg:aaroncc":"GR",
    "qs_pg:gn_country":"GR",
    "qs_pg:gn_fcode":"PPL",
    "qs_pg:gn_pop":0,
    "qs_pg:name":"Aedipsos",
    "qs_pg:name_adm0":"\u0395\u03bb\u03bb\u03ac\u03b4\u03b1",
    "qs_pg:name_adm1":"Thessaly and Continental Greece",
    "qs_pg:photos_9k":1,
    "qs_pg:photos_9r":3,
    "qs_pg:photos_all":135,
    "qs_pg:photos_sr":0,
    "qs_pg:pop_sr":0,
    "qs_pg:qs_pg_placetype":"locality",
    "qs_pg:qs_pg_placetype_gp":"Town",
    "qs_pg:woe_adm0":23424833,
    "woe:adm0_id":23424833,
    "woe:name_adm0":"\u0395\u03bb\u03bb\u03ac\u03b4\u03b1",
    "woe:name_adm1":"Thessaly and Continental Greece",
    "woe:placetype":"Town",
    "wof:name":"Aedipsos",
    "wof:placetype":"locality"
},
  "geometry": {"coordinates":[23.04588,38.88054],"type":"Point"}
}