{
  "type": "Feature",
  "properties": {
    "gn:admin1_code":"ESYE24",
    "gn:admin2_code":"29.0",
    "gn:admin3_code":"9162",
    "gn:asciiname":"Mesopotamia",
    "gn:country_code":"GR",
    "gn:dem":111,
    "gn:feature_class":"P",
    "gn:feature_code":"PPL",
    "gn:name":"Mesopotami\u00e1",
    "gn:population":377,
    "gn:timezone":"Europe/Athens",
    "iso:country":"GR",
    "name:ell_x_historical":[
        "\u03a7\u03b1\u03bb\u03af\u03bb\u03b7"
    ],
    "name:ell_x_preferred":[
        "\u039c\u03b5\u03c3\u03bf\u03c0\u03bf\u03c4\u03b1\u03bc\u03b9\u03ac"
    ],
    "name:ell_x_variant":[
        "\u03a7\u03b1\u03bb\u03af\u03bb\u03b7",
        "\u039c\u03b5\u03c3\u03bf\u03c0\u03bf\u03c4\u03b1\u03bc\u03af\u03b1"
    ],
    "name:eng_x_preferred":[
        "Mesopotamia"
    ],
    "name:und_x_variant":[
        "Khal\u00edli",
        "Mesopotami\u00e1"
    ],
    "wof:name":"Mesopotamia",
    "wof:placetype":"locality",
    "wof:population":377
},
  "geometry": {"coordinates":[22.16599,38.92436],"type":"Point"}
}