{
  "type": "Feature",
  "properties": {
    "gn:admin1_code":"ESYE11",
    "gn:admin2_code":"1.0",
    "gn:admin3_code":"9007",
    "gn:asciiname":"Sitaria",
    "gn:country_code":"GR",
    "gn:dem":113,
    "gn:feature_class":"P",
    "gn:feature_code":"PPL",
    "gn:name":"Sitari\u00e1",
    "gn:population":0,
    "gn:timezone":"Europe/Athens",
    "iso:country":"GR",
    "name:bul_x_preferred":[
        "\u0420\u043e\u0441\u0435\u043d"
    ],
    "name:ceb_x_preferred":[
        "Sitari\u00e1"
    ],
    "name:ell_x_preferred":[
        "Sitari\u00e1"
    ],
    "name:ell_x_variant":[
        "\u03a3\u03b9\u03c4\u03b1\u03c1\u03b9\u03ac",
        "\u03a3\u03b9\u03c4\u03b1\u03c1\u03b9\u03ac \u03a6\u03bb\u03ce\u03c1\u03b9\u03bd\u03b1\u03c2"
    ],
    "name:mkd_x_preferred":[
        "\u0420\u043e\u0441\u0435\u043d"
    ],
    "name:srp_x_preferred":[
        "\u0420\u043e\u0441\u0435\u043d"
    ],
    "wof:name":"Sitaria",
    "wof:placetype":"locality"
},
  "geometry": {"coordinates":[26.40299000000001,41.44879],"type":"Point"}
}