{
  "type": "Feature",
  "properties": {
    "gn:country":"GR",
    "gn:fcode":"PPL",
    "gn:population":11886,
    "iso:country":"GR",
    "name:ara_x_preferred":[
        "\u0646\u064a\u0627 \u0647\u0627\u0644\u064a\u0643\u0627\u0631\u0646\u0627\u0633\u0648\u0633"
    ],
    "name:arz_x_preferred":[
        "\u0646\u064a\u0627 \u0647\u0627\u0644\u064a\u0643\u0627\u0631\u0646\u0627\u0633\u0648\u0633"
    ],
    "name:ast_x_preferred":[
        "Nea Alikarnassos"
    ],
    "name:ceb_x_preferred":[
        "N\u00e9a Alikarnass\u00f3s"
    ],
    "name:deu_x_preferred":[
        "Nea Alikarnassos"
    ],
    "name:ell_x_preferred":[
        "\u039d\u03ad\u03b1 \u0391\u03bb\u03b9\u03ba\u03b1\u03c1\u03bd\u03b1\u03c3\u03c3\u03cc\u03c2"
    ],
    "name:ell_x_variant":[
        "N\u00e9a Alikarnas\u00f3s",
        "\u039d\u03ad\u03b1 \u0391\u03bb\u03b9\u03ba\u03b1\u03c1\u03bd\u03b1\u03c3\u03c3\u03cc\u03c2 \u0397\u03c1\u03b1\u03ba\u03bb\u03b5\u03af\u03bf\u03c5"
    ],
    "name:eng_x_preferred":[
        "Nea Alikarnassos"
    ],
    "name:fin_x_preferred":[
        "N\u00e9a Alikarnass\u00f3s"
    ],
    "name:fra_x_preferred":[
        "N\u00e9a Alikarnass\u00f3s"
    ],
    "name:hun_x_preferred":[
        "N\u00e9a Alikarnasz\u00f3sz"
    ],
    "name:ita_x_preferred":[
        "Nea Alikarnassos"
    ],
    "name:nld_x_preferred":[
        "Nea Alikarnassos"
    ],
    "name:nno_x_preferred":[
        "N\u00e9a Alikarnass\u00f3s"
    ],
    "name:por_x_preferred":[
        "N\u00e9a Alicarnass\u00f3s"
    ],
    "name:swe_x_preferred":[
        "N\u00e9a Alikarnass\u00f3s"
    ],
    "name:und_x_variant":[
        "Alikarnass\u00f3s"
    ],
    "name:urd_x_preferred":[
        "\u0646\u06cc\u0627 \u0622\u0644\u06cc\u06a9\u0627\u0631\u0646\u0627\u0633\u0648\u0633"
    ],
    "qs_pg:aaroncc":"GR",
    "qs_pg:gn_country":"GR",
    "qs_pg:gn_fcode":"PPL",
    "qs_pg:gn_pop":11886,
    "qs_pg:name":"Nea Alikarnasos",
    "qs_pg:name_adm0":"\u0395\u03bb\u03bb\u03ac\u03b4\u03b1",
    "qs_pg:name_adm1":"Crete",
    "qs_pg:photos":141,
    "qs_pg:photos_1k":29,
    "qs_pg:photos_9k":1,
    "qs_pg:photos_9r":3,
    "qs_pg:photos_all":141,
    "qs_pg:photos_sr":3,
    "qs_pg:pop_sr":6,
    "qs_pg:qs_pg_placetype":"locality",
    "qs_pg:qs_pg_placetype_gp":"Town",
    "qs_pg:woe_adm0":23424833,
    "woe:adm0_id":23424833,
    "woe:name_adm0":"\u0395\u03bb\u03bb\u03ac\u03b4\u03b1",
    "woe:name_adm1":"Crete",
    "woe:placetype":"Town",
    "wof:name":"Nea Alikarnasos",
    "wof:placetype":"locality",
    "wof:population":11886
},
  "geometry": {"coordinates":[25.15895,35.33977],"type":"Point"}
}