{
  "type": "Feature",
  "properties": {
    "gn:admin1_code":"ESYE43",
    "gn:admin2_code":"43.0",
    "gn:admin3_code":"9319",
    "gn:asciiname":"Kalamitsi Alexandrou",
    "gn:country_code":"GR",
    "gn:dem":149,
    "gn:feature_class":"P",
    "gn:feature_code":"PPL",
    "gn:name":"Kalam\u00edtsi Alex\u00e1ndrou",
    "gn:population":0,
    "gn:timezone":"Europe/Athens",
    "iso:country":"GR",
    "name:ell_x_preferred":[
        "Kalam\u00edtsi Alex\u00e1ndrou"
    ],
    "name:ell_x_variant":[
        "\u039a\u03b1\u03bb\u03b1\u03bc\u03af\u03c4\u03c3\u03b9 \u0391\u03bb\u03b5\u03be\u03ac\u03bd\u03b4\u03c1\u03bf\u03c5",
        "\u039a\u03b1\u03bb\u03b1\u03bc\u03af\u03c4\u03c3\u03b9\u03bf\u03bd \u0391\u03bb\u03b5\u03be\u03ac\u03bd\u03b4\u03c1\u03bf\u03c5"
    ],
    "name:und_x_variant":[
        "Kalam\u00edtsi Al\u00e9xandros",
        "Kalam\u00edtsion Alex\u00e1ndrou"
    ],
    "wof:name":"Kalamitsi Alexandrou",
    "wof:placetype":"locality"
},
  "geometry": {"coordinates":[24.2202,35.38174],"type":"Point"}
}