{
  "type": "Feature",
  "properties": {
    "gn:admin1_code":"ESYE43",
    "gn:admin2_code":"43.0",
    "gn:admin3_code":"9323",
    "gn:asciiname":"Peristeri",
    "gn:country_code":"GR",
    "gn:dem":114,
    "gn:feature_class":"P",
    "gn:feature_code":"PPL",
    "gn:name":"Perist\u00e9ri",
    "gn:population":0,
    "gn:timezone":"Europe/Athens",
    "iso:country":"GR",
    "name:ara_x_preferred":[
        "\u0628\u064a\u0631\u064a\u0633\u062a\u064a\u0631\u064a"
    ],
    "name:ast_x_preferred":[
        "Peristeri"
    ],
    "name:bul_x_preferred":[
        "\u041f\u0435\u0440\u0438\u0441\u0442\u0435\u0440\u0438"
    ],
    "name:cat_x_preferred":[
        "Peristeri"
    ],
    "name:ceb_x_preferred":[
        "Perist\u00e9ri"
    ],
    "name:deu_x_preferred":[
        "Peristeri"
    ],
    "name:ell_x_preferred":[
        "Perist\u00e9ri"
    ],
    "name:ell_x_variant":[
        "\u03a0\u03b5\u03c1\u03b9\u03c3\u03c4\u03ad\u03c1\u03b9",
        "\u03a0\u03b5\u03c1\u03b9\u03c3\u03c4\u03ad\u03c1\u03b9 \u0391\u03c4\u03c4\u03b9\u03ba\u03ae\u03c2"
    ],
    "name:eus_x_preferred":[
        "Peristeri"
    ],
    "name:fas_x_preferred":[
        "\u067e\u0631\u06cc\u0633\u062a\u0631\u06cc"
    ],
    "name:fin_x_preferred":[
        "Perist\u00e9ri"
    ],
    "name:fra_x_preferred":[
        "Perist\u00e9ri"
    ],
    "name:hun_x_preferred":[
        "Periszt\u00e9ri"
    ],
    "name:ind_x_preferred":[
        "Peristeri"
    ],
    "name:ita_x_preferred":[
        "Peristeri"
    ],
    "name:kor_x_preferred":[
        "\ud398\ub9ac\uc2a4\ud14c\ub9ac"
    ],
    "name:lav_x_preferred":[
        "Peristeri"
    ],
    "name:lit_x_preferred":[
        "Peristerijas"
    ],
    "name:nld_x_preferred":[
        "Peristeri"
    ],
    "name:nno_x_preferred":[
        "Perist\u00e9ri"
    ],
    "name:pol_x_preferred":[
        "Peristeri"
    ],
    "name:por_x_preferred":[
        "Peristeri"
    ],
    "name:ron_x_preferred":[
        "Peristerion"
    ],
    "name:rus_x_preferred":[
        "\u041f\u0435\u0440\u0438\u0441\u0442\u0435\u0440\u0438\u043e\u043d"
    ],
    "name:spa_x_preferred":[
        "Peristeri"
    ],
    "name:srp_x_preferred":[
        "\u041f\u0435\u0440\u0438\u0441\u0442\u0435\u0440\u0438"
    ],
    "name:swe_x_preferred":[
        "Perist\u00e9ri"
    ],
    "name:tur_x_preferred":[
        "Peristeri"
    ],
    "name:ukr_x_preferred":[
        "\u041f\u0435\u0440\u0456\u0441\u0442\u0435\u0440\u0456"
    ],
    "name:urd_x_preferred":[
        "\u067e\u06cc\u0631\u06cc\u0633\u062a\u06cc\u0631\u06cc"
    ],
    "name:vie_x_preferred":[
        "Peristeri"
    ],
    "name:vol_x_preferred":[
        "Peristeri"
    ],
    "name:war_x_preferred":[
        "Peristeri"
    ],
    "name:zho_x_preferred":[
        "\u4f69\u91cc\u65af\u7279\u91cc"
    ],
    "wof:name":"Peristeri",
    "wof:placetype":"locality"
},
  "geometry": {"coordinates":[23.79733,35.5056],"type":"Point"}
}