{
  "type": "Feature",
  "properties": {
    "gn:admin1_code":"ESYE43",
    "gn:admin2_code":"43.0",
    "gn:admin3_code":"9323",
    "gn:asciiname":"Peristeri",
    "gn:country_code":"GR",
    "gn:dem":114,
    "gn:feature_class":"P",
    "gn:feature_code":"PPL",
    "gn:name":"Perist\u00e9ri",
    "gn:population":0,
    "gn:timezone":"Europe/Athens",
    "iso:country":"GR",
    "name:ell_x_preferred":[
        "Perist\u00e9ri"
    ],
    "name:ell_x_variant":[
        "\u03a0\u03b5\u03c1\u03b9\u03c3\u03c4\u03ad\u03c1\u03b9"
    ],
    "wof:name":"Peristeri",
    "wof:placetype":"locality"
},
  "geometry": {"coordinates":[23.79733,35.5056],"type":"Point"}
}