{
  "type": "Feature",
  "properties": {
    "gn:admin1_code":"ESYE22",
    "gn:asciiname":"Kastanida",
    "gn:country_code":"GR",
    "gn:dem":197,
    "gn:feature_class":"P",
    "gn:feature_code":"PPL",
    "gn:name":"Kastan\u00edda",
    "gn:population":0,
    "gn:timezone":"Europe/Athens",
    "iso:country":"GR",
    "name:ell_x_preferred":[
        "Kastan\u00edda"
    ],
    "name:ell_x_variant":[
        "\u039a\u03b1\u03c3\u03c4\u03b1\u03bd\u03af\u03b4\u03b1"
    ],
    "wof:name":"Kastanida",
    "wof:placetype":"locality"
},
  "geometry": {"coordinates":[20.13893,39.21585],"type":"Point"}
}