{
  "type": "Feature",
  "properties": {
    "gn:admin1_code":"ESYE42",
    "gn:admin2_code":"49.0",
    "gn:admin3_code":"9290",
    "gn:asciiname":"Psarrou",
    "gn:country_code":"GR",
    "gn:dem":9,
    "gn:feature_class":"P",
    "gn:feature_code":"PPL",
    "gn:name":"Psarro\u00fa",
    "gn:population":20,
    "gn:timezone":"Europe/Athens",
    "iso:country":"GR",
    "name:ell_x_preferred":[
        "\u03a8\u03b1\u03c1\u03c1\u03bf\u03cd"
    ],
    "name:eng_x_preferred":[
        "Psarrou"
    ],
    "name:eng_x_variant":[
        "Psarroy",
        "Psarou"
    ],
    "name:pol_x_preferred":[
        "Psaru"
    ],
    "wof:name":"Psarrou",
    "wof:placetype":"locality",
    "wof:population":20
},
  "geometry": {"coordinates":[25.33645,37.41664],"type":"Point"}
}