{
  "type": "Feature",
  "properties": {
    "gn:admin1_code":"ESYE43",
    "gn:admin2_code":"45.0",
    "gn:admin3_code":"9307",
    "gn:asciiname":"Apostoloi",
    "gn:cc2":"GR",
    "gn:country_code":"GR",
    "gn:dem":351,
    "gn:feature_class":"P",
    "gn:feature_code":"PPL",
    "gn:name":"Ap\u00f3stoloi",
    "gn:population":0,
    "gn:timezone":"Europe/Athens",
    "iso:country":"GR",
    "name:und_x_variant":[
        "\u00c1no Ap\u00f3stoloi",
        "Ap\u00f3stoloi"
    ],
    "wof:name":"Apostoloi",
    "wof:placetype":"locality"
},
  "geometry": {"coordinates":[25.29868,35.21968],"type":"Point"}
}