{
  "type": "Feature",
  "properties": {
    "gn:admin1_code":"ESYE43",
    "gn:admin2_code":"45.0",
    "gn:admin3_code":"9304",
    "gn:asciiname":"Agios Ioannis",
    "gn:country_code":"GR",
    "gn:dem":7,
    "gn:feature_class":"P",
    "gn:feature_code":"PPL",
    "gn:name":"\u00c1gios Io\u00e1nnis",
    "gn:population":0,
    "gn:timezone":"Europe/Athens",
    "iso:country":"GR",
    "name:ceb_x_preferred":[
        "Agios Ioannis"
    ],
    "name:deu_x_preferred":[
        "Agios Ioannis"
    ],
    "name:ell_x_preferred":[
        "\u00c1gios Io\u00e1nnis"
    ],
    "name:ell_x_variant":[
        "\u0386\u03b3\u03b9\u03bf\u03c2 \u0399\u03c9\u03ac\u03bd\u03bd\u03b7\u03c2"
    ],
    "name:hye_x_preferred":[
        "\u0531\u0575\u0578\u057d \u0545\u0578\u0561\u0576\u056b\u057d"
    ],
    "name:sco_x_preferred":[
        "Agios Ioannis"
    ],
    "name:swe_x_preferred":[
        "Agios Ioannis"
    ],
    "wof:name":"Agios Ioannis",
    "wof:placetype":"locality"
},
  "geometry": {"coordinates":[25.05193,34.94181],"type":"Point"}
}