{
  "type": "Feature",
  "properties": {
    "gn:admin1_code":"ESYE43",
    "gn:admin2_code":"45.0",
    "gn:admin3_code":"9308.0",
    "gn:asciiname":"Neo Kalamaki",
    "gn:country_code":"GR",
    "gn:dem":27,
    "gn:feature_class":"P",
    "gn:feature_code":"PPL",
    "gn:name":"N\u00e9o Kalam\u00e1ki",
    "gn:population":27,
    "gn:timezone":"Europe/Athens",
    "iso:country":"GR",
    "name:ell_x_preferred":[
        "\u039d\u03ad\u03bf \u039a\u03b1\u03bb\u03b1\u03bc\u03ac\u03ba\u03b9"
    ],
    "name:eng_x_preferred":[
        "Neo Kalamaki"
    ],
    "wof:name":"Neo Kalamaki",
    "wof:placetype":"locality",
    "wof:population":27
},
  "geometry": {"coordinates":[24.76325,35.02536],"type":"Point"}
}