{
  "type": "Feature",
  "properties": {
    "gn:admin1_code":"ESYE21",
    "gn:admin2_code":"17.0",
    "gn:admin3_code":"9083",
    "gn:asciiname":"Sakellariko",
    "gn:country_code":"GR",
    "gn:dem":366,
    "gn:feature_class":"P",
    "gn:feature_code":"PPL",
    "gn:name":"Sakellarik\u00f3",
    "gn:population":54,
    "gn:timezone":"Europe/Athens",
    "iso:country":"GR",
    "name:ell_x_preferred":[
        "\u03a3\u03b1\u03ba\u03b5\u03bb\u03bb\u03b1\u03c1\u03b9\u03ba\u03cc"
    ],
    "name:ell_x_variant":[
        "\u039a\u03bf\u03c5\u03c4\u03c1\u03bf\u03c5\u03bb\u03ac\u03b4\u03b5\u03c2"
    ],
    "name:eng_x_preferred":[
        "Sakellariko"
    ],
    "name:eng_x_variant":[
        "Koutroulades"
    ],
    "name:und_x_variant":[
        "Koutourl\u00e1dhes",
        "Koutourl\u00e1des",
        "Koutroul\u00e1des"
    ],
    "wof:name":"Sakellariko",
    "wof:placetype":"locality",
    "wof:population":54
},
  "geometry": {"coordinates":[20.63194,39.75605],"type":"Point"}
}