{
  "type": "Feature",
  "properties": {
    "gn:admin1_code":"ESYE31",
    "gn:admin2_code":"445407.0",
    "gn:admin3_code":"9230.0",
    "gn:asciiname":"Makryammos",
    "gn:country_code":"GR",
    "gn:dem":65,
    "gn:feature_class":"P",
    "gn:feature_code":"PPL",
    "gn:name":"Makr\u00fdammos",
    "gn:population":0,
    "gn:timezone":"Europe/Athens",
    "iso:country":"GR",
    "name:ell_x_preferred":[
        "Makr\u00fdammos"
    ],
    "name:ell_x_variant":[
        "\u039c\u03b1\u03ba\u03c1\u03cd\u03b1\u03bc\u03bc\u03bf\u03c2"
    ],
    "wof:name":"Makryammos",
    "wof:placetype":"locality"
},
  "geometry": {"coordinates":[23.49587,38.04596],"type":"Point"}
}