{
  "type": "Feature",
  "properties": {
    "gn:gn_country":"GR",
    "gn:gn_fcode":"PPL",
    "gn:gn_pop":144,
    "gn:population":83,
    "iso:country":"GR",
    "name:bul_x_preferred":[
        "\u041d\u0438\u0432\u0438\u0446\u0438"
    ],
    "name:bul_x_variant":[
        "\u041f\u0441\u0430\u0440\u0430\u0434\u0435\u0441"
    ],
    "name:ell_x_historical":[
        "\u039d\u03af\u03b2\u03b9\u03c4\u03c3\u03b1",
        "\u039d\u03af\u03b2\u03b9\u03c3\u03c4\u03b1",
        "\u039d\u03af\u03b2\u03b9\u03c4\u03c3\u03b9"
    ],
    "name:ell_x_preferred":[
        "\u03a8\u03b1\u03c1\u03ac\u03b4\u03b5\u03c2"
    ],
    "name:ell_x_variant":[
        "\u039d\u03af\u03b2\u03b9\u03c4\u03c3\u03b1",
        "\u039d\u03af\u03b2\u03b9\u03c3\u03c4\u03b1",
        "\u039d\u03af\u03b2\u03b9\u03c4\u03c3\u03b9",
        "\u03a8\u03b1\u03c1\u03ac\u03b4\u03b5\u03c2 \u03a6\u03bb\u03ce\u03c1\u03b9\u03bd\u03b1\u03c2"
    ],
    "name:eng_x_historical":[
        "Nivista",
        "Nivitsa"
    ],
    "name:eng_x_preferred":[
        "Psarades"
    ],
    "name:eng_x_variant":[
        "Nivista",
        "Nivitsa"
    ],
    "name:fin_x_preferred":[
        "Psar\u00e1des"
    ],
    "name:mkd_x_preferred":[
        "\u041d\u0438\u0432\u0438\u0446\u0438"
    ],
    "name:nld_x_preferred":[
        "Psarades"
    ],
    "name:sqi_x_preferred":[
        "Nivic\u00eb"
    ],
    "name:sqi_x_variant":[
        "Nivica"
    ],
    "name:unk_x_variant":[
        "Nivici"
    ],
    "qs_pg:aaroncc":"GR",
    "qs_pg:gn_country":"GR",
    "qs_pg:gn_fcode":"PPL",
    "qs_pg:gn_pop":144,
    "qs_pg:name":"Psar\u00e1des",
    "qs_pg:photos_9r":0,
    "qs_pg:photos_sr":0,
    "qs_pg:pop_sr":1,
    "qs_pg:qs_pg_placetype":"locality",
    "wof:name":"Psar\u00e1des",
    "wof:placetype":"locality",
    "wof:population":83
},
  "geometry": {"coordinates":[21.02833,40.82917],"type":"Point"}
}