{
  "type": "Feature",
  "properties": {
    "gn:gn_country":"GR",
    "gn:gn_fcode":"PPL",
    "gn:gn_pop":106,
    "gn:population":46,
    "iso:country":"GR",
    "name:ell_x_preferred":[
        "\u0386\u03b3\u03b9\u03bf\u03c2 \u039a\u03bf\u03c3\u03bc\u03ac\u03c2"
    ],
    "name:eng_x_preferred":[
        "Agios Kosmas"
    ],
    "name:unk_x_variant":[
        "\u00c1yios Kosm\u00e1s"
    ],
    "qs_pg:aaroncc":"GR",
    "qs_pg:gn_country":"GR",
    "qs_pg:gn_fcode":"PPL",
    "qs_pg:gn_pop":106,
    "qs_pg:name":"\u00c1gios Kosm\u00e1s",
    "qs_pg:photos_9r":0,
    "qs_pg:photos_sr":0,
    "qs_pg:pop_sr":1,
    "qs_pg:qs_pg_placetype":"locality",
    "wof:name":"\u00c1gios Kosm\u00e1s",
    "wof:placetype":"locality",
    "wof:population":46
},
  "geometry": {"coordinates":[20.56861,39.9725],"type":"Point"}
}