{
  "type": "Feature",
  "properties": {
    "gn:admin1_code":"ESYE11",
    "gn:admin2_code":"1.0",
    "gn:admin3_code":"9006",
    "gn:asciiname":"Trifylli",
    "gn:country_code":"GR",
    "gn:dem":64,
    "gn:feature_class":"P",
    "gn:feature_code":"PPL",
    "gn:name":"Trif\u00fdlli",
    "gn:population":0,
    "gn:timezone":"Europe/Athens",
    "iso:country":"GR",
    "name:ell_x_preferred":[
        "Trif\u00fdlli"
    ],
    "name:ell_x_variant":[
        "\u03a4\u03c1\u03b9\u03c6\u03cd\u03bb\u03bb\u03b9",
        "Trif\u00fdllion",
        "\u03a4\u03c1\u03b9\u03c6\u03cd\u03bb\u03bb\u03b9\u03bf\u03bd"
    ],
    "name:und_x_variant":[
        "Trif\u00edlion",
        "Trif\u00edllion"
    ],
    "wof:name":"Trifylli",
    "wof:placetype":"locality"
},
  "geometry": {"coordinates":[26.20994,40.98153],"type":"Point"}
}