{
  "type": "Feature",
  "properties": {
    "gn:admin1_code":"ESYE24",
    "gn:admin2_code":"34.0",
    "gn:admin3_code":"9155",
    "gn:asciiname":"Nea Lampsakos",
    "gn:country_code":"GR",
    "gn:dem":8,
    "gn:feature_class":"P",
    "gn:feature_code":"PPL",
    "gn:name":"N\u00e9a L\u00e1mpsakos",
    "gn:population":2196,
    "gn:timezone":"Europe/Athens",
    "iso:country":"GR",
    "name:ell_x_preferred":[
        "\u039d\u03ad\u03b1 \u039b\u03ac\u03bc\u03c8\u03b1\u03ba\u03bf\u03c2"
    ],
    "name:eng_x_preferred":[
        "Nea Lampsakos"
    ],
    "wof:name":"Nea Lampsakos",
    "wof:placetype":"locality",
    "wof:population":2196
},
  "geometry": {"coordinates":[23.62824,38.43729],"type":"Point"}
}