{
  "type": "Feature",
  "properties": {
    "gn:admin1_code":"ESYE13",
    "gn:admin2_code":"11.0",
    "gn:admin3_code":"9068",
    "gn:asciiname":"Kipari",
    "gn:country_code":"GR",
    "gn:dem":745,
    "gn:feature_class":"P",
    "gn:feature_code":"PPL",
    "gn:name":"Kip\u00e1ri",
    "gn:population":0,
    "gn:timezone":"Europe/Athens",
    "iso:country":"GR",
    "name:ell_x_preferred":[
        "\u039a\u03b7\u03c0\u03ac\u03c1\u03b9"
    ],
    "name:ell_x_variant":[
        "\u039a\u03b7\u03c0\u03ac\u03c1\u03b9\u03bf\u03bd"
    ],
    "name:und_x_variant":[
        "Kip\u00e1ri",
        "Kip\u00e1rion"
    ],
    "wof:name":"Kipari",
    "wof:placetype":"locality"
},
  "geometry": {"coordinates":[21.67528,40.3266],"type":"Point"}
}