{
  "type": "Feature",
  "properties": {
    "gn:population":1628,
    "iso:country":"GR",
    "name:ara_x_preferred":[
        "\u0628\u0627\u062a\u064a\u062a\u064a\u0631\u064a"
    ],
    "name:ceb_x_preferred":[
        "Patit\u00edrion"
    ],
    "name:deu_x_preferred":[
        "Patitiri"
    ],
    "name:ell_x_preferred":[
        "\u03a0\u03b1\u03c4\u03b7\u03c4\u03ae\u03c1\u03b9\u03bf\u03bd"
    ],
    "name:ell_x_variant":[
        "\u03a0\u03b1\u03c4\u03b7\u03c4\u03ae\u03c1\u03b9",
        "\u03a0\u03b1\u03c4\u03b7\u03c4\u03ae\u03c1\u03b9 \u0391\u03bb\u03bf\u03bd\u03bd\u03ae\u03c3\u03bf\u03c5"
    ],
    "name:eng_x_preferred":[
        "Patitiri"
    ],
    "name:fin_x_preferred":[
        "Patit\u00edri"
    ],
    "name:fra_x_preferred":[
        "Patitiri"
    ],
    "name:nld_x_preferred":[
        "Patitiri"
    ],
    "name:nno_x_preferred":[
        "Patit\u00edri"
    ],
    "name:swe_x_preferred":[
        "Patit\u00edrion"
    ],
    "qs:a0":"Greece",
    "qs:a1":"*\u0398\u0395\u03a3\u03a3\u0391\u039b\u0399\u0391",
    "qs:a1_alt":"UESSALIA",
    "qs:a1r":"0",
    "qs:a2_alt":"MAGNHSIA",
    "qs:adm0":"Greece",
    "qs:la_lc":"*",
    "qs:level":"locality",
    "qs:loc":"\u03a0\u0391\u03a4\u0397\u03a4\u0397\u03a1\u0399\u039f\u039d",
    "qs:loc_alt":"PAUTHRION",
    "qs:pop":0,
    "qs:type":"buffered point",
    "wd:wordcount":53,
    "wof:name":"\u03a0\u0391\u03a4\u0397\u03a4\u0397\u03a1\u0399\u039f\u039d",
    "wof:placetype":"locality",
    "wof:population":1628
},
  "geometry": {"coordinates":[23.863568,39.144497],"type":"Point"}
}