{
  "type": "Feature",
  "properties": {
    "gn:admin1_code":"ESYE25",
    "gn:asciiname":"Pigadhion",
    "gn:cc2":"GR",
    "gn:country_code":"GR",
    "gn:dem":38,
    "gn:feature_class":"P",
    "gn:feature_code":"PPL",
    "gn:name":"Pig\u00e1dhion",
    "gn:population":0,
    "gn:timezone":"Europe/Athens",
    "iso:country":"GR",
    "name:und_x_variant":[
        "K\u00f3kla",
        "Ko\u00fala",
        "Pig\u00e1dhi",
        "Pig\u00e1dhion"
    ],
    "wof:name":"Pigadhion",
    "wof:placetype":"locality"
},
  "geometry": {"coordinates":[21.39227,37.90743],"type":"Point"}
}