{
  "type": "Feature",
  "properties": {
    "iso:country":"GR",
    "name:ceb_x_preferred":[
        "Kalamaki"
    ],
    "name:deu_x_preferred":[
        "Kalamaki"
    ],
    "name:ell_x_preferred":[
        "\u039a\u03b1\u03bb\u03b1\u03bc\u03ac\u03ba\u03b9"
    ],
    "name:ita_x_preferred":[
        "Kalamaki"
    ],
    "name:rus_x_preferred":[
        "\u041a\u0430\u043b\u0430\u043c\u0430\u043a\u0438\u043e\u043d"
    ],
    "name:swe_x_preferred":[
        "Kalamaki"
    ],
    "qs_pg:aaroncc":"GR",
    "qs_pg:name":"Kalamaki",
    "qs_pg:name_adm0":"\u0395\u03bb\u03bb\u03ac\u03b4\u03b1",
    "qs_pg:name_adm1":"Crete",
    "qs_pg:photos":532,
    "qs_pg:photos_1k":108,
    "qs_pg:photos_9k":2,
    "qs_pg:photos_9r":5,
    "qs_pg:photos_all":532,
    "qs_pg:photos_sr":7,
    "qs_pg:pop_sr":0,
    "qs_pg:qs_pg_placetype":"locality",
    "qs_pg:qs_pg_placetype_gp":"Town",
    "qs_pg:woe_adm0":23424833,
    "woe:adm0_id":23424833,
    "woe:name_adm0":"\u0395\u03bb\u03bb\u03ac\u03b4\u03b1",
    "woe:name_adm1":"Crete",
    "woe:placetype":"Town",
    "wof:name":"Kalamaki",
    "wof:placetype":"locality"
},
  "geometry": {"coordinates":[23.969035,35.513155],"type":"Point"}
}