{
  "type": "Feature",
  "properties": {
    "gn:admin1_code":"ESYE43",
    "gn:admin2_code":"43.0",
    "gn:admin3_code":"9323",
    "gn:asciiname":"Kato Kefala",
    "gn:country_code":"GR",
    "gn:dem":290,
    "gn:feature_class":"P",
    "gn:feature_code":"PPL",
    "gn:name":"K\u00e1to Kef\u00e1la",
    "gn:population":0,
    "gn:timezone":"Europe/Athens",
    "iso:country":"GR",
    "name:ell_x_preferred":[
        "K\u00e1to Kef\u00e1la"
    ],
    "name:ell_x_variant":[
        "\u039a\u03ac\u03c4\u03c9 \u039a\u03b5\u03c6\u03ac\u03bb\u03b1"
    ],
    "wof:name":"Kato Kefala",
    "wof:placetype":"locality"
},
  "geometry": {"coordinates":[23.79013,35.44407],"type":"Point"}
}