{
  "type": "Feature",
  "properties": {
    "gn:gn_country":"GR",
    "gn:gn_fcode":"PPL",
    "gn:gn_pop":194,
    "gn:population":86,
    "iso:country":"GR",
    "name:ell_x_preferred":[
        "\u039a\u03b1\u03c3\u03c4\u03b5\u03bb\u03bb\u03ac\u03bd\u03bf\u03b9 \u0393\u03cd\u03c1\u03bf\u03c5"
    ],
    "name:ell_x_variant":[
        "\u039a\u03b1\u03c3\u03c4\u03b5\u03bb\u03bb\u03ac\u03bd\u03bf\u03b9 \u0391\u03b3\u03af\u03bf\u03c5 \u0393\u03b5\u03c9\u03c1\u03b3\u03af\u03bf\u03c5",
        "\u039a\u03b1\u03c3\u03c4\u03b5\u03bb\u03bb\u03ac\u03bd\u03bf\u03b9"
    ],
    "name:eng_x_preferred":[
        "Kastellanoi Gyrou"
    ],
    "name:eng_x_variant":[
        "Kastellanoi Agiou Georgiou"
    ],
    "name:unk_x_variant":[
        "G\u00fdrou"
    ],
    "qs_pg:aaroncc":"GR",
    "qs_pg:gn_country":"GR",
    "qs_pg:gn_fcode":"PPL",
    "qs_pg:gn_pop":194,
    "qs_pg:name":"Kastell\u00e1noi",
    "qs_pg:photos_9r":0,
    "qs_pg:photos_sr":0,
    "qs_pg:pop_sr":1,
    "qs_pg:qs_pg_placetype":"locality",
    "wof:name":"Kastell\u00e1noi",
    "wof:placetype":"locality",
    "wof:population":86
},
  "geometry": {"coordinates":[19.7325,39.70889],"type":"Point"}
}