{
  "type": "Feature",
  "properties": {
    "gn:gn_country":"GR",
    "gn:gn_fcode":"ADM3",
    "gn:gn_pop":2488,
    "gn:population":2488,
    "iso:country":"GR",
    "name:ell_x_preferred":[
        "\u0391\u03c1\u03b3\u03b9\u03b8\u03ad\u03b1\u03c2"
    ],
    "qs_pg:aaroncc":"GR",
    "qs_pg:gn_country":"GR",
    "qs_pg:gn_fcode":"ADM3",
    "qs_pg:gn_pop":2488,
    "qs_pg:name":"Dimos Argithea",
    "qs_pg:photos_9r":0,
    "qs_pg:photos_sr":0,
    "qs_pg:pop_sr":4,
    "qs_pg:qs_pg_placetype":"localadmin",
    "wof:name":"Dimos Argithea",
    "wof:placetype":"localadmin",
    "wof:population":2488
},
  "geometry": {"coordinates":[21.48588,39.29296],"type":"Point"}
}