{
  "type": "Feature",
  "properties": {
    "gn:gn_country":"GR",
    "gn:gn_fcode":"PPL",
    "gn:gn_pop":1616,
    "gn:population":693,
    "iso:country":"GR",
    "name:ell_x_historical":[
        "\u0391\u03b6\u03af\u03b6\u03b9"
    ],
    "name:ell_x_preferred":[
        "\u039a\u03ac\u03c4\u03c9 \u0386\u03c3\u03c3\u03bf\u03c2"
    ],
    "name:ell_x_variant":[
        "\u0391\u03b6\u03af\u03b6\u03b9"
    ],
    "name:eng_x_preferred":[
        "Kato Assos"
    ],
    "name:unk_x_variant":[
        "Az\u00edzion"
    ],
    "qs_pg:aaroncc":"GR",
    "qs_pg:gn_country":"GR",
    "qs_pg:gn_fcode":"PPL",
    "qs_pg:gn_pop":1616,
    "qs_pg:name":"Kato Assos",
    "qs_pg:name_adm0":"\u0395\u03bb\u03bb\u03ac\u03b4\u03b1",
    "qs_pg:name_adm1":"Peloponnese Western Greece and the Ionian Islands",
    "qs_pg:photos_9k":1,
    "qs_pg:photos_9r":4,
    "qs_pg:photos_all":184,
    "qs_pg:photos_sr":0,
    "qs_pg:pop_sr":3,
    "qs_pg:qs_pg_placetype":"locality",
    "qs_pg:qs_pg_placetype_gp":"Town",
    "qs_pg:woe_adm0":23424833,
    "woe:adm0_id":23424833,
    "woe:name_adm0":"\u0395\u03bb\u03bb\u03ac\u03b4\u03b1",
    "woe:name_adm1":"Peloponnese Western Greece and the Ionian Islands",
    "woe:placetype":"Town",
    "wof:name":"Kato Assos",
    "wof:placetype":"locality",
    "wof:population":693
},
  "geometry": {"coordinates":[22.83333,37.95],"type":"Point"}
}