{
  "type": "Feature",
  "properties": {
    "gn:country":"GR",
    "gn:fcode":"PPL",
    "gn:population":22,
    "iso:country":"GR",
    "name:ell_x_preferred":[
        "\u039c\u03b1\u03c1\u03b1\u03b8\u03ad\u03b1"
    ],
    "name:eng_x_preferred":[
        "Marathea"
    ],
    "name:und_x_variant":[
        "Marathi\u00e1"
    ],
    "qs_pg:aaroncc":"GR",
    "qs_pg:gn_country":"GR",
    "qs_pg:gn_fcode":"PPL",
    "qs_pg:gn_pop":22,
    "qs_pg:name":"Marath\u00e9a",
    "qs_pg:photos_9r":0,
    "qs_pg:photos_sr":0,
    "qs_pg:pop_sr":1,
    "qs_pg:qs_pg_placetype":"locality",
    "wof:name":"Marath\u00e9a",
    "wof:placetype":"locality",
    "wof:population":20
},
  "geometry": {"coordinates":[22.91667,37.55],"type":"Point"}
}