{
  "type": "Feature",
  "properties": {
    "gn:admin1_code":"ESYE43",
    "gn:admin2_code":"45.0",
    "gn:admin3_code":"9308.0",
    "gn:asciiname":"Afrathias",
    "gn:country_code":"GR",
    "gn:dem":2,
    "gn:feature_class":"P",
    "gn:feature_code":"PPL",
    "gn:name":"Afrathi\u00e1s",
    "gn:population":35,
    "gn:timezone":"Europe/Athens",
    "iso:country":"GR",
    "name:ell_x_preferred":[
        "\u0391\u03c6\u03c1\u03b1\u03b8\u03b9\u03ac\u03c2"
    ],
    "name:eng_x_preferred":[
        "Afrathias"
    ],
    "wof:name":"Afrathias",
    "wof:placetype":"locality",
    "wof:population":35
},
  "geometry": {"coordinates":[24.75763,35.04899],"type":"Point"}
}