{
  "type": "Feature",
  "properties": {
    "gn:admin1_code":"ESYE23",
    "gn:admin2_code":"31.0",
    "gn:admin3_code":"9128",
    "gn:asciiname":"Elatou",
    "gn:cc2":"GR",
    "gn:country_code":"GR",
    "gn:dem":1020,
    "gn:feature_class":"P",
    "gn:feature_code":"PPL",
    "gn:name":"Elato\u00fa",
    "gn:population":0,
    "gn:timezone":"Europe/Athens",
    "iso:country":"GR",
    "name:und_x_variant":[
        "Eletso\u00fa",
        "Elatso\u00fa"
    ],
    "wof:name":"Elatou",
    "wof:placetype":"locality"
},
  "geometry": {"coordinates":[21.97669,38.58474],"type":"Point"}
}