{
  "type": "Feature",
  "properties": {
    "gn:admin1_code":"ESYE24",
    "gn:admin2_code":"34.0",
    "gn:admin3_code":"9148",
    "gn:asciiname":"Limnionas",
    "gn:cc2":"GR",
    "gn:country_code":"GR",
    "gn:dem":12,
    "gn:feature_class":"P",
    "gn:feature_code":"PPL",
    "gn:name":"Limni\u00f3nas",
    "gn:population":0,
    "gn:timezone":"Europe/Athens",
    "iso:country":"GR",
    "name:und_x_variant":[
        "Limi\u00f3nas",
        "Limni\u00f3nas"
    ],
    "wof:name":"Limnionas",
    "wof:placetype":"locality"
},
  "geometry": {"coordinates":[23.75244,38.71185],"type":"Point"}
}