{
  "type": "Feature",
  "properties": {
    "gn:admin1_code":"ESYE24",
    "gn:admin2_code":"34.0",
    "gn:admin3_code":"9151",
    "gn:asciiname":"Plagia",
    "gn:country_code":"GR",
    "gn:dem":345,
    "gn:feature_class":"P",
    "gn:feature_code":"PPL",
    "gn:name":"Plagi\u00e1",
    "gn:population":0,
    "gn:timezone":"Europe/Athens",
    "iso:country":"GR",
    "name:ell_x_preferred":[
        "Plagi\u00e1"
    ],
    "name:ell_x_variant":[
        "\u03a0\u03bb\u03b1\u03b3\u03b9\u03ac"
    ],
    "name:und_x_variant":[
        "Playi\u00e1"
    ],
    "wof:name":"Plagia",
    "wof:placetype":"locality"
},
  "geometry": {"coordinates":[24.37631,38.14981],"type":"Point"}
}