{
  "type": "Feature",
  "properties": {
    "gn:admin1_code":"ESYE22",
    "gn:admin2_code":"25.0",
    "gn:admin3_code":"9118",
    "gn:asciiname":"Podoriones",
    "gn:cc2":"GR",
    "gn:country_code":"GR",
    "gn:dem":123,
    "gn:feature_class":"P",
    "gn:feature_code":"PPL",
    "gn:name":"Podori\u00f3nes",
    "gn:population":0,
    "gn:timezone":"Europe/Athens",
    "iso:country":"GR",
    "name:und_x_variant":[
        "Pandori\u00f3nes",
        "Pondori\u00f3nes"
    ],
    "wof:name":"Podoriones",
    "wof:placetype":"locality"
},
  "geometry": {"coordinates":[20.08861,39.37833],"type":"Point"}
}