{
  "type": "Feature",
  "properties": {
    "gn:gn_country":"GR",
    "gn:gn_fcode":"PPL",
    "gn:gn_pop":0,
    "gn:population":681,
    "iso:country":"GR",
    "name:ell_x_preferred":[
        "\u03a0\u03b1\u03c1\u03b1\u03bb\u03af\u03b1 \u0394\u03b9\u03bf\u03bd\u03c5\u03c3\u03af\u03bf\u03c5"
    ],
    "name:eng_x_preferred":[
        "Paralia Dionysiou"
    ],
    "qs_pg:aaroncc":"GR",
    "qs_pg:gn_country":"GR",
    "qs_pg:gn_fcode":"PPL",
    "qs_pg:gn_pop":0,
    "qs_pg:name":"Paralia Dionysiou",
    "qs_pg:name_adm0":"\u0395\u03bb\u03bb\u03ac\u03b4\u03b1",
    "qs_pg:name_adm1":"Macedonia and Thrace",
    "qs_pg:photos":54,
    "qs_pg:photos_1k":11,
    "qs_pg:photos_9k":1,
    "qs_pg:photos_9r":2,
    "qs_pg:photos_all":54,
    "qs_pg:photos_sr":2,
    "qs_pg:pop_sr":0,
    "qs_pg:qs_pg_placetype":"locality",
    "qs_pg:qs_pg_placetype_gp":"Town",
    "qs_pg:woe_adm0":23424833,
    "woe:adm0_id":23424833,
    "woe:name_adm0":"\u0395\u03bb\u03bb\u03ac\u03b4\u03b1",
    "woe:name_adm1":"Macedonia and Thrace",
    "woe:placetype":"Town",
    "wof:name":"Paralia Dionysiou",
    "wof:placetype":"locality",
    "wof:population":681
},
  "geometry": {"coordinates":[23.24982,40.25045],"type":"Point"}
}