{
  "type": "Feature",
  "properties": {
    "gn:admin1_code":"ESYE22",
    "gn:admin2_code":"25.0",
    "gn:admin3_code":"9118",
    "gn:asciiname":"Vasilika Agiou Ioannou",
    "gn:country_code":"GR",
    "gn:dem":53,
    "gn:feature_class":"P",
    "gn:feature_code":"PPL",
    "gn:name":"Vasilik\u00e1 Ag\u00edou Io\u00e1nnou",
    "gn:population":278,
    "gn:timezone":"Europe/Athens",
    "iso:country":"GR",
    "name:ell_x_preferred":[
        "\u0392\u03b1\u03c3\u03b9\u03bb\u03b9\u03ba\u03ac \u0391\u03b3\u03af\u03bf\u03c5 \u0399\u03c9\u03ac\u03bd\u03bd\u03bf\u03c5"
    ],
    "name:eng_x_preferred":[
        "Vasilika Agiou Ioannou"
    ],
    "wof:name":"Vasilika Agiou Ioannou",
    "wof:placetype":"locality",
    "wof:population":278
},
  "geometry": {"coordinates":[19.82856,39.62063],"type":"Point"}
}