{
  "type": "Feature",
  "properties": {
    "gn:admin1_code":"ESYE31",
    "gn:admin2_code":"445406.0",
    "gn:admin3_code":"9227",
    "gn:asciiname":"Neo Sykamino",
    "gn:country_code":"GR",
    "gn:dem":93,
    "gn:feature_class":"P",
    "gn:feature_code":"PPL",
    "gn:name":"N\u00e9o Syk\u00e1mino",
    "gn:population":272,
    "gn:timezone":"Europe/Athens",
    "iso:country":"GR",
    "name:ell_x_preferred":[
        "\u039d\u03ad\u03bf \u03a3\u03c5\u03ba\u03ac\u03bc\u03b9\u03bd\u03bf"
    ],
    "name:eng_x_preferred":[
        "Neo Sykamino"
    ],
    "wof:name":"Neo Sykamino",
    "wof:placetype":"locality",
    "wof:population":272
},
  "geometry": {"coordinates":[23.70099,38.31691],"type":"Point"}
}