{
  "type": "Feature",
  "properties": {
    "gn:admin1_code":"ESYE43",
    "gn:admin2_code":"44.0",
    "gn:admin3_code":"9317",
    "gn:asciiname":"Pasalitai",
    "gn:cc2":"GR",
    "gn:country_code":"GR",
    "gn:dem":289,
    "gn:feature_class":"P",
    "gn:feature_code":"PPL",
    "gn:name":"Pasal\u00edtai",
    "gn:population":0,
    "gn:timezone":"Europe/Athens",
    "iso:country":"GR",
    "name:und_x_variant":[
        "Pasal\u00edtes",
        "Pasal\u00edtai"
    ],
    "wof:name":"Pasalitai",
    "wof:placetype":"locality"
},
  "geometry": {"coordinates":[24.71907,35.33991],"type":"Point"}
}