{
  "type": "Feature",
  "properties": {
    "gn:country":"GR",
    "gn:fcode":"PPL",
    "gn:population":77,
    "iso:country":"GR",
    "name:ell_x_preferred":[
        "\u039a\u03bf\u03bc\u03bd\u03ae\u03bd\u03b5\u03b9\u03bf"
    ],
    "name:ell_x_variant":[
        "\u039a\u03bf\u03bc\u03bd\u03ae\u03bd\u03b5\u03b9\u03bf\u03bd"
    ],
    "name:und_x_variant":[
        "Komn\u00edneio"
    ],
    "qs_pg:aaroncc":"GR",
    "qs_pg:gn_country":"GR",
    "qs_pg:gn_fcode":"PPL",
    "qs_pg:gn_pop":77,
    "qs_pg:name":"Komnineio",
    "qs_pg:name_adm0":"\u0395\u03bb\u03bb\u03ac\u03b4\u03b1",
    "qs_pg:name_adm1":"Macedonia and Thrace",
    "qs_pg:photos_9k":1,
    "qs_pg:photos_9r":1,
    "qs_pg:photos_all":1,
    "qs_pg:photos_sr":0,
    "qs_pg:pop_sr":1,
    "qs_pg:qs_pg_placetype":"locality",
    "qs_pg:qs_pg_placetype_gp":"Town",
    "qs_pg:woe_adm0":23424833,
    "woe:adm0_id":23424833,
    "woe:name_adm0":"\u0395\u03bb\u03bb\u03ac\u03b4\u03b1",
    "woe:name_adm1":"Macedonia and Thrace",
    "woe:placetype":"Town",
    "wof:name":"Komnineio",
    "wof:placetype":"locality",
    "wof:population":77
},
  "geometry": {"coordinates":[22.16444,40.51861],"type":"Point"}
}