{
  "type": "Feature",
  "properties": {
    "gn:admin1_code":"ESYE25",
    "gn:admin2_code":"42.0",
    "gn:admin3_code":"9248",
    "gn:asciiname":"Steros",
    "gn:country_code":"GR",
    "gn:dem":274,
    "gn:feature_class":"P",
    "gn:feature_code":"PPL",
    "gn:name":"Steros",
    "gn:population":0,
    "gn:timezone":"Europe/Athens",
    "iso:country":"GR",
    "name:und_x_variant":[
        "Stavr\u00f3s"
    ],
    "wof:name":"Steros",
    "wof:placetype":"locality"
},
  "geometry": {"coordinates":[22.41828,36.68492],"type":"Point"}
}