{
  "type": "Feature",
  "properties": {
    "gn:population":1556,
    "iso:country":"GR",
    "name:ast_x_preferred":[
        "Andros"
    ],
    "name:ceb_x_preferred":[
        "Andros"
    ],
    "name:ces_x_preferred":[
        "Andros"
    ],
    "name:deu_x_preferred":[
        "Verwaltungsgliederung von Andros"
    ],
    "name:deu_x_variant":[
        "Andros"
    ],
    "name:ell_x_preferred":[
        "\u0386\u03bd\u03b4\u03c1\u03bf\u03c2"
    ],
    "name:ell_x_variant":[
        "\u0391\u039d\u0394\u03a1\u039f\u03a5"
    ],
    "name:eng_x_preferred":[
        "Andros"
    ],
    "name:est_x_preferred":[
        "\u00c1ndros"
    ],
    "name:fas_x_preferred":[
        "\u0622\u0646\u062f\u0631\u0648\u0633"
    ],
    "name:fin_x_preferred":[
        "\u00c1ndros"
    ],
    "name:fra_x_preferred":[
        "\u00c1ndros"
    ],
    "name:ita_x_preferred":[
        "Chora Andros"
    ],
    "name:jpn_x_preferred":[
        "\u30a2\u30f3\u30c9\u30ed\u30b9"
    ],
    "name:lat_x_preferred":[
        "Andros"
    ],
    "name:nld_x_preferred":[
        "Andros"
    ],
    "name:nno_x_preferred":[
        "\u00c1ndros by"
    ],
    "name:pol_x_preferred":[
        "Jednostka regionalna Andros"
    ],
    "name:rus_x_preferred":[
        "\u0410\u043d\u0434\u0440\u043e\u0441"
    ],
    "name:srp_x_preferred":[
        "\u0410\u043d\u0434\u0440\u043e\u0441"
    ],
    "name:und_x_variant":[
        "K\u00e1stron"
    ],
    "qs:a0":"Greece",
    "qs:a1":"*\u039d\u039f\u03a4\u0399\u039f \u0391\u0399\u0393\u0391\u0399\u039f",
    "qs:a1_alt":"NOTIO AIGAIO",
    "qs:a1r":"0",
    "qs:a2_alt":"KYKLADES",
    "qs:adm0":"Greece",
    "qs:la_lc":"*",
    "qs:level":"locality",
    "qs:loc":"\u0391\u039d\u0394\u03a1\u039f\u03a3",
    "qs:loc_alt":"ANDROS",
    "qs:pop":0,
    "qs:type":"buffered point",
    "wof:name":"\u0391\u039d\u0394\u03a1\u039f\u03a3",
    "wof:placetype":"locality",
    "wof:population":1556
},
  "geometry": {"coordinates":[24.93727,37.836798],"type":"Point"}
}