{
  "type": "Feature",
  "properties": {
    "gn:admin1_code":"ESYE23",
    "gn:admin2_code":"39.0",
    "gn:admin3_code":"9136",
    "gn:asciiname":"Karmion",
    "gn:country_code":"GR",
    "gn:dem":489,
    "gn:feature_class":"P",
    "gn:feature_code":"PPL",
    "gn:name":"K\u00e1rmion",
    "gn:population":21,
    "gn:timezone":"Europe/Athens",
    "iso:country":"GR",
    "name:ell_x_preferred":[
        "\u039a\u03ac\u03c1\u03bc\u03b9\u03bf"
    ],
    "name:eng_x_preferred":[
        "Karmio"
    ],
    "name:und_x_variant":[
        "K\u00e1rmi",
        "K\u00e1rmion"
    ],
    "wof:name":"Karmion",
    "wof:placetype":"locality",
    "wof:population":21
},
  "geometry": {"coordinates":[21.92918,37.50544],"type":"Point"}
}