{
  "type": "Feature",
  "properties": {
    "gn:country":"GR",
    "gn:fcode":"PPLA3",
    "gn:population":1732,
    "iso:country":"GR",
    "name:ara_x_preferred":[
        "\u0633\u0643\u064a\u0631\u0648\u0633"
    ],
    "name:bul_x_preferred":[
        "\u0421\u043a\u0438\u0440\u043e\u0441"
    ],
    "name:cat_x_preferred":[
        "Skiros"
    ],
    "name:ceb_x_preferred":[
        "N\u00edsos Sk\u00fdros"
    ],
    "name:ces_x_preferred":[
        "Skyros"
    ],
    "name:dan_x_preferred":[
        "Sk\u00edros"
    ],
    "name:deu_x_preferred":[
        "Skyros"
    ],
    "name:ell_x_preferred":[
        "\u03a3\u03ba\u03cd\u03c1\u03bf\u03c2"
    ],
    "name:est_x_preferred":[
        "Sk\u00fdrose saar"
    ],
    "name:fin_x_preferred":[
        "Sk\u00fdros"
    ],
    "name:fra_x_preferred":[
        "Skyros"
    ],
    "name:glg_x_preferred":[
        "Esciro"
    ],
    "name:heb_x_preferred":[
        "\u05e1\u05e7\u05d9\u05e8\u05d5\u05e1"
    ],
    "name:hun_x_preferred":[
        "Szk\u00edrosz"
    ],
    "name:ind_x_preferred":[
        "Skyros"
    ],
    "name:ita_x_preferred":[
        "Sciro"
    ],
    "name:jpn_x_preferred":[
        "\u30b9\u30ad\u30ed\u30b9\u5cf6"
    ],
    "name:kat_x_preferred":[
        "\u10e1\u10d9\u10d8\u10e0\u10dd\u10e1\u10d8"
    ],
    "name:lat_x_preferred":[
        "Scyros"
    ],
    "name:lit_x_preferred":[
        "Skiras"
    ],
    "name:mkd_x_preferred":[
        "\u0421\u043a\u0438\u0440\u043e\u0441"
    ],
    "name:nld_x_preferred":[
        "Skyros"
    ],
    "name:nno_x_preferred":[
        "Sk\u00fdros"
    ],
    "name:nor_x_preferred":[
        "Skiros"
    ],
    "name:pol_x_preferred":[
        "Skiros"
    ],
    "name:por_x_preferred":[
        "Esquiro"
    ],
    "name:ron_x_preferred":[
        "Skyros"
    ],
    "name:rus_x_preferred":[
        "\u0421\u043a\u0438\u0440\u043e\u0441"
    ],
    "name:spa_x_preferred":[
        "Esciros"
    ],
    "name:sqi_x_preferred":[
        "Skyros"
    ],
    "name:srp_x_preferred":[
        "\u0421\u043a\u0438\u0440\u043e\u0441"
    ],
    "name:swe_x_preferred":[
        "Skyros"
    ],
    "name:tha_x_preferred":[
        "\u0e2a\u0e44\u0e01\u0e23\u0e2d\u0e2a"
    ],
    "name:tur_x_preferred":[
        "\u0130skiri"
    ],
    "name:ukr_x_preferred":[
        "\u0421\u043a\u0456\u0440\u043e\u0441"
    ],
    "name:vie_x_preferred":[
        "Skyros"
    ],
    "name:zho_x_preferred":[
        "\u65af\u57fa\u7f57\u65af\u5c9b"
    ],
    "qs_pg:aaroncc":"GR",
    "qs_pg:gn_country":"GR",
    "qs_pg:gn_fcode":"PPLA3",
    "qs_pg:gn_pop":1732,
    "qs_pg:name":"Skyros",
    "qs_pg:name_adm0":"\u0395\u03bb\u03bb\u03ac\u03b4\u03b1",
    "qs_pg:name_adm1":"Thessaly and Continental Greece",
    "qs_pg:photos":185,
    "qs_pg:photos_1k":37,
    "qs_pg:photos_9k":3,
    "qs_pg:photos_9r":5,
    "qs_pg:photos_all":575,
    "qs_pg:photos_sr":4,
    "qs_pg:pop_sr":3,
    "qs_pg:qs_pg_placetype":"localadmin",
    "qs_pg:qs_pg_placetype_gp":"LocalAdmin",
    "qs_pg:woe_adm0":23424833,
    "woe:adm0_id":23424833,
    "woe:name_adm0":"\u0395\u03bb\u03bb\u03ac\u03b4\u03b1",
    "woe:name_adm1":"Thessaly and Continental Greece",
    "woe:placetype":"LocalAdmin",
    "wof:name":"Skyros",
    "wof:placetype":"localadmin",
    "wof:population":1732
},
  "geometry": {"coordinates":[24.56306,38.90417],"type":"Point"}
}