{
  "type": "Feature",
  "properties": {
    "gn:country":"GR",
    "gn:fcode":"PPL",
    "gn:population":303,
    "iso:country":"GR",
    "name:ceb_x_preferred":[
        "Mastich\u00e1rion"
    ],
    "name:deu_x_preferred":[
        "Mastichari"
    ],
    "name:ell_x_preferred":[
        "\u039c\u03b1\u03c3\u03c4\u03b9\u03c7\u03ac\u03c1\u03b9"
    ],
    "name:ell_x_variant":[
        "\u039c\u03b1\u03c3\u03c4\u03b9\u03c7\u03ac\u03c1\u03b9\u03bf\u03bd",
        "\u039c\u03b1\u03c3\u03c4\u03b9\u03c7\u03ac\u03c1\u03b9 \u039a\u03c9"
    ],
    "name:eng_x_preferred":[
        "Mastihari"
    ],
    "name:fin_x_preferred":[
        "Mastich\u00e1ri"
    ],
    "name:nld_x_preferred":[
        "Mastichari"
    ],
    "name:rus_x_preferred":[
        "\u041c\u0430\u0441\u0442\u0438\u0445\u0430\u0440\u0438\u043e\u043d"
    ],
    "name:swe_x_preferred":[
        "Mastich\u00e1rion"
    ],
    "name:und_x_variant":[
        "Chori\u00f3 Mastich\u00e1rion"
    ],
    "qs_pg:aaroncc":"GR",
    "qs_pg:gn_country":"GR",
    "qs_pg:gn_fcode":"PPL",
    "qs_pg:gn_pop":303,
    "qs_pg:name":"Mastikharion",
    "qs_pg:name_adm0":"\u0395\u03bb\u03bb\u03ac\u03b4\u03b1",
    "qs_pg:name_adm1":"Aegean",
    "qs_pg:photos_9k":1,
    "qs_pg:photos_9r":1,
    "qs_pg:photos_all":3,
    "qs_pg:photos_sr":0,
    "qs_pg:pop_sr":2,
    "qs_pg:qs_pg_placetype":"locality",
    "qs_pg:qs_pg_placetype_gp":"Town",
    "qs_pg:woe_adm0":23424833,
    "woe:adm0_id":23424833,
    "woe:name_adm0":"\u0395\u03bb\u03bb\u03ac\u03b4\u03b1",
    "woe:name_adm1":"Aegean",
    "woe:placetype":"Town",
    "wof:name":"Mastikharion",
    "wof:placetype":"locality",
    "wof:population":303
},
  "geometry": {"coordinates":[27.07556,36.84889],"type":"Point"}
}