{
  "type": "Feature",
  "properties": {
    "gn:admin1_code":"ESYE23",
    "gn:admin2_code":"31.0",
    "gn:admin3_code":"9123",
    "gn:asciiname":"Ayia Marina",
    "gn:country_code":"GR",
    "gn:dem":75,
    "gn:feature_class":"P",
    "gn:feature_code":"PPL",
    "gn:name":"Ay\u00eda Mar\u00edna",
    "gn:population":97,
    "gn:timezone":"Europe/Athens",
    "iso:country":"GR",
    "name:ell_x_preferred":[
        "\u0391\u03b3\u03af\u03b1 \u039c\u03b1\u03c1\u03af\u03bd\u03b1"
    ],
    "name:eng_x_preferred":[
        "Agia Marina"
    ],
    "wof:name":"Ayia Marina",
    "wof:placetype":"locality",
    "wof:population":97
},
  "geometry": {"coordinates":[21.49237,38.52635],"type":"Point"}
}