{
  "type": "Feature",
  "properties": {
    "gn:admin1_code":"ESYE12",
    "gn:admin2_code":"13.0",
    "gn:admin3_code":"9027",
    "gn:asciiname":"Apollonia",
    "gn:country_code":"GR",
    "gn:dem":49,
    "gn:feature_class":"P",
    "gn:feature_code":"PPL",
    "gn:name":"Apollon\u00eda",
    "gn:population":0,
    "gn:timezone":"Europe/Athens",
    "iso:country":"GR",
    "name:bul_x_preferred":[
        "\u0410\u043f\u043e\u043b\u043e\u043d\u0438\u044f \u041c\u0438\u0433\u0434\u043e\u043d\u0441\u043a\u0430"
    ],
    "name:deu_x_preferred":[
        "Apollonia Mygdoniorum"
    ],
    "name:ell_x_preferred":[
        "\u0391\u03c0\u03bf\u03bb\u03bb\u03c9\u03bd\u03af\u03b1"
    ],
    "name:ell_x_variant":[
        "\u0391\u03c0\u03bf\u03bb\u03bb\u03c9\u03bd\u03af\u03b1 \u039c\u03c5\u03b3\u03b4\u03bf\u03bd\u03af\u03b1\u03c2"
    ],
    "name:ita_x_preferred":[
        "Apollonia"
    ],
    "name:lat_x_preferred":[
        "Apollonia"
    ],
    "name:nld_x_preferred":[
        "Apollonia"
    ],
    "name:por_x_preferred":[
        "Apol\u00f4nia"
    ],
    "name:spa_x_preferred":[
        "Apolonia"
    ],
    "name:und_x_variant":[
        "Pazaro\u00fadha",
        "Apollon\u00eda"
    ],
    "wof:name":"Apollonia",
    "wof:placetype":"locality"
},
  "geometry": {"coordinates":[23.4888,40.64074],"type":"Point"}
}