{
  "type": "Feature",
  "properties": {
    "gn:admin1_code":"ESYE12",
    "gn:admin2_code":"13.0",
    "gn:admin3_code":"9027",
    "gn:asciiname":"Apollonia",
    "gn:country_code":"GR",
    "gn:dem":49,
    "gn:feature_class":"P",
    "gn:feature_code":"PPL",
    "gn:name":"Apollon\u00eda",
    "gn:population":0,
    "gn:timezone":"Europe/Athens",
    "iso:country":"GR",
    "name:ell_x_preferred":[
        "\u0391\u03c0\u03bf\u03bb\u03bb\u03c9\u03bd\u03af\u03b1"
    ],
    "name:und_x_variant":[
        "Pazaro\u00fadha",
        "Apollon\u00eda"
    ],
    "wof:name":"Apollonia",
    "wof:placetype":"locality"
},
  "geometry": {"coordinates":[23.4888,40.64074],"type":"Point"}
}