{
  "type": "Feature",
  "properties": {
    "gn:admin1_code":"ESYE11",
    "gn:admin2_code":"1.0",
    "gn:admin3_code":"9007",
    "gn:asciiname":"Mikrochori",
    "gn:country_code":"GR",
    "gn:dem":31,
    "gn:feature_class":"P",
    "gn:feature_code":"PPL",
    "gn:name":"Mikroch\u00f3ri",
    "gn:population":0,
    "gn:timezone":"Europe/Athens",
    "iso:country":"GR",
    "name:ell_x_preferred":[
        "Mikroch\u00f3ri"
    ],
    "name:ell_x_variant":[
        "\u039c\u03b9\u03ba\u03c1\u03bf\u03c7\u03ce\u03c1\u03b9",
        "Mikrokh\u00f3rion",
        "Mikroch\u00f3rion",
        "\u039c\u03b9\u03ba\u03c1\u03bf\u03c7\u03ce\u03c1\u03b9\u03bf\u03bd"
    ],
    "wof:name":"Mikrochori",
    "wof:placetype":"locality"
},
  "geometry": {"coordinates":[26.5916,41.34104],"type":"Point"}
}