{
  "type": "Feature",
  "properties": {
    "gn:admin1_code":"ESYE23",
    "gn:admin2_code":"38.0",
    "gn:admin3_code":"9131",
    "gn:asciiname":"Kato Alissos",
    "gn:country_code":"GR",
    "gn:dem":38,
    "gn:feature_class":"P",
    "gn:feature_code":"PPL",
    "gn:name":"K\u00e1to Aliss\u00f3s",
    "gn:population":0,
    "gn:timezone":"Europe/Athens",
    "iso:country":"GR",
    "name:ell_x_preferred":[
        "K\u00e1to Aliss\u00f3s"
    ],
    "name:ell_x_variant":[
        "\u039a\u03ac\u03c4\u03c9 \u0391\u03bb\u03b9\u03c3\u03c3\u03cc\u03c2"
    ],
    "wof:name":"Kato Alissos",
    "wof:placetype":"locality"
},
  "geometry": {"coordinates":[21.57575,38.14107],"type":"Point"}
}