{
  "type": "Feature",
  "properties": {
    "gn:population":1220,
    "iso:country":"GR",
    "name:ara_x_preferred":[
        "\u0623\u0646\u062c\u0644\u0648\u0643\u0627\u0633\u062a\u0631\u0648\u0646\u060c \u0623\u064a\u062a\u0648\u0644\u064a\u0627 \u0643\u064a \u0623\u0643\u0627\u0631\u0646\u0627\u0646\u064a\u0627"
    ],
    "name:ell_x_preferred":[
        "\u0391\u03b3\u03b3\u03b5\u03bb\u03cc\u03ba\u03b1\u03c3\u03c4\u03c1\u03bf\u03bd"
    ],
    "name:ell_x_variant":[
        "\u0391\u03b3\u03b3\u03b5\u03bb\u03cc\u03ba\u03b1\u03c3\u03c4\u03c1\u03bf",
        "\u0391\u03b3\u03b3\u03b5\u03bb\u03cc\u03ba\u03b1\u03c3\u03c4\u03c1\u03bf \u0391\u03b9\u03c4\u03c9\u03bb\u03bf\u03b1\u03ba\u03b1\u03c1\u03bd\u03b1\u03bd\u03af\u03b1\u03c2"
    ],
    "name:eng_x_preferred":[
        "Angelokastro"
    ],
    "name:ita_x_preferred":[
        "Angelocastro"
    ],
    "name:jpn_x_preferred":[
        "\u30a2\u30f3\u30b2\u30ed\u30ab\u30b9\u30c8\u30ed"
    ],
    "name:nld_x_preferred":[
        "Angelokastro"
    ],
    "name:nno_x_preferred":[
        "Angel\u00f3kastro"
    ],
    "name:ron_x_preferred":[
        "Angelokastro"
    ],
    "name:spa_x_preferred":[
        "Municipalidad de Angelokastro"
    ],
    "name:swe_x_preferred":[
        "Angel\u00f3kastro"
    ],
    "name:tur_x_preferred":[
        "Angelokastro"
    ],
    "name:unk_x_variant":[
        "Angel\u00f3kastro"
    ],
    "qs:a0":"Greece",
    "qs:a1":"*\u0394\u03a5\u03a4\u0399\u039a\u0397 \u0395\u039b\u039b\u0391\u0394\u0391",
    "qs:a1_alt":"DYTIKH ELLADA",
    "qs:a1r":"0",
    "qs:a2_alt":"AITVLIA KAI AKARNANIA",
    "qs:adm0":"Greece",
    "qs:la_lc":"*",
    "qs:level":"locality",
    "qs:loc":"\u0391\u0393\u0393\u0395\u039b\u039f\u039a\u0391\u03a3\u03a4\u03a1\u039f\u039d",
    "qs:loc_alt":"AGGELOKASTRON",
    "qs:pop":0,
    "qs:type":"buffered point",
    "wof:name":"\u0391\u0393\u0393\u0395\u039b\u039f\u039a\u0391\u03a3\u03a4\u03a1\u039f\u039d",
    "wof:placetype":"locality",
    "wof:population":1220
},
  "geometry": {"coordinates":[21.297342,38.567368],"type":"Point"}
}