{
  "type": "Feature",
  "properties": {
    "gn:admin1_code":"ESYE25",
    "gn:admin2_code":"41.0",
    "gn:admin3_code":"9239",
    "gn:asciiname":"Zoni",
    "gn:country_code":"GR",
    "gn:dem":504,
    "gn:feature_class":"P",
    "gn:feature_code":"PPL",
    "gn:name":"Z\u00f3ni",
    "gn:population":0,
    "gn:timezone":"Europe/Athens",
    "iso:country":"GR",
    "name:bul_x_preferred":[
        "\u0417\u043e\u043d\u0438"
    ],
    "name:ceb_x_preferred":[
        "Zoni"
    ],
    "name:ell_x_preferred":[
        "\u0396\u03ce\u03bd\u03b7"
    ],
    "name:ind_x_preferred":[
        "Zoni"
    ],
    "name:und_x_variant":[
        "Zoun\u00e1ti",
        "Z\u00f3ni"
    ],
    "wof:name":"Zoni",
    "wof:placetype":"locality"
},
  "geometry": {"coordinates":[22.1198,37.46218],"type":"Point"}
}