{
  "type": "Feature",
  "properties": {
    "gn:gn_country":"GR",
    "gn:gn_fcode":"PPL",
    "gn:gn_pop":3758,
    "gn:population":3752,
    "iso:country":"GR",
    "name:ara_x_preferred":[
        "\u0644\u064a\u0643\u0633\u0648\u0631\u064a"
    ],
    "name:cat_x_preferred":[
        "Lixouri"
    ],
    "name:deu_x_preferred":[
        "Lixouri"
    ],
    "name:ell_x_preferred":[
        "\u039b\u03b7\u03be\u03bf\u03cd\u03c1\u03b9\u03bf\u03bd"
    ],
    "name:ell_x_variant":[
        "\u039b\u03b7\u03be\u03bf\u03cd\u03c1\u03b9"
    ],
    "name:eng_x_preferred":[
        "Lixouri"
    ],
    "name:fin_x_preferred":[
        "Lixo\u00fari"
    ],
    "name:fra_x_preferred":[
        "Lixouri"
    ],
    "name:hrv_x_preferred":[
        "Liksuri"
    ],
    "name:hye_x_preferred":[
        "\u053c\u056b\u056f\u057d\u0578\u0582\u0580\u056b\u0578\u0576"
    ],
    "name:ita_x_preferred":[
        "Lixouri"
    ],
    "name:jpn_x_preferred":[
        "\u30ea\u30af\u30b9\u30ea"
    ],
    "name:lat_x_preferred":[
        "Lexurium"
    ],
    "name:nld_x_preferred":[
        "Lixouri"
    ],
    "name:nno_x_preferred":[
        "Lixo\u00fari"
    ],
    "name:pol_x_preferred":[
        "Lixouri"
    ],
    "name:por_x_preferred":[
        "Lixouri"
    ],
    "name:ron_x_preferred":[
        "Lixouri"
    ],
    "name:rus_x_preferred":[
        "\u041b\u0438\u043a\u0441\u0443\u0440\u0438\u043e\u043d"
    ],
    "name:spa_x_preferred":[
        "Lixouri"
    ],
    "name:srp_x_preferred":[
        "\u041b\u0438\u043a\u0441\u0443\u0440\u0438"
    ],
    "name:swe_x_preferred":[
        "Lixo\u00fari"
    ],
    "name:unk_x_variant":[
        "Lixuri"
    ],
    "qs_pg:aaroncc":"GR",
    "qs_pg:gn_country":"GR",
    "qs_pg:gn_fcode":"PPL",
    "qs_pg:gn_pop":3758,
    "qs_pg:name":"Lixourion",
    "qs_pg:name_adm0":"\u0395\u03bb\u03bb\u03ac\u03b4\u03b1",
    "qs_pg:name_adm1":"Peloponnese Western Greece and the Ionian Islands",
    "qs_pg:photos_9r":0,
    "qs_pg:photos_sr":0,
    "qs_pg:pop_sr":4,
    "qs_pg:qs_pg_placetype":"locality",
    "qs_pg:qs_pg_placetype_gp":"Town",
    "qs_pg:woe_adm0":23424833,
    "woe:adm0_id":23424833,
    "woe:name_adm0":"\u0395\u03bb\u03bb\u03ac\u03b4\u03b1",
    "woe:name_adm1":"Peloponnese Western Greece and the Ionian Islands",
    "woe:placetype":"Town",
    "wof:name":"Lixourion",
    "wof:placetype":"locality",
    "wof:population":3752
},
  "geometry": {"coordinates":[20.43139,38.20194],"type":"Point"}
}