{
  "type": "Feature",
  "properties": {
    "iso:country":"GR",
    "name:ell_x_preferred":[
        "\u0391\u03bd\u03b8\u03bf\u03c7\u03ce\u03c1\u03b9"
    ],
    "qs_pg:aaroncc":"GR",
    "qs_pg:name":"Anthochori",
    "qs_pg:name_adm0":"\u0395\u03bb\u03bb\u03ac\u03b4\u03b1",
    "qs_pg:name_adm1":"Thessaly and Continental Greece",
    "qs_pg:photos":45,
    "qs_pg:photos_1k":9,
    "qs_pg:photos_9k":1,
    "qs_pg:photos_9r":2,
    "qs_pg:photos_all":45,
    "qs_pg:photos_sr":2,
    "qs_pg:pop_sr":0,
    "qs_pg:qs_pg_placetype":"locality",
    "qs_pg:qs_pg_placetype_gp":"Town",
    "qs_pg:woe_adm0":23424833,
    "woe:adm0_id":23424833,
    "woe:name_adm0":"\u0395\u03bb\u03bb\u03ac\u03b4\u03b1",
    "woe:name_adm1":"Thessaly and Continental Greece",
    "woe:placetype":"Town",
    "wof:name":"Anthochori",
    "wof:placetype":"locality"
},
  "geometry": {"coordinates":[21.663322,39.354343],"type":"Point"}
}