{
  "type": "Feature",
  "properties": {
    "gn:admin1_code":"ESYE25",
    "gn:admin2_code":"42.0",
    "gn:admin3_code":"9251",
    "gn:asciiname":"Agios Georgios",
    "gn:country_code":"GR",
    "gn:dem":20,
    "gn:feature_class":"P",
    "gn:feature_code":"PPL",
    "gn:name":"\u00c1gios Ge\u00f3rgios",
    "gn:population":0,
    "gn:timezone":"Europe/Athens",
    "iso:country":"GR",
    "name:ell_x_preferred":[
        "\u00c1gios Ge\u00f3rgios"
    ],
    "name:ell_x_variant":[
        "\u0386\u03b3\u03b9\u03bf\u03c2 \u0393\u03b5\u03ce\u03c1\u03b3\u03b9\u03bf\u03c2"
    ],
    "name:und_x_variant":[
        "\u00c1yios Ye\u00f3ryios"
    ],
    "wof:name":"Agios Georgios",
    "wof:placetype":"locality"
},
  "geometry": {"coordinates":[23.00327,36.54107],"type":"Point"}
}