{
  "type": "Feature",
  "properties": {
    "gn:admin1_code":"ESYE43",
    "gn:admin2_code":"43.0",
    "gn:admin3_code":"9319",
    "gn:asciiname":"Tsikoliana",
    "gn:country_code":"GR",
    "gn:dem":187,
    "gn:feature_class":"P",
    "gn:feature_code":"PPL",
    "gn:name":"Tsikolian\u00e1",
    "gn:population":0,
    "gn:timezone":"Europe/Athens",
    "iso:country":"GR",
    "name:ell_x_preferred":[
        "Tsikolian\u00e1"
    ],
    "name:ell_x_variant":[
        "\u03a4\u03c3\u03b9\u03ba\u03bf\u03bb\u03b9\u03b1\u03bd\u03ac"
    ],
    "wof:name":"Tsikoliana",
    "wof:placetype":"locality"
},
  "geometry": {"coordinates":[24.19038,35.40653],"type":"Point"}
}