{
  "type": "Feature",
  "properties": {
    "gn:admin1_code":"ESYE43",
    "gn:admin2_code":"44.0",
    "gn:admin3_code":"9314",
    "gn:asciiname":"Palaioloutra",
    "gn:country_code":"GR",
    "gn:dem":360,
    "gn:feature_class":"P",
    "gn:feature_code":"PPL",
    "gn:name":"Palai\u00f3loutra",
    "gn:population":0,
    "gn:timezone":"Europe/Athens",
    "iso:country":"GR",
    "wof:name":"Palaioloutra",
    "wof:placetype":"locality"
},
  "geometry": {"coordinates":[24.44029,35.24155],"type":"Point"}
}