{
  "type": "Feature",
  "properties": {
    "gn:gn_country":"GR",
    "gn:gn_fcode":"PPL",
    "gn:gn_pop":262,
    "gn:population":262,
    "iso:country":"GR",
    "name:bul_x_preferred":[
        "\u0414\u0435\u043c\u0438\u0440\u0434\u0436\u0438\u043a"
    ],
    "name:ell_x_preferred":[
        "Dimari\u00f3"
    ],
    "name:ell_x_variant":[
        "Dimari\u00f3n",
        "\u0394\u03b7\u03bc\u03b1\u03c1\u03b9\u03cc",
        "\u0394\u03b7\u03bc\u03b1\u03c1\u03b9\u03cc\u03bd",
        "\u0394\u03b7\u03bc\u03ac\u03c1\u03b9 \u0386\u03c1\u03c4\u03b1\u03c2"
    ],
    "name:eng_x_preferred":[
        "Dimari"
    ],
    "name:nld_x_preferred":[
        "Dimari"
    ],
    "name:swe_x_preferred":[
        "Dimari\u00f3"
    ],
    "name:unk_x_variant":[
        "Dhimari\u00f3n"
    ],
    "qs_pg:aaroncc":"GR",
    "qs_pg:gn_country":"GR",
    "qs_pg:gn_fcode":"PPL",
    "qs_pg:gn_pop":262,
    "qs_pg:name":"Dim\u00e1rion",
    "qs_pg:photos_9r":0,
    "qs_pg:photos_sr":0,
    "qs_pg:pop_sr":2,
    "qs_pg:qs_pg_placetype":"locality",
    "wof:name":"Dim\u00e1rion",
    "wof:placetype":"locality",
    "wof:population":262
},
  "geometry": {"coordinates":[21.15444,39.1525],"type":"Point"}
}