{
  "type": "Feature",
  "properties": {
    "gn:admin1_code":"ESYE41",
    "gn:asciiname":"Christos",
    "gn:country_code":"GR",
    "gn:dem":448,
    "gn:feature_class":"P",
    "gn:feature_code":"PPL",
    "gn:name":"Chr\u00edstos",
    "gn:population":0,
    "gn:timezone":"Europe/Athens",
    "iso:country":"GR",
    "name:deu_x_preferred":[
        "Christos"
    ],
    "name:ell_x_preferred":[
        "Chr\u00edstos"
    ],
    "name:ell_x_variant":[
        "\u03a7\u03c1\u03af\u03c3\u03c4\u03bf\u03c2"
    ],
    "name:fra_x_preferred":[
        "Christos"
    ],
    "name:jpn_x_preferred":[
        "\u30d5\u30ea\u30b9\u30c8\u30b9"
    ],
    "wof:name":"Christos",
    "wof:placetype":"locality"
},
  "geometry": {"coordinates":[26.0808,37.60087],"type":"Point"}
}