{
  "type": "Feature",
  "properties": {
    "gn:population":892,
    "iso:country":"GR",
    "name:ara_x_preferred":[
        "\u0645\u064a\u062b\u0627\u0646\u0627"
    ],
    "name:cat_x_preferred":[
        "Methana"
    ],
    "name:ceb_x_preferred":[
        "M\u00e9thana"
    ],
    "name:deu_x_preferred":[
        "Methana"
    ],
    "name:ell_x_preferred":[
        "\u039c\u03ad\u03b8\u03b1\u03bd\u03b1"
    ],
    "name:ell_x_variant":[
        "M\u00e9thana"
    ],
    "name:eng_x_preferred":[
        "Methana"
    ],
    "name:eng_x_variant":[
        "M\u00e9thana"
    ],
    "name:eus_x_preferred":[
        "Methana"
    ],
    "name:fin_x_preferred":[
        "M\u00e9thana"
    ],
    "name:fra_x_preferred":[
        "Methana"
    ],
    "name:heb_x_preferred":[
        "\u05de\u05ea\u05d0\u05e0\u05d4"
    ],
    "name:hye_x_preferred":[
        "\u0544\u0565\u057f\u0561\u0576\u0561"
    ],
    "name:ita_x_preferred":[
        "Methana"
    ],
    "name:jpn_x_preferred":[
        "\u30e1\u30bf\u30ca"
    ],
    "name:lat_x_preferred":[
        "Methana"
    ],
    "name:nld_x_preferred":[
        "Methana"
    ],
    "name:nno_x_preferred":[
        "M\u00e9thana"
    ],
    "name:nob_x_preferred":[
        "Methana"
    ],
    "name:rus_x_preferred":[
        "\u041c\u0435\u0442\u0430\u043d\u0430"
    ],
    "name:spa_x_preferred":[
        "Metana"
    ],
    "name:spa_x_variant":[
        "Methana"
    ],
    "name:swe_x_preferred":[
        "M\u00e9thana"
    ],
    "name:tur_x_preferred":[
        "Metana"
    ],
    "name:und_x_variant":[
        "\u039c\u0395\u0398\u0391\u039d\u0391"
    ],
    "qs:a0":"Greece",
    "qs:a1":"*\u0391\u03a4\u03a4\u0399\u039a\u0397",
    "qs:a1_alt":"ATTIKH",
    "qs:a1r":"0",
    "qs:a2_alt":"PEIRAIAS",
    "qs:adm0":"Greece",
    "qs:la_lc":"*",
    "qs:level":"locality",
    "qs:loc":"\u039c\u0395\u0398\u0391\u039d\u0391",
    "qs:loc_alt":"MEUANA",
    "qs:pop":0,
    "qs:type":"buffered point",
    "wd:wordcount":752,
    "wof:lang":[
        "eng"
    ],
    "wof:name":"\u039c\u0395\u0398\u0391\u039d\u0391",
    "wof:placetype":"locality",
    "wof:population":892
},
  "geometry": {"coordinates":[23.390423,37.581227],"type":"Point"}
}