{
  "type": "Feature",
  "properties": {
    "gn:admin1_code":"ESYE24",
    "gn:admin2_code":"32.0",
    "gn:admin3_code":"9166",
    "gn:asciiname":"Longos",
    "gn:country_code":"GR",
    "gn:dem":8,
    "gn:feature_class":"P",
    "gn:feature_code":"PPL",
    "gn:name":"L\u00f3ngos",
    "gn:population":0,
    "gn:timezone":"Europe/Athens",
    "iso:country":"GR",
    "name:ceb_x_preferred":[
        "Longos"
    ],
    "name:ell_x_preferred":[
        "L\u00f3ngos"
    ],
    "name:ell_x_variant":[
        "\u039b\u03cc\u03b3\u03b3\u03bf\u03c2"
    ],
    "name:glg_x_preferred":[
        "Longos"
    ],
    "name:ind_x_preferred":[
        "Longos"
    ],
    "name:swe_x_preferred":[
        "Longos"
    ],
    "wof:name":"Longos",
    "wof:placetype":"locality"
},
  "geometry": {"coordinates":[21.89812,38.40019],"type":"Point"}
}