{
  "type": "Feature",
  "properties": {
    "gn:admin1_code":"ESYE23",
    "gn:admin2_code":"31.0",
    "gn:admin3_code":"9123",
    "gn:asciiname":"Tsounaiika",
    "gn:country_code":"GR",
    "gn:dem":189,
    "gn:feature_class":"P",
    "gn:feature_code":"PPL",
    "gn:name":"Tsouna\u00edika",
    "gn:population":36,
    "gn:timezone":"Europe/Athens",
    "iso:country":"GR",
    "name:ell_x_preferred":[
        "\u03a4\u03c3\u03bf\u03c5\u03bd\u03b1\u03af\u03b9\u03ba\u03b1"
    ],
    "name:eng_x_preferred":[
        "Tsounaiika"
    ],
    "name:und_x_variant":[
        "Tsin\u00e9\u00efka",
        "Tsina\u00edika"
    ],
    "wof:name":"Tsounaiika",
    "wof:placetype":"locality",
    "wof:population":36
},
  "geometry": {"coordinates":[21.44089,38.75355],"type":"Point"}
}