{
  "type": "Feature",
  "properties": {
    "gn:admin1_code":"ESYE25",
    "gn:admin2_code":"37.0",
    "gn:admin3_code":"9246",
    "gn:asciiname":"Ano Loutro",
    "gn:country_code":"GR",
    "gn:dem":201,
    "gn:feature_class":"P",
    "gn:feature_code":"PPL",
    "gn:name":"\u00c1no Loutr\u00f3",
    "gn:population":48,
    "gn:timezone":"Europe/Athens",
    "iso:country":"GR",
    "name:ell_x_preferred":[
        "\u0386\u03bd\u03c9 \u039b\u03bf\u03c5\u03c4\u03c1\u03cc"
    ],
    "name:eng_x_preferred":[
        "Ano Loutro"
    ],
    "name:und_x_variant":[
        "\u00c1no Loutr\u00f3",
        "\u00c1no Loutr\u00f3n"
    ],
    "wof:name":"Ano Loutro",
    "wof:placetype":"locality",
    "wof:population":48
},
  "geometry": {"coordinates":[22.53927,38.09476],"type":"Point"}
}