{
  "type": "Feature",
  "properties": {
    "gn:population":1140,
    "iso:country":"GR",
    "name:ara_x_preferred":[
        "\u0628\u062a\u064a\u0644\u064a\u0648\u0633"
    ],
    "name:ceb_x_preferred":[
        "Ptele\u00f3s"
    ],
    "name:deu_x_preferred":[
        "Pteleos"
    ],
    "name:ell_x_historical":[
        "\u03a0\u03c4\u03b5\u03bb\u03b5\u03cc\u03bd"
    ],
    "name:ell_x_preferred":[
        "\u0394\u03ae\u03bc\u03bf\u03c2 \u0391\u03bb\u03bc\u03c5\u03c1\u03bf\u03cd#\u03a0\u03c4\u03b5\u03bb\u03b5\u03bf\u03cd"
    ],
    "name:ell_x_variant":[
        "\u03a0\u03c4\u03b5\u03bb\u03b5\u03cc\u03c2",
        "\u03a0\u03c4\u03b5\u03bb\u03b5\u03cc\u03bd",
        "\u03a0\u03c4\u03b5\u03bb\u03b5\u03cc\u03c2 \u039c\u03b1\u03b3\u03bd\u03b7\u03c3\u03af\u03b1\u03c2"
    ],
    "name:eng_x_preferred":[
        "Pteleos"
    ],
    "name:fin_x_preferred":[
        "Ptele\u00f3s"
    ],
    "name:fra_x_preferred":[
        "Pteleos"
    ],
    "name:ita_x_preferred":[
        "Pteleos"
    ],
    "name:jpn_x_preferred":[
        "\u30d7\u30c6\u30ec\u30aa\u30b9"
    ],
    "name:nld_x_preferred":[
        "Pteleos"
    ],
    "name:nno_x_preferred":[
        "Ptele\u00f3s"
    ],
    "name:pol_x_preferred":[
        "Almiros"
    ],
    "name:por_x_preferred":[
        "Pteleos"
    ],
    "name:rus_x_preferred":[
        "\u041f\u0442\u0435\u043b\u0435\u043e\u0441"
    ],
    "name:swe_x_preferred":[
        "Ptele\u00f3s"
    ],
    "name:und_x_variant":[
        "Fteli\u00f3"
    ],
    "qs:a0":"Greece",
    "qs:a1":"*\u0398\u0395\u03a3\u03a3\u0391\u039b\u0399\u0391",
    "qs:a1_alt":"UESSALIA",
    "qs:a1r":"0",
    "qs:a2_alt":"MAGNHSIA",
    "qs:adm0":"Greece",
    "qs:la_lc":"*",
    "qs:level":"locality",
    "qs:loc":"\u03a0\u03a4\u0395\u039b\u0395\u039f\u03a3",
    "qs:loc_alt":"PTELEOS",
    "qs:pop":0,
    "qs:type":"buffered point",
    "wd:wordcount":165,
    "wof:name":"\u03a0\u03a4\u0395\u039b\u0395\u039f\u03a3",
    "wof:placetype":"locality",
    "wof:population":1140
},
  "geometry": {"coordinates":[22.953194,39.052425],"type":"Point"}
}