{
  "type": "Feature",
  "properties": {
    "gn:gn_country":"GR",
    "gn:gn_fcode":"PPL",
    "gn:gn_pop":724,
    "gn:population":724,
    "iso:country":"GR",
    "name:ceb_x_preferred":[
        "\u00c1zoros"
    ],
    "name:ell_x_preferred":[
        "\u0386\u03b6\u03c9\u03c1\u03bf\u03c2"
    ],
    "name:ell_x_variant":[
        "\u0386\u03b6\u03c9\u03c1\u03bf\u03c2 \u039b\u03ac\u03c1\u03b9\u03c3\u03b1\u03c2"
    ],
    "name:eng_x_preferred":[
        "Azoros"
    ],
    "name:nld_x_preferred":[
        "Azoros"
    ],
    "name:swe_x_preferred":[
        "\u00c1zoros"
    ],
    "name:unk_x_variant":[
        "Vouv\u00e1la"
    ],
    "qs_pg:aaroncc":"GR",
    "qs_pg:gn_country":"GR",
    "qs_pg:gn_fcode":"PPL",
    "qs_pg:gn_pop":724,
    "qs_pg:name":"Azoros",
    "qs_pg:name_adm0":"\u0395\u03bb\u03bb\u03ac\u03b4\u03b1",
    "qs_pg:name_adm1":"Thessaly and Continental Greece",
    "qs_pg:photos_9k":1,
    "qs_pg:photos_9r":1,
    "qs_pg:photos_all":1,
    "qs_pg:photos_sr":0,
    "qs_pg:pop_sr":2,
    "qs_pg:qs_pg_placetype":"locality",
    "qs_pg:qs_pg_placetype_gp":"Town",
    "qs_pg:woe_adm0":23424833,
    "woe:adm0_id":23424833,
    "woe:name_adm0":"\u0395\u03bb\u03bb\u03ac\u03b4\u03b1",
    "woe:name_adm1":"Thessaly and Continental Greece",
    "woe:placetype":"Town",
    "wof:name":"Azoros",
    "wof:placetype":"locality",
    "wof:population":724
},
  "geometry": {"coordinates":[22.07194,39.99944],"type":"Point"}
}