{
  "type": "Feature",
  "properties": {
    "gn:population":1251,
    "iso:country":"GR",
    "name:ell_x_preferred":[
        "\u03a0\u03ac\u03bc\u03c6\u03b9\u03bb\u03b1"
    ],
    "name:und_x_variant":[
        "P\u00e1mfila"
    ],
    "qs:a0":"Greece",
    "qs:a1":"*\u0392\u039f\u03a1\u0395\u0399\u039f \u0391\u0399\u0393\u0391\u0399\u039f",
    "qs:a1_alt":"BOREIO AIGAIO",
    "qs:a1r":"0",
    "qs:a2_alt":"LESBOS",
    "qs:adm0":"Greece",
    "qs:la_lc":"*",
    "qs:level":"locality",
    "qs:loc":"\u03a0\u0391\u039c\u03a6\u0399\u039b\u0391",
    "qs:loc_alt":"PAMFILA",
    "qs:pop":0,
    "qs:type":"buffered point",
    "wof:name":"\u03a0\u0391\u039c\u03a6\u0399\u039b\u0391",
    "wof:placetype":"locality",
    "wof:population":1251
},
  "geometry": {"coordinates":[26.52142,39.157799],"type":"Point"}
}