{
  "type": "Feature",
  "properties": {
    "gn:admin1_code":"ESYE23",
    "gn:admin2_code":"38.0",
    "gn:admin3_code":"9131",
    "gn:asciiname":"Pournari",
    "gn:country_code":"GR",
    "gn:dem":213,
    "gn:feature_class":"P",
    "gn:feature_code":"PPL",
    "gn:name":"Pourn\u00e1ri",
    "gn:population":0,
    "gn:timezone":"Europe/Athens",
    "iso:country":"GR",
    "name:ell_x_preferred":[
        "\u03a0\u03bf\u03c5\u03c1\u03bd\u03ac\u03c1\u03b9"
    ],
    "name:ell_x_variant":[
        "\u03a0\u03bf\u03c5\u03c1\u03bd\u03ac\u03c1\u03b9\u03bf\u03bd"
    ],
    "name:und_x_variant":[
        "Purnari",
        "Pourn\u00e1ri",
        "Pourn\u00e1rion"
    ],
    "wof:name":"Pournari",
    "wof:placetype":"locality"
},
  "geometry": {"coordinates":[21.52556,38.07217],"type":"Point"}
}