{
  "type": "Feature",
  "properties": {
    "gn:country":"GR",
    "gn:fcode":"PPL",
    "gn:population":378,
    "iso:country":"GR",
    "name:ceb_x_preferred":[
        "Psathot\u00f3pi"
    ],
    "name:ell_x_preferred":[
        "\u03a8\u03b1\u03b8\u03bf\u03c4\u03cc\u03c0\u03b9"
    ],
    "name:ell_x_variant":[
        "\u03a8\u03b1\u03b8\u03bf\u03c4\u03cc\u03c0\u03b9\u03bf\u03bd",
        "\u03a8\u03b1\u03b8\u03bf\u03c4\u03cc\u03c0\u03b9 \u0386\u03c1\u03c4\u03b1\u03c2"
    ],
    "name:eng_x_preferred":[
        "Psathotopi"
    ],
    "name:eng_x_variant":[
        "Psathotopi Artas"
    ],
    "name:sqi_x_preferred":[
        "Alibej"
    ],
    "name:swe_x_preferred":[
        "Psathot\u00f3pi"
    ],
    "name:und_x_variant":[
        "Al\u00ed B\u00e9\u00ef"
    ],
    "qs_pg:aaroncc":"GR",
    "qs_pg:gn_country":"GR",
    "qs_pg:gn_fcode":"PPL",
    "qs_pg:gn_pop":378,
    "qs_pg:name":"Psathotopi",
    "qs_pg:name_adm0":"\u0395\u03bb\u03bb\u03ac\u03b4\u03b1",
    "qs_pg:name_adm1":"Epirus and Western Macedonia",
    "qs_pg:photos_9r":0,
    "qs_pg:photos_sr":0,
    "qs_pg:pop_sr":2,
    "qs_pg:qs_pg_placetype":"locality",
    "qs_pg:qs_pg_placetype_gp":"Town",
    "qs_pg:woe_adm0":23424833,
    "woe:adm0_id":23424833,
    "woe:name_adm0":"\u0395\u03bb\u03bb\u03ac\u03b4\u03b1",
    "woe:name_adm1":"Epirus and Western Macedonia",
    "woe:placetype":"Town",
    "wof:name":"Psathotopi",
    "wof:placetype":"locality",
    "wof:population":194
},
  "geometry": {"coordinates":[20.95083,39.085],"type":"Point"}
}