{
  "type": "Feature",
  "properties": {
    "gn:admin1_code":"ESYE23",
    "gn:admin2_code":"38.0",
    "gn:admin3_code":"9132",
    "gn:asciiname":"Papakostaiika",
    "gn:country_code":"GR",
    "gn:dem":210,
    "gn:feature_class":"P",
    "gn:feature_code":"PPL",
    "gn:name":"Papakosta\u00edika",
    "gn:population":0,
    "gn:timezone":"Europe/Athens",
    "iso:country":"GR",
    "name:ell_x_preferred":[
        "Papakosta\u00edika"
    ],
    "name:ell_x_variant":[
        "\u03a0\u03b1\u03c0\u03b1\u03ba\u03c9\u03c3\u03c4\u03b1\u03af\u03b9\u03ba\u03b1"
    ],
    "wof:name":"Papakostaiika",
    "wof:placetype":"locality"
},
  "geometry": {"coordinates":[21.71203,38.04578],"type":"Point"}
}