{
  "type": "Feature",
  "properties": {
    "gn:admin1_code":"ESYE13",
    "gn:admin2_code":"8.0",
    "gn:admin3_code":"9071",
    "gn:asciiname":"Levkon",
    "gn:country_code":"GR",
    "gn:dem":929,
    "gn:feature_class":"P",
    "gn:feature_code":"PPL",
    "gn:name":"Levk\u00f3n",
    "gn:population":116,
    "gn:timezone":"Europe/Athens",
    "iso:country":"GR",
    "name:ell_x_historical":[
        "\u03a0\u03cc\u03c0\u03bb\u03b7",
        "\u03a0\u03ce\u03c0\u03bb\u03b7"
    ],
    "name:ell_x_preferred":[
        "\u039b\u03b5\u03c5\u03ba\u03ce\u03bd\u03b1\u03c2"
    ],
    "name:ell_x_variant":[
        "\u039b\u03b5\u03c5\u03ba\u03ce\u03bd",
        "\u03a0\u03cc\u03c0\u03bb\u03b7",
        "\u03a0\u03ce\u03c0\u03bb\u03b7"
    ],
    "name:eng_x_historical":[
        "Popli"
    ],
    "name:eng_x_preferred":[
        "Lefkonas"
    ],
    "name:eng_x_variant":[
        "Popli"
    ],
    "name:mkd_x_preferred":[
        "\u041f\u2019\u043f\u043b\u0438"
    ],
    "name:und_x_variant":[
        "P\u00f3pli",
        "Levk\u00f3nas",
        "Levk\u00f3n"
    ],
    "wof:name":"Levkon",
    "wof:placetype":"locality",
    "wof:population":116
},
  "geometry": {"coordinates":[21.1401,40.7899],"type":"Point"}
}