{
  "type": "Feature",
  "properties": {
    "gn:admin1_code":"ESYE25",
    "gn:admin2_code":"41.0",
    "gn:admin3_code":"9239",
    "gn:asciiname":"Gefyra",
    "gn:country_code":"GR",
    "gn:dem":419,
    "gn:feature_class":"P",
    "gn:feature_code":"PPL",
    "gn:name":"G\u00e9fyra",
    "gn:population":0,
    "gn:timezone":"Europe/Athens",
    "iso:country":"GR",
    "name:ell_x_preferred":[
        "\u0393\u03ad\u03c6\u03c5\u03c1\u03b1"
    ],
    "name:ell_x_variant":[
        "G\u00e9fyra"
    ],
    "name:und_x_variant":[
        "Kos\u00e9",
        "Kios\u00e9",
        "Y\u00e9fira"
    ],
    "wof:name":"Gefyra",
    "wof:placetype":"locality"
},
  "geometry": {"coordinates":[22.14268,37.36232],"type":"Point"}
}