{
  "type": "Feature",
  "properties": {
    "gn:admin1_code":"ESYE31",
    "gn:admin2_code":"445407.0",
    "gn:admin3_code":"9230",
    "gn:asciiname":"Kryo Pigadi",
    "gn:country_code":"GR",
    "gn:dem":542,
    "gn:feature_class":"P",
    "gn:feature_code":"PPL",
    "gn:name":"Kryo Pig\u00e1di",
    "gn:population":17,
    "gn:timezone":"Europe/Athens",
    "iso:country":"GR",
    "name:ell_x_preferred":[
        "\u039a\u03c1\u03cd\u03bf \u03a0\u03b7\u03b3\u03ac\u03b4\u03b9"
    ],
    "name:eng_x_preferred":[
        "Kryo Pigadi"
    ],
    "name:und_x_variant":[
        "Krio Pigadi"
    ],
    "wof:name":"Kryo Pigadi",
    "wof:placetype":"locality",
    "wof:population":17
},
  "geometry": {"coordinates":[23.29488,38.14401],"type":"Point"}
}