{
  "type": "Feature",
  "properties": {
    "gn:admin1_code":"ESYE23",
    "gn:admin2_code":"31.0",
    "gn:admin3_code":"9125",
    "gn:asciiname":"Malesiada",
    "gn:country_code":"GR",
    "gn:dem":391,
    "gn:feature_class":"P",
    "gn:feature_code":"PPL",
    "gn:name":"Malesi\u00e1da",
    "gn:population":0,
    "gn:timezone":"Europe/Athens",
    "iso:country":"GR",
    "name:ell_x_preferred":[
        "Malesi\u00e1da"
    ],
    "name:ell_x_variant":[
        "\u039c\u03b1\u03bb\u03b5\u03c3\u03b9\u03ac\u03b4\u03b1"
    ],
    "name:und_x_variant":[
        "Malesi\u00e1dha",
        "Melesi\u00e1dha"
    ],
    "wof:name":"Malesiada",
    "wof:placetype":"locality"
},
  "geometry": {"coordinates":[21.33111,38.901],"type":"Point"}
}