{
  "type": "Feature",
  "properties": {
    "gn:admin1_code":"ESYE43",
    "gn:admin2_code":"43.0",
    "gn:admin3_code":"9323",
    "gn:asciiname":"Koulkouthiana",
    "gn:country_code":"GR",
    "gn:dem":80,
    "gn:feature_class":"P",
    "gn:feature_code":"PPL",
    "gn:name":"Koulkouthian\u00e1",
    "gn:population":0,
    "gn:timezone":"Europe/Athens",
    "iso:country":"GR",
    "name:ell_x_preferred":[
        "\u039a\u03bf\u03c5\u03bb\u03ba\u03bf\u03c5\u03b8\u03b9\u03b1\u03bd\u03ac"
    ],
    "name:und_x_variant":[
        "Koulouko\u00fathiana",
        "Koulkouthian\u00e1"
    ],
    "wof:name":"Koulkouthiana",
    "wof:placetype":"locality"
},
  "geometry": {"coordinates":[23.80517,35.47979],"type":"Point"}
}