{
  "type": "Feature",
  "properties": {
    "gn:admin1_code":"ESYE23",
    "gn:admin2_code":"31.0",
    "gn:admin3_code":"9123",
    "gn:asciiname":"Paliochori",
    "gn:country_code":"GR",
    "gn:dem":389,
    "gn:feature_class":"P",
    "gn:feature_code":"PPL",
    "gn:name":"Palioch\u00f3ri",
    "gn:population":0,
    "gn:timezone":"Europe/Athens",
    "iso:country":"GR",
    "name:ell_x_preferred":[
        "Palioch\u00f3ri"
    ],
    "name:ell_x_variant":[
        "\u03a0\u03b1\u03bb\u03b9\u03bf\u03c7\u03ce\u03c1\u03b9"
    ],
    "name:und_x_variant":[
        "Paliokh\u00f3ri"
    ],
    "wof:name":"Paliochori",
    "wof:placetype":"locality"
},
  "geometry": {"coordinates":[21.50597,38.74722],"type":"Point"}
}