{
  "type": "Feature",
  "properties": {
    "gn:admin1_code":"ESYE11",
    "gn:admin2_code":"2.0",
    "gn:admin3_code":"9019",
    "gn:asciiname":"Mystakas",
    "gn:country_code":"GR",
    "gn:dem":40,
    "gn:feature_class":"P",
    "gn:feature_code":"PPL",
    "gn:name":"M\u00fdstakas",
    "gn:population":0,
    "gn:timezone":"Europe/Athens",
    "iso:country":"GR",
    "name:ell_x_preferred":[
        "M\u00fdstakas"
    ],
    "name:ell_x_variant":[
        "\u039c\u03cd\u03c3\u03c4\u03b1\u03ba\u03b1\u03c2",
        "M\u00edstakas"
    ],
    "wof:name":"Mystakas",
    "wof:placetype":"locality"
},
  "geometry": {"coordinates":[25.64946,41.08118],"type":"Point"}
}