{
  "type": "Feature",
  "properties": {
    "gn:admin1_code":"ESYE23",
    "gn:admin2_code":"38.0",
    "gn:admin3_code":"9130",
    "gn:asciiname":"Lakka",
    "gn:country_code":"GR",
    "gn:dem":447,
    "gn:feature_class":"P",
    "gn:feature_code":"PPL",
    "gn:name":"L\u00e1kka",
    "gn:population":147,
    "gn:timezone":"Europe/Athens",
    "iso:country":"GR",
    "name:deu_x_preferred":[
        "Lakka"
    ],
    "name:ell_x_preferred":[
        "\u039b\u03ac\u03ba\u03ba\u03b1"
    ],
    "name:eng_x_preferred":[
        "Lakka"
    ],
    "name:nor_x_preferred":[
        "Lakka"
    ],
    "name:pol_x_preferred":[
        "Lapponia Lakka"
    ],
    "name:swe_x_preferred":[
        "Lakka"
    ],
    "name:und_x_variant":[
        "Gr\u00f3pa",
        "L\u00e1kka"
    ],
    "wof:name":"Lakka",
    "wof:placetype":"locality",
    "wof:population":147
},
  "geometry": {"coordinates":[21.986,38.2389],"type":"Point"}
}