{
  "type": "Feature",
  "properties": {
    "gn:admin1_code":"ESYE23",
    "gn:admin2_code":"38.0",
    "gn:admin3_code":"9132",
    "gn:asciiname":"Agios Dimitrios",
    "gn:country_code":"GR",
    "gn:dem":346,
    "gn:feature_class":"P",
    "gn:feature_code":"PPL",
    "gn:name":"\u00c1gios Dim\u00edtrios",
    "gn:population":0,
    "gn:timezone":"Europe/Athens",
    "iso:country":"GR",
    "name:ell_x_preferred":[
        "\u00c1gios Dim\u00edtrios"
    ],
    "name:ell_x_variant":[
        "\u0386\u03b3\u03b9\u03bf\u03c2 \u0394\u03b7\u03bc\u03ae\u03c4\u03c1\u03b9\u03bf\u03c2"
    ],
    "name:und_x_variant":[
        "\u00c1yios Dhim\u00edtrios"
    ],
    "wof:name":"Agios Dimitrios",
    "wof:placetype":"locality"
},
  "geometry": {"coordinates":[21.76075,37.99961],"type":"Point"}
}