{
  "type": "Feature",
  "properties": {
    "gn:admin1_code":"ESYE22",
    "gn:admin2_code":"27.0",
    "gn:admin3_code":"9120",
    "gn:asciiname":"Kateleios",
    "gn:country_code":"GR",
    "gn:dem":34,
    "gn:feature_class":"P",
    "gn:feature_code":"PPL",
    "gn:name":"Katelei\u00f3s",
    "gn:population":0,
    "gn:timezone":"Europe/Athens",
    "iso:country":"GR",
    "name:ell_x_preferred":[
        "Katelei\u00f3s"
    ],
    "name:ell_x_variant":[
        "\u039a\u03b1\u03c4\u03b5\u03bb\u03b5\u03b9\u03cc\u03c2"
    ],
    "name:und_x_variant":[
        "\u00c1no Kateli\u00f3s"
    ],
    "wof:name":"Kateleios",
    "wof:placetype":"locality"
},
  "geometry": {"coordinates":[20.75339,38.07789],"type":"Point"}
}