{
  "type": "Feature",
  "properties": {
    "gn:admin1_code":"ESYE25",
    "gn:asciiname":"Stafidhokambos",
    "gn:cc2":"GR",
    "gn:country_code":"GR",
    "gn:dem":14,
    "gn:feature_class":"P",
    "gn:feature_code":"PPL",
    "gn:name":"Stafidh\u00f3kambos",
    "gn:population":0,
    "gn:timezone":"Europe/Athens",
    "iso:country":"GR",
    "name:ell_x_preferred":[
        "\u03a3\u03c4\u03b1\u03c6\u03b9\u03b4\u03cc\u03ba\u03b1\u03bc\u03c0\u03bf\u03c2"
    ],
    "name:und_x_variant":[
        "Br\u00e1ti",
        "Stafidh\u00f3kambos"
    ],
    "wof:name":"Stafidhokambos",
    "wof:placetype":"locality"
},
  "geometry": {"coordinates":[21.29236,37.89463],"type":"Point"}
}