{
  "type": "Feature",
  "properties": {
    "gn:admin1_code":"ESYE25",
    "gn:admin2_code":"42.0",
    "gn:admin3_code":"9248",
    "gn:asciiname":"Melissa",
    "gn:country_code":"GR",
    "gn:dem":275,
    "gn:feature_class":"P",
    "gn:feature_code":"PPL",
    "gn:name":"M\u00e9lissa",
    "gn:population":0,
    "gn:timezone":"Europe/Athens",
    "iso:country":"GR",
    "name:ell_x_preferred":[
        "\u039c\u03ad\u03bb\u03b9\u03c3\u03c3\u03b1"
    ],
    "name:und_x_variant":[
        "Malits\u00edna",
        "M\u00e9lissa"
    ],
    "wof:name":"Melissa",
    "wof:placetype":"locality"
},
  "geometry": {"coordinates":[22.45825,36.81605],"type":"Point"}
}