{
  "type": "Feature",
  "properties": {
    "gn:admin1_code":"ESYE25",
    "gn:admin2_code":"42.0",
    "gn:admin3_code":"9248",
    "gn:asciiname":"Melissa",
    "gn:country_code":"GR",
    "gn:dem":275,
    "gn:feature_class":"P",
    "gn:feature_code":"PPL",
    "gn:name":"M\u00e9lissa",
    "gn:population":0,
    "gn:timezone":"Europe/Athens",
    "iso:country":"GR",
    "name:ara_x_preferred":[
        "\u0645\u064a\u0644\u064a\u0633\u0627"
    ],
    "name:bel_x_preferred":[
        "\u041c\u0435\u043b\u0456\u0441\u0430"
    ],
    "name:ces_x_preferred":[
        "Melissa"
    ],
    "name:deu_x_preferred":[
        "Melissa"
    ],
    "name:ell_x_preferred":[
        "\u039c\u03ad\u03bb\u03b9\u03c3\u03c3\u03b1"
    ],
    "name:fin_x_preferred":[
        "Melissa"
    ],
    "name:fra_x_preferred":[
        "Melissa"
    ],
    "name:ind_x_preferred":[
        "Melissa"
    ],
    "name:ita_x_preferred":[
        "Melissa"
    ],
    "name:ltz_x_preferred":[
        "Melissa"
    ],
    "name:nld_x_preferred":[
        "Melissa"
    ],
    "name:nno_x_preferred":[
        "Melissa"
    ],
    "name:nor_x_preferred":[
        "Melissa"
    ],
    "name:ron_x_preferred":[
        "Melissa"
    ],
    "name:rus_x_preferred":[
        "\u041c\u0435\u043b\u0438\u0441\u0441\u0430"
    ],
    "name:swe_x_preferred":[
        "Melissa"
    ],
    "name:tur_x_preferred":[
        "Melissa"
    ],
    "name:und_x_variant":[
        "Malits\u00edna",
        "M\u00e9lissa"
    ],
    "name:zho_x_preferred":[
        "\u6885\u5229\u8428"
    ],
    "wof:name":"Melissa",
    "wof:placetype":"locality"
},
  "geometry": {"coordinates":[22.45825,36.81605],"type":"Point"}
}