{
  "type": "Feature",
  "properties": {
    "gn:admin1_code":"ESYE43",
    "gn:admin2_code":"46.0",
    "gn:admin3_code":"9310.0",
    "gn:asciiname":"Nispitas",
    "gn:country_code":"GR",
    "gn:dem":243,
    "gn:feature_class":"P",
    "gn:feature_code":"PPL",
    "gn:name":"Nisp\u00edtas",
    "gn:population":25,
    "gn:timezone":"Europe/Athens",
    "iso:country":"GR",
    "name:ell_x_preferred":[
        "\u039d\u03b9\u03c3\u03c0\u03ae\u03c4\u03b1\u03c2"
    ],
    "name:eng_x_preferred":[
        "Nispitas"
    ],
    "wof:name":"Nispitas",
    "wof:placetype":"locality",
    "wof:population":25
},
  "geometry": {"coordinates":[25.59671,35.26004000000001],"type":"Point"}
}