{
  "type": "Feature",
  "properties": {
    "gn:admin1_code":"ESYE14",
    "gn:admin2_code":"22.0",
    "gn:admin3_code":"9112",
    "gn:asciiname":"Katalyma",
    "gn:country_code":"GR",
    "gn:dem":228,
    "gn:feature_class":"P",
    "gn:feature_code":"PPL",
    "gn:name":"Kat\u00e1lyma",
    "gn:population":0,
    "gn:timezone":"Europe/Athens",
    "iso:country":"GR",
    "wof:name":"Katalyma",
    "wof:placetype":"locality"
},
  "geometry": {"coordinates":[21.58667,39.69667000000001],"type":"Point"}
}