{
  "type": "Feature",
  "properties": {
    "gn:admin1_code":"ESYE11",
    "gn:admin2_code":"2.0",
    "gn:admin3_code":"9022",
    "gn:asciiname":"Aetokoryfi",
    "gn:country_code":"GR",
    "gn:dem":51,
    "gn:feature_class":"P",
    "gn:feature_code":"PPL",
    "gn:name":"Aetokoryf\u00ed",
    "gn:population":0,
    "gn:timezone":"Europe/Athens",
    "iso:country":"GR",
    "name:ell_x_preferred":[
        "Aetokoryf\u00ed"
    ],
    "name:ell_x_variant":[
        "\u0391\u03b5\u03c4\u03bf\u03ba\u03bf\u03c1\u03c5\u03c6\u03ae",
        "A\u00ebtokorif\u00ed"
    ],
    "wof:name":"Aetokoryfi",
    "wof:placetype":"locality"
},
  "geometry": {"coordinates":[25.61196,40.98054000000001],"type":"Point"}
}