{
  "type": "Feature",
  "properties": {
    "gn:admin1_code":"ESYE14",
    "gn:admin2_code":"21.0",
    "gn:admin3_code":"9103",
    "gn:asciiname":"Platanos",
    "gn:country_code":"GR",
    "gn:dem":331,
    "gn:feature_class":"P",
    "gn:feature_code":"PPL",
    "gn:name":"Pl\u00e1tanos",
    "gn:population":0,
    "gn:timezone":"Europe/Athens",
    "iso:country":"GR",
    "name:ell_x_preferred":[
        "\u03a0\u03bb\u03ac\u03c4\u03b1\u03bd\u03bf\u03c2"
    ],
    "name:und_x_variant":[
        "Chakerl\u00ed",
        "Isakerl\u00edon",
        "Pl\u00e1tanos"
    ],
    "wof:name":"Platanos",
    "wof:placetype":"locality"
},
  "geometry": {"coordinates":[22.51064,39.22519000000001],"type":"Point"}
}