{
  "type": "Feature",
  "properties": {
    "iso:country":"GR",
    "name:ara_x_preferred":[
        "\u062f\u064a\u0627\u0643\u0648\u0628\u062a\u0648"
    ],
    "name:ell_x_preferred":[
        "\u0394\u03ae\u03bc\u03bf\u03c2 \u0394\u03b9\u03b1\u03ba\u03bf\u03c0\u03c4\u03bf\u03cd"
    ],
    "name:ell_x_variant":[
        "\u0394\u03b9\u03b1\u03ba\u03bf\u03c0\u03c4\u03cc \u0391\u03c7\u03b1\u0390\u03b1\u03c2"
    ],
    "name:eng_x_preferred":[
        "Diakopto"
    ],
    "name:fin_x_preferred":[
        "Diakopt\u00f3"
    ],
    "name:fra_x_preferred":[
        "Diakopto"
    ],
    "name:hye_x_preferred":[
        "\u0534\u056b\u0561\u056f\u0578\u057a\u057f\u0578\u0576"
    ],
    "name:ita_x_preferred":[
        "Diakopto"
    ],
    "name:jpn_x_preferred":[
        "\u30c7\u30a3\u30a2\u30b3\u30d7\u30c8"
    ],
    "name:lat_x_preferred":[
        "Diacoptum"
    ],
    "name:nld_x_preferred":[
        "Diakopto"
    ],
    "name:nno_x_preferred":[
        "Diakopt\u00f3"
    ],
    "name:ron_x_preferred":[
        "Diakopto"
    ],
    "name:rus_x_preferred":[
        "\u0414\u044c\u044f\u043a\u043e\u043f\u0442\u043e"
    ],
    "name:rus_x_variant":[
        "\u0414\u0438\u0430\u043a\u043e\u043f\u0442\u043e\u043d"
    ],
    "name:und_x_variant":[
        "Dhiakoft\u00f3n"
    ],
    "qs:a0":"Greece",
    "qs:a1":"*\u0394\u03a5\u03a4\u0399\u039a\u0397 \u0395\u039b\u039b\u0391\u0394\u0391",
    "qs:a1_alt":"DYTIKH ELLADA",
    "qs:a1r":"0",
    "qs:a2_alt":"AXAIA",
    "qs:adm0":"Greece",
    "qs:la_lc":"*",
    "qs:level":"locality",
    "qs:loc":"\u0394\u0399\u0391\u039a\u039f\u03a0\u03a4\u039f\u039d",
    "qs:loc_alt":"DIAKOPTON",
    "qs:pop":0,
    "qs:type":"buffered point",
    "wd:wordcount":334,
    "wof:name":"\u0394\u0399\u0391\u039a\u039f\u03a0\u03a4\u039f\u039d",
    "wof:placetype":"locality"
},
  "geometry": {"coordinates":[22.199222,38.189655],"type":"Point"}
}