{
  "type": "Feature",
  "properties": {
    "gn:gn_country":"GR",
    "gn:gn_fcode":"ADM3",
    "gn:gn_pop":30562,
    "gn:population":26550,
    "iso:country":"GR",
    "name:ell_x_preferred":[
        "\u0391\u03b3\u03af\u03b1\u03c2 \u0392\u03b1\u03c1\u03b2\u03ac\u03c1\u03b1\u03c2"
    ],
    "qs_pg:aaroncc":"GR",
    "qs_pg:gn_country":"GR",
    "qs_pg:gn_fcode":"ADM3",
    "qs_pg:gn_pop":30562,
    "qs_pg:name":"Agia Varvara",
    "qs_pg:name_adm0":"\u0395\u03bb\u03bb\u03ac\u03b4\u03b1",
    "qs_pg:name_adm1":"Attica",
    "qs_pg:photos_9r":0,
    "qs_pg:photos_sr":0,
    "qs_pg:pop_sr":7,
    "qs_pg:qs_pg_placetype":"localadmin",
    "qs_pg:qs_pg_placetype_gp":"LocalAdmin",
    "qs_pg:woe_adm0":23424833,
    "woe:adm0_id":23424833,
    "woe:name_adm0":"\u0395\u03bb\u03bb\u03ac\u03b4\u03b1",
    "woe:name_adm1":"Attica",
    "woe:placetype":"LocalAdmin",
    "wof:name":"Agia Varvara",
    "wof:placetype":"localadmin",
    "wof:population":26550
},
  "geometry": {"coordinates":[23.65697,37.9922],"type":"Point"}
}