{
  "type": "Feature",
  "properties": {
    "gn:gn_country":"GR",
    "gn:gn_fcode":"ADM3",
    "gn:gn_pop":30562,
    "gn:population":26550,
    "iso:country":"GR",
    "name:ara_x_preferred":[
        "\u0623\u063a\u064a\u0627 \u0641\u0627\u0631\u0641\u0627\u0631\u0627"
    ],
    "name:bul_x_preferred":[
        "\u0410\u0433\u0438\u044f \u0412\u0430\u0440\u0432\u0430\u0440\u0430"
    ],
    "name:ceb_x_preferred":[
        "Ag\u00eda Varv\u00e1ra"
    ],
    "name:deu_x_preferred":[
        "Agia Varvara"
    ],
    "name:ell_x_preferred":[
        "\u0391\u03b3\u03af\u03b1\u03c2 \u0392\u03b1\u03c1\u03b2\u03ac\u03c1\u03b1\u03c2"
    ],
    "name:ell_x_variant":[
        "\u0391\u03b3\u03af\u03b1 \u0392\u03b1\u03c1\u03b2\u03ac\u03c1\u03b1 \u0391\u03c4\u03c4\u03b9\u03ba\u03ae\u03c2"
    ],
    "name:fas_x_preferred":[
        "\u0622\u06cc\u06cc\u0627 \u0648\u0627\u0631\u0648\u0627\u0631\u0627"
    ],
    "name:fin_x_preferred":[
        "Ag\u00eda Varv\u00e1ra"
    ],
    "name:fra_x_preferred":[
        "Ag\u00eda Varv\u00e1ra"
    ],
    "name:hye_x_preferred":[
        "\u0531\u0575\u056b\u0561-\u054e\u0561\u0580\u057e\u0561\u057c\u0561"
    ],
    "name:ita_x_preferred":[
        "Agia Varvara"
    ],
    "name:nld_x_preferred":[
        "Agia Varvara"
    ],
    "name:nno_x_preferred":[
        "Aj\u00eda Varv\u00e1ra"
    ],
    "name:pol_x_preferred":[
        "Ajia Warwara"
    ],
    "name:ron_x_preferred":[
        "Agia Varvara"
    ],
    "name:rus_x_preferred":[
        "\u0410\u0439\u0438\u044f-\u0412\u0430\u0440\u0432\u0430\u0440\u0430"
    ],
    "name:spa_x_preferred":[
        "Ag\u00eda Varvara"
    ],
    "name:srp_x_preferred":[
        "\u0410\u0433\u0438\u0458\u0430 \u0412\u0430\u0440\u0432\u0430\u0440\u0430"
    ],
    "name:swe_x_preferred":[
        "Ag\u00eda Varv\u00e1ra"
    ],
    "name:tur_x_preferred":[
        "Aya Varvara"
    ],
    "name:ukr_x_preferred":[
        "\u0410\u044f-\u0412\u0430\u0440\u0432\u0430\u0440\u0430"
    ],
    "name:urd_x_preferred":[
        "\u0622\u0626\u06cc\u0627 \u0648\u0627\u0648\u0627\u0631\u0627"
    ],
    "name:vie_x_preferred":[
        "Agia Varvara"
    ],
    "name:zho_x_preferred":[
        "\u963f\u5947\u4e9e\u74e6\u723e\u74e6\u62c9"
    ],
    "qs_pg:aaroncc":"GR",
    "qs_pg:gn_country":"GR",
    "qs_pg:gn_fcode":"ADM3",
    "qs_pg:gn_pop":30562,
    "qs_pg:name":"Agia Varvara",
    "qs_pg:name_adm0":"\u0395\u03bb\u03bb\u03ac\u03b4\u03b1",
    "qs_pg:name_adm1":"Attica",
    "qs_pg:photos_9r":0,
    "qs_pg:photos_sr":0,
    "qs_pg:pop_sr":7,
    "qs_pg:qs_pg_placetype":"localadmin",
    "qs_pg:qs_pg_placetype_gp":"LocalAdmin",
    "qs_pg:woe_adm0":23424833,
    "woe:adm0_id":23424833,
    "woe:name_adm0":"\u0395\u03bb\u03bb\u03ac\u03b4\u03b1",
    "woe:name_adm1":"Attica",
    "woe:placetype":"LocalAdmin",
    "wof:name":"Agia Varvara",
    "wof:placetype":"localadmin",
    "wof:population":26550
},
  "geometry": {"coordinates":[23.65697,37.9922],"type":"Point"}
}