{
  "type": "Feature",
  "properties": {
    "gn:admin1_code":"ESYE24",
    "gn:admin2_code":"34.0",
    "gn:admin3_code":"9152",
    "gn:asciiname":"Kato Lofiskos",
    "gn:country_code":"GR",
    "gn:dem":74,
    "gn:feature_class":"P",
    "gn:feature_code":"PPL",
    "gn:name":"K\u00e1to Lof\u00edskos",
    "gn:population":0,
    "gn:timezone":"Europe/Athens",
    "iso:country":"GR",
    "name:ell_x_preferred":[
        "K\u00e1to Lof\u00edskos"
    ],
    "name:ell_x_variant":[
        "\u039a\u03ac\u03c4\u03c9 \u039b\u03bf\u03c6\u03af\u03c3\u03ba\u03bf\u03c2"
    ],
    "name:und_x_variant":[
        "Sklir\u00f3"
    ],
    "wof:name":"Kato Lofiskos",
    "wof:placetype":"locality"
},
  "geometry": {"coordinates":[24.11753,38.47525],"type":"Point"}
}