{
  "type": "Feature",
  "properties": {
    "gn:gn_country":"GR",
    "gn:gn_fcode":"PPL",
    "gn:gn_pop":150,
    "gn:population":150,
    "iso:country":"GR",
    "name:ell_x_preferred":[
        "Kolch\u00edda"
    ],
    "name:ell_x_variant":[
        "\u039a\u03bf\u03bb\u03c7\u03af\u03b4\u03b1",
        "\u039a\u03bf\u03bb\u03c7\u03af\u03c2"
    ],
    "name:unk_x_variant":[
        "Kolkh\u00eds"
    ],
    "qs_pg:aaroncc":"GR",
    "qs_pg:gn_country":"GR",
    "qs_pg:gn_fcode":"PPL",
    "qs_pg:gn_pop":150,
    "qs_pg:name":"Kolch\u00eds",
    "qs_pg:photos_9r":0,
    "qs_pg:photos_sr":0,
    "qs_pg:pop_sr":1,
    "qs_pg:qs_pg_placetype":"locality",
    "wof:name":"Kolch\u00eds",
    "wof:placetype":"locality",
    "wof:population":150
},
  "geometry": {"coordinates":[22.88944,40.94056],"type":"Point"}
}