{
  "type": "Feature",
  "properties": {
    "gn:admin1_code":"ESYE25",
    "gn:admin2_code":"41.0",
    "gn:admin3_code":"9239",
    "gn:asciiname":"Akovos",
    "gn:country_code":"GR",
    "gn:dem":907,
    "gn:feature_class":"P",
    "gn:feature_code":"PPL",
    "gn:name":"\u00c1kovos",
    "gn:population":0,
    "gn:timezone":"Europe/Athens",
    "iso:country":"GR",
    "name:ell_x_preferred":[
        "\u0386\u03ba\u03bf\u03b2\u03bf\u03c2"
    ],
    "name:und_x_variant":[
        "\u00c1kovos"
    ],
    "wof:name":"Akovos",
    "wof:placetype":"locality"
},
  "geometry": {"coordinates":[22.16206,37.19300000000001],"type":"Point"}
}