{
  "type": "Feature",
  "properties": {
    "gn:admin1_code":"ESYE12",
    "gn:admin2_code":"13.0",
    "gn:admin3_code":"9030",
    "gn:asciiname":"Kladharon",
    "gn:country_code":"GR",
    "gn:dem":292,
    "gn:feature_class":"P",
    "gn:feature_code":"PPL",
    "gn:name":"Kladharon",
    "gn:population":0,
    "gn:timezone":"Europe/Athens",
    "iso:country":"GR",
    "name:und_x_variant":[
        "Chip\u00edsl\u00ed",
        "Kladharon",
        "Kladher\u00f3n"
    ],
    "wof:name":"Kladharon",
    "wof:placetype":"locality"
},
  "geometry": {"coordinates":[23.13333,40.41667],"type":"Point"}
}