{
  "type": "Feature",
  "properties": {
    "gn:admin1_code":"ESYE13",
    "gn:admin2_code":"10.0",
    "gn:admin3_code":"9062",
    "gn:asciiname":"Anoixi",
    "gn:country_code":"GR",
    "gn:dem":557,
    "gn:feature_class":"P",
    "gn:feature_code":"PPL",
    "gn:name":"\u00c1noixi",
    "gn:population":167,
    "gn:timezone":"Europe/Athens",
    "iso:country":"GR",
    "name:ell_x_preferred":[
        "\u0386\u03bd\u03bf\u03b9\u03be\u03b7"
    ],
    "name:und_x_variant":[
        "Gr\u00e9os",
        "\u00c1noixi",
        "Gri\u00e1",
        "\u00c1noixis"
    ],
    "wof:name":"Anoixi",
    "wof:placetype":"locality",
    "wof:population":167
},
  "geometry": {"coordinates":[21.57282,39.9136],"type":"Point"}
}