{
  "type": "Feature",
  "properties": {
    "gn:admin1_code":"ESYE21",
    "gn:admin2_code":"20.0",
    "gn:admin3_code":"9074",
    "gn:asciiname":"Manifavaiika",
    "gn:country_code":"GR",
    "gn:dem":615,
    "gn:feature_class":"P",
    "gn:feature_code":"PPL",
    "gn:name":"Manifava\u00edika",
    "gn:population":0,
    "gn:timezone":"Europe/Athens",
    "iso:country":"GR",
    "wof:name":"Manifavaiika",
    "wof:placetype":"locality"
},
  "geometry": {"coordinates":[21.21611,39.13417000000001],"type":"Point"}
}