{
  "type": "Feature",
  "properties": {
    "gn:admin1_code":"ESYE25",
    "gn:admin2_code":"42.0",
    "gn:admin3_code":"9248",
    "gn:asciiname":"Pyrrichos",
    "gn:country_code":"GR",
    "gn:dem":397,
    "gn:feature_class":"P",
    "gn:feature_code":"PPL",
    "gn:name":"P\u00fdrrichos",
    "gn:population":32,
    "gn:timezone":"Europe/Athens",
    "iso:country":"GR",
    "name:ell_x_preferred":[
        "\u03a0\u03cd\u03c1\u03c1\u03b9\u03c7\u03bf\u03c2"
    ],
    "name:und_x_variant":[
        "K\u00e1valon",
        "P\u00edrrikhos",
        "Pyrrichos"
    ],
    "wof:name":"Pyrrichos",
    "wof:placetype":"locality",
    "wof:population":32
},
  "geometry": {"coordinates":[22.4358,36.65667],"type":"Point"}
}