{
  "type": "Feature",
  "properties": {
    "gn:admin1_code":"ESYE23",
    "gn:admin2_code":"39.0",
    "gn:admin3_code":"9138",
    "gn:asciiname":"Kotroni",
    "gn:country_code":"GR",
    "gn:dem":767,
    "gn:feature_class":"P",
    "gn:feature_code":"PPL",
    "gn:name":"Kotr\u00f3ni",
    "gn:population":0,
    "gn:timezone":"Europe/Athens",
    "iso:country":"GR",
    "name:ell_x_historical":[
        "\u039a\u03bf\u03c4\u03c1\u03ce\u03bd\u03b9\u03bf\u03bd"
    ],
    "name:ell_x_preferred":[
        "\u039a\u03bf\u03c4\u03c1\u03ce\u03bd\u03b9"
    ],
    "name:ell_x_variant":[
        "Kotr\u00f3ni",
        "Kotr\u00f3nion",
        "\u039a\u03bf\u03c4\u03c1\u03ce\u03bd\u03b9\u03bf\u03bd",
        "\u039a\u03bf\u03c4\u03c1\u03ce\u03bd\u03b9 \u039c\u03af\u03bd\u03b8\u03b7\u03c2"
    ],
    "wof:name":"Kotroni",
    "wof:placetype":"locality"
},
  "geometry": {"coordinates":[21.75694,37.50692],"type":"Point"}
}