{
  "type": "Feature",
  "properties": {
    "gn:admin1_code":"ESYE42",
    "gn:admin2_code":"47.0",
    "gn:admin3_code":"9296.0",
    "gn:asciiname":"Agia Eleousa",
    "gn:country_code":"GR",
    "gn:dem":239,
    "gn:feature_class":"P",
    "gn:feature_code":"PPL",
    "gn:name":"Agia Eleo\u00fasa",
    "gn:population":0,
    "gn:timezone":"Europe/Athens",
    "iso:country":"GR",
    "name:ell_x_preferred":[
        "\u0391\u03b3\u03af\u03b1 \u0395\u03bb\u03b5\u03bf\u03cd\u03c3\u03b1"
    ],
    "wof:name":"Agia Eleousa",
    "wof:placetype":"locality"
},
  "geometry": {"coordinates":[28.03707,36.27401],"type":"Point"}
}