{
  "type": "Feature",
  "properties": {
    "gn:admin1_code":"ESYE24",
    "gn:admin2_code":"29.0",
    "gn:admin3_code":"9164",
    "gn:asciiname":"Dhrymaria",
    "gn:country_code":"GR",
    "gn:dem":5,
    "gn:feature_class":"P",
    "gn:feature_code":"PPL",
    "gn:name":"Dhrym\u00e1ria",
    "gn:population":2,
    "gn:timezone":"Europe/Athens",
    "iso:country":"GR",
    "name:ell_x_preferred":[
        "\u0394\u03c1\u03c5\u03bc\u03ac\u03c1\u03b9\u03b1"
    ],
    "name:eng_x_preferred":[
        "Drymaria"
    ],
    "wof:name":"Dhrymaria",
    "wof:placetype":"locality",
    "wof:population":2
},
  "geometry": {"coordinates":[22.9934,38.95841],"type":"Point"}
}