{
  "type": "Feature",
  "properties": {
    "gn:gn_country":"GR",
    "gn:gn_fcode":"PPL",
    "gn:gn_pop":1193,
    "gn:population":1258,
    "iso:country":"GR",
    "name:ell_x_preferred":[
        "\u0393\u03c1\u03b1\u03bc\u03bc\u03b5\u03bd\u03af\u03c4\u03c3\u03b1"
    ],
    "name:eng_x_preferred":[
        "Grammenitsa"
    ],
    "name:unk_x_variant":[
        "Gramen\u00edtsa"
    ],
    "qs_pg:aaroncc":"GR",
    "qs_pg:gn_country":"GR",
    "qs_pg:gn_fcode":"PPL",
    "qs_pg:gn_pop":1193,
    "qs_pg:name":"Grammenitsa",
    "qs_pg:name_adm0":"\u0395\u03bb\u03bb\u03ac\u03b4\u03b1",
    "qs_pg:name_adm1":"Epirus and Western Macedonia",
    "qs_pg:photos_9r":0,
    "qs_pg:photos_sr":0,
    "qs_pg:pop_sr":3,
    "qs_pg:qs_pg_placetype":"locality",
    "qs_pg:qs_pg_placetype_gp":"Town",
    "qs_pg:woe_adm0":23424833,
    "woe:adm0_id":23424833,
    "woe:name_adm0":"\u0395\u03bb\u03bb\u03ac\u03b4\u03b1",
    "woe:name_adm1":"Epirus and Western Macedonia",
    "woe:placetype":"Town",
    "wof:name":"Grammenitsa",
    "wof:placetype":"locality",
    "wof:population":1258
},
  "geometry": {"coordinates":[20.98056,39.18306],"type":"Point"}
}