{
  "type": "Feature",
  "properties": {
    "gn:admin1_code":"ESYE43",
    "gn:admin2_code":"45.0",
    "gn:admin3_code":"9303",
    "gn:asciiname":"Apostolianos",
    "gn:cc2":"GR",
    "gn:country_code":"GR",
    "gn:dem":433,
    "gn:feature_class":"P",
    "gn:feature_code":"PPL",
    "gn:name":"Apostolian\u00f3s",
    "gn:population":0,
    "gn:timezone":"Europe/Athens",
    "iso:country":"GR",
    "name:und_x_variant":[
        "Apostoliano\u00fa",
        "Apostolian\u00f3",
        "Apostolian\u00f3s"
    ],
    "wof:name":"Apostolianos",
    "wof:placetype":"locality"
},
  "geometry": {"coordinates":[25.38333,35.03333],"type":"Point"}
}