{
  "type": "Feature",
  "properties": {
    "gn:admin1_code":"ESYE14",
    "gn:admin2_code":"24.0",
    "gn:admin3_code":"9110",
    "gn:asciiname":"Platanias",
    "gn:country_code":"GR",
    "gn:dem":8,
    "gn:feature_class":"P",
    "gn:feature_code":"PPL",
    "gn:name":"Platanias",
    "gn:population":0,
    "gn:timezone":"Europe/Athens",
    "iso:country":"GR",
    "name:cat_x_preferred":[
        "Platani\u00e0s"
    ],
    "name:ceb_x_preferred":[
        "Platani\u00e1s"
    ],
    "name:deu_x_preferred":[
        "Platanias"
    ],
    "name:ell_x_preferred":[
        "\u0394\u03ae\u03bc\u03bf\u03c2 \u03a0\u03bb\u03b1\u03c4\u03b1\u03bd\u03b9\u03ac"
    ],
    "name:fin_x_preferred":[
        "Platani\u00e1s"
    ],
    "name:fra_x_preferred":[
        "Platanias"
    ],
    "name:ita_x_preferred":[
        "Platanias"
    ],
    "name:nld_x_preferred":[
        "Platanias"
    ],
    "name:nno_x_preferred":[
        "Platani\u00e1s"
    ],
    "name:nor_x_preferred":[
        "Platanias"
    ],
    "name:pol_x_preferred":[
        "Platanias"
    ],
    "name:por_x_preferred":[
        "Platani\u00e1s"
    ],
    "name:rus_x_preferred":[
        "\u041f\u043b\u0430\u0442\u0430\u043d\u044c\u044f\u0441"
    ],
    "name:spa_x_preferred":[
        "Platanias"
    ],
    "name:tur_x_preferred":[
        "Platanyas"
    ],
    "name:vie_x_preferred":[
        "Platanias"
    ],
    "name:zho_x_preferred":[
        "\u666e\u62c9\u5766\u4e9a\u65af"
    ],
    "wof:name":"Platanias",
    "wof:placetype":"locality"
},
  "geometry": {"coordinates":[23.43837000000001,39.14431],"type":"Point"}
}