{
  "type": "Feature",
  "properties": {
    "gn:admin1_code":"ESYE14",
    "gn:admin2_code":"24.0",
    "gn:admin3_code":"9110",
    "gn:asciiname":"Platanias",
    "gn:country_code":"GR",
    "gn:dem":8,
    "gn:feature_class":"P",
    "gn:feature_code":"PPL",
    "gn:name":"Platanias",
    "gn:population":0,
    "gn:timezone":"Europe/Athens",
    "iso:country":"GR",
    "wof:name":"Platanias",
    "wof:placetype":"locality"
},
  "geometry": {"coordinates":[23.43837000000001,39.14431],"type":"Point"}
}