{
  "type": "Feature",
  "properties": {
    "gn:admin1_code":"ESYE43",
    "gn:admin2_code":"43.0",
    "gn:admin3_code":"9321",
    "gn:asciiname":"Livadhaki",
    "gn:country_code":"GR",
    "gn:dem":610,
    "gn:feature_class":"P",
    "gn:feature_code":"PPL",
    "gn:name":"Livadh\u00e1ki",
    "gn:population":0,
    "gn:timezone":"Europe/Athens",
    "iso:country":"GR",
    "wof:name":"Livadhaki",
    "wof:placetype":"locality"
},
  "geometry": {"coordinates":[23.83333,35.33333],"type":"Point"}
}