{
  "type": "Feature",
  "properties": {
    "gn:admin1_code":"ESYE42",
    "gn:admin2_code":"47.0",
    "gn:admin3_code":"9280",
    "gn:asciiname":"Pyles",
    "gn:country_code":"GR",
    "gn:dem":328,
    "gn:feature_class":"P",
    "gn:feature_code":"PPL",
    "gn:name":"Pyl\u00e9s",
    "gn:population":0,
    "gn:timezone":"Europe/Athens",
    "iso:country":"GR",
    "name:ell_x_preferred":[
        "Pyl\u00e9s"
    ],
    "name:ell_x_variant":[
        "\u03a0\u03c5\u03bb\u03ad\u03c2",
        "Pyla\u00ed",
        "\u03a0\u03c5\u03bb\u03b1\u03af"
    ],
    "name:und_x_variant":[
        "Pil\u00e9s",
        "Pile",
        "Pila\u00ed"
    ],
    "wof:name":"Pyles",
    "wof:placetype":"locality"
},
  "geometry": {"coordinates":[27.13351,35.53187],"type":"Point"}
}