{
  "type": "Feature",
  "properties": {
    "gn:country":"GR",
    "gn:fcode":"ADM3",
    "gn:population":11470,
    "iso:country":"GR",
    "name:ara_x_preferred":[
        "\u0643\u064a\u0633\u0627\u0645\u0648\u0633"
    ],
    "name:bul_x_preferred":[
        "\u041a\u0438\u0441\u0430\u043c\u043e\u0441"
    ],
    "name:cat_x_preferred":[
        "K\u00edssamos"
    ],
    "name:ceb_x_preferred":[
        "K\u00edssamos"
    ],
    "name:deu_x_preferred":[
        "Kissamos"
    ],
    "name:ell_x_preferred":[
        "\u039a\u03b9\u03c3\u03c3\u03ac\u03bc\u03bf\u03c5"
    ],
    "name:ell_x_variant":[
        "\u039a\u03af\u03c3\u03c3\u03b1\u03bc\u03bf\u03c2",
        "\u039a\u03af\u03c3\u03b1\u03bc\u03bf\u03c2"
    ],
    "name:est_x_preferred":[
        "K\u00edssamos"
    ],
    "name:fin_x_preferred":[
        "K\u00edssamos"
    ],
    "name:fra_x_preferred":[
        "Kissamos"
    ],
    "name:ita_x_preferred":[
        "Kissamos"
    ],
    "name:lat_x_preferred":[
        "Cissamus"
    ],
    "name:lit_x_preferred":[
        "Kisamas"
    ],
    "name:nld_x_preferred":[
        "Kissamos"
    ],
    "name:nno_x_preferred":[
        "K\u00edssamos"
    ],
    "name:pol_x_preferred":[
        "Kisamos"
    ],
    "name:por_x_preferred":[
        "C\u00edssamos"
    ],
    "name:rus_x_preferred":[
        "\u041a\u0438\u0441\u0430\u043c\u043e\u0441"
    ],
    "name:spa_x_preferred":[
        "K\u00edsamos"
    ],
    "name:swe_x_preferred":[
        "Kissamos"
    ],
    "name:tur_x_preferred":[
        "Kisamu"
    ],
    "name:urd_x_preferred":[
        "\u06a9\u06cc\u0633\u0627\u0645\u0648\u0633"
    ],
    "name:vie_x_preferred":[
        "Kissamos"
    ],
    "qs_pg:aaroncc":"GR",
    "qs_pg:gn_country":"GR",
    "qs_pg:gn_fcode":"ADM3",
    "qs_pg:gn_pop":11470,
    "qs_pg:name":"Kissamos",
    "qs_pg:name_adm0":"\u0395\u03bb\u03bb\u03ac\u03b4\u03b1",
    "qs_pg:name_adm1":"Crete",
    "qs_pg:photos_9k":11,
    "qs_pg:photos_9r":10,
    "qs_pg:photos_all":2569,
    "qs_pg:photos_sr":0,
    "qs_pg:pop_sr":6,
    "qs_pg:qs_pg_placetype":"localadmin",
    "qs_pg:qs_pg_placetype_gp":"LocalAdmin",
    "qs_pg:woe_adm0":23424833,
    "woe:adm0_id":23424833,
    "woe:name_adm0":"\u0395\u03bb\u03bb\u03ac\u03b4\u03b1",
    "woe:name_adm1":"Crete",
    "woe:placetype":"LocalAdmin",
    "wof:name":"Kissamos",
    "wof:placetype":"localadmin",
    "wof:population":11470
},
  "geometry": {"coordinates":[23.6558,35.48965],"type":"Point"}
}