{
  "type": "Feature",
  "properties": {
    "gn:admin1_code":"ESYE23",
    "gn:admin2_code":"38.0",
    "gn:admin3_code":"9133",
    "gn:asciiname":"Ano Lousoi",
    "gn:country_code":"GR",
    "gn:dem":1099,
    "gn:feature_class":"P",
    "gn:feature_code":"PPL",
    "gn:name":"\u00c1no Louso\u00ed",
    "gn:population":0,
    "gn:timezone":"Europe/Athens",
    "iso:country":"GR",
    "name:ell_x_preferred":[
        "\u0386\u03bd\u03c9 \u039b\u03bf\u03c5\u03c3\u03bf\u03af"
    ],
    "name:und_x_variant":[
        "Soudhen\u00e1 Theot\u00f3kou",
        "\u00c1no Souden\u00e1",
        "\u00c1no Louso\u00ed"
    ],
    "wof:name":"Ano Lousoi",
    "wof:placetype":"locality"
},
  "geometry": {"coordinates":[22.1395,38.00131],"type":"Point"}
}