{
  "type": "Feature",
  "properties": {
    "gn:admin1_code":"ESYE25",
    "gn:admin2_code":"42.0",
    "gn:admin3_code":"9250",
    "gn:asciiname":"Ampelochori",
    "gn:country_code":"GR",
    "gn:dem":180,
    "gn:feature_class":"P",
    "gn:feature_code":"PPL",
    "gn:name":"Ampeloch\u00f3ri",
    "gn:population":0,
    "gn:timezone":"Europe/Athens",
    "iso:country":"GR",
    "name:ell_x_preferred":[
        "Ampeloch\u00f3ri"
    ],
    "name:ell_x_variant":[
        "\u0391\u03bc\u03c0\u03b5\u03bb\u03bf\u03c7\u03ce\u03c1\u03b9",
        "Ampeloch\u00f3rion",
        "\u0391\u03bc\u03c0\u03b5\u03bb\u03bf\u03c7\u03ce\u03c1\u03b9\u03bf\u03bd"
    ],
    "name:und_x_variant":[
        "Gr\u00e1mmousa",
        "Gr\u00e1mousa"
    ],
    "wof:name":"Ampelochori",
    "wof:placetype":"locality"
},
  "geometry": {"coordinates":[22.6531,36.90601],"type":"Point"}
}