{
  "type": "Feature",
  "properties": {
    "gn:admin1_code":"ESYE23",
    "gn:admin2_code":"38.0",
    "gn:admin3_code":"9132",
    "gn:asciiname":"Mirali",
    "gn:country_code":"GR",
    "gn:dem":556,
    "gn:feature_class":"P",
    "gn:feature_code":"PPL",
    "gn:name":"M\u00edrali",
    "gn:population":0,
    "gn:timezone":"Europe/Athens",
    "iso:country":"GR",
    "name:ell_x_preferred":[
        "M\u00edrali"
    ],
    "name:ell_x_variant":[
        "M\u00edralion",
        "\u039c\u03af\u03c1\u03b1\u03bb\u03b9",
        "\u039c\u03af\u03c1\u03b1\u03bb\u03b9\u03bf\u03bd"
    ],
    "wof:name":"Mirali",
    "wof:placetype":"locality"
},
  "geometry": {"coordinates":[21.81575,38.10794],"type":"Point"}
}