{
  "type": "Feature",
  "properties": {
    "gn:admin1_code":"ESYE25",
    "gn:admin2_code":"36.0",
    "gn:admin3_code":"9235",
    "gn:asciiname":"Avlona",
    "gn:country_code":"GR",
    "gn:dem":70,
    "gn:feature_class":"P",
    "gn:feature_code":"PPL",
    "gn:name":"Avl\u00f3na",
    "gn:population":80,
    "gn:timezone":"Europe/Athens",
    "iso:country":"GR",
    "name:ell_x_preferred":[
        "\u0391\u03c5\u03bb\u03ce\u03bd\u03b1"
    ],
    "name:eng_x_preferred":[
        "Avlona"
    ],
    "wof:name":"Avlona",
    "wof:placetype":"locality",
    "wof:population":80
},
  "geometry": {"coordinates":[23.16467,37.3926],"type":"Point"}
}