{
  "type": "Feature",
  "properties": {
    "gn:admin1_code":"ESYE43",
    "gn:admin2_code":"45.0",
    "gn:admin3_code":"9304",
    "gn:asciiname":"Apoini",
    "gn:country_code":"GR",
    "gn:dem":303,
    "gn:feature_class":"P",
    "gn:feature_code":"PPL",
    "gn:name":"Apo\u1e2fni",
    "gn:population":0,
    "gn:timezone":"Europe/Athens",
    "iso:country":"GR",
    "name:ell_x_preferred":[
        "\u0391\u03c0\u03bf\u0390\u03bd\u03b9"
    ],
    "name:ell_x_variant":[
        "\u0391\u03c0\u03bf\u0390\u03bd\u03b9\u03bf\u03bd"
    ],
    "name:und_x_variant":[
        "Apo\u1e2fni",
        "Apo\u1e2fnion"
    ],
    "wof:name":"Apoini",
    "wof:placetype":"locality"
},
  "geometry": {"coordinates":[25.1228,35.05229],"type":"Point"}
}