{
  "type": "Feature",
  "properties": {
    "gn:country":"GR",
    "gn:fcode":"PPL",
    "gn:population":31,
    "iso:country":"GR",
    "name:bul_x_preferred":[
        "\u041f\u043e\u043b\u0438\u0444\u0438\u0442\u043e"
    ],
    "name:ell_x_preferred":[
        "\u03a0\u03bf\u03bb\u03cd\u03c6\u03c5\u03c4\u03bf"
    ],
    "name:ell_x_variant":[
        "\u03a0\u03bf\u03bb\u03cd\u03c6\u03c5\u03c4\u03bf\u03bd",
        "\u03a0\u03bf\u03bb\u03cd\u03c6\u03c5\u03c4\u03bf \u039a\u03bf\u03b6\u03ac\u03bd\u03b7\u03c2"
    ],
    "name:eng_x_preferred":[
        "Polyfyto"
    ],
    "name:mkd_x_preferred":[
        "\u0412\u0438\u0442\u0438\u0432\u0458\u0430\u043d\u0438"
    ],
    "name:nld_x_preferred":[
        "Polyfyto"
    ],
    "name:und_x_variant":[
        "Pol\u00edfiton"
    ],
    "qs_pg:aaroncc":"GR",
    "qs_pg:gn_country":"GR",
    "qs_pg:gn_fcode":"PPL",
    "qs_pg:gn_pop":31,
    "qs_pg:name":"Pol\u00fdfyton",
    "qs_pg:photos_9r":0,
    "qs_pg:photos_sr":0,
    "qs_pg:pop_sr":1,
    "qs_pg:qs_pg_placetype":"locality",
    "wof:name":"Pol\u00fdfyton",
    "wof:placetype":"locality",
    "wof:population":31
},
  "geometry": {"coordinates":[22.11444,40.31639],"type":"Point"}
}