{
  "type": "Feature",
  "properties": {
    "gn:admin1_code":"ESYE11",
    "gn:admin2_code":"14.0",
    "gn:admin3_code":"9011",
    "gn:asciiname":"Chrysi Ammoudia",
    "gn:country_code":"GR",
    "gn:dem":22,
    "gn:feature_class":"P",
    "gn:feature_code":"PPL",
    "gn:name":"Chrys\u00ed Ammoudi\u00e1",
    "gn:population":77,
    "gn:timezone":"Europe/Athens",
    "iso:country":"GR",
    "name:ell_x_preferred":[
        "\u03a7\u03c1\u03c5\u03c3\u03ae \u0391\u03bc\u03bc\u03bf\u03c5\u03b4\u03b9\u03ac"
    ],
    "name:ell_x_variant":[
        "\u03a3\u03ba\u03ac\u03bb\u03b1 \u03a0\u03b1\u03bd\u03b1\u03b3\u03af\u03b1\u03c2"
    ],
    "name:eng_x_colloquial":[
        "Golden Beach"
    ],
    "name:eng_x_preferred":[
        "Chrysi Ammoudia"
    ],
    "name:eng_x_variant":[
        "Skala Panagias",
        "Golden Beach"
    ],
    "wof:name":"Chrysi Ammoudia",
    "wof:placetype":"locality",
    "wof:population":77
},
  "geometry": {"coordinates":[24.75767,40.72892],"type":"Point"}
}