{
  "type": "Feature",
  "properties": {
    "gn:gn_country":"GR",
    "gn:gn_fcode":"PPL",
    "gn:gn_pop":713,
    "gn:population":713,
    "iso:country":"GR",
    "name:ara_x_preferred":[
        "\u0646\u064a \u0643\u064a\u0631\u0627\u0633\u064a\u0627\u060c \u062b\u064a\u0633\u0627\u0644\u0648\u0646\u064a\u0643\u064a"
    ],
    "name:bul_x_preferred":[
        "\u041d\u0435\u0430 \u041a\u0435\u0440\u0430\u0441\u0438\u044f"
    ],
    "name:dut_x_preferred":[
        "Nea Kerasia"
    ],
    "name:ell_x_preferred":[
        "\u039d\u03ad\u03b1 \u039a\u03b5\u03c1\u03b1\u03c3\u03b9\u03ac"
    ],
    "name:eng_x_preferred":[
        "Nea Kerasia"
    ],
    "name:gre_x_preferred":[
        "\u039d\u03ad\u03b1 \u039a\u03b5\u03c1\u03b1\u03c3\u03b9\u03ac \u0398\u03b5\u03c3\u03c3\u03b1\u03bb\u03bf\u03bd\u03af\u03ba\u03b7\u03c2"
    ],
    "name:mac_x_preferred":[
        "\u040c\u0443\u0447\u0443\u043a \u041a\u0430\u0440\u0430 \u0411\u0443\u0440\u0443\u043d"
    ],
    "name:swe_x_preferred":[
        "N\u00e9a Kerasi\u00e1"
    ],
    "name:unk_x_variant":[
        "Keras\u00e9a"
    ],
    "qs_pg:aaroncc":"GR",
    "qs_pg:gn_country":"GR",
    "qs_pg:gn_fcode":"PPL",
    "qs_pg:gn_pop":713,
    "qs_pg:name":"N\u00e9a Kerasi\u00e1",
    "qs_pg:photos_9r":0,
    "qs_pg:photos_sr":0,
    "qs_pg:pop_sr":2,
    "qs_pg:qs_pg_placetype":"locality",
    "wof:name":"N\u00e9a Kerasi\u00e1",
    "wof:placetype":"locality",
    "wof:population":713
},
  "geometry": {"coordinates":[22.86921,40.47596],"type":"Point"}
}