{
  "type": "Feature",
  "properties": {
    "gn:elevation":148,
    "gn:population":961,
    "iso:country":"GR",
    "name:ell_x_historical":[
        "\u03a4\u03c3\u03ac\u03ba\u03c9\u03bd\u03b5\u03c2",
        "\u03a4\u03c3\u03ac\u03ba\u03c9\u03bd \u039c\u03b1\u03c7\u03b1\u03bb\u03ac"
    ],
    "name:ell_x_preferred":[
        "\u03a4\u03c3\u03ac\u03ba\u03bf\u03b9"
    ],
    "name:ell_x_variant":[
        "\u03a4\u03c3\u03ac\u03ba\u03c9\u03bd\u03b5\u03c2",
        "\u03a4\u03c3\u03ac\u03ba\u03c9\u03bd \u039c\u03b1\u03c7\u03b1\u03bb\u03ac"
    ],
    "name:und_x_variant":[
        "Ts\u00e1kones"
    ],
    "qs:a0":"Greece",
    "qs:a1":"*\u039a\u0395\u039d\u03a4\u03a1\u0399\u039a\u0397 \u039c\u0391\u039a\u0395\u0394\u039f\u039d\u0399\u0391",
    "qs:a1_alt":"KENTRIKH MAKEDONIA",
    "qs:a1r":"0",
    "qs:a2_alt":"PELLA",
    "qs:adm0":"Greece",
    "qs:la_lc":"*",
    "qs:level":"locality",
    "qs:loc":"\u03a4\u03a3\u0391\u039a\u039f\u0399",
    "qs:loc_alt":"TSAKOI",
    "qs:pop":0,
    "qs:type":"buffered point",
    "wof:name":"\u03a4\u03a3\u0391\u039a\u039f\u0399",
    "wof:placetype":"locality",
    "wof:population":961
},
  "geometry": {"coordinates":[22.042154,40.955902],"type":"Point"}
}