{
  "type": "Feature",
  "properties": {
    "gn:admin1_code":"ESYE13",
    "gn:admin2_code":"11.0",
    "gn:admin3_code":"9066",
    "gn:asciiname":"Loukomi",
    "gn:country_code":"GR",
    "gn:dem":710,
    "gn:feature_class":"P",
    "gn:feature_code":"PPL",
    "gn:name":"Louk\u00f3mi",
    "gn:population":0,
    "gn:timezone":"Europe/Athens",
    "iso:country":"GR",
    "name:bul_x_preferred":[
        "\u041b\u0443\u043a\u043e\u043c\u0438"
    ],
    "name:ell_x_preferred":[
        "Louk\u00f3mi"
    ],
    "name:ell_x_variant":[
        "\u039b\u03bf\u03c5\u03ba\u03cc\u03bc\u03b9"
    ],
    "name:mkd_x_preferred":[
        "\u041b\u043e\u043a\u043e\u043c"
    ],
    "wof:name":"Loukomi",
    "wof:placetype":"locality"
},
  "geometry": {"coordinates":[21.34576,40.27],"type":"Point"}
}