{
  "type": "Feature",
  "properties": {
    "gn:country":"GR",
    "gn:fcode":"PPL",
    "gn:population":111,
    "iso:country":"GR",
    "name:ell_x_preferred":[
        "\u039c\u03bf\u03c5\u03c1\u03b3\u03ba\u03ac\u03bd\u03b7"
    ],
    "name:und_x_variant":[
        "Ch\u00e1ni Mourng\u00e1ni"
    ],
    "qs_pg:aaroncc":"GR",
    "qs_pg:gn_country":"GR",
    "qs_pg:gn_fcode":"PPL",
    "qs_pg:gn_pop":111,
    "qs_pg:name":"Mourgk\u00e1ni",
    "qs_pg:photos_9r":0,
    "qs_pg:photos_sr":0,
    "qs_pg:pop_sr":1,
    "qs_pg:qs_pg_placetype":"locality",
    "wof:name":"Mourgk\u00e1ni",
    "wof:placetype":"locality",
    "wof:population":111
},
  "geometry": {"coordinates":[21.54139,39.73694],"type":"Point"}
}