{
  "type": "Feature",
  "properties": {
    "gn:admin1_code":"ESYE43",
    "gn:admin2_code":"45.0",
    "gn:admin3_code":"9306",
    "gn:asciiname":"Aidhonokhorion",
    "gn:cc2":"GR",
    "gn:country_code":"GR",
    "gn:dem":533,
    "gn:feature_class":"P",
    "gn:feature_code":"PPL",
    "gn:name":"A\u00efdhonokh\u00f3rion",
    "gn:population":0,
    "gn:timezone":"Europe/Athens",
    "iso:country":"GR",
    "name:und_x_variant":[
        "Met\u00f3khia Kamari\u00f3tou",
        "A\u00efdhonokh\u00f3rion"
    ],
    "wof:name":"Aidhonokhorion",
    "wof:placetype":"locality"
},
  "geometry": {"coordinates":[24.92058,35.32332],"type":"Point"}
}