{
  "type": "Feature",
  "properties": {
    "gn:gn_country":"GR",
    "gn:gn_fcode":"PPL",
    "gn:gn_pop":217,
    "gn:population":217,
    "iso:country":"GR",
    "name:ell_x_preferred":[
        "\u039f\u03c1\u03b8\u03bf\u03b2\u03bf\u03cd\u03bd\u03b9"
    ],
    "name:ell_x_variant":[
        "\u039f\u03c1\u03b8\u03bf\u03b2\u03bf\u03cd\u03bd\u03b9\u03bf\u03bd"
    ],
    "name:unk_x_variant":[
        "Tsourana\u00edoi"
    ],
    "qs_pg:aaroncc":"GR",
    "qs_pg:gn_country":"GR",
    "qs_pg:gn_fcode":"PPL",
    "qs_pg:gn_pop":217,
    "qs_pg:name":"Orthovo\u00fanion",
    "qs_pg:photos_9r":0,
    "qs_pg:photos_sr":0,
    "qs_pg:pop_sr":2,
    "qs_pg:qs_pg_placetype":"locality",
    "wof:name":"Orthovo\u00fanion",
    "wof:placetype":"locality",
    "wof:population":217
},
  "geometry": {"coordinates":[21.4675,39.76278],"type":"Point"}
}