{
  "type": "Feature",
  "properties": {
    "gn:admin1_code":"ESYE25",
    "gn:admin2_code":"42.0",
    "gn:admin3_code":"9252",
    "gn:asciiname":"Nikhorion",
    "gn:cc2":"GR",
    "gn:country_code":"GR",
    "gn:dem":598,
    "gn:feature_class":"P",
    "gn:feature_code":"PPL",
    "gn:name":"Nikh\u00f3rion",
    "gn:population":0,
    "gn:timezone":"Europe/Athens",
    "iso:country":"GR",
    "name:ell_x_preferred":[
        "\u039d\u03b9\u03c7\u03ce\u03c1\u03b9"
    ],
    "name:ell_x_variant":[
        "\u039d\u03b9\u03c7\u03ce\u03c1\u03b9\u03bf\u03bd"
    ],
    "name:und_x_variant":[
        "Nikh\u00f3ri",
        "Nikh\u00f3rion"
    ],
    "wof:name":"Nikhorion",
    "wof:placetype":"locality"
},
  "geometry": {"coordinates":[22.41632,36.9709],"type":"Point"}
}