{
  "type": "Feature",
  "properties": {
    "gn:admin1_code":"ESYE43",
    "gn:admin2_code":"43.0",
    "gn:admin3_code":"9325",
    "gn:asciiname":"Stavros",
    "gn:country_code":"GR",
    "gn:dem":3,
    "gn:feature_class":"P",
    "gn:feature_code":"PPL",
    "gn:name":"Stavros",
    "gn:population":460,
    "gn:timezone":"Europe/Athens",
    "iso:country":"GR",
    "name:ell_x_preferred":[
        "\u03a3\u03c4\u03b1\u03c5\u03c1\u03cc\u03c2"
    ],
    "name:ell_x_variant":[
        "\u03a3\u03c4\u03b1\u03c5\u03c1\u03cc\u03c2 \u0391\u03ba\u03c1\u03c9\u03c4\u03b7\u03c1\u03af\u03bf\u03c5",
        "\u03a3\u03c4\u03b1\u03c5\u03c1\u03cc\u03c2 \u03a7\u03b1\u03bd\u03af\u03c9\u03bd"
    ],
    "name:eng_x_preferred":[
        "Stavros"
    ],
    "name:eng_x_variant":[
        "Stavr\u00f3s"
    ],
    "name:fra_x_preferred":[
        "St\u00e1vros"
    ],
    "name:nld_x_preferred":[
        "Stavros"
    ],
    "wof:name":"Stavros",
    "wof:placetype":"locality",
    "wof:population":460
},
  "geometry": {"coordinates":[24.09255,35.59077],"type":"Point"}
}