{
  "type": "Feature",
  "properties": {
    "gn:admin1_code":"ESYE25",
    "gn:admin2_code":"41.0",
    "gn:admin3_code":"9241.0",
    "gn:asciiname":"Moni Kandilas",
    "gn:country_code":"GR",
    "gn:dem":880,
    "gn:feature_class":"P",
    "gn:feature_code":"PPLR",
    "gn:name":"Mon\u00ed Kand\u00edlas",
    "gn:population":3,
    "gn:timezone":"Europe/Athens",
    "iso:country":"GR",
    "name:ell_x_preferred":[
        "\u039c\u03bf\u03bd\u03ae \u039a\u03b1\u03bd\u03b4\u03ae\u03bb\u03b1\u03c2"
    ],
    "name:eng_x_preferred":[
        "Moni Kandilas"
    ],
    "wof:name":"Moni Kandilas",
    "wof:placetype":"locality",
    "wof:population":3
},
  "geometry": {"coordinates":[22.37532,37.76251],"type":"Point"}
}