{
  "type": "Feature",
  "properties": {
    "gn:country":"GR",
    "gn:fcode":"PPL",
    "gn:population":35,
    "iso:country":"GR",
    "name:ell_x_preferred":[
        "\u00c1no Potami\u00e1"
    ],
    "name:ell_x_variant":[
        "\u0386\u03bd\u03c9 \u03a0\u03bf\u03c4\u03b1\u03bc\u03b9\u03ac"
    ],
    "qs_pg:aaroncc":"GR",
    "qs_pg:gn_country":"GR",
    "qs_pg:gn_fcode":"PPL",
    "qs_pg:gn_pop":35,
    "qs_pg:name":"Ano Potamia",
    "qs_pg:name_adm0":"\u0395\u03bb\u03bb\u03ac\u03b4\u03b1",
    "qs_pg:name_adm1":"Thessaly and Continental Greece",
    "qs_pg:photos_9r":0,
    "qs_pg:photos_sr":0,
    "qs_pg:pop_sr":1,
    "qs_pg:qs_pg_placetype":"locality",
    "qs_pg:qs_pg_placetype_gp":"Town",
    "qs_pg:woe_adm0":23424833,
    "woe:adm0_id":23424833,
    "woe:name_adm0":"\u0395\u03bb\u03bb\u03ac\u03b4\u03b1",
    "woe:name_adm1":"Thessaly and Continental Greece",
    "woe:placetype":"Town",
    "wof:name":"Ano Potamia",
    "wof:placetype":"locality",
    "wof:population":35
},
  "geometry": {"coordinates":[21.52667,39.10667],"type":"Point"}
}