{
  "type": "Feature",
  "properties": {
    "gn:country":"GR",
    "gn:fcode":"PPL",
    "gn:population":228,
    "iso:country":"GR",
    "name:ell_x_preferred":[
        "\u03a0\u03b1\u03bb\u03b1\u03b9\u03bf\u03c7\u03ce\u03c1\u03b9 \u039c\u03c0\u03cc\u03c4\u03c3\u03b1\u03c1\u03b7"
    ],
    "name:eng_x_preferred":[
        "Palaiochori Botsari"
    ],
    "name:und_x_variant":[
        "Palaiokh\u00f3rion"
    ],
    "qs_pg:aaroncc":"GR",
    "qs_pg:gn_country":"GR",
    "qs_pg:gn_fcode":"PPL",
    "qs_pg:gn_pop":228,
    "qs_pg:name":"Palaioch\u00f3rion",
    "qs_pg:photos_9r":0,
    "qs_pg:photos_sr":0,
    "qs_pg:pop_sr":2,
    "qs_pg:qs_pg_placetype":"locality",
    "wof:name":"Palaioch\u00f3rion",
    "wof:placetype":"locality",
    "wof:population":132
},
  "geometry": {"coordinates":[20.71222,39.34639],"type":"Point"}
}