{
  "type": "Feature",
  "properties": {
    "gn:admin1_code":"ESYE43",
    "gn:admin2_code":"43.0",
    "gn:admin3_code":"9321",
    "gn:asciiname":"Kampanos",
    "gn:country_code":"GR",
    "gn:dem":371,
    "gn:feature_class":"P",
    "gn:feature_code":"PPL",
    "gn:name":"Kampan\u00f3s",
    "gn:population":0,
    "gn:timezone":"Europe/Athens",
    "iso:country":"GR",
    "name:ell_x_preferred":[
        "Kampan\u00f3s"
    ],
    "name:ell_x_variant":[
        "\u039a\u03b1\u03bc\u03c0\u03b1\u03bd\u03cc\u03c2"
    ],
    "name:und_x_variant":[
        "Kambano\u00fa",
        "Kamban\u00f3s"
    ],
    "wof:name":"Kampanos",
    "wof:placetype":"locality"
},
  "geometry": {"coordinates":[23.79847,35.31045],"type":"Point"}
}