{
  "type": "Feature",
  "properties": {
    "gn:admin1_code":"ESYE13",
    "gn:admin2_code":"11.0",
    "gn:admin3_code":"9067",
    "gn:asciiname":"Pentavrysos",
    "gn:country_code":"GR",
    "gn:dem":597,
    "gn:feature_class":"P",
    "gn:feature_code":"PPL",
    "gn:name":"Pent\u00e1vrysos",
    "gn:population":0,
    "gn:timezone":"Europe/Athens",
    "iso:country":"GR",
    "name:ell_x_preferred":[
        "Pent\u00e1vrysos"
    ],
    "name:ell_x_variant":[
        "\u03a0\u03b5\u03bd\u03c4\u03ac\u03b2\u03c1\u03c5\u03c3\u03bf\u03c2"
    ],
    "name:und_x_variant":[
        "Pend\u00e1vrison",
        "Pend\u00e1vrisos"
    ],
    "wof:name":"Pentavrysos",
    "wof:placetype":"locality"
},
  "geometry": {"coordinates":[21.72136,40.5549],"type":"Point"}
}