{
  "type": "Feature",
  "properties": {
    "gn:admin1_code":"ESYE21",
    "gn:admin2_code":"17.0",
    "gn:admin3_code":"9087",
    "gn:asciiname":"Bolaiika",
    "gn:country_code":"GR",
    "gn:dem":398,
    "gn:feature_class":"P",
    "gn:feature_code":"PPL",
    "gn:name":"Bola\u00edika",
    "gn:population":66,
    "gn:timezone":"Europe/Athens",
    "iso:country":"GR",
    "name:ell_x_preferred":[
        "\u039c\u03c0\u03bf\u03bb\u03b1\u03af\u03b9\u03ba\u03b1"
    ],
    "name:eng_x_preferred":[
        "Bolaiika"
    ],
    "name:und_x_variant":[
        "Gkorits\u00e1",
        "Gor\u00edtsa",
        "Limpo\u00fasda",
        "Bola\u00edika"
    ],
    "wof:name":"Bolaiika",
    "wof:placetype":"locality",
    "wof:population":66
},
  "geometry": {"coordinates":[20.55508,39.86231],"type":"Point"}
}