{
  "type": "Feature",
  "properties": {
    "gn:admin1_code":"ESYE43",
    "gn:admin2_code":"45.0",
    "gn:admin3_code":"9303",
    "gn:asciiname":"Sidonia",
    "gn:country_code":"GR",
    "gn:dem":6,
    "gn:feature_class":"P",
    "gn:feature_code":"PPL",
    "gn:name":"Sidon\u00eda",
    "gn:population":0,
    "gn:timezone":"Europe/Athens",
    "iso:country":"GR",
    "name:ces_x_preferred":[
        "Sidonia"
    ],
    "name:deu_x_preferred":[
        "Sidonia"
    ],
    "name:ell_x_preferred":[
        "Sidon\u00eda"
    ],
    "name:ell_x_variant":[
        "\u03a3\u03b9\u03b4\u03c9\u03bd\u03af\u03b1"
    ],
    "name:nld_x_preferred":[
        "Sidonia"
    ],
    "name:slk_x_preferred":[
        "Sid\u00f3nia"
    ],
    "wof:name":"Sidonia",
    "wof:placetype":"locality"
},
  "geometry": {"coordinates":[25.49779,34.985],"type":"Point"}
}