{
  "type": "Feature",
  "properties": {
    "gn:admin1_code":"ESYE31",
    "gn:admin2_code":"445406.0",
    "gn:admin3_code":"9219",
    "gn:asciiname":"Charakas",
    "gn:country_code":"GR",
    "gn:dem":27,
    "gn:feature_class":"P",
    "gn:feature_code":"PPL",
    "gn:name":"Ch\u00e1rakas",
    "gn:population":0,
    "gn:timezone":"Europe/Athens",
    "iso:country":"GR",
    "name:ell_x_preferred":[
        "\u03a7\u03ac\u03c1\u03b1\u03ba\u03b1\u03c2"
    ],
    "name:ell_x_variant":[
        "\u03a7\u03ac\u03c1\u03b1\u03ba\u03b1\u03c2 \u0397\u03c1\u03b1\u03ba\u03bb\u03b5\u03af\u03bf\u03c5"
    ],
    "name:eng_x_preferred":[
        "Charakas"
    ],
    "name:fin_x_preferred":[
        "Ch\u00e1rakas"
    ],
    "wof:name":"Charakas",
    "wof:placetype":"locality"
},
  "geometry": {"coordinates":[23.96517,37.66949],"type":"Point"}
}