{
  "type": "Feature",
  "properties": {
    "gn:country":"GR",
    "gn:fcode":"PPL",
    "gn:population":268,
    "iso:country":"GR",
    "name:ell_x_preferred":[
        "\u03a0\u03b5\u03c5\u03ba\u03c9\u03c4\u03cc"
    ],
    "name:ell_x_variant":[
        "\u03a0\u03b5\u03c5\u03ba\u03c9\u03c4\u03cc\u03bd"
    ],
    "name:eng_x_preferred":[
        "Pefkoto"
    ],
    "name:und_x_variant":[
        "Pefkot\u00f3"
    ],
    "qs_pg:aaroncc":"GR",
    "qs_pg:gn_country":"GR",
    "qs_pg:gn_fcode":"PPL",
    "qs_pg:gn_pop":268,
    "qs_pg:name":"Pefkot\u00f3n",
    "qs_pg:photos_9r":0,
    "qs_pg:photos_sr":0,
    "qs_pg:pop_sr":2,
    "qs_pg:qs_pg_placetype":"locality",
    "wof:name":"Pefkot\u00f3n",
    "wof:placetype":"locality",
    "wof:population":268
},
  "geometry": {"coordinates":[22.08472,41.075],"type":"Point"}
}