{
  "type": "Feature",
  "properties": {
    "gn:admin1_code":"ESYE24",
    "gn:admin2_code":"34.0",
    "gn:admin3_code":"9152",
    "gn:asciiname":"Karavos",
    "gn:country_code":"GR",
    "gn:dem":10,
    "gn:feature_class":"P",
    "gn:feature_code":"PPL",
    "gn:name":"K\u00e1ravos",
    "gn:population":0,
    "gn:timezone":"Europe/Athens",
    "iso:country":"GR",
    "name:ell_x_preferred":[
        "K\u00e1ravos"
    ],
    "name:ell_x_variant":[
        "\u039a\u03ac\u03c1\u03b1\u03b2\u03bf\u03c2"
    ],
    "wof:name":"Karavos",
    "wof:placetype":"locality"
},
  "geometry": {"coordinates":[24.04486,38.39831],"type":"Point"}
}