{
  "type": "Feature",
  "properties": {
    "gn:admin1_code":"ESYE25",
    "gn:admin2_code":"37.0",
    "gn:admin3_code":"9243",
    "gn:asciiname":"Thymeli",
    "gn:country_code":"GR",
    "gn:dem":75,
    "gn:feature_class":"P",
    "gn:feature_code":"PPL",
    "gn:name":"Thym\u00e9li",
    "gn:population":9,
    "gn:timezone":"Europe/Athens",
    "iso:country":"GR",
    "name:ell_x_preferred":[
        "\u0398\u03c5\u03bc\u03ad\u03bb\u03b7"
    ],
    "name:eng_x_preferred":[
        "Thymeli"
    ],
    "name:und_x_variant":[
        "Thimeli"
    ],
    "wof:name":"Thymeli",
    "wof:placetype":"locality",
    "wof:population":9
},
  "geometry": {"coordinates":[22.98005,37.85611],"type":"Point"}
}