{
  "type": "Feature",
  "properties": {
    "gn:admin1_code":"ESYE31",
    "gn:admin2_code":"406101.0",
    "gn:admin3_code":"9213",
    "gn:asciiname":"Skapeti",
    "gn:country_code":"GR",
    "gn:dem":270,
    "gn:feature_class":"P",
    "gn:feature_code":"PPL",
    "gn:name":"Skap\u00e9ti",
    "gn:population":94,
    "gn:timezone":"Europe/Athens",
    "iso:country":"GR",
    "name:ell_x_preferred":[
        "\u03a3\u03ba\u03b1\u03c0\u03ad\u03c4\u03b9"
    ],
    "name:eng_x_preferred":[
        "Skapeti"
    ],
    "name:und_x_variant":[
        "Skap\u00e9ti",
        "Skap\u00e9tion"
    ],
    "wof:name":"Skapeti",
    "wof:placetype":"locality",
    "wof:population":94
},
  "geometry": {"coordinates":[23.303,37.52134],"type":"Point"}
}