{
  "type": "Feature",
  "properties": {
    "iso:country":"GR",
    "qs:a0":"Greece",
    "qs:a1":"*\u0398\u0395\u03a3\u03a3\u0391\u039b\u0399\u0391",
    "qs:a1_alt":"UESSALIA",
    "qs:a1r":"0",
    "qs:a2_alt":"TRIKALA",
    "qs:adm0":"Greece",
    "qs:la_lc":"*",
    "qs:level":"locality",
    "qs:loc":"\u03a0\u0397\u0393\u0397",
    "qs:loc_alt":"PHGH",
    "qs:pop":0,
    "qs:type":"buffered point",
    "wof:name":"\u03a0\u0397\u0393\u0397",
    "wof:placetype":"locality"
},
  "geometry": {"coordinates":[21.699843,39.510876],"type":"Point"}
}