{
  "type": "Feature",
  "properties": {
    "gn:admin1_code":"ESYE12",
    "gn:admin2_code":"5.0",
    "gn:admin3_code":"9053",
    "gn:asciiname":"Mavrolofos",
    "gn:country_code":"GR",
    "gn:dem":103,
    "gn:feature_class":"P",
    "gn:feature_code":"PPL",
    "gn:name":"Mavr\u00f3lofos",
    "gn:population":658,
    "gn:timezone":"Europe/Athens",
    "iso:country":"GR",
    "name:bul_x_historical":[
        "\u041a\u0430\u0440\u0430\u0442\u043e\u043f\u0440\u0430\u043a"
    ],
    "name:bul_x_preferred":[
        "\u041a\u0430\u0440\u0430\u0442\u043e\u043f\u0440\u0430\u043a"
    ],
    "name:bul_x_variant":[
        "\u041c\u0430\u0432\u0440\u043e\u043b\u043e\u0444\u043e\u0441"
    ],
    "name:ell_x_historical":[
        "\u039a\u03b1\u03c1\u03ac \u03a4\u03bf\u03c0\u03c1\u03ac\u03ba"
    ],
    "name:ell_x_preferred":[
        "\u039c\u03b1\u03c5\u03c1\u03cc\u03bb\u03bf\u03c6\u03bf\u03c2"
    ],
    "name:ell_x_variant":[
        "Mavr\u00f3lofos",
        "\u039a\u03b1\u03c1\u03ac \u03a4\u03bf\u03c0\u03c1\u03ac\u03ba"
    ],
    "name:eng_x_preferred":[
        "Mavrolofos"
    ],
    "name:tur_x_historical":[
        "Kara Toprak"
    ],
    "name:tur_x_preferred":[
        "Kara Toprak"
    ],
    "wof:name":"Mavrolofos",
    "wof:placetype":"locality",
    "wof:population":658
},
  "geometry": {"coordinates":[23.87124,40.9129],"type":"Point"}
}