{
  "type": "Feature",
  "properties": {
    "gn:admin1_code":"ESYE41",
    "gn:asciiname":"Karavostamo",
    "gn:country_code":"GR",
    "gn:dem":119,
    "gn:feature_class":"P",
    "gn:feature_code":"PPL",
    "gn:name":"Karav\u00f3stamo",
    "gn:population":0,
    "gn:timezone":"Europe/Athens",
    "iso:country":"GR",
    "name:ell_x_preferred":[
        "Karav\u00f3stamo"
    ],
    "name:ell_x_variant":[
        "\u039a\u03b1\u03c1\u03b1\u03b2\u03cc\u03c3\u03c4\u03b1\u03bc\u03bf"
    ],
    "wof:name":"Karavostamo",
    "wof:placetype":"locality"
},
  "geometry": {"coordinates":[26.22063,37.62998],"type":"Point"}
}