{
  "type": "Feature",
  "properties": {
    "gn:admin1_code":"ESYE43",
    "gn:admin2_code":"45.0",
    "gn:admin3_code":"9302",
    "gn:asciiname":"Kefaladhos",
    "gn:cc2":"GR",
    "gn:country_code":"GR",
    "gn:dem":262,
    "gn:feature_class":"P",
    "gn:feature_code":"PPL",
    "gn:name":"Kefal\u00e1dhos",
    "gn:population":0,
    "gn:timezone":"Europe/Athens",
    "iso:country":"GR",
    "name:und_x_variant":[
        "Kefal\u00e1dhes",
        "Kefal\u00e1dhos"
    ],
    "wof:name":"Kefaladhos",
    "wof:placetype":"locality"
},
  "geometry": {"coordinates":[25.18092,35.05115],"type":"Point"}
}