{
  "type": "Feature",
  "properties": {
    "gn:admin1_code":"ESYE43",
    "gn:admin2_code":"44.0",
    "gn:admin3_code":"9316",
    "gn:asciiname":"Livadha",
    "gn:cc2":"GR",
    "gn:country_code":"GR",
    "gn:dem":474,
    "gn:feature_class":"P",
    "gn:feature_code":"PPL",
    "gn:name":"Liv\u00e1dha",
    "gn:population":0,
    "gn:timezone":"Europe/Athens",
    "iso:country":"GR",
    "name:und_x_variant":[
        "Liv\u00e1dhia",
        "Liv\u00e1dha"
    ],
    "wof:name":"Livadha",
    "wof:placetype":"locality"
},
  "geometry": {"coordinates":[24.85614,35.31078],"type":"Point"}
}