{
  "type": "Feature",
  "properties": {
    "gn:admin1_code":"ESYE25",
    "gn:admin2_code":"40.0",
    "gn:admin3_code":"9253",
    "gn:asciiname":"Kentron",
    "gn:country_code":"GR",
    "gn:dem":613,
    "gn:feature_class":"P",
    "gn:feature_code":"PPL",
    "gn:name":"K\u00e9ntron",
    "gn:population":17,
    "gn:timezone":"Europe/Athens",
    "iso:country":"GR",
    "name:ell_x_historical":[
        "\u039c\u03c0\u03af\u03bb\u03b9\u03bf\u03b2\u03b1",
        "\u039c\u03c0\u03af\u03bb\u03bf\u03b2\u03b1"
    ],
    "name:ell_x_preferred":[
        "\u039a\u03ad\u03bd\u03c4\u03c1\u03bf"
    ],
    "name:ell_x_variant":[
        "\u039a\u03ad\u03bd\u03c4\u03c1\u03bf\u03bd",
        "\u039c\u03c0\u03af\u03bb\u03b9\u03bf\u03b2\u03b1",
        "\u039c\u03c0\u03af\u03bb\u03bf\u03b2\u03b1"
    ],
    "name:eng_x_preferred":[
        "Kentro"
    ],
    "name:und_x_variant":[
        "B\u00edliova",
        "K\u00e9ndron",
        "K\u00e9ndro"
    ],
    "wof:name":"Kentron",
    "wof:placetype":"locality",
    "wof:population":17
},
  "geometry": {"coordinates":[22.25011,36.9532],"type":"Point"}
}