{
  "type": "Feature",
  "properties": {
    "gn:admin1_code":"ESYE14",
    "gn:admin2_code":"21.0",
    "gn:admin3_code":"9097",
    "gn:asciiname":"Kalyvia Elafou",
    "gn:country_code":"GR",
    "gn:dem":92,
    "gn:feature_class":"P",
    "gn:feature_code":"PPL",
    "gn:name":"Kal\u00fdvia El\u00e1fou",
    "gn:population":0,
    "gn:timezone":"Europe/Athens",
    "iso:country":"GR",
    "name:ell_x_preferred":[
        "Kal\u00fdvia El\u00e1fou"
    ],
    "name:ell_x_variant":[
        "\u039a\u03b1\u03bb\u03cd\u03b2\u03b9\u03b1 \u0395\u03bb\u03ac\u03c6\u03bf\u03c5"
    ],
    "name:und_x_variant":[
        "Kal\u00edvia Voulgarin\u00eds",
        "Kal\u00edvia El\u00e1fou"
    ],
    "wof:name":"Kalyvia Elafou",
    "wof:placetype":"locality"
},
  "geometry": {"coordinates":[22.77569,39.56036],"type":"Point"}
}