{
  "type": "Feature",
  "properties": {
    "gn:gn_country":"GR",
    "gn:gn_fcode":"ADM3",
    "gn:gn_pop":81024,
    "gn:population":78153,
    "iso:country":"GR",
    "name:ara_x_preferred":[
        "\u0625\u064a\u0644\u064a\u0648\u0628\u0648\u0644\u064a"
    ],
    "name:bul_x_preferred":[
        "\u0418\u043b\u0438\u0443\u043f\u043e\u043b\u0438"
    ],
    "name:ceb_x_preferred":[
        "Ilio\u00fapoli"
    ],
    "name:deu_x_preferred":[
        "Ilioupoli"
    ],
    "name:ell_x_preferred":[
        "\u0397\u03bb\u03b9\u03bf\u03cd\u03c0\u03bf\u03bb\u03b7\u03c2"
    ],
    "name:ell_x_variant":[
        "\u0397\u03bb\u03b9\u03bf\u03cd\u03c0\u03bf\u03bb\u03b7 \u0391\u03c4\u03c4\u03b9\u03ba\u03ae\u03c2"
    ],
    "name:fin_x_preferred":[
        "Ilio\u00fapoli"
    ],
    "name:fra_x_preferred":[
        "H\u00e9liopolis"
    ],
    "name:hun_x_preferred":[
        "Ili\u00fapoli"
    ],
    "name:ita_x_preferred":[
        "\u012alioupol\u012b"
    ],
    "name:nld_x_preferred":[
        "Ilioupoli"
    ],
    "name:nno_x_preferred":[
        "Ilio\u00fapoli"
    ],
    "name:pol_x_preferred":[
        "Iliupoli"
    ],
    "name:ron_x_preferred":[
        "Ilioupolis"
    ],
    "name:rus_x_preferred":[
        "\u0418\u043b\u044c\u044e\u043f\u043e\u043b\u0438\u0441"
    ],
    "name:spa_x_preferred":[
        "Heli\u00f3polis"
    ],
    "name:srp_x_preferred":[
        "\u0418\u043b\u0438\u0458\u0443\u043f\u043e\u043b\u0438"
    ],
    "name:swe_x_preferred":[
        "Ilioupoli"
    ],
    "name:tur_x_preferred":[
        "\u0130liupoli"
    ],
    "name:ukr_x_preferred":[
        "\u0406\u043b\u0456\u0443\u043f\u043e\u043b\u0456"
    ],
    "name:urd_x_preferred":[
        "\u0627\u0644\u06cc\u0624\u067e\u0648\u0644\u06cc"
    ],
    "name:vie_x_preferred":[
        "Ilioupoli"
    ],
    "qs_pg:aaroncc":"GR",
    "qs_pg:gn_country":"GR",
    "qs_pg:gn_fcode":"ADM3",
    "qs_pg:gn_pop":81024,
    "qs_pg:name":"Ilioupoli",
    "qs_pg:name_adm0":"\u0395\u03bb\u03bb\u03ac\u03b4\u03b1",
    "qs_pg:name_adm1":"Attica",
    "qs_pg:photos_9k":1,
    "qs_pg:photos_9r":4,
    "qs_pg:photos_all":199,
    "qs_pg:photos_sr":0,
    "qs_pg:pop_sr":8,
    "qs_pg:qs_pg_placetype":"localadmin",
    "qs_pg:qs_pg_placetype_gp":"LocalAdmin",
    "qs_pg:woe_adm0":23424833,
    "woe:adm0_id":23424833,
    "woe:name_adm0":"\u0395\u03bb\u03bb\u03ac\u03b4\u03b1",
    "woe:name_adm1":"Attica",
    "woe:placetype":"LocalAdmin",
    "wof:name":"Ilioupoli",
    "wof:placetype":"localadmin",
    "wof:population":78153
},
  "geometry": {"coordinates":[23.76983,37.93146],"type":"Point"}
}