{
  "type": "Feature",
  "properties": {
    "gn:gn_country":"GR",
    "gn:gn_fcode":"PPL",
    "gn:gn_pop":107,
    "gn:population":92,
    "iso:country":"GR",
    "name:ell_x_preferred":[
        "\u03a0\u03cc\u03c1\u03c4\u03b1"
    ],
    "name:eng_x_preferred":[
        "Porta"
    ],
    "name:unk_x_variant":[
        "P\u00f3rtes"
    ],
    "qs_pg:aaroncc":"GR",
    "qs_pg:gn_country":"GR",
    "qs_pg:gn_fcode":"PPL",
    "qs_pg:gn_pop":107,
    "qs_pg:name":"Porta",
    "qs_pg:name_adm0":"\u0395\u03bb\u03bb\u03ac\u03b4\u03b1",
    "qs_pg:name_adm1":"Peloponnese Western Greece and the Ionian Islands",
    "qs_pg:photos_9r":0,
    "qs_pg:photos_sr":0,
    "qs_pg:pop_sr":1,
    "qs_pg:qs_pg_placetype":"locality",
    "qs_pg:qs_pg_placetype_gp":"Town",
    "qs_pg:woe_adm0":23424833,
    "woe:adm0_id":23424833,
    "woe:name_adm0":"\u0395\u03bb\u03bb\u03ac\u03b4\u03b1",
    "woe:name_adm1":"Peloponnese Western Greece and the Ionian Islands",
    "woe:placetype":"Town",
    "wof:name":"Porta",
    "wof:placetype":"locality",
    "wof:population":92
},
  "geometry": {"coordinates":[19.91611,39.75],"type":"Point"}
}