{
  "type": "Feature",
  "properties": {
    "gn:admin1_code":"ESYE14",
    "gn:admin2_code":"24.0",
    "gn:admin3_code":"9107",
    "gn:asciiname":"Paltsi",
    "gn:country_code":"GR",
    "gn:dem":11,
    "gn:feature_class":"P",
    "gn:feature_code":"PPL",
    "gn:name":"P\u00e1ltsi",
    "gn:population":0,
    "gn:timezone":"Europe/Athens",
    "iso:country":"GR",
    "name:ell_x_preferred":[
        "P\u00e1ltsi"
    ],
    "name:ell_x_variant":[
        "\u03a0\u03ac\u03bb\u03c4\u03c3\u03b7"
    ],
    "name:und_x_variant":[
        "Balts\u00ed"
    ],
    "wof:name":"Paltsi",
    "wof:placetype":"locality"
},
  "geometry": {"coordinates":[23.31153,39.23222],"type":"Point"}
}