{
  "type": "Feature",
  "properties": {
    "gn:admin1_code":"ESYE25",
    "gn:admin2_code":"41.0",
    "gn:admin3_code":"9239",
    "gn:asciiname":"Ellinitsa",
    "gn:country_code":"GR",
    "gn:dem":512,
    "gn:feature_class":"P",
    "gn:feature_code":"PPL",
    "gn:name":"Ellin\u00edtsa",
    "gn:population":0,
    "gn:timezone":"Europe/Athens",
    "iso:country":"GR",
    "name:ell_x_preferred":[
        "\u0395\u03bb\u03bb\u03b7\u03bd\u03af\u03c4\u03c3\u03b1"
    ],
    "name:und_x_variant":[
        "M\u00edmi",
        "M\u00e9mi",
        "Ellin\u00edtsa"
    ],
    "wof:name":"Ellinitsa",
    "wof:placetype":"locality"
},
  "geometry": {"coordinates":[22.11997,37.30009],"type":"Point"}
}