{
  "type": "Feature",
  "properties": {
    "gn:admin1_code":"ESYE11",
    "gn:admin2_code":"4.0",
    "gn:admin3_code":"9003",
    "gn:asciiname":"Mesovouni",
    "gn:country_code":"GR",
    "gn:dem":764,
    "gn:feature_class":"P",
    "gn:feature_code":"PPL",
    "gn:name":"Mesovo\u00fani",
    "gn:population":0,
    "gn:timezone":"Europe/Athens",
    "iso:country":"GR",
    "name:ceb_x_preferred":[
        "Mesovouni"
    ],
    "name:ell_x_preferred":[
        "\u039c\u03b5\u03c3\u03bf\u03b2\u03bf\u03cd\u03bd\u03b9"
    ],
    "name:swe_x_preferred":[
        "Mesovouni"
    ],
    "name:und_x_variant":[
        "Sidh\u00e9rova",
        "Mesovo\u00fani"
    ],
    "wof:name":"Mesovouni",
    "wof:placetype":"locality"
},
  "geometry": {"coordinates":[24.07547000000001,41.34639],"type":"Point"}
}