{
  "type": "Feature",
  "properties": {
    "gn:admin1_code":"ESYE22",
    "gn:admin2_code":"25.0",
    "gn:admin3_code":"9118",
    "gn:asciiname":"Kokkini",
    "gn:country_code":"GR",
    "gn:dem":288,
    "gn:feature_class":"P",
    "gn:feature_code":"PPL",
    "gn:name":"K\u00f3kkini",
    "gn:population":53,
    "gn:timezone":"Europe/Athens",
    "iso:country":"GR",
    "name:ell_x_preferred":[
        "\u039a\u03cc\u03ba\u03ba\u03b9\u03bd\u03b7"
    ],
    "name:eng_x_preferred":[
        "Kokkini"
    ],
    "wof:name":"Kokkini",
    "wof:placetype":"locality",
    "wof:population":53
},
  "geometry": {"coordinates":[19.92585,39.75511],"type":"Point"}
}