{
  "type": "Feature",
  "properties": {
    "gn:admin1_code":"ESYE43",
    "gn:admin2_code":"45.0",
    "gn:admin3_code":"9302",
    "gn:asciiname":"Ampela",
    "gn:country_code":"GR",
    "gn:dem":191,
    "gn:feature_class":"P",
    "gn:feature_code":"PPL",
    "gn:name":"Ampel\u00e1",
    "gn:population":0,
    "gn:timezone":"Europe/Athens",
    "iso:country":"GR",
    "name:ell_x_preferred":[
        "Ampel\u00e1"
    ],
    "name:ell_x_variant":[
        "\u0391\u03bc\u03c0\u03b5\u03bb\u03ac"
    ],
    "wof:name":"Ampela",
    "wof:placetype":"locality"
},
  "geometry": {"coordinates":[25.17631,35.27800999999999],"type":"Point"}
}