{
  "type": "Feature",
  "properties": {
    "gn:admin1_code":"ESYE11",
    "gn:admin2_code":"4.0",
    "gn:admin3_code":"9004",
    "gn:asciiname":"Temenos",
    "gn:country_code":"GR",
    "gn:dem":154,
    "gn:feature_class":"P",
    "gn:feature_code":"PPL",
    "gn:name":"T\u00e9menos",
    "gn:population":0,
    "gn:timezone":"Europe/Athens",
    "iso:country":"GR",
    "name:ell_x_preferred":[
        "\u03a4\u03ad\u03bc\u03b5\u03bd\u03bf\u03c2"
    ],
    "name:und_x_variant":[
        "Jam\u00ed-Mahal\u00e9",
        "T\u00e9menos"
    ],
    "wof:name":"Temenos",
    "wof:placetype":"locality"
},
  "geometry": {"coordinates":[24.4727,41.28635],"type":"Point"}
}