{
  "type": "Feature",
  "properties": {
    "gn:admin1_code":"ESYE11",
    "gn:admin2_code":"4.0",
    "gn:admin3_code":"9004",
    "gn:asciiname":"Temenos",
    "gn:country_code":"GR",
    "gn:dem":154,
    "gn:feature_class":"P",
    "gn:feature_code":"PPL",
    "gn:name":"T\u00e9menos",
    "gn:population":0,
    "gn:timezone":"Europe/Athens",
    "iso:country":"GR",
    "name:cat_x_preferred":[
        "T\u00e8menos"
    ],
    "name:dan_x_preferred":[
        "Temenos"
    ],
    "name:deu_x_preferred":[
        "Temenos"
    ],
    "name:ell_x_preferred":[
        "\u03a4\u03ad\u03bc\u03b5\u03bd\u03bf\u03c2"
    ],
    "name:eus_x_preferred":[
        "Temenos"
    ],
    "name:fin_x_preferred":[
        "Temenos"
    ],
    "name:fra_x_preferred":[
        "T\u00e9m\u00e9nos"
    ],
    "name:glg_x_preferred":[
        "T\u00e9menos"
    ],
    "name:hun_x_preferred":[
        "Temenosz"
    ],
    "name:ita_x_preferred":[
        "Temenos"
    ],
    "name:lat_x_preferred":[
        "Temenos"
    ],
    "name:nld_x_preferred":[
        "Temenos"
    ],
    "name:nor_x_preferred":[
        "Temenos"
    ],
    "name:pol_x_preferred":[
        "Temenos"
    ],
    "name:rus_x_preferred":[
        "\u0422\u0435\u043c\u0435\u043d\u043e\u0441"
    ],
    "name:spa_x_preferred":[
        "T\u00e9menos"
    ],
    "name:swe_x_preferred":[
        "Temenos"
    ],
    "name:tur_x_preferred":[
        "Temenos"
    ],
    "name:ukr_x_preferred":[
        "\u0422\u0435\u043c\u0435\u043d\u043e\u0441"
    ],
    "name:und_x_variant":[
        "Jam\u00ed-Mahal\u00e9"
    ],
    "wof:name":"Temenos",
    "wof:placetype":"locality"
},
  "geometry": {"coordinates":[24.4727,41.28635],"type":"Point"}
}