{
  "type": "Feature",
  "properties": {
    "gn:admin1_code":"ESYE25",
    "gn:admin2_code":"40.0",
    "gn:admin3_code":"9256",
    "gn:asciiname":"Diavolitsi",
    "gn:country_code":"GR",
    "gn:dem":107,
    "gn:feature_class":"P",
    "gn:feature_code":"PPL",
    "gn:name":"Diavol\u00edtsi",
    "gn:population":0,
    "gn:timezone":"Europe/Athens",
    "iso:country":"GR",
    "name:ell_x_preferred":[
        "Diavol\u00edtsi"
    ],
    "name:ell_x_variant":[
        "\u0394\u03b9\u03b1\u03b2\u03bf\u03bb\u03af\u03c4\u03c3\u03b9",
        "Diavol\u00edtsion",
        "\u0394\u03b9\u03b1\u03b2\u03bf\u03bb\u03af\u03c4\u03c3\u03b9\u03bf\u03bd"
    ],
    "name:und_x_variant":[
        "Dhiavol\u00edsti",
        "Dhiavol\u00edtsi",
        "Dhiavol\u00edtsion"
    ],
    "wof:name":"Diavolitsi",
    "wof:placetype":"locality"
},
  "geometry": {"coordinates":[21.9682,37.29982],"type":"Point"}
}