{
  "type": "Feature",
  "properties": {
    "gn:country":"GR",
    "gn:fcode":"PPL",
    "gn:population":914,
    "iso:country":"GR",
    "name:ara_x_preferred":[
        "\u063a\u0648\u0631\u063a\u0648\u0628\u064a\u060c \u0643\u064a\u0644\u0643\u064a\u0633"
    ],
    "name:ara_x_variant":[
        "\u063a\u0648\u0631\u063a\u0648\u0628\u064a"
    ],
    "name:bul_x_preferred":[
        "\u0413\u043e\u0440\u0433\u043e\u043f\u0438\u043a"
    ],
    "name:ceb_x_preferred":[
        "Gorg\u00f3pi"
    ],
    "name:ell_x_preferred":[
        "\u0393\u03bf\u03c1\u03b3\u03cc\u03c0\u03b7"
    ],
    "name:ell_x_variant":[
        "\u0393\u03bf\u03c1\u03b3\u03cc\u03c0\u03b7 \u039a\u03b9\u03bb\u03ba\u03af\u03c2"
    ],
    "name:eng_x_preferred":[
        "Gorgopi"
    ],
    "name:mkd_x_preferred":[
        "\u0413\u043e\u0440\u0433\u043e\u043f\u0438\u043a"
    ],
    "name:nld_x_preferred":[
        "Gorgopi"
    ],
    "name:swe_x_preferred":[
        "Gorg\u00f3pi"
    ],
    "qs_pg:aaroncc":"GR",
    "qs_pg:gn_country":"GR",
    "qs_pg:gn_fcode":"PPL",
    "qs_pg:gn_pop":914,
    "qs_pg:name":"Gorg\u00f3pi",
    "qs_pg:photos_9r":0,
    "qs_pg:photos_sr":0,
    "qs_pg:pop_sr":2,
    "qs_pg:qs_pg_placetype":"locality",
    "wof:name":"Gorg\u00f3pi",
    "wof:placetype":"locality",
    "wof:population":914
},
  "geometry": {"coordinates":[22.51306,40.95889],"type":"Point"}
}