{
  "type": "Feature",
  "properties": {
    "gn:admin1_code":"ESYE25",
    "gn:admin2_code":"40.0",
    "gn:admin3_code":"9256",
    "gn:asciiname":"Vrysoula",
    "gn:country_code":"GR",
    "gn:dem":115,
    "gn:feature_class":"P",
    "gn:feature_code":"PPL",
    "gn:name":"Vryso\u00fala",
    "gn:population":0,
    "gn:timezone":"Europe/Athens",
    "iso:country":"GR",
    "name:ell_x_preferred":[
        "Vryso\u00fala"
    ],
    "name:ell_x_variant":[
        "\u0392\u03c1\u03c5\u03c3\u03bf\u03cd\u03bb\u03b1"
    ],
    "name:und_x_variant":[
        "Pazar\u00e1ki",
        "Pazar\u00e1kion",
        "Vriso\u00fala"
    ],
    "wof:name":"Vrysoula",
    "wof:placetype":"locality"
},
  "geometry": {"coordinates":[21.93889,37.30685],"type":"Point"}
}