{
  "type": "Feature",
  "properties": {
    "gn:admin1_code":"ESYE31",
    "gn:admin2_code":"445406.0",
    "gn:admin3_code":"9227.0",
    "gn:asciiname":"Drosia",
    "gn:country_code":"GR",
    "gn:dem":36,
    "gn:feature_class":"P",
    "gn:feature_code":"PPL",
    "gn:name":"Drosi\u00e1",
    "gn:population":0,
    "gn:timezone":"Europe/Athens",
    "iso:country":"GR",
    "name:ara_x_preferred":[
        "\u062f\u0631\u0648\u0633\u064a\u0627"
    ],
    "name:ceb_x_preferred":[
        "Drosi\u00e1"
    ],
    "name:deu_x_preferred":[
        "Drosia"
    ],
    "name:ell_x_preferred":[
        "Drosi\u00e1"
    ],
    "name:ell_x_variant":[
        "\u0394\u03c1\u03bf\u03c3\u03b9\u03ac",
        "\u0394\u03c1\u03bf\u03c3\u03b9\u03ac \u0391\u03c4\u03c4\u03b9\u03ba\u03ae\u03c2"
    ],
    "name:fin_x_preferred":[
        "Drosi\u00e1"
    ],
    "name:ita_x_preferred":[
        "Drosia"
    ],
    "name:nno_x_preferred":[
        "Drosi\u00e1"
    ],
    "name:ron_x_preferred":[
        "Drosia"
    ],
    "name:swe_x_preferred":[
        "Drosi\u00e1"
    ],
    "wof:name":"Drosia",
    "wof:placetype":"locality"
},
  "geometry": {"coordinates":[23.70119,38.32864],"type":"Point"}
}