{
  "type": "Feature",
  "properties": {
    "gn:admin1_code":"ESYE25",
    "gn:admin2_code":"42.0",
    "gn:admin3_code":"9252",
    "gn:asciiname":"Ayia Irini",
    "gn:cc2":"GR",
    "gn:country_code":"GR",
    "gn:dem":360,
    "gn:feature_class":"P",
    "gn:feature_code":"PPL",
    "gn:name":"Ay\u00eda Ir\u00edni",
    "gn:population":0,
    "gn:timezone":"Europe/Athens",
    "iso:country":"GR",
    "name:ell_x_historical":[
        "\u0392\u03ac\u03c1\u03c3\u03bf\u03b2\u03b1"
    ],
    "name:ell_x_preferred":[
        "\u0391\u03b3\u03af\u03b1 \u0395\u03b9\u03c1\u03ae\u03bd\u03b7"
    ],
    "name:ell_x_variant":[
        "\u0392\u03ac\u03c1\u03c3\u03bf\u03b2\u03b1"
    ],
    "name:und_x_variant":[
        "V\u00e1rsova",
        "Ay\u00eda Ir\u00edni"
    ],
    "wof:name":"Ayia Irini",
    "wof:placetype":"locality"
},
  "geometry": {"coordinates":[22.36795,37.09808],"type":"Point"}
}