{
  "type": "Feature",
  "properties": {
    "gn:admin1_code":"ESYE24",
    "gn:admin2_code":"33.0",
    "gn:admin3_code":"9144",
    "gn:asciiname":"Ypato",
    "gn:country_code":"GR",
    "gn:dem":201,
    "gn:feature_class":"P",
    "gn:feature_code":"PPL",
    "gn:name":"\u00ddpato",
    "gn:population":0,
    "gn:timezone":"Europe/Athens",
    "iso:country":"GR",
    "name:ell_x_preferred":[
        "\u00ddpato"
    ],
    "name:ell_x_variant":[
        "\u038e\u03c0\u03b1\u03c4\u03bf",
        "\u00ddpaton",
        "\u038e\u03c0\u03b1\u03c4\u03bf\u03bd",
        "\u038e\u03c0\u03b1\u03c4\u03bf \u0392\u03bf\u03b9\u03c9\u03c4\u03af\u03b1\u03c2"
    ],
    "name:sqi_x_preferred":[
        "Shirxhi"
    ],
    "name:und_x_variant":[
        "S\u00edrtzion",
        "S\u00edrtzi",
        "\u00cdpaton"
    ],
    "wof:name":"Ypato",
    "wof:placetype":"locality"
},
  "geometry": {"coordinates":[23.3939,38.3882],"type":"Point"}
}