{
  "type": "Feature",
  "properties": {
    "gn:admin1_code":"ESYE24",
    "gn:admin2_code":"30.0",
    "gn:admin3_code":"9156",
    "gn:asciiname":"Palaiomylos",
    "gn:country_code":"GR",
    "gn:dem":881,
    "gn:feature_class":"P",
    "gn:feature_code":"PPL",
    "gn:name":"Palai\u00f3mylos",
    "gn:population":0,
    "gn:timezone":"Europe/Athens",
    "iso:country":"GR",
    "name:ell_x_preferred":[
        "Palai\u00f3mylos"
    ],
    "name:ell_x_variant":[
        "\u03a0\u03b1\u03bb\u03b1\u03b9\u03cc\u03bc\u03c5\u03bb\u03bf\u03c2"
    ],
    "wof:name":"Palaiomylos",
    "wof:placetype":"locality"
},
  "geometry": {"coordinates":[21.52669,39.11619],"type":"Point"}
}