{
  "type": "Feature",
  "properties": {
    "gn:gn_country":"GR",
    "gn:gn_fcode":"PPL",
    "gn:gn_pop":700,
    "gn:population":700,
    "iso:country":"GR",
    "name:bul_x_preferred":[
        "\u041a\u0430\u0440\u043f\u0435\u0440\u043e"
    ],
    "name:ell_x_preferred":[
        "\u039a\u03b1\u03c1\u03c0\u03b5\u03c1\u03cc"
    ],
    "name:ell_x_variant":[
        "\u039a\u03b1\u03c1\u03c0\u03b5\u03c1\u03cc\u03bd",
        "\u039a\u03b1\u03c1\u03c0\u03b5\u03c1\u03cc \u0393\u03c1\u03b5\u03b2\u03b5\u03bd\u03ce\u03bd"
    ],
    "name:eng_x_preferred":[
        "Karpero"
    ],
    "name:mkd_x_preferred":[
        "\u0414\u0438\u043c\u0435\u043d\u0438\u0446\u0430"
    ],
    "name:nld_x_preferred":[
        "Karpero"
    ],
    "name:nno_x_preferred":[
        "Karper\u00f3"
    ],
    "name:unk_x_variant":[
        "Dhimin\u00edtsa"
    ],
    "qs_pg:aaroncc":"GR",
    "qs_pg:gn_country":"GR",
    "qs_pg:gn_fcode":"PPL",
    "qs_pg:gn_pop":700,
    "qs_pg:name":"Karper\u00f3n",
    "qs_pg:photos_9r":0,
    "qs_pg:photos_sr":0,
    "qs_pg:pop_sr":2,
    "qs_pg:qs_pg_placetype":"locality",
    "wof:name":"Karper\u00f3n",
    "wof:placetype":"locality",
    "wof:population":700
},
  "geometry": {"coordinates":[21.61306,39.94667],"type":"Point"}
}