{
  "type": "Feature",
  "properties": {
    "gn:admin1_code":"ESYE23",
    "gn:admin2_code":"39.0",
    "gn:admin3_code":"9135",
    "gn:asciiname":"Alikonitaiika",
    "gn:country_code":"GR",
    "gn:dem":0,
    "gn:feature_class":"P",
    "gn:feature_code":"PPL",
    "gn:name":"Alikonita\u00edika",
    "gn:population":0,
    "gn:timezone":"Europe/Athens",
    "iso:country":"GR",
    "name:ell_x_preferred":[
        "Alikonita\u00edika"
    ],
    "name:ell_x_variant":[
        "\u0391\u03bb\u03b9\u03ba\u03bf\u03bd\u03b9\u03c4\u03b1\u03af\u03b9\u03ba\u03b1"
    ],
    "name:und_x_variant":[
        "Alikanita\u00edika"
    ],
    "wof:name":"Alikonitaiika",
    "wof:placetype":"locality"
},
  "geometry": {"coordinates":[21.26394,37.97972],"type":"Point"}
}