{
  "type": "Feature",
  "properties": {
    "gn:admin1_code":"ESYE14",
    "gn:admin2_code":"23.0",
    "gn:admin3_code":"9094",
    "gn:asciiname":"Palaiochori",
    "gn:country_code":"GR",
    "gn:dem":863,
    "gn:feature_class":"P",
    "gn:feature_code":"PPL",
    "gn:name":"Palaioch\u00f3ri",
    "gn:population":0,
    "gn:timezone":"Europe/Athens",
    "iso:country":"GR",
    "name:ceb_x_preferred":[
        "Palaiochori"
    ],
    "name:ell_x_preferred":[
        "\u03a0\u03b1\u03bb\u03b1\u03b9\u03bf\u03c7\u03ce\u03c1\u03b9"
    ],
    "name:ell_x_variant":[
        "\u03a0\u03b1\u03bb\u03b1\u03b9\u03bf\u03c7\u03ce\u03c1\u03b9\u03bf\u03bd"
    ],
    "name:swe_x_preferred":[
        "Palaiochori"
    ],
    "name:und_x_variant":[
        "Palaioch\u00f3ri",
        "Paliokh\u00f3ri",
        "Palaiokh\u00f3rion",
        "Palaioch\u00f3rion"
    ],
    "wof:name":"Palaiochori",
    "wof:placetype":"locality"
},
  "geometry": {"coordinates":[21.59958,39.37272],"type":"Point"}
}