{
  "type": "Feature",
  "properties": {
    "gn:admin1_code":"ESYE43",
    "gn:admin2_code":"45.0",
    "gn:admin3_code":"9307",
    "gn:asciiname":"Diavaide",
    "gn:country_code":"GR",
    "gn:dem":353,
    "gn:feature_class":"P",
    "gn:feature_code":"PPL",
    "gn:name":"Diava\u00efd\u00e9",
    "gn:population":0,
    "gn:timezone":"Europe/Athens",
    "iso:country":"GR",
    "name:ell_x_preferred":[
        "Diava\u00efd\u00e9"
    ],
    "name:ell_x_variant":[
        "\u0394\u03b9\u03b1\u03b2\u03b1\u03ca\u03b4\u03ad",
        "Dhiava\u00efdh\u00e9"
    ],
    "wof:name":"Diavaide",
    "wof:placetype":"locality"
},
  "geometry": {"coordinates":[25.34602000000001,35.20401],"type":"Point"}
}