{
  "type": "Feature",
  "properties": {
    "gn:admin1_code":"ESYE31",
    "gn:admin2_code":"406101.0",
    "gn:admin3_code":"9209",
    "gn:asciiname":"Kryoneri Kythiron",
    "gn:country_code":"GR",
    "gn:dem":81,
    "gn:feature_class":"P",
    "gn:feature_code":"PPL",
    "gn:name":"Kryon\u00e9ri Kyth\u00edron",
    "gn:population":4,
    "gn:timezone":"Europe/Athens",
    "iso:country":"GR",
    "name:ell_x_historical":[
        "\u039d\u03c4\u03b5\u03bd\u03c4\u03b9\u03ac\u03bd\u03b9\u03ba\u03b1"
    ],
    "name:ell_x_preferred":[
        "\u039a\u03c1\u03c5\u03bf\u03bd\u03ad\u03c1\u03b9 \u039a\u03c5\u03b8\u03ae\u03c1\u03c9\u03bd"
    ],
    "name:ell_x_variant":[
        "\u039d\u03c4\u03b5\u03bd\u03c4\u03b9\u03ac\u03bd\u03b9\u03ba\u03b1",
        "\u039a\u03c1\u03c5\u03bf\u03bd\u03ad\u03c1\u03b9\u03bf\u03bd"
    ],
    "name:eng_x_preferred":[
        "Kryoneri Kythiron"
    ],
    "name:und_x_variant":[
        "Dedi\u00e1nika",
        "Dendi\u00e1nika"
    ],
    "wof:name":"Kryoneri Kythiron",
    "wof:placetype":"locality",
    "wof:population":4
},
  "geometry": {"coordinates":[22.94771,36.35383],"type":"Point"}
}