{
  "type": "Feature",
  "properties": {
    "gn:admin1_code":"ESYE23",
    "gn:admin2_code":"39.0",
    "gn:admin3_code":"9138.0",
    "gn:asciiname":"Kotroni",
    "gn:country_code":"GR",
    "gn:dem":218,
    "gn:feature_class":"P",
    "gn:feature_code":"PPL",
    "gn:name":"Kotr\u00f3ni",
    "gn:population":0,
    "gn:timezone":"Europe/Athens",
    "iso:country":"GR",
    "name:ell_x_preferred":[
        "\u039a\u03bf\u03c4\u03c1\u03ce\u03bd\u03b9"
    ],
    "name:ell_x_variant":[
        "\u039a\u03bf\u03c4\u03c1\u03ce\u03bd\u03b9 \u039e\u03b7\u03c1\u03bf\u03c7\u03c9\u03c1\u03af\u03bf\u03c5",
        "\u039a\u03bf\u03c4\u03c1\u03ce\u03bd\u03b9 \u03a0\u03ac\u03c4\u03c1\u03b1\u03c2"
    ],
    "name:ron_x_preferred":[
        "Kotroni"
    ],
    "wof:name":"Kotroni",
    "wof:placetype":"locality"
},
  "geometry": {"coordinates":[21.64053,37.51757],"type":"Point"}
}