{
  "type": "Feature",
  "properties": {
    "gn:admin1_code":"ESYE43",
    "gn:admin2_code":"46.0",
    "gn:admin3_code":"9310",
    "gn:asciiname":"Atzimpraga",
    "gn:country_code":"GR",
    "gn:dem":275,
    "gn:feature_class":"P",
    "gn:feature_code":"PPL",
    "gn:name":"Atzimprag\u00e1",
    "gn:population":52,
    "gn:timezone":"Europe/Athens",
    "iso:country":"GR",
    "name:ell_x_colloquial":[
        "\u0391\u03c4\u03b6\u03b9\u03bc\u03c0\u03c1\u03b1\u03b3\u03ac"
    ],
    "name:ell_x_preferred":[
        "\u0391\u03c4\u03b6\u03b9\u03bc\u03c0\u03c1\u03b1\u03b3\u03ac"
    ],
    "name:ell_x_variant":[
        "\u0391\u03c4\u03c3\u03b9\u03bc\u03c0\u03c1\u03b1\u03b3\u03ac",
        "\u0391\u03c4\u03b6\u03b9\u03bc\u03c0\u03c1\u03ac\u03b3\u03b1"
    ],
    "name:und_x_variant":[
        "Atsimbrag\u00e1",
        "Atsiprani\u00e1",
        "Atsimbrayi\u00e1",
        "Atsimprag\u00e1"
    ],
    "wof:name":"Atzimpraga",
    "wof:placetype":"locality",
    "wof:population":52
},
  "geometry": {"coordinates":[25.70724,35.2346],"type":"Point"}
}