{
  "type": "Feature",
  "properties": {
    "gn:population":1165,
    "iso:country":"GR",
    "name:ara_x_preferred":[
        "\u0645\u064a\u062b\u0648\u0646\u064a"
    ],
    "name:cat_x_preferred":[
        "Modona"
    ],
    "name:cat_x_variant":[
        "Mod\u00f3"
    ],
    "name:ceb_x_preferred":[
        "Meth\u00f3ni"
    ],
    "name:deu_x_preferred":[
        "Methoni"
    ],
    "name:ell_x_preferred":[
        "\u039c\u03b5\u03b8\u03ce\u03bd\u03b7 \u039c\u03b5\u03c3\u03c3\u03b7\u03bd\u03af\u03b1\u03c2"
    ],
    "name:ell_x_variant":[
        "\u039c\u03b5\u03b8\u03ce\u03bd\u03b7"
    ],
    "name:eng_x_preferred":[
        "Methoni"
    ],
    "name:fas_x_preferred":[
        "\u0645\u062b\u0648\u0646\u06cc"
    ],
    "name:fin_x_preferred":[
        "Meth\u00f3ni"
    ],
    "name:fra_x_preferred":[
        "Modon"
    ],
    "name:glg_x_preferred":[
        "Modon"
    ],
    "name:grc_x_preferred":[
        "\u039c\u03b5\u03b8\u03ce\u03bd\u03b7 \u03a0\u03b9\u03b5\u03c1\u03af\u03b1\u03c2"
    ],
    "name:hbs_x_preferred":[
        "Metoni"
    ],
    "name:hye_x_preferred":[
        "\u0544\u0565\u0569\u0578\u0576\u056b"
    ],
    "name:ita_x_preferred":[
        "Modone"
    ],
    "name:jpn_x_preferred":[
        "\u30e1\u30bd\u30cb"
    ],
    "name:nld_x_preferred":[
        "Methone"
    ],
    "name:nno_x_preferred":[
        "Meth\u00f3ni"
    ],
    "name:pol_x_preferred":[
        "Metoni"
    ],
    "name:pol_x_variant":[
        "Methoni"
    ],
    "name:por_x_preferred":[
        "Modon"
    ],
    "name:ron_x_preferred":[
        "Methoni"
    ],
    "name:rus_x_preferred":[
        "\u041c\u0435\u0442\u043e\u043d\u0438"
    ],
    "name:spa_x_preferred":[
        "Modona"
    ],
    "name:swe_x_preferred":[
        "Methone"
    ],
    "name:tur_x_preferred":[
        "Methone"
    ],
    "name:unk_x_variant":[
        "N\u00e9on Elevtherokh\u00f3rion"
    ],
    "name:vec_x_preferred":[
        "Modon"
    ],
    "qs:a0":"Greece",
    "qs:a1":"*\u03a0\u0395\u039b\u039f\u03a0\u039f\u039d\u039d\u0397\u03a3\u039f\u03a3",
    "qs:a1_alt":"PELOPONNHSOS",
    "qs:a1r":"0",
    "qs:a2_alt":"MESSHNIA",
    "qs:adm0":"Greece",
    "qs:la_lc":"*",
    "qs:level":"locality",
    "qs:loc":"\u039c\u0395\u0398\u03a9\u039d\u0397",
    "qs:loc_alt":"MEUVNH",
    "qs:pop":0,
    "qs:type":"buffered point",
    "wd:wordcount":1879,
    "wof:name":"\u039c\u0395\u0398\u03a9\u039d\u0397",
    "wof:placetype":"locality",
    "wof:population":1165
},
  "geometry": {"coordinates":[21.705015,36.818375],"type":"Point"}
}