{
  "type": "Feature",
  "properties": {
    "gn:admin1_code":"ESYE25",
    "gn:admin2_code":"40.0",
    "gn:admin3_code":"9256",
    "gn:asciiname":"Kallirroei",
    "gn:country_code":"GR",
    "gn:dem":123,
    "gn:feature_class":"P",
    "gn:feature_code":"PPL",
    "gn:name":"Kallirr\u00f6\u1e2f",
    "gn:population":273,
    "gn:timezone":"Europe/Athens",
    "iso:country":"GR",
    "name:ell_x_historical":[
        "\u039c\u03c0\u03bf\u03cd\u03b3\u03b1"
    ],
    "name:ell_x_preferred":[
        "\u039a\u03b1\u03bb\u03bb\u03b9\u03c1\u03cc\u03b7"
    ],
    "name:ell_x_variant":[
        "\u039c\u03c0\u03bf\u03cd\u03b3\u03b1"
    ],
    "name:und_x_variant":[
        "Bo\u00fara",
        "Kallir\u00f3i",
        "Bo\u00faga",
        "Kallirr\u00f6\u1e2f"
    ],
    "wof:name":"Kallirroei",
    "wof:placetype":"locality",
    "wof:population":273
},
  "geometry": {"coordinates":[21.93008,37.26627],"type":"Point"}
}