{
  "type": "Feature",
  "properties": {
    "gn:admin1_code":"ESYE31",
    "gn:admin2_code":"406101.0",
    "gn:admin3_code":"9211.0",
    "gn:asciiname":"Xeno",
    "gn:country_code":"GR",
    "gn:dem":17,
    "gn:feature_class":"P",
    "gn:feature_code":"PPL",
    "gn:name":"X\u00e9no",
    "gn:population":0,
    "gn:timezone":"Europe/Athens",
    "iso:country":"GR",
    "name:ell_x_preferred":[
        "X\u00e9no"
    ],
    "name:ell_x_variant":[
        "\u039e\u03ad\u03bd\u03bf"
    ],
    "wof:name":"Xeno",
    "wof:placetype":"locality"
},
  "geometry": {"coordinates":[23.4503,37.9652],"type":"Point"}
}