{
  "type": "Feature",
  "properties": {
    "gn:admin1_code":"ESYE31",
    "gn:admin2_code":"406101.0",
    "gn:admin3_code":"9213",
    "gn:asciiname":"Ayioi Theodhoroi Methanon",
    "gn:country_code":"GR",
    "gn:dem":128,
    "gn:feature_class":"P",
    "gn:feature_code":"PPL",
    "gn:name":"\u00c1yioi The\u00f3dhoroi Meth\u00e1non",
    "gn:population":45,
    "gn:timezone":"Europe/Athens",
    "iso:country":"GR",
    "name:ell_x_preferred":[
        "\u0386\u03b3\u03b9\u03bf\u03b9 \u0398\u03b5\u03cc\u03b4\u03c9\u03c1\u03bf\u03b9 \u039c\u03b5\u03b8\u03ac\u03bd\u03c9\u03bd"
    ],
    "name:eng_x_preferred":[
        "Agioi Theodoroi Methanon"
    ],
    "wof:name":"Ayioi Theodhoroi Methanon",
    "wof:placetype":"locality",
    "wof:population":45
},
  "geometry": {"coordinates":[23.39879,37.62091],"type":"Point"}
}