{
  "type": "Feature",
  "properties": {
    "gn:population":1357,
    "iso:country":"GR",
    "name:ara_x_preferred":[
        "\u0623\u0641\u0627\u062a\u0648\u0646"
    ],
    "name:ara_x_variant":[
        "\u0623\u0641\u0627\u062a\u0648"
    ],
    "name:ceb_x_preferred":[
        "\u00c1vato"
    ],
    "name:ell_x_preferred":[
        "\u0386\u03b2\u03b1\u03c4\u03bf \u039e\u03ac\u03bd\u03b8\u03b7\u03c2"
    ],
    "name:ell_x_variant":[
        "\u0386\u03b2\u03b1\u03c4\u03bf\u03bd",
        "\u00c1vato",
        "\u0386\u03b2\u03b1\u03c4\u03bf"
    ],
    "name:eng_x_preferred":[
        "Avato"
    ],
    "name:fra_x_preferred":[
        "Avato"
    ],
    "name:nld_x_preferred":[
        "Avato"
    ],
    "name:srp_x_preferred":[
        "\u0410\u0432\u0430\u0442\u043e"
    ],
    "name:swe_x_preferred":[
        "\u00c1vato"
    ],
    "name:tur_x_preferred":[
        "Beyk\u00f6y\u00fc"
    ],
    "name:unk_x_variant":[
        "\u00c1vaton"
    ],
    "qs:a0":"Greece",
    "qs:a1":"*\u0391\u039d\u0391\u03a4\u039f\u039b\u0399\u039a\u0397 \u039c\u0391\u039a\u0395\u0394\u039f\u039d\u0399\u0391 \u039a\u0391\u0399 \u0398\u03a1\u0391\u039a\u0397",
    "qs:a1_alt":"ANATOLIKH MAKEDONIA KAI URAKH",
    "qs:a1r":"0",
    "qs:a2_alt":"JANUH",
    "qs:adm0":"Greece",
    "qs:la_lc":"*",
    "qs:level":"locality",
    "qs:loc":"\u0391\u0392\u0391\u03a4\u039f\u039d",
    "qs:loc_alt":"ABATON",
    "qs:pop":0,
    "qs:type":"buffered point",
    "wd:wordcount":143,
    "wof:name":"\u0391\u0392\u0391\u03a4\u039f\u039d",
    "wof:placetype":"locality",
    "wof:population":1357
},
  "geometry": {"coordinates":[24.814182,40.964401],"type":"Point"}
}