{
  "type": "Feature",
  "properties": {
    "gn:admin1_code":"ESYE22",
    "gn:admin2_code":"25.0",
    "gn:admin3_code":"9118",
    "gn:asciiname":"Roumanades",
    "gn:country_code":"GR",
    "gn:dem":50,
    "gn:feature_class":"P",
    "gn:feature_code":"PPL",
    "gn:name":"Rouman\u00e1des",
    "gn:population":32,
    "gn:timezone":"Europe/Athens",
    "iso:country":"GR",
    "name:ell_x_preferred":[
        "\u03a1\u03bf\u03c5\u03bc\u03b1\u03bd\u03ac\u03b4\u03b5\u03c2"
    ],
    "name:eng_x_preferred":[
        "Roumanades"
    ],
    "name:und_x_variant":[
        "Rouman\u00e1dhes",
        "Rouman\u00e1des"
    ],
    "wof:name":"Roumanades",
    "wof:placetype":"locality",
    "wof:population":32
},
  "geometry": {"coordinates":[19.99433,39.43964],"type":"Point"}
}