{
  "type": "Feature",
  "properties": {
    "gn:admin1_code":"ESYE22",
    "gn:admin2_code":"27.0",
    "gn:admin3_code":"9120",
    "gn:asciiname":"Kleismata",
    "gn:country_code":"GR",
    "gn:dem":135,
    "gn:feature_class":"P",
    "gn:feature_code":"PPL",
    "gn:name":"Kle\u00edsmata",
    "gn:population":0,
    "gn:timezone":"Europe/Athens",
    "iso:country":"GR",
    "name:ell_x_preferred":[
        "Kle\u00edsmata"
    ],
    "name:ell_x_variant":[
        "\u039a\u03bb\u03b5\u03af\u03c3\u03bc\u03b1\u03c4\u03b1"
    ],
    "name:und_x_variant":[
        "Kl\u00edsmata"
    ],
    "wof:name":"Kleismata",
    "wof:placetype":"locality"
},
  "geometry": {"coordinates":[20.55669,38.10506],"type":"Point"}
}