{
  "type": "Feature",
  "properties": {
    "gn:gn_country":"GR",
    "gn:gn_fcode":"PPL",
    "gn:gn_pop":162,
    "gn:population":129,
    "iso:country":"GR",
    "name:ell_x_preferred":[
        "\u039a\u03c1\u03c5\u03bf\u03bd\u03ad\u03c1\u03b9"
    ],
    "name:ell_x_variant":[
        "\u039a\u03c1\u03c5\u03bf\u03bd\u03ad\u03c1\u03b9\u03bf\u03bd"
    ],
    "name:eng_x_preferred":[
        "Kryoneri"
    ],
    "name:unk_x_variant":[
        "Krion\u00e9rion"
    ],
    "qs_pg:aaroncc":"GR",
    "qs_pg:gn_country":"GR",
    "qs_pg:gn_fcode":"PPL",
    "qs_pg:gn_pop":162,
    "qs_pg:name":"Kryon\u00e9rion",
    "qs_pg:photos_9r":0,
    "qs_pg:photos_sr":0,
    "qs_pg:pop_sr":1,
    "qs_pg:qs_pg_placetype":"locality",
    "wof:name":"Kryon\u00e9rion",
    "wof:placetype":"locality",
    "wof:population":129
},
  "geometry": {"coordinates":[20.50111,39.88556],"type":"Point"}
}