{
  "type": "Feature",
  "properties": {
    "gn:population":2589,
    "iso:country":"GR",
    "name:ara_x_preferred":[
        "\u0628\u0627\u0644\u064a\u0631\u0648\u0633\u060c \u0623\u064a\u062a\u0648\u0644\u064a\u0627 \u0643\u064a \u0623\u0643\u0627\u0631\u0646\u0627\u0646\u064a\u0627"
    ],
    "name:ell_x_preferred":[
        "\u0394\u03ae\u03bc\u03bf\u03c2 \u039a\u03b5\u03ba\u03c1\u03bf\u03c0\u03af\u03b1\u03c2"
    ],
    "name:ell_x_variant":[
        "\u03a0\u03ac\u03bb\u03b1\u03b9\u03c1\u03bf\u03c2",
        "\u03a0\u03ac\u03bb\u03b1\u03b9\u03c1\u03bf\u03c2 \u0391\u03b9\u03c4\u03c9\u03bb\u03bf\u03b1\u03ba\u03b1\u03c1\u03bd\u03b1\u03bd\u03af\u03b1\u03c2"
    ],
    "name:eng_x_preferred":[
        "P\u00e1lairos"
    ],
    "name:fin_x_preferred":[
        "P\u00e1lairos"
    ],
    "name:ita_x_preferred":[
        "Kekropia"
    ],
    "name:jpn_x_preferred":[
        "\u30b1\u30af\u30ed\u30d4\u30a2"
    ],
    "name:nld_x_preferred":[
        "Palairos"
    ],
    "name:nno_x_preferred":[
        "P\u00e1leros"
    ],
    "name:ron_x_preferred":[
        "Kekropia"
    ],
    "name:spa_x_preferred":[
        "Palero"
    ],
    "name:swe_x_preferred":[
        "P\u00e1lairos"
    ],
    "name:unk_x_variant":[
        "Zav\u00e9dha"
    ],
    "qs:a0":"Greece",
    "qs:a1":"*\u0394\u03a5\u03a4\u0399\u039a\u0397 \u0395\u039b\u039b\u0391\u0394\u0391",
    "qs:a1_alt":"DYTIKH ELLADA",
    "qs:a1r":"0",
    "qs:a2_alt":"AITVLIA KAI AKARNANIA",
    "qs:adm0":"Greece",
    "qs:la_lc":"*",
    "qs:level":"locality",
    "qs:loc":"\u03a0\u0391\u039b\u0391\u0399\u03a1\u039f\u03a3",
    "qs:loc_alt":"PALAIROS",
    "qs:pop":0,
    "qs:type":"buffered point",
    "wd:wordcount":306,
    "wof:name":"\u03a0\u0391\u039b\u0391\u0399\u03a1\u039f\u03a3",
    "wof:placetype":"locality",
    "wof:population":2589
},
  "geometry": {"coordinates":[20.883726,38.781875],"type":"Point"}
}