{
  "type": "Feature",
  "properties": {
    "gn:admin1_code":"ESYE13",
    "gn:admin2_code":"11.0",
    "gn:admin3_code":"9068",
    "gn:asciiname":"Pontokomi",
    "gn:country_code":"GR",
    "gn:dem":706,
    "gn:feature_class":"P",
    "gn:feature_code":"PPL",
    "gn:name":"Pontok\u00f3mi",
    "gn:population":0,
    "gn:timezone":"Europe/Athens",
    "iso:country":"GR",
    "name:ara_x_preferred":[
        "\u0628\u0648\u0646\u062a\u0648\u0643\u0648\u0645\u064a"
    ],
    "name:bul_x_preferred":[
        "\u041f\u043e\u043d\u0434\u043e\u043a\u043e\u043c\u0438"
    ],
    "name:ell_x_preferred":[
        "Pontok\u00f3mi"
    ],
    "name:ell_x_variant":[
        "\u03a0\u03bf\u03bd\u03c4\u03bf\u03ba\u03ce\u03bc\u03b7",
        "\u03a0\u03bf\u03bd\u03c4\u03bf\u03ba\u03ce\u03bc\u03b7 \u039a\u03bf\u03b6\u03ac\u03bd\u03b7\u03c2"
    ],
    "name:mkd_x_preferred":[
        "\u0412\u0440\u0434\u043e\u043c\u0438\u0446\u0438"
    ],
    "name:srp_x_preferred":[
        "\u041f\u043e\u043d\u0434\u043e\u043a\u043e\u043c\u0438"
    ],
    "name:und_x_variant":[
        "Ertom\u00fas",
        "Pondok\u00f3mi"
    ],
    "wof:name":"Pontokomi",
    "wof:placetype":"locality"
},
  "geometry": {"coordinates":[21.76195,40.41047],"type":"Point"}
}