{
  "type": "Feature",
  "properties": {
    "gn:admin1_code":"ESYE13",
    "gn:admin2_code":"11.0",
    "gn:admin3_code":"9068",
    "gn:asciiname":"Pontokomi",
    "gn:country_code":"GR",
    "gn:dem":706,
    "gn:feature_class":"P",
    "gn:feature_code":"PPL",
    "gn:name":"Pontok\u00f3mi",
    "gn:population":0,
    "gn:timezone":"Europe/Athens",
    "iso:country":"GR",
    "name:ell_x_preferred":[
        "Pontok\u00f3mi"
    ],
    "name:ell_x_variant":[
        "\u03a0\u03bf\u03bd\u03c4\u03bf\u03ba\u03ce\u03bc\u03b7"
    ],
    "name:und_x_variant":[
        "Ertom\u00fas",
        "Pondok\u00f3mi"
    ],
    "wof:name":"Pontokomi",
    "wof:placetype":"locality"
},
  "geometry": {"coordinates":[21.76195,40.41047],"type":"Point"}
}