{
  "type": "Feature",
  "properties": {
    "gn:admin1_code":"ESYE43",
    "gn:admin2_code":"43.0",
    "gn:admin3_code":"9321",
    "gn:asciiname":"Skafi",
    "gn:country_code":"GR",
    "gn:dem":498,
    "gn:feature_class":"P",
    "gn:feature_code":"PPL",
    "gn:name":"Sk\u00e1fi",
    "gn:population":0,
    "gn:timezone":"Europe/Athens",
    "iso:country":"GR",
    "name:ell_x_preferred":[
        "\u03a3\u03ba\u03ac\u03c6\u03b7"
    ],
    "name:und_x_variant":[
        "Skafidh\u00e1ki",
        "Sk\u00e1fi"
    ],
    "wof:name":"Skafi",
    "wof:placetype":"locality"
},
  "geometry": {"coordinates":[23.79039,35.32274],"type":"Point"}
}