{
  "type": "Feature",
  "properties": {
    "gn:admin1_code":"ESYE14",
    "gn:admin2_code":"24.0",
    "gn:admin3_code":"9108",
    "gn:asciiname":"Kokolaiika",
    "gn:country_code":"GR",
    "gn:dem":190,
    "gn:feature_class":"P",
    "gn:feature_code":"PPL",
    "gn:name":"Kokola\u00edika",
    "gn:population":102,
    "gn:timezone":"Europe/Athens",
    "iso:country":"GR",
    "name:ell_x_preferred":[
        "\u039a\u03bf\u03ba\u03bf\u03bb\u03b1\u03af\u03b9\u03ba\u03b1"
    ],
    "name:eng_x_preferred":[
        "Kokolaiika"
    ],
    "wof:name":"Kokolaiika",
    "wof:placetype":"locality",
    "wof:population":102
},
  "geometry": {"coordinates":[22.74874,39.31667],"type":"Point"}
}