{
  "type": "Feature",
  "properties": {
    "gn:admin1_code":"ESYE11",
    "gn:admin2_code":"14.0",
    "gn:admin3_code":"9014",
    "gn:asciiname":"Moni Agiou Panteleimonos",
    "gn:country_code":"GR",
    "gn:dem":331,
    "gn:feature_class":"P",
    "gn:feature_code":"PPLR",
    "gn:name":"Mon\u00ed Ag\u00edou Pantele\u00edmonos",
    "gn:population":15,
    "gn:timezone":"Europe/Athens",
    "iso:country":"GR",
    "name:ell_x_preferred":[
        "\u039c\u03bf\u03bd\u03ae \u0391\u03b3\u03af\u03bf\u03c5 \u03a0\u03b1\u03bd\u03c4\u03b5\u03bb\u03b5\u03ae\u03bc\u03bf\u03bd\u03bf\u03c2"
    ],
    "wof:name":"Moni Agiou Panteleimonos",
    "wof:placetype":"locality",
    "wof:population":15
},
  "geometry": {"coordinates":[24.19001,40.89117],"type":"Point"}
}