{
  "type": "Feature",
  "properties": {
    "gn:admin1_code":"ESYE13",
    "gn:admin2_code":"9.0",
    "gn:admin3_code":"9065",
    "gn:asciiname":"Ampelokipoi",
    "gn:country_code":"GR",
    "gn:dem":645,
    "gn:feature_class":"P",
    "gn:feature_code":"PPL",
    "gn:name":"Ampel\u00f3kipoi",
    "gn:population":668,
    "gn:timezone":"Europe/Athens",
    "iso:country":"GR",
    "name:bul_x_preferred":[
        "\u0410\u043c\u0431\u0435\u043b\u043e\u043a\u0438\u043f\u0438"
    ],
    "name:deu_x_preferred":[
        "Ambelokipi"
    ],
    "name:ell_x_preferred":[
        "\u0391\u03bc\u03c0\u03b5\u03bb\u03cc\u03ba\u03b7\u03c0\u03bf\u03b9"
    ],
    "name:eng_x_preferred":[
        "Ampelokipoi"
    ],
    "name:fin_x_preferred":[
        "Ampel\u00f3kipoi"
    ],
    "name:und_x_variant":[
        "Sdr\u00e1ltsi",
        "Ambel\u00f3kipoi",
        "Ampel\u00f3kipoi"
    ],
    "wof:name":"Ampelokipoi",
    "wof:placetype":"locality",
    "wof:population":668
},
  "geometry": {"coordinates":[21.31001,40.46582],"type":"Point"}
}