{
  "type": "Feature",
  "properties": {
    "gn:admin1_code":"ESYE12",
    "gn:admin2_code":"5.0",
    "gn:admin3_code":"9050",
    "gn:asciiname":"Oreskeia",
    "gn:country_code":"GR",
    "gn:dem":118,
    "gn:feature_class":"P",
    "gn:feature_code":"PPL",
    "gn:name":"Or\u00e9skeia",
    "gn:population":57,
    "gn:timezone":"Europe/Athens",
    "iso:country":"GR",
    "name:ell_x_preferred":[
        "\u039f\u03c1\u03ad\u03c3\u03ba\u03b5\u03b9\u03b1"
    ],
    "name:ell_x_variant":[
        "Or\u00e9skeia"
    ],
    "name:eng_x_preferred":[
        "Oreskeia"
    ],
    "name:und_x_variant":[
        "Or\u00e9stia",
        "Or\u00e9skia"
    ],
    "wof:name":"Oreskeia",
    "wof:placetype":"locality",
    "wof:population":57
},
  "geometry": {"coordinates":[23.64327,40.8556],"type":"Point"}
}