{
  "type": "Feature",
  "properties": {
    "gn:admin1_code":"ESYE43",
    "gn:admin2_code":"43.0",
    "gn:admin3_code":"9321",
    "gn:asciiname":"Farangi",
    "gn:country_code":"GR",
    "gn:dem":581,
    "gn:feature_class":"P",
    "gn:feature_code":"PPL",
    "gn:name":"Far\u00e1ngi",
    "gn:population":0,
    "gn:timezone":"Europe/Athens",
    "iso:country":"GR",
    "name:ell_x_preferred":[
        "Far\u00e1ngi"
    ],
    "name:ell_x_variant":[
        "\u03a6\u03b1\u03c1\u03ac\u03b3\u03b3\u03b9",
        "Far\u00e1ngion",
        "\u03a6\u03b1\u03c1\u03ac\u03b3\u03b3\u03b9\u03bf\u03bd"
    ],
    "wof:name":"Farangi",
    "wof:placetype":"locality"
},
  "geometry": {"coordinates":[23.6512,35.33013],"type":"Point"}
}