{
  "type": "Feature",
  "properties": {
    "gn:admin1_code":"ESYE43",
    "gn:admin2_code":"45.0",
    "gn:admin3_code":"9302",
    "gn:asciiname":"Partheni",
    "gn:country_code":"GR",
    "gn:dem":484,
    "gn:feature_class":"P",
    "gn:feature_code":"PPL",
    "gn:name":"Parth\u00e9ni",
    "gn:population":0,
    "gn:timezone":"Europe/Athens",
    "iso:country":"GR",
    "name:ell_x_preferred":[
        "Parth\u00e9ni"
    ],
    "name:ell_x_variant":[
        "\u03a0\u03b1\u03c1\u03b8\u03ad\u03bd\u03b9",
        "Parth\u00e9nion",
        "\u03a0\u03b1\u03c1\u03b8\u03ad\u03bd\u03b9\u03bf\u03bd"
    ],
    "wof:name":"Partheni",
    "wof:placetype":"locality"
},
  "geometry": {"coordinates":[25.16503,35.16272],"type":"Point"}
}