{
  "type": "Feature",
  "properties": {
    "gn:admin1_code":"ESYE43",
    "gn:admin2_code":"43.0",
    "gn:admin3_code":"9325",
    "gn:asciiname":"Madaro",
    "gn:country_code":"GR",
    "gn:dem":564,
    "gn:feature_class":"P",
    "gn:feature_code":"PPL",
    "gn:name":"Madar\u00f3",
    "gn:population":0,
    "gn:timezone":"Europe/Athens",
    "iso:country":"GR",
    "name:ell_x_preferred":[
        "Madar\u00f3"
    ],
    "name:ell_x_variant":[
        "\u039c\u03b1\u03b4\u03b1\u03c1\u03cc",
        "Madar\u00f3n",
        "\u039c\u03b1\u03b4\u03b1\u03c1\u03cc\u03bd"
    ],
    "name:und_x_variant":[
        "Madhar\u00f3",
        "Madhar\u00f3n"
    ],
    "wof:name":"Madaro",
    "wof:placetype":"locality"
},
  "geometry": {"coordinates":[24.07274,35.39607],"type":"Point"}
}