{
  "type": "Feature",
  "properties": {
    "gn:admin1_code":"ESYE23",
    "gn:admin2_code":"38.0",
    "gn:admin3_code":"9133",
    "gn:asciiname":"Dechouni",
    "gn:country_code":"GR",
    "gn:dem":851,
    "gn:feature_class":"P",
    "gn:feature_code":"PPL",
    "gn:name":"Decho\u00fani",
    "gn:population":0,
    "gn:timezone":"Europe/Athens",
    "iso:country":"GR",
    "name:ell_x_preferred":[
        "Decho\u00fani"
    ],
    "name:ell_x_variant":[
        "\u0394\u03b5\u03c7\u03bf\u03cd\u03bd\u03b9",
        "Decho\u00fanion",
        "\u0394\u03b5\u03c7\u03bf\u03cd\u03bd\u03b9\u03bf\u03bd"
    ],
    "name:und_x_variant":[
        "Dhekho\u00fani",
        "Dhekho\u00fanion"
    ],
    "wof:name":"Dechouni",
    "wof:placetype":"locality"
},
  "geometry": {"coordinates":[21.92817,37.83631],"type":"Point"}
}