{
  "type": "Feature",
  "properties": {
    "gn:country":"GR",
    "gn:fcode":"PPL",
    "gn:population":174,
    "iso:country":"GR",
    "name:ceb_x_preferred":[
        "Ar\u00edsti"
    ],
    "name:ell_x_historical":[
        "\u0391\u03c1\u03c4\u03c3\u03af\u03c3\u03c4\u03b1"
    ],
    "name:ell_x_preferred":[
        "\u0391\u03c1\u03af\u03c3\u03c4\u03b7"
    ],
    "name:ell_x_variant":[
        "\u0391\u03c1\u03c4\u03c3\u03af\u03c3\u03c4\u03b1",
        "\u0391\u03c1\u03af\u03c3\u03c4\u03b7 \u0399\u03c9\u03b1\u03bd\u03bd\u03af\u03bd\u03c9\u03bd"
    ],
    "name:eng_x_preferred":[
        "Aristi"
    ],
    "name:fra_x_preferred":[
        "Aristi"
    ],
    "name:mkd_x_preferred":[
        "\u0410\u0440\u0447\u0438\u0448\u0442\u0430"
    ],
    "name:nld_x_preferred":[
        "Aristi"
    ],
    "name:rus_x_preferred":[
        "\u0410\u0440\u0438\u0441\u0442\u0438"
    ],
    "name:swe_x_preferred":[
        "Ar\u00edsti"
    ],
    "name:und_x_variant":[
        "Arts\u00edsta"
    ],
    "qs_pg:aaroncc":"GR",
    "qs_pg:gn_country":"GR",
    "qs_pg:gn_fcode":"PPL",
    "qs_pg:gn_pop":174,
    "qs_pg:name":"Aristi",
    "qs_pg:name_adm0":"\u0395\u03bb\u03bb\u03ac\u03b4\u03b1",
    "qs_pg:name_adm1":"Epirus and Western Macedonia",
    "qs_pg:photos":78,
    "qs_pg:photos_1k":16,
    "qs_pg:photos_9k":1,
    "qs_pg:photos_9r":3,
    "qs_pg:photos_all":78,
    "qs_pg:photos_sr":3,
    "qs_pg:pop_sr":1,
    "qs_pg:qs_pg_placetype":"locality",
    "qs_pg:qs_pg_placetype_gp":"Town",
    "qs_pg:woe_adm0":23424833,
    "woe:adm0_id":23424833,
    "woe:name_adm0":"\u0395\u03bb\u03bb\u03ac\u03b4\u03b1",
    "woe:name_adm1":"Epirus and Western Macedonia",
    "woe:placetype":"Town",
    "wof:name":"Aristi",
    "wof:placetype":"locality",
    "wof:population":128
},
  "geometry": {"coordinates":[20.67361,39.93306],"type":"Point"}
}