{
  "type": "Feature",
  "properties": {
    "gn:admin1_code":"ESYE24",
    "gn:admin2_code":"34.0",
    "gn:admin3_code":"9152",
    "gn:asciiname":"Agia Sofia",
    "gn:country_code":"GR",
    "gn:dem":109,
    "gn:feature_class":"P",
    "gn:feature_code":"PPL",
    "gn:name":"Ag\u00eda Sof\u00eda",
    "gn:population":0,
    "gn:timezone":"Europe/Athens",
    "iso:country":"GR",
    "name:ell_x_preferred":[
        "Ag\u00eda Sof\u00eda"
    ],
    "name:ell_x_variant":[
        "\u0391\u03b3\u03af\u03b1 \u03a3\u03bf\u03c6\u03af\u03b1"
    ],
    "name:und_x_variant":[
        "Ay\u00eda Sof\u00eda"
    ],
    "wof:name":"Agia Sofia",
    "wof:placetype":"locality"
},
  "geometry": {"coordinates":[24.08236,38.39178],"type":"Point"}
}