{
  "type": "Feature",
  "properties": {
    "gn:admin1_code":"ESYE11",
    "gn:admin2_code":"2.0",
    "gn:admin3_code":"9022",
    "gn:asciiname":"Kizari",
    "gn:country_code":"GR",
    "gn:dem":169,
    "gn:feature_class":"P",
    "gn:feature_code":"PPL",
    "gn:name":"Kiz\u00e1ri",
    "gn:population":0,
    "gn:timezone":"Europe/Athens",
    "iso:country":"GR",
    "name:ell_x_preferred":[
        "Kiz\u00e1ri"
    ],
    "name:ell_x_variant":[
        "\u039a\u03b9\u03b6\u03ac\u03c1\u03b9",
        "\u039a\u03b9\u03b6\u03ac\u03c1\u03b9\u03bf\u03bd"
    ],
    "name:und_x_variant":[
        "K\u00edzeri",
        "Kisl\u00e1ri",
        "Kiz\u00e1rion"
    ],
    "wof:name":"Kizari",
    "wof:placetype":"locality"
},
  "geometry": {"coordinates":[25.76785,41.06131],"type":"Point"}
}