{
  "type": "Feature",
  "properties": {
    "gn:country":"GR",
    "gn:fcode":"PPL",
    "gn:population":95,
    "iso:country":"GR",
    "name:ell_x_preferred":[
        "\u039c\u03b7\u03bb\u03b9\u03ac"
    ],
    "name:und_x_variant":[
        "Kost\u00e1na"
    ],
    "qs_pg:aaroncc":"GR",
    "qs_pg:gn_country":"GR",
    "qs_pg:gn_fcode":"PPL",
    "qs_pg:gn_pop":95,
    "qs_pg:name":"Mil\u00e9a",
    "qs_pg:photos_9r":0,
    "qs_pg:photos_sr":0,
    "qs_pg:pop_sr":1,
    "qs_pg:qs_pg_placetype":"locality",
    "wof:name":"Mil\u00e9a",
    "wof:placetype":"locality",
    "wof:population":95
},
  "geometry": {"coordinates":[20.41917,39.72889],"type":"Point"}
}