{
  "type": "Feature",
  "properties": {
    "iso:country":"GR",
    "name:ceb_x_preferred":[
        "Tripoli Airport"
    ],
    "name:deu_x_preferred":[
        "Flugplatz Tripoli"
    ],
    "name:ell_x_preferred":[
        "\u0391\u03b5\u03c1\u03bf\u03c0\u03bf\u03c1\u03b9\u03ba\u03ae \u0392\u03ac\u03c3\u03b7 \u03a4\u03c1\u03b9\u03c0\u03cc\u03bb\u03b5\u03c9\u03c2"
    ],
    "name:ell_x_variant":[
        "\u0391\u03b5\u03c1\u03bf\u03b4\u03c1\u03cc\u03bc\u03b9\u03bf \u03a4\u03c1\u03b9\u03c0\u03cc\u03bb\u03b5\u03c9\u03c2"
    ],
    "name:eng_x_preferred":[
        "Tripoli Airport"
    ],
    "name:eng_x_variant":[
        "LGTP"
    ],
    "name:jpn_x_preferred":[
        "\u30c8\u30ea\u30dd\u30ea\u7a7a\u6e2f"
    ],
    "name:msa_x_preferred":[
        "Lapangan Terbang Tripolis AB"
    ],
    "name:ron_x_preferred":[
        "Aeroportul Tripoli"
    ],
    "name:swe_x_preferred":[
        "Tripoli Airport"
    ],
    "name:tgk_x_preferred":[
        "\u0424\u0443\u0440\u0443\u0434\u0433\u043e\u04b3\u0438 \u0442\u0440\u043e\u0431\u043b\u0441"
    ],
    "oa:elevation_ft":"2113",
    "oa:type":"small_airport",
    "wd:wordcount":55,
    "woe:hierarchy":{
        "country_id":23424833,
        "county_id":12591119,
        "localadmin_id":24543854,
        "planet_id":1,
        "state_id":12577887
    },
    "wof:name":"Tripolis Airport",
    "wof:placetype":"campus"
},
  "geometry": {"coordinates":[22.4015,37.5268],"type":"Point"}
}