{
  "type": "Feature",
  "properties": {
    "gn:population":1337,
    "iso:country":"GR",
    "name:ara_x_preferred":[
        "\u0623\u064a\u064a\u0648\u0633 \u0633\u0628\u064a\u0631\u064a\u062f\u0648\u0646\u060c \u0628\u064a\u0631\u064a\u0627"
    ],
    "name:ara_x_variant":[
        "\u0623\u064a\u064a\u0648\u0633 \u0633\u0628\u064a\u0631\u064a\u062f\u0648\u0646"
    ],
    "name:bul_x_preferred":[
        "\u0410\u0433\u0438\u043e\u0441 \u0421\u043f\u0438\u0440\u0438\u0434\u043e\u043d\u0430\u0441"
    ],
    "name:ceb_x_preferred":[
        "\u00c1gios Spyr\u00eddon"
    ],
    "name:ell_x_preferred":[
        "\u0386\u03b3\u03b9\u03bf\u03c2 \u03a3\u03c0\u03c5\u03c1\u03af\u03b4\u03c9\u03bd"
    ],
    "name:ell_x_variant":[
        "\u0386\u03b3\u03b9\u03bf\u03c2 \u03a3\u03c0\u03c5\u03c1\u03af\u03b4\u03c9\u03bd\u03b1\u03c2 \u03a0\u03b9\u03b5\u03c1\u03af\u03b1\u03c2"
    ],
    "name:eng_x_preferred":[
        "Agios Spyridonas"
    ],
    "name:mkd_x_preferred":[
        "\u041a\u043e\u043d\u0434\u0430\u0440\u0438\u043e\u0442\u0441\u043a\u0438 \u041a\u043e\u043b\u0438\u0431\u0438"
    ],
    "name:nld_x_preferred":[
        "Agios Spyridonas"
    ],
    "name:swe_x_preferred":[
        "\u00c1gios Spyr\u00eddon"
    ],
    "name:unk_x_variant":[
        "Kal\u00fdvia Kontariot\u00edssis"
    ],
    "qs:a0":"Greece",
    "qs:a1":"*\u039a\u0395\u039d\u03a4\u03a1\u0399\u039a\u0397 \u039c\u0391\u039a\u0395\u0394\u039f\u039d\u0399\u0391",
    "qs:a1_alt":"KENTRIKH MAKEDONIA",
    "qs:a1r":"0",
    "qs:a2_alt":"PIERIA",
    "qs:adm0":"Greece",
    "qs:la_lc":"*",
    "qs:level":"locality",
    "qs:loc":"\u0391\u0393\u0399\u039f\u03a3 \u03a3\u03a0\u03a5\u03a1\u0399\u0394\u03a9\u039d",
    "qs:loc_alt":"AGIOS SPYRIDVN",
    "qs:pop":0,
    "qs:type":"buffered point",
    "wof:name":"\u0391\u0393\u0399\u039f\u03a3 \u03a3\u03a0\u03a5\u03a1\u0399\u0394\u03a9\u039d",
    "wof:placetype":"locality",
    "wof:population":1337
},
  "geometry": {"coordinates":[22.444803,40.207962],"type":"Point"}
}