{
  "type": "Feature",
  "properties": {
    "gn:admin1_code":"ESYE25",
    "gn:admin2_code":"36.0",
    "gn:admin3_code":"9235",
    "gn:asciiname":"Pigadhia",
    "gn:country_code":"GR",
    "gn:dem":6,
    "gn:feature_class":"P",
    "gn:feature_code":"PPL",
    "gn:name":"Pig\u00e1dhia",
    "gn:population":52,
    "gn:timezone":"Europe/Athens",
    "iso:country":"GR",
    "name:ell_x_preferred":[
        "\u03a0\u03b7\u03b3\u03ac\u03b4\u03b9\u03b1"
    ],
    "name:eng_x_preferred":[
        "Pigadia"
    ],
    "wof:name":"Pigadhia",
    "wof:placetype":"locality",
    "wof:population":52
},
  "geometry": {"coordinates":[23.37573,37.41322],"type":"Point"}
}