{
  "type": "Feature",
  "properties": {
    "gn:admin1_code":"ESYE14",
    "gn:admin2_code":"21.0",
    "gn:admin3_code":"9100",
    "gn:asciiname":"Koutsochero",
    "gn:country_code":"GR",
    "gn:dem":89,
    "gn:feature_class":"P",
    "gn:feature_code":"PPL",
    "gn:name":"Kouts\u00f3chero",
    "gn:population":327,
    "gn:timezone":"Europe/Athens",
    "iso:country":"GR",
    "name:ell_x_preferred":[
        "\u039a\u03bf\u03c5\u03c4\u03c3\u03cc\u03c7\u03b5\u03c1\u03bf"
    ],
    "name:ell_x_variant":[
        "\u039a\u03bf\u03c5\u03c4\u03c3\u03cc\u03c7\u03b5\u03c1\u03bf\u03bd"
    ],
    "name:eng_x_preferred":[
        "Koutsochero"
    ],
    "name:und_x_variant":[
        "Kouts\u00f3chero",
        "Kouts\u00f3kheron",
        "Kouts\u00f3cheron"
    ],
    "wof:name":"Koutsochero",
    "wof:placetype":"locality",
    "wof:population":327
},
  "geometry": {"coordinates":[22.23333,39.60833],"type":"Point"}
}