{
  "type": "Feature",
  "properties": {
    "gn:country":"GR",
    "gn:fcode":"PPL",
    "gn:population":333,
    "iso:country":"GR",
    "name:ell_x_preferred":[
        "\u0392\u03bb\u03b1\u03c7\u03ac\u03b2\u03b1"
    ],
    "name:und_x_variant":[
        "Vlakh\u00e1va"
    ],
    "qs_pg:aaroncc":"GR",
    "qs_pg:gn_country":"GR",
    "qs_pg:gn_fcode":"PPL",
    "qs_pg:gn_pop":333,
    "qs_pg:name":"Vlach\u00e1va",
    "qs_pg:photos_9r":0,
    "qs_pg:photos_sr":0,
    "qs_pg:pop_sr":2,
    "qs_pg:qs_pg_placetype":"locality",
    "wof:name":"Vlach\u00e1va",
    "wof:placetype":"locality",
    "wof:population":333
},
  "geometry": {"coordinates":[21.65111,39.7725],"type":"Point"}
}