{
  "type": "Feature",
  "properties": {
    "gn:admin1_code":"ESYE14",
    "gn:admin2_code":"22.0",
    "gn:admin3_code":"9115",
    "gn:asciiname":"Diaselo",
    "gn:country_code":"GR",
    "gn:dem":501,
    "gn:feature_class":"P",
    "gn:feature_code":"PPL",
    "gn:name":"Di\u00e1selo",
    "gn:population":0,
    "gn:timezone":"Europe/Athens",
    "iso:country":"GR",
    "name:ell_x_preferred":[
        "Di\u00e1selo"
    ],
    "name:ell_x_variant":[
        "\u0394\u03b9\u03ac\u03c3\u03b5\u03bb\u03bf",
        "Di\u00e1selon",
        "\u0394\u03b9\u03ac\u03c3\u03b5\u03bb\u03bf\u03bd"
    ],
    "name:und_x_variant":[
        "P\u00e1nitsa",
        "Dhi\u00e1selon",
        "Dhi\u00e1sellon"
    ],
    "wof:name":"Diaselo",
    "wof:placetype":"locality"
},
  "geometry": {"coordinates":[22.01656,39.70242],"type":"Point"}
}