{
  "type": "Feature",
  "properties": {
    "gn:population":1447,
    "iso:country":"GR",
    "name:ara_x_preferred":[
        "\u0644\u0627\u0641\u0627\u0631\u0627"
    ],
    "name:bul_x_preferred":[
        "\u0421\u0430\u043b\u0442\u0438\u043a\u043e\u0432\u043e"
    ],
    "name:ell_x_preferred":[
        "\u039b\u03ac\u03b2\u03b1\u03c1\u03b1 \u0388\u03b2\u03c1\u03bf\u03c5"
    ],
    "name:ell_x_variant":[
        "\u039b\u03ac\u03b2\u03b1\u03c1\u03b1"
    ],
    "name:eng_x_preferred":[
        "Lavara"
    ],
    "name:jpn_x_preferred":[
        "\u30e9\u30f4\u30a1\u30e9"
    ],
    "name:nld_x_preferred":[
        "Lavara"
    ],
    "name:nno_x_preferred":[
        "L\u00e1vara"
    ],
    "name:ron_x_preferred":[
        "Lavara"
    ],
    "name:swe_x_preferred":[
        "L\u00e1vara"
    ],
    "name:unk_x_variant":[
        "L\u00e1vara"
    ],
    "qs:a0":"Greece",
    "qs:a1":"*\u0391\u039d\u0391\u03a4\u039f\u039b\u0399\u039a\u0397 \u039c\u0391\u039a\u0395\u0394\u039f\u039d\u0399\u0391 \u039a\u0391\u0399 \u0398\u03a1\u0391\u039a\u0397",
    "qs:a1_alt":"ANATOLIKH MAKEDONIA KAI URAKH",
    "qs:a1r":"0",
    "qs:a2_alt":"EBROS",
    "qs:adm0":"Greece",
    "qs:la_lc":"*",
    "qs:level":"locality",
    "qs:loc":"\u039b\u0391\u0392\u0391\u03a1\u0391",
    "qs:loc_alt":"LABARA",
    "qs:pop":0,
    "qs:type":"buffered point",
    "wd:wordcount":75,
    "wof:name":"\u039b\u0391\u0392\u0391\u03a1\u0391",
    "wof:placetype":"locality",
    "wof:population":1447
},
  "geometry": {"coordinates":[26.385092,41.270275],"type":"Point"}
}