{
  "type": "Feature",
  "properties": {
    "gn:admin1_code":"ESYE31",
    "gn:admin2_code":"406101.0",
    "gn:admin3_code":"9209",
    "gn:asciiname":"Araioi",
    "gn:country_code":"GR",
    "gn:dem":358,
    "gn:feature_class":"P",
    "gn:feature_code":"PPL",
    "gn:name":"Ara\u00edoi",
    "gn:population":15,
    "gn:timezone":"Europe/Athens",
    "iso:country":"GR",
    "name:ell_x_preferred":[
        "\u0391\u03c1\u03b1\u03b9\u03bf\u03af"
    ],
    "name:eng_x_preferred":[
        "Araioi"
    ],
    "name:und_x_variant":[
        "Ar\u00e9oi",
        "Ar\u00e9on",
        "Ara\u00edoi"
    ],
    "wof:name":"Araioi",
    "wof:placetype":"locality",
    "wof:population":15
},
  "geometry": {"coordinates":[22.95696,36.24566],"type":"Point"}
}