{
  "type": "Feature",
  "properties": {
    "gn:admin1_code":"ESYE22",
    "gn:admin2_code":"27.0",
    "gn:admin3_code":"9120",
    "gn:asciiname":"Dichalia",
    "gn:country_code":"GR",
    "gn:dem":86,
    "gn:feature_class":"P",
    "gn:feature_code":"PPL",
    "gn:name":"Dich\u00e1lia",
    "gn:population":0,
    "gn:timezone":"Europe/Athens",
    "iso:country":"GR",
    "name:ell_x_preferred":[
        "Dich\u00e1lia"
    ],
    "name:ell_x_variant":[
        "\u0394\u03b9\u03c7\u03ac\u03bb\u03b9\u03b1"
    ],
    "name:und_x_variant":[
        "Dhikh\u00e1lia"
    ],
    "wof:name":"Dichalia",
    "wof:placetype":"locality"
},
  "geometry": {"coordinates":[20.6675,38.27369],"type":"Point"}
}