{
  "type": "Feature",
  "properties": {
    "gn:admin1_code":"ESYE25",
    "gn:asciiname":"Markopoulon",
    "gn:country_code":"GR",
    "gn:dem":43,
    "gn:feature_class":"P",
    "gn:feature_code":"PPL",
    "gn:name":"Mark\u00f3poulon",
    "gn:population":0,
    "gn:timezone":"Europe/Athens",
    "iso:country":"GR",
    "wof:name":"Markopoulon",
    "wof:placetype":"locality"
},
  "geometry": {"coordinates":[21.32652,37.89639],"type":"Point"}
}