{
  "type": "Feature",
  "properties": {
    "gn:gn_country":"GR",
    "gn:gn_fcode":"PPL",
    "gn:gn_pop":0,
    "iso:country":"GR",
    "name:ara_x_preferred":[
        "\u0628\u0627\u0633\u062a\u064a\u062f\u0627\u060c \u062f\u0648\u062f\u064a\u0643\u0627\u0646\u064a\u0633\u0648\u0633"
    ],
    "name:ara_x_variant":[
        "\u0628\u0627\u0633\u062a\u064a\u062f\u0627"
    ],
    "name:deu_x_preferred":[
        "Pastida"
    ],
    "name:ell_x_preferred":[
        "\u03a0\u03b1\u03c3\u03c4\u03af\u03b4\u03b1 \u03a1\u03cc\u03b4\u03bf\u03c5"
    ],
    "name:eng_x_preferred":[
        "Pastida"
    ],
    "name:fin_x_preferred":[
        "Past\u00edda"
    ],
    "name:nld_x_preferred":[
        "Pastida"
    ],
    "name:nno_x_preferred":[
        "Past\u00edda"
    ],
    "qs_pg:aaroncc":"GR",
    "qs_pg:gn_country":"GR",
    "qs_pg:gn_fcode":"PPL",
    "qs_pg:gn_pop":0,
    "qs_pg:name":"Pastida",
    "qs_pg:name_adm0":"\u0395\u03bb\u03bb\u03ac\u03b4\u03b1",
    "qs_pg:name_adm1":"Aegean",
    "qs_pg:photos":255,
    "qs_pg:photos_1k":52,
    "qs_pg:photos_9k":1,
    "qs_pg:photos_9r":4,
    "qs_pg:photos_all":255,
    "qs_pg:photos_sr":5,
    "qs_pg:pop_sr":0,
    "qs_pg:qs_pg_placetype":"locality",
    "qs_pg:qs_pg_placetype_gp":"Town",
    "qs_pg:woe_adm0":23424833,
    "woe:adm0_id":23424833,
    "woe:name_adm0":"\u0395\u03bb\u03bb\u03ac\u03b4\u03b1",
    "woe:name_adm1":"Aegean",
    "woe:placetype":"Town",
    "wof:name":"Pastida",
    "wof:placetype":"locality"
},
  "geometry": {"coordinates":[28.13702,36.38685],"type":"Point"}
}