{
  "type": "Feature",
  "properties": {
    "gn:admin1_code":"ESYE25",
    "gn:admin2_code":"40.0",
    "gn:admin3_code":"9254",
    "gn:asciiname":"Aithaia",
    "gn:country_code":"GR",
    "gn:dem":35,
    "gn:feature_class":"P",
    "gn:feature_code":"PPL",
    "gn:name":"A\u00edthaia",
    "gn:population":0,
    "gn:timezone":"Europe/Athens",
    "iso:country":"GR",
    "name:ell_x_preferred":[
        "A\u00edthaia"
    ],
    "name:ell_x_variant":[
        "\u0391\u03af\u03b8\u03b1\u03b9\u03b1"
    ],
    "wof:name":"Aithaia",
    "wof:placetype":"locality"
},
  "geometry": {"coordinates":[22.04529,37.09449],"type":"Point"}
}