{
  "type": "Feature",
  "properties": {
    "gn:admin1_code":"ESYE23",
    "gn:admin2_code":"31.0",
    "gn:admin3_code":"9126",
    "gn:asciiname":"Myrtia",
    "gn:country_code":"GR",
    "gn:dem":193,
    "gn:feature_class":"P",
    "gn:feature_code":"PPL",
    "gn:name":"Myrti\u00e1",
    "gn:population":0,
    "gn:timezone":"Europe/Athens",
    "iso:country":"GR",
    "name:ell_x_preferred":[
        "Myrti\u00e1"
    ],
    "name:ell_x_variant":[
        "\u039c\u03c5\u03c1\u03c4\u03b9\u03ac"
    ],
    "name:und_x_variant":[
        "Gour\u00edtsa",
        "Mirti\u00e1",
        "\u00c1no Mirti\u00e1",
        "Mirt\u00e9a"
    ],
    "wof:name":"Myrtia",
    "wof:placetype":"locality"
},
  "geometry": {"coordinates":[21.61742000000001,38.58789],"type":"Point"}
}