{
  "type": "Feature",
  "properties": {
    "gn:admin1_code":"ESYE25",
    "gn:admin2_code":"42.0",
    "gn:admin3_code":"9252",
    "gn:asciiname":"Tseramion",
    "gn:cc2":"GR",
    "gn:country_code":"GR",
    "gn:dem":216,
    "gn:feature_class":"P",
    "gn:feature_code":"PPL",
    "gn:name":"Tseram\u00edon",
    "gn:population":0,
    "gn:timezone":"Europe/Athens",
    "iso:country":"GR",
    "name:ell_x_preferred":[
        "\u03a4\u03c3\u03b5\u03c1\u03b1\u03bc\u03b9\u03cc"
    ],
    "name:ell_x_variant":[
        "\u03a4\u03c3\u03b5\u03c1\u03b1\u03bc\u03b9\u03cc\u03bd"
    ],
    "name:und_x_variant":[
        "Tserasm\u00f3",
        "Tseram\u00edon"
    ],
    "wof:name":"Tseramion",
    "wof:placetype":"locality"
},
  "geometry": {"coordinates":[22.41189,37.04531],"type":"Point"}
}