{
  "type": "Feature",
  "properties": {
    "gn:admin1_code":"ESYE22",
    "gn:admin2_code":"27.0",
    "gn:admin3_code":"9120",
    "gn:asciiname":"Markantonata",
    "gn:country_code":"GR",
    "gn:dem":146,
    "gn:feature_class":"P",
    "gn:feature_code":"PPL",
    "gn:name":"Markanton\u00e1ta",
    "gn:population":0,
    "gn:timezone":"Europe/Athens",
    "iso:country":"GR",
    "name:ell_x_preferred":[
        "Markanton\u00e1ta"
    ],
    "name:ell_x_variant":[
        "\u039c\u03b1\u03c1\u03ba\u03b1\u03bd\u03c4\u03c9\u03bd\u03ac\u03c4\u03b1"
    ],
    "name:und_x_variant":[
        "Markandon\u00e1ta"
    ],
    "wof:name":"Markantonata",
    "wof:placetype":"locality"
},
  "geometry": {"coordinates":[20.55181,38.45992],"type":"Point"}
}