{
  "type": "Feature",
  "properties": {
    "gn:admin1_code":"ESYE12",
    "gn:admin2_code":"6.0",
    "gn:admin3_code":"9040",
    "gn:asciiname":"Synoikismos Pikrolimnis",
    "gn:country_code":"GR",
    "gn:dem":100,
    "gn:feature_class":"P",
    "gn:feature_code":"PPL",
    "gn:name":"Synoikism\u00f3s Pikrol\u00edmnis",
    "gn:population":0,
    "gn:timezone":"Europe/Athens",
    "iso:country":"GR",
    "name:ell_x_preferred":[
        "Synoikism\u00f3s Pikrol\u00edmnis"
    ],
    "name:ell_x_variant":[
        "\u03a3\u03c5\u03bd\u03bf\u03b9\u03ba\u03b9\u03c3\u03bc\u03cc\u03c2 \u03a0\u03b9\u03ba\u03c1\u03bf\u03bb\u03af\u03bc\u03bd\u03b7\u03c2"
    ],
    "wof:name":"Synoikismos Pikrolimnis",
    "wof:placetype":"locality"
},
  "geometry": {"coordinates":[22.81395,40.86771],"type":"Point"}
}