{
  "type": "Feature",
  "properties": {
    "gn:admin1_code":"ESYE42",
    "gn:admin2_code":"49.0",
    "gn:admin3_code":"9301",
    "gn:asciiname":"Myrsini",
    "gn:country_code":"GR",
    "gn:dem":371,
    "gn:feature_class":"P",
    "gn:feature_code":"PPL",
    "gn:name":"Myrs\u00edni",
    "gn:population":0,
    "gn:timezone":"Europe/Athens",
    "iso:country":"GR",
    "name:und_x_variant":[
        "Mousoulo\u00fa",
        "Myrs\u00edni",
        "\u039c\u03c5\u03c1\u03c3\u03af\u03bd\u03b7"
    ],
    "wof:name":"Myrsini",
    "wof:placetype":"locality"
},
  "geometry": {"coordinates":[25.20186,37.583],"type":"Point"}
}