{
  "type": "Feature",
  "properties": {
    "gn:admin1_code":"ESYE42",
    "gn:admin2_code":"49.0",
    "gn:admin3_code":"9291",
    "gn:asciiname":"Aegiali",
    "gn:country_code":"GR",
    "gn:dem":418,
    "gn:feature_class":"P",
    "gn:feature_code":"PPL",
    "gn:name":"Aegiali",
    "gn:population":261,
    "gn:timezone":"Europe/Athens",
    "iso:country":"GR",
    "name:ell_x_preferred":[
        "\u0391\u03b9\u03b3\u03b9\u03ac\u03bb\u03b7"
    ],
    "name:eng_x_preferred":[
        "Aigiali"
    ],
    "wof:name":"Aegiali",
    "wof:placetype":"locality",
    "wof:population":261
},
  "geometry": {"coordinates":[25.99809,36.90642],"type":"Point"}
}