{
  "type": "Feature",
  "properties": {
    "gn:admin1_code":"ESYE25",
    "gn:admin2_code":"41.0",
    "gn:admin3_code":"9241",
    "gn:asciiname":"Mavriki",
    "gn:country_code":"GR",
    "gn:dem":903,
    "gn:feature_class":"P",
    "gn:feature_code":"PPL",
    "gn:name":"Mavr\u00edki",
    "gn:population":0,
    "gn:timezone":"Europe/Athens",
    "iso:country":"GR",
    "name:ell_x_preferred":[
        "\u039c\u03b1\u03c5\u03c1\u03af\u03ba\u03b9"
    ],
    "name:ell_x_variant":[
        "\u039c\u03b1\u03c5\u03c1\u03af\u03ba\u03b9\u03bf\u03bd"
    ],
    "name:ron_x_preferred":[
        "Mavriki"
    ],
    "name:und_x_variant":[
        "Mavr\u00edki",
        "Mavr\u00edkion"
    ],
    "wof:name":"Mavriki",
    "wof:placetype":"locality"
},
  "geometry": {"coordinates":[22.45117,37.39],"type":"Point"}
}