{
  "type": "Feature",
  "properties": {
    "gn:gn_country":"GR",
    "gn:gn_fcode":"PPL",
    "gn:gn_pop":0,
    "gn:population":541,
    "iso:country":"GR",
    "name:bul_x_preferred":[
        "\u041f\u0430\u0442\u043c\u043e\u0441"
    ],
    "name:cze_x_preferred":[
        "Patmos"
    ],
    "name:dut_x_preferred":[
        "Chor\u00e1"
    ],
    "name:ell_x_preferred":[
        "\u03a0\u03ac\u03c4\u03bc\u03bf\u03c2"
    ],
    "name:ell_x_variant":[
        "\u03a7\u03ce\u03c1\u03b1"
    ],
    "name:eng_x_preferred":[
        "Patmos"
    ],
    "name:fin_x_preferred":[
        "Ch\u00f3ra"
    ],
    "name:fra_x_preferred":[
        "Patmos"
    ],
    "name:gre_x_preferred":[
        "\u03a0\u03ac\u03c4\u03bc\u03bf\u03c2"
    ],
    "name:rus_x_preferred":[
        "\u041f\u0430\u0442\u043c\u043e\u0441"
    ],
    "name:unk_x_variant":[
        "Kh\u00f3ra"
    ],
    "qs_pg:aaroncc":"GR",
    "qs_pg:gn_country":"GR",
    "qs_pg:gn_fcode":"PPL",
    "qs_pg:gn_pop":0,
    "qs_pg:name":"Patmos",
    "qs_pg:name_adm0":"\u0395\u03bb\u03bb\u03ac\u03b4\u03b1",
    "qs_pg:name_adm1":"Aegean",
    "qs_pg:photos":813,
    "qs_pg:photos_1k":165,
    "qs_pg:photos_9k":4,
    "qs_pg:photos_9r":6,
    "qs_pg:photos_all":813,
    "qs_pg:photos_sr":9,
    "qs_pg:pop_sr":0,
    "qs_pg:qs_pg_placetype":"locality",
    "qs_pg:qs_pg_placetype_gp":"Town",
    "qs_pg:woe_adm0":23424833,
    "woe:adm0_id":23424833,
    "woe:name_adm0":"\u0395\u03bb\u03bb\u03ac\u03b4\u03b1",
    "woe:name_adm1":"Aegean",
    "woe:placetype":"Town",
    "wof:name":"Patmos",
    "wof:placetype":"locality",
    "wof:population":541
},
  "geometry": {"coordinates":[26.54406,37.32355],"type":"Point"}
}