{
  "type": "Feature",
  "properties": {
    "gn:country":"GR",
    "gn:fcode":"PPL",
    "gn:population":0,
    "iso:country":"GR",
    "name:ell_x_preferred":[
        "Kon\u00edstres"
    ],
    "name:ell_x_variant":[
        "\u039a\u03bf\u03bd\u03af\u03c3\u03c4\u03c1\u03b5\u03c2",
        "\u0394\u03ae\u03bc\u03bf\u03c2 \u039a\u03bf\u03bd\u03b9\u03c3\u03c4\u03c1\u03ce\u03bd"
    ],
    "name:eng_x_preferred":[
        "Konistres"
    ],
    "name:fin_x_preferred":[
        "Kon\u00edstres"
    ],
    "name:fra_x_preferred":[
        "Konistres"
    ],
    "name:ita_x_preferred":[
        "Konistres"
    ],
    "name:jpn_x_preferred":[
        "\u30b3\u30cb\u30b9\u30c8\u30ec\u30b9"
    ],
    "name:lat_x_preferred":[
        "Conistrae"
    ],
    "name:nld_x_preferred":[
        "Konistres"
    ],
    "name:nno_x_preferred":[
        "Kon\u00edstres"
    ],
    "name:und_x_variant":[
        "Konistracs"
    ],
    "qs_pg:aaroncc":"GR",
    "qs_pg:gn_country":"GR",
    "qs_pg:gn_fcode":"PPL",
    "qs_pg:gn_pop":0,
    "qs_pg:name":"Konistres",
    "qs_pg:name_adm0":"\u0395\u03bb\u03bb\u03ac\u03b4\u03b1",
    "qs_pg:name_adm1":"Thessaly and Continental Greece",
    "qs_pg:photos_9k":1,
    "qs_pg:photos_9r":1,
    "qs_pg:photos_all":2,
    "qs_pg:photos_sr":0,
    "qs_pg:pop_sr":0,
    "qs_pg:qs_pg_placetype":"locality",
    "qs_pg:qs_pg_placetype_gp":"Town",
    "qs_pg:woe_adm0":23424833,
    "woe:adm0_id":23424833,
    "woe:name_adm0":"\u0395\u03bb\u03bb\u03ac\u03b4\u03b1",
    "woe:name_adm1":"Thessaly and Continental Greece",
    "woe:placetype":"Town",
    "wof:name":"Konistres",
    "wof:placetype":"locality"
},
  "geometry": {"coordinates":[24.06667,38.56667],"type":"Point"}
}