{
  "type": "Feature",
  "properties": {
    "gn:admin1_code":"ESYE13",
    "gn:admin2_code":"11.0",
    "gn:admin3_code":"9068",
    "gn:asciiname":"Sideras",
    "gn:country_code":"GR",
    "gn:dem":917,
    "gn:feature_class":"P",
    "gn:feature_code":"PPL",
    "gn:name":"Sider\u00e1s",
    "gn:population":0,
    "gn:timezone":"Europe/Athens",
    "iso:country":"GR",
    "name:bul_x_preferred":[
        "\u0421\u0438\u0434\u0435\u0440\u0430\u0441"
    ],
    "name:ell_x_preferred":[
        "Sider\u00e1s"
    ],
    "name:ell_x_variant":[
        "\u03a3\u03b9\u03b4\u03b5\u03c1\u03ac\u03c2",
        "\u03a3\u03b9\u03b4\u03b5\u03c1\u03ac\u03c2 \u039a\u03bf\u03b6\u03ac\u03bd\u03b7\u03c2"
    ],
    "name:mkd_x_preferred":[
        "\u0414\u0438\u043c\u0438\u0440\u045f\u0438\u043b\u0435\u0440"
    ],
    "name:srp_x_preferred":[
        "\u0421\u0438\u0434\u0435\u0440\u0430\u0441"
    ],
    "name:und_x_variant":[
        "Demirjil\u00e1r",
        "Sidher\u00e1s"
    ],
    "wof:name":"Sideras",
    "wof:placetype":"locality"
},
  "geometry": {"coordinates":[21.69454,40.3845],"type":"Point"}
}