{
  "type": "Feature",
  "properties": {
    "gn:admin1_code":"ESYE13",
    "gn:admin2_code":"11.0",
    "gn:admin3_code":"9068",
    "gn:asciiname":"Sideras",
    "gn:country_code":"GR",
    "gn:dem":917,
    "gn:feature_class":"P",
    "gn:feature_code":"PPL",
    "gn:name":"Sider\u00e1s",
    "gn:population":0,
    "gn:timezone":"Europe/Athens",
    "iso:country":"GR",
    "name:ell_x_preferred":[
        "Sider\u00e1s"
    ],
    "name:ell_x_variant":[
        "\u03a3\u03b9\u03b4\u03b5\u03c1\u03ac\u03c2"
    ],
    "name:und_x_variant":[
        "Demirjil\u00e1r",
        "Sidher\u00e1s"
    ],
    "wof:name":"Sideras",
    "wof:placetype":"locality"
},
  "geometry": {"coordinates":[21.69454,40.3845],"type":"Point"}
}