{
  "type": "Feature",
  "properties": {
    "gn:admin1_code":"ESYE23",
    "gn:admin2_code":"31.0",
    "gn:admin3_code":"9128",
    "gn:asciiname":"Perdikovrysi",
    "gn:country_code":"GR",
    "gn:dem":674,
    "gn:feature_class":"P",
    "gn:feature_code":"PPL",
    "gn:name":"Perdik\u00f3vrysi",
    "gn:population":0,
    "gn:timezone":"Europe/Athens",
    "iso:country":"GR",
    "name:ell_x_preferred":[
        "Perdik\u00f3vrysi"
    ],
    "name:ell_x_variant":[
        "\u03a0\u03b5\u03c1\u03b4\u03b9\u03ba\u03cc\u03b2\u03c1\u03c5\u03c3\u03b7"
    ],
    "name:und_x_variant":[
        "Sin\u00edsta",
        "Perdhik\u00f3vrisi"
    ],
    "wof:name":"Perdikovrysi",
    "wof:placetype":"locality"
},
  "geometry": {"coordinates":[21.90125,38.66017],"type":"Point"}
}