{
  "type": "Feature",
  "properties": {
    "gn:admin1_code":"ESYE31",
    "gn:admin2_code":"445406.0",
    "gn:admin3_code":"9227.0",
    "gn:asciiname":"Oikismos Lachnon",
    "gn:country_code":"GR",
    "gn:dem":111,
    "gn:feature_class":"P",
    "gn:feature_code":"PPL",
    "gn:name":"Oikism\u00f3s Lachn\u00f3n",
    "gn:population":0,
    "gn:timezone":"Europe/Athens",
    "iso:country":"GR",
    "name:ell_x_preferred":[
        "Oikism\u00f3s Lachn\u00f3n"
    ],
    "name:ell_x_variant":[
        "\u039f\u03b9\u03ba\u03b9\u03c3\u03bc\u03cc\u03c2 \u039b\u03b1\u03c7\u03bd\u03ce\u03bd"
    ],
    "wof:name":"Oikismos Lachnon",
    "wof:placetype":"locality"
},
  "geometry": {"coordinates":[23.81467,38.3014],"type":"Point"}
}