{
  "type": "Feature",
  "properties": {
    "gn:admin1_code":"ESYE43",
    "gn:admin2_code":"46.0",
    "gn:admin3_code":"9313",
    "gn:asciiname":"Kellaria",
    "gn:cc2":"GR",
    "gn:country_code":"GR",
    "gn:dem":263,
    "gn:feature_class":"P",
    "gn:feature_code":"PPL",
    "gn:name":"Kell\u00e1ria",
    "gn:population":0,
    "gn:timezone":"Europe/Athens",
    "iso:country":"GR",
    "name:und_x_variant":[
        "Kel\u00e1ria",
        "Kell\u00e1ria"
    ],
    "wof:name":"Kellaria",
    "wof:placetype":"locality"
},
  "geometry": {"coordinates":[26.22454,35.13942],"type":"Point"}
}