{
  "type": "Feature",
  "properties": {
    "gn:admin1_code":"ESYE43",
    "gn:admin2_code":"45.0",
    "gn:admin3_code":"9303",
    "gn:asciiname":"Sarakinos",
    "gn:country_code":"GR",
    "gn:dem":86,
    "gn:feature_class":"P",
    "gn:feature_code":"PPL",
    "gn:name":"Sarakin\u00f3s",
    "gn:population":0,
    "gn:timezone":"Europe/Athens",
    "iso:country":"GR",
    "name:ell_x_preferred":[
        "Sarakin\u00f3s"
    ],
    "name:ell_x_variant":[
        "\u03a3\u03b1\u03c1\u03b1\u03ba\u03b7\u03bd\u03cc\u03c2"
    ],
    "wof:name":"Sarakinos",
    "wof:placetype":"locality"
},
  "geometry": {"coordinates":[25.31016,34.98808],"type":"Point"}
}