{
  "type": "Feature",
  "properties": {
    "gn:gn_country":"GR",
    "gn:gn_fcode":"PPL",
    "gn:gn_pop":293,
    "gn:population":211,
    "iso:country":"GR",
    "name:ell_x_preferred":[
        "\u0393\u03c1\u03af\u03bc\u03c0\u03bf\u03b2\u03bf"
    ],
    "name:ell_x_variant":[
        "\u0393\u03c1\u03af\u03bc\u03c0\u03bf\u03b2\u03bf\u03bd"
    ],
    "name:eng_x_preferred":[
        "Grimpovo"
    ],
    "name:unk_x_variant":[
        "Gr\u00edmpovo"
    ],
    "qs_pg:aaroncc":"GR",
    "qs_pg:gn_country":"GR",
    "qs_pg:gn_fcode":"PPL",
    "qs_pg:gn_pop":293,
    "qs_pg:name":"Gr\u00edmpovon",
    "qs_pg:photos_9r":0,
    "qs_pg:photos_sr":0,
    "qs_pg:pop_sr":2,
    "qs_pg:qs_pg_placetype":"locality",
    "wof:name":"Gr\u00edmpovon",
    "wof:placetype":"locality",
    "wof:population":211
},
  "geometry": {"coordinates":[20.95639,39.21167],"type":"Point"}
}