{
  "type": "Feature",
  "properties": {
    "gn:gn_country":"GR",
    "gn:gn_fcode":"PPL",
    "gn:gn_pop":668,
    "gn:population":668,
    "iso:country":"GR",
    "name:ell_x_preferred":[
        "Episkop\u00ed"
    ],
    "name:ell_x_variant":[
        "\u0395\u03c0\u03b9\u03c3\u03ba\u03bf\u03c0\u03ae"
    ],
    "qs_pg:aaroncc":"GR",
    "qs_pg:gn_country":"GR",
    "qs_pg:gn_fcode":"PPL",
    "qs_pg:gn_pop":668,
    "qs_pg:name":"Episkopi",
    "qs_pg:name_adm0":"\u0395\u03bb\u03bb\u03ac\u03b4\u03b1",
    "qs_pg:name_adm1":"Macedonia and Thrace",
    "qs_pg:photos_9r":0,
    "qs_pg:photos_sr":0,
    "qs_pg:pop_sr":2,
    "qs_pg:qs_pg_placetype":"locality",
    "qs_pg:qs_pg_placetype_gp":"Town",
    "qs_pg:woe_adm0":23424833,
    "woe:adm0_id":23424833,
    "woe:name_adm0":"\u0395\u03bb\u03bb\u03ac\u03b4\u03b1",
    "woe:name_adm1":"Macedonia and Thrace",
    "woe:placetype":"Town",
    "wof:name":"Episkopi",
    "wof:placetype":"locality",
    "wof:population":668
},
  "geometry": {"coordinates":[22.36389,40.59056],"type":"Point"}
}