{
  "type": "Feature",
  "properties": {
    "gn:admin1_code":"ESYE13",
    "gn:admin2_code":"9.0",
    "gn:admin3_code":"9063",
    "gn:asciiname":"Chalara",
    "gn:country_code":"GR",
    "gn:dem":870,
    "gn:feature_class":"P",
    "gn:feature_code":"PPL",
    "gn:name":"Ch\u00e1lara",
    "gn:population":13,
    "gn:timezone":"Europe/Athens",
    "iso:country":"GR",
    "name:ell_x_historical":[
        "\u03a0\u03bf\u03b4\u03bf\u03b2\u03af\u03c3\u03c4\u03b1"
    ],
    "name:ell_x_preferred":[
        "\u03a7\u03ac\u03bb\u03b1\u03c1\u03b1"
    ],
    "name:ell_x_variant":[
        "\u03a0\u03bf\u03b4\u03bf\u03b2\u03af\u03c3\u03c4\u03b1"
    ],
    "name:eng_x_preferred":[
        "Chalara"
    ],
    "name:und_x_variant":[
        "Podhov\u00edtsa",
        "Kh\u00e1lara",
        "Ch\u00e1lara"
    ],
    "wof:name":"Chalara",
    "wof:placetype":"locality",
    "wof:population":13
},
  "geometry": {"coordinates":[21.23294,40.64552],"type":"Point"}
}