{
  "type": "Feature",
  "properties": {
    "gn:admin1_code":"ESYE24",
    "gn:admin2_code":"29.0",
    "gn:admin3_code":"9160",
    "gn:asciiname":"Dhivri",
    "gn:country_code":"GR",
    "gn:dem":809,
    "gn:feature_class":"P",
    "gn:feature_code":"PPL",
    "gn:name":"Dh\u00edvri",
    "gn:population":192,
    "gn:timezone":"Europe/Athens",
    "iso:country":"GR",
    "name:ell_x_preferred":[
        "\u0394\u03af\u03b2\u03c1\u03b7"
    ],
    "name:eng_x_preferred":[
        "Divri"
    ],
    "name:und_x_variant":[
        "D\u00edvri",
        "Dh\u00edvri"
    ],
    "wof:name":"Dhivri",
    "wof:placetype":"locality",
    "wof:population":192
},
  "geometry": {"coordinates":[22.45318,38.97581],"type":"Point"}
}