{
  "type": "Feature",
  "properties": {
    "gn:admin1_code":"ESYE13",
    "gn:admin2_code":"11.0",
    "gn:admin3_code":"9066",
    "gn:asciiname":"Platania",
    "gn:country_code":"GR",
    "gn:dem":675,
    "gn:feature_class":"P",
    "gn:feature_code":"PPL",
    "gn:name":"Platani\u00e1",
    "gn:population":0,
    "gn:timezone":"Europe/Athens",
    "iso:country":"GR",
    "name:ell_x_preferred":[
        "Platani\u00e1"
    ],
    "name:ell_x_variant":[
        "\u03a0\u03bb\u03b1\u03c4\u03b1\u03bd\u03b9\u03ac"
    ],
    "wof:name":"Platania",
    "wof:placetype":"locality"
},
  "geometry": {"coordinates":[21.34746,40.38352],"type":"Point"}
}