{
  "type": "Feature",
  "properties": {
    "gn:gn_country":"GR",
    "gn:gn_fcode":"PPL",
    "gn:gn_pop":96,
    "gn:population":60,
    "iso:country":"GR",
    "name:ell_x_preferred":[
        "L\u00e1ista"
    ],
    "name:ell_x_variant":[
        "\u039b\u03ac\u03b9\u03c3\u03c4\u03b1",
        "\u039b\u03b1\u0390\u03c3\u03c4\u03b1"
    ],
    "name:eng_x_preferred":[
        "Laista"
    ],
    "name:unk_x_variant":[
        "Laitsa"
    ],
    "qs_pg:aaroncc":"GR",
    "qs_pg:gn_country":"GR",
    "qs_pg:gn_fcode":"PPL",
    "qs_pg:gn_pop":96,
    "qs_pg:name":"Laista",
    "qs_pg:name_adm0":"\u0395\u03bb\u03bb\u03ac\u03b4\u03b1",
    "qs_pg:name_adm1":"Epirus and Western Macedonia",
    "qs_pg:photos_9k":1,
    "qs_pg:photos_9r":1,
    "qs_pg:photos_all":4,
    "qs_pg:photos_sr":0,
    "qs_pg:pop_sr":1,
    "qs_pg:qs_pg_placetype":"locality",
    "qs_pg:qs_pg_placetype_gp":"Town",
    "qs_pg:woe_adm0":23424833,
    "woe:adm0_id":23424833,
    "woe:name_adm0":"\u0395\u03bb\u03bb\u03ac\u03b4\u03b1",
    "woe:name_adm1":"Epirus and Western Macedonia",
    "woe:placetype":"Town",
    "wof:name":"Laista",
    "wof:placetype":"locality",
    "wof:population":60
},
  "geometry": {"coordinates":[20.95278,39.97333],"type":"Point"}
}