{
  "type": "Feature",
  "properties": {
    "gn:admin1_code":"ESYE43",
    "gn:admin2_code":"43.0",
    "gn:admin3_code":"9322.0",
    "gn:asciiname":"Agios Antonios Kallergianon",
    "gn:country_code":"GR",
    "gn:dem":26,
    "gn:feature_class":"P",
    "gn:feature_code":"PPL",
    "gn:name":"\u00c1gios Ant\u00f3nios Kallergian\u00f3n",
    "gn:population":284,
    "gn:timezone":"Europe/Athens",
    "iso:country":"GR",
    "name:ell_x_preferred":[
        "\u0386\u03b3\u03b9\u03bf\u03c2 \u0391\u03bd\u03c4\u03ce\u03bd\u03b9\u03bf\u03c2 \u039a\u03b1\u03bb\u03bb\u03b5\u03c1\u03b3\u03b9\u03b1\u03bd\u03ce\u03bd"
    ],
    "name:eng_x_preferred":[
        "Agios Antonios Kallergianon"
    ],
    "wof:name":"Agios Antonios Kallergianon",
    "wof:placetype":"locality",
    "wof:population":284
},
  "geometry": {"coordinates":[23.6667,35.49092],"type":"Point"}
}