{
  "type": "Feature",
  "properties": {
    "gn:gn_country":"GR",
    "gn:gn_fcode":"PPL",
    "gn:gn_pop":518,
    "gn:population":458,
    "iso:country":"GR",
    "name:ell_x_preferred":[
        "\u0391\u03b3\u03ba\u03b5\u03bb\u03ce\u03bd\u03b1"
    ],
    "name:ell_x_variant":[
        "Angil\u00f3na",
        "\u0391\u03b3\u03b3\u03b5\u03bb\u03ce\u03bd\u03b1",
        "Angel\u00f3na",
        "Agkel\u00f3na"
    ],
    "name:eng_x_preferred":[
        "Angelona"
    ],
    "name:unk_x_variant":[
        "Angel\u00f3na"
    ],
    "qs_pg:aaroncc":"GR",
    "qs_pg:gn_country":"GR",
    "qs_pg:gn_fcode":"PPL",
    "qs_pg:gn_pop":518,
    "qs_pg:name":"Agkel\u00f3na",
    "qs_pg:photos_9r":0,
    "qs_pg:photos_sr":0,
    "qs_pg:pop_sr":2,
    "qs_pg:qs_pg_placetype":"locality",
    "wof:name":"Agkel\u00f3na",
    "wof:placetype":"locality",
    "wof:population":458
},
  "geometry": {"coordinates":[22.96857,36.75198],"type":"Point"}
}