{
  "type": "Feature",
  "properties": {
    "gn:admin1_code":"ESYE11",
    "gn:admin2_code":"1.0",
    "gn:admin3_code":"9007",
    "gn:asciiname":"Neon Lilion",
    "gn:cc2":"GR",
    "gn:country_code":"GR",
    "gn:dem":38,
    "gn:feature_class":"P",
    "gn:feature_code":"PPL",
    "gn:name":"N\u00e9on Lil\u00edon",
    "gn:population":0,
    "gn:timezone":"Europe/Athens",
    "iso:country":"GR",
    "name:und_x_variant":[
        "N\u00e9on Lil\u00ed",
        "N\u00e9on Lil\u00edon"
    ],
    "wof:name":"Neon Lilion",
    "wof:placetype":"locality"
},
  "geometry": {"coordinates":[26.56667,41.41667],"type":"Point"}
}