{
  "type": "Feature",
  "properties": {
    "gn:admin1_code":"ESYE21",
    "gn:admin2_code":"19.0",
    "gn:admin3_code":"9090",
    "gn:asciiname":"Neochori",
    "gn:country_code":"GR",
    "gn:dem":34,
    "gn:feature_class":"P",
    "gn:feature_code":"PPL",
    "gn:name":"Neoch\u00f3ri",
    "gn:population":0,
    "gn:timezone":"Europe/Athens",
    "iso:country":"GR",
    "name:ell_x_preferred":[
        "Neoch\u00f3ri"
    ],
    "name:ell_x_variant":[
        "\u039d\u03b5\u03bf\u03c7\u03ce\u03c1\u03b9",
        "Neoch\u00f3rion",
        "\u039d\u03b5\u03bf\u03c7\u03ce\u03c1\u03b9\u03bf\u03bd"
    ],
    "name:und_x_variant":[
        "Neokh\u00f3rion"
    ],
    "wof:name":"Neochori",
    "wof:placetype":"locality"
},
  "geometry": {"coordinates":[20.7805,38.98411],"type":"Point"}
}