{
  "type": "Feature",
  "properties": {
    "gn:country":"GR",
    "gn:fcode":"PPL",
    "gn:population":520,
    "iso:country":"GR",
    "name:ell_x_preferred":[
        "\u039a\u03c5\u03c8\u03ad\u03bb\u03b7"
    ],
    "name:und_x_variant":[
        "Neokh\u00f3rion"
    ],
    "qs_pg:aaroncc":"GR",
    "qs_pg:gn_country":"GR",
    "qs_pg:gn_fcode":"PPL",
    "qs_pg:gn_pop":520,
    "qs_pg:name":"Kyps\u00e9li",
    "qs_pg:photos_9r":0,
    "qs_pg:photos_sr":0,
    "qs_pg:pop_sr":2,
    "qs_pg:qs_pg_placetype":"locality",
    "wof:name":"Kyps\u00e9li",
    "wof:placetype":"locality",
    "wof:population":520
},
  "geometry": {"coordinates":[22.49361,40.55611],"type":"Point"}
}