{
  "type": "Feature",
  "properties": {
    "gn:admin1_code":"ESYE25",
    "gn:admin2_code":"40.0",
    "gn:admin3_code":"9258",
    "gn:asciiname":"Kanavaiika",
    "gn:country_code":"GR",
    "gn:dem":329,
    "gn:feature_class":"P",
    "gn:feature_code":"PPL",
    "gn:name":"Kanava\u00edika",
    "gn:population":0,
    "gn:timezone":"Europe/Athens",
    "iso:country":"GR",
    "name:ell_x_preferred":[
        "Kanava\u00edika"
    ],
    "name:ell_x_variant":[
        "\u039a\u03b1\u03bd\u03b1\u03b2\u03b1\u03af\u03b9\u03ba\u03b1"
    ],
    "wof:name":"Kanavaiika",
    "wof:placetype":"locality"
},
  "geometry": {"coordinates":[21.675,37.18438],"type":"Point"}
}