{
  "type": "Feature",
  "properties": {
    "gn:admin1_code":"ESYE13",
    "gn:admin2_code":"8.0",
    "gn:admin3_code":"9072",
    "gn:asciiname":"Drosopigi",
    "gn:country_code":"GR",
    "gn:dem":935,
    "gn:feature_class":"P",
    "gn:feature_code":"PPL",
    "gn:name":"Drosopig\u00ed",
    "gn:population":239,
    "gn:timezone":"Europe/Athens",
    "iso:country":"GR",
    "name:bul_x_preferred":[
        "\u0411\u0435\u043b \u043a\u0430\u043c\u0435\u043d"
    ],
    "name:ceb_x_preferred":[
        "Drosopig\u00ed"
    ],
    "name:ell_x_historical":[
        "\u039c\u03c0\u03b5\u03bb\u03ba\u03b1\u03bc\u03ad\u03bd\u03b7",
        "\u039c\u03c0\u03b5\u03bb \u039a\u03ac\u03bc\u03b5\u03bd",
        "\u039c\u03c0\u03ad\u03bb\u03ba\u03b1\u03bc\u03b5\u03bd"
    ],
    "name:ell_x_preferred":[
        "\u0394\u03c1\u03bf\u03c3\u03bf\u03c0\u03b7\u03b3\u03ae"
    ],
    "name:ell_x_variant":[
        "\u039c\u03c0\u03b5\u03bb\u03ba\u03b1\u03bc\u03ad\u03bd\u03b7",
        "\u039c\u03c0\u03b5\u03bb \u039a\u03ac\u03bc\u03b5\u03bd",
        "\u039c\u03c0\u03ad\u03bb\u03ba\u03b1\u03bc\u03b5\u03bd",
        "\u0394\u03c1\u03bf\u03c3\u03bf\u03c0\u03b7\u03b3\u03ae \u03a6\u03bb\u03ce\u03c1\u03b9\u03bd\u03b1\u03c2"
    ],
    "name:eng_x_historical":[
        "Belkam\u00e9ni"
    ],
    "name:eng_x_preferred":[
        "Drosopigi"
    ],
    "name:eng_x_variant":[
        "Belkam\u00e9ni"
    ],
    "name:mkd_x_preferred":[
        "\u0411\u0435\u043b \u041a\u0430\u043c\u0435\u043d"
    ],
    "name:sqi_x_preferred":[
        "Bellkameni"
    ],
    "name:srp_x_preferred":[
        "\u0411\u0435\u043b \u041a\u0430\u043c\u0435\u043d"
    ],
    "name:und_x_variant":[
        "Dhrosopiy\u00ed"
    ],
    "wof:name":"Drosopigi",
    "wof:placetype":"locality",
    "wof:population":239
},
  "geometry": {"coordinates":[21.45428,40.68923],"type":"Point"}
}