{
  "type": "Feature",
  "properties": {
    "gn:admin1_code":"ESYE41",
    "gn:admin2_code":"51.0",
    "gn:admin3_code":"9261",
    "gn:asciiname":"Kournela",
    "gn:country_code":"GR",
    "gn:dem":391,
    "gn:feature_class":"P",
    "gn:feature_code":"PPL",
    "gn:name":"Kourn\u00e9la",
    "gn:population":2,
    "gn:timezone":"Europe/Athens",
    "iso:country":"GR",
    "name:ell_x_preferred":[
        "\u039a\u03bf\u03c5\u03c1\u03bd\u03ad\u03bb\u03b1"
    ],
    "wof:name":"Kournela",
    "wof:placetype":"locality",
    "wof:population":2
},
  "geometry": {"coordinates":[26.3365,38.99771],"type":"Point"}
}