{
  "type": "Feature",
  "properties": {
    "gn:country":"GR",
    "gn:fcode":"PPL",
    "gn:population":109,
    "iso:country":"GR",
    "name:ell_x_preferred":[
        "\u0392\u03b1\u03b2\u03bf\u03cd\u03c1\u03b9"
    ],
    "name:ell_x_variant":[
        "\u0392\u03b1\u03b2\u03bf\u03cd\u03c1\u03b9\u03bf\u03bd"
    ],
    "name:und_x_variant":[
        "Vavo\u00fari"
    ],
    "qs_pg:aaroncc":"GR",
    "qs_pg:gn_country":"GR",
    "qs_pg:gn_fcode":"PPL",
    "qs_pg:gn_pop":109,
    "qs_pg:name":"Vavourion",
    "qs_pg:name_adm0":"\u0395\u03bb\u03bb\u03ac\u03b4\u03b1",
    "qs_pg:name_adm1":"Epirus and Western Macedonia",
    "qs_pg:photos_9k":1,
    "qs_pg:photos_9r":1,
    "qs_pg:photos_all":1,
    "qs_pg:photos_sr":0,
    "qs_pg:pop_sr":1,
    "qs_pg:qs_pg_placetype":"locality",
    "qs_pg:qs_pg_placetype_gp":"Town",
    "qs_pg:woe_adm0":23424833,
    "woe:adm0_id":23424833,
    "woe:name_adm0":"\u0395\u03bb\u03bb\u03ac\u03b4\u03b1",
    "woe:name_adm1":"Epirus and Western Macedonia",
    "woe:placetype":"Town",
    "wof:name":"Vavourion",
    "wof:placetype":"locality",
    "wof:population":109
},
  "geometry": {"coordinates":[20.3925,39.76444],"type":"Point"}
}