{
  "type": "Feature",
  "properties": {
    "iso:country":"GR",
    "name:ara_x_preferred":[
        "\u062f\u064a\u0627\u0641\u0627\u062a\u0627"
    ],
    "name:bul_x_preferred":[
        "\u0414\u043e\u0434\u0443\u043b\u0430\u0440\u0438"
    ],
    "name:ceb_x_preferred":[
        "Diavat\u00e1"
    ],
    "name:ell_x_preferred":[
        "\u0394\u03b9\u03b1\u03b2\u03b1\u03c4\u03ac \u0398\u03b5\u03c3\u03c3\u03b1\u03bb\u03bf\u03bd\u03af\u03ba\u03b7\u03c2"
    ],
    "name:ell_x_variant":[
        "\u0394\u03b9\u03b1\u03b2\u03b1\u03c4\u03ac"
    ],
    "name:eng_x_preferred":[
        "Diavata"
    ],
    "name:fas_x_preferred":[
        "\u062f\u06cc\u0627\u0648\u0627\u062a\u0627"
    ],
    "name:mkd_x_preferred":[
        "\u0414\u043e\u0434\u0443\u043b\u0430\u0440\u0438"
    ],
    "name:nld_x_preferred":[
        "Diavata"
    ],
    "name:nno_x_preferred":[
        "Diavat\u00e1"
    ],
    "name:swe_x_preferred":[
        "Diavat\u00e1"
    ],
    "qs_pg:aaroncc":"GR",
    "qs_pg:name":"Diavata",
    "qs_pg:name_adm0":"\u0395\u03bb\u03bb\u03ac\u03b4\u03b1",
    "qs_pg:name_adm1":"Macedonia and Thrace",
    "qs_pg:photos":68,
    "qs_pg:photos_1k":14,
    "qs_pg:photos_9k":1,
    "qs_pg:photos_9r":2,
    "qs_pg:photos_all":68,
    "qs_pg:photos_sr":2,
    "qs_pg:pop_sr":0,
    "qs_pg:qs_pg_placetype":"locality",
    "qs_pg:qs_pg_placetype_gp":"Town",
    "qs_pg:woe_adm0":23424833,
    "woe:adm0_id":23424833,
    "woe:name_adm0":"\u0395\u03bb\u03bb\u03ac\u03b4\u03b1",
    "woe:name_adm1":"Macedonia and Thrace",
    "woe:placetype":"Town",
    "wof:name":"Diavata",
    "wof:placetype":"locality"
},
  "geometry": {"coordinates":[22.838054,40.698816],"type":"Point"}
}