{
  "type": "Feature",
  "properties": {
    "gn:admin1_code":"ESYE43",
    "gn:admin2_code":"43.0",
    "gn:admin3_code":"9319",
    "gn:asciiname":"Almirida",
    "gn:country_code":"GR",
    "gn:dem":1,
    "gn:feature_class":"P",
    "gn:feature_code":"PPL",
    "gn:name":"Almirida",
    "gn:population":0,
    "gn:timezone":"Europe/Athens",
    "iso:country":"GR",
    "name:ell_x_preferred":[
        "\u0391\u03bb\u03bc\u03c5\u03c1\u03af\u03b4\u03b1"
    ],
    "name:eng_x_preferred":[
        "Almyrida"
    ],
    "name:fin_x_preferred":[
        "Almyr\u00edda"
    ],
    "name:nor_x_preferred":[
        "Almyrida"
    ],
    "name:und_x_variant":[
        "Almir\u00f3s"
    ],
    "wof:name":"Almirida",
    "wof:placetype":"locality"
},
  "geometry": {"coordinates":[24.20101,35.44847],"type":"Point"}
}