{
  "type": "Feature",
  "properties": {
    "gn:admin1_code":"ESYE25",
    "gn:admin2_code":"40.0",
    "gn:admin3_code":"9255",
    "gn:asciiname":"Kefalovryso",
    "gn:country_code":"GR",
    "gn:dem":587,
    "gn:feature_class":"P",
    "gn:feature_code":"PPL",
    "gn:name":"Kefal\u00f3vryso",
    "gn:population":0,
    "gn:timezone":"Europe/Athens",
    "iso:country":"GR",
    "name:ceb_x_preferred":[
        "Kefal\u00f3vryso"
    ],
    "name:ell_x_preferred":[
        "Kefal\u00f3vryso"
    ],
    "name:ell_x_variant":[
        "\u039a\u03b5\u03c6\u03b1\u03bb\u03cc\u03b2\u03c1\u03c5\u03c3\u03bf",
        "Kefal\u00f3vryson",
        "\u039a\u03b5\u03c6\u03b1\u03bb\u03cc\u03b2\u03c1\u03c5\u03c3\u03bf\u03bd"
    ],
    "name:swe_x_preferred":[
        "Kefalovryso"
    ],
    "name:und_x_variant":[
        "Khalv\u00e1tsou",
        "Kefal\u00f3vrison"
    ],
    "wof:name":"Kefalovryso",
    "wof:placetype":"locality"
},
  "geometry": {"coordinates":[21.80118,37.14731],"type":"Point"}
}