{
  "type": "Feature",
  "properties": {
    "gn:admin1_code":"ESYE23",
    "gn:admin2_code":"31.0",
    "gn:admin3_code":"9123",
    "gn:asciiname":"Kastanoula",
    "gn:country_code":"GR",
    "gn:dem":794,
    "gn:feature_class":"P",
    "gn:feature_code":"PPL",
    "gn:name":"Kastano\u00fala",
    "gn:population":106,
    "gn:timezone":"Europe/Athens",
    "iso:country":"GR",
    "name:ell_x_preferred":[
        "\u039a\u03b1\u03c3\u03c4\u03b1\u03bd\u03bf\u03cd\u03bb\u03b1"
    ],
    "name:eng_x_preferred":[
        "Kastanoula"
    ],
    "wof:name":"Kastanoula",
    "wof:placetype":"locality",
    "wof:population":106
},
  "geometry": {"coordinates":[21.53423,38.76004],"type":"Point"}
}