{
  "type": "Feature",
  "properties": {
    "gn:admin1_code":"ESYE23",
    "gn:admin2_code":"31.0",
    "gn:admin3_code":"9123",
    "gn:asciiname":"Piryion",
    "gn:country_code":"GR",
    "gn:dem":458,
    "gn:feature_class":"P",
    "gn:feature_code":"PPL",
    "gn:name":"Piry\u00edon",
    "gn:population":53,
    "gn:timezone":"Europe/Athens",
    "iso:country":"GR",
    "name:ell_x_preferred":[
        "\u03a0\u03c5\u03c1\u03b3\u03af"
    ],
    "name:ell_x_variant":[
        "\u03a0\u03c5\u03c1\u03b3\u03af\u03bf\u03bd"
    ],
    "name:eng_x_preferred":[
        "Pyrgi"
    ],
    "name:und_x_variant":[
        "Vel\u00e1ousta",
        "Piry\u00ed",
        "Piry\u00edon"
    ],
    "wof:name":"Piryion",
    "wof:placetype":"locality",
    "wof:population":53
},
  "geometry": {"coordinates":[21.42222000000001,38.68172],"type":"Point"}
}