{
  "type": "Feature",
  "properties": {
    "gn:admin1_code":"ESYE21",
    "gn:admin2_code":"20.0",
    "gn:admin3_code":"9074",
    "gn:asciiname":"Kamaroula",
    "gn:country_code":"GR",
    "gn:dem":208,
    "gn:feature_class":"P",
    "gn:feature_code":"PPL",
    "gn:name":"Kamaro\u00fala",
    "gn:population":0,
    "gn:timezone":"Europe/Athens",
    "iso:country":"GR",
    "name:ell_x_preferred":[
        "\u039a\u03b1\u03bc\u03b1\u03c1\u03bf\u03cd\u03bb\u03b1"
    ],
    "name:und_x_variant":[
        "Sinoikism\u00f3s Kamaro\u00fala",
        "Synoikism\u00f3s Kamaro\u00fala",
        "Kamaro\u00fala"
    ],
    "wof:name":"Kamaroula",
    "wof:placetype":"locality"
},
  "geometry": {"coordinates":[21.15642,39.23556],"type":"Point"}
}