{
  "type": "Feature",
  "properties": {
    "gn:country":"GR",
    "gn:fcode":"PPL",
    "gn:population":933,
    "iso:country":"GR",
    "name:ell_x_preferred":[
        "\u03a0\u03c1\u03cc\u03b4\u03c1\u03bf\u03bc\u03bf\u03c2"
    ],
    "name:und_x_variant":[
        "Palai\u00f3s Pr\u00f3dhromos"
    ],
    "qs_pg:aaroncc":"GR",
    "qs_pg:gn_country":"GR",
    "qs_pg:gn_fcode":"PPL",
    "qs_pg:gn_pop":933,
    "qs_pg:name":"Prodhromos",
    "qs_pg:name_adm0":"\u0395\u03bb\u03bb\u03ac\u03b4\u03b1",
    "qs_pg:name_adm1":"Macedonia and Thrace",
    "qs_pg:photos_9k":1,
    "qs_pg:photos_9r":1,
    "qs_pg:photos_all":1,
    "qs_pg:photos_sr":0,
    "qs_pg:pop_sr":2,
    "qs_pg:qs_pg_placetype":"locality",
    "qs_pg:qs_pg_placetype_gp":"Town",
    "qs_pg:woe_adm0":23424833,
    "woe:adm0_id":23424833,
    "woe:name_adm0":"\u0395\u03bb\u03bb\u03ac\u03b4\u03b1",
    "woe:name_adm1":"Macedonia and Thrace",
    "woe:placetype":"Town",
    "wof:name":"Prodhromos",
    "wof:placetype":"locality",
    "wof:population":933
},
  "geometry": {"coordinates":[22.39667,40.55083],"type":"Point"}
}