{
  "type": "Feature",
  "properties": {
    "gn:admin1_code":"ESYE25",
    "gn:admin2_code":"40.0",
    "gn:admin3_code":"9256",
    "gn:asciiname":"Katsaros",
    "gn:country_code":"GR",
    "gn:dem":99,
    "gn:feature_class":"P",
    "gn:feature_code":"PPL",
    "gn:name":"Katsar\u00f3s",
    "gn:population":0,
    "gn:timezone":"Europe/Athens",
    "iso:country":"GR",
    "name:ell_x_preferred":[
        "\u039a\u03b1\u03c4\u03c3\u03b1\u03c1\u03cc\u03c2"
    ],
    "name:und_x_variant":[
        "Katsaro\u00fa",
        "Katsar\u00f3s"
    ],
    "wof:name":"Katsaros",
    "wof:placetype":"locality"
},
  "geometry": {"coordinates":[22.02919,37.21885],"type":"Point"}
}