{
  "type": "Feature",
  "properties": {
    "gn:country":"GR",
    "gn:fcode":"ADM3",
    "gn:population":17251,
    "iso:country":"GR",
    "name:ell_x_preferred":[
        "\u0392\u03ad\u03bb\u03bf\u03c5 - \u0392\u03cc\u03c7\u03b1\u03c2"
    ],
    "qs_pg:aaroncc":"GR",
    "qs_pg:gn_country":"GR",
    "qs_pg:gn_fcode":"ADM3",
    "qs_pg:gn_pop":17251,
    "qs_pg:name":"Dimos Velo-Vocha",
    "qs_pg:photos_9r":0,
    "qs_pg:photos_sr":0,
    "qs_pg:pop_sr":6,
    "qs_pg:qs_pg_placetype":"localadmin",
    "wof:name":"Dimos Velo-Vocha",
    "wof:placetype":"localadmin",
    "wof:population":17251
},
  "geometry": {"coordinates":[22.7411,37.9152],"type":"Point"}
}