{
  "type": "Feature",
  "properties": {
    "iso:country":"GR",
    "qs:a0":"Greece",
    "qs:a1":"*\u0394\u03a5\u03a4\u0399\u039a\u0397 \u0395\u039b\u039b\u0391\u0394\u0391",
    "qs:a1_alt":"DYTIKH ELLADA",
    "qs:a1r":"0",
    "qs:a2_alt":"HLEIA",
    "qs:adm0":"Greece",
    "qs:la_lc":"*",
    "qs:level":"locality",
    "qs:loc":"\u039d\u0395\u039f\u03a7\u03a9\u03a1\u0399\u039f\u039d",
    "qs:loc_alt":"NEOXVRION",
    "qs:pop":0,
    "qs:type":"buffered point",
    "wof:name":"\u039d\u0395\u039f\u03a7\u03a9\u03a1\u0399\u039f\u039d",
    "wof:placetype":"locality"
},
  "geometry": {"coordinates":[21.165898,37.893703],"type":"Point"}
}