{
  "type": "Feature",
  "properties": {
    "gn:admin1_code":"ESYE42",
    "gn:admin2_code":"49.0",
    "gn:admin3_code":"9269.0",
    "gn:asciiname":"Klisidi",
    "gn:country_code":"GR",
    "gn:dem":1,
    "gn:feature_class":"P",
    "gn:feature_code":"PPL",
    "gn:name":"Klisidi",
    "gn:population":0,
    "gn:timezone":"Europe/Athens",
    "iso:country":"GR",
    "name:ell_x_preferred":[
        "\u039a\u03bb\u03b7\u03c3\u03af\u03b4\u03b9"
    ],
    "wof:name":"Klisidi",
    "wof:placetype":"locality"
},
  "geometry": {"coordinates":[25.7758,36.34598],"type":"Point"}
}