{
  "type": "Feature",
  "properties": {
    "gn:admin1_code":"ESYE43",
    "gn:admin2_code":"45.0",
    "gn:admin3_code":"9306",
    "gn:asciiname":"Dhamasta",
    "gn:country_code":"GR",
    "gn:dem":401,
    "gn:feature_class":"P",
    "gn:feature_code":"PPL",
    "gn:name":"Dham\u00e1sta",
    "gn:population":0,
    "gn:timezone":"Europe/Athens",
    "iso:country":"GR",
    "name:ell_x_preferred":[
        "\u0394\u03b1\u03bc\u03ac\u03c3\u03c4\u03b1"
    ],
    "wof:name":"Dhamasta",
    "wof:placetype":"locality"
},
  "geometry": {"coordinates":[24.92291,35.35399],"type":"Point"}
}