{
  "type": "Feature",
  "properties": {
    "gn:admin1_code":"ESYE42",
    "gn:admin2_code":"49.0",
    "gn:admin3_code":"9301",
    "gn:asciiname":"Tzados",
    "gn:country_code":"GR",
    "gn:dem":402,
    "gn:feature_class":"P",
    "gn:feature_code":"PPL",
    "gn:name":"Tz\u00e1dos",
    "gn:population":0,
    "gn:timezone":"Europe/Athens",
    "iso:country":"GR",
    "name:und_x_variant":[
        "Tz\u00e1dos",
        "\u03a4\u03b6\u03ac\u03b4\u03bf\u03c2"
    ],
    "wof:name":"Tzados",
    "wof:placetype":"locality"
},
  "geometry": {"coordinates":[25.18601,37.57319],"type":"Point"}
}