{
  "type": "Feature",
  "properties": {
    "gn:country":"GR",
    "gn:fcode":"PPL",
    "gn:population":206,
    "iso:country":"GR",
    "name:bul_x_preferred":[
        "\u0410\u0440\u0433\u0438\u0442\u0438\u044f"
    ],
    "name:ceb_x_preferred":[
        "Dimos Argithea"
    ],
    "name:deu_x_preferred":[
        "Argithea"
    ],
    "name:ell_x_preferred":[
        "\u0391\u03c1\u03b3\u03b9\u03b8\u03ad\u03b1"
    ],
    "name:ell_x_variant":[
        "\u0394\u03ae\u03bc\u03bf\u03c2 \u0391\u03c1\u03b3\u03b9\u03b8\u03ad\u03b1\u03c2"
    ],
    "name:fin_x_preferred":[
        "Argith\u00e9a"
    ],
    "name:fra_x_preferred":[
        "Argithea"
    ],
    "name:ita_x_preferred":[
        "Argithea"
    ],
    "name:nld_x_preferred":[
        "Argithea"
    ],
    "name:nno_x_preferred":[
        "Arjith\u00e9a"
    ],
    "name:pol_x_preferred":[
        "Arjitea"
    ],
    "name:spa_x_preferred":[
        "Argitea"
    ],
    "name:swe_x_preferred":[
        "Dimos Argithea"
    ],
    "name:tur_x_preferred":[
        "Aryitea"
    ],
    "name:und_x_variant":[
        "Kn\u00edsovon"
    ],
    "name:vie_x_preferred":[
        "Argithea"
    ],
    "qs_pg:aaroncc":"GR",
    "qs_pg:gn_country":"GR",
    "qs_pg:gn_fcode":"PPL",
    "qs_pg:gn_pop":206,
    "qs_pg:name":"Argithea",
    "qs_pg:name_adm0":"\u0395\u03bb\u03bb\u03ac\u03b4\u03b1",
    "qs_pg:name_adm1":"Thessaly and Continental Greece",
    "qs_pg:photos_9k":1,
    "qs_pg:photos_9r":1,
    "qs_pg:photos_all":1,
    "qs_pg:photos_sr":0,
    "qs_pg:pop_sr":2,
    "qs_pg:qs_pg_placetype":"locality",
    "qs_pg:qs_pg_placetype_gp":"Town",
    "qs_pg:woe_adm0":23424833,
    "woe:adm0_id":23424833,
    "woe:name_adm0":"\u0395\u03bb\u03bb\u03ac\u03b4\u03b1",
    "woe:name_adm1":"Thessaly and Continental Greece",
    "woe:placetype":"Town",
    "wof:name":"Argithea",
    "wof:placetype":"locality",
    "wof:population":206
},
  "geometry": {"coordinates":[21.53833,39.35556],"type":"Point"}
}