{
  "type": "Feature",
  "properties": {
    "gn:admin1_code":"ESYE23",
    "gn:admin2_code":"39.0",
    "gn:admin3_code":"9140",
    "gn:asciiname":"Kardiakafti",
    "gn:country_code":"GR",
    "gn:dem":12,
    "gn:feature_class":"P",
    "gn:feature_code":"PPL",
    "gn:name":"Kardiak\u00e1fti",
    "gn:population":0,
    "gn:timezone":"Europe/Athens",
    "iso:country":"GR",
    "name:ell_x_preferred":[
        "Kardiak\u00e1fti"
    ],
    "name:ell_x_variant":[
        "\u039a\u03b1\u03c1\u03b4\u03b9\u03b1\u03ba\u03b1\u03cd\u03c4\u03b9",
        "Kardiak\u00e1ftion",
        "\u039a\u03b1\u03c1\u03b4\u03b9\u03b1\u03ba\u03b1\u03cd\u03c4\u03b9\u03bf\u03bd",
        "\u039a\u03b1\u03c1\u03b4\u03b9\u03b1\u03ba\u03b1\u03cd\u03c4\u03b9 \u0397\u03bb\u03b5\u03af\u03b1\u03c2"
    ],
    "name:ron_x_preferred":[
        "Kardiakafti"
    ],
    "name:und_x_variant":[
        "Kardhiok\u00e1vtion",
        "Kardhiak\u00e1vti",
        "Kardhiak\u00e1vtion"
    ],
    "wof:name":"Kardiakafti",
    "wof:placetype":"locality"
},
  "geometry": {"coordinates":[21.24139,37.87731],"type":"Point"}
}