{
  "type": "Feature",
  "properties": {
    "gn:admin1_code":"ESYE12",
    "gn:admin2_code":"13.0",
    "gn:admin3_code":"9034",
    "gn:asciiname":"Nikopolis",
    "gn:cc2":"GR",
    "gn:country_code":"GR",
    "gn:dem":570,
    "gn:feature_class":"P",
    "gn:feature_code":"PPL",
    "gn:name":"Nik\u00f3polis",
    "gn:population":0,
    "gn:timezone":"Europe/Athens",
    "iso:country":"GR",
    "name:ell_x_preferred":[
        "\u039d\u03b9\u03ba\u03cc\u03c0\u03bf\u03bb\u03b7"
    ],
    "name:und_x_variant":[
        "Z\u00e1rova"
    ],
    "wof:name":"Nikopolis",
    "wof:placetype":"locality"
},
  "geometry": {"coordinates":[23.18042,40.88748],"type":"Point"}
}