{
  "type": "Feature",
  "properties": {
    "gn:admin1_code":"ESYE24",
    "gn:admin2_code":"29.0",
    "gn:admin3_code":"9162",
    "gn:asciiname":"Klonion",
    "gn:country_code":"GR",
    "gn:dem":305,
    "gn:feature_class":"P",
    "gn:feature_code":"PPL",
    "gn:name":"Klon\u00edon",
    "gn:population":144,
    "gn:timezone":"Europe/Athens",
    "iso:country":"GR",
    "name:ell_x_preferred":[
        "\u039a\u03bb\u03c9\u03bd\u03af"
    ],
    "name:ell_x_variant":[
        "\u039a\u03bb\u03c9\u03bd\u03af\u03bf\u03bd"
    ],
    "name:eng_x_preferred":[
        "Kloni"
    ],
    "name:und_x_variant":[
        "Klon\u00ed",
        "Kl\u00f3nion"
    ],
    "wof:name":"Klonion",
    "wof:placetype":"locality",
    "wof:population":144
},
  "geometry": {"coordinates":[22.10238,38.90409],"type":"Point"}
}