{
  "type": "Feature",
  "properties": {
    "gn:admin1_code":"ESYE22",
    "gn:admin2_code":"27.0",
    "gn:admin3_code":"9120",
    "gn:asciiname":"Poros, Kefalonia",
    "gn:country_code":"GR",
    "gn:dem":127,
    "gn:feature_class":"P",
    "gn:feature_code":"PPL",
    "gn:name":"Poros, Kefalonia",
    "gn:population":0,
    "gn:timezone":"Europe/Athens",
    "iso:country":"GR",
    "wof:name":"Poros, Kefalonia",
    "wof:placetype":"locality"
},
  "geometry": {"coordinates":[20.76667,38.15],"type":"Point"}
}