{
  "type": "Feature",
  "properties": {
    "gn:admin1_code":"ESYE31",
    "gn:admin2_code":"406101.0",
    "gn:admin3_code":"9214",
    "gn:asciiname":"Moni Profitou Iliou",
    "gn:country_code":"GR",
    "gn:dem":475,
    "gn:feature_class":"P",
    "gn:feature_code":"PPLR",
    "gn:name":"Mon\u00ed Prof\u00edtou Ilio\u00fa",
    "gn:population":2,
    "gn:timezone":"Europe/Athens",
    "iso:country":"GR",
    "name:ell_x_preferred":[
        "\u039c\u03bf\u03bd\u03ae \u03a0\u03c1\u03bf\u03c6\u03ae\u03c4\u03bf\u03c5 \u0397\u03bb\u03b9\u03bf\u03cd"
    ],
    "wof:name":"Moni Profitou Iliou",
    "wof:placetype":"locality",
    "wof:population":2
},
  "geometry": {"coordinates":[23.46303,37.33457],"type":"Point"}
}