{
  "type": "Feature",
  "properties": {
    "gn:country":"GR",
    "gn:fcode":"PPL",
    "gn:population":0,
    "iso:country":"GR",
    "name:arz_x_preferred":[
        "\u0643\u0627\u0644\u0648\u0633\u0643\u0648\u067e\u0649"
    ],
    "name:bul_x_preferred":[
        "\u041a\u0430\u043b\u043e\u0441\u043a\u043e\u043f\u0438"
    ],
    "name:deu_x_preferred":[
        "Kaloskopi"
    ],
    "name:ell_x_historical":[
        "\u039a\u03bf\u03c5\u03ba\u03bf\u03c5\u03b2\u03af\u03c3\u03c4\u03b1",
        "\u039a\u03bf\u03c5\u03ba\u03bf\u03b2\u03af\u03c4\u03c3\u03b1",
        "\u039a\u03bf\u03c5\u03ba\u03ba\u03bf\u03c5\u03b2\u03af\u03c4\u03c3\u03b1"
    ],
    "name:ell_x_preferred":[
        "\u039a\u03b1\u03bb\u03bf\u03c3\u03ba\u03bf\u03c0\u03ae"
    ],
    "name:ell_x_variant":[
        "\u039a\u03bf\u03c5\u03ba\u03bf\u03c5\u03b2\u03af\u03c3\u03c4\u03b1",
        "\u039a\u03bf\u03c5\u03ba\u03bf\u03b2\u03af\u03c4\u03c3\u03b1",
        "\u039a\u03bf\u03c5\u03ba\u03ba\u03bf\u03c5\u03b2\u03af\u03c4\u03c3\u03b1",
        "\u039a\u03b1\u03bb\u03bf\u03c3\u03ba\u03bf\u03c0\u03ae \u03a6\u03c9\u03ba\u03af\u03b4\u03b1\u03c2"
    ],
    "name:eng_x_historical":[
        "Koukovitsa",
        "Koukkouvitsa"
    ],
    "name:eng_x_preferred":[
        "Koukovitsa"
    ],
    "name:eng_x_variant":[
        "Kaloskopi",
        "Koukkouvitsa"
    ],
    "name:fra_x_preferred":[
        "Kaloskopi"
    ],
    "name:nld_x_preferred":[
        "Kaloskopi"
    ],
    "name:rus_x_preferred":[
        "\u041a\u0430\u043b\u043e\u0441\u043a\u043e\u043f\u0438"
    ],
    "name:und_x_variant":[
        "Koukouv\u00edsta"
    ],
    "qs_pg:aaroncc":"GR",
    "qs_pg:gn_country":"GR",
    "qs_pg:gn_fcode":"PPL",
    "qs_pg:gn_pop":0,
    "qs_pg:name":"Kaloskopi",
    "qs_pg:name_adm0":"\u0395\u03bb\u03bb\u03ac\u03b4\u03b1",
    "qs_pg:name_adm1":"Thessaly and Continental Greece",
    "qs_pg:photos":79,
    "qs_pg:photos_1k":16,
    "qs_pg:photos_9k":1,
    "qs_pg:photos_9r":3,
    "qs_pg:photos_all":79,
    "qs_pg:photos_sr":3,
    "qs_pg:pop_sr":0,
    "qs_pg:qs_pg_placetype":"locality",
    "qs_pg:qs_pg_placetype_gp":"Town",
    "qs_pg:woe_adm0":23424833,
    "woe:adm0_id":23424833,
    "woe:name_adm0":"\u0395\u03bb\u03bb\u03ac\u03b4\u03b1",
    "woe:name_adm1":"Thessaly and Continental Greece",
    "woe:placetype":"Town",
    "wof:name":"Kaloskopi",
    "wof:placetype":"locality"
},
  "geometry": {"coordinates":[22.33333,38.68333],"type":"Point"}
}