{
  "type": "Feature",
  "properties": {
    "gn:admin1_code":"ESYE25",
    "gn:admin2_code":"42.0",
    "gn:admin3_code":"9252",
    "gn:asciiname":"Pera Chora",
    "gn:country_code":"GR",
    "gn:dem":723,
    "gn:feature_class":"P",
    "gn:feature_code":"PPL",
    "gn:name":"P\u00e9ra Ch\u00f3ra",
    "gn:population":0,
    "gn:timezone":"Europe/Athens",
    "iso:country":"GR",
    "name:ell_x_preferred":[
        "\u03a0\u03ad\u03c1\u03b1 \u03a7\u03ce\u03c1\u03b1"
    ],
    "name:ell_x_variant":[
        "P\u00e9ra Ch\u00f3ra"
    ],
    "name:und_x_variant":[
        "P\u00e9ra Kh\u00f3ra"
    ],
    "wof:name":"Pera Chora",
    "wof:placetype":"locality"
},
  "geometry": {"coordinates":[22.39897,36.97214],"type":"Point"}
}