{
  "type": "Feature",
  "properties": {
    "gn:admin1_code":"ESYE23",
    "gn:admin2_code":"38.0",
    "gn:admin3_code":"9131",
    "gn:asciiname":"Gomosto",
    "gn:country_code":"GR",
    "gn:dem":34,
    "gn:feature_class":"P",
    "gn:feature_code":"PPL",
    "gn:name":"Gomost\u00f3",
    "gn:population":0,
    "gn:timezone":"Europe/Athens",
    "iso:country":"GR",
    "name:ell_x_preferred":[
        "Gomost\u00f3"
    ],
    "name:ell_x_variant":[
        "\u0393\u03bf\u03bc\u03bf\u03c3\u03c4\u03cc",
        "\u0393\u03bf\u03bc\u03bf\u03c3\u03c4\u03cc\u03bd",
        "\u0393\u03bf\u03bc\u03bf\u03c3\u03c4\u03cc \u0391\u03c7\u03b1\u0390\u03b1\u03c2"
    ],
    "name:ron_x_preferred":[
        "Gomosto"
    ],
    "name:und_x_variant":[
        "Gomost\u00f3s",
        "Gomost\u00f3n"
    ],
    "wof:name":"Gomosto",
    "wof:placetype":"locality"
},
  "geometry": {"coordinates":[21.50325,38.12086],"type":"Point"}
}