{
  "type": "Feature",
  "properties": {
    "gn:population":10563,
    "iso:country":"GR",
    "name:ara_x_preferred":[
        "\u063a\u0631\u064a\u0641\u064a\u0646\u0627"
    ],
    "name:bel_x_preferred":[
        "\u0413\u043e\u0440\u0430\u0434 \u0413\u0440\u044d\u0432\u0435\u043d\u0430"
    ],
    "name:bul_x_preferred":[
        "\u0413\u0440\u0435\u0432\u0435\u043d\u0430"
    ],
    "name:ceb_x_preferred":[
        "Greven\u00e1"
    ],
    "name:ces_x_preferred":[
        "Grevena"
    ],
    "name:deu_x_preferred":[
        "Grevena"
    ],
    "name:ell_x_preferred":[
        "\u0393\u03c1\u03b5\u03b2\u03b5\u03bd\u03ac"
    ],
    "name:eng_x_preferred":[
        "Grevena"
    ],
    "name:eus_x_preferred":[
        "Grevena"
    ],
    "name:fin_x_preferred":[
        "Greven\u00e1"
    ],
    "name:fra_x_preferred":[
        "Gr\u00e9v\u00e9na"
    ],
    "name:fra_x_variant":[
        "Grevena"
    ],
    "name:hbs_x_preferred":[
        "Grevena"
    ],
    "name:hrv_x_preferred":[
        "Grevena"
    ],
    "name:ita_x_preferred":[
        "Grevena"
    ],
    "name:jpn_x_preferred":[
        "\u30b0\u30ec\u30f4\u30a7\u30ca"
    ],
    "name:kor_x_preferred":[
        "\uadf8\ub808\ubca0\ub098"
    ],
    "name:lat_x_preferred":[
        "Grebena"
    ],
    "name:lit_x_preferred":[
        "Grevena"
    ],
    "name:mkd_x_preferred":[
        "\u0413\u0440\u0435\u0431\u0435\u043d"
    ],
    "name:nld_x_preferred":[
        "Grevena"
    ],
    "name:nno_x_preferred":[
        "Greven\u00e1"
    ],
    "name:pol_x_preferred":[
        "Grewena"
    ],
    "name:ron_x_preferred":[
        "Grevena"
    ],
    "name:rus_x_preferred":[
        "\u0413\u0440\u0435\u0432\u0435\u043d\u0430"
    ],
    "name:slk_x_preferred":[
        "Grevena"
    ],
    "name:spa_x_preferred":[
        "Greven\u00e1"
    ],
    "name:sqi_x_preferred":[
        "Grebeneja"
    ],
    "name:sqi_x_variant":[
        "Grebena"
    ],
    "name:srp_x_preferred":[
        "\u0413\u0440\u0435\u0431\u0435\u043d"
    ],
    "name:swe_x_preferred":[
        "Greven\u00e1"
    ],
    "name:tur_x_preferred":[
        "Grebene"
    ],
    "name:ukr_x_preferred":[
        "\u0413\u0440\u0435\u0432\u0435\u043d\u0430"
    ],
    "name:urd_x_preferred":[
        "\u06af\u0631\u06cc\u0648\u06cc\u0646\u0627"
    ],
    "name:vie_x_preferred":[
        "Grevena"
    ],
    "name:war_x_preferred":[
        "Grevena"
    ],
    "name:zho_x_preferred":[
        "\u683c\u96f7\u97e6\u7eb3"
    ],
    "qs:a0":"Greece",
    "qs:a1":"*\u0394\u03a5\u03a4\u0399\u039a\u0397 \u039c\u0391\u039a\u0395\u0394\u039f\u039d\u0399\u0391",
    "qs:a1_alt":"DYTIKH MAKEDONIA",
    "qs:a1r":"0",
    "qs:a2_alt":"GREBENA",
    "qs:adm0":"Greece",
    "qs:la_lc":"*",
    "qs:level":"locality",
    "qs:loc":"\u0393\u03a1\u0395\u0392\u0395\u039d\u0391",
    "qs:loc_alt":"GREBENA",
    "qs:pop":0,
    "qs:type":"buffered point",
    "wd:wordcount":449,
    "wof:name":"\u0393\u03a1\u0395\u0392\u0395\u039d\u0391",
    "wof:placetype":"locality",
    "wof:population":10563
},
  "geometry": {"coordinates":[21.426412,40.083599],"type":"Point"}
}