{
  "type": "Feature",
  "properties": {
    "gn:admin1_code":"ESYE24",
    "gn:admin2_code":"32.0",
    "gn:admin3_code":"9166",
    "gn:asciiname":"Marathias",
    "gn:cc2":"GR",
    "gn:country_code":"GR",
    "gn:dem":11,
    "gn:feature_class":"P",
    "gn:feature_code":"PPL",
    "gn:name":"Marathi\u00e1s",
    "gn:population":0,
    "gn:timezone":"Europe/Athens",
    "iso:country":"GR",
    "name:und_x_variant":[
        "Marathi\u00e1",
        "Marathi\u00e1s"
    ],
    "wof:name":"Marathias",
    "wof:placetype":"locality"
},
  "geometry": {"coordinates":[22.01197,38.39347],"type":"Point"}
}