{
  "type": "Feature",
  "properties": {
    "gn:admin1_code":"ESYE14",
    "gn:admin2_code":"21.0",
    "gn:admin3_code":"9099",
    "gn:asciiname":"Prodromos",
    "gn:country_code":"GR",
    "gn:dem":60,
    "gn:feature_class":"P",
    "gn:feature_code":"PPL",
    "gn:name":"Pr\u00f3dromos",
    "gn:population":0,
    "gn:timezone":"Europe/Athens",
    "iso:country":"GR",
    "name:ceb_x_preferred":[
        "Pr\u00f3dromos"
    ],
    "name:deu_x_preferred":[
        "Prodromos"
    ],
    "name:ell_x_preferred":[
        "Pr\u00f3dromos"
    ],
    "name:ell_x_variant":[
        "\u03a0\u03c1\u03cc\u03b4\u03c1\u03bf\u03bc\u03bf\u03c2"
    ],
    "name:swe_x_preferred":[
        "Prodromos"
    ],
    "name:und_x_variant":[
        "Sar\u00edznion",
        "Sar\u00edmion",
        "Pr\u00f3dhromos"
    ],
    "wof:name":"Prodromos",
    "wof:placetype":"locality"
},
  "geometry": {"coordinates":[22.58711,39.59161],"type":"Point"}
}