{
  "type": "Feature",
  "properties": {
    "gn:admin1_code":"ESYE11",
    "gn:admin2_code":"2.0",
    "gn:admin3_code":"9022",
    "gn:asciiname":"Salmoni",
    "gn:country_code":"GR",
    "gn:dem":77,
    "gn:feature_class":"P",
    "gn:feature_code":"PPL",
    "gn:name":"Salm\u00f3ni",
    "gn:population":0,
    "gn:timezone":"Europe/Athens",
    "iso:country":"GR",
    "name:ell_x_preferred":[
        "\u03a3\u03b1\u03bb\u03bc\u03ce\u03bd\u03b7"
    ],
    "name:ell_x_variant":[
        "Salm\u00f3ni"
    ],
    "wof:name":"Salmoni",
    "wof:placetype":"locality"
},
  "geometry": {"coordinates":[25.53392,41.00436],"type":"Point"}
}