{
  "type": "Feature",
  "properties": {
    "gn:admin1_code":"ESYE14",
    "gn:admin2_code":"21.0",
    "gn:admin3_code":"9099",
    "gn:asciiname":"Nees Karyes",
    "gn:country_code":"GR",
    "gn:dem":137,
    "gn:feature_class":"P",
    "gn:feature_code":"PPL",
    "gn:name":"N\u00e9es Kary\u00e9s",
    "gn:population":0,
    "gn:timezone":"Europe/Athens",
    "iso:country":"GR",
    "name:ell_x_preferred":[
        "N\u00e9es Kary\u00e9s"
    ],
    "name:ell_x_variant":[
        "\u039d\u03ad\u03b5\u03c2 \u039a\u03b1\u03c1\u03c5\u03ad\u03c2",
        "N\u00e9ai Karya\u00ed",
        "\u039d\u03ad\u03b1\u03b9 \u039a\u03b1\u03c1\u03c5\u03b1\u03af"
    ],
    "name:und_x_variant":[
        "N\u00e9a Karia\u00ed",
        "N\u00e9ai Karia\u00ed"
    ],
    "wof:name":"Nees Karyes",
    "wof:placetype":"locality"
},
  "geometry": {"coordinates":[22.46944,39.51067000000001],"type":"Point"}
}