{
  "type": "Feature",
  "properties": {
    "gn:admin1_code":"ESYE23",
    "gn:admin2_code":"39.0",
    "gn:admin3_code":"9136",
    "gn:asciiname":"Ploutochori",
    "gn:country_code":"GR",
    "gn:dem":225,
    "gn:feature_class":"P",
    "gn:feature_code":"PPL",
    "gn:name":"Ploutoch\u00f3ri",
    "gn:population":0,
    "gn:timezone":"Europe/Athens",
    "iso:country":"GR",
    "name:ell_x_preferred":[
        "Ploutoch\u00f3ri"
    ],
    "name:ell_x_variant":[
        "\u03a0\u03bb\u03bf\u03c5\u03c4\u03bf\u03c7\u03ce\u03c1\u03b9",
        "Ploutoch\u00f3rion",
        "\u03a0\u03bb\u03bf\u03c5\u03c4\u03bf\u03c7\u03ce\u03c1\u03b9\u03bf\u03bd"
    ],
    "name:und_x_variant":[
        "T\u00f3yia",
        "Ploutokh\u00f3ri",
        "Ploutokh\u00f3rion"
    ],
    "wof:name":"Ploutochori",
    "wof:placetype":"locality"
},
  "geometry": {"coordinates":[21.70817000000001,37.61214],"type":"Point"}
}