{
  "type": "Feature",
  "properties": {
    "gn:population":1611,
    "iso:country":"GR",
    "name:ara_x_preferred":[
        "\u0643\u064a\u0631\u064a\u0627\u060c \u062f\u0631\u0627\u0645\u0627"
    ],
    "name:ara_x_variant":[
        "\u0643\u064a\u0631\u064a\u0627"
    ],
    "name:bul_x_preferred":[
        "\u041a\u0438\u0440\u0438\u044f"
    ],
    "name:ceb_x_preferred":[
        "K\u00fdria"
    ],
    "name:ell_x_preferred":[
        "\u039a\u03cd\u03c1\u03b9\u03b1"
    ],
    "name:ell_x_variant":[
        "K\u00fdria",
        "\u039a\u03cd\u03c1\u03b3\u03b9\u03b1",
        "\u039a\u03cd\u03c1\u03b3\u03b9\u03b1 \u0394\u03c1\u03ac\u03bc\u03b1\u03c2"
    ],
    "name:eng_x_preferred":[
        "Kyrgia"
    ],
    "name:mkd_x_preferred":[
        "\u041e\u0440\u0433\u0430\u043d\u045f\u0438"
    ],
    "name:nld_x_preferred":[
        "Kyrgia"
    ],
    "name:pol_x_preferred":[
        "Kiria"
    ],
    "name:swe_x_preferred":[
        "K\u00fdria"
    ],
    "name:unk_x_variant":[
        "Organtz\u00ed"
    ],
    "qs:a0":"Greece",
    "qs:a1":"*\u0391\u039d\u0391\u03a4\u039f\u039b\u0399\u039a\u0397 \u039c\u0391\u039a\u0395\u0394\u039f\u039d\u0399\u0391 \u039a\u0391\u0399 \u0398\u03a1\u0391\u039a\u0397",
    "qs:a1_alt":"ANATOLIKH MAKEDONIA KAI URAKH",
    "qs:a1r":"0",
    "qs:a2_alt":"DRAMA",
    "qs:adm0":"Greece",
    "qs:la_lc":"*",
    "qs:level":"locality",
    "qs:loc":"\u039a\u03a5\u03a1\u0399\u0391",
    "qs:loc_alt":"KYRIA",
    "qs:pop":0,
    "qs:type":"buffered point",
    "wof:name":"\u039a\u03a5\u03a1\u0399\u0391",
    "wof:placetype":"locality",
    "wof:population":1611
},
  "geometry": {"coordinates":[24.289189,41.09845],"type":"Point"}
}