{
  "type": "Feature",
  "properties": {
    "gn:country":"GR",
    "gn:fcode":"PPL",
    "gn:population":138,
    "iso:country":"GR",
    "name:ell_x_preferred":[
        "\u0386\u03b3\u03b9\u03bf\u03c2 \u03a7\u03b1\u03c1\u03ac\u03bb\u03b1\u03bc\u03c0\u03bf\u03c2"
    ],
    "name:und_x_variant":[
        "\u00c1yios Khar\u00e1lambos"
    ],
    "qs_pg:aaroncc":"GR",
    "qs_pg:gn_country":"GR",
    "qs_pg:gn_fcode":"PPL",
    "qs_pg:gn_pop":138,
    "qs_pg:name":"\u00c1gios Char\u00e1lampos",
    "qs_pg:photos_9r":0,
    "qs_pg:photos_sr":0,
    "qs_pg:pop_sr":1,
    "qs_pg:qs_pg_placetype":"locality",
    "wof:name":"\u00c1gios Char\u00e1lampos",
    "wof:placetype":"locality",
    "wof:population":138
},
  "geometry": {"coordinates":[22.81333,41.20278],"type":"Point"}
}