{
  "type": "Feature",
  "properties": {
    "gn:population":1158,
    "iso:country":"GR",
    "name:ceb_x_preferred":[
        "Arrian\u00e1"
    ],
    "name:ell_x_preferred":[
        "\u0391\u03c1\u03c1\u03b9\u03b1\u03bd\u03ac"
    ],
    "name:ell_x_variant":[
        "\u0391\u03c1\u03c1\u03b9\u03b1\u03bd\u03ac \u03a1\u03bf\u03b4\u03cc\u03c0\u03b7\u03c2"
    ],
    "name:eng_x_preferred":[
        "Arriana"
    ],
    "name:lit_x_preferred":[
        "Ariana"
    ],
    "name:nld_x_preferred":[
        "Arriana"
    ],
    "name:rus_x_preferred":[
        "\u0410\u0440\u0438\u0430\u043d\u0430"
    ],
    "name:swe_x_preferred":[
        "Arrian\u00e1"
    ],
    "name:tur_x_preferred":[
        "Kozlukebir"
    ],
    "name:unk_x_variant":[
        "Kuzl\u00fa Keb\u00edr"
    ],
    "qs:a0":"Greece",
    "qs:a1":"*\u0391\u039d\u0391\u03a4\u039f\u039b\u0399\u039a\u0397 \u039c\u0391\u039a\u0395\u0394\u039f\u039d\u0399\u0391 \u039a\u0391\u0399 \u0398\u03a1\u0391\u039a\u0397",
    "qs:a1_alt":"ANATOLIKH MAKEDONIA KAI URAKH",
    "qs:a1r":"0",
    "qs:a2_alt":"RODOPH",
    "qs:adm0":"Greece",
    "qs:la_lc":"*",
    "qs:level":"locality",
    "qs:loc":"\u0391\u03a1\u03a1\u0399\u0391\u039d\u0391",
    "qs:loc_alt":"ARRIANA",
    "qs:pop":0,
    "qs:type":"buffered point",
    "wof:name":"\u0391\u03a1\u03a1\u0399\u0391\u039d\u0391",
    "wof:placetype":"locality",
    "wof:population":1158
},
  "geometry": {"coordinates":[25.695581,41.081669],"type":"Point"}
}