{
  "type": "Feature",
  "properties": {
    "gn:admin1_code":"ESYE12",
    "gn:admin2_code":"5.0",
    "gn:admin3_code":"9051",
    "gn:asciiname":"Pethelinos",
    "gn:country_code":"GR",
    "gn:dem":10,
    "gn:feature_class":"P",
    "gn:feature_code":"PPL",
    "gn:name":"Pethelin\u00f3s",
    "gn:population":474,
    "gn:timezone":"Europe/Athens",
    "iso:country":"GR",
    "name:bul_x_preferred":[
        "\u041f\u0435\u0442\u0435\u043b\u0438\u043d\u043e\u0441"
    ],
    "name:ell_x_preferred":[
        "\u03a0\u03b5\u03b8\u03b5\u03bb\u03b9\u03bd\u03cc\u03c2"
    ],
    "name:ell_x_variant":[
        "\u03a0\u03bf\u03c4\u03bf\u03bb\u03b9\u03bd\u03cc\u03c2"
    ],
    "name:eng_x_preferred":[
        "Pethelinos"
    ],
    "name:mkd_x_preferred":[
        "\u041f\u0435\u0442\u0435\u043b\u0438\u043d\u043e\u0441"
    ],
    "name:und_x_variant":[
        "Petelin\u00f3s",
        "Pethelin\u00f3s"
    ],
    "wof:name":"Pethelinos",
    "wof:placetype":"locality",
    "wof:population":474
},
  "geometry": {"coordinates":[23.7112,40.96064000000001],"type":"Point"}
}