{
  "type": "Feature",
  "properties": {
    "gn:admin1_code":"ESYE42",
    "gn:admin2_code":"49.0",
    "gn:admin3_code":"9268",
    "gn:asciiname":"Katakoilos",
    "gn:country_code":"GR",
    "gn:dem":271,
    "gn:feature_class":"P",
    "gn:feature_code":"PPL",
    "gn:name":"Kat\u00e1koilos",
    "gn:population":0,
    "gn:timezone":"Europe/Athens",
    "iso:country":"GR",
    "name:ell_x_preferred":[
        "Kat\u00e1koilos"
    ],
    "name:ell_x_variant":[
        "\u039a\u03b1\u03c4\u03ac\u03ba\u03bf\u03b9\u03bb\u03bf\u03c2"
    ],
    "wof:name":"Katakoilos",
    "wof:placetype":"locality"
},
  "geometry": {"coordinates":[24.82066,37.86682],"type":"Point"}
}