{
  "type": "Feature",
  "properties": {
    "gn:admin1_code":"ESYE42",
    "gn:admin2_code":"49.0",
    "gn:admin3_code":"9292.0",
    "gn:asciiname":"Mesi Potamia",
    "gn:country_code":"GR",
    "gn:dem":149,
    "gn:feature_class":"P",
    "gn:feature_code":"PPL",
    "gn:name":"M\u00e9si Potami\u00e1",
    "gn:population":59,
    "gn:timezone":"Europe/Athens",
    "iso:country":"GR",
    "name:ell_x_preferred":[
        "\u039c\u03ad\u03c3\u03b7 \u03a0\u03bf\u03c4\u03b1\u03bc\u03b9\u03ac"
    ],
    "name:eng_x_preferred":[
        "Mesi Potamia"
    ],
    "wof:name":"Mesi Potamia",
    "wof:placetype":"locality",
    "wof:population":59
},
  "geometry": {"coordinates":[25.44363,37.06853],"type":"Point"}
}