{
  "type": "Feature",
  "properties": {
    "gn:admin1_code":"ESYE43",
    "gn:admin2_code":"45.0",
    "gn:admin3_code":"9302",
    "gn:asciiname":"Alagnion",
    "gn:cc2":"GR",
    "gn:country_code":"GR",
    "gn:dem":469,
    "gn:feature_class":"P",
    "gn:feature_code":"PPL",
    "gn:name":"Al\u00e1gnion",
    "gn:population":0,
    "gn:timezone":"Europe/Athens",
    "iso:country":"GR",
    "name:und_x_variant":[
        "Al\u00e1gni",
        "Al\u00e1gnion"
    ],
    "wof:name":"Alagnion",
    "wof:placetype":"locality"
},
  "geometry": {"coordinates":[25.21062,35.1743],"type":"Point"}
}