{
  "type": "Feature",
  "properties": {
    "gn:admin1_code":"ESYE11",
    "gn:admin2_code":"1.0",
    "gn:admin3_code":"9008",
    "gn:asciiname":"Krios",
    "gn:country_code":"GR",
    "gn:dem":76,
    "gn:feature_class":"P",
    "gn:feature_code":"PPL",
    "gn:name":"Kri\u00f3s",
    "gn:population":0,
    "gn:timezone":"Europe/Athens",
    "iso:country":"GR",
    "name:ell_x_preferred":[
        "Kri\u00f3s"
    ],
    "name:ell_x_variant":[
        "\u039a\u03c1\u03b9\u03cc\u03c2"
    ],
    "name:jpn_x_preferred":[
        "\u30af\u30ea\u30aa\u30b9"
    ],
    "name:slk_x_preferred":[
        "Krios"
    ],
    "wof:name":"Krios",
    "wof:placetype":"locality"
},
  "geometry": {"coordinates":[26.35432,41.66723],"type":"Point"}
}