{
  "type": "Feature",
  "properties": {
    "gn:country":"GR",
    "gn:fcode":"PPL",
    "gn:population":151,
    "iso:country":"GR",
    "name:ell_x_preferred":[
        "\u039a\u03bf\u03bc\u03bd\u03b7\u03bd\u03ac\u03b4\u03b5\u03c2"
    ],
    "name:eng_x_preferred":[
        "Komninades"
    ],
    "name:und_x_variant":[
        "Si\u00e1ki"
    ],
    "qs_pg:aaroncc":"GR",
    "qs_pg:gn_country":"GR",
    "qs_pg:gn_fcode":"PPL",
    "qs_pg:gn_pop":151,
    "qs_pg:name":"Komninadhes",
    "qs_pg:name_adm0":"\u0395\u03bb\u03bb\u03ac\u03b4\u03b1",
    "qs_pg:name_adm1":"Epirus and Western Macedonia",
    "qs_pg:photos_9r":0,
    "qs_pg:photos_sr":0,
    "qs_pg:pop_sr":1,
    "qs_pg:qs_pg_placetype":"locality",
    "qs_pg:qs_pg_placetype_gp":"Town",
    "qs_pg:woe_adm0":23424833,
    "woe:adm0_id":23424833,
    "woe:name_adm0":"\u0395\u03bb\u03bb\u03ac\u03b4\u03b1",
    "woe:name_adm1":"Epirus and Western Macedonia",
    "woe:placetype":"Town",
    "wof:name":"Komninadhes",
    "wof:placetype":"locality",
    "wof:population":78
},
  "geometry": {"coordinates":[20.99556,40.52083],"type":"Point"}
}