{
  "type": "Feature",
  "properties": {
    "gn:gn_country":"GR",
    "gn:gn_fcode":"ADM3",
    "gn:gn_pop":142923,
    "gn:population":142923,
    "iso:country":"GR",
    "name:ell_x_preferred":[
        "\u0392\u03cc\u03bb\u03bf\u03c5"
    ],
    "qs_pg:aaroncc":"GR",
    "qs_pg:gn_country":"GR",
    "qs_pg:gn_fcode":"ADM3",
    "qs_pg:gn_pop":142923,
    "qs_pg:name":"Dimos Volos",
    "qs_pg:photos_9r":0,
    "qs_pg:photos_sr":0,
    "qs_pg:pop_sr":9,
    "qs_pg:qs_pg_placetype":"localadmin",
    "wof:name":"Dimos Volos",
    "wof:placetype":"localadmin",
    "wof:population":142923
},
  "geometry": {"coordinates":[22.90835,39.35723],"type":"Point"}
}