{
  "type": "Feature",
  "properties": {
    "gn:population":5838,
    "iso:country":"GR",
    "name:ara_x_preferred":[
        "\u0623\u0648\u0641\u0631\u064a\u0627"
    ],
    "name:dut_x_preferred":[
        "Ovrya"
    ],
    "name:ell_x_preferred":[
        "\u039f\u03b2\u03c1\u03c5\u03ac \u0391\u03c7\u03b1\u0390\u03b1\u03c2"
    ],
    "name:ell_x_variant":[
        "\u039f\u03b2\u03c1\u03b9\u03ac",
        "\u039f\u03b2\u03c1\u03c5\u03ac"
    ],
    "name:eng_x_preferred":[
        "Ovrya"
    ],
    "name:gre_x_preferred":[
        "\u039f\u03b2\u03c1\u03c5\u03ac \u0391\u03c7\u03b1\u0390\u03b1\u03c2"
    ],
    "name:jpn_x_preferred":[
        "\u30aa\u30f4\u30ea\u30a2"
    ],
    "name:nno_x_preferred":[
        "Ovry\u00e1"
    ],
    "name:ron_x_preferred":[
        "Ovrya"
    ],
    "name:rum_x_preferred":[
        "Ovrya"
    ],
    "name:swe_x_preferred":[
        "Ovri\u00e1"
    ],
    "name:unk_x_variant":[
        "Ovri\u00e1"
    ],
    "qs:a0":"Greece",
    "qs:a1":"*\u0394\u03a5\u03a4\u0399\u039a\u0397 \u0395\u039b\u039b\u0391\u0394\u0391",
    "qs:a1_alt":"DYTIKH ELLADA",
    "qs:a1r":"0",
    "qs:a2_alt":"AXAIA",
    "qs:adm0":"Greece",
    "qs:la_lc":"*",
    "qs:level":"locality",
    "qs:loc":"\u039f\u0392\u03a1\u0399\u0391",
    "qs:loc_alt":"OBRIA",
    "qs:pop":0,
    "qs:type":"buffered point",
    "wd:wordcount":130,
    "wof:name":"\u039f\u0392\u03a1\u0399\u0391",
    "wof:placetype":"locality",
    "wof:population":5838
},
  "geometry": {"coordinates":[21.721165,38.186539],"type":"Point"}
}