{
  "type": "Feature",
  "properties": {
    "gn:admin1_code":"ESYE21",
    "gn:admin2_code":"17.0",
    "gn:admin3_code":"9086",
    "gn:asciiname":"Gounari",
    "gn:country_code":"GR",
    "gn:dem":959,
    "gn:feature_class":"P",
    "gn:feature_code":"PPLL",
    "gn:name":"Go\u00fanari",
    "gn:population":0,
    "gn:timezone":"Europe/Athens",
    "iso:country":"GR",
    "name:ell_x_preferred":[
        "Go\u00fanari"
    ],
    "name:ell_x_variant":[
        "\u0393\u03bf\u03cd\u03bd\u03b1\u03c1\u03b7"
    ],
    "wof:name":"Gounari",
    "wof:placetype":"locality"
},
  "geometry": {"coordinates":[21.03929,39.75696],"type":"Point"}
}