{
  "type": "Feature",
  "properties": {
    "gn:admin1_code":"ESYE23",
    "gn:admin2_code":"38.0",
    "gn:admin3_code":"9130",
    "gn:asciiname":"Kalamias",
    "gn:country_code":"GR",
    "gn:dem":433,
    "gn:feature_class":"P",
    "gn:feature_code":"PPL",
    "gn:name":"Kalami\u00e1s",
    "gn:population":0,
    "gn:timezone":"Europe/Athens",
    "iso:country":"GR",
    "name:ell_x_preferred":[
        "Kalami\u00e1s"
    ],
    "name:ell_x_variant":[
        "\u039a\u03b1\u03bb\u03b1\u03bc\u03b9\u03ac\u03c2"
    ],
    "wof:name":"Kalamias",
    "wof:placetype":"locality"
},
  "geometry": {"coordinates":[22.26692,38.14819],"type":"Point"}
}