{
  "type": "Feature",
  "properties": {
    "gn:admin1_code":"ESYE43",
    "gn:admin2_code":"46.0",
    "gn:admin3_code":"9310",
    "gn:asciiname":"Peronides",
    "gn:country_code":"GR",
    "gn:dem":479,
    "gn:feature_class":"P",
    "gn:feature_code":"PPL",
    "gn:name":"Peron\u00eddes",
    "gn:population":5,
    "gn:timezone":"Europe/Athens",
    "iso:country":"GR",
    "name:ell_x_preferred":[
        "\u03a0\u03b5\u03c1\u03bf\u03bd\u03af\u03b4\u03b5\u03c2"
    ],
    "name:eng_x_preferred":[
        "Peronides"
    ],
    "name:und_x_variant":[
        "Peron\u00eddes"
    ],
    "wof:name":"Peronides",
    "wof:placetype":"locality",
    "wof:population":5
},
  "geometry": {"coordinates":[25.63609,35.30455999999999],"type":"Point"}
}