{
  "type": "Feature",
  "properties": {
    "gn:admin1_code":"ESYE23",
    "gn:admin2_code":"39.0",
    "gn:admin3_code":"9136",
    "gn:asciiname":"Pappadou",
    "gn:country_code":"GR",
    "gn:dem":82,
    "gn:feature_class":"P",
    "gn:feature_code":"PPL",
    "gn:name":"Pappado\u00fa",
    "gn:population":0,
    "gn:timezone":"Europe/Athens",
    "iso:country":"GR",
    "name:ell_x_preferred":[
        "Pappado\u00fa"
    ],
    "name:ell_x_variant":[
        "\u03a0\u03b1\u03c0\u03c0\u03b1\u03b4\u03bf\u03cd"
    ],
    "name:und_x_variant":[
        "Pap\u00e1dhou",
        "Pappadho\u00fa"
    ],
    "wof:name":"Pappadou",
    "wof:placetype":"locality"
},
  "geometry": {"coordinates":[21.74353,37.60569],"type":"Point"}
}