{
  "type": "Feature",
  "properties": {
    "gn:gn_country":"GR",
    "gn:gn_fcode":"ADM3",
    "gn:gn_pop":21759,
    "gn:population":21759,
    "iso:country":"GR",
    "name:ell_x_preferred":[
        "\u03a3\u03bf\u03c6\u03ac\u03b4\u03c9\u03bd"
    ],
    "qs_pg:aaroncc":"GR",
    "qs_pg:gn_country":"GR",
    "qs_pg:gn_fcode":"ADM3",
    "qs_pg:gn_pop":21759,
    "qs_pg:name":"Dimos Sofades",
    "qs_pg:photos_9r":0,
    "qs_pg:photos_sr":0,
    "qs_pg:pop_sr":7,
    "qs_pg:qs_pg_placetype":"localadmin",
    "wof:name":"Dimos Sofades",
    "wof:placetype":"localadmin",
    "wof:population":21759
},
  "geometry": {"coordinates":[22.08585,39.23736],"type":"Point"}
}