{
  "type": "Feature",
  "properties": {
    "gn:country":"GR",
    "gn:fcode":"PPL",
    "gn:population":490,
    "iso:country":"GR",
    "name:ell_x_preferred":[
        "\u039a\u03b1\u03c3\u03c4\u03b1\u03bd\u03b9\u03ac"
    ],
    "name:und_x_variant":[
        "Kastan\u00e9a"
    ],
    "qs_pg:aaroncc":"GR",
    "qs_pg:gn_country":"GR",
    "qs_pg:gn_fcode":"PPL",
    "qs_pg:gn_pop":490,
    "qs_pg:name":"Kastani\u00e1",
    "qs_pg:photos_9r":0,
    "qs_pg:photos_sr":0,
    "qs_pg:pop_sr":2,
    "qs_pg:qs_pg_placetype":"locality",
    "wof:name":"Kastani\u00e1",
    "wof:placetype":"locality",
    "wof:population":490
},
  "geometry": {"coordinates":[21.37861,39.71028],"type":"Point"}
}