{
  "type": "Feature",
  "properties": {
    "gn:country":"GR",
    "gn:fcode":"PPL",
    "gn:population":159,
    "iso:country":"GR",
    "name:arz_x_preferred":[
        "\u067e\u0631\u0648\u0633\u064a\u0644\u064a\u0648"
    ],
    "name:ceb_x_preferred":[
        "Pros\u00edlio"
    ],
    "name:ell_x_historical":[
        "\u03a7\u03b1\u03bb\u03ac\u03c3\u03bc\u03b1\u03c4\u03b1",
        "\u0394\u03bf\u03b2\u03af\u03c3\u03b4\u03b9\u03b1\u03bd\u03b1"
    ],
    "name:ell_x_preferred":[
        "\u03a0\u03c1\u03bf\u03c3\u03ae\u03bb\u03b9\u03bf"
    ],
    "name:ell_x_variant":[
        "\u03a0\u03c1\u03bf\u03c3\u03ae\u03bb\u03b9\u03bf\u03bd",
        "\u03a7\u03b1\u03bb\u03ac\u03c3\u03bc\u03b1\u03c4\u03b1",
        "\u0394\u03bf\u03b2\u03af\u03c3\u03b4\u03b9\u03b1\u03bd\u03b1",
        "\u03a0\u03c1\u03bf\u03c3\u03ae\u03bb\u03b9\u03bf \u0399\u03c9\u03b1\u03bd\u03bd\u03af\u03bd\u03c9\u03bd"
    ],
    "name:eng_x_preferred":[
        "Prosilio"
    ],
    "name:nld_x_preferred":[
        "Prosilio"
    ],
    "name:sqi_x_preferred":[
        "Korsacka"
    ],
    "name:swe_x_preferred":[
        "Pros\u00edlio"
    ],
    "qs_pg:aaroncc":"GR",
    "qs_pg:gn_country":"GR",
    "qs_pg:gn_fcode":"PPL",
    "qs_pg:gn_pop":159,
    "qs_pg:name":"Prosilio",
    "qs_pg:name_adm0":"\u0395\u03bb\u03bb\u03ac\u03b4\u03b1",
    "qs_pg:name_adm1":"Epirus and Western Macedonia",
    "qs_pg:photos_9k":1,
    "qs_pg:photos_9r":1,
    "qs_pg:photos_all":1,
    "qs_pg:photos_sr":0,
    "qs_pg:pop_sr":1,
    "qs_pg:qs_pg_placetype":"locality",
    "qs_pg:qs_pg_placetype_gp":"Town",
    "qs_pg:woe_adm0":23424833,
    "woe:adm0_id":23424833,
    "woe:name_adm0":"\u0395\u03bb\u03bb\u03ac\u03b4\u03b1",
    "woe:name_adm1":"Epirus and Western Macedonia",
    "woe:placetype":"Town",
    "wof:name":"Prosilio",
    "wof:placetype":"locality",
    "wof:population":101
},
  "geometry": {"coordinates":[21.085,39.57222],"type":"Point"}
}