{
  "type": "Feature",
  "properties": {
    "gn:admin1_code":"ESYE43",
    "gn:admin2_code":"43.0",
    "gn:admin3_code":"9325",
    "gn:asciiname":"Matthoudiana",
    "gn:country_code":"GR",
    "gn:dem":568,
    "gn:feature_class":"P",
    "gn:feature_code":"PPL",
    "gn:name":"Matthoudian\u00e1",
    "gn:population":0,
    "gn:timezone":"Europe/Athens",
    "iso:country":"GR",
    "name:ell_x_preferred":[
        "Matthoudian\u00e1"
    ],
    "name:ell_x_variant":[
        "\u039c\u03b1\u03c4\u03b8\u03bf\u03c5\u03b4\u03b9\u03b1\u03bd\u03ac"
    ],
    "wof:name":"Matthoudiana",
    "wof:placetype":"locality"
},
  "geometry": {"coordinates":[24.06997,35.40839000000001],"type":"Point"}
}