{
  "type": "Feature",
  "properties": {
    "gn:admin1_code":"ESYE12",
    "gn:admin2_code":"15.0",
    "gn:admin3_code":"9058",
    "gn:asciiname":"Nea Silata",
    "gn:country_code":"GR",
    "gn:dem":56,
    "gn:feature_class":"P",
    "gn:feature_code":"PPL",
    "gn:name":"N\u00e9a S\u00edlata",
    "gn:population":788,
    "gn:timezone":"Europe/Athens",
    "iso:country":"GR",
    "name:ell_x_preferred":[
        "\u039d\u03ad\u03b1 \u03a3\u03af\u03bb\u03b1\u03c4\u03b1"
    ],
    "name:eng_x_preferred":[
        "Nea Silata"
    ],
    "name:und_x_variant":[
        "Karvi\u00e1",
        "N\u00e9a Sill\u00e1ta",
        "N\u00e9a S\u00edlata"
    ],
    "wof:name":"Nea Silata",
    "wof:placetype":"locality",
    "wof:population":788
},
  "geometry": {"coordinates":[23.1336,40.32946],"type":"Point"}
}