{
  "type": "Feature",
  "properties": {
    "gn:country":"GR",
    "gn:fcode":"PPL",
    "gn:population":268,
    "iso:country":"GR",
    "name:ell_x_preferred":[
        "\u0393\u03b5\u03c1\u03b1\u03ba\u03ac\u03c1\u03b9"
    ],
    "name:ell_x_variant":[
        "\u0393\u03b5\u03c1\u03b1\u03ba\u03ac\u03c1\u03b9\u03bf\u03bd"
    ],
    "name:und_x_variant":[
        "Yerak\u00e1rion"
    ],
    "qs_pg:aaroncc":"GR",
    "qs_pg:gn_country":"GR",
    "qs_pg:gn_fcode":"PPL",
    "qs_pg:gn_pop":268,
    "qs_pg:name":"Gerak\u00e1rion",
    "qs_pg:photos_9r":0,
    "qs_pg:photos_sr":0,
    "qs_pg:pop_sr":2,
    "qs_pg:qs_pg_placetype":"locality",
    "wof:name":"Gerak\u00e1rion",
    "wof:placetype":"locality",
    "wof:population":268
},
  "geometry": {"coordinates":[21.845,39.80444],"type":"Point"}
}