{
  "type": "Feature",
  "properties": {
    "gn:gn_country":"GR",
    "gn:gn_fcode":"PPL",
    "gn:gn_pop":190,
    "gn:population":190,
    "iso:country":"GR",
    "name:ell_x_preferred":[
        "\u039c\u03b5\u03bb\u03ac\u03c4\u03b5\u03c2"
    ],
    "name:ell_x_variant":[
        "\u039c\u03b5\u03bb\u03ac\u03c4\u03b1\u03b9"
    ],
    "name:unk_x_variant":[
        "Mel\u00e1tes"
    ],
    "qs_pg:aaroncc":"GR",
    "qs_pg:gn_country":"GR",
    "qs_pg:gn_fcode":"PPL",
    "qs_pg:gn_pop":190,
    "qs_pg:name":"Melatai",
    "qs_pg:name_adm0":"\u0395\u03bb\u03bb\u03ac\u03b4\u03b1",
    "qs_pg:name_adm1":"Epirus and Western Macedonia",
    "qs_pg:photos_9k":1,
    "qs_pg:photos_9r":1,
    "qs_pg:photos_all":1,
    "qs_pg:photos_sr":0,
    "qs_pg:pop_sr":1,
    "qs_pg:qs_pg_placetype":"locality",
    "qs_pg:qs_pg_placetype_gp":"Town",
    "qs_pg:woe_adm0":23424833,
    "woe:adm0_id":23424833,
    "woe:name_adm0":"\u0395\u03bb\u03bb\u03ac\u03b4\u03b1",
    "woe:name_adm1":"Epirus and Western Macedonia",
    "woe:placetype":"Town",
    "wof:name":"Melatai",
    "wof:placetype":"locality",
    "wof:population":190
},
  "geometry": {"coordinates":[21.10306,39.24083],"type":"Point"}
}