{
  "type": "Feature",
  "properties": {
    "gn:admin1_code":"ESYE25",
    "gn:admin2_code":"42.0",
    "gn:admin3_code":"9248",
    "gn:asciiname":"Argilia",
    "gn:country_code":"GR",
    "gn:dem":142,
    "gn:feature_class":"P",
    "gn:feature_code":"PPL",
    "gn:name":"Argili\u00e1",
    "gn:population":19,
    "gn:timezone":"Europe/Athens",
    "iso:country":"GR",
    "name:ell_x_historical":[
        "\u0391\u03c1\u03b3\u03b7\u03bb\u03b9\u03ac"
    ],
    "name:ell_x_preferred":[
        "\u0391\u03c1\u03b3\u03b9\u03bb\u03b9\u03ac"
    ],
    "name:ell_x_variant":[
        "\u0391\u03c1\u03b3\u03b7\u03bb\u03b9\u03ac"
    ],
    "name:eng_x_preferred":[
        "Argilia"
    ],
    "name:und_x_variant":[
        "Aryili\u00e1",
        "Argili\u00e1",
        "Agrili\u00e1"
    ],
    "wof:name":"Argilia",
    "wof:placetype":"locality",
    "wof:population":19
},
  "geometry": {"coordinates":[22.46719,36.59422],"type":"Point"}
}