{
  "type": "Feature",
  "properties": {
    "gn:admin1_code":"ESYE13",
    "gn:admin2_code":"11.0",
    "gn:admin3_code":"9067",
    "gn:asciiname":"Foufas",
    "gn:country_code":"GR",
    "gn:dem":657,
    "gn:feature_class":"P",
    "gn:feature_code":"PPL",
    "gn:name":"Fo\u00fafas",
    "gn:population":0,
    "gn:timezone":"Europe/Athens",
    "iso:country":"GR",
    "name:bul_x_preferred":[
        "\u041f\u0430\u043b\u0435\u043e\u0440"
    ],
    "name:ell_x_preferred":[
        "\u03a6\u03bf\u03cd\u03c6\u03b1\u03c2"
    ],
    "name:ell_x_variant":[
        "\u03a6\u03bf\u03cd\u03c6\u03b1\u03c2 \u039a\u03bf\u03b6\u03ac\u03bd\u03b7\u03c2"
    ],
    "name:mkd_x_preferred":[
        "\u041f\u0430\u043b\u0435\u043e\u0440"
    ],
    "name:und_x_variant":[
        "Palaiokh\u00f3rion",
        "Fo\u00fafas"
    ],
    "wof:name":"Foufas",
    "wof:placetype":"locality"
},
  "geometry": {"coordinates":[21.55683,40.52252],"type":"Point"}
}