{
  "type": "Feature",
  "properties": {
    "gn:admin1_code":"ESYE11",
    "gn:admin2_code":"14.0",
    "gn:admin3_code":"9012",
    "gn:asciiname":"Limnia",
    "gn:country_code":"GR",
    "gn:dem":705,
    "gn:feature_class":"P",
    "gn:feature_code":"PPL",
    "gn:name":"Limni\u00e1",
    "gn:population":35,
    "gn:timezone":"Europe/Athens",
    "iso:country":"GR",
    "name:ell_x_preferred":[
        "\u039b\u03b9\u03bc\u03bd\u03b9\u03ac"
    ],
    "name:eng_x_preferred":[
        "Limnia"
    ],
    "name:und_x_variant":[
        "Limi\u00e1",
        "Suyuj\u00fak",
        "Limni\u00e1"
    ],
    "wof:name":"Limnia",
    "wof:placetype":"locality",
    "wof:population":35
},
  "geometry": {"coordinates":[24.40277,41.08191],"type":"Point"}
}