{
  "type": "Feature",
  "properties": {
    "gn:admin1_code":"ESYE14",
    "gn:admin2_code":"23.0",
    "gn:admin3_code":"9096",
    "gn:asciiname":"Paschalitsa",
    "gn:country_code":"GR",
    "gn:dem":103,
    "gn:feature_class":"P",
    "gn:feature_code":"PPL",
    "gn:name":"Paschal\u00edtsa",
    "gn:population":0,
    "gn:timezone":"Europe/Athens",
    "iso:country":"GR",
    "name:ell_x_preferred":[
        "Paschal\u00edtsa"
    ],
    "name:ell_x_variant":[
        "\u03a0\u03b1\u03c3\u03c7\u03b1\u03bb\u03af\u03c4\u03c3\u03b1"
    ],
    "name:und_x_variant":[
        "So\u00fapi",
        "Paskhal\u00edtsa"
    ],
    "wof:name":"Paschalitsa",
    "wof:placetype":"locality"
},
  "geometry": {"coordinates":[22.20952,39.35562],"type":"Point"}
}