{
  "type": "Feature",
  "properties": {
    "gn:admin1_code":"ESYE25",
    "gn:admin2_code":"37.0",
    "gn:admin3_code":"9246",
    "gn:asciiname":"Korfiotissa",
    "gn:country_code":"GR",
    "gn:dem":682,
    "gn:feature_class":"P",
    "gn:feature_code":"PPL",
    "gn:name":"Korfi\u00f3tissa",
    "gn:population":75,
    "gn:timezone":"Europe/Athens",
    "iso:country":"GR",
    "name:ell_x_preferred":[
        "\u039a\u03bf\u03c1\u03c6\u03b9\u03ce\u03c4\u03b9\u03c3\u03c3\u03b1"
    ],
    "name:eng_x_preferred":[
        "Korfiotissa"
    ],
    "name:und_x_variant":[
        "Ko\u00fatsi",
        "Korfi\u00f3tissa"
    ],
    "wof:name":"Korfiotissa",
    "wof:placetype":"locality",
    "wof:population":75
},
  "geometry": {"coordinates":[22.53094,38.07355],"type":"Point"}
}