{
  "type": "Feature",
  "properties": {
    "gn:country":"GR",
    "gn:fcode":"PPL",
    "gn:population":83,
    "iso:country":"GR",
    "name:ell_x_preferred":[
        "\u03a1\u03cc\u03b3\u03ba\u03b9\u03b1"
    ],
    "name:und_x_variant":[
        "R\u00f3ngia"
    ],
    "qs_pg:aaroncc":"GR",
    "qs_pg:gn_country":"GR",
    "qs_pg:gn_fcode":"PPL",
    "qs_pg:gn_pop":83,
    "qs_pg:name":"R\u00f3gkia",
    "qs_pg:photos_9r":0,
    "qs_pg:photos_sr":0,
    "qs_pg:pop_sr":1,
    "qs_pg:qs_pg_placetype":"locality",
    "wof:name":"R\u00f3gkia",
    "wof:placetype":"locality",
    "wof:population":83
},
  "geometry": {"coordinates":[21.44639,39.21778],"type":"Point"}
}