{
  "type": "Feature",
  "properties": {
    "iso:country":"GR",
    "name:bul_x_preferred":[
        "\u041f\u043e\u043b\u0438\u0444\u0438\u0442\u043e"
    ],
    "name:dut_x_preferred":[
        "Polyfyto"
    ],
    "name:eng_x_preferred":[
        "Polyfyto"
    ],
    "name:gre_x_preferred":[
        "\u03a0\u03bf\u03bb\u03cd\u03c6\u03c5\u03c4\u03bf \u039a\u03bf\u03b6\u03ac\u03bd\u03b7\u03c2"
    ],
    "qs_pg:aaroncc":"GR",
    "qs_pg:name":"Polyfyto",
    "qs_pg:name_adm0":"\u0395\u03bb\u03bb\u03ac\u03b4\u03b1",
    "qs_pg:name_adm1":"Epirus and Western Macedonia",
    "qs_pg:photos":22,
    "qs_pg:photos_1k":4,
    "qs_pg:photos_9k":1,
    "qs_pg:photos_9r":1,
    "qs_pg:photos_all":22,
    "qs_pg:photos_sr":1,
    "qs_pg:pop_sr":0,
    "qs_pg:qs_pg_placetype":"locality",
    "qs_pg:qs_pg_placetype_gp":"Town",
    "qs_pg:woe_adm0":23424833,
    "woe:adm0_id":23424833,
    "woe:name_adm0":"\u0395\u03bb\u03bb\u03ac\u03b4\u03b1",
    "woe:name_adm1":"Epirus and Western Macedonia",
    "woe:placetype":"Town",
    "wof:name":"Polyfyto",
    "wof:placetype":"locality"
},
  "geometry": {"coordinates":[22.12744,40.326294],"type":"Point"}
}