{
  "type": "Feature",
  "properties": {
    "gn:country":"GR",
    "gn:fcode":"PPL",
    "gn:population":87,
    "iso:country":"GR",
    "name:ell_x_preferred":[
        "\u039a\u03b1\u03b2\u03b1\u03bb\u03ac\u03c1\u03b9"
    ],
    "name:ell_x_variant":[
        "\u039a\u03b1\u03b2\u03b1\u03bb\u03bb\u03ac\u03c1\u03b9",
        "\u039a\u03b1\u03b2\u03b1\u03bb\u03bb\u03ac\u03c1\u03b9\u03bf\u03bd"
    ],
    "name:eng_x_preferred":[
        "Kavallari"
    ],
    "name:und_x_variant":[
        "Kavall\u00e1ri"
    ],
    "qs_pg:aaroncc":"GR",
    "qs_pg:gn_country":"GR",
    "qs_pg:gn_fcode":"PPL",
    "qs_pg:gn_pop":87,
    "qs_pg:name":"Kavall\u00e1rion",
    "qs_pg:photos_9r":0,
    "qs_pg:photos_sr":0,
    "qs_pg:pop_sr":1,
    "qs_pg:qs_pg_placetype":"locality",
    "wof:name":"Kavall\u00e1rion",
    "wof:placetype":"locality",
    "wof:population":78
},
  "geometry": {"coordinates":[20.91528,39.74306],"type":"Point"}
}