{
  "type": "Feature",
  "properties": {
    "gn:population":2236,
    "iso:country":"GR",
    "name:ara_x_preferred":[
        "\u0646\u064a\u0643\u064a\u0633\u064a\u0627\u0646\u064a"
    ],
    "name:bul_x_preferred":[
        "\u041d\u0438\u043a\u0438\u0449\u0430\u043d"
    ],
    "name:ceb_x_preferred":[
        "Nik\u00edsiani"
    ],
    "name:ell_x_preferred":[
        "\u039d\u03b9\u03ba\u03ae\u03c3\u03b9\u03b1\u03bd\u03b7"
    ],
    "name:eng_x_preferred":[
        "Nikisiani"
    ],
    "name:mkd_x_preferred":[
        "\u041d\u0438\u043a\u0438\u0448\u0458\u0430\u043d"
    ],
    "name:nno_x_preferred":[
        "Nik\u00edsiani"
    ],
    "name:swe_x_preferred":[
        "Nik\u00edsiani"
    ],
    "name:unk_x_variant":[
        "Nik\u00edsiani"
    ],
    "qs:a0":"Greece",
    "qs:a1":"*\u0391\u039d\u0391\u03a4\u039f\u039b\u0399\u039a\u0397 \u039c\u0391\u039a\u0395\u0394\u039f\u039d\u0399\u0391 \u039a\u0391\u0399 \u0398\u03a1\u0391\u039a\u0397",
    "qs:a1_alt":"ANATOLIKH MAKEDONIA KAI URAKH",
    "qs:a1r":"0",
    "qs:a2_alt":"KABALA",
    "qs:adm0":"Greece",
    "qs:la_lc":"*",
    "qs:level":"locality",
    "qs:loc":"\u039d\u0399\u039a\u0397\u03a3\u0399\u0391\u039d\u0397",
    "qs:loc_alt":"NIKHSIANH",
    "qs:pop":0,
    "qs:type":"buffered point",
    "wof:name":"\u039d\u0399\u039a\u0397\u03a3\u0399\u0391\u039d\u0397",
    "wof:placetype":"locality",
    "wof:population":2236
},
  "geometry": {"coordinates":[24.141804,40.948883],"type":"Point"}
}