{
  "type": "Feature",
  "properties": {
    "gn:admin1_code":"ESYE13",
    "gn:admin2_code":"10.0",
    "gn:admin3_code":"9061",
    "gn:asciiname":"Lagkadakia",
    "gn:country_code":"GR",
    "gn:dem":629,
    "gn:feature_class":"P",
    "gn:feature_code":"PPL",
    "gn:name":"Lagkad\u00e1kia",
    "gn:population":0,
    "gn:timezone":"Europe/Athens",
    "iso:country":"GR",
    "name:ell_x_preferred":[
        "Lagkad\u00e1kia"
    ],
    "name:ell_x_variant":[
        "\u039b\u03b1\u03b3\u03ba\u03b1\u03b4\u03ac\u03ba\u03b9\u03b1"
    ],
    "name:und_x_variant":[
        "Lo\u00fatsisno",
        "Langadh\u00e1kia"
    ],
    "wof:name":"Lagkadakia",
    "wof:placetype":"locality"
},
  "geometry": {"coordinates":[21.52493,40.12278],"type":"Point"}
}