{
  "type": "Feature",
  "properties": {
    "gn:country":"GR",
    "gn:fcode":"PPLA3",
    "gn:population":61888,
    "iso:country":"GR",
    "name:ara_x_preferred":[
        "\u0641\u064a\u0631\u0648\u0646\u0627\u0633"
    ],
    "name:bul_x_preferred":[
        "\u0412\u0438\u0440\u043e\u043d\u0430\u0441"
    ],
    "name:ceb_x_preferred":[
        "V\u00fdronas"
    ],
    "name:ces_x_preferred":[
        "Vyronas"
    ],
    "name:deu_x_preferred":[
        "Vyronas"
    ],
    "name:ell_x_preferred":[
        "\u0392\u03cd\u03c1\u03c9\u03bd"
    ],
    "name:ell_x_variant":[
        "\u0392\u03cd\u03c1\u03c9\u03bd\u03b1\u03c2"
    ],
    "name:fas_x_preferred":[
        "\u0648\u06cc\u0631\u0648\u0646\u0627\u0633"
    ],
    "name:fin_x_preferred":[
        "V\u00fdronas"
    ],
    "name:fra_x_preferred":[
        "V\u00fdronas"
    ],
    "name:ita_x_preferred":[
        "Vironos"
    ],
    "name:lit_x_preferred":[
        "Vironas"
    ],
    "name:nld_x_preferred":[
        "Vyronas"
    ],
    "name:nno_x_preferred":[
        "V\u00fdronas"
    ],
    "name:pol_x_preferred":[
        "Wironas"
    ],
    "name:ron_x_preferred":[
        "Vyron"
    ],
    "name:rus_x_preferred":[
        "\u0412\u0438\u0440\u043e\u043d"
    ],
    "name:srp_x_preferred":[
        "\u0412\u0438\u0440\u043e\u043d\u0430\u0441"
    ],
    "name:swe_x_preferred":[
        "V\u00fdronas"
    ],
    "name:tur_x_preferred":[
        "Vironas"
    ],
    "name:ukr_x_preferred":[
        "\u0412\u0456\u0440\u043e\u043d\u0430\u0441"
    ],
    "name:und_x_variant":[
        "V\u00edron"
    ],
    "name:urd_x_preferred":[
        "\u0648\u06cc\u0631\u0648\u0646\u0627\u0633"
    ],
    "name:vie_x_preferred":[
        "Vyron"
    ],
    "qs_pg:aaroncc":"GR",
    "qs_pg:gn_country":"GR",
    "qs_pg:gn_fcode":"PPLA3",
    "qs_pg:gn_pop":61888,
    "qs_pg:name":"Vyronas",
    "qs_pg:name_adm0":"\u0395\u03bb\u03bb\u03ac\u03b4\u03b1",
    "qs_pg:name_adm1":"Attica",
    "qs_pg:photos":64,
    "qs_pg:photos_1k":13,
    "qs_pg:photos_9k":1,
    "qs_pg:photos_9r":2,
    "qs_pg:photos_all":64,
    "qs_pg:photos_sr":2,
    "qs_pg:pop_sr":8,
    "qs_pg:qs_pg_placetype":"neighbourhood",
    "qs_pg:qs_pg_placetype_gp":"Suburb",
    "qs_pg:woe_adm0":23424833,
    "woe:adm0_id":23424833,
    "woe:name_adm0":"\u0395\u03bb\u03bb\u03ac\u03b4\u03b1",
    "woe:name_adm1":"Attica",
    "woe:placetype":"Suburb",
    "wof:name":"Vyronas",
    "wof:placetype":"neighbourhood",
    "wof:population":61308
},
  "geometry": {"coordinates":[23.75,37.96667],"type":"Point"}
}