{
  "type": "Feature",
  "properties": {
    "gn:gn_country":"GR",
    "gn:gn_fcode":"PPLA3",
    "gn:gn_pop":61888,
    "gn:population":61308,
    "iso:country":"GR",
    "name:ell_x_preferred":[
        "\u0392\u03cd\u03c1\u03c9\u03bd"
    ],
    "name:ell_x_variant":[
        "\u0392\u03cd\u03c1\u03c9\u03bd\u03b1\u03c2"
    ],
    "name:unk_x_variant":[
        "V\u00edron"
    ],
    "qs_pg:aaroncc":"GR",
    "qs_pg:gn_country":"GR",
    "qs_pg:gn_fcode":"PPLA3",
    "qs_pg:gn_pop":61888,
    "qs_pg:name":"Vyronas",
    "qs_pg:name_adm0":"\u0395\u03bb\u03bb\u03ac\u03b4\u03b1",
    "qs_pg:name_adm1":"Attica",
    "qs_pg:photos":64,
    "qs_pg:photos_1k":13,
    "qs_pg:photos_9k":1,
    "qs_pg:photos_9r":2,
    "qs_pg:photos_all":64,
    "qs_pg:photos_sr":2,
    "qs_pg:pop_sr":8,
    "qs_pg:qs_pg_placetype":"neighbourhood",
    "qs_pg:qs_pg_placetype_gp":"Suburb",
    "qs_pg:woe_adm0":23424833,
    "woe:adm0_id":23424833,
    "woe:name_adm0":"\u0395\u03bb\u03bb\u03ac\u03b4\u03b1",
    "woe:name_adm1":"Attica",
    "woe:placetype":"Suburb",
    "wof:name":"Vyronas",
    "wof:placetype":"neighbourhood",
    "wof:population":61308
},
  "geometry": {"coordinates":[23.75,37.96667],"type":"Point"}
}