{
  "type": "Feature",
  "properties": {
    "gn:admin1_code":"ESYE24",
    "gn:admin2_code":"30.0",
    "gn:admin3_code":"9157",
    "gn:asciiname":"Isomata",
    "gn:country_code":"GR",
    "gn:dem":619,
    "gn:feature_class":"P",
    "gn:feature_code":"PPL",
    "gn:name":"Is\u00f3mata",
    "gn:population":15,
    "gn:timezone":"Europe/Athens",
    "iso:country":"GR",
    "name:ell_x_preferred":[
        "\u0399\u03c3\u03ce\u03bc\u03b1\u03c4\u03b1"
    ],
    "wof:name":"Isomata",
    "wof:placetype":"locality",
    "wof:population":15
},
  "geometry": {"coordinates":[21.61745,38.78209],"type":"Point"}
}