{
  "type": "Feature",
  "properties": {
    "gn:admin1_code":"ESYE22",
    "gn:admin2_code":"25.0",
    "gn:admin3_code":"9118",
    "gn:asciiname":"Garnades",
    "gn:country_code":"GR",
    "gn:dem":118,
    "gn:feature_class":"P",
    "gn:feature_code":"PPL",
    "gn:name":"Garn\u00e1des",
    "gn:population":45,
    "gn:timezone":"Europe/Athens",
    "iso:country":"GR",
    "name:ell_x_preferred":[
        "\u0393\u03b1\u03c1\u03bd\u03ac\u03b4\u03b5\u03c2"
    ],
    "name:eng_x_preferred":[
        "Garnades"
    ],
    "wof:name":"Garnades",
    "wof:placetype":"locality",
    "wof:population":45
},
  "geometry": {"coordinates":[19.66248,39.76499],"type":"Point"}
}