{
  "type": "Feature",
  "properties": {
    "gn:gn_country":"GR",
    "gn:gn_fcode":"PPL",
    "gn:gn_pop":436,
    "gn:population":281,
    "iso:country":"GR",
    "name:ell_x_historical":[
        "\u03a4\u03ad\u03c1\u03c1\u03bf\u03b2\u03bf\u03bd",
        "\u03a4\u03ad\u03c1\u03c1\u03bf\u03b2\u03bf"
    ],
    "name:ell_x_preferred":[
        "\u03a4\u03ad\u03c1\u03bf\u03b2\u03bf"
    ],
    "name:ell_x_variant":[
        "\u03a4\u03ad\u03c1\u03bf\u03b2\u03bf\u03bd",
        "\u03a4\u03ad\u03c1\u03c1\u03bf\u03b2\u03bf\u03bd",
        "\u03a4\u03ad\u03c1\u03c1\u03bf\u03b2\u03bf"
    ],
    "name:eng_x_preferred":[
        "Terovo"
    ],
    "name:unk_x_variant":[
        "T\u00e9rrovon"
    ],
    "qs_pg:aaroncc":"GR",
    "qs_pg:gn_country":"GR",
    "qs_pg:gn_fcode":"PPL",
    "qs_pg:gn_pop":436,
    "qs_pg:name":"Terovon",
    "qs_pg:name_adm0":"\u0395\u03bb\u03bb\u03ac\u03b4\u03b1",
    "qs_pg:name_adm1":"Epirus and Western Macedonia",
    "qs_pg:photos_9k":1,
    "qs_pg:photos_9r":1,
    "qs_pg:photos_all":1,
    "qs_pg:photos_sr":0,
    "qs_pg:pop_sr":2,
    "qs_pg:qs_pg_placetype":"locality",
    "qs_pg:qs_pg_placetype_gp":"Town",
    "qs_pg:woe_adm0":23424833,
    "woe:adm0_id":23424833,
    "woe:name_adm0":"\u0395\u03bb\u03bb\u03ac\u03b4\u03b1",
    "woe:name_adm1":"Epirus and Western Macedonia",
    "woe:placetype":"Town",
    "wof:name":"Terovon",
    "wof:placetype":"locality",
    "wof:population":281
},
  "geometry": {"coordinates":[20.87417,39.41111],"type":"Point"}
}