{
  "type": "Feature",
  "properties": {
    "gn:gn_country":"GR",
    "gn:gn_fcode":"PPL",
    "gn:gn_pop":1498,
    "gn:population":1218,
    "iso:country":"GR",
    "name:ell_x_preferred":[
        "\u03a7\u03ce\u03c1\u03b1"
    ],
    "name:eng_x_preferred":[
        "Chora"
    ],
    "name:unk_x_variant":[
        "Kh\u00f3ra"
    ],
    "qs_pg:aaroncc":"GR",
    "qs_pg:gn_country":"GR",
    "qs_pg:gn_fcode":"PPL",
    "qs_pg:gn_pop":1498,
    "qs_pg:name":"Ch\u00f3ra",
    "qs_pg:photos_9r":0,
    "qs_pg:photos_sr":0,
    "qs_pg:pop_sr":3,
    "qs_pg:qs_pg_placetype":"locality",
    "wof:name":"Ch\u00f3ra",
    "wof:placetype":"locality",
    "wof:population":1218
},
  "geometry": {"coordinates":[26.90556,37.70361],"type":"Point"}
}