{
  "type": "Feature",
  "properties": {
    "gn:country":"GR",
    "gn:fcode":"ADM3",
    "gn:population":17752,
    "iso:country":"GR",
    "name:ell_x_preferred":[
        "\u0391\u03c1\u03b9\u03c3\u03c4\u03bf\u03c4\u03ad\u03bb\u03b7"
    ],
    "qs_pg:aaroncc":"GR",
    "qs_pg:gn_country":"GR",
    "qs_pg:gn_fcode":"ADM3",
    "qs_pg:gn_pop":17752,
    "qs_pg:name":"Dimos Aristotelis",
    "qs_pg:photos_9r":0,
    "qs_pg:photos_sr":0,
    "qs_pg:pop_sr":6,
    "qs_pg:qs_pg_placetype":"localadmin",
    "wof:name":"Dimos Aristotelis",
    "wof:placetype":"localadmin",
    "wof:population":17752
},
  "geometry": {"coordinates":[23.7236,40.48309],"type":"Point"}
}