{
  "type": "Feature",
  "properties": {
    "gn:admin1_code":"ESYE25",
    "gn:admin2_code":"40.0",
    "gn:admin3_code":"9258",
    "gn:asciiname":"Kato Kopanaki",
    "gn:country_code":"GR",
    "gn:dem":168,
    "gn:feature_class":"P",
    "gn:feature_code":"PPL",
    "gn:name":"K\u00e1to Kopan\u00e1ki",
    "gn:population":0,
    "gn:timezone":"Europe/Athens",
    "iso:country":"GR",
    "name:ell_x_preferred":[
        "\u039a\u03ac\u03c4\u03c9 \u039a\u03bf\u03c0\u03b1\u03bd\u03ac\u03ba\u03b9"
    ],
    "name:ell_x_variant":[
        "\u039a\u03ac\u03c4\u03c9 \u039a\u03bf\u03c0\u03b1\u03bd\u03ac\u03ba\u03b9\u03bf\u03bd"
    ],
    "name:und_x_variant":[
        "K\u00e1to Kopan\u00e1ki",
        "K\u00e1to Kopan\u00e1kion"
    ],
    "wof:name":"Kato Kopanaki",
    "wof:placetype":"locality"
},
  "geometry": {"coordinates":[21.81079,37.2837],"type":"Point"}
}