{
  "type": "Feature",
  "properties": {
    "gn:gn_country":"GR",
    "gn:gn_fcode":"PPL",
    "gn:gn_pop":94,
    "gn:population":94,
    "iso:country":"GR",
    "name:ell_x_preferred":[
        "\u03a0\u03ad\u03c1\u03b1 \u039d\u03b5\u03b2\u03c1\u03cc\u03c0\u03bf\u03bb\u03b7"
    ],
    "name:ell_x_variant":[
        "\u03a0\u03ad\u03c1\u03b1 \u039d\u03b5\u03b2\u03c1\u03cc\u03c0\u03bf\u03bb\u03b9\u03c2"
    ],
    "name:unk_x_variant":[
        "P\u00e9ra Nevr\u00f3poli"
    ],
    "qs_pg:aaroncc":"GR",
    "qs_pg:gn_country":"GR",
    "qs_pg:gn_fcode":"PPL",
    "qs_pg:gn_pop":94,
    "qs_pg:name":"P\u00e9ra Nevr\u00f3polis",
    "qs_pg:photos_9r":0,
    "qs_pg:photos_sr":0,
    "qs_pg:pop_sr":1,
    "qs_pg:qs_pg_placetype":"locality",
    "wof:name":"P\u00e9ra Nevr\u00f3polis",
    "wof:placetype":"locality",
    "wof:population":94
},
  "geometry": {"coordinates":[21.23917,39.33556],"type":"Point"}
}