{
  "type": "Feature",
  "properties": {
    "gn:admin1_code":"ESYE24",
    "gn:admin2_code":"29.0",
    "gn:admin3_code":"9163",
    "gn:asciiname":"Ayia Trias",
    "gn:country_code":"GR",
    "gn:dem":13,
    "gn:feature_class":"P",
    "gn:feature_code":"PPL",
    "gn:name":"Ay\u00eda Tri\u00e1s",
    "gn:population":282,
    "gn:timezone":"Europe/Athens",
    "iso:country":"GR",
    "name:ell_x_preferred":[
        "\u0391\u03b3\u03af\u03b1 \u03a4\u03c1\u03b9\u03ac\u03b4\u03b1"
    ],
    "name:eng_x_preferred":[
        "Agia Triada"
    ],
    "wof:name":"Ayia Trias",
    "wof:placetype":"locality",
    "wof:population":282
},
  "geometry": {"coordinates":[22.60244,38.8162],"type":"Point"}
}