{
  "type": "Feature",
  "properties": {
    "gn:admin1_code":"ESYE43",
    "gn:admin2_code":"44.0",
    "gn:admin3_code":"9318",
    "gn:asciiname":"Charkia",
    "gn:country_code":"GR",
    "gn:dem":525,
    "gn:feature_class":"P",
    "gn:feature_code":"PPL",
    "gn:name":"Ch\u00e1rkia",
    "gn:population":62,
    "gn:timezone":"Europe/Athens",
    "iso:country":"GR",
    "name:ell_x_preferred":[
        "\u03a7\u03ac\u03c1\u03ba\u03b9\u03b1"
    ],
    "name:eng_x_preferred":[
        "Charkia"
    ],
    "name:und_x_variant":[
        "Ch\u00e1rkia",
        "Kh\u00e1rkia"
    ],
    "wof:name":"Charkia",
    "wof:placetype":"locality",
    "wof:population":62
},
  "geometry": {"coordinates":[24.58745,35.30749],"type":"Point"}
}