{
  "type": "Feature",
  "properties": {
    "gn:country":"GR",
    "gn:fcode":"PPL",
    "gn:population":259,
    "iso:country":"GR",
    "name:ell_x_preferred":[
        "Kalogrian\u00ed"
    ],
    "name:ell_x_variant":[
        "\u039a\u03b1\u03bb\u03bf\u03b3\u03c1\u03b9\u03b1\u03bd\u03ae"
    ],
    "qs_pg:aaroncc":"GR",
    "qs_pg:gn_country":"GR",
    "qs_pg:gn_fcode":"PPL",
    "qs_pg:gn_pop":259,
    "qs_pg:name":"Kalogriani",
    "qs_pg:name_adm0":"\u0395\u03bb\u03bb\u03ac\u03b4\u03b1",
    "qs_pg:name_adm1":"Thessaly and Continental Greece",
    "qs_pg:photos_9r":0,
    "qs_pg:photos_sr":0,
    "qs_pg:pop_sr":2,
    "qs_pg:qs_pg_placetype":"locality",
    "qs_pg:qs_pg_placetype_gp":"Town",
    "qs_pg:woe_adm0":23424833,
    "woe:adm0_id":23424833,
    "woe:name_adm0":"\u0395\u03bb\u03bb\u03ac\u03b4\u03b1",
    "woe:name_adm1":"Thessaly and Continental Greece",
    "woe:placetype":"Town",
    "wof:name":"Kalogriani",
    "wof:placetype":"locality",
    "wof:population":259
},
  "geometry": {"coordinates":[21.48694,39.64806],"type":"Point"}
}