{
  "type": "Feature",
  "properties": {
    "gn:gn_country":"GR",
    "gn:gn_fcode":"PPL",
    "gn:gn_pop":87,
    "gn:population":87,
    "iso:country":"GR",
    "name:ell_x_preferred":[
        "\u03a7\u03b1\u03c1\u03b1\u03c5\u03b3\u03ae"
    ],
    "name:unk_x_variant":[
        "L\u00edkosse"
    ],
    "qs_pg:aaroncc":"GR",
    "qs_pg:gn_country":"GR",
    "qs_pg:gn_fcode":"PPL",
    "qs_pg:gn_pop":87,
    "qs_pg:name":"Charavg\u00ed",
    "qs_pg:photos_9r":0,
    "qs_pg:photos_sr":0,
    "qs_pg:pop_sr":1,
    "qs_pg:qs_pg_placetype":"locality",
    "wof:name":"Charavg\u00ed",
    "wof:placetype":"locality",
    "wof:population":87
},
  "geometry": {"coordinates":[20.47444,39.68972],"type":"Point"}
}