{
  "type": "Feature",
  "properties": {
    "gn:admin1_code":"ESYE21",
    "gn:admin2_code":"17.0",
    "gn:admin3_code":"9081",
    "gn:asciiname":"Taksiarchis",
    "gn:country_code":"GR",
    "gn:dem":692,
    "gn:feature_class":"P",
    "gn:feature_code":"PPL",
    "gn:name":"Taksi\u00e1rchis",
    "gn:population":98,
    "gn:timezone":"Europe/Athens",
    "iso:country":"GR",
    "name:ell_x_preferred":[
        "\u03a4\u03b1\u03be\u03b9\u03ac\u03c1\u03c7\u03b7\u03c2"
    ],
    "name:eng_x_preferred":[
        "Taksiarchis"
    ],
    "wof:name":"Taksiarchis",
    "wof:placetype":"locality",
    "wof:population":98
},
  "geometry": {"coordinates":[20.90179,39.55991],"type":"Point"}
}