{
  "type": "Feature",
  "properties": {
    "gn:gn_country":"GR",
    "gn:gn_fcode":"ADM3",
    "gn:gn_pop":13451,
    "gn:population":13451,
    "iso:country":"GR",
    "name:ara_x_preferred":[
        "\u062b\u0627\u0633\u0648\u0633"
    ],
    "name:bel_x_preferred":[
        "\u0422\u0430\u0441\u0430\u0441"
    ],
    "name:bre_x_preferred":[
        "Enez Thasos"
    ],
    "name:bul_x_preferred":[
        "\u0422\u0430\u0441\u043e\u0441"
    ],
    "name:cat_x_preferred":[
        "Tassos"
    ],
    "name:ceb_x_preferred":[
        "Nis\u00ed Th\u00e1sos"
    ],
    "name:ces_x_preferred":[
        "Thasos"
    ],
    "name:dan_x_preferred":[
        "Thassos"
    ],
    "name:deu_x_preferred":[
        "Thasos"
    ],
    "name:ell_x_preferred":[
        "\u0398\u03ac\u03c3\u03bf\u03c5"
    ],
    "name:ell_x_variant":[
        "\u0398\u03ac\u03c3\u03bf\u03c2"
    ],
    "name:eng_x_preferred":[
        "Thassos"
    ],
    "name:est_x_preferred":[
        "Th\u00e1sose saar"
    ],
    "name:eus_x_preferred":[
        "Tasos"
    ],
    "name:fas_x_preferred":[
        "\u062a\u0627\u0633\u0648\u0633"
    ],
    "name:fin_x_preferred":[
        "Th\u00e1sos"
    ],
    "name:fra_x_preferred":[
        "Thasos"
    ],
    "name:glg_x_preferred":[
        "Thasos"
    ],
    "name:hun_x_preferred":[
        "Th\u00e1szosz"
    ],
    "name:hye_x_preferred":[
        "\u0539\u0561\u057d\u0578\u057d"
    ],
    "name:ind_x_preferred":[
        "Thasos"
    ],
    "name:ita_x_preferred":[
        "Taso"
    ],
    "name:jpn_x_preferred":[
        "\u30bf\u30bd\u30b9\u5cf6"
    ],
    "name:kor_x_preferred":[
        "\ud0c0\uc18c\uc2a4\uc12c"
    ],
    "name:lat_x_preferred":[
        "Thasos"
    ],
    "name:lit_x_preferred":[
        "Tasas"
    ],
    "name:mal_x_preferred":[
        "\u0d24\u0d3e\u0d38\u0d38\u0d4d"
    ],
    "name:mkd_x_preferred":[
        "\u0422\u0430\u0441\u043e\u0441"
    ],
    "name:nld_x_preferred":[
        "Thasos"
    ],
    "name:nno_x_preferred":[
        "Th\u00e1sos"
    ],
    "name:nor_x_preferred":[
        "Thasos"
    ],
    "name:pol_x_preferred":[
        "Tasos"
    ],
    "name:por_x_preferred":[
        "Tasos"
    ],
    "name:ron_x_preferred":[
        "Thasos"
    ],
    "name:rus_x_preferred":[
        "\u0422\u0430\u0441\u043e\u0441"
    ],
    "name:sco_x_preferred":[
        "Thasos"
    ],
    "name:slk_x_preferred":[
        "Thasos"
    ],
    "name:spa_x_preferred":[
        "Tasos"
    ],
    "name:sqi_x_preferred":[
        "Tash\u00ebzi"
    ],
    "name:srp_x_preferred":[
        "\u0422\u0430\u0441\u043e\u0441"
    ],
    "name:swe_x_preferred":[
        "Thassos"
    ],
    "name:tur_x_preferred":[
        "Ta\u015foz"
    ],
    "name:ukr_x_preferred":[
        "\u0422\u0430\u0441\u043e\u0441"
    ],
    "name:urd_x_preferred":[
        "\u062a\u06be\u0627\u0633\u0648\u0633"
    ],
    "name:vie_x_preferred":[
        "Thasos"
    ],
    "name:zho_x_preferred":[
        "\u8428\u7d22\u65af\u5c9b"
    ],
    "qs_pg:aaroncc":"GR",
    "qs_pg:gn_country":"GR",
    "qs_pg:gn_fcode":"ADM3",
    "qs_pg:gn_pop":13451,
    "qs_pg:name":"Thasos",
    "qs_pg:photos_9r":0,
    "qs_pg:photos_sr":0,
    "qs_pg:pop_sr":6,
    "qs_pg:qs_pg_placetype":"localadmin",
    "wof:name":"Thasos",
    "wof:placetype":"localadmin",
    "wof:population":13451
},
  "geometry": {"coordinates":[24.65323,40.68531],"type":"Point"}
}