{
  "type": "Feature",
  "properties": {
    "gn:gn_country":"GR",
    "gn:gn_fcode":"ADM3",
    "gn:gn_pop":13451,
    "gn:population":13451,
    "iso:country":"GR",
    "name:ell_x_preferred":[
        "\u0398\u03ac\u03c3\u03bf\u03c5"
    ],
    "name:ell_x_variant":[
        "\u0398\u03ac\u03c3\u03bf\u03c2"
    ],
    "name:eng_x_preferred":[
        "Thassos"
    ],
    "qs_pg:aaroncc":"GR",
    "qs_pg:gn_country":"GR",
    "qs_pg:gn_fcode":"ADM3",
    "qs_pg:gn_pop":13451,
    "qs_pg:name":"Thasos",
    "qs_pg:photos_9r":0,
    "qs_pg:photos_sr":0,
    "qs_pg:pop_sr":6,
    "qs_pg:qs_pg_placetype":"localadmin",
    "wof:name":"Thasos",
    "wof:placetype":"localadmin",
    "wof:population":13451
},
  "geometry": {"coordinates":[24.65323,40.68531],"type":"Point"}
}