{
  "type": "Feature",
  "properties": {
    "gn:admin1_code":"ESYE23",
    "gn:admin2_code":"38.0",
    "gn:admin3_code":"9130",
    "gn:asciiname":"Vounaki",
    "gn:country_code":"GR",
    "gn:dem":1076,
    "gn:feature_class":"P",
    "gn:feature_code":"PPL",
    "gn:name":"Voun\u00e1ki",
    "gn:population":0,
    "gn:timezone":"Europe/Athens",
    "iso:country":"GR",
    "name:ell_x_preferred":[
        "\u0392\u03bf\u03c5\u03bd\u03ac\u03ba\u03b9"
    ],
    "name:ell_x_variant":[
        "\u0392\u03bf\u03c5\u03bd\u03ac\u03ba\u03b9\u03bf\u03bd"
    ],
    "name:und_x_variant":[
        "Voun\u00e1ki",
        "Voun\u00e1kion"
    ],
    "wof:name":"Vounaki",
    "wof:placetype":"locality"
},
  "geometry": {"coordinates":[22.26581,38.02075],"type":"Point"}
}