{
  "type": "Feature",
  "properties": {
    "gn:admin1_code":"ESYE13",
    "gn:admin2_code":"9.0",
    "gn:admin3_code":"9065",
    "gn:asciiname":"Kremasto",
    "gn:country_code":"GR",
    "gn:dem":725,
    "gn:feature_class":"P",
    "gn:feature_code":"PPL",
    "gn:name":"Kremast\u00f3",
    "gn:population":9,
    "gn:timezone":"Europe/Athens",
    "iso:country":"GR",
    "name:ell_x_preferred":[
        "\u039a\u03c1\u03b5\u03bc\u03b1\u03c3\u03c4\u03cc"
    ],
    "name:eng_x_preferred":[
        "Kremasto"
    ],
    "name:und_x_variant":[
        "Kremast\u00f3"
    ],
    "wof:name":"Kremasto",
    "wof:placetype":"locality",
    "wof:population":9
},
  "geometry": {"coordinates":[21.24772,40.43752],"type":"Point"}
}