{
  "type": "Feature",
  "properties": {
    "gn:admin1_code":"ESYE13",
    "gn:admin2_code":"9.0",
    "gn:admin3_code":"9063",
    "gn:asciiname":"Pentavryso",
    "gn:country_code":"GR",
    "gn:dem":783,
    "gn:feature_class":"P",
    "gn:feature_code":"PPL",
    "gn:name":"Pent\u00e1vryso",
    "gn:population":599,
    "gn:timezone":"Europe/Athens",
    "iso:country":"GR",
    "name:bul_x_preferred":[
        "\u0416\u0435\u043b\u0435\u0433\u043e\u0436\u0435"
    ],
    "name:ceb_x_preferred":[
        "Pent\u00e1vryso"
    ],
    "name:ell_x_historical":[
        "\u0396\u03b5\u03bb\u03b9\u03b3\u03ba\u03cc\u03c3\u03b4\u03b7"
    ],
    "name:ell_x_preferred":[
        "\u03a0\u03b5\u03bd\u03c4\u03ac\u03b2\u03c1\u03c5\u03c3\u03bf"
    ],
    "name:ell_x_variant":[
        "\u03a0\u03b5\u03bd\u03c4\u03ac\u03b2\u03c1\u03c5\u03c3\u03bf\u03bd",
        "\u03a0\u03b5\u03bd\u03c4\u03ac\u03b2\u03c1\u03c5\u03c3\u03bf\u03c2",
        "\u0396\u03b5\u03bb\u03b9\u03b3\u03ba\u03cc\u03c3\u03b4\u03b7",
        "\u03a0\u03b5\u03bd\u03c4\u03ac\u03b2\u03c1\u03c5\u03c3\u03bf \u039a\u03b1\u03c3\u03c4\u03bf\u03c1\u03b9\u03ac\u03c2"
    ],
    "name:eng_x_preferred":[
        "Pentavryso"
    ],
    "name:mkd_x_preferred":[
        "\u0416\u0435\u043b\u043e\u0433\u043e\u0436\u0435"
    ],
    "name:sqi_x_preferred":[
        "Zelegozhdi"
    ],
    "name:swe_x_preferred":[
        "Pent\u00e1vryso"
    ],
    "name:und_x_variant":[
        "Zeleg\u00f3sdi",
        "Pend\u00e1vrison",
        "Pent\u00e1vryson"
    ],
    "wof:name":"Pentavryso",
    "wof:placetype":"locality",
    "wof:population":599
},
  "geometry": {"coordinates":[21.14216,40.45376],"type":"Point"}
}