{
  "type": "Feature",
  "properties": {
    "gn:admin1_code":"ESYE43",
    "gn:admin2_code":"45.0",
    "gn:admin3_code":"9303",
    "gn:asciiname":"Sikologos",
    "gn:country_code":"GR",
    "gn:dem":562,
    "gn:feature_class":"P",
    "gn:feature_code":"PPL",
    "gn:name":"Sikol\u00f3gos",
    "gn:population":0,
    "gn:timezone":"Europe/Athens",
    "iso:country":"GR",
    "name:ell_x_preferred":[
        "\u03a3\u03c5\u03ba\u03bf\u03bb\u03cc\u03b3\u03bf\u03c2 \u0397\u03c1\u03b1\u03ba\u03bb\u03b5\u03af\u03bf\u03c5"
    ],
    "name:pol_x_preferred":[
        "Sikologos"
    ],
    "wof:name":"Sikologos",
    "wof:placetype":"locality"
},
  "geometry": {"coordinates":[25.51283,35.01942],"type":"Point"}
}