{
  "type": "Feature",
  "properties": {
    "gn:population":1378,
    "iso:country":"GR",
    "name:ara_x_preferred":[
        "\u0628\u064a\u0631\u064a\u0641\u0648\u0644\u064a\u0648\u0646"
    ],
    "name:deu_x_preferred":[
        "Perivoli"
    ],
    "name:dut_x_preferred":[
        "Perivoli"
    ],
    "name:ell_x_preferred":[
        "\u03a0\u03b5\u03c1\u03b9\u03b2\u03cc\u03bb\u03b9 \u039a\u03ad\u03c1\u03ba\u03c5\u03c1\u03b1\u03c2"
    ],
    "name:ell_x_variant":[
        "\u03a0\u03b5\u03c1\u03b9\u03b2\u03cc\u03bb\u03b9\u03bf\u03bd",
        "\u03a0\u03b5\u03c1\u03b9\u03b2\u03cc\u03bb\u03b9"
    ],
    "name:eng_x_preferred":[
        "Perivoli"
    ],
    "name:ger_x_preferred":[
        "Perivoli"
    ],
    "name:gre_x_preferred":[
        "\u03a0\u03b5\u03c1\u03b9\u03b2\u03cc\u03bb\u03b9 \u039a\u03ad\u03c1\u03ba\u03c5\u03c1\u03b1\u03c2"
    ],
    "name:swe_x_preferred":[
        "Periv\u00f3li"
    ],
    "name:unk_x_variant":[
        "Periv\u00f3li"
    ],
    "qs:a0":"Greece",
    "qs:a1":"*\u0399\u039f\u039d\u0399\u0391 \u039d\u0397\u03a3\u0399\u0391",
    "qs:a1_alt":"IONIA NHSIA",
    "qs:a1r":"0",
    "qs:a2_alt":"KERKYRA",
    "qs:adm0":"Greece",
    "qs:la_lc":"*",
    "qs:level":"locality",
    "qs:loc":"\u03a0\u0395\u03a1\u0399\u0392\u039f\u039b\u0399\u039f\u039d",
    "qs:loc_alt":"PERIBOLION",
    "qs:pop":0,
    "qs:type":"buffered point",
    "wd:wordcount":135,
    "wof:name":"\u03a0\u0395\u03a1\u0399\u0392\u039f\u039b\u0399\u039f\u039d",
    "wof:placetype":"locality",
    "wof:population":1378
},
  "geometry": {"coordinates":[20.018173,39.419254],"type":"Point"}
}