{
  "type": "Feature",
  "properties": {
    "gn:admin1_code":"ESYE14",
    "gn:admin2_code":"24.0",
    "gn:admin3_code":"9104",
    "gn:asciiname":"Neokhorakion",
    "gn:country_code":"GR",
    "gn:dem":317,
    "gn:feature_class":"P",
    "gn:feature_code":"PPL",
    "gn:name":"Neokhor\u00e1kion",
    "gn:population":118,
    "gn:timezone":"Europe/Athens",
    "iso:country":"GR",
    "name:ell_x_historical":[
        "\u0399\u03bd\u03c4\u03b6\u03ad\u03ba"
    ],
    "name:ell_x_preferred":[
        "\u039d\u03b5\u03bf\u03c7\u03c9\u03c1\u03ac\u03ba\u03b9"
    ],
    "name:ell_x_variant":[
        "\u0399\u03bd\u03c4\u03b6\u03ad\u03ba",
        "\u039d\u03b5\u03bf\u03c7\u03c9\u03c1\u03ac\u03ba\u03b9\u03bf\u03bd"
    ],
    "name:eng_x_preferred":[
        "Neochoraki"
    ],
    "name:und_x_variant":[
        "Ij\u00e9ki",
        "Neokhor\u00e1ki",
        "Neokhor\u00e1kion"
    ],
    "wof:name":"Neokhorakion",
    "wof:placetype":"locality",
    "wof:population":118
},
  "geometry": {"coordinates":[22.61973,39.16823],"type":"Point"}
}