{
  "type": "Feature",
  "properties": {
    "gn:admin1_code":"ESYE22",
    "gn:admin2_code":"26.0",
    "gn:admin3_code":"9121",
    "gn:asciiname":"Lazarata",
    "gn:country_code":"GR",
    "gn:dem":421,
    "gn:feature_class":"P",
    "gn:feature_code":"PPL",
    "gn:name":"Lazar\u00e1ta",
    "gn:population":526,
    "gn:timezone":"Europe/Athens",
    "iso:country":"GR",
    "name:ell_x_preferred":[
        "\u039b\u03b1\u03b6\u03b1\u03c1\u03ac\u03c4\u03b1"
    ],
    "name:eng_x_preferred":[
        "Lazarata"
    ],
    "name:und_x_variant":[
        "Lazar\u00e1ta"
    ],
    "wof:name":"Lazarata",
    "wof:placetype":"locality",
    "wof:population":526
},
  "geometry": {"coordinates":[20.6676,38.77771],"type":"Point"}
}