{
  "type": "Feature",
  "properties": {
    "gn:admin1_code":"ESYE31",
    "gn:admin2_code":"406101.0",
    "gn:admin3_code":"9209",
    "gn:asciiname":"Potamos Antikythiron",
    "gn:country_code":"GR",
    "gn:dem":12,
    "gn:feature_class":"P",
    "gn:feature_code":"PPL",
    "gn:name":"Potam\u00f3s Antikyth\u00edron",
    "gn:population":34,
    "gn:timezone":"Europe/Athens",
    "iso:country":"GR",
    "name:ell_x_preferred":[
        "\u03a0\u03bf\u03c4\u03b1\u03bc\u03cc\u03c2 \u0391\u03bd\u03c4\u03b9\u03ba\u03c5\u03b8\u03ae\u03c1\u03c9\u03bd"
    ],
    "name:ell_x_variant":[
        "Potam\u00f3s",
        "\u03a0\u03bf\u03c4\u03b1\u03bc\u03cc\u03c2"
    ],
    "name:eng_x_preferred":[
        "Potamos Antikythiron"
    ],
    "wof:name":"Potamos Antikythiron",
    "wof:placetype":"locality",
    "wof:population":34
},
  "geometry": {"coordinates":[23.28902,35.88159],"type":"Point"}
}