{
  "type": "Feature",
  "properties": {
    "gn:population":971,
    "iso:country":"GR",
    "name:ell_x_preferred":[
        "\u0386\u03b3\u03b9\u03bf\u03c2 \u03a3\u03c0\u03c5\u03c1\u03af\u03b4\u03c9\u03bd"
    ],
    "name:ell_x_variant":[
        "\u0386\u03b3\u03b9\u03bf\u03c2 \u03a3\u03c0\u03c5\u03c1\u03af\u03b4\u03c9\u03bd\u03b1\u03c2"
    ],
    "name:eng_x_preferred":[
        "Agios Spyridon"
    ],
    "name:unk_x_variant":[
        "Im\u00e1m Cha\u00fcs"
    ],
    "qs:a0":"Greece",
    "qs:a1":"*\u0397\u03a0\u0395\u0399\u03a1\u039f\u03a3",
    "qs:a1_alt":"HPEIROS",
    "qs:a1r":"0",
    "qs:a2_alt":"ARTA",
    "qs:adm0":"Greece",
    "qs:la_lc":"*",
    "qs:level":"locality",
    "qs:loc":"\u0391\u0393\u0399\u039f\u03a3 \u03a3\u03a0\u03a5\u03a1\u0399\u0394\u03a9\u039d",
    "qs:loc_alt":"AGIOS SPYRIDVN",
    "qs:pop":0,
    "qs:type":"buffered point",
    "wof:name":"\u0391\u0393\u0399\u039f\u03a3 \u03a3\u03a0\u03a5\u03a1\u0399\u0394\u03a9\u039d",
    "wof:placetype":"locality",
    "wof:population":971
},
  "geometry": {"coordinates":[20.864601,39.144794],"type":"Point"}
}