{
  "type": "Feature",
  "properties": {
    "gn:admin1_code":"ESYE23",
    "gn:admin2_code":"38.0",
    "gn:admin3_code":"9132",
    "gn:asciiname":"Katsaitaiika",
    "gn:country_code":"GR",
    "gn:dem":955,
    "gn:feature_class":"P",
    "gn:feature_code":"PPL",
    "gn:name":"Katsa\u00efta\u00edika",
    "gn:population":0,
    "gn:timezone":"Europe/Athens",
    "iso:country":"GR",
    "name:ell_x_preferred":[
        "\u039a\u03b1\u03c4\u03c3\u03b1\u03ca\u03c4\u03b1\u03af\u03b9\u03ba\u03b1"
    ],
    "name:und_x_variant":[
        "Katsait\u00e9\u00efka",
        "Katsa\u00efta\u00edika"
    ],
    "wof:name":"Katsaitaiika",
    "wof:placetype":"locality"
},
  "geometry": {"coordinates":[21.89061,38.11783],"type":"Point"}
}