{
  "type": "Feature",
  "properties": {
    "gn:admin1_code":"ESYE25",
    "gn:admin2_code":"42.0",
    "gn:admin3_code":"9248",
    "gn:asciiname":"Sotiras",
    "gn:country_code":"GR",
    "gn:dem":364,
    "gn:feature_class":"P",
    "gn:feature_code":"PPL",
    "gn:name":"Sot\u00edras",
    "gn:population":28,
    "gn:timezone":"Europe/Athens",
    "iso:country":"GR",
    "name:ell_x_preferred":[
        "\u03a3\u03c9\u03c4\u03ae\u03c1\u03b1\u03c2"
    ],
    "name:eng_x_preferred":[
        "Sotiras"
    ],
    "name:und_x_variant":[
        "Kousko\u00fani",
        "Kousko\u00fanion",
        "Sot\u00edras"
    ],
    "wof:name":"Sotiras",
    "wof:placetype":"locality",
    "wof:population":28
},
  "geometry": {"coordinates":[22.39194,36.67064],"type":"Point"}
}