{
  "type": "Feature",
  "properties": {
    "gn:admin1_code":"ESYE43",
    "gn:admin2_code":"45.0",
    "gn:admin3_code":"9303",
    "gn:asciiname":"Faflagkos",
    "gn:country_code":"GR",
    "gn:dem":18,
    "gn:feature_class":"P",
    "gn:feature_code":"PPL",
    "gn:name":"Fafl\u00e1gkos",
    "gn:population":0,
    "gn:timezone":"Europe/Athens",
    "iso:country":"GR",
    "name:ell_x_preferred":[
        "Fafl\u00e1gkos"
    ],
    "name:ell_x_variant":[
        "\u03a6\u03b1\u03c6\u03bb\u03ac\u03b3\u03ba\u03bf\u03c2"
    ],
    "wof:name":"Faflagkos",
    "wof:placetype":"locality"
},
  "geometry": {"coordinates":[25.47538,34.99064],"type":"Point"}
}