{
  "type": "Feature",
  "properties": {
    "gn:admin1_code":"ESYE22",
    "gn:admin2_code":"25.0",
    "gn:admin3_code":"9118",
    "gn:asciiname":"Riliatika",
    "gn:country_code":"GR",
    "gn:dem":145,
    "gn:feature_class":"P",
    "gn:feature_code":"PPL",
    "gn:name":"Rili\u00e1tika",
    "gn:population":32,
    "gn:timezone":"Europe/Athens",
    "iso:country":"GR",
    "name:ell_x_preferred":[
        "\u03a1\u03b9\u03bb\u03b9\u03ac\u03c4\u03b9\u03ba\u03b1"
    ],
    "name:eng_x_preferred":[
        "Riliatika"
    ],
    "wof:name":"Riliatika",
    "wof:placetype":"locality",
    "wof:population":32
},
  "geometry": {"coordinates":[19.84607,39.791],"type":"Point"}
}