{
  "type": "Feature",
  "properties": {
    "gn:admin1_code":"ESYE43",
    "gn:admin2_code":"43.0",
    "gn:admin3_code":"9321",
    "gn:asciiname":"Psariana",
    "gn:country_code":"GR",
    "gn:dem":398,
    "gn:feature_class":"P",
    "gn:feature_code":"PPL",
    "gn:name":"Psarian\u00e1",
    "gn:population":0,
    "gn:timezone":"Europe/Athens",
    "iso:country":"GR",
    "name:ell_x_preferred":[
        "Psarian\u00e1"
    ],
    "name:ell_x_variant":[
        "\u03a8\u03b1\u03c1\u03b9\u03b1\u03bd\u03ac"
    ],
    "wof:name":"Psariana",
    "wof:placetype":"locality"
},
  "geometry": {"coordinates":[23.70451,35.3493],"type":"Point"}
}