{
  "type": "Feature",
  "properties": {
    "gn:admin1_code":"ESYE22",
    "gn:admin2_code":"26.0",
    "gn:admin3_code":"9121",
    "gn:asciiname":"Kharadhiatika",
    "gn:country_code":"GR",
    "gn:dem":104,
    "gn:feature_class":"P",
    "gn:feature_code":"PPL",
    "gn:name":"Kharadhi\u00e1tika",
    "gn:population":142,
    "gn:timezone":"Europe/Athens",
    "iso:country":"GR",
    "name:ell_x_preferred":[
        "\u03a7\u03b1\u03c1\u03b1\u03b4\u03b9\u03ac\u03c4\u03b9\u03ba\u03b1"
    ],
    "name:eng_x_preferred":[
        "Charadiatika"
    ],
    "name:und_x_variant":[
        "Charadiatika"
    ],
    "wof:name":"Kharadhiatika",
    "wof:placetype":"locality",
    "wof:population":142
},
  "geometry": {"coordinates":[20.68819,38.68584],"type":"Point"}
}