{
  "type": "Feature",
  "properties": {
    "gn:admin1_code":"ESYE24",
    "gn:admin2_code":"29.0",
    "gn:admin3_code":"9159",
    "gn:asciiname":"Sofiadha",
    "gn:country_code":"GR",
    "gn:dem":119,
    "gn:feature_class":"P",
    "gn:feature_code":"PPL",
    "gn:name":"Sofi\u00e1dha",
    "gn:population":235,
    "gn:timezone":"Europe/Athens",
    "iso:country":"GR",
    "name:ell_x_preferred":[
        "\u03a3\u03bf\u03c6\u03b9\u03ac\u03b4\u03b1"
    ],
    "name:eng_x_preferred":[
        "Sofiada"
    ],
    "name:und_x_variant":[
        "Ts\u00edfliari",
        "Sofi\u00e1dhes",
        "Tsoufl\u00e1r",
        "Sofi\u00e1dha"
    ],
    "wof:name":"Sofiadha",
    "wof:placetype":"locality",
    "wof:population":235
},
  "geometry": {"coordinates":[22.25236,39.20441],"type":"Point"}
}