{
  "type": "Feature",
  "properties": {
    "gn:admin1_code":"ESYE25",
    "gn:admin2_code":"42.0",
    "gn:admin3_code":"9248",
    "gn:asciiname":"Kouloumion",
    "gn:country_code":"GR",
    "gn:dem":144,
    "gn:feature_class":"P",
    "gn:feature_code":"PPL",
    "gn:name":"Koulo\u00famion",
    "gn:population":17,
    "gn:timezone":"Europe/Athens",
    "iso:country":"GR",
    "name:ell_x_preferred":[
        "\u039a\u03bf\u03c5\u03bb\u03bf\u03cd\u03bc\u03b9"
    ],
    "name:eng_x_preferred":[
        "Kouloumi"
    ],
    "name:und_x_variant":[
        "Kalo\u00fami",
        "Koulo\u00famion"
    ],
    "wof:name":"Kouloumion",
    "wof:placetype":"locality",
    "wof:population":17
},
  "geometry": {"coordinates":[22.39932,36.56919],"type":"Point"}
}