{
  "type": "Feature",
  "properties": {
    "gn:gn_country":"GR",
    "gn:gn_fcode":"PPLA3",
    "gn:gn_pop":4562,
    "gn:population":4562,
    "iso:country":"GR",
    "name:ell_x_preferred":[
        "\u03a3\u03ba\u03cd\u03b4\u03c1\u03b1"
    ],
    "name:unk_x_variant":[
        "Vertek\u00f3p"
    ],
    "qs_pg:aaroncc":"GR",
    "qs_pg:gn_country":"GR",
    "qs_pg:gn_fcode":"PPLA3",
    "qs_pg:gn_pop":4562,
    "qs_pg:name":"Skydra",
    "qs_pg:name_adm0":"\u0395\u03bb\u03bb\u03ac\u03b4\u03b1",
    "qs_pg:name_adm1":"Macedonia and Thrace",
    "qs_pg:photos_9k":1,
    "qs_pg:photos_9r":4,
    "qs_pg:photos_all":189,
    "qs_pg:photos_sr":0,
    "qs_pg:pop_sr":4,
    "qs_pg:qs_pg_placetype":"localadmin",
    "qs_pg:qs_pg_placetype_gp":"LocalAdmin",
    "qs_pg:woe_adm0":23424833,
    "woe:adm0_id":23424833,
    "woe:name_adm0":"\u0395\u03bb\u03bb\u03ac\u03b4\u03b1",
    "woe:name_adm1":"Macedonia and Thrace",
    "woe:placetype":"LocalAdmin",
    "wof:name":"Skydra",
    "wof:placetype":"localadmin",
    "wof:population":4562
},
  "geometry": {"coordinates":[22.15194,40.76722],"type":"Point"}
}