{
  "type": "Feature",
  "properties": {
    "gn:gn_country":"GR",
    "gn:gn_fcode":"PPL",
    "gn:gn_pop":150,
    "gn:population":78,
    "iso:country":"GR",
    "name:bul_x_preferred":[
        "\u0412\u0440\u043e\u043d\u0434\u0435\u0440\u043e"
    ],
    "name:bul_x_variant":[
        "\u0413\u0440\u0430\u0436\u0434\u0435\u043d"
    ],
    "name:ell_x_historical":[
        "\u0393\u03ba\u03c1\u03ac\u03c3\u03b4\u03b5\u03bd\u03b9"
    ],
    "name:ell_x_preferred":[
        "\u0392\u03c1\u03bf\u03bd\u03c4\u03b5\u03c1\u03cc"
    ],
    "name:ell_x_variant":[
        "\u0392\u03c1\u03bf\u03bd\u03c4\u03b5\u03c1\u03cc\u03bd",
        "\u0393\u03ba\u03c1\u03ac\u03c3\u03b4\u03b5\u03bd\u03b9"
    ],
    "name:eng_x_historical":[
        "Gkrasdeni"
    ],
    "name:eng_x_preferred":[
        "Vrontero"
    ],
    "name:eng_x_variant":[
        "Vronteron",
        "Gkrasdeni"
    ],
    "name:unk_x_variant":[
        "Grasd\u00e9n"
    ],
    "qs_pg:aaroncc":"GR",
    "qs_pg:gn_country":"GR",
    "qs_pg:gn_fcode":"PPL",
    "qs_pg:gn_pop":150,
    "qs_pg:name":"Vronter\u00f3n",
    "qs_pg:photos_9r":0,
    "qs_pg:photos_sr":0,
    "qs_pg:pop_sr":1,
    "qs_pg:qs_pg_placetype":"locality",
    "wof:name":"Vronter\u00f3n",
    "wof:placetype":"locality",
    "wof:population":78
},
  "geometry": {"coordinates":[21.015,40.74306],"type":"Point"}
}