{
  "type": "Feature",
  "properties": {
    "gn:admin1_code":"ESYE11",
    "gn:admin2_code":"14.0",
    "gn:admin3_code":"9014",
    "gn:asciiname":"Nea Peramos",
    "gn:country_code":"GR",
    "gn:dem":6,
    "gn:feature_class":"P",
    "gn:feature_code":"PPL",
    "gn:name":"N\u00e9a P\u00e9ramos",
    "gn:population":3514,
    "gn:timezone":"Europe/Athens",
    "iso:country":"GR",
    "name:ell_x_preferred":[
        "\u039d\u03ad\u03b1 \u03a0\u03ad\u03c1\u03b1\u03bc\u03bf\u03c2"
    ],
    "name:eng_x_preferred":[
        "Nea Peramos"
    ],
    "name:und_x_variant":[
        "N\u00e9a P\u00e9ramos"
    ],
    "wof:name":"Nea Peramos",
    "wof:placetype":"locality",
    "wof:population":3514
},
  "geometry": {"coordinates":[24.3013,40.83854],"type":"Point"}
}