{
  "type": "Feature",
  "properties": {
    "gn:admin1_code":"ESYE11",
    "gn:admin2_code":"14.0",
    "gn:admin3_code":"9014",
    "gn:asciiname":"Nea Peramos",
    "gn:country_code":"GR",
    "gn:dem":6,
    "gn:feature_class":"P",
    "gn:feature_code":"PPL",
    "gn:name":"N\u00e9a P\u00e9ramos",
    "gn:population":3514,
    "gn:timezone":"Europe/Athens",
    "iso:country":"GR",
    "name:ara_x_preferred":[
        "\u0646\u064a \u0628\u064a\u0631\u0627\u0645\u0648\u0633"
    ],
    "name:bul_x_preferred":[
        "\u041d\u0435\u0430 \u041f\u0435\u0440\u0430\u043c\u043e\u0441"
    ],
    "name:ceb_x_preferred":[
        "N\u00e9a P\u00e9ramos"
    ],
    "name:deu_x_preferred":[
        "Nea Peramos"
    ],
    "name:ell_x_preferred":[
        "\u039d\u03ad\u03b1 \u03a0\u03ad\u03c1\u03b1\u03bc\u03bf\u03c2"
    ],
    "name:ell_x_variant":[
        "\u039d\u03ad\u03b1 \u03a0\u03ad\u03c1\u03b1\u03bc\u03bf\u03c2 \u039a\u03b1\u03b2\u03ac\u03bb\u03b1\u03c2"
    ],
    "name:eng_x_preferred":[
        "Nea Peramos"
    ],
    "name:und_x_variant":[
        "N\u00e9a P\u00e9ramos"
    ],
    "wof:name":"Nea Peramos",
    "wof:placetype":"locality",
    "wof:population":3514
},
  "geometry": {"coordinates":[24.3013,40.83854],"type":"Point"}
}