{
  "type": "Feature",
  "properties": {
    "gn:admin1_code":"ESYE43",
    "gn:admin2_code":"43.0",
    "gn:admin3_code":"9323",
    "gn:asciiname":"Kardiamiana",
    "gn:country_code":"GR",
    "gn:dem":259,
    "gn:feature_class":"P",
    "gn:feature_code":"PPL",
    "gn:name":"Kardiamian\u00e1",
    "gn:population":0,
    "gn:timezone":"Europe/Athens",
    "iso:country":"GR",
    "name:ell_x_preferred":[
        "Kardiamian\u00e1"
    ],
    "name:ell_x_variant":[
        "\u039a\u03b1\u03c1\u03b4\u03b9\u03b1\u03bc\u03b9\u03b1\u03bd\u03ac"
    ],
    "name:und_x_variant":[
        "Sinoikism\u00f3s Kardhiamiana",
        "Kardhiamian\u00e1"
    ],
    "wof:name":"Kardiamiana",
    "wof:placetype":"locality"
},
  "geometry": {"coordinates":[23.84588,35.42503],"type":"Point"}
}