{
  "type": "Feature",
  "properties": {
    "gn:admin1_code":"ESYE31",
    "gn:admin2_code":"406101.0",
    "gn:admin3_code":"9209",
    "gn:asciiname":"Stathianika",
    "gn:country_code":"GR",
    "gn:dem":330,
    "gn:feature_class":"P",
    "gn:feature_code":"PPL",
    "gn:name":"Stathi\u00e1nika",
    "gn:population":7,
    "gn:timezone":"Europe/Athens",
    "iso:country":"GR",
    "name:ell_x_preferred":[
        "\u03a3\u03c4\u03b1\u03b8\u03b9\u03ac\u03bd\u03b9\u03ba\u03b1"
    ],
    "name:ell_x_variant":[
        "\u0395\u03c5\u03c3\u03c4\u03b1\u03b8\u03b9\u03ac\u03bd\u03b9\u03ba\u03b1"
    ],
    "name:eng_x_preferred":[
        "Stathianika"
    ],
    "name:und_x_variant":[
        "Evstathi\u00e1nika",
        "Stathi\u00e1nika"
    ],
    "wof:name":"Stathianika",
    "wof:placetype":"locality",
    "wof:population":7
},
  "geometry": {"coordinates":[22.97293,36.21004],"type":"Point"}
}