{
  "type": "Feature",
  "properties": {
    "gn:admin1_code":"ESYE42",
    "gn:admin2_code":"49.0",
    "gn:admin3_code":"9301",
    "gn:asciiname":"Falatados",
    "gn:country_code":"GR",
    "gn:dem":388,
    "gn:feature_class":"P",
    "gn:feature_code":"PPL",
    "gn:name":"Falat\u00e1dos",
    "gn:population":0,
    "gn:timezone":"Europe/Athens",
    "iso:country":"GR",
    "name:und_x_variant":[
        "Falat\u00e1dos",
        "\u03a6\u03b1\u03bb\u03b1\u03c4\u03ac\u03b4\u03bf\u03c2"
    ],
    "wof:name":"Falatados",
    "wof:placetype":"locality"
},
  "geometry": {"coordinates":[25.19119,37.5826],"type":"Point"}
}