{
  "type": "Feature",
  "properties": {
    "gn:admin1_code":"ESYE11",
    "gn:admin2_code":"4.0",
    "gn:admin3_code":"9005",
    "gn:asciiname":"Megalokampos",
    "gn:country_code":"GR",
    "gn:dem":71,
    "gn:feature_class":"P",
    "gn:feature_code":"PPL",
    "gn:name":"Megal\u00f3kampos",
    "gn:population":0,
    "gn:timezone":"Europe/Athens",
    "iso:country":"GR",
    "name:ell_x_preferred":[
        "Megal\u00f3kampos"
    ],
    "name:ell_x_variant":[
        "\u039c\u03b5\u03b3\u03b1\u03bb\u03cc\u03ba\u03b1\u03bc\u03c0\u03bf\u03c2"
    ],
    "name:und_x_variant":[
        "Meg\u00e1lo Sividr\u00edk",
        "Megal\u00f3kambos"
    ],
    "wof:name":"Megalokampos",
    "wof:placetype":"locality"
},
  "geometry": {"coordinates":[23.99639,41.11223],"type":"Point"}
}