{
  "type": "Feature",
  "properties": {
    "gn:admin1_code":"ESYE12",
    "gn:admin2_code":"5.0",
    "gn:admin3_code":"9049",
    "gn:asciiname":"Nea Mesolakkia",
    "gn:country_code":"GR",
    "gn:dem":31,
    "gn:feature_class":"P",
    "gn:feature_code":"PPL",
    "gn:name":"N\u00e9a Mesolakki\u00e1",
    "gn:population":325,
    "gn:timezone":"Europe/Athens",
    "iso:country":"GR",
    "name:ell_x_preferred":[
        "\u039d\u03ad\u03b1 \u039c\u03b5\u03c3\u03bf\u03bb\u03b1\u03ba\u03ba\u03b9\u03ac"
    ],
    "name:ell_x_variant":[
        "N\u00e9a Mesolakki\u00e1"
    ],
    "name:eng_x_preferred":[
        "Nea Mesolakkia"
    ],
    "wof:name":"Nea Mesolakkia",
    "wof:placetype":"locality",
    "wof:population":325
},
  "geometry": {"coordinates":[23.85444,40.84711],"type":"Point"}
}