{
  "type": "Feature",
  "properties": {
    "gn:admin1_code":"ESYE12",
    "gn:admin2_code":"13.0",
    "gn:admin3_code":"9038",
    "gn:asciiname":"Balaiika",
    "gn:country_code":"GR",
    "gn:dem":236,
    "gn:feature_class":"P",
    "gn:feature_code":"PPL",
    "gn:name":"Bala\u00edika",
    "gn:population":0,
    "gn:timezone":"Europe/Athens",
    "iso:country":"GR",
    "name:ell_x_preferred":[
        "\u039c\u03c0\u03b1\u03bb\u03b1\u03af\u03b9\u03ba\u03b1"
    ],
    "name:und_x_variant":[
        "Bala\u00edika",
        "Bal\u00e1"
    ],
    "wof:name":"Balaiika",
    "wof:placetype":"locality"
},
  "geometry": {"coordinates":[22.76757000000001,40.79092],"type":"Point"}
}