{
  "type": "Feature",
  "properties": {
    "gn:admin1_code":"ESYE23",
    "gn:admin2_code":"31.0",
    "gn:admin3_code":"9126",
    "gn:asciiname":"Koftra",
    "gn:country_code":"GR",
    "gn:dem":217,
    "gn:feature_class":"P",
    "gn:feature_code":"PPL",
    "gn:name":"K\u00f3ftra",
    "gn:population":0,
    "gn:timezone":"Europe/Athens",
    "iso:country":"GR",
    "name:ell_x_preferred":[
        "K\u00f3ftra"
    ],
    "name:ell_x_variant":[
        "\u039a\u03cc\u03c6\u03c4\u03c1\u03b1"
    ],
    "wof:name":"Koftra",
    "wof:placetype":"locality"
},
  "geometry": {"coordinates":[21.71456,38.51042],"type":"Point"}
}