{
  "type": "Feature",
  "properties": {
    "gn:admin1_code":"ESYE14",
    "gn:admin2_code":"22.0",
    "gn:admin3_code":"9113",
    "gn:asciiname":"Drosochori",
    "gn:country_code":"GR",
    "gn:dem":917,
    "gn:feature_class":"P",
    "gn:feature_code":"PPL",
    "gn:name":"Drosoch\u00f3ri",
    "gn:population":0,
    "gn:timezone":"Europe/Athens",
    "iso:country":"GR",
    "name:ell_x_preferred":[
        "\u0394\u03c1\u03bf\u03c3\u03bf\u03c7\u03ce\u03c1\u03b9"
    ],
    "name:ell_x_variant":[
        "\u0394\u03c1\u03bf\u03c3\u03bf\u03c7\u03ce\u03c1\u03b9\u03bf\u03bd"
    ],
    "name:und_x_variant":[
        "Tiflos\u00e9llion",
        "Drosoch\u00f3ri",
        "Tyflos\u00e9llion",
        "Tiflos\u00e9li",
        "Tiflos\u00e9lion",
        "Tifros\u00e9llion",
        "Drosoch\u00f3rion"
    ],
    "wof:name":"Drosochori",
    "wof:placetype":"locality"
},
  "geometry": {"coordinates":[21.35807,39.53799],"type":"Point"}
}