{
  "type": "Feature",
  "properties": {
    "gn:admin1_code":"ESYE25",
    "gn:admin2_code":"40.0",
    "gn:admin3_code":"9257",
    "gn:asciiname":"Koumaro",
    "gn:country_code":"GR",
    "gn:dem":387,
    "gn:feature_class":"P",
    "gn:feature_code":"PPL",
    "gn:name":"Ko\u00famaro",
    "gn:population":0,
    "gn:timezone":"Europe/Athens",
    "iso:country":"GR",
    "name:ell_x_preferred":[
        "\u039a\u03bf\u03cd\u03bc\u03b1\u03c1\u03bf"
    ],
    "name:ell_x_variant":[
        "\u039a\u03bf\u03cd\u03bc\u03b1\u03c1\u03bf\u03bd"
    ],
    "name:und_x_variant":[
        "Ko\u00famaro",
        "Ko\u00famaron"
    ],
    "wof:name":"Koumaro",
    "wof:placetype":"locality"
},
  "geometry": {"coordinates":[21.80173,37.03572],"type":"Point"}
}