{
  "type": "Feature",
  "properties": {
    "gn:admin1_code":"ESYE43",
    "gn:admin2_code":"43.0",
    "gn:admin3_code":"9321",
    "gn:asciiname":"Kountouriana",
    "gn:country_code":"GR",
    "gn:dem":420,
    "gn:feature_class":"P",
    "gn:feature_code":"PPL",
    "gn:name":"Kountourian\u00e1",
    "gn:population":0,
    "gn:timezone":"Europe/Athens",
    "iso:country":"GR",
    "name:ell_x_preferred":[
        "Kountourian\u00e1"
    ],
    "name:ell_x_variant":[
        "\u039a\u03bf\u03c5\u03bd\u03c4\u03bf\u03c5\u03c1\u03b9\u03b1\u03bd\u03ac"
    ],
    "wof:name":"Kountouriana",
    "wof:placetype":"locality"
},
  "geometry": {"coordinates":[23.72038,35.34973],"type":"Point"}
}