{
  "type": "Feature",
  "properties": {
    "iso:country":"GR",
    "name:deu_x_preferred":[
        "Solygia"
    ],
    "name:ell_x_preferred":[
        "\u03b4\u03b7\u03bc\u03bf\u03c4\u03b9\u03ba\u03ae \u03b5\u03bd\u03cc\u03c4\u03b7\u03c4\u03b1 \u03a3\u03bf\u03bb\u03c5\u03b3\u03b5\u03af\u03b1\u03c2"
    ],
    "name:eng_x_preferred":[
        "Solygeia"
    ],
    "name:fin_x_preferred":[
        "Solyge\u00eda"
    ],
    "name:fra_x_preferred":[
        "Solygeia"
    ],
    "name:ita_x_preferred":[
        "Solygeia"
    ],
    "name:jpn_x_preferred":[
        "\u30bd\u30ea\u30ae\u30a2"
    ],
    "name:nld_x_preferred":[
        "Solygeia"
    ],
    "name:nno_x_preferred":[
        "Solyj\u00eda"
    ],
    "name:ron_x_preferred":[
        "Solygeia"
    ],
    "qs_pg:aaroncc":"GR",
    "qs_pg:name":"Solygeia",
    "qs_pg:name_adm0":"\u0395\u03bb\u03bb\u03ac\u03b4\u03b1",
    "qs_pg:name_adm1":"Peloponnese Western Greece and the Ionian Islands",
    "qs_pg:photos":13,
    "qs_pg:photos_1k":3,
    "qs_pg:photos_9k":1,
    "qs_pg:photos_9r":1,
    "qs_pg:photos_all":13,
    "qs_pg:photos_sr":1,
    "qs_pg:pop_sr":0,
    "qs_pg:qs_pg_placetype":"locality",
    "qs_pg:qs_pg_placetype_gp":"Town",
    "qs_pg:woe_adm0":23424833,
    "woe:adm0_id":23424833,
    "woe:name_adm0":"\u0395\u03bb\u03bb\u03ac\u03b4\u03b1",
    "woe:name_adm1":"Peloponnese Western Greece and the Ionian Islands",
    "woe:placetype":"Town",
    "wof:name":"Solygeia",
    "wof:placetype":"locality"
},
  "geometry": {"coordinates":[23.116344,37.839861],"type":"Point"}
}