{
  "type": "Feature",
  "properties": {
    "gn:admin1_code":"ESYE25",
    "gn:admin2_code":"42.0",
    "gn:admin3_code":"9248",
    "gn:asciiname":"Rachi",
    "gn:country_code":"GR",
    "gn:dem":184,
    "gn:feature_class":"P",
    "gn:feature_code":"PPL",
    "gn:name":"R\u00e1chi",
    "gn:population":0,
    "gn:timezone":"Europe/Athens",
    "iso:country":"GR",
    "name:ell_x_preferred":[
        "R\u00e1chi"
    ],
    "name:ell_x_variant":[
        "\u03a1\u03ac\u03c7\u03b7"
    ],
    "name:und_x_variant":[
        "R\u00e1khi"
    ],
    "wof:name":"Rachi",
    "wof:placetype":"locality"
},
  "geometry": {"coordinates":[22.53528,36.78195],"type":"Point"}
}