{
  "type": "Feature",
  "properties": {
    "gn:gn_country":"GR",
    "gn:gn_fcode":"ADM3",
    "gn:gn_pop":12597,
    "gn:population":12597,
    "iso:country":"GR",
    "name:ell_x_preferred":[
        "\u03a0\u03ac\u03c1\u03b3\u03b1\u03c2"
    ],
    "qs_pg:aaroncc":"GR",
    "qs_pg:gn_country":"GR",
    "qs_pg:gn_fcode":"ADM3",
    "qs_pg:gn_pop":12597,
    "qs_pg:name":"Dimos Parga",
    "qs_pg:photos_9r":0,
    "qs_pg:photos_sr":0,
    "qs_pg:pop_sr":6,
    "qs_pg:qs_pg_placetype":"localadmin",
    "wof:name":"Dimos Parga",
    "wof:placetype":"localadmin",
    "wof:population":12597
},
  "geometry": {"coordinates":[20.53083,39.26106],"type":"Point"}
}