{
  "type": "Feature",
  "properties": {
    "gn:admin1_code":"ESYE11",
    "gn:admin2_code":"1.0",
    "gn:admin3_code":"9008",
    "gn:asciiname":"Palli",
    "gn:country_code":"GR",
    "gn:dem":63,
    "gn:feature_class":"P",
    "gn:feature_code":"PPL",
    "gn:name":"P\u00e1lli",
    "gn:population":0,
    "gn:timezone":"Europe/Athens",
    "iso:country":"GR",
    "name:ell_x_preferred":[
        "P\u00e1lli"
    ],
    "name:ell_x_variant":[
        "\u03a0\u03ac\u03bb\u03bb\u03b7"
    ],
    "wof:name":"Palli",
    "wof:placetype":"locality"
},
  "geometry": {"coordinates":[26.27327,41.68846],"type":"Point"}
}