{
  "type": "Feature",
  "properties": {
    "gn:country":"GR",
    "gn:fcode":"PPL",
    "gn:population":5,
    "iso:country":"GR",
    "name:ell_x_preferred":[
        "\u03a3\u03b1\u03bc\u03b9\u03bf\u03c0\u03bf\u03cd\u03bb\u03b1"
    ],
    "name:eng_x_preferred":[
        "Samiopoula"
    ],
    "qs_pg:aaroncc":"GR",
    "qs_pg:gn_country":"GR",
    "qs_pg:gn_fcode":"PPL",
    "qs_pg:gn_pop":5,
    "qs_pg:name":"Samiopo\u00fala",
    "qs_pg:photos_9r":0,
    "qs_pg:photos_sr":0,
    "qs_pg:pop_sr":1,
    "qs_pg:qs_pg_placetype":"locality",
    "wof:name":"Samiopo\u00fala",
    "wof:placetype":"locality",
    "wof:population":4
},
  "geometry": {"coordinates":[26.79139,37.62861],"type":"Point"}
}