{
  "type": "Feature",
  "properties": {
    "gn:admin1_code":"ESYE43",
    "gn:admin2_code":"43.0",
    "gn:admin3_code":"9323",
    "gn:asciiname":"Vrisai",
    "gn:cc2":"GR",
    "gn:country_code":"GR",
    "gn:dem":46,
    "gn:feature_class":"P",
    "gn:feature_code":"PPL",
    "gn:name":"Vr\u00edsai",
    "gn:population":0,
    "gn:timezone":"Europe/Athens",
    "iso:country":"GR",
    "name:ell_x_preferred":[
        "\u0392\u03c1\u03cd\u03c3\u03b5\u03c2"
    ],
    "name:eng_x_preferred":[
        "Vrisses"
    ],
    "name:und_x_variant":[
        "Vr\u00edsses",
        "Vr\u00edses"
    ],
    "wof:name":"Vrisai",
    "wof:placetype":"locality"
},
  "geometry": {"coordinates":[23.8902,35.49324],"type":"Point"}
}