{
  "type": "Feature",
  "properties": {
    "gn:admin1_code":"ESYE24",
    "gn:admin2_code":"34.0",
    "gn:admin3_code":"9152",
    "gn:asciiname":"Akhladheri",
    "gn:cc2":"GR",
    "gn:country_code":"GR",
    "gn:dem":245,
    "gn:feature_class":"P",
    "gn:feature_code":"PPL",
    "gn:name":"Akhladher\u00ed",
    "gn:population":0,
    "gn:timezone":"Europe/Athens",
    "iso:country":"GR",
    "name:und_x_variant":[
        "Akhladeri",
        "Akhladher\u00ed"
    ],
    "wof:name":"Akhladheri",
    "wof:placetype":"locality"
},
  "geometry": {"coordinates":[24.17174,38.47508],"type":"Point"}
}