{
  "type": "Feature",
  "properties": {
    "gn:admin1_code":"ESYE13",
    "gn:admin2_code":"11.0",
    "gn:admin3_code":"9066",
    "gn:asciiname":"Koiladi",
    "gn:country_code":"GR",
    "gn:dem":776,
    "gn:feature_class":"P",
    "gn:feature_code":"PPL",
    "gn:name":"Koil\u00e1di",
    "gn:population":0,
    "gn:timezone":"Europe/Athens",
    "iso:country":"GR",
    "name:bih_x_preferred":[
        "\u0915\u094b\u0907\u0932\u093e\u0921\u0940"
    ],
    "name:ceb_x_preferred":[
        "Koiladi"
    ],
    "name:ell_x_preferred":[
        "Koil\u00e1di"
    ],
    "name:ell_x_variant":[
        "\u039a\u03bf\u03b9\u03bb\u03ac\u03b4\u03b9",
        "Koil\u00e1dion",
        "\u039a\u03bf\u03b9\u03bb\u03ac\u03b4\u03b9\u03bf\u03bd"
    ],
    "name:fra_x_preferred":[
        "Koiladi"
    ],
    "name:mai_x_preferred":[
        "\u0915\u094b\u0907\u0932\u093e\u0921\u0940"
    ],
    "name:msa_x_preferred":[
        "Koiladi"
    ],
    "name:nep_x_preferred":[
        "\u0915\u094b\u0907\u0932\u093e\u0921\u0940"
    ],
    "name:new_x_preferred":[
        "\u0915\u094b\u0907\u0932\u093e\u0921\u0940 \u0917\u093e\u0935\u093f\u0938"
    ],
    "name:pol_x_preferred":[
        "Koiladi"
    ],
    "name:und_x_variant":[
        "Tsaval\u00e9ri",
        "Koil\u00e1dhi",
        "Koil\u00e1dhion"
    ],
    "wof:name":"Koiladi",
    "wof:placetype":"locality"
},
  "geometry": {"coordinates":[21.19767,40.26492],"type":"Point"}
}