{
  "type": "Feature",
  "properties": {
    "gn:admin1_code":"ESYE14",
    "gn:admin2_code":"23.0",
    "gn:admin3_code":"9091",
    "gn:asciiname":"Noules",
    "gn:country_code":"GR",
    "gn:dem":476,
    "gn:feature_class":"P",
    "gn:feature_code":"PPL",
    "gn:name":"No\u00fales",
    "gn:population":0,
    "gn:timezone":"Europe/Athens",
    "iso:country":"GR",
    "wof:name":"Noules",
    "wof:placetype":"locality"
},
  "geometry": {"coordinates":[21.42361,39.24667],"type":"Point"}
}