{
  "type": "Feature",
  "properties": {
    "gn:admin1_code":"ESYE12",
    "gn:admin2_code":"5.0",
    "gn:admin3_code":"9054",
    "gn:asciiname":"Koumaria",
    "gn:country_code":"GR",
    "gn:dem":17,
    "gn:feature_class":"P",
    "gn:feature_code":"PPL",
    "gn:name":"Koumari\u00e1",
    "gn:population":381,
    "gn:timezone":"Europe/Athens",
    "iso:country":"GR",
    "name:bul_x_preferred":[
        "\u041a\u043e\u043c\u0430\u0440\u044f\u043d"
    ],
    "name:ell_x_historical":[
        "\u039a\u03bf\u03c5\u03bc\u03ac\u03c1\u03b3\u03b9\u03b1\u03bd\u03bd\u03b7"
    ],
    "name:ell_x_preferred":[
        "\u039a\u03bf\u03c5\u03bc\u03b1\u03c1\u03b9\u03ac"
    ],
    "name:ell_x_variant":[
        "\u039a\u03bf\u03c5\u03bc\u03ac\u03c1\u03b3\u03b9\u03b1\u03bd\u03bd\u03b7"
    ],
    "name:und_x_variant":[
        "Koum\u00e1ryianni",
        "Koumari\u00e1"
    ],
    "wof:name":"Koumaria",
    "wof:placetype":"locality",
    "wof:population":381
},
  "geometry": {"coordinates":[23.43476,41.01591],"type":"Point"}
}