{
  "type": "Feature",
  "properties": {
    "gn:population":647,
    "iso:country":"GR",
    "name:bul_x_preferred":[
        "\u041c\u0443\u0449\u0435\u043d\u0438"
    ],
    "name:ell_x_preferred":[
        "\u039c\u03bf\u03c5\u03c3\u03b8\u03ad\u03bd\u03b7"
    ],
    "name:mkd_x_preferred":[
        "\u041c\u043e\u0448\u0442\u0438\u0458\u0430\u043d"
    ],
    "name:unk_x_variant":[
        "Mousth\u00e9ni"
    ],
    "qs:a0":"Greece",
    "qs:a1":"*\u0391\u039d\u0391\u03a4\u039f\u039b\u0399\u039a\u0397 \u039c\u0391\u039a\u0395\u0394\u039f\u039d\u0399\u0391 \u039a\u0391\u0399 \u0398\u03a1\u0391\u039a\u0397",
    "qs:a1_alt":"ANATOLIKH MAKEDONIA KAI URAKH",
    "qs:a1r":"0",
    "qs:a2_alt":"KABALA",
    "qs:adm0":"Greece",
    "qs:la_lc":"*",
    "qs:level":"locality",
    "qs:loc":"\u039c\u039f\u03a5\u03a3\u0398\u0395\u039d\u0397",
    "qs:loc_alt":"MOYSUENH",
    "qs:pop":0,
    "qs:type":"buffered point",
    "wof:name":"\u039c\u039f\u03a5\u03a3\u0398\u0395\u039d\u0397",
    "wof:placetype":"locality",
    "wof:population":647
},
  "geometry": {"coordinates":[24.112211,40.863789],"type":"Point"}
}