{
  "type": "Feature",
  "properties": {
    "gn:admin1_code":"ESYE43",
    "gn:admin2_code":"46.0",
    "gn:admin3_code":"9311",
    "gn:asciiname":"Aspros Potamos",
    "gn:country_code":"GR",
    "gn:dem":37,
    "gn:feature_class":"P",
    "gn:feature_code":"PPL",
    "gn:name":"\u00c1spros Potam\u00f3s",
    "gn:population":35,
    "gn:timezone":"Europe/Athens",
    "iso:country":"GR",
    "name:ell_x_preferred":[
        "\u0386\u03c3\u03c0\u03c1\u03bf\u03c2 \u03a0\u03bf\u03c4\u03b1\u03bc\u03cc\u03c2"
    ],
    "name:eng_x_preferred":[
        "Aspros Potamos"
    ],
    "name:und_x_variant":[
        "\u00c1spros Potam\u00f3s"
    ],
    "wof:name":"Aspros Potamos",
    "wof:placetype":"locality",
    "wof:population":35
},
  "geometry": {"coordinates":[25.98705,35.04766],"type":"Point"}
}