{
  "type": "Feature",
  "properties": {
    "gn:country":"GR",
    "gn:fcode":"PPL",
    "gn:population":130,
    "iso:country":"GR",
    "name:ell_x_preferred":[
        "\u039a\u03c5\u03c1\u03ac \u03a0\u03b1\u03bd\u03b1\u03b3\u03b9\u03ac"
    ],
    "name:und_x_variant":[
        "Borov\u00e1ri"
    ],
    "qs_pg:aaroncc":"GR",
    "qs_pg:gn_country":"GR",
    "qs_pg:gn_fcode":"PPL",
    "qs_pg:gn_pop":130,
    "qs_pg:name":"Kyr\u00e1 Panagi\u00e1",
    "qs_pg:photos_9r":0,
    "qs_pg:photos_sr":0,
    "qs_pg:pop_sr":1,
    "qs_pg:qs_pg_placetype":"locality",
    "wof:name":"Kyr\u00e1 Panagi\u00e1",
    "wof:placetype":"locality",
    "wof:population":130
},
  "geometry": {"coordinates":[20.485,39.3975],"type":"Point"}
}