{
  "type": "Feature",
  "properties": {
    "gn:admin1_code":"ESYE23",
    "gn:admin2_code":"39.0",
    "gn:admin3_code":"9141",
    "gn:asciiname":"Magoula",
    "gn:country_code":"GR",
    "gn:dem":57,
    "gn:feature_class":"P",
    "gn:feature_code":"PPL",
    "gn:name":"Mago\u00fala",
    "gn:population":0,
    "gn:timezone":"Europe/Athens",
    "iso:country":"GR",
    "name:ell_x_preferred":[
        "\u039c\u03b1\u03b3\u03bf\u03cd\u03bb\u03b1"
    ],
    "name:und_x_variant":[
        "Mapo\u00fala",
        "Mago\u00fala"
    ],
    "wof:name":"Magoula",
    "wof:placetype":"locality"
},
  "geometry": {"coordinates":[21.53664,37.727],"type":"Point"}
}