{
  "type": "Feature",
  "properties": {
    "gn:admin1_code":"ESYE25",
    "gn:admin2_code":"41.0",
    "gn:admin3_code":"9239",
    "gn:asciiname":"Kamara",
    "gn:country_code":"GR",
    "gn:dem":555,
    "gn:feature_class":"P",
    "gn:feature_code":"PPL",
    "gn:name":"Kam\u00e1ra",
    "gn:population":0,
    "gn:timezone":"Europe/Athens",
    "iso:country":"GR",
    "name:ceb_x_preferred":[
        "Kamara"
    ],
    "name:deu_x_preferred":[
        "Kamara"
    ],
    "name:ell_x_preferred":[
        "Kam\u00e1ra"
    ],
    "name:ell_x_variant":[
        "\u039a\u03b1\u03bc\u03ac\u03c1\u03b1"
    ],
    "name:fin_x_preferred":[
        "Kamara"
    ],
    "name:fra_x_preferred":[
        "Kamara"
    ],
    "name:heb_x_preferred":[
        "\u05e7\u05de\u05d0\u05e8\u05d4"
    ],
    "name:ita_x_preferred":[
        "Kamara"
    ],
    "name:lav_x_preferred":[
        "Kamara"
    ],
    "name:que_x_preferred":[
        "Kamara"
    ],
    "name:rus_x_preferred":[
        "\u041a\u0430\u043c\u0430\u0440\u0430"
    ],
    "name:swe_x_preferred":[
        "Kamara"
    ],
    "wof:name":"Kamara",
    "wof:placetype":"locality"
},
  "geometry": {"coordinates":[22.18101,37.24161],"type":"Point"}
}