{
  "type": "Feature",
  "properties": {
    "gn:gn_country":"GR",
    "gn:gn_fcode":"PPL",
    "gn:gn_pop":132,
    "gn:population":132,
    "iso:country":"GR",
    "name:ell_x_preferred":[
        "\u03a6\u03bb\u03bf\u03c1\u03b9\u03ac\u03b4\u03b1"
    ],
    "name:unk_x_variant":[
        "Li\u00e1skovo"
    ],
    "qs_pg:aaroncc":"GR",
    "qs_pg:gn_country":"GR",
    "qs_pg:gn_fcode":"PPL",
    "qs_pg:gn_pop":132,
    "qs_pg:name":"Flori\u00e1da",
    "qs_pg:photos_9r":0,
    "qs_pg:photos_sr":0,
    "qs_pg:pop_sr":1,
    "qs_pg:qs_pg_placetype":"locality",
    "wof:name":"Flori\u00e1da",
    "wof:placetype":"locality",
    "wof:population":132
},
  "geometry": {"coordinates":[21.15806,39.10611],"type":"Point"}
}