{
  "type": "Feature",
  "properties": {
    "gn:country":"GR",
    "gn:fcode":"PPL",
    "gn:population":0,
    "iso:country":"GR",
    "name:ceb_x_preferred":[
        "Kampos"
    ],
    "name:deu_x_preferred":[
        "Kambos"
    ],
    "name:ell_x_preferred":[
        "\u039a\u03ac\u03bc\u03c0\u03bf\u03c2"
    ],
    "name:fin_x_preferred":[
        "K\u00e1mpos"
    ],
    "name:srp_x_preferred":[
        "\u041a\u0430\u043c\u043f\u043e\u0441"
    ],
    "name:swe_x_preferred":[
        "Kampos"
    ],
    "qs_pg:aaroncc":"GR",
    "qs_pg:gn_country":"GR",
    "qs_pg:gn_fcode":"PPL",
    "qs_pg:gn_pop":0,
    "qs_pg:name":"Kampos",
    "qs_pg:name_adm0":"\u0395\u03bb\u03bb\u03ac\u03b4\u03b1",
    "qs_pg:name_adm1":"Aegean",
    "qs_pg:photos_9k":1,
    "qs_pg:photos_9r":1,
    "qs_pg:photos_all":1,
    "qs_pg:photos_sr":0,
    "qs_pg:pop_sr":0,
    "qs_pg:qs_pg_placetype":"locality",
    "qs_pg:qs_pg_placetype_gp":"Town",
    "qs_pg:woe_adm0":23424833,
    "woe:adm0_id":23424833,
    "woe:name_adm0":"\u0395\u03bb\u03bb\u03ac\u03b4\u03b1",
    "woe:name_adm1":"Aegean",
    "woe:placetype":"Town",
    "wof:name":"Kampos",
    "wof:placetype":"locality"
},
  "geometry": {"coordinates":[26.12334,38.32246],"type":"Point"}
}