{
  "type": "Feature",
  "properties": {
    "gn:admin1_code":"ESYE25",
    "gn:admin2_code":"42.0",
    "gn:admin3_code":"9248",
    "gn:asciiname":"Akrogiali",
    "gn:country_code":"GR",
    "gn:dem":285,
    "gn:feature_class":"P",
    "gn:feature_code":"PPL",
    "gn:name":"Akrogi\u00e1li",
    "gn:population":12,
    "gn:timezone":"Europe/Athens",
    "iso:country":"GR",
    "name:ell_x_historical":[
        "\u03a0\u03b9\u03cc\u03bd\u03c4\u03b5\u03c2",
        "\u0391\u03bd\u03c4\u03c1\u03bf\u03b3\u03b9\u03ac\u03bb\u03b9"
    ],
    "name:ell_x_preferred":[
        "\u0391\u03ba\u03c1\u03bf\u03b3\u03b9\u03ac\u03bb\u03b9"
    ],
    "name:ell_x_variant":[
        "\u0391\u03ba\u03c1\u03bf\u03b3\u03b9\u03ac\u03bb\u03b9\u03bf",
        "\u03a0\u03b9\u03cc\u03bd\u03c4\u03b5\u03c2",
        "\u0391\u03bd\u03c4\u03c1\u03bf\u03b3\u03b9\u03ac\u03bb\u03b9"
    ],
    "name:eng_x_historical":[
        "Piontes"
    ],
    "name:eng_x_preferred":[
        "Piontes"
    ],
    "name:eng_x_variant":[
        "Akrogiali"
    ],
    "name:und_x_variant":[
        "Pi\u00f3ndes",
        "Andoyi\u00e1li",
        "Akroyi\u00e1lion",
        "Akrogiali",
        "Akrogialio"
    ],
    "wof:name":"Akrogiali",
    "wof:placetype":"locality",
    "wof:population":12
},
  "geometry": {"coordinates":[22.49161,36.47542],"type":"Point"}
}