{
  "type": "Feature",
  "properties": {
    "gn:admin1_code":"ESYE13",
    "gn:admin2_code":"10.0",
    "gn:admin3_code":"9061",
    "gn:asciiname":"Amygdalies",
    "gn:country_code":"GR",
    "gn:dem":837,
    "gn:feature_class":"P",
    "gn:feature_code":"PPL",
    "gn:name":"Amygdali\u00e9s",
    "gn:population":0,
    "gn:timezone":"Europe/Athens",
    "iso:country":"GR",
    "name:ell_x_preferred":[
        "Amygdali\u00e9s"
    ],
    "name:ell_x_variant":[
        "\u0391\u03bc\u03c5\u03b3\u03b4\u03b1\u03bb\u03b9\u03ad\u03c2",
        "Amygdal\u00e9ai",
        "\u0391\u03bc\u03c5\u03b3\u03b4\u03b1\u03bb\u03ad\u03b1\u03b9"
    ],
    "name:und_x_variant":[
        "Pikriven\u00edtsa",
        "Amigdhali\u00e9s",
        "Amigdhal\u00e9ai"
    ],
    "wof:name":"Amygdalies",
    "wof:placetype":"locality"
},
  "geometry": {"coordinates":[21.37393,40.15643],"type":"Point"}
}