{
  "type": "Feature",
  "properties": {
    "gn:gn_country":"GR",
    "gn:gn_fcode":"PPL",
    "gn:gn_pop":55,
    "gn:population":55,
    "iso:country":"GR",
    "name:ell_x_preferred":[
        "Omal\u00ed"
    ],
    "name:ell_x_variant":[
        "\u039f\u03bc\u03b1\u03bb\u03ae"
    ],
    "qs_pg:aaroncc":"GR",
    "qs_pg:gn_country":"GR",
    "qs_pg:gn_fcode":"PPL",
    "qs_pg:gn_pop":55,
    "qs_pg:name":"Omal\u00ed",
    "qs_pg:photos_9r":0,
    "qs_pg:photos_sr":0,
    "qs_pg:pop_sr":1,
    "qs_pg:qs_pg_placetype":"locality",
    "wof:name":"Omal\u00ed",
    "wof:placetype":"locality",
    "wof:population":55
},
  "geometry": {"coordinates":[21.1775,39.37556],"type":"Point"}
}