{
  "type": "Feature",
  "properties": {
    "gn:admin1_code":"ESYE43",
    "gn:admin2_code":"43.0",
    "gn:admin3_code":"9322",
    "gn:asciiname":"Kera",
    "gn:country_code":"GR",
    "gn:dem":203,
    "gn:feature_class":"P",
    "gn:feature_code":"PPL",
    "gn:name":"Ker\u00e1",
    "gn:population":36,
    "gn:timezone":"Europe/Athens",
    "iso:country":"GR",
    "name:ceb_x_preferred":[
        "Kera"
    ],
    "name:ell_x_preferred":[
        "\u039a\u03b5\u03c1\u03ac"
    ],
    "name:eng_x_preferred":[
        "Kera"
    ],
    "name:ita_x_preferred":[
        "Kera"
    ],
    "name:lav_x_preferred":[
        "Kera"
    ],
    "name:swe_x_preferred":[
        "Kera"
    ],
    "name:und_x_variant":[
        "Ker\u00e1"
    ],
    "wof:name":"Kera",
    "wof:placetype":"locality",
    "wof:population":36
},
  "geometry": {"coordinates":[23.72624,35.46987],"type":"Point"}
}