{
  "type": "Feature",
  "properties": {
    "gn:admin1_code":"ESYE11",
    "gn:admin2_code":"2.0",
    "gn:admin3_code":"9020",
    "gn:asciiname":"Palladio",
    "gn:country_code":"GR",
    "gn:dem":12,
    "gn:feature_class":"P",
    "gn:feature_code":"PPL",
    "gn:name":"Pall\u00e1dio",
    "gn:population":0,
    "gn:timezone":"Europe/Athens",
    "iso:country":"GR",
    "name:ell_x_preferred":[
        "Pall\u00e1dio"
    ],
    "name:ell_x_variant":[
        "\u03a0\u03b1\u03bb\u03bb\u03ac\u03b4\u03b9\u03bf",
        "Pall\u00e1dhion",
        "Pall\u00e1dion",
        "\u03a0\u03b1\u03bb\u03bb\u03ac\u03b4\u03b9\u03bf\u03bd"
    ],
    "wof:name":"Palladio",
    "wof:placetype":"locality"
},
  "geometry": {"coordinates":[25.23554,41.06126],"type":"Point"}
}