{
  "type": "Feature",
  "properties": {
    "gn:admin1_code":"ESYE31",
    "gn:admin2_code":"445406.0",
    "gn:admin3_code":"9219",
    "gn:asciiname":"Ari",
    "gn:country_code":"GR",
    "gn:dem":64,
    "gn:feature_class":"P",
    "gn:feature_code":"PPL",
    "gn:name":"Ar\u00ed",
    "gn:population":208,
    "gn:timezone":"Europe/Athens",
    "iso:country":"GR",
    "name:ell_x_preferred":[
        "\u0391\u03c1\u03af"
    ],
    "name:eng_x_preferred":[
        "Ari"
    ],
    "wof:name":"Ari",
    "wof:placetype":"locality",
    "wof:population":208
},
  "geometry": {"coordinates":[23.98088,37.74639000000001],"type":"Point"}
}