{
  "type": "Feature",
  "properties": {
    "gn:admin1_code":"ESYE31",
    "gn:admin2_code":"445406.0",
    "gn:admin3_code":"9219",
    "gn:asciiname":"Ari",
    "gn:country_code":"GR",
    "gn:dem":64,
    "gn:feature_class":"P",
    "gn:feature_code":"PPL",
    "gn:name":"Ar\u00ed",
    "gn:population":208,
    "gn:timezone":"Europe/Athens",
    "iso:country":"GR",
    "name:cat_x_preferred":[
        "Ari"
    ],
    "name:ceb_x_preferred":[
        "Ari"
    ],
    "name:ell_x_preferred":[
        "\u0391\u03c1\u03af"
    ],
    "name:eng_x_preferred":[
        "Ari"
    ],
    "name:heb_x_preferred":[
        "\u05d0\u05e8\u05d9"
    ],
    "name:ita_x_preferred":[
        "Ari"
    ],
    "name:lim_x_preferred":[
        "Ari"
    ],
    "name:nld_x_preferred":[
        "Ari"
    ],
    "name:pol_x_preferred":[
        "Ari"
    ],
    "name:por_x_preferred":[
        "Ari"
    ],
    "name:rus_x_preferred":[
        "\u0410\u0440\u0438"
    ],
    "name:slk_x_preferred":[
        "Ari"
    ],
    "name:srp_x_preferred":[
        "\u0410\u0440\u0438"
    ],
    "name:swe_x_preferred":[
        "Ari"
    ],
    "name:ukr_x_preferred":[
        "\u0410\u0440\u0456"
    ],
    "name:zho_x_preferred":[
        "Ari"
    ],
    "wof:name":"Ari",
    "wof:placetype":"locality",
    "wof:population":208
},
  "geometry": {"coordinates":[23.98088,37.74639000000001],"type":"Point"}
}